Compiled from "Timing.java"
public class org.hl7.fhir.dstu3.model.Timing$TimingRepeatComponent extends org.hl7.fhir.dstu3.model.Element implements org.hl7.fhir.instance.model.api.IBaseDatatypeElement {
  protected org.hl7.fhir.dstu3.model.Type bounds;

  protected org.hl7.fhir.dstu3.model.IntegerType count;

  protected org.hl7.fhir.dstu3.model.IntegerType countMax;

  protected org.hl7.fhir.dstu3.model.DecimalType duration;

  protected org.hl7.fhir.dstu3.model.DecimalType durationMax;

  protected org.hl7.fhir.dstu3.model.Enumeration<org.hl7.fhir.dstu3.model.Timing$UnitsOfTime> durationUnit;

  protected org.hl7.fhir.dstu3.model.IntegerType frequency;

  protected org.hl7.fhir.dstu3.model.IntegerType frequencyMax;

  protected org.hl7.fhir.dstu3.model.DecimalType period;

  protected org.hl7.fhir.dstu3.model.DecimalType periodMax;

  protected org.hl7.fhir.dstu3.model.Enumeration<org.hl7.fhir.dstu3.model.Timing$UnitsOfTime> periodUnit;

  protected java.util.List<org.hl7.fhir.dstu3.model.Enumeration<org.hl7.fhir.dstu3.model.Timing$DayOfWeek>> dayOfWeek;

  protected java.util.List<org.hl7.fhir.dstu3.model.TimeType> timeOfDay;

  protected java.util.List<org.hl7.fhir.dstu3.model.Enumeration<org.hl7.fhir.dstu3.model.Timing$EventTiming>> when;

  protected org.hl7.fhir.dstu3.model.UnsignedIntType offset;

  private static final long serialVersionUID;

  public org.hl7.fhir.dstu3.model.Timing$TimingRepeatComponent();
    Code:
       0: aload_0
       1: invokespecial #1                  // Method org/hl7/fhir/dstu3/model/Element."<init>":()V
       4: return

  public org.hl7.fhir.dstu3.model.Type getBounds();
    Code:
       0: aload_0
       1: getfield      #2                  // Field bounds:Lorg/hl7/fhir/dstu3/model/Type;
       4: areturn

  public org.hl7.fhir.dstu3.model.Duration getBoundsDuration() throws org.hl7.fhir.exceptions.FHIRException;
    Code:
       0: aload_0
       1: getfield      #2                  // Field bounds:Lorg/hl7/fhir/dstu3/model/Type;
       4: ifnonnull     9
       7: aconst_null
       8: areturn
       9: aload_0
      10: getfield      #2                  // Field bounds:Lorg/hl7/fhir/dstu3/model/Type;
      13: instanceof    #3                  // class org/hl7/fhir/dstu3/model/Duration
      16: ifne          60
      19: new           #4                  // class org/hl7/fhir/exceptions/FHIRException
      22: dup
      23: new           #5                  // class java/lang/StringBuilder
      26: dup
      27: invokespecial #6                  // Method java/lang/StringBuilder."<init>":()V
      30: ldc           #7                  // String Type mismatch: the type Duration was expected, but
      32: invokevirtual #8                  // Method java/lang/StringBuilder.append:(Ljava/lang/String;)Ljava/lang/StringBuilder;
      35: aload_0
      36: getfield      #2                  // Field bounds:Lorg/hl7/fhir/dstu3/model/Type;
      39: invokevirtual #9                  // Method java/lang/Object.getClass:()Ljava/lang/Class;
      42: invokevirtual #10                 // Method java/lang/Class.getName:()Ljava/lang/String;
      45: invokevirtual #8                  // Method java/lang/StringBuilder.append:(Ljava/lang/String;)Ljava/lang/StringBuilder;
      48: ldc           #11                 // String  was encountered
      50: invokevirtual #8                  // Method java/lang/StringBuilder.append:(Ljava/lang/String;)Ljava/lang/StringBuilder;
      53: invokevirtual #12                 // Method java/lang/StringBuilder.toString:()Ljava/lang/String;
      56: invokespecial #13                 // Method org/hl7/fhir/exceptions/FHIRException."<init>":(Ljava/lang/String;)V
      59: athrow
      60: aload_0
      61: getfield      #2                  // Field bounds:Lorg/hl7/fhir/dstu3/model/Type;
      64: checkcast     #3                  // class org/hl7/fhir/dstu3/model/Duration
      67: areturn

  public boolean hasBoundsDuration();
    Code:
       0: aload_0
       1: ifnull        18
       4: aload_0
       5: getfield      #2                  // Field bounds:Lorg/hl7/fhir/dstu3/model/Type;
       8: instanceof    #3                  // class org/hl7/fhir/dstu3/model/Duration
      11: ifeq          18
      14: iconst_1
      15: goto          19
      18: iconst_0
      19: ireturn

  public org.hl7.fhir.dstu3.model.Range getBoundsRange() throws org.hl7.fhir.exceptions.FHIRException;
    Code:
       0: aload_0
       1: getfield      #2                  // Field bounds:Lorg/hl7/fhir/dstu3/model/Type;
       4: ifnonnull     9
       7: aconst_null
       8: areturn
       9: aload_0
      10: getfield      #2                  // Field bounds:Lorg/hl7/fhir/dstu3/model/Type;
      13: instanceof    #14                 // class org/hl7/fhir/dstu3/model/Range
      16: ifne          60
      19: new           #4                  // class org/hl7/fhir/exceptions/FHIRException
      22: dup
      23: new           #5                  // class java/lang/StringBuilder
      26: dup
      27: invokespecial #6                  // Method java/lang/StringBuilder."<init>":()V
      30: ldc           #15                 // String Type mismatch: the type Range was expected, but
      32: invokevirtual #8                  // Method java/lang/StringBuilder.append:(Ljava/lang/String;)Ljava/lang/StringBuilder;
      35: aload_0
      36: getfield      #2                  // Field bounds:Lorg/hl7/fhir/dstu3/model/Type;
      39: invokevirtual #9                  // Method java/lang/Object.getClass:()Ljava/lang/Class;
      42: invokevirtual #10                 // Method java/lang/Class.getName:()Ljava/lang/String;
      45: invokevirtual #8                  // Method java/lang/StringBuilder.append:(Ljava/lang/String;)Ljava/lang/StringBuilder;
      48: ldc           #11                 // String  was encountered
      50: invokevirtual #8                  // Method java/lang/StringBuilder.append:(Ljava/lang/String;)Ljava/lang/StringBuilder;
      53: invokevirtual #12                 // Method java/lang/StringBuilder.toString:()Ljava/lang/String;
      56: invokespecial #13                 // Method org/hl7/fhir/exceptions/FHIRException."<init>":(Ljava/lang/String;)V
      59: athrow
      60: aload_0
      61: getfield      #2                  // Field bounds:Lorg/hl7/fhir/dstu3/model/Type;
      64: checkcast     #14                 // class org/hl7/fhir/dstu3/model/Range
      67: areturn

  public boolean hasBoundsRange();
    Code:
       0: aload_0
       1: ifnull        18
       4: aload_0
       5: getfield      #2                  // Field bounds:Lorg/hl7/fhir/dstu3/model/Type;
       8: instanceof    #14                 // class org/hl7/fhir/dstu3/model/Range
      11: ifeq          18
      14: iconst_1
      15: goto          19
      18: iconst_0
      19: ireturn

  public org.hl7.fhir.dstu3.model.Period getBoundsPeriod() throws org.hl7.fhir.exceptions.FHIRException;
    Code:
       0: aload_0
       1: getfield      #2                  // Field bounds:Lorg/hl7/fhir/dstu3/model/Type;
       4: ifnonnull     9
       7: aconst_null
       8: areturn
       9: aload_0
      10: getfield      #2                  // Field bounds:Lorg/hl7/fhir/dstu3/model/Type;
      13: instanceof    #16                 // class org/hl7/fhir/dstu3/model/Period
      16: ifne          60
      19: new           #4                  // class org/hl7/fhir/exceptions/FHIRException
      22: dup
      23: new           #5                  // class java/lang/StringBuilder
      26: dup
      27: invokespecial #6                  // Method java/lang/StringBuilder."<init>":()V
      30: ldc           #17                 // String Type mismatch: the type Period was expected, but
      32: invokevirtual #8                  // Method java/lang/StringBuilder.append:(Ljava/lang/String;)Ljava/lang/StringBuilder;
      35: aload_0
      36: getfield      #2                  // Field bounds:Lorg/hl7/fhir/dstu3/model/Type;
      39: invokevirtual #9                  // Method java/lang/Object.getClass:()Ljava/lang/Class;
      42: invokevirtual #10                 // Method java/lang/Class.getName:()Ljava/lang/String;
      45: invokevirtual #8                  // Method java/lang/StringBuilder.append:(Ljava/lang/String;)Ljava/lang/StringBuilder;
      48: ldc           #11                 // String  was encountered
      50: invokevirtual #8                  // Method java/lang/StringBuilder.append:(Ljava/lang/String;)Ljava/lang/StringBuilder;
      53: invokevirtual #12                 // Method java/lang/StringBuilder.toString:()Ljava/lang/String;
      56: invokespecial #13                 // Method org/hl7/fhir/exceptions/FHIRException."<init>":(Ljava/lang/String;)V
      59: athrow
      60: aload_0
      61: getfield      #2                  // Field bounds:Lorg/hl7/fhir/dstu3/model/Type;
      64: checkcast     #16                 // class org/hl7/fhir/dstu3/model/Period
      67: areturn

  public boolean hasBoundsPeriod();
    Code:
       0: aload_0
       1: ifnull        18
       4: aload_0
       5: getfield      #2                  // Field bounds:Lorg/hl7/fhir/dstu3/model/Type;
       8: instanceof    #16                 // class org/hl7/fhir/dstu3/model/Period
      11: ifeq          18
      14: iconst_1
      15: goto          19
      18: iconst_0
      19: ireturn

  public boolean hasBounds();
    Code:
       0: aload_0
       1: getfield      #2                  // Field bounds:Lorg/hl7/fhir/dstu3/model/Type;
       4: ifnull        21
       7: aload_0
       8: getfield      #2                  // Field bounds:Lorg/hl7/fhir/dstu3/model/Type;
      11: invokevirtual #18                 // Method org/hl7/fhir/dstu3/model/Type.isEmpty:()Z
      14: ifne          21
      17: iconst_1
      18: goto          22
      21: iconst_0
      22: ireturn

  public org.hl7.fhir.dstu3.model.Timing$TimingRepeatComponent setBounds(org.hl7.fhir.dstu3.model.Type) throws org.hl7.fhir.exceptions.FHIRFormatError;
    Code:
       0: aload_1
       1: ifnull        55
       4: aload_1
       5: instanceof    #3                  // class org/hl7/fhir/dstu3/model/Duration
       8: ifne          55
      11: aload_1
      12: instanceof    #14                 // class org/hl7/fhir/dstu3/model/Range
      15: ifne          55
      18: aload_1
      19: instanceof    #16                 // class org/hl7/fhir/dstu3/model/Period
      22: ifne          55
      25: new           #19                 // class org/hl7/fhir/exceptions/FHIRFormatError
      28: dup
      29: new           #5                  // class java/lang/StringBuilder
      32: dup
      33: invokespecial #6                  // Method java/lang/StringBuilder."<init>":()V
      36: ldc           #20                 // String Not the right type for Timing.repeat.bounds[x]:
      38: invokevirtual #8                  // Method java/lang/StringBuilder.append:(Ljava/lang/String;)Ljava/lang/StringBuilder;
      41: aload_1
      42: invokevirtual #21                 // Method org/hl7/fhir/dstu3/model/Type.fhirType:()Ljava/lang/String;
      45: invokevirtual #8                  // Method java/lang/StringBuilder.append:(Ljava/lang/String;)Ljava/lang/StringBuilder;
      48: invokevirtual #12                 // Method java/lang/StringBuilder.toString:()Ljava/lang/String;
      51: invokespecial #22                 // Method org/hl7/fhir/exceptions/FHIRFormatError."<init>":(Ljava/lang/String;)V
      54: athrow
      55: aload_0
      56: aload_1
      57: putfield      #2                  // Field bounds:Lorg/hl7/fhir/dstu3/model/Type;
      60: aload_0
      61: areturn

  public org.hl7.fhir.dstu3.model.IntegerType getCountElement();
    Code:
       0: aload_0
       1: getfield      #23                 // Field count:Lorg/hl7/fhir/dstu3/model/IntegerType;
       4: ifnonnull     40
       7: invokestatic  #24                 // Method org/hl7/fhir/dstu3/model/Configuration.errorOnAutoCreate:()Z
      10: ifeq          23
      13: new           #25                 // class java/lang/Error
      16: dup
      17: ldc           #26                 // String Attempt to auto-create TimingRepeatComponent.count
      19: invokespecial #27                 // Method java/lang/Error."<init>":(Ljava/lang/String;)V
      22: athrow
      23: invokestatic  #28                 // Method org/hl7/fhir/dstu3/model/Configuration.doAutoCreate:()Z
      26: ifeq          40
      29: aload_0
      30: new           #29                 // class org/hl7/fhir/dstu3/model/IntegerType
      33: dup
      34: invokespecial #30                 // Method org/hl7/fhir/dstu3/model/IntegerType."<init>":()V
      37: putfield      #23                 // Field count:Lorg/hl7/fhir/dstu3/model/IntegerType;
      40: aload_0
      41: getfield      #23                 // Field count:Lorg/hl7/fhir/dstu3/model/IntegerType;
      44: areturn

  public boolean hasCountElement();
    Code:
       0: aload_0
       1: getfield      #23                 // Field count:Lorg/hl7/fhir/dstu3/model/IntegerType;
       4: ifnull        21
       7: aload_0
       8: getfield      #23                 // Field count:Lorg/hl7/fhir/dstu3/model/IntegerType;
      11: invokevirtual #31                 // Method org/hl7/fhir/dstu3/model/IntegerType.isEmpty:()Z
      14: ifne          21
      17: iconst_1
      18: goto          22
      21: iconst_0
      22: ireturn

  public boolean hasCount();
    Code:
       0: aload_0
       1: getfield      #23                 // Field count:Lorg/hl7/fhir/dstu3/model/IntegerType;
       4: ifnull        21
       7: aload_0
       8: getfield      #23                 // Field count:Lorg/hl7/fhir/dstu3/model/IntegerType;
      11: invokevirtual #31                 // Method org/hl7/fhir/dstu3/model/IntegerType.isEmpty:()Z
      14: ifne          21
      17: iconst_1
      18: goto          22
      21: iconst_0
      22: ireturn

  public org.hl7.fhir.dstu3.model.Timing$TimingRepeatComponent setCountElement(org.hl7.fhir.dstu3.model.IntegerType);
    Code:
       0: aload_0
       1: aload_1
       2: putfield      #23                 // Field count:Lorg/hl7/fhir/dstu3/model/IntegerType;
       5: aload_0
       6: areturn

  public int getCount();
    Code:
       0: aload_0
       1: getfield      #23                 // Field count:Lorg/hl7/fhir/dstu3/model/IntegerType;
       4: ifnull        17
       7: aload_0
       8: getfield      #23                 // Field count:Lorg/hl7/fhir/dstu3/model/IntegerType;
      11: invokevirtual #31                 // Method org/hl7/fhir/dstu3/model/IntegerType.isEmpty:()Z
      14: ifeq          21
      17: iconst_0
      18: goto          34
      21: aload_0
      22: getfield      #23                 // Field count:Lorg/hl7/fhir/dstu3/model/IntegerType;
      25: invokevirtual #32                 // Method org/hl7/fhir/dstu3/model/IntegerType.getValue:()Ljava/lang/Object;
      28: checkcast     #33                 // class java/lang/Integer
      31: invokevirtual #34                 // Method java/lang/Integer.intValue:()I
      34: ireturn

  public org.hl7.fhir.dstu3.model.Timing$TimingRepeatComponent setCount(int);
    Code:
       0: aload_0
       1: getfield      #23                 // Field count:Lorg/hl7/fhir/dstu3/model/IntegerType;
       4: ifnonnull     18
       7: aload_0
       8: new           #29                 // class org/hl7/fhir/dstu3/model/IntegerType
      11: dup
      12: invokespecial #30                 // Method org/hl7/fhir/dstu3/model/IntegerType."<init>":()V
      15: putfield      #23                 // Field count:Lorg/hl7/fhir/dstu3/model/IntegerType;
      18: aload_0
      19: getfield      #23                 // Field count:Lorg/hl7/fhir/dstu3/model/IntegerType;
      22: iload_1
      23: invokestatic  #35                 // Method java/lang/Integer.valueOf:(I)Ljava/lang/Integer;
      26: invokevirtual #36                 // Method org/hl7/fhir/dstu3/model/IntegerType.setValue:(Ljava/lang/Object;)Lorg/hl7/fhir/dstu3/model/PrimitiveType;
      29: pop
      30: aload_0
      31: areturn

  public org.hl7.fhir.dstu3.model.IntegerType getCountMaxElement();
    Code:
       0: aload_0
       1: getfield      #37                 // Field countMax:Lorg/hl7/fhir/dstu3/model/IntegerType;
       4: ifnonnull     40
       7: invokestatic  #24                 // Method org/hl7/fhir/dstu3/model/Configuration.errorOnAutoCreate:()Z
      10: ifeq          23
      13: new           #25                 // class java/lang/Error
      16: dup
      17: ldc           #38                 // String Attempt to auto-create TimingRepeatComponent.countMax
      19: invokespecial #27                 // Method java/lang/Error."<init>":(Ljava/lang/String;)V
      22: athrow
      23: invokestatic  #28                 // Method org/hl7/fhir/dstu3/model/Configuration.doAutoCreate:()Z
      26: ifeq          40
      29: aload_0
      30: new           #29                 // class org/hl7/fhir/dstu3/model/IntegerType
      33: dup
      34: invokespecial #30                 // Method org/hl7/fhir/dstu3/model/IntegerType."<init>":()V
      37: putfield      #37                 // Field countMax:Lorg/hl7/fhir/dstu3/model/IntegerType;
      40: aload_0
      41: getfield      #37                 // Field countMax:Lorg/hl7/fhir/dstu3/model/IntegerType;
      44: areturn

  public boolean hasCountMaxElement();
    Code:
       0: aload_0
       1: getfield      #37                 // Field countMax:Lorg/hl7/fhir/dstu3/model/IntegerType;
       4: ifnull        21
       7: aload_0
       8: getfield      #37                 // Field countMax:Lorg/hl7/fhir/dstu3/model/IntegerType;
      11: invokevirtual #31                 // Method org/hl7/fhir/dstu3/model/IntegerType.isEmpty:()Z
      14: ifne          21
      17: iconst_1
      18: goto          22
      21: iconst_0
      22: ireturn

  public boolean hasCountMax();
    Code:
       0: aload_0
       1: getfield      #37                 // Field countMax:Lorg/hl7/fhir/dstu3/model/IntegerType;
       4: ifnull        21
       7: aload_0
       8: getfield      #37                 // Field countMax:Lorg/hl7/fhir/dstu3/model/IntegerType;
      11: invokevirtual #31                 // Method org/hl7/fhir/dstu3/model/IntegerType.isEmpty:()Z
      14: ifne          21
      17: iconst_1
      18: goto          22
      21: iconst_0
      22: ireturn

  public org.hl7.fhir.dstu3.model.Timing$TimingRepeatComponent setCountMaxElement(org.hl7.fhir.dstu3.model.IntegerType);
    Code:
       0: aload_0
       1: aload_1
       2: putfield      #37                 // Field countMax:Lorg/hl7/fhir/dstu3/model/IntegerType;
       5: aload_0
       6: areturn

  public int getCountMax();
    Code:
       0: aload_0
       1: getfield      #37                 // Field countMax:Lorg/hl7/fhir/dstu3/model/IntegerType;
       4: ifnull        17
       7: aload_0
       8: getfield      #37                 // Field countMax:Lorg/hl7/fhir/dstu3/model/IntegerType;
      11: invokevirtual #31                 // Method org/hl7/fhir/dstu3/model/IntegerType.isEmpty:()Z
      14: ifeq          21
      17: iconst_0
      18: goto          34
      21: aload_0
      22: getfield      #37                 // Field countMax:Lorg/hl7/fhir/dstu3/model/IntegerType;
      25: invokevirtual #32                 // Method org/hl7/fhir/dstu3/model/IntegerType.getValue:()Ljava/lang/Object;
      28: checkcast     #33                 // class java/lang/Integer
      31: invokevirtual #34                 // Method java/lang/Integer.intValue:()I
      34: ireturn

  public org.hl7.fhir.dstu3.model.Timing$TimingRepeatComponent setCountMax(int);
    Code:
       0: aload_0
       1: getfield      #37                 // Field countMax:Lorg/hl7/fhir/dstu3/model/IntegerType;
       4: ifnonnull     18
       7: aload_0
       8: new           #29                 // class org/hl7/fhir/dstu3/model/IntegerType
      11: dup
      12: invokespecial #30                 // Method org/hl7/fhir/dstu3/model/IntegerType."<init>":()V
      15: putfield      #37                 // Field countMax:Lorg/hl7/fhir/dstu3/model/IntegerType;
      18: aload_0
      19: getfield      #37                 // Field countMax:Lorg/hl7/fhir/dstu3/model/IntegerType;
      22: iload_1
      23: invokestatic  #35                 // Method java/lang/Integer.valueOf:(I)Ljava/lang/Integer;
      26: invokevirtual #36                 // Method org/hl7/fhir/dstu3/model/IntegerType.setValue:(Ljava/lang/Object;)Lorg/hl7/fhir/dstu3/model/PrimitiveType;
      29: pop
      30: aload_0
      31: areturn

  public org.hl7.fhir.dstu3.model.DecimalType getDurationElement();
    Code:
       0: aload_0
       1: getfield      #39                 // Field duration:Lorg/hl7/fhir/dstu3/model/DecimalType;
       4: ifnonnull     40
       7: invokestatic  #24                 // Method org/hl7/fhir/dstu3/model/Configuration.errorOnAutoCreate:()Z
      10: ifeq          23
      13: new           #25                 // class java/lang/Error
      16: dup
      17: ldc           #40                 // String Attempt to auto-create TimingRepeatComponent.duration
      19: invokespecial #27                 // Method java/lang/Error."<init>":(Ljava/lang/String;)V
      22: athrow
      23: invokestatic  #28                 // Method org/hl7/fhir/dstu3/model/Configuration.doAutoCreate:()Z
      26: ifeq          40
      29: aload_0
      30: new           #41                 // class org/hl7/fhir/dstu3/model/DecimalType
      33: dup
      34: invokespecial #42                 // Method org/hl7/fhir/dstu3/model/DecimalType."<init>":()V
      37: putfield      #39                 // Field duration:Lorg/hl7/fhir/dstu3/model/DecimalType;
      40: aload_0
      41: getfield      #39                 // Field duration:Lorg/hl7/fhir/dstu3/model/DecimalType;
      44: areturn

  public boolean hasDurationElement();
    Code:
       0: aload_0
       1: getfield      #39                 // Field duration:Lorg/hl7/fhir/dstu3/model/DecimalType;
       4: ifnull        21
       7: aload_0
       8: getfield      #39                 // Field duration:Lorg/hl7/fhir/dstu3/model/DecimalType;
      11: invokevirtual #43                 // Method org/hl7/fhir/dstu3/model/DecimalType.isEmpty:()Z
      14: ifne          21
      17: iconst_1
      18: goto          22
      21: iconst_0
      22: ireturn

  public boolean hasDuration();
    Code:
       0: aload_0
       1: getfield      #39                 // Field duration:Lorg/hl7/fhir/dstu3/model/DecimalType;
       4: ifnull        21
       7: aload_0
       8: getfield      #39                 // Field duration:Lorg/hl7/fhir/dstu3/model/DecimalType;
      11: invokevirtual #43                 // Method org/hl7/fhir/dstu3/model/DecimalType.isEmpty:()Z
      14: ifne          21
      17: iconst_1
      18: goto          22
      21: iconst_0
      22: ireturn

  public org.hl7.fhir.dstu3.model.Timing$TimingRepeatComponent setDurationElement(org.hl7.fhir.dstu3.model.DecimalType);
    Code:
       0: aload_0
       1: aload_1
       2: putfield      #39                 // Field duration:Lorg/hl7/fhir/dstu3/model/DecimalType;
       5: aload_0
       6: areturn

  public java.math.BigDecimal getDuration();
    Code:
       0: aload_0
       1: getfield      #39                 // Field duration:Lorg/hl7/fhir/dstu3/model/DecimalType;
       4: ifnonnull     11
       7: aconst_null
       8: goto          21
      11: aload_0
      12: getfield      #39                 // Field duration:Lorg/hl7/fhir/dstu3/model/DecimalType;
      15: invokevirtual #44                 // Method org/hl7/fhir/dstu3/model/DecimalType.getValue:()Ljava/lang/Object;
      18: checkcast     #45                 // class java/math/BigDecimal
      21: areturn

  public org.hl7.fhir.dstu3.model.Timing$TimingRepeatComponent setDuration(java.math.BigDecimal);
    Code:
       0: aload_1
       1: ifnonnull     12
       4: aload_0
       5: aconst_null
       6: putfield      #39                 // Field duration:Lorg/hl7/fhir/dstu3/model/DecimalType;
       9: goto          39
      12: aload_0
      13: getfield      #39                 // Field duration:Lorg/hl7/fhir/dstu3/model/DecimalType;
      16: ifnonnull     30
      19: aload_0
      20: new           #41                 // class org/hl7/fhir/dstu3/model/DecimalType
      23: dup
      24: invokespecial #42                 // Method org/hl7/fhir/dstu3/model/DecimalType."<init>":()V
      27: putfield      #39                 // Field duration:Lorg/hl7/fhir/dstu3/model/DecimalType;
      30: aload_0
      31: getfield      #39                 // Field duration:Lorg/hl7/fhir/dstu3/model/DecimalType;
      34: aload_1
      35: invokevirtual #46                 // Method org/hl7/fhir/dstu3/model/DecimalType.setValue:(Ljava/lang/Object;)Lorg/hl7/fhir/dstu3/model/PrimitiveType;
      38: pop
      39: aload_0
      40: areturn

  public org.hl7.fhir.dstu3.model.Timing$TimingRepeatComponent setDuration(long);
    Code:
       0: aload_0
       1: new           #41                 // class org/hl7/fhir/dstu3/model/DecimalType
       4: dup
       5: invokespecial #42                 // Method org/hl7/fhir/dstu3/model/DecimalType."<init>":()V
       8: putfield      #39                 // Field duration:Lorg/hl7/fhir/dstu3/model/DecimalType;
      11: aload_0
      12: getfield      #39                 // Field duration:Lorg/hl7/fhir/dstu3/model/DecimalType;
      15: lload_1
      16: invokevirtual #47                 // Method org/hl7/fhir/dstu3/model/DecimalType.setValue:(J)V
      19: aload_0
      20: areturn

  public org.hl7.fhir.dstu3.model.Timing$TimingRepeatComponent setDuration(double);
    Code:
       0: aload_0
       1: new           #41                 // class org/hl7/fhir/dstu3/model/DecimalType
       4: dup
       5: invokespecial #42                 // Method org/hl7/fhir/dstu3/model/DecimalType."<init>":()V
       8: putfield      #39                 // Field duration:Lorg/hl7/fhir/dstu3/model/DecimalType;
      11: aload_0
      12: getfield      #39                 // Field duration:Lorg/hl7/fhir/dstu3/model/DecimalType;
      15: dload_1
      16: invokevirtual #48                 // Method org/hl7/fhir/dstu3/model/DecimalType.setValue:(D)V
      19: aload_0
      20: areturn

  public org.hl7.fhir.dstu3.model.DecimalType getDurationMaxElement();
    Code:
       0: aload_0
       1: getfield      #49                 // Field durationMax:Lorg/hl7/fhir/dstu3/model/DecimalType;
       4: ifnonnull     40
       7: invokestatic  #24                 // Method org/hl7/fhir/dstu3/model/Configuration.errorOnAutoCreate:()Z
      10: ifeq          23
      13: new           #25                 // class java/lang/Error
      16: dup
      17: ldc           #50                 // String Attempt to auto-create TimingRepeatComponent.durationMax
      19: invokespecial #27                 // Method java/lang/Error."<init>":(Ljava/lang/String;)V
      22: athrow
      23: invokestatic  #28                 // Method org/hl7/fhir/dstu3/model/Configuration.doAutoCreate:()Z
      26: ifeq          40
      29: aload_0
      30: new           #41                 // class org/hl7/fhir/dstu3/model/DecimalType
      33: dup
      34: invokespecial #42                 // Method org/hl7/fhir/dstu3/model/DecimalType."<init>":()V
      37: putfield      #49                 // Field durationMax:Lorg/hl7/fhir/dstu3/model/DecimalType;
      40: aload_0
      41: getfield      #49                 // Field durationMax:Lorg/hl7/fhir/dstu3/model/DecimalType;
      44: areturn

  public boolean hasDurationMaxElement();
    Code:
       0: aload_0
       1: getfield      #49                 // Field durationMax:Lorg/hl7/fhir/dstu3/model/DecimalType;
       4: ifnull        21
       7: aload_0
       8: getfield      #49                 // Field durationMax:Lorg/hl7/fhir/dstu3/model/DecimalType;
      11: invokevirtual #43                 // Method org/hl7/fhir/dstu3/model/DecimalType.isEmpty:()Z
      14: ifne          21
      17: iconst_1
      18: goto          22
      21: iconst_0
      22: ireturn

  public boolean hasDurationMax();
    Code:
       0: aload_0
       1: getfield      #49                 // Field durationMax:Lorg/hl7/fhir/dstu3/model/DecimalType;
       4: ifnull        21
       7: aload_0
       8: getfield      #49                 // Field durationMax:Lorg/hl7/fhir/dstu3/model/DecimalType;
      11: invokevirtual #43                 // Method org/hl7/fhir/dstu3/model/DecimalType.isEmpty:()Z
      14: ifne          21
      17: iconst_1
      18: goto          22
      21: iconst_0
      22: ireturn

  public org.hl7.fhir.dstu3.model.Timing$TimingRepeatComponent setDurationMaxElement(org.hl7.fhir.dstu3.model.DecimalType);
    Code:
       0: aload_0
       1: aload_1
       2: putfield      #49                 // Field durationMax:Lorg/hl7/fhir/dstu3/model/DecimalType;
       5: aload_0
       6: areturn

  public java.math.BigDecimal getDurationMax();
    Code:
       0: aload_0
       1: getfield      #49                 // Field durationMax:Lorg/hl7/fhir/dstu3/model/DecimalType;
       4: ifnonnull     11
       7: aconst_null
       8: goto          21
      11: aload_0
      12: getfield      #49                 // Field durationMax:Lorg/hl7/fhir/dstu3/model/DecimalType;
      15: invokevirtual #44                 // Method org/hl7/fhir/dstu3/model/DecimalType.getValue:()Ljava/lang/Object;
      18: checkcast     #45                 // class java/math/BigDecimal
      21: areturn

  public org.hl7.fhir.dstu3.model.Timing$TimingRepeatComponent setDurationMax(java.math.BigDecimal);
    Code:
       0: aload_1
       1: ifnonnull     12
       4: aload_0
       5: aconst_null
       6: putfield      #49                 // Field durationMax:Lorg/hl7/fhir/dstu3/model/DecimalType;
       9: goto          39
      12: aload_0
      13: getfield      #49                 // Field durationMax:Lorg/hl7/fhir/dstu3/model/DecimalType;
      16: ifnonnull     30
      19: aload_0
      20: new           #41                 // class org/hl7/fhir/dstu3/model/DecimalType
      23: dup
      24: invokespecial #42                 // Method org/hl7/fhir/dstu3/model/DecimalType."<init>":()V
      27: putfield      #49                 // Field durationMax:Lorg/hl7/fhir/dstu3/model/DecimalType;
      30: aload_0
      31: getfield      #49                 // Field durationMax:Lorg/hl7/fhir/dstu3/model/DecimalType;
      34: aload_1
      35: invokevirtual #46                 // Method org/hl7/fhir/dstu3/model/DecimalType.setValue:(Ljava/lang/Object;)Lorg/hl7/fhir/dstu3/model/PrimitiveType;
      38: pop
      39: aload_0
      40: areturn

  public org.hl7.fhir.dstu3.model.Timing$TimingRepeatComponent setDurationMax(long);
    Code:
       0: aload_0
       1: new           #41                 // class org/hl7/fhir/dstu3/model/DecimalType
       4: dup
       5: invokespecial #42                 // Method org/hl7/fhir/dstu3/model/DecimalType."<init>":()V
       8: putfield      #49                 // Field durationMax:Lorg/hl7/fhir/dstu3/model/DecimalType;
      11: aload_0
      12: getfield      #49                 // Field durationMax:Lorg/hl7/fhir/dstu3/model/DecimalType;
      15: lload_1
      16: invokevirtual #47                 // Method org/hl7/fhir/dstu3/model/DecimalType.setValue:(J)V
      19: aload_0
      20: areturn

  public org.hl7.fhir.dstu3.model.Timing$TimingRepeatComponent setDurationMax(double);
    Code:
       0: aload_0
       1: new           #41                 // class org/hl7/fhir/dstu3/model/DecimalType
       4: dup
       5: invokespecial #42                 // Method org/hl7/fhir/dstu3/model/DecimalType."<init>":()V
       8: putfield      #49                 // Field durationMax:Lorg/hl7/fhir/dstu3/model/DecimalType;
      11: aload_0
      12: getfield      #49                 // Field durationMax:Lorg/hl7/fhir/dstu3/model/DecimalType;
      15: dload_1
      16: invokevirtual #48                 // Method org/hl7/fhir/dstu3/model/DecimalType.setValue:(D)V
      19: aload_0
      20: areturn

  public org.hl7.fhir.dstu3.model.Enumeration<org.hl7.fhir.dstu3.model.Timing$UnitsOfTime> getDurationUnitElement();
    Code:
       0: aload_0
       1: getfield      #51                 // Field durationUnit:Lorg/hl7/fhir/dstu3/model/Enumeration;
       4: ifnonnull     47
       7: invokestatic  #24                 // Method org/hl7/fhir/dstu3/model/Configuration.errorOnAutoCreate:()Z
      10: ifeq          23
      13: new           #25                 // class java/lang/Error
      16: dup
      17: ldc           #52                 // String Attempt to auto-create TimingRepeatComponent.durationUnit
      19: invokespecial #27                 // Method java/lang/Error."<init>":(Ljava/lang/String;)V
      22: athrow
      23: invokestatic  #28                 // Method org/hl7/fhir/dstu3/model/Configuration.doAutoCreate:()Z
      26: ifeq          47
      29: aload_0
      30: new           #53                 // class org/hl7/fhir/dstu3/model/Enumeration
      33: dup
      34: new           #54                 // class org/hl7/fhir/dstu3/model/Timing$UnitsOfTimeEnumFactory
      37: dup
      38: invokespecial #55                 // Method org/hl7/fhir/dstu3/model/Timing$UnitsOfTimeEnumFactory."<init>":()V
      41: invokespecial #56                 // Method org/hl7/fhir/dstu3/model/Enumeration."<init>":(Lorg/hl7/fhir/dstu3/model/EnumFactory;)V
      44: putfield      #51                 // Field durationUnit:Lorg/hl7/fhir/dstu3/model/Enumeration;
      47: aload_0
      48: getfield      #51                 // Field durationUnit:Lorg/hl7/fhir/dstu3/model/Enumeration;
      51: areturn

  public boolean hasDurationUnitElement();
    Code:
       0: aload_0
       1: getfield      #51                 // Field durationUnit:Lorg/hl7/fhir/dstu3/model/Enumeration;
       4: ifnull        21
       7: aload_0
       8: getfield      #51                 // Field durationUnit:Lorg/hl7/fhir/dstu3/model/Enumeration;
      11: invokevirtual #57                 // Method org/hl7/fhir/dstu3/model/Enumeration.isEmpty:()Z
      14: ifne          21
      17: iconst_1
      18: goto          22
      21: iconst_0
      22: ireturn

  public boolean hasDurationUnit();
    Code:
       0: aload_0
       1: getfield      #51                 // Field durationUnit:Lorg/hl7/fhir/dstu3/model/Enumeration;
       4: ifnull        21
       7: aload_0
       8: getfield      #51                 // Field durationUnit:Lorg/hl7/fhir/dstu3/model/Enumeration;
      11: invokevirtual #57                 // Method org/hl7/fhir/dstu3/model/Enumeration.isEmpty:()Z
      14: ifne          21
      17: iconst_1
      18: goto          22
      21: iconst_0
      22: ireturn

  public org.hl7.fhir.dstu3.model.Timing$TimingRepeatComponent setDurationUnitElement(org.hl7.fhir.dstu3.model.Enumeration<org.hl7.fhir.dstu3.model.Timing$UnitsOfTime>);
    Code:
       0: aload_0
       1: aload_1
       2: putfield      #51                 // Field durationUnit:Lorg/hl7/fhir/dstu3/model/Enumeration;
       5: aload_0
       6: areturn

  public org.hl7.fhir.dstu3.model.Timing$UnitsOfTime getDurationUnit();
    Code:
       0: aload_0
       1: getfield      #51                 // Field durationUnit:Lorg/hl7/fhir/dstu3/model/Enumeration;
       4: ifnonnull     11
       7: aconst_null
       8: goto          21
      11: aload_0
      12: getfield      #51                 // Field durationUnit:Lorg/hl7/fhir/dstu3/model/Enumeration;
      15: invokevirtual #58                 // Method org/hl7/fhir/dstu3/model/Enumeration.getValue:()Ljava/lang/Object;
      18: checkcast     #59                 // class org/hl7/fhir/dstu3/model/Timing$UnitsOfTime
      21: areturn

  public org.hl7.fhir.dstu3.model.Timing$TimingRepeatComponent setDurationUnit(org.hl7.fhir.dstu3.model.Timing$UnitsOfTime);
    Code:
       0: aload_1
       1: ifnonnull     12
       4: aload_0
       5: aconst_null
       6: putfield      #51                 // Field durationUnit:Lorg/hl7/fhir/dstu3/model/Enumeration;
       9: goto          46
      12: aload_0
      13: getfield      #51                 // Field durationUnit:Lorg/hl7/fhir/dstu3/model/Enumeration;
      16: ifnonnull     37
      19: aload_0
      20: new           #53                 // class org/hl7/fhir/dstu3/model/Enumeration
      23: dup
      24: new           #54                 // class org/hl7/fhir/dstu3/model/Timing$UnitsOfTimeEnumFactory
      27: dup
      28: invokespecial #55                 // Method org/hl7/fhir/dstu3/model/Timing$UnitsOfTimeEnumFactory."<init>":()V
      31: invokespecial #56                 // Method org/hl7/fhir/dstu3/model/Enumeration."<init>":(Lorg/hl7/fhir/dstu3/model/EnumFactory;)V
      34: putfield      #51                 // Field durationUnit:Lorg/hl7/fhir/dstu3/model/Enumeration;
      37: aload_0
      38: getfield      #51                 // Field durationUnit:Lorg/hl7/fhir/dstu3/model/Enumeration;
      41: aload_1
      42: invokevirtual #60                 // Method org/hl7/fhir/dstu3/model/Enumeration.setValue:(Ljava/lang/Object;)Lorg/hl7/fhir/dstu3/model/PrimitiveType;
      45: pop
      46: aload_0
      47: areturn

  public org.hl7.fhir.dstu3.model.IntegerType getFrequencyElement();
    Code:
       0: aload_0
       1: getfield      #61                 // Field frequency:Lorg/hl7/fhir/dstu3/model/IntegerType;
       4: ifnonnull     40
       7: invokestatic  #24                 // Method org/hl7/fhir/dstu3/model/Configuration.errorOnAutoCreate:()Z
      10: ifeq          23
      13: new           #25                 // class java/lang/Error
      16: dup
      17: ldc           #62                 // String Attempt to auto-create TimingRepeatComponent.frequency
      19: invokespecial #27                 // Method java/lang/Error."<init>":(Ljava/lang/String;)V
      22: athrow
      23: invokestatic  #28                 // Method org/hl7/fhir/dstu3/model/Configuration.doAutoCreate:()Z
      26: ifeq          40
      29: aload_0
      30: new           #29                 // class org/hl7/fhir/dstu3/model/IntegerType
      33: dup
      34: invokespecial #30                 // Method org/hl7/fhir/dstu3/model/IntegerType."<init>":()V
      37: putfield      #61                 // Field frequency:Lorg/hl7/fhir/dstu3/model/IntegerType;
      40: aload_0
      41: getfield      #61                 // Field frequency:Lorg/hl7/fhir/dstu3/model/IntegerType;
      44: areturn

  public boolean hasFrequencyElement();
    Code:
       0: aload_0
       1: getfield      #61                 // Field frequency:Lorg/hl7/fhir/dstu3/model/IntegerType;
       4: ifnull        21
       7: aload_0
       8: getfield      #61                 // Field frequency:Lorg/hl7/fhir/dstu3/model/IntegerType;
      11: invokevirtual #31                 // Method org/hl7/fhir/dstu3/model/IntegerType.isEmpty:()Z
      14: ifne          21
      17: iconst_1
      18: goto          22
      21: iconst_0
      22: ireturn

  public boolean hasFrequency();
    Code:
       0: aload_0
       1: getfield      #61                 // Field frequency:Lorg/hl7/fhir/dstu3/model/IntegerType;
       4: ifnull        21
       7: aload_0
       8: getfield      #61                 // Field frequency:Lorg/hl7/fhir/dstu3/model/IntegerType;
      11: invokevirtual #31                 // Method org/hl7/fhir/dstu3/model/IntegerType.isEmpty:()Z
      14: ifne          21
      17: iconst_1
      18: goto          22
      21: iconst_0
      22: ireturn

  public org.hl7.fhir.dstu3.model.Timing$TimingRepeatComponent setFrequencyElement(org.hl7.fhir.dstu3.model.IntegerType);
    Code:
       0: aload_0
       1: aload_1
       2: putfield      #61                 // Field frequency:Lorg/hl7/fhir/dstu3/model/IntegerType;
       5: aload_0
       6: areturn

  public int getFrequency();
    Code:
       0: aload_0
       1: getfield      #61                 // Field frequency:Lorg/hl7/fhir/dstu3/model/IntegerType;
       4: ifnull        17
       7: aload_0
       8: getfield      #61                 // Field frequency:Lorg/hl7/fhir/dstu3/model/IntegerType;
      11: invokevirtual #31                 // Method org/hl7/fhir/dstu3/model/IntegerType.isEmpty:()Z
      14: ifeq          21
      17: iconst_0
      18: goto          34
      21: aload_0
      22: getfield      #61                 // Field frequency:Lorg/hl7/fhir/dstu3/model/IntegerType;
      25: invokevirtual #32                 // Method org/hl7/fhir/dstu3/model/IntegerType.getValue:()Ljava/lang/Object;
      28: checkcast     #33                 // class java/lang/Integer
      31: invokevirtual #34                 // Method java/lang/Integer.intValue:()I
      34: ireturn

  public org.hl7.fhir.dstu3.model.Timing$TimingRepeatComponent setFrequency(int);
    Code:
       0: aload_0
       1: getfield      #61                 // Field frequency:Lorg/hl7/fhir/dstu3/model/IntegerType;
       4: ifnonnull     18
       7: aload_0
       8: new           #29                 // class org/hl7/fhir/dstu3/model/IntegerType
      11: dup
      12: invokespecial #30                 // Method org/hl7/fhir/dstu3/model/IntegerType."<init>":()V
      15: putfield      #61                 // Field frequency:Lorg/hl7/fhir/dstu3/model/IntegerType;
      18: aload_0
      19: getfield      #61                 // Field frequency:Lorg/hl7/fhir/dstu3/model/IntegerType;
      22: iload_1
      23: invokestatic  #35                 // Method java/lang/Integer.valueOf:(I)Ljava/lang/Integer;
      26: invokevirtual #36                 // Method org/hl7/fhir/dstu3/model/IntegerType.setValue:(Ljava/lang/Object;)Lorg/hl7/fhir/dstu3/model/PrimitiveType;
      29: pop
      30: aload_0
      31: areturn

  public org.hl7.fhir.dstu3.model.IntegerType getFrequencyMaxElement();
    Code:
       0: aload_0
       1: getfield      #63                 // Field frequencyMax:Lorg/hl7/fhir/dstu3/model/IntegerType;
       4: ifnonnull     40
       7: invokestatic  #24                 // Method org/hl7/fhir/dstu3/model/Configuration.errorOnAutoCreate:()Z
      10: ifeq          23
      13: new           #25                 // class java/lang/Error
      16: dup
      17: ldc           #64                 // String Attempt to auto-create TimingRepeatComponent.frequencyMax
      19: invokespecial #27                 // Method java/lang/Error."<init>":(Ljava/lang/String;)V
      22: athrow
      23: invokestatic  #28                 // Method org/hl7/fhir/dstu3/model/Configuration.doAutoCreate:()Z
      26: ifeq          40
      29: aload_0
      30: new           #29                 // class org/hl7/fhir/dstu3/model/IntegerType
      33: dup
      34: invokespecial #30                 // Method org/hl7/fhir/dstu3/model/IntegerType."<init>":()V
      37: putfield      #63                 // Field frequencyMax:Lorg/hl7/fhir/dstu3/model/IntegerType;
      40: aload_0
      41: getfield      #63                 // Field frequencyMax:Lorg/hl7/fhir/dstu3/model/IntegerType;
      44: areturn

  public boolean hasFrequencyMaxElement();
    Code:
       0: aload_0
       1: getfield      #63                 // Field frequencyMax:Lorg/hl7/fhir/dstu3/model/IntegerType;
       4: ifnull        21
       7: aload_0
       8: getfield      #63                 // Field frequencyMax:Lorg/hl7/fhir/dstu3/model/IntegerType;
      11: invokevirtual #31                 // Method org/hl7/fhir/dstu3/model/IntegerType.isEmpty:()Z
      14: ifne          21
      17: iconst_1
      18: goto          22
      21: iconst_0
      22: ireturn

  public boolean hasFrequencyMax();
    Code:
       0: aload_0
       1: getfield      #63                 // Field frequencyMax:Lorg/hl7/fhir/dstu3/model/IntegerType;
       4: ifnull        21
       7: aload_0
       8: getfield      #63                 // Field frequencyMax:Lorg/hl7/fhir/dstu3/model/IntegerType;
      11: invokevirtual #31                 // Method org/hl7/fhir/dstu3/model/IntegerType.isEmpty:()Z
      14: ifne          21
      17: iconst_1
      18: goto          22
      21: iconst_0
      22: ireturn

  public org.hl7.fhir.dstu3.model.Timing$TimingRepeatComponent setFrequencyMaxElement(org.hl7.fhir.dstu3.model.IntegerType);
    Code:
       0: aload_0
       1: aload_1
       2: putfield      #63                 // Field frequencyMax:Lorg/hl7/fhir/dstu3/model/IntegerType;
       5: aload_0
       6: areturn

  public int getFrequencyMax();
    Code:
       0: aload_0
       1: getfield      #63                 // Field frequencyMax:Lorg/hl7/fhir/dstu3/model/IntegerType;
       4: ifnull        17
       7: aload_0
       8: getfield      #63                 // Field frequencyMax:Lorg/hl7/fhir/dstu3/model/IntegerType;
      11: invokevirtual #31                 // Method org/hl7/fhir/dstu3/model/IntegerType.isEmpty:()Z
      14: ifeq          21
      17: iconst_0
      18: goto          34
      21: aload_0
      22: getfield      #63                 // Field frequencyMax:Lorg/hl7/fhir/dstu3/model/IntegerType;
      25: invokevirtual #32                 // Method org/hl7/fhir/dstu3/model/IntegerType.getValue:()Ljava/lang/Object;
      28: checkcast     #33                 // class java/lang/Integer
      31: invokevirtual #34                 // Method java/lang/Integer.intValue:()I
      34: ireturn

  public org.hl7.fhir.dstu3.model.Timing$TimingRepeatComponent setFrequencyMax(int);
    Code:
       0: aload_0
       1: getfield      #63                 // Field frequencyMax:Lorg/hl7/fhir/dstu3/model/IntegerType;
       4: ifnonnull     18
       7: aload_0
       8: new           #29                 // class org/hl7/fhir/dstu3/model/IntegerType
      11: dup
      12: invokespecial #30                 // Method org/hl7/fhir/dstu3/model/IntegerType."<init>":()V
      15: putfield      #63                 // Field frequencyMax:Lorg/hl7/fhir/dstu3/model/IntegerType;
      18: aload_0
      19: getfield      #63                 // Field frequencyMax:Lorg/hl7/fhir/dstu3/model/IntegerType;
      22: iload_1
      23: invokestatic  #35                 // Method java/lang/Integer.valueOf:(I)Ljava/lang/Integer;
      26: invokevirtual #36                 // Method org/hl7/fhir/dstu3/model/IntegerType.setValue:(Ljava/lang/Object;)Lorg/hl7/fhir/dstu3/model/PrimitiveType;
      29: pop
      30: aload_0
      31: areturn

  public org.hl7.fhir.dstu3.model.DecimalType getPeriodElement();
    Code:
       0: aload_0
       1: getfield      #65                 // Field period:Lorg/hl7/fhir/dstu3/model/DecimalType;
       4: ifnonnull     40
       7: invokestatic  #24                 // Method org/hl7/fhir/dstu3/model/Configuration.errorOnAutoCreate:()Z
      10: ifeq          23
      13: new           #25                 // class java/lang/Error
      16: dup
      17: ldc           #66                 // String Attempt to auto-create TimingRepeatComponent.period
      19: invokespecial #27                 // Method java/lang/Error."<init>":(Ljava/lang/String;)V
      22: athrow
      23: invokestatic  #28                 // Method org/hl7/fhir/dstu3/model/Configuration.doAutoCreate:()Z
      26: ifeq          40
      29: aload_0
      30: new           #41                 // class org/hl7/fhir/dstu3/model/DecimalType
      33: dup
      34: invokespecial #42                 // Method org/hl7/fhir/dstu3/model/DecimalType."<init>":()V
      37: putfield      #65                 // Field period:Lorg/hl7/fhir/dstu3/model/DecimalType;
      40: aload_0
      41: getfield      #65                 // Field period:Lorg/hl7/fhir/dstu3/model/DecimalType;
      44: areturn

  public boolean hasPeriodElement();
    Code:
       0: aload_0
       1: getfield      #65                 // Field period:Lorg/hl7/fhir/dstu3/model/DecimalType;
       4: ifnull        21
       7: aload_0
       8: getfield      #65                 // Field period:Lorg/hl7/fhir/dstu3/model/DecimalType;
      11: invokevirtual #43                 // Method org/hl7/fhir/dstu3/model/DecimalType.isEmpty:()Z
      14: ifne          21
      17: iconst_1
      18: goto          22
      21: iconst_0
      22: ireturn

  public boolean hasPeriod();
    Code:
       0: aload_0
       1: getfield      #65                 // Field period:Lorg/hl7/fhir/dstu3/model/DecimalType;
       4: ifnull        21
       7: aload_0
       8: getfield      #65                 // Field period:Lorg/hl7/fhir/dstu3/model/DecimalType;
      11: invokevirtual #43                 // Method org/hl7/fhir/dstu3/model/DecimalType.isEmpty:()Z
      14: ifne          21
      17: iconst_1
      18: goto          22
      21: iconst_0
      22: ireturn

  public org.hl7.fhir.dstu3.model.Timing$TimingRepeatComponent setPeriodElement(org.hl7.fhir.dstu3.model.DecimalType);
    Code:
       0: aload_0
       1: aload_1
       2: putfield      #65                 // Field period:Lorg/hl7/fhir/dstu3/model/DecimalType;
       5: aload_0
       6: areturn

  public java.math.BigDecimal getPeriod();
    Code:
       0: aload_0
       1: getfield      #65                 // Field period:Lorg/hl7/fhir/dstu3/model/DecimalType;
       4: ifnonnull     11
       7: aconst_null
       8: goto          21
      11: aload_0
      12: getfield      #65                 // Field period:Lorg/hl7/fhir/dstu3/model/DecimalType;
      15: invokevirtual #44                 // Method org/hl7/fhir/dstu3/model/DecimalType.getValue:()Ljava/lang/Object;
      18: checkcast     #45                 // class java/math/BigDecimal
      21: areturn

  public org.hl7.fhir.dstu3.model.Timing$TimingRepeatComponent setPeriod(java.math.BigDecimal);
    Code:
       0: aload_1
       1: ifnonnull     12
       4: aload_0
       5: aconst_null
       6: putfield      #65                 // Field period:Lorg/hl7/fhir/dstu3/model/DecimalType;
       9: goto          39
      12: aload_0
      13: getfield      #65                 // Field period:Lorg/hl7/fhir/dstu3/model/DecimalType;
      16: ifnonnull     30
      19: aload_0
      20: new           #41                 // class org/hl7/fhir/dstu3/model/DecimalType
      23: dup
      24: invokespecial #42                 // Method org/hl7/fhir/dstu3/model/DecimalType."<init>":()V
      27: putfield      #65                 // Field period:Lorg/hl7/fhir/dstu3/model/DecimalType;
      30: aload_0
      31: getfield      #65                 // Field period:Lorg/hl7/fhir/dstu3/model/DecimalType;
      34: aload_1
      35: invokevirtual #46                 // Method org/hl7/fhir/dstu3/model/DecimalType.setValue:(Ljava/lang/Object;)Lorg/hl7/fhir/dstu3/model/PrimitiveType;
      38: pop
      39: aload_0
      40: areturn

  public org.hl7.fhir.dstu3.model.Timing$TimingRepeatComponent setPeriod(long);
    Code:
       0: aload_0
       1: new           #41                 // class org/hl7/fhir/dstu3/model/DecimalType
       4: dup
       5: invokespecial #42                 // Method org/hl7/fhir/dstu3/model/DecimalType."<init>":()V
       8: putfield      #65                 // Field period:Lorg/hl7/fhir/dstu3/model/DecimalType;
      11: aload_0
      12: getfield      #65                 // Field period:Lorg/hl7/fhir/dstu3/model/DecimalType;
      15: lload_1
      16: invokevirtual #47                 // Method org/hl7/fhir/dstu3/model/DecimalType.setValue:(J)V
      19: aload_0
      20: areturn

  public org.hl7.fhir.dstu3.model.Timing$TimingRepeatComponent setPeriod(double);
    Code:
       0: aload_0
       1: new           #41                 // class org/hl7/fhir/dstu3/model/DecimalType
       4: dup
       5: invokespecial #42                 // Method org/hl7/fhir/dstu3/model/DecimalType."<init>":()V
       8: putfield      #65                 // Field period:Lorg/hl7/fhir/dstu3/model/DecimalType;
      11: aload_0
      12: getfield      #65                 // Field period:Lorg/hl7/fhir/dstu3/model/DecimalType;
      15: dload_1
      16: invokevirtual #48                 // Method org/hl7/fhir/dstu3/model/DecimalType.setValue:(D)V
      19: aload_0
      20: areturn

  public org.hl7.fhir.dstu3.model.DecimalType getPeriodMaxElement();
    Code:
       0: aload_0
       1: getfield      #67                 // Field periodMax:Lorg/hl7/fhir/dstu3/model/DecimalType;
       4: ifnonnull     40
       7: invokestatic  #24                 // Method org/hl7/fhir/dstu3/model/Configuration.errorOnAutoCreate:()Z
      10: ifeq          23
      13: new           #25                 // class java/lang/Error
      16: dup
      17: ldc           #68                 // String Attempt to auto-create TimingRepeatComponent.periodMax
      19: invokespecial #27                 // Method java/lang/Error."<init>":(Ljava/lang/String;)V
      22: athrow
      23: invokestatic  #28                 // Method org/hl7/fhir/dstu3/model/Configuration.doAutoCreate:()Z
      26: ifeq          40
      29: aload_0
      30: new           #41                 // class org/hl7/fhir/dstu3/model/DecimalType
      33: dup
      34: invokespecial #42                 // Method org/hl7/fhir/dstu3/model/DecimalType."<init>":()V
      37: putfield      #67                 // Field periodMax:Lorg/hl7/fhir/dstu3/model/DecimalType;
      40: aload_0
      41: getfield      #67                 // Field periodMax:Lorg/hl7/fhir/dstu3/model/DecimalType;
      44: areturn

  public boolean hasPeriodMaxElement();
    Code:
       0: aload_0
       1: getfield      #67                 // Field periodMax:Lorg/hl7/fhir/dstu3/model/DecimalType;
       4: ifnull        21
       7: aload_0
       8: getfield      #67                 // Field periodMax:Lorg/hl7/fhir/dstu3/model/DecimalType;
      11: invokevirtual #43                 // Method org/hl7/fhir/dstu3/model/DecimalType.isEmpty:()Z
      14: ifne          21
      17: iconst_1
      18: goto          22
      21: iconst_0
      22: ireturn

  public boolean hasPeriodMax();
    Code:
       0: aload_0
       1: getfield      #67                 // Field periodMax:Lorg/hl7/fhir/dstu3/model/DecimalType;
       4: ifnull        21
       7: aload_0
       8: getfield      #67                 // Field periodMax:Lorg/hl7/fhir/dstu3/model/DecimalType;
      11: invokevirtual #43                 // Method org/hl7/fhir/dstu3/model/DecimalType.isEmpty:()Z
      14: ifne          21
      17: iconst_1
      18: goto          22
      21: iconst_0
      22: ireturn

  public org.hl7.fhir.dstu3.model.Timing$TimingRepeatComponent setPeriodMaxElement(org.hl7.fhir.dstu3.model.DecimalType);
    Code:
       0: aload_0
       1: aload_1
       2: putfield      #67                 // Field periodMax:Lorg/hl7/fhir/dstu3/model/DecimalType;
       5: aload_0
       6: areturn

  public java.math.BigDecimal getPeriodMax();
    Code:
       0: aload_0
       1: getfield      #67                 // Field periodMax:Lorg/hl7/fhir/dstu3/model/DecimalType;
       4: ifnonnull     11
       7: aconst_null
       8: goto          21
      11: aload_0
      12: getfield      #67                 // Field periodMax:Lorg/hl7/fhir/dstu3/model/DecimalType;
      15: invokevirtual #44                 // Method org/hl7/fhir/dstu3/model/DecimalType.getValue:()Ljava/lang/Object;
      18: checkcast     #45                 // class java/math/BigDecimal
      21: areturn

  public org.hl7.fhir.dstu3.model.Timing$TimingRepeatComponent setPeriodMax(java.math.BigDecimal);
    Code:
       0: aload_1
       1: ifnonnull     12
       4: aload_0
       5: aconst_null
       6: putfield      #67                 // Field periodMax:Lorg/hl7/fhir/dstu3/model/DecimalType;
       9: goto          39
      12: aload_0
      13: getfield      #67                 // Field periodMax:Lorg/hl7/fhir/dstu3/model/DecimalType;
      16: ifnonnull     30
      19: aload_0
      20: new           #41                 // class org/hl7/fhir/dstu3/model/DecimalType
      23: dup
      24: invokespecial #42                 // Method org/hl7/fhir/dstu3/model/DecimalType."<init>":()V
      27: putfield      #67                 // Field periodMax:Lorg/hl7/fhir/dstu3/model/DecimalType;
      30: aload_0
      31: getfield      #67                 // Field periodMax:Lorg/hl7/fhir/dstu3/model/DecimalType;
      34: aload_1
      35: invokevirtual #46                 // Method org/hl7/fhir/dstu3/model/DecimalType.setValue:(Ljava/lang/Object;)Lorg/hl7/fhir/dstu3/model/PrimitiveType;
      38: pop
      39: aload_0
      40: areturn

  public org.hl7.fhir.dstu3.model.Timing$TimingRepeatComponent setPeriodMax(long);
    Code:
       0: aload_0
       1: new           #41                 // class org/hl7/fhir/dstu3/model/DecimalType
       4: dup
       5: invokespecial #42                 // Method org/hl7/fhir/dstu3/model/DecimalType."<init>":()V
       8: putfield      #67                 // Field periodMax:Lorg/hl7/fhir/dstu3/model/DecimalType;
      11: aload_0
      12: getfield      #67                 // Field periodMax:Lorg/hl7/fhir/dstu3/model/DecimalType;
      15: lload_1
      16: invokevirtual #47                 // Method org/hl7/fhir/dstu3/model/DecimalType.setValue:(J)V
      19: aload_0
      20: areturn

  public org.hl7.fhir.dstu3.model.Timing$TimingRepeatComponent setPeriodMax(double);
    Code:
       0: aload_0
       1: new           #41                 // class org/hl7/fhir/dstu3/model/DecimalType
       4: dup
       5: invokespecial #42                 // Method org/hl7/fhir/dstu3/model/DecimalType."<init>":()V
       8: putfield      #67                 // Field periodMax:Lorg/hl7/fhir/dstu3/model/DecimalType;
      11: aload_0
      12: getfield      #67                 // Field periodMax:Lorg/hl7/fhir/dstu3/model/DecimalType;
      15: dload_1
      16: invokevirtual #48                 // Method org/hl7/fhir/dstu3/model/DecimalType.setValue:(D)V
      19: aload_0
      20: areturn

  public org.hl7.fhir.dstu3.model.Enumeration<org.hl7.fhir.dstu3.model.Timing$UnitsOfTime> getPeriodUnitElement();
    Code:
       0: aload_0
       1: getfield      #69                 // Field periodUnit:Lorg/hl7/fhir/dstu3/model/Enumeration;
       4: ifnonnull     47
       7: invokestatic  #24                 // Method org/hl7/fhir/dstu3/model/Configuration.errorOnAutoCreate:()Z
      10: ifeq          23
      13: new           #25                 // class java/lang/Error
      16: dup
      17: ldc           #70                 // String Attempt to auto-create TimingRepeatComponent.periodUnit
      19: invokespecial #27                 // Method java/lang/Error."<init>":(Ljava/lang/String;)V
      22: athrow
      23: invokestatic  #28                 // Method org/hl7/fhir/dstu3/model/Configuration.doAutoCreate:()Z
      26: ifeq          47
      29: aload_0
      30: new           #53                 // class org/hl7/fhir/dstu3/model/Enumeration
      33: dup
      34: new           #54                 // class org/hl7/fhir/dstu3/model/Timing$UnitsOfTimeEnumFactory
      37: dup
      38: invokespecial #55                 // Method org/hl7/fhir/dstu3/model/Timing$UnitsOfTimeEnumFactory."<init>":()V
      41: invokespecial #56                 // Method org/hl7/fhir/dstu3/model/Enumeration."<init>":(Lorg/hl7/fhir/dstu3/model/EnumFactory;)V
      44: putfield      #69                 // Field periodUnit:Lorg/hl7/fhir/dstu3/model/Enumeration;
      47: aload_0
      48: getfield      #69                 // Field periodUnit:Lorg/hl7/fhir/dstu3/model/Enumeration;
      51: areturn

  public boolean hasPeriodUnitElement();
    Code:
       0: aload_0
       1: getfield      #69                 // Field periodUnit:Lorg/hl7/fhir/dstu3/model/Enumeration;
       4: ifnull        21
       7: aload_0
       8: getfield      #69                 // Field periodUnit:Lorg/hl7/fhir/dstu3/model/Enumeration;
      11: invokevirtual #57                 // Method org/hl7/fhir/dstu3/model/Enumeration.isEmpty:()Z
      14: ifne          21
      17: iconst_1
      18: goto          22
      21: iconst_0
      22: ireturn

  public boolean hasPeriodUnit();
    Code:
       0: aload_0
       1: getfield      #69                 // Field periodUnit:Lorg/hl7/fhir/dstu3/model/Enumeration;
       4: ifnull        21
       7: aload_0
       8: getfield      #69                 // Field periodUnit:Lorg/hl7/fhir/dstu3/model/Enumeration;
      11: invokevirtual #57                 // Method org/hl7/fhir/dstu3/model/Enumeration.isEmpty:()Z
      14: ifne          21
      17: iconst_1
      18: goto          22
      21: iconst_0
      22: ireturn

  public org.hl7.fhir.dstu3.model.Timing$TimingRepeatComponent setPeriodUnitElement(org.hl7.fhir.dstu3.model.Enumeration<org.hl7.fhir.dstu3.model.Timing$UnitsOfTime>);
    Code:
       0: aload_0
       1: aload_1
       2: putfield      #69                 // Field periodUnit:Lorg/hl7/fhir/dstu3/model/Enumeration;
       5: aload_0
       6: areturn

  public org.hl7.fhir.dstu3.model.Timing$UnitsOfTime getPeriodUnit();
    Code:
       0: aload_0
       1: getfield      #69                 // Field periodUnit:Lorg/hl7/fhir/dstu3/model/Enumeration;
       4: ifnonnull     11
       7: aconst_null
       8: goto          21
      11: aload_0
      12: getfield      #69                 // Field periodUnit:Lorg/hl7/fhir/dstu3/model/Enumeration;
      15: invokevirtual #58                 // Method org/hl7/fhir/dstu3/model/Enumeration.getValue:()Ljava/lang/Object;
      18: checkcast     #59                 // class org/hl7/fhir/dstu3/model/Timing$UnitsOfTime
      21: areturn

  public org.hl7.fhir.dstu3.model.Timing$TimingRepeatComponent setPeriodUnit(org.hl7.fhir.dstu3.model.Timing$UnitsOfTime);
    Code:
       0: aload_1
       1: ifnonnull     12
       4: aload_0
       5: aconst_null
       6: putfield      #69                 // Field periodUnit:Lorg/hl7/fhir/dstu3/model/Enumeration;
       9: goto          46
      12: aload_0
      13: getfield      #69                 // Field periodUnit:Lorg/hl7/fhir/dstu3/model/Enumeration;
      16: ifnonnull     37
      19: aload_0
      20: new           #53                 // class org/hl7/fhir/dstu3/model/Enumeration
      23: dup
      24: new           #54                 // class org/hl7/fhir/dstu3/model/Timing$UnitsOfTimeEnumFactory
      27: dup
      28: invokespecial #55                 // Method org/hl7/fhir/dstu3/model/Timing$UnitsOfTimeEnumFactory."<init>":()V
      31: invokespecial #56                 // Method org/hl7/fhir/dstu3/model/Enumeration."<init>":(Lorg/hl7/fhir/dstu3/model/EnumFactory;)V
      34: putfield      #69                 // Field periodUnit:Lorg/hl7/fhir/dstu3/model/Enumeration;
      37: aload_0
      38: getfield      #69                 // Field periodUnit:Lorg/hl7/fhir/dstu3/model/Enumeration;
      41: aload_1
      42: invokevirtual #60                 // Method org/hl7/fhir/dstu3/model/Enumeration.setValue:(Ljava/lang/Object;)Lorg/hl7/fhir/dstu3/model/PrimitiveType;
      45: pop
      46: aload_0
      47: areturn

  public java.util.List<org.hl7.fhir.dstu3.model.Enumeration<org.hl7.fhir.dstu3.model.Timing$DayOfWeek>> getDayOfWeek();
    Code:
       0: aload_0
       1: getfield      #71                 // Field dayOfWeek:Ljava/util/List;
       4: ifnonnull     18
       7: aload_0
       8: new           #72                 // class java/util/ArrayList
      11: dup
      12: invokespecial #73                 // Method java/util/ArrayList."<init>":()V
      15: putfield      #71                 // Field dayOfWeek:Ljava/util/List;
      18: aload_0
      19: getfield      #71                 // Field dayOfWeek:Ljava/util/List;
      22: areturn

  public org.hl7.fhir.dstu3.model.Timing$TimingRepeatComponent setDayOfWeek(java.util.List<org.hl7.fhir.dstu3.model.Enumeration<org.hl7.fhir.dstu3.model.Timing$DayOfWeek>>);
    Code:
       0: aload_0
       1: aload_1
       2: putfield      #71                 // Field dayOfWeek:Ljava/util/List;
       5: aload_0
       6: areturn

  public boolean hasDayOfWeek();
    Code:
       0: aload_0
       1: getfield      #71                 // Field dayOfWeek:Ljava/util/List;
       4: ifnonnull     9
       7: iconst_0
       8: ireturn
       9: aload_0
      10: getfield      #71                 // Field dayOfWeek:Ljava/util/List;
      13: invokeinterface #74,  1           // InterfaceMethod java/util/List.iterator:()Ljava/util/Iterator;
      18: astore_1
      19: aload_1
      20: invokeinterface #75,  1           // InterfaceMethod java/util/Iterator.hasNext:()Z
      25: ifeq          50
      28: aload_1
      29: invokeinterface #76,  1           // InterfaceMethod java/util/Iterator.next:()Ljava/lang/Object;
      34: checkcast     #53                 // class org/hl7/fhir/dstu3/model/Enumeration
      37: astore_2
      38: aload_2
      39: invokevirtual #57                 // Method org/hl7/fhir/dstu3/model/Enumeration.isEmpty:()Z
      42: ifne          47
      45: iconst_1
      46: ireturn
      47: goto          19
      50: iconst_0
      51: ireturn

  public org.hl7.fhir.dstu3.model.Enumeration<org.hl7.fhir.dstu3.model.Timing$DayOfWeek> addDayOfWeekElement();
    Code:
       0: new           #53                 // class org/hl7/fhir/dstu3/model/Enumeration
       3: dup
       4: new           #77                 // class org/hl7/fhir/dstu3/model/Timing$DayOfWeekEnumFactory
       7: dup
       8: invokespecial #78                 // Method org/hl7/fhir/dstu3/model/Timing$DayOfWeekEnumFactory."<init>":()V
      11: invokespecial #56                 // Method org/hl7/fhir/dstu3/model/Enumeration."<init>":(Lorg/hl7/fhir/dstu3/model/EnumFactory;)V
      14: astore_1
      15: aload_0
      16: getfield      #71                 // Field dayOfWeek:Ljava/util/List;
      19: ifnonnull     33
      22: aload_0
      23: new           #72                 // class java/util/ArrayList
      26: dup
      27: invokespecial #73                 // Method java/util/ArrayList."<init>":()V
      30: putfield      #71                 // Field dayOfWeek:Ljava/util/List;
      33: aload_0
      34: getfield      #71                 // Field dayOfWeek:Ljava/util/List;
      37: aload_1
      38: invokeinterface #79,  2           // InterfaceMethod java/util/List.add:(Ljava/lang/Object;)Z
      43: pop
      44: aload_1
      45: areturn

  public org.hl7.fhir.dstu3.model.Timing$TimingRepeatComponent addDayOfWeek(org.hl7.fhir.dstu3.model.Timing$DayOfWeek);
    Code:
       0: new           #53                 // class org/hl7/fhir/dstu3/model/Enumeration
       3: dup
       4: new           #77                 // class org/hl7/fhir/dstu3/model/Timing$DayOfWeekEnumFactory
       7: dup
       8: invokespecial #78                 // Method org/hl7/fhir/dstu3/model/Timing$DayOfWeekEnumFactory."<init>":()V
      11: invokespecial #56                 // Method org/hl7/fhir/dstu3/model/Enumeration."<init>":(Lorg/hl7/fhir/dstu3/model/EnumFactory;)V
      14: astore_2
      15: aload_2
      16: aload_1
      17: invokevirtual #60                 // Method org/hl7/fhir/dstu3/model/Enumeration.setValue:(Ljava/lang/Object;)Lorg/hl7/fhir/dstu3/model/PrimitiveType;
      20: pop
      21: aload_0
      22: getfield      #71                 // Field dayOfWeek:Ljava/util/List;
      25: ifnonnull     39
      28: aload_0
      29: new           #72                 // class java/util/ArrayList
      32: dup
      33: invokespecial #73                 // Method java/util/ArrayList."<init>":()V
      36: putfield      #71                 // Field dayOfWeek:Ljava/util/List;
      39: aload_0
      40: getfield      #71                 // Field dayOfWeek:Ljava/util/List;
      43: aload_2
      44: invokeinterface #79,  2           // InterfaceMethod java/util/List.add:(Ljava/lang/Object;)Z
      49: pop
      50: aload_0
      51: areturn

  public boolean hasDayOfWeek(org.hl7.fhir.dstu3.model.Timing$DayOfWeek);
    Code:
       0: aload_0
       1: getfield      #71                 // Field dayOfWeek:Ljava/util/List;
       4: ifnonnull     9
       7: iconst_0
       8: ireturn
       9: aload_0
      10: getfield      #71                 // Field dayOfWeek:Ljava/util/List;
      13: invokeinterface #74,  1           // InterfaceMethod java/util/List.iterator:()Ljava/util/Iterator;
      18: astore_2
      19: aload_2
      20: invokeinterface #75,  1           // InterfaceMethod java/util/Iterator.hasNext:()Z
      25: ifeq          57
      28: aload_2
      29: invokeinterface #76,  1           // InterfaceMethod java/util/Iterator.next:()Ljava/lang/Object;
      34: checkcast     #53                 // class org/hl7/fhir/dstu3/model/Enumeration
      37: astore_3
      38: aload_3
      39: invokevirtual #58                 // Method org/hl7/fhir/dstu3/model/Enumeration.getValue:()Ljava/lang/Object;
      42: checkcast     #80                 // class org/hl7/fhir/dstu3/model/Timing$DayOfWeek
      45: aload_1
      46: invokevirtual #81                 // Method org/hl7/fhir/dstu3/model/Timing$DayOfWeek.equals:(Ljava/lang/Object;)Z
      49: ifeq          54
      52: iconst_1
      53: ireturn
      54: goto          19
      57: iconst_0
      58: ireturn

  public java.util.List<org.hl7.fhir.dstu3.model.TimeType> getTimeOfDay();
    Code:
       0: aload_0
       1: getfield      #82                 // Field timeOfDay:Ljava/util/List;
       4: ifnonnull     18
       7: aload_0
       8: new           #72                 // class java/util/ArrayList
      11: dup
      12: invokespecial #73                 // Method java/util/ArrayList."<init>":()V
      15: putfield      #82                 // Field timeOfDay:Ljava/util/List;
      18: aload_0
      19: getfield      #82                 // Field timeOfDay:Ljava/util/List;
      22: areturn

  public org.hl7.fhir.dstu3.model.Timing$TimingRepeatComponent setTimeOfDay(java.util.List<org.hl7.fhir.dstu3.model.TimeType>);
    Code:
       0: aload_0
       1: aload_1
       2: putfield      #82                 // Field timeOfDay:Ljava/util/List;
       5: aload_0
       6: areturn

  public boolean hasTimeOfDay();
    Code:
       0: aload_0
       1: getfield      #82                 // Field timeOfDay:Ljava/util/List;
       4: ifnonnull     9
       7: iconst_0
       8: ireturn
       9: aload_0
      10: getfield      #82                 // Field timeOfDay:Ljava/util/List;
      13: invokeinterface #74,  1           // InterfaceMethod java/util/List.iterator:()Ljava/util/Iterator;
      18: astore_1
      19: aload_1
      20: invokeinterface #75,  1           // InterfaceMethod java/util/Iterator.hasNext:()Z
      25: ifeq          50
      28: aload_1
      29: invokeinterface #76,  1           // InterfaceMethod java/util/Iterator.next:()Ljava/lang/Object;
      34: checkcast     #83                 // class org/hl7/fhir/dstu3/model/TimeType
      37: astore_2
      38: aload_2
      39: invokevirtual #84                 // Method org/hl7/fhir/dstu3/model/TimeType.isEmpty:()Z
      42: ifne          47
      45: iconst_1
      46: ireturn
      47: goto          19
      50: iconst_0
      51: ireturn

  public org.hl7.fhir.dstu3.model.TimeType addTimeOfDayElement();
    Code:
       0: new           #83                 // class org/hl7/fhir/dstu3/model/TimeType
       3: dup
       4: invokespecial #85                 // Method org/hl7/fhir/dstu3/model/TimeType."<init>":()V
       7: astore_1
       8: aload_0
       9: getfield      #82                 // Field timeOfDay:Ljava/util/List;
      12: ifnonnull     26
      15: aload_0
      16: new           #72                 // class java/util/ArrayList
      19: dup
      20: invokespecial #73                 // Method java/util/ArrayList."<init>":()V
      23: putfield      #82                 // Field timeOfDay:Ljava/util/List;
      26: aload_0
      27: getfield      #82                 // Field timeOfDay:Ljava/util/List;
      30: aload_1
      31: invokeinterface #79,  2           // InterfaceMethod java/util/List.add:(Ljava/lang/Object;)Z
      36: pop
      37: aload_1
      38: areturn

  public org.hl7.fhir.dstu3.model.Timing$TimingRepeatComponent addTimeOfDay(java.lang.String);
    Code:
       0: new           #83                 // class org/hl7/fhir/dstu3/model/TimeType
       3: dup
       4: invokespecial #85                 // Method org/hl7/fhir/dstu3/model/TimeType."<init>":()V
       7: astore_2
       8: aload_2
       9: aload_1
      10: invokevirtual #86                 // Method org/hl7/fhir/dstu3/model/TimeType.setValue:(Ljava/lang/Object;)Lorg/hl7/fhir/dstu3/model/PrimitiveType;
      13: pop
      14: aload_0
      15: getfield      #82                 // Field timeOfDay:Ljava/util/List;
      18: ifnonnull     32
      21: aload_0
      22: new           #72                 // class java/util/ArrayList
      25: dup
      26: invokespecial #73                 // Method java/util/ArrayList."<init>":()V
      29: putfield      #82                 // Field timeOfDay:Ljava/util/List;
      32: aload_0
      33: getfield      #82                 // Field timeOfDay:Ljava/util/List;
      36: aload_2
      37: invokeinterface #79,  2           // InterfaceMethod java/util/List.add:(Ljava/lang/Object;)Z
      42: pop
      43: aload_0
      44: areturn

  public boolean hasTimeOfDay(java.lang.String);
    Code:
       0: aload_0
       1: getfield      #82                 // Field timeOfDay:Ljava/util/List;
       4: ifnonnull     9
       7: iconst_0
       8: ireturn
       9: aload_0
      10: getfield      #82                 // Field timeOfDay:Ljava/util/List;
      13: invokeinterface #74,  1           // InterfaceMethod java/util/List.iterator:()Ljava/util/Iterator;
      18: astore_2
      19: aload_2
      20: invokeinterface #75,  1           // InterfaceMethod java/util/Iterator.hasNext:()Z
      25: ifeq          57
      28: aload_2
      29: invokeinterface #76,  1           // InterfaceMethod java/util/Iterator.next:()Ljava/lang/Object;
      34: checkcast     #83                 // class org/hl7/fhir/dstu3/model/TimeType
      37: astore_3
      38: aload_3
      39: invokevirtual #87                 // Method org/hl7/fhir/dstu3/model/TimeType.getValue:()Ljava/lang/Object;
      42: checkcast     #88                 // class java/lang/String
      45: aload_1
      46: invokevirtual #89                 // Method java/lang/String.equals:(Ljava/lang/Object;)Z
      49: ifeq          54
      52: iconst_1
      53: ireturn
      54: goto          19
      57: iconst_0
      58: ireturn

  public java.util.List<org.hl7.fhir.dstu3.model.Enumeration<org.hl7.fhir.dstu3.model.Timing$EventTiming>> getWhen();
    Code:
       0: aload_0
       1: getfield      #90                 // Field when:Ljava/util/List;
       4: ifnonnull     18
       7: aload_0
       8: new           #72                 // class java/util/ArrayList
      11: dup
      12: invokespecial #73                 // Method java/util/ArrayList."<init>":()V
      15: putfield      #90                 // Field when:Ljava/util/List;
      18: aload_0
      19: getfield      #90                 // Field when:Ljava/util/List;
      22: areturn

  public org.hl7.fhir.dstu3.model.Timing$TimingRepeatComponent setWhen(java.util.List<org.hl7.fhir.dstu3.model.Enumeration<org.hl7.fhir.dstu3.model.Timing$EventTiming>>);
    Code:
       0: aload_0
       1: aload_1
       2: putfield      #90                 // Field when:Ljava/util/List;
       5: aload_0
       6: areturn

  public boolean hasWhen();
    Code:
       0: aload_0
       1: getfield      #90                 // Field when:Ljava/util/List;
       4: ifnonnull     9
       7: iconst_0
       8: ireturn
       9: aload_0
      10: getfield      #90                 // Field when:Ljava/util/List;
      13: invokeinterface #74,  1           // InterfaceMethod java/util/List.iterator:()Ljava/util/Iterator;
      18: astore_1
      19: aload_1
      20: invokeinterface #75,  1           // InterfaceMethod java/util/Iterator.hasNext:()Z
      25: ifeq          50
      28: aload_1
      29: invokeinterface #76,  1           // InterfaceMethod java/util/Iterator.next:()Ljava/lang/Object;
      34: checkcast     #53                 // class org/hl7/fhir/dstu3/model/Enumeration
      37: astore_2
      38: aload_2
      39: invokevirtual #57                 // Method org/hl7/fhir/dstu3/model/Enumeration.isEmpty:()Z
      42: ifne          47
      45: iconst_1
      46: ireturn
      47: goto          19
      50: iconst_0
      51: ireturn

  public org.hl7.fhir.dstu3.model.Enumeration<org.hl7.fhir.dstu3.model.Timing$EventTiming> addWhenElement();
    Code:
       0: new           #53                 // class org/hl7/fhir/dstu3/model/Enumeration
       3: dup
       4: new           #91                 // class org/hl7/fhir/dstu3/model/Timing$EventTimingEnumFactory
       7: dup
       8: invokespecial #92                 // Method org/hl7/fhir/dstu3/model/Timing$EventTimingEnumFactory."<init>":()V
      11: invokespecial #56                 // Method org/hl7/fhir/dstu3/model/Enumeration."<init>":(Lorg/hl7/fhir/dstu3/model/EnumFactory;)V
      14: astore_1
      15: aload_0
      16: getfield      #90                 // Field when:Ljava/util/List;
      19: ifnonnull     33
      22: aload_0
      23: new           #72                 // class java/util/ArrayList
      26: dup
      27: invokespecial #73                 // Method java/util/ArrayList."<init>":()V
      30: putfield      #90                 // Field when:Ljava/util/List;
      33: aload_0
      34: getfield      #90                 // Field when:Ljava/util/List;
      37: aload_1
      38: invokeinterface #79,  2           // InterfaceMethod java/util/List.add:(Ljava/lang/Object;)Z
      43: pop
      44: aload_1
      45: areturn

  public org.hl7.fhir.dstu3.model.Timing$TimingRepeatComponent addWhen(org.hl7.fhir.dstu3.model.Timing$EventTiming);
    Code:
       0: new           #53                 // class org/hl7/fhir/dstu3/model/Enumeration
       3: dup
       4: new           #91                 // class org/hl7/fhir/dstu3/model/Timing$EventTimingEnumFactory
       7: dup
       8: invokespecial #92                 // Method org/hl7/fhir/dstu3/model/Timing$EventTimingEnumFactory."<init>":()V
      11: invokespecial #56                 // Method org/hl7/fhir/dstu3/model/Enumeration."<init>":(Lorg/hl7/fhir/dstu3/model/EnumFactory;)V
      14: astore_2
      15: aload_2
      16: aload_1
      17: invokevirtual #60                 // Method org/hl7/fhir/dstu3/model/Enumeration.setValue:(Ljava/lang/Object;)Lorg/hl7/fhir/dstu3/model/PrimitiveType;
      20: pop
      21: aload_0
      22: getfield      #90                 // Field when:Ljava/util/List;
      25: ifnonnull     39
      28: aload_0
      29: new           #72                 // class java/util/ArrayList
      32: dup
      33: invokespecial #73                 // Method java/util/ArrayList."<init>":()V
      36: putfield      #90                 // Field when:Ljava/util/List;
      39: aload_0
      40: getfield      #90                 // Field when:Ljava/util/List;
      43: aload_2
      44: invokeinterface #79,  2           // InterfaceMethod java/util/List.add:(Ljava/lang/Object;)Z
      49: pop
      50: aload_0
      51: areturn

  public boolean hasWhen(org.hl7.fhir.dstu3.model.Timing$EventTiming);
    Code:
       0: aload_0
       1: getfield      #90                 // Field when:Ljava/util/List;
       4: ifnonnull     9
       7: iconst_0
       8: ireturn
       9: aload_0
      10: getfield      #90                 // Field when:Ljava/util/List;
      13: invokeinterface #74,  1           // InterfaceMethod java/util/List.iterator:()Ljava/util/Iterator;
      18: astore_2
      19: aload_2
      20: invokeinterface #75,  1           // InterfaceMethod java/util/Iterator.hasNext:()Z
      25: ifeq          57
      28: aload_2
      29: invokeinterface #76,  1           // InterfaceMethod java/util/Iterator.next:()Ljava/lang/Object;
      34: checkcast     #53                 // class org/hl7/fhir/dstu3/model/Enumeration
      37: astore_3
      38: aload_3
      39: invokevirtual #58                 // Method org/hl7/fhir/dstu3/model/Enumeration.getValue:()Ljava/lang/Object;
      42: checkcast     #93                 // class org/hl7/fhir/dstu3/model/Timing$EventTiming
      45: aload_1
      46: invokevirtual #94                 // Method org/hl7/fhir/dstu3/model/Timing$EventTiming.equals:(Ljava/lang/Object;)Z
      49: ifeq          54
      52: iconst_1
      53: ireturn
      54: goto          19
      57: iconst_0
      58: ireturn

  public org.hl7.fhir.dstu3.model.UnsignedIntType getOffsetElement();
    Code:
       0: aload_0
       1: getfield      #95                 // Field offset:Lorg/hl7/fhir/dstu3/model/UnsignedIntType;
       4: ifnonnull     40
       7: invokestatic  #24                 // Method org/hl7/fhir/dstu3/model/Configuration.errorOnAutoCreate:()Z
      10: ifeq          23
      13: new           #25                 // class java/lang/Error
      16: dup
      17: ldc           #96                 // String Attempt to auto-create TimingRepeatComponent.offset
      19: invokespecial #27                 // Method java/lang/Error."<init>":(Ljava/lang/String;)V
      22: athrow
      23: invokestatic  #28                 // Method org/hl7/fhir/dstu3/model/Configuration.doAutoCreate:()Z
      26: ifeq          40
      29: aload_0
      30: new           #97                 // class org/hl7/fhir/dstu3/model/UnsignedIntType
      33: dup
      34: invokespecial #98                 // Method org/hl7/fhir/dstu3/model/UnsignedIntType."<init>":()V
      37: putfield      #95                 // Field offset:Lorg/hl7/fhir/dstu3/model/UnsignedIntType;
      40: aload_0
      41: getfield      #95                 // Field offset:Lorg/hl7/fhir/dstu3/model/UnsignedIntType;
      44: areturn

  public boolean hasOffsetElement();
    Code:
       0: aload_0
       1: getfield      #95                 // Field offset:Lorg/hl7/fhir/dstu3/model/UnsignedIntType;
       4: ifnull        21
       7: aload_0
       8: getfield      #95                 // Field offset:Lorg/hl7/fhir/dstu3/model/UnsignedIntType;
      11: invokevirtual #99                 // Method org/hl7/fhir/dstu3/model/UnsignedIntType.isEmpty:()Z
      14: ifne          21
      17: iconst_1
      18: goto          22
      21: iconst_0
      22: ireturn

  public boolean hasOffset();
    Code:
       0: aload_0
       1: getfield      #95                 // Field offset:Lorg/hl7/fhir/dstu3/model/UnsignedIntType;
       4: ifnull        21
       7: aload_0
       8: getfield      #95                 // Field offset:Lorg/hl7/fhir/dstu3/model/UnsignedIntType;
      11: invokevirtual #99                 // Method org/hl7/fhir/dstu3/model/UnsignedIntType.isEmpty:()Z
      14: ifne          21
      17: iconst_1
      18: goto          22
      21: iconst_0
      22: ireturn

  public org.hl7.fhir.dstu3.model.Timing$TimingRepeatComponent setOffsetElement(org.hl7.fhir.dstu3.model.UnsignedIntType);
    Code:
       0: aload_0
       1: aload_1
       2: putfield      #95                 // Field offset:Lorg/hl7/fhir/dstu3/model/UnsignedIntType;
       5: aload_0
       6: areturn

  public int getOffset();
    Code:
       0: aload_0
       1: getfield      #95                 // Field offset:Lorg/hl7/fhir/dstu3/model/UnsignedIntType;
       4: ifnull        17
       7: aload_0
       8: getfield      #95                 // Field offset:Lorg/hl7/fhir/dstu3/model/UnsignedIntType;
      11: invokevirtual #99                 // Method org/hl7/fhir/dstu3/model/UnsignedIntType.isEmpty:()Z
      14: ifeq          21
      17: iconst_0
      18: goto          34
      21: aload_0
      22: getfield      #95                 // Field offset:Lorg/hl7/fhir/dstu3/model/UnsignedIntType;
      25: invokevirtual #100                // Method org/hl7/fhir/dstu3/model/UnsignedIntType.getValue:()Ljava/lang/Object;
      28: checkcast     #33                 // class java/lang/Integer
      31: invokevirtual #34                 // Method java/lang/Integer.intValue:()I
      34: ireturn

  public org.hl7.fhir.dstu3.model.Timing$TimingRepeatComponent setOffset(int);
    Code:
       0: aload_0
       1: getfield      #95                 // Field offset:Lorg/hl7/fhir/dstu3/model/UnsignedIntType;
       4: ifnonnull     18
       7: aload_0
       8: new           #97                 // class org/hl7/fhir/dstu3/model/UnsignedIntType
      11: dup
      12: invokespecial #98                 // Method org/hl7/fhir/dstu3/model/UnsignedIntType."<init>":()V
      15: putfield      #95                 // Field offset:Lorg/hl7/fhir/dstu3/model/UnsignedIntType;
      18: aload_0
      19: getfield      #95                 // Field offset:Lorg/hl7/fhir/dstu3/model/UnsignedIntType;
      22: iload_1
      23: invokestatic  #35                 // Method java/lang/Integer.valueOf:(I)Ljava/lang/Integer;
      26: invokevirtual #101                // Method org/hl7/fhir/dstu3/model/UnsignedIntType.setValue:(Ljava/lang/Object;)Lorg/hl7/fhir/dstu3/model/PrimitiveType;
      29: pop
      30: aload_0
      31: areturn

  protected void listChildren(java.util.List<org.hl7.fhir.dstu3.model.Property>);
    Code:
       0: aload_0
       1: aload_1
       2: invokespecial #102                // Method org/hl7/fhir/dstu3/model/Element.listChildren:(Ljava/util/List;)V
       5: aload_1
       6: new           #103                // class org/hl7/fhir/dstu3/model/Property
       9: dup
      10: ldc           #104                // String bounds[x]
      12: ldc           #105                // String Duration|Range|Period
      14: ldc           #106                // String Either a duration for the length of the timing schedule, a range of possible length, or outer bounds for start and/or end limits of the timing schedule.
      16: iconst_0
      17: iconst_1
      18: aload_0
      19: getfield      #2                  // Field bounds:Lorg/hl7/fhir/dstu3/model/Type;
      22: invokespecial #107                // Method org/hl7/fhir/dstu3/model/Property."<init>":(Ljava/lang/String;Ljava/lang/String;Ljava/lang/String;IILorg/hl7/fhir/dstu3/model/Base;)V
      25: invokeinterface #79,  2           // InterfaceMethod java/util/List.add:(Ljava/lang/Object;)Z
      30: pop
      31: aload_1
      32: new           #103                // class org/hl7/fhir/dstu3/model/Property
      35: dup
      36: ldc           #108                // String count
      38: ldc           #109                // String integer
      40: ldc           #110                // String A total count of the desired number of repetitions.
      42: iconst_0
      43: iconst_1
      44: aload_0
      45: getfield      #23                 // Field count:Lorg/hl7/fhir/dstu3/model/IntegerType;
      48: invokespecial #107                // Method org/hl7/fhir/dstu3/model/Property."<init>":(Ljava/lang/String;Ljava/lang/String;Ljava/lang/String;IILorg/hl7/fhir/dstu3/model/Base;)V
      51: invokeinterface #79,  2           // InterfaceMethod java/util/List.add:(Ljava/lang/Object;)Z
      56: pop
      57: aload_1
      58: new           #103                // class org/hl7/fhir/dstu3/model/Property
      61: dup
      62: ldc           #111                // String countMax
      64: ldc           #109                // String integer
      66: ldc           #112                // String A maximum value for the count of the desired repetitions (e.g. do something 6-8 times).
      68: iconst_0
      69: iconst_1
      70: aload_0
      71: getfield      #37                 // Field countMax:Lorg/hl7/fhir/dstu3/model/IntegerType;
      74: invokespecial #107                // Method org/hl7/fhir/dstu3/model/Property."<init>":(Ljava/lang/String;Ljava/lang/String;Ljava/lang/String;IILorg/hl7/fhir/dstu3/model/Base;)V
      77: invokeinterface #79,  2           // InterfaceMethod java/util/List.add:(Ljava/lang/Object;)Z
      82: pop
      83: aload_1
      84: new           #103                // class org/hl7/fhir/dstu3/model/Property
      87: dup
      88: ldc           #113                // String duration
      90: ldc           #114                // String decimal
      92: ldc           #115                // String How long this thing happens for when it happens.
      94: iconst_0
      95: iconst_1
      96: aload_0
      97: getfield      #39                 // Field duration:Lorg/hl7/fhir/dstu3/model/DecimalType;
     100: invokespecial #107                // Method org/hl7/fhir/dstu3/model/Property."<init>":(Ljava/lang/String;Ljava/lang/String;Ljava/lang/String;IILorg/hl7/fhir/dstu3/model/Base;)V
     103: invokeinterface #79,  2           // InterfaceMethod java/util/List.add:(Ljava/lang/Object;)Z
     108: pop
     109: aload_1
     110: new           #103                // class org/hl7/fhir/dstu3/model/Property
     113: dup
     114: ldc           #116                // String durationMax
     116: ldc           #114                // String decimal
     118: ldc           #117                // String The upper limit of how long this thing happens for when it happens.
     120: iconst_0
     121: iconst_1
     122: aload_0
     123: getfield      #49                 // Field durationMax:Lorg/hl7/fhir/dstu3/model/DecimalType;
     126: invokespecial #107                // Method org/hl7/fhir/dstu3/model/Property."<init>":(Ljava/lang/String;Ljava/lang/String;Ljava/lang/String;IILorg/hl7/fhir/dstu3/model/Base;)V
     129: invokeinterface #79,  2           // InterfaceMethod java/util/List.add:(Ljava/lang/Object;)Z
     134: pop
     135: aload_1
     136: new           #103                // class org/hl7/fhir/dstu3/model/Property
     139: dup
     140: ldc           #118                // String durationUnit
     142: ldc           #119                // String code
     144: ldc           #120                // String The units of time for the duration, in UCUM units.
     146: iconst_0
     147: iconst_1
     148: aload_0
     149: getfield      #51                 // Field durationUnit:Lorg/hl7/fhir/dstu3/model/Enumeration;
     152: invokespecial #107                // Method org/hl7/fhir/dstu3/model/Property."<init>":(Ljava/lang/String;Ljava/lang/String;Ljava/lang/String;IILorg/hl7/fhir/dstu3/model/Base;)V
     155: invokeinterface #79,  2           // InterfaceMethod java/util/List.add:(Ljava/lang/Object;)Z
     160: pop
     161: aload_1
     162: new           #103                // class org/hl7/fhir/dstu3/model/Property
     165: dup
     166: ldc           #121                // String frequency
     168: ldc           #109                // String integer
     170: ldc           #122                // String The number of times to repeat the action within the specified period / period range (i.e. both period and periodMax provided).
     172: iconst_0
     173: iconst_1
     174: aload_0
     175: getfield      #61                 // Field frequency:Lorg/hl7/fhir/dstu3/model/IntegerType;
     178: invokespecial #107                // Method org/hl7/fhir/dstu3/model/Property."<init>":(Ljava/lang/String;Ljava/lang/String;Ljava/lang/String;IILorg/hl7/fhir/dstu3/model/Base;)V
     181: invokeinterface #79,  2           // InterfaceMethod java/util/List.add:(Ljava/lang/Object;)Z
     186: pop
     187: aload_1
     188: new           #103                // class org/hl7/fhir/dstu3/model/Property
     191: dup
     192: ldc           #123                // String frequencyMax
     194: ldc           #109                // String integer
     196: ldc           #124                // String If present, indicates that the frequency is a range - so to repeat between [frequency] and [frequencyMax] times within the period or period range.
     198: iconst_0
     199: iconst_1
     200: aload_0
     201: getfield      #63                 // Field frequencyMax:Lorg/hl7/fhir/dstu3/model/IntegerType;
     204: invokespecial #107                // Method org/hl7/fhir/dstu3/model/Property."<init>":(Ljava/lang/String;Ljava/lang/String;Ljava/lang/String;IILorg/hl7/fhir/dstu3/model/Base;)V
     207: invokeinterface #79,  2           // InterfaceMethod java/util/List.add:(Ljava/lang/Object;)Z
     212: pop
     213: aload_1
     214: new           #103                // class org/hl7/fhir/dstu3/model/Property
     217: dup
     218: ldc           #125                // String period
     220: ldc           #114                // String decimal
     222: ldc           #126                // String Indicates the duration of time over which repetitions are to occur; e.g. to express \"3 times per day\", 3 would be the frequency and \"1 day\" would be the period.
     224: iconst_0
     225: iconst_1
     226: aload_0
     227: getfield      #65                 // Field period:Lorg/hl7/fhir/dstu3/model/DecimalType;
     230: invokespecial #107                // Method org/hl7/fhir/dstu3/model/Property."<init>":(Ljava/lang/String;Ljava/lang/String;Ljava/lang/String;IILorg/hl7/fhir/dstu3/model/Base;)V
     233: invokeinterface #79,  2           // InterfaceMethod java/util/List.add:(Ljava/lang/Object;)Z
     238: pop
     239: aload_1
     240: new           #103                // class org/hl7/fhir/dstu3/model/Property
     243: dup
     244: ldc           #127                // String periodMax
     246: ldc           #114                // String decimal
     248: ldc           #128                // String If present, indicates that the period is a range from [period] to [periodMax], allowing expressing concepts such as \"do this once every 3-5 days.
     250: iconst_0
     251: iconst_1
     252: aload_0
     253: getfield      #67                 // Field periodMax:Lorg/hl7/fhir/dstu3/model/DecimalType;
     256: invokespecial #107                // Method org/hl7/fhir/dstu3/model/Property."<init>":(Ljava/lang/String;Ljava/lang/String;Ljava/lang/String;IILorg/hl7/fhir/dstu3/model/Base;)V
     259: invokeinterface #79,  2           // InterfaceMethod java/util/List.add:(Ljava/lang/Object;)Z
     264: pop
     265: aload_1
     266: new           #103                // class org/hl7/fhir/dstu3/model/Property
     269: dup
     270: ldc           #129                // String periodUnit
     272: ldc           #119                // String code
     274: ldc           #130                // String The units of time for the period in UCUM units.
     276: iconst_0
     277: iconst_1
     278: aload_0
     279: getfield      #69                 // Field periodUnit:Lorg/hl7/fhir/dstu3/model/Enumeration;
     282: invokespecial #107                // Method org/hl7/fhir/dstu3/model/Property."<init>":(Ljava/lang/String;Ljava/lang/String;Ljava/lang/String;IILorg/hl7/fhir/dstu3/model/Base;)V
     285: invokeinterface #79,  2           // InterfaceMethod java/util/List.add:(Ljava/lang/Object;)Z
     290: pop
     291: aload_1
     292: new           #103                // class org/hl7/fhir/dstu3/model/Property
     295: dup
     296: ldc           #131                // String dayOfWeek
     298: ldc           #119                // String code
     300: ldc           #132                // String If one or more days of week is provided, then the action happens only on the specified day(s).
     302: iconst_0
     303: ldc           #133                // int 2147483647
     305: aload_0
     306: getfield      #71                 // Field dayOfWeek:Ljava/util/List;
     309: invokespecial #134                // Method org/hl7/fhir/dstu3/model/Property."<init>":(Ljava/lang/String;Ljava/lang/String;Ljava/lang/String;IILjava/util/List;)V
     312: invokeinterface #79,  2           // InterfaceMethod java/util/List.add:(Ljava/lang/Object;)Z
     317: pop
     318: aload_1
     319: new           #103                // class org/hl7/fhir/dstu3/model/Property
     322: dup
     323: ldc           #135                // String timeOfDay
     325: ldc           #136                // String time
     327: ldc           #137                // String Specified time of day for action to take place.
     329: iconst_0
     330: ldc           #133                // int 2147483647
     332: aload_0
     333: getfield      #82                 // Field timeOfDay:Ljava/util/List;
     336: invokespecial #134                // Method org/hl7/fhir/dstu3/model/Property."<init>":(Ljava/lang/String;Ljava/lang/String;Ljava/lang/String;IILjava/util/List;)V
     339: invokeinterface #79,  2           // InterfaceMethod java/util/List.add:(Ljava/lang/Object;)Z
     344: pop
     345: aload_1
     346: new           #103                // class org/hl7/fhir/dstu3/model/Property
     349: dup
     350: ldc           #138                // String when
     352: ldc           #119                // String code
     354: ldc           #139                // String Real world events that the occurrence of the event should be tied to.
     356: iconst_0
     357: ldc           #133                // int 2147483647
     359: aload_0
     360: getfield      #90                 // Field when:Ljava/util/List;
     363: invokespecial #134                // Method org/hl7/fhir/dstu3/model/Property."<init>":(Ljava/lang/String;Ljava/lang/String;Ljava/lang/String;IILjava/util/List;)V
     366: invokeinterface #79,  2           // InterfaceMethod java/util/List.add:(Ljava/lang/Object;)Z
     371: pop
     372: aload_1
     373: new           #103                // class org/hl7/fhir/dstu3/model/Property
     376: dup
     377: ldc           #140                // String offset
     379: ldc           #141                // String unsignedInt
     381: ldc           #142                // String The number of minutes from the event. If the event code does not indicate whether the minutes is before or after the event, then the offset is assumed to be after the event.
     383: iconst_0
     384: iconst_1
     385: aload_0
     386: getfield      #95                 // Field offset:Lorg/hl7/fhir/dstu3/model/UnsignedIntType;
     389: invokespecial #107                // Method org/hl7/fhir/dstu3/model/Property."<init>":(Ljava/lang/String;Ljava/lang/String;Ljava/lang/String;IILorg/hl7/fhir/dstu3/model/Base;)V
     392: invokeinterface #79,  2           // InterfaceMethod java/util/List.add:(Ljava/lang/Object;)Z
     397: pop
     398: return

  public org.hl7.fhir.dstu3.model.Property getNamedProperty(int, java.lang.String, boolean) throws org.hl7.fhir.exceptions.FHIRException;
    Code:
       0: iload_1
       1: lookupswitch  { // 19
           -1992012396: 304
           -1935429320: 344
           -1383205195: 184
           -1149635157: 164
           -1043481386: 244
           -1019779949: 527
           -1001768056: 224
            -991726143: 404
            -730552025: 464
            -478083280: 324
            -372044331: 284
            -189193367: 204
             -70023844: 364
               3648314: 506
              21434232: 485
              94851343: 264
             384367333: 444
             566580195: 424
            1273846376: 384
               default: 547
          }
     164: new           #103                // class org/hl7/fhir/dstu3/model/Property
     167: dup
     168: ldc           #104                // String bounds[x]
     170: ldc           #105                // String Duration|Range|Period
     172: ldc           #106                // String Either a duration for the length of the timing schedule, a range of possible length, or outer bounds for start and/or end limits of the timing schedule.
     174: iconst_0
     175: iconst_1
     176: aload_0
     177: getfield      #2                  // Field bounds:Lorg/hl7/fhir/dstu3/model/Type;
     180: invokespecial #107                // Method org/hl7/fhir/dstu3/model/Property."<init>":(Ljava/lang/String;Ljava/lang/String;Ljava/lang/String;IILorg/hl7/fhir/dstu3/model/Base;)V
     183: areturn
     184: new           #103                // class org/hl7/fhir/dstu3/model/Property
     187: dup
     188: ldc           #104                // String bounds[x]
     190: ldc           #105                // String Duration|Range|Period
     192: ldc           #106                // String Either a duration for the length of the timing schedule, a range of possible length, or outer bounds for start and/or end limits of the timing schedule.
     194: iconst_0
     195: iconst_1
     196: aload_0
     197: getfield      #2                  // Field bounds:Lorg/hl7/fhir/dstu3/model/Type;
     200: invokespecial #107                // Method org/hl7/fhir/dstu3/model/Property."<init>":(Ljava/lang/String;Ljava/lang/String;Ljava/lang/String;IILorg/hl7/fhir/dstu3/model/Base;)V
     203: areturn
     204: new           #103                // class org/hl7/fhir/dstu3/model/Property
     207: dup
     208: ldc           #104                // String bounds[x]
     210: ldc           #105                // String Duration|Range|Period
     212: ldc           #106                // String Either a duration for the length of the timing schedule, a range of possible length, or outer bounds for start and/or end limits of the timing schedule.
     214: iconst_0
     215: iconst_1
     216: aload_0
     217: getfield      #2                  // Field bounds:Lorg/hl7/fhir/dstu3/model/Type;
     220: invokespecial #107                // Method org/hl7/fhir/dstu3/model/Property."<init>":(Ljava/lang/String;Ljava/lang/String;Ljava/lang/String;IILorg/hl7/fhir/dstu3/model/Base;)V
     223: areturn
     224: new           #103                // class org/hl7/fhir/dstu3/model/Property
     227: dup
     228: ldc           #104                // String bounds[x]
     230: ldc           #105                // String Duration|Range|Period
     232: ldc           #106                // String Either a duration for the length of the timing schedule, a range of possible length, or outer bounds for start and/or end limits of the timing schedule.
     234: iconst_0
     235: iconst_1
     236: aload_0
     237: getfield      #2                  // Field bounds:Lorg/hl7/fhir/dstu3/model/Type;
     240: invokespecial #107                // Method org/hl7/fhir/dstu3/model/Property."<init>":(Ljava/lang/String;Ljava/lang/String;Ljava/lang/String;IILorg/hl7/fhir/dstu3/model/Base;)V
     243: areturn
     244: new           #103                // class org/hl7/fhir/dstu3/model/Property
     247: dup
     248: ldc           #104                // String bounds[x]
     250: ldc           #105                // String Duration|Range|Period
     252: ldc           #106                // String Either a duration for the length of the timing schedule, a range of possible length, or outer bounds for start and/or end limits of the timing schedule.
     254: iconst_0
     255: iconst_1
     256: aload_0
     257: getfield      #2                  // Field bounds:Lorg/hl7/fhir/dstu3/model/Type;
     260: invokespecial #107                // Method org/hl7/fhir/dstu3/model/Property."<init>":(Ljava/lang/String;Ljava/lang/String;Ljava/lang/String;IILorg/hl7/fhir/dstu3/model/Base;)V
     263: areturn
     264: new           #103                // class org/hl7/fhir/dstu3/model/Property
     267: dup
     268: ldc           #108                // String count
     270: ldc           #109                // String integer
     272: ldc           #110                // String A total count of the desired number of repetitions.
     274: iconst_0
     275: iconst_1
     276: aload_0
     277: getfield      #23                 // Field count:Lorg/hl7/fhir/dstu3/model/IntegerType;
     280: invokespecial #107                // Method org/hl7/fhir/dstu3/model/Property."<init>":(Ljava/lang/String;Ljava/lang/String;Ljava/lang/String;IILorg/hl7/fhir/dstu3/model/Base;)V
     283: areturn
     284: new           #103                // class org/hl7/fhir/dstu3/model/Property
     287: dup
     288: ldc           #111                // String countMax
     290: ldc           #109                // String integer
     292: ldc           #112                // String A maximum value for the count of the desired repetitions (e.g. do something 6-8 times).
     294: iconst_0
     295: iconst_1
     296: aload_0
     297: getfield      #37                 // Field countMax:Lorg/hl7/fhir/dstu3/model/IntegerType;
     300: invokespecial #107                // Method org/hl7/fhir/dstu3/model/Property."<init>":(Ljava/lang/String;Ljava/lang/String;Ljava/lang/String;IILorg/hl7/fhir/dstu3/model/Base;)V
     303: areturn
     304: new           #103                // class org/hl7/fhir/dstu3/model/Property
     307: dup
     308: ldc           #113                // String duration
     310: ldc           #114                // String decimal
     312: ldc           #115                // String How long this thing happens for when it happens.
     314: iconst_0
     315: iconst_1
     316: aload_0
     317: getfield      #39                 // Field duration:Lorg/hl7/fhir/dstu3/model/DecimalType;
     320: invokespecial #107                // Method org/hl7/fhir/dstu3/model/Property."<init>":(Ljava/lang/String;Ljava/lang/String;Ljava/lang/String;IILorg/hl7/fhir/dstu3/model/Base;)V
     323: areturn
     324: new           #103                // class org/hl7/fhir/dstu3/model/Property
     327: dup
     328: ldc           #116                // String durationMax
     330: ldc           #114                // String decimal
     332: ldc           #117                // String The upper limit of how long this thing happens for when it happens.
     334: iconst_0
     335: iconst_1
     336: aload_0
     337: getfield      #49                 // Field durationMax:Lorg/hl7/fhir/dstu3/model/DecimalType;
     340: invokespecial #107                // Method org/hl7/fhir/dstu3/model/Property."<init>":(Ljava/lang/String;Ljava/lang/String;Ljava/lang/String;IILorg/hl7/fhir/dstu3/model/Base;)V
     343: areturn
     344: new           #103                // class org/hl7/fhir/dstu3/model/Property
     347: dup
     348: ldc           #118                // String durationUnit
     350: ldc           #119                // String code
     352: ldc           #120                // String The units of time for the duration, in UCUM units.
     354: iconst_0
     355: iconst_1
     356: aload_0
     357: getfield      #51                 // Field durationUnit:Lorg/hl7/fhir/dstu3/model/Enumeration;
     360: invokespecial #107                // Method org/hl7/fhir/dstu3/model/Property."<init>":(Ljava/lang/String;Ljava/lang/String;Ljava/lang/String;IILorg/hl7/fhir/dstu3/model/Base;)V
     363: areturn
     364: new           #103                // class org/hl7/fhir/dstu3/model/Property
     367: dup
     368: ldc           #121                // String frequency
     370: ldc           #109                // String integer
     372: ldc           #122                // String The number of times to repeat the action within the specified period / period range (i.e. both period and periodMax provided).
     374: iconst_0
     375: iconst_1
     376: aload_0
     377: getfield      #61                 // Field frequency:Lorg/hl7/fhir/dstu3/model/IntegerType;
     380: invokespecial #107                // Method org/hl7/fhir/dstu3/model/Property."<init>":(Ljava/lang/String;Ljava/lang/String;Ljava/lang/String;IILorg/hl7/fhir/dstu3/model/Base;)V
     383: areturn
     384: new           #103                // class org/hl7/fhir/dstu3/model/Property
     387: dup
     388: ldc           #123                // String frequencyMax
     390: ldc           #109                // String integer
     392: ldc           #124                // String If present, indicates that the frequency is a range - so to repeat between [frequency] and [frequencyMax] times within the period or period range.
     394: iconst_0
     395: iconst_1
     396: aload_0
     397: getfield      #63                 // Field frequencyMax:Lorg/hl7/fhir/dstu3/model/IntegerType;
     400: invokespecial #107                // Method org/hl7/fhir/dstu3/model/Property."<init>":(Ljava/lang/String;Ljava/lang/String;Ljava/lang/String;IILorg/hl7/fhir/dstu3/model/Base;)V
     403: areturn
     404: new           #103                // class org/hl7/fhir/dstu3/model/Property
     407: dup
     408: ldc           #125                // String period
     410: ldc           #114                // String decimal
     412: ldc           #126                // String Indicates the duration of time over which repetitions are to occur; e.g. to express \"3 times per day\", 3 would be the frequency and \"1 day\" would be the period.
     414: iconst_0
     415: iconst_1
     416: aload_0
     417: getfield      #65                 // Field period:Lorg/hl7/fhir/dstu3/model/DecimalType;
     420: invokespecial #107                // Method org/hl7/fhir/dstu3/model/Property."<init>":(Ljava/lang/String;Ljava/lang/String;Ljava/lang/String;IILorg/hl7/fhir/dstu3/model/Base;)V
     423: areturn
     424: new           #103                // class org/hl7/fhir/dstu3/model/Property
     427: dup
     428: ldc           #127                // String periodMax
     430: ldc           #114                // String decimal
     432: ldc           #128                // String If present, indicates that the period is a range from [period] to [periodMax], allowing expressing concepts such as \"do this once every 3-5 days.
     434: iconst_0
     435: iconst_1
     436: aload_0
     437: getfield      #67                 // Field periodMax:Lorg/hl7/fhir/dstu3/model/DecimalType;
     440: invokespecial #107                // Method org/hl7/fhir/dstu3/model/Property."<init>":(Ljava/lang/String;Ljava/lang/String;Ljava/lang/String;IILorg/hl7/fhir/dstu3/model/Base;)V
     443: areturn
     444: new           #103                // class org/hl7/fhir/dstu3/model/Property
     447: dup
     448: ldc           #129                // String periodUnit
     450: ldc           #119                // String code
     452: ldc           #130                // String The units of time for the period in UCUM units.
     454: iconst_0
     455: iconst_1
     456: aload_0
     457: getfield      #69                 // Field periodUnit:Lorg/hl7/fhir/dstu3/model/Enumeration;
     460: invokespecial #107                // Method org/hl7/fhir/dstu3/model/Property."<init>":(Ljava/lang/String;Ljava/lang/String;Ljava/lang/String;IILorg/hl7/fhir/dstu3/model/Base;)V
     463: areturn
     464: new           #103                // class org/hl7/fhir/dstu3/model/Property
     467: dup
     468: ldc           #131                // String dayOfWeek
     470: ldc           #119                // String code
     472: ldc           #132                // String If one or more days of week is provided, then the action happens only on the specified day(s).
     474: iconst_0
     475: ldc           #133                // int 2147483647
     477: aload_0
     478: getfield      #71                 // Field dayOfWeek:Ljava/util/List;
     481: invokespecial #134                // Method org/hl7/fhir/dstu3/model/Property."<init>":(Ljava/lang/String;Ljava/lang/String;Ljava/lang/String;IILjava/util/List;)V
     484: areturn
     485: new           #103                // class org/hl7/fhir/dstu3/model/Property
     488: dup
     489: ldc           #135                // String timeOfDay
     491: ldc           #136                // String time
     493: ldc           #137                // String Specified time of day for action to take place.
     495: iconst_0
     496: ldc           #133                // int 2147483647
     498: aload_0
     499: getfield      #82                 // Field timeOfDay:Ljava/util/List;
     502: invokespecial #134                // Method org/hl7/fhir/dstu3/model/Property."<init>":(Ljava/lang/String;Ljava/lang/String;Ljava/lang/String;IILjava/util/List;)V
     505: areturn
     506: new           #103                // class org/hl7/fhir/dstu3/model/Property
     509: dup
     510: ldc           #138                // String when
     512: ldc           #119                // String code
     514: ldc           #139                // String Real world events that the occurrence of the event should be tied to.
     516: iconst_0
     517: ldc           #133                // int 2147483647
     519: aload_0
     520: getfield      #90                 // Field when:Ljava/util/List;
     523: invokespecial #134                // Method org/hl7/fhir/dstu3/model/Property."<init>":(Ljava/lang/String;Ljava/lang/String;Ljava/lang/String;IILjava/util/List;)V
     526: areturn
     527: new           #103                // class org/hl7/fhir/dstu3/model/Property
     530: dup
     531: ldc           #140                // String offset
     533: ldc           #141                // String unsignedInt
     535: ldc           #142                // String The number of minutes from the event. If the event code does not indicate whether the minutes is before or after the event, then the offset is assumed to be after the event.
     537: iconst_0
     538: iconst_1
     539: aload_0
     540: getfield      #95                 // Field offset:Lorg/hl7/fhir/dstu3/model/UnsignedIntType;
     543: invokespecial #107                // Method org/hl7/fhir/dstu3/model/Property."<init>":(Ljava/lang/String;Ljava/lang/String;Ljava/lang/String;IILorg/hl7/fhir/dstu3/model/Base;)V
     546: areturn
     547: aload_0
     548: iload_1
     549: aload_2
     550: iload_3
     551: invokespecial #143                // Method org/hl7/fhir/dstu3/model/Element.getNamedProperty:(ILjava/lang/String;Z)Lorg/hl7/fhir/dstu3/model/Property;
     554: areturn

  public org.hl7.fhir.dstu3.model.Base[] getProperty(int, java.lang.String, boolean) throws org.hl7.fhir.exceptions.FHIRException;
    Code:
       0: iload_1
       1: lookupswitch  { // 15
           -1992012396: 210
           -1935429320: 262
           -1383205195: 132
           -1019779949: 535
            -991726143: 340
            -730552025: 418
            -478083280: 236
            -372044331: 184
             -70023844: 288
               3648314: 496
              21434232: 457
              94851343: 158
             384367333: 392
             566580195: 366
            1273846376: 314
               default: 561
          }
     132: aload_0
     133: getfield      #2                  // Field bounds:Lorg/hl7/fhir/dstu3/model/Type;
     136: ifnonnull     146
     139: iconst_0
     140: anewarray     #144                // class org/hl7/fhir/dstu3/model/Base
     143: goto          157
     146: iconst_1
     147: anewarray     #144                // class org/hl7/fhir/dstu3/model/Base
     150: dup
     151: iconst_0
     152: aload_0
     153: getfield      #2                  // Field bounds:Lorg/hl7/fhir/dstu3/model/Type;
     156: aastore
     157: areturn
     158: aload_0
     159: getfield      #23                 // Field count:Lorg/hl7/fhir/dstu3/model/IntegerType;
     162: ifnonnull     172
     165: iconst_0
     166: anewarray     #144                // class org/hl7/fhir/dstu3/model/Base
     169: goto          183
     172: iconst_1
     173: anewarray     #144                // class org/hl7/fhir/dstu3/model/Base
     176: dup
     177: iconst_0
     178: aload_0
     179: getfield      #23                 // Field count:Lorg/hl7/fhir/dstu3/model/IntegerType;
     182: aastore
     183: areturn
     184: aload_0
     185: getfield      #37                 // Field countMax:Lorg/hl7/fhir/dstu3/model/IntegerType;
     188: ifnonnull     198
     191: iconst_0
     192: anewarray     #144                // class org/hl7/fhir/dstu3/model/Base
     195: goto          209
     198: iconst_1
     199: anewarray     #144                // class org/hl7/fhir/dstu3/model/Base
     202: dup
     203: iconst_0
     204: aload_0
     205: getfield      #37                 // Field countMax:Lorg/hl7/fhir/dstu3/model/IntegerType;
     208: aastore
     209: areturn
     210: aload_0
     211: getfield      #39                 // Field duration:Lorg/hl7/fhir/dstu3/model/DecimalType;
     214: ifnonnull     224
     217: iconst_0
     218: anewarray     #144                // class org/hl7/fhir/dstu3/model/Base
     221: goto          235
     224: iconst_1
     225: anewarray     #144                // class org/hl7/fhir/dstu3/model/Base
     228: dup
     229: iconst_0
     230: aload_0
     231: getfield      #39                 // Field duration:Lorg/hl7/fhir/dstu3/model/DecimalType;
     234: aastore
     235: areturn
     236: aload_0
     237: getfield      #49                 // Field durationMax:Lorg/hl7/fhir/dstu3/model/DecimalType;
     240: ifnonnull     250
     243: iconst_0
     244: anewarray     #144                // class org/hl7/fhir/dstu3/model/Base
     247: goto          261
     250: iconst_1
     251: anewarray     #144                // class org/hl7/fhir/dstu3/model/Base
     254: dup
     255: iconst_0
     256: aload_0
     257: getfield      #49                 // Field durationMax:Lorg/hl7/fhir/dstu3/model/DecimalType;
     260: aastore
     261: areturn
     262: aload_0
     263: getfield      #51                 // Field durationUnit:Lorg/hl7/fhir/dstu3/model/Enumeration;
     266: ifnonnull     276
     269: iconst_0
     270: anewarray     #144                // class org/hl7/fhir/dstu3/model/Base
     273: goto          287
     276: iconst_1
     277: anewarray     #144                // class org/hl7/fhir/dstu3/model/Base
     280: dup
     281: iconst_0
     282: aload_0
     283: getfield      #51                 // Field durationUnit:Lorg/hl7/fhir/dstu3/model/Enumeration;
     286: aastore
     287: areturn
     288: aload_0
     289: getfield      #61                 // Field frequency:Lorg/hl7/fhir/dstu3/model/IntegerType;
     292: ifnonnull     302
     295: iconst_0
     296: anewarray     #144                // class org/hl7/fhir/dstu3/model/Base
     299: goto          313
     302: iconst_1
     303: anewarray     #144                // class org/hl7/fhir/dstu3/model/Base
     306: dup
     307: iconst_0
     308: aload_0
     309: getfield      #61                 // Field frequency:Lorg/hl7/fhir/dstu3/model/IntegerType;
     312: aastore
     313: areturn
     314: aload_0
     315: getfield      #63                 // Field frequencyMax:Lorg/hl7/fhir/dstu3/model/IntegerType;
     318: ifnonnull     328
     321: iconst_0
     322: anewarray     #144                // class org/hl7/fhir/dstu3/model/Base
     325: goto          339
     328: iconst_1
     329: anewarray     #144                // class org/hl7/fhir/dstu3/model/Base
     332: dup
     333: iconst_0
     334: aload_0
     335: getfield      #63                 // Field frequencyMax:Lorg/hl7/fhir/dstu3/model/IntegerType;
     338: aastore
     339: areturn
     340: aload_0
     341: getfield      #65                 // Field period:Lorg/hl7/fhir/dstu3/model/DecimalType;
     344: ifnonnull     354
     347: iconst_0
     348: anewarray     #144                // class org/hl7/fhir/dstu3/model/Base
     351: goto          365
     354: iconst_1
     355: anewarray     #144                // class org/hl7/fhir/dstu3/model/Base
     358: dup
     359: iconst_0
     360: aload_0
     361: getfield      #65                 // Field period:Lorg/hl7/fhir/dstu3/model/DecimalType;
     364: aastore
     365: areturn
     366: aload_0
     367: getfield      #67                 // Field periodMax:Lorg/hl7/fhir/dstu3/model/DecimalType;
     370: ifnonnull     380
     373: iconst_0
     374: anewarray     #144                // class org/hl7/fhir/dstu3/model/Base
     377: goto          391
     380: iconst_1
     381: anewarray     #144                // class org/hl7/fhir/dstu3/model/Base
     384: dup
     385: iconst_0
     386: aload_0
     387: getfield      #67                 // Field periodMax:Lorg/hl7/fhir/dstu3/model/DecimalType;
     390: aastore
     391: areturn
     392: aload_0
     393: getfield      #69                 // Field periodUnit:Lorg/hl7/fhir/dstu3/model/Enumeration;
     396: ifnonnull     406
     399: iconst_0
     400: anewarray     #144                // class org/hl7/fhir/dstu3/model/Base
     403: goto          417
     406: iconst_1
     407: anewarray     #144                // class org/hl7/fhir/dstu3/model/Base
     410: dup
     411: iconst_0
     412: aload_0
     413: getfield      #69                 // Field periodUnit:Lorg/hl7/fhir/dstu3/model/Enumeration;
     416: aastore
     417: areturn
     418: aload_0
     419: getfield      #71                 // Field dayOfWeek:Ljava/util/List;
     422: ifnonnull     432
     425: iconst_0
     426: anewarray     #144                // class org/hl7/fhir/dstu3/model/Base
     429: goto          456
     432: aload_0
     433: getfield      #71                 // Field dayOfWeek:Ljava/util/List;
     436: aload_0
     437: getfield      #71                 // Field dayOfWeek:Ljava/util/List;
     440: invokeinterface #145,  1          // InterfaceMethod java/util/List.size:()I
     445: anewarray     #144                // class org/hl7/fhir/dstu3/model/Base
     448: invokeinterface #146,  2          // InterfaceMethod java/util/List.toArray:([Ljava/lang/Object;)[Ljava/lang/Object;
     453: checkcast     #147                // class "[Lorg/hl7/fhir/dstu3/model/Base;"
     456: areturn
     457: aload_0
     458: getfield      #82                 // Field timeOfDay:Ljava/util/List;
     461: ifnonnull     471
     464: iconst_0
     465: anewarray     #144                // class org/hl7/fhir/dstu3/model/Base
     468: goto          495
     471: aload_0
     472: getfield      #82                 // Field timeOfDay:Ljava/util/List;
     475: aload_0
     476: getfield      #82                 // Field timeOfDay:Ljava/util/List;
     479: invokeinterface #145,  1          // InterfaceMethod java/util/List.size:()I
     484: anewarray     #144                // class org/hl7/fhir/dstu3/model/Base
     487: invokeinterface #146,  2          // InterfaceMethod java/util/List.toArray:([Ljava/lang/Object;)[Ljava/lang/Object;
     492: checkcast     #147                // class "[Lorg/hl7/fhir/dstu3/model/Base;"
     495: areturn
     496: aload_0
     497: getfield      #90                 // Field when:Ljava/util/List;
     500: ifnonnull     510
     503: iconst_0
     504: anewarray     #144                // class org/hl7/fhir/dstu3/model/Base
     507: goto          534
     510: aload_0
     511: getfield      #90                 // Field when:Ljava/util/List;
     514: aload_0
     515: getfield      #90                 // Field when:Ljava/util/List;
     518: invokeinterface #145,  1          // InterfaceMethod java/util/List.size:()I
     523: anewarray     #144                // class org/hl7/fhir/dstu3/model/Base
     526: invokeinterface #146,  2          // InterfaceMethod java/util/List.toArray:([Ljava/lang/Object;)[Ljava/lang/Object;
     531: checkcast     #147                // class "[Lorg/hl7/fhir/dstu3/model/Base;"
     534: areturn
     535: aload_0
     536: getfield      #95                 // Field offset:Lorg/hl7/fhir/dstu3/model/UnsignedIntType;
     539: ifnonnull     549
     542: iconst_0
     543: anewarray     #144                // class org/hl7/fhir/dstu3/model/Base
     546: goto          560
     549: iconst_1
     550: anewarray     #144                // class org/hl7/fhir/dstu3/model/Base
     553: dup
     554: iconst_0
     555: aload_0
     556: getfield      #95                 // Field offset:Lorg/hl7/fhir/dstu3/model/UnsignedIntType;
     559: aastore
     560: areturn
     561: aload_0
     562: iload_1
     563: aload_2
     564: iload_3
     565: invokespecial #148                // Method org/hl7/fhir/dstu3/model/Element.getProperty:(ILjava/lang/String;Z)[Lorg/hl7/fhir/dstu3/model/Base;
     568: areturn

  public org.hl7.fhir.dstu3.model.Base setProperty(int, java.lang.String, org.hl7.fhir.dstu3.model.Base) throws org.hl7.fhir.exceptions.FHIRException;
    Code:
       0: iload_1
       1: lookupswitch  { // 15
           -1992012396: 165
           -1935429320: 187
           -1383205195: 132
           -1019779949: 364
            -991726143: 235
            -730552025: 283
            -478083280: 176
            -372044331: 154
             -70023844: 213
               3648314: 332
              21434232: 315
              94851343: 143
             384367333: 257
             566580195: 246
            1273846376: 224
               default: 375
          }
     132: aload_0
     133: aload_0
     134: aload_3
     135: invokevirtual #149                // Method castToType:(Lorg/hl7/fhir/dstu3/model/Base;)Lorg/hl7/fhir/dstu3/model/Type;
     138: putfield      #2                  // Field bounds:Lorg/hl7/fhir/dstu3/model/Type;
     141: aload_3
     142: areturn
     143: aload_0
     144: aload_0
     145: aload_3
     146: invokevirtual #150                // Method castToInteger:(Lorg/hl7/fhir/dstu3/model/Base;)Lorg/hl7/fhir/dstu3/model/IntegerType;
     149: putfield      #23                 // Field count:Lorg/hl7/fhir/dstu3/model/IntegerType;
     152: aload_3
     153: areturn
     154: aload_0
     155: aload_0
     156: aload_3
     157: invokevirtual #150                // Method castToInteger:(Lorg/hl7/fhir/dstu3/model/Base;)Lorg/hl7/fhir/dstu3/model/IntegerType;
     160: putfield      #37                 // Field countMax:Lorg/hl7/fhir/dstu3/model/IntegerType;
     163: aload_3
     164: areturn
     165: aload_0
     166: aload_0
     167: aload_3
     168: invokevirtual #151                // Method castToDecimal:(Lorg/hl7/fhir/dstu3/model/Base;)Lorg/hl7/fhir/dstu3/model/DecimalType;
     171: putfield      #39                 // Field duration:Lorg/hl7/fhir/dstu3/model/DecimalType;
     174: aload_3
     175: areturn
     176: aload_0
     177: aload_0
     178: aload_3
     179: invokevirtual #151                // Method castToDecimal:(Lorg/hl7/fhir/dstu3/model/Base;)Lorg/hl7/fhir/dstu3/model/DecimalType;
     182: putfield      #49                 // Field durationMax:Lorg/hl7/fhir/dstu3/model/DecimalType;
     185: aload_3
     186: areturn
     187: new           #54                 // class org/hl7/fhir/dstu3/model/Timing$UnitsOfTimeEnumFactory
     190: dup
     191: invokespecial #55                 // Method org/hl7/fhir/dstu3/model/Timing$UnitsOfTimeEnumFactory."<init>":()V
     194: aload_0
     195: aload_3
     196: invokevirtual #152                // Method castToCode:(Lorg/hl7/fhir/dstu3/model/Base;)Lorg/hl7/fhir/dstu3/model/CodeType;
     199: invokevirtual #153                // Method org/hl7/fhir/dstu3/model/Timing$UnitsOfTimeEnumFactory.fromType:(Lorg/hl7/fhir/dstu3/model/Base;)Lorg/hl7/fhir/dstu3/model/Enumeration;
     202: astore_3
     203: aload_0
     204: aload_3
     205: checkcast     #53                 // class org/hl7/fhir/dstu3/model/Enumeration
     208: putfield      #51                 // Field durationUnit:Lorg/hl7/fhir/dstu3/model/Enumeration;
     211: aload_3
     212: areturn
     213: aload_0
     214: aload_0
     215: aload_3
     216: invokevirtual #150                // Method castToInteger:(Lorg/hl7/fhir/dstu3/model/Base;)Lorg/hl7/fhir/dstu3/model/IntegerType;
     219: putfield      #61                 // Field frequency:Lorg/hl7/fhir/dstu3/model/IntegerType;
     222: aload_3
     223: areturn
     224: aload_0
     225: aload_0
     226: aload_3
     227: invokevirtual #150                // Method castToInteger:(Lorg/hl7/fhir/dstu3/model/Base;)Lorg/hl7/fhir/dstu3/model/IntegerType;
     230: putfield      #63                 // Field frequencyMax:Lorg/hl7/fhir/dstu3/model/IntegerType;
     233: aload_3
     234: areturn
     235: aload_0
     236: aload_0
     237: aload_3
     238: invokevirtual #151                // Method castToDecimal:(Lorg/hl7/fhir/dstu3/model/Base;)Lorg/hl7/fhir/dstu3/model/DecimalType;
     241: putfield      #65                 // Field period:Lorg/hl7/fhir/dstu3/model/DecimalType;
     244: aload_3
     245: areturn
     246: aload_0
     247: aload_0
     248: aload_3
     249: invokevirtual #151                // Method castToDecimal:(Lorg/hl7/fhir/dstu3/model/Base;)Lorg/hl7/fhir/dstu3/model/DecimalType;
     252: putfield      #67                 // Field periodMax:Lorg/hl7/fhir/dstu3/model/DecimalType;
     255: aload_3
     256: areturn
     257: new           #54                 // class org/hl7/fhir/dstu3/model/Timing$UnitsOfTimeEnumFactory
     260: dup
     261: invokespecial #55                 // Method org/hl7/fhir/dstu3/model/Timing$UnitsOfTimeEnumFactory."<init>":()V
     264: aload_0
     265: aload_3
     266: invokevirtual #152                // Method castToCode:(Lorg/hl7/fhir/dstu3/model/Base;)Lorg/hl7/fhir/dstu3/model/CodeType;
     269: invokevirtual #153                // Method org/hl7/fhir/dstu3/model/Timing$UnitsOfTimeEnumFactory.fromType:(Lorg/hl7/fhir/dstu3/model/Base;)Lorg/hl7/fhir/dstu3/model/Enumeration;
     272: astore_3
     273: aload_0
     274: aload_3
     275: checkcast     #53                 // class org/hl7/fhir/dstu3/model/Enumeration
     278: putfield      #69                 // Field periodUnit:Lorg/hl7/fhir/dstu3/model/Enumeration;
     281: aload_3
     282: areturn
     283: new           #77                 // class org/hl7/fhir/dstu3/model/Timing$DayOfWeekEnumFactory
     286: dup
     287: invokespecial #78                 // Method org/hl7/fhir/dstu3/model/Timing$DayOfWeekEnumFactory."<init>":()V
     290: aload_0
     291: aload_3
     292: invokevirtual #152                // Method castToCode:(Lorg/hl7/fhir/dstu3/model/Base;)Lorg/hl7/fhir/dstu3/model/CodeType;
     295: invokevirtual #154                // Method org/hl7/fhir/dstu3/model/Timing$DayOfWeekEnumFactory.fromType:(Lorg/hl7/fhir/dstu3/model/Base;)Lorg/hl7/fhir/dstu3/model/Enumeration;
     298: astore_3
     299: aload_0
     300: invokevirtual #155                // Method getDayOfWeek:()Ljava/util/List;
     303: aload_3
     304: checkcast     #53                 // class org/hl7/fhir/dstu3/model/Enumeration
     307: invokeinterface #79,  2           // InterfaceMethod java/util/List.add:(Ljava/lang/Object;)Z
     312: pop
     313: aload_3
     314: areturn
     315: aload_0
     316: invokevirtual #156                // Method getTimeOfDay:()Ljava/util/List;
     319: aload_0
     320: aload_3
     321: invokevirtual #157                // Method castToTime:(Lorg/hl7/fhir/dstu3/model/Base;)Lorg/hl7/fhir/dstu3/model/TimeType;
     324: invokeinterface #79,  2           // InterfaceMethod java/util/List.add:(Ljava/lang/Object;)Z
     329: pop
     330: aload_3
     331: areturn
     332: new           #91                 // class org/hl7/fhir/dstu3/model/Timing$EventTimingEnumFactory
     335: dup
     336: invokespecial #92                 // Method org/hl7/fhir/dstu3/model/Timing$EventTimingEnumFactory."<init>":()V
     339: aload_0
     340: aload_3
     341: invokevirtual #152                // Method castToCode:(Lorg/hl7/fhir/dstu3/model/Base;)Lorg/hl7/fhir/dstu3/model/CodeType;
     344: invokevirtual #158                // Method org/hl7/fhir/dstu3/model/Timing$EventTimingEnumFactory.fromType:(Lorg/hl7/fhir/dstu3/model/Base;)Lorg/hl7/fhir/dstu3/model/Enumeration;
     347: astore_3
     348: aload_0
     349: invokevirtual #159                // Method getWhen:()Ljava/util/List;
     352: aload_3
     353: checkcast     #53                 // class org/hl7/fhir/dstu3/model/Enumeration
     356: invokeinterface #79,  2           // InterfaceMethod java/util/List.add:(Ljava/lang/Object;)Z
     361: pop
     362: aload_3
     363: areturn
     364: aload_0
     365: aload_0
     366: aload_3
     367: invokevirtual #160                // Method castToUnsignedInt:(Lorg/hl7/fhir/dstu3/model/Base;)Lorg/hl7/fhir/dstu3/model/UnsignedIntType;
     370: putfield      #95                 // Field offset:Lorg/hl7/fhir/dstu3/model/UnsignedIntType;
     373: aload_3
     374: areturn
     375: aload_0
     376: iload_1
     377: aload_2
     378: aload_3
     379: invokespecial #161                // Method org/hl7/fhir/dstu3/model/Element.setProperty:(ILjava/lang/String;Lorg/hl7/fhir/dstu3/model/Base;)Lorg/hl7/fhir/dstu3/model/Base;
     382: areturn

  public org.hl7.fhir.dstu3.model.Base setProperty(java.lang.String, org.hl7.fhir.dstu3.model.Base) throws org.hl7.fhir.exceptions.FHIRException;
    Code:
       0: aload_1
       1: ldc           #104                // String bounds[x]
       3: invokevirtual #89                 // Method java/lang/String.equals:(Ljava/lang/Object;)Z
       6: ifeq          21
       9: aload_0
      10: aload_0
      11: aload_2
      12: invokevirtual #149                // Method castToType:(Lorg/hl7/fhir/dstu3/model/Base;)Lorg/hl7/fhir/dstu3/model/Type;
      15: putfield      #2                  // Field bounds:Lorg/hl7/fhir/dstu3/model/Type;
      18: goto          400
      21: aload_1
      22: ldc           #108                // String count
      24: invokevirtual #89                 // Method java/lang/String.equals:(Ljava/lang/Object;)Z
      27: ifeq          42
      30: aload_0
      31: aload_0
      32: aload_2
      33: invokevirtual #150                // Method castToInteger:(Lorg/hl7/fhir/dstu3/model/Base;)Lorg/hl7/fhir/dstu3/model/IntegerType;
      36: putfield      #23                 // Field count:Lorg/hl7/fhir/dstu3/model/IntegerType;
      39: goto          400
      42: aload_1
      43: ldc           #111                // String countMax
      45: invokevirtual #89                 // Method java/lang/String.equals:(Ljava/lang/Object;)Z
      48: ifeq          63
      51: aload_0
      52: aload_0
      53: aload_2
      54: invokevirtual #150                // Method castToInteger:(Lorg/hl7/fhir/dstu3/model/Base;)Lorg/hl7/fhir/dstu3/model/IntegerType;
      57: putfield      #37                 // Field countMax:Lorg/hl7/fhir/dstu3/model/IntegerType;
      60: goto          400
      63: aload_1
      64: ldc           #113                // String duration
      66: invokevirtual #89                 // Method java/lang/String.equals:(Ljava/lang/Object;)Z
      69: ifeq          84
      72: aload_0
      73: aload_0
      74: aload_2
      75: invokevirtual #151                // Method castToDecimal:(Lorg/hl7/fhir/dstu3/model/Base;)Lorg/hl7/fhir/dstu3/model/DecimalType;
      78: putfield      #39                 // Field duration:Lorg/hl7/fhir/dstu3/model/DecimalType;
      81: goto          400
      84: aload_1
      85: ldc           #116                // String durationMax
      87: invokevirtual #89                 // Method java/lang/String.equals:(Ljava/lang/Object;)Z
      90: ifeq          105
      93: aload_0
      94: aload_0
      95: aload_2
      96: invokevirtual #151                // Method castToDecimal:(Lorg/hl7/fhir/dstu3/model/Base;)Lorg/hl7/fhir/dstu3/model/DecimalType;
      99: putfield      #49                 // Field durationMax:Lorg/hl7/fhir/dstu3/model/DecimalType;
     102: goto          400
     105: aload_1
     106: ldc           #118                // String durationUnit
     108: invokevirtual #89                 // Method java/lang/String.equals:(Ljava/lang/Object;)Z
     111: ifeq          141
     114: new           #54                 // class org/hl7/fhir/dstu3/model/Timing$UnitsOfTimeEnumFactory
     117: dup
     118: invokespecial #55                 // Method org/hl7/fhir/dstu3/model/Timing$UnitsOfTimeEnumFactory."<init>":()V
     121: aload_0
     122: aload_2
     123: invokevirtual #152                // Method castToCode:(Lorg/hl7/fhir/dstu3/model/Base;)Lorg/hl7/fhir/dstu3/model/CodeType;
     126: invokevirtual #153                // Method org/hl7/fhir/dstu3/model/Timing$UnitsOfTimeEnumFactory.fromType:(Lorg/hl7/fhir/dstu3/model/Base;)Lorg/hl7/fhir/dstu3/model/Enumeration;
     129: astore_2
     130: aload_0
     131: aload_2
     132: checkcast     #53                 // class org/hl7/fhir/dstu3/model/Enumeration
     135: putfield      #51                 // Field durationUnit:Lorg/hl7/fhir/dstu3/model/Enumeration;
     138: goto          400
     141: aload_1
     142: ldc           #121                // String frequency
     144: invokevirtual #89                 // Method java/lang/String.equals:(Ljava/lang/Object;)Z
     147: ifeq          162
     150: aload_0
     151: aload_0
     152: aload_2
     153: invokevirtual #150                // Method castToInteger:(Lorg/hl7/fhir/dstu3/model/Base;)Lorg/hl7/fhir/dstu3/model/IntegerType;
     156: putfield      #61                 // Field frequency:Lorg/hl7/fhir/dstu3/model/IntegerType;
     159: goto          400
     162: aload_1
     163: ldc           #123                // String frequencyMax
     165: invokevirtual #89                 // Method java/lang/String.equals:(Ljava/lang/Object;)Z
     168: ifeq          183
     171: aload_0
     172: aload_0
     173: aload_2
     174: invokevirtual #150                // Method castToInteger:(Lorg/hl7/fhir/dstu3/model/Base;)Lorg/hl7/fhir/dstu3/model/IntegerType;
     177: putfield      #63                 // Field frequencyMax:Lorg/hl7/fhir/dstu3/model/IntegerType;
     180: goto          400
     183: aload_1
     184: ldc           #125                // String period
     186: invokevirtual #89                 // Method java/lang/String.equals:(Ljava/lang/Object;)Z
     189: ifeq          204
     192: aload_0
     193: aload_0
     194: aload_2
     195: invokevirtual #151                // Method castToDecimal:(Lorg/hl7/fhir/dstu3/model/Base;)Lorg/hl7/fhir/dstu3/model/DecimalType;
     198: putfield      #65                 // Field period:Lorg/hl7/fhir/dstu3/model/DecimalType;
     201: goto          400
     204: aload_1
     205: ldc           #127                // String periodMax
     207: invokevirtual #89                 // Method java/lang/String.equals:(Ljava/lang/Object;)Z
     210: ifeq          225
     213: aload_0
     214: aload_0
     215: aload_2
     216: invokevirtual #151                // Method castToDecimal:(Lorg/hl7/fhir/dstu3/model/Base;)Lorg/hl7/fhir/dstu3/model/DecimalType;
     219: putfield      #67                 // Field periodMax:Lorg/hl7/fhir/dstu3/model/DecimalType;
     222: goto          400
     225: aload_1
     226: ldc           #129                // String periodUnit
     228: invokevirtual #89                 // Method java/lang/String.equals:(Ljava/lang/Object;)Z
     231: ifeq          261
     234: new           #54                 // class org/hl7/fhir/dstu3/model/Timing$UnitsOfTimeEnumFactory
     237: dup
     238: invokespecial #55                 // Method org/hl7/fhir/dstu3/model/Timing$UnitsOfTimeEnumFactory."<init>":()V
     241: aload_0
     242: aload_2
     243: invokevirtual #152                // Method castToCode:(Lorg/hl7/fhir/dstu3/model/Base;)Lorg/hl7/fhir/dstu3/model/CodeType;
     246: invokevirtual #153                // Method org/hl7/fhir/dstu3/model/Timing$UnitsOfTimeEnumFactory.fromType:(Lorg/hl7/fhir/dstu3/model/Base;)Lorg/hl7/fhir/dstu3/model/Enumeration;
     249: astore_2
     250: aload_0
     251: aload_2
     252: checkcast     #53                 // class org/hl7/fhir/dstu3/model/Enumeration
     255: putfield      #69                 // Field periodUnit:Lorg/hl7/fhir/dstu3/model/Enumeration;
     258: goto          400
     261: aload_1
     262: ldc           #131                // String dayOfWeek
     264: invokevirtual #89                 // Method java/lang/String.equals:(Ljava/lang/Object;)Z
     267: ifeq          303
     270: new           #77                 // class org/hl7/fhir/dstu3/model/Timing$DayOfWeekEnumFactory
     273: dup
     274: invokespecial #78                 // Method org/hl7/fhir/dstu3/model/Timing$DayOfWeekEnumFactory."<init>":()V
     277: aload_0
     278: aload_2
     279: invokevirtual #152                // Method castToCode:(Lorg/hl7/fhir/dstu3/model/Base;)Lorg/hl7/fhir/dstu3/model/CodeType;
     282: invokevirtual #154                // Method org/hl7/fhir/dstu3/model/Timing$DayOfWeekEnumFactory.fromType:(Lorg/hl7/fhir/dstu3/model/Base;)Lorg/hl7/fhir/dstu3/model/Enumeration;
     285: astore_2
     286: aload_0
     287: invokevirtual #155                // Method getDayOfWeek:()Ljava/util/List;
     290: aload_2
     291: checkcast     #53                 // class org/hl7/fhir/dstu3/model/Enumeration
     294: invokeinterface #79,  2           // InterfaceMethod java/util/List.add:(Ljava/lang/Object;)Z
     299: pop
     300: goto          400
     303: aload_1
     304: ldc           #135                // String timeOfDay
     306: invokevirtual #89                 // Method java/lang/String.equals:(Ljava/lang/Object;)Z
     309: ifeq          330
     312: aload_0
     313: invokevirtual #156                // Method getTimeOfDay:()Ljava/util/List;
     316: aload_0
     317: aload_2
     318: invokevirtual #157                // Method castToTime:(Lorg/hl7/fhir/dstu3/model/Base;)Lorg/hl7/fhir/dstu3/model/TimeType;
     321: invokeinterface #79,  2           // InterfaceMethod java/util/List.add:(Ljava/lang/Object;)Z
     326: pop
     327: goto          400
     330: aload_1
     331: ldc           #138                // String when
     333: invokevirtual #89                 // Method java/lang/String.equals:(Ljava/lang/Object;)Z
     336: ifeq          372
     339: new           #91                 // class org/hl7/fhir/dstu3/model/Timing$EventTimingEnumFactory
     342: dup
     343: invokespecial #92                 // Method org/hl7/fhir/dstu3/model/Timing$EventTimingEnumFactory."<init>":()V
     346: aload_0
     347: aload_2
     348: invokevirtual #152                // Method castToCode:(Lorg/hl7/fhir/dstu3/model/Base;)Lorg/hl7/fhir/dstu3/model/CodeType;
     351: invokevirtual #158                // Method org/hl7/fhir/dstu3/model/Timing$EventTimingEnumFactory.fromType:(Lorg/hl7/fhir/dstu3/model/Base;)Lorg/hl7/fhir/dstu3/model/Enumeration;
     354: astore_2
     355: aload_0
     356: invokevirtual #159                // Method getWhen:()Ljava/util/List;
     359: aload_2
     360: checkcast     #53                 // class org/hl7/fhir/dstu3/model/Enumeration
     363: invokeinterface #79,  2           // InterfaceMethod java/util/List.add:(Ljava/lang/Object;)Z
     368: pop
     369: goto          400
     372: aload_1
     373: ldc           #140                // String offset
     375: invokevirtual #89                 // Method java/lang/String.equals:(Ljava/lang/Object;)Z
     378: ifeq          393
     381: aload_0
     382: aload_0
     383: aload_2
     384: invokevirtual #160                // Method castToUnsignedInt:(Lorg/hl7/fhir/dstu3/model/Base;)Lorg/hl7/fhir/dstu3/model/UnsignedIntType;
     387: putfield      #95                 // Field offset:Lorg/hl7/fhir/dstu3/model/UnsignedIntType;
     390: goto          400
     393: aload_0
     394: aload_1
     395: aload_2
     396: invokespecial #162                // Method org/hl7/fhir/dstu3/model/Element.setProperty:(Ljava/lang/String;Lorg/hl7/fhir/dstu3/model/Base;)Lorg/hl7/fhir/dstu3/model/Base;
     399: areturn
     400: aload_2
     401: areturn

  public org.hl7.fhir.dstu3.model.Base makeProperty(int, java.lang.String) throws org.hl7.fhir.exceptions.FHIRException;
    Code:
       0: iload_1
       1: lookupswitch  { // 16
           -1992012396: 160
           -1935429320: 170
           -1383205195: 145
           -1149635157: 140
           -1019779949: 215
            -991726143: 185
            -730552025: 200
            -478083280: 165
            -372044331: 155
             -70023844: 175
               3648314: 210
              21434232: 205
              94851343: 150
             384367333: 195
             566580195: 190
            1273846376: 180
               default: 220
          }
     140: aload_0
     141: invokevirtual #163                // Method getBounds:()Lorg/hl7/fhir/dstu3/model/Type;
     144: areturn
     145: aload_0
     146: invokevirtual #163                // Method getBounds:()Lorg/hl7/fhir/dstu3/model/Type;
     149: areturn
     150: aload_0
     151: invokevirtual #164                // Method getCountElement:()Lorg/hl7/fhir/dstu3/model/IntegerType;
     154: areturn
     155: aload_0
     156: invokevirtual #165                // Method getCountMaxElement:()Lorg/hl7/fhir/dstu3/model/IntegerType;
     159: areturn
     160: aload_0
     161: invokevirtual #166                // Method getDurationElement:()Lorg/hl7/fhir/dstu3/model/DecimalType;
     164: areturn
     165: aload_0
     166: invokevirtual #167                // Method getDurationMaxElement:()Lorg/hl7/fhir/dstu3/model/DecimalType;
     169: areturn
     170: aload_0
     171: invokevirtual #168                // Method getDurationUnitElement:()Lorg/hl7/fhir/dstu3/model/Enumeration;
     174: areturn
     175: aload_0
     176: invokevirtual #169                // Method getFrequencyElement:()Lorg/hl7/fhir/dstu3/model/IntegerType;
     179: areturn
     180: aload_0
     181: invokevirtual #170                // Method getFrequencyMaxElement:()Lorg/hl7/fhir/dstu3/model/IntegerType;
     184: areturn
     185: aload_0
     186: invokevirtual #171                // Method getPeriodElement:()Lorg/hl7/fhir/dstu3/model/DecimalType;
     189: areturn
     190: aload_0
     191: invokevirtual #172                // Method getPeriodMaxElement:()Lorg/hl7/fhir/dstu3/model/DecimalType;
     194: areturn
     195: aload_0
     196: invokevirtual #173                // Method getPeriodUnitElement:()Lorg/hl7/fhir/dstu3/model/Enumeration;
     199: areturn
     200: aload_0
     201: invokevirtual #174                // Method addDayOfWeekElement:()Lorg/hl7/fhir/dstu3/model/Enumeration;
     204: areturn
     205: aload_0
     206: invokevirtual #175                // Method addTimeOfDayElement:()Lorg/hl7/fhir/dstu3/model/TimeType;
     209: areturn
     210: aload_0
     211: invokevirtual #176                // Method addWhenElement:()Lorg/hl7/fhir/dstu3/model/Enumeration;
     214: areturn
     215: aload_0
     216: invokevirtual #177                // Method getOffsetElement:()Lorg/hl7/fhir/dstu3/model/UnsignedIntType;
     219: areturn
     220: aload_0
     221: iload_1
     222: aload_2
     223: invokespecial #178                // Method org/hl7/fhir/dstu3/model/Element.makeProperty:(ILjava/lang/String;)Lorg/hl7/fhir/dstu3/model/Base;
     226: areturn

  public java.lang.String[] getTypesForProperty(int, java.lang.String) throws org.hl7.fhir.exceptions.FHIRException;
    Code:
       0: iload_1
       1: lookupswitch  { // 15
           -1992012396: 172
           -1935429320: 192
           -1383205195: 132
           -1019779949: 282
            -991726143: 222
            -730552025: 252
            -478083280: 182
            -372044331: 162
             -70023844: 202
               3648314: 272
              21434232: 262
              94851343: 152
             384367333: 242
             566580195: 232
            1273846376: 212
               default: 292
          }
     132: iconst_3
     133: anewarray     #88                 // class java/lang/String
     136: dup
     137: iconst_0
     138: ldc           #179                // String Duration
     140: aastore
     141: dup
     142: iconst_1
     143: ldc           #180                // String Range
     145: aastore
     146: dup
     147: iconst_2
     148: ldc           #181                // String Period
     150: aastore
     151: areturn
     152: iconst_1
     153: anewarray     #88                 // class java/lang/String
     156: dup
     157: iconst_0
     158: ldc           #109                // String integer
     160: aastore
     161: areturn
     162: iconst_1
     163: anewarray     #88                 // class java/lang/String
     166: dup
     167: iconst_0
     168: ldc           #109                // String integer
     170: aastore
     171: areturn
     172: iconst_1
     173: anewarray     #88                 // class java/lang/String
     176: dup
     177: iconst_0
     178: ldc           #114                // String decimal
     180: aastore
     181: areturn
     182: iconst_1
     183: anewarray     #88                 // class java/lang/String
     186: dup
     187: iconst_0
     188: ldc           #114                // String decimal
     190: aastore
     191: areturn
     192: iconst_1
     193: anewarray     #88                 // class java/lang/String
     196: dup
     197: iconst_0
     198: ldc           #119                // String code
     200: aastore
     201: areturn
     202: iconst_1
     203: anewarray     #88                 // class java/lang/String
     206: dup
     207: iconst_0
     208: ldc           #109                // String integer
     210: aastore
     211: areturn
     212: iconst_1
     213: anewarray     #88                 // class java/lang/String
     216: dup
     217: iconst_0
     218: ldc           #109                // String integer
     220: aastore
     221: areturn
     222: iconst_1
     223: anewarray     #88                 // class java/lang/String
     226: dup
     227: iconst_0
     228: ldc           #114                // String decimal
     230: aastore
     231: areturn
     232: iconst_1
     233: anewarray     #88                 // class java/lang/String
     236: dup
     237: iconst_0
     238: ldc           #114                // String decimal
     240: aastore
     241: areturn
     242: iconst_1
     243: anewarray     #88                 // class java/lang/String
     246: dup
     247: iconst_0
     248: ldc           #119                // String code
     250: aastore
     251: areturn
     252: iconst_1
     253: anewarray     #88                 // class java/lang/String
     256: dup
     257: iconst_0
     258: ldc           #119                // String code
     260: aastore
     261: areturn
     262: iconst_1
     263: anewarray     #88                 // class java/lang/String
     266: dup
     267: iconst_0
     268: ldc           #136                // String time
     270: aastore
     271: areturn
     272: iconst_1
     273: anewarray     #88                 // class java/lang/String
     276: dup
     277: iconst_0
     278: ldc           #119                // String code
     280: aastore
     281: areturn
     282: iconst_1
     283: anewarray     #88                 // class java/lang/String
     286: dup
     287: iconst_0
     288: ldc           #141                // String unsignedInt
     290: aastore
     291: areturn
     292: aload_0
     293: iload_1
     294: aload_2
     295: invokespecial #182                // Method org/hl7/fhir/dstu3/model/Element.getTypesForProperty:(ILjava/lang/String;)[Ljava/lang/String;
     298: areturn

  public org.hl7.fhir.dstu3.model.Base addChild(java.lang.String) throws org.hl7.fhir.exceptions.FHIRException;
    Code:
       0: aload_1
       1: ldc           #183                // String boundsDuration
       3: invokevirtual #89                 // Method java/lang/String.equals:(Ljava/lang/Object;)Z
       6: ifeq          25
       9: aload_0
      10: new           #3                  // class org/hl7/fhir/dstu3/model/Duration
      13: dup
      14: invokespecial #184                // Method org/hl7/fhir/dstu3/model/Duration."<init>":()V
      17: putfield      #2                  // Field bounds:Lorg/hl7/fhir/dstu3/model/Type;
      20: aload_0
      21: getfield      #2                  // Field bounds:Lorg/hl7/fhir/dstu3/model/Type;
      24: areturn
      25: aload_1
      26: ldc           #185                // String boundsRange
      28: invokevirtual #89                 // Method java/lang/String.equals:(Ljava/lang/Object;)Z
      31: ifeq          50
      34: aload_0
      35: new           #14                 // class org/hl7/fhir/dstu3/model/Range
      38: dup
      39: invokespecial #186                // Method org/hl7/fhir/dstu3/model/Range."<init>":()V
      42: putfield      #2                  // Field bounds:Lorg/hl7/fhir/dstu3/model/Type;
      45: aload_0
      46: getfield      #2                  // Field bounds:Lorg/hl7/fhir/dstu3/model/Type;
      49: areturn
      50: aload_1
      51: ldc           #187                // String boundsPeriod
      53: invokevirtual #89                 // Method java/lang/String.equals:(Ljava/lang/Object;)Z
      56: ifeq          75
      59: aload_0
      60: new           #16                 // class org/hl7/fhir/dstu3/model/Period
      63: dup
      64: invokespecial #188                // Method org/hl7/fhir/dstu3/model/Period."<init>":()V
      67: putfield      #2                  // Field bounds:Lorg/hl7/fhir/dstu3/model/Type;
      70: aload_0
      71: getfield      #2                  // Field bounds:Lorg/hl7/fhir/dstu3/model/Type;
      74: areturn
      75: aload_1
      76: ldc           #108                // String count
      78: invokevirtual #89                 // Method java/lang/String.equals:(Ljava/lang/Object;)Z
      81: ifeq          94
      84: new           #4                  // class org/hl7/fhir/exceptions/FHIRException
      87: dup
      88: ldc           #189                // String Cannot call addChild on a primitive type Timing.count
      90: invokespecial #13                 // Method org/hl7/fhir/exceptions/FHIRException."<init>":(Ljava/lang/String;)V
      93: athrow
      94: aload_1
      95: ldc           #111                // String countMax
      97: invokevirtual #89                 // Method java/lang/String.equals:(Ljava/lang/Object;)Z
     100: ifeq          113
     103: new           #4                  // class org/hl7/fhir/exceptions/FHIRException
     106: dup
     107: ldc           #190                // String Cannot call addChild on a primitive type Timing.countMax
     109: invokespecial #13                 // Method org/hl7/fhir/exceptions/FHIRException."<init>":(Ljava/lang/String;)V
     112: athrow
     113: aload_1
     114: ldc           #113                // String duration
     116: invokevirtual #89                 // Method java/lang/String.equals:(Ljava/lang/Object;)Z
     119: ifeq          132
     122: new           #4                  // class org/hl7/fhir/exceptions/FHIRException
     125: dup
     126: ldc           #191                // String Cannot call addChild on a primitive type Timing.duration
     128: invokespecial #13                 // Method org/hl7/fhir/exceptions/FHIRException."<init>":(Ljava/lang/String;)V
     131: athrow
     132: aload_1
     133: ldc           #116                // String durationMax
     135: invokevirtual #89                 // Method java/lang/String.equals:(Ljava/lang/Object;)Z
     138: ifeq          151
     141: new           #4                  // class org/hl7/fhir/exceptions/FHIRException
     144: dup
     145: ldc           #192                // String Cannot call addChild on a primitive type Timing.durationMax
     147: invokespecial #13                 // Method org/hl7/fhir/exceptions/FHIRException."<init>":(Ljava/lang/String;)V
     150: athrow
     151: aload_1
     152: ldc           #118                // String durationUnit
     154: invokevirtual #89                 // Method java/lang/String.equals:(Ljava/lang/Object;)Z
     157: ifeq          170
     160: new           #4                  // class org/hl7/fhir/exceptions/FHIRException
     163: dup
     164: ldc           #193                // String Cannot call addChild on a primitive type Timing.durationUnit
     166: invokespecial #13                 // Method org/hl7/fhir/exceptions/FHIRException."<init>":(Ljava/lang/String;)V
     169: athrow
     170: aload_1
     171: ldc           #121                // String frequency
     173: invokevirtual #89                 // Method java/lang/String.equals:(Ljava/lang/Object;)Z
     176: ifeq          189
     179: new           #4                  // class org/hl7/fhir/exceptions/FHIRException
     182: dup
     183: ldc           #194                // String Cannot call addChild on a primitive type Timing.frequency
     185: invokespecial #13                 // Method org/hl7/fhir/exceptions/FHIRException."<init>":(Ljava/lang/String;)V
     188: athrow
     189: aload_1
     190: ldc           #123                // String frequencyMax
     192: invokevirtual #89                 // Method java/lang/String.equals:(Ljava/lang/Object;)Z
     195: ifeq          208
     198: new           #4                  // class org/hl7/fhir/exceptions/FHIRException
     201: dup
     202: ldc           #195                // String Cannot call addChild on a primitive type Timing.frequencyMax
     204: invokespecial #13                 // Method org/hl7/fhir/exceptions/FHIRException."<init>":(Ljava/lang/String;)V
     207: athrow
     208: aload_1
     209: ldc           #125                // String period
     211: invokevirtual #89                 // Method java/lang/String.equals:(Ljava/lang/Object;)Z
     214: ifeq          227
     217: new           #4                  // class org/hl7/fhir/exceptions/FHIRException
     220: dup
     221: ldc           #196                // String Cannot call addChild on a primitive type Timing.period
     223: invokespecial #13                 // Method org/hl7/fhir/exceptions/FHIRException."<init>":(Ljava/lang/String;)V
     226: athrow
     227: aload_1
     228: ldc           #127                // String periodMax
     230: invokevirtual #89                 // Method java/lang/String.equals:(Ljava/lang/Object;)Z
     233: ifeq          246
     236: new           #4                  // class org/hl7/fhir/exceptions/FHIRException
     239: dup
     240: ldc           #197                // String Cannot call addChild on a primitive type Timing.periodMax
     242: invokespecial #13                 // Method org/hl7/fhir/exceptions/FHIRException."<init>":(Ljava/lang/String;)V
     245: athrow
     246: aload_1
     247: ldc           #129                // String periodUnit
     249: invokevirtual #89                 // Method java/lang/String.equals:(Ljava/lang/Object;)Z
     252: ifeq          265
     255: new           #4                  // class org/hl7/fhir/exceptions/FHIRException
     258: dup
     259: ldc           #198                // String Cannot call addChild on a primitive type Timing.periodUnit
     261: invokespecial #13                 // Method org/hl7/fhir/exceptions/FHIRException."<init>":(Ljava/lang/String;)V
     264: athrow
     265: aload_1
     266: ldc           #131                // String dayOfWeek
     268: invokevirtual #89                 // Method java/lang/String.equals:(Ljava/lang/Object;)Z
     271: ifeq          284
     274: new           #4                  // class org/hl7/fhir/exceptions/FHIRException
     277: dup
     278: ldc           #199                // String Cannot call addChild on a primitive type Timing.dayOfWeek
     280: invokespecial #13                 // Method org/hl7/fhir/exceptions/FHIRException."<init>":(Ljava/lang/String;)V
     283: athrow
     284: aload_1
     285: ldc           #135                // String timeOfDay
     287: invokevirtual #89                 // Method java/lang/String.equals:(Ljava/lang/Object;)Z
     290: ifeq          303
     293: new           #4                  // class org/hl7/fhir/exceptions/FHIRException
     296: dup
     297: ldc           #200                // String Cannot call addChild on a primitive type Timing.timeOfDay
     299: invokespecial #13                 // Method org/hl7/fhir/exceptions/FHIRException."<init>":(Ljava/lang/String;)V
     302: athrow
     303: aload_1
     304: ldc           #138                // String when
     306: invokevirtual #89                 // Method java/lang/String.equals:(Ljava/lang/Object;)Z
     309: ifeq          322
     312: new           #4                  // class org/hl7/fhir/exceptions/FHIRException
     315: dup
     316: ldc           #201                // String Cannot call addChild on a primitive type Timing.when
     318: invokespecial #13                 // Method org/hl7/fhir/exceptions/FHIRException."<init>":(Ljava/lang/String;)V
     321: athrow
     322: aload_1
     323: ldc           #140                // String offset
     325: invokevirtual #89                 // Method java/lang/String.equals:(Ljava/lang/Object;)Z
     328: ifeq          341
     331: new           #4                  // class org/hl7/fhir/exceptions/FHIRException
     334: dup
     335: ldc           #202                // String Cannot call addChild on a primitive type Timing.offset
     337: invokespecial #13                 // Method org/hl7/fhir/exceptions/FHIRException."<init>":(Ljava/lang/String;)V
     340: athrow
     341: aload_0
     342: aload_1
     343: invokespecial #203                // Method org/hl7/fhir/dstu3/model/Element.addChild:(Ljava/lang/String;)Lorg/hl7/fhir/dstu3/model/Base;
     346: areturn

  public org.hl7.fhir.dstu3.model.Timing$TimingRepeatComponent copy();
    Code:
       0: new           #204                // class org/hl7/fhir/dstu3/model/Timing$TimingRepeatComponent
       3: dup
       4: invokespecial #205                // Method "<init>":()V
       7: astore_1
       8: aload_0
       9: aload_1
      10: invokevirtual #206                // Method copyValues:(Lorg/hl7/fhir/dstu3/model/Element;)V
      13: aload_1
      14: aload_0
      15: getfield      #2                  // Field bounds:Lorg/hl7/fhir/dstu3/model/Type;
      18: ifnonnull     25
      21: aconst_null
      22: goto          32
      25: aload_0
      26: getfield      #2                  // Field bounds:Lorg/hl7/fhir/dstu3/model/Type;
      29: invokevirtual #207                // Method org/hl7/fhir/dstu3/model/Type.copy:()Lorg/hl7/fhir/dstu3/model/Type;
      32: putfield      #2                  // Field bounds:Lorg/hl7/fhir/dstu3/model/Type;
      35: aload_1
      36: aload_0
      37: getfield      #23                 // Field count:Lorg/hl7/fhir/dstu3/model/IntegerType;
      40: ifnonnull     47
      43: aconst_null
      44: goto          54
      47: aload_0
      48: getfield      #23                 // Field count:Lorg/hl7/fhir/dstu3/model/IntegerType;
      51: invokevirtual #208                // Method org/hl7/fhir/dstu3/model/IntegerType.copy:()Lorg/hl7/fhir/dstu3/model/IntegerType;
      54: putfield      #23                 // Field count:Lorg/hl7/fhir/dstu3/model/IntegerType;
      57: aload_1
      58: aload_0
      59: getfield      #37                 // Field countMax:Lorg/hl7/fhir/dstu3/model/IntegerType;
      62: ifnonnull     69
      65: aconst_null
      66: goto          76
      69: aload_0
      70: getfield      #37                 // Field countMax:Lorg/hl7/fhir/dstu3/model/IntegerType;
      73: invokevirtual #208                // Method org/hl7/fhir/dstu3/model/IntegerType.copy:()Lorg/hl7/fhir/dstu3/model/IntegerType;
      76: putfield      #37                 // Field countMax:Lorg/hl7/fhir/dstu3/model/IntegerType;
      79: aload_1
      80: aload_0
      81: getfield      #39                 // Field duration:Lorg/hl7/fhir/dstu3/model/DecimalType;
      84: ifnonnull     91
      87: aconst_null
      88: goto          98
      91: aload_0
      92: getfield      #39                 // Field duration:Lorg/hl7/fhir/dstu3/model/DecimalType;
      95: invokevirtual #209                // Method org/hl7/fhir/dstu3/model/DecimalType.copy:()Lorg/hl7/fhir/dstu3/model/DecimalType;
      98: putfield      #39                 // Field duration:Lorg/hl7/fhir/dstu3/model/DecimalType;
     101: aload_1
     102: aload_0
     103: getfield      #49                 // Field durationMax:Lorg/hl7/fhir/dstu3/model/DecimalType;
     106: ifnonnull     113
     109: aconst_null
     110: goto          120
     113: aload_0
     114: getfield      #49                 // Field durationMax:Lorg/hl7/fhir/dstu3/model/DecimalType;
     117: invokevirtual #209                // Method org/hl7/fhir/dstu3/model/DecimalType.copy:()Lorg/hl7/fhir/dstu3/model/DecimalType;
     120: putfield      #49                 // Field durationMax:Lorg/hl7/fhir/dstu3/model/DecimalType;
     123: aload_1
     124: aload_0
     125: getfield      #51                 // Field durationUnit:Lorg/hl7/fhir/dstu3/model/Enumeration;
     128: ifnonnull     135
     131: aconst_null
     132: goto          142
     135: aload_0
     136: getfield      #51                 // Field durationUnit:Lorg/hl7/fhir/dstu3/model/Enumeration;
     139: invokevirtual #210                // Method org/hl7/fhir/dstu3/model/Enumeration.copy:()Lorg/hl7/fhir/dstu3/model/Enumeration;
     142: putfield      #51                 // Field durationUnit:Lorg/hl7/fhir/dstu3/model/Enumeration;
     145: aload_1
     146: aload_0
     147: getfield      #61                 // Field frequency:Lorg/hl7/fhir/dstu3/model/IntegerType;
     150: ifnonnull     157
     153: aconst_null
     154: goto          164
     157: aload_0
     158: getfield      #61                 // Field frequency:Lorg/hl7/fhir/dstu3/model/IntegerType;
     161: invokevirtual #208                // Method org/hl7/fhir/dstu3/model/IntegerType.copy:()Lorg/hl7/fhir/dstu3/model/IntegerType;
     164: putfield      #61                 // Field frequency:Lorg/hl7/fhir/dstu3/model/IntegerType;
     167: aload_1
     168: aload_0
     169: getfield      #63                 // Field frequencyMax:Lorg/hl7/fhir/dstu3/model/IntegerType;
     172: ifnonnull     179
     175: aconst_null
     176: goto          186
     179: aload_0
     180: getfield      #63                 // Field frequencyMax:Lorg/hl7/fhir/dstu3/model/IntegerType;
     183: invokevirtual #208                // Method org/hl7/fhir/dstu3/model/IntegerType.copy:()Lorg/hl7/fhir/dstu3/model/IntegerType;
     186: putfield      #63                 // Field frequencyMax:Lorg/hl7/fhir/dstu3/model/IntegerType;
     189: aload_1
     190: aload_0
     191: getfield      #65                 // Field period:Lorg/hl7/fhir/dstu3/model/DecimalType;
     194: ifnonnull     201
     197: aconst_null
     198: goto          208
     201: aload_0
     202: getfield      #65                 // Field period:Lorg/hl7/fhir/dstu3/model/DecimalType;
     205: invokevirtual #209                // Method org/hl7/fhir/dstu3/model/DecimalType.copy:()Lorg/hl7/fhir/dstu3/model/DecimalType;
     208: putfield      #65                 // Field period:Lorg/hl7/fhir/dstu3/model/DecimalType;
     211: aload_1
     212: aload_0
     213: getfield      #67                 // Field periodMax:Lorg/hl7/fhir/dstu3/model/DecimalType;
     216: ifnonnull     223
     219: aconst_null
     220: goto          230
     223: aload_0
     224: getfield      #67                 // Field periodMax:Lorg/hl7/fhir/dstu3/model/DecimalType;
     227: invokevirtual #209                // Method org/hl7/fhir/dstu3/model/DecimalType.copy:()Lorg/hl7/fhir/dstu3/model/DecimalType;
     230: putfield      #67                 // Field periodMax:Lorg/hl7/fhir/dstu3/model/DecimalType;
     233: aload_1
     234: aload_0
     235: getfield      #69                 // Field periodUnit:Lorg/hl7/fhir/dstu3/model/Enumeration;
     238: ifnonnull     245
     241: aconst_null
     242: goto          252
     245: aload_0
     246: getfield      #69                 // Field periodUnit:Lorg/hl7/fhir/dstu3/model/Enumeration;
     249: invokevirtual #210                // Method org/hl7/fhir/dstu3/model/Enumeration.copy:()Lorg/hl7/fhir/dstu3/model/Enumeration;
     252: putfield      #69                 // Field periodUnit:Lorg/hl7/fhir/dstu3/model/Enumeration;
     255: aload_0
     256: getfield      #71                 // Field dayOfWeek:Ljava/util/List;
     259: ifnull        319
     262: aload_1
     263: new           #72                 // class java/util/ArrayList
     266: dup
     267: invokespecial #73                 // Method java/util/ArrayList."<init>":()V
     270: putfield      #71                 // Field dayOfWeek:Ljava/util/List;
     273: aload_0
     274: getfield      #71                 // Field dayOfWeek:Ljava/util/List;
     277: invokeinterface #74,  1           // InterfaceMethod java/util/List.iterator:()Ljava/util/Iterator;
     282: astore_2
     283: aload_2
     284: invokeinterface #75,  1           // InterfaceMethod java/util/Iterator.hasNext:()Z
     289: ifeq          319
     292: aload_2
     293: invokeinterface #76,  1           // InterfaceMethod java/util/Iterator.next:()Ljava/lang/Object;
     298: checkcast     #53                 // class org/hl7/fhir/dstu3/model/Enumeration
     301: astore_3
     302: aload_1
     303: getfield      #71                 // Field dayOfWeek:Ljava/util/List;
     306: aload_3
     307: invokevirtual #210                // Method org/hl7/fhir/dstu3/model/Enumeration.copy:()Lorg/hl7/fhir/dstu3/model/Enumeration;
     310: invokeinterface #79,  2           // InterfaceMethod java/util/List.add:(Ljava/lang/Object;)Z
     315: pop
     316: goto          283
     319: aload_0
     320: getfield      #82                 // Field timeOfDay:Ljava/util/List;
     323: ifnull        383
     326: aload_1
     327: new           #72                 // class java/util/ArrayList
     330: dup
     331: invokespecial #73                 // Method java/util/ArrayList."<init>":()V
     334: putfield      #82                 // Field timeOfDay:Ljava/util/List;
     337: aload_0
     338: getfield      #82                 // Field timeOfDay:Ljava/util/List;
     341: invokeinterface #74,  1           // InterfaceMethod java/util/List.iterator:()Ljava/util/Iterator;
     346: astore_2
     347: aload_2
     348: invokeinterface #75,  1           // InterfaceMethod java/util/Iterator.hasNext:()Z
     353: ifeq          383
     356: aload_2
     357: invokeinterface #76,  1           // InterfaceMethod java/util/Iterator.next:()Ljava/lang/Object;
     362: checkcast     #83                 // class org/hl7/fhir/dstu3/model/TimeType
     365: astore_3
     366: aload_1
     367: getfield      #82                 // Field timeOfDay:Ljava/util/List;
     370: aload_3
     371: invokevirtual #211                // Method org/hl7/fhir/dstu3/model/TimeType.copy:()Lorg/hl7/fhir/dstu3/model/TimeType;
     374: invokeinterface #79,  2           // InterfaceMethod java/util/List.add:(Ljava/lang/Object;)Z
     379: pop
     380: goto          347
     383: aload_0
     384: getfield      #90                 // Field when:Ljava/util/List;
     387: ifnull        447
     390: aload_1
     391: new           #72                 // class java/util/ArrayList
     394: dup
     395: invokespecial #73                 // Method java/util/ArrayList."<init>":()V
     398: putfield      #90                 // Field when:Ljava/util/List;
     401: aload_0
     402: getfield      #90                 // Field when:Ljava/util/List;
     405: invokeinterface #74,  1           // InterfaceMethod java/util/List.iterator:()Ljava/util/Iterator;
     410: astore_2
     411: aload_2
     412: invokeinterface #75,  1           // InterfaceMethod java/util/Iterator.hasNext:()Z
     417: ifeq          447
     420: aload_2
     421: invokeinterface #76,  1           // InterfaceMethod java/util/Iterator.next:()Ljava/lang/Object;
     426: checkcast     #53                 // class org/hl7/fhir/dstu3/model/Enumeration
     429: astore_3
     430: aload_1
     431: getfield      #90                 // Field when:Ljava/util/List;
     434: aload_3
     435: invokevirtual #210                // Method org/hl7/fhir/dstu3/model/Enumeration.copy:()Lorg/hl7/fhir/dstu3/model/Enumeration;
     438: invokeinterface #79,  2           // InterfaceMethod java/util/List.add:(Ljava/lang/Object;)Z
     443: pop
     444: goto          411
     447: aload_1
     448: aload_0
     449: getfield      #95                 // Field offset:Lorg/hl7/fhir/dstu3/model/UnsignedIntType;
     452: ifnonnull     459
     455: aconst_null
     456: goto          466
     459: aload_0
     460: getfield      #95                 // Field offset:Lorg/hl7/fhir/dstu3/model/UnsignedIntType;
     463: invokevirtual #212                // Method org/hl7/fhir/dstu3/model/UnsignedIntType.copy:()Lorg/hl7/fhir/dstu3/model/UnsignedIntType;
     466: putfield      #95                 // Field offset:Lorg/hl7/fhir/dstu3/model/UnsignedIntType;
     469: aload_1
     470: areturn

  public boolean equalsDeep(org.hl7.fhir.dstu3.model.Base);
    Code:
       0: aload_0
       1: aload_1
       2: invokespecial #213                // Method org/hl7/fhir/dstu3/model/Element.equalsDeep:(Lorg/hl7/fhir/dstu3/model/Base;)Z
       5: ifne          10
       8: iconst_0
       9: ireturn
      10: aload_1
      11: instanceof    #204                // class org/hl7/fhir/dstu3/model/Timing$TimingRepeatComponent
      14: ifne          19
      17: iconst_0
      18: ireturn
      19: aload_1
      20: checkcast     #204                // class org/hl7/fhir/dstu3/model/Timing$TimingRepeatComponent
      23: astore_2
      24: aload_0
      25: getfield      #2                  // Field bounds:Lorg/hl7/fhir/dstu3/model/Type;
      28: aload_2
      29: getfield      #2                  // Field bounds:Lorg/hl7/fhir/dstu3/model/Type;
      32: iconst_1
      33: invokestatic  #214                // Method compareDeep:(Lorg/hl7/fhir/dstu3/model/Base;Lorg/hl7/fhir/dstu3/model/Base;Z)Z
      36: ifeq          253
      39: aload_0
      40: getfield      #23                 // Field count:Lorg/hl7/fhir/dstu3/model/IntegerType;
      43: aload_2
      44: getfield      #23                 // Field count:Lorg/hl7/fhir/dstu3/model/IntegerType;
      47: iconst_1
      48: invokestatic  #214                // Method compareDeep:(Lorg/hl7/fhir/dstu3/model/Base;Lorg/hl7/fhir/dstu3/model/Base;Z)Z
      51: ifeq          253
      54: aload_0
      55: getfield      #37                 // Field countMax:Lorg/hl7/fhir/dstu3/model/IntegerType;
      58: aload_2
      59: getfield      #37                 // Field countMax:Lorg/hl7/fhir/dstu3/model/IntegerType;
      62: iconst_1
      63: invokestatic  #214                // Method compareDeep:(Lorg/hl7/fhir/dstu3/model/Base;Lorg/hl7/fhir/dstu3/model/Base;Z)Z
      66: ifeq          253
      69: aload_0
      70: getfield      #39                 // Field duration:Lorg/hl7/fhir/dstu3/model/DecimalType;
      73: aload_2
      74: getfield      #39                 // Field duration:Lorg/hl7/fhir/dstu3/model/DecimalType;
      77: iconst_1
      78: invokestatic  #214                // Method compareDeep:(Lorg/hl7/fhir/dstu3/model/Base;Lorg/hl7/fhir/dstu3/model/Base;Z)Z
      81: ifeq          253
      84: aload_0
      85: getfield      #49                 // Field durationMax:Lorg/hl7/fhir/dstu3/model/DecimalType;
      88: aload_2
      89: getfield      #49                 // Field durationMax:Lorg/hl7/fhir/dstu3/model/DecimalType;
      92: iconst_1
      93: invokestatic  #214                // Method compareDeep:(Lorg/hl7/fhir/dstu3/model/Base;Lorg/hl7/fhir/dstu3/model/Base;Z)Z
      96: ifeq          253
      99: aload_0
     100: getfield      #51                 // Field durationUnit:Lorg/hl7/fhir/dstu3/model/Enumeration;
     103: aload_2
     104: getfield      #51                 // Field durationUnit:Lorg/hl7/fhir/dstu3/model/Enumeration;
     107: iconst_1
     108: invokestatic  #214                // Method compareDeep:(Lorg/hl7/fhir/dstu3/model/Base;Lorg/hl7/fhir/dstu3/model/Base;Z)Z
     111: ifeq          253
     114: aload_0
     115: getfield      #61                 // Field frequency:Lorg/hl7/fhir/dstu3/model/IntegerType;
     118: aload_2
     119: getfield      #61                 // Field frequency:Lorg/hl7/fhir/dstu3/model/IntegerType;
     122: iconst_1
     123: invokestatic  #214                // Method compareDeep:(Lorg/hl7/fhir/dstu3/model/Base;Lorg/hl7/fhir/dstu3/model/Base;Z)Z
     126: ifeq          253
     129: aload_0
     130: getfield      #63                 // Field frequencyMax:Lorg/hl7/fhir/dstu3/model/IntegerType;
     133: aload_2
     134: getfield      #63                 // Field frequencyMax:Lorg/hl7/fhir/dstu3/model/IntegerType;
     137: iconst_1
     138: invokestatic  #214                // Method compareDeep:(Lorg/hl7/fhir/dstu3/model/Base;Lorg/hl7/fhir/dstu3/model/Base;Z)Z
     141: ifeq          253
     144: aload_0
     145: getfield      #65                 // Field period:Lorg/hl7/fhir/dstu3/model/DecimalType;
     148: aload_2
     149: getfield      #65                 // Field period:Lorg/hl7/fhir/dstu3/model/DecimalType;
     152: iconst_1
     153: invokestatic  #214                // Method compareDeep:(Lorg/hl7/fhir/dstu3/model/Base;Lorg/hl7/fhir/dstu3/model/Base;Z)Z
     156: ifeq          253
     159: aload_0
     160: getfield      #67                 // Field periodMax:Lorg/hl7/fhir/dstu3/model/DecimalType;
     163: aload_2
     164: getfield      #67                 // Field periodMax:Lorg/hl7/fhir/dstu3/model/DecimalType;
     167: iconst_1
     168: invokestatic  #214                // Method compareDeep:(Lorg/hl7/fhir/dstu3/model/Base;Lorg/hl7/fhir/dstu3/model/Base;Z)Z
     171: ifeq          253
     174: aload_0
     175: getfield      #69                 // Field periodUnit:Lorg/hl7/fhir/dstu3/model/Enumeration;
     178: aload_2
     179: getfield      #69                 // Field periodUnit:Lorg/hl7/fhir/dstu3/model/Enumeration;
     182: iconst_1
     183: invokestatic  #214                // Method compareDeep:(Lorg/hl7/fhir/dstu3/model/Base;Lorg/hl7/fhir/dstu3/model/Base;Z)Z
     186: ifeq          253
     189: aload_0
     190: getfield      #71                 // Field dayOfWeek:Ljava/util/List;
     193: aload_2
     194: getfield      #71                 // Field dayOfWeek:Ljava/util/List;
     197: iconst_1
     198: invokestatic  #215                // Method compareDeep:(Ljava/util/List;Ljava/util/List;Z)Z
     201: ifeq          253
     204: aload_0
     205: getfield      #82                 // Field timeOfDay:Ljava/util/List;
     208: aload_2
     209: getfield      #82                 // Field timeOfDay:Ljava/util/List;
     212: iconst_1
     213: invokestatic  #215                // Method compareDeep:(Ljava/util/List;Ljava/util/List;Z)Z
     216: ifeq          253
     219: aload_0
     220: getfield      #90                 // Field when:Ljava/util/List;
     223: aload_2
     224: getfield      #90                 // Field when:Ljava/util/List;
     227: iconst_1
     228: invokestatic  #215                // Method compareDeep:(Ljava/util/List;Ljava/util/List;Z)Z
     231: ifeq          253
     234: aload_0
     235: getfield      #95                 // Field offset:Lorg/hl7/fhir/dstu3/model/UnsignedIntType;
     238: aload_2
     239: getfield      #95                 // Field offset:Lorg/hl7/fhir/dstu3/model/UnsignedIntType;
     242: iconst_1
     243: invokestatic  #214                // Method compareDeep:(Lorg/hl7/fhir/dstu3/model/Base;Lorg/hl7/fhir/dstu3/model/Base;Z)Z
     246: ifeq          253
     249: iconst_1
     250: goto          254
     253: iconst_0
     254: ireturn

  public boolean equalsShallow(org.hl7.fhir.dstu3.model.Base);
    Code:
       0: aload_0
       1: aload_1
       2: invokespecial #216                // Method org/hl7/fhir/dstu3/model/Element.equalsShallow:(Lorg/hl7/fhir/dstu3/model/Base;)Z
       5: ifne          10
       8: iconst_0
       9: ireturn
      10: aload_1
      11: instanceof    #204                // class org/hl7/fhir/dstu3/model/Timing$TimingRepeatComponent
      14: ifne          19
      17: iconst_0
      18: ireturn
      19: aload_1
      20: checkcast     #204                // class org/hl7/fhir/dstu3/model/Timing$TimingRepeatComponent
      23: astore_2
      24: aload_0
      25: getfield      #23                 // Field count:Lorg/hl7/fhir/dstu3/model/IntegerType;
      28: aload_2
      29: getfield      #23                 // Field count:Lorg/hl7/fhir/dstu3/model/IntegerType;
      32: iconst_1
      33: invokestatic  #217                // Method compareValues:(Lorg/hl7/fhir/dstu3/model/PrimitiveType;Lorg/hl7/fhir/dstu3/model/PrimitiveType;Z)Z
      36: ifeq          238
      39: aload_0
      40: getfield      #37                 // Field countMax:Lorg/hl7/fhir/dstu3/model/IntegerType;
      43: aload_2
      44: getfield      #37                 // Field countMax:Lorg/hl7/fhir/dstu3/model/IntegerType;
      47: iconst_1
      48: invokestatic  #217                // Method compareValues:(Lorg/hl7/fhir/dstu3/model/PrimitiveType;Lorg/hl7/fhir/dstu3/model/PrimitiveType;Z)Z
      51: ifeq          238
      54: aload_0
      55: getfield      #39                 // Field duration:Lorg/hl7/fhir/dstu3/model/DecimalType;
      58: aload_2
      59: getfield      #39                 // Field duration:Lorg/hl7/fhir/dstu3/model/DecimalType;
      62: iconst_1
      63: invokestatic  #217                // Method compareValues:(Lorg/hl7/fhir/dstu3/model/PrimitiveType;Lorg/hl7/fhir/dstu3/model/PrimitiveType;Z)Z
      66: ifeq          238
      69: aload_0
      70: getfield      #49                 // Field durationMax:Lorg/hl7/fhir/dstu3/model/DecimalType;
      73: aload_2
      74: getfield      #49                 // Field durationMax:Lorg/hl7/fhir/dstu3/model/DecimalType;
      77: iconst_1
      78: invokestatic  #217                // Method compareValues:(Lorg/hl7/fhir/dstu3/model/PrimitiveType;Lorg/hl7/fhir/dstu3/model/PrimitiveType;Z)Z
      81: ifeq          238
      84: aload_0
      85: getfield      #51                 // Field durationUnit:Lorg/hl7/fhir/dstu3/model/Enumeration;
      88: aload_2
      89: getfield      #51                 // Field durationUnit:Lorg/hl7/fhir/dstu3/model/Enumeration;
      92: iconst_1
      93: invokestatic  #217                // Method compareValues:(Lorg/hl7/fhir/dstu3/model/PrimitiveType;Lorg/hl7/fhir/dstu3/model/PrimitiveType;Z)Z
      96: ifeq          238
      99: aload_0
     100: getfield      #61                 // Field frequency:Lorg/hl7/fhir/dstu3/model/IntegerType;
     103: aload_2
     104: getfield      #61                 // Field frequency:Lorg/hl7/fhir/dstu3/model/IntegerType;
     107: iconst_1
     108: invokestatic  #217                // Method compareValues:(Lorg/hl7/fhir/dstu3/model/PrimitiveType;Lorg/hl7/fhir/dstu3/model/PrimitiveType;Z)Z
     111: ifeq          238
     114: aload_0
     115: getfield      #63                 // Field frequencyMax:Lorg/hl7/fhir/dstu3/model/IntegerType;
     118: aload_2
     119: getfield      #63                 // Field frequencyMax:Lorg/hl7/fhir/dstu3/model/IntegerType;
     122: iconst_1
     123: invokestatic  #217                // Method compareValues:(Lorg/hl7/fhir/dstu3/model/PrimitiveType;Lorg/hl7/fhir/dstu3/model/PrimitiveType;Z)Z
     126: ifeq          238
     129: aload_0
     130: getfield      #65                 // Field period:Lorg/hl7/fhir/dstu3/model/DecimalType;
     133: aload_2
     134: getfield      #65                 // Field period:Lorg/hl7/fhir/dstu3/model/DecimalType;
     137: iconst_1
     138: invokestatic  #217                // Method compareValues:(Lorg/hl7/fhir/dstu3/model/PrimitiveType;Lorg/hl7/fhir/dstu3/model/PrimitiveType;Z)Z
     141: ifeq          238
     144: aload_0
     145: getfield      #67                 // Field periodMax:Lorg/hl7/fhir/dstu3/model/DecimalType;
     148: aload_2
     149: getfield      #67                 // Field periodMax:Lorg/hl7/fhir/dstu3/model/DecimalType;
     152: iconst_1
     153: invokestatic  #217                // Method compareValues:(Lorg/hl7/fhir/dstu3/model/PrimitiveType;Lorg/hl7/fhir/dstu3/model/PrimitiveType;Z)Z
     156: ifeq          238
     159: aload_0
     160: getfield      #69                 // Field periodUnit:Lorg/hl7/fhir/dstu3/model/Enumeration;
     163: aload_2
     164: getfield      #69                 // Field periodUnit:Lorg/hl7/fhir/dstu3/model/Enumeration;
     167: iconst_1
     168: invokestatic  #217                // Method compareValues:(Lorg/hl7/fhir/dstu3/model/PrimitiveType;Lorg/hl7/fhir/dstu3/model/PrimitiveType;Z)Z
     171: ifeq          238
     174: aload_0
     175: getfield      #71                 // Field dayOfWeek:Ljava/util/List;
     178: aload_2
     179: getfield      #71                 // Field dayOfWeek:Ljava/util/List;
     182: iconst_1
     183: invokestatic  #218                // Method compareValues:(Ljava/util/List;Ljava/util/List;Z)Z
     186: ifeq          238
     189: aload_0
     190: getfield      #82                 // Field timeOfDay:Ljava/util/List;
     193: aload_2
     194: getfield      #82                 // Field timeOfDay:Ljava/util/List;
     197: iconst_1
     198: invokestatic  #218                // Method compareValues:(Ljava/util/List;Ljava/util/List;Z)Z
     201: ifeq          238
     204: aload_0
     205: getfield      #90                 // Field when:Ljava/util/List;
     208: aload_2
     209: getfield      #90                 // Field when:Ljava/util/List;
     212: iconst_1
     213: invokestatic  #218                // Method compareValues:(Ljava/util/List;Ljava/util/List;Z)Z
     216: ifeq          238
     219: aload_0
     220: getfield      #95                 // Field offset:Lorg/hl7/fhir/dstu3/model/UnsignedIntType;
     223: aload_2
     224: getfield      #95                 // Field offset:Lorg/hl7/fhir/dstu3/model/UnsignedIntType;
     227: iconst_1
     228: invokestatic  #217                // Method compareValues:(Lorg/hl7/fhir/dstu3/model/PrimitiveType;Lorg/hl7/fhir/dstu3/model/PrimitiveType;Z)Z
     231: ifeq          238
     234: iconst_1
     235: goto          239
     238: iconst_0
     239: ireturn

  public boolean isEmpty();
    Code:
       0: aload_0
       1: invokespecial #219                // Method org/hl7/fhir/dstu3/model/Element.isEmpty:()Z
       4: ifeq          136
       7: bipush        15
       9: anewarray     #220                // class java/lang/Object
      12: dup
      13: iconst_0
      14: aload_0
      15: getfield      #2                  // Field bounds:Lorg/hl7/fhir/dstu3/model/Type;
      18: aastore
      19: dup
      20: iconst_1
      21: aload_0
      22: getfield      #23                 // Field count:Lorg/hl7/fhir/dstu3/model/IntegerType;
      25: aastore
      26: dup
      27: iconst_2
      28: aload_0
      29: getfield      #37                 // Field countMax:Lorg/hl7/fhir/dstu3/model/IntegerType;
      32: aastore
      33: dup
      34: iconst_3
      35: aload_0
      36: getfield      #39                 // Field duration:Lorg/hl7/fhir/dstu3/model/DecimalType;
      39: aastore
      40: dup
      41: iconst_4
      42: aload_0
      43: getfield      #49                 // Field durationMax:Lorg/hl7/fhir/dstu3/model/DecimalType;
      46: aastore
      47: dup
      48: iconst_5
      49: aload_0
      50: getfield      #51                 // Field durationUnit:Lorg/hl7/fhir/dstu3/model/Enumeration;
      53: aastore
      54: dup
      55: bipush        6
      57: aload_0
      58: getfield      #61                 // Field frequency:Lorg/hl7/fhir/dstu3/model/IntegerType;
      61: aastore
      62: dup
      63: bipush        7
      65: aload_0
      66: getfield      #63                 // Field frequencyMax:Lorg/hl7/fhir/dstu3/model/IntegerType;
      69: aastore
      70: dup
      71: bipush        8
      73: aload_0
      74: getfield      #65                 // Field period:Lorg/hl7/fhir/dstu3/model/DecimalType;
      77: aastore
      78: dup
      79: bipush        9
      81: aload_0
      82: getfield      #67                 // Field periodMax:Lorg/hl7/fhir/dstu3/model/DecimalType;
      85: aastore
      86: dup
      87: bipush        10
      89: aload_0
      90: getfield      #69                 // Field periodUnit:Lorg/hl7/fhir/dstu3/model/Enumeration;
      93: aastore
      94: dup
      95: bipush        11
      97: aload_0
      98: getfield      #71                 // Field dayOfWeek:Ljava/util/List;
     101: aastore
     102: dup
     103: bipush        12
     105: aload_0
     106: getfield      #82                 // Field timeOfDay:Ljava/util/List;
     109: aastore
     110: dup
     111: bipush        13
     113: aload_0
     114: getfield      #90                 // Field when:Ljava/util/List;
     117: aastore
     118: dup
     119: bipush        14
     121: aload_0
     122: getfield      #95                 // Field offset:Lorg/hl7/fhir/dstu3/model/UnsignedIntType;
     125: aastore
     126: invokestatic  #221                // Method ca/uhn/fhir/util/ElementUtil.isEmpty:([Ljava/lang/Object;)Z
     129: ifeq          136
     132: iconst_1
     133: goto          137
     136: iconst_0
     137: ireturn

  public java.lang.String fhirType();
    Code:
       0: ldc           #222                // String Timing.repeat
       2: areturn

  public org.hl7.fhir.dstu3.model.Element copy();
    Code:
       0: aload_0
       1: invokevirtual #223                // Method copy:()Lorg/hl7/fhir/dstu3/model/Timing$TimingRepeatComponent;
       4: areturn
}
