Compiled from "UuidType.java"
public class org.hl7.fhir.dstu3.model.UuidType extends org.hl7.fhir.dstu3.model.UriType {
  private static final long serialVersionUID;

  public org.hl7.fhir.dstu3.model.UuidType();
    Code:
       0: aload_0
       1: invokespecial #1                  // Method org/hl7/fhir/dstu3/model/UriType."<init>":()V
       4: return

  public org.hl7.fhir.dstu3.model.UuidType(java.lang.String);
    Code:
       0: aload_0
       1: aload_1
       2: invokespecial #2                  // Method org/hl7/fhir/dstu3/model/UriType."<init>":(Ljava/lang/String;)V
       5: return

  public org.hl7.fhir.dstu3.model.UuidType(java.net.URI);
    Code:
       0: aload_0
       1: aload_1
       2: invokespecial #3                  // Method org/hl7/fhir/dstu3/model/UriType."<init>":(Ljava/net/URI;)V
       5: return

  public org.hl7.fhir.dstu3.model.UuidType copy();
    Code:
       0: new           #4                  // class org/hl7/fhir/dstu3/model/UuidType
       3: dup
       4: aload_0
       5: invokevirtual #5                  // Method getValue:()Ljava/lang/Object;
       8: checkcast     #6                  // class java/lang/String
      11: invokespecial #7                  // Method "<init>":(Ljava/lang/String;)V
      14: areturn

  public java.lang.String fhirType();
    Code:
       0: ldc           #8                  // String uuid
       2: areturn

  public org.hl7.fhir.dstu3.model.UriType copy();
    Code:
       0: aload_0
       1: invokevirtual #9                  // Method copy:()Lorg/hl7/fhir/dstu3/model/UuidType;
       4: areturn

  public org.hl7.fhir.dstu3.model.Type copy();
    Code:
       0: aload_0
       1: invokevirtual #9                  // Method copy:()Lorg/hl7/fhir/dstu3/model/UuidType;
       4: areturn

  public org.hl7.fhir.dstu3.model.Element copy();
    Code:
       0: aload_0
       1: invokevirtual #9                  // Method copy:()Lorg/hl7/fhir/dstu3/model/UuidType;
       4: areturn
}
