Compiled from "Lifecycle.java"
public class org.apache.bookkeeper.common.component.Lifecycle {
  private volatile org.apache.bookkeeper.common.component.Lifecycle$State state;

  public org.apache.bookkeeper.common.component.Lifecycle();
    Code:
       0: aload_0
       1: invokespecial #1                  // Method java/lang/Object."<init>":()V
       4: aload_0
       5: getstatic     #2                  // Field org/apache/bookkeeper/common/component/Lifecycle$State.INITIALIZED:Lorg/apache/bookkeeper/common/component/Lifecycle$State;
       8: putfield      #3                  // Field state:Lorg/apache/bookkeeper/common/component/Lifecycle$State;
      11: return

  public org.apache.bookkeeper.common.component.Lifecycle$State state();
    Code:
       0: aload_0
       1: getfield      #3                  // Field state:Lorg/apache/bookkeeper/common/component/Lifecycle$State;
       4: areturn

  public boolean initialized();
    Code:
       0: aload_0
       1: getfield      #3                  // Field state:Lorg/apache/bookkeeper/common/component/Lifecycle$State;
       4: getstatic     #2                  // Field org/apache/bookkeeper/common/component/Lifecycle$State.INITIALIZED:Lorg/apache/bookkeeper/common/component/Lifecycle$State;
       7: if_acmpne     14
      10: iconst_1
      11: goto          15
      14: iconst_0
      15: ireturn

  public boolean started();
    Code:
       0: aload_0
       1: getfield      #3                  // Field state:Lorg/apache/bookkeeper/common/component/Lifecycle$State;
       4: getstatic     #4                  // Field org/apache/bookkeeper/common/component/Lifecycle$State.STARTED:Lorg/apache/bookkeeper/common/component/Lifecycle$State;
       7: if_acmpne     14
      10: iconst_1
      11: goto          15
      14: iconst_0
      15: ireturn

  public boolean stopped();
    Code:
       0: aload_0
       1: getfield      #3                  // Field state:Lorg/apache/bookkeeper/common/component/Lifecycle$State;
       4: getstatic     #5                  // Field org/apache/bookkeeper/common/component/Lifecycle$State.STOPPED:Lorg/apache/bookkeeper/common/component/Lifecycle$State;
       7: if_acmpne     14
      10: iconst_1
      11: goto          15
      14: iconst_0
      15: ireturn

  public boolean closed();
    Code:
       0: aload_0
       1: getfield      #3                  // Field state:Lorg/apache/bookkeeper/common/component/Lifecycle$State;
       4: getstatic     #6                  // Field org/apache/bookkeeper/common/component/Lifecycle$State.CLOSED:Lorg/apache/bookkeeper/common/component/Lifecycle$State;
       7: if_acmpne     14
      10: iconst_1
      11: goto          15
      14: iconst_0
      15: ireturn

  public boolean stoppedOrClosed();
    Code:
       0: aload_0
       1: getfield      #3                  // Field state:Lorg/apache/bookkeeper/common/component/Lifecycle$State;
       4: astore_1
       5: aload_1
       6: getstatic     #5                  // Field org/apache/bookkeeper/common/component/Lifecycle$State.STOPPED:Lorg/apache/bookkeeper/common/component/Lifecycle$State;
       9: if_acmpeq     19
      12: aload_1
      13: getstatic     #6                  // Field org/apache/bookkeeper/common/component/Lifecycle$State.CLOSED:Lorg/apache/bookkeeper/common/component/Lifecycle$State;
      16: if_acmpne     23
      19: iconst_1
      20: goto          24
      23: iconst_0
      24: ireturn

  public boolean canMoveToStarted() throws java.lang.IllegalStateException;
    Code:
       0: aload_0
       1: getfield      #3                  // Field state:Lorg/apache/bookkeeper/common/component/Lifecycle$State;
       4: astore_1
       5: aload_1
       6: getstatic     #2                  // Field org/apache/bookkeeper/common/component/Lifecycle$State.INITIALIZED:Lorg/apache/bookkeeper/common/component/Lifecycle$State;
       9: if_acmpeq     19
      12: aload_1
      13: getstatic     #5                  // Field org/apache/bookkeeper/common/component/Lifecycle$State.STOPPED:Lorg/apache/bookkeeper/common/component/Lifecycle$State;
      16: if_acmpne     21
      19: iconst_1
      20: ireturn
      21: aload_1
      22: getstatic     #4                  // Field org/apache/bookkeeper/common/component/Lifecycle$State.STARTED:Lorg/apache/bookkeeper/common/component/Lifecycle$State;
      25: if_acmpne     30
      28: iconst_0
      29: ireturn
      30: aload_1
      31: getstatic     #6                  // Field org/apache/bookkeeper/common/component/Lifecycle$State.CLOSED:Lorg/apache/bookkeeper/common/component/Lifecycle$State;
      34: if_acmpne     47
      37: new           #7                  // class java/lang/IllegalStateException
      40: dup
      41: ldc           #8                  // String Can\'t move to started state when closed
      43: invokespecial #9                  // Method java/lang/IllegalStateException."<init>":(Ljava/lang/String;)V
      46: athrow
      47: new           #7                  // class java/lang/IllegalStateException
      50: dup
      51: ldc           #10                 // String Can\'t move to started with unknown state
      53: invokespecial #9                  // Method java/lang/IllegalStateException."<init>":(Ljava/lang/String;)V
      56: athrow

  public boolean moveToStarted() throws java.lang.IllegalStateException;
    Code:
       0: aload_0
       1: getfield      #3                  // Field state:Lorg/apache/bookkeeper/common/component/Lifecycle$State;
       4: astore_1
       5: aload_1
       6: getstatic     #2                  // Field org/apache/bookkeeper/common/component/Lifecycle$State.INITIALIZED:Lorg/apache/bookkeeper/common/component/Lifecycle$State;
       9: if_acmpeq     19
      12: aload_1
      13: getstatic     #5                  // Field org/apache/bookkeeper/common/component/Lifecycle$State.STOPPED:Lorg/apache/bookkeeper/common/component/Lifecycle$State;
      16: if_acmpne     28
      19: aload_0
      20: getstatic     #4                  // Field org/apache/bookkeeper/common/component/Lifecycle$State.STARTED:Lorg/apache/bookkeeper/common/component/Lifecycle$State;
      23: putfield      #3                  // Field state:Lorg/apache/bookkeeper/common/component/Lifecycle$State;
      26: iconst_1
      27: ireturn
      28: aload_1
      29: getstatic     #4                  // Field org/apache/bookkeeper/common/component/Lifecycle$State.STARTED:Lorg/apache/bookkeeper/common/component/Lifecycle$State;
      32: if_acmpne     37
      35: iconst_0
      36: ireturn
      37: aload_1
      38: getstatic     #6                  // Field org/apache/bookkeeper/common/component/Lifecycle$State.CLOSED:Lorg/apache/bookkeeper/common/component/Lifecycle$State;
      41: if_acmpne     54
      44: new           #7                  // class java/lang/IllegalStateException
      47: dup
      48: ldc           #8                  // String Can\'t move to started state when closed
      50: invokespecial #9                  // Method java/lang/IllegalStateException."<init>":(Ljava/lang/String;)V
      53: athrow
      54: new           #7                  // class java/lang/IllegalStateException
      57: dup
      58: ldc           #10                 // String Can\'t move to started with unknown state
      60: invokespecial #9                  // Method java/lang/IllegalStateException."<init>":(Ljava/lang/String;)V
      63: athrow

  public boolean canMoveToStopped() throws java.lang.IllegalStateException;
    Code:
       0: aload_0
       1: getfield      #3                  // Field state:Lorg/apache/bookkeeper/common/component/Lifecycle$State;
       4: astore_1
       5: aload_1
       6: getstatic     #4                  // Field org/apache/bookkeeper/common/component/Lifecycle$State.STARTED:Lorg/apache/bookkeeper/common/component/Lifecycle$State;
       9: if_acmpne     14
      12: iconst_1
      13: ireturn
      14: aload_1
      15: getstatic     #2                  // Field org/apache/bookkeeper/common/component/Lifecycle$State.INITIALIZED:Lorg/apache/bookkeeper/common/component/Lifecycle$State;
      18: if_acmpeq     28
      21: aload_1
      22: getstatic     #5                  // Field org/apache/bookkeeper/common/component/Lifecycle$State.STOPPED:Lorg/apache/bookkeeper/common/component/Lifecycle$State;
      25: if_acmpne     30
      28: iconst_0
      29: ireturn
      30: aload_1
      31: getstatic     #6                  // Field org/apache/bookkeeper/common/component/Lifecycle$State.CLOSED:Lorg/apache/bookkeeper/common/component/Lifecycle$State;
      34: if_acmpne     47
      37: new           #7                  // class java/lang/IllegalStateException
      40: dup
      41: ldc           #11                 // String Can\'t move to stopped state when closed
      43: invokespecial #9                  // Method java/lang/IllegalStateException."<init>":(Ljava/lang/String;)V
      46: athrow
      47: new           #7                  // class java/lang/IllegalStateException
      50: dup
      51: ldc           #12                 // String Can\'t move to stopped with unknown state
      53: invokespecial #9                  // Method java/lang/IllegalStateException."<init>":(Ljava/lang/String;)V
      56: athrow

  public boolean moveToStopped() throws java.lang.IllegalStateException;
    Code:
       0: aload_0
       1: getfield      #3                  // Field state:Lorg/apache/bookkeeper/common/component/Lifecycle$State;
       4: astore_1
       5: aload_1
       6: getstatic     #4                  // Field org/apache/bookkeeper/common/component/Lifecycle$State.STARTED:Lorg/apache/bookkeeper/common/component/Lifecycle$State;
       9: if_acmpne     21
      12: aload_0
      13: getstatic     #5                  // Field org/apache/bookkeeper/common/component/Lifecycle$State.STOPPED:Lorg/apache/bookkeeper/common/component/Lifecycle$State;
      16: putfield      #3                  // Field state:Lorg/apache/bookkeeper/common/component/Lifecycle$State;
      19: iconst_1
      20: ireturn
      21: aload_1
      22: getstatic     #2                  // Field org/apache/bookkeeper/common/component/Lifecycle$State.INITIALIZED:Lorg/apache/bookkeeper/common/component/Lifecycle$State;
      25: if_acmpeq     35
      28: aload_1
      29: getstatic     #5                  // Field org/apache/bookkeeper/common/component/Lifecycle$State.STOPPED:Lorg/apache/bookkeeper/common/component/Lifecycle$State;
      32: if_acmpne     37
      35: iconst_0
      36: ireturn
      37: aload_1
      38: getstatic     #6                  // Field org/apache/bookkeeper/common/component/Lifecycle$State.CLOSED:Lorg/apache/bookkeeper/common/component/Lifecycle$State;
      41: if_acmpne     54
      44: new           #7                  // class java/lang/IllegalStateException
      47: dup
      48: ldc           #11                 // String Can\'t move to stopped state when closed
      50: invokespecial #9                  // Method java/lang/IllegalStateException."<init>":(Ljava/lang/String;)V
      53: athrow
      54: new           #7                  // class java/lang/IllegalStateException
      57: dup
      58: ldc           #12                 // String Can\'t move to stopped with unknown state
      60: invokespecial #9                  // Method java/lang/IllegalStateException."<init>":(Ljava/lang/String;)V
      63: athrow

  public boolean canMoveToClosed() throws java.lang.IllegalStateException;
    Code:
       0: aload_0
       1: getfield      #3                  // Field state:Lorg/apache/bookkeeper/common/component/Lifecycle$State;
       4: astore_1
       5: aload_1
       6: getstatic     #6                  // Field org/apache/bookkeeper/common/component/Lifecycle$State.CLOSED:Lorg/apache/bookkeeper/common/component/Lifecycle$State;
       9: if_acmpne     14
      12: iconst_0
      13: ireturn
      14: aload_1
      15: getstatic     #4                  // Field org/apache/bookkeeper/common/component/Lifecycle$State.STARTED:Lorg/apache/bookkeeper/common/component/Lifecycle$State;
      18: if_acmpne     31
      21: new           #7                  // class java/lang/IllegalStateException
      24: dup
      25: ldc           #13                 // String Can\'t move to closed before moving to stopped mode
      27: invokespecial #9                  // Method java/lang/IllegalStateException."<init>":(Ljava/lang/String;)V
      30: athrow
      31: iconst_1
      32: ireturn

  public boolean moveToClosed() throws java.lang.IllegalStateException;
    Code:
       0: aload_0
       1: getfield      #3                  // Field state:Lorg/apache/bookkeeper/common/component/Lifecycle$State;
       4: astore_1
       5: aload_1
       6: getstatic     #6                  // Field org/apache/bookkeeper/common/component/Lifecycle$State.CLOSED:Lorg/apache/bookkeeper/common/component/Lifecycle$State;
       9: if_acmpne     14
      12: iconst_0
      13: ireturn
      14: aload_1
      15: getstatic     #4                  // Field org/apache/bookkeeper/common/component/Lifecycle$State.STARTED:Lorg/apache/bookkeeper/common/component/Lifecycle$State;
      18: if_acmpne     31
      21: new           #7                  // class java/lang/IllegalStateException
      24: dup
      25: ldc           #13                 // String Can\'t move to closed before moving to stopped mode
      27: invokespecial #9                  // Method java/lang/IllegalStateException."<init>":(Ljava/lang/String;)V
      30: athrow
      31: aload_0
      32: getstatic     #6                  // Field org/apache/bookkeeper/common/component/Lifecycle$State.CLOSED:Lorg/apache/bookkeeper/common/component/Lifecycle$State;
      35: putfield      #3                  // Field state:Lorg/apache/bookkeeper/common/component/Lifecycle$State;
      38: iconst_1
      39: ireturn

  public java.lang.String toString();
    Code:
       0: aload_0
       1: getfield      #3                  // Field state:Lorg/apache/bookkeeper/common/component/Lifecycle$State;
       4: invokevirtual #14                 // Method org/apache/bookkeeper/common/component/Lifecycle$State.toString:()Ljava/lang/String;
       7: areturn
}
