Compiled from "DataSourceBuilder.java"
public class org.apache.axis2.builder.DataSourceBuilder$ByteArrayDataSourceEx extends org.apache.axiom.attachments.ByteArrayDataSource implements org.apache.axiom.om.OMDataSource {
  private byte[] bytes;

  final org.apache.axis2.builder.DataSourceBuilder this$0;

  public org.apache.axis2.builder.DataSourceBuilder$ByteArrayDataSourceEx(org.apache.axis2.builder.DataSourceBuilder, byte[], java.lang.String);
    Code:
       0: aload_0
       1: aload_1
       2: putfield      #1                  // Field this$0:Lorg/apache/axis2/builder/DataSourceBuilder;
       5: aload_0
       6: aload_2
       7: aload_3
       8: invokespecial #2                  // Method org/apache/axiom/attachments/ByteArrayDataSource."<init>":([BLjava/lang/String;)V
      11: aload_0
      12: aload_2
      13: putfield      #3                  // Field bytes:[B
      16: return

  public void serialize(java.io.OutputStream, org.apache.axiom.om.OMOutputFormat) throws javax.xml.stream.XMLStreamException;
    Code:
       0: aload_1
       1: aload_0
       2: getfield      #3                  // Field bytes:[B
       5: invokevirtual #4                  // Method java/io/OutputStream.write:([B)V
       8: goto          21
      11: astore_3
      12: new           #6                  // class javax/xml/stream/XMLStreamException
      15: dup
      16: aload_3
      17: invokespecial #7                  // Method javax/xml/stream/XMLStreamException."<init>":(Ljava/lang/Throwable;)V
      20: athrow
      21: return
    Exception table:
       from    to  target type
           0     8    11   Class java/io/IOException

  public java.lang.String getContentType();
    Code:
       0: aload_0
       1: invokespecial #8                  // Method org/apache/axiom/attachments/ByteArrayDataSource.getContentType:()Ljava/lang/String;
       4: areturn

  public void serialize(java.io.Writer, org.apache.axiom.om.OMOutputFormat) throws javax.xml.stream.XMLStreamException;
    Code:
       0: new           #9                  // class java/lang/UnsupportedOperationException
       3: dup
       4: ldc           #10                 // String FIXME
       6: invokespecial #11                 // Method java/lang/UnsupportedOperationException."<init>":(Ljava/lang/String;)V
       9: athrow

  public void serialize(javax.xml.stream.XMLStreamWriter) throws javax.xml.stream.XMLStreamException;
    Code:
       0: new           #9                  // class java/lang/UnsupportedOperationException
       3: dup
       4: ldc           #10                 // String FIXME
       6: invokespecial #11                 // Method java/lang/UnsupportedOperationException."<init>":(Ljava/lang/String;)V
       9: athrow

  public javax.xml.stream.XMLStreamReader getReader() throws javax.xml.stream.XMLStreamException;
    Code:
       0: new           #9                  // class java/lang/UnsupportedOperationException
       3: dup
       4: ldc           #10                 // String FIXME
       6: invokespecial #11                 // Method java/lang/UnsupportedOperationException."<init>":(Ljava/lang/String;)V
       9: athrow
}
