Compiled from "HttpContentCompressor.java"
final class io.netty.handler.codec.http.HttpContentCompressor$ZstdEncoderFactory implements io.netty.handler.codec.http.CompressionEncoderFactory {
  final io.netty.handler.codec.http.HttpContentCompressor this$0;

  private io.netty.handler.codec.http.HttpContentCompressor$ZstdEncoderFactory(io.netty.handler.codec.http.HttpContentCompressor);
    Code:
       0: aload_0
       1: aload_1
       2: putfield      #2                  // Field this$0:Lio/netty/handler/codec/http/HttpContentCompressor;
       5: aload_0
       6: invokespecial #3                  // Method java/lang/Object."<init>":()V
       9: return

  public io.netty.handler.codec.MessageToByteEncoder<io.netty.buffer.ByteBuf> createEncoder();
    Code:
       0: new           #4                  // class io/netty/handler/codec/compression/ZstdEncoder
       3: dup
       4: aload_0
       5: getfield      #2                  // Field this$0:Lio/netty/handler/codec/http/HttpContentCompressor;
       8: invokestatic  #5                  // Method io/netty/handler/codec/http/HttpContentCompressor.access$700:(Lio/netty/handler/codec/http/HttpContentCompressor;)Lio/netty/handler/codec/compression/ZstdOptions;
      11: invokevirtual #6                  // Method io/netty/handler/codec/compression/ZstdOptions.compressionLevel:()I
      14: aload_0
      15: getfield      #2                  // Field this$0:Lio/netty/handler/codec/http/HttpContentCompressor;
      18: invokestatic  #5                  // Method io/netty/handler/codec/http/HttpContentCompressor.access$700:(Lio/netty/handler/codec/http/HttpContentCompressor;)Lio/netty/handler/codec/compression/ZstdOptions;
      21: invokevirtual #7                  // Method io/netty/handler/codec/compression/ZstdOptions.blockSize:()I
      24: aload_0
      25: getfield      #2                  // Field this$0:Lio/netty/handler/codec/http/HttpContentCompressor;
      28: invokestatic  #5                  // Method io/netty/handler/codec/http/HttpContentCompressor.access$700:(Lio/netty/handler/codec/http/HttpContentCompressor;)Lio/netty/handler/codec/compression/ZstdOptions;
      31: invokevirtual #8                  // Method io/netty/handler/codec/compression/ZstdOptions.maxEncodeSize:()I
      34: invokespecial #9                  // Method io/netty/handler/codec/compression/ZstdEncoder."<init>":(III)V
      37: areturn

  io.netty.handler.codec.http.HttpContentCompressor$ZstdEncoderFactory(io.netty.handler.codec.http.HttpContentCompressor, io.netty.handler.codec.http.HttpContentCompressor$1);
    Code:
       0: aload_0
       1: aload_1
       2: invokespecial #1                  // Method "<init>":(Lio/netty/handler/codec/http/HttpContentCompressor;)V
       5: return
}
