Compiled from "Token.java"
final class org.jsoup.parser.Token$Character extends org.jsoup.parser.Token {
  private java.lang.String data;

  org.jsoup.parser.Token$Character();
    Code:
       0: aload_0
       1: aconst_null
       2: invokespecial #1                  // Method org/jsoup/parser/Token."<init>":(Lorg/jsoup/parser/Token$1;)V
       5: aload_0
       6: getstatic     #2                  // Field org/jsoup/parser/Token$TokenType.Character:Lorg/jsoup/parser/Token$TokenType;
       9: putfield      #3                  // Field type:Lorg/jsoup/parser/Token$TokenType;
      12: return

  org.jsoup.parser.Token reset();
    Code:
       0: aload_0
       1: aconst_null
       2: putfield      #4                  // Field data:Ljava/lang/String;
       5: aload_0
       6: areturn

  org.jsoup.parser.Token$Character data(java.lang.String);
    Code:
       0: aload_0
       1: aload_1
       2: putfield      #4                  // Field data:Ljava/lang/String;
       5: aload_0
       6: areturn

  java.lang.String getData();
    Code:
       0: aload_0
       1: getfield      #4                  // Field data:Ljava/lang/String;
       4: areturn

  public java.lang.String toString();
    Code:
       0: aload_0
       1: invokevirtual #5                  // Method getData:()Ljava/lang/String;
       4: areturn
}
