Compiled from "LinkedDataFetchingException.java"
public class won.protocol.rest.LinkedDataFetchingException extends java.lang.RuntimeException {
  private java.net.URI resourceUri;

  public won.protocol.rest.LinkedDataFetchingException(java.net.URI);
    Code:
       0: aload_0
       1: aload_1
       2: ldc           #1                  // String Error fetching linked data for {0}
       4: iconst_1
       5: anewarray     #2                  // class java/lang/Object
       8: dup
       9: iconst_0
      10: aload_1
      11: aastore
      12: invokestatic  #3                  // Method java/text/MessageFormat.format:(Ljava/lang/String;[Ljava/lang/Object;)Ljava/lang/String;
      15: aconst_null
      16: invokespecial #4                  // Method "<init>":(Ljava/net/URI;Ljava/lang/String;Ljava/lang/Throwable;)V
      19: return

  public won.protocol.rest.LinkedDataFetchingException(java.net.URI, java.lang.String, java.lang.Throwable);
    Code:
       0: aload_0
       1: aload_2
       2: aload_3
       3: invokespecial #5                  // Method java/lang/RuntimeException."<init>":(Ljava/lang/String;Ljava/lang/Throwable;)V
       6: aload_0
       7: aload_1
       8: putfield      #6                  // Field resourceUri:Ljava/net/URI;
      11: return

  public won.protocol.rest.LinkedDataFetchingException(java.net.URI, java.lang.String);
    Code:
       0: aload_0
       1: aload_1
       2: aload_2
       3: aconst_null
       4: invokespecial #4                  // Method "<init>":(Ljava/net/URI;Ljava/lang/String;Ljava/lang/Throwable;)V
       7: return

  public won.protocol.rest.LinkedDataFetchingException(java.net.URI, java.lang.Throwable);
    Code:
       0: aload_0
       1: aload_1
       2: ldc           #1                  // String Error fetching linked data for {0}
       4: iconst_1
       5: anewarray     #2                  // class java/lang/Object
       8: dup
       9: iconst_0
      10: aload_1
      11: aastore
      12: invokestatic  #3                  // Method java/text/MessageFormat.format:(Ljava/lang/String;[Ljava/lang/Object;)Ljava/lang/String;
      15: aload_2
      16: invokespecial #4                  // Method "<init>":(Ljava/net/URI;Ljava/lang/String;Ljava/lang/Throwable;)V
      19: return

  public java.net.URI getResourceUri();
    Code:
       0: aload_0
       1: getfield      #6                  // Field resourceUri:Ljava/net/URI;
       4: areturn
}
