Compiled from "EndpointConfigFactory.java"
public final class org.jboss.as.remoting.EndpointConfigFactory {
  private org.jboss.as.remoting.EndpointConfigFactory();
    Code:
       0: aload_0
       1: invokespecial #1                  // Method java/lang/Object."<init>":()V
       4: return

  public static org.xnio.OptionMap populate(org.jboss.as.controller.ExpressionResolver, org.jboss.dmr.ModelNode) throws org.jboss.as.controller.OperationFailedException;
    Code:
       0: invokestatic  #2                  // Method org/xnio/OptionMap.builder:()Lorg/xnio/OptionMap$Builder;
       3: getstatic     #3                  // Field org/xnio/Options.TCP_NODELAY:Lorg/xnio/Option;
       6: getstatic     #4                  // Field java/lang/Boolean.TRUE:Ljava/lang/Boolean;
       9: invokevirtual #5                  // Method org/xnio/OptionMap$Builder.set:(Lorg/xnio/Option;Ljava/lang/Object;)Lorg/xnio/OptionMap$Builder;
      12: getstatic     #6                  // Field org/xnio/Options.REUSE_ADDRESSES:Lorg/xnio/Option;
      15: iconst_1
      16: invokevirtual #7                  // Method org/xnio/OptionMap$Builder.set:(Lorg/xnio/Option;Z)Lorg/xnio/OptionMap$Builder;
      19: aload_0
      20: aload_1
      21: getstatic     #8                  // Field org/jboss/as/remoting/RemotingEndpointResource.OPTIONS:Ljava/util/List;
      24: invokestatic  #9                  // Method org/wildfly/extension/io/OptionList.resolveOptions:(Lorg/jboss/as/controller/ExpressionResolver;Lorg/jboss/dmr/ModelNode;Ljava/util/Collection;)Lorg/xnio/OptionMap;
      27: invokevirtual #10                 // Method org/xnio/OptionMap$Builder.addAll:(Lorg/xnio/OptionMap;)Lorg/xnio/OptionMap$Builder;
      30: astore_2
      31: aload_2
      32: invokevirtual #11                 // Method org/xnio/OptionMap$Builder.getMap:()Lorg/xnio/OptionMap;
      35: areturn

  public static org.xnio.OptionMap create(org.jboss.as.controller.ExpressionResolver, org.jboss.dmr.ModelNode, org.xnio.OptionMap) throws org.jboss.as.controller.OperationFailedException;
    Code:
       0: invokestatic  #2                  // Method org/xnio/OptionMap.builder:()Lorg/xnio/OptionMap$Builder;
       3: aload_2
       4: invokevirtual #10                 // Method org/xnio/OptionMap$Builder.addAll:(Lorg/xnio/OptionMap;)Lorg/xnio/OptionMap$Builder;
       7: getstatic     #12                 // Field org/xnio/Options.WORKER_READ_THREADS:Lorg/xnio/Option;
      10: getstatic     #13                 // Field org/jboss/as/remoting/RemotingSubsystemRootResource.WORKER_READ_THREADS:Lorg/jboss/as/controller/SimpleAttributeDefinition;
      13: aload_0
      14: aload_1
      15: invokevirtual #14                 // Method org/jboss/as/controller/SimpleAttributeDefinition.resolveModelAttribute:(Lorg/jboss/as/controller/ExpressionResolver;Lorg/jboss/dmr/ModelNode;)Lorg/jboss/dmr/ModelNode;
      18: invokevirtual #15                 // Method org/jboss/dmr/ModelNode.asInt:()I
      21: invokevirtual #16                 // Method org/xnio/OptionMap$Builder.set:(Lorg/xnio/Option;I)Lorg/xnio/OptionMap$Builder;
      24: getstatic     #17                 // Field org/xnio/Options.WORKER_TASK_CORE_THREADS:Lorg/xnio/Option;
      27: getstatic     #18                 // Field org/jboss/as/remoting/RemotingSubsystemRootResource.WORKER_TASK_CORE_THREADS:Lorg/jboss/as/controller/SimpleAttributeDefinition;
      30: aload_0
      31: aload_1
      32: invokevirtual #14                 // Method org/jboss/as/controller/SimpleAttributeDefinition.resolveModelAttribute:(Lorg/jboss/as/controller/ExpressionResolver;Lorg/jboss/dmr/ModelNode;)Lorg/jboss/dmr/ModelNode;
      35: invokevirtual #15                 // Method org/jboss/dmr/ModelNode.asInt:()I
      38: invokevirtual #16                 // Method org/xnio/OptionMap$Builder.set:(Lorg/xnio/Option;I)Lorg/xnio/OptionMap$Builder;
      41: getstatic     #19                 // Field org/xnio/Options.WORKER_TASK_KEEPALIVE:Lorg/xnio/Option;
      44: getstatic     #20                 // Field org/jboss/as/remoting/RemotingSubsystemRootResource.WORKER_TASK_KEEPALIVE:Lorg/jboss/as/controller/SimpleAttributeDefinition;
      47: aload_0
      48: aload_1
      49: invokevirtual #14                 // Method org/jboss/as/controller/SimpleAttributeDefinition.resolveModelAttribute:(Lorg/jboss/as/controller/ExpressionResolver;Lorg/jboss/dmr/ModelNode;)Lorg/jboss/dmr/ModelNode;
      52: invokevirtual #15                 // Method org/jboss/dmr/ModelNode.asInt:()I
      55: invokevirtual #16                 // Method org/xnio/OptionMap$Builder.set:(Lorg/xnio/Option;I)Lorg/xnio/OptionMap$Builder;
      58: getstatic     #21                 // Field org/xnio/Options.WORKER_TASK_LIMIT:Lorg/xnio/Option;
      61: getstatic     #22                 // Field org/jboss/as/remoting/RemotingSubsystemRootResource.WORKER_TASK_LIMIT:Lorg/jboss/as/controller/SimpleAttributeDefinition;
      64: aload_0
      65: aload_1
      66: invokevirtual #14                 // Method org/jboss/as/controller/SimpleAttributeDefinition.resolveModelAttribute:(Lorg/jboss/as/controller/ExpressionResolver;Lorg/jboss/dmr/ModelNode;)Lorg/jboss/dmr/ModelNode;
      69: invokevirtual #15                 // Method org/jboss/dmr/ModelNode.asInt:()I
      72: invokevirtual #16                 // Method org/xnio/OptionMap$Builder.set:(Lorg/xnio/Option;I)Lorg/xnio/OptionMap$Builder;
      75: getstatic     #23                 // Field org/xnio/Options.WORKER_TASK_MAX_THREADS:Lorg/xnio/Option;
      78: getstatic     #24                 // Field org/jboss/as/remoting/RemotingSubsystemRootResource.WORKER_TASK_MAX_THREADS:Lorg/jboss/as/controller/SimpleAttributeDefinition;
      81: aload_0
      82: aload_1
      83: invokevirtual #14                 // Method org/jboss/as/controller/SimpleAttributeDefinition.resolveModelAttribute:(Lorg/jboss/as/controller/ExpressionResolver;Lorg/jboss/dmr/ModelNode;)Lorg/jboss/dmr/ModelNode;
      86: invokevirtual #15                 // Method org/jboss/dmr/ModelNode.asInt:()I
      89: invokevirtual #16                 // Method org/xnio/OptionMap$Builder.set:(Lorg/xnio/Option;I)Lorg/xnio/OptionMap$Builder;
      92: getstatic     #25                 // Field org/xnio/Options.WORKER_WRITE_THREADS:Lorg/xnio/Option;
      95: getstatic     #26                 // Field org/jboss/as/remoting/RemotingSubsystemRootResource.WORKER_WRITE_THREADS:Lorg/jboss/as/controller/SimpleAttributeDefinition;
      98: aload_0
      99: aload_1
     100: invokevirtual #14                 // Method org/jboss/as/controller/SimpleAttributeDefinition.resolveModelAttribute:(Lorg/jboss/as/controller/ExpressionResolver;Lorg/jboss/dmr/ModelNode;)Lorg/jboss/dmr/ModelNode;
     103: invokevirtual #15                 // Method org/jboss/dmr/ModelNode.asInt:()I
     106: invokevirtual #16                 // Method org/xnio/OptionMap$Builder.set:(Lorg/xnio/Option;I)Lorg/xnio/OptionMap$Builder;
     109: getstatic     #12                 // Field org/xnio/Options.WORKER_READ_THREADS:Lorg/xnio/Option;
     112: getstatic     #13                 // Field org/jboss/as/remoting/RemotingSubsystemRootResource.WORKER_READ_THREADS:Lorg/jboss/as/controller/SimpleAttributeDefinition;
     115: aload_0
     116: aload_1
     117: invokevirtual #14                 // Method org/jboss/as/controller/SimpleAttributeDefinition.resolveModelAttribute:(Lorg/jboss/as/controller/ExpressionResolver;Lorg/jboss/dmr/ModelNode;)Lorg/jboss/dmr/ModelNode;
     120: invokevirtual #15                 // Method org/jboss/dmr/ModelNode.asInt:()I
     123: invokevirtual #16                 // Method org/xnio/OptionMap$Builder.set:(Lorg/xnio/Option;I)Lorg/xnio/OptionMap$Builder;
     126: invokevirtual #11                 // Method org/xnio/OptionMap$Builder.getMap:()Lorg/xnio/OptionMap;
     129: astore_3
     130: aload_3
     131: areturn
}
