Compiled from "RealmSecurityProvider.java"
class org.jboss.as.remoting.RealmSecurityProvider implements org.jboss.as.remoting.RemotingSecurityProvider {
  static final java.lang.String SASL_OPT_REALM_PROPERTY;

  static final java.lang.String SASL_OPT_ALT_PROTO_PROPERTY;

  static final java.lang.String SASL_OPT_PRE_DIGESTED_PROPERTY;

  static final java.lang.String SASL_OPT_LOCAL_DEFAULT_USER;

  static final java.lang.String SASL_OPT_LOCAL_USER_CHALLENGE_PATH;

  static final java.lang.String SASL_OPT_SUBJECT_FACTORY;

  static final java.lang.String ANONYMOUS;

  static final java.lang.String DIGEST_MD5;

  static final java.lang.String EXTERNAL;

  static final java.lang.String GSSAPI;

  static final java.lang.String JBOSS_LOCAL_USER;

  static final java.lang.String PLAIN;

  private final org.jboss.as.domain.management.SecurityRealm realm;

  private final javax.security.auth.callback.CallbackHandler serverCallbackHandler;

  private final java.lang.String tokensDir;

  org.jboss.as.remoting.RealmSecurityProvider(org.jboss.as.domain.management.SecurityRealm, javax.security.auth.callback.CallbackHandler, java.lang.String);
    Code:
       0: aload_0
       1: invokespecial #4                  // Method java/lang/Object."<init>":()V
       4: aload_0
       5: aload_1
       6: putfield      #2                  // Field realm:Lorg/jboss/as/domain/management/SecurityRealm;
       9: aload_0
      10: aload_2
      11: putfield      #3                  // Field serverCallbackHandler:Ljavax/security/auth/callback/CallbackHandler;
      14: aload_0
      15: aload_3
      16: putfield      #5                  // Field tokensDir:Ljava/lang/String;
      19: return

  public org.xnio.OptionMap getOptionMap();
    Code:
       0: new           #6                  // class java/util/LinkedList
       3: dup
       4: invokespecial #7                  // Method java/util/LinkedList."<init>":()V
       7: astore_1
       8: new           #8                  // class java/util/HashSet
      11: dup
      12: invokespecial #9                  // Method java/util/HashSet."<init>":()V
      15: astore_2
      16: invokestatic  #10                 // Method org/xnio/OptionMap.builder:()Lorg/xnio/OptionMap$Builder;
      19: astore_3
      20: aload_0
      21: getfield      #2                  // Field realm:Lorg/jboss/as/domain/management/SecurityRealm;
      24: ifnonnull     57
      27: aload_1
      28: ldc           #12                 // String ANONYMOUS
      30: invokeinterface #13,  2           // InterfaceMethod java/util/List.add:(Ljava/lang/Object;)Z
      35: pop
      36: aload_3
      37: getstatic     #14                 // Field org/xnio/Options.SASL_POLICY_NOANONYMOUS:Lorg/xnio/Option;
      40: iconst_0
      41: invokevirtual #15                 // Method org/xnio/OptionMap$Builder.set:(Lorg/xnio/Option;Z)Lorg/xnio/OptionMap$Builder;
      44: pop
      45: aload_3
      46: getstatic     #16                 // Field org/xnio/Options.SSL_ENABLED:Lorg/xnio/Option;
      49: iconst_0
      50: invokevirtual #15                 // Method org/xnio/OptionMap$Builder.set:(Lorg/xnio/Option;Z)Lorg/xnio/OptionMap$Builder;
      53: pop
      54: goto          459
      57: aload_0
      58: getfield      #2                  // Field realm:Lorg/jboss/as/domain/management/SecurityRealm;
      61: invokeinterface #17,  1           // InterfaceMethod org/jboss/as/domain/management/SecurityRealm.getSupportedAuthenticationMechanisms:()Ljava/util/Set;
      66: astore        4
      68: aload         4
      70: getstatic     #18                 // Field org/jboss/as/domain/management/AuthMechanism.LOCAL:Lorg/jboss/as/domain/management/AuthMechanism;
      73: invokeinterface #19,  2           // InterfaceMethod java/util/Set.contains:(Ljava/lang/Object;)Z
      78: ifeq          163
      81: aload_1
      82: ldc           #20                 // String JBOSS-LOCAL-USER
      84: invokeinterface #13,  2           // InterfaceMethod java/util/List.add:(Ljava/lang/Object;)Z
      89: pop
      90: aload_0
      91: getfield      #2                  // Field realm:Lorg/jboss/as/domain/management/SecurityRealm;
      94: getstatic     #18                 // Field org/jboss/as/domain/management/AuthMechanism.LOCAL:Lorg/jboss/as/domain/management/AuthMechanism;
      97: invokeinterface #21,  2           // InterfaceMethod org/jboss/as/domain/management/SecurityRealm.getMechanismConfig:(Lorg/jboss/as/domain/management/AuthMechanism;)Ljava/util/Map;
     102: astore        5
     104: aload         5
     106: ldc           #22                 // String org.jboss.as.domain.management.local.default_user
     108: invokeinterface #23,  2           // InterfaceMethod java/util/Map.containsKey:(Ljava/lang/Object;)Z
     113: ifeq          140
     116: aload_2
     117: ldc           #24                 // String jboss.sasl.local-user.default-user
     119: aload         5
     121: ldc           #22                 // String org.jboss.as.domain.management.local.default_user
     123: invokeinterface #25,  2           // InterfaceMethod java/util/Map.get:(Ljava/lang/Object;)Ljava/lang/Object;
     128: checkcast     #26                 // class java/lang/String
     131: invokestatic  #27                 // Method org/xnio/Property.of:(Ljava/lang/String;Ljava/lang/String;)Lorg/xnio/Property;
     134: invokeinterface #28,  2           // InterfaceMethod java/util/Set.add:(Ljava/lang/Object;)Z
     139: pop
     140: aload_0
     141: getfield      #5                  // Field tokensDir:Ljava/lang/String;
     144: ifnull        163
     147: aload_2
     148: ldc           #29                 // String jboss.sasl.local-user.challenge-path
     150: aload_0
     151: getfield      #5                  // Field tokensDir:Ljava/lang/String;
     154: invokestatic  #27                 // Method org/xnio/Property.of:(Ljava/lang/String;Ljava/lang/String;)Lorg/xnio/Property;
     157: invokeinterface #28,  2           // InterfaceMethod java/util/Set.add:(Ljava/lang/Object;)Z
     162: pop
     163: aload         4
     165: getstatic     #30                 // Field org/jboss/as/domain/management/AuthMechanism.KERBEROS:Lorg/jboss/as/domain/management/AuthMechanism;
     168: invokeinterface #19,  2           // InterfaceMethod java/util/Set.contains:(Ljava/lang/Object;)Z
     173: ifeq          206
     176: aload_1
     177: ldc           #31                 // String GSSAPI
     179: invokeinterface #13,  2           // InterfaceMethod java/util/List.add:(Ljava/lang/Object;)Z
     184: pop
     185: aload_2
     186: ldc           #32                 // String org.jboss.sasl.gssapi.subject_factory
     188: new           #33                 // class org/jboss/as/remoting/RealmSecurityProvider$RealmSubjectFactory
     191: dup
     192: aload_0
     193: aconst_null
     194: invokespecial #34                 // Method org/jboss/as/remoting/RealmSecurityProvider$RealmSubjectFactory."<init>":(Lorg/jboss/as/remoting/RealmSecurityProvider;Lorg/jboss/as/remoting/RealmSecurityProvider$1;)V
     197: invokestatic  #35                 // Method org/xnio/Property.of:(Ljava/lang/String;Ljava/lang/Object;)Lorg/xnio/Property;
     200: invokeinterface #28,  2           // InterfaceMethod java/util/Set.add:(Ljava/lang/Object;)Z
     205: pop
     206: aload         4
     208: getstatic     #36                 // Field org/jboss/as/domain/management/AuthMechanism.DIGEST:Lorg/jboss/as/domain/management/AuthMechanism;
     211: invokeinterface #19,  2           // InterfaceMethod java/util/Set.contains:(Ljava/lang/Object;)Z
     216: ifeq          332
     219: aload_1
     220: ldc           #37                 // String DIGEST-MD5
     222: invokeinterface #13,  2           // InterfaceMethod java/util/List.add:(Ljava/lang/Object;)Z
     227: pop
     228: aload_2
     229: ldc           #38                 // String com.sun.security.sasl.digest.realm
     231: aload_0
     232: getfield      #2                  // Field realm:Lorg/jboss/as/domain/management/SecurityRealm;
     235: invokeinterface #39,  1           // InterfaceMethod org/jboss/as/domain/management/SecurityRealm.getName:()Ljava/lang/String;
     240: invokestatic  #27                 // Method org/xnio/Property.of:(Ljava/lang/String;Ljava/lang/String;)Lorg/xnio/Property;
     243: invokeinterface #28,  2           // InterfaceMethod java/util/Set.add:(Ljava/lang/Object;)Z
     248: pop
     249: aload_2
     250: ldc           #40                 // String org.jboss.sasl.digest.alternative_protocols
     252: ldc           #41                 // String remote,remoting
     254: invokestatic  #27                 // Method org/xnio/Property.of:(Ljava/lang/String;Ljava/lang/String;)Lorg/xnio/Property;
     257: invokeinterface #28,  2           // InterfaceMethod java/util/Set.add:(Ljava/lang/Object;)Z
     262: pop
     263: aload_0
     264: getfield      #2                  // Field realm:Lorg/jboss/as/domain/management/SecurityRealm;
     267: getstatic     #36                 // Field org/jboss/as/domain/management/AuthMechanism.DIGEST:Lorg/jboss/as/domain/management/AuthMechanism;
     270: invokeinterface #21,  2           // InterfaceMethod org/jboss/as/domain/management/SecurityRealm.getMechanismConfig:(Lorg/jboss/as/domain/management/AuthMechanism;)Ljava/util/Map;
     275: astore        5
     277: iconst_1
     278: istore        6
     280: aload         5
     282: ldc           #42                 // String org.jboss.as.domain.management.digest.plain_text
     284: invokeinterface #23,  2           // InterfaceMethod java/util/Map.containsKey:(Ljava/lang/Object;)Z
     289: ifeq          309
     292: aload         5
     294: ldc           #42                 // String org.jboss.as.domain.management.digest.plain_text
     296: invokeinterface #25,  2           // InterfaceMethod java/util/Map.get:(Ljava/lang/Object;)Ljava/lang/Object;
     301: checkcast     #26                 // class java/lang/String
     304: invokestatic  #43                 // Method java/lang/Boolean.parseBoolean:(Ljava/lang/String;)Z
     307: istore        6
     309: iload         6
     311: ifne          332
     314: aload_2
     315: ldc           #44                 // String org.jboss.sasl.digest.pre_digested
     317: getstatic     #45                 // Field java/lang/Boolean.TRUE:Ljava/lang/Boolean;
     320: invokevirtual #46                 // Method java/lang/Boolean.toString:()Ljava/lang/String;
     323: invokestatic  #27                 // Method org/xnio/Property.of:(Ljava/lang/String;Ljava/lang/String;)Lorg/xnio/Property;
     326: invokeinterface #28,  2           // InterfaceMethod java/util/Set.add:(Ljava/lang/Object;)Z
     331: pop
     332: aload         4
     334: getstatic     #47                 // Field org/jboss/as/domain/management/AuthMechanism.PLAIN:Lorg/jboss/as/domain/management/AuthMechanism;
     337: invokeinterface #19,  2           // InterfaceMethod java/util/Set.contains:(Ljava/lang/Object;)Z
     342: ifeq          363
     345: aload_1
     346: ldc           #48                 // String PLAIN
     348: invokeinterface #13,  2           // InterfaceMethod java/util/List.add:(Ljava/lang/Object;)Z
     353: pop
     354: aload_3
     355: getstatic     #49                 // Field org/xnio/Options.SASL_POLICY_NOPLAINTEXT:Lorg/xnio/Option;
     358: iconst_0
     359: invokevirtual #15                 // Method org/xnio/OptionMap$Builder.set:(Lorg/xnio/Option;Z)Lorg/xnio/OptionMap$Builder;
     362: pop
     363: aload_0
     364: getfield      #2                  // Field realm:Lorg/jboss/as/domain/management/SecurityRealm;
     367: invokeinterface #50,  1           // InterfaceMethod org/jboss/as/domain/management/SecurityRealm.getSSLContext:()Ljavax/net/ssl/SSLContext;
     372: ifnonnull     387
     375: aload_3
     376: getstatic     #16                 // Field org/xnio/Options.SSL_ENABLED:Lorg/xnio/Option;
     379: iconst_0
     380: invokevirtual #15                 // Method org/xnio/OptionMap$Builder.set:(Lorg/xnio/Option;Z)Lorg/xnio/OptionMap$Builder;
     383: pop
     384: goto          459
     387: aload         4
     389: getstatic     #51                 // Field org/jboss/as/domain/management/AuthMechanism.CLIENT_CERT:Lorg/jboss/as/domain/management/AuthMechanism;
     392: invokeinterface #19,  2           // InterfaceMethod java/util/Set.contains:(Ljava/lang/Object;)Z
     397: ifeq          441
     400: aload_3
     401: getstatic     #16                 // Field org/xnio/Options.SSL_ENABLED:Lorg/xnio/Option;
     404: iconst_1
     405: invokevirtual #15                 // Method org/xnio/OptionMap$Builder.set:(Lorg/xnio/Option;Z)Lorg/xnio/OptionMap$Builder;
     408: pop
     409: aload_3
     410: getstatic     #52                 // Field org/xnio/Options.SSL_STARTTLS:Lorg/xnio/Option;
     413: iconst_1
     414: invokevirtual #15                 // Method org/xnio/OptionMap$Builder.set:(Lorg/xnio/Option;Z)Lorg/xnio/OptionMap$Builder;
     417: pop
     418: aload_1
     419: iconst_0
     420: ldc           #53                 // String EXTERNAL
     422: invokeinterface #54,  3           // InterfaceMethod java/util/List.add:(ILjava/lang/Object;)V
     427: aload_3
     428: getstatic     #55                 // Field org/xnio/Options.SSL_CLIENT_AUTH_MODE:Lorg/xnio/Option;
     431: getstatic     #56                 // Field org/xnio/SslClientAuthMode.REQUESTED:Lorg/xnio/SslClientAuthMode;
     434: invokevirtual #57                 // Method org/xnio/OptionMap$Builder.set:(Lorg/xnio/Option;Ljava/lang/Object;)Lorg/xnio/OptionMap$Builder;
     437: pop
     438: goto          459
     441: aload_3
     442: getstatic     #16                 // Field org/xnio/Options.SSL_ENABLED:Lorg/xnio/Option;
     445: iconst_1
     446: invokevirtual #15                 // Method org/xnio/OptionMap$Builder.set:(Lorg/xnio/Option;Z)Lorg/xnio/OptionMap$Builder;
     449: pop
     450: aload_3
     451: getstatic     #52                 // Field org/xnio/Options.SSL_STARTTLS:Lorg/xnio/Option;
     454: iconst_1
     455: invokevirtual #15                 // Method org/xnio/OptionMap$Builder.set:(Lorg/xnio/Option;Z)Lorg/xnio/OptionMap$Builder;
     458: pop
     459: aload_1
     460: invokeinterface #58,  1           // InterfaceMethod java/util/List.size:()I
     465: ifne          477
     468: getstatic     #59                 // Field org/jboss/as/remoting/logging/RemotingLogger.ROOT_LOGGER:Lorg/jboss/as/remoting/logging/RemotingLogger;
     471: invokeinterface #60,  1           // InterfaceMethod org/jboss/as/remoting/logging/RemotingLogger.noSupportingMechanismsForRealm:()Ljava/lang/IllegalStateException;
     476: athrow
     477: aload_3
     478: getstatic     #61                 // Field org/xnio/Options.SASL_MECHANISMS:Lorg/xnio/Option;
     481: aload_1
     482: invokestatic  #62                 // Method org/xnio/Sequence.of:(Ljava/util/Collection;)Lorg/xnio/Sequence;
     485: invokevirtual #57                 // Method org/xnio/OptionMap$Builder.set:(Lorg/xnio/Option;Ljava/lang/Object;)Lorg/xnio/OptionMap$Builder;
     488: pop
     489: aload_3
     490: getstatic     #63                 // Field org/xnio/Options.SASL_PROPERTIES:Lorg/xnio/Option;
     493: aload_2
     494: invokestatic  #62                 // Method org/xnio/Sequence.of:(Ljava/util/Collection;)Lorg/xnio/Sequence;
     497: invokevirtual #57                 // Method org/xnio/OptionMap$Builder.set:(Lorg/xnio/Option;Ljava/lang/Object;)Lorg/xnio/OptionMap$Builder;
     500: pop
     501: aload_3
     502: invokevirtual #64                 // Method org/xnio/OptionMap$Builder.getMap:()Lorg/xnio/OptionMap;
     505: areturn

  public org.jboss.remoting3.security.ServerAuthenticationProvider getServerAuthenticationProvider();
    Code:
       0: new           #65                 // class org/jboss/as/remoting/RealmSecurityProvider$1
       3: dup
       4: aload_0
       5: invokespecial #66                 // Method org/jboss/as/remoting/RealmSecurityProvider$1."<init>":(Lorg/jboss/as/remoting/RealmSecurityProvider;)V
       8: areturn

  public org.xnio.ssl.XnioSsl getXnioSsl();
    Code:
       0: aload_0
       1: getfield      #2                  // Field realm:Lorg/jboss/as/domain/management/SecurityRealm;
       4: ifnull        21
       7: aload_0
       8: getfield      #2                  // Field realm:Lorg/jboss/as/domain/management/SecurityRealm;
      11: invokeinterface #50,  1           // InterfaceMethod org/jboss/as/domain/management/SecurityRealm.getSSLContext:()Ljavax/net/ssl/SSLContext;
      16: dup
      17: astore_1
      18: ifnonnull     23
      21: aconst_null
      22: areturn
      23: new           #67                 // class org/xnio/ssl/JsseXnioSsl
      26: dup
      27: ldc           #68                 // class org/jboss/remoting3/Remoting
      29: invokevirtual #69                 // Method java/lang/Class.getClassLoader:()Ljava/lang/ClassLoader;
      32: invokestatic  #70                 // Method org/xnio/Xnio.getInstance:(Ljava/lang/ClassLoader;)Lorg/xnio/Xnio;
      35: getstatic     #71                 // Field org/xnio/OptionMap.EMPTY:Lorg/xnio/OptionMap;
      38: aload_1
      39: invokespecial #72                 // Method org/xnio/ssl/JsseXnioSsl."<init>":(Lorg/xnio/Xnio;Lorg/xnio/OptionMap;Ljavax/net/ssl/SSLContext;)V
      42: areturn

  public javax.security.auth.callback.CallbackHandler getCallbackHandler(java.lang.String);
    Code:
       0: ldc           #12                 // String ANONYMOUS
       2: aload_1
       3: invokevirtual #73                 // Method java/lang/String.equals:(Ljava/lang/Object;)Z
       6: ifeq          33
       9: aload_0
      10: getfield      #2                  // Field realm:Lorg/jboss/as/domain/management/SecurityRealm;
      13: ifnonnull     33
      16: new           #74                 // class org/jboss/as/remoting/RealmSecurityProvider$RealmCallbackHandler
      19: dup
      20: aload_0
      21: new           #75                 // class org/jboss/as/remoting/RealmSecurityProvider$2
      24: dup
      25: aload_0
      26: invokespecial #76                 // Method org/jboss/as/remoting/RealmSecurityProvider$2."<init>":(Lorg/jboss/as/remoting/RealmSecurityProvider;)V
      29: invokespecial #77                 // Method org/jboss/as/remoting/RealmSecurityProvider$RealmCallbackHandler."<init>":(Lorg/jboss/as/remoting/RealmSecurityProvider;Lorg/jboss/as/domain/management/AuthorizingCallbackHandler;)V
      32: areturn
      33: ldc           #20                 // String JBOSS-LOCAL-USER
      35: aload_1
      36: invokevirtual #73                 // Method java/lang/String.equals:(Ljava/lang/Object;)Z
      39: ifeq          63
      42: new           #74                 // class org/jboss/as/remoting/RealmSecurityProvider$RealmCallbackHandler
      45: dup
      46: aload_0
      47: aload_0
      48: getfield      #2                  // Field realm:Lorg/jboss/as/domain/management/SecurityRealm;
      51: getstatic     #18                 // Field org/jboss/as/domain/management/AuthMechanism.LOCAL:Lorg/jboss/as/domain/management/AuthMechanism;
      54: invokeinterface #78,  2           // InterfaceMethod org/jboss/as/domain/management/SecurityRealm.getAuthorizingCallbackHandler:(Lorg/jboss/as/domain/management/AuthMechanism;)Lorg/jboss/as/domain/management/AuthorizingCallbackHandler;
      59: invokespecial #77                 // Method org/jboss/as/remoting/RealmSecurityProvider$RealmCallbackHandler."<init>":(Lorg/jboss/as/remoting/RealmSecurityProvider;Lorg/jboss/as/domain/management/AuthorizingCallbackHandler;)V
      62: areturn
      63: ldc           #53                 // String EXTERNAL
      65: aload_1
      66: invokevirtual #73                 // Method java/lang/String.equals:(Ljava/lang/Object;)Z
      69: ifeq          93
      72: new           #74                 // class org/jboss/as/remoting/RealmSecurityProvider$RealmCallbackHandler
      75: dup
      76: aload_0
      77: aload_0
      78: getfield      #2                  // Field realm:Lorg/jboss/as/domain/management/SecurityRealm;
      81: getstatic     #51                 // Field org/jboss/as/domain/management/AuthMechanism.CLIENT_CERT:Lorg/jboss/as/domain/management/AuthMechanism;
      84: invokeinterface #78,  2           // InterfaceMethod org/jboss/as/domain/management/SecurityRealm.getAuthorizingCallbackHandler:(Lorg/jboss/as/domain/management/AuthMechanism;)Lorg/jboss/as/domain/management/AuthorizingCallbackHandler;
      89: invokespecial #77                 // Method org/jboss/as/remoting/RealmSecurityProvider$RealmCallbackHandler."<init>":(Lorg/jboss/as/remoting/RealmSecurityProvider;Lorg/jboss/as/domain/management/AuthorizingCallbackHandler;)V
      92: areturn
      93: ldc           #37                 // String DIGEST-MD5
      95: aload_1
      96: invokevirtual #73                 // Method java/lang/String.equals:(Ljava/lang/Object;)Z
      99: ifeq          126
     102: new           #74                 // class org/jboss/as/remoting/RealmSecurityProvider$RealmCallbackHandler
     105: dup
     106: aload_0
     107: aload_0
     108: getfield      #2                  // Field realm:Lorg/jboss/as/domain/management/SecurityRealm;
     111: getstatic     #36                 // Field org/jboss/as/domain/management/AuthMechanism.DIGEST:Lorg/jboss/as/domain/management/AuthMechanism;
     114: invokeinterface #78,  2           // InterfaceMethod org/jboss/as/domain/management/SecurityRealm.getAuthorizingCallbackHandler:(Lorg/jboss/as/domain/management/AuthMechanism;)Lorg/jboss/as/domain/management/AuthorizingCallbackHandler;
     119: invokespecial #77                 // Method org/jboss/as/remoting/RealmSecurityProvider$RealmCallbackHandler."<init>":(Lorg/jboss/as/remoting/RealmSecurityProvider;Lorg/jboss/as/domain/management/AuthorizingCallbackHandler;)V
     122: astore_2
     123: goto          194
     126: ldc           #48                 // String PLAIN
     128: aload_1
     129: invokevirtual #73                 // Method java/lang/String.equals:(Ljava/lang/Object;)Z
     132: ifeq          159
     135: new           #74                 // class org/jboss/as/remoting/RealmSecurityProvider$RealmCallbackHandler
     138: dup
     139: aload_0
     140: aload_0
     141: getfield      #2                  // Field realm:Lorg/jboss/as/domain/management/SecurityRealm;
     144: getstatic     #47                 // Field org/jboss/as/domain/management/AuthMechanism.PLAIN:Lorg/jboss/as/domain/management/AuthMechanism;
     147: invokeinterface #78,  2           // InterfaceMethod org/jboss/as/domain/management/SecurityRealm.getAuthorizingCallbackHandler:(Lorg/jboss/as/domain/management/AuthMechanism;)Lorg/jboss/as/domain/management/AuthorizingCallbackHandler;
     152: invokespecial #77                 // Method org/jboss/as/remoting/RealmSecurityProvider$RealmCallbackHandler."<init>":(Lorg/jboss/as/remoting/RealmSecurityProvider;Lorg/jboss/as/domain/management/AuthorizingCallbackHandler;)V
     155: astore_2
     156: goto          194
     159: ldc           #31                 // String GSSAPI
     161: aload_1
     162: invokevirtual #73                 // Method java/lang/String.equals:(Ljava/lang/Object;)Z
     165: ifeq          192
     168: new           #74                 // class org/jboss/as/remoting/RealmSecurityProvider$RealmCallbackHandler
     171: dup
     172: aload_0
     173: aload_0
     174: getfield      #2                  // Field realm:Lorg/jboss/as/domain/management/SecurityRealm;
     177: getstatic     #30                 // Field org/jboss/as/domain/management/AuthMechanism.KERBEROS:Lorg/jboss/as/domain/management/AuthMechanism;
     180: invokeinterface #78,  2           // InterfaceMethod org/jboss/as/domain/management/SecurityRealm.getAuthorizingCallbackHandler:(Lorg/jboss/as/domain/management/AuthMechanism;)Lorg/jboss/as/domain/management/AuthorizingCallbackHandler;
     185: invokespecial #77                 // Method org/jboss/as/remoting/RealmSecurityProvider$RealmCallbackHandler."<init>":(Lorg/jboss/as/remoting/RealmSecurityProvider;Lorg/jboss/as/domain/management/AuthorizingCallbackHandler;)V
     188: astore_2
     189: goto          194
     192: aconst_null
     193: areturn
     194: aload_0
     195: getfield      #3                  // Field serverCallbackHandler:Ljavax/security/auth/callback/CallbackHandler;
     198: ifnonnull     203
     201: aload_2
     202: areturn
     203: new           #79                 // class org/jboss/as/remoting/RealmSecurityProvider$3
     206: dup
     207: aload_0
     208: aload_2
     209: invokespecial #80                 // Method org/jboss/as/remoting/RealmSecurityProvider$3."<init>":(Lorg/jboss/as/remoting/RealmSecurityProvider;Lorg/jboss/as/remoting/RealmSecurityProvider$RealmCallbackHandler;)V
     212: areturn

  static javax.security.auth.callback.CallbackHandler access$100(org.jboss.as.remoting.RealmSecurityProvider);
    Code:
       0: aload_0
       1: getfield      #3                  // Field serverCallbackHandler:Ljavax/security/auth/callback/CallbackHandler;
       4: areturn

  static org.jboss.as.domain.management.SecurityRealm access$300(org.jboss.as.remoting.RealmSecurityProvider);
    Code:
       0: aload_0
       1: getfield      #2                  // Field realm:Lorg/jboss/as/domain/management/SecurityRealm;
       4: areturn
}
