Compiled from "XnioUtil.java"
class org.jboss.as.remoting.XnioUtil {
  org.jboss.as.remoting.XnioUtil();
    Code:
       0: aload_0
       1: invokespecial #1                  // Method java/lang/Object."<init>":()V
       4: return

  static org.xnio.Xnio getXnio() throws org.jboss.modules.ModuleLoadException;
    Code:
       0: aconst_null
       1: ldc           #2                  // String org.jboss.xnio.nio
       3: invokestatic  #3                  // Method org/jboss/modules/ModuleIdentifier.fromString:(Ljava/lang/String;)Lorg/jboss/modules/ModuleIdentifier;
       6: invokestatic  #4                  // Method org/jboss/modules/Module.getModuleFromCallerModuleLoader:(Lorg/jboss/modules/ModuleIdentifier;)Lorg/jboss/modules/Module;
       9: invokevirtual #5                  // Method org/jboss/modules/Module.getClassLoader:()Lorg/jboss/modules/ModuleClassLoader;
      12: invokestatic  #6                  // Method org/xnio/Xnio.getInstance:(Ljava/lang/String;Ljava/lang/ClassLoader;)Lorg/xnio/Xnio;
      15: areturn
}
