Compiled from "EsHadoopSecurityException.java"
public class org.elasticsearch.hadoop.security.EsHadoopSecurityException extends java.security.GeneralSecurityException {
  public org.elasticsearch.hadoop.security.EsHadoopSecurityException();
    Code:
       0: aload_0
       1: invokespecial #1                  // Method java/security/GeneralSecurityException."<init>":()V
       4: return

  public org.elasticsearch.hadoop.security.EsHadoopSecurityException(java.lang.String);
    Code:
       0: aload_0
       1: aload_1
       2: invokespecial #7                  // Method java/security/GeneralSecurityException."<init>":(Ljava/lang/String;)V
       5: return

  public org.elasticsearch.hadoop.security.EsHadoopSecurityException(java.lang.String, java.lang.Throwable);
    Code:
       0: aload_0
       1: aload_1
       2: aload_2
       3: invokespecial #10                 // Method java/security/GeneralSecurityException."<init>":(Ljava/lang/String;Ljava/lang/Throwable;)V
       6: return

  public org.elasticsearch.hadoop.security.EsHadoopSecurityException(java.lang.Throwable);
    Code:
       0: aload_0
       1: aload_1
       2: invokespecial #13                 // Method java/security/GeneralSecurityException."<init>":(Ljava/lang/Throwable;)V
       5: return
}
