Compiled from "SerializableContextualFactory.java"
abstract class org.jboss.weld.context.SerializableContextualFactory$AbstractSerializableBean<B extends javax.enterprise.inject.spi.Bean<I>, I> extends org.jboss.weld.bean.ForwardingBean<I> implements org.jboss.weld.serialization.spi.helpers.SerializableContextual<B, I>, org.jboss.weld.bean.WrappedContextual<I> {
  private static final long serialVersionUID;

  private final org.jboss.weld.context.SerializableContextualFactory$SerializableContextualHolder<B, I> holder;

  org.jboss.weld.context.SerializableContextualFactory$AbstractSerializableBean(java.lang.String, B, org.jboss.weld.serialization.spi.ContextualStore, org.jboss.weld.serialization.BeanIdentifierIndex);
    Code:
       0: aload_0
       1: invokespecial #1                  // Method org/jboss/weld/bean/ForwardingBean."<init>":()V
       4: aload_0
       5: new           #2                  // class org/jboss/weld/context/SerializableContextualFactory$SerializableContextualHolder
       8: dup
       9: aload_1
      10: aload_2
      11: aload_3
      12: aload         4
      14: invokespecial #3                  // Method org/jboss/weld/context/SerializableContextualFactory$SerializableContextualHolder."<init>":(Ljava/lang/String;Ljavax/enterprise/context/spi/Contextual;Lorg/jboss/weld/serialization/spi/ContextualStore;Lorg/jboss/weld/serialization/BeanIdentifierIndex;)V
      17: putfield      #4                  // Field holder:Lorg/jboss/weld/context/SerializableContextualFactory$SerializableContextualHolder;
      20: return

  public B get();
    Code:
       0: aload_0
       1: getfield      #4                  // Field holder:Lorg/jboss/weld/context/SerializableContextualFactory$SerializableContextualHolder;
       4: invokevirtual #5                  // Method org/jboss/weld/context/SerializableContextualFactory$SerializableContextualHolder.get:()Ljavax/enterprise/context/spi/Contextual;
       7: checkcast     #6                  // class javax/enterprise/inject/spi/Bean
      10: areturn

  public javax.enterprise.inject.spi.Bean<I> delegate();
    Code:
       0: aload_0
       1: invokevirtual #7                  // Method get:()Ljavax/enterprise/inject/spi/Bean;
       4: areturn

  public boolean equals(java.lang.Object);
    Code:
       0: aload_1
       1: instanceof    #8                  // class org/jboss/weld/context/SerializableContextualFactory$AbstractSerializableBean
       4: ifeq          22
       7: aload_0
       8: invokevirtual #9                  // Method delegate:()Ljavax/enterprise/inject/spi/Bean;
      11: aload_1
      12: checkcast     #8                  // class org/jboss/weld/context/SerializableContextualFactory$AbstractSerializableBean
      15: invokevirtual #7                  // Method get:()Ljavax/enterprise/inject/spi/Bean;
      18: invokevirtual #10                 // Method java/lang/Object.equals:(Ljava/lang/Object;)Z
      21: ireturn
      22: aload_0
      23: invokevirtual #9                  // Method delegate:()Ljavax/enterprise/inject/spi/Bean;
      26: aload_1
      27: invokevirtual #10                 // Method java/lang/Object.equals:(Ljava/lang/Object;)Z
      30: ireturn

  public int hashCode();
    Code:
       0: aload_0
       1: invokevirtual #9                  // Method delegate:()Ljavax/enterprise/inject/spi/Bean;
       4: invokevirtual #11                 // Method java/lang/Object.hashCode:()I
       7: ireturn

  public javax.enterprise.context.spi.Contextual delegate();
    Code:
       0: aload_0
       1: invokevirtual #9                  // Method delegate:()Ljavax/enterprise/inject/spi/Bean;
       4: areturn

  public javax.enterprise.context.spi.Contextual get();
    Code:
       0: aload_0
       1: invokevirtual #7                  // Method get:()Ljavax/enterprise/inject/spi/Bean;
       4: areturn
}
