Compiled from "HentOppgaveOppgaveIkkeFunnet.java"
public class no.nav.tjeneste.virksomhet.oppgave.v3.binding.HentOppgaveOppgaveIkkeFunnet extends java.lang.Exception {
  private no.nav.tjeneste.virksomhet.oppgave.v3.feil.OppgaveIkkeFunnet faultInfo;

  public no.nav.tjeneste.virksomhet.oppgave.v3.binding.HentOppgaveOppgaveIkkeFunnet(java.lang.String, no.nav.tjeneste.virksomhet.oppgave.v3.feil.OppgaveIkkeFunnet);
    Code:
       0: aload_0
       1: aload_1
       2: invokespecial #1                  // Method java/lang/Exception."<init>":(Ljava/lang/String;)V
       5: aload_0
       6: aload_2
       7: putfield      #2                  // Field faultInfo:Lno/nav/tjeneste/virksomhet/oppgave/v3/feil/OppgaveIkkeFunnet;
      10: return

  public no.nav.tjeneste.virksomhet.oppgave.v3.binding.HentOppgaveOppgaveIkkeFunnet(java.lang.String, no.nav.tjeneste.virksomhet.oppgave.v3.feil.OppgaveIkkeFunnet, java.lang.Throwable);
    Code:
       0: aload_0
       1: aload_1
       2: aload_3
       3: invokespecial #3                  // Method java/lang/Exception."<init>":(Ljava/lang/String;Ljava/lang/Throwable;)V
       6: aload_0
       7: aload_2
       8: putfield      #2                  // Field faultInfo:Lno/nav/tjeneste/virksomhet/oppgave/v3/feil/OppgaveIkkeFunnet;
      11: return

  public no.nav.tjeneste.virksomhet.oppgave.v3.feil.OppgaveIkkeFunnet getFaultInfo();
    Code:
       0: aload_0
       1: getfield      #2                  // Field faultInfo:Lno/nav/tjeneste/virksomhet/oppgave/v3/feil/OppgaveIkkeFunnet;
       4: areturn
}
