Compiled from "DefaultUriTemplateHandler.java"
public class org.springframework.web.util.DefaultUriTemplateHandler extends org.springframework.web.util.AbstractUriTemplateHandler {
  private boolean parsePath;

  private boolean strictEncoding;

  public org.springframework.web.util.DefaultUriTemplateHandler();
    Code:
       0: aload_0
       1: invokespecial #1                  // Method org/springframework/web/util/AbstractUriTemplateHandler."<init>":()V
       4: return

  public void setParsePath(boolean);
    Code:
       0: aload_0
       1: iload_1
       2: putfield      #2                  // Field parsePath:Z
       5: return

  public boolean shouldParsePath();
    Code:
       0: aload_0
       1: getfield      #2                  // Field parsePath:Z
       4: ireturn

  public void setStrictEncoding(boolean);
    Code:
       0: aload_0
       1: iload_1
       2: putfield      #3                  // Field strictEncoding:Z
       5: return

  public boolean isStrictEncoding();
    Code:
       0: aload_0
       1: getfield      #3                  // Field strictEncoding:Z
       4: ireturn

  protected java.net.URI expandInternal(java.lang.String, java.util.Map<java.lang.String, ?>);
    Code:
       0: aload_0
       1: aload_1
       2: invokevirtual #4                  // Method initUriComponentsBuilder:(Ljava/lang/String;)Lorg/springframework/web/util/UriComponentsBuilder;
       5: astore_3
       6: aload_0
       7: aload_3
       8: aload_2
       9: invokevirtual #5                  // Method expandAndEncode:(Lorg/springframework/web/util/UriComponentsBuilder;Ljava/util/Map;)Lorg/springframework/web/util/UriComponents;
      12: astore        4
      14: aload_0
      15: aload         4
      17: invokespecial #6                  // Method createUri:(Lorg/springframework/web/util/UriComponents;)Ljava/net/URI;
      20: areturn

  protected java.net.URI expandInternal(java.lang.String, java.lang.Object...);
    Code:
       0: aload_0
       1: aload_1
       2: invokevirtual #4                  // Method initUriComponentsBuilder:(Ljava/lang/String;)Lorg/springframework/web/util/UriComponentsBuilder;
       5: astore_3
       6: aload_0
       7: aload_3
       8: aload_2
       9: invokevirtual #7                  // Method expandAndEncode:(Lorg/springframework/web/util/UriComponentsBuilder;[Ljava/lang/Object;)Lorg/springframework/web/util/UriComponents;
      12: astore        4
      14: aload_0
      15: aload         4
      17: invokespecial #6                  // Method createUri:(Lorg/springframework/web/util/UriComponents;)Ljava/net/URI;
      20: areturn

  protected org.springframework.web.util.UriComponentsBuilder initUriComponentsBuilder(java.lang.String);
    Code:
       0: aload_1
       1: invokestatic  #8                  // Method org/springframework/web/util/UriComponentsBuilder.fromUriString:(Ljava/lang/String;)Lorg/springframework/web/util/UriComponentsBuilder;
       4: astore_2
       5: aload_0
       6: invokevirtual #9                  // Method shouldParsePath:()Z
       9: ifeq          80
      12: aload_0
      13: invokevirtual #10                 // Method isStrictEncoding:()Z
      16: ifne          80
      19: aload_2
      20: invokevirtual #11                 // Method org/springframework/web/util/UriComponentsBuilder.build:()Lorg/springframework/web/util/UriComponents;
      23: invokevirtual #12                 // Method org/springframework/web/util/UriComponents.getPathSegments:()Ljava/util/List;
      26: astore_3
      27: aload_2
      28: aconst_null
      29: invokevirtual #13                 // Method org/springframework/web/util/UriComponentsBuilder.replacePath:(Ljava/lang/String;)Lorg/springframework/web/util/UriComponentsBuilder;
      32: pop
      33: aload_3
      34: invokeinterface #14,  1           // InterfaceMethod java/util/List.iterator:()Ljava/util/Iterator;
      39: astore        4
      41: aload         4
      43: invokeinterface #15,  1           // InterfaceMethod java/util/Iterator.hasNext:()Z
      48: ifeq          80
      51: aload         4
      53: invokeinterface #16,  1           // InterfaceMethod java/util/Iterator.next:()Ljava/lang/Object;
      58: checkcast     #17                 // class java/lang/String
      61: astore        5
      63: aload_2
      64: iconst_1
      65: anewarray     #17                 // class java/lang/String
      68: dup
      69: iconst_0
      70: aload         5
      72: aastore
      73: invokevirtual #18                 // Method org/springframework/web/util/UriComponentsBuilder.pathSegment:([Ljava/lang/String;)Lorg/springframework/web/util/UriComponentsBuilder;
      76: pop
      77: goto          41
      80: aload_2
      81: areturn

  protected org.springframework.web.util.UriComponents expandAndEncode(org.springframework.web.util.UriComponentsBuilder, java.util.Map<java.lang.String, ?>);
    Code:
       0: aload_0
       1: invokevirtual #10                 // Method isStrictEncoding:()Z
       4: ifne          16
       7: aload_1
       8: aload_2
       9: invokevirtual #19                 // Method org/springframework/web/util/UriComponentsBuilder.buildAndExpand:(Ljava/util/Map;)Lorg/springframework/web/util/UriComponents;
      12: invokevirtual #20                 // Method org/springframework/web/util/UriComponents.encode:()Lorg/springframework/web/util/UriComponents;
      15: areturn
      16: new           #21                 // class java/util/HashMap
      19: dup
      20: aload_2
      21: invokeinterface #22,  1           // InterfaceMethod java/util/Map.size:()I
      26: invokespecial #23                 // Method java/util/HashMap."<init>":(I)V
      29: astore_3
      30: aload_2
      31: invokeinterface #24,  1           // InterfaceMethod java/util/Map.entrySet:()Ljava/util/Set;
      36: invokeinterface #25,  1           // InterfaceMethod java/util/Set.iterator:()Ljava/util/Iterator;
      41: astore        4
      43: aload         4
      45: invokeinterface #15,  1           // InterfaceMethod java/util/Iterator.hasNext:()Z
      50: ifeq          93
      53: aload         4
      55: invokeinterface #16,  1           // InterfaceMethod java/util/Iterator.next:()Ljava/lang/Object;
      60: checkcast     #26                 // class java/util/Map$Entry
      63: astore        5
      65: aload_3
      66: aload         5
      68: invokeinterface #27,  1           // InterfaceMethod java/util/Map$Entry.getKey:()Ljava/lang/Object;
      73: aload_0
      74: aload         5
      76: invokeinterface #28,  1           // InterfaceMethod java/util/Map$Entry.getValue:()Ljava/lang/Object;
      81: invokespecial #29                 // Method applyStrictEncoding:(Ljava/lang/Object;)Ljava/lang/String;
      84: invokeinterface #30,  3           // InterfaceMethod java/util/Map.put:(Ljava/lang/Object;Ljava/lang/Object;)Ljava/lang/Object;
      89: pop
      90: goto          43
      93: aload_1
      94: aload_3
      95: invokevirtual #19                 // Method org/springframework/web/util/UriComponentsBuilder.buildAndExpand:(Ljava/util/Map;)Lorg/springframework/web/util/UriComponents;
      98: areturn

  protected org.springframework.web.util.UriComponents expandAndEncode(org.springframework.web.util.UriComponentsBuilder, java.lang.Object[]);
    Code:
       0: aload_0
       1: invokevirtual #10                 // Method isStrictEncoding:()Z
       4: ifne          16
       7: aload_1
       8: aload_2
       9: invokevirtual #31                 // Method org/springframework/web/util/UriComponentsBuilder.buildAndExpand:([Ljava/lang/Object;)Lorg/springframework/web/util/UriComponents;
      12: invokevirtual #20                 // Method org/springframework/web/util/UriComponents.encode:()Lorg/springframework/web/util/UriComponents;
      15: areturn
      16: aload_2
      17: arraylength
      18: anewarray     #32                 // class java/lang/Object
      21: astore_3
      22: iconst_0
      23: istore        4
      25: iload         4
      27: aload_2
      28: arraylength
      29: if_icmpge     50
      32: aload_3
      33: iload         4
      35: aload_0
      36: aload_2
      37: iload         4
      39: aaload
      40: invokespecial #29                 // Method applyStrictEncoding:(Ljava/lang/Object;)Ljava/lang/String;
      43: aastore
      44: iinc          4, 1
      47: goto          25
      50: aload_1
      51: aload_3
      52: invokevirtual #31                 // Method org/springframework/web/util/UriComponentsBuilder.buildAndExpand:([Ljava/lang/Object;)Lorg/springframework/web/util/UriComponents;
      55: areturn

  private java.lang.String applyStrictEncoding(java.lang.Object);
    Code:
       0: aload_1
       1: ifnull        11
       4: aload_1
       5: invokevirtual #33                 // Method java/lang/Object.toString:()Ljava/lang/String;
       8: goto          13
      11: ldc           #34                 // String
      13: astore_2
      14: aload_2
      15: ldc           #35                 // String UTF-8
      17: invokestatic  #36                 // Method org/springframework/web/util/UriUtils.encode:(Ljava/lang/String;Ljava/lang/String;)Ljava/lang/String;
      20: areturn
      21: astore_3
      22: new           #38                 // class java/lang/IllegalStateException
      25: dup
      26: ldc           #39                 // String Failed to encode URI variable
      28: aload_3
      29: invokespecial #40                 // Method java/lang/IllegalStateException."<init>":(Ljava/lang/String;Ljava/lang/Throwable;)V
      32: athrow
    Exception table:
       from    to  target type
          14    20    21   Class java/io/UnsupportedEncodingException

  private java.net.URI createUri(org.springframework.web.util.UriComponents);
    Code:
       0: new           #41                 // class java/net/URI
       3: dup
       4: aload_1
       5: invokevirtual #42                 // Method org/springframework/web/util/UriComponents.toUriString:()Ljava/lang/String;
       8: invokespecial #43                 // Method java/net/URI."<init>":(Ljava/lang/String;)V
      11: areturn
      12: astore_2
      13: new           #38                 // class java/lang/IllegalStateException
      16: dup
      17: new           #45                 // class java/lang/StringBuilder
      20: dup
      21: invokespecial #46                 // Method java/lang/StringBuilder."<init>":()V
      24: ldc           #47                 // String Could not create URI object:
      26: invokevirtual #48                 // Method java/lang/StringBuilder.append:(Ljava/lang/String;)Ljava/lang/StringBuilder;
      29: aload_2
      30: invokevirtual #49                 // Method java/net/URISyntaxException.getMessage:()Ljava/lang/String;
      33: invokevirtual #48                 // Method java/lang/StringBuilder.append:(Ljava/lang/String;)Ljava/lang/StringBuilder;
      36: invokevirtual #50                 // Method java/lang/StringBuilder.toString:()Ljava/lang/String;
      39: aload_2
      40: invokespecial #40                 // Method java/lang/IllegalStateException."<init>":(Ljava/lang/String;Ljava/lang/Throwable;)V
      43: athrow
    Exception table:
       from    to  target type
           0    11    12   Class java/net/URISyntaxException
}
