Compiled from "SecurityProperties.java"
public class org.springframework.boot.autoconfigure.security.SecurityProperties implements org.springframework.boot.autoconfigure.security.SecurityPrerequisite {
  public static final int BASIC_AUTH_ORDER;

  public static final int IGNORED_ORDER;

  public static final int DEFAULT_FILTER_ORDER;

  private final org.springframework.boot.autoconfigure.security.SecurityProperties$Filter filter;

  private org.springframework.boot.autoconfigure.security.SecurityProperties$User user;

  public org.springframework.boot.autoconfigure.security.SecurityProperties();
    Code:
       0: aload_0
       1: invokespecial #3                  // Method java/lang/Object."<init>":()V
       4: aload_0
       5: new           #4                  // class org/springframework/boot/autoconfigure/security/SecurityProperties$Filter
       8: dup
       9: invokespecial #5                  // Method org/springframework/boot/autoconfigure/security/SecurityProperties$Filter."<init>":()V
      12: putfield      #6                  // Field filter:Lorg/springframework/boot/autoconfigure/security/SecurityProperties$Filter;
      15: aload_0
      16: new           #7                  // class org/springframework/boot/autoconfigure/security/SecurityProperties$User
      19: dup
      20: invokespecial #8                  // Method org/springframework/boot/autoconfigure/security/SecurityProperties$User."<init>":()V
      23: putfield      #9                  // Field user:Lorg/springframework/boot/autoconfigure/security/SecurityProperties$User;
      26: return

  public org.springframework.boot.autoconfigure.security.SecurityProperties$User getUser();
    Code:
       0: aload_0
       1: getfield      #9                  // Field user:Lorg/springframework/boot/autoconfigure/security/SecurityProperties$User;
       4: areturn

  public org.springframework.boot.autoconfigure.security.SecurityProperties$Filter getFilter();
    Code:
       0: aload_0
       1: getfield      #6                  // Field filter:Lorg/springframework/boot/autoconfigure/security/SecurityProperties$Filter;
       4: areturn
}
