Compiled from "HibernateEntityStatistics.java"
public class org.jboss.as.jpa.hibernate5.management.HibernateEntityStatistics extends org.jboss.as.jpa.hibernate5.management.HibernateAbstractStatistics {
  public static final java.lang.String OPERATION_ENTITY_DELETE_COUNT;

  public static final java.lang.String OPERATION_ENTITY_INSERT_COUNT;

  public static final java.lang.String OPERATION_ENTITY_LOAD_COUNT;

  public static final java.lang.String OPERATION_ENTITY_FETCH_COUNT;

  public static final java.lang.String OPERATION_ENTITY_UPDATE_COUNT;

  public static final java.lang.String OPERATION_OPTIMISTIC_FAILURE_COUNT;

  private org.jipijapa.management.spi.Operation entityDeleteCount;

  private org.jipijapa.management.spi.Operation entityFetchCount;

  private org.jipijapa.management.spi.Operation entityInsertCount;

  private org.jipijapa.management.spi.Operation entityLoadCount;

  private org.jipijapa.management.spi.Operation entityUpdateCount;

  private org.jipijapa.management.spi.Operation optimisticFailureCount;

  public org.jboss.as.jpa.hibernate5.management.HibernateEntityStatistics();
    Code:
       0: aload_0
       1: invokespecial #2                  // Method org/jboss/as/jpa/hibernate5/management/HibernateAbstractStatistics."<init>":()V
       4: aload_0
       5: new           #3                  // class org/jboss/as/jpa/hibernate5/management/HibernateEntityStatistics$1
       8: dup
       9: aload_0
      10: invokespecial #4                  // Method org/jboss/as/jpa/hibernate5/management/HibernateEntityStatistics$1."<init>":(Lorg/jboss/as/jpa/hibernate5/management/HibernateEntityStatistics;)V
      13: putfield      #5                  // Field entityDeleteCount:Lorg/jipijapa/management/spi/Operation;
      16: aload_0
      17: new           #6                  // class org/jboss/as/jpa/hibernate5/management/HibernateEntityStatistics$2
      20: dup
      21: aload_0
      22: invokespecial #7                  // Method org/jboss/as/jpa/hibernate5/management/HibernateEntityStatistics$2."<init>":(Lorg/jboss/as/jpa/hibernate5/management/HibernateEntityStatistics;)V
      25: putfield      #8                  // Field entityFetchCount:Lorg/jipijapa/management/spi/Operation;
      28: aload_0
      29: new           #9                  // class org/jboss/as/jpa/hibernate5/management/HibernateEntityStatistics$3
      32: dup
      33: aload_0
      34: invokespecial #10                 // Method org/jboss/as/jpa/hibernate5/management/HibernateEntityStatistics$3."<init>":(Lorg/jboss/as/jpa/hibernate5/management/HibernateEntityStatistics;)V
      37: putfield      #11                 // Field entityInsertCount:Lorg/jipijapa/management/spi/Operation;
      40: aload_0
      41: new           #12                 // class org/jboss/as/jpa/hibernate5/management/HibernateEntityStatistics$4
      44: dup
      45: aload_0
      46: invokespecial #13                 // Method org/jboss/as/jpa/hibernate5/management/HibernateEntityStatistics$4."<init>":(Lorg/jboss/as/jpa/hibernate5/management/HibernateEntityStatistics;)V
      49: putfield      #14                 // Field entityLoadCount:Lorg/jipijapa/management/spi/Operation;
      52: aload_0
      53: new           #15                 // class org/jboss/as/jpa/hibernate5/management/HibernateEntityStatistics$5
      56: dup
      57: aload_0
      58: invokespecial #16                 // Method org/jboss/as/jpa/hibernate5/management/HibernateEntityStatistics$5."<init>":(Lorg/jboss/as/jpa/hibernate5/management/HibernateEntityStatistics;)V
      61: putfield      #17                 // Field entityUpdateCount:Lorg/jipijapa/management/spi/Operation;
      64: aload_0
      65: new           #18                 // class org/jboss/as/jpa/hibernate5/management/HibernateEntityStatistics$6
      68: dup
      69: aload_0
      70: invokespecial #19                 // Method org/jboss/as/jpa/hibernate5/management/HibernateEntityStatistics$6."<init>":(Lorg/jboss/as/jpa/hibernate5/management/HibernateEntityStatistics;)V
      73: putfield      #20                 // Field optimisticFailureCount:Lorg/jipijapa/management/spi/Operation;
      76: aload_0
      77: getfield      #21                 // Field operations:Ljava/util/Map;
      80: ldc           #23                 // String entity-delete-count
      82: aload_0
      83: getfield      #5                  // Field entityDeleteCount:Lorg/jipijapa/management/spi/Operation;
      86: invokeinterface #24,  3           // InterfaceMethod java/util/Map.put:(Ljava/lang/Object;Ljava/lang/Object;)Ljava/lang/Object;
      91: pop
      92: aload_0
      93: getfield      #25                 // Field types:Ljava/util/Map;
      96: ldc           #23                 // String entity-delete-count
      98: ldc           #26                 // class java/lang/Long
     100: invokeinterface #24,  3           // InterfaceMethod java/util/Map.put:(Ljava/lang/Object;Ljava/lang/Object;)Ljava/lang/Object;
     105: pop
     106: aload_0
     107: getfield      #21                 // Field operations:Ljava/util/Map;
     110: ldc           #27                 // String entity-insert-count
     112: aload_0
     113: getfield      #11                 // Field entityInsertCount:Lorg/jipijapa/management/spi/Operation;
     116: invokeinterface #24,  3           // InterfaceMethod java/util/Map.put:(Ljava/lang/Object;Ljava/lang/Object;)Ljava/lang/Object;
     121: pop
     122: aload_0
     123: getfield      #25                 // Field types:Ljava/util/Map;
     126: ldc           #27                 // String entity-insert-count
     128: ldc           #26                 // class java/lang/Long
     130: invokeinterface #24,  3           // InterfaceMethod java/util/Map.put:(Ljava/lang/Object;Ljava/lang/Object;)Ljava/lang/Object;
     135: pop
     136: aload_0
     137: getfield      #21                 // Field operations:Ljava/util/Map;
     140: ldc           #28                 // String entity-load-count
     142: aload_0
     143: getfield      #14                 // Field entityLoadCount:Lorg/jipijapa/management/spi/Operation;
     146: invokeinterface #24,  3           // InterfaceMethod java/util/Map.put:(Ljava/lang/Object;Ljava/lang/Object;)Ljava/lang/Object;
     151: pop
     152: aload_0
     153: getfield      #25                 // Field types:Ljava/util/Map;
     156: ldc           #28                 // String entity-load-count
     158: ldc           #26                 // class java/lang/Long
     160: invokeinterface #24,  3           // InterfaceMethod java/util/Map.put:(Ljava/lang/Object;Ljava/lang/Object;)Ljava/lang/Object;
     165: pop
     166: aload_0
     167: getfield      #21                 // Field operations:Ljava/util/Map;
     170: ldc           #29                 // String entity-fetch-count
     172: aload_0
     173: getfield      #8                  // Field entityFetchCount:Lorg/jipijapa/management/spi/Operation;
     176: invokeinterface #24,  3           // InterfaceMethod java/util/Map.put:(Ljava/lang/Object;Ljava/lang/Object;)Ljava/lang/Object;
     181: pop
     182: aload_0
     183: getfield      #25                 // Field types:Ljava/util/Map;
     186: ldc           #29                 // String entity-fetch-count
     188: ldc           #26                 // class java/lang/Long
     190: invokeinterface #24,  3           // InterfaceMethod java/util/Map.put:(Ljava/lang/Object;Ljava/lang/Object;)Ljava/lang/Object;
     195: pop
     196: aload_0
     197: getfield      #21                 // Field operations:Ljava/util/Map;
     200: ldc           #30                 // String entity-update-count
     202: aload_0
     203: getfield      #17                 // Field entityUpdateCount:Lorg/jipijapa/management/spi/Operation;
     206: invokeinterface #24,  3           // InterfaceMethod java/util/Map.put:(Ljava/lang/Object;Ljava/lang/Object;)Ljava/lang/Object;
     211: pop
     212: aload_0
     213: getfield      #25                 // Field types:Ljava/util/Map;
     216: ldc           #30                 // String entity-update-count
     218: ldc           #26                 // class java/lang/Long
     220: invokeinterface #24,  3           // InterfaceMethod java/util/Map.put:(Ljava/lang/Object;Ljava/lang/Object;)Ljava/lang/Object;
     225: pop
     226: aload_0
     227: getfield      #21                 // Field operations:Ljava/util/Map;
     230: ldc           #31                 // String optimistic-failure-count
     232: aload_0
     233: getfield      #20                 // Field optimisticFailureCount:Lorg/jipijapa/management/spi/Operation;
     236: invokeinterface #24,  3           // InterfaceMethod java/util/Map.put:(Ljava/lang/Object;Ljava/lang/Object;)Ljava/lang/Object;
     241: pop
     242: aload_0
     243: getfield      #25                 // Field types:Ljava/util/Map;
     246: ldc           #31                 // String optimistic-failure-count
     248: ldc           #26                 // class java/lang/Long
     250: invokeinterface #24,  3           // InterfaceMethod java/util/Map.put:(Ljava/lang/Object;Ljava/lang/Object;)Ljava/lang/Object;
     255: pop
     256: return

  private org.hibernate.stat.Statistics getBaseStatistics(javax.persistence.EntityManagerFactory);
    Code:
       0: aload_1
       1: ifnonnull     6
       4: aconst_null
       5: areturn
       6: aload_1
       7: ldc           #32                 // class org/hibernate/SessionFactory
       9: invokeinterface #33,  2           // InterfaceMethod javax/persistence/EntityManagerFactory.unwrap:(Ljava/lang/Class;)Ljava/lang/Object;
      14: checkcast     #32                 // class org/hibernate/SessionFactory
      17: astore_2
      18: aload_2
      19: ifnull        29
      22: aload_2
      23: invokeinterface #34,  1           // InterfaceMethod org/hibernate/SessionFactory.getStatistics:()Lorg/hibernate/stat/Statistics;
      28: areturn
      29: aconst_null
      30: areturn

  private org.hibernate.stat.EntityStatistics getStatistics(javax.persistence.EntityManagerFactory, java.lang.String);
    Code:
       0: aload_1
       1: ifnonnull     6
       4: aconst_null
       5: areturn
       6: aload_1
       7: ldc           #32                 // class org/hibernate/SessionFactory
       9: invokeinterface #33,  2           // InterfaceMethod javax/persistence/EntityManagerFactory.unwrap:(Ljava/lang/Class;)Ljava/lang/Object;
      14: checkcast     #32                 // class org/hibernate/SessionFactory
      17: astore_3
      18: aload_3
      19: ifnull        35
      22: aload_3
      23: invokeinterface #34,  1           // InterfaceMethod org/hibernate/SessionFactory.getStatistics:()Lorg/hibernate/stat/Statistics;
      28: aload_2
      29: invokeinterface #35,  2           // InterfaceMethod org/hibernate/stat/Statistics.getEntityStatistics:(Ljava/lang/String;)Lorg/hibernate/stat/EntityStatistics;
      34: areturn
      35: aconst_null
      36: areturn

  public java.util.Set<java.lang.String> getNames();
    Code:
       0: aload_0
       1: getfield      #21                 // Field operations:Ljava/util/Map;
       4: invokeinterface #36,  1           // InterfaceMethod java/util/Map.keySet:()Ljava/util/Set;
       9: invokestatic  #37                 // Method java/util/Collections.unmodifiableSet:(Ljava/util/Set;)Ljava/util/Set;
      12: areturn

  public java.util.Collection<java.lang.String> getDynamicChildrenNames(org.jipijapa.management.spi.EntityManagerFactoryAccess, org.jipijapa.management.spi.PathAddress);
    Code:
       0: aload_0
       1: aload_1
       2: aload_2
       3: ldc           #39                 // String hibernate-persistence-unit
       5: invokeinterface #40,  2           // InterfaceMethod org/jipijapa/management/spi/PathAddress.getValue:(Ljava/lang/String;)Ljava/lang/String;
      10: invokeinterface #41,  2           // InterfaceMethod org/jipijapa/management/spi/EntityManagerFactoryAccess.entityManagerFactory:(Ljava/lang/String;)Ljavax/persistence/EntityManagerFactory;
      15: invokespecial #42                 // Method getBaseStatistics:(Ljavax/persistence/EntityManagerFactory;)Lorg/hibernate/stat/Statistics;
      18: astore_3
      19: aload_3
      20: ifnull        38
      23: aload_3
      24: invokeinterface #43,  1           // InterfaceMethod org/hibernate/stat/Statistics.getEntityNames:()[Ljava/lang/String;
      29: invokestatic  #44                 // Method java/util/Arrays.asList:([Ljava/lang/Object;)Ljava/util/List;
      32: invokestatic  #45                 // Method java/util/Collections.unmodifiableCollection:(Ljava/util/Collection;)Ljava/util/Collection;
      35: goto          41
      38: getstatic     #46                 // Field java/util/Collections.EMPTY_LIST:Ljava/util/List;
      41: areturn

  static org.hibernate.stat.EntityStatistics access$000(org.jboss.as.jpa.hibernate5.management.HibernateEntityStatistics, javax.persistence.EntityManagerFactory, java.lang.String);
    Code:
       0: aload_0
       1: aload_1
       2: aload_2
       3: invokespecial #1                  // Method getStatistics:(Ljavax/persistence/EntityManagerFactory;Ljava/lang/String;)Lorg/hibernate/stat/EntityStatistics;
       6: areturn
}
