Compiled from "VelocityServlet.java"
public abstract class org.apache.velocity.servlet.VelocityServlet extends javax.servlet.http.HttpServlet {
  public static final java.lang.String REQUEST;

  public static final java.lang.String RESPONSE;

  public static final java.lang.String CONTENT_TYPE;

  public static final java.lang.String DEFAULT_CONTENT_TYPE;

  public static final java.lang.String DEFAULT_OUTPUT_ENCODING;

  private static java.lang.String defaultContentType;

  protected static final java.lang.String INIT_PROPS_KEY;

  private static final java.lang.String OLD_INIT_PROPS_KEY;

  private static org.apache.velocity.util.SimplePool writerPool;

  public org.apache.velocity.servlet.VelocityServlet();
    Code:
       0: aload_0
       1: invokespecial #1                  // Method javax/servlet/http/HttpServlet."<init>":()V
       4: return

  public void init(javax.servlet.ServletConfig) throws javax.servlet.ServletException;
    Code:
       0: aload_0
       1: aload_1
       2: invokespecial #2                  // Method javax/servlet/http/HttpServlet.init:(Ljavax/servlet/ServletConfig;)V
       5: aload_0
       6: aload_1
       7: invokevirtual #3                  // Method initVelocity:(Ljavax/servlet/ServletConfig;)V
      10: ldc           #4                  // String default.contentType
      12: ldc           #5                  // String text/html
      14: invokestatic  #6                  // Method org/apache/velocity/runtime/RuntimeSingleton.getString:(Ljava/lang/String;Ljava/lang/String;)Ljava/lang/String;
      17: putstatic     #7                  // Field defaultContentType:Ljava/lang/String;
      20: return

  protected void initVelocity(javax.servlet.ServletConfig) throws javax.servlet.ServletException;
    Code:
       0: aload_0
       1: aload_1
       2: invokevirtual #8                  // Method loadConfiguration:(Ljavax/servlet/ServletConfig;)Ljava/util/Properties;
       5: astore_2
       6: aload_2
       7: invokestatic  #9                  // Method org/apache/velocity/app/Velocity.init:(Ljava/util/Properties;)V
      10: goto          42
      13: astore_2
      14: new           #11                 // class javax/servlet/ServletException
      17: dup
      18: new           #12                 // class java/lang/StringBuffer
      21: dup
      22: invokespecial #13                 // Method java/lang/StringBuffer."<init>":()V
      25: ldc           #14                 // String Error initializing Velocity:
      27: invokevirtual #15                 // Method java/lang/StringBuffer.append:(Ljava/lang/String;)Ljava/lang/StringBuffer;
      30: aload_2
      31: invokevirtual #16                 // Method java/lang/StringBuffer.append:(Ljava/lang/Object;)Ljava/lang/StringBuffer;
      34: invokevirtual #17                 // Method java/lang/StringBuffer.toString:()Ljava/lang/String;
      37: aload_2
      38: invokespecial #18                 // Method javax/servlet/ServletException."<init>":(Ljava/lang/String;Ljava/lang/Throwable;)V
      41: athrow
      42: return
    Exception table:
       from    to  target type
           0    10    13   Class java/lang/Exception

  protected java.util.Properties loadConfiguration(javax.servlet.ServletConfig) throws java.io.IOException, java.io.FileNotFoundException;
    Code:
       0: aload_1
       1: ldc           #19                 // String org.apache.velocity.properties
       3: invokeinterface #20,  2           // InterfaceMethod javax/servlet/ServletConfig.getInitParameter:(Ljava/lang/String;)Ljava/lang/String;
       8: astore_2
       9: aload_2
      10: ifnull        20
      13: aload_2
      14: invokevirtual #21                 // Method java/lang/String.length:()I
      17: ifne          106
      20: aload_1
      21: invokeinterface #22,  1           // InterfaceMethod javax/servlet/ServletConfig.getServletContext:()Ljavax/servlet/ServletContext;
      26: astore_3
      27: aload_1
      28: ldc           #23                 // String properties
      30: invokeinterface #20,  2           // InterfaceMethod javax/servlet/ServletConfig.getInitParameter:(Ljava/lang/String;)Ljava/lang/String;
      35: astore_2
      36: aload_2
      37: ifnull        47
      40: aload_2
      41: invokevirtual #21                 // Method java/lang/String.length:()I
      44: ifne          98
      47: aload_3
      48: ldc           #19                 // String org.apache.velocity.properties
      50: invokeinterface #24,  2           // InterfaceMethod javax/servlet/ServletContext.getInitParameter:(Ljava/lang/String;)Ljava/lang/String;
      55: astore_2
      56: aload_2
      57: ifnull        67
      60: aload_2
      61: invokevirtual #21                 // Method java/lang/String.length:()I
      64: ifne          106
      67: aload_3
      68: ldc           #23                 // String properties
      70: invokeinterface #24,  2           // InterfaceMethod javax/servlet/ServletContext.getInitParameter:(Ljava/lang/String;)Ljava/lang/String;
      75: astore_2
      76: aload_2
      77: ifnull        106
      80: aload_2
      81: invokevirtual #21                 // Method java/lang/String.length:()I
      84: ifle          106
      87: aload_3
      88: ldc           #25                 // String Use of the properties initialization parameter \'properties\' has been deprecated by \'org.apache.velocity.properties\'
      90: invokeinterface #26,  2           // InterfaceMethod javax/servlet/ServletContext.log:(Ljava/lang/String;)V
      95: goto          106
      98: aload_3
      99: ldc           #25                 // String Use of the properties initialization parameter \'properties\' has been deprecated by \'org.apache.velocity.properties\'
     101: invokeinterface #26,  2           // InterfaceMethod javax/servlet/ServletContext.log:(Ljava/lang/String;)V
     106: new           #27                 // class java/util/Properties
     109: dup
     110: invokespecial #28                 // Method java/util/Properties."<init>":()V
     113: astore_3
     114: aload_2
     115: ifnull        132
     118: aload_3
     119: aload_0
     120: invokevirtual #29                 // Method getServletContext:()Ljavax/servlet/ServletContext;
     123: aload_2
     124: invokeinterface #30,  2           // InterfaceMethod javax/servlet/ServletContext.getResourceAsStream:(Ljava/lang/String;)Ljava/io/InputStream;
     129: invokevirtual #31                 // Method java/util/Properties.load:(Ljava/io/InputStream;)V
     132: aload_3
     133: areturn

  public void doGet(javax.servlet.http.HttpServletRequest, javax.servlet.http.HttpServletResponse) throws javax.servlet.ServletException, java.io.IOException;
    Code:
       0: aload_0
       1: aload_1
       2: aload_2
       3: invokevirtual #32                 // Method doRequest:(Ljavax/servlet/http/HttpServletRequest;Ljavax/servlet/http/HttpServletResponse;)V
       6: return

  public void doPost(javax.servlet.http.HttpServletRequest, javax.servlet.http.HttpServletResponse) throws javax.servlet.ServletException, java.io.IOException;
    Code:
       0: aload_0
       1: aload_1
       2: aload_2
       3: invokevirtual #32                 // Method doRequest:(Ljavax/servlet/http/HttpServletRequest;Ljavax/servlet/http/HttpServletResponse;)V
       6: return

  protected void doRequest(javax.servlet.http.HttpServletRequest, javax.servlet.http.HttpServletResponse) throws javax.servlet.ServletException, java.io.IOException;
    Code:
       0: aconst_null
       1: astore_3
       2: aload_0
       3: aload_1
       4: aload_2
       5: invokevirtual #33                 // Method createContext:(Ljavax/servlet/http/HttpServletRequest;Ljavax/servlet/http/HttpServletResponse;)Lorg/apache/velocity/context/Context;
       8: astore_3
       9: aload_0
      10: aload_1
      11: aload_2
      12: invokevirtual #34                 // Method setContentType:(Ljavax/servlet/http/HttpServletRequest;Ljavax/servlet/http/HttpServletResponse;)V
      15: aload_0
      16: aload_1
      17: aload_2
      18: aload_3
      19: invokevirtual #35                 // Method handleRequest:(Ljavax/servlet/http/HttpServletRequest;Ljavax/servlet/http/HttpServletResponse;Lorg/apache/velocity/context/Context;)Lorg/apache/velocity/Template;
      22: astore        4
      24: aload         4
      26: ifnonnull     37
      29: aload_0
      30: aload_1
      31: aload_2
      32: aload_3
      33: invokevirtual #36                 // Method requestCleanup:(Ljavax/servlet/http/HttpServletRequest;Ljavax/servlet/http/HttpServletResponse;Lorg/apache/velocity/context/Context;)V
      36: return
      37: aload_0
      38: aload         4
      40: aload_3
      41: aload_2
      42: invokevirtual #37                 // Method mergeTemplate:(Lorg/apache/velocity/Template;Lorg/apache/velocity/context/Context;Ljavax/servlet/http/HttpServletResponse;)V
      45: aload_0
      46: aload_1
      47: aload_2
      48: aload_3
      49: invokevirtual #36                 // Method requestCleanup:(Ljavax/servlet/http/HttpServletRequest;Ljavax/servlet/http/HttpServletResponse;Lorg/apache/velocity/context/Context;)V
      52: goto          87
      55: astore        4
      57: aload_0
      58: aload_1
      59: aload_2
      60: aload         4
      62: invokevirtual #38                 // Method error:(Ljavax/servlet/http/HttpServletRequest;Ljavax/servlet/http/HttpServletResponse;Ljava/lang/Exception;)V
      65: aload_0
      66: aload_1
      67: aload_2
      68: aload_3
      69: invokevirtual #36                 // Method requestCleanup:(Ljavax/servlet/http/HttpServletRequest;Ljavax/servlet/http/HttpServletResponse;Lorg/apache/velocity/context/Context;)V
      72: goto          87
      75: astore        5
      77: aload_0
      78: aload_1
      79: aload_2
      80: aload_3
      81: invokevirtual #36                 // Method requestCleanup:(Ljavax/servlet/http/HttpServletRequest;Ljavax/servlet/http/HttpServletResponse;Lorg/apache/velocity/context/Context;)V
      84: aload         5
      86: athrow
      87: return
    Exception table:
       from    to  target type
           2    29    55   Class java/lang/Exception
          37    45    55   Class java/lang/Exception
           2    29    75   any
          37    45    75   any
          55    65    75   any
          75    77    75   any

  protected void requestCleanup(javax.servlet.http.HttpServletRequest, javax.servlet.http.HttpServletResponse, org.apache.velocity.context.Context);
    Code:
       0: return

  protected void mergeTemplate(org.apache.velocity.Template, org.apache.velocity.context.Context, javax.servlet.http.HttpServletResponse) throws org.apache.velocity.exception.ResourceNotFoundException, org.apache.velocity.exception.ParseErrorException, org.apache.velocity.exception.MethodInvocationException, java.io.IOException, java.io.UnsupportedEncodingException, java.lang.Exception;
    Code:
       0: aload_3
       1: invokeinterface #39,  1           // InterfaceMethod javax/servlet/http/HttpServletResponse.getOutputStream:()Ljavax/servlet/ServletOutputStream;
       6: astore        4
       8: aconst_null
       9: astore        5
      11: aload_3
      12: invokeinterface #40,  1           // InterfaceMethod javax/servlet/http/HttpServletResponse.getCharacterEncoding:()Ljava/lang/String;
      17: astore        6
      19: getstatic     #41                 // Field writerPool:Lorg/apache/velocity/util/SimplePool;
      22: invokevirtual #42                 // Method org/apache/velocity/util/SimplePool.get:()Ljava/lang/Object;
      25: checkcast     #43                 // class org/apache/velocity/io/VelocityWriter
      28: astore        5
      30: aload         5
      32: ifnonnull     62
      35: new           #43                 // class org/apache/velocity/io/VelocityWriter
      38: dup
      39: new           #44                 // class java/io/OutputStreamWriter
      42: dup
      43: aload         4
      45: aload         6
      47: invokespecial #45                 // Method java/io/OutputStreamWriter."<init>":(Ljava/io/OutputStream;Ljava/lang/String;)V
      50: sipush        4096
      53: iconst_1
      54: invokespecial #46                 // Method org/apache/velocity/io/VelocityWriter."<init>":(Ljava/io/Writer;IZ)V
      57: astore        5
      59: goto          78
      62: aload         5
      64: new           #44                 // class java/io/OutputStreamWriter
      67: dup
      68: aload         4
      70: aload         6
      72: invokespecial #45                 // Method java/io/OutputStreamWriter."<init>":(Ljava/io/OutputStream;Ljava/lang/String;)V
      75: invokevirtual #47                 // Method org/apache/velocity/io/VelocityWriter.recycle:(Ljava/io/Writer;)V
      78: aload_1
      79: aload_2
      80: aload         5
      82: invokevirtual #48                 // Method org/apache/velocity/Template.merge:(Lorg/apache/velocity/context/Context;Ljava/io/Writer;)V
      85: jsr           99
      88: goto          132
      91: astore        7
      93: jsr           99
      96: aload         7
      98: athrow
      99: astore        8
     101: aload         5
     103: ifnull        130
     106: aload         5
     108: invokevirtual #49                 // Method org/apache/velocity/io/VelocityWriter.flush:()V
     111: goto          116
     114: astore        9
     116: aload         5
     118: aconst_null
     119: invokevirtual #47                 // Method org/apache/velocity/io/VelocityWriter.recycle:(Ljava/io/Writer;)V
     122: getstatic     #41                 // Field writerPool:Lorg/apache/velocity/util/SimplePool;
     125: aload         5
     127: invokevirtual #51                 // Method org/apache/velocity/util/SimplePool.put:(Ljava/lang/Object;)V
     130: ret           8
     132: return
    Exception table:
       from    to  target type
          19    88    91   any
          91    96    91   any
         106   111   114   Class java/io/IOException

  protected void setContentType(javax.servlet.http.HttpServletRequest, javax.servlet.http.HttpServletResponse);
    Code:
       0: getstatic     #7                  // Field defaultContentType:Ljava/lang/String;
       3: astore_3
       4: aload_3
       5: bipush        59
       7: invokevirtual #52                 // Method java/lang/String.lastIndexOf:(I)I
      10: iconst_1
      11: iadd
      12: istore        4
      14: iload         4
      16: ifle          40
      19: iload         4
      21: aload_3
      22: invokevirtual #21                 // Method java/lang/String.length:()I
      25: if_icmpge     82
      28: aload_3
      29: ldc           #53                 // String charset
      31: iload         4
      33: invokevirtual #54                 // Method java/lang/String.indexOf:(Ljava/lang/String;I)I
      36: iconst_m1
      37: if_icmpne     82
      40: aload_0
      41: aload_1
      42: invokevirtual #55                 // Method chooseCharacterEncoding:(Ljavax/servlet/http/HttpServletRequest;)Ljava/lang/String;
      45: astore        5
      47: ldc           #56                 // String ISO-8859-1
      49: aload         5
      51: invokevirtual #57                 // Method java/lang/String.equalsIgnoreCase:(Ljava/lang/String;)Z
      54: ifne          82
      57: new           #12                 // class java/lang/StringBuffer
      60: dup
      61: invokespecial #13                 // Method java/lang/StringBuffer."<init>":()V
      64: aload_3
      65: invokevirtual #15                 // Method java/lang/StringBuffer.append:(Ljava/lang/String;)Ljava/lang/StringBuffer;
      68: ldc           #58                 // String ; charset=
      70: invokevirtual #15                 // Method java/lang/StringBuffer.append:(Ljava/lang/String;)Ljava/lang/StringBuffer;
      73: aload         5
      75: invokevirtual #15                 // Method java/lang/StringBuffer.append:(Ljava/lang/String;)Ljava/lang/StringBuffer;
      78: invokevirtual #17                 // Method java/lang/StringBuffer.toString:()Ljava/lang/String;
      81: astore_3
      82: aload_2
      83: aload_3
      84: invokeinterface #59,  2           // InterfaceMethod javax/servlet/http/HttpServletResponse.setContentType:(Ljava/lang/String;)V
      89: return

  protected java.lang.String chooseCharacterEncoding(javax.servlet.http.HttpServletRequest);
    Code:
       0: ldc           #60                 // String output.encoding
       2: ldc           #56                 // String ISO-8859-1
       4: invokestatic  #6                  // Method org/apache/velocity/runtime/RuntimeSingleton.getString:(Ljava/lang/String;Ljava/lang/String;)Ljava/lang/String;
       7: areturn

  protected org.apache.velocity.context.Context createContext(javax.servlet.http.HttpServletRequest, javax.servlet.http.HttpServletResponse);
    Code:
       0: new           #61                 // class org/apache/velocity/VelocityContext
       3: dup
       4: invokespecial #62                 // Method org/apache/velocity/VelocityContext."<init>":()V
       7: astore_3
       8: aload_3
       9: ldc           #63                 // String req
      11: aload_1
      12: invokevirtual #64                 // Method org/apache/velocity/VelocityContext.put:(Ljava/lang/String;Ljava/lang/Object;)Ljava/lang/Object;
      15: pop
      16: aload_3
      17: ldc           #65                 // String res
      19: aload_2
      20: invokevirtual #64                 // Method org/apache/velocity/VelocityContext.put:(Ljava/lang/String;Ljava/lang/Object;)Ljava/lang/Object;
      23: pop
      24: aload_3
      25: areturn

  public org.apache.velocity.Template getTemplate(java.lang.String) throws org.apache.velocity.exception.ResourceNotFoundException, org.apache.velocity.exception.ParseErrorException, java.lang.Exception;
    Code:
       0: aload_1
       1: invokestatic  #66                 // Method org/apache/velocity/runtime/RuntimeSingleton.getTemplate:(Ljava/lang/String;)Lorg/apache/velocity/Template;
       4: areturn

  public org.apache.velocity.Template getTemplate(java.lang.String, java.lang.String) throws org.apache.velocity.exception.ResourceNotFoundException, org.apache.velocity.exception.ParseErrorException, java.lang.Exception;
    Code:
       0: aload_1
       1: aload_2
       2: invokestatic  #67                 // Method org/apache/velocity/runtime/RuntimeSingleton.getTemplate:(Ljava/lang/String;Ljava/lang/String;)Lorg/apache/velocity/Template;
       5: areturn

  protected org.apache.velocity.Template handleRequest(javax.servlet.http.HttpServletRequest, javax.servlet.http.HttpServletResponse, org.apache.velocity.context.Context) throws java.lang.Exception;
    Code:
       0: aload_0
       1: aload_3
       2: invokevirtual #68                 // Method handleRequest:(Lorg/apache/velocity/context/Context;)Lorg/apache/velocity/Template;
       5: astore        4
       7: aload         4
       9: ifnonnull     22
      12: new           #10                 // class java/lang/Exception
      15: dup
      16: ldc           #69                 // String handleRequest(Context) returned null - no template selected!
      18: invokespecial #70                 // Method java/lang/Exception."<init>":(Ljava/lang/String;)V
      21: athrow
      22: aload         4
      24: areturn

  protected org.apache.velocity.Template handleRequest(org.apache.velocity.context.Context) throws java.lang.Exception;
    Code:
       0: new           #10                 // class java/lang/Exception
       3: dup
       4: ldc           #71                 // String You must override VelocityServlet.handleRequest( Context)  or VelocityServlet.handleRequest( HttpServletRequest,  HttpServletResponse, Context)
       6: invokespecial #70                 // Method java/lang/Exception."<init>":(Ljava/lang/String;)V
       9: athrow

  protected void error(javax.servlet.http.HttpServletRequest, javax.servlet.http.HttpServletResponse, java.lang.Exception) throws javax.servlet.ServletException, java.io.IOException;
    Code:
       0: new           #12                 // class java/lang/StringBuffer
       3: dup
       4: invokespecial #13                 // Method java/lang/StringBuffer."<init>":()V
       7: astore        4
       9: aload         4
      11: ldc           #72                 // String <html>
      13: invokevirtual #15                 // Method java/lang/StringBuffer.append:(Ljava/lang/String;)Ljava/lang/StringBuffer;
      16: pop
      17: aload         4
      19: ldc           #73                 // String <title>Error</title>
      21: invokevirtual #15                 // Method java/lang/StringBuffer.append:(Ljava/lang/String;)Ljava/lang/StringBuffer;
      24: pop
      25: aload         4
      27: ldc           #74                 // String <body bgcolor=\"#ffffff\">
      29: invokevirtual #15                 // Method java/lang/StringBuffer.append:(Ljava/lang/String;)Ljava/lang/StringBuffer;
      32: pop
      33: aload         4
      35: ldc           #75                 // String <h2>VelocityServlet: Error processing the template</h2>
      37: invokevirtual #15                 // Method java/lang/StringBuffer.append:(Ljava/lang/String;)Ljava/lang/StringBuffer;
      40: pop
      41: aload         4
      43: ldc           #76                 // String <pre>
      45: invokevirtual #15                 // Method java/lang/StringBuffer.append:(Ljava/lang/String;)Ljava/lang/StringBuffer;
      48: pop
      49: aload_3
      50: invokevirtual #77                 // Method java/lang/Exception.getMessage:()Ljava/lang/String;
      53: astore        5
      55: aload         5
      57: ifnull        87
      60: aload         5
      62: invokevirtual #78                 // Method java/lang/String.trim:()Ljava/lang/String;
      65: invokevirtual #21                 // Method java/lang/String.length:()I
      68: ifle          87
      71: aload         4
      73: aload         5
      75: invokevirtual #15                 // Method java/lang/StringBuffer.append:(Ljava/lang/String;)Ljava/lang/StringBuffer;
      78: pop
      79: aload         4
      81: ldc           #79                 // String <br>
      83: invokevirtual #15                 // Method java/lang/StringBuffer.append:(Ljava/lang/String;)Ljava/lang/StringBuffer;
      86: pop
      87: new           #80                 // class java/io/StringWriter
      90: dup
      91: invokespecial #81                 // Method java/io/StringWriter."<init>":()V
      94: astore        6
      96: aload_3
      97: new           #82                 // class java/io/PrintWriter
     100: dup
     101: aload         6
     103: invokespecial #83                 // Method java/io/PrintWriter."<init>":(Ljava/io/Writer;)V
     106: invokevirtual #84                 // Method java/lang/Exception.printStackTrace:(Ljava/io/PrintWriter;)V
     109: aload         4
     111: aload         6
     113: invokevirtual #85                 // Method java/io/StringWriter.toString:()Ljava/lang/String;
     116: invokevirtual #15                 // Method java/lang/StringBuffer.append:(Ljava/lang/String;)Ljava/lang/StringBuffer;
     119: pop
     120: aload         4
     122: ldc           #86                 // String </pre>
     124: invokevirtual #15                 // Method java/lang/StringBuffer.append:(Ljava/lang/String;)Ljava/lang/StringBuffer;
     127: pop
     128: aload         4
     130: ldc           #87                 // String </body>
     132: invokevirtual #15                 // Method java/lang/StringBuffer.append:(Ljava/lang/String;)Ljava/lang/StringBuffer;
     135: pop
     136: aload         4
     138: ldc           #88                 // String </html>
     140: invokevirtual #15                 // Method java/lang/StringBuffer.append:(Ljava/lang/String;)Ljava/lang/StringBuffer;
     143: pop
     144: aload_2
     145: invokeinterface #39,  1           // InterfaceMethod javax/servlet/http/HttpServletResponse.getOutputStream:()Ljavax/servlet/ServletOutputStream;
     150: aload         4
     152: invokevirtual #17                 // Method java/lang/StringBuffer.toString:()Ljava/lang/String;
     155: invokevirtual #89                 // Method javax/servlet/ServletOutputStream.print:(Ljava/lang/String;)V
     158: return

  static {};
    Code:
       0: new           #90                 // class org/apache/velocity/util/SimplePool
       3: dup
       4: bipush        40
       6: invokespecial #91                 // Method org/apache/velocity/util/SimplePool."<init>":(I)V
       9: putstatic     #41                 // Field writerPool:Lorg/apache/velocity/util/SimplePool;
      12: return
}
