Compiled from "OWLDLProfile.java"
public class org.apache.jena.ontology.impl.OWLDLProfile extends org.apache.jena.ontology.impl.OWLProfile {
  protected static java.lang.Object[][] s_supportsCheckData;

  private static java.util.HashMap<java.lang.Class<?>, org.apache.jena.ontology.impl.OWLProfile$SupportsCheck> s_supportsChecks;

  public org.apache.jena.ontology.impl.OWLDLProfile();
    Code:
       0: aload_0
       1: invokespecial #1                  // Method org/apache/jena/ontology/impl/OWLProfile."<init>":()V
       4: return

  public java.lang.String getLabel();
    Code:
       0: ldc           #2                  // String OWL DL
       2: areturn

  public static boolean containsSome(org.apache.jena.enhanced.EnhGraph, org.apache.jena.graph.Node, org.apache.jena.rdf.model.Property);
    Code:
       0: aload_0
       1: aload_1
       2: aload_2
       3: invokestatic  #3                  // Method org/apache/jena/ontology/impl/AbstractProfile.containsSome:(Lorg/apache/jena/enhanced/EnhGraph;Lorg/apache/jena/graph/Node;Lorg/apache/jena/rdf/model/Property;)Z
       6: ireturn

  protected java.util.Map<java.lang.Class<?>, org.apache.jena.ontology.impl.OWLProfile$SupportsCheck> getCheckTable();
    Code:
       0: getstatic     #4                  // Field s_supportsChecks:Ljava/util/HashMap;
       3: areturn

  static {};
    Code:
       0: bipush        21
       2: anewarray     #5                  // class "[Ljava/lang/Object;"
       5: dup
       6: iconst_0
       7: iconst_2
       8: anewarray     #6                  // class java/lang/Object
      11: dup
      12: iconst_0
      13: ldc           #7                  // class org/apache/jena/ontology/AllDifferent
      15: aastore
      16: dup
      17: iconst_1
      18: new           #8                  // class org/apache/jena/ontology/impl/OWLDLProfile$1
      21: dup
      22: invokespecial #9                  // Method org/apache/jena/ontology/impl/OWLDLProfile$1."<init>":()V
      25: aastore
      26: aastore
      27: dup
      28: iconst_1
      29: iconst_2
      30: anewarray     #6                  // class java/lang/Object
      33: dup
      34: iconst_0
      35: ldc           #10                 // class org/apache/jena/ontology/AnnotationProperty
      37: aastore
      38: dup
      39: iconst_1
      40: new           #11                 // class org/apache/jena/ontology/impl/OWLDLProfile$2
      43: dup
      44: invokespecial #12                 // Method org/apache/jena/ontology/impl/OWLDLProfile$2."<init>":()V
      47: aastore
      48: aastore
      49: dup
      50: iconst_2
      51: iconst_2
      52: anewarray     #6                  // class java/lang/Object
      55: dup
      56: iconst_0
      57: ldc           #13                 // class org/apache/jena/ontology/OntClass
      59: aastore
      60: dup
      61: iconst_1
      62: new           #14                 // class org/apache/jena/ontology/impl/OWLDLProfile$3
      65: dup
      66: invokespecial #15                 // Method org/apache/jena/ontology/impl/OWLDLProfile$3."<init>":()V
      69: aastore
      70: aastore
      71: dup
      72: iconst_3
      73: iconst_2
      74: anewarray     #6                  // class java/lang/Object
      77: dup
      78: iconst_0
      79: ldc           #16                 // class org/apache/jena/ontology/DatatypeProperty
      81: aastore
      82: dup
      83: iconst_1
      84: new           #17                 // class org/apache/jena/ontology/impl/OWLDLProfile$4
      87: dup
      88: invokespecial #18                 // Method org/apache/jena/ontology/impl/OWLDLProfile$4."<init>":()V
      91: aastore
      92: aastore
      93: dup
      94: iconst_4
      95: iconst_2
      96: anewarray     #6                  // class java/lang/Object
      99: dup
     100: iconst_0
     101: ldc           #19                 // class org/apache/jena/ontology/ObjectProperty
     103: aastore
     104: dup
     105: iconst_1
     106: new           #20                 // class org/apache/jena/ontology/impl/OWLDLProfile$5
     109: dup
     110: invokespecial #21                 // Method org/apache/jena/ontology/impl/OWLDLProfile$5."<init>":()V
     113: aastore
     114: aastore
     115: dup
     116: iconst_5
     117: iconst_2
     118: anewarray     #6                  // class java/lang/Object
     121: dup
     122: iconst_0
     123: ldc           #22                 // class org/apache/jena/ontology/FunctionalProperty
     125: aastore
     126: dup
     127: iconst_1
     128: new           #23                 // class org/apache/jena/ontology/impl/OWLDLProfile$6
     131: dup
     132: invokespecial #24                 // Method org/apache/jena/ontology/impl/OWLDLProfile$6."<init>":()V
     135: aastore
     136: aastore
     137: dup
     138: bipush        6
     140: iconst_2
     141: anewarray     #6                  // class java/lang/Object
     144: dup
     145: iconst_0
     146: ldc           #25                 // class org/apache/jena/ontology/InverseFunctionalProperty
     148: aastore
     149: dup
     150: iconst_1
     151: new           #26                 // class org/apache/jena/ontology/impl/OWLDLProfile$7
     154: dup
     155: invokespecial #27                 // Method org/apache/jena/ontology/impl/OWLDLProfile$7."<init>":()V
     158: aastore
     159: aastore
     160: dup
     161: bipush        7
     163: iconst_2
     164: anewarray     #6                  // class java/lang/Object
     167: dup
     168: iconst_0
     169: ldc           #28                 // class org/apache/jena/rdf/model/RDFList
     171: aastore
     172: dup
     173: iconst_1
     174: new           #29                 // class org/apache/jena/ontology/impl/OWLDLProfile$8
     177: dup
     178: invokespecial #30                 // Method org/apache/jena/ontology/impl/OWLDLProfile$8."<init>":()V
     181: aastore
     182: aastore
     183: dup
     184: bipush        8
     186: iconst_2
     187: anewarray     #6                  // class java/lang/Object
     190: dup
     191: iconst_0
     192: ldc           #31                 // class org/apache/jena/ontology/OntProperty
     194: aastore
     195: dup
     196: iconst_1
     197: new           #32                 // class org/apache/jena/ontology/impl/OWLDLProfile$9
     200: dup
     201: invokespecial #33                 // Method org/apache/jena/ontology/impl/OWLDLProfile$9."<init>":()V
     204: aastore
     205: aastore
     206: dup
     207: bipush        9
     209: iconst_2
     210: anewarray     #6                  // class java/lang/Object
     213: dup
     214: iconst_0
     215: ldc           #34                 // class org/apache/jena/ontology/Ontology
     217: aastore
     218: dup
     219: iconst_1
     220: new           #35                 // class org/apache/jena/ontology/impl/OWLDLProfile$10
     223: dup
     224: invokespecial #36                 // Method org/apache/jena/ontology/impl/OWLDLProfile$10."<init>":()V
     227: aastore
     228: aastore
     229: dup
     230: bipush        10
     232: iconst_2
     233: anewarray     #6                  // class java/lang/Object
     236: dup
     237: iconst_0
     238: ldc           #37                 // class org/apache/jena/ontology/Restriction
     240: aastore
     241: dup
     242: iconst_1
     243: new           #38                 // class org/apache/jena/ontology/impl/OWLDLProfile$11
     246: dup
     247: invokespecial #39                 // Method org/apache/jena/ontology/impl/OWLDLProfile$11."<init>":()V
     250: aastore
     251: aastore
     252: dup
     253: bipush        11
     255: iconst_2
     256: anewarray     #6                  // class java/lang/Object
     259: dup
     260: iconst_0
     261: ldc           #40                 // class org/apache/jena/ontology/AllValuesFromRestriction
     263: aastore
     264: dup
     265: iconst_1
     266: new           #41                 // class org/apache/jena/ontology/impl/OWLDLProfile$12
     269: dup
     270: invokespecial #42                 // Method org/apache/jena/ontology/impl/OWLDLProfile$12."<init>":()V
     273: aastore
     274: aastore
     275: dup
     276: bipush        12
     278: iconst_2
     279: anewarray     #6                  // class java/lang/Object
     282: dup
     283: iconst_0
     284: ldc           #43                 // class org/apache/jena/ontology/SomeValuesFromRestriction
     286: aastore
     287: dup
     288: iconst_1
     289: new           #44                 // class org/apache/jena/ontology/impl/OWLDLProfile$13
     292: dup
     293: invokespecial #45                 // Method org/apache/jena/ontology/impl/OWLDLProfile$13."<init>":()V
     296: aastore
     297: aastore
     298: dup
     299: bipush        13
     301: iconst_2
     302: anewarray     #6                  // class java/lang/Object
     305: dup
     306: iconst_0
     307: ldc           #46                 // class org/apache/jena/ontology/HasValueRestriction
     309: aastore
     310: dup
     311: iconst_1
     312: new           #47                 // class org/apache/jena/ontology/impl/OWLDLProfile$14
     315: dup
     316: invokespecial #48                 // Method org/apache/jena/ontology/impl/OWLDLProfile$14."<init>":()V
     319: aastore
     320: aastore
     321: dup
     322: bipush        14
     324: iconst_2
     325: anewarray     #6                  // class java/lang/Object
     328: dup
     329: iconst_0
     330: ldc           #49                 // class org/apache/jena/ontology/CardinalityRestriction
     332: aastore
     333: dup
     334: iconst_1
     335: new           #50                 // class org/apache/jena/ontology/impl/OWLDLProfile$15
     338: dup
     339: invokespecial #51                 // Method org/apache/jena/ontology/impl/OWLDLProfile$15."<init>":()V
     342: aastore
     343: aastore
     344: dup
     345: bipush        15
     347: iconst_2
     348: anewarray     #6                  // class java/lang/Object
     351: dup
     352: iconst_0
     353: ldc           #52                 // class org/apache/jena/ontology/MinCardinalityRestriction
     355: aastore
     356: dup
     357: iconst_1
     358: new           #53                 // class org/apache/jena/ontology/impl/OWLDLProfile$16
     361: dup
     362: invokespecial #54                 // Method org/apache/jena/ontology/impl/OWLDLProfile$16."<init>":()V
     365: aastore
     366: aastore
     367: dup
     368: bipush        16
     370: iconst_2
     371: anewarray     #6                  // class java/lang/Object
     374: dup
     375: iconst_0
     376: ldc           #55                 // class org/apache/jena/ontology/MaxCardinalityRestriction
     378: aastore
     379: dup
     380: iconst_1
     381: new           #56                 // class org/apache/jena/ontology/impl/OWLDLProfile$17
     384: dup
     385: invokespecial #57                 // Method org/apache/jena/ontology/impl/OWLDLProfile$17."<init>":()V
     388: aastore
     389: aastore
     390: dup
     391: bipush        17
     393: iconst_2
     394: anewarray     #6                  // class java/lang/Object
     397: dup
     398: iconst_0
     399: ldc           #58                 // class org/apache/jena/ontology/SymmetricProperty
     401: aastore
     402: dup
     403: iconst_1
     404: new           #59                 // class org/apache/jena/ontology/impl/OWLDLProfile$18
     407: dup
     408: invokespecial #60                 // Method org/apache/jena/ontology/impl/OWLDLProfile$18."<init>":()V
     411: aastore
     412: aastore
     413: dup
     414: bipush        18
     416: iconst_2
     417: anewarray     #6                  // class java/lang/Object
     420: dup
     421: iconst_0
     422: ldc           #61                 // class org/apache/jena/ontology/TransitiveProperty
     424: aastore
     425: dup
     426: iconst_1
     427: new           #62                 // class org/apache/jena/ontology/impl/OWLDLProfile$19
     430: dup
     431: invokespecial #63                 // Method org/apache/jena/ontology/impl/OWLDLProfile$19."<init>":()V
     434: aastore
     435: aastore
     436: dup
     437: bipush        19
     439: iconst_2
     440: anewarray     #6                  // class java/lang/Object
     443: dup
     444: iconst_0
     445: ldc           #64                 // class org/apache/jena/ontology/Individual
     447: aastore
     448: dup
     449: iconst_1
     450: new           #65                 // class org/apache/jena/ontology/impl/OWLDLProfile$20
     453: dup
     454: invokespecial #66                 // Method org/apache/jena/ontology/impl/OWLDLProfile$20."<init>":()V
     457: aastore
     458: aastore
     459: dup
     460: bipush        20
     462: iconst_2
     463: anewarray     #6                  // class java/lang/Object
     466: dup
     467: iconst_0
     468: ldc           #67                 // class org/apache/jena/ontology/DataRange
     470: aastore
     471: dup
     472: iconst_1
     473: new           #68                 // class org/apache/jena/ontology/impl/OWLDLProfile$21
     476: dup
     477: invokespecial #69                 // Method org/apache/jena/ontology/impl/OWLDLProfile$21."<init>":()V
     480: aastore
     481: aastore
     482: putstatic     #70                 // Field s_supportsCheckData:[[Ljava/lang/Object;
     485: new           #71                 // class java/util/HashMap
     488: dup
     489: invokespecial #72                 // Method java/util/HashMap."<init>":()V
     492: putstatic     #4                  // Field s_supportsChecks:Ljava/util/HashMap;
     495: getstatic     #70                 // Field s_supportsCheckData:[[Ljava/lang/Object;
     498: astore_0
     499: aload_0
     500: arraylength
     501: istore_1
     502: iconst_0
     503: istore_2
     504: iload_2
     505: iload_1
     506: if_icmpge     538
     509: aload_0
     510: iload_2
     511: aaload
     512: astore_3
     513: getstatic     #4                  // Field s_supportsChecks:Ljava/util/HashMap;
     516: aload_3
     517: iconst_0
     518: aaload
     519: checkcast     #73                 // class java/lang/Class
     522: aload_3
     523: iconst_1
     524: aaload
     525: checkcast     #74                 // class org/apache/jena/ontology/impl/OWLProfile$SupportsCheck
     528: invokevirtual #75                 // Method java/util/HashMap.put:(Ljava/lang/Object;Ljava/lang/Object;)Ljava/lang/Object;
     531: pop
     532: iinc          2, 1
     535: goto          504
     538: return
}
