Compiled from "OWLProfile.java"
public class org.apache.jena.ontology.impl.OWLProfile extends org.apache.jena.ontology.impl.AbstractProfile {
  private static java.lang.Object[][] s_supportsCheckData;

  private static java.util.HashMap<java.lang.Class<?>, org.apache.jena.ontology.impl.OWLProfile$SupportsCheck> s_supportsChecks;

  public org.apache.jena.ontology.impl.OWLProfile();
    Code:
       0: aload_0
       1: invokespecial #1                  // Method org/apache/jena/ontology/impl/AbstractProfile."<init>":()V
       4: return

  public java.lang.String NAMESPACE();
    Code:
       0: invokestatic  #2                  // Method org/apache/jena/vocabulary/OWL.getURI:()Ljava/lang/String;
       3: areturn

  public org.apache.jena.rdf.model.Resource CLASS();
    Code:
       0: getstatic     #3                  // Field org/apache/jena/vocabulary/OWL.Class:Lorg/apache/jena/rdf/model/Resource;
       3: areturn

  public org.apache.jena.rdf.model.Resource RESTRICTION();
    Code:
       0: getstatic     #4                  // Field org/apache/jena/vocabulary/OWL.Restriction:Lorg/apache/jena/rdf/model/Resource;
       3: areturn

  public org.apache.jena.rdf.model.Resource THING();
    Code:
       0: getstatic     #5                  // Field org/apache/jena/vocabulary/OWL.Thing:Lorg/apache/jena/rdf/model/Resource;
       3: areturn

  public org.apache.jena.rdf.model.Resource NOTHING();
    Code:
       0: getstatic     #6                  // Field org/apache/jena/vocabulary/OWL.Nothing:Lorg/apache/jena/rdf/model/Resource;
       3: areturn

  public org.apache.jena.rdf.model.Resource PROPERTY();
    Code:
       0: getstatic     #7                  // Field org/apache/jena/vocabulary/RDF.Property:Lorg/apache/jena/rdf/model/Resource;
       3: areturn

  public org.apache.jena.rdf.model.Resource OBJECT_PROPERTY();
    Code:
       0: getstatic     #8                  // Field org/apache/jena/vocabulary/OWL.ObjectProperty:Lorg/apache/jena/rdf/model/Resource;
       3: areturn

  public org.apache.jena.rdf.model.Resource DATATYPE_PROPERTY();
    Code:
       0: getstatic     #9                  // Field org/apache/jena/vocabulary/OWL.DatatypeProperty:Lorg/apache/jena/rdf/model/Resource;
       3: areturn

  public org.apache.jena.rdf.model.Resource TRANSITIVE_PROPERTY();
    Code:
       0: getstatic     #10                 // Field org/apache/jena/vocabulary/OWL.TransitiveProperty:Lorg/apache/jena/rdf/model/Resource;
       3: areturn

  public org.apache.jena.rdf.model.Resource SYMMETRIC_PROPERTY();
    Code:
       0: getstatic     #11                 // Field org/apache/jena/vocabulary/OWL.SymmetricProperty:Lorg/apache/jena/rdf/model/Resource;
       3: areturn

  public org.apache.jena.rdf.model.Resource FUNCTIONAL_PROPERTY();
    Code:
       0: getstatic     #12                 // Field org/apache/jena/vocabulary/OWL.FunctionalProperty:Lorg/apache/jena/rdf/model/Resource;
       3: areturn

  public org.apache.jena.rdf.model.Resource INVERSE_FUNCTIONAL_PROPERTY();
    Code:
       0: getstatic     #13                 // Field org/apache/jena/vocabulary/OWL.InverseFunctionalProperty:Lorg/apache/jena/rdf/model/Resource;
       3: areturn

  public org.apache.jena.rdf.model.Resource ALL_DIFFERENT();
    Code:
       0: getstatic     #14                 // Field org/apache/jena/vocabulary/OWL.AllDifferent:Lorg/apache/jena/rdf/model/Resource;
       3: areturn

  public org.apache.jena.rdf.model.Resource ONTOLOGY();
    Code:
       0: getstatic     #15                 // Field org/apache/jena/vocabulary/OWL.Ontology:Lorg/apache/jena/rdf/model/Resource;
       3: areturn

  public org.apache.jena.rdf.model.Resource DEPRECATED_CLASS();
    Code:
       0: getstatic     #16                 // Field org/apache/jena/vocabulary/OWL.DeprecatedClass:Lorg/apache/jena/rdf/model/Resource;
       3: areturn

  public org.apache.jena.rdf.model.Resource DEPRECATED_PROPERTY();
    Code:
       0: getstatic     #17                 // Field org/apache/jena/vocabulary/OWL.DeprecatedProperty:Lorg/apache/jena/rdf/model/Resource;
       3: areturn

  public org.apache.jena.rdf.model.Resource ANNOTATION_PROPERTY();
    Code:
       0: getstatic     #18                 // Field org/apache/jena/vocabulary/OWL.AnnotationProperty:Lorg/apache/jena/rdf/model/Resource;
       3: areturn

  public org.apache.jena.rdf.model.Resource ONTOLOGY_PROPERTY();
    Code:
       0: getstatic     #19                 // Field org/apache/jena/vocabulary/OWL.OntologyProperty:Lorg/apache/jena/rdf/model/Resource;
       3: areturn

  public org.apache.jena.rdf.model.Resource LIST();
    Code:
       0: getstatic     #20                 // Field org/apache/jena/vocabulary/RDF.List:Lorg/apache/jena/rdf/model/Resource;
       3: areturn

  public org.apache.jena.rdf.model.Resource NIL();
    Code:
       0: getstatic     #21                 // Field org/apache/jena/vocabulary/RDF.nil:Lorg/apache/jena/rdf/model/Resource;
       3: areturn

  public org.apache.jena.rdf.model.Resource DATARANGE();
    Code:
       0: getstatic     #22                 // Field org/apache/jena/vocabulary/OWL.DataRange:Lorg/apache/jena/rdf/model/Resource;
       3: areturn

  public org.apache.jena.rdf.model.Property EQUIVALENT_PROPERTY();
    Code:
       0: getstatic     #23                 // Field org/apache/jena/vocabulary/OWL.equivalentProperty:Lorg/apache/jena/rdf/model/Property;
       3: areturn

  public org.apache.jena.rdf.model.Property EQUIVALENT_CLASS();
    Code:
       0: getstatic     #24                 // Field org/apache/jena/vocabulary/OWL.equivalentClass:Lorg/apache/jena/rdf/model/Property;
       3: areturn

  public org.apache.jena.rdf.model.Property DISJOINT_WITH();
    Code:
       0: getstatic     #25                 // Field org/apache/jena/vocabulary/OWL.disjointWith:Lorg/apache/jena/rdf/model/Property;
       3: areturn

  public org.apache.jena.rdf.model.Property SAME_INDIVIDUAL_AS();
    Code:
       0: aconst_null
       1: areturn

  public org.apache.jena.rdf.model.Property SAME_AS();
    Code:
       0: getstatic     #26                 // Field org/apache/jena/vocabulary/OWL.sameAs:Lorg/apache/jena/rdf/model/Property;
       3: areturn

  public org.apache.jena.rdf.model.Property DIFFERENT_FROM();
    Code:
       0: getstatic     #27                 // Field org/apache/jena/vocabulary/OWL.differentFrom:Lorg/apache/jena/rdf/model/Property;
       3: areturn

  public org.apache.jena.rdf.model.Property DISTINCT_MEMBERS();
    Code:
       0: getstatic     #28                 // Field org/apache/jena/vocabulary/OWL.distinctMembers:Lorg/apache/jena/rdf/model/Property;
       3: areturn

  public org.apache.jena.rdf.model.Property UNION_OF();
    Code:
       0: getstatic     #29                 // Field org/apache/jena/vocabulary/OWL.unionOf:Lorg/apache/jena/rdf/model/Property;
       3: areturn

  public org.apache.jena.rdf.model.Property INTERSECTION_OF();
    Code:
       0: getstatic     #30                 // Field org/apache/jena/vocabulary/OWL.intersectionOf:Lorg/apache/jena/rdf/model/Property;
       3: areturn

  public org.apache.jena.rdf.model.Property COMPLEMENT_OF();
    Code:
       0: getstatic     #31                 // Field org/apache/jena/vocabulary/OWL.complementOf:Lorg/apache/jena/rdf/model/Property;
       3: areturn

  public org.apache.jena.rdf.model.Property ONE_OF();
    Code:
       0: getstatic     #32                 // Field org/apache/jena/vocabulary/OWL.oneOf:Lorg/apache/jena/rdf/model/Property;
       3: areturn

  public org.apache.jena.rdf.model.Property ON_PROPERTY();
    Code:
       0: getstatic     #33                 // Field org/apache/jena/vocabulary/OWL.onProperty:Lorg/apache/jena/rdf/model/Property;
       3: areturn

  public org.apache.jena.rdf.model.Property ALL_VALUES_FROM();
    Code:
       0: getstatic     #34                 // Field org/apache/jena/vocabulary/OWL.allValuesFrom:Lorg/apache/jena/rdf/model/Property;
       3: areturn

  public org.apache.jena.rdf.model.Property HAS_VALUE();
    Code:
       0: getstatic     #35                 // Field org/apache/jena/vocabulary/OWL.hasValue:Lorg/apache/jena/rdf/model/Property;
       3: areturn

  public org.apache.jena.rdf.model.Property SOME_VALUES_FROM();
    Code:
       0: getstatic     #36                 // Field org/apache/jena/vocabulary/OWL.someValuesFrom:Lorg/apache/jena/rdf/model/Property;
       3: areturn

  public org.apache.jena.rdf.model.Property MIN_CARDINALITY();
    Code:
       0: getstatic     #37                 // Field org/apache/jena/vocabulary/OWL.minCardinality:Lorg/apache/jena/rdf/model/Property;
       3: areturn

  public org.apache.jena.rdf.model.Property MAX_CARDINALITY();
    Code:
       0: getstatic     #38                 // Field org/apache/jena/vocabulary/OWL.maxCardinality:Lorg/apache/jena/rdf/model/Property;
       3: areturn

  public org.apache.jena.rdf.model.Property CARDINALITY();
    Code:
       0: getstatic     #39                 // Field org/apache/jena/vocabulary/OWL.cardinality:Lorg/apache/jena/rdf/model/Property;
       3: areturn

  public org.apache.jena.rdf.model.Property INVERSE_OF();
    Code:
       0: getstatic     #40                 // Field org/apache/jena/vocabulary/OWL.inverseOf:Lorg/apache/jena/rdf/model/Property;
       3: areturn

  public org.apache.jena.rdf.model.Property IMPORTS();
    Code:
       0: getstatic     #41                 // Field org/apache/jena/vocabulary/OWL.imports:Lorg/apache/jena/rdf/model/Property;
       3: areturn

  public org.apache.jena.rdf.model.Property PRIOR_VERSION();
    Code:
       0: getstatic     #42                 // Field org/apache/jena/vocabulary/OWL.priorVersion:Lorg/apache/jena/rdf/model/Property;
       3: areturn

  public org.apache.jena.rdf.model.Property BACKWARD_COMPATIBLE_WITH();
    Code:
       0: getstatic     #43                 // Field org/apache/jena/vocabulary/OWL.backwardCompatibleWith:Lorg/apache/jena/rdf/model/Property;
       3: areturn

  public org.apache.jena.rdf.model.Property INCOMPATIBLE_WITH();
    Code:
       0: getstatic     #44                 // Field org/apache/jena/vocabulary/OWL.incompatibleWith:Lorg/apache/jena/rdf/model/Property;
       3: areturn

  public org.apache.jena.rdf.model.Property SUB_PROPERTY_OF();
    Code:
       0: getstatic     #45                 // Field org/apache/jena/vocabulary/RDFS.subPropertyOf:Lorg/apache/jena/rdf/model/Property;
       3: areturn

  public org.apache.jena.rdf.model.Property SUB_CLASS_OF();
    Code:
       0: getstatic     #46                 // Field org/apache/jena/vocabulary/RDFS.subClassOf:Lorg/apache/jena/rdf/model/Property;
       3: areturn

  public org.apache.jena.rdf.model.Property DOMAIN();
    Code:
       0: getstatic     #47                 // Field org/apache/jena/vocabulary/RDFS.domain:Lorg/apache/jena/rdf/model/Property;
       3: areturn

  public org.apache.jena.rdf.model.Property RANGE();
    Code:
       0: getstatic     #48                 // Field org/apache/jena/vocabulary/RDFS.range:Lorg/apache/jena/rdf/model/Property;
       3: areturn

  public org.apache.jena.rdf.model.Property FIRST();
    Code:
       0: getstatic     #49                 // Field org/apache/jena/vocabulary/RDF.first:Lorg/apache/jena/rdf/model/Property;
       3: areturn

  public org.apache.jena.rdf.model.Property REST();
    Code:
       0: getstatic     #50                 // Field org/apache/jena/vocabulary/RDF.rest:Lorg/apache/jena/rdf/model/Property;
       3: areturn

  public org.apache.jena.rdf.model.Property MIN_CARDINALITY_Q();
    Code:
       0: aconst_null
       1: areturn

  public org.apache.jena.rdf.model.Property MAX_CARDINALITY_Q();
    Code:
       0: aconst_null
       1: areturn

  public org.apache.jena.rdf.model.Property CARDINALITY_Q();
    Code:
       0: aconst_null
       1: areturn

  public org.apache.jena.rdf.model.Property HAS_CLASS_Q();
    Code:
       0: aconst_null
       1: areturn

  public org.apache.jena.rdf.model.Property VERSION_INFO();
    Code:
       0: getstatic     #51                 // Field org/apache/jena/vocabulary/OWL.versionInfo:Lorg/apache/jena/rdf/model/Property;
       3: areturn

  public org.apache.jena.rdf.model.Property LABEL();
    Code:
       0: getstatic     #52                 // Field org/apache/jena/vocabulary/RDFS.label:Lorg/apache/jena/rdf/model/Property;
       3: areturn

  public org.apache.jena.rdf.model.Property COMMENT();
    Code:
       0: getstatic     #53                 // Field org/apache/jena/vocabulary/RDFS.comment:Lorg/apache/jena/rdf/model/Property;
       3: areturn

  public org.apache.jena.rdf.model.Property SEE_ALSO();
    Code:
       0: getstatic     #54                 // Field org/apache/jena/vocabulary/RDFS.seeAlso:Lorg/apache/jena/rdf/model/Property;
       3: areturn

  public org.apache.jena.rdf.model.Property IS_DEFINED_BY();
    Code:
       0: getstatic     #55                 // Field org/apache/jena/vocabulary/RDFS.isDefinedBy:Lorg/apache/jena/rdf/model/Property;
       3: areturn

  protected org.apache.jena.rdf.model.Resource[][] aliasTable();
    Code:
       0: iconst_0
       1: anewarray     #56                 // class "[Lorg/apache/jena/rdf/model/Resource;"
       4: areturn

  public java.util.Iterator<org.apache.jena.rdf.model.Resource> getAxiomTypes();
    Code:
       0: iconst_1
       1: anewarray     #57                 // class org/apache/jena/rdf/model/Resource
       4: dup
       5: iconst_0
       6: getstatic     #14                 // Field org/apache/jena/vocabulary/OWL.AllDifferent:Lorg/apache/jena/rdf/model/Resource;
       9: aastore
      10: invokestatic  #58                 // Method java/util/Arrays.asList:([Ljava/lang/Object;)Ljava/util/List;
      13: invokeinterface #59,  1           // InterfaceMethod java/util/List.iterator:()Ljava/util/Iterator;
      18: areturn

  public java.util.Iterator<org.apache.jena.rdf.model.Resource> getAnnotationProperties();
    Code:
       0: iconst_5
       1: anewarray     #57                 // class org/apache/jena/rdf/model/Resource
       4: dup
       5: iconst_0
       6: getstatic     #51                 // Field org/apache/jena/vocabulary/OWL.versionInfo:Lorg/apache/jena/rdf/model/Property;
       9: aastore
      10: dup
      11: iconst_1
      12: getstatic     #52                 // Field org/apache/jena/vocabulary/RDFS.label:Lorg/apache/jena/rdf/model/Property;
      15: aastore
      16: dup
      17: iconst_2
      18: getstatic     #54                 // Field org/apache/jena/vocabulary/RDFS.seeAlso:Lorg/apache/jena/rdf/model/Property;
      21: aastore
      22: dup
      23: iconst_3
      24: getstatic     #53                 // Field org/apache/jena/vocabulary/RDFS.comment:Lorg/apache/jena/rdf/model/Property;
      27: aastore
      28: dup
      29: iconst_4
      30: getstatic     #55                 // Field org/apache/jena/vocabulary/RDFS.isDefinedBy:Lorg/apache/jena/rdf/model/Property;
      33: aastore
      34: invokestatic  #58                 // Method java/util/Arrays.asList:([Ljava/lang/Object;)Ljava/util/List;
      37: invokeinterface #59,  1           // InterfaceMethod java/util/List.iterator:()Ljava/util/Iterator;
      42: areturn

  public java.util.Iterator<org.apache.jena.rdf.model.Resource> getClassDescriptionTypes();
    Code:
       0: iconst_2
       1: anewarray     #57                 // class org/apache/jena/rdf/model/Resource
       4: dup
       5: iconst_0
       6: getstatic     #3                  // Field org/apache/jena/vocabulary/OWL.Class:Lorg/apache/jena/rdf/model/Resource;
       9: aastore
      10: dup
      11: iconst_1
      12: getstatic     #4                  // Field org/apache/jena/vocabulary/OWL.Restriction:Lorg/apache/jena/rdf/model/Resource;
      15: aastore
      16: invokestatic  #58                 // Method java/util/Arrays.asList:([Ljava/lang/Object;)Ljava/util/List;
      19: invokeinterface #59,  1           // InterfaceMethod java/util/List.iterator:()Ljava/util/Iterator;
      24: areturn

  public <T> boolean isSupported(org.apache.jena.graph.Node, org.apache.jena.enhanced.EnhGraph, java.lang.Class<T>);
    Code:
       0: aload_2
       1: instanceof    #60                 // class org/apache/jena/ontology/OntModel
       4: ifeq          61
       7: aload_2
       8: checkcast     #60                 // class org/apache/jena/ontology/OntModel
      11: astore        4
      13: aload         4
      15: invokeinterface #61,  1           // InterfaceMethod org/apache/jena/ontology/OntModel.strictMode:()Z
      20: ifne          25
      23: iconst_1
      24: ireturn
      25: aload_0
      26: invokevirtual #62                 // Method getCheckTable:()Ljava/util/Map;
      29: aload_3
      30: invokeinterface #63,  2           // InterfaceMethod java/util/Map.get:(Ljava/lang/Object;)Ljava/lang/Object;
      35: checkcast     #64                 // class org/apache/jena/ontology/impl/OWLProfile$SupportsCheck
      38: astore        5
      40: aload         5
      42: ifnull        59
      45: aload         5
      47: aload_1
      48: aload_2
      49: invokevirtual #65                 // Method org/apache/jena/ontology/impl/OWLProfile$SupportsCheck.doCheck:(Lorg/apache/jena/graph/Node;Lorg/apache/jena/enhanced/EnhGraph;)Z
      52: ifeq          59
      55: iconst_1
      56: goto          60
      59: iconst_0
      60: ireturn
      61: iconst_0
      62: ireturn

  public java.lang.String getLabel();
    Code:
       0: ldc           #66                 // String OWL Full
       2: areturn

  public static boolean containsSome(org.apache.jena.enhanced.EnhGraph, org.apache.jena.graph.Node, org.apache.jena.rdf.model.Property);
    Code:
       0: aload_0
       1: aload_1
       2: aload_2
       3: invokestatic  #67                 // Method org/apache/jena/ontology/impl/AbstractProfile.containsSome:(Lorg/apache/jena/enhanced/EnhGraph;Lorg/apache/jena/graph/Node;Lorg/apache/jena/rdf/model/Property;)Z
       6: ireturn

  protected java.util.Map<java.lang.Class<?>, org.apache.jena.ontology.impl.OWLProfile$SupportsCheck> getCheckTable();
    Code:
       0: getstatic     #68                 // Field s_supportsChecks:Ljava/util/HashMap;
       3: areturn

  static {};
    Code:
       0: bipush        21
       2: anewarray     #69                 // class "[Ljava/lang/Object;"
       5: dup
       6: iconst_0
       7: iconst_2
       8: anewarray     #70                 // class java/lang/Object
      11: dup
      12: iconst_0
      13: ldc           #71                 // class org/apache/jena/ontology/AllDifferent
      15: aastore
      16: dup
      17: iconst_1
      18: new           #72                 // class org/apache/jena/ontology/impl/OWLProfile$1
      21: dup
      22: invokespecial #73                 // Method org/apache/jena/ontology/impl/OWLProfile$1."<init>":()V
      25: aastore
      26: aastore
      27: dup
      28: iconst_1
      29: iconst_2
      30: anewarray     #70                 // class java/lang/Object
      33: dup
      34: iconst_0
      35: ldc           #74                 // class org/apache/jena/ontology/AnnotationProperty
      37: aastore
      38: dup
      39: iconst_1
      40: new           #75                 // class org/apache/jena/ontology/impl/OWLProfile$2
      43: dup
      44: invokespecial #76                 // Method org/apache/jena/ontology/impl/OWLProfile$2."<init>":()V
      47: aastore
      48: aastore
      49: dup
      50: iconst_2
      51: iconst_2
      52: anewarray     #70                 // class java/lang/Object
      55: dup
      56: iconst_0
      57: ldc           #77                 // class org/apache/jena/ontology/OntClass
      59: aastore
      60: dup
      61: iconst_1
      62: new           #78                 // class org/apache/jena/ontology/impl/OWLProfile$3
      65: dup
      66: invokespecial #79                 // Method org/apache/jena/ontology/impl/OWLProfile$3."<init>":()V
      69: aastore
      70: aastore
      71: dup
      72: iconst_3
      73: iconst_2
      74: anewarray     #70                 // class java/lang/Object
      77: dup
      78: iconst_0
      79: ldc           #80                 // class org/apache/jena/ontology/DatatypeProperty
      81: aastore
      82: dup
      83: iconst_1
      84: new           #81                 // class org/apache/jena/ontology/impl/OWLProfile$4
      87: dup
      88: invokespecial #82                 // Method org/apache/jena/ontology/impl/OWLProfile$4."<init>":()V
      91: aastore
      92: aastore
      93: dup
      94: iconst_4
      95: iconst_2
      96: anewarray     #70                 // class java/lang/Object
      99: dup
     100: iconst_0
     101: ldc           #83                 // class org/apache/jena/ontology/ObjectProperty
     103: aastore
     104: dup
     105: iconst_1
     106: new           #84                 // class org/apache/jena/ontology/impl/OWLProfile$5
     109: dup
     110: invokespecial #85                 // Method org/apache/jena/ontology/impl/OWLProfile$5."<init>":()V
     113: aastore
     114: aastore
     115: dup
     116: iconst_5
     117: iconst_2
     118: anewarray     #70                 // class java/lang/Object
     121: dup
     122: iconst_0
     123: ldc           #86                 // class org/apache/jena/ontology/FunctionalProperty
     125: aastore
     126: dup
     127: iconst_1
     128: new           #87                 // class org/apache/jena/ontology/impl/OWLProfile$6
     131: dup
     132: invokespecial #88                 // Method org/apache/jena/ontology/impl/OWLProfile$6."<init>":()V
     135: aastore
     136: aastore
     137: dup
     138: bipush        6
     140: iconst_2
     141: anewarray     #70                 // class java/lang/Object
     144: dup
     145: iconst_0
     146: ldc           #89                 // class org/apache/jena/ontology/InverseFunctionalProperty
     148: aastore
     149: dup
     150: iconst_1
     151: new           #90                 // class org/apache/jena/ontology/impl/OWLProfile$7
     154: dup
     155: invokespecial #91                 // Method org/apache/jena/ontology/impl/OWLProfile$7."<init>":()V
     158: aastore
     159: aastore
     160: dup
     161: bipush        7
     163: iconst_2
     164: anewarray     #70                 // class java/lang/Object
     167: dup
     168: iconst_0
     169: ldc           #92                 // class org/apache/jena/rdf/model/RDFList
     171: aastore
     172: dup
     173: iconst_1
     174: new           #93                 // class org/apache/jena/ontology/impl/OWLProfile$8
     177: dup
     178: invokespecial #94                 // Method org/apache/jena/ontology/impl/OWLProfile$8."<init>":()V
     181: aastore
     182: aastore
     183: dup
     184: bipush        8
     186: iconst_2
     187: anewarray     #70                 // class java/lang/Object
     190: dup
     191: iconst_0
     192: ldc           #95                 // class org/apache/jena/ontology/OntProperty
     194: aastore
     195: dup
     196: iconst_1
     197: new           #96                 // class org/apache/jena/ontology/impl/OWLProfile$9
     200: dup
     201: invokespecial #97                 // Method org/apache/jena/ontology/impl/OWLProfile$9."<init>":()V
     204: aastore
     205: aastore
     206: dup
     207: bipush        9
     209: iconst_2
     210: anewarray     #70                 // class java/lang/Object
     213: dup
     214: iconst_0
     215: ldc           #98                 // class org/apache/jena/ontology/Ontology
     217: aastore
     218: dup
     219: iconst_1
     220: new           #99                 // class org/apache/jena/ontology/impl/OWLProfile$10
     223: dup
     224: invokespecial #100                // Method org/apache/jena/ontology/impl/OWLProfile$10."<init>":()V
     227: aastore
     228: aastore
     229: dup
     230: bipush        10
     232: iconst_2
     233: anewarray     #70                 // class java/lang/Object
     236: dup
     237: iconst_0
     238: ldc           #101                // class org/apache/jena/ontology/Restriction
     240: aastore
     241: dup
     242: iconst_1
     243: new           #102                // class org/apache/jena/ontology/impl/OWLProfile$11
     246: dup
     247: invokespecial #103                // Method org/apache/jena/ontology/impl/OWLProfile$11."<init>":()V
     250: aastore
     251: aastore
     252: dup
     253: bipush        11
     255: iconst_2
     256: anewarray     #70                 // class java/lang/Object
     259: dup
     260: iconst_0
     261: ldc           #104                // class org/apache/jena/ontology/HasValueRestriction
     263: aastore
     264: dup
     265: iconst_1
     266: new           #105                // class org/apache/jena/ontology/impl/OWLProfile$12
     269: dup
     270: invokespecial #106                // Method org/apache/jena/ontology/impl/OWLProfile$12."<init>":()V
     273: aastore
     274: aastore
     275: dup
     276: bipush        12
     278: iconst_2
     279: anewarray     #70                 // class java/lang/Object
     282: dup
     283: iconst_0
     284: ldc           #107                // class org/apache/jena/ontology/AllValuesFromRestriction
     286: aastore
     287: dup
     288: iconst_1
     289: new           #108                // class org/apache/jena/ontology/impl/OWLProfile$13
     292: dup
     293: invokespecial #109                // Method org/apache/jena/ontology/impl/OWLProfile$13."<init>":()V
     296: aastore
     297: aastore
     298: dup
     299: bipush        13
     301: iconst_2
     302: anewarray     #70                 // class java/lang/Object
     305: dup
     306: iconst_0
     307: ldc           #110                // class org/apache/jena/ontology/SomeValuesFromRestriction
     309: aastore
     310: dup
     311: iconst_1
     312: new           #111                // class org/apache/jena/ontology/impl/OWLProfile$14
     315: dup
     316: invokespecial #112                // Method org/apache/jena/ontology/impl/OWLProfile$14."<init>":()V
     319: aastore
     320: aastore
     321: dup
     322: bipush        14
     324: iconst_2
     325: anewarray     #70                 // class java/lang/Object
     328: dup
     329: iconst_0
     330: ldc           #113                // class org/apache/jena/ontology/CardinalityRestriction
     332: aastore
     333: dup
     334: iconst_1
     335: new           #114                // class org/apache/jena/ontology/impl/OWLProfile$15
     338: dup
     339: invokespecial #115                // Method org/apache/jena/ontology/impl/OWLProfile$15."<init>":()V
     342: aastore
     343: aastore
     344: dup
     345: bipush        15
     347: iconst_2
     348: anewarray     #70                 // class java/lang/Object
     351: dup
     352: iconst_0
     353: ldc           #116                // class org/apache/jena/ontology/MinCardinalityRestriction
     355: aastore
     356: dup
     357: iconst_1
     358: new           #117                // class org/apache/jena/ontology/impl/OWLProfile$16
     361: dup
     362: invokespecial #118                // Method org/apache/jena/ontology/impl/OWLProfile$16."<init>":()V
     365: aastore
     366: aastore
     367: dup
     368: bipush        16
     370: iconst_2
     371: anewarray     #70                 // class java/lang/Object
     374: dup
     375: iconst_0
     376: ldc           #119                // class org/apache/jena/ontology/MaxCardinalityRestriction
     378: aastore
     379: dup
     380: iconst_1
     381: new           #120                // class org/apache/jena/ontology/impl/OWLProfile$17
     384: dup
     385: invokespecial #121                // Method org/apache/jena/ontology/impl/OWLProfile$17."<init>":()V
     388: aastore
     389: aastore
     390: dup
     391: bipush        17
     393: iconst_2
     394: anewarray     #70                 // class java/lang/Object
     397: dup
     398: iconst_0
     399: ldc           #122                // class org/apache/jena/ontology/SymmetricProperty
     401: aastore
     402: dup
     403: iconst_1
     404: new           #123                // class org/apache/jena/ontology/impl/OWLProfile$18
     407: dup
     408: invokespecial #124                // Method org/apache/jena/ontology/impl/OWLProfile$18."<init>":()V
     411: aastore
     412: aastore
     413: dup
     414: bipush        18
     416: iconst_2
     417: anewarray     #70                 // class java/lang/Object
     420: dup
     421: iconst_0
     422: ldc           #125                // class org/apache/jena/ontology/TransitiveProperty
     424: aastore
     425: dup
     426: iconst_1
     427: new           #126                // class org/apache/jena/ontology/impl/OWLProfile$19
     430: dup
     431: invokespecial #127                // Method org/apache/jena/ontology/impl/OWLProfile$19."<init>":()V
     434: aastore
     435: aastore
     436: dup
     437: bipush        19
     439: iconst_2
     440: anewarray     #70                 // class java/lang/Object
     443: dup
     444: iconst_0
     445: ldc           #128                // class org/apache/jena/ontology/Individual
     447: aastore
     448: dup
     449: iconst_1
     450: new           #129                // class org/apache/jena/ontology/impl/OWLProfile$20
     453: dup
     454: invokespecial #130                // Method org/apache/jena/ontology/impl/OWLProfile$20."<init>":()V
     457: aastore
     458: aastore
     459: dup
     460: bipush        20
     462: iconst_2
     463: anewarray     #70                 // class java/lang/Object
     466: dup
     467: iconst_0
     468: ldc           #131                // class org/apache/jena/ontology/DataRange
     470: aastore
     471: dup
     472: iconst_1
     473: new           #132                // class org/apache/jena/ontology/impl/OWLProfile$21
     476: dup
     477: invokespecial #133                // Method org/apache/jena/ontology/impl/OWLProfile$21."<init>":()V
     480: aastore
     481: aastore
     482: putstatic     #134                // Field s_supportsCheckData:[[Ljava/lang/Object;
     485: new           #135                // class java/util/HashMap
     488: dup
     489: invokespecial #136                // Method java/util/HashMap."<init>":()V
     492: putstatic     #68                 // Field s_supportsChecks:Ljava/util/HashMap;
     495: getstatic     #134                // Field s_supportsCheckData:[[Ljava/lang/Object;
     498: astore_0
     499: aload_0
     500: arraylength
     501: istore_1
     502: iconst_0
     503: istore_2
     504: iload_2
     505: iload_1
     506: if_icmpge     538
     509: aload_0
     510: iload_2
     511: aaload
     512: astore_3
     513: getstatic     #68                 // Field s_supportsChecks:Ljava/util/HashMap;
     516: aload_3
     517: iconst_0
     518: aaload
     519: checkcast     #137                // class java/lang/Class
     522: aload_3
     523: iconst_1
     524: aaload
     525: checkcast     #64                 // class org/apache/jena/ontology/impl/OWLProfile$SupportsCheck
     528: invokevirtual #138                // Method java/util/HashMap.put:(Ljava/lang/Object;Ljava/lang/Object;)Ljava/lang/Object;
     531: pop
     532: iinc          2, 1
     535: goto          504
     538: return
}
