Compiled from "Proxy.java"
public class org.apache.cxf.ws.rm.Proxy {
  private static final java.util.logging.Logger LOG;

  private org.apache.cxf.ws.rm.RMEndpoint reliableEndpoint;

  private org.apache.cxf.ws.rm.v200702.Identifier offeredIdentifier;

  public org.apache.cxf.ws.rm.Proxy(org.apache.cxf.ws.rm.RMEndpoint);
    Code:
       0: aload_0
       1: invokespecial #2                  // Method java/lang/Object."<init>":()V
       4: aload_0
       5: aload_1
       6: putfield      #1                  // Field reliableEndpoint:Lorg/apache/cxf/ws/rm/RMEndpoint;
       9: return

  org.apache.cxf.ws.rm.RMEndpoint getReliableEndpoint();
    Code:
       0: aload_0
       1: getfield      #1                  // Field reliableEndpoint:Lorg/apache/cxf/ws/rm/RMEndpoint;
       4: areturn

  void acknowledge(org.apache.cxf.ws.rm.DestinationSequence) throws org.apache.cxf.ws.rm.RMException;
    Code:
       0: aload_1
       1: invokevirtual #3                  // Method org/apache/cxf/ws/rm/DestinationSequence.getProtocol:()Lorg/apache/cxf/ws/rm/ProtocolVariation;
       4: astore_2
       5: aload_1
       6: invokevirtual #4                  // Method org/apache/cxf/ws/rm/DestinationSequence.getAcksTo:()Lorg/apache/cxf/ws/addressing/EndpointReferenceType;
       9: invokevirtual #5                  // Method org/apache/cxf/ws/addressing/EndpointReferenceType.getAddress:()Lorg/apache/cxf/ws/addressing/AttributedURIType;
      12: invokevirtual #6                  // Method org/apache/cxf/ws/addressing/AttributedURIType.getValue:()Ljava/lang/String;
      15: astore_3
      16: invokestatic  #7                  // Method org/apache/cxf/ws/rm/RMUtils.getAddressingConstants:()Lorg/apache/cxf/ws/addressing/AddressingConstants;
      19: invokevirtual #8                  // Method org/apache/cxf/ws/addressing/AddressingConstants.getAnonymousURI:()Ljava/lang/String;
      22: aload_3
      23: invokevirtual #9                  // Method java/lang/String.equals:(Ljava/lang/Object;)Z
      26: ifeq          41
      29: getstatic     #10                 // Field LOG:Ljava/util/logging/Logger;
      32: getstatic     #11                 // Field java/util/logging/Level.WARNING:Ljava/util/logging/Level;
      35: ldc           #12                 // String STANDALONE_ANON_ACKS_NOT_SUPPORTED
      37: invokevirtual #13                 // Method java/util/logging/Logger.log:(Ljava/util/logging/Level;Ljava/lang/String;)V
      40: return
      41: aload_2
      42: invokevirtual #14                 // Method org/apache/cxf/ws/rm/ProtocolVariation.getConstants:()Lorg/apache/cxf/ws/rm/RMConstants;
      45: astore        4
      47: aload_0
      48: getfield      #1                  // Field reliableEndpoint:Lorg/apache/cxf/ws/rm/RMEndpoint;
      51: aload_2
      52: invokevirtual #15                 // Method org/apache/cxf/ws/rm/RMEndpoint.getEndpoint:(Lorg/apache/cxf/ws/rm/ProtocolVariation;)Lorg/apache/cxf/endpoint/Endpoint;
      55: invokeinterface #16,  1           // InterfaceMethod org/apache/cxf/endpoint/Endpoint.getEndpointInfo:()Lorg/apache/cxf/service/model/EndpointInfo;
      60: invokevirtual #17                 // Method org/apache/cxf/service/model/EndpointInfo.getService:()Lorg/apache/cxf/service/model/ServiceInfo;
      63: invokevirtual #18                 // Method org/apache/cxf/service/model/ServiceInfo.getInterface:()Lorg/apache/cxf/service/model/InterfaceInfo;
      66: aload         4
      68: invokevirtual #19                 // Method org/apache/cxf/ws/rm/RMConstants.getSequenceAckOperationName:()Ljavax/xml/namespace/QName;
      71: invokevirtual #20                 // Method org/apache/cxf/service/model/InterfaceInfo.getOperation:(Ljavax/xml/namespace/QName;)Lorg/apache/cxf/service/model/OperationInfo;
      74: astore        5
      76: aload_0
      77: aload         5
      79: aload_2
      80: iconst_1
      81: anewarray     #21                 // class java/lang/Object
      84: dup
      85: iconst_0
      86: aload_1
      87: aastore
      88: invokevirtual #22                 // Method invoke:(Lorg/apache/cxf/service/model/OperationInfo;Lorg/apache/cxf/ws/rm/ProtocolVariation;[Ljava/lang/Object;)Ljava/lang/Object;
      91: pop
      92: return

  void terminate(org.apache.cxf.ws.rm.SourceSequence) throws org.apache.cxf.ws.rm.RMException;
    Code:
       0: aload_1
       1: invokevirtual #23                 // Method org/apache/cxf/ws/rm/SourceSequence.getProtocol:()Lorg/apache/cxf/ws/rm/ProtocolVariation;
       4: astore_2
       5: aload_2
       6: invokevirtual #14                 // Method org/apache/cxf/ws/rm/ProtocolVariation.getConstants:()Lorg/apache/cxf/ws/rm/RMConstants;
       9: astore_3
      10: aload_0
      11: getfield      #1                  // Field reliableEndpoint:Lorg/apache/cxf/ws/rm/RMEndpoint;
      14: aload_2
      15: invokevirtual #15                 // Method org/apache/cxf/ws/rm/RMEndpoint.getEndpoint:(Lorg/apache/cxf/ws/rm/ProtocolVariation;)Lorg/apache/cxf/endpoint/Endpoint;
      18: invokeinterface #16,  1           // InterfaceMethod org/apache/cxf/endpoint/Endpoint.getEndpointInfo:()Lorg/apache/cxf/service/model/EndpointInfo;
      23: invokevirtual #17                 // Method org/apache/cxf/service/model/EndpointInfo.getService:()Lorg/apache/cxf/service/model/ServiceInfo;
      26: invokevirtual #18                 // Method org/apache/cxf/service/model/ServiceInfo.getInterface:()Lorg/apache/cxf/service/model/InterfaceInfo;
      29: aload_3
      30: invokevirtual #24                 // Method org/apache/cxf/ws/rm/RMConstants.getTerminateSequenceOperationName:()Ljavax/xml/namespace/QName;
      33: invokevirtual #20                 // Method org/apache/cxf/service/model/InterfaceInfo.getOperation:(Ljavax/xml/namespace/QName;)Lorg/apache/cxf/service/model/OperationInfo;
      36: astore        4
      38: new           #25                 // class org/apache/cxf/ws/rm/v200702/TerminateSequenceType
      41: dup
      42: invokespecial #26                 // Method org/apache/cxf/ws/rm/v200702/TerminateSequenceType."<init>":()V
      45: astore        5
      47: aload         5
      49: aload_1
      50: invokevirtual #27                 // Method org/apache/cxf/ws/rm/SourceSequence.getIdentifier:()Lorg/apache/cxf/ws/rm/v200702/Identifier;
      53: invokevirtual #28                 // Method org/apache/cxf/ws/rm/v200702/TerminateSequenceType.setIdentifier:(Lorg/apache/cxf/ws/rm/v200702/Identifier;)V
      56: aload         5
      58: aload_1
      59: invokevirtual #29                 // Method org/apache/cxf/ws/rm/SourceSequence.getCurrentMessageNr:()J
      62: invokestatic  #30                 // Method java/lang/Long.valueOf:(J)Ljava/lang/Long;
      65: invokevirtual #31                 // Method org/apache/cxf/ws/rm/v200702/TerminateSequenceType.setLastMsgNumber:(Ljava/lang/Long;)V
      68: aload_2
      69: invokevirtual #32                 // Method org/apache/cxf/ws/rm/ProtocolVariation.getCodec:()Lorg/apache/cxf/ws/rm/EncoderDecoder;
      72: astore        6
      74: aload_0
      75: aload         4
      77: aload_2
      78: iconst_1
      79: anewarray     #21                 // class java/lang/Object
      82: dup
      83: iconst_0
      84: aload         6
      86: aload         5
      88: invokevirtual #33                 // Method org/apache/cxf/ws/rm/EncoderDecoder.convertToSend:(Lorg/apache/cxf/ws/rm/v200702/TerminateSequenceType;)Ljava/lang/Object;
      91: aastore
      92: invokevirtual #22                 // Method invoke:(Lorg/apache/cxf/service/model/OperationInfo;Lorg/apache/cxf/ws/rm/ProtocolVariation;[Ljava/lang/Object;)Ljava/lang/Object;
      95: pop
      96: return

  void terminate(org.apache.cxf.ws.rm.DestinationSequence) throws org.apache.cxf.ws.rm.RMException;
    Code:
       0: aload_1
       1: invokevirtual #3                  // Method org/apache/cxf/ws/rm/DestinationSequence.getProtocol:()Lorg/apache/cxf/ws/rm/ProtocolVariation;
       4: astore_2
       5: aload_2
       6: invokevirtual #14                 // Method org/apache/cxf/ws/rm/ProtocolVariation.getConstants:()Lorg/apache/cxf/ws/rm/RMConstants;
       9: astore_3
      10: aload_0
      11: getfield      #1                  // Field reliableEndpoint:Lorg/apache/cxf/ws/rm/RMEndpoint;
      14: aload_2
      15: invokevirtual #15                 // Method org/apache/cxf/ws/rm/RMEndpoint.getEndpoint:(Lorg/apache/cxf/ws/rm/ProtocolVariation;)Lorg/apache/cxf/endpoint/Endpoint;
      18: invokeinterface #16,  1           // InterfaceMethod org/apache/cxf/endpoint/Endpoint.getEndpointInfo:()Lorg/apache/cxf/service/model/EndpointInfo;
      23: invokevirtual #17                 // Method org/apache/cxf/service/model/EndpointInfo.getService:()Lorg/apache/cxf/service/model/ServiceInfo;
      26: invokevirtual #18                 // Method org/apache/cxf/service/model/ServiceInfo.getInterface:()Lorg/apache/cxf/service/model/InterfaceInfo;
      29: aload_3
      30: invokevirtual #24                 // Method org/apache/cxf/ws/rm/RMConstants.getTerminateSequenceOperationName:()Ljavax/xml/namespace/QName;
      33: invokevirtual #20                 // Method org/apache/cxf/service/model/InterfaceInfo.getOperation:(Ljavax/xml/namespace/QName;)Lorg/apache/cxf/service/model/OperationInfo;
      36: astore        4
      38: new           #25                 // class org/apache/cxf/ws/rm/v200702/TerminateSequenceType
      41: dup
      42: invokespecial #26                 // Method org/apache/cxf/ws/rm/v200702/TerminateSequenceType."<init>":()V
      45: astore        5
      47: aload         5
      49: aload_1
      50: invokevirtual #34                 // Method org/apache/cxf/ws/rm/DestinationSequence.getIdentifier:()Lorg/apache/cxf/ws/rm/v200702/Identifier;
      53: invokevirtual #28                 // Method org/apache/cxf/ws/rm/v200702/TerminateSequenceType.setIdentifier:(Lorg/apache/cxf/ws/rm/v200702/Identifier;)V
      56: aload         5
      58: aload_1
      59: invokevirtual #35                 // Method org/apache/cxf/ws/rm/DestinationSequence.getLastMessageNumber:()J
      62: invokestatic  #30                 // Method java/lang/Long.valueOf:(J)Ljava/lang/Long;
      65: invokevirtual #31                 // Method org/apache/cxf/ws/rm/v200702/TerminateSequenceType.setLastMsgNumber:(Ljava/lang/Long;)V
      68: aload_2
      69: invokevirtual #32                 // Method org/apache/cxf/ws/rm/ProtocolVariation.getCodec:()Lorg/apache/cxf/ws/rm/EncoderDecoder;
      72: astore        6
      74: aload_0
      75: aload         4
      77: aload_2
      78: iconst_1
      79: anewarray     #21                 // class java/lang/Object
      82: dup
      83: iconst_0
      84: aload         6
      86: aload         5
      88: invokevirtual #33                 // Method org/apache/cxf/ws/rm/EncoderDecoder.convertToSend:(Lorg/apache/cxf/ws/rm/v200702/TerminateSequenceType;)Ljava/lang/Object;
      91: aastore
      92: invokevirtual #22                 // Method invoke:(Lorg/apache/cxf/service/model/OperationInfo;Lorg/apache/cxf/ws/rm/ProtocolVariation;[Ljava/lang/Object;)Ljava/lang/Object;
      95: pop
      96: return

  void createSequenceResponse(java.lang.Object, org.apache.cxf.ws.rm.ProtocolVariation) throws org.apache.cxf.ws.rm.RMException;
    Code:
       0: getstatic     #10                 // Field LOG:Ljava/util/logging/Logger;
       3: ldc           #36                 // String sending CreateSequenceResponse from client side
       5: invokevirtual #37                 // Method java/util/logging/Logger.fine:(Ljava/lang/String;)V
       8: aload_2
       9: invokevirtual #14                 // Method org/apache/cxf/ws/rm/ProtocolVariation.getConstants:()Lorg/apache/cxf/ws/rm/RMConstants;
      12: astore_3
      13: aload_0
      14: getfield      #1                  // Field reliableEndpoint:Lorg/apache/cxf/ws/rm/RMEndpoint;
      17: aload_2
      18: invokevirtual #15                 // Method org/apache/cxf/ws/rm/RMEndpoint.getEndpoint:(Lorg/apache/cxf/ws/rm/ProtocolVariation;)Lorg/apache/cxf/endpoint/Endpoint;
      21: invokeinterface #16,  1           // InterfaceMethod org/apache/cxf/endpoint/Endpoint.getEndpointInfo:()Lorg/apache/cxf/service/model/EndpointInfo;
      26: invokevirtual #17                 // Method org/apache/cxf/service/model/EndpointInfo.getService:()Lorg/apache/cxf/service/model/ServiceInfo;
      29: invokevirtual #18                 // Method org/apache/cxf/service/model/ServiceInfo.getInterface:()Lorg/apache/cxf/service/model/InterfaceInfo;
      32: aload_3
      33: invokevirtual #38                 // Method org/apache/cxf/ws/rm/RMConstants.getCreateSequenceResponseOnewayOperationName:()Ljavax/xml/namespace/QName;
      36: invokevirtual #20                 // Method org/apache/cxf/service/model/InterfaceInfo.getOperation:(Ljavax/xml/namespace/QName;)Lorg/apache/cxf/service/model/OperationInfo;
      39: astore        4
      41: aload_0
      42: aload         4
      44: aload_2
      45: iconst_1
      46: anewarray     #21                 // class java/lang/Object
      49: dup
      50: iconst_0
      51: aload_1
      52: aastore
      53: invokevirtual #22                 // Method invoke:(Lorg/apache/cxf/service/model/OperationInfo;Lorg/apache/cxf/ws/rm/ProtocolVariation;[Ljava/lang/Object;)Ljava/lang/Object;
      56: pop
      57: return

  public org.apache.cxf.ws.rm.v200702.CreateSequenceResponseType createSequence(org.apache.cxf.ws.addressing.EndpointReferenceType, org.apache.cxf.ws.addressing.RelatesToType, boolean, org.apache.cxf.ws.rm.ProtocolVariation, org.apache.cxf.message.Exchange, java.util.Map<java.lang.String, java.lang.Object>) throws org.apache.cxf.ws.rm.RMException;
    Code:
       0: aload_0
       1: getfield      #1                  // Field reliableEndpoint:Lorg/apache/cxf/ws/rm/RMEndpoint;
       4: invokevirtual #39                 // Method org/apache/cxf/ws/rm/RMEndpoint.getManager:()Lorg/apache/cxf/ws/rm/RMManager;
       7: invokevirtual #40                 // Method org/apache/cxf/ws/rm/RMManager.getSourcePolicy:()Lorg/apache/cxf/ws/rm/manager/SourcePolicyType;
      10: astore        7
      12: new           #41                 // class org/apache/cxf/ws/rm/v200702/CreateSequenceType
      15: dup
      16: invokespecial #42                 // Method org/apache/cxf/ws/rm/v200702/CreateSequenceType."<init>":()V
      19: astore        8
      21: aload         7
      23: invokevirtual #43                 // Method org/apache/cxf/ws/rm/manager/SourcePolicyType.getAcksTo:()Ljava/lang/String;
      26: astore        9
      28: aconst_null
      29: astore        10
      31: aconst_null
      32: aload         9
      34: if_acmpeq     47
      37: aload         9
      39: invokestatic  #44                 // Method org/apache/cxf/ws/rm/RMUtils.createReference:(Ljava/lang/String;)Lorg/apache/cxf/ws/addressing/EndpointReferenceType;
      42: astore        10
      44: goto          50
      47: aload_1
      48: astore        10
      50: aload         8
      52: aload         10
      54: invokevirtual #45                 // Method org/apache/cxf/ws/rm/v200702/CreateSequenceType.setAcksTo:(Lorg/apache/cxf/ws/addressing/EndpointReferenceType;)V
      57: aload         7
      59: invokevirtual #46                 // Method org/apache/cxf/ws/rm/manager/SourcePolicyType.getSequenceExpiration:()Ljavax/xml/datatype/Duration;
      62: astore        11
      64: aconst_null
      65: aload         11
      67: if_acmpeq     93
      70: new           #47                 // class org/apache/cxf/ws/rm/v200702/Expires
      73: dup
      74: invokespecial #48                 // Method org/apache/cxf/ws/rm/v200702/Expires."<init>":()V
      77: astore        12
      79: aload         12
      81: aload         11
      83: invokevirtual #49                 // Method org/apache/cxf/ws/rm/v200702/Expires.setValue:(Ljavax/xml/datatype/Duration;)V
      86: aload         8
      88: aload         12
      90: invokevirtual #50                 // Method org/apache/cxf/ws/rm/v200702/CreateSequenceType.setExpires:(Lorg/apache/cxf/ws/rm/v200702/Expires;)V
      93: aload         7
      95: invokevirtual #51                 // Method org/apache/cxf/ws/rm/manager/SourcePolicyType.isIncludeOffer:()Z
      98: ifeq          181
     101: new           #52                 // class org/apache/cxf/ws/rm/v200702/OfferType
     104: dup
     105: invokespecial #53                 // Method org/apache/cxf/ws/rm/v200702/OfferType."<init>":()V
     108: astore        12
     110: aload         7
     112: invokevirtual #54                 // Method org/apache/cxf/ws/rm/manager/SourcePolicyType.getOfferedSequenceExpiration:()Ljavax/xml/datatype/Duration;
     115: astore        11
     117: aconst_null
     118: aload         11
     120: if_acmpeq     146
     123: new           #47                 // class org/apache/cxf/ws/rm/v200702/Expires
     126: dup
     127: invokespecial #48                 // Method org/apache/cxf/ws/rm/v200702/Expires."<init>":()V
     130: astore        13
     132: aload         13
     134: aload         11
     136: invokevirtual #49                 // Method org/apache/cxf/ws/rm/v200702/Expires.setValue:(Ljavax/xml/datatype/Duration;)V
     139: aload         12
     141: aload         13
     143: invokevirtual #55                 // Method org/apache/cxf/ws/rm/v200702/OfferType.setExpires:(Lorg/apache/cxf/ws/rm/v200702/Expires;)V
     146: aload         12
     148: aload_0
     149: getfield      #1                  // Field reliableEndpoint:Lorg/apache/cxf/ws/rm/RMEndpoint;
     152: invokevirtual #56                 // Method org/apache/cxf/ws/rm/RMEndpoint.getSource:()Lorg/apache/cxf/ws/rm/Source;
     155: invokevirtual #57                 // Method org/apache/cxf/ws/rm/Source.generateSequenceIdentifier:()Lorg/apache/cxf/ws/rm/v200702/Identifier;
     158: invokevirtual #58                 // Method org/apache/cxf/ws/rm/v200702/OfferType.setIdentifier:(Lorg/apache/cxf/ws/rm/v200702/Identifier;)V
     161: aload         12
     163: aload         10
     165: invokevirtual #59                 // Method org/apache/cxf/ws/rm/v200702/OfferType.setEndpoint:(Lorg/apache/cxf/ws/addressing/EndpointReferenceType;)V
     168: aload         8
     170: aload         12
     172: invokevirtual #60                 // Method org/apache/cxf/ws/rm/v200702/CreateSequenceType.setOffer:(Lorg/apache/cxf/ws/rm/v200702/OfferType;)V
     175: aload_0
     176: aload         12
     178: invokevirtual #61                 // Method setOfferedIdentifier:(Lorg/apache/cxf/ws/rm/v200702/OfferType;)V
     181: aload_0
     182: getfield      #1                  // Field reliableEndpoint:Lorg/apache/cxf/ws/rm/RMEndpoint;
     185: aload         4
     187: invokevirtual #15                 // Method org/apache/cxf/ws/rm/RMEndpoint.getEndpoint:(Lorg/apache/cxf/ws/rm/ProtocolVariation;)Lorg/apache/cxf/endpoint/Endpoint;
     190: invokeinterface #16,  1           // InterfaceMethod org/apache/cxf/endpoint/Endpoint.getEndpointInfo:()Lorg/apache/cxf/service/model/EndpointInfo;
     195: invokevirtual #17                 // Method org/apache/cxf/service/model/EndpointInfo.getService:()Lorg/apache/cxf/service/model/ServiceInfo;
     198: invokevirtual #18                 // Method org/apache/cxf/service/model/ServiceInfo.getInterface:()Lorg/apache/cxf/service/model/InterfaceInfo;
     201: astore        12
     203: aload         4
     205: invokevirtual #32                 // Method org/apache/cxf/ws/rm/ProtocolVariation.getCodec:()Lorg/apache/cxf/ws/rm/EncoderDecoder;
     208: astore        13
     210: aload         13
     212: invokevirtual #62                 // Method org/apache/cxf/ws/rm/EncoderDecoder.getConstants:()Lorg/apache/cxf/ws/rm/RMConstants;
     215: astore        14
     217: iload_3
     218: ifeq          234
     221: aload         12
     223: aload         14
     225: invokevirtual #63                 // Method org/apache/cxf/ws/rm/RMConstants.getCreateSequenceOnewayOperationName:()Ljavax/xml/namespace/QName;
     228: invokevirtual #20                 // Method org/apache/cxf/service/model/InterfaceInfo.getOperation:(Ljavax/xml/namespace/QName;)Lorg/apache/cxf/service/model/OperationInfo;
     231: goto          244
     234: aload         12
     236: aload         14
     238: invokevirtual #64                 // Method org/apache/cxf/ws/rm/RMConstants.getCreateSequenceOperationName:()Ljavax/xml/namespace/QName;
     241: invokevirtual #20                 // Method org/apache/cxf/service/model/InterfaceInfo.getOperation:(Ljavax/xml/namespace/QName;)Lorg/apache/cxf/service/model/OperationInfo;
     244: astore        15
     246: aload         13
     248: aload         8
     250: invokevirtual #65                 // Method org/apache/cxf/ws/rm/EncoderDecoder.convertToSend:(Lorg/apache/cxf/ws/rm/v200702/CreateSequenceType;)Ljava/lang/Object;
     253: astore        16
     255: iload_3
     256: ifeq          320
     259: getstatic     #10                 // Field LOG:Ljava/util/logging/Logger;
     262: ldc           #66                 // String sending CreateSequenceRequest from server side
     264: invokevirtual #37                 // Method java/util/logging/Logger.fine:(Ljava/lang/String;)V
     267: new           #67                 // class org/apache/cxf/ws/rm/Proxy$1
     270: dup
     271: aload_0
     272: aload         15
     274: aload         4
     276: aload         16
     278: aload         5
     280: invokespecial #68                 // Method org/apache/cxf/ws/rm/Proxy$1."<init>":(Lorg/apache/cxf/ws/rm/Proxy;Lorg/apache/cxf/service/model/OperationInfo;Lorg/apache/cxf/ws/rm/ProtocolVariation;Ljava/lang/Object;Lorg/apache/cxf/message/Exchange;)V
     283: astore        17
     285: aload_0
     286: getfield      #1                  // Field reliableEndpoint:Lorg/apache/cxf/ws/rm/RMEndpoint;
     289: invokevirtual #69                 // Method org/apache/cxf/ws/rm/RMEndpoint.getApplicationEndpoint:()Lorg/apache/cxf/endpoint/Endpoint;
     292: invokeinterface #70,  1           // InterfaceMethod org/apache/cxf/endpoint/Endpoint.getExecutor:()Ljava/util/concurrent/Executor;
     297: astore        18
     299: aload         18
     301: ifnonnull     309
     304: invokestatic  #71                 // Method org/apache/cxf/workqueue/SynchronousExecutor.getInstance:()Lorg/apache/cxf/workqueue/SynchronousExecutor;
     307: astore        18
     309: aload         18
     311: aload         17
     313: invokeinterface #72,  2           // InterfaceMethod java/util/concurrent/Executor.execute:(Ljava/lang/Runnable;)V
     318: aconst_null
     319: areturn
     320: aload_0
     321: aload         15
     323: aload         4
     325: iconst_1
     326: anewarray     #21                 // class java/lang/Object
     329: dup
     330: iconst_0
     331: aload         16
     333: aastore
     334: aload         6
     336: aload         5
     338: invokevirtual #73                 // Method invoke:(Lorg/apache/cxf/service/model/OperationInfo;Lorg/apache/cxf/ws/rm/ProtocolVariation;[Ljava/lang/Object;Ljava/util/Map;Lorg/apache/cxf/message/Exchange;)Ljava/lang/Object;
     341: astore        17
     343: aload         13
     345: aload         17
     347: invokevirtual #74                 // Method org/apache/cxf/ws/rm/EncoderDecoder.convertReceivedCreateSequenceResponse:(Ljava/lang/Object;)Lorg/apache/cxf/ws/rm/v200702/CreateSequenceResponseType;
     350: areturn

  void lastMessage(org.apache.cxf.ws.rm.SourceSequence) throws org.apache.cxf.ws.rm.RMException;
    Code:
       0: aload_1
       1: invokevirtual #23                 // Method org/apache/cxf/ws/rm/SourceSequence.getProtocol:()Lorg/apache/cxf/ws/rm/ProtocolVariation;
       4: astore_2
       5: aload_1
       6: invokevirtual #75                 // Method org/apache/cxf/ws/rm/SourceSequence.getTarget:()Lorg/apache/cxf/ws/addressing/EndpointReferenceType;
       9: astore_3
      10: aconst_null
      11: astore        4
      13: aconst_null
      14: aload_3
      15: if_acmpeq     24
      18: aload_3
      19: invokevirtual #5                  // Method org/apache/cxf/ws/addressing/EndpointReferenceType.getAddress:()Lorg/apache/cxf/ws/addressing/AttributedURIType;
      22: astore        4
      24: aconst_null
      25: astore        5
      27: aconst_null
      28: aload         4
      30: if_acmpeq     40
      33: aload         4
      35: invokevirtual #6                  // Method org/apache/cxf/ws/addressing/AttributedURIType.getValue:()Ljava/lang/String;
      38: astore        5
      40: aload         5
      42: ifnonnull     57
      45: getstatic     #10                 // Field LOG:Ljava/util/logging/Logger;
      48: getstatic     #11                 // Field java/util/logging/Level.WARNING:Ljava/util/logging/Level;
      51: ldc           #76                 // String STANDALONE_CLOSE_SEQUENCE_NO_TARGET_MSG
      53: invokevirtual #13                 // Method java/util/logging/Logger.log:(Ljava/util/logging/Level;Ljava/lang/String;)V
      56: return
      57: invokestatic  #7                  // Method org/apache/cxf/ws/rm/RMUtils.getAddressingConstants:()Lorg/apache/cxf/ws/addressing/AddressingConstants;
      60: invokevirtual #8                  // Method org/apache/cxf/ws/addressing/AddressingConstants.getAnonymousURI:()Ljava/lang/String;
      63: aload         5
      65: invokevirtual #9                  // Method java/lang/String.equals:(Ljava/lang/Object;)Z
      68: ifeq          83
      71: getstatic     #10                 // Field LOG:Ljava/util/logging/Logger;
      74: getstatic     #11                 // Field java/util/logging/Level.WARNING:Ljava/util/logging/Level;
      77: ldc           #77                 // String STANDALONE_CLOSE_SEQUENCE_ANON_TARGET_MSG
      79: invokevirtual #13                 // Method java/util/logging/Logger.log:(Ljava/util/logging/Level;Ljava/lang/String;)V
      82: return
      83: aload_2
      84: invokevirtual #14                 // Method org/apache/cxf/ws/rm/ProtocolVariation.getConstants:()Lorg/apache/cxf/ws/rm/RMConstants;
      87: astore        6
      89: aload_0
      90: getfield      #1                  // Field reliableEndpoint:Lorg/apache/cxf/ws/rm/RMEndpoint;
      93: aload_2
      94: invokevirtual #15                 // Method org/apache/cxf/ws/rm/RMEndpoint.getEndpoint:(Lorg/apache/cxf/ws/rm/ProtocolVariation;)Lorg/apache/cxf/endpoint/Endpoint;
      97: invokeinterface #16,  1           // InterfaceMethod org/apache/cxf/endpoint/Endpoint.getEndpointInfo:()Lorg/apache/cxf/service/model/EndpointInfo;
     102: invokevirtual #17                 // Method org/apache/cxf/service/model/EndpointInfo.getService:()Lorg/apache/cxf/service/model/ServiceInfo;
     105: invokevirtual #18                 // Method org/apache/cxf/service/model/ServiceInfo.getInterface:()Lorg/apache/cxf/service/model/InterfaceInfo;
     108: aload         6
     110: invokevirtual #78                 // Method org/apache/cxf/ws/rm/RMConstants.getCloseSequenceOperationName:()Ljavax/xml/namespace/QName;
     113: invokevirtual #20                 // Method org/apache/cxf/service/model/InterfaceInfo.getOperation:(Ljavax/xml/namespace/QName;)Lorg/apache/cxf/service/model/OperationInfo;
     116: astore        7
     118: new           #79                 // class java/util/HashMap
     121: dup
     122: ldc_w         #80                 // class org/apache/cxf/ws/rm/SourceSequence
     125: invokevirtual #81                 // Method java/lang/Class.getName:()Ljava/lang/String;
     128: aload_1
     129: invokestatic  #82                 // Method java/util/Collections.singletonMap:(Ljava/lang/Object;Ljava/lang/Object;)Ljava/util/Map;
     132: invokespecial #83                 // Method java/util/HashMap."<init>":(Ljava/util/Map;)V
     135: astore        8
     137: aload         6
     139: instanceof    #84                 // class org/apache/cxf/ws/rm/RM11Constants
     142: ifeq          197
     145: new           #85                 // class org/apache/cxf/ws/rm/v200702/CloseSequenceType
     148: dup
     149: invokespecial #86                 // Method org/apache/cxf/ws/rm/v200702/CloseSequenceType."<init>":()V
     152: astore        9
     154: aload         9
     156: aload_1
     157: invokevirtual #27                 // Method org/apache/cxf/ws/rm/SourceSequence.getIdentifier:()Lorg/apache/cxf/ws/rm/v200702/Identifier;
     160: invokevirtual #87                 // Method org/apache/cxf/ws/rm/v200702/CloseSequenceType.setIdentifier:(Lorg/apache/cxf/ws/rm/v200702/Identifier;)V
     163: aload         9
     165: aload_1
     166: invokevirtual #29                 // Method org/apache/cxf/ws/rm/SourceSequence.getCurrentMessageNr:()J
     169: invokestatic  #30                 // Method java/lang/Long.valueOf:(J)Ljava/lang/Long;
     172: invokevirtual #88                 // Method org/apache/cxf/ws/rm/v200702/CloseSequenceType.setLastMsgNumber:(Ljava/lang/Long;)V
     175: aload_0
     176: aload         7
     178: aload_2
     179: iconst_1
     180: anewarray     #21                 // class java/lang/Object
     183: dup
     184: iconst_0
     185: aload         9
     187: aastore
     188: aload         8
     190: invokevirtual #89                 // Method invoke:(Lorg/apache/cxf/service/model/OperationInfo;Lorg/apache/cxf/ws/rm/ProtocolVariation;[Ljava/lang/Object;Ljava/util/Map;)Ljava/lang/Object;
     193: pop
     194: goto          211
     197: aload_0
     198: aload         7
     200: aload_2
     201: iconst_0
     202: anewarray     #21                 // class java/lang/Object
     205: aload         8
     207: invokevirtual #89                 // Method invoke:(Lorg/apache/cxf/service/model/OperationInfo;Lorg/apache/cxf/ws/rm/ProtocolVariation;[Ljava/lang/Object;Ljava/util/Map;)Ljava/lang/Object;
     210: pop
     211: return

  void ackRequested(org.apache.cxf.ws.rm.SourceSequence) throws org.apache.cxf.ws.rm.RMException;
    Code:
       0: aload_1
       1: invokevirtual #23                 // Method org/apache/cxf/ws/rm/SourceSequence.getProtocol:()Lorg/apache/cxf/ws/rm/ProtocolVariation;
       4: astore_2
       5: aload_1
       6: invokevirtual #75                 // Method org/apache/cxf/ws/rm/SourceSequence.getTarget:()Lorg/apache/cxf/ws/addressing/EndpointReferenceType;
       9: astore_3
      10: aconst_null
      11: astore        4
      13: aconst_null
      14: aload_3
      15: if_acmpeq     24
      18: aload_3
      19: invokevirtual #5                  // Method org/apache/cxf/ws/addressing/EndpointReferenceType.getAddress:()Lorg/apache/cxf/ws/addressing/AttributedURIType;
      22: astore        4
      24: aconst_null
      25: astore        5
      27: aconst_null
      28: aload         4
      30: if_acmpeq     40
      33: aload         4
      35: invokevirtual #6                  // Method org/apache/cxf/ws/addressing/AttributedURIType.getValue:()Ljava/lang/String;
      38: astore        5
      40: aload         5
      42: ifnonnull     57
      45: getstatic     #10                 // Field LOG:Ljava/util/logging/Logger;
      48: getstatic     #11                 // Field java/util/logging/Level.WARNING:Ljava/util/logging/Level;
      51: ldc           #90                 // String STANDALONE_ACK_REQUESTED_NO_TARGET_MSG
      53: invokevirtual #13                 // Method java/util/logging/Logger.log:(Ljava/util/logging/Level;Ljava/lang/String;)V
      56: return
      57: invokestatic  #7                  // Method org/apache/cxf/ws/rm/RMUtils.getAddressingConstants:()Lorg/apache/cxf/ws/addressing/AddressingConstants;
      60: invokevirtual #8                  // Method org/apache/cxf/ws/addressing/AddressingConstants.getAnonymousURI:()Ljava/lang/String;
      63: aload         5
      65: invokevirtual #9                  // Method java/lang/String.equals:(Ljava/lang/Object;)Z
      68: ifeq          83
      71: getstatic     #10                 // Field LOG:Ljava/util/logging/Logger;
      74: getstatic     #11                 // Field java/util/logging/Level.WARNING:Ljava/util/logging/Level;
      77: ldc           #91                 // String STANDALONE_ACK_REQUESTED_ANON_TARGET_MSG
      79: invokevirtual #13                 // Method java/util/logging/Logger.log:(Ljava/util/logging/Level;Ljava/lang/String;)V
      82: return
      83: aload_2
      84: invokevirtual #14                 // Method org/apache/cxf/ws/rm/ProtocolVariation.getConstants:()Lorg/apache/cxf/ws/rm/RMConstants;
      87: astore        6
      89: aload_0
      90: getfield      #1                  // Field reliableEndpoint:Lorg/apache/cxf/ws/rm/RMEndpoint;
      93: aload_2
      94: invokevirtual #15                 // Method org/apache/cxf/ws/rm/RMEndpoint.getEndpoint:(Lorg/apache/cxf/ws/rm/ProtocolVariation;)Lorg/apache/cxf/endpoint/Endpoint;
      97: invokeinterface #16,  1           // InterfaceMethod org/apache/cxf/endpoint/Endpoint.getEndpointInfo:()Lorg/apache/cxf/service/model/EndpointInfo;
     102: invokevirtual #17                 // Method org/apache/cxf/service/model/EndpointInfo.getService:()Lorg/apache/cxf/service/model/ServiceInfo;
     105: invokevirtual #18                 // Method org/apache/cxf/service/model/ServiceInfo.getInterface:()Lorg/apache/cxf/service/model/InterfaceInfo;
     108: aload         6
     110: invokevirtual #92                 // Method org/apache/cxf/ws/rm/RMConstants.getAckRequestedOperationName:()Ljavax/xml/namespace/QName;
     113: invokevirtual #20                 // Method org/apache/cxf/service/model/InterfaceInfo.getOperation:(Ljavax/xml/namespace/QName;)Lorg/apache/cxf/service/model/OperationInfo;
     116: astore        7
     118: aload_0
     119: aload         7
     121: aload_2
     122: iconst_0
     123: anewarray     #21                 // class java/lang/Object
     126: invokevirtual #22                 // Method invoke:(Lorg/apache/cxf/service/model/OperationInfo;Lorg/apache/cxf/ws/rm/ProtocolVariation;[Ljava/lang/Object;)Ljava/lang/Object;
     129: pop
     130: return

  org.apache.cxf.ws.rm.v200702.Identifier getOfferedIdentifier();
    Code:
       0: aload_0
       1: getfield      #93                 // Field offeredIdentifier:Lorg/apache/cxf/ws/rm/v200702/Identifier;
       4: areturn

  void setOfferedIdentifier(org.apache.cxf.ws.rm.v200702.OfferType);
    Code:
       0: aload_1
       1: ifnull        12
       4: aload_0
       5: aload_1
       6: invokevirtual #94                 // Method org/apache/cxf/ws/rm/v200702/OfferType.getIdentifier:()Lorg/apache/cxf/ws/rm/v200702/Identifier;
       9: putfield      #93                 // Field offeredIdentifier:Lorg/apache/cxf/ws/rm/v200702/Identifier;
      12: return

  java.lang.Object invoke(org.apache.cxf.service.model.OperationInfo, org.apache.cxf.ws.rm.ProtocolVariation, java.lang.Object[], java.util.Map<java.lang.String, java.lang.Object>, org.apache.cxf.message.Exchange) throws org.apache.cxf.ws.rm.RMException;
    Code:
       0: getstatic     #10                 // Field LOG:Ljava/util/logging/Logger;
       3: getstatic     #95                 // Field java/util/logging/Level.INFO:Ljava/util/logging/Level;
       6: invokevirtual #96                 // Method java/util/logging/Logger.isLoggable:(Ljava/util/logging/Level;)Z
       9: ifeq          35
      12: getstatic     #10                 // Field LOG:Ljava/util/logging/Logger;
      15: getstatic     #95                 // Field java/util/logging/Level.INFO:Ljava/util/logging/Level;
      18: ldc           #97                 // String Sending out-of-band RM protocol message {0}.
      20: aload_1
      21: ifnonnull     28
      24: aconst_null
      25: goto          32
      28: aload_1
      29: invokevirtual #98                 // Method org/apache/cxf/service/model/OperationInfo.getName:()Ljavax/xml/namespace/QName;
      32: invokevirtual #99                 // Method java/util/logging/Logger.log:(Ljava/util/logging/Level;Ljava/lang/String;Ljava/lang/Object;)V
      35: aload_0
      36: getfield      #1                  // Field reliableEndpoint:Lorg/apache/cxf/ws/rm/RMEndpoint;
      39: invokevirtual #39                 // Method org/apache/cxf/ws/rm/RMEndpoint.getManager:()Lorg/apache/cxf/ws/rm/RMManager;
      42: astore        6
      44: aload         6
      46: invokevirtual #100                // Method org/apache/cxf/ws/rm/RMManager.getBus:()Lorg/apache/cxf/Bus;
      49: astore        7
      51: aload_0
      52: getfield      #1                  // Field reliableEndpoint:Lorg/apache/cxf/ws/rm/RMEndpoint;
      55: aload_2
      56: invokevirtual #15                 // Method org/apache/cxf/ws/rm/RMEndpoint.getEndpoint:(Lorg/apache/cxf/ws/rm/ProtocolVariation;)Lorg/apache/cxf/endpoint/Endpoint;
      59: astore        8
      61: aload_0
      62: getfield      #1                  // Field reliableEndpoint:Lorg/apache/cxf/ws/rm/RMEndpoint;
      65: aload_2
      66: invokevirtual #101                // Method org/apache/cxf/ws/rm/RMEndpoint.getBindingInfo:(Lorg/apache/cxf/ws/rm/ProtocolVariation;)Lorg/apache/cxf/service/model/BindingInfo;
      69: astore        9
      71: aload_0
      72: getfield      #1                  // Field reliableEndpoint:Lorg/apache/cxf/ws/rm/RMEndpoint;
      75: invokevirtual #102                // Method org/apache/cxf/ws/rm/RMEndpoint.getConduit:()Lorg/apache/cxf/transport/Conduit;
      78: astore        10
      80: aconst_null
      81: astore        11
      83: aload_3
      84: arraylength
      85: ifle          173
      88: aload_3
      89: iconst_0
      90: aaload
      91: instanceof    #103                // class org/apache/cxf/ws/rm/DestinationSequence
      94: ifeq          173
      97: aload_3
      98: iconst_0
      99: aaload
     100: checkcast     #103                // class org/apache/cxf/ws/rm/DestinationSequence
     103: invokevirtual #4                  // Method org/apache/cxf/ws/rm/DestinationSequence.getAcksTo:()Lorg/apache/cxf/ws/addressing/EndpointReferenceType;
     106: astore        12
     108: aload         12
     110: invokevirtual #5                  // Method org/apache/cxf/ws/addressing/EndpointReferenceType.getAddress:()Lorg/apache/cxf/ws/addressing/AttributedURIType;
     113: invokevirtual #6                  // Method org/apache/cxf/ws/addressing/AttributedURIType.getValue:()Ljava/lang/String;
     116: astore        13
     118: new           #104                // class org/apache/cxf/ws/addressing/AttributedURIType
     121: dup
     122: invokespecial #105                // Method org/apache/cxf/ws/addressing/AttributedURIType."<init>":()V
     125: astore        14
     127: aload         14
     129: aload         13
     131: invokevirtual #106                // Method org/apache/cxf/ws/addressing/AttributedURIType.setValue:(Ljava/lang/String;)V
     134: new           #107                // class org/apache/cxf/ws/addressing/EndpointReferenceType
     137: dup
     138: invokespecial #108                // Method org/apache/cxf/ws/addressing/EndpointReferenceType."<init>":()V
     141: astore        15
     143: aload         15
     145: aload         14
     147: invokevirtual #109                // Method org/apache/cxf/ws/addressing/EndpointReferenceType.setAddress:(Lorg/apache/cxf/ws/addressing/AttributedURIType;)V
     150: aload_0
     151: aload         7
     153: aload         8
     155: aload_2
     156: aload         10
     158: aload         15
     160: invokevirtual #110                // Method createClient:(Lorg/apache/cxf/Bus;Lorg/apache/cxf/endpoint/Endpoint;Lorg/apache/cxf/ws/rm/ProtocolVariation;Lorg/apache/cxf/transport/Conduit;Lorg/apache/cxf/ws/addressing/EndpointReferenceType;)Lorg/apache/cxf/endpoint/Client;
     163: astore        11
     165: iconst_0
     166: anewarray     #21                 // class java/lang/Object
     169: astore_3
     170: goto          197
     173: aload_0
     174: getfield      #1                  // Field reliableEndpoint:Lorg/apache/cxf/ws/rm/RMEndpoint;
     177: invokevirtual #111                // Method org/apache/cxf/ws/rm/RMEndpoint.getReplyTo:()Lorg/apache/cxf/ws/addressing/EndpointReferenceType;
     180: astore        12
     182: aload_0
     183: aload         7
     185: aload         8
     187: aload_2
     188: aload         10
     190: aload         12
     192: invokevirtual #110                // Method createClient:(Lorg/apache/cxf/Bus;Lorg/apache/cxf/endpoint/Endpoint;Lorg/apache/cxf/ws/rm/ProtocolVariation;Lorg/apache/cxf/transport/Conduit;Lorg/apache/cxf/ws/addressing/EndpointReferenceType;)Lorg/apache/cxf/endpoint/Client;
     195: astore        11
     197: aload         9
     199: aload_1
     200: invokevirtual #112                // Method org/apache/cxf/service/model/BindingInfo.getOperation:(Lorg/apache/cxf/service/model/OperationInfo;)Lorg/apache/cxf/service/model/BindingOperationInfo;
     203: astore        12
     205: aload         4
     207: ifnull        224
     210: aload         11
     212: invokeinterface #113,  1          // InterfaceMethod org/apache/cxf/endpoint/Client.getRequestContext:()Ljava/util/Map;
     217: aload         4
     219: invokeinterface #114,  2          // InterfaceMethod java/util/Map.putAll:(Ljava/util/Map;)V
     224: aload         11
     226: aload         12
     228: aload_3
     229: aload         4
     231: aload         5
     233: invokeinterface #115,  5          // InterfaceMethod org/apache/cxf/endpoint/Client.invoke:(Lorg/apache/cxf/service/model/BindingOperationInfo;[Ljava/lang/Object;Ljava/util/Map;Lorg/apache/cxf/message/Exchange;)[Ljava/lang/Object;
     238: astore        13
     240: aload         13
     242: ifnull        256
     245: aload         13
     247: arraylength
     248: ifle          256
     251: aload         13
     253: iconst_0
     254: aaload
     255: areturn
     256: goto          322
     259: astore        13
     261: new           #117                // class org/apache/cxf/common/i18n/Message
     264: dup
     265: ldc           #118                // String SEND_PROTOCOL_MSG_FAILED_EXC
     267: getstatic     #10                 // Field LOG:Ljava/util/logging/Logger;
     270: iconst_1
     271: anewarray     #21                 // class java/lang/Object
     274: dup
     275: iconst_0
     276: aload_1
     277: ifnonnull     284
     280: aconst_null
     281: goto          288
     284: aload_1
     285: invokevirtual #98                 // Method org/apache/cxf/service/model/OperationInfo.getName:()Ljavax/xml/namespace/QName;
     288: aastore
     289: invokespecial #119                // Method org/apache/cxf/common/i18n/Message."<init>":(Ljava/lang/String;Ljava/util/logging/Logger;[Ljava/lang/Object;)V
     292: astore        14
     294: getstatic     #10                 // Field LOG:Ljava/util/logging/Logger;
     297: getstatic     #120                // Field java/util/logging/Level.SEVERE:Ljava/util/logging/Level;
     300: aload         14
     302: invokevirtual #121                // Method org/apache/cxf/common/i18n/Message.toString:()Ljava/lang/String;
     305: aload         13
     307: invokevirtual #122                // Method java/util/logging/Logger.log:(Ljava/util/logging/Level;Ljava/lang/String;Ljava/lang/Throwable;)V
     310: new           #123                // class org/apache/cxf/ws/rm/RMException
     313: dup
     314: aload         14
     316: aload         13
     318: invokespecial #124                // Method org/apache/cxf/ws/rm/RMException."<init>":(Lorg/apache/cxf/common/i18n/Message;Ljava/lang/Throwable;)V
     321: athrow
     322: aconst_null
     323: areturn
    Exception table:
       from    to  target type
         205   255   259   Class java/lang/Exception

  java.lang.Object invoke(org.apache.cxf.service.model.OperationInfo, org.apache.cxf.ws.rm.ProtocolVariation, java.lang.Object[], java.util.Map<java.lang.String, java.lang.Object>) throws org.apache.cxf.ws.rm.RMException;
    Code:
       0: aload_0
       1: aload_1
       2: aload_2
       3: aload_3
       4: aload         4
       6: new           #125                // class org/apache/cxf/message/ExchangeImpl
       9: dup
      10: invokespecial #126                // Method org/apache/cxf/message/ExchangeImpl."<init>":()V
      13: invokevirtual #73                 // Method invoke:(Lorg/apache/cxf/service/model/OperationInfo;Lorg/apache/cxf/ws/rm/ProtocolVariation;[Ljava/lang/Object;Ljava/util/Map;Lorg/apache/cxf/message/Exchange;)Ljava/lang/Object;
      16: areturn

  java.lang.Object invoke(org.apache.cxf.service.model.OperationInfo, org.apache.cxf.ws.rm.ProtocolVariation, java.lang.Object[]) throws org.apache.cxf.ws.rm.RMException;
    Code:
       0: aload_0
       1: aload_1
       2: aload_2
       3: aload_3
       4: aconst_null
       5: invokevirtual #89                 // Method invoke:(Lorg/apache/cxf/service/model/OperationInfo;Lorg/apache/cxf/ws/rm/ProtocolVariation;[Ljava/lang/Object;Ljava/util/Map;)Ljava/lang/Object;
       8: areturn

  protected org.apache.cxf.endpoint.Client createClient(org.apache.cxf.Bus, org.apache.cxf.endpoint.Endpoint, org.apache.cxf.ws.rm.ProtocolVariation, org.apache.cxf.transport.Conduit, org.apache.cxf.ws.addressing.EndpointReferenceType);
    Code:
       0: new           #127                // class org/apache/cxf/ws/rm/Proxy$2
       3: dup
       4: aload_0
       5: aload         4
       7: aload         5
       9: invokespecial #128                // Method org/apache/cxf/ws/rm/Proxy$2."<init>":(Lorg/apache/cxf/ws/rm/Proxy;Lorg/apache/cxf/transport/Conduit;Lorg/apache/cxf/ws/addressing/EndpointReferenceType;)V
      12: astore        6
      14: new           #129                // class org/apache/cxf/ws/rm/Proxy$RMClient
      17: dup
      18: aload_0
      19: aload_1
      20: aload_2
      21: aload         6
      23: invokespecial #130                // Method org/apache/cxf/ws/rm/Proxy$RMClient."<init>":(Lorg/apache/cxf/ws/rm/Proxy;Lorg/apache/cxf/Bus;Lorg/apache/cxf/endpoint/Endpoint;Lorg/apache/cxf/endpoint/ConduitSelector;)V
      26: astore        7
      28: aload         7
      30: invokevirtual #131                // Method org/apache/cxf/ws/rm/Proxy$RMClient.getRequestContext:()Ljava/util/Map;
      33: astore        8
      35: aload         8
      37: ldc           #132                // String org.apache.cxf.ws.rm.namespace
      39: aload_3
      40: invokevirtual #133                // Method org/apache/cxf/ws/rm/ProtocolVariation.getWSRMNamespace:()Ljava/lang/String;
      43: invokeinterface #134,  3          // InterfaceMethod java/util/Map.put:(Ljava/lang/Object;Ljava/lang/Object;)Ljava/lang/Object;
      48: pop
      49: aload         8
      51: ldc           #135                // String org.apache.cxf.ws.rm.wsa-namespace
      53: aload_3
      54: invokevirtual #136                // Method org/apache/cxf/ws/rm/ProtocolVariation.getWSANamespace:()Ljava/lang/String;
      57: invokeinterface #134,  3          // InterfaceMethod java/util/Map.put:(Ljava/lang/Object;Ljava/lang/Object;)Ljava/lang/Object;
      62: pop
      63: aload         7
      65: areturn

  void setReliableEndpoint(org.apache.cxf.ws.rm.RMEndpoint);
    Code:
       0: aload_0
       1: aload_1
       2: putfield      #1                  // Field reliableEndpoint:Lorg/apache/cxf/ws/rm/RMEndpoint;
       5: return

  static org.apache.cxf.ws.rm.RMEndpoint access$000(org.apache.cxf.ws.rm.Proxy);
    Code:
       0: aload_0
       1: getfield      #1                  // Field reliableEndpoint:Lorg/apache/cxf/ws/rm/RMEndpoint;
       4: areturn

  static {};
    Code:
       0: ldc_w         #137                // class org/apache/cxf/ws/rm/Proxy
       3: invokestatic  #138                // Method org/apache/cxf/common/logging/LogUtils.getL7dLogger:(Ljava/lang/Class;)Ljava/util/logging/Logger;
       6: putstatic     #10                 // Field LOG:Ljava/util/logging/Logger;
       9: return
}
