Compiled from "RMCaptureOutInterceptor.java"
class org.apache.cxf.ws.rm.RMCaptureOutInterceptor$CaptureStart extends org.apache.cxf.phase.AbstractPhaseInterceptor<org.apache.cxf.message.Message> {
  final org.apache.cxf.ws.rm.RMCaptureOutInterceptor this$0;

  org.apache.cxf.ws.rm.RMCaptureOutInterceptor$CaptureStart(org.apache.cxf.ws.rm.RMCaptureOutInterceptor);
    Code:
       0: aload_0
       1: aload_1
       2: putfield      #1                  // Field this$0:Lorg/apache/cxf/ws/rm/RMCaptureOutInterceptor;
       5: aload_0
       6: ldc           #2                  // String pre-protocol
       8: invokespecial #3                  // Method org/apache/cxf/phase/AbstractPhaseInterceptor."<init>":(Ljava/lang/String;)V
      11: return

  public void handleMessage(org.apache.cxf.message.Message) throws org.apache.cxf.interceptor.Fault;
    Code:
       0: aload_1
       1: ldc_w         #4                  // class javax/xml/stream/XMLStreamWriter
       4: invokeinterface #5,  2            // InterfaceMethod org/apache/cxf/message/Message.getContent:(Ljava/lang/Class;)Ljava/lang/Object;
       9: checkcast     #4                  // class javax/xml/stream/XMLStreamWriter
      12: astore_2
      13: aload_1
      14: ldc           #6                  // String RM_ORIGINAL_WRITER
      16: aload_2
      17: invokeinterface #7,  3            // InterfaceMethod org/apache/cxf/message/Message.put:(Ljava/lang/Object;Ljava/lang/Object;)Ljava/lang/Object;
      22: pop
      23: new           #8                  // class org/apache/cxf/ws/rm/CapturingXMLWriter
      26: dup
      27: aload_2
      28: invokespecial #9                  // Method org/apache/cxf/ws/rm/CapturingXMLWriter."<init>":(Ljavax/xml/stream/XMLStreamWriter;)V
      31: astore_2
      32: aload_1
      33: ldc           #10                 // String RM_CAPTURING_WRITER
      35: aload_2
      36: invokeinterface #7,  3            // InterfaceMethod org/apache/cxf/message/Message.put:(Ljava/lang/Object;Ljava/lang/Object;)Ljava/lang/Object;
      41: pop
      42: aload_1
      43: ldc_w         #4                  // class javax/xml/stream/XMLStreamWriter
      46: aload_2
      47: invokeinterface #11,  3           // InterfaceMethod org/apache/cxf/message/Message.setContent:(Ljava/lang/Class;Ljava/lang/Object;)V
      52: aload_1
      53: ldc           #12                 // String disable.outputstream.optimization
      55: getstatic     #13                 // Field java/lang/Boolean.TRUE:Ljava/lang/Boolean;
      58: invokeinterface #7,  3            // InterfaceMethod org/apache/cxf/message/Message.put:(Ljava/lang/Object;Ljava/lang/Object;)Ljava/lang/Object;
      63: pop
      64: return
}
