Compiled from "RMEndpoint.java"
public class org.apache.cxf.ws.rm.RMEndpoint {
  private static final java.util.logging.Logger LOG;

  private static final java.lang.String SERVICE_NAME;

  private static final java.lang.String INTERFACE_NAME;

  private static final java.lang.String BINDING_NAME;

  private static final java.lang.String CREATE_PART_NAME;

  private static final java.lang.String CREATE_RESPONSE_PART_NAME;

  private static final java.lang.String TERMINATE_PART_NAME;

  private static final java.lang.String TERMINATE_RESPONSE_PART_NAME;

  private static final java.lang.String CLOSE_PART_NAME;

  private static final java.lang.String CLOSE_RESPONSE_PART_NAME;

  private static javax.xml.validation.Schema rmSchema;

  private org.apache.cxf.ws.rm.RMManager manager;

  private org.apache.cxf.endpoint.Endpoint applicationEndpoint;

  private org.apache.cxf.transport.Conduit conduit;

  private org.apache.cxf.ws.addressing.EndpointReferenceType replyTo;

  private org.apache.cxf.ws.rm.Source source;

  private org.apache.cxf.ws.rm.Destination destination;

  private java.util.Map<org.apache.cxf.ws.rm.ProtocolVariation, org.apache.cxf.ws.rm.WrappedService> services;

  private java.util.Map<org.apache.cxf.ws.rm.ProtocolVariation, org.apache.cxf.endpoint.Endpoint> endpoints;

  private java.lang.Object tokenStore;

  private org.apache.cxf.ws.rm.Proxy proxy;

  private org.apache.cxf.ws.rm.Servant servant;

  private long lastApplicationMessage;

  private long lastControlMessage;

  private java.util.concurrent.atomic.AtomicInteger applicationMessageCount;

  private java.util.concurrent.atomic.AtomicInteger controlMessageCount;

  private org.apache.cxf.management.InstrumentationManager instrumentationManager;

  private org.apache.cxf.ws.rm.RMConfiguration configuration;

  private org.apache.cxf.ws.rm.ManagedRMEndpoint managedEndpoint;

  private javax.management.modelmbean.RequiredModelMBean modelMBean;

  private java.util.concurrent.atomic.AtomicInteger acknowledgementSequence;

  public org.apache.cxf.ws.rm.RMEndpoint(org.apache.cxf.ws.rm.RMManager, org.apache.cxf.endpoint.Endpoint);
    Code:
       0: aload_0
       1: invokespecial #1                  // Method java/lang/Object."<init>":()V
       4: aload_0
       5: aload_1
       6: putfield      #2                  // Field manager:Lorg/apache/cxf/ws/rm/RMManager;
       9: aload_0
      10: aload_2
      11: putfield      #3                  // Field applicationEndpoint:Lorg/apache/cxf/endpoint/Endpoint;
      14: aload_0
      15: new           #4                  // class org/apache/cxf/ws/rm/Source
      18: dup
      19: aload_0
      20: invokespecial #5                  // Method org/apache/cxf/ws/rm/Source."<init>":(Lorg/apache/cxf/ws/rm/RMEndpoint;)V
      23: putfield      #6                  // Field source:Lorg/apache/cxf/ws/rm/Source;
      26: aload_0
      27: new           #7                  // class org/apache/cxf/ws/rm/Destination
      30: dup
      31: aload_0
      32: invokespecial #8                  // Method org/apache/cxf/ws/rm/Destination."<init>":(Lorg/apache/cxf/ws/rm/RMEndpoint;)V
      35: putfield      #9                  // Field destination:Lorg/apache/cxf/ws/rm/Destination;
      38: aload_0
      39: new           #10                 // class org/apache/cxf/ws/rm/Proxy
      42: dup
      43: aload_0
      44: invokespecial #11                 // Method org/apache/cxf/ws/rm/Proxy."<init>":(Lorg/apache/cxf/ws/rm/RMEndpoint;)V
      47: putfield      #12                 // Field proxy:Lorg/apache/cxf/ws/rm/Proxy;
      50: aload_0
      51: new           #13                 // class org/apache/cxf/ws/rm/Servant
      54: dup
      55: aload_0
      56: invokespecial #14                 // Method org/apache/cxf/ws/rm/Servant."<init>":(Lorg/apache/cxf/ws/rm/RMEndpoint;)V
      59: putfield      #15                 // Field servant:Lorg/apache/cxf/ws/rm/Servant;
      62: aload_0
      63: new           #16                 // class java/util/HashMap
      66: dup
      67: invokespecial #17                 // Method java/util/HashMap."<init>":()V
      70: putfield      #18                 // Field services:Ljava/util/Map;
      73: aload_0
      74: new           #16                 // class java/util/HashMap
      77: dup
      78: invokespecial #17                 // Method java/util/HashMap."<init>":()V
      81: putfield      #19                 // Field endpoints:Ljava/util/Map;
      84: aload_0
      85: new           #20                 // class java/util/concurrent/atomic/AtomicInteger
      88: dup
      89: invokespecial #21                 // Method java/util/concurrent/atomic/AtomicInteger."<init>":()V
      92: putfield      #22                 // Field applicationMessageCount:Ljava/util/concurrent/atomic/AtomicInteger;
      95: aload_0
      96: new           #20                 // class java/util/concurrent/atomic/AtomicInteger
      99: dup
     100: invokespecial #21                 // Method java/util/concurrent/atomic/AtomicInteger."<init>":()V
     103: putfield      #23                 // Field controlMessageCount:Ljava/util/concurrent/atomic/AtomicInteger;
     106: aload_0
     107: new           #20                 // class java/util/concurrent/atomic/AtomicInteger
     110: dup
     111: invokespecial #21                 // Method java/util/concurrent/atomic/AtomicInteger."<init>":()V
     114: putfield      #24                 // Field acknowledgementSequence:Ljava/util/concurrent/atomic/AtomicInteger;
     117: aload_0
     118: aload_2
     119: invokeinterface #25,  1           // InterfaceMethod org/apache/cxf/endpoint/Endpoint.getEndpointInfo:()Lorg/apache/cxf/service/model/EndpointInfo;
     124: ldc           #26                 // String org.apache.cxf.ws.security.tokenstore.TokenStore
     126: invokevirtual #27                 // Method org/apache/cxf/service/model/EndpointInfo.getProperty:(Ljava/lang/String;)Ljava/lang/Object;
     129: putfield      #28                 // Field tokenStore:Ljava/lang/Object;
     132: return

  public org.apache.cxf.ws.rm.RMManager getManager();
    Code:
       0: aload_0
       1: getfield      #2                  // Field manager:Lorg/apache/cxf/ws/rm/RMManager;
       4: areturn

  public org.apache.cxf.endpoint.Endpoint getApplicationEndpoint();
    Code:
       0: aload_0
       1: getfield      #3                  // Field applicationEndpoint:Lorg/apache/cxf/endpoint/Endpoint;
       4: areturn

  public org.apache.cxf.endpoint.Endpoint getEndpoint(org.apache.cxf.ws.rm.ProtocolVariation);
    Code:
       0: aload_0
       1: getfield      #19                 // Field endpoints:Ljava/util/Map;
       4: aload_1
       5: invokeinterface #29,  2           // InterfaceMethod java/util/Map.get:(Ljava/lang/Object;)Ljava/lang/Object;
      10: checkcast     #30                 // class org/apache/cxf/endpoint/Endpoint
      13: areturn

  public org.apache.cxf.service.Service getService(org.apache.cxf.ws.rm.ProtocolVariation);
    Code:
       0: aload_0
       1: getfield      #18                 // Field services:Ljava/util/Map;
       4: aload_1
       5: invokeinterface #29,  2           // InterfaceMethod java/util/Map.get:(Ljava/lang/Object;)Ljava/lang/Object;
      10: checkcast     #31                 // class org/apache/cxf/service/Service
      13: areturn

  public org.apache.cxf.service.model.BindingInfo getBindingInfo(org.apache.cxf.ws.rm.ProtocolVariation);
    Code:
       0: new           #32                 // class javax/xml/namespace/QName
       3: dup
       4: aload_1
       5: invokevirtual #33                 // Method org/apache/cxf/ws/rm/ProtocolVariation.getWSRMNamespace:()Ljava/lang/String;
       8: ldc           #34                 // String SequenceAbstractSoapBinding
      10: invokespecial #35                 // Method javax/xml/namespace/QName."<init>":(Ljava/lang/String;Ljava/lang/String;)V
      13: astore_2
      14: aload_0
      15: getfield      #18                 // Field services:Ljava/util/Map;
      18: aload_1
      19: invokeinterface #29,  2           // InterfaceMethod java/util/Map.get:(Ljava/lang/Object;)Ljava/lang/Object;
      24: checkcast     #36                 // class org/apache/cxf/ws/rm/WrappedService
      27: invokevirtual #37                 // Method org/apache/cxf/ws/rm/WrappedService.getServiceInfo:()Lorg/apache/cxf/service/model/ServiceInfo;
      30: aload_2
      31: invokevirtual #38                 // Method org/apache/cxf/service/model/ServiceInfo.getBinding:(Ljavax/xml/namespace/QName;)Lorg/apache/cxf/service/model/BindingInfo;
      34: areturn

  public org.apache.cxf.ws.rm.Proxy getProxy();
    Code:
       0: aload_0
       1: getfield      #12                 // Field proxy:Lorg/apache/cxf/ws/rm/Proxy;
       4: areturn

  public org.apache.cxf.ws.rm.Servant getServant();
    Code:
       0: aload_0
       1: getfield      #15                 // Field servant:Lorg/apache/cxf/ws/rm/Servant;
       4: areturn

  public org.apache.cxf.ws.rm.Destination getDestination();
    Code:
       0: aload_0
       1: getfield      #9                  // Field destination:Lorg/apache/cxf/ws/rm/Destination;
       4: areturn

  public void setDestination(org.apache.cxf.ws.rm.Destination);
    Code:
       0: aload_0
       1: aload_1
       2: putfield      #9                  // Field destination:Lorg/apache/cxf/ws/rm/Destination;
       5: return

  public org.apache.cxf.ws.rm.Source getSource();
    Code:
       0: aload_0
       1: getfield      #6                  // Field source:Lorg/apache/cxf/ws/rm/Source;
       4: areturn

  public void setSource(org.apache.cxf.ws.rm.Source);
    Code:
       0: aload_0
       1: aload_1
       2: putfield      #6                  // Field source:Lorg/apache/cxf/ws/rm/Source;
       5: return

  public long getLastApplicationMessage();
    Code:
       0: aload_0
       1: getfield      #39                 // Field lastApplicationMessage:J
       4: lreturn

  public int getApplicationMessageCount();
    Code:
       0: aload_0
       1: getfield      #22                 // Field applicationMessageCount:Ljava/util/concurrent/atomic/AtomicInteger;
       4: invokevirtual #40                 // Method java/util/concurrent/atomic/AtomicInteger.get:()I
       7: ireturn

  public void receivedApplicationMessage();
    Code:
       0: aload_0
       1: invokestatic  #41                 // Method java/lang/System.currentTimeMillis:()J
       4: putfield      #39                 // Field lastApplicationMessage:J
       7: aload_0
       8: getfield      #22                 // Field applicationMessageCount:Ljava/util/concurrent/atomic/AtomicInteger;
      11: invokevirtual #42                 // Method java/util/concurrent/atomic/AtomicInteger.incrementAndGet:()I
      14: pop
      15: return

  public long getLastControlMessage();
    Code:
       0: aload_0
       1: getfield      #43                 // Field lastControlMessage:J
       4: lreturn

  public int getControlMessageCount();
    Code:
       0: aload_0
       1: getfield      #23                 // Field controlMessageCount:Ljava/util/concurrent/atomic/AtomicInteger;
       4: invokevirtual #40                 // Method java/util/concurrent/atomic/AtomicInteger.get:()I
       7: ireturn

  public void receivedControlMessage();
    Code:
       0: aload_0
       1: invokestatic  #41                 // Method java/lang/System.currentTimeMillis:()J
       4: putfield      #43                 // Field lastControlMessage:J
       7: aload_0
       8: getfield      #23                 // Field controlMessageCount:Ljava/util/concurrent/atomic/AtomicInteger;
      11: invokevirtual #42                 // Method java/util/concurrent/atomic/AtomicInteger.incrementAndGet:()I
      14: pop
      15: return

  public org.apache.cxf.transport.Conduit getConduit();
    Code:
       0: aload_0
       1: getfield      #44                 // Field conduit:Lorg/apache/cxf/transport/Conduit;
       4: areturn

  public org.apache.cxf.ws.rm.RMConfiguration getConfiguration();
    Code:
       0: aload_0
       1: getfield      #45                 // Field configuration:Lorg/apache/cxf/ws/rm/RMConfiguration;
       4: areturn

  org.apache.cxf.ws.addressing.EndpointReferenceType getReplyTo();
    Code:
       0: aload_0
       1: getfield      #46                 // Field replyTo:Lorg/apache/cxf/ws/addressing/EndpointReferenceType;
       4: areturn

  public void handleAccept(java.lang.String, long, org.apache.cxf.message.Message);
    Code:
       0: aload         4
       2: ldc           #47                 // String org.apache.cxf.rm.clientCallback
       4: invokeinterface #48,  2           // InterfaceMethod org/apache/cxf/message/Message.get:(Ljava/lang/Object;)Ljava/lang/Object;
       9: astore        5
      11: aload         5
      13: instanceof    #49                 // class org/apache/cxf/ws/rm/MessageCallback
      16: ifeq          31
      19: aload         5
      21: checkcast     #49                 // class org/apache/cxf/ws/rm/MessageCallback
      24: aload_1
      25: lload_2
      26: invokeinterface #50,  4           // InterfaceMethod org/apache/cxf/ws/rm/MessageCallback.messageAccepted:(Ljava/lang/String;J)V
      31: return

  public void handleAcknowledgment(java.lang.String, long, org.apache.cxf.message.Message);
    Code:
       0: aload_0
       1: getfield      #51                 // Field modelMBean:Ljavax/management/modelmbean/RequiredModelMBean;
       4: ifnull        72
       7: aload_0
       8: getfield      #24                 // Field acknowledgementSequence:Ljava/util/concurrent/atomic/AtomicInteger;
      11: invokevirtual #42                 // Method java/util/concurrent/atomic/AtomicInteger.incrementAndGet:()I
      14: istore        5
      16: aload_0
      17: getfield      #51                 // Field modelMBean:Ljavax/management/modelmbean/RequiredModelMBean;
      20: new           #52                 // class org/apache/cxf/ws/rm/AcknowledgementNotification
      23: dup
      24: aload_0
      25: iload         5
      27: i2l
      28: aload_1
      29: lload_2
      30: invokespecial #53                 // Method org/apache/cxf/ws/rm/AcknowledgementNotification."<init>":(Ljava/lang/Object;JLjava/lang/String;J)V
      33: invokevirtual #54                 // Method javax/management/modelmbean/RequiredModelMBean.sendNotification:(Ljavax/management/Notification;)V
      36: goto          72
      39: astore        6
      41: getstatic     #56                 // Field LOG:Ljava/util/logging/Logger;
      44: getstatic     #57                 // Field java/util/logging/Level.WARNING:Ljava/util/logging/Level;
      47: ldc           #58                 // String Error handling JMX notification
      49: aload         6
      51: invokevirtual #59                 // Method java/util/logging/Logger.log:(Ljava/util/logging/Level;Ljava/lang/String;Ljava/lang/Throwable;)V
      54: goto          72
      57: astore        6
      59: getstatic     #56                 // Field LOG:Ljava/util/logging/Logger;
      62: getstatic     #57                 // Field java/util/logging/Level.WARNING:Ljava/util/logging/Level;
      65: ldc           #58                 // String Error handling JMX notification
      67: aload         6
      69: invokevirtual #59                 // Method java/util/logging/Logger.log:(Ljava/util/logging/Level;Ljava/lang/String;Ljava/lang/Throwable;)V
      72: aload         4
      74: ldc           #47                 // String org.apache.cxf.rm.clientCallback
      76: invokeinterface #48,  2           // InterfaceMethod org/apache/cxf/message/Message.get:(Ljava/lang/Object;)Ljava/lang/Object;
      81: astore        5
      83: aload         5
      85: instanceof    #49                 // class org/apache/cxf/ws/rm/MessageCallback
      88: ifeq          103
      91: aload         5
      93: checkcast     #49                 // class org/apache/cxf/ws/rm/MessageCallback
      96: aload_1
      97: lload_2
      98: invokeinterface #61,  4           // InterfaceMethod org/apache/cxf/ws/rm/MessageCallback.messageAcknowledged:(Ljava/lang/String;J)V
     103: return
    Exception table:
       from    to  target type
          16    36    39   Class javax/management/RuntimeOperationsException
          16    36    57   Class javax/management/MBeanException

  void initialise(org.apache.cxf.ws.rm.RMConfiguration, org.apache.cxf.transport.Conduit, org.apache.cxf.ws.addressing.EndpointReferenceType, org.apache.cxf.transport.Destination, org.apache.cxf.message.Message);
    Code:
       0: aload_0
       1: aload_1
       2: putfield      #45                 // Field configuration:Lorg/apache/cxf/ws/rm/RMConfiguration;
       5: aload_0
       6: aload_2
       7: putfield      #44                 // Field conduit:Lorg/apache/cxf/transport/Conduit;
      10: aload_0
      11: aload_3
      12: putfield      #46                 // Field replyTo:Lorg/apache/cxf/ws/addressing/EndpointReferenceType;
      15: aload_0
      16: invokevirtual #62                 // Method createServices:()V
      19: aload_0
      20: aload         4
      22: invokevirtual #63                 // Method createEndpoints:(Lorg/apache/cxf/transport/Destination;)V
      25: aload_0
      26: aload         5
      28: invokevirtual #64                 // Method setPolicies:(Lorg/apache/cxf/message/Message;)V
      31: aload_0
      32: getfield      #2                  // Field manager:Lorg/apache/cxf/ws/rm/RMManager;
      35: ifnull        238
      38: aload_0
      39: getfield      #2                  // Field manager:Lorg/apache/cxf/ws/rm/RMManager;
      42: invokevirtual #65                 // Method org/apache/cxf/ws/rm/RMManager.getBus:()Lorg/apache/cxf/Bus;
      45: ifnull        238
      48: aload_0
      49: new           #66                 // class org/apache/cxf/ws/rm/ManagedRMEndpoint
      52: dup
      53: aload_0
      54: invokespecial #67                 // Method org/apache/cxf/ws/rm/ManagedRMEndpoint."<init>":(Lorg/apache/cxf/ws/rm/RMEndpoint;)V
      57: putfield      #68                 // Field managedEndpoint:Lorg/apache/cxf/ws/rm/ManagedRMEndpoint;
      60: aload_0
      61: aload_0
      62: getfield      #2                  // Field manager:Lorg/apache/cxf/ws/rm/RMManager;
      65: invokevirtual #65                 // Method org/apache/cxf/ws/rm/RMManager.getBus:()Lorg/apache/cxf/Bus;
      68: ldc_w         #69                 // class org/apache/cxf/management/InstrumentationManager
      71: invokeinterface #70,  2           // InterfaceMethod org/apache/cxf/Bus.getExtension:(Ljava/lang/Class;)Ljava/lang/Object;
      76: checkcast     #69                 // class org/apache/cxf/management/InstrumentationManager
      79: putfield      #71                 // Field instrumentationManager:Lorg/apache/cxf/management/InstrumentationManager;
      82: aload_0
      83: getfield      #71                 // Field instrumentationManager:Lorg/apache/cxf/management/InstrumentationManager;
      86: ifnull        238
      89: new           #72                 // class org/apache/cxf/management/jmx/export/runtime/ModelMBeanAssembler
      92: dup
      93: invokespecial #73                 // Method org/apache/cxf/management/jmx/export/runtime/ModelMBeanAssembler."<init>":()V
      96: astore        6
      98: aload         6
     100: aload_0
     101: getfield      #68                 // Field managedEndpoint:Lorg/apache/cxf/ws/rm/ManagedRMEndpoint;
     104: invokevirtual #74                 // Method java/lang/Object.getClass:()Ljava/lang/Class;
     107: invokevirtual #75                 // Method org/apache/cxf/management/jmx/export/runtime/ModelMBeanAssembler.getModelMbeanInfo:(Ljava/lang/Class;)Ljavax/management/modelmbean/ModelMBeanInfo;
     110: astore        7
     112: aload_0
     113: getfield      #71                 // Field instrumentationManager:Lorg/apache/cxf/management/InstrumentationManager;
     116: invokeinterface #76,  1           // InterfaceMethod org/apache/cxf/management/InstrumentationManager.getMBeanServer:()Ljavax/management/MBeanServer;
     121: astore        8
     123: aload         8
     125: ifnonnull     142
     128: getstatic     #56                 // Field LOG:Ljava/util/logging/Logger;
     131: getstatic     #57                 // Field java/util/logging/Level.WARNING:Ljava/util/logging/Level;
     134: ldc           #77                 // String MBeanServer not available.
     136: invokevirtual #78                 // Method java/util/logging/Logger.log:(Ljava/util/logging/Level;Ljava/lang/String;)V
     139: goto          238
     142: aload         8
     144: ldc           #79                 // String javax.management.modelmbean.RequiredModelMBean
     146: invokeinterface #80,  2           // InterfaceMethod javax/management/MBeanServer.instantiate:(Ljava/lang/String;)Ljava/lang/Object;
     151: checkcast     #81                 // class javax/management/modelmbean/RequiredModelMBean
     154: astore        9
     156: aload         9
     158: aload         7
     160: invokevirtual #82                 // Method javax/management/modelmbean/RequiredModelMBean.setModelMBeanInfo:(Ljavax/management/modelmbean/ModelMBeanInfo;)V
     163: aload         9
     165: aload_0
     166: getfield      #68                 // Field managedEndpoint:Lorg/apache/cxf/ws/rm/ManagedRMEndpoint;
     169: ldc           #83                 // String ObjectReference
     171: invokevirtual #84                 // Method javax/management/modelmbean/RequiredModelMBean.setManagedResource:(Ljava/lang/Object;Ljava/lang/String;)V
     174: goto          192
     177: astore        10
     179: new           #86                 // class javax/management/JMException
     182: dup
     183: aload         10
     185: invokevirtual #87                 // Method javax/management/modelmbean/InvalidTargetObjectTypeException.getMessage:()Ljava/lang/String;
     188: invokespecial #88                 // Method javax/management/JMException."<init>":(Ljava/lang/String;)V
     191: athrow
     192: aload_0
     193: getfield      #68                 // Field managedEndpoint:Lorg/apache/cxf/ws/rm/ManagedRMEndpoint;
     196: invokevirtual #89                 // Method org/apache/cxf/ws/rm/ManagedRMEndpoint.getObjectName:()Ljavax/management/ObjectName;
     199: astore        10
     201: aload_0
     202: getfield      #71                 // Field instrumentationManager:Lorg/apache/cxf/management/InstrumentationManager;
     205: aload         9
     207: aload         10
     209: invokeinterface #90,  3           // InterfaceMethod org/apache/cxf/management/InstrumentationManager.register:(Ljava/lang/Object;Ljavax/management/ObjectName;)V
     214: aload_0
     215: aload         9
     217: putfield      #51                 // Field modelMBean:Ljavax/management/modelmbean/RequiredModelMBean;
     220: goto          238
     223: astore        9
     225: getstatic     #56                 // Field LOG:Ljava/util/logging/Logger;
     228: getstatic     #57                 // Field java/util/logging/Level.WARNING:Ljava/util/logging/Level;
     231: ldc           #91                 // String Registering ManagedRMEndpoint failed.
     233: aload         9
     235: invokevirtual #59                 // Method java/util/logging/Logger.log:(Ljava/util/logging/Level;Ljava/lang/String;Ljava/lang/Throwable;)V
     238: return
    Exception table:
       from    to  target type
         163   174   177   Class javax/management/modelmbean/InvalidTargetObjectTypeException
         142   220   223   Class javax/management/JMException

  void createServices();
    Code:
       0: invokestatic  #92                 // Method org/apache/cxf/ws/rm/ProtocolVariation.values:()[Lorg/apache/cxf/ws/rm/ProtocolVariation;
       3: astore_1
       4: aload_1
       5: arraylength
       6: istore_2
       7: iconst_0
       8: istore_3
       9: iload_3
      10: iload_2
      11: if_icmpge     31
      14: aload_1
      15: iload_3
      16: aaload
      17: astore        4
      19: aload_0
      20: aload         4
      22: invokevirtual #93                 // Method createService:(Lorg/apache/cxf/ws/rm/ProtocolVariation;)V
      25: iinc          3, 1
      28: goto          9
      31: return

  void createService(org.apache.cxf.ws.rm.ProtocolVariation);
    Code:
       0: new           #94                 // class org/apache/cxf/service/model/ServiceInfo
       3: dup
       4: invokespecial #95                 // Method org/apache/cxf/service/model/ServiceInfo."<init>":()V
       7: astore_2
       8: aload_2
       9: ldc_w         #96                 // class javax/xml/validation/Schema
      12: invokevirtual #97                 // Method java/lang/Class.getName:()Ljava/lang/String;
      15: invokestatic  #98                 // Method getSchema:()Ljavax/xml/validation/Schema;
      18: invokevirtual #99                 // Method org/apache/cxf/service/model/ServiceInfo.setProperty:(Ljava/lang/String;Ljava/lang/Object;)V
      21: new           #32                 // class javax/xml/namespace/QName
      24: dup
      25: aload_1
      26: invokevirtual #33                 // Method org/apache/cxf/ws/rm/ProtocolVariation.getWSRMNamespace:()Ljava/lang/String;
      29: ldc           #100                // String SequenceAbstractService
      31: invokespecial #35                 // Method javax/xml/namespace/QName."<init>":(Ljava/lang/String;Ljava/lang/String;)V
      34: astore_3
      35: aload_2
      36: aload_3
      37: invokevirtual #101                // Method org/apache/cxf/service/model/ServiceInfo.setName:(Ljavax/xml/namespace/QName;)V
      40: aload_0
      41: aload_2
      42: aload_1
      43: invokevirtual #102                // Method buildInterfaceInfo:(Lorg/apache/cxf/service/model/ServiceInfo;Lorg/apache/cxf/ws/rm/ProtocolVariation;)V
      46: new           #36                 // class org/apache/cxf/ws/rm/WrappedService
      49: dup
      50: aload_0
      51: getfield      #3                  // Field applicationEndpoint:Lorg/apache/cxf/endpoint/Endpoint;
      54: invokeinterface #103,  1          // InterfaceMethod org/apache/cxf/endpoint/Endpoint.getService:()Lorg/apache/cxf/service/Service;
      59: aload_3
      60: aload_2
      61: invokespecial #104                // Method org/apache/cxf/ws/rm/WrappedService."<init>":(Lorg/apache/cxf/service/Service;Ljavax/xml/namespace/QName;Lorg/apache/cxf/service/model/ServiceInfo;)V
      64: astore        4
      66: aconst_null
      67: astore        5
      69: aload_1
      70: invokevirtual #105                // Method org/apache/cxf/ws/rm/ProtocolVariation.getCodec:()Lorg/apache/cxf/ws/rm/EncoderDecoder;
      73: invokevirtual #106                // Method org/apache/cxf/ws/rm/EncoderDecoder.getCreateSequenceType:()Ljava/lang/Class;
      76: astore        6
      78: aload         6
      80: invokestatic  #107                // Method org/apache/cxf/common/util/PackageUtils.getPackageName:(Ljava/lang/Class;)Ljava/lang/String;
      83: aload         6
      85: invokevirtual #108                // Method java/lang/Class.getClassLoader:()Ljava/lang/ClassLoader;
      88: invokestatic  #109                // Method javax/xml/bind/JAXBContext.newInstance:(Ljava/lang/String;Ljava/lang/ClassLoader;)Ljavax/xml/bind/JAXBContext;
      91: astore        7
      93: new           #110                // class org/apache/cxf/jaxb/JAXBDataBinding
      96: dup
      97: aload         7
      99: invokespecial #111                // Method org/apache/cxf/jaxb/JAXBDataBinding."<init>":(Ljavax/xml/bind/JAXBContext;)V
     102: astore        5
     104: goto          119
     107: astore        7
     109: new           #113                // class org/apache/cxf/service/factory/ServiceConstructionException
     112: dup
     113: aload         7
     115: invokespecial #114                // Method org/apache/cxf/service/factory/ServiceConstructionException."<init>":(Ljava/lang/Throwable;)V
     118: athrow
     119: aload         4
     121: aload         5
     123: invokevirtual #115                // Method org/apache/cxf/ws/rm/WrappedService.setDataBinding:(Lorg/apache/cxf/databinding/DataBinding;)V
     126: aload         4
     128: aload_0
     129: getfield      #15                 // Field servant:Lorg/apache/cxf/ws/rm/Servant;
     132: invokevirtual #116                // Method org/apache/cxf/ws/rm/WrappedService.setInvoker:(Lorg/apache/cxf/service/invoker/Invoker;)V
     135: aload_0
     136: getfield      #18                 // Field services:Ljava/util/Map;
     139: aload_1
     140: aload         4
     142: invokeinterface #117,  3          // InterfaceMethod java/util/Map.put:(Ljava/lang/Object;Ljava/lang/Object;)Ljava/lang/Object;
     147: pop
     148: return
    Exception table:
       from    to  target type
          78   104   107   Class javax/xml/bind/JAXBException

  private static synchronized javax.xml.validation.Schema getSchema();
    Code:
       0: getstatic     #118                // Field rmSchema:Ljavax/xml/validation/Schema;
       3: ifnonnull     77
       6: ldc           #119                // String http://www.w3.org/2001/XMLSchema
       8: invokestatic  #120                // Method javax/xml/validation/SchemaFactory.newInstance:(Ljava/lang/String;)Ljavax/xml/validation/SchemaFactory;
      11: astore_0
      12: new           #121                // class javax/xml/transform/stream/StreamSource
      15: dup
      16: ldc_w         #122                // class org/apache/cxf/ws/rm/RMEndpoint
      19: ldc           #123                // String /schemas/wsdl/addressing.xsd
      21: invokevirtual #124                // Method java/lang/Class.getResource:(Ljava/lang/String;)Ljava/net/URL;
      24: invokevirtual #125                // Method java/net/URL.openStream:()Ljava/io/InputStream;
      27: ldc           #126                // String http://schemas.xmlsoap.org/ws/2004/08/addressing
      29: invokespecial #127                // Method javax/xml/transform/stream/StreamSource."<init>":(Ljava/io/InputStream;Ljava/lang/String;)V
      32: astore_1
      33: new           #121                // class javax/xml/transform/stream/StreamSource
      36: dup
      37: ldc_w         #122                // class org/apache/cxf/ws/rm/RMEndpoint
      40: ldc           #128                // String /schemas/wsdl/wsrm.xsd
      42: invokevirtual #124                // Method java/lang/Class.getResource:(Ljava/lang/String;)Ljava/net/URL;
      45: invokevirtual #125                // Method java/net/URL.openStream:()Ljava/io/InputStream;
      48: invokespecial #129                // Method javax/xml/transform/stream/StreamSource."<init>":(Ljava/io/InputStream;)V
      51: astore_2
      52: iconst_2
      53: anewarray     #130                // class javax/xml/transform/Source
      56: dup
      57: iconst_0
      58: aload_1
      59: aastore
      60: dup
      61: iconst_1
      62: aload_2
      63: aastore
      64: astore_3
      65: aload_0
      66: aload_3
      67: invokevirtual #131                // Method javax/xml/validation/SchemaFactory.newSchema:([Ljavax/xml/transform/Source;)Ljavax/xml/validation/Schema;
      70: putstatic     #118                // Field rmSchema:Ljavax/xml/validation/Schema;
      73: goto          77
      76: astore_0
      77: getstatic     #118                // Field rmSchema:Ljavax/xml/validation/Schema;
      80: areturn
    Exception table:
       from    to  target type
           6    73    76   Class java/lang/Exception

  void createEndpoints(org.apache.cxf.transport.Destination);
    Code:
       0: invokestatic  #92                 // Method org/apache/cxf/ws/rm/ProtocolVariation.values:()[Lorg/apache/cxf/ws/rm/ProtocolVariation;
       3: astore_2
       4: aload_2
       5: arraylength
       6: istore_3
       7: iconst_0
       8: istore        4
      10: iload         4
      12: iload_3
      13: if_icmpge     35
      16: aload_2
      17: iload         4
      19: aaload
      20: astore        5
      22: aload_0
      23: aload_1
      24: aload         5
      26: invokevirtual #133                // Method createEndpoint:(Lorg/apache/cxf/transport/Destination;Lorg/apache/cxf/ws/rm/ProtocolVariation;)V
      29: iinc          4, 1
      32: goto          10
      35: return

  void createEndpoint(org.apache.cxf.transport.Destination, org.apache.cxf.ws.rm.ProtocolVariation);
    Code:
       0: new           #32                 // class javax/xml/namespace/QName
       3: dup
       4: aload_2
       5: invokevirtual #33                 // Method org/apache/cxf/ws/rm/ProtocolVariation.getWSRMNamespace:()Ljava/lang/String;
       8: ldc           #34                 // String SequenceAbstractSoapBinding
      10: invokespecial #35                 // Method javax/xml/namespace/QName."<init>":(Ljava/lang/String;Ljava/lang/String;)V
      13: astore_3
      14: aload_0
      15: getfield      #18                 // Field services:Ljava/util/Map;
      18: aload_2
      19: invokeinterface #29,  2           // InterfaceMethod java/util/Map.get:(Ljava/lang/Object;)Ljava/lang/Object;
      24: checkcast     #36                 // class org/apache/cxf/ws/rm/WrappedService
      27: astore        4
      29: aload         4
      31: invokevirtual #37                 // Method org/apache/cxf/ws/rm/WrappedService.getServiceInfo:()Lorg/apache/cxf/service/model/ServiceInfo;
      34: astore        5
      36: aload_0
      37: aload         5
      39: aload_2
      40: invokevirtual #134                // Method buildBindingInfo:(Lorg/apache/cxf/service/model/ServiceInfo;Lorg/apache/cxf/ws/rm/ProtocolVariation;)V
      43: aload_0
      44: getfield      #3                  // Field applicationEndpoint:Lorg/apache/cxf/endpoint/Endpoint;
      47: invokeinterface #25,  1           // InterfaceMethod org/apache/cxf/endpoint/Endpoint.getEndpointInfo:()Lorg/apache/cxf/service/model/EndpointInfo;
      52: astore        6
      54: aload         6
      56: invokevirtual #135                // Method org/apache/cxf/service/model/EndpointInfo.getTransportId:()Ljava/lang/String;
      59: astore        7
      61: new           #136                // class org/apache/cxf/service/model/EndpointInfo
      64: dup
      65: aload         5
      67: aload         7
      69: invokespecial #137                // Method org/apache/cxf/service/model/EndpointInfo."<init>":(Lorg/apache/cxf/service/model/ServiceInfo;Ljava/lang/String;)V
      72: astore        8
      74: aload_1
      75: ifnull        87
      78: aload         8
      80: getstatic     #138                // Field org/apache/cxf/ws/addressing/MAPAggregator.DECOUPLED_DESTINATION:Ljava/lang/String;
      83: aload_1
      84: invokevirtual #139                // Method org/apache/cxf/service/model/EndpointInfo.setProperty:(Ljava/lang/String;Ljava/lang/Object;)V
      87: aload         8
      89: aload         6
      91: invokevirtual #140                // Method org/apache/cxf/service/model/EndpointInfo.getAddress:()Ljava/lang/String;
      94: invokevirtual #141                // Method org/apache/cxf/service/model/EndpointInfo.setAddress:(Ljava/lang/String;)V
      97: aload         8
      99: aload_2
     100: invokevirtual #33                 // Method org/apache/cxf/ws/rm/ProtocolVariation.getWSRMNamespace:()Ljava/lang/String;
     103: invokestatic  #142                // Method org/apache/cxf/ws/rm/RMUtils.getConstants:(Ljava/lang/String;)Lorg/apache/cxf/ws/rm/RMConstants;
     106: invokevirtual #143                // Method org/apache/cxf/ws/rm/RMConstants.getPortName:()Ljavax/xml/namespace/QName;
     109: invokevirtual #144                // Method org/apache/cxf/service/model/EndpointInfo.setName:(Ljavax/xml/namespace/QName;)V
     112: aload         8
     114: aload         5
     116: aload_3
     117: invokevirtual #38                 // Method org/apache/cxf/service/model/ServiceInfo.getBinding:(Ljavax/xml/namespace/QName;)Lorg/apache/cxf/service/model/BindingInfo;
     120: invokevirtual #145                // Method org/apache/cxf/service/model/EndpointInfo.setBinding:(Lorg/apache/cxf/service/model/BindingInfo;)V
     123: aload_0
     124: aload         6
     126: invokevirtual #146                // Method getUsingAddressing:(Lorg/apache/cxf/service/model/EndpointInfo;)Ljava/lang/Object;
     129: astore        9
     131: aconst_null
     132: aload         9
     134: if_acmpeq     144
     137: aload         8
     139: aload         9
     141: invokevirtual #147                // Method org/apache/cxf/service/model/EndpointInfo.addExtensor:(Ljava/lang/Object;)V
     144: aload         5
     146: aload         8
     148: invokevirtual #148                // Method org/apache/cxf/service/model/ServiceInfo.addEndpoint:(Lorg/apache/cxf/service/model/EndpointInfo;)V
     151: aload         8
     153: ldc           #26                 // String org.apache.cxf.ws.security.tokenstore.TokenStore
     155: aload_0
     156: getfield      #28                 // Field tokenStore:Ljava/lang/Object;
     159: invokevirtual #139                // Method org/apache/cxf/service/model/EndpointInfo.setProperty:(Ljava/lang/String;Ljava/lang/Object;)V
     162: new           #149                // class org/apache/cxf/ws/rm/WrappedEndpoint
     165: dup
     166: aload_0
     167: getfield      #3                  // Field applicationEndpoint:Lorg/apache/cxf/endpoint/Endpoint;
     170: aload         8
     172: aload         4
     174: invokespecial #150                // Method org/apache/cxf/ws/rm/WrappedEndpoint."<init>":(Lorg/apache/cxf/endpoint/Endpoint;Lorg/apache/cxf/service/model/EndpointInfo;Lorg/apache/cxf/service/Service;)V
     177: astore        10
     179: aload_0
     180: getfield      #3                  // Field applicationEndpoint:Lorg/apache/cxf/endpoint/Endpoint;
     183: invokeinterface #25,  1           // InterfaceMethod org/apache/cxf/endpoint/Endpoint.getEndpointInfo:()Lorg/apache/cxf/service/model/EndpointInfo;
     188: ifnull        281
     191: aload_0
     192: getfield      #3                  // Field applicationEndpoint:Lorg/apache/cxf/endpoint/Endpoint;
     195: invokeinterface #25,  1           // InterfaceMethod org/apache/cxf/endpoint/Endpoint.getEndpointInfo:()Lorg/apache/cxf/service/model/EndpointInfo;
     200: invokevirtual #151                // Method org/apache/cxf/service/model/EndpointInfo.getProperties:()Ljava/util/Map;
     203: ifnull        281
     206: aload_0
     207: getfield      #3                  // Field applicationEndpoint:Lorg/apache/cxf/endpoint/Endpoint;
     210: invokeinterface #25,  1           // InterfaceMethod org/apache/cxf/endpoint/Endpoint.getEndpointInfo:()Lorg/apache/cxf/service/model/EndpointInfo;
     215: invokevirtual #151                // Method org/apache/cxf/service/model/EndpointInfo.getProperties:()Ljava/util/Map;
     218: invokeinterface #152,  1          // InterfaceMethod java/util/Map.keySet:()Ljava/util/Set;
     223: invokeinterface #153,  1          // InterfaceMethod java/util/Set.iterator:()Ljava/util/Iterator;
     228: astore        11
     230: aload         11
     232: invokeinterface #154,  1          // InterfaceMethod java/util/Iterator.hasNext:()Z
     237: ifeq          281
     240: aload         11
     242: invokeinterface #155,  1          // InterfaceMethod java/util/Iterator.next:()Ljava/lang/Object;
     247: checkcast     #156                // class java/lang/String
     250: astore        12
     252: aload         10
     254: invokeinterface #25,  1           // InterfaceMethod org/apache/cxf/endpoint/Endpoint.getEndpointInfo:()Lorg/apache/cxf/service/model/EndpointInfo;
     259: aload         12
     261: aload_0
     262: getfield      #3                  // Field applicationEndpoint:Lorg/apache/cxf/endpoint/Endpoint;
     265: invokeinterface #25,  1           // InterfaceMethod org/apache/cxf/endpoint/Endpoint.getEndpointInfo:()Lorg/apache/cxf/service/model/EndpointInfo;
     270: aload         12
     272: invokevirtual #27                 // Method org/apache/cxf/service/model/EndpointInfo.getProperty:(Ljava/lang/String;)Ljava/lang/Object;
     275: invokevirtual #139                // Method org/apache/cxf/service/model/EndpointInfo.setProperty:(Ljava/lang/String;Ljava/lang/Object;)V
     278: goto          230
     281: aload         4
     283: aload         10
     285: invokevirtual #157                // Method org/apache/cxf/ws/rm/WrappedService.setEndpoint:(Lorg/apache/cxf/endpoint/Endpoint;)V
     288: aload_0
     289: getfield      #19                 // Field endpoints:Ljava/util/Map;
     292: aload_2
     293: aload         10
     295: invokeinterface #117,  3          // InterfaceMethod java/util/Map.put:(Ljava/lang/Object;Ljava/lang/Object;)Ljava/lang/Object;
     300: pop
     301: return

  void setPolicies(org.apache.cxf.message.Message);
    Code:
       0: aload_0
       1: getfield      #2                  // Field manager:Lorg/apache/cxf/ws/rm/RMManager;
       4: invokevirtual #65                 // Method org/apache/cxf/ws/rm/RMManager.getBus:()Lorg/apache/cxf/Bus;
       7: ldc_w         #158                // class org/apache/cxf/ws/policy/PolicyEngine
      10: invokeinterface #70,  2           // InterfaceMethod org/apache/cxf/Bus.getExtension:(Ljava/lang/Class;)Ljava/lang/Object;
      15: checkcast     #158                // class org/apache/cxf/ws/policy/PolicyEngine
      18: astore_2
      19: aconst_null
      20: aload_2
      21: if_acmpeq     33
      24: aload_2
      25: invokeinterface #159,  1          // InterfaceMethod org/apache/cxf/ws/policy/PolicyEngine.isEnabled:()Z
      30: ifne          34
      33: return
      34: aload_0
      35: getfield      #19                 // Field endpoints:Ljava/util/Map;
      38: invokeinterface #160,  1          // InterfaceMethod java/util/Map.values:()Ljava/util/Collection;
      43: invokeinterface #161,  1          // InterfaceMethod java/util/Collection.iterator:()Ljava/util/Iterator;
      48: astore_3
      49: aload_3
      50: invokeinterface #154,  1          // InterfaceMethod java/util/Iterator.hasNext:()Z
      55: ifeq          297
      58: aload_3
      59: invokeinterface #155,  1          // InterfaceMethod java/util/Iterator.next:()Ljava/lang/Object;
      64: checkcast     #30                 // class org/apache/cxf/endpoint/Endpoint
      67: astore        4
      69: aload         4
      71: invokeinterface #25,  1           // InterfaceMethod org/apache/cxf/endpoint/Endpoint.getEndpointInfo:()Lorg/apache/cxf/service/model/EndpointInfo;
      76: astore        5
      78: aconst_null
      79: aload_0
      80: getfield      #44                 // Field conduit:Lorg/apache/cxf/transport/Conduit;
      83: if_acmpne     106
      86: aload_2
      87: aload_0
      88: getfield      #3                  // Field applicationEndpoint:Lorg/apache/cxf/endpoint/Endpoint;
      91: invokeinterface #25,  1           // InterfaceMethod org/apache/cxf/endpoint/Endpoint.getEndpointInfo:()Lorg/apache/cxf/service/model/EndpointInfo;
      96: aconst_null
      97: aload_1
      98: invokeinterface #162,  4          // InterfaceMethod org/apache/cxf/ws/policy/PolicyEngine.getServerEndpointPolicy:(Lorg/apache/cxf/service/model/EndpointInfo;Lorg/apache/cxf/transport/Destination;Lorg/apache/cxf/message/Message;)Lorg/apache/cxf/ws/policy/EndpointPolicy;
     103: goto          126
     106: aload_2
     107: aload_0
     108: getfield      #3                  // Field applicationEndpoint:Lorg/apache/cxf/endpoint/Endpoint;
     111: invokeinterface #25,  1           // InterfaceMethod org/apache/cxf/endpoint/Endpoint.getEndpointInfo:()Lorg/apache/cxf/service/model/EndpointInfo;
     116: aload_0
     117: getfield      #44                 // Field conduit:Lorg/apache/cxf/transport/Conduit;
     120: aload_1
     121: invokeinterface #163,  4          // InterfaceMethod org/apache/cxf/ws/policy/PolicyEngine.getClientEndpointPolicy:(Lorg/apache/cxf/service/model/EndpointInfo;Lorg/apache/cxf/transport/Conduit;Lorg/apache/cxf/message/Message;)Lorg/apache/cxf/ws/policy/EndpointPolicy;
     126: astore        6
     128: aload_0
     129: getfield      #44                 // Field conduit:Lorg/apache/cxf/transport/Conduit;
     132: ifnull        148
     135: aload_2
     136: aload         5
     138: aload         6
     140: invokeinterface #164,  3          // InterfaceMethod org/apache/cxf/ws/policy/PolicyEngine.setClientEndpointPolicy:(Lorg/apache/cxf/service/model/EndpointInfo;Lorg/apache/cxf/ws/policy/EndpointPolicy;)V
     145: goto          158
     148: aload_2
     149: aload         5
     151: aload         6
     153: invokeinterface #165,  3          // InterfaceMethod org/apache/cxf/ws/policy/PolicyEngine.setServerEndpointPolicy:(Lorg/apache/cxf/service/model/EndpointInfo;Lorg/apache/cxf/ws/policy/EndpointPolicy;)V
     158: new           #166                // class org/apache/cxf/ws/policy/EffectivePolicyImpl
     161: dup
     162: invokespecial #167                // Method org/apache/cxf/ws/policy/EffectivePolicyImpl."<init>":()V
     165: astore        7
     167: aload         7
     169: aload         6
     171: aload_2
     172: iconst_0
     173: iconst_0
     174: aload_1
     175: invokevirtual #168                // Method org/apache/cxf/ws/policy/EffectivePolicyImpl.initialise:(Lorg/apache/cxf/ws/policy/EndpointPolicy;Lorg/apache/cxf/ws/policy/PolicyEngine;ZZLorg/apache/cxf/message/Message;)V
     178: new           #166                // class org/apache/cxf/ws/policy/EffectivePolicyImpl
     181: dup
     182: invokespecial #167                // Method org/apache/cxf/ws/policy/EffectivePolicyImpl."<init>":()V
     185: astore        8
     187: aload         8
     189: aload         6
     191: aload_2
     192: iconst_1
     193: iconst_0
     194: aload_1
     195: invokevirtual #168                // Method org/apache/cxf/ws/policy/EffectivePolicyImpl.initialise:(Lorg/apache/cxf/ws/policy/EndpointPolicy;Lorg/apache/cxf/ws/policy/PolicyEngine;ZZLorg/apache/cxf/message/Message;)V
     198: aload         5
     200: invokevirtual #169                // Method org/apache/cxf/service/model/EndpointInfo.getBinding:()Lorg/apache/cxf/service/model/BindingInfo;
     203: astore        9
     205: aload         9
     207: invokevirtual #170                // Method org/apache/cxf/service/model/BindingInfo.getOperations:()Ljava/util/Collection;
     210: astore        10
     212: aload         10
     214: invokeinterface #161,  1          // InterfaceMethod java/util/Collection.iterator:()Ljava/util/Iterator;
     219: astore        11
     221: aload         11
     223: invokeinterface #154,  1          // InterfaceMethod java/util/Iterator.hasNext:()Z
     228: ifeq          294
     231: aload         11
     233: invokeinterface #155,  1          // InterfaceMethod java/util/Iterator.next:()Ljava/lang/Object;
     238: checkcast     #171                // class org/apache/cxf/service/model/BindingOperationInfo
     241: astore        12
     243: aload_2
     244: aload         5
     246: aload         12
     248: aload         8
     250: invokeinterface #172,  4          // InterfaceMethod org/apache/cxf/ws/policy/PolicyEngine.setEffectiveServerRequestPolicy:(Lorg/apache/cxf/service/model/EndpointInfo;Lorg/apache/cxf/service/model/BindingOperationInfo;Lorg/apache/cxf/ws/policy/EffectivePolicy;)V
     255: aload_2
     256: aload         5
     258: aload         12
     260: aload         7
     262: invokeinterface #173,  4          // InterfaceMethod org/apache/cxf/ws/policy/PolicyEngine.setEffectiveServerResponsePolicy:(Lorg/apache/cxf/service/model/EndpointInfo;Lorg/apache/cxf/service/model/BindingOperationInfo;Lorg/apache/cxf/ws/policy/EffectivePolicy;)V
     267: aload_2
     268: aload         5
     270: aload         12
     272: aload         7
     274: invokeinterface #174,  4          // InterfaceMethod org/apache/cxf/ws/policy/PolicyEngine.setEffectiveClientRequestPolicy:(Lorg/apache/cxf/service/model/EndpointInfo;Lorg/apache/cxf/service/model/BindingOperationInfo;Lorg/apache/cxf/ws/policy/EffectivePolicy;)V
     279: aload_2
     280: aload         5
     282: aload         12
     284: aload         8
     286: invokeinterface #175,  4          // InterfaceMethod org/apache/cxf/ws/policy/PolicyEngine.setEffectiveClientResponsePolicy:(Lorg/apache/cxf/service/model/EndpointInfo;Lorg/apache/cxf/service/model/BindingOperationInfo;Lorg/apache/cxf/ws/policy/EffectivePolicy;)V
     291: goto          221
     294: goto          49
     297: return

  void buildInterfaceInfo(org.apache.cxf.service.model.ServiceInfo, org.apache.cxf.ws.rm.ProtocolVariation);
    Code:
       0: new           #32                 // class javax/xml/namespace/QName
       3: dup
       4: aload_2
       5: invokevirtual #33                 // Method org/apache/cxf/ws/rm/ProtocolVariation.getWSRMNamespace:()Ljava/lang/String;
       8: ldc           #176                // String SequenceAbstractPortType
      10: invokespecial #35                 // Method javax/xml/namespace/QName."<init>":(Ljava/lang/String;Ljava/lang/String;)V
      13: astore_3
      14: new           #177                // class org/apache/cxf/service/model/InterfaceInfo
      17: dup
      18: aload_1
      19: aload_3
      20: invokespecial #178                // Method org/apache/cxf/service/model/InterfaceInfo."<init>":(Lorg/apache/cxf/service/model/ServiceInfo;Ljavax/xml/namespace/QName;)V
      23: astore        4
      25: aload_0
      26: aload         4
      28: aload_2
      29: invokevirtual #179                // Method buildOperationInfo:(Lorg/apache/cxf/service/model/InterfaceInfo;Lorg/apache/cxf/ws/rm/ProtocolVariation;)V
      32: return

  void buildOperationInfo(org.apache.cxf.service.model.InterfaceInfo, org.apache.cxf.ws.rm.ProtocolVariation);
    Code:
       0: aload_0
       1: aload_1
       2: aload_2
       3: invokevirtual #180                // Method buildCreateSequenceOperationInfo:(Lorg/apache/cxf/service/model/InterfaceInfo;Lorg/apache/cxf/ws/rm/ProtocolVariation;)V
       6: aload_0
       7: aload_1
       8: aload_2
       9: invokevirtual #181                // Method buildTerminateSequenceOperationInfo:(Lorg/apache/cxf/service/model/InterfaceInfo;Lorg/apache/cxf/ws/rm/ProtocolVariation;)V
      12: aload_0
      13: aload_1
      14: aload_2
      15: invokevirtual #182                // Method buildSequenceAckOperationInfo:(Lorg/apache/cxf/service/model/InterfaceInfo;Lorg/apache/cxf/ws/rm/ProtocolVariation;)V
      18: aload_0
      19: aload_1
      20: aload_2
      21: invokevirtual #183                // Method buildCloseSequenceOperationInfo:(Lorg/apache/cxf/service/model/InterfaceInfo;Lorg/apache/cxf/ws/rm/ProtocolVariation;)V
      24: aload_0
      25: aload_1
      26: aload_2
      27: invokevirtual #184                // Method buildAckRequestedOperationInfo:(Lorg/apache/cxf/service/model/InterfaceInfo;Lorg/apache/cxf/ws/rm/ProtocolVariation;)V
      30: return

  void buildCreateSequenceOperationInfo(org.apache.cxf.service.model.InterfaceInfo, org.apache.cxf.ws.rm.ProtocolVariation);
    Code:
       0: aconst_null
       1: astore_3
       2: aconst_null
       3: astore        4
       5: aconst_null
       6: astore        5
       8: aload_2
       9: invokevirtual #185                // Method org/apache/cxf/ws/rm/ProtocolVariation.getConstants:()Lorg/apache/cxf/ws/rm/RMConstants;
      12: astore        6
      14: aload_1
      15: aload         6
      17: invokevirtual #186                // Method org/apache/cxf/ws/rm/RMConstants.getCreateSequenceOperationName:()Ljavax/xml/namespace/QName;
      20: invokevirtual #187                // Method org/apache/cxf/service/model/InterfaceInfo.addOperation:(Ljavax/xml/namespace/QName;)Lorg/apache/cxf/service/model/OperationInfo;
      23: astore_3
      24: aload_3
      25: aload         6
      27: invokevirtual #186                // Method org/apache/cxf/ws/rm/RMConstants.getCreateSequenceOperationName:()Ljavax/xml/namespace/QName;
      30: getstatic     #188                // Field org/apache/cxf/service/model/MessageInfo$Type.INPUT:Lorg/apache/cxf/service/model/MessageInfo$Type;
      33: invokevirtual #189                // Method org/apache/cxf/service/model/OperationInfo.createMessage:(Ljavax/xml/namespace/QName;Lorg/apache/cxf/service/model/MessageInfo$Type;)Lorg/apache/cxf/service/model/MessageInfo;
      36: astore        5
      38: aload_3
      39: aload         5
      41: invokevirtual #190                // Method org/apache/cxf/service/model/MessageInfo.getName:()Ljavax/xml/namespace/QName;
      44: invokevirtual #191                // Method javax/xml/namespace/QName.getLocalPart:()Ljava/lang/String;
      47: aload         5
      49: invokevirtual #192                // Method org/apache/cxf/service/model/OperationInfo.setInput:(Ljava/lang/String;Lorg/apache/cxf/service/model/MessageInfo;)V
      52: aload         5
      54: ldc           #193                // String create
      56: invokevirtual #194                // Method org/apache/cxf/service/model/MessageInfo.addMessagePart:(Ljava/lang/String;)Lorg/apache/cxf/service/model/MessagePartInfo;
      59: astore        4
      61: aload         4
      63: aload         6
      65: invokevirtual #186                // Method org/apache/cxf/ws/rm/RMConstants.getCreateSequenceOperationName:()Ljavax/xml/namespace/QName;
      68: invokevirtual #195                // Method org/apache/cxf/service/model/MessagePartInfo.setElementQName:(Ljavax/xml/namespace/QName;)V
      71: aload         4
      73: iconst_1
      74: invokevirtual #196                // Method org/apache/cxf/service/model/MessagePartInfo.setElement:(Z)V
      77: aload         4
      79: aload_2
      80: invokevirtual #105                // Method org/apache/cxf/ws/rm/ProtocolVariation.getCodec:()Lorg/apache/cxf/ws/rm/EncoderDecoder;
      83: invokevirtual #106                // Method org/apache/cxf/ws/rm/EncoderDecoder.getCreateSequenceType:()Ljava/lang/Class;
      86: invokevirtual #197                // Method org/apache/cxf/service/model/MessagePartInfo.setTypeClass:(Ljava/lang/Class;)V
      89: aload_3
      90: aload         6
      92: invokevirtual #198                // Method org/apache/cxf/ws/rm/RMConstants.getCreateSequenceResponseOperationName:()Ljavax/xml/namespace/QName;
      95: getstatic     #199                // Field org/apache/cxf/service/model/MessageInfo$Type.OUTPUT:Lorg/apache/cxf/service/model/MessageInfo$Type;
      98: invokevirtual #189                // Method org/apache/cxf/service/model/OperationInfo.createMessage:(Ljavax/xml/namespace/QName;Lorg/apache/cxf/service/model/MessageInfo$Type;)Lorg/apache/cxf/service/model/MessageInfo;
     101: astore        5
     103: aload_3
     104: aload         5
     106: invokevirtual #190                // Method org/apache/cxf/service/model/MessageInfo.getName:()Ljavax/xml/namespace/QName;
     109: invokevirtual #191                // Method javax/xml/namespace/QName.getLocalPart:()Ljava/lang/String;
     112: aload         5
     114: invokevirtual #200                // Method org/apache/cxf/service/model/OperationInfo.setOutput:(Ljava/lang/String;Lorg/apache/cxf/service/model/MessageInfo;)V
     117: aload         5
     119: ldc           #201                // String createResponse
     121: invokevirtual #194                // Method org/apache/cxf/service/model/MessageInfo.addMessagePart:(Ljava/lang/String;)Lorg/apache/cxf/service/model/MessagePartInfo;
     124: astore        4
     126: aload         4
     128: aload         6
     130: invokevirtual #198                // Method org/apache/cxf/ws/rm/RMConstants.getCreateSequenceResponseOperationName:()Ljavax/xml/namespace/QName;
     133: invokevirtual #195                // Method org/apache/cxf/service/model/MessagePartInfo.setElementQName:(Ljavax/xml/namespace/QName;)V
     136: aload         4
     138: iconst_1
     139: invokevirtual #196                // Method org/apache/cxf/service/model/MessagePartInfo.setElement:(Z)V
     142: aload         4
     144: aload_2
     145: invokevirtual #105                // Method org/apache/cxf/ws/rm/ProtocolVariation.getCodec:()Lorg/apache/cxf/ws/rm/EncoderDecoder;
     148: invokevirtual #202                // Method org/apache/cxf/ws/rm/EncoderDecoder.getCreateSequenceResponseType:()Ljava/lang/Class;
     151: invokevirtual #197                // Method org/apache/cxf/service/model/MessagePartInfo.setTypeClass:(Ljava/lang/Class;)V
     154: aload         4
     156: iconst_0
     157: invokevirtual #203                // Method org/apache/cxf/service/model/MessagePartInfo.setIndex:(I)V
     160: aload_1
     161: aload         6
     163: invokevirtual #204                // Method org/apache/cxf/ws/rm/RMConstants.getCreateSequenceOnewayOperationName:()Ljavax/xml/namespace/QName;
     166: invokevirtual #187                // Method org/apache/cxf/service/model/InterfaceInfo.addOperation:(Ljavax/xml/namespace/QName;)Lorg/apache/cxf/service/model/OperationInfo;
     169: astore_3
     170: aload_3
     171: aload         6
     173: invokevirtual #204                // Method org/apache/cxf/ws/rm/RMConstants.getCreateSequenceOnewayOperationName:()Ljavax/xml/namespace/QName;
     176: getstatic     #188                // Field org/apache/cxf/service/model/MessageInfo$Type.INPUT:Lorg/apache/cxf/service/model/MessageInfo$Type;
     179: invokevirtual #189                // Method org/apache/cxf/service/model/OperationInfo.createMessage:(Ljavax/xml/namespace/QName;Lorg/apache/cxf/service/model/MessageInfo$Type;)Lorg/apache/cxf/service/model/MessageInfo;
     182: astore        5
     184: aload_3
     185: aload         5
     187: invokevirtual #190                // Method org/apache/cxf/service/model/MessageInfo.getName:()Ljavax/xml/namespace/QName;
     190: invokevirtual #191                // Method javax/xml/namespace/QName.getLocalPart:()Ljava/lang/String;
     193: aload         5
     195: invokevirtual #192                // Method org/apache/cxf/service/model/OperationInfo.setInput:(Ljava/lang/String;Lorg/apache/cxf/service/model/MessageInfo;)V
     198: aload         5
     200: ldc           #193                // String create
     202: invokevirtual #194                // Method org/apache/cxf/service/model/MessageInfo.addMessagePart:(Ljava/lang/String;)Lorg/apache/cxf/service/model/MessagePartInfo;
     205: astore        4
     207: aload         4
     209: aload         6
     211: invokevirtual #204                // Method org/apache/cxf/ws/rm/RMConstants.getCreateSequenceOnewayOperationName:()Ljavax/xml/namespace/QName;
     214: invokevirtual #195                // Method org/apache/cxf/service/model/MessagePartInfo.setElementQName:(Ljavax/xml/namespace/QName;)V
     217: aload         4
     219: iconst_1
     220: invokevirtual #196                // Method org/apache/cxf/service/model/MessagePartInfo.setElement:(Z)V
     223: aload         4
     225: aload_2
     226: invokevirtual #105                // Method org/apache/cxf/ws/rm/ProtocolVariation.getCodec:()Lorg/apache/cxf/ws/rm/EncoderDecoder;
     229: invokevirtual #106                // Method org/apache/cxf/ws/rm/EncoderDecoder.getCreateSequenceType:()Ljava/lang/Class;
     232: invokevirtual #197                // Method org/apache/cxf/service/model/MessagePartInfo.setTypeClass:(Ljava/lang/Class;)V
     235: aload_1
     236: aload         6
     238: invokevirtual #205                // Method org/apache/cxf/ws/rm/RMConstants.getCreateSequenceResponseOnewayOperationName:()Ljavax/xml/namespace/QName;
     241: invokevirtual #187                // Method org/apache/cxf/service/model/InterfaceInfo.addOperation:(Ljavax/xml/namespace/QName;)Lorg/apache/cxf/service/model/OperationInfo;
     244: astore_3
     245: aload_3
     246: aload         6
     248: invokevirtual #205                // Method org/apache/cxf/ws/rm/RMConstants.getCreateSequenceResponseOnewayOperationName:()Ljavax/xml/namespace/QName;
     251: getstatic     #188                // Field org/apache/cxf/service/model/MessageInfo$Type.INPUT:Lorg/apache/cxf/service/model/MessageInfo$Type;
     254: invokevirtual #189                // Method org/apache/cxf/service/model/OperationInfo.createMessage:(Ljavax/xml/namespace/QName;Lorg/apache/cxf/service/model/MessageInfo$Type;)Lorg/apache/cxf/service/model/MessageInfo;
     257: astore        5
     259: aload_3
     260: aload         5
     262: invokevirtual #190                // Method org/apache/cxf/service/model/MessageInfo.getName:()Ljavax/xml/namespace/QName;
     265: invokevirtual #191                // Method javax/xml/namespace/QName.getLocalPart:()Ljava/lang/String;
     268: aload         5
     270: invokevirtual #192                // Method org/apache/cxf/service/model/OperationInfo.setInput:(Ljava/lang/String;Lorg/apache/cxf/service/model/MessageInfo;)V
     273: aload         5
     275: ldc           #201                // String createResponse
     277: invokevirtual #194                // Method org/apache/cxf/service/model/MessageInfo.addMessagePart:(Ljava/lang/String;)Lorg/apache/cxf/service/model/MessagePartInfo;
     280: astore        4
     282: aload         4
     284: aload         6
     286: invokevirtual #205                // Method org/apache/cxf/ws/rm/RMConstants.getCreateSequenceResponseOnewayOperationName:()Ljavax/xml/namespace/QName;
     289: invokevirtual #195                // Method org/apache/cxf/service/model/MessagePartInfo.setElementQName:(Ljavax/xml/namespace/QName;)V
     292: aload         4
     294: iconst_1
     295: invokevirtual #196                // Method org/apache/cxf/service/model/MessagePartInfo.setElement:(Z)V
     298: aload         4
     300: aload_2
     301: invokevirtual #105                // Method org/apache/cxf/ws/rm/ProtocolVariation.getCodec:()Lorg/apache/cxf/ws/rm/EncoderDecoder;
     304: invokevirtual #202                // Method org/apache/cxf/ws/rm/EncoderDecoder.getCreateSequenceResponseType:()Ljava/lang/Class;
     307: invokevirtual #197                // Method org/apache/cxf/service/model/MessagePartInfo.setTypeClass:(Ljava/lang/Class;)V
     310: return

  void buildTerminateSequenceOperationInfo(org.apache.cxf.service.model.InterfaceInfo, org.apache.cxf.ws.rm.ProtocolVariation);
    Code:
       0: aconst_null
       1: astore_3
       2: aconst_null
       3: astore        4
       5: aconst_null
       6: astore        5
       8: aload_2
       9: invokevirtual #185                // Method org/apache/cxf/ws/rm/ProtocolVariation.getConstants:()Lorg/apache/cxf/ws/rm/RMConstants;
      12: astore        6
      14: aload_1
      15: aload         6
      17: invokevirtual #206                // Method org/apache/cxf/ws/rm/RMConstants.getTerminateSequenceOperationName:()Ljavax/xml/namespace/QName;
      20: invokevirtual #187                // Method org/apache/cxf/service/model/InterfaceInfo.addOperation:(Ljavax/xml/namespace/QName;)Lorg/apache/cxf/service/model/OperationInfo;
      23: astore_3
      24: aload_3
      25: aload         6
      27: invokevirtual #206                // Method org/apache/cxf/ws/rm/RMConstants.getTerminateSequenceOperationName:()Ljavax/xml/namespace/QName;
      30: getstatic     #188                // Field org/apache/cxf/service/model/MessageInfo$Type.INPUT:Lorg/apache/cxf/service/model/MessageInfo$Type;
      33: invokevirtual #189                // Method org/apache/cxf/service/model/OperationInfo.createMessage:(Ljavax/xml/namespace/QName;Lorg/apache/cxf/service/model/MessageInfo$Type;)Lorg/apache/cxf/service/model/MessageInfo;
      36: astore        5
      38: aload_3
      39: aload         5
      41: invokevirtual #190                // Method org/apache/cxf/service/model/MessageInfo.getName:()Ljavax/xml/namespace/QName;
      44: invokevirtual #191                // Method javax/xml/namespace/QName.getLocalPart:()Ljava/lang/String;
      47: aload         5
      49: invokevirtual #192                // Method org/apache/cxf/service/model/OperationInfo.setInput:(Ljava/lang/String;Lorg/apache/cxf/service/model/MessageInfo;)V
      52: aload         5
      54: ldc           #207                // String terminate
      56: invokevirtual #194                // Method org/apache/cxf/service/model/MessageInfo.addMessagePart:(Ljava/lang/String;)Lorg/apache/cxf/service/model/MessagePartInfo;
      59: astore        4
      61: aload         4
      63: aload         6
      65: invokevirtual #206                // Method org/apache/cxf/ws/rm/RMConstants.getTerminateSequenceOperationName:()Ljavax/xml/namespace/QName;
      68: invokevirtual #195                // Method org/apache/cxf/service/model/MessagePartInfo.setElementQName:(Ljavax/xml/namespace/QName;)V
      71: aload         4
      73: iconst_1
      74: invokevirtual #196                // Method org/apache/cxf/service/model/MessagePartInfo.setElement:(Z)V
      77: aload         4
      79: aload_2
      80: invokevirtual #105                // Method org/apache/cxf/ws/rm/ProtocolVariation.getCodec:()Lorg/apache/cxf/ws/rm/EncoderDecoder;
      83: invokevirtual #208                // Method org/apache/cxf/ws/rm/EncoderDecoder.getTerminateSequenceType:()Ljava/lang/Class;
      86: invokevirtual #197                // Method org/apache/cxf/service/model/MessagePartInfo.setTypeClass:(Ljava/lang/Class;)V
      89: ldc           #209                // String http://docs.oasis-open.org/ws-rx/wsrm/200702
      91: aload_2
      92: invokevirtual #33                 // Method org/apache/cxf/ws/rm/ProtocolVariation.getWSRMNamespace:()Ljava/lang/String;
      95: invokevirtual #210                // Method java/lang/String.equals:(Ljava/lang/Object;)Z
      98: ifeq          174
     101: aload_3
     102: getstatic     #211                // Field org/apache/cxf/ws/rm/RM11Constants.INSTANCE:Lorg/apache/cxf/ws/rm/RM11Constants;
     105: invokevirtual #212                // Method org/apache/cxf/ws/rm/RM11Constants.getTerminateSequenceResponseOperationName:()Ljavax/xml/namespace/QName;
     108: getstatic     #199                // Field org/apache/cxf/service/model/MessageInfo$Type.OUTPUT:Lorg/apache/cxf/service/model/MessageInfo$Type;
     111: invokevirtual #189                // Method org/apache/cxf/service/model/OperationInfo.createMessage:(Ljavax/xml/namespace/QName;Lorg/apache/cxf/service/model/MessageInfo$Type;)Lorg/apache/cxf/service/model/MessageInfo;
     114: astore        5
     116: aload_3
     117: aload         5
     119: invokevirtual #190                // Method org/apache/cxf/service/model/MessageInfo.getName:()Ljavax/xml/namespace/QName;
     122: invokevirtual #191                // Method javax/xml/namespace/QName.getLocalPart:()Ljava/lang/String;
     125: aload         5
     127: invokevirtual #200                // Method org/apache/cxf/service/model/OperationInfo.setOutput:(Ljava/lang/String;Lorg/apache/cxf/service/model/MessageInfo;)V
     130: aload         5
     132: ldc           #213                // String terminateResponse
     134: invokevirtual #194                // Method org/apache/cxf/service/model/MessageInfo.addMessagePart:(Ljava/lang/String;)Lorg/apache/cxf/service/model/MessagePartInfo;
     137: astore        4
     139: aload         4
     141: getstatic     #211                // Field org/apache/cxf/ws/rm/RM11Constants.INSTANCE:Lorg/apache/cxf/ws/rm/RM11Constants;
     144: invokevirtual #212                // Method org/apache/cxf/ws/rm/RM11Constants.getTerminateSequenceResponseOperationName:()Ljavax/xml/namespace/QName;
     147: invokevirtual #195                // Method org/apache/cxf/service/model/MessagePartInfo.setElementQName:(Ljavax/xml/namespace/QName;)V
     150: aload         4
     152: iconst_1
     153: invokevirtual #196                // Method org/apache/cxf/service/model/MessagePartInfo.setElement:(Z)V
     156: aload         4
     158: aload_2
     159: invokevirtual #105                // Method org/apache/cxf/ws/rm/ProtocolVariation.getCodec:()Lorg/apache/cxf/ws/rm/EncoderDecoder;
     162: invokevirtual #214                // Method org/apache/cxf/ws/rm/EncoderDecoder.getTerminateSequenceResponseType:()Ljava/lang/Class;
     165: invokevirtual #197                // Method org/apache/cxf/service/model/MessagePartInfo.setTypeClass:(Ljava/lang/Class;)V
     168: aload         4
     170: iconst_0
     171: invokevirtual #203                // Method org/apache/cxf/service/model/MessagePartInfo.setIndex:(I)V
     174: aload_1
     175: aload         6
     177: invokevirtual #215                // Method org/apache/cxf/ws/rm/RMConstants.getTerminateSequenceAnonymousOperationName:()Ljavax/xml/namespace/QName;
     180: invokevirtual #187                // Method org/apache/cxf/service/model/InterfaceInfo.addOperation:(Ljavax/xml/namespace/QName;)Lorg/apache/cxf/service/model/OperationInfo;
     183: astore_3
     184: aload_3
     185: aload         6
     187: invokevirtual #215                // Method org/apache/cxf/ws/rm/RMConstants.getTerminateSequenceAnonymousOperationName:()Ljavax/xml/namespace/QName;
     190: getstatic     #199                // Field org/apache/cxf/service/model/MessageInfo$Type.OUTPUT:Lorg/apache/cxf/service/model/MessageInfo$Type;
     193: invokevirtual #189                // Method org/apache/cxf/service/model/OperationInfo.createMessage:(Ljavax/xml/namespace/QName;Lorg/apache/cxf/service/model/MessageInfo$Type;)Lorg/apache/cxf/service/model/MessageInfo;
     196: astore        5
     198: aload_3
     199: aload         5
     201: invokevirtual #190                // Method org/apache/cxf/service/model/MessageInfo.getName:()Ljavax/xml/namespace/QName;
     204: invokevirtual #191                // Method javax/xml/namespace/QName.getLocalPart:()Ljava/lang/String;
     207: aload         5
     209: invokevirtual #200                // Method org/apache/cxf/service/model/OperationInfo.setOutput:(Ljava/lang/String;Lorg/apache/cxf/service/model/MessageInfo;)V
     212: aload         5
     214: ldc           #207                // String terminate
     216: invokevirtual #194                // Method org/apache/cxf/service/model/MessageInfo.addMessagePart:(Ljava/lang/String;)Lorg/apache/cxf/service/model/MessagePartInfo;
     219: astore        4
     221: aload         4
     223: aload         6
     225: invokevirtual #206                // Method org/apache/cxf/ws/rm/RMConstants.getTerminateSequenceOperationName:()Ljavax/xml/namespace/QName;
     228: invokevirtual #195                // Method org/apache/cxf/service/model/MessagePartInfo.setElementQName:(Ljavax/xml/namespace/QName;)V
     231: aload         4
     233: iconst_1
     234: invokevirtual #196                // Method org/apache/cxf/service/model/MessagePartInfo.setElement:(Z)V
     237: aload         4
     239: aload_2
     240: invokevirtual #105                // Method org/apache/cxf/ws/rm/ProtocolVariation.getCodec:()Lorg/apache/cxf/ws/rm/EncoderDecoder;
     243: invokevirtual #208                // Method org/apache/cxf/ws/rm/EncoderDecoder.getTerminateSequenceType:()Ljava/lang/Class;
     246: invokevirtual #197                // Method org/apache/cxf/service/model/MessagePartInfo.setTypeClass:(Ljava/lang/Class;)V
     249: return

  void buildSequenceAckOperationInfo(org.apache.cxf.service.model.InterfaceInfo, org.apache.cxf.ws.rm.ProtocolVariation);
    Code:
       0: aconst_null
       1: astore_3
       2: aconst_null
       3: astore        4
       5: aload_2
       6: invokevirtual #185                // Method org/apache/cxf/ws/rm/ProtocolVariation.getConstants:()Lorg/apache/cxf/ws/rm/RMConstants;
       9: astore        5
      11: aload_1
      12: aload         5
      14: invokevirtual #216                // Method org/apache/cxf/ws/rm/RMConstants.getSequenceAckOperationName:()Ljavax/xml/namespace/QName;
      17: invokevirtual #187                // Method org/apache/cxf/service/model/InterfaceInfo.addOperation:(Ljavax/xml/namespace/QName;)Lorg/apache/cxf/service/model/OperationInfo;
      20: astore_3
      21: aload_3
      22: aload         5
      24: invokevirtual #216                // Method org/apache/cxf/ws/rm/RMConstants.getSequenceAckOperationName:()Ljavax/xml/namespace/QName;
      27: getstatic     #188                // Field org/apache/cxf/service/model/MessageInfo$Type.INPUT:Lorg/apache/cxf/service/model/MessageInfo$Type;
      30: invokevirtual #189                // Method org/apache/cxf/service/model/OperationInfo.createMessage:(Ljavax/xml/namespace/QName;Lorg/apache/cxf/service/model/MessageInfo$Type;)Lorg/apache/cxf/service/model/MessageInfo;
      33: astore        4
      35: aload_3
      36: aload         4
      38: invokevirtual #190                // Method org/apache/cxf/service/model/MessageInfo.getName:()Ljavax/xml/namespace/QName;
      41: invokevirtual #191                // Method javax/xml/namespace/QName.getLocalPart:()Ljava/lang/String;
      44: aload         4
      46: invokevirtual #192                // Method org/apache/cxf/service/model/OperationInfo.setInput:(Ljava/lang/String;Lorg/apache/cxf/service/model/MessageInfo;)V
      49: return

  void buildCloseSequenceOperationInfo(org.apache.cxf.service.model.InterfaceInfo, org.apache.cxf.ws.rm.ProtocolVariation);
    Code:
       0: aconst_null
       1: astore_3
       2: aconst_null
       3: astore        4
       5: aload_2
       6: invokevirtual #185                // Method org/apache/cxf/ws/rm/ProtocolVariation.getConstants:()Lorg/apache/cxf/ws/rm/RMConstants;
       9: astore        5
      11: aload_1
      12: aload         5
      14: invokevirtual #217                // Method org/apache/cxf/ws/rm/RMConstants.getCloseSequenceOperationName:()Ljavax/xml/namespace/QName;
      17: invokevirtual #187                // Method org/apache/cxf/service/model/InterfaceInfo.addOperation:(Ljavax/xml/namespace/QName;)Lorg/apache/cxf/service/model/OperationInfo;
      20: astore_3
      21: aload_3
      22: aload         5
      24: invokevirtual #217                // Method org/apache/cxf/ws/rm/RMConstants.getCloseSequenceOperationName:()Ljavax/xml/namespace/QName;
      27: getstatic     #188                // Field org/apache/cxf/service/model/MessageInfo$Type.INPUT:Lorg/apache/cxf/service/model/MessageInfo$Type;
      30: invokevirtual #189                // Method org/apache/cxf/service/model/OperationInfo.createMessage:(Ljavax/xml/namespace/QName;Lorg/apache/cxf/service/model/MessageInfo$Type;)Lorg/apache/cxf/service/model/MessageInfo;
      33: astore        4
      35: aload_3
      36: aload         4
      38: invokevirtual #190                // Method org/apache/cxf/service/model/MessageInfo.getName:()Ljavax/xml/namespace/QName;
      41: invokevirtual #191                // Method javax/xml/namespace/QName.getLocalPart:()Ljava/lang/String;
      44: aload         4
      46: invokevirtual #192                // Method org/apache/cxf/service/model/OperationInfo.setInput:(Ljava/lang/String;Lorg/apache/cxf/service/model/MessageInfo;)V
      49: ldc           #209                // String http://docs.oasis-open.org/ws-rx/wsrm/200702
      51: aload_2
      52: invokevirtual #33                 // Method org/apache/cxf/ws/rm/ProtocolVariation.getWSRMNamespace:()Ljava/lang/String;
      55: invokevirtual #210                // Method java/lang/String.equals:(Ljava/lang/Object;)Z
      58: ifeq          163
      61: aload         4
      63: ldc           #218                // String close
      65: invokevirtual #194                // Method org/apache/cxf/service/model/MessageInfo.addMessagePart:(Ljava/lang/String;)Lorg/apache/cxf/service/model/MessagePartInfo;
      68: astore        6
      70: aload         6
      72: aload         5
      74: invokevirtual #217                // Method org/apache/cxf/ws/rm/RMConstants.getCloseSequenceOperationName:()Ljavax/xml/namespace/QName;
      77: invokevirtual #195                // Method org/apache/cxf/service/model/MessagePartInfo.setElementQName:(Ljavax/xml/namespace/QName;)V
      80: aload         6
      82: iconst_1
      83: invokevirtual #196                // Method org/apache/cxf/service/model/MessagePartInfo.setElement:(Z)V
      86: aload         6
      88: ldc_w         #219                // class org/apache/cxf/ws/rm/v200702/CloseSequenceType
      91: invokevirtual #197                // Method org/apache/cxf/service/model/MessagePartInfo.setTypeClass:(Ljava/lang/Class;)V
      94: aload_3
      95: getstatic     #211                // Field org/apache/cxf/ws/rm/RM11Constants.INSTANCE:Lorg/apache/cxf/ws/rm/RM11Constants;
      98: invokevirtual #220                // Method org/apache/cxf/ws/rm/RM11Constants.getCloseSequenceResponseOperationName:()Ljavax/xml/namespace/QName;
     101: getstatic     #199                // Field org/apache/cxf/service/model/MessageInfo$Type.OUTPUT:Lorg/apache/cxf/service/model/MessageInfo$Type;
     104: invokevirtual #189                // Method org/apache/cxf/service/model/OperationInfo.createMessage:(Ljavax/xml/namespace/QName;Lorg/apache/cxf/service/model/MessageInfo$Type;)Lorg/apache/cxf/service/model/MessageInfo;
     107: astore        4
     109: aload_3
     110: aload         4
     112: invokevirtual #190                // Method org/apache/cxf/service/model/MessageInfo.getName:()Ljavax/xml/namespace/QName;
     115: invokevirtual #191                // Method javax/xml/namespace/QName.getLocalPart:()Ljava/lang/String;
     118: aload         4
     120: invokevirtual #200                // Method org/apache/cxf/service/model/OperationInfo.setOutput:(Ljava/lang/String;Lorg/apache/cxf/service/model/MessageInfo;)V
     123: aload         4
     125: ldc           #221                // String closeResponse
     127: invokevirtual #194                // Method org/apache/cxf/service/model/MessageInfo.addMessagePart:(Ljava/lang/String;)Lorg/apache/cxf/service/model/MessagePartInfo;
     130: astore        6
     132: aload         6
     134: getstatic     #211                // Field org/apache/cxf/ws/rm/RM11Constants.INSTANCE:Lorg/apache/cxf/ws/rm/RM11Constants;
     137: invokevirtual #220                // Method org/apache/cxf/ws/rm/RM11Constants.getCloseSequenceResponseOperationName:()Ljavax/xml/namespace/QName;
     140: invokevirtual #195                // Method org/apache/cxf/service/model/MessagePartInfo.setElementQName:(Ljavax/xml/namespace/QName;)V
     143: aload         6
     145: iconst_1
     146: invokevirtual #196                // Method org/apache/cxf/service/model/MessagePartInfo.setElement:(Z)V
     149: aload         6
     151: ldc_w         #222                // class org/apache/cxf/ws/rm/v200702/CloseSequenceResponseType
     154: invokevirtual #197                // Method org/apache/cxf/service/model/MessagePartInfo.setTypeClass:(Ljava/lang/Class;)V
     157: aload         6
     159: iconst_0
     160: invokevirtual #203                // Method org/apache/cxf/service/model/MessagePartInfo.setIndex:(I)V
     163: return

  void buildAckRequestedOperationInfo(org.apache.cxf.service.model.InterfaceInfo, org.apache.cxf.ws.rm.ProtocolVariation);
    Code:
       0: aconst_null
       1: astore_3
       2: aconst_null
       3: astore        4
       5: aload_2
       6: invokevirtual #185                // Method org/apache/cxf/ws/rm/ProtocolVariation.getConstants:()Lorg/apache/cxf/ws/rm/RMConstants;
       9: astore        5
      11: aload_1
      12: aload         5
      14: invokevirtual #223                // Method org/apache/cxf/ws/rm/RMConstants.getAckRequestedOperationName:()Ljavax/xml/namespace/QName;
      17: invokevirtual #187                // Method org/apache/cxf/service/model/InterfaceInfo.addOperation:(Ljavax/xml/namespace/QName;)Lorg/apache/cxf/service/model/OperationInfo;
      20: astore_3
      21: aload_3
      22: aload         5
      24: invokevirtual #223                // Method org/apache/cxf/ws/rm/RMConstants.getAckRequestedOperationName:()Ljavax/xml/namespace/QName;
      27: getstatic     #188                // Field org/apache/cxf/service/model/MessageInfo$Type.INPUT:Lorg/apache/cxf/service/model/MessageInfo$Type;
      30: invokevirtual #189                // Method org/apache/cxf/service/model/OperationInfo.createMessage:(Ljavax/xml/namespace/QName;Lorg/apache/cxf/service/model/MessageInfo$Type;)Lorg/apache/cxf/service/model/MessageInfo;
      33: astore        4
      35: aload_3
      36: aload         4
      38: invokevirtual #190                // Method org/apache/cxf/service/model/MessageInfo.getName:()Ljavax/xml/namespace/QName;
      41: invokevirtual #191                // Method javax/xml/namespace/QName.getLocalPart:()Ljava/lang/String;
      44: aload         4
      46: invokevirtual #192                // Method org/apache/cxf/service/model/OperationInfo.setInput:(Ljava/lang/String;Lorg/apache/cxf/service/model/MessageInfo;)V
      49: return

  void buildBindingInfo(org.apache.cxf.service.model.ServiceInfo, org.apache.cxf.ws.rm.ProtocolVariation);
    Code:
       0: aconst_null
       1: aload_0
       2: getfield      #3                  // Field applicationEndpoint:Lorg/apache/cxf/endpoint/Endpoint;
       5: if_acmpeq     448
       8: new           #32                 // class javax/xml/namespace/QName
      11: dup
      12: aload_2
      13: invokevirtual #33                 // Method org/apache/cxf/ws/rm/ProtocolVariation.getWSRMNamespace:()Ljava/lang/String;
      16: ldc           #34                 // String SequenceAbstractSoapBinding
      18: invokespecial #35                 // Method javax/xml/namespace/QName."<init>":(Ljava/lang/String;Ljava/lang/String;)V
      21: astore_3
      22: aload_0
      23: getfield      #3                  // Field applicationEndpoint:Lorg/apache/cxf/endpoint/Endpoint;
      26: invokeinterface #25,  1           // InterfaceMethod org/apache/cxf/endpoint/Endpoint.getEndpointInfo:()Lorg/apache/cxf/service/model/EndpointInfo;
      31: invokevirtual #169                // Method org/apache/cxf/service/model/EndpointInfo.getBinding:()Lorg/apache/cxf/service/model/BindingInfo;
      34: checkcast     #224                // class org/apache/cxf/binding/soap/model/SoapBindingInfo
      37: astore        4
      39: aload         4
      41: invokevirtual #225                // Method org/apache/cxf/binding/soap/model/SoapBindingInfo.getSoapVersion:()Lorg/apache/cxf/binding/soap/SoapVersion;
      44: astore        5
      46: aload         4
      48: invokevirtual #226                // Method org/apache/cxf/binding/soap/model/SoapBindingInfo.getBindingId:()Ljava/lang/String;
      51: astore        6
      53: new           #224                // class org/apache/cxf/binding/soap/model/SoapBindingInfo
      56: dup
      57: aload_1
      58: aload         6
      60: aload         5
      62: invokespecial #227                // Method org/apache/cxf/binding/soap/model/SoapBindingInfo."<init>":(Lorg/apache/cxf/service/model/ServiceInfo;Ljava/lang/String;Lorg/apache/cxf/binding/soap/SoapVersion;)V
      65: astore        7
      67: aload         7
      69: aload_3
      70: invokevirtual #228                // Method org/apache/cxf/binding/soap/model/SoapBindingInfo.setName:(Ljavax/xml/namespace/QName;)V
      73: aconst_null
      74: astore        8
      76: aload_2
      77: invokevirtual #185                // Method org/apache/cxf/ws/rm/ProtocolVariation.getConstants:()Lorg/apache/cxf/ws/rm/RMConstants;
      80: astore        9
      82: aload         7
      84: aload         9
      86: invokevirtual #186                // Method org/apache/cxf/ws/rm/RMConstants.getCreateSequenceOperationName:()Ljavax/xml/namespace/QName;
      89: aload         9
      91: invokevirtual #186                // Method org/apache/cxf/ws/rm/RMConstants.getCreateSequenceOperationName:()Ljavax/xml/namespace/QName;
      94: invokevirtual #191                // Method javax/xml/namespace/QName.getLocalPart:()Ljava/lang/String;
      97: aconst_null
      98: invokevirtual #229                // Method org/apache/cxf/binding/soap/model/SoapBindingInfo.buildOperation:(Ljavax/xml/namespace/QName;Ljava/lang/String;Ljava/lang/String;)Lorg/apache/cxf/service/model/BindingOperationInfo;
     101: astore        8
     103: aload_0
     104: aload         8
     106: aload         9
     108: invokevirtual #230                // Method org/apache/cxf/ws/rm/RMConstants.getCreateSequenceAction:()Ljava/lang/String;
     111: aload         9
     113: invokevirtual #231                // Method org/apache/cxf/ws/rm/RMConstants.getCreateSequenceResponseAction:()Ljava/lang/String;
     116: invokespecial #232                // Method addAction:(Lorg/apache/cxf/service/model/BindingOperationInfo;Ljava/lang/String;Ljava/lang/String;)V
     119: aload         7
     121: aload         8
     123: invokevirtual #233                // Method org/apache/cxf/binding/soap/model/SoapBindingInfo.addOperation:(Lorg/apache/cxf/service/model/BindingOperationInfo;)V
     126: aload         7
     128: aload         9
     130: invokevirtual #206                // Method org/apache/cxf/ws/rm/RMConstants.getTerminateSequenceOperationName:()Ljavax/xml/namespace/QName;
     133: aload         9
     135: invokevirtual #206                // Method org/apache/cxf/ws/rm/RMConstants.getTerminateSequenceOperationName:()Ljavax/xml/namespace/QName;
     138: invokevirtual #191                // Method javax/xml/namespace/QName.getLocalPart:()Ljava/lang/String;
     141: aconst_null
     142: invokevirtual #229                // Method org/apache/cxf/binding/soap/model/SoapBindingInfo.buildOperation:(Ljavax/xml/namespace/QName;Ljava/lang/String;Ljava/lang/String;)Lorg/apache/cxf/service/model/BindingOperationInfo;
     145: astore        8
     147: ldc           #209                // String http://docs.oasis-open.org/ws-rx/wsrm/200702
     149: aload_2
     150: invokevirtual #33                 // Method org/apache/cxf/ws/rm/ProtocolVariation.getWSRMNamespace:()Ljava/lang/String;
     153: invokevirtual #210                // Method java/lang/String.equals:(Ljava/lang/Object;)Z
     156: ifeq          179
     159: aload_0
     160: aload         8
     162: aload         9
     164: invokevirtual #234                // Method org/apache/cxf/ws/rm/RMConstants.getTerminateSequenceAction:()Ljava/lang/String;
     167: getstatic     #211                // Field org/apache/cxf/ws/rm/RM11Constants.INSTANCE:Lorg/apache/cxf/ws/rm/RM11Constants;
     170: invokevirtual #235                // Method org/apache/cxf/ws/rm/RM11Constants.getTerminateSequenceResponseAction:()Ljava/lang/String;
     173: invokespecial #232                // Method addAction:(Lorg/apache/cxf/service/model/BindingOperationInfo;Ljava/lang/String;Ljava/lang/String;)V
     176: goto          190
     179: aload_0
     180: aload         8
     182: aload         9
     184: invokevirtual #234                // Method org/apache/cxf/ws/rm/RMConstants.getTerminateSequenceAction:()Ljava/lang/String;
     187: invokespecial #236                // Method addAction:(Lorg/apache/cxf/service/model/BindingOperationInfo;Ljava/lang/String;)V
     190: aload         7
     192: aload         8
     194: invokevirtual #233                // Method org/apache/cxf/binding/soap/model/SoapBindingInfo.addOperation:(Lorg/apache/cxf/service/model/BindingOperationInfo;)V
     197: aload         7
     199: aload         9
     201: invokevirtual #215                // Method org/apache/cxf/ws/rm/RMConstants.getTerminateSequenceAnonymousOperationName:()Ljavax/xml/namespace/QName;
     204: aconst_null
     205: aload         9
     207: invokevirtual #215                // Method org/apache/cxf/ws/rm/RMConstants.getTerminateSequenceAnonymousOperationName:()Ljavax/xml/namespace/QName;
     210: invokevirtual #191                // Method javax/xml/namespace/QName.getLocalPart:()Ljava/lang/String;
     213: invokevirtual #229                // Method org/apache/cxf/binding/soap/model/SoapBindingInfo.buildOperation:(Ljavax/xml/namespace/QName;Ljava/lang/String;Ljava/lang/String;)Lorg/apache/cxf/service/model/BindingOperationInfo;
     216: astore        8
     218: aload_0
     219: aload         8
     221: aload         9
     223: invokevirtual #234                // Method org/apache/cxf/ws/rm/RMConstants.getTerminateSequenceAction:()Ljava/lang/String;
     226: invokespecial #236                // Method addAction:(Lorg/apache/cxf/service/model/BindingOperationInfo;Ljava/lang/String;)V
     229: aload         7
     231: aload         8
     233: invokevirtual #233                // Method org/apache/cxf/binding/soap/model/SoapBindingInfo.addOperation:(Lorg/apache/cxf/service/model/BindingOperationInfo;)V
     236: aload         7
     238: aload         9
     240: invokevirtual #216                // Method org/apache/cxf/ws/rm/RMConstants.getSequenceAckOperationName:()Ljavax/xml/namespace/QName;
     243: aconst_null
     244: aconst_null
     245: invokevirtual #229                // Method org/apache/cxf/binding/soap/model/SoapBindingInfo.buildOperation:(Ljavax/xml/namespace/QName;Ljava/lang/String;Ljava/lang/String;)Lorg/apache/cxf/service/model/BindingOperationInfo;
     248: astore        8
     250: aload_0
     251: aload         8
     253: aload         9
     255: invokevirtual #237                // Method org/apache/cxf/ws/rm/RMConstants.getSequenceAckAction:()Ljava/lang/String;
     258: invokespecial #236                // Method addAction:(Lorg/apache/cxf/service/model/BindingOperationInfo;Ljava/lang/String;)V
     261: aload         7
     263: aload         8
     265: invokevirtual #233                // Method org/apache/cxf/binding/soap/model/SoapBindingInfo.addOperation:(Lorg/apache/cxf/service/model/BindingOperationInfo;)V
     268: aload         7
     270: aload         9
     272: invokevirtual #217                // Method org/apache/cxf/ws/rm/RMConstants.getCloseSequenceOperationName:()Ljavax/xml/namespace/QName;
     275: aconst_null
     276: aconst_null
     277: invokevirtual #229                // Method org/apache/cxf/binding/soap/model/SoapBindingInfo.buildOperation:(Ljavax/xml/namespace/QName;Ljava/lang/String;Ljava/lang/String;)Lorg/apache/cxf/service/model/BindingOperationInfo;
     280: astore        8
     282: ldc           #209                // String http://docs.oasis-open.org/ws-rx/wsrm/200702
     284: aload_2
     285: invokevirtual #33                 // Method org/apache/cxf/ws/rm/ProtocolVariation.getWSRMNamespace:()Ljava/lang/String;
     288: invokevirtual #210                // Method java/lang/String.equals:(Ljava/lang/Object;)Z
     291: ifeq          314
     294: aload_0
     295: aload         8
     297: aload         9
     299: invokevirtual #238                // Method org/apache/cxf/ws/rm/RMConstants.getCloseSequenceAction:()Ljava/lang/String;
     302: getstatic     #211                // Field org/apache/cxf/ws/rm/RM11Constants.INSTANCE:Lorg/apache/cxf/ws/rm/RM11Constants;
     305: invokevirtual #239                // Method org/apache/cxf/ws/rm/RM11Constants.getCloseSequenceResponseAction:()Ljava/lang/String;
     308: invokespecial #232                // Method addAction:(Lorg/apache/cxf/service/model/BindingOperationInfo;Ljava/lang/String;Ljava/lang/String;)V
     311: goto          325
     314: aload_0
     315: aload         8
     317: aload         9
     319: invokevirtual #238                // Method org/apache/cxf/ws/rm/RMConstants.getCloseSequenceAction:()Ljava/lang/String;
     322: invokespecial #236                // Method addAction:(Lorg/apache/cxf/service/model/BindingOperationInfo;Ljava/lang/String;)V
     325: aload         7
     327: aload         8
     329: invokevirtual #233                // Method org/apache/cxf/binding/soap/model/SoapBindingInfo.addOperation:(Lorg/apache/cxf/service/model/BindingOperationInfo;)V
     332: aload         7
     334: aload         9
     336: invokevirtual #223                // Method org/apache/cxf/ws/rm/RMConstants.getAckRequestedOperationName:()Ljavax/xml/namespace/QName;
     339: aconst_null
     340: aconst_null
     341: invokevirtual #229                // Method org/apache/cxf/binding/soap/model/SoapBindingInfo.buildOperation:(Ljavax/xml/namespace/QName;Ljava/lang/String;Ljava/lang/String;)Lorg/apache/cxf/service/model/BindingOperationInfo;
     344: astore        8
     346: aload_0
     347: aload         8
     349: aload         9
     351: invokevirtual #240                // Method org/apache/cxf/ws/rm/RMConstants.getAckRequestedAction:()Ljava/lang/String;
     354: invokespecial #236                // Method addAction:(Lorg/apache/cxf/service/model/BindingOperationInfo;Ljava/lang/String;)V
     357: aload         7
     359: aload         8
     361: invokevirtual #233                // Method org/apache/cxf/binding/soap/model/SoapBindingInfo.addOperation:(Lorg/apache/cxf/service/model/BindingOperationInfo;)V
     364: aload         7
     366: aload         9
     368: invokevirtual #204                // Method org/apache/cxf/ws/rm/RMConstants.getCreateSequenceOnewayOperationName:()Ljavax/xml/namespace/QName;
     371: aload         9
     373: invokevirtual #204                // Method org/apache/cxf/ws/rm/RMConstants.getCreateSequenceOnewayOperationName:()Ljavax/xml/namespace/QName;
     376: invokevirtual #191                // Method javax/xml/namespace/QName.getLocalPart:()Ljava/lang/String;
     379: aconst_null
     380: invokevirtual #229                // Method org/apache/cxf/binding/soap/model/SoapBindingInfo.buildOperation:(Ljavax/xml/namespace/QName;Ljava/lang/String;Ljava/lang/String;)Lorg/apache/cxf/service/model/BindingOperationInfo;
     383: astore        8
     385: aload_0
     386: aload         8
     388: aload         9
     390: invokevirtual #230                // Method org/apache/cxf/ws/rm/RMConstants.getCreateSequenceAction:()Ljava/lang/String;
     393: invokespecial #236                // Method addAction:(Lorg/apache/cxf/service/model/BindingOperationInfo;Ljava/lang/String;)V
     396: aload         7
     398: aload         8
     400: invokevirtual #233                // Method org/apache/cxf/binding/soap/model/SoapBindingInfo.addOperation:(Lorg/apache/cxf/service/model/BindingOperationInfo;)V
     403: aload         7
     405: aload         9
     407: invokevirtual #205                // Method org/apache/cxf/ws/rm/RMConstants.getCreateSequenceResponseOnewayOperationName:()Ljavax/xml/namespace/QName;
     410: aload         9
     412: invokevirtual #205                // Method org/apache/cxf/ws/rm/RMConstants.getCreateSequenceResponseOnewayOperationName:()Ljavax/xml/namespace/QName;
     415: invokevirtual #191                // Method javax/xml/namespace/QName.getLocalPart:()Ljava/lang/String;
     418: aconst_null
     419: invokevirtual #229                // Method org/apache/cxf/binding/soap/model/SoapBindingInfo.buildOperation:(Ljavax/xml/namespace/QName;Ljava/lang/String;Ljava/lang/String;)Lorg/apache/cxf/service/model/BindingOperationInfo;
     422: astore        8
     424: aload_0
     425: aload         8
     427: aload         9
     429: invokevirtual #231                // Method org/apache/cxf/ws/rm/RMConstants.getCreateSequenceResponseAction:()Ljava/lang/String;
     432: invokespecial #236                // Method addAction:(Lorg/apache/cxf/service/model/BindingOperationInfo;Ljava/lang/String;)V
     435: aload         7
     437: aload         8
     439: invokevirtual #233                // Method org/apache/cxf/binding/soap/model/SoapBindingInfo.addOperation:(Lorg/apache/cxf/service/model/BindingOperationInfo;)V
     442: aload_1
     443: aload         7
     445: invokevirtual #241                // Method org/apache/cxf/service/model/ServiceInfo.addBinding:(Lorg/apache/cxf/service/model/BindingInfo;)V
     448: return

  private void addAction(org.apache.cxf.service.model.BindingOperationInfo, java.lang.String);
    Code:
       0: aload_0
       1: aload_1
       2: aload_2
       3: aload_2
       4: invokespecial #232                // Method addAction:(Lorg/apache/cxf/service/model/BindingOperationInfo;Ljava/lang/String;Ljava/lang/String;)V
       7: return

  private void addAction(org.apache.cxf.service.model.BindingOperationInfo, java.lang.String, java.lang.String);
    Code:
       0: new           #242                // class org/apache/cxf/binding/soap/model/SoapOperationInfo
       3: dup
       4: invokespecial #243                // Method org/apache/cxf/binding/soap/model/SoapOperationInfo."<init>":()V
       7: astore        4
       9: aload         4
      11: aload_2
      12: invokevirtual #244                // Method org/apache/cxf/binding/soap/model/SoapOperationInfo.setAction:(Ljava/lang/String;)V
      15: aload_1
      16: aload         4
      18: invokevirtual #245                // Method org/apache/cxf/service/model/BindingOperationInfo.addExtensor:(Ljava/lang/Object;)V
      21: aload_1
      22: invokevirtual #246                // Method org/apache/cxf/service/model/BindingOperationInfo.getOperationInfo:()Lorg/apache/cxf/service/model/OperationInfo;
      25: invokevirtual #247                // Method org/apache/cxf/service/model/OperationInfo.getInput:()Lorg/apache/cxf/service/model/MessageInfo;
      28: astore        5
      30: aload         5
      32: ifnull        44
      35: aload         5
      37: getstatic     #248                // Field org/apache/cxf/ws/addressing/JAXWSAConstants.WSAW_ACTION_QNAME:Ljavax/xml/namespace/QName;
      40: aload_2
      41: invokevirtual #249                // Method org/apache/cxf/service/model/MessageInfo.addExtensionAttribute:(Ljavax/xml/namespace/QName;Ljava/lang/Object;)V
      44: aload_1
      45: invokevirtual #246                // Method org/apache/cxf/service/model/BindingOperationInfo.getOperationInfo:()Lorg/apache/cxf/service/model/OperationInfo;
      48: invokevirtual #250                // Method org/apache/cxf/service/model/OperationInfo.getOutput:()Lorg/apache/cxf/service/model/MessageInfo;
      51: astore        5
      53: aload         5
      55: ifnull        67
      58: aload         5
      60: getstatic     #248                // Field org/apache/cxf/ws/addressing/JAXWSAConstants.WSAW_ACTION_QNAME:Ljavax/xml/namespace/QName;
      63: aload_3
      64: invokevirtual #249                // Method org/apache/cxf/service/model/MessageInfo.addExtensionAttribute:(Ljavax/xml/namespace/QName;Ljava/lang/Object;)V
      67: return

  java.lang.Object getUsingAddressing(org.apache.cxf.service.model.EndpointInfo);
    Code:
       0: aconst_null
       1: aload_1
       2: if_acmpne     7
       5: aconst_null
       6: areturn
       7: aconst_null
       8: astore_2
       9: aload_1
      10: ldc_w         #251                // class javax/wsdl/extensions/ExtensibilityElement
      13: invokevirtual #252                // Method org/apache/cxf/service/model/EndpointInfo.getExtensors:(Ljava/lang/Class;)Ljava/util/List;
      16: astore_3
      17: aload_0
      18: aload_3
      19: invokevirtual #253                // Method getUsingAddressing:(Ljava/util/List;)Ljava/lang/Object;
      22: astore_2
      23: aconst_null
      24: aload_2
      25: if_acmpeq     30
      28: aload_2
      29: areturn
      30: aload_1
      31: invokevirtual #169                // Method org/apache/cxf/service/model/EndpointInfo.getBinding:()Lorg/apache/cxf/service/model/BindingInfo;
      34: ifnull        50
      37: aload_1
      38: invokevirtual #169                // Method org/apache/cxf/service/model/EndpointInfo.getBinding:()Lorg/apache/cxf/service/model/BindingInfo;
      41: ldc_w         #251                // class javax/wsdl/extensions/ExtensibilityElement
      44: invokevirtual #254                // Method org/apache/cxf/service/model/BindingInfo.getExtensors:(Ljava/lang/Class;)Ljava/util/List;
      47: goto          51
      50: aconst_null
      51: astore_3
      52: aload_0
      53: aload_3
      54: invokevirtual #253                // Method getUsingAddressing:(Ljava/util/List;)Ljava/lang/Object;
      57: astore_2
      58: aconst_null
      59: aload_2
      60: if_acmpeq     65
      63: aload_2
      64: areturn
      65: aload_1
      66: invokevirtual #255                // Method org/apache/cxf/service/model/EndpointInfo.getService:()Lorg/apache/cxf/service/model/ServiceInfo;
      69: ifnull        85
      72: aload_1
      73: invokevirtual #255                // Method org/apache/cxf/service/model/EndpointInfo.getService:()Lorg/apache/cxf/service/model/ServiceInfo;
      76: ldc_w         #251                // class javax/wsdl/extensions/ExtensibilityElement
      79: invokevirtual #256                // Method org/apache/cxf/service/model/ServiceInfo.getExtensors:(Ljava/lang/Class;)Ljava/util/List;
      82: goto          86
      85: aconst_null
      86: astore_3
      87: aload_0
      88: aload_3
      89: invokevirtual #253                // Method getUsingAddressing:(Ljava/util/List;)Ljava/lang/Object;
      92: astore_2
      93: aconst_null
      94: aload_2
      95: if_acmpeq     100
      98: aload_2
      99: areturn
     100: aload_2
     101: areturn

  java.lang.Object getUsingAddressing(java.util.List<javax.wsdl.extensions.ExtensibilityElement>);
    Code:
       0: aconst_null
       1: astore_2
       2: aload_1
       3: ifnull        55
       6: aload_1
       7: invokeinterface #257,  1          // InterfaceMethod java/util/List.iterator:()Ljava/util/Iterator;
      12: astore_3
      13: aload_3
      14: invokeinterface #154,  1          // InterfaceMethod java/util/Iterator.hasNext:()Z
      19: ifeq          55
      22: aload_3
      23: invokeinterface #155,  1          // InterfaceMethod java/util/Iterator.next:()Ljava/lang/Object;
      28: checkcast     #251                // class javax/wsdl/extensions/ExtensibilityElement
      31: astore        4
      33: getstatic     #258                // Field org/apache/cxf/ws/addressing/Names.WSAW_USING_ADDRESSING_QNAME:Ljavax/xml/namespace/QName;
      36: aload         4
      38: invokeinterface #259,  1          // InterfaceMethod javax/wsdl/extensions/ExtensibilityElement.getElementType:()Ljavax/xml/namespace/QName;
      43: invokevirtual #260                // Method javax/xml/namespace/QName.equals:(Ljava/lang/Object;)Z
      46: ifeq          52
      49: aload         4
      51: astore_2
      52: goto          13
      55: aload_2
      56: areturn

  void setAplicationEndpoint(org.apache.cxf.endpoint.Endpoint);
    Code:
       0: aload_0
       1: aload_1
       2: putfield      #3                  // Field applicationEndpoint:Lorg/apache/cxf/endpoint/Endpoint;
       5: return

  void setManager(org.apache.cxf.ws.rm.RMManager);
    Code:
       0: aload_0
       1: aload_1
       2: putfield      #2                  // Field manager:Lorg/apache/cxf/ws/rm/RMManager;
       5: return

  void shutdown();
    Code:
       0: aload_0
       1: invokevirtual #261                // Method getDestination:()Lorg/apache/cxf/ws/rm/Destination;
       4: invokevirtual #262                // Method org/apache/cxf/ws/rm/Destination.getAllSequences:()Ljava/util/Collection;
       7: invokeinterface #161,  1          // InterfaceMethod java/util/Collection.iterator:()Ljava/util/Iterator;
      12: astore_1
      13: aload_1
      14: invokeinterface #154,  1          // InterfaceMethod java/util/Iterator.hasNext:()Z
      19: ifeq          43
      22: aload_1
      23: invokeinterface #155,  1          // InterfaceMethod java/util/Iterator.next:()Ljava/lang/Object;
      28: checkcast     #263                // class org/apache/cxf/ws/rm/DestinationSequence
      31: astore_2
      32: aload_2
      33: invokevirtual #264                // Method org/apache/cxf/ws/rm/DestinationSequence.cancelDeferredAcknowledgments:()V
      36: aload_2
      37: invokevirtual #265                // Method org/apache/cxf/ws/rm/DestinationSequence.cancelTermination:()V
      40: goto          13
      43: aload_0
      44: getfield      #2                  // Field manager:Lorg/apache/cxf/ws/rm/RMManager;
      47: invokevirtual #266                // Method org/apache/cxf/ws/rm/RMManager.getSourcePolicy:()Lorg/apache/cxf/ws/rm/manager/SourcePolicyType;
      50: astore_1
      51: aconst_null
      52: astore_2
      53: aconst_null
      54: aload_1
      55: if_acmpeq     63
      58: aload_1
      59: invokevirtual #267                // Method org/apache/cxf/ws/rm/manager/SourcePolicyType.getSequenceTerminationPolicy:()Lorg/apache/cxf/ws/rm/manager/SequenceTerminationPolicyType;
      62: astore_2
      63: aconst_null
      64: aload_2
      65: if_acmpeq     162
      68: aload_2
      69: invokevirtual #268                // Method org/apache/cxf/ws/rm/manager/SequenceTerminationPolicyType.isTerminateOnShutdown:()Z
      72: ifeq          162
      75: aload_0
      76: getfield      #6                  // Field source:Lorg/apache/cxf/ws/rm/Source;
      79: invokevirtual #269                // Method org/apache/cxf/ws/rm/Source.getAllUnacknowledgedSequences:()Ljava/util/Collection;
      82: astore_3
      83: getstatic     #56                 // Field LOG:Ljava/util/logging/Logger;
      86: getstatic     #270                // Field java/util/logging/Level.FINE:Ljava/util/logging/Level;
      89: ldc_w         #271                // String Trying to terminate {0} sequences
      92: aload_3
      93: invokeinterface #272,  1          // InterfaceMethod java/util/Collection.size:()I
      98: invokestatic  #273                // Method java/lang/Integer.valueOf:(I)Ljava/lang/Integer;
     101: invokevirtual #274                // Method java/util/logging/Logger.log:(Ljava/util/logging/Level;Ljava/lang/String;Ljava/lang/Object;)V
     104: aload_3
     105: invokeinterface #161,  1          // InterfaceMethod java/util/Collection.iterator:()Ljava/util/Iterator;
     110: astore        4
     112: aload         4
     114: invokeinterface #154,  1          // InterfaceMethod java/util/Iterator.hasNext:()Z
     119: ifeq          162
     122: aload         4
     124: invokeinterface #155,  1          // InterfaceMethod java/util/Iterator.next:()Ljava/lang/Object;
     129: checkcast     #275                // class org/apache/cxf/ws/rm/SourceSequence
     132: astore        5
     134: aload         5
     136: invokevirtual #276                // Method org/apache/cxf/ws/rm/SourceSequence.isLastMessage:()Z
     139: ifeq          145
     142: goto          154
     145: aload_0
     146: invokevirtual #277                // Method getProxy:()Lorg/apache/cxf/ws/rm/Proxy;
     149: aload         5
     151: invokevirtual #278                // Method org/apache/cxf/ws/rm/Proxy.lastMessage:(Lorg/apache/cxf/ws/rm/SourceSequence;)V
     154: goto          159
     157: astore        6
     159: goto          112
     162: aload_0
     163: invokevirtual #280                // Method getSource:()Lorg/apache/cxf/ws/rm/Source;
     166: invokevirtual #281                // Method org/apache/cxf/ws/rm/Source.getAllSequences:()Ljava/util/Collection;
     169: invokeinterface #161,  1          // InterfaceMethod java/util/Collection.iterator:()Ljava/util/Iterator;
     174: astore_3
     175: aload_3
     176: invokeinterface #154,  1          // InterfaceMethod java/util/Iterator.hasNext:()Z
     181: ifeq          212
     184: aload_3
     185: invokeinterface #155,  1          // InterfaceMethod java/util/Iterator.next:()Ljava/lang/Object;
     190: checkcast     #275                // class org/apache/cxf/ws/rm/SourceSequence
     193: astore        4
     195: aload_0
     196: getfield      #2                  // Field manager:Lorg/apache/cxf/ws/rm/RMManager;
     199: invokevirtual #282                // Method org/apache/cxf/ws/rm/RMManager.getRetransmissionQueue:()Lorg/apache/cxf/ws/rm/RetransmissionQueue;
     202: aload         4
     204: invokeinterface #283,  2          // InterfaceMethod org/apache/cxf/ws/rm/RetransmissionQueue.stop:(Lorg/apache/cxf/ws/rm/SourceSequence;)V
     209: goto          175
     212: return
    Exception table:
       from    to  target type
         134   154   157   Class org/apache/cxf/ws/rm/RMException

  int getProcessingSourceSequenceCount();
    Code:
       0: aload_0
       1: getfield      #6                  // Field source:Lorg/apache/cxf/ws/rm/Source;
       4: ifnull        17
       7: aload_0
       8: getfield      #6                  // Field source:Lorg/apache/cxf/ws/rm/Source;
      11: invokevirtual #284                // Method org/apache/cxf/ws/rm/Source.getProcessingSequenceCount:()I
      14: goto          18
      17: iconst_0
      18: ireturn

  int getCompletedSourceSequenceCount();
    Code:
       0: aload_0
       1: getfield      #6                  // Field source:Lorg/apache/cxf/ws/rm/Source;
       4: ifnull        17
       7: aload_0
       8: getfield      #6                  // Field source:Lorg/apache/cxf/ws/rm/Source;
      11: invokevirtual #285                // Method org/apache/cxf/ws/rm/Source.getCompletedSequenceCount:()I
      14: goto          18
      17: iconst_0
      18: ireturn

  int getProcessingDestinationSequenceCount();
    Code:
       0: aload_0
       1: getfield      #9                  // Field destination:Lorg/apache/cxf/ws/rm/Destination;
       4: ifnull        17
       7: aload_0
       8: getfield      #9                  // Field destination:Lorg/apache/cxf/ws/rm/Destination;
      11: invokevirtual #286                // Method org/apache/cxf/ws/rm/Destination.getProcessingSequenceCount:()I
      14: goto          18
      17: iconst_0
      18: ireturn

  int getCompletedDestinationSequenceCount();
    Code:
       0: aload_0
       1: getfield      #9                  // Field destination:Lorg/apache/cxf/ws/rm/Destination;
       4: ifnull        17
       7: aload_0
       8: getfield      #9                  // Field destination:Lorg/apache/cxf/ws/rm/Destination;
      11: invokevirtual #287                // Method org/apache/cxf/ws/rm/Destination.getCompletedSequenceCount:()I
      14: goto          18
      17: iconst_0
      18: ireturn

  static {};
    Code:
       0: ldc_w         #122                // class org/apache/cxf/ws/rm/RMEndpoint
       3: invokestatic  #288                // Method org/apache/cxf/common/logging/LogUtils.getL7dLogger:(Ljava/lang/Class;)Ljava/util/logging/Logger;
       6: putstatic     #56                 // Field LOG:Ljava/util/logging/Logger;
       9: return
}
