Compiled from "ColumnSchema.kt"
public abstract class org.jetbrains.kotlinx.dataframe.schema.ColumnSchema {
  public org.jetbrains.kotlinx.dataframe.schema.ColumnSchema();
    Code:
       0: aload_0
       1: invokespecial #8                  // Method java/lang/Object."<init>":()V
       4: return

  public abstract org.jetbrains.kotlinx.dataframe.columns.ColumnKind getKind();

  public abstract boolean getNullable();

  public abstract kotlin.reflect.KType getType();

  public boolean equals(java.lang.Object);
    Code:
       0: aload_1
       1: instanceof    #2                  // class org/jetbrains/kotlinx/dataframe/schema/ColumnSchema
       4: ifeq          14
       7: aload_1
       8: checkcast     #2                  // class org/jetbrains/kotlinx/dataframe/schema/ColumnSchema
      11: goto          15
      14: aconst_null
      15: dup
      16: ifnonnull     22
      19: pop
      20: iconst_0
      21: ireturn
      22: astore_2
      23: aload_2
      24: invokevirtual #22                 // Method getKind:()Lorg/jetbrains/kotlinx/dataframe/columns/ColumnKind;
      27: aload_0
      28: invokevirtual #22                 // Method getKind:()Lorg/jetbrains/kotlinx/dataframe/columns/ColumnKind;
      31: if_acmpeq     36
      34: iconst_0
      35: ireturn
      36: aload_2
      37: invokevirtual #24                 // Method getNullable:()Z
      40: aload_0
      41: invokevirtual #24                 // Method getNullable:()Z
      44: if_icmpeq     49
      47: iconst_0
      48: ireturn
      49: aload_0
      50: astore_3
      51: aload_3
      52: instanceof    #26                 // class org/jetbrains/kotlinx/dataframe/schema/ColumnSchema$Value
      55: ifeq          73
      58: aload_0
      59: invokevirtual #28                 // Method getType:()Lkotlin/reflect/KType;
      62: aload_2
      63: checkcast     #26                 // class org/jetbrains/kotlinx/dataframe/schema/ColumnSchema$Value
      66: invokevirtual #29                 // Method org/jetbrains/kotlinx/dataframe/schema/ColumnSchema$Value.getType:()Lkotlin/reflect/KType;
      69: invokestatic  #35                 // Method kotlin/jvm/internal/Intrinsics.areEqual:(Ljava/lang/Object;Ljava/lang/Object;)Z
      72: ireturn
      73: aload_3
      74: instanceof    #37                 // class org/jetbrains/kotlinx/dataframe/schema/ColumnSchema$Group
      77: ifeq          98
      80: aload_0
      81: checkcast     #37                 // class org/jetbrains/kotlinx/dataframe/schema/ColumnSchema$Group
      84: invokevirtual #41                 // Method org/jetbrains/kotlinx/dataframe/schema/ColumnSchema$Group.getSchema:()Lorg/jetbrains/kotlinx/dataframe/schema/DataFrameSchema;
      87: aload_2
      88: checkcast     #37                 // class org/jetbrains/kotlinx/dataframe/schema/ColumnSchema$Group
      91: invokevirtual #41                 // Method org/jetbrains/kotlinx/dataframe/schema/ColumnSchema$Group.getSchema:()Lorg/jetbrains/kotlinx/dataframe/schema/DataFrameSchema;
      94: invokestatic  #35                 // Method kotlin/jvm/internal/Intrinsics.areEqual:(Ljava/lang/Object;Ljava/lang/Object;)Z
      97: ireturn
      98: aload_3
      99: instanceof    #43                 // class org/jetbrains/kotlinx/dataframe/schema/ColumnSchema$Frame
     102: ifeq          123
     105: aload_0
     106: checkcast     #43                 // class org/jetbrains/kotlinx/dataframe/schema/ColumnSchema$Frame
     109: invokevirtual #44                 // Method org/jetbrains/kotlinx/dataframe/schema/ColumnSchema$Frame.getSchema:()Lorg/jetbrains/kotlinx/dataframe/schema/DataFrameSchema;
     112: aload_2
     113: checkcast     #43                 // class org/jetbrains/kotlinx/dataframe/schema/ColumnSchema$Frame
     116: invokevirtual #44                 // Method org/jetbrains/kotlinx/dataframe/schema/ColumnSchema$Frame.getSchema:()Lorg/jetbrains/kotlinx/dataframe/schema/DataFrameSchema;
     119: invokestatic  #35                 // Method kotlin/jvm/internal/Intrinsics.areEqual:(Ljava/lang/Object;Ljava/lang/Object;)Z
     122: ireturn
     123: new           #46                 // class kotlin/NotImplementedError
     126: dup
     127: aconst_null
     128: iconst_1
     129: aconst_null
     130: invokespecial #49                 // Method kotlin/NotImplementedError."<init>":(Ljava/lang/String;ILkotlin/jvm/internal/DefaultConstructorMarker;)V
     133: athrow

  public final org.jetbrains.kotlinx.dataframe.schema.CompareResult compare(org.jetbrains.kotlinx.dataframe.schema.ColumnSchema);
    Code:
       0: aload_1
       1: ldc           #55                 // String other
       3: invokestatic  #59                 // Method kotlin/jvm/internal/Intrinsics.checkNotNullParameter:(Ljava/lang/Object;Ljava/lang/String;)V
       6: aload_0
       7: invokevirtual #22                 // Method getKind:()Lorg/jetbrains/kotlinx/dataframe/columns/ColumnKind;
      10: aload_1
      11: invokevirtual #22                 // Method getKind:()Lorg/jetbrains/kotlinx/dataframe/columns/ColumnKind;
      14: if_acmpeq     21
      17: getstatic     #65                 // Field org/jetbrains/kotlinx/dataframe/schema/CompareResult.None:Lorg/jetbrains/kotlinx/dataframe/schema/CompareResult;
      20: areturn
      21: aload_0
      22: aload_1
      23: if_acmpne     30
      26: getstatic     #68                 // Field org/jetbrains/kotlinx/dataframe/schema/CompareResult.Equals:Lorg/jetbrains/kotlinx/dataframe/schema/CompareResult;
      29: areturn
      30: aload_0
      31: astore_2
      32: aload_2
      33: instanceof    #26                 // class org/jetbrains/kotlinx/dataframe/schema/ColumnSchema$Value
      36: ifeq          53
      39: aload_0
      40: checkcast     #26                 // class org/jetbrains/kotlinx/dataframe/schema/ColumnSchema$Value
      43: aload_1
      44: checkcast     #26                 // class org/jetbrains/kotlinx/dataframe/schema/ColumnSchema$Value
      47: invokevirtual #71                 // Method org/jetbrains/kotlinx/dataframe/schema/ColumnSchema$Value.compare:(Lorg/jetbrains/kotlinx/dataframe/schema/ColumnSchema$Value;)Lorg/jetbrains/kotlinx/dataframe/schema/CompareResult;
      50: goto          106
      53: aload_2
      54: instanceof    #37                 // class org/jetbrains/kotlinx/dataframe/schema/ColumnSchema$Group
      57: ifeq          74
      60: aload_0
      61: checkcast     #37                 // class org/jetbrains/kotlinx/dataframe/schema/ColumnSchema$Group
      64: aload_1
      65: checkcast     #37                 // class org/jetbrains/kotlinx/dataframe/schema/ColumnSchema$Group
      68: invokevirtual #74                 // Method org/jetbrains/kotlinx/dataframe/schema/ColumnSchema$Group.compare:(Lorg/jetbrains/kotlinx/dataframe/schema/ColumnSchema$Group;)Lorg/jetbrains/kotlinx/dataframe/schema/CompareResult;
      71: goto          106
      74: aload_2
      75: instanceof    #43                 // class org/jetbrains/kotlinx/dataframe/schema/ColumnSchema$Frame
      78: ifeq          95
      81: aload_0
      82: checkcast     #43                 // class org/jetbrains/kotlinx/dataframe/schema/ColumnSchema$Frame
      85: aload_1
      86: checkcast     #43                 // class org/jetbrains/kotlinx/dataframe/schema/ColumnSchema$Frame
      89: invokevirtual #77                 // Method org/jetbrains/kotlinx/dataframe/schema/ColumnSchema$Frame.compare:(Lorg/jetbrains/kotlinx/dataframe/schema/ColumnSchema$Frame;)Lorg/jetbrains/kotlinx/dataframe/schema/CompareResult;
      92: goto          106
      95: new           #46                 // class kotlin/NotImplementedError
      98: dup
      99: aconst_null
     100: iconst_1
     101: aconst_null
     102: invokespecial #49                 // Method kotlin/NotImplementedError."<init>":(Ljava/lang/String;ILkotlin/jvm/internal/DefaultConstructorMarker;)V
     105: athrow
     106: areturn
}
