Compiled from "EsApmDB.kt"
public final class kr.jadekim.jext.apm.es.exposed.EsApmDBKt {
  public static final kr.jadekim.jext.exposed.ReadDB tracingApm(kr.jadekim.jext.exposed.ReadDB);
    Code:
       0: aload_0
       1: ldc           #9                  // String <this>
       3: invokestatic  #15                 // Method kotlin/jvm/internal/Intrinsics.checkNotNullParameter:(Ljava/lang/Object;Ljava/lang/String;)V
       6: new           #17                 // class kr/jadekim/jext/apm/es/exposed/ESReadDB
       9: dup
      10: aload_0
      11: invokespecial #21                 // Method kr/jadekim/jext/apm/es/exposed/ESReadDB."<init>":(Lkr/jadekim/jext/exposed/ReadDB;)V
      14: checkcast     #23                 // class kr/jadekim/jext/exposed/ReadDB
      17: areturn

  public static final kr.jadekim.jext.exposed.CrudDB tracingApm(kr.jadekim.jext.exposed.CrudDB);
    Code:
       0: aload_0
       1: ldc           #9                  // String <this>
       3: invokestatic  #15                 // Method kotlin/jvm/internal/Intrinsics.checkNotNullParameter:(Ljava/lang/Object;Ljava/lang/String;)V
       6: new           #28                 // class kr/jadekim/jext/apm/es/exposed/ESCrudDB
       9: dup
      10: aload_0
      11: invokespecial #31                 // Method kr/jadekim/jext/apm/es/exposed/ESCrudDB."<init>":(Lkr/jadekim/jext/exposed/CrudDB;)V
      14: checkcast     #33                 // class kr/jadekim/jext/exposed/CrudDB
      17: areturn
}
