Compiled from "AllLogRule.java"
public class org.xwiki.test.AllLogRule$LogStatement extends org.junit.runners.model.Statement {
  private final org.junit.runners.model.Statement statement;

  final org.xwiki.test.AllLogRule this$0;

  public org.xwiki.test.AllLogRule$LogStatement(org.xwiki.test.AllLogRule, org.junit.runners.model.Statement);
    Code:
       0: aload_0
       1: aload_1
       2: putfield      #1                  // Field this$0:Lorg/xwiki/test/AllLogRule;
       5: aload_0
       6: invokespecial #2                  // Method org/junit/runners/model/Statement."<init>":()V
       9: aload_0
      10: aload_2
      11: putfield      #3                  // Field statement:Lorg/junit/runners/model/Statement;
      14: return

  public void evaluate() throws java.lang.Throwable;
    Code:
       0: aload_0
       1: invokespecial #4                  // Method before:()V
       4: iconst_1
       5: istore_1
       6: aload_0
       7: getfield      #3                  // Field statement:Lorg/junit/runners/model/Statement;
      10: invokevirtual #5                  // Method org/junit/runners/model/Statement.evaluate:()V
      13: aload_0
      14: iload_1
      15: invokespecial #6                  // Method after:(Z)V
      18: goto          34
      21: astore_2
      22: iconst_0
      23: istore_1
      24: aload_2
      25: athrow
      26: astore_3
      27: aload_0
      28: iload_1
      29: invokespecial #6                  // Method after:(Z)V
      32: aload_3
      33: athrow
      34: return
    Exception table:
       from    to  target type
           6    13    21   Class java/lang/Throwable
           6    13    26   any
          21    27    26   any

  private void before() throws java.lang.Throwable;
    Code:
       0: aload_0
       1: getfield      #1                  // Field this$0:Lorg/xwiki/test/AllLogRule;
       4: invokestatic  #8                  // Method org/xwiki/test/AllLogRule.access$000:(Lorg/xwiki/test/AllLogRule;)V
       7: aload_0
       8: getfield      #1                  // Field this$0:Lorg/xwiki/test/AllLogRule;
      11: invokestatic  #9                  // Method org/xwiki/test/AllLogRule.access$100:(Lorg/xwiki/test/AllLogRule;)Lch/qos/logback/core/read/ListAppender;
      14: invokevirtual #10                 // Method ch/qos/logback/core/read/ListAppender.start:()V
      17: return

  private void after(boolean) throws java.lang.Throwable;
    Code:
       0: aload_0
       1: getfield      #1                  // Field this$0:Lorg/xwiki/test/AllLogRule;
       4: invokestatic  #9                  // Method org/xwiki/test/AllLogRule.access$100:(Lorg/xwiki/test/AllLogRule;)Lch/qos/logback/core/read/ListAppender;
       7: invokevirtual #11                 // Method ch/qos/logback/core/read/ListAppender.stop:()V
      10: aload_0
      11: getfield      #1                  // Field this$0:Lorg/xwiki/test/AllLogRule;
      14: iload_1
      15: invokestatic  #12                 // Method org/xwiki/test/AllLogRule.access$200:(Lorg/xwiki/test/AllLogRule;Z)V
      18: return
}
