Compiled from "DecimalNode.java"
public class org.apache.jena.tdb.store.DecimalNode {
  java.math.BigDecimal decimal;

  static final int SCALE_LEN;

  static final int VALUE_LEN;

  static final int ENC_LEN;

  static final long MAX_VALUE;

  static final long MIN_VALUE;

  static final int MAX_SCALE;

  static final int MIN_SCALE;

  static final java.math.BigInteger MAX_I;

  static final java.math.BigInteger MIN_I;

  private static int SCALE_LO;

  private static int SCALE_HI;

  private static int VALUE_LO;

  private static int VALUE_HI;

  private int scale;

  private long value;

  public static org.apache.jena.tdb.store.DecimalNode valueOf(java.math.BigDecimal);
    Code:
       0: aload_0
       1: invokevirtual #2                  // Method java/math/BigDecimal.scale:()I
       4: istore_1
       5: aload_0
       6: invokevirtual #3                  // Method java/math/BigDecimal.unscaledValue:()Ljava/math/BigInteger;
       9: astore_2
      10: aload_2
      11: getstatic     #4                  // Field MAX_I:Ljava/math/BigInteger;
      14: invokevirtual #5                  // Method java/math/BigInteger.compareTo:(Ljava/math/BigInteger;)I
      17: ifgt          30
      20: aload_2
      21: getstatic     #6                  // Field MIN_I:Ljava/math/BigInteger;
      24: invokevirtual #5                  // Method java/math/BigInteger.compareTo:(Ljava/math/BigInteger;)I
      27: ifge          32
      30: aconst_null
      31: areturn
      32: aload_2
      33: invokevirtual #7                  // Method java/math/BigInteger.longValue:()J
      36: iload_1
      37: invokestatic  #8                  // Method valueOf:(JI)Lorg/apache/jena/tdb/store/DecimalNode;
      40: areturn

  public static org.apache.jena.tdb.store.DecimalNode valueOf(long, int);
    Code:
       0: iload_2
       1: bipush        -128
       3: if_icmplt     12
       6: iload_2
       7: bipush        127
       9: if_icmple     14
      12: aconst_null
      13: areturn
      14: lload_0
      15: ldc2_w        #9                  // long -140737488355328l
      18: lcmp
      19: iflt          30
      22: lload_0
      23: ldc2_w        #11                 // long 140737488355327l
      26: lcmp
      27: ifle          32
      30: aconst_null
      31: areturn
      32: new           #1                  // class org/apache/jena/tdb/store/DecimalNode
      35: dup
      36: lload_0
      37: iload_2
      38: invokespecial #13                 // Method "<init>":(JI)V
      41: areturn

  private org.apache.jena.tdb.store.DecimalNode(long, int);
    Code:
       0: aload_0
       1: invokespecial #14                 // Method java/lang/Object."<init>":()V
       4: aload_0
       5: aconst_null
       6: putfield      #15                 // Field decimal:Ljava/math/BigDecimal;
       9: aload_0
      10: iload_3
      11: putfield      #16                 // Field scale:I
      14: aload_0
      15: lload_1
      16: putfield      #17                 // Field value:J
      19: return

  public long pack();
    Code:
       0: aload_0
       1: getfield      #17                 // Field value:J
       4: aload_0
       5: getfield      #16                 // Field scale:I
       8: invokestatic  #18                 // Method pack:(JI)J
      11: lreturn

  public static long pack(long, int);
    Code:
       0: lconst_0
       1: ldc2_w        #20                 // long 2l
       4: bipush        56
       6: bipush        64
       8: invokestatic  #23                 // Method org/apache/jena/atlas/lib/BitsLong.pack:(JJII)J
      11: lstore_3
      12: lload_3
      13: iload_2
      14: i2l
      15: getstatic     #24                 // Field SCALE_LO:I
      18: getstatic     #25                 // Field SCALE_HI:I
      21: invokestatic  #23                 // Method org/apache/jena/atlas/lib/BitsLong.pack:(JJII)J
      24: lstore_3
      25: lload_3
      26: lload_0
      27: getstatic     #26                 // Field VALUE_LO:I
      30: getstatic     #27                 // Field VALUE_HI:I
      33: invokestatic  #23                 // Method org/apache/jena/atlas/lib/BitsLong.pack:(JJII)J
      36: lstore_3
      37: lload_3
      38: lreturn

  public static org.apache.jena.tdb.store.DecimalNode unpack(long);
    Code:
       0: lload_0
       1: getstatic     #24                 // Field SCALE_LO:I
       4: getstatic     #25                 // Field SCALE_HI:I
       7: invokestatic  #28                 // Method org/apache/jena/atlas/lib/BitsLong.unpack:(JII)J
      10: l2i
      11: istore_2
      12: lload_0
      13: getstatic     #26                 // Field VALUE_LO:I
      16: getstatic     #27                 // Field VALUE_HI:I
      19: invokestatic  #28                 // Method org/apache/jena/atlas/lib/BitsLong.unpack:(JII)J
      22: lstore_3
      23: new           #1                  // class org/apache/jena/tdb/store/DecimalNode
      26: dup
      27: lload_3
      28: iload_2
      29: invokespecial #13                 // Method "<init>":(JI)V
      32: areturn

  public static java.math.BigDecimal unpackAsBigDecimal(long);
    Code:
       0: lload_0
       1: getstatic     #24                 // Field SCALE_LO:I
       4: getstatic     #25                 // Field SCALE_HI:I
       7: invokestatic  #28                 // Method org/apache/jena/atlas/lib/BitsLong.unpack:(JII)J
      10: l2i
      11: istore_2
      12: lload_0
      13: getstatic     #26                 // Field VALUE_LO:I
      16: getstatic     #27                 // Field VALUE_HI:I
      19: invokestatic  #28                 // Method org/apache/jena/atlas/lib/BitsLong.unpack:(JII)J
      22: lstore_3
      23: lload_3
      24: getstatic     #27                 // Field VALUE_HI:I
      27: iconst_1
      28: isub
      29: invokestatic  #29                 // Method org/apache/jena/atlas/lib/BitsLong.isSet:(JI)Z
      32: ifeq          45
      35: lload_3
      36: ldc2_w        #30                 // long -1l
      39: getstatic     #27                 // Field VALUE_HI:I
      42: lshl
      43: lor
      44: lstore_3
      45: lload_3
      46: iload_2
      47: invokestatic  #32                 // Method java/math/BigDecimal.valueOf:(JI)Ljava/math/BigDecimal;
      50: areturn

  public java.math.BigDecimal get();
    Code:
       0: aload_0
       1: getfield      #15                 // Field decimal:Ljava/math/BigDecimal;
       4: ifnonnull     22
       7: aload_0
       8: aload_0
       9: getfield      #17                 // Field value:J
      12: aload_0
      13: getfield      #16                 // Field scale:I
      16: invokestatic  #32                 // Method java/math/BigDecimal.valueOf:(JI)Ljava/math/BigDecimal;
      19: putfield      #15                 // Field decimal:Ljava/math/BigDecimal;
      22: aload_0
      23: getfield      #15                 // Field decimal:Ljava/math/BigDecimal;
      26: areturn

  public java.lang.String toString();
    Code:
       0: aload_0
       1: invokevirtual #33                 // Method get:()Ljava/math/BigDecimal;
       4: invokevirtual #34                 // Method java/math/BigDecimal.toPlainString:()Ljava/lang/String;
       7: areturn

  public int getScale();
    Code:
       0: aload_0
       1: getfield      #16                 // Field scale:I
       4: ireturn

  public long getValue();
    Code:
       0: aload_0
       1: getfield      #17                 // Field value:J
       4: lreturn

  static {};
    Code:
       0: ldc2_w        #11                 // long 140737488355327l
       3: invokestatic  #35                 // Method java/math/BigInteger.valueOf:(J)Ljava/math/BigInteger;
       6: putstatic     #4                  // Field MAX_I:Ljava/math/BigInteger;
       9: ldc2_w        #9                  // long -140737488355328l
      12: invokestatic  #35                 // Method java/math/BigInteger.valueOf:(J)Ljava/math/BigInteger;
      15: putstatic     #6                  // Field MIN_I:Ljava/math/BigInteger;
      18: bipush        48
      20: putstatic     #24                 // Field SCALE_LO:I
      23: bipush        56
      25: putstatic     #25                 // Field SCALE_HI:I
      28: iconst_0
      29: putstatic     #26                 // Field VALUE_LO:I
      32: getstatic     #26                 // Field VALUE_LO:I
      35: bipush        48
      37: iadd
      38: putstatic     #27                 // Field VALUE_HI:I
      41: return
}
