Compiled from "NodeId.java"
public final class org.apache.jena.tdb.store.NodeId {
  public static final org.apache.jena.tdb.store.NodeId NodeDoesNotExist;

  public static final org.apache.jena.tdb.store.NodeId NodeIdAny;

  private static final boolean enableInlineLiterals;

  public static final int SIZE;

  final long value;

  public static final int NONE;

  public static final int INTEGER;

  public static final int DECIMAL;

  public static final int DATE;

  public static final int DATETIME;

  public static final int BOOLEAN;

  public static final int SHORT_STRING;

  public static final int SPECIAL;

  private static org.apache.jena.datatypes.RDFDatatype[] datatypes;

  public static org.apache.jena.tdb.store.NodeId create(long);
    Code:
       0: lload_0
       1: getstatic     #2                  // Field NodeDoesNotExist:Lorg/apache/jena/tdb/store/NodeId;
       4: getfield      #3                  // Field value:J
       7: lcmp
       8: ifne          15
      11: getstatic     #2                  // Field NodeDoesNotExist:Lorg/apache/jena/tdb/store/NodeId;
      14: areturn
      15: lload_0
      16: getstatic     #4                  // Field NodeIdAny:Lorg/apache/jena/tdb/store/NodeId;
      19: getfield      #3                  // Field value:J
      22: lcmp
      23: ifne          30
      26: getstatic     #4                  // Field NodeIdAny:Lorg/apache/jena/tdb/store/NodeId;
      29: areturn
      30: new           #5                  // class org/apache/jena/tdb/store/NodeId
      33: dup
      34: lload_0
      35: invokespecial #6                  // Method "<init>":(J)V
      38: areturn

  public static org.apache.jena.tdb.store.NodeId create(byte[]);
    Code:
       0: aload_0
       1: iconst_0
       2: invokestatic  #7                  // Method create:([BI)Lorg/apache/jena/tdb/store/NodeId;
       5: areturn

  public static org.apache.jena.tdb.store.NodeId create(java.nio.ByteBuffer);
    Code:
       0: aload_0
       1: iconst_0
       2: invokestatic  #8                  // Method create:(Ljava/nio/ByteBuffer;I)Lorg/apache/jena/tdb/store/NodeId;
       5: areturn

  public static org.apache.jena.tdb.store.NodeId create(byte[], int);
    Code:
       0: aload_0
       1: iload_1
       2: invokestatic  #9                  // Method org/apache/jena/atlas/lib/Bytes.getLong:([BI)J
       5: lstore_2
       6: lload_2
       7: invokestatic  #10                 // Method create:(J)Lorg/apache/jena/tdb/store/NodeId;
      10: areturn

  public static org.apache.jena.tdb.store.NodeId create(java.nio.ByteBuffer, int);
    Code:
       0: aload_0
       1: iload_1
       2: invokevirtual #11                 // Method java/nio/ByteBuffer.getLong:(I)J
       5: lstore_2
       6: lload_2
       7: invokestatic  #10                 // Method create:(J)Lorg/apache/jena/tdb/store/NodeId;
      10: areturn

  public org.apache.jena.tdb.store.NodeId(long);
    Code:
       0: aload_0
       1: invokespecial #12                 // Method java/lang/Object."<init>":()V
       4: aload_0
       5: lload_1
       6: putfield      #3                  // Field value:J
       9: return

  public void toByteBuffer(java.nio.ByteBuffer, int);
    Code:
       0: aload_1
       1: iload_2
       2: aload_0
       3: getfield      #3                  // Field value:J
       6: invokevirtual #13                 // Method java/nio/ByteBuffer.putLong:(IJ)Ljava/nio/ByteBuffer;
       9: pop
      10: return

  public void toBytes(byte[], int);
    Code:
       0: aload_0
       1: getfield      #3                  // Field value:J
       4: aload_1
       5: iload_2
       6: invokestatic  #14                 // Method org/apache/jena/atlas/lib/Bytes.setLong:(J[BI)V
       9: return

  public boolean isDirect();
    Code:
       0: aload_0
       1: invokevirtual #15                 // Method type:()I
       4: ifeq          21
       7: aload_0
       8: invokevirtual #15                 // Method type:()I
      11: sipush        255
      14: if_icmpeq     21
      17: iconst_1
      18: goto          22
      21: iconst_0
      22: ireturn

  public int type();
    Code:
       0: aload_0
       1: getfield      #3                  // Field value:J
       4: bipush        56
       6: bipush        64
       8: invokestatic  #16                 // Method org/apache/jena/atlas/lib/BitsLong.unpack:(JII)J
      11: l2i
      12: ireturn

  static long setType(long, int);
    Code:
       0: lload_0
       1: iload_2
       2: i2l
       3: bipush        56
       5: bipush        64
       7: invokestatic  #17                 // Method org/apache/jena/atlas/lib/BitsLong.pack:(JJII)J
      10: lreturn

  public long getId();
    Code:
       0: aload_0
       1: getfield      #3                  // Field value:J
       4: lreturn

  public int hashCode();
    Code:
       0: aload_0
       1: getfield      #3                  // Field value:J
       4: l2i
       5: aload_0
       6: getfield      #3                  // Field value:J
       9: bipush        32
      11: lshr
      12: l2i
      13: ixor
      14: ireturn

  public boolean equals(java.lang.Object);
    Code:
       0: aload_0
       1: aload_1
       2: if_acmpne     7
       5: iconst_1
       6: ireturn
       7: aload_1
       8: instanceof    #5                  // class org/apache/jena/tdb/store/NodeId
      11: ifne          16
      14: iconst_0
      15: ireturn
      16: aload_0
      17: getfield      #3                  // Field value:J
      20: aload_1
      21: checkcast     #5                  // class org/apache/jena/tdb/store/NodeId
      24: getfield      #3                  // Field value:J
      27: lcmp
      28: ifne          35
      31: iconst_1
      32: goto          36
      35: iconst_0
      36: ireturn

  public java.lang.String toString();
    Code:
       0: aload_0
       1: getstatic     #2                  // Field NodeDoesNotExist:Lorg/apache/jena/tdb/store/NodeId;
       4: if_acmpne     10
       7: ldc           #18                 // String [DoesNotExist]
       9: areturn
      10: aload_0
      11: getstatic     #4                  // Field NodeIdAny:Lorg/apache/jena/tdb/store/NodeId;
      14: if_acmpne     20
      17: ldc           #19                 // String [Any]
      19: areturn
      20: ldc           #20                 // String [%016X]
      22: iconst_1
      23: anewarray     #21                 // class java/lang/Object
      26: dup
      27: iconst_0
      28: aload_0
      29: getfield      #3                  // Field value:J
      32: invokestatic  #22                 // Method java/lang/Long.valueOf:(J)Ljava/lang/Long;
      35: aastore
      36: invokestatic  #23                 // Method java/lang/String.format:(Ljava/lang/String;[Ljava/lang/Object;)Ljava/lang/String;
      39: areturn

  public static org.apache.jena.tdb.store.NodeId inline(org.apache.jena.graph.Node);
    Code:
       0: aload_0
       1: ifnonnull     30
       4: ldc           #5                  // class org/apache/jena/tdb/store/NodeId
       6: new           #24                 // class java/lang/StringBuilder
       9: dup
      10: invokespecial #25                 // Method java/lang/StringBuilder."<init>":()V
      13: ldc           #26                 // String Null node:
      15: invokevirtual #27                 // Method java/lang/StringBuilder.append:(Ljava/lang/String;)Ljava/lang/StringBuilder;
      18: aload_0
      19: invokevirtual #28                 // Method java/lang/StringBuilder.append:(Ljava/lang/Object;)Ljava/lang/StringBuilder;
      22: invokevirtual #29                 // Method java/lang/StringBuilder.toString:()Ljava/lang/String;
      25: invokestatic  #30                 // Method org/apache/jena/atlas/logging/Log.warn:(Ljava/lang/Class;Ljava/lang/String;)V
      28: aconst_null
      29: areturn
      30: getstatic     #31                 // Field enableInlineLiterals:Z
      33: ifne          38
      36: aconst_null
      37: areturn
      38: aload_0
      39: invokevirtual #32                 // Method org/apache/jena/graph/Node.isLiteral:()Z
      42: ifne          47
      45: aconst_null
      46: areturn
      47: aload_0
      48: invokestatic  #33                 // Method org/apache/jena/sparql/util/NodeUtils.isSimpleString:(Lorg/apache/jena/graph/Node;)Z
      51: ifne          61
      54: aload_0
      55: invokestatic  #34                 // Method org/apache/jena/sparql/util/NodeUtils.isLangString:(Lorg/apache/jena/graph/Node;)Z
      58: ifeq          63
      61: aconst_null
      62: areturn
      63: aload_0
      64: invokestatic  #35                 // Method inline$:(Lorg/apache/jena/graph/Node;)Lorg/apache/jena/tdb/store/NodeId;
      67: areturn
      68: astore_1
      69: ldc           #5                  // class org/apache/jena/tdb/store/NodeId
      71: new           #24                 // class java/lang/StringBuilder
      74: dup
      75: invokespecial #25                 // Method java/lang/StringBuilder."<init>":()V
      78: ldc           #37                 // String Failed to process
      80: invokevirtual #27                 // Method java/lang/StringBuilder.append:(Ljava/lang/String;)Ljava/lang/StringBuilder;
      83: aload_0
      84: invokevirtual #28                 // Method java/lang/StringBuilder.append:(Ljava/lang/Object;)Ljava/lang/StringBuilder;
      87: invokevirtual #29                 // Method java/lang/StringBuilder.toString:()Ljava/lang/String;
      90: invokestatic  #30                 // Method org/apache/jena/atlas/logging/Log.warn:(Ljava/lang/Class;Ljava/lang/String;)V
      93: aconst_null
      94: areturn
    Exception table:
       from    to  target type
          63    67    68   Class java/lang/Throwable

  public static boolean hasInlineDatatype(org.apache.jena.graph.Node);
    Code:
       0: aload_0
       1: invokevirtual #38                 // Method org/apache/jena/graph/Node.getLiteralDatatype:()Lorg/apache/jena/datatypes/RDFDatatype;
       4: astore_1
       5: getstatic     #39                 // Field datatypes:[Lorg/apache/jena/datatypes/RDFDatatype;
       8: astore_2
       9: aload_2
      10: arraylength
      11: istore_3
      12: iconst_0
      13: istore        4
      15: iload         4
      17: iload_3
      18: if_icmpge     44
      21: aload_2
      22: iload         4
      24: aaload
      25: astore        5
      27: aload         5
      29: aload_1
      30: invokevirtual #40                 // Method java/lang/Object.equals:(Ljava/lang/Object;)Z
      33: ifeq          38
      36: iconst_1
      37: ireturn
      38: iinc          4, 1
      41: goto          15
      44: iconst_0
      45: ireturn

  private static org.apache.jena.tdb.store.NodeId inline$(org.apache.jena.graph.Node);
    Code:
       0: aload_0
       1: invokevirtual #41                 // Method org/apache/jena/graph/Node.getLiteral:()Lorg/apache/jena/graph/impl/LiteralLabel;
       4: astore_1
       5: aload_0
       6: invokevirtual #38                 // Method org/apache/jena/graph/Node.getLiteralDatatype:()Lorg/apache/jena/datatypes/RDFDatatype;
       9: getstatic     #42                 // Field org/apache/jena/datatypes/xsd/XSDDatatype.XSDdecimal:Lorg/apache/jena/datatypes/xsd/XSDDatatype;
      12: invokevirtual #40                 // Method java/lang/Object.equals:(Ljava/lang/Object;)Z
      15: ifeq          70
      18: getstatic     #42                 // Field org/apache/jena/datatypes/xsd/XSDDatatype.XSDdecimal:Lorg/apache/jena/datatypes/xsd/XSDDatatype;
      21: aload_1
      22: invokevirtual #43                 // Method org/apache/jena/datatypes/xsd/XSDDatatype.isValidLiteral:(Lorg/apache/jena/graph/impl/LiteralLabel;)Z
      25: ifne          30
      28: aconst_null
      29: areturn
      30: new           #44                 // class java/math/BigDecimal
      33: dup
      34: aload_1
      35: invokeinterface #45,  1           // InterfaceMethod org/apache/jena/graph/impl/LiteralLabel.getLexicalForm:()Ljava/lang/String;
      40: invokevirtual #46                 // Method java/lang/String.trim:()Ljava/lang/String;
      43: invokespecial #47                 // Method java/math/BigDecimal."<init>":(Ljava/lang/String;)V
      46: astore_2
      47: aload_2
      48: invokestatic  #48                 // Method org/apache/jena/tdb/store/DecimalNode.valueOf:(Ljava/math/BigDecimal;)Lorg/apache/jena/tdb/store/DecimalNode;
      51: astore_3
      52: aload_3
      53: ifnull        68
      56: new           #5                  // class org/apache/jena/tdb/store/NodeId
      59: dup
      60: aload_3
      61: invokevirtual #49                 // Method org/apache/jena/tdb/store/DecimalNode.pack:()J
      64: invokespecial #6                  // Method "<init>":(J)V
      67: areturn
      68: aconst_null
      69: areturn
      70: getstatic     #50                 // Field org/apache/jena/datatypes/xsd/XSDDatatype.XSDinteger:Lorg/apache/jena/datatypes/xsd/XSDDatatype;
      73: aload_1
      74: invokevirtual #43                 // Method org/apache/jena/datatypes/xsd/XSDDatatype.isValidLiteral:(Lorg/apache/jena/graph/impl/LiteralLabel;)Z
      77: ifeq          136
      80: aload_1
      81: invokeinterface #45,  1           // InterfaceMethod org/apache/jena/graph/impl/LiteralLabel.getLexicalForm:()Ljava/lang/String;
      86: invokevirtual #51                 // Method java/lang/String.length:()I
      89: bipush        19
      91: if_icmple     96
      94: aconst_null
      95: areturn
      96: aload_1
      97: invokeinterface #52,  1           // InterfaceMethod org/apache/jena/graph/impl/LiteralLabel.getValue:()Ljava/lang/Object;
     102: checkcast     #53                 // class java/lang/Number
     105: invokevirtual #54                 // Method java/lang/Number.longValue:()J
     108: lstore_2
     109: lload_2
     110: invokestatic  #55                 // Method org/apache/jena/tdb/store/IntegerNode.pack:(J)J
     113: lstore_2
     114: lload_2
     115: ldc2_w        #56                 // long -1l
     118: lcmp
     119: ifeq          131
     122: new           #5                  // class org/apache/jena/tdb/store/NodeId
     125: dup
     126: lload_2
     127: invokespecial #6                  // Method "<init>":(J)V
     130: areturn
     131: aconst_null
     132: areturn
     133: astore_2
     134: aconst_null
     135: areturn
     136: getstatic     #58                 // Field org/apache/jena/datatypes/xsd/XSDDatatype.XSDdateTime:Lorg/apache/jena/datatypes/xsd/XSDDatatype;
     139: aload_1
     140: invokevirtual #43                 // Method org/apache/jena/datatypes/xsd/XSDDatatype.isValidLiteral:(Lorg/apache/jena/graph/impl/LiteralLabel;)Z
     143: ifeq          181
     146: aload_1
     147: invokeinterface #45,  1           // InterfaceMethod org/apache/jena/graph/impl/LiteralLabel.getLexicalForm:()Ljava/lang/String;
     152: invokestatic  #59                 // Method org/apache/jena/tdb/store/DateTimeNode.packDateTime:(Ljava/lang/String;)J
     155: lstore_2
     156: lload_2
     157: ldc2_w        #56                 // long -1l
     160: lcmp
     161: ifne          166
     164: aconst_null
     165: areturn
     166: lload_2
     167: iconst_4
     168: invokestatic  #60                 // Method setType:(JI)J
     171: lstore_2
     172: new           #5                  // class org/apache/jena/tdb/store/NodeId
     175: dup
     176: lload_2
     177: invokespecial #6                  // Method "<init>":(J)V
     180: areturn
     181: getstatic     #61                 // Field org/apache/jena/datatypes/xsd/XSDDatatype.XSDdate:Lorg/apache/jena/datatypes/xsd/XSDDatatype;
     184: aload_1
     185: invokevirtual #43                 // Method org/apache/jena/datatypes/xsd/XSDDatatype.isValidLiteral:(Lorg/apache/jena/graph/impl/LiteralLabel;)Z
     188: ifeq          226
     191: aload_1
     192: invokeinterface #45,  1           // InterfaceMethod org/apache/jena/graph/impl/LiteralLabel.getLexicalForm:()Ljava/lang/String;
     197: invokestatic  #62                 // Method org/apache/jena/tdb/store/DateTimeNode.packDate:(Ljava/lang/String;)J
     200: lstore_2
     201: lload_2
     202: ldc2_w        #56                 // long -1l
     205: lcmp
     206: ifne          211
     209: aconst_null
     210: areturn
     211: lload_2
     212: iconst_3
     213: invokestatic  #60                 // Method setType:(JI)J
     216: lstore_2
     217: new           #5                  // class org/apache/jena/tdb/store/NodeId
     220: dup
     221: lload_2
     222: invokespecial #6                  // Method "<init>":(J)V
     225: areturn
     226: getstatic     #63                 // Field org/apache/jena/datatypes/xsd/XSDDatatype.XSDboolean:Lorg/apache/jena/datatypes/xsd/XSDDatatype;
     229: aload_1
     230: invokevirtual #43                 // Method org/apache/jena/datatypes/xsd/XSDDatatype.isValidLiteral:(Lorg/apache/jena/graph/impl/LiteralLabel;)Z
     233: ifeq          276
     236: lconst_0
     237: lstore_2
     238: aload_1
     239: invokeinterface #52,  1           // InterfaceMethod org/apache/jena/graph/impl/LiteralLabel.getValue:()Ljava/lang/Object;
     244: checkcast     #64                 // class java/lang/Boolean
     247: invokevirtual #65                 // Method java/lang/Boolean.booleanValue:()Z
     250: istore        4
     252: lload_2
     253: iconst_5
     254: invokestatic  #60                 // Method setType:(JI)J
     257: lstore_2
     258: iload         4
     260: ifeq          267
     263: lload_2
     264: lconst_1
     265: lor
     266: lstore_2
     267: new           #5                  // class org/apache/jena/tdb/store/NodeId
     270: dup
     271: lload_2
     272: invokespecial #6                  // Method "<init>":(J)V
     275: areturn
     276: aconst_null
     277: areturn
    Exception table:
       from    to  target type
          96   130   133   Class java/lang/Throwable
         131   132   133   Class java/lang/Throwable

  public static boolean isInline(org.apache.jena.tdb.store.NodeId);
    Code:
       0: aload_0
       1: getstatic     #2                  // Field NodeDoesNotExist:Lorg/apache/jena/tdb/store/NodeId;
       4: if_acmpne     9
       7: iconst_0
       8: ireturn
       9: aload_0
      10: getfield      #3                  // Field value:J
      13: lstore_1
      14: aload_0
      15: invokevirtual #15                 // Method type:()I
      18: istore_3
      19: iload_3
      20: lookupswitch  { // 7
                     0: 88
                     1: 92
                     2: 92
                     3: 92
                     4: 92
                     5: 92
                   255: 90
               default: 94
          }
      88: iconst_0
      89: ireturn
      90: iconst_0
      91: ireturn
      92: iconst_1
      93: ireturn
      94: new           #66                 // class org/apache/jena/tdb/TDBException
      97: dup
      98: new           #24                 // class java/lang/StringBuilder
     101: dup
     102: invokespecial #25                 // Method java/lang/StringBuilder."<init>":()V
     105: ldc           #67                 // String Unrecognized node id type:
     107: invokevirtual #27                 // Method java/lang/StringBuilder.append:(Ljava/lang/String;)Ljava/lang/StringBuilder;
     110: iload_3
     111: invokevirtual #68                 // Method java/lang/StringBuilder.append:(I)Ljava/lang/StringBuilder;
     114: invokevirtual #29                 // Method java/lang/StringBuilder.toString:()Ljava/lang/String;
     117: invokespecial #69                 // Method org/apache/jena/tdb/TDBException."<init>":(Ljava/lang/String;)V
     120: athrow

  public static org.apache.jena.graph.Node extract(org.apache.jena.tdb.store.NodeId);
    Code:
       0: aload_0
       1: getstatic     #2                  // Field NodeDoesNotExist:Lorg/apache/jena/tdb/store/NodeId;
       4: if_acmpne     9
       7: aconst_null
       8: areturn
       9: aload_0
      10: getfield      #3                  // Field value:J
      13: lstore_1
      14: aload_0
      15: invokevirtual #15                 // Method type:()I
      18: istore_3
      19: iload_3
      20: lookupswitch  { // 7
                     0: 88
                     1: 92
                     2: 114
                     3: 162
                     4: 136
                     5: 188
                   255: 90
               default: 248
          }
      88: aconst_null
      89: areturn
      90: aconst_null
      91: areturn
      92: lload_1
      93: invokestatic  #70                 // Method org/apache/jena/tdb/store/IntegerNode.unpack:(J)J
      96: lstore        4
      98: lload         4
     100: invokestatic  #71                 // Method java/lang/Long.toString:(J)Ljava/lang/String;
     103: getstatic     #50                 // Field org/apache/jena/datatypes/xsd/XSDDatatype.XSDinteger:Lorg/apache/jena/datatypes/xsd/XSDDatatype;
     106: invokestatic  #72                 // Method org/apache/jena/graph/NodeFactory.createLiteral:(Ljava/lang/String;Lorg/apache/jena/datatypes/RDFDatatype;)Lorg/apache/jena/graph/Node;
     109: astore        6
     111: aload         6
     113: areturn
     114: lload_1
     115: invokestatic  #73                 // Method org/apache/jena/tdb/store/DecimalNode.unpackAsBigDecimal:(J)Ljava/math/BigDecimal;
     118: astore        4
     120: aload         4
     122: invokevirtual #74                 // Method java/math/BigDecimal.toPlainString:()Ljava/lang/String;
     125: astore        5
     127: aload         5
     129: getstatic     #42                 // Field org/apache/jena/datatypes/xsd/XSDDatatype.XSDdecimal:Lorg/apache/jena/datatypes/xsd/XSDDatatype;
     132: invokestatic  #72                 // Method org/apache/jena/graph/NodeFactory.createLiteral:(Ljava/lang/String;Lorg/apache/jena/datatypes/RDFDatatype;)Lorg/apache/jena/graph/Node;
     135: areturn
     136: lload_1
     137: bipush        56
     139: bipush        64
     141: invokestatic  #75                 // Method org/apache/jena/atlas/lib/BitsLong.clear:(JII)J
     144: lstore        4
     146: lload         4
     148: invokestatic  #76                 // Method org/apache/jena/tdb/store/DateTimeNode.unpackDateTime:(J)Ljava/lang/String;
     151: astore        6
     153: aload         6
     155: getstatic     #58                 // Field org/apache/jena/datatypes/xsd/XSDDatatype.XSDdateTime:Lorg/apache/jena/datatypes/xsd/XSDDatatype;
     158: invokestatic  #72                 // Method org/apache/jena/graph/NodeFactory.createLiteral:(Ljava/lang/String;Lorg/apache/jena/datatypes/RDFDatatype;)Lorg/apache/jena/graph/Node;
     161: areturn
     162: lload_1
     163: bipush        56
     165: bipush        64
     167: invokestatic  #75                 // Method org/apache/jena/atlas/lib/BitsLong.clear:(JII)J
     170: lstore        4
     172: lload         4
     174: invokestatic  #77                 // Method org/apache/jena/tdb/store/DateTimeNode.unpackDate:(J)Ljava/lang/String;
     177: astore        6
     179: aload         6
     181: getstatic     #61                 // Field org/apache/jena/datatypes/xsd/XSDDatatype.XSDdate:Lorg/apache/jena/datatypes/xsd/XSDDatatype;
     184: invokestatic  #72                 // Method org/apache/jena/graph/NodeFactory.createLiteral:(Ljava/lang/String;Lorg/apache/jena/datatypes/RDFDatatype;)Lorg/apache/jena/graph/Node;
     187: areturn
     188: lload_1
     189: bipush        56
     191: bipush        64
     193: invokestatic  #75                 // Method org/apache/jena/atlas/lib/BitsLong.clear:(JII)J
     196: lstore        4
     198: lload         4
     200: lconst_0
     201: lcmp
     202: ifne          209
     205: getstatic     #78                 // Field org/apache/jena/sparql/graph/NodeConst.nodeFalse:Lorg/apache/jena/graph/Node;
     208: areturn
     209: lload         4
     211: lconst_1
     212: lcmp
     213: ifne          220
     216: getstatic     #79                 // Field org/apache/jena/sparql/graph/NodeConst.nodeTrue:Lorg/apache/jena/graph/Node;
     219: areturn
     220: new           #66                 // class org/apache/jena/tdb/TDBException
     223: dup
     224: new           #24                 // class java/lang/StringBuilder
     227: dup
     228: invokespecial #25                 // Method java/lang/StringBuilder."<init>":()V
     231: ldc           #80                 // String Unrecognized boolean node id :
     233: invokevirtual #27                 // Method java/lang/StringBuilder.append:(Ljava/lang/String;)Ljava/lang/StringBuilder;
     236: lload         4
     238: invokevirtual #81                 // Method java/lang/StringBuilder.append:(J)Ljava/lang/StringBuilder;
     241: invokevirtual #29                 // Method java/lang/StringBuilder.toString:()Ljava/lang/String;
     244: invokespecial #69                 // Method org/apache/jena/tdb/TDBException."<init>":(Ljava/lang/String;)V
     247: athrow
     248: new           #66                 // class org/apache/jena/tdb/TDBException
     251: dup
     252: new           #24                 // class java/lang/StringBuilder
     255: dup
     256: invokespecial #25                 // Method java/lang/StringBuilder."<init>":()V
     259: ldc           #67                 // String Unrecognized node id type:
     261: invokevirtual #27                 // Method java/lang/StringBuilder.append:(Ljava/lang/String;)Ljava/lang/StringBuilder;
     264: iload_3
     265: invokevirtual #68                 // Method java/lang/StringBuilder.append:(I)Ljava/lang/StringBuilder;
     268: invokevirtual #29                 // Method java/lang/StringBuilder.toString:()Ljava/lang/String;
     271: invokespecial #69                 // Method org/apache/jena/tdb/TDBException."<init>":(Ljava/lang/String;)V
     274: athrow

  public final boolean isConcrete();
    Code:
       0: aload_0
       1: invokestatic  #82                 // Method isAny:(Lorg/apache/jena/tdb/store/NodeId;)Z
       4: ifne          18
       7: aload_0
       8: invokestatic  #83                 // Method isDoesNotExist:(Lorg/apache/jena/tdb/store/NodeId;)Z
      11: ifne          18
      14: iconst_1
      15: goto          19
      18: iconst_0
      19: ireturn

  public static final boolean isConcrete(org.apache.jena.tdb.store.NodeId);
    Code:
       0: aload_0
       1: ifnonnull     6
       4: iconst_0
       5: ireturn
       6: aload_0
       7: getstatic     #4                  // Field NodeIdAny:Lorg/apache/jena/tdb/store/NodeId;
      10: if_acmpne     15
      13: iconst_0
      14: ireturn
      15: aload_0
      16: getstatic     #2                  // Field NodeDoesNotExist:Lorg/apache/jena/tdb/store/NodeId;
      19: if_acmpne     24
      22: iconst_0
      23: ireturn
      24: iconst_1
      25: ireturn

  public static final boolean isAny(org.apache.jena.tdb.store.NodeId);
    Code:
       0: aload_0
       1: getstatic     #4                  // Field NodeIdAny:Lorg/apache/jena/tdb/store/NodeId;
       4: if_acmpeq     11
       7: aload_0
       8: ifnonnull     15
      11: iconst_1
      12: goto          16
      15: iconst_0
      16: ireturn

  public static final boolean isDoesNotExist(org.apache.jena.tdb.store.NodeId);
    Code:
       0: aload_0
       1: getstatic     #2                  // Field NodeDoesNotExist:Lorg/apache/jena/tdb/store/NodeId;
       4: if_acmpne     11
       7: iconst_1
       8: goto          12
      11: iconst_0
      12: ireturn

  static {};
    Code:
       0: new           #5                  // class org/apache/jena/tdb/store/NodeId
       3: dup
       4: ldc2_w        #84                 // long -8l
       7: invokespecial #6                  // Method "<init>":(J)V
      10: putstatic     #2                  // Field NodeDoesNotExist:Lorg/apache/jena/tdb/store/NodeId;
      13: new           #5                  // class org/apache/jena/tdb/store/NodeId
      16: dup
      17: ldc2_w        #86                 // long -9l
      20: invokespecial #6                  // Method "<init>":(J)V
      23: putstatic     #4                  // Field NodeIdAny:Lorg/apache/jena/tdb/store/NodeId;
      26: getstatic     #88                 // Field org/apache/jena/tdb/sys/SystemTDB.enableInlineLiterals:Z
      29: putstatic     #31                 // Field enableInlineLiterals:Z
      32: bipush        13
      34: anewarray     #89                 // class org/apache/jena/datatypes/RDFDatatype
      37: dup
      38: iconst_0
      39: getstatic     #42                 // Field org/apache/jena/datatypes/xsd/XSDDatatype.XSDdecimal:Lorg/apache/jena/datatypes/xsd/XSDDatatype;
      42: aastore
      43: dup
      44: iconst_1
      45: getstatic     #50                 // Field org/apache/jena/datatypes/xsd/XSDDatatype.XSDinteger:Lorg/apache/jena/datatypes/xsd/XSDDatatype;
      48: aastore
      49: dup
      50: iconst_2
      51: getstatic     #90                 // Field org/apache/jena/datatypes/xsd/XSDDatatype.XSDlong:Lorg/apache/jena/datatypes/xsd/XSDDatatype;
      54: aastore
      55: dup
      56: iconst_3
      57: getstatic     #91                 // Field org/apache/jena/datatypes/xsd/XSDDatatype.XSDint:Lorg/apache/jena/datatypes/xsd/XSDDatatype;
      60: aastore
      61: dup
      62: iconst_4
      63: getstatic     #92                 // Field org/apache/jena/datatypes/xsd/XSDDatatype.XSDshort:Lorg/apache/jena/datatypes/xsd/XSDDatatype;
      66: aastore
      67: dup
      68: iconst_5
      69: getstatic     #93                 // Field org/apache/jena/datatypes/xsd/XSDDatatype.XSDbyte:Lorg/apache/jena/datatypes/xsd/XSDDatatype;
      72: aastore
      73: dup
      74: bipush        6
      76: getstatic     #94                 // Field org/apache/jena/datatypes/xsd/XSDDatatype.XSDunsignedLong:Lorg/apache/jena/datatypes/xsd/XSDDatatype;
      79: aastore
      80: dup
      81: bipush        7
      83: getstatic     #95                 // Field org/apache/jena/datatypes/xsd/XSDDatatype.XSDunsignedInt:Lorg/apache/jena/datatypes/xsd/XSDDatatype;
      86: aastore
      87: dup
      88: bipush        8
      90: getstatic     #96                 // Field org/apache/jena/datatypes/xsd/XSDDatatype.XSDunsignedShort:Lorg/apache/jena/datatypes/xsd/XSDDatatype;
      93: aastore
      94: dup
      95: bipush        9
      97: getstatic     #97                 // Field org/apache/jena/datatypes/xsd/XSDDatatype.XSDunsignedByte:Lorg/apache/jena/datatypes/xsd/XSDDatatype;
     100: aastore
     101: dup
     102: bipush        10
     104: getstatic     #58                 // Field org/apache/jena/datatypes/xsd/XSDDatatype.XSDdateTime:Lorg/apache/jena/datatypes/xsd/XSDDatatype;
     107: aastore
     108: dup
     109: bipush        11
     111: getstatic     #61                 // Field org/apache/jena/datatypes/xsd/XSDDatatype.XSDdate:Lorg/apache/jena/datatypes/xsd/XSDDatatype;
     114: aastore
     115: dup
     116: bipush        12
     118: getstatic     #63                 // Field org/apache/jena/datatypes/xsd/XSDDatatype.XSDboolean:Lorg/apache/jena/datatypes/xsd/XSDDatatype;
     121: aastore
     122: putstatic     #39                 // Field datatypes:[Lorg/apache/jena/datatypes/RDFDatatype;
     125: return
}
