Compiled from "DiscardUnknownFieldsParser.java"
public final class com.google.protobuf.DiscardUnknownFieldsParser {
  public static final <T extends com.google.protobuf.Message> com.google.protobuf.Parser<T> wrap(com.google.protobuf.Parser<T>);
    Code:
       0: new           #1                  // class com/google/protobuf/DiscardUnknownFieldsParser$1
       3: dup
       4: aload_0
       5: invokespecial #2                  // Method com/google/protobuf/DiscardUnknownFieldsParser$1."<init>":(Lcom/google/protobuf/Parser;)V
       8: areturn

  private com.google.protobuf.DiscardUnknownFieldsParser();
    Code:
       0: aload_0
       1: invokespecial #3                  // Method java/lang/Object."<init>":()V
       4: return
}
