Compiled from "GeneratedMessageLite.java"
public final class com.google.protobuf.GeneratedMessageLite$SerializedForm implements java.io.Serializable {
  private static final long serialVersionUID;

  private final java.lang.Class<?> messageClass;

  private final java.lang.String messageClassName;

  private final byte[] asBytes;

  public static com.google.protobuf.GeneratedMessageLite$SerializedForm of(com.google.protobuf.MessageLite);
    Code:
       0: new           #1                  // class com/google/protobuf/GeneratedMessageLite$SerializedForm
       3: dup
       4: aload_0
       5: invokespecial #2                  // Method "<init>":(Lcom/google/protobuf/MessageLite;)V
       8: areturn

  com.google.protobuf.GeneratedMessageLite$SerializedForm(com.google.protobuf.MessageLite);
    Code:
       0: aload_0
       1: invokespecial #3                  // Method java/lang/Object."<init>":()V
       4: aload_0
       5: aload_1
       6: invokevirtual #4                  // Method java/lang/Object.getClass:()Ljava/lang/Class;
       9: putfield      #5                  // Field messageClass:Ljava/lang/Class;
      12: aload_0
      13: aload_0
      14: getfield      #5                  // Field messageClass:Ljava/lang/Class;
      17: invokevirtual #6                  // Method java/lang/Class.getName:()Ljava/lang/String;
      20: putfield      #7                  // Field messageClassName:Ljava/lang/String;
      23: aload_0
      24: aload_1
      25: invokeinterface #8,  1            // InterfaceMethod com/google/protobuf/MessageLite.toByteArray:()[B
      30: putfield      #9                  // Field asBytes:[B
      33: return

  protected java.lang.Object readResolve() throws java.io.ObjectStreamException;
    Code:
       0: aload_0
       1: invokespecial #10                 // Method resolveMessageClass:()Ljava/lang/Class;
       4: astore_1
       5: aload_1
       6: ldc           #11                 // String DEFAULT_INSTANCE
       8: invokevirtual #12                 // Method java/lang/Class.getDeclaredField:(Ljava/lang/String;)Ljava/lang/reflect/Field;
      11: astore_2
      12: aload_2
      13: iconst_1
      14: invokevirtual #13                 // Method java/lang/reflect/Field.setAccessible:(Z)V
      17: aload_2
      18: aconst_null
      19: invokevirtual #14                 // Method java/lang/reflect/Field.get:(Ljava/lang/Object;)Ljava/lang/Object;
      22: checkcast     #15                 // class com/google/protobuf/MessageLite
      25: astore_3
      26: aload_3
      27: invokeinterface #16,  1           // InterfaceMethod com/google/protobuf/MessageLite.newBuilderForType:()Lcom/google/protobuf/MessageLite$Builder;
      32: aload_0
      33: getfield      #9                  // Field asBytes:[B
      36: invokeinterface #17,  2           // InterfaceMethod com/google/protobuf/MessageLite$Builder.mergeFrom:([B)Lcom/google/protobuf/MessageLite$Builder;
      41: invokeinterface #18,  1           // InterfaceMethod com/google/protobuf/MessageLite$Builder.buildPartial:()Lcom/google/protobuf/MessageLite;
      46: areturn
      47: astore_1
      48: new           #20                 // class java/lang/RuntimeException
      51: dup
      52: new           #21                 // class java/lang/StringBuilder
      55: dup
      56: invokespecial #22                 // Method java/lang/StringBuilder."<init>":()V
      59: ldc           #23                 // String Unable to find proto buffer class:
      61: invokevirtual #24                 // Method java/lang/StringBuilder.append:(Ljava/lang/String;)Ljava/lang/StringBuilder;
      64: aload_0
      65: getfield      #7                  // Field messageClassName:Ljava/lang/String;
      68: invokevirtual #24                 // Method java/lang/StringBuilder.append:(Ljava/lang/String;)Ljava/lang/StringBuilder;
      71: invokevirtual #25                 // Method java/lang/StringBuilder.toString:()Ljava/lang/String;
      74: aload_1
      75: invokespecial #26                 // Method java/lang/RuntimeException."<init>":(Ljava/lang/String;Ljava/lang/Throwable;)V
      78: athrow
      79: astore_1
      80: aload_0
      81: invokespecial #28                 // Method readResolveFallback:()Ljava/lang/Object;
      84: areturn
      85: astore_1
      86: new           #20                 // class java/lang/RuntimeException
      89: dup
      90: new           #21                 // class java/lang/StringBuilder
      93: dup
      94: invokespecial #22                 // Method java/lang/StringBuilder."<init>":()V
      97: ldc           #30                 // String Unable to call DEFAULT_INSTANCE in
      99: invokevirtual #24                 // Method java/lang/StringBuilder.append:(Ljava/lang/String;)Ljava/lang/StringBuilder;
     102: aload_0
     103: getfield      #7                  // Field messageClassName:Ljava/lang/String;
     106: invokevirtual #24                 // Method java/lang/StringBuilder.append:(Ljava/lang/String;)Ljava/lang/StringBuilder;
     109: invokevirtual #25                 // Method java/lang/StringBuilder.toString:()Ljava/lang/String;
     112: aload_1
     113: invokespecial #26                 // Method java/lang/RuntimeException."<init>":(Ljava/lang/String;Ljava/lang/Throwable;)V
     116: athrow
     117: astore_1
     118: new           #20                 // class java/lang/RuntimeException
     121: dup
     122: ldc           #32                 // String Unable to call parsePartialFrom
     124: aload_1
     125: invokespecial #26                 // Method java/lang/RuntimeException."<init>":(Ljava/lang/String;Ljava/lang/Throwable;)V
     128: athrow
     129: astore_1
     130: new           #20                 // class java/lang/RuntimeException
     133: dup
     134: ldc           #34                 // String Unable to understand proto buffer
     136: aload_1
     137: invokespecial #26                 // Method java/lang/RuntimeException."<init>":(Ljava/lang/String;Ljava/lang/Throwable;)V
     140: athrow
    Exception table:
       from    to  target type
           0    46    47   Class java/lang/ClassNotFoundException
           0    46    79   Class java/lang/NoSuchFieldException
           0    46    85   Class java/lang/SecurityException
           0    46   117   Class java/lang/IllegalAccessException
           0    46   129   Class com/google/protobuf/InvalidProtocolBufferException

  private java.lang.Object readResolveFallback() throws java.io.ObjectStreamException;
    Code:
       0: aload_0
       1: invokespecial #10                 // Method resolveMessageClass:()Ljava/lang/Class;
       4: astore_1
       5: aload_1
       6: ldc           #35                 // String defaultInstance
       8: invokevirtual #12                 // Method java/lang/Class.getDeclaredField:(Ljava/lang/String;)Ljava/lang/reflect/Field;
      11: astore_2
      12: aload_2
      13: iconst_1
      14: invokevirtual #13                 // Method java/lang/reflect/Field.setAccessible:(Z)V
      17: aload_2
      18: aconst_null
      19: invokevirtual #14                 // Method java/lang/reflect/Field.get:(Ljava/lang/Object;)Ljava/lang/Object;
      22: checkcast     #15                 // class com/google/protobuf/MessageLite
      25: astore_3
      26: aload_3
      27: invokeinterface #16,  1           // InterfaceMethod com/google/protobuf/MessageLite.newBuilderForType:()Lcom/google/protobuf/MessageLite$Builder;
      32: aload_0
      33: getfield      #9                  // Field asBytes:[B
      36: invokeinterface #17,  2           // InterfaceMethod com/google/protobuf/MessageLite$Builder.mergeFrom:([B)Lcom/google/protobuf/MessageLite$Builder;
      41: invokeinterface #18,  1           // InterfaceMethod com/google/protobuf/MessageLite$Builder.buildPartial:()Lcom/google/protobuf/MessageLite;
      46: areturn
      47: astore_1
      48: new           #20                 // class java/lang/RuntimeException
      51: dup
      52: new           #21                 // class java/lang/StringBuilder
      55: dup
      56: invokespecial #22                 // Method java/lang/StringBuilder."<init>":()V
      59: ldc           #23                 // String Unable to find proto buffer class:
      61: invokevirtual #24                 // Method java/lang/StringBuilder.append:(Ljava/lang/String;)Ljava/lang/StringBuilder;
      64: aload_0
      65: getfield      #7                  // Field messageClassName:Ljava/lang/String;
      68: invokevirtual #24                 // Method java/lang/StringBuilder.append:(Ljava/lang/String;)Ljava/lang/StringBuilder;
      71: invokevirtual #25                 // Method java/lang/StringBuilder.toString:()Ljava/lang/String;
      74: aload_1
      75: invokespecial #26                 // Method java/lang/RuntimeException."<init>":(Ljava/lang/String;Ljava/lang/Throwable;)V
      78: athrow
      79: astore_1
      80: new           #20                 // class java/lang/RuntimeException
      83: dup
      84: new           #21                 // class java/lang/StringBuilder
      87: dup
      88: invokespecial #22                 // Method java/lang/StringBuilder."<init>":()V
      91: ldc           #36                 // String Unable to find defaultInstance in
      93: invokevirtual #24                 // Method java/lang/StringBuilder.append:(Ljava/lang/String;)Ljava/lang/StringBuilder;
      96: aload_0
      97: getfield      #7                  // Field messageClassName:Ljava/lang/String;
     100: invokevirtual #24                 // Method java/lang/StringBuilder.append:(Ljava/lang/String;)Ljava/lang/StringBuilder;
     103: invokevirtual #25                 // Method java/lang/StringBuilder.toString:()Ljava/lang/String;
     106: aload_1
     107: invokespecial #26                 // Method java/lang/RuntimeException."<init>":(Ljava/lang/String;Ljava/lang/Throwable;)V
     110: athrow
     111: astore_1
     112: new           #20                 // class java/lang/RuntimeException
     115: dup
     116: new           #21                 // class java/lang/StringBuilder
     119: dup
     120: invokespecial #22                 // Method java/lang/StringBuilder."<init>":()V
     123: ldc           #37                 // String Unable to call defaultInstance in
     125: invokevirtual #24                 // Method java/lang/StringBuilder.append:(Ljava/lang/String;)Ljava/lang/StringBuilder;
     128: aload_0
     129: getfield      #7                  // Field messageClassName:Ljava/lang/String;
     132: invokevirtual #24                 // Method java/lang/StringBuilder.append:(Ljava/lang/String;)Ljava/lang/StringBuilder;
     135: invokevirtual #25                 // Method java/lang/StringBuilder.toString:()Ljava/lang/String;
     138: aload_1
     139: invokespecial #26                 // Method java/lang/RuntimeException."<init>":(Ljava/lang/String;Ljava/lang/Throwable;)V
     142: athrow
     143: astore_1
     144: new           #20                 // class java/lang/RuntimeException
     147: dup
     148: ldc           #32                 // String Unable to call parsePartialFrom
     150: aload_1
     151: invokespecial #26                 // Method java/lang/RuntimeException."<init>":(Ljava/lang/String;Ljava/lang/Throwable;)V
     154: athrow
     155: astore_1
     156: new           #20                 // class java/lang/RuntimeException
     159: dup
     160: ldc           #34                 // String Unable to understand proto buffer
     162: aload_1
     163: invokespecial #26                 // Method java/lang/RuntimeException."<init>":(Ljava/lang/String;Ljava/lang/Throwable;)V
     166: athrow
    Exception table:
       from    to  target type
           0    46    47   Class java/lang/ClassNotFoundException
           0    46    79   Class java/lang/NoSuchFieldException
           0    46   111   Class java/lang/SecurityException
           0    46   143   Class java/lang/IllegalAccessException
           0    46   155   Class com/google/protobuf/InvalidProtocolBufferException

  private java.lang.Class<?> resolveMessageClass() throws java.lang.ClassNotFoundException;
    Code:
       0: aload_0
       1: getfield      #5                  // Field messageClass:Ljava/lang/Class;
       4: ifnull        14
       7: aload_0
       8: getfield      #5                  // Field messageClass:Ljava/lang/Class;
      11: goto          21
      14: aload_0
      15: getfield      #7                  // Field messageClassName:Ljava/lang/String;
      18: invokestatic  #38                 // Method java/lang/Class.forName:(Ljava/lang/String;)Ljava/lang/Class;
      21: areturn
}
