Compiled from "SingleFieldBuilder.java"
public class com.google.protobuf.SingleFieldBuilder<MType extends com.google.protobuf.GeneratedMessage, BType extends com.google.protobuf.GeneratedMessage$Builder, IType extends com.google.protobuf.MessageOrBuilder> implements com.google.protobuf.GeneratedMessage$BuilderParent {
  private com.google.protobuf.GeneratedMessage$BuilderParent parent;

  private BType builder;

  private MType message;

  private boolean isClean;

  public com.google.protobuf.SingleFieldBuilder(MType, com.google.protobuf.GeneratedMessage$BuilderParent, boolean);
    Code:
       0: aload_0
       1: invokespecial #1                  // Method java/lang/Object."<init>":()V
       4: aload_0
       5: aload_1
       6: invokestatic  #2                  // Method com/google/protobuf/Internal.checkNotNull:(Ljava/lang/Object;)Ljava/lang/Object;
       9: checkcast     #3                  // class com/google/protobuf/GeneratedMessage
      12: putfield      #4                  // Field message:Lcom/google/protobuf/GeneratedMessage;
      15: aload_0
      16: aload_2
      17: putfield      #5                  // Field parent:Lcom/google/protobuf/GeneratedMessage$BuilderParent;
      20: aload_0
      21: iload_3
      22: putfield      #6                  // Field isClean:Z
      25: return

  public void dispose();
    Code:
       0: aload_0
       1: aconst_null
       2: putfield      #5                  // Field parent:Lcom/google/protobuf/GeneratedMessage$BuilderParent;
       5: return

  public MType getMessage();
    Code:
       0: aload_0
       1: getfield      #4                  // Field message:Lcom/google/protobuf/GeneratedMessage;
       4: ifnonnull     21
       7: aload_0
       8: aload_0
       9: getfield      #7                  // Field builder:Lcom/google/protobuf/GeneratedMessage$Builder;
      12: invokevirtual #8                  // Method com/google/protobuf/GeneratedMessage$Builder.buildPartial:()Lcom/google/protobuf/Message;
      15: checkcast     #3                  // class com/google/protobuf/GeneratedMessage
      18: putfield      #4                  // Field message:Lcom/google/protobuf/GeneratedMessage;
      21: aload_0
      22: getfield      #4                  // Field message:Lcom/google/protobuf/GeneratedMessage;
      25: areturn

  public MType build();
    Code:
       0: aload_0
       1: iconst_1
       2: putfield      #6                  // Field isClean:Z
       5: aload_0
       6: invokevirtual #9                  // Method getMessage:()Lcom/google/protobuf/GeneratedMessage;
       9: areturn

  public BType getBuilder();
    Code:
       0: aload_0
       1: getfield      #7                  // Field builder:Lcom/google/protobuf/GeneratedMessage$Builder;
       4: ifnonnull     41
       7: aload_0
       8: aload_0
       9: getfield      #4                  // Field message:Lcom/google/protobuf/GeneratedMessage;
      12: aload_0
      13: invokevirtual #10                 // Method com/google/protobuf/GeneratedMessage.newBuilderForType:(Lcom/google/protobuf/GeneratedMessage$BuilderParent;)Lcom/google/protobuf/Message$Builder;
      16: checkcast     #11                 // class com/google/protobuf/GeneratedMessage$Builder
      19: putfield      #7                  // Field builder:Lcom/google/protobuf/GeneratedMessage$Builder;
      22: aload_0
      23: getfield      #7                  // Field builder:Lcom/google/protobuf/GeneratedMessage$Builder;
      26: aload_0
      27: getfield      #4                  // Field message:Lcom/google/protobuf/GeneratedMessage;
      30: invokevirtual #12                 // Method com/google/protobuf/GeneratedMessage$Builder.mergeFrom:(Lcom/google/protobuf/Message;)Lcom/google/protobuf/AbstractMessage$Builder;
      33: pop
      34: aload_0
      35: getfield      #7                  // Field builder:Lcom/google/protobuf/GeneratedMessage$Builder;
      38: invokevirtual #13                 // Method com/google/protobuf/GeneratedMessage$Builder.markClean:()V
      41: aload_0
      42: getfield      #7                  // Field builder:Lcom/google/protobuf/GeneratedMessage$Builder;
      45: areturn

  public IType getMessageOrBuilder();
    Code:
       0: aload_0
       1: getfield      #7                  // Field builder:Lcom/google/protobuf/GeneratedMessage$Builder;
       4: ifnull        12
       7: aload_0
       8: getfield      #7                  // Field builder:Lcom/google/protobuf/GeneratedMessage$Builder;
      11: areturn
      12: aload_0
      13: getfield      #4                  // Field message:Lcom/google/protobuf/GeneratedMessage;
      16: areturn

  public com.google.protobuf.SingleFieldBuilder<MType, BType, IType> setMessage(MType);
    Code:
       0: aload_0
       1: aload_1
       2: invokestatic  #2                  // Method com/google/protobuf/Internal.checkNotNull:(Ljava/lang/Object;)Ljava/lang/Object;
       5: checkcast     #3                  // class com/google/protobuf/GeneratedMessage
       8: putfield      #4                  // Field message:Lcom/google/protobuf/GeneratedMessage;
      11: aload_0
      12: getfield      #7                  // Field builder:Lcom/google/protobuf/GeneratedMessage$Builder;
      15: ifnull        30
      18: aload_0
      19: getfield      #7                  // Field builder:Lcom/google/protobuf/GeneratedMessage$Builder;
      22: invokevirtual #14                 // Method com/google/protobuf/GeneratedMessage$Builder.dispose:()V
      25: aload_0
      26: aconst_null
      27: putfield      #7                  // Field builder:Lcom/google/protobuf/GeneratedMessage$Builder;
      30: aload_0
      31: invokespecial #15                 // Method onChanged:()V
      34: aload_0
      35: areturn

  public com.google.protobuf.SingleFieldBuilder<MType, BType, IType> mergeFrom(MType);
    Code:
       0: aload_0
       1: getfield      #7                  // Field builder:Lcom/google/protobuf/GeneratedMessage$Builder;
       4: ifnonnull     29
       7: aload_0
       8: getfield      #4                  // Field message:Lcom/google/protobuf/GeneratedMessage;
      11: aload_0
      12: getfield      #4                  // Field message:Lcom/google/protobuf/GeneratedMessage;
      15: invokevirtual #16                 // Method com/google/protobuf/GeneratedMessage.getDefaultInstanceForType:()Lcom/google/protobuf/Message;
      18: if_acmpne     29
      21: aload_0
      22: aload_1
      23: putfield      #4                  // Field message:Lcom/google/protobuf/GeneratedMessage;
      26: goto          38
      29: aload_0
      30: invokevirtual #17                 // Method getBuilder:()Lcom/google/protobuf/GeneratedMessage$Builder;
      33: aload_1
      34: invokevirtual #12                 // Method com/google/protobuf/GeneratedMessage$Builder.mergeFrom:(Lcom/google/protobuf/Message;)Lcom/google/protobuf/AbstractMessage$Builder;
      37: pop
      38: aload_0
      39: invokespecial #15                 // Method onChanged:()V
      42: aload_0
      43: areturn

  public com.google.protobuf.SingleFieldBuilder<MType, BType, IType> clear();
    Code:
       0: aload_0
       1: aload_0
       2: getfield      #4                  // Field message:Lcom/google/protobuf/GeneratedMessage;
       5: ifnull        18
       8: aload_0
       9: getfield      #4                  // Field message:Lcom/google/protobuf/GeneratedMessage;
      12: invokevirtual #16                 // Method com/google/protobuf/GeneratedMessage.getDefaultInstanceForType:()Lcom/google/protobuf/Message;
      15: goto          25
      18: aload_0
      19: getfield      #7                  // Field builder:Lcom/google/protobuf/GeneratedMessage$Builder;
      22: invokevirtual #18                 // Method com/google/protobuf/GeneratedMessage$Builder.getDefaultInstanceForType:()Lcom/google/protobuf/Message;
      25: checkcast     #3                  // class com/google/protobuf/GeneratedMessage
      28: checkcast     #3                  // class com/google/protobuf/GeneratedMessage
      31: putfield      #4                  // Field message:Lcom/google/protobuf/GeneratedMessage;
      34: aload_0
      35: getfield      #7                  // Field builder:Lcom/google/protobuf/GeneratedMessage$Builder;
      38: ifnull        53
      41: aload_0
      42: getfield      #7                  // Field builder:Lcom/google/protobuf/GeneratedMessage$Builder;
      45: invokevirtual #14                 // Method com/google/protobuf/GeneratedMessage$Builder.dispose:()V
      48: aload_0
      49: aconst_null
      50: putfield      #7                  // Field builder:Lcom/google/protobuf/GeneratedMessage$Builder;
      53: aload_0
      54: invokespecial #15                 // Method onChanged:()V
      57: aload_0
      58: areturn

  private void onChanged();
    Code:
       0: aload_0
       1: getfield      #7                  // Field builder:Lcom/google/protobuf/GeneratedMessage$Builder;
       4: ifnull        12
       7: aload_0
       8: aconst_null
       9: putfield      #4                  // Field message:Lcom/google/protobuf/GeneratedMessage;
      12: aload_0
      13: getfield      #6                  // Field isClean:Z
      16: ifeq          40
      19: aload_0
      20: getfield      #5                  // Field parent:Lcom/google/protobuf/GeneratedMessage$BuilderParent;
      23: ifnull        40
      26: aload_0
      27: getfield      #5                  // Field parent:Lcom/google/protobuf/GeneratedMessage$BuilderParent;
      30: invokeinterface #19,  1           // InterfaceMethod com/google/protobuf/GeneratedMessage$BuilderParent.markDirty:()V
      35: aload_0
      36: iconst_0
      37: putfield      #6                  // Field isClean:Z
      40: return

  public void markDirty();
    Code:
       0: aload_0
       1: invokespecial #15                 // Method onChanged:()V
       4: return
}
