Compiled from "UnsafeUtil.java"
final class com.google.protobuf.UnsafeUtil$Android64MemoryAccessor extends com.google.protobuf.UnsafeUtil$MemoryAccessor {
  com.google.protobuf.UnsafeUtil$Android64MemoryAccessor(sun.misc.Unsafe);
    Code:
       0: aload_0
       1: aload_1
       2: invokespecial #1                  // Method com/google/protobuf/UnsafeUtil$MemoryAccessor."<init>":(Lsun/misc/Unsafe;)V
       5: return

  public java.lang.Object getStaticObject(java.lang.reflect.Field);
    Code:
       0: aload_1
       1: aconst_null
       2: invokevirtual #2                  // Method java/lang/reflect/Field.get:(Ljava/lang/Object;)Ljava/lang/Object;
       5: areturn
       6: astore_2
       7: aconst_null
       8: areturn
    Exception table:
       from    to  target type
           0     5     6   Class java/lang/IllegalAccessException

  public byte getByte(java.lang.Object, long);
    Code:
       0: getstatic     #4                  // Field com/google/protobuf/UnsafeUtil.IS_BIG_ENDIAN:Z
       3: ifeq          12
       6: aload_1
       7: lload_2
       8: invokestatic  #5                  // Method com/google/protobuf/UnsafeUtil.access$200:(Ljava/lang/Object;J)B
      11: ireturn
      12: aload_1
      13: lload_2
      14: invokestatic  #6                  // Method com/google/protobuf/UnsafeUtil.access$300:(Ljava/lang/Object;J)B
      17: ireturn

  public void putByte(java.lang.Object, long, byte);
    Code:
       0: getstatic     #4                  // Field com/google/protobuf/UnsafeUtil.IS_BIG_ENDIAN:Z
       3: ifeq          16
       6: aload_1
       7: lload_2
       8: iload         4
      10: invokestatic  #7                  // Method com/google/protobuf/UnsafeUtil.access$400:(Ljava/lang/Object;JB)V
      13: goto          23
      16: aload_1
      17: lload_2
      18: iload         4
      20: invokestatic  #8                  // Method com/google/protobuf/UnsafeUtil.access$500:(Ljava/lang/Object;JB)V
      23: return

  public boolean getBoolean(java.lang.Object, long);
    Code:
       0: getstatic     #4                  // Field com/google/protobuf/UnsafeUtil.IS_BIG_ENDIAN:Z
       3: ifeq          12
       6: aload_1
       7: lload_2
       8: invokestatic  #9                  // Method com/google/protobuf/UnsafeUtil.access$600:(Ljava/lang/Object;J)Z
      11: ireturn
      12: aload_1
      13: lload_2
      14: invokestatic  #10                 // Method com/google/protobuf/UnsafeUtil.access$700:(Ljava/lang/Object;J)Z
      17: ireturn

  public void putBoolean(java.lang.Object, long, boolean);
    Code:
       0: getstatic     #4                  // Field com/google/protobuf/UnsafeUtil.IS_BIG_ENDIAN:Z
       3: ifeq          16
       6: aload_1
       7: lload_2
       8: iload         4
      10: invokestatic  #11                 // Method com/google/protobuf/UnsafeUtil.access$800:(Ljava/lang/Object;JZ)V
      13: goto          23
      16: aload_1
      17: lload_2
      18: iload         4
      20: invokestatic  #12                 // Method com/google/protobuf/UnsafeUtil.access$900:(Ljava/lang/Object;JZ)V
      23: return

  public float getFloat(java.lang.Object, long);
    Code:
       0: aload_0
       1: aload_1
       2: lload_2
       3: invokevirtual #13                 // Method getInt:(Ljava/lang/Object;J)I
       6: invokestatic  #14                 // Method java/lang/Float.intBitsToFloat:(I)F
       9: freturn

  public void putFloat(java.lang.Object, long, float);
    Code:
       0: aload_0
       1: aload_1
       2: lload_2
       3: fload         4
       5: invokestatic  #15                 // Method java/lang/Float.floatToIntBits:(F)I
       8: invokevirtual #16                 // Method putInt:(Ljava/lang/Object;JI)V
      11: return

  public double getDouble(java.lang.Object, long);
    Code:
       0: aload_0
       1: aload_1
       2: lload_2
       3: invokevirtual #17                 // Method getLong:(Ljava/lang/Object;J)J
       6: invokestatic  #18                 // Method java/lang/Double.longBitsToDouble:(J)D
       9: dreturn

  public void putDouble(java.lang.Object, long, double);
    Code:
       0: aload_0
       1: aload_1
       2: lload_2
       3: dload         4
       5: invokestatic  #19                 // Method java/lang/Double.doubleToLongBits:(D)J
       8: invokevirtual #20                 // Method putLong:(Ljava/lang/Object;JJ)V
      11: return

  public boolean supportsUnsafeByteBufferOperations();
    Code:
       0: iconst_0
       1: ireturn

  public byte getByte(long);
    Code:
       0: new           #21                 // class java/lang/UnsupportedOperationException
       3: dup
       4: invokespecial #22                 // Method java/lang/UnsupportedOperationException."<init>":()V
       7: athrow

  public void putByte(long, byte);
    Code:
       0: new           #21                 // class java/lang/UnsupportedOperationException
       3: dup
       4: invokespecial #22                 // Method java/lang/UnsupportedOperationException."<init>":()V
       7: athrow

  public int getInt(long);
    Code:
       0: new           #21                 // class java/lang/UnsupportedOperationException
       3: dup
       4: invokespecial #22                 // Method java/lang/UnsupportedOperationException."<init>":()V
       7: athrow

  public void putInt(long, int);
    Code:
       0: new           #21                 // class java/lang/UnsupportedOperationException
       3: dup
       4: invokespecial #22                 // Method java/lang/UnsupportedOperationException."<init>":()V
       7: athrow

  public long getLong(long);
    Code:
       0: new           #21                 // class java/lang/UnsupportedOperationException
       3: dup
       4: invokespecial #22                 // Method java/lang/UnsupportedOperationException."<init>":()V
       7: athrow

  public void putLong(long, long);
    Code:
       0: new           #21                 // class java/lang/UnsupportedOperationException
       3: dup
       4: invokespecial #22                 // Method java/lang/UnsupportedOperationException."<init>":()V
       7: athrow

  public void copyMemory(long, byte[], long, long);
    Code:
       0: new           #21                 // class java/lang/UnsupportedOperationException
       3: dup
       4: invokespecial #22                 // Method java/lang/UnsupportedOperationException."<init>":()V
       7: athrow

  public void copyMemory(byte[], long, long, long);
    Code:
       0: new           #21                 // class java/lang/UnsupportedOperationException
       3: dup
       4: invokespecial #22                 // Method java/lang/UnsupportedOperationException."<init>":()V
       7: athrow
}
