Compiled from "CodePointLengthValidator.java"
public class org.hibernate.validator.internal.constraintvalidators.hv.CodePointLengthValidator implements jakarta.validation.ConstraintValidator<org.hibernate.validator.constraints.CodePointLength, java.lang.CharSequence> {
  private static final org.hibernate.validator.internal.util.logging.Log LOG;

  private int min;

  private int max;

  private org.hibernate.validator.constraints.CodePointLength$NormalizationStrategy normalizationStrategy;

  public org.hibernate.validator.internal.constraintvalidators.hv.CodePointLengthValidator();
    Code:
       0: aload_0
       1: invokespecial #1                  // Method java/lang/Object."<init>":()V
       4: return

  public void initialize(org.hibernate.validator.constraints.CodePointLength);
    Code:
       0: aload_0
       1: aload_1
       2: invokeinterface #7,  1            // InterfaceMethod org/hibernate/validator/constraints/CodePointLength.min:()I
       7: putfield      #13                 // Field min:I
      10: aload_0
      11: aload_1
      12: invokeinterface #18,  1           // InterfaceMethod org/hibernate/validator/constraints/CodePointLength.max:()I
      17: putfield      #21                 // Field max:I
      20: aload_0
      21: aload_1
      22: invokeinterface #23,  1           // InterfaceMethod org/hibernate/validator/constraints/CodePointLength.normalizationStrategy:()Lorg/hibernate/validator/constraints/CodePointLength$NormalizationStrategy;
      27: putfield      #27                 // Field normalizationStrategy:Lorg/hibernate/validator/constraints/CodePointLength$NormalizationStrategy;
      30: aload_0
      31: invokevirtual #30                 // Method validateParameters:()V
      34: return

  public boolean isValid(java.lang.CharSequence, jakarta.validation.ConstraintValidatorContext);
    Code:
       0: aload_1
       1: ifnonnull     6
       4: iconst_1
       5: ireturn
       6: aload_0
       7: getfield      #27                 // Field normalizationStrategy:Lorg/hibernate/validator/constraints/CodePointLength$NormalizationStrategy;
      10: aload_1
      11: invokevirtual #33                 // Method org/hibernate/validator/constraints/CodePointLength$NormalizationStrategy.normalize:(Ljava/lang/CharSequence;)Ljava/lang/CharSequence;
      14: invokeinterface #39,  1           // InterfaceMethod java/lang/CharSequence.toString:()Ljava/lang/String;
      19: astore_3
      20: aload_3
      21: iconst_0
      22: aload_3
      23: invokevirtual #45                 // Method java/lang/String.length:()I
      26: invokevirtual #50                 // Method java/lang/String.codePointCount:(II)I
      29: istore        4
      31: iload         4
      33: aload_0
      34: getfield      #13                 // Field min:I
      37: if_icmplt     53
      40: iload         4
      42: aload_0
      43: getfield      #21                 // Field max:I
      46: if_icmpgt     53
      49: iconst_1
      50: goto          54
      53: iconst_0
      54: ireturn

  private void validateParameters();
    Code:
       0: aload_0
       1: getfield      #13                 // Field min:I
       4: ifge          16
       7: getstatic     #54                 // Field LOG:Lorg/hibernate/validator/internal/util/logging/Log;
      10: invokeinterface #58,  1           // InterfaceMethod org/hibernate/validator/internal/util/logging/Log.getMinCannotBeNegativeException:()Ljava/lang/IllegalArgumentException;
      15: athrow
      16: aload_0
      17: getfield      #21                 // Field max:I
      20: ifge          32
      23: getstatic     #54                 // Field LOG:Lorg/hibernate/validator/internal/util/logging/Log;
      26: invokeinterface #64,  1           // InterfaceMethod org/hibernate/validator/internal/util/logging/Log.getMaxCannotBeNegativeException:()Ljava/lang/IllegalArgumentException;
      31: athrow
      32: aload_0
      33: getfield      #21                 // Field max:I
      36: aload_0
      37: getfield      #13                 // Field min:I
      40: if_icmpge     52
      43: getstatic     #54                 // Field LOG:Lorg/hibernate/validator/internal/util/logging/Log;
      46: invokeinterface #67,  1           // InterfaceMethod org/hibernate/validator/internal/util/logging/Log.getLengthCannotBeNegativeException:()Ljava/lang/IllegalArgumentException;
      51: athrow
      52: return

  public boolean isValid(java.lang.Object, jakarta.validation.ConstraintValidatorContext);
    Code:
       0: aload_0
       1: aload_1
       2: checkcast     #40                 // class java/lang/CharSequence
       5: aload_2
       6: invokevirtual #70                 // Method isValid:(Ljava/lang/CharSequence;Ljakarta/validation/ConstraintValidatorContext;)Z
       9: ireturn

  public void initialize(java.lang.annotation.Annotation);
    Code:
       0: aload_0
       1: aload_1
       2: checkcast     #8                  // class org/hibernate/validator/constraints/CodePointLength
       5: invokevirtual #74                 // Method initialize:(Lorg/hibernate/validator/constraints/CodePointLength;)V
       8: return

  static {};
    Code:
       0: invokestatic  #78                 // Method java/lang/invoke/MethodHandles.lookup:()Ljava/lang/invoke/MethodHandles$Lookup;
       3: invokestatic  #84                 // Method org/hibernate/validator/internal/util/logging/LoggerFactory.make:(Ljava/lang/invoke/MethodHandles$Lookup;)Lorg/hibernate/validator/internal/util/logging/Log;
       6: putstatic     #54                 // Field LOG:Lorg/hibernate/validator/internal/util/logging/Log;
       9: return
}
