Compiled from "Authorization.java"
final class software.amazon.awssdk.services.mediapackagevod.model.Authorization$BuilderImpl implements software.amazon.awssdk.services.mediapackagevod.model.Authorization$Builder {
  private java.lang.String cdnIdentifierSecret;

  private java.lang.String secretsRoleArn;

  private software.amazon.awssdk.services.mediapackagevod.model.Authorization$BuilderImpl();
    Code:
       0: aload_0
       1: invokespecial #5                  // Method java/lang/Object."<init>":()V
       4: return

  private software.amazon.awssdk.services.mediapackagevod.model.Authorization$BuilderImpl(software.amazon.awssdk.services.mediapackagevod.model.Authorization);
    Code:
       0: aload_0
       1: invokespecial #5                  // Method java/lang/Object."<init>":()V
       4: aload_0
       5: aload_1
       6: invokestatic  #6                  // Method software/amazon/awssdk/services/mediapackagevod/model/Authorization.access$400:(Lsoftware/amazon/awssdk/services/mediapackagevod/model/Authorization;)Ljava/lang/String;
       9: invokevirtual #7                  // Method cdnIdentifierSecret:(Ljava/lang/String;)Lsoftware/amazon/awssdk/services/mediapackagevod/model/Authorization$Builder;
      12: pop
      13: aload_0
      14: aload_1
      15: invokestatic  #8                  // Method software/amazon/awssdk/services/mediapackagevod/model/Authorization.access$500:(Lsoftware/amazon/awssdk/services/mediapackagevod/model/Authorization;)Ljava/lang/String;
      18: invokevirtual #9                  // Method secretsRoleArn:(Ljava/lang/String;)Lsoftware/amazon/awssdk/services/mediapackagevod/model/Authorization$Builder;
      21: pop
      22: return

  public final java.lang.String getCdnIdentifierSecret();
    Code:
       0: aload_0
       1: getfield      #4                  // Field cdnIdentifierSecret:Ljava/lang/String;
       4: areturn

  public final software.amazon.awssdk.services.mediapackagevod.model.Authorization$Builder cdnIdentifierSecret(java.lang.String);
    Code:
       0: aload_0
       1: aload_1
       2: putfield      #4                  // Field cdnIdentifierSecret:Ljava/lang/String;
       5: aload_0
       6: areturn

  public final void setCdnIdentifierSecret(java.lang.String);
    Code:
       0: aload_0
       1: aload_1
       2: putfield      #4                  // Field cdnIdentifierSecret:Ljava/lang/String;
       5: return

  public final java.lang.String getSecretsRoleArn();
    Code:
       0: aload_0
       1: getfield      #3                  // Field secretsRoleArn:Ljava/lang/String;
       4: areturn

  public final software.amazon.awssdk.services.mediapackagevod.model.Authorization$Builder secretsRoleArn(java.lang.String);
    Code:
       0: aload_0
       1: aload_1
       2: putfield      #3                  // Field secretsRoleArn:Ljava/lang/String;
       5: aload_0
       6: areturn

  public final void setSecretsRoleArn(java.lang.String);
    Code:
       0: aload_0
       1: aload_1
       2: putfield      #3                  // Field secretsRoleArn:Ljava/lang/String;
       5: return

  public software.amazon.awssdk.services.mediapackagevod.model.Authorization build();
    Code:
       0: new           #10                 // class software/amazon/awssdk/services/mediapackagevod/model/Authorization
       3: dup
       4: aload_0
       5: aconst_null
       6: invokespecial #11                 // Method software/amazon/awssdk/services/mediapackagevod/model/Authorization."<init>":(Lsoftware/amazon/awssdk/services/mediapackagevod/model/Authorization$BuilderImpl;Lsoftware/amazon/awssdk/services/mediapackagevod/model/Authorization$1;)V
       9: areturn

  public java.util.List<software.amazon.awssdk.core.SdkField<?>> sdkFields();
    Code:
       0: invokestatic  #12                 // Method software/amazon/awssdk/services/mediapackagevod/model/Authorization.access$700:()Ljava/util/List;
       3: areturn

  public java.lang.Object build();
    Code:
       0: aload_0
       1: invokevirtual #13                 // Method build:()Lsoftware/amazon/awssdk/services/mediapackagevod/model/Authorization;
       4: areturn

  static java.lang.String access$000(software.amazon.awssdk.services.mediapackagevod.model.Authorization$BuilderImpl);
    Code:
       0: aload_0
       1: getfield      #4                  // Field cdnIdentifierSecret:Ljava/lang/String;
       4: areturn

  static java.lang.String access$100(software.amazon.awssdk.services.mediapackagevod.model.Authorization$BuilderImpl);
    Code:
       0: aload_0
       1: getfield      #3                  // Field secretsRoleArn:Ljava/lang/String;
       4: areturn

  software.amazon.awssdk.services.mediapackagevod.model.Authorization$BuilderImpl(software.amazon.awssdk.services.mediapackagevod.model.Authorization, software.amazon.awssdk.services.mediapackagevod.model.Authorization$1);
    Code:
       0: aload_0
       1: aload_1
       2: invokespecial #2                  // Method "<init>":(Lsoftware/amazon/awssdk/services/mediapackagevod/model/Authorization;)V
       5: return

  software.amazon.awssdk.services.mediapackagevod.model.Authorization$BuilderImpl(software.amazon.awssdk.services.mediapackagevod.model.Authorization$1);
    Code:
       0: aload_0
       1: invokespecial #1                  // Method "<init>":()V
       4: return
}
