Compiled from "CreatePackagingGroupRequest.java"
final class software.amazon.awssdk.services.mediapackagevod.model.CreatePackagingGroupRequest$BuilderImpl extends software.amazon.awssdk.services.mediapackagevod.model.MediaPackageVodRequest$BuilderImpl implements software.amazon.awssdk.services.mediapackagevod.model.CreatePackagingGroupRequest$Builder {
  private software.amazon.awssdk.services.mediapackagevod.model.Authorization authorization;

  private software.amazon.awssdk.services.mediapackagevod.model.EgressAccessLogs egressAccessLogs;

  private java.lang.String id;

  private java.util.Map<java.lang.String, java.lang.String> tags;

  private software.amazon.awssdk.services.mediapackagevod.model.CreatePackagingGroupRequest$BuilderImpl();
    Code:
       0: aload_0
       1: invokespecial #7                  // Method software/amazon/awssdk/services/mediapackagevod/model/MediaPackageVodRequest$BuilderImpl."<init>":()V
       4: aload_0
       5: invokestatic  #8                  // Method software/amazon/awssdk/core/util/DefaultSdkAutoConstructMap.getInstance:()Lsoftware/amazon/awssdk/core/util/DefaultSdkAutoConstructMap;
       8: putfield      #3                  // Field tags:Ljava/util/Map;
      11: return

  private software.amazon.awssdk.services.mediapackagevod.model.CreatePackagingGroupRequest$BuilderImpl(software.amazon.awssdk.services.mediapackagevod.model.CreatePackagingGroupRequest);
    Code:
       0: aload_0
       1: aload_1
       2: invokespecial #9                  // Method software/amazon/awssdk/services/mediapackagevod/model/MediaPackageVodRequest$BuilderImpl."<init>":(Lsoftware/amazon/awssdk/services/mediapackagevod/model/MediaPackageVodRequest;)V
       5: aload_0
       6: invokestatic  #8                  // Method software/amazon/awssdk/core/util/DefaultSdkAutoConstructMap.getInstance:()Lsoftware/amazon/awssdk/core/util/DefaultSdkAutoConstructMap;
       9: putfield      #3                  // Field tags:Ljava/util/Map;
      12: aload_0
      13: aload_1
      14: invokestatic  #10                 // Method software/amazon/awssdk/services/mediapackagevod/model/CreatePackagingGroupRequest.access$600:(Lsoftware/amazon/awssdk/services/mediapackagevod/model/CreatePackagingGroupRequest;)Lsoftware/amazon/awssdk/services/mediapackagevod/model/Authorization;
      17: invokevirtual #11                 // Method authorization:(Lsoftware/amazon/awssdk/services/mediapackagevod/model/Authorization;)Lsoftware/amazon/awssdk/services/mediapackagevod/model/CreatePackagingGroupRequest$Builder;
      20: pop
      21: aload_0
      22: aload_1
      23: invokestatic  #12                 // Method software/amazon/awssdk/services/mediapackagevod/model/CreatePackagingGroupRequest.access$700:(Lsoftware/amazon/awssdk/services/mediapackagevod/model/CreatePackagingGroupRequest;)Lsoftware/amazon/awssdk/services/mediapackagevod/model/EgressAccessLogs;
      26: invokevirtual #13                 // Method egressAccessLogs:(Lsoftware/amazon/awssdk/services/mediapackagevod/model/EgressAccessLogs;)Lsoftware/amazon/awssdk/services/mediapackagevod/model/CreatePackagingGroupRequest$Builder;
      29: pop
      30: aload_0
      31: aload_1
      32: invokestatic  #14                 // Method software/amazon/awssdk/services/mediapackagevod/model/CreatePackagingGroupRequest.access$800:(Lsoftware/amazon/awssdk/services/mediapackagevod/model/CreatePackagingGroupRequest;)Ljava/lang/String;
      35: invokevirtual #15                 // Method id:(Ljava/lang/String;)Lsoftware/amazon/awssdk/services/mediapackagevod/model/CreatePackagingGroupRequest$Builder;
      38: pop
      39: aload_0
      40: aload_1
      41: invokestatic  #16                 // Method software/amazon/awssdk/services/mediapackagevod/model/CreatePackagingGroupRequest.access$900:(Lsoftware/amazon/awssdk/services/mediapackagevod/model/CreatePackagingGroupRequest;)Ljava/util/Map;
      44: invokevirtual #17                 // Method tags:(Ljava/util/Map;)Lsoftware/amazon/awssdk/services/mediapackagevod/model/CreatePackagingGroupRequest$Builder;
      47: pop
      48: return

  public final software.amazon.awssdk.services.mediapackagevod.model.Authorization$Builder getAuthorization();
    Code:
       0: aload_0
       1: getfield      #6                  // Field authorization:Lsoftware/amazon/awssdk/services/mediapackagevod/model/Authorization;
       4: ifnull        17
       7: aload_0
       8: getfield      #6                  // Field authorization:Lsoftware/amazon/awssdk/services/mediapackagevod/model/Authorization;
      11: invokevirtual #18                 // Method software/amazon/awssdk/services/mediapackagevod/model/Authorization.toBuilder:()Lsoftware/amazon/awssdk/services/mediapackagevod/model/Authorization$Builder;
      14: goto          18
      17: aconst_null
      18: areturn

  public final software.amazon.awssdk.services.mediapackagevod.model.CreatePackagingGroupRequest$Builder authorization(software.amazon.awssdk.services.mediapackagevod.model.Authorization);
    Code:
       0: aload_0
       1: aload_1
       2: putfield      #6                  // Field authorization:Lsoftware/amazon/awssdk/services/mediapackagevod/model/Authorization;
       5: aload_0
       6: areturn

  public final void setAuthorization(software.amazon.awssdk.services.mediapackagevod.model.Authorization$BuilderImpl);
    Code:
       0: aload_0
       1: aload_1
       2: ifnull        12
       5: aload_1
       6: invokevirtual #19                 // Method software/amazon/awssdk/services/mediapackagevod/model/Authorization$BuilderImpl.build:()Lsoftware/amazon/awssdk/services/mediapackagevod/model/Authorization;
       9: goto          13
      12: aconst_null
      13: putfield      #6                  // Field authorization:Lsoftware/amazon/awssdk/services/mediapackagevod/model/Authorization;
      16: return

  public final software.amazon.awssdk.services.mediapackagevod.model.EgressAccessLogs$Builder getEgressAccessLogs();
    Code:
       0: aload_0
       1: getfield      #5                  // Field egressAccessLogs:Lsoftware/amazon/awssdk/services/mediapackagevod/model/EgressAccessLogs;
       4: ifnull        17
       7: aload_0
       8: getfield      #5                  // Field egressAccessLogs:Lsoftware/amazon/awssdk/services/mediapackagevod/model/EgressAccessLogs;
      11: invokevirtual #20                 // Method software/amazon/awssdk/services/mediapackagevod/model/EgressAccessLogs.toBuilder:()Lsoftware/amazon/awssdk/services/mediapackagevod/model/EgressAccessLogs$Builder;
      14: goto          18
      17: aconst_null
      18: areturn

  public final software.amazon.awssdk.services.mediapackagevod.model.CreatePackagingGroupRequest$Builder egressAccessLogs(software.amazon.awssdk.services.mediapackagevod.model.EgressAccessLogs);
    Code:
       0: aload_0
       1: aload_1
       2: putfield      #5                  // Field egressAccessLogs:Lsoftware/amazon/awssdk/services/mediapackagevod/model/EgressAccessLogs;
       5: aload_0
       6: areturn

  public final void setEgressAccessLogs(software.amazon.awssdk.services.mediapackagevod.model.EgressAccessLogs$BuilderImpl);
    Code:
       0: aload_0
       1: aload_1
       2: ifnull        12
       5: aload_1
       6: invokevirtual #21                 // Method software/amazon/awssdk/services/mediapackagevod/model/EgressAccessLogs$BuilderImpl.build:()Lsoftware/amazon/awssdk/services/mediapackagevod/model/EgressAccessLogs;
       9: goto          13
      12: aconst_null
      13: putfield      #5                  // Field egressAccessLogs:Lsoftware/amazon/awssdk/services/mediapackagevod/model/EgressAccessLogs;
      16: return

  public final java.lang.String getId();
    Code:
       0: aload_0
       1: getfield      #4                  // Field id:Ljava/lang/String;
       4: areturn

  public final software.amazon.awssdk.services.mediapackagevod.model.CreatePackagingGroupRequest$Builder id(java.lang.String);
    Code:
       0: aload_0
       1: aload_1
       2: putfield      #4                  // Field id:Ljava/lang/String;
       5: aload_0
       6: areturn

  public final void setId(java.lang.String);
    Code:
       0: aload_0
       1: aload_1
       2: putfield      #4                  // Field id:Ljava/lang/String;
       5: return

  public final java.util.Map<java.lang.String, java.lang.String> getTags();
    Code:
       0: aload_0
       1: getfield      #3                  // Field tags:Ljava/util/Map;
       4: instanceof    #22                 // class software/amazon/awssdk/core/util/SdkAutoConstructMap
       7: ifeq          12
      10: aconst_null
      11: areturn
      12: aload_0
      13: getfield      #3                  // Field tags:Ljava/util/Map;
      16: areturn

  public final software.amazon.awssdk.services.mediapackagevod.model.CreatePackagingGroupRequest$Builder tags(java.util.Map<java.lang.String, java.lang.String>);
    Code:
       0: aload_0
       1: aload_1
       2: invokestatic  #23                 // Method software/amazon/awssdk/services/mediapackagevod/model/TagsCopier.copy:(Ljava/util/Map;)Ljava/util/Map;
       5: putfield      #3                  // Field tags:Ljava/util/Map;
       8: aload_0
       9: areturn

  public final void setTags(java.util.Map<java.lang.String, java.lang.String>);
    Code:
       0: aload_0
       1: aload_1
       2: invokestatic  #23                 // Method software/amazon/awssdk/services/mediapackagevod/model/TagsCopier.copy:(Ljava/util/Map;)Ljava/util/Map;
       5: putfield      #3                  // Field tags:Ljava/util/Map;
       8: return

  public software.amazon.awssdk.services.mediapackagevod.model.CreatePackagingGroupRequest$Builder overrideConfiguration(software.amazon.awssdk.awscore.AwsRequestOverrideConfiguration);
    Code:
       0: aload_0
       1: aload_1
       2: invokespecial #24                 // Method software/amazon/awssdk/services/mediapackagevod/model/MediaPackageVodRequest$BuilderImpl.overrideConfiguration:(Lsoftware/amazon/awssdk/awscore/AwsRequestOverrideConfiguration;)Lsoftware/amazon/awssdk/awscore/AwsRequest$Builder;
       5: pop
       6: aload_0
       7: areturn

  public software.amazon.awssdk.services.mediapackagevod.model.CreatePackagingGroupRequest$Builder overrideConfiguration(java.util.function.Consumer<software.amazon.awssdk.awscore.AwsRequestOverrideConfiguration$Builder>);
    Code:
       0: aload_0
       1: aload_1
       2: invokespecial #25                 // Method software/amazon/awssdk/services/mediapackagevod/model/MediaPackageVodRequest$BuilderImpl.overrideConfiguration:(Ljava/util/function/Consumer;)Lsoftware/amazon/awssdk/awscore/AwsRequest$Builder;
       5: pop
       6: aload_0
       7: areturn

  public software.amazon.awssdk.services.mediapackagevod.model.CreatePackagingGroupRequest build();
    Code:
       0: new           #26                 // class software/amazon/awssdk/services/mediapackagevod/model/CreatePackagingGroupRequest
       3: dup
       4: aload_0
       5: aconst_null
       6: invokespecial #27                 // Method software/amazon/awssdk/services/mediapackagevod/model/CreatePackagingGroupRequest."<init>":(Lsoftware/amazon/awssdk/services/mediapackagevod/model/CreatePackagingGroupRequest$BuilderImpl;Lsoftware/amazon/awssdk/services/mediapackagevod/model/CreatePackagingGroupRequest$1;)V
       9: areturn

  public java.util.List<software.amazon.awssdk.core.SdkField<?>> sdkFields();
    Code:
       0: invokestatic  #28                 // Method software/amazon/awssdk/services/mediapackagevod/model/CreatePackagingGroupRequest.access$1100:()Ljava/util/List;
       3: areturn

  public software.amazon.awssdk.services.mediapackagevod.model.MediaPackageVodRequest build();
    Code:
       0: aload_0
       1: invokevirtual #29                 // Method build:()Lsoftware/amazon/awssdk/services/mediapackagevod/model/CreatePackagingGroupRequest;
       4: areturn

  public software.amazon.awssdk.awscore.AwsRequest build();
    Code:
       0: aload_0
       1: invokevirtual #29                 // Method build:()Lsoftware/amazon/awssdk/services/mediapackagevod/model/CreatePackagingGroupRequest;
       4: areturn

  public software.amazon.awssdk.awscore.AwsRequest$Builder overrideConfiguration(java.util.function.Consumer);
    Code:
       0: aload_0
       1: aload_1
       2: invokevirtual #30                 // Method overrideConfiguration:(Ljava/util/function/Consumer;)Lsoftware/amazon/awssdk/services/mediapackagevod/model/CreatePackagingGroupRequest$Builder;
       5: areturn

  public software.amazon.awssdk.awscore.AwsRequest$Builder overrideConfiguration(software.amazon.awssdk.awscore.AwsRequestOverrideConfiguration);
    Code:
       0: aload_0
       1: aload_1
       2: invokevirtual #31                 // Method overrideConfiguration:(Lsoftware/amazon/awssdk/awscore/AwsRequestOverrideConfiguration;)Lsoftware/amazon/awssdk/services/mediapackagevod/model/CreatePackagingGroupRequest$Builder;
       5: areturn

  public software.amazon.awssdk.core.SdkRequest build();
    Code:
       0: aload_0
       1: invokevirtual #29                 // Method build:()Lsoftware/amazon/awssdk/services/mediapackagevod/model/CreatePackagingGroupRequest;
       4: areturn

  public java.lang.Object build();
    Code:
       0: aload_0
       1: invokevirtual #29                 // Method build:()Lsoftware/amazon/awssdk/services/mediapackagevod/model/CreatePackagingGroupRequest;
       4: areturn

  static software.amazon.awssdk.services.mediapackagevod.model.Authorization access$000(software.amazon.awssdk.services.mediapackagevod.model.CreatePackagingGroupRequest$BuilderImpl);
    Code:
       0: aload_0
       1: getfield      #6                  // Field authorization:Lsoftware/amazon/awssdk/services/mediapackagevod/model/Authorization;
       4: areturn

  static software.amazon.awssdk.services.mediapackagevod.model.EgressAccessLogs access$100(software.amazon.awssdk.services.mediapackagevod.model.CreatePackagingGroupRequest$BuilderImpl);
    Code:
       0: aload_0
       1: getfield      #5                  // Field egressAccessLogs:Lsoftware/amazon/awssdk/services/mediapackagevod/model/EgressAccessLogs;
       4: areturn

  static java.lang.String access$200(software.amazon.awssdk.services.mediapackagevod.model.CreatePackagingGroupRequest$BuilderImpl);
    Code:
       0: aload_0
       1: getfield      #4                  // Field id:Ljava/lang/String;
       4: areturn

  static java.util.Map access$300(software.amazon.awssdk.services.mediapackagevod.model.CreatePackagingGroupRequest$BuilderImpl);
    Code:
       0: aload_0
       1: getfield      #3                  // Field tags:Ljava/util/Map;
       4: areturn

  software.amazon.awssdk.services.mediapackagevod.model.CreatePackagingGroupRequest$BuilderImpl(software.amazon.awssdk.services.mediapackagevod.model.CreatePackagingGroupRequest, software.amazon.awssdk.services.mediapackagevod.model.CreatePackagingGroupRequest$1);
    Code:
       0: aload_0
       1: aload_1
       2: invokespecial #2                  // Method "<init>":(Lsoftware/amazon/awssdk/services/mediapackagevod/model/CreatePackagingGroupRequest;)V
       5: return

  software.amazon.awssdk.services.mediapackagevod.model.CreatePackagingGroupRequest$BuilderImpl(software.amazon.awssdk.services.mediapackagevod.model.CreatePackagingGroupRequest$1);
    Code:
       0: aload_0
       1: invokespecial #1                  // Method "<init>":()V
       4: return
}
