Compiled from "DashPackage.java"
public interface software.amazon.awssdk.services.mediapackagevod.model.DashPackage$Builder extends software.amazon.awssdk.core.SdkPojo, software.amazon.awssdk.utils.builder.CopyableBuilder<software.amazon.awssdk.services.mediapackagevod.model.DashPackage$Builder, software.amazon.awssdk.services.mediapackagevod.model.DashPackage> {
  public abstract software.amazon.awssdk.services.mediapackagevod.model.DashPackage$Builder dashManifests(java.util.Collection<software.amazon.awssdk.services.mediapackagevod.model.DashManifest>);

  public abstract software.amazon.awssdk.services.mediapackagevod.model.DashPackage$Builder dashManifests(software.amazon.awssdk.services.mediapackagevod.model.DashManifest...);

  public abstract software.amazon.awssdk.services.mediapackagevod.model.DashPackage$Builder dashManifests(java.util.function.Consumer<software.amazon.awssdk.services.mediapackagevod.model.DashManifest$Builder>...);

  public abstract software.amazon.awssdk.services.mediapackagevod.model.DashPackage$Builder encryption(software.amazon.awssdk.services.mediapackagevod.model.DashEncryption);

  public default software.amazon.awssdk.services.mediapackagevod.model.DashPackage$Builder encryption(java.util.function.Consumer<software.amazon.awssdk.services.mediapackagevod.model.DashEncryption$Builder>);
    Code:
       0: aload_0
       1: invokestatic  #1                  // Method software/amazon/awssdk/services/mediapackagevod/model/DashEncryption.builder:()Lsoftware/amazon/awssdk/services/mediapackagevod/model/DashEncryption$Builder;
       4: aload_1
       5: invokeinterface #2,  2            // InterfaceMethod software/amazon/awssdk/services/mediapackagevod/model/DashEncryption$Builder.applyMutation:(Ljava/util/function/Consumer;)Lsoftware/amazon/awssdk/utils/builder/SdkBuilder;
      10: checkcast     #3                  // class software/amazon/awssdk/services/mediapackagevod/model/DashEncryption$Builder
      13: invokeinterface #4,  1            // InterfaceMethod software/amazon/awssdk/services/mediapackagevod/model/DashEncryption$Builder.build:()Ljava/lang/Object;
      18: checkcast     #5                  // class software/amazon/awssdk/services/mediapackagevod/model/DashEncryption
      21: invokeinterface #6,  2            // InterfaceMethod encryption:(Lsoftware/amazon/awssdk/services/mediapackagevod/model/DashEncryption;)Lsoftware/amazon/awssdk/services/mediapackagevod/model/DashPackage$Builder;
      26: areturn

  public abstract software.amazon.awssdk.services.mediapackagevod.model.DashPackage$Builder periodTriggersWithStrings(java.util.Collection<java.lang.String>);

  public abstract software.amazon.awssdk.services.mediapackagevod.model.DashPackage$Builder periodTriggersWithStrings(java.lang.String...);

  public abstract software.amazon.awssdk.services.mediapackagevod.model.DashPackage$Builder periodTriggers(java.util.Collection<software.amazon.awssdk.services.mediapackagevod.model.PeriodTriggersElement>);

  public abstract software.amazon.awssdk.services.mediapackagevod.model.DashPackage$Builder periodTriggers(software.amazon.awssdk.services.mediapackagevod.model.PeriodTriggersElement...);

  public abstract software.amazon.awssdk.services.mediapackagevod.model.DashPackage$Builder segmentDurationSeconds(java.lang.Integer);

  public abstract software.amazon.awssdk.services.mediapackagevod.model.DashPackage$Builder segmentTemplateFormat(java.lang.String);

  public abstract software.amazon.awssdk.services.mediapackagevod.model.DashPackage$Builder segmentTemplateFormat(software.amazon.awssdk.services.mediapackagevod.model.SegmentTemplateFormat);
}
