Compiled from "UpdatePackagingGroupRequest.java"
final class software.amazon.awssdk.services.mediapackagevod.model.UpdatePackagingGroupRequest$BuilderImpl extends software.amazon.awssdk.services.mediapackagevod.model.MediaPackageVodRequest$BuilderImpl implements software.amazon.awssdk.services.mediapackagevod.model.UpdatePackagingGroupRequest$Builder {
  private software.amazon.awssdk.services.mediapackagevod.model.Authorization authorization;

  private java.lang.String id;

  private software.amazon.awssdk.services.mediapackagevod.model.UpdatePackagingGroupRequest$BuilderImpl();
    Code:
       0: aload_0
       1: invokespecial #5                  // Method software/amazon/awssdk/services/mediapackagevod/model/MediaPackageVodRequest$BuilderImpl."<init>":()V
       4: return

  private software.amazon.awssdk.services.mediapackagevod.model.UpdatePackagingGroupRequest$BuilderImpl(software.amazon.awssdk.services.mediapackagevod.model.UpdatePackagingGroupRequest);
    Code:
       0: aload_0
       1: aload_1
       2: invokespecial #6                  // Method software/amazon/awssdk/services/mediapackagevod/model/MediaPackageVodRequest$BuilderImpl."<init>":(Lsoftware/amazon/awssdk/services/mediapackagevod/model/MediaPackageVodRequest;)V
       5: aload_0
       6: aload_1
       7: invokestatic  #7                  // Method software/amazon/awssdk/services/mediapackagevod/model/UpdatePackagingGroupRequest.access$400:(Lsoftware/amazon/awssdk/services/mediapackagevod/model/UpdatePackagingGroupRequest;)Lsoftware/amazon/awssdk/services/mediapackagevod/model/Authorization;
      10: invokevirtual #8                  // Method authorization:(Lsoftware/amazon/awssdk/services/mediapackagevod/model/Authorization;)Lsoftware/amazon/awssdk/services/mediapackagevod/model/UpdatePackagingGroupRequest$Builder;
      13: pop
      14: aload_0
      15: aload_1
      16: invokestatic  #9                  // Method software/amazon/awssdk/services/mediapackagevod/model/UpdatePackagingGroupRequest.access$500:(Lsoftware/amazon/awssdk/services/mediapackagevod/model/UpdatePackagingGroupRequest;)Ljava/lang/String;
      19: invokevirtual #10                 // Method id:(Ljava/lang/String;)Lsoftware/amazon/awssdk/services/mediapackagevod/model/UpdatePackagingGroupRequest$Builder;
      22: pop
      23: return

  public final software.amazon.awssdk.services.mediapackagevod.model.Authorization$Builder getAuthorization();
    Code:
       0: aload_0
       1: getfield      #4                  // Field authorization:Lsoftware/amazon/awssdk/services/mediapackagevod/model/Authorization;
       4: ifnull        17
       7: aload_0
       8: getfield      #4                  // Field authorization:Lsoftware/amazon/awssdk/services/mediapackagevod/model/Authorization;
      11: invokevirtual #11                 // Method software/amazon/awssdk/services/mediapackagevod/model/Authorization.toBuilder:()Lsoftware/amazon/awssdk/services/mediapackagevod/model/Authorization$Builder;
      14: goto          18
      17: aconst_null
      18: areturn

  public final software.amazon.awssdk.services.mediapackagevod.model.UpdatePackagingGroupRequest$Builder authorization(software.amazon.awssdk.services.mediapackagevod.model.Authorization);
    Code:
       0: aload_0
       1: aload_1
       2: putfield      #4                  // Field authorization:Lsoftware/amazon/awssdk/services/mediapackagevod/model/Authorization;
       5: aload_0
       6: areturn

  public final void setAuthorization(software.amazon.awssdk.services.mediapackagevod.model.Authorization$BuilderImpl);
    Code:
       0: aload_0
       1: aload_1
       2: ifnull        12
       5: aload_1
       6: invokevirtual #12                 // Method software/amazon/awssdk/services/mediapackagevod/model/Authorization$BuilderImpl.build:()Lsoftware/amazon/awssdk/services/mediapackagevod/model/Authorization;
       9: goto          13
      12: aconst_null
      13: putfield      #4                  // Field authorization:Lsoftware/amazon/awssdk/services/mediapackagevod/model/Authorization;
      16: return

  public final java.lang.String getId();
    Code:
       0: aload_0
       1: getfield      #3                  // Field id:Ljava/lang/String;
       4: areturn

  public final software.amazon.awssdk.services.mediapackagevod.model.UpdatePackagingGroupRequest$Builder id(java.lang.String);
    Code:
       0: aload_0
       1: aload_1
       2: putfield      #3                  // Field id:Ljava/lang/String;
       5: aload_0
       6: areturn

  public final void setId(java.lang.String);
    Code:
       0: aload_0
       1: aload_1
       2: putfield      #3                  // Field id:Ljava/lang/String;
       5: return

  public software.amazon.awssdk.services.mediapackagevod.model.UpdatePackagingGroupRequest$Builder overrideConfiguration(software.amazon.awssdk.awscore.AwsRequestOverrideConfiguration);
    Code:
       0: aload_0
       1: aload_1
       2: invokespecial #13                 // Method software/amazon/awssdk/services/mediapackagevod/model/MediaPackageVodRequest$BuilderImpl.overrideConfiguration:(Lsoftware/amazon/awssdk/awscore/AwsRequestOverrideConfiguration;)Lsoftware/amazon/awssdk/awscore/AwsRequest$Builder;
       5: pop
       6: aload_0
       7: areturn

  public software.amazon.awssdk.services.mediapackagevod.model.UpdatePackagingGroupRequest$Builder overrideConfiguration(java.util.function.Consumer<software.amazon.awssdk.awscore.AwsRequestOverrideConfiguration$Builder>);
    Code:
       0: aload_0
       1: aload_1
       2: invokespecial #14                 // Method software/amazon/awssdk/services/mediapackagevod/model/MediaPackageVodRequest$BuilderImpl.overrideConfiguration:(Ljava/util/function/Consumer;)Lsoftware/amazon/awssdk/awscore/AwsRequest$Builder;
       5: pop
       6: aload_0
       7: areturn

  public software.amazon.awssdk.services.mediapackagevod.model.UpdatePackagingGroupRequest build();
    Code:
       0: new           #15                 // class software/amazon/awssdk/services/mediapackagevod/model/UpdatePackagingGroupRequest
       3: dup
       4: aload_0
       5: aconst_null
       6: invokespecial #16                 // Method software/amazon/awssdk/services/mediapackagevod/model/UpdatePackagingGroupRequest."<init>":(Lsoftware/amazon/awssdk/services/mediapackagevod/model/UpdatePackagingGroupRequest$BuilderImpl;Lsoftware/amazon/awssdk/services/mediapackagevod/model/UpdatePackagingGroupRequest$1;)V
       9: areturn

  public java.util.List<software.amazon.awssdk.core.SdkField<?>> sdkFields();
    Code:
       0: invokestatic  #17                 // Method software/amazon/awssdk/services/mediapackagevod/model/UpdatePackagingGroupRequest.access$700:()Ljava/util/List;
       3: areturn

  public software.amazon.awssdk.services.mediapackagevod.model.MediaPackageVodRequest build();
    Code:
       0: aload_0
       1: invokevirtual #18                 // Method build:()Lsoftware/amazon/awssdk/services/mediapackagevod/model/UpdatePackagingGroupRequest;
       4: areturn

  public software.amazon.awssdk.awscore.AwsRequest build();
    Code:
       0: aload_0
       1: invokevirtual #18                 // Method build:()Lsoftware/amazon/awssdk/services/mediapackagevod/model/UpdatePackagingGroupRequest;
       4: areturn

  public software.amazon.awssdk.awscore.AwsRequest$Builder overrideConfiguration(java.util.function.Consumer);
    Code:
       0: aload_0
       1: aload_1
       2: invokevirtual #19                 // Method overrideConfiguration:(Ljava/util/function/Consumer;)Lsoftware/amazon/awssdk/services/mediapackagevod/model/UpdatePackagingGroupRequest$Builder;
       5: areturn

  public software.amazon.awssdk.awscore.AwsRequest$Builder overrideConfiguration(software.amazon.awssdk.awscore.AwsRequestOverrideConfiguration);
    Code:
       0: aload_0
       1: aload_1
       2: invokevirtual #20                 // Method overrideConfiguration:(Lsoftware/amazon/awssdk/awscore/AwsRequestOverrideConfiguration;)Lsoftware/amazon/awssdk/services/mediapackagevod/model/UpdatePackagingGroupRequest$Builder;
       5: areturn

  public software.amazon.awssdk.core.SdkRequest build();
    Code:
       0: aload_0
       1: invokevirtual #18                 // Method build:()Lsoftware/amazon/awssdk/services/mediapackagevod/model/UpdatePackagingGroupRequest;
       4: areturn

  public java.lang.Object build();
    Code:
       0: aload_0
       1: invokevirtual #18                 // Method build:()Lsoftware/amazon/awssdk/services/mediapackagevod/model/UpdatePackagingGroupRequest;
       4: areturn

  static software.amazon.awssdk.services.mediapackagevod.model.Authorization access$000(software.amazon.awssdk.services.mediapackagevod.model.UpdatePackagingGroupRequest$BuilderImpl);
    Code:
       0: aload_0
       1: getfield      #4                  // Field authorization:Lsoftware/amazon/awssdk/services/mediapackagevod/model/Authorization;
       4: areturn

  static java.lang.String access$100(software.amazon.awssdk.services.mediapackagevod.model.UpdatePackagingGroupRequest$BuilderImpl);
    Code:
       0: aload_0
       1: getfield      #3                  // Field id:Ljava/lang/String;
       4: areturn

  software.amazon.awssdk.services.mediapackagevod.model.UpdatePackagingGroupRequest$BuilderImpl(software.amazon.awssdk.services.mediapackagevod.model.UpdatePackagingGroupRequest, software.amazon.awssdk.services.mediapackagevod.model.UpdatePackagingGroupRequest$1);
    Code:
       0: aload_0
       1: aload_1
       2: invokespecial #2                  // Method "<init>":(Lsoftware/amazon/awssdk/services/mediapackagevod/model/UpdatePackagingGroupRequest;)V
       5: return

  software.amazon.awssdk.services.mediapackagevod.model.UpdatePackagingGroupRequest$BuilderImpl(software.amazon.awssdk.services.mediapackagevod.model.UpdatePackagingGroupRequest$1);
    Code:
       0: aload_0
       1: invokespecial #1                  // Method "<init>":()V
       4: return
}
