Compiled from "Execution.java"
public class org.apache.maven.plugin.lifecycle.Execution implements java.io.Serializable {
  private java.lang.Object configuration;

  private java.util.List<java.lang.String> goals;

  public org.apache.maven.plugin.lifecycle.Execution();
    Code:
       0: aload_0
       1: invokespecial #1                  // Method java/lang/Object."<init>":()V
       4: return

  public void addGoal(java.lang.String);
    Code:
       0: aload_0
       1: invokevirtual #2                  // Method getGoals:()Ljava/util/List;
       4: aload_1
       5: invokeinterface #3,  2            // InterfaceMethod java/util/List.add:(Ljava/lang/Object;)Z
      10: pop
      11: return

  public java.lang.Object getConfiguration();
    Code:
       0: aload_0
       1: getfield      #4                  // Field configuration:Ljava/lang/Object;
       4: areturn

  public java.util.List<java.lang.String> getGoals();
    Code:
       0: aload_0
       1: getfield      #5                  // Field goals:Ljava/util/List;
       4: ifnonnull     18
       7: aload_0
       8: new           #6                  // class java/util/ArrayList
      11: dup
      12: invokespecial #7                  // Method java/util/ArrayList."<init>":()V
      15: putfield      #5                  // Field goals:Ljava/util/List;
      18: aload_0
      19: getfield      #5                  // Field goals:Ljava/util/List;
      22: areturn

  public void removeGoal(java.lang.String);
    Code:
       0: aload_0
       1: invokevirtual #2                  // Method getGoals:()Ljava/util/List;
       4: aload_1
       5: invokeinterface #8,  2            // InterfaceMethod java/util/List.remove:(Ljava/lang/Object;)Z
      10: pop
      11: return

  public void setConfiguration(java.lang.Object);
    Code:
       0: aload_0
       1: aload_1
       2: putfield      #4                  // Field configuration:Ljava/lang/Object;
       5: return

  public void setGoals(java.util.List<java.lang.String>);
    Code:
       0: aload_0
       1: aload_1
       2: putfield      #5                  // Field goals:Ljava/util/List;
       5: return
}
