Compiled from "ContextNames.java"
public class org.jboss.as.naming.deployment.ContextNames$BindInfo {
  private final org.jboss.msc.service.ServiceName parentContextServiceName;

  private final org.jboss.msc.service.ServiceName binderServiceName;

  private final java.lang.String bindName;

  private final java.lang.String absoluteJndiName;

  private org.jboss.as.naming.deployment.ContextNames$BindInfo(org.jboss.msc.service.ServiceName, java.lang.String);
    Code:
       0: aload_0
       1: invokespecial #2                  // Method java/lang/Object."<init>":()V
       4: aload_0
       5: aload_1
       6: putfield      #3                  // Field parentContextServiceName:Lorg/jboss/msc/service/ServiceName;
       9: aload_0
      10: aload_1
      11: aload_2
      12: invokestatic  #4                  // Method org/jboss/as/naming/deployment/ContextNames.buildServiceName:(Lorg/jboss/msc/service/ServiceName;Ljava/lang/String;)Lorg/jboss/msc/service/ServiceName;
      15: putfield      #5                  // Field binderServiceName:Lorg/jboss/msc/service/ServiceName;
      18: aload_0
      19: aload_2
      20: putfield      #6                  // Field bindName:Ljava/lang/String;
      23: aload_0
      24: aload_0
      25: invokespecial #7                  // Method generateAbsoluteJndiName:()Ljava/lang/String;
      28: putfield      #8                  // Field absoluteJndiName:Ljava/lang/String;
      31: return

  public org.jboss.msc.service.ServiceName getParentContextServiceName();
    Code:
       0: aload_0
       1: getfield      #3                  // Field parentContextServiceName:Lorg/jboss/msc/service/ServiceName;
       4: areturn

  public org.jboss.msc.service.ServiceName getBinderServiceName();
    Code:
       0: aload_0
       1: getfield      #5                  // Field binderServiceName:Lorg/jboss/msc/service/ServiceName;
       4: areturn

  public java.lang.String getBindName();
    Code:
       0: aload_0
       1: getfield      #6                  // Field bindName:Ljava/lang/String;
       4: areturn

  public java.lang.String getAbsoluteJndiName();
    Code:
       0: aload_0
       1: getfield      #8                  // Field absoluteJndiName:Ljava/lang/String;
       4: areturn

  public java.lang.String toString();
    Code:
       0: new           #9                  // class java/lang/StringBuilder
       3: dup
       4: invokespecial #10                 // Method java/lang/StringBuilder."<init>":()V
       7: ldc           #11                 // String BindInfo{parentContextServiceName=
       9: invokevirtual #12                 // Method java/lang/StringBuilder.append:(Ljava/lang/String;)Ljava/lang/StringBuilder;
      12: aload_0
      13: getfield      #3                  // Field parentContextServiceName:Lorg/jboss/msc/service/ServiceName;
      16: invokevirtual #13                 // Method java/lang/StringBuilder.append:(Ljava/lang/Object;)Ljava/lang/StringBuilder;
      19: ldc           #14                 // String , binderServiceName=
      21: invokevirtual #12                 // Method java/lang/StringBuilder.append:(Ljava/lang/String;)Ljava/lang/StringBuilder;
      24: aload_0
      25: getfield      #5                  // Field binderServiceName:Lorg/jboss/msc/service/ServiceName;
      28: invokevirtual #13                 // Method java/lang/StringBuilder.append:(Ljava/lang/Object;)Ljava/lang/StringBuilder;
      31: ldc           #15                 // String , bindName=\'
      33: invokevirtual #12                 // Method java/lang/StringBuilder.append:(Ljava/lang/String;)Ljava/lang/StringBuilder;
      36: aload_0
      37: getfield      #6                  // Field bindName:Ljava/lang/String;
      40: invokevirtual #12                 // Method java/lang/StringBuilder.append:(Ljava/lang/String;)Ljava/lang/StringBuilder;
      43: bipush        39
      45: invokevirtual #16                 // Method java/lang/StringBuilder.append:(C)Ljava/lang/StringBuilder;
      48: bipush        125
      50: invokevirtual #16                 // Method java/lang/StringBuilder.append:(C)Ljava/lang/StringBuilder;
      53: invokevirtual #17                 // Method java/lang/StringBuilder.toString:()Ljava/lang/String;
      56: areturn

  private java.lang.String generateAbsoluteJndiName();
    Code:
       0: new           #18                 // class java/lang/StringBuffer
       3: dup
       4: invokespecial #19                 // Method java/lang/StringBuffer."<init>":()V
       7: astore_1
       8: aload_0
       9: getfield      #3                  // Field parentContextServiceName:Lorg/jboss/msc/service/ServiceName;
      12: getstatic     #20                 // Field org/jboss/as/naming/deployment/ContextNames.EXPORTED_CONTEXT_SERVICE_NAME:Lorg/jboss/msc/service/ServiceName;
      15: invokevirtual #21                 // Method org/jboss/msc/service/ServiceName.equals:(Lorg/jboss/msc/service/ServiceName;)Z
      18: ifeq          31
      21: aload_1
      22: ldc           #22                 // String java:jboss/exported/
      24: invokevirtual #23                 // Method java/lang/StringBuffer.append:(Ljava/lang/String;)Ljava/lang/StringBuffer;
      27: pop
      28: goto          166
      31: aload_0
      32: getfield      #3                  // Field parentContextServiceName:Lorg/jboss/msc/service/ServiceName;
      35: getstatic     #24                 // Field org/jboss/as/naming/deployment/ContextNames.JBOSS_CONTEXT_SERVICE_NAME:Lorg/jboss/msc/service/ServiceName;
      38: invokevirtual #21                 // Method org/jboss/msc/service/ServiceName.equals:(Lorg/jboss/msc/service/ServiceName;)Z
      41: ifeq          54
      44: aload_1
      45: ldc           #25                 // String java:jboss/
      47: invokevirtual #23                 // Method java/lang/StringBuffer.append:(Ljava/lang/String;)Ljava/lang/StringBuffer;
      50: pop
      51: goto          166
      54: aload_0
      55: getfield      #3                  // Field parentContextServiceName:Lorg/jboss/msc/service/ServiceName;
      58: getstatic     #26                 // Field org/jboss/as/naming/deployment/ContextNames.APPLICATION_CONTEXT_SERVICE_NAME:Lorg/jboss/msc/service/ServiceName;
      61: invokevirtual #21                 // Method org/jboss/msc/service/ServiceName.equals:(Lorg/jboss/msc/service/ServiceName;)Z
      64: ifeq          77
      67: aload_1
      68: ldc           #27                 // String java:app/
      70: invokevirtual #23                 // Method java/lang/StringBuffer.append:(Ljava/lang/String;)Ljava/lang/StringBuffer;
      73: pop
      74: goto          166
      77: aload_0
      78: getfield      #3                  // Field parentContextServiceName:Lorg/jboss/msc/service/ServiceName;
      81: getstatic     #28                 // Field org/jboss/as/naming/deployment/ContextNames.MODULE_CONTEXT_SERVICE_NAME:Lorg/jboss/msc/service/ServiceName;
      84: invokevirtual #21                 // Method org/jboss/msc/service/ServiceName.equals:(Lorg/jboss/msc/service/ServiceName;)Z
      87: ifeq          100
      90: aload_1
      91: ldc           #29                 // String java:module/
      93: invokevirtual #23                 // Method java/lang/StringBuffer.append:(Ljava/lang/String;)Ljava/lang/StringBuffer;
      96: pop
      97: goto          166
     100: aload_0
     101: getfield      #3                  // Field parentContextServiceName:Lorg/jboss/msc/service/ServiceName;
     104: getstatic     #30                 // Field org/jboss/as/naming/deployment/ContextNames.COMPONENT_CONTEXT_SERVICE_NAME:Lorg/jboss/msc/service/ServiceName;
     107: invokevirtual #21                 // Method org/jboss/msc/service/ServiceName.equals:(Lorg/jboss/msc/service/ServiceName;)Z
     110: ifeq          123
     113: aload_1
     114: ldc           #31                 // String java:comp/
     116: invokevirtual #23                 // Method java/lang/StringBuffer.append:(Ljava/lang/String;)Ljava/lang/StringBuffer;
     119: pop
     120: goto          166
     123: aload_0
     124: getfield      #3                  // Field parentContextServiceName:Lorg/jboss/msc/service/ServiceName;
     127: getstatic     #32                 // Field org/jboss/as/naming/deployment/ContextNames.GLOBAL_CONTEXT_SERVICE_NAME:Lorg/jboss/msc/service/ServiceName;
     130: invokevirtual #21                 // Method org/jboss/msc/service/ServiceName.equals:(Lorg/jboss/msc/service/ServiceName;)Z
     133: ifeq          146
     136: aload_1
     137: ldc           #33                 // String java:global/
     139: invokevirtual #23                 // Method java/lang/StringBuffer.append:(Ljava/lang/String;)Ljava/lang/StringBuffer;
     142: pop
     143: goto          166
     146: aload_0
     147: getfield      #3                  // Field parentContextServiceName:Lorg/jboss/msc/service/ServiceName;
     150: getstatic     #34                 // Field org/jboss/as/naming/deployment/ContextNames.JAVA_CONTEXT_SERVICE_NAME:Lorg/jboss/msc/service/ServiceName;
     153: invokevirtual #21                 // Method org/jboss/msc/service/ServiceName.equals:(Lorg/jboss/msc/service/ServiceName;)Z
     156: ifeq          166
     159: aload_1
     160: ldc           #35                 // String java:/
     162: invokevirtual #23                 // Method java/lang/StringBuffer.append:(Ljava/lang/String;)Ljava/lang/StringBuffer;
     165: pop
     166: aload_1
     167: aload_0
     168: getfield      #6                  // Field bindName:Ljava/lang/String;
     171: invokevirtual #23                 // Method java/lang/StringBuffer.append:(Ljava/lang/String;)Ljava/lang/StringBuffer;
     174: pop
     175: aload_1
     176: invokevirtual #36                 // Method java/lang/StringBuffer.toString:()Ljava/lang/String;
     179: areturn

  public void setupLookupInjection(org.jboss.msc.service.ServiceBuilder<?>, org.jboss.msc.inject.Injector<org.jboss.as.naming.ManagedReferenceFactory>, org.jboss.as.server.deployment.DeploymentUnit, boolean);
    Code:
       0: aload_3
       1: getstatic     #37                 // Field org/jboss/as/naming/deployment/Attachments.EXTERNAL_CONTEXTS:Lorg/jboss/as/server/deployment/AttachmentKey;
       4: invokeinterface #38,  2           // InterfaceMethod org/jboss/as/server/deployment/DeploymentUnit.getAttachment:(Lorg/jboss/as/server/deployment/AttachmentKey;)Ljava/lang/Object;
       9: checkcast     #39                 // class org/jboss/as/naming/context/external/ExternalContexts
      12: astore        5
      14: aload         5
      16: ifnull        33
      19: aload         5
      21: aload_0
      22: invokevirtual #40                 // Method getBinderServiceName:()Lorg/jboss/msc/service/ServiceName;
      25: invokeinterface #41,  2           // InterfaceMethod org/jboss/as/naming/context/external/ExternalContexts.getParentExternalContext:(Lorg/jboss/msc/service/ServiceName;)Lorg/jboss/msc/service/ServiceName;
      30: goto          34
      33: aconst_null
      34: astore        6
      36: aload         6
      38: ifnonnull     48
      41: aload_0
      42: invokevirtual #40                 // Method getBinderServiceName:()Lorg/jboss/msc/service/ServiceName;
      45: goto          50
      48: aload         6
      50: astore        7
      52: iload         4
      54: ifeq          63
      57: getstatic     #42                 // Field org/jboss/msc/service/ServiceBuilder$DependencyType.OPTIONAL:Lorg/jboss/msc/service/ServiceBuilder$DependencyType;
      60: goto          66
      63: getstatic     #43                 // Field org/jboss/msc/service/ServiceBuilder$DependencyType.REQUIRED:Lorg/jboss/msc/service/ServiceBuilder$DependencyType;
      66: astore        8
      68: aload_1
      69: aload         8
      71: aload         7
      73: invokeinterface #44,  3           // InterfaceMethod org/jboss/msc/service/ServiceBuilder.addDependency:(Lorg/jboss/msc/service/ServiceBuilder$DependencyType;Lorg/jboss/msc/service/ServiceName;)Lorg/jboss/msc/service/ServiceBuilder;
      78: pop
      79: new           #45                 // class org/jboss/as/naming/deployment/ContextNames$BindInfo$1
      82: dup
      83: aload_0
      84: aload_2
      85: iload         4
      87: invokespecial #46                 // Method org/jboss/as/naming/deployment/ContextNames$BindInfo$1."<init>":(Lorg/jboss/as/naming/deployment/ContextNames$BindInfo;Lorg/jboss/msc/inject/Injector;Z)V
      90: astore        9
      92: aload_1
      93: aload_0
      94: invokevirtual #47                 // Method getParentContextServiceName:()Lorg/jboss/msc/service/ServiceName;
      97: ldc           #48                 // class org/jboss/as/naming/NamingStore
      99: aload         9
     101: invokeinterface #49,  4           // InterfaceMethod org/jboss/msc/service/ServiceBuilder.addDependency:(Lorg/jboss/msc/service/ServiceName;Ljava/lang/Class;Lorg/jboss/msc/inject/Injector;)Lorg/jboss/msc/service/ServiceBuilder;
     106: pop
     107: return

  org.jboss.as.naming.deployment.ContextNames$BindInfo(org.jboss.msc.service.ServiceName, java.lang.String, org.jboss.as.naming.deployment.ContextNames$1);
    Code:
       0: aload_0
       1: aload_1
       2: aload_2
       3: invokespecial #1                  // Method "<init>":(Lorg/jboss/msc/service/ServiceName;Ljava/lang/String;)V
       6: return
}
