Compiled from "RuntimeBindReleaseService.java"
public class org.jboss.as.naming.deployment.RuntimeBindReleaseService$References {
  private volatile java.util.List<org.jboss.as.naming.service.BinderService> services;

  private org.jboss.as.naming.deployment.RuntimeBindReleaseService$References();
    Code:
       0: aload_0
       1: invokespecial #2                  // Method java/lang/Object."<init>":()V
       4: return

  public void add(org.jboss.as.naming.service.BinderService);
    Code:
       0: aload_0
       1: dup
       2: astore_2
       3: monitorenter
       4: aload_0
       5: getfield      #3                  // Field services:Ljava/util/List;
       8: ifnonnull     22
      11: aload_0
      12: new           #4                  // class java/util/ArrayList
      15: dup
      16: invokespecial #5                  // Method java/util/ArrayList."<init>":()V
      19: putfield      #3                  // Field services:Ljava/util/List;
      22: aload_0
      23: getfield      #3                  // Field services:Ljava/util/List;
      26: aload_1
      27: invokeinterface #6,  2            // InterfaceMethod java/util/List.add:(Ljava/lang/Object;)Z
      32: pop
      33: aload_2
      34: monitorexit
      35: goto          43
      38: astore_3
      39: aload_2
      40: monitorexit
      41: aload_3
      42: athrow
      43: return
    Exception table:
       from    to  target type
           4    35    38   any
          38    41    38   any

  public boolean contains(org.jboss.msc.service.ServiceName);
    Code:
       0: aload_0
       1: dup
       2: astore_2
       3: monitorenter
       4: aload_0
       5: getfield      #3                  // Field services:Ljava/util/List;
       8: ifnull        60
      11: aload_0
      12: getfield      #3                  // Field services:Ljava/util/List;
      15: invokeinterface #7,  1            // InterfaceMethod java/util/List.iterator:()Ljava/util/Iterator;
      20: astore_3
      21: aload_3
      22: invokeinterface #8,  1            // InterfaceMethod java/util/Iterator.hasNext:()Z
      27: ifeq          60
      30: aload_3
      31: invokeinterface #9,  1            // InterfaceMethod java/util/Iterator.next:()Ljava/lang/Object;
      36: checkcast     #10                 // class org/jboss/as/naming/service/BinderService
      39: astore        4
      41: aload_1
      42: aload         4
      44: invokevirtual #11                 // Method org/jboss/as/naming/service/BinderService.getServiceName:()Lorg/jboss/msc/service/ServiceName;
      47: invokevirtual #12                 // Method org/jboss/msc/service/ServiceName.equals:(Lorg/jboss/msc/service/ServiceName;)Z
      50: ifeq          57
      53: iconst_1
      54: aload_2
      55: monitorexit
      56: ireturn
      57: goto          21
      60: iconst_0
      61: aload_2
      62: monitorexit
      63: ireturn
      64: astore        5
      66: aload_2
      67: monitorexit
      68: aload         5
      70: athrow
    Exception table:
       from    to  target type
           4    56    64   any
          57    63    64   any
          64    68    64   any

  public void releaseAll();
    Code:
       0: aload_0
       1: dup
       2: astore_1
       3: monitorenter
       4: aload_0
       5: getfield      #3                  // Field services:Ljava/util/List;
       8: ifnull        67
      11: aload_0
      12: getfield      #3                  // Field services:Ljava/util/List;
      15: invokeinterface #7,  1            // InterfaceMethod java/util/List.iterator:()Ljava/util/Iterator;
      20: astore_2
      21: aload_2
      22: invokeinterface #8,  1            // InterfaceMethod java/util/Iterator.hasNext:()Z
      27: ifeq          62
      30: aload_2
      31: invokeinterface #9,  1            // InterfaceMethod java/util/Iterator.next:()Ljava/lang/Object;
      36: checkcast     #10                 // class org/jboss/as/naming/service/BinderService
      39: astore_3
      40: aload_3
      41: invokevirtual #13                 // Method org/jboss/as/naming/service/BinderService.release:()V
      44: goto          59
      47: astore        4
      49: getstatic     #15                 // Field org/jboss/as/naming/logging/NamingLogger.ROOT_LOGGER:Lorg/jboss/as/naming/logging/NamingLogger;
      52: aload         4
      54: invokeinterface #16,  2           // InterfaceMethod org/jboss/as/naming/logging/NamingLogger.failedToReleaseBinderService:(Ljava/lang/Throwable;)V
      59: goto          21
      62: aload_0
      63: aconst_null
      64: putfield      #3                  // Field services:Ljava/util/List;
      67: aload_1
      68: monitorexit
      69: goto          79
      72: astore        5
      74: aload_1
      75: monitorexit
      76: aload         5
      78: athrow
      79: return
    Exception table:
       from    to  target type
          40    44    47   Class java/lang/Throwable
           4    69    72   any
          72    76    72   any

  org.jboss.as.naming.deployment.RuntimeBindReleaseService$References(org.jboss.as.naming.deployment.RuntimeBindReleaseService$1);
    Code:
       0: aload_0
       1: invokespecial #1                  // Method "<init>":()V
       4: return
}
