Compiled from "OptimisticLockStyle.java"
public final class org.hibernate.engine.OptimisticLockStyle extends java.lang.Enum<org.hibernate.engine.OptimisticLockStyle> {
  public static final org.hibernate.engine.OptimisticLockStyle NONE;

  public static final org.hibernate.engine.OptimisticLockStyle VERSION;

  public static final org.hibernate.engine.OptimisticLockStyle DIRTY;

  public static final org.hibernate.engine.OptimisticLockStyle ALL;

  private final int oldCode;

  private static final org.hibernate.engine.OptimisticLockStyle[] $VALUES;

  public static org.hibernate.engine.OptimisticLockStyle[] values();
    Code:
       0: getstatic     #1                  // Field $VALUES:[Lorg/hibernate/engine/OptimisticLockStyle;
       3: invokevirtual #2                  // Method "[Lorg/hibernate/engine/OptimisticLockStyle;".clone:()Ljava/lang/Object;
       6: checkcast     #3                  // class "[Lorg/hibernate/engine/OptimisticLockStyle;"
       9: areturn

  public static org.hibernate.engine.OptimisticLockStyle valueOf(java.lang.String);
    Code:
       0: ldc           #4                  // class org/hibernate/engine/OptimisticLockStyle
       2: aload_0
       3: invokestatic  #5                  // Method java/lang/Enum.valueOf:(Ljava/lang/Class;Ljava/lang/String;)Ljava/lang/Enum;
       6: checkcast     #4                  // class org/hibernate/engine/OptimisticLockStyle
       9: areturn

  private org.hibernate.engine.OptimisticLockStyle(int);
    Code:
       0: aload_0
       1: aload_1
       2: iload_2
       3: invokespecial #6                  // Method java/lang/Enum."<init>":(Ljava/lang/String;I)V
       6: aload_0
       7: iload_3
       8: putfield      #7                  // Field oldCode:I
      11: return

  public int getOldCode();
    Code:
       0: aload_0
       1: getfield      #7                  // Field oldCode:I
       4: ireturn

  public static org.hibernate.engine.OptimisticLockStyle interpretOldCode(int);
    Code:
       0: iload_0
       1: tableswitch   { // -1 to 2
                    -1: 32
                     0: 36
                     1: 40
                     2: 44
               default: 48
          }
      32: getstatic     #8                  // Field NONE:Lorg/hibernate/engine/OptimisticLockStyle;
      35: areturn
      36: getstatic     #9                  // Field VERSION:Lorg/hibernate/engine/OptimisticLockStyle;
      39: areturn
      40: getstatic     #10                 // Field DIRTY:Lorg/hibernate/engine/OptimisticLockStyle;
      43: areturn
      44: getstatic     #11                 // Field ALL:Lorg/hibernate/engine/OptimisticLockStyle;
      47: areturn
      48: new           #12                 // class java/lang/IllegalArgumentException
      51: dup
      52: new           #13                 // class java/lang/StringBuilder
      55: dup
      56: invokespecial #14                 // Method java/lang/StringBuilder."<init>":()V
      59: ldc           #15                 // String Illegal legacy optimistic lock style code :
      61: invokevirtual #16                 // Method java/lang/StringBuilder.append:(Ljava/lang/String;)Ljava/lang/StringBuilder;
      64: iload_0
      65: invokevirtual #17                 // Method java/lang/StringBuilder.append:(I)Ljava/lang/StringBuilder;
      68: invokevirtual #18                 // Method java/lang/StringBuilder.toString:()Ljava/lang/String;
      71: invokespecial #19                 // Method java/lang/IllegalArgumentException."<init>":(Ljava/lang/String;)V
      74: athrow

  static {};
    Code:
       0: new           #4                  // class org/hibernate/engine/OptimisticLockStyle
       3: dup
       4: ldc           #20                 // String NONE
       6: iconst_0
       7: iconst_m1
       8: invokespecial #21                 // Method "<init>":(Ljava/lang/String;II)V
      11: putstatic     #8                  // Field NONE:Lorg/hibernate/engine/OptimisticLockStyle;
      14: new           #4                  // class org/hibernate/engine/OptimisticLockStyle
      17: dup
      18: ldc           #22                 // String VERSION
      20: iconst_1
      21: iconst_0
      22: invokespecial #21                 // Method "<init>":(Ljava/lang/String;II)V
      25: putstatic     #9                  // Field VERSION:Lorg/hibernate/engine/OptimisticLockStyle;
      28: new           #4                  // class org/hibernate/engine/OptimisticLockStyle
      31: dup
      32: ldc           #23                 // String DIRTY
      34: iconst_2
      35: iconst_1
      36: invokespecial #21                 // Method "<init>":(Ljava/lang/String;II)V
      39: putstatic     #10                 // Field DIRTY:Lorg/hibernate/engine/OptimisticLockStyle;
      42: new           #4                  // class org/hibernate/engine/OptimisticLockStyle
      45: dup
      46: ldc           #24                 // String ALL
      48: iconst_3
      49: iconst_2
      50: invokespecial #21                 // Method "<init>":(Ljava/lang/String;II)V
      53: putstatic     #11                 // Field ALL:Lorg/hibernate/engine/OptimisticLockStyle;
      56: iconst_4
      57: anewarray     #4                  // class org/hibernate/engine/OptimisticLockStyle
      60: dup
      61: iconst_0
      62: getstatic     #8                  // Field NONE:Lorg/hibernate/engine/OptimisticLockStyle;
      65: aastore
      66: dup
      67: iconst_1
      68: getstatic     #9                  // Field VERSION:Lorg/hibernate/engine/OptimisticLockStyle;
      71: aastore
      72: dup
      73: iconst_2
      74: getstatic     #10                 // Field DIRTY:Lorg/hibernate/engine/OptimisticLockStyle;
      77: aastore
      78: dup
      79: iconst_3
      80: getstatic     #11                 // Field ALL:Lorg/hibernate/engine/OptimisticLockStyle;
      83: aastore
      84: putstatic     #1                  // Field $VALUES:[Lorg/hibernate/engine/OptimisticLockStyle;
      87: return
}
