Compiled from "FoBoBs.scala"
public class net.liftmodules.FoBoBs.package$FoBoResources$ {
  public static final net.liftmodules.FoBoBs.package$FoBoResources$ MODULE$;

  private scala.runtime.BoxedUnit bootstrap311;

  private scala.runtime.BoxedUnit bootstrap301;

  private scala.runtime.BoxedUnit bootstrap300;

  private volatile byte bitmap$0;

  public static {};
    Code:
       0: new           #2                  // class net/liftmodules/FoBoBs/package$FoBoResources$
       3: invokespecial #12                 // Method "<init>":()V
       6: return

  private void bootstrap311$lzycompute();
    Code:
       0: aload_0
       1: dup
       2: astore_1
       3: monitorenter
       4: aload_0
       5: getfield      #21                 // Field bitmap$0:B
       8: iconst_1
       9: iand
      10: i2b
      11: iconst_0
      12: if_icmpne     39
      15: getstatic     #26                 // Field net/liftweb/http/ResourceServer$.MODULE$:Lnet/liftweb/http/ResourceServer$;
      18: new           #28                 // class net/liftmodules/FoBoBs/package$FoBoResources$$anonfun$bootstrap311$1
      21: dup
      22: invokespecial #29                 // Method net/liftmodules/FoBoBs/package$FoBoResources$$anonfun$bootstrap311$1."<init>":()V
      25: invokevirtual #33                 // Method net/liftweb/http/ResourceServer$.rewrite:(Lscala/PartialFunction;)V
      28: aload_0
      29: aload_0
      30: getfield      #21                 // Field bitmap$0:B
      33: iconst_1
      34: ior
      35: i2b
      36: putfield      #21                 // Field bitmap$0:B
      39: getstatic     #38                 // Field scala/runtime/BoxedUnit.UNIT:Lscala/runtime/BoxedUnit;
      42: pop
      43: aload_1
      44: monitorexit
      45: return
      46: aload_1
      47: monitorexit
      48: athrow
    Exception table:
       from    to  target type
           4    45    46   any

  private void bootstrap301$lzycompute();
    Code:
       0: aload_0
       1: dup
       2: astore_1
       3: monitorenter
       4: aload_0
       5: getfield      #21                 // Field bitmap$0:B
       8: iconst_2
       9: iand
      10: i2b
      11: iconst_0
      12: if_icmpne     39
      15: getstatic     #26                 // Field net/liftweb/http/ResourceServer$.MODULE$:Lnet/liftweb/http/ResourceServer$;
      18: new           #44                 // class net/liftmodules/FoBoBs/package$FoBoResources$$anonfun$bootstrap301$1
      21: dup
      22: invokespecial #45                 // Method net/liftmodules/FoBoBs/package$FoBoResources$$anonfun$bootstrap301$1."<init>":()V
      25: invokevirtual #33                 // Method net/liftweb/http/ResourceServer$.rewrite:(Lscala/PartialFunction;)V
      28: aload_0
      29: aload_0
      30: getfield      #21                 // Field bitmap$0:B
      33: iconst_2
      34: ior
      35: i2b
      36: putfield      #21                 // Field bitmap$0:B
      39: getstatic     #38                 // Field scala/runtime/BoxedUnit.UNIT:Lscala/runtime/BoxedUnit;
      42: pop
      43: aload_1
      44: monitorexit
      45: return
      46: aload_1
      47: monitorexit
      48: athrow
    Exception table:
       from    to  target type
           4    45    46   any

  private void bootstrap300$lzycompute();
    Code:
       0: aload_0
       1: dup
       2: astore_1
       3: monitorenter
       4: aload_0
       5: getfield      #21                 // Field bitmap$0:B
       8: iconst_4
       9: iand
      10: i2b
      11: iconst_0
      12: if_icmpne     39
      15: getstatic     #26                 // Field net/liftweb/http/ResourceServer$.MODULE$:Lnet/liftweb/http/ResourceServer$;
      18: new           #48                 // class net/liftmodules/FoBoBs/package$FoBoResources$$anonfun$bootstrap300$1
      21: dup
      22: invokespecial #49                 // Method net/liftmodules/FoBoBs/package$FoBoResources$$anonfun$bootstrap300$1."<init>":()V
      25: invokevirtual #33                 // Method net/liftweb/http/ResourceServer$.rewrite:(Lscala/PartialFunction;)V
      28: aload_0
      29: aload_0
      30: getfield      #21                 // Field bitmap$0:B
      33: iconst_4
      34: ior
      35: i2b
      36: putfield      #21                 // Field bitmap$0:B
      39: getstatic     #38                 // Field scala/runtime/BoxedUnit.UNIT:Lscala/runtime/BoxedUnit;
      42: pop
      43: aload_1
      44: monitorexit
      45: return
      46: aload_1
      47: monitorexit
      48: athrow
    Exception table:
       from    to  target type
           4    45    46   any

  public void bootstrap311();
    Code:
       0: aload_0
       1: getfield      #21                 // Field bitmap$0:B
       4: iconst_1
       5: iand
       6: i2b
       7: iconst_0
       8: if_icmpne     15
      11: aload_0
      12: invokespecial #51                 // Method bootstrap311$lzycompute:()V
      15: return

  public void bootstrap301();
    Code:
       0: aload_0
       1: getfield      #21                 // Field bitmap$0:B
       4: iconst_2
       5: iand
       6: i2b
       7: iconst_0
       8: if_icmpne     15
      11: aload_0
      12: invokespecial #53                 // Method bootstrap301$lzycompute:()V
      15: return

  public void bootstrap300();
    Code:
       0: aload_0
       1: getfield      #21                 // Field bitmap$0:B
       4: iconst_4
       5: iand
       6: i2b
       7: iconst_0
       8: if_icmpne     15
      11: aload_0
      12: invokespecial #55                 // Method bootstrap300$lzycompute:()V
      15: return

  public net.liftmodules.FoBoBs.package$FoBoResources$();
    Code:
       0: aload_0
       1: invokespecial #56                 // Method java/lang/Object."<init>":()V
       4: aload_0
       5: putstatic     #58                 // Field MODULE$:Lnet/liftmodules/FoBoBs/package$FoBoResources$;
       8: return
}
