Compiled from "FastTreeMap.java"
public class org.apache.commons.collections.FastTreeMap extends java.util.TreeMap {
  protected java.util.TreeMap map;

  protected boolean fast;

  public org.apache.commons.collections.FastTreeMap();
    Code:
       0: aload_0
       1: invokespecial #1                  // Method java/util/TreeMap."<init>":()V
       4: aload_0
       5: aconst_null
       6: putfield      #2                  // Field map:Ljava/util/TreeMap;
       9: aload_0
      10: iconst_0
      11: putfield      #3                  // Field fast:Z
      14: aload_0
      15: new           #4                  // class java/util/TreeMap
      18: dup
      19: invokespecial #1                  // Method java/util/TreeMap."<init>":()V
      22: putfield      #2                  // Field map:Ljava/util/TreeMap;
      25: return

  public org.apache.commons.collections.FastTreeMap(java.util.Comparator);
    Code:
       0: aload_0
       1: invokespecial #1                  // Method java/util/TreeMap."<init>":()V
       4: aload_0
       5: aconst_null
       6: putfield      #2                  // Field map:Ljava/util/TreeMap;
       9: aload_0
      10: iconst_0
      11: putfield      #3                  // Field fast:Z
      14: aload_0
      15: new           #4                  // class java/util/TreeMap
      18: dup
      19: aload_1
      20: invokespecial #5                  // Method java/util/TreeMap."<init>":(Ljava/util/Comparator;)V
      23: putfield      #2                  // Field map:Ljava/util/TreeMap;
      26: return

  public org.apache.commons.collections.FastTreeMap(java.util.Map);
    Code:
       0: aload_0
       1: invokespecial #1                  // Method java/util/TreeMap."<init>":()V
       4: aload_0
       5: aconst_null
       6: putfield      #2                  // Field map:Ljava/util/TreeMap;
       9: aload_0
      10: iconst_0
      11: putfield      #3                  // Field fast:Z
      14: aload_0
      15: new           #4                  // class java/util/TreeMap
      18: dup
      19: aload_1
      20: invokespecial #6                  // Method java/util/TreeMap."<init>":(Ljava/util/Map;)V
      23: putfield      #2                  // Field map:Ljava/util/TreeMap;
      26: return

  public org.apache.commons.collections.FastTreeMap(java.util.SortedMap);
    Code:
       0: aload_0
       1: invokespecial #1                  // Method java/util/TreeMap."<init>":()V
       4: aload_0
       5: aconst_null
       6: putfield      #2                  // Field map:Ljava/util/TreeMap;
       9: aload_0
      10: iconst_0
      11: putfield      #3                  // Field fast:Z
      14: aload_0
      15: new           #4                  // class java/util/TreeMap
      18: dup
      19: aload_1
      20: invokespecial #7                  // Method java/util/TreeMap."<init>":(Ljava/util/SortedMap;)V
      23: putfield      #2                  // Field map:Ljava/util/TreeMap;
      26: return

  public boolean getFast();
    Code:
       0: aload_0
       1: getfield      #3                  // Field fast:Z
       4: ireturn

  public void setFast(boolean);
    Code:
       0: aload_0
       1: iload_1
       2: putfield      #3                  // Field fast:Z
       5: return

  public java.lang.Object get(java.lang.Object);
    Code:
       0: aload_0
       1: getfield      #3                  // Field fast:Z
       4: ifeq          16
       7: aload_0
       8: getfield      #2                  // Field map:Ljava/util/TreeMap;
      11: aload_1
      12: invokevirtual #8                  // Method java/util/TreeMap.get:(Ljava/lang/Object;)Ljava/lang/Object;
      15: areturn
      16: aload_0
      17: getfield      #2                  // Field map:Ljava/util/TreeMap;
      20: dup
      21: astore_2
      22: monitorenter
      23: aload_0
      24: getfield      #2                  // Field map:Ljava/util/TreeMap;
      27: aload_1
      28: invokevirtual #8                  // Method java/util/TreeMap.get:(Ljava/lang/Object;)Ljava/lang/Object;
      31: aload_2
      32: monitorexit
      33: areturn
      34: astore_3
      35: aload_2
      36: monitorexit
      37: aload_3
      38: athrow
    Exception table:
       from    to  target type
          23    33    34   any
          34    37    34   any

  public int size();
    Code:
       0: aload_0
       1: getfield      #3                  // Field fast:Z
       4: ifeq          15
       7: aload_0
       8: getfield      #2                  // Field map:Ljava/util/TreeMap;
      11: invokevirtual #9                  // Method java/util/TreeMap.size:()I
      14: ireturn
      15: aload_0
      16: getfield      #2                  // Field map:Ljava/util/TreeMap;
      19: dup
      20: astore_1
      21: monitorenter
      22: aload_0
      23: getfield      #2                  // Field map:Ljava/util/TreeMap;
      26: invokevirtual #9                  // Method java/util/TreeMap.size:()I
      29: aload_1
      30: monitorexit
      31: ireturn
      32: astore_2
      33: aload_1
      34: monitorexit
      35: aload_2
      36: athrow
    Exception table:
       from    to  target type
          22    31    32   any
          32    35    32   any

  public boolean isEmpty();
    Code:
       0: aload_0
       1: getfield      #3                  // Field fast:Z
       4: ifeq          15
       7: aload_0
       8: getfield      #2                  // Field map:Ljava/util/TreeMap;
      11: invokevirtual #10                 // Method java/util/TreeMap.isEmpty:()Z
      14: ireturn
      15: aload_0
      16: getfield      #2                  // Field map:Ljava/util/TreeMap;
      19: dup
      20: astore_1
      21: monitorenter
      22: aload_0
      23: getfield      #2                  // Field map:Ljava/util/TreeMap;
      26: invokevirtual #10                 // Method java/util/TreeMap.isEmpty:()Z
      29: aload_1
      30: monitorexit
      31: ireturn
      32: astore_2
      33: aload_1
      34: monitorexit
      35: aload_2
      36: athrow
    Exception table:
       from    to  target type
          22    31    32   any
          32    35    32   any

  public boolean containsKey(java.lang.Object);
    Code:
       0: aload_0
       1: getfield      #3                  // Field fast:Z
       4: ifeq          16
       7: aload_0
       8: getfield      #2                  // Field map:Ljava/util/TreeMap;
      11: aload_1
      12: invokevirtual #11                 // Method java/util/TreeMap.containsKey:(Ljava/lang/Object;)Z
      15: ireturn
      16: aload_0
      17: getfield      #2                  // Field map:Ljava/util/TreeMap;
      20: dup
      21: astore_2
      22: monitorenter
      23: aload_0
      24: getfield      #2                  // Field map:Ljava/util/TreeMap;
      27: aload_1
      28: invokevirtual #11                 // Method java/util/TreeMap.containsKey:(Ljava/lang/Object;)Z
      31: aload_2
      32: monitorexit
      33: ireturn
      34: astore_3
      35: aload_2
      36: monitorexit
      37: aload_3
      38: athrow
    Exception table:
       from    to  target type
          23    33    34   any
          34    37    34   any

  public boolean containsValue(java.lang.Object);
    Code:
       0: aload_0
       1: getfield      #3                  // Field fast:Z
       4: ifeq          16
       7: aload_0
       8: getfield      #2                  // Field map:Ljava/util/TreeMap;
      11: aload_1
      12: invokevirtual #12                 // Method java/util/TreeMap.containsValue:(Ljava/lang/Object;)Z
      15: ireturn
      16: aload_0
      17: getfield      #2                  // Field map:Ljava/util/TreeMap;
      20: dup
      21: astore_2
      22: monitorenter
      23: aload_0
      24: getfield      #2                  // Field map:Ljava/util/TreeMap;
      27: aload_1
      28: invokevirtual #12                 // Method java/util/TreeMap.containsValue:(Ljava/lang/Object;)Z
      31: aload_2
      32: monitorexit
      33: ireturn
      34: astore_3
      35: aload_2
      36: monitorexit
      37: aload_3
      38: athrow
    Exception table:
       from    to  target type
          23    33    34   any
          34    37    34   any

  public java.util.Comparator comparator();
    Code:
       0: aload_0
       1: getfield      #3                  // Field fast:Z
       4: ifeq          15
       7: aload_0
       8: getfield      #2                  // Field map:Ljava/util/TreeMap;
      11: invokevirtual #13                 // Method java/util/TreeMap.comparator:()Ljava/util/Comparator;
      14: areturn
      15: aload_0
      16: getfield      #2                  // Field map:Ljava/util/TreeMap;
      19: dup
      20: astore_1
      21: monitorenter
      22: aload_0
      23: getfield      #2                  // Field map:Ljava/util/TreeMap;
      26: invokevirtual #13                 // Method java/util/TreeMap.comparator:()Ljava/util/Comparator;
      29: aload_1
      30: monitorexit
      31: areturn
      32: astore_2
      33: aload_1
      34: monitorexit
      35: aload_2
      36: athrow
    Exception table:
       from    to  target type
          22    31    32   any
          32    35    32   any

  public java.lang.Object firstKey();
    Code:
       0: aload_0
       1: getfield      #3                  // Field fast:Z
       4: ifeq          15
       7: aload_0
       8: getfield      #2                  // Field map:Ljava/util/TreeMap;
      11: invokevirtual #14                 // Method java/util/TreeMap.firstKey:()Ljava/lang/Object;
      14: areturn
      15: aload_0
      16: getfield      #2                  // Field map:Ljava/util/TreeMap;
      19: dup
      20: astore_1
      21: monitorenter
      22: aload_0
      23: getfield      #2                  // Field map:Ljava/util/TreeMap;
      26: invokevirtual #14                 // Method java/util/TreeMap.firstKey:()Ljava/lang/Object;
      29: aload_1
      30: monitorexit
      31: areturn
      32: astore_2
      33: aload_1
      34: monitorexit
      35: aload_2
      36: athrow
    Exception table:
       from    to  target type
          22    31    32   any
          32    35    32   any

  public java.lang.Object lastKey();
    Code:
       0: aload_0
       1: getfield      #3                  // Field fast:Z
       4: ifeq          15
       7: aload_0
       8: getfield      #2                  // Field map:Ljava/util/TreeMap;
      11: invokevirtual #15                 // Method java/util/TreeMap.lastKey:()Ljava/lang/Object;
      14: areturn
      15: aload_0
      16: getfield      #2                  // Field map:Ljava/util/TreeMap;
      19: dup
      20: astore_1
      21: monitorenter
      22: aload_0
      23: getfield      #2                  // Field map:Ljava/util/TreeMap;
      26: invokevirtual #15                 // Method java/util/TreeMap.lastKey:()Ljava/lang/Object;
      29: aload_1
      30: monitorexit
      31: areturn
      32: astore_2
      33: aload_1
      34: monitorexit
      35: aload_2
      36: athrow
    Exception table:
       from    to  target type
          22    31    32   any
          32    35    32   any

  public java.lang.Object put(java.lang.Object, java.lang.Object);
    Code:
       0: aload_0
       1: getfield      #3                  // Field fast:Z
       4: ifeq          50
       7: aload_0
       8: dup
       9: astore_3
      10: monitorenter
      11: aload_0
      12: getfield      #2                  // Field map:Ljava/util/TreeMap;
      15: invokevirtual #16                 // Method java/util/TreeMap.clone:()Ljava/lang/Object;
      18: checkcast     #4                  // class java/util/TreeMap
      21: astore        4
      23: aload         4
      25: aload_1
      26: aload_2
      27: invokevirtual #17                 // Method java/util/TreeMap.put:(Ljava/lang/Object;Ljava/lang/Object;)Ljava/lang/Object;
      30: astore        5
      32: aload_0
      33: aload         4
      35: putfield      #2                  // Field map:Ljava/util/TreeMap;
      38: aload         5
      40: aload_3
      41: monitorexit
      42: areturn
      43: astore        6
      45: aload_3
      46: monitorexit
      47: aload         6
      49: athrow
      50: aload_0
      51: getfield      #2                  // Field map:Ljava/util/TreeMap;
      54: dup
      55: astore_3
      56: monitorenter
      57: aload_0
      58: getfield      #2                  // Field map:Ljava/util/TreeMap;
      61: aload_1
      62: aload_2
      63: invokevirtual #17                 // Method java/util/TreeMap.put:(Ljava/lang/Object;Ljava/lang/Object;)Ljava/lang/Object;
      66: aload_3
      67: monitorexit
      68: areturn
      69: astore        7
      71: aload_3
      72: monitorexit
      73: aload         7
      75: athrow
    Exception table:
       from    to  target type
          11    42    43   any
          43    47    43   any
          57    68    69   any
          69    73    69   any

  public void putAll(java.util.Map);
    Code:
       0: aload_0
       1: getfield      #3                  // Field fast:Z
       4: ifeq          47
       7: aload_0
       8: dup
       9: astore_2
      10: monitorenter
      11: aload_0
      12: getfield      #2                  // Field map:Ljava/util/TreeMap;
      15: invokevirtual #16                 // Method java/util/TreeMap.clone:()Ljava/lang/Object;
      18: checkcast     #4                  // class java/util/TreeMap
      21: astore_3
      22: aload_3
      23: aload_1
      24: invokevirtual #18                 // Method java/util/TreeMap.putAll:(Ljava/util/Map;)V
      27: aload_0
      28: aload_3
      29: putfield      #2                  // Field map:Ljava/util/TreeMap;
      32: aload_2
      33: monitorexit
      34: goto          44
      37: astore        4
      39: aload_2
      40: monitorexit
      41: aload         4
      43: athrow
      44: goto          74
      47: aload_0
      48: getfield      #2                  // Field map:Ljava/util/TreeMap;
      51: dup
      52: astore_2
      53: monitorenter
      54: aload_0
      55: getfield      #2                  // Field map:Ljava/util/TreeMap;
      58: aload_1
      59: invokevirtual #18                 // Method java/util/TreeMap.putAll:(Ljava/util/Map;)V
      62: aload_2
      63: monitorexit
      64: goto          74
      67: astore        5
      69: aload_2
      70: monitorexit
      71: aload         5
      73: athrow
      74: return
    Exception table:
       from    to  target type
          11    34    37   any
          37    41    37   any
          54    64    67   any
          67    71    67   any

  public java.lang.Object remove(java.lang.Object);
    Code:
       0: aload_0
       1: getfield      #3                  // Field fast:Z
       4: ifeq          46
       7: aload_0
       8: dup
       9: astore_2
      10: monitorenter
      11: aload_0
      12: getfield      #2                  // Field map:Ljava/util/TreeMap;
      15: invokevirtual #16                 // Method java/util/TreeMap.clone:()Ljava/lang/Object;
      18: checkcast     #4                  // class java/util/TreeMap
      21: astore_3
      22: aload_3
      23: aload_1
      24: invokevirtual #19                 // Method java/util/TreeMap.remove:(Ljava/lang/Object;)Ljava/lang/Object;
      27: astore        4
      29: aload_0
      30: aload_3
      31: putfield      #2                  // Field map:Ljava/util/TreeMap;
      34: aload         4
      36: aload_2
      37: monitorexit
      38: areturn
      39: astore        5
      41: aload_2
      42: monitorexit
      43: aload         5
      45: athrow
      46: aload_0
      47: getfield      #2                  // Field map:Ljava/util/TreeMap;
      50: dup
      51: astore_2
      52: monitorenter
      53: aload_0
      54: getfield      #2                  // Field map:Ljava/util/TreeMap;
      57: aload_1
      58: invokevirtual #19                 // Method java/util/TreeMap.remove:(Ljava/lang/Object;)Ljava/lang/Object;
      61: aload_2
      62: monitorexit
      63: areturn
      64: astore        6
      66: aload_2
      67: monitorexit
      68: aload         6
      70: athrow
    Exception table:
       from    to  target type
          11    38    39   any
          39    43    39   any
          53    63    64   any
          64    68    64   any

  public void clear();
    Code:
       0: aload_0
       1: getfield      #3                  // Field fast:Z
       4: ifeq          35
       7: aload_0
       8: dup
       9: astore_1
      10: monitorenter
      11: aload_0
      12: new           #4                  // class java/util/TreeMap
      15: dup
      16: invokespecial #1                  // Method java/util/TreeMap."<init>":()V
      19: putfield      #2                  // Field map:Ljava/util/TreeMap;
      22: aload_1
      23: monitorexit
      24: goto          32
      27: astore_2
      28: aload_1
      29: monitorexit
      30: aload_2
      31: athrow
      32: goto          59
      35: aload_0
      36: getfield      #2                  // Field map:Ljava/util/TreeMap;
      39: dup
      40: astore_1
      41: monitorenter
      42: aload_0
      43: getfield      #2                  // Field map:Ljava/util/TreeMap;
      46: invokevirtual #20                 // Method java/util/TreeMap.clear:()V
      49: aload_1
      50: monitorexit
      51: goto          59
      54: astore_3
      55: aload_1
      56: monitorexit
      57: aload_3
      58: athrow
      59: return
    Exception table:
       from    to  target type
          11    24    27   any
          27    30    27   any
          42    51    54   any
          54    57    54   any

  public boolean equals(java.lang.Object);
    Code:
       0: aload_1
       1: aload_0
       2: if_acmpne     7
       5: iconst_1
       6: ireturn
       7: aload_1
       8: instanceof    #21                 // class java/util/Map
      11: ifne          16
      14: iconst_0
      15: ireturn
      16: aload_1
      17: checkcast     #21                 // class java/util/Map
      20: astore_2
      21: aload_0
      22: getfield      #3                  // Field fast:Z
      25: ifeq          149
      28: aload_2
      29: invokeinterface #22,  1           // InterfaceMethod java/util/Map.size:()I
      34: aload_0
      35: getfield      #2                  // Field map:Ljava/util/TreeMap;
      38: invokevirtual #9                  // Method java/util/TreeMap.size:()I
      41: if_icmpeq     46
      44: iconst_0
      45: ireturn
      46: aload_0
      47: getfield      #2                  // Field map:Ljava/util/TreeMap;
      50: invokevirtual #23                 // Method java/util/TreeMap.entrySet:()Ljava/util/Set;
      53: invokeinterface #24,  1           // InterfaceMethod java/util/Set.iterator:()Ljava/util/Iterator;
      58: astore_3
      59: aload_3
      60: invokeinterface #25,  1           // InterfaceMethod java/util/Iterator.hasNext:()Z
      65: ifeq          147
      68: aload_3
      69: invokeinterface #26,  1           // InterfaceMethod java/util/Iterator.next:()Ljava/lang/Object;
      74: checkcast     #27                 // class java/util/Map$Entry
      77: astore        4
      79: aload         4
      81: invokeinterface #28,  1           // InterfaceMethod java/util/Map$Entry.getKey:()Ljava/lang/Object;
      86: astore        5
      88: aload         4
      90: invokeinterface #29,  1           // InterfaceMethod java/util/Map$Entry.getValue:()Ljava/lang/Object;
      95: astore        6
      97: aload         6
      99: ifnonnull     126
     102: aload_2
     103: aload         5
     105: invokeinterface #30,  2           // InterfaceMethod java/util/Map.get:(Ljava/lang/Object;)Ljava/lang/Object;
     110: ifnonnull     124
     113: aload_2
     114: aload         5
     116: invokeinterface #31,  2           // InterfaceMethod java/util/Map.containsKey:(Ljava/lang/Object;)Z
     121: ifne          144
     124: iconst_0
     125: ireturn
     126: aload         6
     128: aload_2
     129: aload         5
     131: invokeinterface #30,  2           // InterfaceMethod java/util/Map.get:(Ljava/lang/Object;)Ljava/lang/Object;
     136: invokevirtual #32                 // Method java/lang/Object.equals:(Ljava/lang/Object;)Z
     139: ifne          144
     142: iconst_0
     143: ireturn
     144: goto          59
     147: iconst_1
     148: ireturn
     149: aload_0
     150: getfield      #2                  // Field map:Ljava/util/TreeMap;
     153: dup
     154: astore_3
     155: monitorenter
     156: aload_2
     157: invokeinterface #22,  1           // InterfaceMethod java/util/Map.size:()I
     162: aload_0
     163: getfield      #2                  // Field map:Ljava/util/TreeMap;
     166: invokevirtual #9                  // Method java/util/TreeMap.size:()I
     169: if_icmpeq     176
     172: iconst_0
     173: aload_3
     174: monitorexit
     175: ireturn
     176: aload_0
     177: getfield      #2                  // Field map:Ljava/util/TreeMap;
     180: invokevirtual #23                 // Method java/util/TreeMap.entrySet:()Ljava/util/Set;
     183: invokeinterface #24,  1           // InterfaceMethod java/util/Set.iterator:()Ljava/util/Iterator;
     188: astore        4
     190: aload         4
     192: invokeinterface #25,  1           // InterfaceMethod java/util/Iterator.hasNext:()Z
     197: ifeq          284
     200: aload         4
     202: invokeinterface #26,  1           // InterfaceMethod java/util/Iterator.next:()Ljava/lang/Object;
     207: checkcast     #27                 // class java/util/Map$Entry
     210: astore        5
     212: aload         5
     214: invokeinterface #28,  1           // InterfaceMethod java/util/Map$Entry.getKey:()Ljava/lang/Object;
     219: astore        6
     221: aload         5
     223: invokeinterface #29,  1           // InterfaceMethod java/util/Map$Entry.getValue:()Ljava/lang/Object;
     228: astore        7
     230: aload         7
     232: ifnonnull     261
     235: aload_2
     236: aload         6
     238: invokeinterface #30,  2           // InterfaceMethod java/util/Map.get:(Ljava/lang/Object;)Ljava/lang/Object;
     243: ifnonnull     257
     246: aload_2
     247: aload         6
     249: invokeinterface #31,  2           // InterfaceMethod java/util/Map.containsKey:(Ljava/lang/Object;)Z
     254: ifne          281
     257: iconst_0
     258: aload_3
     259: monitorexit
     260: ireturn
     261: aload         7
     263: aload_2
     264: aload         6
     266: invokeinterface #30,  2           // InterfaceMethod java/util/Map.get:(Ljava/lang/Object;)Ljava/lang/Object;
     271: invokevirtual #32                 // Method java/lang/Object.equals:(Ljava/lang/Object;)Z
     274: ifne          281
     277: iconst_0
     278: aload_3
     279: monitorexit
     280: ireturn
     281: goto          190
     284: iconst_1
     285: aload_3
     286: monitorexit
     287: ireturn
     288: astore        8
     290: aload_3
     291: monitorexit
     292: aload         8
     294: athrow
    Exception table:
       from    to  target type
         156   175   288   any
         176   260   288   any
         261   280   288   any
         281   287   288   any
         288   292   288   any

  public int hashCode();
    Code:
       0: aload_0
       1: getfield      #3                  // Field fast:Z
       4: ifeq          48
       7: iconst_0
       8: istore_1
       9: aload_0
      10: getfield      #2                  // Field map:Ljava/util/TreeMap;
      13: invokevirtual #23                 // Method java/util/TreeMap.entrySet:()Ljava/util/Set;
      16: invokeinterface #24,  1           // InterfaceMethod java/util/Set.iterator:()Ljava/util/Iterator;
      21: astore_2
      22: aload_2
      23: invokeinterface #25,  1           // InterfaceMethod java/util/Iterator.hasNext:()Z
      28: ifeq          46
      31: iload_1
      32: aload_2
      33: invokeinterface #26,  1           // InterfaceMethod java/util/Iterator.next:()Ljava/lang/Object;
      38: invokevirtual #33                 // Method java/lang/Object.hashCode:()I
      41: iadd
      42: istore_1
      43: goto          22
      46: iload_1
      47: ireturn
      48: aload_0
      49: getfield      #2                  // Field map:Ljava/util/TreeMap;
      52: dup
      53: astore_1
      54: monitorenter
      55: iconst_0
      56: istore_2
      57: aload_0
      58: getfield      #2                  // Field map:Ljava/util/TreeMap;
      61: invokevirtual #23                 // Method java/util/TreeMap.entrySet:()Ljava/util/Set;
      64: invokeinterface #24,  1           // InterfaceMethod java/util/Set.iterator:()Ljava/util/Iterator;
      69: astore_3
      70: aload_3
      71: invokeinterface #25,  1           // InterfaceMethod java/util/Iterator.hasNext:()Z
      76: ifeq          94
      79: iload_2
      80: aload_3
      81: invokeinterface #26,  1           // InterfaceMethod java/util/Iterator.next:()Ljava/lang/Object;
      86: invokevirtual #33                 // Method java/lang/Object.hashCode:()I
      89: iadd
      90: istore_2
      91: goto          70
      94: iload_2
      95: aload_1
      96: monitorexit
      97: ireturn
      98: astore        4
     100: aload_1
     101: monitorexit
     102: aload         4
     104: athrow
    Exception table:
       from    to  target type
          55    97    98   any
          98   102    98   any

  public java.lang.Object clone();
    Code:
       0: aconst_null
       1: astore_1
       2: aload_0
       3: getfield      #3                  // Field fast:Z
       6: ifeq          24
       9: new           #34                 // class org/apache/commons/collections/FastTreeMap
      12: dup
      13: aload_0
      14: getfield      #2                  // Field map:Ljava/util/TreeMap;
      17: invokespecial #35                 // Method "<init>":(Ljava/util/SortedMap;)V
      20: astore_1
      21: goto          53
      24: aload_0
      25: getfield      #2                  // Field map:Ljava/util/TreeMap;
      28: dup
      29: astore_2
      30: monitorenter
      31: new           #34                 // class org/apache/commons/collections/FastTreeMap
      34: dup
      35: aload_0
      36: getfield      #2                  // Field map:Ljava/util/TreeMap;
      39: invokespecial #35                 // Method "<init>":(Ljava/util/SortedMap;)V
      42: astore_1
      43: aload_2
      44: monitorexit
      45: goto          53
      48: astore_3
      49: aload_2
      50: monitorexit
      51: aload_3
      52: athrow
      53: aload_1
      54: aload_0
      55: invokevirtual #36                 // Method getFast:()Z
      58: invokevirtual #37                 // Method setFast:(Z)V
      61: aload_1
      62: areturn
    Exception table:
       from    to  target type
          31    45    48   any
          48    51    48   any

  public java.util.SortedMap headMap(java.lang.Object);
    Code:
       0: aload_0
       1: getfield      #3                  // Field fast:Z
       4: ifeq          16
       7: aload_0
       8: getfield      #2                  // Field map:Ljava/util/TreeMap;
      11: aload_1
      12: invokevirtual #38                 // Method java/util/TreeMap.headMap:(Ljava/lang/Object;)Ljava/util/SortedMap;
      15: areturn
      16: aload_0
      17: getfield      #2                  // Field map:Ljava/util/TreeMap;
      20: dup
      21: astore_2
      22: monitorenter
      23: aload_0
      24: getfield      #2                  // Field map:Ljava/util/TreeMap;
      27: aload_1
      28: invokevirtual #38                 // Method java/util/TreeMap.headMap:(Ljava/lang/Object;)Ljava/util/SortedMap;
      31: aload_2
      32: monitorexit
      33: areturn
      34: astore_3
      35: aload_2
      36: monitorexit
      37: aload_3
      38: athrow
    Exception table:
       from    to  target type
          23    33    34   any
          34    37    34   any

  public java.util.SortedMap subMap(java.lang.Object, java.lang.Object);
    Code:
       0: aload_0
       1: getfield      #3                  // Field fast:Z
       4: ifeq          17
       7: aload_0
       8: getfield      #2                  // Field map:Ljava/util/TreeMap;
      11: aload_1
      12: aload_2
      13: invokevirtual #39                 // Method java/util/TreeMap.subMap:(Ljava/lang/Object;Ljava/lang/Object;)Ljava/util/SortedMap;
      16: areturn
      17: aload_0
      18: getfield      #2                  // Field map:Ljava/util/TreeMap;
      21: dup
      22: astore_3
      23: monitorenter
      24: aload_0
      25: getfield      #2                  // Field map:Ljava/util/TreeMap;
      28: aload_1
      29: aload_2
      30: invokevirtual #39                 // Method java/util/TreeMap.subMap:(Ljava/lang/Object;Ljava/lang/Object;)Ljava/util/SortedMap;
      33: aload_3
      34: monitorexit
      35: areturn
      36: astore        4
      38: aload_3
      39: monitorexit
      40: aload         4
      42: athrow
    Exception table:
       from    to  target type
          24    35    36   any
          36    40    36   any

  public java.util.SortedMap tailMap(java.lang.Object);
    Code:
       0: aload_0
       1: getfield      #3                  // Field fast:Z
       4: ifeq          16
       7: aload_0
       8: getfield      #2                  // Field map:Ljava/util/TreeMap;
      11: aload_1
      12: invokevirtual #40                 // Method java/util/TreeMap.tailMap:(Ljava/lang/Object;)Ljava/util/SortedMap;
      15: areturn
      16: aload_0
      17: getfield      #2                  // Field map:Ljava/util/TreeMap;
      20: dup
      21: astore_2
      22: monitorenter
      23: aload_0
      24: getfield      #2                  // Field map:Ljava/util/TreeMap;
      27: aload_1
      28: invokevirtual #40                 // Method java/util/TreeMap.tailMap:(Ljava/lang/Object;)Ljava/util/SortedMap;
      31: aload_2
      32: monitorexit
      33: areturn
      34: astore_3
      35: aload_2
      36: monitorexit
      37: aload_3
      38: athrow
    Exception table:
       from    to  target type
          23    33    34   any
          34    37    34   any

  public java.util.Set entrySet();
    Code:
       0: new           #41                 // class org/apache/commons/collections/FastTreeMap$EntrySet
       3: dup
       4: aload_0
       5: aconst_null
       6: invokespecial #42                 // Method org/apache/commons/collections/FastTreeMap$EntrySet."<init>":(Lorg/apache/commons/collections/FastTreeMap;Lorg/apache/commons/collections/FastTreeMap$1;)V
       9: areturn

  public java.util.Set keySet();
    Code:
       0: new           #43                 // class org/apache/commons/collections/FastTreeMap$KeySet
       3: dup
       4: aload_0
       5: aconst_null
       6: invokespecial #44                 // Method org/apache/commons/collections/FastTreeMap$KeySet."<init>":(Lorg/apache/commons/collections/FastTreeMap;Lorg/apache/commons/collections/FastTreeMap$1;)V
       9: areturn

  public java.util.Collection values();
    Code:
       0: new           #45                 // class org/apache/commons/collections/FastTreeMap$Values
       3: dup
       4: aload_0
       5: aconst_null
       6: invokespecial #46                 // Method org/apache/commons/collections/FastTreeMap$Values."<init>":(Lorg/apache/commons/collections/FastTreeMap;Lorg/apache/commons/collections/FastTreeMap$1;)V
       9: areturn
}
