Compiled from "AbstractUrlHandlerMapping.java"
class org.springframework.web.servlet.handler.AbstractUrlHandlerMapping$PathExposingHandlerInterceptor extends org.springframework.web.servlet.handler.HandlerInterceptorAdapter {
  private final java.lang.String bestMatchingPattern;

  private final java.lang.String pathWithinMapping;

  final org.springframework.web.servlet.handler.AbstractUrlHandlerMapping this$0;

  public org.springframework.web.servlet.handler.AbstractUrlHandlerMapping$PathExposingHandlerInterceptor(org.springframework.web.servlet.handler.AbstractUrlHandlerMapping, java.lang.String, java.lang.String);
    Code:
       0: aload_0
       1: aload_1
       2: putfield      #1                  // Field this$0:Lorg/springframework/web/servlet/handler/AbstractUrlHandlerMapping;
       5: aload_0
       6: invokespecial #2                  // Method org/springframework/web/servlet/handler/HandlerInterceptorAdapter."<init>":()V
       9: aload_0
      10: aload_2
      11: putfield      #3                  // Field bestMatchingPattern:Ljava/lang/String;
      14: aload_0
      15: aload_3
      16: putfield      #4                  // Field pathWithinMapping:Ljava/lang/String;
      19: return

  public boolean preHandle(javax.servlet.http.HttpServletRequest, javax.servlet.http.HttpServletResponse, java.lang.Object);
    Code:
       0: aload_0
       1: getfield      #1                  // Field this$0:Lorg/springframework/web/servlet/handler/AbstractUrlHandlerMapping;
       4: aload_0
       5: getfield      #3                  // Field bestMatchingPattern:Ljava/lang/String;
       8: aload_0
       9: getfield      #4                  // Field pathWithinMapping:Ljava/lang/String;
      12: aload_1
      13: invokevirtual #5                  // Method org/springframework/web/servlet/handler/AbstractUrlHandlerMapping.exposePathWithinMapping:(Ljava/lang/String;Ljava/lang/String;Ljavax/servlet/http/HttpServletRequest;)V
      16: aload_1
      17: getstatic     #6                  // Field org/springframework/web/servlet/HandlerMapping.INTROSPECT_TYPE_LEVEL_MAPPING:Ljava/lang/String;
      20: aload_0
      21: getfield      #1                  // Field this$0:Lorg/springframework/web/servlet/handler/AbstractUrlHandlerMapping;
      24: invokevirtual #7                  // Method org/springframework/web/servlet/handler/AbstractUrlHandlerMapping.supportsTypeLevelMappings:()Z
      27: invokestatic  #8                  // Method java/lang/Boolean.valueOf:(Z)Ljava/lang/Boolean;
      30: invokeinterface #9,  3            // InterfaceMethod javax/servlet/http/HttpServletRequest.setAttribute:(Ljava/lang/String;Ljava/lang/Object;)V
      35: iconst_1
      36: ireturn
}
