Compiled from "HandlerInterceptorAdapter.java"
public abstract class org.springframework.web.servlet.handler.HandlerInterceptorAdapter implements org.springframework.web.servlet.AsyncHandlerInterceptor {
  public org.springframework.web.servlet.handler.HandlerInterceptorAdapter();
    Code:
       0: aload_0
       1: invokespecial #1                  // Method java/lang/Object."<init>":()V
       4: return

  public boolean preHandle(javax.servlet.http.HttpServletRequest, javax.servlet.http.HttpServletResponse, java.lang.Object) throws java.lang.Exception;
    Code:
       0: iconst_1
       1: ireturn

  public void postHandle(javax.servlet.http.HttpServletRequest, javax.servlet.http.HttpServletResponse, java.lang.Object, org.springframework.web.servlet.ModelAndView) throws java.lang.Exception;
    Code:
       0: return

  public void afterCompletion(javax.servlet.http.HttpServletRequest, javax.servlet.http.HttpServletResponse, java.lang.Object, java.lang.Exception) throws java.lang.Exception;
    Code:
       0: return

  public void afterConcurrentHandlingStarted(javax.servlet.http.HttpServletRequest, javax.servlet.http.HttpServletResponse, java.lang.Object) throws java.lang.Exception;
    Code:
       0: return
}
