Compiled from "TypeConversionSupport.java"
class org.apache.activemq.util.TypeConversionSupport$ConversionKey {
  final java.lang.Class<?> from;

  final java.lang.Class<?> to;

  final int hashCode;

  public org.apache.activemq.util.TypeConversionSupport$ConversionKey(java.lang.Class<?>, java.lang.Class<?>);
    Code:
       0: aload_0
       1: invokespecial #1                  // Method java/lang/Object."<init>":()V
       4: aload_0
       5: aload_1
       6: putfield      #2                  // Field from:Ljava/lang/Class;
       9: aload_0
      10: aload_2
      11: putfield      #3                  // Field to:Ljava/lang/Class;
      14: aload_0
      15: aload_1
      16: invokevirtual #4                  // Method java/lang/Object.hashCode:()I
      19: aload_2
      20: invokevirtual #4                  // Method java/lang/Object.hashCode:()I
      23: iconst_1
      24: ishl
      25: ixor
      26: putfield      #5                  // Field hashCode:I
      29: return

  public boolean equals(java.lang.Object);
    Code:
       0: aload_1
       1: checkcast     #6                  // class org/apache/activemq/util/TypeConversionSupport$ConversionKey
       4: astore_2
       5: aload_2
       6: getfield      #2                  // Field from:Ljava/lang/Class;
       9: aload_0
      10: getfield      #2                  // Field from:Ljava/lang/Class;
      13: if_acmpne     31
      16: aload_2
      17: getfield      #3                  // Field to:Ljava/lang/Class;
      20: aload_0
      21: getfield      #3                  // Field to:Ljava/lang/Class;
      24: if_acmpne     31
      27: iconst_1
      28: goto          32
      31: iconst_0
      32: ireturn

  public int hashCode();
    Code:
       0: aload_0
       1: getfield      #5                  // Field hashCode:I
       4: ireturn
}
