Compiled from "MethodList.java"
public class net.bytebuddy.description.method.MethodList$TypeSubstituting extends net.bytebuddy.description.method.MethodList$AbstractBase<net.bytebuddy.description.method.MethodDescription$InGenericShape> {
  protected final net.bytebuddy.description.type.TypeDescription$Generic declaringType;

  protected final java.util.List<? extends net.bytebuddy.description.method.MethodDescription> methodDescriptions;

  protected final net.bytebuddy.description.type.TypeDescription$Generic$Visitor<? extends net.bytebuddy.description.type.TypeDescription$Generic> visitor;

  public net.bytebuddy.description.method.MethodList$TypeSubstituting(net.bytebuddy.description.type.TypeDescription$Generic, java.util.List<? extends net.bytebuddy.description.method.MethodDescription>, net.bytebuddy.description.type.TypeDescription$Generic$Visitor<? extends net.bytebuddy.description.type.TypeDescription$Generic>);
    Code:
       0: aload_0
       1: invokespecial #39                 // Method net/bytebuddy/description/method/MethodList$AbstractBase."<init>":()V
       4: aload_0
       5: aload_1
       6: putfield      #41                 // Field declaringType:Lnet/bytebuddy/description/type/TypeDescription$Generic;
       9: aload_0
      10: aload_2
      11: putfield      #43                 // Field methodDescriptions:Ljava/util/List;
      14: aload_0
      15: aload_3
      16: putfield      #45                 // Field visitor:Lnet/bytebuddy/description/type/TypeDescription$Generic$Visitor;
      19: return

  public net.bytebuddy.description.method.MethodDescription$InGenericShape get(int);
    Code:
       0: new           #25                 // class net/bytebuddy/description/method/MethodDescription$TypeSubstituting
       3: dup
       4: aload_0
       5: getfield      #41                 // Field declaringType:Lnet/bytebuddy/description/type/TypeDescription$Generic;
       8: aload_0
       9: getfield      #43                 // Field methodDescriptions:Ljava/util/List;
      12: iload_1
      13: invokeinterface #54,  2           // InterfaceMethod java/util/List.get:(I)Ljava/lang/Object;
      18: checkcast     #21                 // class net/bytebuddy/description/method/MethodDescription
      21: aload_0
      22: getfield      #45                 // Field visitor:Lnet/bytebuddy/description/type/TypeDescription$Generic$Visitor;
      25: invokespecial #57                 // Method net/bytebuddy/description/method/MethodDescription$TypeSubstituting."<init>":(Lnet/bytebuddy/description/type/TypeDescription$Generic;Lnet/bytebuddy/description/method/MethodDescription;Lnet/bytebuddy/description/type/TypeDescription$Generic$Visitor;)V
      28: areturn

  public int size();
    Code:
       0: aload_0
       1: getfield      #43                 // Field methodDescriptions:Ljava/util/List;
       4: invokeinterface #63,  1           // InterfaceMethod java/util/List.size:()I
       9: ireturn

  public java.lang.Object get(int);
    Code:
       0: aload_0
       1: iload_1
       2: invokevirtual #65                 // Method get:(I)Lnet/bytebuddy/description/method/MethodDescription$InGenericShape;
       5: areturn
}
