Compiled from "ParameterDescription.java"
public class net.bytebuddy.description.method.ParameterDescription$ForLoadedParameter$OfMethod extends net.bytebuddy.description.method.ParameterDescription$ForLoadedParameter<java.lang.reflect.Method> {
  protected net.bytebuddy.description.method.ParameterDescription$ForLoadedParameter$OfMethod(java.lang.reflect.Method, int, net.bytebuddy.description.method.ParameterDescription$ForLoadedParameter$ParameterAnnotationSource);
    Code:
       0: aload_0
       1: aload_1
       2: iload_2
       3: aload_3
       4: invokespecial #51                 // Method net/bytebuddy/description/method/ParameterDescription$ForLoadedParameter."<init>":(Ljava/lang/reflect/AccessibleObject;ILnet/bytebuddy/description/method/ParameterDescription$ForLoadedParameter$ParameterAnnotationSource;)V
       7: return

  public net.bytebuddy.description.method.MethodDescription$InDefinedShape getDeclaringMethod();
    Code:
       0: new           #25                 // class net/bytebuddy/description/method/MethodDescription$ForLoadedMethod
       3: dup
       4: aload_0
       5: getfield      #70                 // Field executable:Ljava/lang/reflect/AccessibleObject;
       8: checkcast     #72                 // class java/lang/reflect/Method
      11: invokespecial #75                 // Method net/bytebuddy/description/method/MethodDescription$ForLoadedMethod."<init>":(Ljava/lang/reflect/Method;)V
      14: areturn

  public net.bytebuddy.description.type.TypeDescription$Generic getType();
    Code:
       0: getstatic     #81                 // Field net/bytebuddy/description/type/TypeDescription$AbstractBase.RAW_TYPES:Z
       3: ifeq          25
       6: aload_0
       7: getfield      #70                 // Field executable:Ljava/lang/reflect/AccessibleObject;
      10: checkcast     #72                 // class java/lang/reflect/Method
      13: invokevirtual #85                 // Method java/lang/reflect/Method.getParameterTypes:()[Ljava/lang/Class;
      16: aload_0
      17: getfield      #87                 // Field index:I
      20: aaload
      21: invokestatic  #91                 // Method net/bytebuddy/description/type/TypeDescription$Generic$OfNonGenericType$ForLoadedType.of:(Ljava/lang/Class;)Lnet/bytebuddy/description/type/TypeDescription$Generic;
      24: areturn
      25: new           #31                 // class net/bytebuddy/description/type/TypeDescription$Generic$LazyProjection$OfMethodParameter
      28: dup
      29: aload_0
      30: getfield      #70                 // Field executable:Ljava/lang/reflect/AccessibleObject;
      33: checkcast     #72                 // class java/lang/reflect/Method
      36: aload_0
      37: getfield      #87                 // Field index:I
      40: aload_0
      41: getfield      #70                 // Field executable:Ljava/lang/reflect/AccessibleObject;
      44: checkcast     #72                 // class java/lang/reflect/Method
      47: invokevirtual #85                 // Method java/lang/reflect/Method.getParameterTypes:()[Ljava/lang/Class;
      50: invokespecial #94                 // Method net/bytebuddy/description/type/TypeDescription$Generic$LazyProjection$OfMethodParameter."<init>":(Ljava/lang/reflect/Method;I[Ljava/lang/Class;)V
      53: areturn

  public net.bytebuddy.description.annotation.AnnotationList getDeclaredAnnotations();
    Code:
       0: new           #34                 // class net/bytebuddy/description/annotation/AnnotationList$ForLoadedAnnotations
       3: dup
       4: aload_0
       5: getfield      #98                 // Field parameterAnnotationSource:Lnet/bytebuddy/description/method/ParameterDescription$ForLoadedParameter$ParameterAnnotationSource;
       8: invokeinterface #102,  1          // InterfaceMethod net/bytebuddy/description/method/ParameterDescription$ForLoadedParameter$ParameterAnnotationSource.getParameterAnnotations:()[[Ljava/lang/annotation/Annotation;
      13: aload_0
      14: getfield      #87                 // Field index:I
      17: aaload
      18: invokespecial #105                // Method net/bytebuddy/description/annotation/AnnotationList$ForLoadedAnnotations."<init>":([Ljava/lang/annotation/Annotation;)V
      21: areturn

  public net.bytebuddy.description.method.MethodDescription getDeclaringMethod();
    Code:
       0: aload_0
       1: invokevirtual #108                // Method getDeclaringMethod:()Lnet/bytebuddy/description/method/MethodDescription$InDefinedShape;
       4: areturn
}
