Compiled from "LazySpringBeanAutowiringSupport.java"
public abstract class won.protocol.util.LazySpringBeanAutowiringSupport extends org.springframework.web.context.support.SpringBeanAutowiringSupport {
  public won.protocol.util.LazySpringBeanAutowiringSupport();
    Code:
       0: aload_0
       1: invokespecial #1                  // Method org/springframework/web/context/support/SpringBeanAutowiringSupport."<init>":()V
       4: return

  protected void wireDependenciesLazily();
    Code:
       0: aload_0
       1: invokevirtual #2                  // Method isWired:()Z
       4: ifne          11
       7: aload_0
       8: invokestatic  #3                  // Method processInjectionBasedOnCurrentContext:(Ljava/lang/Object;)V
      11: return

  protected abstract boolean isWired();
}
