Compiled from "ExmlComponentClassGenerator.java"
public final class net.jangaroo.exml.generator.ExmlComponentClassGenerator {
  private net.jangaroo.exml.config.ExmlConfiguration config;

  public net.jangaroo.exml.generator.ExmlComponentClassGenerator(net.jangaroo.exml.config.ExmlConfiguration);
    Code:
       0: aload_0
       1: invokespecial #1                  // Method java/lang/Object."<init>":()V
       4: aload_0
       5: aload_1
       6: putfield      #2                  // Field config:Lnet/jangaroo/exml/config/ExmlConfiguration;
       9: return

  public java.io.File computeComponentClassTarget(net.jangaroo.exml.model.ExmlModel);
    Code:
       0: aload_1
       1: invokevirtual #3                  // Method net/jangaroo/exml/model/ExmlModel.getPackageName:()Ljava/lang/String;
       4: aload_1
       5: invokevirtual #4                  // Method net/jangaroo/exml/model/ExmlModel.getClassName:()Ljava/lang/String;
       8: aload_0
       9: getfield      #2                  // Field config:Lnet/jangaroo/exml/config/ExmlConfiguration;
      12: invokevirtual #5                  // Method net/jangaroo/exml/config/ExmlConfiguration.getOutputDirectory:()Ljava/io/File;
      15: ldc           #6                  // String .as
      17: invokestatic  #7                  // Method net/jangaroo/utils/CompilerUtils.fileFromQName:(Ljava/lang/String;Ljava/lang/String;Ljava/io/File;Ljava/lang/String;)Ljava/io/File;
      20: areturn

  public void generateClass(net.jangaroo.exml.model.ExmlModel, java.io.Writer) throws java.io.IOException, freemarker.template.TemplateException;
    Code:
       0: new           #8                  // class freemarker/template/Configuration
       3: dup
       4: invokespecial #9                  // Method freemarker/template/Configuration."<init>":()V
       7: astore_3
       8: aload_3
       9: ldc_w         #10                 // class net/jangaroo/exml/generator/ExmlComponentClassModel
      12: ldc           #11                 // String /
      14: invokevirtual #12                 // Method freemarker/template/Configuration.setClassForTemplateLoading:(Ljava/lang/Class;Ljava/lang/String;)V
      17: aload_3
      18: new           #13                 // class freemarker/template/DefaultObjectWrapper
      21: dup
      22: invokespecial #14                 // Method freemarker/template/DefaultObjectWrapper."<init>":()V
      25: invokevirtual #15                 // Method freemarker/template/Configuration.setObjectWrapper:(Lfreemarker/template/ObjectWrapper;)V
      28: aload_3
      29: ldc           #16                 // String /net/jangaroo/exml/templates/exml_component_class.ftl
      31: invokevirtual #17                 // Method freemarker/template/Configuration.getTemplate:(Ljava/lang/String;)Lfreemarker/template/Template;
      34: astore        4
      36: new           #10                 // class net/jangaroo/exml/generator/ExmlComponentClassModel
      39: dup
      40: aload_1
      41: invokespecial #18                 // Method net/jangaroo/exml/generator/ExmlComponentClassModel."<init>":(Lnet/jangaroo/exml/model/ExmlModel;)V
      44: astore        5
      46: aload         4
      48: aload         5
      50: aload_2
      51: invokevirtual #19                 // Method freemarker/template/Template.createProcessingEnvironment:(Ljava/lang/Object;Ljava/io/Writer;)Lfreemarker/core/Environment;
      54: astore        6
      56: aload         6
      58: ldc           #20                 // String UTF-8
      60: invokevirtual #21                 // Method freemarker/core/Environment.setOutputEncoding:(Ljava/lang/String;)V
      63: aload         6
      65: invokevirtual #22                 // Method freemarker/core/Environment.process:()V
      68: return

  public java.io.File generateClass(net.jangaroo.exml.model.ExmlModel) throws java.io.IOException, freemarker.template.TemplateException;
    Code:
       0: aload_0
       1: aload_1
       2: invokevirtual #23                 // Method computeComponentClassTarget:(Lnet/jangaroo/exml/model/ExmlModel;)Ljava/io/File;
       5: astore_2
       6: aconst_null
       7: astore_3
       8: aload_2
       9: invokevirtual #24                 // Method java/io/File.getParentFile:()Ljava/io/File;
      12: invokevirtual #25                 // Method java/io/File.mkdirs:()Z
      15: pop
      16: new           #26                 // class java/io/OutputStreamWriter
      19: dup
      20: new           #27                 // class java/io/FileOutputStream
      23: dup
      24: aload_2
      25: invokespecial #28                 // Method java/io/FileOutputStream."<init>":(Ljava/io/File;)V
      28: ldc           #20                 // String UTF-8
      30: invokespecial #29                 // Method java/io/OutputStreamWriter."<init>":(Ljava/io/OutputStream;Ljava/lang/String;)V
      33: astore_3
      34: aload_0
      35: aload_1
      36: aload_3
      37: invokevirtual #30                 // Method generateClass:(Lnet/jangaroo/exml/model/ExmlModel;Ljava/io/Writer;)V
      40: aload_2
      41: astore        4
      43: aload_3
      44: ifnull        51
      47: aload_3
      48: invokevirtual #31                 // Method java/io/Writer.close:()V
      51: goto          56
      54: astore        5
      56: aload         4
      58: areturn
      59: astore        6
      61: aload_3
      62: ifnull        69
      65: aload_3
      66: invokevirtual #31                 // Method java/io/Writer.close:()V
      69: goto          74
      72: astore        7
      74: aload         6
      76: athrow
    Exception table:
       from    to  target type
          43    51    54   Class java/io/IOException
           8    43    59   any
          61    69    72   Class java/io/IOException
          59    61    59   any
}
