Compiled from "CharMatcher.java"
final class com.google.common.base.CharMatcher$InRange extends com.google.common.base.CharMatcher$FastMatcher {
  private final char startInclusive;

  private final char endInclusive;

  com.google.common.base.CharMatcher$InRange(char, char);
    Code:
       0: aload_0
       1: invokespecial #1                  // Method com/google/common/base/CharMatcher$FastMatcher."<init>":()V
       4: iload_2
       5: iload_1
       6: if_icmplt     13
       9: iconst_1
      10: goto          14
      13: iconst_0
      14: invokestatic  #2                  // Method com/google/common/base/Preconditions.checkArgument:(Z)V
      17: aload_0
      18: iload_1
      19: putfield      #3                  // Field startInclusive:C
      22: aload_0
      23: iload_2
      24: putfield      #4                  // Field endInclusive:C
      27: return

  public boolean matches(char);
    Code:
       0: aload_0
       1: getfield      #3                  // Field startInclusive:C
       4: iload_1
       5: if_icmpgt     20
       8: iload_1
       9: aload_0
      10: getfield      #4                  // Field endInclusive:C
      13: if_icmpgt     20
      16: iconst_1
      17: goto          21
      20: iconst_0
      21: ireturn

  void setBits(java.util.BitSet);
    Code:
       0: aload_1
       1: aload_0
       2: getfield      #3                  // Field startInclusive:C
       5: aload_0
       6: getfield      #4                  // Field endInclusive:C
       9: iconst_1
      10: iadd
      11: invokevirtual #5                  // Method java/util/BitSet.set:(II)V
      14: return

  public java.lang.String toString();
    Code:
       0: aload_0
       1: getfield      #3                  // Field startInclusive:C
       4: invokestatic  #6                  // Method com/google/common/base/CharMatcher.access$100:(C)Ljava/lang/String;
       7: astore_1
       8: aload_0
       9: getfield      #4                  // Field endInclusive:C
      12: invokestatic  #6                  // Method com/google/common/base/CharMatcher.access$100:(C)Ljava/lang/String;
      15: astore_2
      16: bipush        27
      18: aload_1
      19: invokestatic  #7                  // Method java/lang/String.valueOf:(Ljava/lang/Object;)Ljava/lang/String;
      22: invokevirtual #8                  // Method java/lang/String.length:()I
      25: iadd
      26: aload_2
      27: invokestatic  #7                  // Method java/lang/String.valueOf:(Ljava/lang/Object;)Ljava/lang/String;
      30: invokevirtual #8                  // Method java/lang/String.length:()I
      33: iadd
      34: new           #9                  // class java/lang/StringBuilder
      37: dup_x1
      38: swap
      39: invokespecial #10                 // Method java/lang/StringBuilder."<init>":(I)V
      42: ldc           #11                 // String CharMatcher.inRange(\'
      44: invokevirtual #12                 // Method java/lang/StringBuilder.append:(Ljava/lang/String;)Ljava/lang/StringBuilder;
      47: aload_1
      48: invokevirtual #12                 // Method java/lang/StringBuilder.append:(Ljava/lang/String;)Ljava/lang/StringBuilder;
      51: ldc           #13                 // String \', \'
      53: invokevirtual #12                 // Method java/lang/StringBuilder.append:(Ljava/lang/String;)Ljava/lang/StringBuilder;
      56: aload_2
      57: invokevirtual #12                 // Method java/lang/StringBuilder.append:(Ljava/lang/String;)Ljava/lang/StringBuilder;
      60: ldc           #14                 // String \')
      62: invokevirtual #12                 // Method java/lang/StringBuilder.append:(Ljava/lang/String;)Ljava/lang/StringBuilder;
      65: invokevirtual #15                 // Method java/lang/StringBuilder.toString:()Ljava/lang/String;
      68: areturn
}
