Compiled from "SecurityUtils.java"
public final class com.google.api.client.util.SecurityUtils {
  public static java.security.KeyStore getDefaultKeyStore() throws java.security.KeyStoreException;
    Code:
       0: invokestatic  #15                 // Method java/security/KeyStore.getDefaultType:()Ljava/lang/String;
       3: invokestatic  #19                 // Method java/security/KeyStore.getInstance:(Ljava/lang/String;)Ljava/security/KeyStore;
       6: areturn

  public static java.security.KeyStore getJavaKeyStore() throws java.security.KeyStoreException;
    Code:
       0: ldc           #22                 // String JKS
       2: invokestatic  #19                 // Method java/security/KeyStore.getInstance:(Ljava/lang/String;)Ljava/security/KeyStore;
       5: areturn

  public static java.security.KeyStore getPkcs12KeyStore() throws java.security.KeyStoreException;
    Code:
       0: ldc           #25                 // String PKCS12
       2: invokestatic  #19                 // Method java/security/KeyStore.getInstance:(Ljava/lang/String;)Ljava/security/KeyStore;
       5: areturn

  public static void loadKeyStore(java.security.KeyStore, java.io.InputStream, java.lang.String) throws java.io.IOException, java.security.GeneralSecurityException;
    Code:
       0: aload_0
       1: aload_1
       2: aload_2
       3: invokevirtual #37                 // Method java/lang/String.toCharArray:()[C
       6: invokevirtual #41                 // Method java/security/KeyStore.load:(Ljava/io/InputStream;[C)V
       9: aload_1
      10: invokevirtual #47                 // Method java/io/InputStream.close:()V
      13: goto          23
      16: astore_3
      17: aload_1
      18: invokevirtual #47                 // Method java/io/InputStream.close:()V
      21: aload_3
      22: athrow
      23: return
    Exception table:
       from    to  target type
           0     9    16   any
          16    17    16   any

  public static java.security.PrivateKey getPrivateKey(java.security.KeyStore, java.lang.String, java.lang.String) throws java.security.GeneralSecurityException;
    Code:
       0: aload_0
       1: aload_1
       2: aload_2
       3: invokevirtual #37                 // Method java/lang/String.toCharArray:()[C
       6: invokevirtual #59                 // Method java/security/KeyStore.getKey:(Ljava/lang/String;[C)Ljava/security/Key;
       9: checkcast     #61                 // class java/security/PrivateKey
      12: areturn

  public static java.security.PrivateKey loadPrivateKeyFromKeyStore(java.security.KeyStore, java.io.InputStream, java.lang.String, java.lang.String, java.lang.String) throws java.io.IOException, java.security.GeneralSecurityException;
    Code:
       0: aload_0
       1: aload_1
       2: aload_2
       3: invokestatic  #67                 // Method loadKeyStore:(Ljava/security/KeyStore;Ljava/io/InputStream;Ljava/lang/String;)V
       6: aload_0
       7: aload_3
       8: aload         4
      10: invokestatic  #69                 // Method getPrivateKey:(Ljava/security/KeyStore;Ljava/lang/String;Ljava/lang/String;)Ljava/security/PrivateKey;
      13: areturn

  public static java.security.KeyFactory getRsaKeyFactory() throws java.security.NoSuchAlgorithmException;
    Code:
       0: ldc           #75                 // String RSA
       2: invokestatic  #80                 // Method java/security/KeyFactory.getInstance:(Ljava/lang/String;)Ljava/security/KeyFactory;
       5: areturn

  public static java.security.Signature getSha1WithRsaSignatureAlgorithm() throws java.security.NoSuchAlgorithmException;
    Code:
       0: ldc           #84                 // String SHA1withRSA
       2: invokestatic  #89                 // Method java/security/Signature.getInstance:(Ljava/lang/String;)Ljava/security/Signature;
       5: areturn

  public static java.security.Signature getSha256WithRsaSignatureAlgorithm() throws java.security.NoSuchAlgorithmException;
    Code:
       0: ldc           #92                 // String SHA256withRSA
       2: invokestatic  #89                 // Method java/security/Signature.getInstance:(Ljava/lang/String;)Ljava/security/Signature;
       5: areturn

  public static byte[] sign(java.security.Signature, java.security.PrivateKey, byte[]) throws java.security.InvalidKeyException, java.security.SignatureException;
    Code:
       0: aload_0
       1: aload_1
       2: invokevirtual #102                // Method java/security/Signature.initSign:(Ljava/security/PrivateKey;)V
       5: aload_0
       6: aload_2
       7: invokevirtual #106                // Method java/security/Signature.update:([B)V
      10: aload_0
      11: invokevirtual #109                // Method java/security/Signature.sign:()[B
      14: areturn

  public static boolean verify(java.security.Signature, java.security.PublicKey, byte[], byte[]) throws java.security.InvalidKeyException, java.security.SignatureException;
    Code:
       0: aload_0
       1: aload_1
       2: invokevirtual #121                // Method java/security/Signature.initVerify:(Ljava/security/PublicKey;)V
       5: aload_0
       6: aload_3
       7: invokevirtual #106                // Method java/security/Signature.update:([B)V
      10: aload_0
      11: aload_2
      12: invokevirtual #124                // Method java/security/Signature.verify:([B)Z
      15: ireturn
      16: astore        4
      18: iconst_0
      19: ireturn
    Exception table:
       from    to  target type
          10    15    16   Class java/security/SignatureException

  public static java.security.cert.X509Certificate verify(java.security.Signature, javax.net.ssl.X509TrustManager, java.util.List<java.lang.String>, byte[], byte[]) throws java.security.InvalidKeyException, java.security.SignatureException;
    Code:
       0: invokestatic  #136                // Method getX509CertificateFactory:()Ljava/security/cert/CertificateFactory;
       3: astore        5
       5: goto          12
       8: astore        6
      10: aconst_null
      11: areturn
      12: aload_2
      13: invokeinterface #142,  1          // InterfaceMethod java/util/List.size:()I
      18: anewarray     #144                // class java/security/cert/X509Certificate
      21: astore        6
      23: iconst_0
      24: istore        7
      26: aload_2
      27: invokeinterface #148,  1          // InterfaceMethod java/util/List.iterator:()Ljava/util/Iterator;
      32: astore        8
      34: aload         8
      36: invokeinterface #154,  1          // InterfaceMethod java/util/Iterator.hasNext:()Z
      41: ifeq          116
      44: aload         8
      46: invokeinterface #158,  1          // InterfaceMethod java/util/Iterator.next:()Ljava/lang/Object;
      51: checkcast     #33                 // class java/lang/String
      54: astore        9
      56: aload         9
      58: invokestatic  #164                // Method com/google/api/client/util/Base64.decodeBase64:(Ljava/lang/String;)[B
      61: astore        10
      63: new           #166                // class java/io/ByteArrayInputStream
      66: dup
      67: aload         10
      69: invokespecial #169                // Method java/io/ByteArrayInputStream."<init>":([B)V
      72: astore        11
      74: aload         5
      76: aload         11
      78: invokevirtual #175                // Method java/security/cert/CertificateFactory.generateCertificate:(Ljava/io/InputStream;)Ljava/security/cert/Certificate;
      81: astore        12
      83: aload         12
      85: instanceof    #144                // class java/security/cert/X509Certificate
      88: ifne          93
      91: aconst_null
      92: areturn
      93: aload         6
      95: iload         7
      97: iinc          7, 1
     100: aload         12
     102: checkcast     #144                // class java/security/cert/X509Certificate
     105: aastore
     106: goto          113
     109: astore        12
     111: aconst_null
     112: areturn
     113: goto          34
     116: aload_1
     117: aload         6
     119: ldc           #75                 // String RSA
     121: invokeinterface #181,  3          // InterfaceMethod javax/net/ssl/X509TrustManager.checkServerTrusted:([Ljava/security/cert/X509Certificate;Ljava/lang/String;)V
     126: goto          133
     129: astore        8
     131: aconst_null
     132: areturn
     133: aload         6
     135: iconst_0
     136: aaload
     137: invokevirtual #185                // Method java/security/cert/X509Certificate.getPublicKey:()Ljava/security/PublicKey;
     140: astore        8
     142: aload_0
     143: aload         8
     145: aload_3
     146: aload         4
     148: invokestatic  #187                // Method verify:(Ljava/security/Signature;Ljava/security/PublicKey;[B[B)Z
     151: ifeq          159
     154: aload         6
     156: iconst_0
     157: aaload
     158: areturn
     159: aconst_null
     160: areturn
    Exception table:
       from    to  target type
           0     5     8   Class java/security/cert/CertificateException
          74    92   109   Class java/security/cert/CertificateException
          93   106   109   Class java/security/cert/CertificateException
         116   126   129   Class java/security/cert/CertificateException

  public static java.security.cert.CertificateFactory getX509CertificateFactory() throws java.security.cert.CertificateException;
    Code:
       0: ldc           #210                // String X.509
       2: invokestatic  #213                // Method java/security/cert/CertificateFactory.getInstance:(Ljava/lang/String;)Ljava/security/cert/CertificateFactory;
       5: areturn

  public static void loadKeyStoreFromCertificates(java.security.KeyStore, java.security.cert.CertificateFactory, java.io.InputStream) throws java.security.GeneralSecurityException;
    Code:
       0: iconst_0
       1: istore_3
       2: aload_1
       3: aload_2
       4: invokevirtual #219                // Method java/security/cert/CertificateFactory.generateCertificates:(Ljava/io/InputStream;)Ljava/util/Collection;
       7: invokeinterface #222,  1          // InterfaceMethod java/util/Collection.iterator:()Ljava/util/Iterator;
      12: astore        4
      14: aload         4
      16: invokeinterface #154,  1          // InterfaceMethod java/util/Iterator.hasNext:()Z
      21: ifeq          52
      24: aload         4
      26: invokeinterface #158,  1          // InterfaceMethod java/util/Iterator.next:()Ljava/lang/Object;
      31: checkcast     #224                // class java/security/cert/Certificate
      34: astore        5
      36: aload_0
      37: iload_3
      38: invokestatic  #228                // Method java/lang/String.valueOf:(I)Ljava/lang/String;
      41: aload         5
      43: invokevirtual #232                // Method java/security/KeyStore.setCertificateEntry:(Ljava/lang/String;Ljava/security/cert/Certificate;)V
      46: iinc          3, 1
      49: goto          14
      52: return

  private com.google.api.client.util.SecurityUtils();
    Code:
       0: aload_0
       1: invokespecial #236                // Method java/lang/Object."<init>":()V
       4: return
}
