Compiled from "Throwables.java"
public final class com.google.api.client.util.Throwables {
  public static java.lang.RuntimeException propagate(java.lang.Throwable);
    Code:
       0: aload_0
       1: invokestatic  #11                 // Method com/google/api/client/repackaged/com/google/common/base/Throwables.propagate:(Ljava/lang/Throwable;)Ljava/lang/RuntimeException;
       4: areturn

  public static void propagateIfPossible(java.lang.Throwable);
    Code:
       0: aload_0
       1: invokestatic  #17                 // Method com/google/api/client/repackaged/com/google/common/base/Throwables.propagateIfPossible:(Ljava/lang/Throwable;)V
       4: return

  public static <X extends java.lang.Throwable> void propagateIfPossible(java.lang.Throwable, java.lang.Class<X>) throws X;
    Code:
       0: aload_0
       1: aload_1
       2: invokestatic  #22                 // Method com/google/api/client/repackaged/com/google/common/base/Throwables.propagateIfPossible:(Ljava/lang/Throwable;Ljava/lang/Class;)V
       5: return

  private com.google.api.client.util.Throwables();
    Code:
       0: aload_0
       1: invokespecial #29                 // Method java/lang/Object."<init>":()V
       4: return
}
