Compiled from "CorsFilter.scala"
public class wvlet.airframe.http.filter.Cors$CorsFilter implements wvlet.airframe.http.RxHttpFilter {
  private final wvlet.airframe.http.filter.Cors$Policy policy;

  public wvlet.airframe.http.RxHttpFilter andThen(wvlet.airframe.http.RxHttpFilter);
    Code:
       0: aload_0
       1: aload_1
       2: invokestatic  #35                 // InterfaceMethod wvlet/airframe/http/RxHttpFilter.andThen$:(Lwvlet/airframe/http/RxHttpFilter;Lwvlet/airframe/http/RxHttpFilter;)Lwvlet/airframe/http/RxHttpFilter;
       5: areturn

  public wvlet.airframe.http.RxHttpEndpoint andThen(wvlet.airframe.http.RxHttpEndpoint);
    Code:
       0: aload_0
       1: aload_1
       2: invokestatic  #43                 // InterfaceMethod wvlet/airframe/http/RxHttpFilter.andThen$:(Lwvlet/airframe/http/RxHttpFilter;Lwvlet/airframe/http/RxHttpEndpoint;)Lwvlet/airframe/http/RxHttpEndpoint;
       5: areturn

  public wvlet.airframe.http.RxHttpEndpoint andThen(scala.Function1<wvlet.airframe.http.HttpMessage$Request, wvlet.airframe.rx.Rx<wvlet.airframe.http.HttpMessage$Response>>);
    Code:
       0: aload_0
       1: aload_1
       2: invokestatic  #50                 // InterfaceMethod wvlet/airframe/http/RxHttpFilter.andThen$:(Lwvlet/airframe/http/RxHttpFilter;Lscala/Function1;)Lwvlet/airframe/http/RxHttpEndpoint;
       5: areturn

  private scala.Option<java.lang.String> getOrigin(wvlet.airframe.http.HttpMessage$Request);
    Code:
       0: aload_1
       1: invokevirtual #59                 // Method wvlet/airframe/http/HttpMessage$Request.header:()Lwvlet/airframe/http/HttpMultiMap;
       4: ldc           #61                 // String Origin
       6: invokevirtual #67                 // Method wvlet/airframe/http/HttpMultiMap.get:(Ljava/lang/String;)Lscala/Option;
       9: areturn

  private scala.Option<java.lang.String> getMethod(wvlet.airframe.http.HttpMessage$Request);
    Code:
       0: aload_1
       1: invokevirtual #59                 // Method wvlet/airframe/http/HttpMessage$Request.header:()Lwvlet/airframe/http/HttpMultiMap;
       4: ldc           #71                 // String Access-Control-Request-Method
       6: invokevirtual #67                 // Method wvlet/airframe/http/HttpMultiMap.get:(Ljava/lang/String;)Lscala/Option;
       9: areturn

  private scala.util.matching.Regex commaSpace();
    Code:
       0: getstatic     #79                 // Field scala/collection/StringOps$.MODULE$:Lscala/collection/StringOps$;
       3: getstatic     #84                 // Field scala/Predef$.MODULE$:Lscala/Predef$;
       6: ldc           #86                 // String , *
       8: invokevirtual #90                 // Method scala/Predef$.augmentString:(Ljava/lang/String;)Ljava/lang/String;
      11: invokevirtual #94                 // Method scala/collection/StringOps$.r$extension:(Ljava/lang/String;)Lscala/util/matching/Regex;
      14: areturn

  private scala.collection.immutable.Seq<java.lang.String> getHeaders(wvlet.airframe.http.HttpMessage$Request);
    Code:
       0: aload_1
       1: invokevirtual #59                 // Method wvlet/airframe/http/HttpMessage$Request.header:()Lwvlet/airframe/http/HttpMultiMap;
       4: ldc           #99                 // String Access-Control-Request-Headers
       6: invokevirtual #67                 // Method wvlet/airframe/http/HttpMultiMap.get:(Ljava/lang/String;)Lscala/Option;
       9: astore_3
      10: aload_3
      11: instanceof    #101                // class scala/Some
      14: ifeq          58
      17: aload_3
      18: checkcast     #101                // class scala/Some
      21: astore        4
      23: aload         4
      25: invokevirtual #105                // Method scala/Some.value:()Ljava/lang/Object;
      28: checkcast     #107                // class java/lang/String
      31: astore        5
      33: getstatic     #112                // Field scala/collection/ArrayOps$.MODULE$:Lscala/collection/ArrayOps$;
      36: getstatic     #84                 // Field scala/Predef$.MODULE$:Lscala/Predef$;
      39: aload_0
      40: invokespecial #114                // Method commaSpace:()Lscala/util/matching/Regex;
      43: aload         5
      45: invokevirtual #120                // Method scala/util/matching/Regex.split:(Ljava/lang/CharSequence;)[Ljava/lang/String;
      48: checkcast     #122                // class "[Ljava/lang/Object;"
      51: invokevirtual #126                // Method scala/Predef$.refArrayOps:([Ljava/lang/Object;)Ljava/lang/Object;
      54: invokevirtual #130                // Method scala/collection/ArrayOps$.toSeq$extension:(Ljava/lang/Object;)Lscala/collection/immutable/Seq;
      57: areturn
      58: goto          61
      61: getstatic     #135                // Field scala/None$.MODULE$:Lscala/None$;
      64: aload_3
      65: invokevirtual #139                // Method java/lang/Object.equals:(Ljava/lang/Object;)Z
      68: ifeq          75
      71: getstatic     #144                // Field scala/collection/immutable/Nil$.MODULE$:Lscala/collection/immutable/Nil$;
      74: areturn
      75: goto          78
      78: new           #146                // class scala/MatchError
      81: dup
      82: aload_3
      83: invokespecial #150                // Method scala/MatchError."<init>":(Ljava/lang/Object;)V
      86: athrow

  private wvlet.airframe.http.HttpMessage$Response setOriginAndCredential(wvlet.airframe.http.HttpMessage$Response, java.lang.String);
    Code:
       0: aload_1
       1: ldc           #159                // String Access-Control-Allow-Origin
       3: aload_2
       4: invokevirtual #163                // Method wvlet/airframe/http/HttpMessage$Response.withHeader:(Ljava/lang/String;Ljava/lang/String;)Ljava/lang/Object;
       7: checkcast     #19                 // class wvlet/airframe/http/HttpMessage$Response
      10: astore_3
      11: aload_0
      12: getfield      #165                // Field policy:Lwvlet/airframe/http/filter/Cors$Policy;
      15: invokevirtual #169                // Method wvlet/airframe/http/filter/Cors$Policy.supportsCredentials:()Z
      18: ifeq          62
      21: aload_2
      22: ldc           #171                // String *
      24: astore        4
      26: dup
      27: ifnonnull     39
      30: pop
      31: aload         4
      33: ifnull        62
      36: goto          47
      39: aload         4
      41: invokevirtual #139                // Method java/lang/Object.equals:(Ljava/lang/Object;)Z
      44: ifne          62
      47: aload_3
      48: ldc           #173                // String Access-Control-Allow-Credentials
      50: ldc           #175                // String true
      52: invokevirtual #163                // Method wvlet/airframe/http/HttpMessage$Response.withHeader:(Ljava/lang/String;Ljava/lang/String;)Ljava/lang/Object;
      55: checkcast     #19                 // class wvlet/airframe/http/HttpMessage$Response
      58: astore_3
      59: goto          62
      62: aload_3
      63: areturn

  private wvlet.airframe.http.HttpMessage$Response addExposedHeaders(wvlet.airframe.http.HttpMessage$Response);
    Code:
       0: aload_0
       1: getfield      #165                // Field policy:Lwvlet/airframe/http/filter/Cors$Policy;
       4: invokevirtual #184                // Method wvlet/airframe/http/filter/Cors$Policy.exposedHeaders:()Lscala/collection/immutable/Seq;
       7: invokeinterface #189,  1          // InterfaceMethod scala/collection/immutable/Seq.nonEmpty:()Z
      12: ifeq          39
      15: aload_1
      16: ldc           #191                // String Access-Control-Expose-Headers
      18: aload_0
      19: getfield      #165                // Field policy:Lwvlet/airframe/http/filter/Cors$Policy;
      22: invokevirtual #184                // Method wvlet/airframe/http/filter/Cors$Policy.exposedHeaders:()Lscala/collection/immutable/Seq;
      25: ldc           #193                // String ,
      27: invokeinterface #196,  2          // InterfaceMethod scala/collection/immutable/Seq.mkString:(Ljava/lang/String;)Ljava/lang/String;
      32: invokevirtual #163                // Method wvlet/airframe/http/HttpMessage$Response.withHeader:(Ljava/lang/String;Ljava/lang/String;)Ljava/lang/Object;
      35: checkcast     #19                 // class wvlet/airframe/http/HttpMessage$Response
      38: areturn
      39: aload_1
      40: areturn

  private scala.Option<wvlet.airframe.http.HttpMessage$Response> handlePreflight(wvlet.airframe.http.HttpMessage$Request);
    Code:
       0: aload_0
       1: aload_1
       2: invokespecial #200                // Method getOrigin:(Lwvlet/airframe/http/HttpMessage$Request;)Lscala/Option;
       5: aload_0
       6: aload_1
       7: invokedynamic #221,  0            // InvokeDynamic #0:apply:(Lwvlet/airframe/http/filter/Cors$CorsFilter;Lwvlet/airframe/http/HttpMessage$Request;)Lscala/Function1;
      12: invokevirtual #225                // Method scala/Option.flatMap:(Lscala/Function1;)Lscala/Option;
      15: areturn

  private wvlet.airframe.http.HttpMessage$Response handleSimple(wvlet.airframe.http.HttpMessage$Request, wvlet.airframe.http.HttpMessage$Response);
    Code:
       0: aload_0
       1: aload_1
       2: invokespecial #200                // Method getOrigin:(Lwvlet/airframe/http/HttpMessage$Request;)Lscala/Option;
       5: aload_0
       6: aload_2
       7: invokedynamic #237,  0            // InvokeDynamic #1:apply:(Lwvlet/airframe/http/filter/Cors$CorsFilter;Lwvlet/airframe/http/HttpMessage$Response;)Lscala/Function1;
      12: invokevirtual #240                // Method scala/Option.map:(Lscala/Function1;)Lscala/Option;
      15: aload_0
      16: invokedynamic #249,  0            // InvokeDynamic #2:apply:(Lwvlet/airframe/http/filter/Cors$CorsFilter;)Lscala/Function1;
      21: invokevirtual #240                // Method scala/Option.map:(Lscala/Function1;)Lscala/Option;
      24: aload_2
      25: invokedynamic #259,  0            // InvokeDynamic #3:apply:(Lwvlet/airframe/http/HttpMessage$Response;)Lscala/Function0;
      30: invokevirtual #263                // Method scala/Option.getOrElse:(Lscala/Function0;)Ljava/lang/Object;
      33: checkcast     #19                 // class wvlet/airframe/http/HttpMessage$Response
      36: areturn

  public wvlet.airframe.rx.Rx<wvlet.airframe.http.HttpMessage$Response> apply(wvlet.airframe.http.HttpMessage$Request, wvlet.airframe.http.RxHttpEndpoint);
    Code:
       0: aload_1
       1: invokevirtual #270                // Method wvlet/airframe/http/HttpMessage$Request.method:()Ljava/lang/String;
       4: astore        6
       6: aload         6
       8: ifnonnull     15
      11: iconst_0
      12: goto          20
      15: aload         6
      17: invokevirtual #274                // Method java/lang/String.hashCode:()I
      20: tableswitch   { // -531492226 to -531492226
            -531492226: 40
               default: 143
          }
      40: ldc_w         #276                // String OPTIONS
      43: aload         6
      45: invokevirtual #277                // Method java/lang/String.equals:(Ljava/lang/Object;)Z
      48: ifeq          140
      51: aload_0
      52: aload_1
      53: invokespecial #279                // Method handlePreflight:(Lwvlet/airframe/http/HttpMessage$Request;)Lscala/Option;
      56: astore        7
      58: aload         7
      60: instanceof    #101                // class scala/Some
      63: ifeq          99
      66: aload         7
      68: checkcast     #101                // class scala/Some
      71: astore        8
      73: aload         8
      75: invokevirtual #105                // Method scala/Some.value:()Ljava/lang/Object;
      78: checkcast     #19                 // class wvlet/airframe/http/HttpMessage$Response
      81: astore        9
      83: getstatic     #284                // Field wvlet/airframe/rx/Rx$.MODULE$:Lwvlet/airframe/rx/Rx$;
      86: aload         9
      88: invokedynamic #289,  0            // InvokeDynamic #4:apply:(Lwvlet/airframe/http/HttpMessage$Response;)Lscala/Function0;
      93: invokevirtual #293                // Method wvlet/airframe/rx/Rx$.single:(Lscala/Function0;)Lwvlet/airframe/rx/Rx;
      96: goto          168
      99: goto          102
     102: getstatic     #135                // Field scala/None$.MODULE$:Lscala/None$;
     105: aload         7
     107: invokevirtual #139                // Method java/lang/Object.equals:(Ljava/lang/Object;)Z
     110: ifeq          127
     113: getstatic     #284                // Field wvlet/airframe/rx/Rx$.MODULE$:Lwvlet/airframe/rx/Rx$;
     116: invokedynamic #300,  0            // InvokeDynamic #5:apply:()Lscala/Function0;
     121: invokevirtual #293                // Method wvlet/airframe/rx/Rx$.single:(Lscala/Function0;)Lwvlet/airframe/rx/Rx;
     124: goto          168
     127: goto          130
     130: new           #146                // class scala/MatchError
     133: dup
     134: aload         7
     136: invokespecial #150                // Method scala/MatchError."<init>":(Ljava/lang/Object;)V
     139: athrow
     140: goto          146
     143: goto          146
     146: aload_2
     147: aload_1
     148: invokeinterface #305,  2          // InterfaceMethod wvlet/airframe/http/RxHttpEndpoint.apply:(Lwvlet/airframe/http/HttpMessage$Request;)Lwvlet/airframe/rx/Rx;
     153: aload_0
     154: aload_1
     155: invokedynamic #311,  0            // InvokeDynamic #6:apply:(Lwvlet/airframe/http/filter/Cors$CorsFilter;Lwvlet/airframe/http/HttpMessage$Request;)Lscala/Function1;
     160: invokeinterface #316,  2          // InterfaceMethod wvlet/airframe/rx/Rx.map:(Lscala/Function1;)Lwvlet/airframe/rx/Rx;
     165: goto          168
     168: astore        5
     170: aload         5
     172: invokedynamic #323,  0            // InvokeDynamic #7:apply:()Lscala/Function1;
     177: invokeinterface #316,  2          // InterfaceMethod wvlet/airframe/rx/Rx.map:(Lscala/Function1;)Lwvlet/airframe/rx/Rx;
     182: areturn

  public static final void $anonfun$handlePreflight$5(scala.runtime.ObjectRef, scala.concurrent.duration.Duration);
    Code:
       0: aload_0
       1: aload_0
       2: getfield      #334                // Field scala/runtime/ObjectRef.elem:Ljava/lang/Object;
       5: checkcast     #19                 // class wvlet/airframe/http/HttpMessage$Response
       8: ldc_w         #336                // String Access-Control-Max-Age
      11: aload_1
      12: invokevirtual #342                // Method scala/concurrent/duration/Duration.toSeconds:()J
      15: invokestatic  #348                // Method java/lang/Long.toString:(J)Ljava/lang/String;
      18: invokevirtual #163                // Method wvlet/airframe/http/HttpMessage$Response.withHeader:(Ljava/lang/String;Ljava/lang/String;)Ljava/lang/Object;
      21: checkcast     #19                 // class wvlet/airframe/http/HttpMessage$Response
      24: putfield      #334                // Field scala/runtime/ObjectRef.elem:Ljava/lang/Object;
      27: return

  public static final wvlet.airframe.http.HttpMessage$Response $anonfun$handlePreflight$4(wvlet.airframe.http.filter.Cors$CorsFilter, java.lang.String, scala.collection.immutable.Seq, scala.collection.immutable.Seq);
    Code:
       0: getstatic     #361                // Field wvlet/airframe/http/Http$.MODULE$:Lwvlet/airframe/http/Http$;
       3: getstatic     #361                // Field wvlet/airframe/http/Http$.MODULE$:Lwvlet/airframe/http/Http$;
       6: invokevirtual #365                // Method wvlet/airframe/http/Http$.response$default$1:()Lwvlet/airframe/http/HttpStatus;
       9: invokevirtual #368                // Method wvlet/airframe/http/Http$.response:(Lwvlet/airframe/http/HttpStatus;)Lwvlet/airframe/http/HttpMessage$Response;
      12: invokestatic  #372                // Method scala/runtime/ObjectRef.create:(Ljava/lang/Object;)Lscala/runtime/ObjectRef;
      15: astore        4
      17: aload         4
      19: aload_0
      20: aload         4
      22: getfield      #334                // Field scala/runtime/ObjectRef.elem:Ljava/lang/Object;
      25: checkcast     #19                 // class wvlet/airframe/http/HttpMessage$Response
      28: aload_1
      29: invokespecial #374                // Method setOriginAndCredential:(Lwvlet/airframe/http/HttpMessage$Response;Ljava/lang/String;)Lwvlet/airframe/http/HttpMessage$Response;
      32: putfield      #334                // Field scala/runtime/ObjectRef.elem:Ljava/lang/Object;
      35: aload_0
      36: getfield      #165                // Field policy:Lwvlet/airframe/http/filter/Cors$Policy;
      39: invokevirtual #377                // Method wvlet/airframe/http/filter/Cors$Policy.maxAge:()Lscala/Option;
      42: aload         4
      44: invokedynamic #387,  0            // InvokeDynamic #8:apply:(Lscala/runtime/ObjectRef;)Lscala/Function1;
      49: invokevirtual #391                // Method scala/Option.foreach:(Lscala/Function1;)V
      52: aload         4
      54: aload         4
      56: getfield      #334                // Field scala/runtime/ObjectRef.elem:Ljava/lang/Object;
      59: checkcast     #19                 // class wvlet/airframe/http/HttpMessage$Response
      62: ldc_w         #393                // String Access-Control-Allow-Methods
      65: aload_2
      66: ldc           #193                // String ,
      68: invokeinterface #196,  2          // InterfaceMethod scala/collection/immutable/Seq.mkString:(Ljava/lang/String;)Ljava/lang/String;
      73: invokevirtual #163                // Method wvlet/airframe/http/HttpMessage$Response.withHeader:(Ljava/lang/String;Ljava/lang/String;)Ljava/lang/Object;
      76: checkcast     #19                 // class wvlet/airframe/http/HttpMessage$Response
      79: putfield      #334                // Field scala/runtime/ObjectRef.elem:Ljava/lang/Object;
      82: aload         4
      84: aload         4
      86: getfield      #334                // Field scala/runtime/ObjectRef.elem:Ljava/lang/Object;
      89: checkcast     #19                 // class wvlet/airframe/http/HttpMessage$Response
      92: ldc_w         #395                // String Access-Control-Allow-Headers
      95: aload_3
      96: ldc           #193                // String ,
      98: invokeinterface #196,  2          // InterfaceMethod scala/collection/immutable/Seq.mkString:(Ljava/lang/String;)Ljava/lang/String;
     103: invokevirtual #163                // Method wvlet/airframe/http/HttpMessage$Response.withHeader:(Ljava/lang/String;Ljava/lang/String;)Ljava/lang/Object;
     106: checkcast     #19                 // class wvlet/airframe/http/HttpMessage$Response
     109: putfield      #334                // Field scala/runtime/ObjectRef.elem:Ljava/lang/Object;
     112: aload         4
     114: getfield      #334                // Field scala/runtime/ObjectRef.elem:Ljava/lang/Object;
     117: checkcast     #19                 // class wvlet/airframe/http/HttpMessage$Response
     120: areturn

  public static final scala.Option $anonfun$handlePreflight$3(wvlet.airframe.http.filter.Cors$CorsFilter, scala.collection.immutable.Seq, java.lang.String, scala.collection.immutable.Seq);
    Code:
       0: aload_0
       1: getfield      #165                // Field policy:Lwvlet/airframe/http/filter/Cors$Policy;
       4: invokevirtual #403                // Method wvlet/airframe/http/filter/Cors$Policy.allowsHeaders:()Lscala/Function1;
       7: aload_1
       8: invokeinterface #407,  2          // InterfaceMethod scala/Function1.apply:(Ljava/lang/Object;)Ljava/lang/Object;
      13: checkcast     #153                // class scala/Option
      16: aload_0
      17: aload_2
      18: aload_3
      19: invokedynamic #415,  0            // InvokeDynamic #9:apply:(Lwvlet/airframe/http/filter/Cors$CorsFilter;Ljava/lang/String;Lscala/collection/immutable/Seq;)Lscala/Function1;
      24: invokevirtual #240                // Method scala/Option.map:(Lscala/Function1;)Lscala/Option;
      27: areturn

  public static final scala.Option $anonfun$handlePreflight$2(wvlet.airframe.http.filter.Cors$CorsFilter, wvlet.airframe.http.HttpMessage$Request, java.lang.String, java.lang.String);
    Code:
       0: aload_0
       1: aload_1
       2: invokespecial #420                // Method getHeaders:(Lwvlet/airframe/http/HttpMessage$Request;)Lscala/collection/immutable/Seq;
       5: astore        4
       7: aload_0
       8: getfield      #165                // Field policy:Lwvlet/airframe/http/filter/Cors$Policy;
      11: invokevirtual #423                // Method wvlet/airframe/http/filter/Cors$Policy.allowsMethods:()Lscala/Function1;
      14: aload_3
      15: invokeinterface #407,  2          // InterfaceMethod scala/Function1.apply:(Ljava/lang/Object;)Ljava/lang/Object;
      20: checkcast     #153                // class scala/Option
      23: aload_0
      24: aload         4
      26: aload_2
      27: invokedynamic #431,  0            // InvokeDynamic #10:apply:(Lwvlet/airframe/http/filter/Cors$CorsFilter;Lscala/collection/immutable/Seq;Ljava/lang/String;)Lscala/Function1;
      32: invokevirtual #225                // Method scala/Option.flatMap:(Lscala/Function1;)Lscala/Option;
      35: areturn

  public static final scala.Option $anonfun$handlePreflight$1(wvlet.airframe.http.filter.Cors$CorsFilter, wvlet.airframe.http.HttpMessage$Request, java.lang.String);
    Code:
       0: aload_0
       1: aload_1
       2: invokespecial #434                // Method getMethod:(Lwvlet/airframe/http/HttpMessage$Request;)Lscala/Option;
       5: aload_0
       6: aload_1
       7: aload_2
       8: invokedynamic #440,  0            // InvokeDynamic #11:apply:(Lwvlet/airframe/http/filter/Cors$CorsFilter;Lwvlet/airframe/http/HttpMessage$Request;Ljava/lang/String;)Lscala/Function1;
      13: invokevirtual #225                // Method scala/Option.flatMap:(Lscala/Function1;)Lscala/Option;
      16: areturn

  public static final wvlet.airframe.http.HttpMessage$Response $anonfun$handleSimple$1(wvlet.airframe.http.filter.Cors$CorsFilter, wvlet.airframe.http.HttpMessage$Response, java.lang.String);
    Code:
       0: aload_0
       1: aload_1
       2: aload_2
       3: invokespecial #374                // Method setOriginAndCredential:(Lwvlet/airframe/http/HttpMessage$Response;Ljava/lang/String;)Lwvlet/airframe/http/HttpMessage$Response;
       6: areturn

  public static final wvlet.airframe.http.HttpMessage$Response $anonfun$handleSimple$2(wvlet.airframe.http.filter.Cors$CorsFilter, wvlet.airframe.http.HttpMessage$Response);
    Code:
       0: aload_0
       1: aload_1
       2: invokespecial #443                // Method addExposedHeaders:(Lwvlet/airframe/http/HttpMessage$Response;)Lwvlet/airframe/http/HttpMessage$Response;
       5: areturn

  public static final wvlet.airframe.http.HttpMessage$Response $anonfun$handleSimple$3(wvlet.airframe.http.HttpMessage$Response);
    Code:
       0: aload_0
       1: areturn

  public static final wvlet.airframe.http.HttpMessage$Response $anonfun$apply$1(wvlet.airframe.http.HttpMessage$Response);
    Code:
       0: aload_0
       1: areturn

  public static final wvlet.airframe.http.HttpMessage$Response $anonfun$apply$2();
    Code:
       0: getstatic     #361                // Field wvlet/airframe/http/Http$.MODULE$:Lwvlet/airframe/http/Http$;
       3: getstatic     #361                // Field wvlet/airframe/http/Http$.MODULE$:Lwvlet/airframe/http/Http$;
       6: invokevirtual #365                // Method wvlet/airframe/http/Http$.response$default$1:()Lwvlet/airframe/http/HttpStatus;
       9: invokevirtual #368                // Method wvlet/airframe/http/Http$.response:(Lwvlet/airframe/http/HttpStatus;)Lwvlet/airframe/http/HttpMessage$Response;
      12: areturn

  public static final wvlet.airframe.http.HttpMessage$Response $anonfun$apply$3(wvlet.airframe.http.filter.Cors$CorsFilter, wvlet.airframe.http.HttpMessage$Request, wvlet.airframe.http.HttpMessage$Response);
    Code:
       0: aload_0
       1: aload_1
       2: aload_2
       3: invokespecial #448                // Method handleSimple:(Lwvlet/airframe/http/HttpMessage$Request;Lwvlet/airframe/http/HttpMessage$Response;)Lwvlet/airframe/http/HttpMessage$Response;
       6: areturn

  public static final wvlet.airframe.http.HttpMessage$Response $anonfun$apply$4(wvlet.airframe.http.HttpMessage$Response);
    Code:
       0: aload_0
       1: ldc_w         #450                // String Vary
       4: ldc           #61                 // String Origin
       6: invokevirtual #163                // Method wvlet/airframe/http/HttpMessage$Response.withHeader:(Ljava/lang/String;Ljava/lang/String;)Ljava/lang/Object;
       9: checkcast     #19                 // class wvlet/airframe/http/HttpMessage$Response
      12: areturn

  public wvlet.airframe.http.filter.Cors$CorsFilter(wvlet.airframe.http.filter.Cors$Policy);
    Code:
       0: aload_0
       1: aload_1
       2: putfield      #165                // Field policy:Lwvlet/airframe/http/filter/Cors$Policy;
       5: aload_0
       6: invokespecial #454                // Method java/lang/Object."<init>":()V
       9: aload_0
      10: invokestatic  #458                // InterfaceMethod wvlet/airframe/http/RxHttpFilter.$init$:(Lwvlet/airframe/http/RxHttpFilter;)V
      13: return

  public static final java.lang.Object $anonfun$handlePreflight$5$adapted(scala.runtime.ObjectRef, scala.concurrent.duration.Duration);
    Code:
       0: aload_0
       1: aload_1
       2: invokestatic  #460                // Method $anonfun$handlePreflight$5:(Lscala/runtime/ObjectRef;Lscala/concurrent/duration/Duration;)V
       5: getstatic     #466                // Field scala/runtime/BoxedUnit.UNIT:Lscala/runtime/BoxedUnit;
       8: areturn

  private static java.lang.Object $deserializeLambda$(java.lang.invoke.SerializedLambda);
    Code:
       0: aload_0
       1: invokedynamic #478,  0            // InvokeDynamic #12:lambdaDeserialize:(Ljava/lang/invoke/SerializedLambda;)Ljava/lang/Object;
       6: areturn
}
