Compiled from "ConnectorDelegate.java"
class org.springframework.jmx.access.ConnectorDelegate {
  private static final org.apache.commons.logging.Log logger;

  private javax.management.remote.JMXConnector connector;

  org.springframework.jmx.access.ConnectorDelegate();
    Code:
       0: aload_0
       1: invokespecial #1                  // Method java/lang/Object."<init>":()V
       4: return

  public javax.management.MBeanServerConnection connect(javax.management.remote.JMXServiceURL, java.util.Map<java.lang.String, ?>, java.lang.String) throws org.springframework.jmx.MBeanServerNotFoundException;
    Code:
       0: aload_1
       1: ifnull        102
       4: getstatic     #2                  // Field logger:Lorg/apache/commons/logging/Log;
       7: invokeinterface #3,  1            // InterfaceMethod org/apache/commons/logging/Log.isDebugEnabled:()Z
      12: ifeq          47
      15: getstatic     #2                  // Field logger:Lorg/apache/commons/logging/Log;
      18: new           #4                  // class java/lang/StringBuilder
      21: dup
      22: invokespecial #5                  // Method java/lang/StringBuilder."<init>":()V
      25: ldc           #6                  // String Connecting to remote MBeanServer at URL [
      27: invokevirtual #7                  // Method java/lang/StringBuilder.append:(Ljava/lang/String;)Ljava/lang/StringBuilder;
      30: aload_1
      31: invokevirtual #8                  // Method java/lang/StringBuilder.append:(Ljava/lang/Object;)Ljava/lang/StringBuilder;
      34: ldc           #9                  // String ]
      36: invokevirtual #7                  // Method java/lang/StringBuilder.append:(Ljava/lang/String;)Ljava/lang/StringBuilder;
      39: invokevirtual #10                 // Method java/lang/StringBuilder.toString:()Ljava/lang/String;
      42: invokeinterface #11,  2           // InterfaceMethod org/apache/commons/logging/Log.debug:(Ljava/lang/Object;)V
      47: aload_0
      48: aload_1
      49: aload_2
      50: invokestatic  #12                 // Method javax/management/remote/JMXConnectorFactory.connect:(Ljavax/management/remote/JMXServiceURL;Ljava/util/Map;)Ljavax/management/remote/JMXConnector;
      53: putfield      #13                 // Field connector:Ljavax/management/remote/JMXConnector;
      56: aload_0
      57: getfield      #13                 // Field connector:Ljavax/management/remote/JMXConnector;
      60: invokeinterface #14,  1           // InterfaceMethod javax/management/remote/JMXConnector.getMBeanServerConnection:()Ljavax/management/MBeanServerConnection;
      65: areturn
      66: astore        4
      68: new           #16                 // class org/springframework/jmx/MBeanServerNotFoundException
      71: dup
      72: new           #4                  // class java/lang/StringBuilder
      75: dup
      76: invokespecial #5                  // Method java/lang/StringBuilder."<init>":()V
      79: ldc           #17                 // String Could not connect to remote MBeanServer [
      81: invokevirtual #7                  // Method java/lang/StringBuilder.append:(Ljava/lang/String;)Ljava/lang/StringBuilder;
      84: aload_1
      85: invokevirtual #8                  // Method java/lang/StringBuilder.append:(Ljava/lang/Object;)Ljava/lang/StringBuilder;
      88: ldc           #9                  // String ]
      90: invokevirtual #7                  // Method java/lang/StringBuilder.append:(Ljava/lang/String;)Ljava/lang/StringBuilder;
      93: invokevirtual #10                 // Method java/lang/StringBuilder.toString:()Ljava/lang/String;
      96: aload         4
      98: invokespecial #18                 // Method org/springframework/jmx/MBeanServerNotFoundException."<init>":(Ljava/lang/String;Ljava/lang/Throwable;)V
     101: athrow
     102: getstatic     #2                  // Field logger:Lorg/apache/commons/logging/Log;
     105: ldc           #19                 // String Attempting to locate local MBeanServer
     107: invokeinterface #11,  2           // InterfaceMethod org/apache/commons/logging/Log.debug:(Ljava/lang/Object;)V
     112: aload_3
     113: invokestatic  #20                 // Method org/springframework/jmx/support/JmxUtils.locateMBeanServer:(Ljava/lang/String;)Ljavax/management/MBeanServer;
     116: areturn
    Exception table:
       from    to  target type
          47    65    66   Class java/io/IOException

  public void close();
    Code:
       0: aload_0
       1: getfield      #13                 // Field connector:Ljavax/management/remote/JMXConnector;
       4: ifnull        31
       7: aload_0
       8: getfield      #13                 // Field connector:Ljavax/management/remote/JMXConnector;
      11: invokeinterface #21,  1           // InterfaceMethod javax/management/remote/JMXConnector.close:()V
      16: goto          31
      19: astore_1
      20: getstatic     #2                  // Field logger:Lorg/apache/commons/logging/Log;
      23: ldc           #22                 // String Could not close JMX connector
      25: aload_1
      26: invokeinterface #23,  3           // InterfaceMethod org/apache/commons/logging/Log.debug:(Ljava/lang/Object;Ljava/lang/Throwable;)V
      31: return
    Exception table:
       from    to  target type
           7    16    19   Class java/io/IOException

  static {};
    Code:
       0: ldc           #24                 // class org/springframework/jmx/access/ConnectorDelegate
       2: invokestatic  #25                 // Method org/apache/commons/logging/LogFactory.getLog:(Ljava/lang/Class;)Lorg/apache/commons/logging/Log;
       5: putstatic     #2                  // Field logger:Lorg/apache/commons/logging/Log;
       8: return
}
