Compiled from "SimpleKeyInfoReferenceEncryptedKeyResolver.java"
public class org.opensaml.xmlsec.encryption.support.SimpleKeyInfoReferenceEncryptedKeyResolver extends org.opensaml.xmlsec.encryption.support.AbstractEncryptedKeyResolver {
  private final org.slf4j.Logger log;

  private int depthLimit;

  public org.opensaml.xmlsec.encryption.support.SimpleKeyInfoReferenceEncryptedKeyResolver();
    Code:
       0: aload_0
       1: aconst_null
       2: checkcast     #1                  // class java/util/Set
       5: invokespecial #2                  // Method "<init>":(Ljava/util/Set;)V
       8: return

  public org.opensaml.xmlsec.encryption.support.SimpleKeyInfoReferenceEncryptedKeyResolver(java.util.Set<java.lang.String>);
    Code:
       0: aload_0
       1: aload_1
       2: invokespecial #3                  // Method org/opensaml/xmlsec/encryption/support/AbstractEncryptedKeyResolver."<init>":(Ljava/util/Set;)V
       5: aload_0
       6: ldc_w         #4                  // class org/opensaml/xmlsec/encryption/support/SimpleKeyInfoReferenceEncryptedKeyResolver
       9: invokestatic  #5                  // Method org/slf4j/LoggerFactory.getLogger:(Ljava/lang/Class;)Lorg/slf4j/Logger;
      12: putfield      #6                  // Field log:Lorg/slf4j/Logger;
      15: aload_0
      16: iconst_5
      17: putfield      #7                  // Field depthLimit:I
      20: return

  public org.opensaml.xmlsec.encryption.support.SimpleKeyInfoReferenceEncryptedKeyResolver(java.lang.String);
    Code:
       0: aload_0
       1: aload_1
       2: invokestatic  #8                  // Method java/util/Collections.singleton:(Ljava/lang/Object;)Ljava/util/Set;
       5: invokespecial #2                  // Method "<init>":(Ljava/util/Set;)V
       8: return

  public int getDepthLimit();
    Code:
       0: aload_0
       1: getfield      #7                  // Field depthLimit:I
       4: ireturn

  public void setDepthLimit(int);
    Code:
       0: aload_0
       1: iconst_1
       2: iload_1
       3: invokestatic  #9                  // Method java/lang/Math.max:(II)I
       6: putfield      #7                  // Field depthLimit:I
       9: return

  public java.lang.Iterable<org.opensaml.xmlsec.encryption.EncryptedKey> resolve(org.opensaml.xmlsec.encryption.EncryptedData);
    Code:
       0: aload_1
       1: ldc           #10                 // String EncryptedData cannot be null
       3: invokestatic  #11                 // Method net/shibboleth/utilities/java/support/logic/Constraint.isNotNull:(Ljava/lang/Object;Ljava/lang/String;)Ljava/lang/Object;
       6: pop
       7: aload_0
       8: aload_1
       9: invokeinterface #12,  1           // InterfaceMethod org/opensaml/xmlsec/encryption/EncryptedData.getKeyInfo:()Lorg/opensaml/xmlsec/signature/KeyInfo;
      14: aload_0
      15: getfield      #7                  // Field depthLimit:I
      18: invokevirtual #13                 // Method resolveKeyInfo:(Lorg/opensaml/xmlsec/signature/KeyInfo;I)Ljava/lang/Iterable;
      21: areturn

  protected java.lang.Iterable<org.opensaml.xmlsec.encryption.EncryptedKey> resolveKeyInfo(org.opensaml.xmlsec.signature.KeyInfo, int);
    Code:
       0: new           #14                 // class java/util/ArrayList
       3: dup
       4: invokespecial #15                 // Method java/util/ArrayList."<init>":()V
       7: astore_3
       8: aload_1
       9: ifnonnull     14
      12: aload_3
      13: areturn
      14: iload_2
      15: aload_0
      16: getfield      #7                  // Field depthLimit:I
      19: if_icmpge     83
      22: aload_1
      23: invokeinterface #16,  1           // InterfaceMethod org/opensaml/xmlsec/signature/KeyInfo.getEncryptedKeys:()Ljava/util/List;
      28: invokeinterface #17,  1           // InterfaceMethod java/util/List.iterator:()Ljava/util/Iterator;
      33: astore        4
      35: aload         4
      37: invokeinterface #18,  1           // InterfaceMethod java/util/Iterator.hasNext:()Z
      42: ifeq          83
      45: aload         4
      47: invokeinterface #19,  1           // InterfaceMethod java/util/Iterator.next:()Ljava/lang/Object;
      52: checkcast     #20                 // class org/opensaml/xmlsec/encryption/EncryptedKey
      55: astore        5
      57: aload_0
      58: aload         5
      60: invokeinterface #21,  1           // InterfaceMethod org/opensaml/xmlsec/encryption/EncryptedKey.getRecipient:()Ljava/lang/String;
      65: invokevirtual #22                 // Method matchRecipient:(Ljava/lang/String;)Z
      68: ifeq          80
      71: aload_3
      72: aload         5
      74: invokeinterface #23,  2           // InterfaceMethod java/util/List.add:(Ljava/lang/Object;)Z
      79: pop
      80: goto          35
      83: iload_2
      84: ifne          101
      87: aload_0
      88: getfield      #6                  // Field log:Lorg/slf4j/Logger;
      91: ldc           #24                 // String Reached depth limit for KeyInfoReferences
      93: invokeinterface #25,  2           // InterfaceMethod org/slf4j/Logger.info:(Ljava/lang/String;)V
      98: goto          193
     101: aload_1
     102: invokeinterface #26,  1           // InterfaceMethod org/opensaml/xmlsec/signature/KeyInfo.getKeyInfoReferences:()Ljava/util/List;
     107: invokeinterface #17,  1           // InterfaceMethod java/util/List.iterator:()Ljava/util/Iterator;
     112: astore        4
     114: aload         4
     116: invokeinterface #18,  1           // InterfaceMethod java/util/Iterator.hasNext:()Z
     121: ifeq          193
     124: aload         4
     126: invokeinterface #19,  1           // InterfaceMethod java/util/Iterator.next:()Ljava/lang/Object;
     131: checkcast     #27                 // class org/opensaml/xmlsec/signature/KeyInfoReference
     134: astore        5
     136: aload_0
     137: aload_0
     138: aload         5
     140: invokevirtual #28                 // Method dereferenceURI:(Lorg/opensaml/xmlsec/signature/KeyInfoReference;)Lorg/opensaml/xmlsec/signature/KeyInfo;
     143: iload_2
     144: iconst_1
     145: isub
     146: invokevirtual #13                 // Method resolveKeyInfo:(Lorg/opensaml/xmlsec/signature/KeyInfo;I)Ljava/lang/Iterable;
     149: invokeinterface #29,  1           // InterfaceMethod java/lang/Iterable.iterator:()Ljava/util/Iterator;
     154: astore        6
     156: aload         6
     158: invokeinterface #18,  1           // InterfaceMethod java/util/Iterator.hasNext:()Z
     163: ifeq          190
     166: aload         6
     168: invokeinterface #19,  1           // InterfaceMethod java/util/Iterator.next:()Ljava/lang/Object;
     173: checkcast     #20                 // class org/opensaml/xmlsec/encryption/EncryptedKey
     176: astore        7
     178: aload_3
     179: aload         7
     181: invokeinterface #23,  2           // InterfaceMethod java/util/List.add:(Ljava/lang/Object;)Z
     186: pop
     187: goto          156
     190: goto          114
     193: aload_3
     194: areturn

  protected org.opensaml.xmlsec.signature.KeyInfo dereferenceURI(org.opensaml.xmlsec.signature.KeyInfoReference);
    Code:
       0: aload_1
       1: invokeinterface #30,  1           // InterfaceMethod org/opensaml/xmlsec/signature/KeyInfoReference.getURI:()Ljava/lang/String;
       6: astore_2
       7: aload_2
       8: ifnull        27
      11: aload_2
      12: invokevirtual #31                 // Method java/lang/String.isEmpty:()Z
      15: ifne          27
      18: aload_2
      19: ldc           #32                 // String #
      21: invokevirtual #33                 // Method java/lang/String.startsWith:(Ljava/lang/String;)Z
      24: ifne          40
      27: aload_0
      28: getfield      #6                  // Field log:Lorg/slf4j/Logger;
      31: ldc           #34                 // String EncryptedKey KeyInfoReference did not contain a same-document URI reference, cannot process
      33: invokeinterface #35,  2           // InterfaceMethod org/slf4j/Logger.warn:(Ljava/lang/String;)V
      38: aconst_null
      39: areturn
      40: aload_1
      41: aload_2
      42: iconst_1
      43: invokevirtual #36                 // Method java/lang/String.substring:(I)Ljava/lang/String;
      46: invokeinterface #37,  2           // InterfaceMethod org/opensaml/xmlsec/signature/KeyInfoReference.resolveIDFromRoot:(Ljava/lang/String;)Lorg/opensaml/core/xml/XMLObject;
      51: astore_3
      52: aload_3
      53: ifnonnull     69
      56: aload_0
      57: getfield      #6                  // Field log:Lorg/slf4j/Logger;
      60: ldc           #38                 // String EncryptedKey KeyInfoReference URI could not be dereferenced
      62: invokeinterface #35,  2           // InterfaceMethod org/slf4j/Logger.warn:(Ljava/lang/String;)V
      67: aconst_null
      68: areturn
      69: aload_3
      70: instanceof    #39                 // class org/opensaml/xmlsec/signature/KeyInfo
      73: ifne          89
      76: aload_0
      77: getfield      #6                  // Field log:Lorg/slf4j/Logger;
      80: ldc           #40                 // String The product of dereferencing the EncryptedKey KeyInfoReference was not a KeyInfo
      82: invokeinterface #35,  2           // InterfaceMethod org/slf4j/Logger.warn:(Ljava/lang/String;)V
      87: aconst_null
      88: areturn
      89: aload_3
      90: checkcast     #39                 // class org/opensaml/xmlsec/signature/KeyInfo
      93: areturn
}
