Compiled from "Loader.java"
public class org.hibernate.loader.Loader$SqlStatementWrapper {
  private final java.sql.Statement statement;

  private final java.sql.ResultSet resultSet;

  private org.hibernate.loader.Loader$SqlStatementWrapper(java.sql.Statement, java.sql.ResultSet);
    Code:
       0: aload_0
       1: invokespecial #2                  // Method java/lang/Object."<init>":()V
       4: aload_0
       5: aload_2
       6: putfield      #3                  // Field resultSet:Ljava/sql/ResultSet;
       9: aload_0
      10: aload_1
      11: putfield      #4                  // Field statement:Ljava/sql/Statement;
      14: return

  public java.sql.ResultSet getResultSet();
    Code:
       0: aload_0
       1: getfield      #3                  // Field resultSet:Ljava/sql/ResultSet;
       4: areturn

  public java.sql.Statement getStatement();
    Code:
       0: aload_0
       1: getfield      #4                  // Field statement:Ljava/sql/Statement;
       4: areturn

  org.hibernate.loader.Loader$SqlStatementWrapper(java.sql.Statement, java.sql.ResultSet, org.hibernate.loader.Loader$1);
    Code:
       0: aload_0
       1: aload_1
       2: aload_2
       3: invokespecial #1                  // Method "<init>":(Ljava/sql/Statement;Ljava/sql/ResultSet;)V
       6: return
}
