Compiled from "I18nClassloader.java"
class org.sonar.core.i18n.I18nClassloader extends java.net.URLClassLoader {
  private final java.lang.ClassLoader[] pluginClassloaders;

  public org.sonar.core.i18n.I18nClassloader(org.sonar.core.platform.PluginRepository);
    Code:
       0: aload_0
       1: aload_1
       2: invokestatic  #1                  // Method allPluginClassloaders:(Lorg/sonar/core/platform/PluginRepository;)Ljava/util/List;
       5: invokespecial #2                  // Method "<init>":(Ljava/util/List;)V
       8: return

  org.sonar.core.i18n.I18nClassloader(java.util.List<java.lang.ClassLoader>);
    Code:
       0: aload_0
       1: iconst_0
       2: anewarray     #3                  // class java/net/URL
       5: invokespecial #4                  // Method java/net/URLClassLoader."<init>":([Ljava/net/URL;)V
       8: aload_0
       9: aload_1
      10: aload_1
      11: invokeinterface #5,  1            // InterfaceMethod java/util/List.size:()I
      16: anewarray     #6                  // class java/lang/ClassLoader
      19: invokeinterface #7,  2            // InterfaceMethod java/util/List.toArray:([Ljava/lang/Object;)[Ljava/lang/Object;
      24: checkcast     #8                  // class "[Ljava/lang/ClassLoader;"
      27: putfield      #9                  // Field pluginClassloaders:[Ljava/lang/ClassLoader;
      30: return

  public java.net.URL getResource(java.lang.String);
    Code:
       0: aload_0
       1: getfield      #9                  // Field pluginClassloaders:[Ljava/lang/ClassLoader;
       4: astore_2
       5: aload_2
       6: arraylength
       7: istore_3
       8: iconst_0
       9: istore        4
      11: iload         4
      13: iload_3
      14: if_icmpge     45
      17: aload_2
      18: iload         4
      20: aaload
      21: astore        5
      23: aload         5
      25: aload_1
      26: invokevirtual #10                 // Method java/lang/ClassLoader.getResource:(Ljava/lang/String;)Ljava/net/URL;
      29: astore        6
      31: aload         6
      33: ifnull        39
      36: aload         6
      38: areturn
      39: iinc          4, 1
      42: goto          11
      45: aload_0
      46: invokevirtual #11                 // Method java/lang/Object.getClass:()Ljava/lang/Class;
      49: invokevirtual #12                 // Method java/lang/Class.getClassLoader:()Ljava/lang/ClassLoader;
      52: aload_1
      53: invokevirtual #10                 // Method java/lang/ClassLoader.getResource:(Ljava/lang/String;)Ljava/net/URL;
      56: areturn

  protected synchronized java.lang.Class loadClass(java.lang.String, boolean) throws java.lang.ClassNotFoundException;
    Code:
       0: new           #13                 // class java/lang/UnsupportedOperationException
       3: dup
       4: ldc           #14                 // String I18n classloader does support only resources, but not classes
       6: invokespecial #15                 // Method java/lang/UnsupportedOperationException."<init>":(Ljava/lang/String;)V
       9: athrow

  public java.lang.String toString();
    Code:
       0: ldc           #16                 // String i18n-classloader
       2: areturn

  private static java.util.List<java.lang.ClassLoader> allPluginClassloaders(org.sonar.core.platform.PluginRepository);
    Code:
       0: invokestatic  #17                 // Method com/google/common/collect/Lists.newArrayList:()Ljava/util/ArrayList;
       3: astore_1
       4: aload_0
       5: invokeinterface #18,  1           // InterfaceMethod org/sonar/core/platform/PluginRepository.getPluginInfos:()Ljava/util/Collection;
      10: invokeinterface #19,  1           // InterfaceMethod java/util/Collection.iterator:()Ljava/util/Iterator;
      15: astore_2
      16: aload_2
      17: invokeinterface #20,  1           // InterfaceMethod java/util/Iterator.hasNext:()Z
      22: ifeq          65
      25: aload_2
      26: invokeinterface #21,  1           // InterfaceMethod java/util/Iterator.next:()Ljava/lang/Object;
      31: checkcast     #22                 // class org/sonar/core/platform/PluginInfo
      34: astore_3
      35: aload_0
      36: aload_3
      37: invokevirtual #23                 // Method org/sonar/core/platform/PluginInfo.getKey:()Ljava/lang/String;
      40: invokeinterface #24,  2           // InterfaceMethod org/sonar/core/platform/PluginRepository.getPluginInstance:(Ljava/lang/String;)Lorg/sonar/api/Plugin;
      45: astore        4
      47: aload_1
      48: aload         4
      50: invokevirtual #11                 // Method java/lang/Object.getClass:()Ljava/lang/Class;
      53: invokevirtual #12                 // Method java/lang/Class.getClassLoader:()Ljava/lang/ClassLoader;
      56: invokeinterface #25,  2           // InterfaceMethod java/util/List.add:(Ljava/lang/Object;)Z
      61: pop
      62: goto          16
      65: aload_1
      66: ldc           #26                 // class org/sonar/core/i18n/I18nClassloader
      68: invokevirtual #12                 // Method java/lang/Class.getClassLoader:()Ljava/lang/ClassLoader;
      71: invokeinterface #25,  2           // InterfaceMethod java/util/List.add:(Ljava/lang/Object;)Z
      76: pop
      77: aload_1
      78: areturn
}
