Compiled from "NamespaceEventImpl.java"
public class org.codehaus.stax2.ri.evt.NamespaceEventImpl extends org.codehaus.stax2.ri.evt.AttributeEventImpl implements javax.xml.stream.events.Namespace {
  final java.lang.String mPrefix;

  final java.lang.String mURI;

  protected org.codehaus.stax2.ri.evt.NamespaceEventImpl(javax.xml.stream.Location, java.lang.String);
    Code:
       0: aload_0
       1: aload_1
       2: ldc           #1                  // String xmlns
       4: ldc           #2                  // String http://www.w3.org/2000/xmlns/
       6: aconst_null
       7: aload_2
       8: iconst_1
       9: invokespecial #3                  // Method org/codehaus/stax2/ri/evt/AttributeEventImpl."<init>":(Ljavax/xml/stream/Location;Ljava/lang/String;Ljava/lang/String;Ljava/lang/String;Ljava/lang/String;Z)V
      12: aload_0
      13: ldc           #4                  // String
      15: putfield      #5                  // Field mPrefix:Ljava/lang/String;
      18: aload_0
      19: aload_2
      20: putfield      #6                  // Field mURI:Ljava/lang/String;
      23: return

  protected org.codehaus.stax2.ri.evt.NamespaceEventImpl(javax.xml.stream.Location, java.lang.String, java.lang.String);
    Code:
       0: aload_0
       1: aload_1
       2: aload_2
       3: ldc           #2                  // String http://www.w3.org/2000/xmlns/
       5: ldc           #1                  // String xmlns
       7: aload_3
       8: iconst_1
       9: invokespecial #3                  // Method org/codehaus/stax2/ri/evt/AttributeEventImpl."<init>":(Ljavax/xml/stream/Location;Ljava/lang/String;Ljava/lang/String;Ljava/lang/String;Ljava/lang/String;Z)V
      12: aload_0
      13: aload_2
      14: putfield      #5                  // Field mPrefix:Ljava/lang/String;
      17: aload_0
      18: aload_3
      19: putfield      #6                  // Field mURI:Ljava/lang/String;
      22: return

  public static org.codehaus.stax2.ri.evt.NamespaceEventImpl constructDefaultNamespace(javax.xml.stream.Location, java.lang.String);
    Code:
       0: new           #7                  // class org/codehaus/stax2/ri/evt/NamespaceEventImpl
       3: dup
       4: aload_0
       5: aload_1
       6: invokespecial #8                  // Method "<init>":(Ljavax/xml/stream/Location;Ljava/lang/String;)V
       9: areturn

  public static org.codehaus.stax2.ri.evt.NamespaceEventImpl constructNamespace(javax.xml.stream.Location, java.lang.String, java.lang.String);
    Code:
       0: aload_1
       1: ifnull        11
       4: aload_1
       5: invokevirtual #9                  // Method java/lang/String.length:()I
       8: ifne          21
      11: new           #7                  // class org/codehaus/stax2/ri/evt/NamespaceEventImpl
      14: dup
      15: aload_0
      16: aload_2
      17: invokespecial #8                  // Method "<init>":(Ljavax/xml/stream/Location;Ljava/lang/String;)V
      20: areturn
      21: new           #7                  // class org/codehaus/stax2/ri/evt/NamespaceEventImpl
      24: dup
      25: aload_0
      26: aload_1
      27: aload_2
      28: invokespecial #10                 // Method "<init>":(Ljavax/xml/stream/Location;Ljava/lang/String;Ljava/lang/String;)V
      31: areturn

  public java.lang.String getNamespaceURI();
    Code:
       0: aload_0
       1: getfield      #6                  // Field mURI:Ljava/lang/String;
       4: areturn

  public java.lang.String getPrefix();
    Code:
       0: aload_0
       1: getfield      #5                  // Field mPrefix:Ljava/lang/String;
       4: areturn

  public boolean isDefaultNamespaceDeclaration();
    Code:
       0: aload_0
       1: getfield      #5                  // Field mPrefix:Ljava/lang/String;
       4: invokevirtual #9                  // Method java/lang/String.length:()I
       7: ifne          14
      10: iconst_1
      11: goto          15
      14: iconst_0
      15: ireturn

  public int getEventType();
    Code:
       0: bipush        13
       2: ireturn

  public boolean isNamespace();
    Code:
       0: iconst_1
       1: ireturn
}
