Compiled from "SecureHashMap.java"
final class io.undertow.util.SecureHashMap$BranchIterator extends io.undertow.util.SecureHashMap<K, V>.TableIterator {
  private final io.undertow.util.SecureHashMap<K, V>.TableIterator branch0;

  private final io.undertow.util.SecureHashMap<K, V>.TableIterator branch1;

  private boolean branch;

  final io.undertow.util.SecureHashMap this$0;

  io.undertow.util.SecureHashMap$BranchIterator(io.undertow.util.SecureHashMap<K, V>.TableIterator, io.undertow.util.SecureHashMap<K, V>.TableIterator);
    Code:
       0: aload_0
       1: aload_1
       2: putfield      #1                  // Field this$0:Lio/undertow/util/SecureHashMap;
       5: aload_0
       6: aload_1
       7: invokespecial #2                  // Method io/undertow/util/SecureHashMap$TableIterator."<init>":(Lio/undertow/util/SecureHashMap;)V
      10: aload_0
      11: aload_2
      12: putfield      #3                  // Field branch0:Lio/undertow/util/SecureHashMap$TableIterator;
      15: aload_0
      16: aload_3
      17: putfield      #4                  // Field branch1:Lio/undertow/util/SecureHashMap$TableIterator;
      20: return

  public boolean hasNext();
    Code:
       0: aload_0
       1: getfield      #3                  // Field branch0:Lio/undertow/util/SecureHashMap$TableIterator;
       4: invokevirtual #5                  // Method io/undertow/util/SecureHashMap$TableIterator.hasNext:()Z
       7: ifne          20
      10: aload_0
      11: getfield      #4                  // Field branch1:Lio/undertow/util/SecureHashMap$TableIterator;
      14: invokevirtual #5                  // Method io/undertow/util/SecureHashMap$TableIterator.hasNext:()Z
      17: ifeq          24
      20: iconst_1
      21: goto          25
      24: iconst_0
      25: ireturn

  public io.undertow.util.SecureHashMap$Item<K, V> next();
    Code:
       0: aload_0
       1: getfield      #6                  // Field branch:Z
       4: ifeq          15
       7: aload_0
       8: getfield      #4                  // Field branch1:Lio/undertow/util/SecureHashMap$TableIterator;
      11: invokevirtual #7                  // Method io/undertow/util/SecureHashMap$TableIterator.next:()Lio/undertow/util/SecureHashMap$Item;
      14: areturn
      15: aload_0
      16: getfield      #3                  // Field branch0:Lio/undertow/util/SecureHashMap$TableIterator;
      19: invokevirtual #5                  // Method io/undertow/util/SecureHashMap$TableIterator.hasNext:()Z
      22: ifeq          33
      25: aload_0
      26: getfield      #3                  // Field branch0:Lio/undertow/util/SecureHashMap$TableIterator;
      29: invokevirtual #7                  // Method io/undertow/util/SecureHashMap$TableIterator.next:()Lio/undertow/util/SecureHashMap$Item;
      32: areturn
      33: aload_0
      34: iconst_1
      35: putfield      #6                  // Field branch:Z
      38: aload_0
      39: getfield      #4                  // Field branch1:Lio/undertow/util/SecureHashMap$TableIterator;
      42: invokevirtual #7                  // Method io/undertow/util/SecureHashMap$TableIterator.next:()Lio/undertow/util/SecureHashMap$Item;
      45: areturn

  V nextValue();
    Code:
       0: aload_0
       1: getfield      #6                  // Field branch:Z
       4: ifeq          15
       7: aload_0
       8: getfield      #4                  // Field branch1:Lio/undertow/util/SecureHashMap$TableIterator;
      11: invokevirtual #8                  // Method io/undertow/util/SecureHashMap$TableIterator.nextValue:()Ljava/lang/Object;
      14: areturn
      15: aload_0
      16: getfield      #3                  // Field branch0:Lio/undertow/util/SecureHashMap$TableIterator;
      19: invokevirtual #8                  // Method io/undertow/util/SecureHashMap$TableIterator.nextValue:()Ljava/lang/Object;
      22: astore_1
      23: aload_1
      24: invokestatic  #9                  // Method io/undertow/util/SecureHashMap.access$500:()Ljava/lang/Object;
      27: if_acmpeq     32
      30: aload_1
      31: areturn
      32: aload_0
      33: iconst_1
      34: putfield      #6                  // Field branch:Z
      37: aload_0
      38: getfield      #4                  // Field branch1:Lio/undertow/util/SecureHashMap$TableIterator;
      41: invokevirtual #8                  // Method io/undertow/util/SecureHashMap$TableIterator.nextValue:()Ljava/lang/Object;
      44: areturn

  public void remove();
    Code:
       0: aload_0
       1: getfield      #6                  // Field branch:Z
       4: ifeq          17
       7: aload_0
       8: getfield      #3                  // Field branch0:Lio/undertow/util/SecureHashMap$TableIterator;
      11: invokevirtual #10                 // Method io/undertow/util/SecureHashMap$TableIterator.remove:()V
      14: goto          24
      17: aload_0
      18: getfield      #4                  // Field branch1:Lio/undertow/util/SecureHashMap$TableIterator;
      21: invokevirtual #10                 // Method io/undertow/util/SecureHashMap$TableIterator.remove:()V
      24: return

  public java.lang.Object next();
    Code:
       0: aload_0
       1: invokevirtual #11                 // Method next:()Lio/undertow/util/SecureHashMap$Item;
       4: areturn
}
