Compiled from "ThreadLocalContextStorage.java"
final class io.grpc.ThreadLocalContextStorage extends io.grpc.Context$Storage {
  private static final java.util.logging.Logger log;

  static final java.lang.ThreadLocal<io.grpc.Context> localContext;

  io.grpc.ThreadLocalContextStorage();
    Code:
       0: aload_0
       1: invokespecial #1                  // Method io/grpc/Context$Storage."<init>":()V
       4: return

  public io.grpc.Context doAttach(io.grpc.Context);
    Code:
       0: aload_0
       1: invokevirtual #2                  // Method current:()Lio/grpc/Context;
       4: astore_2
       5: getstatic     #3                  // Field localContext:Ljava/lang/ThreadLocal;
       8: aload_1
       9: invokevirtual #4                  // Method java/lang/ThreadLocal.set:(Ljava/lang/Object;)V
      12: aload_2
      13: areturn

  public void detach(io.grpc.Context, io.grpc.Context);
    Code:
       0: aload_0
       1: invokevirtual #2                  // Method current:()Lio/grpc/Context;
       4: aload_1
       5: if_acmpeq     29
       8: getstatic     #5                  // Field log:Ljava/util/logging/Logger;
      11: getstatic     #6                  // Field java/util/logging/Level.SEVERE:Ljava/util/logging/Level;
      14: ldc           #7                  // String Context was not attached when detaching
      16: new           #8                  // class java/lang/Throwable
      19: dup
      20: invokespecial #9                  // Method java/lang/Throwable."<init>":()V
      23: invokevirtual #10                 // Method java/lang/Throwable.fillInStackTrace:()Ljava/lang/Throwable;
      26: invokevirtual #11                 // Method java/util/logging/Logger.log:(Ljava/util/logging/Level;Ljava/lang/String;Ljava/lang/Throwable;)V
      29: aload_2
      30: getstatic     #12                 // Field io/grpc/Context.ROOT:Lio/grpc/Context;
      33: if_acmpeq     46
      36: getstatic     #3                  // Field localContext:Ljava/lang/ThreadLocal;
      39: aload_2
      40: invokevirtual #4                  // Method java/lang/ThreadLocal.set:(Ljava/lang/Object;)V
      43: goto          53
      46: getstatic     #3                  // Field localContext:Ljava/lang/ThreadLocal;
      49: aconst_null
      50: invokevirtual #4                  // Method java/lang/ThreadLocal.set:(Ljava/lang/Object;)V
      53: return

  public io.grpc.Context current();
    Code:
       0: getstatic     #3                  // Field localContext:Ljava/lang/ThreadLocal;
       3: invokevirtual #13                 // Method java/lang/ThreadLocal.get:()Ljava/lang/Object;
       6: checkcast     #14                 // class io/grpc/Context
       9: astore_1
      10: aload_1
      11: ifnonnull     18
      14: getstatic     #12                 // Field io/grpc/Context.ROOT:Lio/grpc/Context;
      17: areturn
      18: aload_1
      19: areturn

  static {};
    Code:
       0: ldc           #15                 // class io/grpc/ThreadLocalContextStorage
       2: invokevirtual #16                 // Method java/lang/Class.getName:()Ljava/lang/String;
       5: invokestatic  #17                 // Method java/util/logging/Logger.getLogger:(Ljava/lang/String;)Ljava/util/logging/Logger;
       8: putstatic     #5                  // Field log:Ljava/util/logging/Logger;
      11: new           #18                 // class java/lang/ThreadLocal
      14: dup
      15: invokespecial #19                 // Method java/lang/ThreadLocal."<init>":()V
      18: putstatic     #3                  // Field localContext:Ljava/lang/ThreadLocal;
      21: return
}
