Compiled from "RichGaugeExporter.java"
public class org.springframework.boot.actuate.metrics.export.RichGaugeExporter extends org.springframework.boot.actuate.metrics.export.AbstractMetricExporter {
  private static final java.lang.String MIN;

  private static final java.lang.String MAX;

  private static final java.lang.String COUNT;

  private static final java.lang.String VALUE;

  private static final java.lang.String AVG;

  private static final java.lang.String ALPHA;

  private final org.springframework.boot.actuate.metrics.rich.RichGaugeReader reader;

  private final org.springframework.boot.actuate.metrics.writer.PrefixMetricWriter writer;

  public org.springframework.boot.actuate.metrics.export.RichGaugeExporter(org.springframework.boot.actuate.metrics.rich.RichGaugeReader, org.springframework.boot.actuate.metrics.writer.PrefixMetricWriter);
    Code:
       0: aload_0
       1: aload_1
       2: aload_2
       3: ldc           #1                  // String
       5: invokespecial #2                  // Method "<init>":(Lorg/springframework/boot/actuate/metrics/rich/RichGaugeReader;Lorg/springframework/boot/actuate/metrics/writer/PrefixMetricWriter;Ljava/lang/String;)V
       8: return

  public org.springframework.boot.actuate.metrics.export.RichGaugeExporter(org.springframework.boot.actuate.metrics.rich.RichGaugeReader, org.springframework.boot.actuate.metrics.writer.PrefixMetricWriter, java.lang.String);
    Code:
       0: aload_0
       1: aload_3
       2: invokespecial #3                  // Method org/springframework/boot/actuate/metrics/export/AbstractMetricExporter."<init>":(Ljava/lang/String;)V
       5: aload_0
       6: aload_1
       7: putfield      #4                  // Field reader:Lorg/springframework/boot/actuate/metrics/rich/RichGaugeReader;
      10: aload_0
      11: aload_2
      12: putfield      #5                  // Field writer:Lorg/springframework/boot/actuate/metrics/writer/PrefixMetricWriter;
      15: return

  protected java.lang.Iterable<org.springframework.boot.actuate.metrics.Metric<?>> next(java.lang.String);
    Code:
       0: aload_0
       1: getfield      #4                  // Field reader:Lorg/springframework/boot/actuate/metrics/rich/RichGaugeReader;
       4: aload_1
       5: invokeinterface #6,  2            // InterfaceMethod org/springframework/boot/actuate/metrics/rich/RichGaugeReader.findOne:(Ljava/lang/String;)Lorg/springframework/boot/actuate/metrics/rich/RichGauge;
      10: astore_2
      11: new           #7                  // class java/util/ArrayList
      14: dup
      15: invokespecial #8                  // Method java/util/ArrayList."<init>":()V
      18: astore_3
      19: aload_3
      20: new           #9                  // class org/springframework/boot/actuate/metrics/Metric
      23: dup
      24: new           #10                 // class java/lang/StringBuilder
      27: dup
      28: invokespecial #11                 // Method java/lang/StringBuilder."<init>":()V
      31: aload_1
      32: invokevirtual #12                 // Method java/lang/StringBuilder.append:(Ljava/lang/String;)Ljava/lang/StringBuilder;
      35: ldc           #14                 // String .min
      37: invokevirtual #12                 // Method java/lang/StringBuilder.append:(Ljava/lang/String;)Ljava/lang/StringBuilder;
      40: invokevirtual #15                 // Method java/lang/StringBuilder.toString:()Ljava/lang/String;
      43: aload_2
      44: invokevirtual #16                 // Method org/springframework/boot/actuate/metrics/rich/RichGauge.getMin:()D
      47: invokestatic  #17                 // Method java/lang/Double.valueOf:(D)Ljava/lang/Double;
      50: invokespecial #18                 // Method org/springframework/boot/actuate/metrics/Metric."<init>":(Ljava/lang/String;Ljava/lang/Number;)V
      53: invokeinterface #19,  2           // InterfaceMethod java/util/Collection.add:(Ljava/lang/Object;)Z
      58: pop
      59: aload_3
      60: new           #9                  // class org/springframework/boot/actuate/metrics/Metric
      63: dup
      64: new           #10                 // class java/lang/StringBuilder
      67: dup
      68: invokespecial #11                 // Method java/lang/StringBuilder."<init>":()V
      71: aload_1
      72: invokevirtual #12                 // Method java/lang/StringBuilder.append:(Ljava/lang/String;)Ljava/lang/StringBuilder;
      75: ldc           #20                 // String .max
      77: invokevirtual #12                 // Method java/lang/StringBuilder.append:(Ljava/lang/String;)Ljava/lang/StringBuilder;
      80: invokevirtual #15                 // Method java/lang/StringBuilder.toString:()Ljava/lang/String;
      83: aload_2
      84: invokevirtual #21                 // Method org/springframework/boot/actuate/metrics/rich/RichGauge.getMax:()D
      87: invokestatic  #17                 // Method java/lang/Double.valueOf:(D)Ljava/lang/Double;
      90: invokespecial #18                 // Method org/springframework/boot/actuate/metrics/Metric."<init>":(Ljava/lang/String;Ljava/lang/Number;)V
      93: invokeinterface #19,  2           // InterfaceMethod java/util/Collection.add:(Ljava/lang/Object;)Z
      98: pop
      99: aload_3
     100: new           #9                  // class org/springframework/boot/actuate/metrics/Metric
     103: dup
     104: new           #10                 // class java/lang/StringBuilder
     107: dup
     108: invokespecial #11                 // Method java/lang/StringBuilder."<init>":()V
     111: aload_1
     112: invokevirtual #12                 // Method java/lang/StringBuilder.append:(Ljava/lang/String;)Ljava/lang/StringBuilder;
     115: ldc           #22                 // String .count
     117: invokevirtual #12                 // Method java/lang/StringBuilder.append:(Ljava/lang/String;)Ljava/lang/StringBuilder;
     120: invokevirtual #15                 // Method java/lang/StringBuilder.toString:()Ljava/lang/String;
     123: aload_2
     124: invokevirtual #23                 // Method org/springframework/boot/actuate/metrics/rich/RichGauge.getCount:()J
     127: invokestatic  #24                 // Method java/lang/Long.valueOf:(J)Ljava/lang/Long;
     130: invokespecial #18                 // Method org/springframework/boot/actuate/metrics/Metric."<init>":(Ljava/lang/String;Ljava/lang/Number;)V
     133: invokeinterface #19,  2           // InterfaceMethod java/util/Collection.add:(Ljava/lang/Object;)Z
     138: pop
     139: aload_3
     140: new           #9                  // class org/springframework/boot/actuate/metrics/Metric
     143: dup
     144: new           #10                 // class java/lang/StringBuilder
     147: dup
     148: invokespecial #11                 // Method java/lang/StringBuilder."<init>":()V
     151: aload_1
     152: invokevirtual #12                 // Method java/lang/StringBuilder.append:(Ljava/lang/String;)Ljava/lang/StringBuilder;
     155: ldc           #25                 // String .val
     157: invokevirtual #12                 // Method java/lang/StringBuilder.append:(Ljava/lang/String;)Ljava/lang/StringBuilder;
     160: invokevirtual #15                 // Method java/lang/StringBuilder.toString:()Ljava/lang/String;
     163: aload_2
     164: invokevirtual #26                 // Method org/springframework/boot/actuate/metrics/rich/RichGauge.getValue:()D
     167: invokestatic  #17                 // Method java/lang/Double.valueOf:(D)Ljava/lang/Double;
     170: invokespecial #18                 // Method org/springframework/boot/actuate/metrics/Metric."<init>":(Ljava/lang/String;Ljava/lang/Number;)V
     173: invokeinterface #19,  2           // InterfaceMethod java/util/Collection.add:(Ljava/lang/Object;)Z
     178: pop
     179: aload_3
     180: new           #9                  // class org/springframework/boot/actuate/metrics/Metric
     183: dup
     184: new           #10                 // class java/lang/StringBuilder
     187: dup
     188: invokespecial #11                 // Method java/lang/StringBuilder."<init>":()V
     191: aload_1
     192: invokevirtual #12                 // Method java/lang/StringBuilder.append:(Ljava/lang/String;)Ljava/lang/StringBuilder;
     195: ldc           #27                 // String .avg
     197: invokevirtual #12                 // Method java/lang/StringBuilder.append:(Ljava/lang/String;)Ljava/lang/StringBuilder;
     200: invokevirtual #15                 // Method java/lang/StringBuilder.toString:()Ljava/lang/String;
     203: aload_2
     204: invokevirtual #28                 // Method org/springframework/boot/actuate/metrics/rich/RichGauge.getAverage:()D
     207: invokestatic  #17                 // Method java/lang/Double.valueOf:(D)Ljava/lang/Double;
     210: invokespecial #18                 // Method org/springframework/boot/actuate/metrics/Metric."<init>":(Ljava/lang/String;Ljava/lang/Number;)V
     213: invokeinterface #19,  2           // InterfaceMethod java/util/Collection.add:(Ljava/lang/Object;)Z
     218: pop
     219: aload_3
     220: new           #9                  // class org/springframework/boot/actuate/metrics/Metric
     223: dup
     224: new           #10                 // class java/lang/StringBuilder
     227: dup
     228: invokespecial #11                 // Method java/lang/StringBuilder."<init>":()V
     231: aload_1
     232: invokevirtual #12                 // Method java/lang/StringBuilder.append:(Ljava/lang/String;)Ljava/lang/StringBuilder;
     235: ldc           #29                 // String .alpha
     237: invokevirtual #12                 // Method java/lang/StringBuilder.append:(Ljava/lang/String;)Ljava/lang/StringBuilder;
     240: invokevirtual #15                 // Method java/lang/StringBuilder.toString:()Ljava/lang/String;
     243: aload_2
     244: invokevirtual #30                 // Method org/springframework/boot/actuate/metrics/rich/RichGauge.getAlpha:()D
     247: invokestatic  #17                 // Method java/lang/Double.valueOf:(D)Ljava/lang/Double;
     250: invokespecial #18                 // Method org/springframework/boot/actuate/metrics/Metric."<init>":(Ljava/lang/String;Ljava/lang/Number;)V
     253: invokeinterface #19,  2           // InterfaceMethod java/util/Collection.add:(Ljava/lang/Object;)Z
     258: pop
     259: aload_3
     260: areturn

  protected java.lang.Iterable<java.lang.String> groups();
    Code:
       0: new           #31                 // class java/util/HashSet
       3: dup
       4: invokespecial #32                 // Method java/util/HashSet."<init>":()V
       7: astore_1
       8: aload_0
       9: getfield      #4                  // Field reader:Lorg/springframework/boot/actuate/metrics/rich/RichGaugeReader;
      12: invokeinterface #33,  1           // InterfaceMethod org/springframework/boot/actuate/metrics/rich/RichGaugeReader.findAll:()Ljava/lang/Iterable;
      17: invokeinterface #34,  1           // InterfaceMethod java/lang/Iterable.iterator:()Ljava/util/Iterator;
      22: astore_2
      23: aload_2
      24: invokeinterface #35,  1           // InterfaceMethod java/util/Iterator.hasNext:()Z
      29: ifeq          56
      32: aload_2
      33: invokeinterface #36,  1           // InterfaceMethod java/util/Iterator.next:()Ljava/lang/Object;
      38: checkcast     #37                 // class org/springframework/boot/actuate/metrics/rich/RichGauge
      41: astore_3
      42: aload_1
      43: aload_3
      44: invokevirtual #38                 // Method org/springframework/boot/actuate/metrics/rich/RichGauge.getName:()Ljava/lang/String;
      47: invokeinterface #19,  2           // InterfaceMethod java/util/Collection.add:(Ljava/lang/Object;)Z
      52: pop
      53: goto          23
      56: aload_1
      57: areturn

  protected void write(java.lang.String, java.util.Collection<org.springframework.boot.actuate.metrics.Metric<?>>);
    Code:
       0: aload_0
       1: getfield      #5                  // Field writer:Lorg/springframework/boot/actuate/metrics/writer/PrefixMetricWriter;
       4: aload_1
       5: aload_2
       6: invokeinterface #39,  3           // InterfaceMethod org/springframework/boot/actuate/metrics/writer/PrefixMetricWriter.set:(Ljava/lang/String;Ljava/util/Collection;)V
      11: return
}
