Compiled from "HttpContinueReadHandler.java"
public class io.undertow.server.handlers.HttpContinueReadHandler implements io.undertow.server.HttpHandler {
  private static final io.undertow.server.ConduitWrapper<org.xnio.conduits.StreamSourceConduit> WRAPPER;

  private final io.undertow.server.HttpHandler handler;

  public io.undertow.server.handlers.HttpContinueReadHandler(io.undertow.server.HttpHandler);
    Code:
       0: aload_0
       1: invokespecial #1                  // Method java/lang/Object."<init>":()V
       4: aload_0
       5: aload_1
       6: putfield      #2                  // Field handler:Lio/undertow/server/HttpHandler;
       9: return

  public void handleRequest(io.undertow.server.HttpServerExchange) throws java.lang.Exception;
    Code:
       0: aload_1
       1: invokestatic  #3                  // Method io/undertow/server/protocol/http/HttpContinue.requiresContinueResponse:(Lio/undertow/server/HttpServerExchange;)Z
       4: ifeq          15
       7: aload_1
       8: getstatic     #4                  // Field WRAPPER:Lio/undertow/server/ConduitWrapper;
      11: invokevirtual #5                  // Method io/undertow/server/HttpServerExchange.addRequestWrapper:(Lio/undertow/server/ConduitWrapper;)Lio/undertow/server/HttpServerExchange;
      14: pop
      15: aload_0
      16: getfield      #2                  // Field handler:Lio/undertow/server/HttpHandler;
      19: aload_1
      20: invokeinterface #6,  2            // InterfaceMethod io/undertow/server/HttpHandler.handleRequest:(Lio/undertow/server/HttpServerExchange;)V
      25: return

  static {};
    Code:
       0: new           #7                  // class io/undertow/server/handlers/HttpContinueReadHandler$1
       3: dup
       4: invokespecial #8                  // Method io/undertow/server/handlers/HttpContinueReadHandler$1."<init>":()V
       7: putstatic     #4                  // Field WRAPPER:Lio/undertow/server/ConduitWrapper;
      10: return
}
