Compiled from "PredicateContextHandler.java"
public class io.undertow.server.handlers.PredicateContextHandler implements io.undertow.server.HttpHandler {
  private final io.undertow.server.HttpHandler next;

  public io.undertow.server.handlers.PredicateContextHandler(io.undertow.server.HttpHandler);
    Code:
       0: aload_0
       1: invokespecial #1                  // Method java/lang/Object."<init>":()V
       4: aload_0
       5: aload_1
       6: putfield      #2                  // Field next:Lio/undertow/server/HttpHandler;
       9: return

  public void handleRequest(io.undertow.server.HttpServerExchange) throws java.lang.Exception;
    Code:
       0: aload_1
       1: getstatic     #3                  // Field io/undertow/predicate/Predicate.PREDICATE_CONTEXT:Lio/undertow/util/AttachmentKey;
       4: new           #4                  // class java/util/TreeMap
       7: dup
       8: invokespecial #5                  // Method java/util/TreeMap."<init>":()V
      11: invokevirtual #6                  // Method io/undertow/server/HttpServerExchange.putAttachment:(Lio/undertow/util/AttachmentKey;Ljava/lang/Object;)Ljava/lang/Object;
      14: pop
      15: aload_0
      16: getfield      #2                  // Field next:Lio/undertow/server/HttpHandler;
      19: aload_1
      20: invokeinterface #7,  2            // InterfaceMethod io/undertow/server/HttpHandler.handleRequest:(Lio/undertow/server/HttpServerExchange;)V
      25: return
}
