Compiled from "NamespaceMapping.java"
public class org.apache.xbean.spring.generator.NamespaceMapping implements java.lang.Comparable {
  private final java.lang.String namespace;

  private final java.util.Set elements;

  private final java.util.Map elementsByName;

  private final org.apache.xbean.spring.generator.ElementMapping rootElement;

  private final java.util.HashMap checkedTypes;

  public org.apache.xbean.spring.generator.NamespaceMapping(java.lang.String, java.util.Set, org.apache.xbean.spring.generator.ElementMapping);
    Code:
       0: aload_0
       1: invokespecial #1                  // Method java/lang/Object."<init>":()V
       4: aload_0
       5: new           #2                  // class java/util/HashMap
       8: dup
       9: invokespecial #3                  // Method java/util/HashMap."<init>":()V
      12: putfield      #4                  // Field checkedTypes:Ljava/util/HashMap;
      15: aload_0
      16: aload_1
      17: putfield      #5                  // Field namespace:Ljava/lang/String;
      20: aload_0
      21: new           #6                  // class java/util/TreeSet
      24: dup
      25: aload_2
      26: invokespecial #7                  // Method java/util/TreeSet."<init>":(Ljava/util/Collection;)V
      29: invokestatic  #8                  // Method java/util/Collections.unmodifiableSet:(Ljava/util/Set;)Ljava/util/Set;
      32: putfield      #9                  // Field elements:Ljava/util/Set;
      35: aload_0
      36: aload_3
      37: putfield      #10                 // Field rootElement:Lorg/apache/xbean/spring/generator/ElementMapping;
      40: new           #2                  // class java/util/HashMap
      43: dup
      44: invokespecial #3                  // Method java/util/HashMap."<init>":()V
      47: astore        4
      49: aload_2
      50: invokeinterface #11,  1           // InterfaceMethod java/util/Set.iterator:()Ljava/util/Iterator;
      55: astore        5
      57: aload         5
      59: invokeinterface #12,  1           // InterfaceMethod java/util/Iterator.hasNext:()Z
      64: ifeq          97
      67: aload         5
      69: invokeinterface #13,  1           // InterfaceMethod java/util/Iterator.next:()Ljava/lang/Object;
      74: checkcast     #14                 // class org/apache/xbean/spring/generator/ElementMapping
      77: astore        6
      79: aload         4
      81: aload         6
      83: invokevirtual #15                 // Method org/apache/xbean/spring/generator/ElementMapping.getElementName:()Ljava/lang/String;
      86: aload         6
      88: invokeinterface #16,  3           // InterfaceMethod java/util/Map.put:(Ljava/lang/Object;Ljava/lang/Object;)Ljava/lang/Object;
      93: pop
      94: goto          57
      97: aload_0
      98: aload         4
     100: invokestatic  #17                 // Method java/util/Collections.unmodifiableMap:(Ljava/util/Map;)Ljava/util/Map;
     103: putfield      #18                 // Field elementsByName:Ljava/util/Map;
     106: return

  public java.lang.String getNamespace();
    Code:
       0: aload_0
       1: getfield      #5                  // Field namespace:Ljava/lang/String;
       4: areturn

  public java.util.Set getElements();
    Code:
       0: aload_0
       1: getfield      #9                  // Field elements:Ljava/util/Set;
       4: areturn

  public org.apache.xbean.spring.generator.ElementMapping getElement(java.lang.String);
    Code:
       0: aload_0
       1: getfield      #18                 // Field elementsByName:Ljava/util/Map;
       4: aload_1
       5: invokeinterface #19,  2           // InterfaceMethod java/util/Map.get:(Ljava/lang/Object;)Ljava/lang/Object;
      10: checkcast     #14                 // class org/apache/xbean/spring/generator/ElementMapping
      13: areturn

  public org.apache.xbean.spring.generator.ElementMapping getRootElement();
    Code:
       0: aload_0
       1: getfield      #10                 // Field rootElement:Lorg/apache/xbean/spring/generator/ElementMapping;
       4: areturn

  public int hashCode();
    Code:
       0: aload_0
       1: getfield      #5                  // Field namespace:Ljava/lang/String;
       4: invokevirtual #20                 // Method java/lang/String.hashCode:()I
       7: ireturn

  public boolean equals(java.lang.Object);
    Code:
       0: aload_1
       1: instanceof    #21                 // class org/apache/xbean/spring/generator/NamespaceMapping
       4: ifeq          22
       7: aload_0
       8: getfield      #5                  // Field namespace:Ljava/lang/String;
      11: aload_1
      12: checkcast     #21                 // class org/apache/xbean/spring/generator/NamespaceMapping
      15: getfield      #5                  // Field namespace:Ljava/lang/String;
      18: invokevirtual #22                 // Method java/lang/String.equals:(Ljava/lang/Object;)Z
      21: ireturn
      22: iconst_0
      23: ireturn

  public int compareTo(java.lang.Object);
    Code:
       0: aload_0
       1: getfield      #5                  // Field namespace:Ljava/lang/String;
       4: aload_1
       5: checkcast     #21                 // class org/apache/xbean/spring/generator/NamespaceMapping
       8: getfield      #5                  // Field namespace:Ljava/lang/String;
      11: invokevirtual #23                 // Method java/lang/String.compareTo:(Ljava/lang/String;)I
      14: ireturn

  public boolean isSimpleType(org.apache.xbean.spring.generator.Type);
    Code:
       0: aload_0
       1: getfield      #4                  // Field checkedTypes:Ljava/util/HashMap;
       4: aload_1
       5: invokevirtual #24                 // Method java/util/HashMap.get:(Ljava/lang/Object;)Ljava/lang/Object;
       8: checkcast     #25                 // class java/lang/Boolean
      11: astore_2
      12: aload_2
      13: ifnonnull     43
      16: aload_1
      17: invokestatic  #26                 // Method org/apache/xbean/spring/generator/Utils.isSimpleType:(Lorg/apache/xbean/spring/generator/Type;)Z
      20: ifeq          29
      23: getstatic     #27                 // Field java/lang/Boolean.TRUE:Ljava/lang/Boolean;
      26: goto          32
      29: getstatic     #28                 // Field java/lang/Boolean.FALSE:Ljava/lang/Boolean;
      32: astore_2
      33: aload_0
      34: getfield      #4                  // Field checkedTypes:Ljava/util/HashMap;
      37: aload_1
      38: aload_2
      39: invokevirtual #29                 // Method java/util/HashMap.put:(Ljava/lang/Object;Ljava/lang/Object;)Ljava/lang/Object;
      42: pop
      43: aload_2
      44: invokevirtual #30                 // Method java/lang/Boolean.booleanValue:()Z
      47: ireturn
}
