Compiled from "MultipartPostMethod.java"
public class org.elasticsearch.hadoop.thirdparty.apache.commons.httpclient.methods.MultipartPostMethod extends org.elasticsearch.hadoop.thirdparty.apache.commons.httpclient.methods.ExpectContinueMethod {
  public static final java.lang.String MULTIPART_FORM_CONTENT_TYPE;

  private static final org.apache.commons.logging.Log LOG;

  private final java.util.List parameters;

  static java.lang.Class class$org$apache$commons$httpclient$methods$MultipartPostMethod;

  public org.elasticsearch.hadoop.thirdparty.apache.commons.httpclient.methods.MultipartPostMethod();
    Code:
       0: aload_0
       1: invokespecial #19                 // Method org/elasticsearch/hadoop/thirdparty/apache/commons/httpclient/methods/ExpectContinueMethod."<init>":()V
       4: aload_0
       5: new           #21                 // class java/util/ArrayList
       8: dup
       9: invokespecial #22                 // Method java/util/ArrayList."<init>":()V
      12: putfield      #24                 // Field parameters:Ljava/util/List;
      15: return

  public org.elasticsearch.hadoop.thirdparty.apache.commons.httpclient.methods.MultipartPostMethod(java.lang.String);
    Code:
       0: aload_0
       1: aload_1
       2: invokespecial #29                 // Method org/elasticsearch/hadoop/thirdparty/apache/commons/httpclient/methods/ExpectContinueMethod."<init>":(Ljava/lang/String;)V
       5: aload_0
       6: new           #21                 // class java/util/ArrayList
       9: dup
      10: invokespecial #22                 // Method java/util/ArrayList."<init>":()V
      13: putfield      #24                 // Field parameters:Ljava/util/List;
      16: return

  protected boolean hasRequestContent();
    Code:
       0: iconst_1
       1: ireturn

  public java.lang.String getName();
    Code:
       0: ldc           #36                 // String POST
       2: areturn

  public void addParameter(java.lang.String, java.lang.String);
    Code:
       0: getstatic     #40                 // Field LOG:Lorg/apache/commons/logging/Log;
       3: ldc           #42                 // String enter addParameter(String parameterName, String parameterValue)
       5: invokeinterface #48,  2           // InterfaceMethod org/apache/commons/logging/Log.trace:(Ljava/lang/Object;)V
      10: new           #50                 // class org/elasticsearch/hadoop/thirdparty/apache/commons/httpclient/methods/multipart/StringPart
      13: dup
      14: aload_1
      15: aload_2
      16: invokespecial #52                 // Method org/elasticsearch/hadoop/thirdparty/apache/commons/httpclient/methods/multipart/StringPart."<init>":(Ljava/lang/String;Ljava/lang/String;)V
      19: astore_3
      20: aload_0
      21: getfield      #24                 // Field parameters:Ljava/util/List;
      24: aload_3
      25: invokeinterface #58,  2           // InterfaceMethod java/util/List.add:(Ljava/lang/Object;)Z
      30: pop
      31: return

  public void addParameter(java.lang.String, java.io.File) throws java.io.FileNotFoundException;
    Code:
       0: getstatic     #40                 // Field LOG:Lorg/apache/commons/logging/Log;
       3: ldc           #67                 // String enter MultipartPostMethod.addParameter(String parameterName, File parameterFile)
       5: invokeinterface #48,  2           // InterfaceMethod org/apache/commons/logging/Log.trace:(Ljava/lang/Object;)V
      10: new           #69                 // class org/elasticsearch/hadoop/thirdparty/apache/commons/httpclient/methods/multipart/FilePart
      13: dup
      14: aload_1
      15: aload_2
      16: invokespecial #71                 // Method org/elasticsearch/hadoop/thirdparty/apache/commons/httpclient/methods/multipart/FilePart."<init>":(Ljava/lang/String;Ljava/io/File;)V
      19: astore_3
      20: aload_0
      21: getfield      #24                 // Field parameters:Ljava/util/List;
      24: aload_3
      25: invokeinterface #58,  2           // InterfaceMethod java/util/List.add:(Ljava/lang/Object;)Z
      30: pop
      31: return

  public void addParameter(java.lang.String, java.lang.String, java.io.File) throws java.io.FileNotFoundException;
    Code:
       0: getstatic     #40                 // Field LOG:Lorg/apache/commons/logging/Log;
       3: ldc           #76                 // String enter MultipartPostMethod.addParameter(String parameterName, String fileName, File parameterFile)
       5: invokeinterface #48,  2           // InterfaceMethod org/apache/commons/logging/Log.trace:(Ljava/lang/Object;)V
      10: new           #69                 // class org/elasticsearch/hadoop/thirdparty/apache/commons/httpclient/methods/multipart/FilePart
      13: dup
      14: aload_1
      15: aload_2
      16: aload_3
      17: invokespecial #78                 // Method org/elasticsearch/hadoop/thirdparty/apache/commons/httpclient/methods/multipart/FilePart."<init>":(Ljava/lang/String;Ljava/lang/String;Ljava/io/File;)V
      20: astore        4
      22: aload_0
      23: getfield      #24                 // Field parameters:Ljava/util/List;
      26: aload         4
      28: invokeinterface #58,  2           // InterfaceMethod java/util/List.add:(Ljava/lang/Object;)Z
      33: pop
      34: return

  public void addPart(org.elasticsearch.hadoop.thirdparty.apache.commons.httpclient.methods.multipart.Part);
    Code:
       0: getstatic     #40                 // Field LOG:Lorg/apache/commons/logging/Log;
       3: ldc           #83                 // String enter addPart(Part part)
       5: invokeinterface #48,  2           // InterfaceMethod org/apache/commons/logging/Log.trace:(Ljava/lang/Object;)V
      10: aload_0
      11: getfield      #24                 // Field parameters:Ljava/util/List;
      14: aload_1
      15: invokeinterface #58,  2           // InterfaceMethod java/util/List.add:(Ljava/lang/Object;)Z
      20: pop
      21: return

  public org.elasticsearch.hadoop.thirdparty.apache.commons.httpclient.methods.multipart.Part[] getParts();
    Code:
       0: aload_0
       1: getfield      #24                 // Field parameters:Ljava/util/List;
       4: aload_0
       5: getfield      #24                 // Field parameters:Ljava/util/List;
       8: invokeinterface #90,  1           // InterfaceMethod java/util/List.size:()I
      13: anewarray     #92                 // class org/elasticsearch/hadoop/thirdparty/apache/commons/httpclient/methods/multipart/Part
      16: invokeinterface #96,  2           // InterfaceMethod java/util/List.toArray:([Ljava/lang/Object;)[Ljava/lang/Object;
      21: checkcast     #98                 // class "[Lorg/elasticsearch/hadoop/thirdparty/apache/commons/httpclient/methods/multipart/Part;"
      24: areturn

  protected void addContentLengthRequestHeader(org.elasticsearch.hadoop.thirdparty.apache.commons.httpclient.HttpState, org.elasticsearch.hadoop.thirdparty.apache.commons.httpclient.HttpConnection) throws java.io.IOException, org.elasticsearch.hadoop.thirdparty.apache.commons.httpclient.HttpException;
    Code:
       0: getstatic     #40                 // Field LOG:Lorg/apache/commons/logging/Log;
       3: ldc           #106                // String enter EntityEnclosingMethod.addContentLengthRequestHeader(HttpState, HttpConnection)
       5: invokeinterface #48,  2           // InterfaceMethod org/apache/commons/logging/Log.trace:(Ljava/lang/Object;)V
      10: aload_0
      11: ldc           #108                // String Content-Length
      13: invokevirtual #114                // Method org/elasticsearch/hadoop/thirdparty/apache/commons/httpclient/HttpMethodBase.getRequestHeader:(Ljava/lang/String;)Lorg/elasticsearch/hadoop/thirdparty/apache/commons/httpclient/Header;
      16: ifnonnull     34
      19: aload_0
      20: invokevirtual #118                // Method getRequestContentLength:()J
      23: lstore_3
      24: aload_0
      25: ldc           #108                // String Content-Length
      27: lload_3
      28: invokestatic  #124                // Method java/lang/String.valueOf:(J)Ljava/lang/String;
      31: invokevirtual #127                // Method org/elasticsearch/hadoop/thirdparty/apache/commons/httpclient/HttpMethodBase.addRequestHeader:(Ljava/lang/String;Ljava/lang/String;)V
      34: aload_0
      35: ldc           #129                // String Transfer-Encoding
      37: invokevirtual #132                // Method org/elasticsearch/hadoop/thirdparty/apache/commons/httpclient/HttpMethodBase.removeRequestHeader:(Ljava/lang/String;)V
      40: return

  protected void addContentTypeRequestHeader(org.elasticsearch.hadoop.thirdparty.apache.commons.httpclient.HttpState, org.elasticsearch.hadoop.thirdparty.apache.commons.httpclient.HttpConnection) throws java.io.IOException, org.elasticsearch.hadoop.thirdparty.apache.commons.httpclient.HttpException;
    Code:
       0: getstatic     #40                 // Field LOG:Lorg/apache/commons/logging/Log;
       3: ldc           #141                // String enter EntityEnclosingMethod.addContentTypeRequestHeader(HttpState, HttpConnection)
       5: invokeinterface #48,  2           // InterfaceMethod org/apache/commons/logging/Log.trace:(Ljava/lang/Object;)V
      10: aload_0
      11: getfield      #24                 // Field parameters:Ljava/util/List;
      14: invokeinterface #144,  1          // InterfaceMethod java/util/List.isEmpty:()Z
      19: ifne          63
      22: new           #146                // class java/lang/StringBuffer
      25: dup
      26: ldc           #9                  // String multipart/form-data
      28: invokespecial #147                // Method java/lang/StringBuffer."<init>":(Ljava/lang/String;)V
      31: astore_3
      32: invokestatic  #150                // Method org/elasticsearch/hadoop/thirdparty/apache/commons/httpclient/methods/multipart/Part.getBoundary:()Ljava/lang/String;
      35: ifnull        53
      38: aload_3
      39: ldc           #152                // String ; boundary=
      41: invokevirtual #156                // Method java/lang/StringBuffer.append:(Ljava/lang/String;)Ljava/lang/StringBuffer;
      44: pop
      45: aload_3
      46: invokestatic  #150                // Method org/elasticsearch/hadoop/thirdparty/apache/commons/httpclient/methods/multipart/Part.getBoundary:()Ljava/lang/String;
      49: invokevirtual #156                // Method java/lang/StringBuffer.append:(Ljava/lang/String;)Ljava/lang/StringBuffer;
      52: pop
      53: aload_0
      54: ldc           #158                // String Content-Type
      56: aload_3
      57: invokevirtual #161                // Method java/lang/StringBuffer.toString:()Ljava/lang/String;
      60: invokevirtual #164                // Method org/elasticsearch/hadoop/thirdparty/apache/commons/httpclient/HttpMethodBase.setRequestHeader:(Ljava/lang/String;Ljava/lang/String;)V
      63: return

  protected void addRequestHeaders(org.elasticsearch.hadoop.thirdparty.apache.commons.httpclient.HttpState, org.elasticsearch.hadoop.thirdparty.apache.commons.httpclient.HttpConnection) throws java.io.IOException, org.elasticsearch.hadoop.thirdparty.apache.commons.httpclient.HttpException;
    Code:
       0: getstatic     #40                 // Field LOG:Lorg/apache/commons/logging/Log;
       3: ldc           #169                // String enter MultipartPostMethod.addRequestHeaders(HttpState state, HttpConnection conn)
       5: invokeinterface #48,  2           // InterfaceMethod org/apache/commons/logging/Log.trace:(Ljava/lang/Object;)V
      10: aload_0
      11: aload_1
      12: aload_2
      13: invokespecial #171                // Method org/elasticsearch/hadoop/thirdparty/apache/commons/httpclient/methods/ExpectContinueMethod.addRequestHeaders:(Lorg/elasticsearch/hadoop/thirdparty/apache/commons/httpclient/HttpState;Lorg/elasticsearch/hadoop/thirdparty/apache/commons/httpclient/HttpConnection;)V
      16: aload_0
      17: aload_1
      18: aload_2
      19: invokevirtual #173                // Method addContentLengthRequestHeader:(Lorg/elasticsearch/hadoop/thirdparty/apache/commons/httpclient/HttpState;Lorg/elasticsearch/hadoop/thirdparty/apache/commons/httpclient/HttpConnection;)V
      22: aload_0
      23: aload_1
      24: aload_2
      25: invokevirtual #175                // Method addContentTypeRequestHeader:(Lorg/elasticsearch/hadoop/thirdparty/apache/commons/httpclient/HttpState;Lorg/elasticsearch/hadoop/thirdparty/apache/commons/httpclient/HttpConnection;)V
      28: return

  protected boolean writeRequestBody(org.elasticsearch.hadoop.thirdparty.apache.commons.httpclient.HttpState, org.elasticsearch.hadoop.thirdparty.apache.commons.httpclient.HttpConnection) throws java.io.IOException, org.elasticsearch.hadoop.thirdparty.apache.commons.httpclient.HttpException;
    Code:
       0: getstatic     #40                 // Field LOG:Lorg/apache/commons/logging/Log;
       3: ldc           #179                // String enter MultipartPostMethod.writeRequestBody(HttpState state, HttpConnection conn)
       5: invokeinterface #48,  2           // InterfaceMethod org/apache/commons/logging/Log.trace:(Ljava/lang/Object;)V
      10: aload_2
      11: invokevirtual #185                // Method org/elasticsearch/hadoop/thirdparty/apache/commons/httpclient/HttpConnection.getRequestOutputStream:()Ljava/io/OutputStream;
      14: astore_3
      15: aload_3
      16: aload_0
      17: invokevirtual #187                // Method getParts:()[Lorg/elasticsearch/hadoop/thirdparty/apache/commons/httpclient/methods/multipart/Part;
      20: invokestatic  #191                // Method org/elasticsearch/hadoop/thirdparty/apache/commons/httpclient/methods/multipart/Part.sendParts:(Ljava/io/OutputStream;[Lorg/elasticsearch/hadoop/thirdparty/apache/commons/httpclient/methods/multipart/Part;)V
      23: iconst_1
      24: ireturn

  protected long getRequestContentLength() throws java.io.IOException;
    Code:
       0: getstatic     #40                 // Field LOG:Lorg/apache/commons/logging/Log;
       3: ldc           #195                // String enter MultipartPostMethod.getRequestContentLength()
       5: invokeinterface #48,  2           // InterfaceMethod org/apache/commons/logging/Log.trace:(Ljava/lang/Object;)V
      10: aload_0
      11: invokevirtual #187                // Method getParts:()[Lorg/elasticsearch/hadoop/thirdparty/apache/commons/httpclient/methods/multipart/Part;
      14: invokestatic  #199                // Method org/elasticsearch/hadoop/thirdparty/apache/commons/httpclient/methods/multipart/Part.getLengthOfParts:([Lorg/elasticsearch/hadoop/thirdparty/apache/commons/httpclient/methods/multipart/Part;)J
      17: lreturn

  public void recycle();
    Code:
       0: getstatic     #40                 // Field LOG:Lorg/apache/commons/logging/Log;
       3: ldc           #202                // String enter MultipartPostMethod.recycle()
       5: invokeinterface #48,  2           // InterfaceMethod org/apache/commons/logging/Log.trace:(Ljava/lang/Object;)V
      10: aload_0
      11: invokespecial #204                // Method org/elasticsearch/hadoop/thirdparty/apache/commons/httpclient/HttpMethodBase.recycle:()V
      14: aload_0
      15: getfield      #24                 // Field parameters:Ljava/util/List;
      18: invokeinterface #207,  1          // InterfaceMethod java/util/List.clear:()V
      23: return

  static java.lang.Class class$(java.lang.String);
    Code:
       0: aload_0
       1: invokestatic  #216                // Method java/lang/Class.forName:(Ljava/lang/String;)Ljava/lang/Class;
       4: areturn
       5: astore_1
       6: new           #218                // class java/lang/NoClassDefFoundError
       9: dup
      10: aload_1
      11: invokevirtual #223                // Method java/lang/Throwable.getMessage:()Ljava/lang/String;
      14: invokespecial #224                // Method java/lang/NoClassDefFoundError."<init>":(Ljava/lang/String;)V
      17: athrow
    Exception table:
       from    to  target type
           0     5     5   Class java/lang/ClassNotFoundException

  static {};
    Code:
       0: getstatic     #230                // Field class$org$apache$commons$httpclient$methods$MultipartPostMethod:Ljava/lang/Class;
       3: ifnonnull     18
       6: ldc           #232                // String org.elasticsearch.hadoop.thirdparty.apache.commons.httpclient.methods.MultipartPostMethod
       8: invokestatic  #234                // Method class$:(Ljava/lang/String;)Ljava/lang/Class;
      11: dup
      12: putstatic     #230                // Field class$org$apache$commons$httpclient$methods$MultipartPostMethod:Ljava/lang/Class;
      15: goto          21
      18: getstatic     #230                // Field class$org$apache$commons$httpclient$methods$MultipartPostMethod:Ljava/lang/Class;
      21: invokestatic  #240                // Method org/apache/commons/logging/LogFactory.getLog:(Ljava/lang/Class;)Lorg/apache/commons/logging/Log;
      24: putstatic     #40                 // Field LOG:Lorg/apache/commons/logging/Log;
      27: return
}
