Compiled from "MustacheViewResolver.java"
public class org.springframework.boot.autoconfigure.mustache.web.MustacheViewResolver extends org.springframework.web.servlet.view.AbstractTemplateViewResolver {
  private com.samskivert.mustache.Mustache$Compiler compiler;

  private java.lang.String charset;

  public org.springframework.boot.autoconfigure.mustache.web.MustacheViewResolver();
    Code:
       0: aload_0
       1: invokespecial #1                  // Method org/springframework/web/servlet/view/AbstractTemplateViewResolver."<init>":()V
       4: aload_0
       5: invokestatic  #2                  // Method com/samskivert/mustache/Mustache.compiler:()Lcom/samskivert/mustache/Mustache$Compiler;
       8: putfield      #3                  // Field compiler:Lcom/samskivert/mustache/Mustache$Compiler;
      11: aload_0
      12: aload_0
      13: invokevirtual #4                  // Method requiredViewClass:()Ljava/lang/Class;
      16: invokevirtual #5                  // Method setViewClass:(Ljava/lang/Class;)V
      19: return

  protected java.lang.Class<?> requiredViewClass();
    Code:
       0: ldc           #6                  // class org/springframework/boot/autoconfigure/mustache/web/MustacheView
       2: areturn

  public void setCompiler(com.samskivert.mustache.Mustache$Compiler);
    Code:
       0: aload_0
       1: aload_1
       2: putfield      #3                  // Field compiler:Lcom/samskivert/mustache/Mustache$Compiler;
       5: return

  public void setCharset(java.lang.String);
    Code:
       0: aload_0
       1: aload_1
       2: putfield      #7                  // Field charset:Ljava/lang/String;
       5: return

  protected org.springframework.web.servlet.View loadView(java.lang.String, java.util.Locale) throws java.lang.Exception;
    Code:
       0: aload_0
       1: aload_1
       2: aload_2
       3: invokespecial #8                  // Method resolveResource:(Ljava/lang/String;Ljava/util/Locale;)Lorg/springframework/core/io/Resource;
       6: astore_3
       7: aload_3
       8: ifnonnull     13
      11: aconst_null
      12: areturn
      13: aload_0
      14: aload_1
      15: aload_2
      16: invokespecial #9                  // Method org/springframework/web/servlet/view/AbstractTemplateViewResolver.loadView:(Ljava/lang/String;Ljava/util/Locale;)Lorg/springframework/web/servlet/View;
      19: checkcast     #6                  // class org/springframework/boot/autoconfigure/mustache/web/MustacheView
      22: astore        4
      24: aload         4
      26: aload_0
      27: aload_3
      28: invokespecial #10                 // Method createTemplate:(Lorg/springframework/core/io/Resource;)Lcom/samskivert/mustache/Template;
      31: invokevirtual #11                 // Method org/springframework/boot/autoconfigure/mustache/web/MustacheView.setTemplate:(Lcom/samskivert/mustache/Template;)V
      34: aload         4
      36: areturn

  private org.springframework.core.io.Resource resolveResource(java.lang.String, java.util.Locale);
    Code:
       0: aload_0
       1: aload_1
       2: aload_0
       3: aload_2
       4: invokespecial #12                 // Method getLocale:(Ljava/util/Locale;)Ljava/lang/String;
       7: invokespecial #13                 // Method resolveFromLocale:(Ljava/lang/String;Ljava/lang/String;)Lorg/springframework/core/io/Resource;
      10: areturn

  private org.springframework.core.io.Resource resolveFromLocale(java.lang.String, java.lang.String);
    Code:
       0: aload_0
       1: invokevirtual #14                 // Method getApplicationContext:()Lorg/springframework/context/ApplicationContext;
       4: new           #15                 // class java/lang/StringBuilder
       7: dup
       8: invokespecial #16                 // Method java/lang/StringBuilder."<init>":()V
      11: aload_0
      12: invokevirtual #17                 // Method getPrefix:()Ljava/lang/String;
      15: invokevirtual #18                 // Method java/lang/StringBuilder.append:(Ljava/lang/String;)Ljava/lang/StringBuilder;
      18: aload_1
      19: invokevirtual #18                 // Method java/lang/StringBuilder.append:(Ljava/lang/String;)Ljava/lang/StringBuilder;
      22: aload_2
      23: invokevirtual #18                 // Method java/lang/StringBuilder.append:(Ljava/lang/String;)Ljava/lang/StringBuilder;
      26: aload_0
      27: invokevirtual #19                 // Method getSuffix:()Ljava/lang/String;
      30: invokevirtual #18                 // Method java/lang/StringBuilder.append:(Ljava/lang/String;)Ljava/lang/StringBuilder;
      33: invokevirtual #20                 // Method java/lang/StringBuilder.toString:()Ljava/lang/String;
      36: invokeinterface #21,  2           // InterfaceMethod org/springframework/context/ApplicationContext.getResource:(Ljava/lang/String;)Lorg/springframework/core/io/Resource;
      41: astore_3
      42: aload_3
      43: ifnull        55
      46: aload_3
      47: invokeinterface #22,  1           // InterfaceMethod org/springframework/core/io/Resource.exists:()Z
      52: ifne          85
      55: aload_2
      56: invokevirtual #23                 // Method java/lang/String.isEmpty:()Z
      59: ifeq          64
      62: aconst_null
      63: areturn
      64: aload_2
      65: ldc           #24                 // String _
      67: invokevirtual #25                 // Method java/lang/String.lastIndexOf:(Ljava/lang/String;)I
      70: istore        4
      72: aload_0
      73: aload_1
      74: aload_2
      75: iconst_0
      76: iload         4
      78: invokevirtual #26                 // Method java/lang/String.substring:(II)Ljava/lang/String;
      81: invokespecial #13                 // Method resolveFromLocale:(Ljava/lang/String;Ljava/lang/String;)Lorg/springframework/core/io/Resource;
      84: areturn
      85: aload_3
      86: areturn

  private java.lang.String getLocale(java.util.Locale);
    Code:
       0: aload_1
       1: ifnonnull     7
       4: ldc           #27                 // String
       6: areturn
       7: new           #28                 // class org/springframework/beans/propertyeditors/LocaleEditor
      10: dup
      11: invokespecial #29                 // Method org/springframework/beans/propertyeditors/LocaleEditor."<init>":()V
      14: astore_2
      15: aload_2
      16: aload_1
      17: invokevirtual #30                 // Method org/springframework/beans/propertyeditors/LocaleEditor.setValue:(Ljava/lang/Object;)V
      20: new           #15                 // class java/lang/StringBuilder
      23: dup
      24: invokespecial #16                 // Method java/lang/StringBuilder."<init>":()V
      27: ldc           #24                 // String _
      29: invokevirtual #18                 // Method java/lang/StringBuilder.append:(Ljava/lang/String;)Ljava/lang/StringBuilder;
      32: aload_2
      33: invokevirtual #31                 // Method org/springframework/beans/propertyeditors/LocaleEditor.getAsText:()Ljava/lang/String;
      36: invokevirtual #18                 // Method java/lang/StringBuilder.append:(Ljava/lang/String;)Ljava/lang/StringBuilder;
      39: invokevirtual #20                 // Method java/lang/StringBuilder.toString:()Ljava/lang/String;
      42: areturn

  private com.samskivert.mustache.Template createTemplate(org.springframework.core.io.Resource) throws java.io.IOException;
    Code:
       0: aload_0
       1: aload_1
       2: invokespecial #32                 // Method getReader:(Lorg/springframework/core/io/Resource;)Ljava/io/Reader;
       5: astore_2
       6: aload_0
       7: getfield      #3                  // Field compiler:Lcom/samskivert/mustache/Mustache$Compiler;
      10: aload_2
      11: invokevirtual #33                 // Method com/samskivert/mustache/Mustache$Compiler.compile:(Ljava/io/Reader;)Lcom/samskivert/mustache/Template;
      14: astore_3
      15: aload_2
      16: invokevirtual #34                 // Method java/io/Reader.close:()V
      19: aload_3
      20: areturn
      21: astore        4
      23: aload_2
      24: invokevirtual #34                 // Method java/io/Reader.close:()V
      27: aload         4
      29: athrow
    Exception table:
       from    to  target type
           6    15    21   any
          21    23    21   any

  private java.io.Reader getReader(org.springframework.core.io.Resource) throws java.io.IOException;
    Code:
       0: aload_0
       1: getfield      #7                  // Field charset:Ljava/lang/String;
       4: ifnull        25
       7: new           #35                 // class java/io/InputStreamReader
      10: dup
      11: aload_1
      12: invokeinterface #36,  1           // InterfaceMethod org/springframework/core/io/Resource.getInputStream:()Ljava/io/InputStream;
      17: aload_0
      18: getfield      #7                  // Field charset:Ljava/lang/String;
      21: invokespecial #37                 // Method java/io/InputStreamReader."<init>":(Ljava/io/InputStream;Ljava/lang/String;)V
      24: areturn
      25: new           #35                 // class java/io/InputStreamReader
      28: dup
      29: aload_1
      30: invokeinterface #36,  1           // InterfaceMethod org/springframework/core/io/Resource.getInputStream:()Ljava/io/InputStream;
      35: invokespecial #38                 // Method java/io/InputStreamReader."<init>":(Ljava/io/InputStream;)V
      38: areturn
}
