Compiled from "RejectModifierPredicate.java"
public class org.springframework.cglib.core.RejectModifierPredicate implements org.springframework.cglib.core.Predicate {
  private int rejectMask;

  public org.springframework.cglib.core.RejectModifierPredicate(int);
    Code:
       0: aload_0
       1: invokespecial #14                 // Method java/lang/Object."<init>":()V
       4: aload_0
       5: iload_1
       6: putfield      #16                 // Field rejectMask:I
       9: return

  public boolean evaluate(java.lang.Object);
    Code:
       0: aload_1
       1: checkcast     #22                 // class java/lang/reflect/Member
       4: invokeinterface #26,  1           // InterfaceMethod java/lang/reflect/Member.getModifiers:()I
       9: aload_0
      10: getfield      #16                 // Field rejectMask:I
      13: iand
      14: ifne          21
      17: iconst_1
      18: goto          22
      21: iconst_0
      22: ireturn
}
