Compiled from "DestinationPolicyType.java"
public class org.apache.cxf.ws.rm.manager.DestinationPolicyType {
  protected org.apache.cxf.ws.rm.manager.AcksPolicyType acksPolicy;

  protected org.apache.cxf.ws.rm.manager.RetryPolicyType retryPolicy;

  protected javax.xml.datatype.Duration sequenceExpiration;

  protected java.lang.Boolean acceptOffers;

  protected java.lang.Integer maxSequences;

  public org.apache.cxf.ws.rm.manager.DestinationPolicyType();
    Code:
       0: aload_0
       1: invokespecial #1                  // Method java/lang/Object."<init>":()V
       4: return

  public org.apache.cxf.ws.rm.manager.AcksPolicyType getAcksPolicy();
    Code:
       0: aload_0
       1: getfield      #2                  // Field acksPolicy:Lorg/apache/cxf/ws/rm/manager/AcksPolicyType;
       4: areturn

  public void setAcksPolicy(org.apache.cxf.ws.rm.manager.AcksPolicyType);
    Code:
       0: aload_0
       1: aload_1
       2: putfield      #2                  // Field acksPolicy:Lorg/apache/cxf/ws/rm/manager/AcksPolicyType;
       5: return

  public boolean isSetAcksPolicy();
    Code:
       0: aload_0
       1: getfield      #2                  // Field acksPolicy:Lorg/apache/cxf/ws/rm/manager/AcksPolicyType;
       4: ifnull        11
       7: iconst_1
       8: goto          12
      11: iconst_0
      12: ireturn

  public org.apache.cxf.ws.rm.manager.RetryPolicyType getRetryPolicy();
    Code:
       0: aload_0
       1: getfield      #3                  // Field retryPolicy:Lorg/apache/cxf/ws/rm/manager/RetryPolicyType;
       4: areturn

  public void setRetryPolicy(org.apache.cxf.ws.rm.manager.RetryPolicyType);
    Code:
       0: aload_0
       1: aload_1
       2: putfield      #3                  // Field retryPolicy:Lorg/apache/cxf/ws/rm/manager/RetryPolicyType;
       5: return

  public boolean isSetRetryPolicy();
    Code:
       0: aload_0
       1: getfield      #3                  // Field retryPolicy:Lorg/apache/cxf/ws/rm/manager/RetryPolicyType;
       4: ifnull        11
       7: iconst_1
       8: goto          12
      11: iconst_0
      12: ireturn

  public void setSequenceExpiration(javax.xml.datatype.Duration);
    Code:
       0: aload_0
       1: aload_1
       2: putfield      #4                  // Field sequenceExpiration:Ljavax/xml/datatype/Duration;
       5: return

  public boolean isSetSequenceExpiration();
    Code:
       0: aload_0
       1: getfield      #4                  // Field sequenceExpiration:Ljavax/xml/datatype/Duration;
       4: ifnull        11
       7: iconst_1
       8: goto          12
      11: iconst_0
      12: ireturn

  public boolean isAcceptOffers();
    Code:
       0: aload_0
       1: getfield      #5                  // Field acceptOffers:Ljava/lang/Boolean;
       4: ifnonnull     9
       7: iconst_1
       8: ireturn
       9: aload_0
      10: getfield      #5                  // Field acceptOffers:Ljava/lang/Boolean;
      13: invokevirtual #6                  // Method java/lang/Boolean.booleanValue:()Z
      16: ireturn

  public void setAcceptOffers(boolean);
    Code:
       0: aload_0
       1: iload_1
       2: invokestatic  #7                  // Method java/lang/Boolean.valueOf:(Z)Ljava/lang/Boolean;
       5: putfield      #5                  // Field acceptOffers:Ljava/lang/Boolean;
       8: return

  public boolean isSetAcceptOffers();
    Code:
       0: aload_0
       1: getfield      #5                  // Field acceptOffers:Ljava/lang/Boolean;
       4: ifnull        11
       7: iconst_1
       8: goto          12
      11: iconst_0
      12: ireturn

  public void unsetAcceptOffers();
    Code:
       0: aload_0
       1: aconst_null
       2: putfield      #5                  // Field acceptOffers:Ljava/lang/Boolean;
       5: return

  public int getMaxSequences();
    Code:
       0: aload_0
       1: getfield      #8                  // Field maxSequences:Ljava/lang/Integer;
       4: ifnonnull     9
       7: iconst_0
       8: ireturn
       9: aload_0
      10: getfield      #8                  // Field maxSequences:Ljava/lang/Integer;
      13: invokevirtual #9                  // Method java/lang/Integer.intValue:()I
      16: ireturn

  public void setMaxSequences(int);
    Code:
       0: aload_0
       1: iload_1
       2: invokestatic  #10                 // Method java/lang/Integer.valueOf:(I)Ljava/lang/Integer;
       5: putfield      #8                  // Field maxSequences:Ljava/lang/Integer;
       8: return

  public boolean isSetMaxSequences();
    Code:
       0: aload_0
       1: getfield      #8                  // Field maxSequences:Ljava/lang/Integer;
       4: ifnull        11
       7: iconst_1
       8: goto          12
      11: iconst_0
      12: ireturn

  public void unsetMaxSequences();
    Code:
       0: aload_0
       1: aconst_null
       2: putfield      #8                  // Field maxSequences:Ljava/lang/Integer;
       5: return

  public javax.xml.datatype.Duration getSequenceExpiration();
    Code:
       0: aconst_null
       1: aload_0
       2: getfield      #4                  // Field sequenceExpiration:Ljavax/xml/datatype/Duration;
       5: if_acmpne     18
       8: invokestatic  #11                 // Method javax/xml/datatype/DatatypeFactory.newInstance:()Ljavax/xml/datatype/DatatypeFactory;
      11: ldc           #12                 // String PT0S
      13: invokevirtual #13                 // Method javax/xml/datatype/DatatypeFactory.newDuration:(Ljava/lang/String;)Ljavax/xml/datatype/Duration;
      16: areturn
      17: astore_1
      18: aload_0
      19: getfield      #4                  // Field sequenceExpiration:Ljavax/xml/datatype/Duration;
      22: areturn
    Exception table:
       from    to  target type
           8    16    17   Class javax/xml/datatype/DatatypeConfigurationException
}
