Compiled from "InvokeDynamic.java"
public class org.modelmapper.internal.bytebuddy.implementation.InvokeDynamic$InvocationProvider$ArgumentProvider$ForClassConstant implements org.modelmapper.internal.bytebuddy.implementation.InvokeDynamic$InvocationProvider$ArgumentProvider {
  private final org.modelmapper.internal.bytebuddy.description.type.TypeDescription typeDescription;

  protected org.modelmapper.internal.bytebuddy.implementation.InvokeDynamic$InvocationProvider$ArgumentProvider$ForClassConstant(org.modelmapper.internal.bytebuddy.description.type.TypeDescription);
    Code:
       0: aload_0
       1: invokespecial #38                 // Method java/lang/Object."<init>":()V
       4: aload_0
       5: aload_1
       6: putfield      #40                 // Field typeDescription:Lorg/modelmapper/internal/bytebuddy/description/type/TypeDescription;
       9: return

  public org.modelmapper.internal.bytebuddy.implementation.InvokeDynamic$InvocationProvider$ArgumentProvider$Resolved resolve(org.modelmapper.internal.bytebuddy.description.type.TypeDescription, org.modelmapper.internal.bytebuddy.description.method.MethodDescription, org.modelmapper.internal.bytebuddy.implementation.bytecode.assign.Assigner, org.modelmapper.internal.bytebuddy.implementation.bytecode.assign.Assigner$Typing);
    Code:
       0: new           #30                 // class org/modelmapper/internal/bytebuddy/implementation/InvokeDynamic$InvocationProvider$ArgumentProvider$Resolved$Simple
       3: dup
       4: aload_0
       5: getfield      #40                 // Field typeDescription:Lorg/modelmapper/internal/bytebuddy/description/type/TypeDescription;
       8: invokestatic  #50                 // Method org/modelmapper/internal/bytebuddy/implementation/bytecode/constant/ClassConstant.of:(Lorg/modelmapper/internal/bytebuddy/description/type/TypeDescription;)Lorg/modelmapper/internal/bytebuddy/implementation/bytecode/StackManipulation;
      11: getstatic     #55                 // Field org/modelmapper/internal/bytebuddy/description/type/TypeDescription.CLASS:Lorg/modelmapper/internal/bytebuddy/description/type/TypeDescription;
      14: invokespecial #58                 // Method org/modelmapper/internal/bytebuddy/implementation/InvokeDynamic$InvocationProvider$ArgumentProvider$Resolved$Simple."<init>":(Lorg/modelmapper/internal/bytebuddy/implementation/bytecode/StackManipulation;Lorg/modelmapper/internal/bytebuddy/description/type/TypeDescription;)V
      17: areturn

  public org.modelmapper.internal.bytebuddy.dynamic.scaffold.InstrumentedType prepare(org.modelmapper.internal.bytebuddy.dynamic.scaffold.InstrumentedType);
    Code:
       0: aload_1
       1: areturn

  public boolean equals(java.lang.Object);
    Code:
       0: aload_0
       1: aload_1
       2: if_acmpne     7
       5: iconst_1
       6: ireturn
       7: aload_1
       8: ifnonnull     13
      11: iconst_0
      12: ireturn
      13: aload_0
      14: invokevirtual #74                 // Method java/lang/Object.getClass:()Ljava/lang/Class;
      17: aload_1
      18: invokevirtual #74                 // Method java/lang/Object.getClass:()Ljava/lang/Class;
      21: if_acmpeq     26
      24: iconst_0
      25: ireturn
      26: aload_0
      27: getfield      #40                 // Field typeDescription:Lorg/modelmapper/internal/bytebuddy/description/type/TypeDescription;
      30: aload_1
      31: checkcast     #2                  // class org/modelmapper/internal/bytebuddy/implementation/InvokeDynamic$InvocationProvider$ArgumentProvider$ForClassConstant
      34: getfield      #40                 // Field typeDescription:Lorg/modelmapper/internal/bytebuddy/description/type/TypeDescription;
      37: invokeinterface #76,  2           // InterfaceMethod org/modelmapper/internal/bytebuddy/description/type/TypeDescription.equals:(Ljava/lang/Object;)Z
      42: ifne          47
      45: iconst_0
      46: ireturn
      47: iconst_1
      48: ireturn

  public int hashCode();
    Code:
       0: bipush        17
       2: bipush        31
       4: imul
       5: aload_0
       6: getfield      #40                 // Field typeDescription:Lorg/modelmapper/internal/bytebuddy/description/type/TypeDescription;
       9: invokeinterface #80,  1           // InterfaceMethod org/modelmapper/internal/bytebuddy/description/type/TypeDescription.hashCode:()I
      14: iadd
      15: ireturn
}
