Compiled from "MethodCall.java"
public class org.modelmapper.internal.bytebuddy.implementation.MethodCall$MethodLocator$ForExplicitMethod implements org.modelmapper.internal.bytebuddy.implementation.MethodCall$MethodLocator {
  private final org.modelmapper.internal.bytebuddy.description.method.MethodDescription methodDescription;

  protected org.modelmapper.internal.bytebuddy.implementation.MethodCall$MethodLocator$ForExplicitMethod(org.modelmapper.internal.bytebuddy.description.method.MethodDescription);
    Code:
       0: aload_0
       1: invokespecial #24                 // Method java/lang/Object."<init>":()V
       4: aload_0
       5: aload_1
       6: putfield      #26                 // Field methodDescription:Lorg/modelmapper/internal/bytebuddy/description/method/MethodDescription;
       9: return

  public org.modelmapper.internal.bytebuddy.description.method.MethodDescription resolve(org.modelmapper.internal.bytebuddy.description.type.TypeDescription, org.modelmapper.internal.bytebuddy.description.method.MethodDescription);
    Code:
       0: aload_0
       1: getfield      #26                 // Field methodDescription:Lorg/modelmapper/internal/bytebuddy/description/method/MethodDescription;
       4: areturn

  public boolean equals(java.lang.Object);
    Code:
       0: aload_0
       1: aload_1
       2: if_acmpne     7
       5: iconst_1
       6: ireturn
       7: aload_1
       8: ifnonnull     13
      11: iconst_0
      12: ireturn
      13: aload_0
      14: invokevirtual #39                 // Method java/lang/Object.getClass:()Ljava/lang/Class;
      17: aload_1
      18: invokevirtual #39                 // Method java/lang/Object.getClass:()Ljava/lang/Class;
      21: if_acmpeq     26
      24: iconst_0
      25: ireturn
      26: aload_0
      27: getfield      #26                 // Field methodDescription:Lorg/modelmapper/internal/bytebuddy/description/method/MethodDescription;
      30: aload_1
      31: checkcast     #2                  // class org/modelmapper/internal/bytebuddy/implementation/MethodCall$MethodLocator$ForExplicitMethod
      34: getfield      #26                 // Field methodDescription:Lorg/modelmapper/internal/bytebuddy/description/method/MethodDescription;
      37: invokeinterface #43,  2           // InterfaceMethod org/modelmapper/internal/bytebuddy/description/method/MethodDescription.equals:(Ljava/lang/Object;)Z
      42: ifne          47
      45: iconst_0
      46: ireturn
      47: iconst_1
      48: ireturn

  public int hashCode();
    Code:
       0: bipush        17
       2: bipush        31
       4: imul
       5: aload_0
       6: getfield      #26                 // Field methodDescription:Lorg/modelmapper/internal/bytebuddy/description/method/MethodDescription;
       9: invokeinterface #47,  1           // InterfaceMethod org/modelmapper/internal/bytebuddy/description/method/MethodDescription.hashCode:()I
      14: iadd
      15: ireturn
}
