Compiled from "MethodCall.java"
public class org.modelmapper.internal.bytebuddy.implementation.MethodCall$ArgumentLoader$ForField$Factory implements org.modelmapper.internal.bytebuddy.implementation.MethodCall$ArgumentLoader$Factory {
  private final java.lang.String name;

  private final org.modelmapper.internal.bytebuddy.dynamic.scaffold.FieldLocator$Factory fieldLocatorFactory;

  public org.modelmapper.internal.bytebuddy.implementation.MethodCall$ArgumentLoader$ForField$Factory(java.lang.String, org.modelmapper.internal.bytebuddy.dynamic.scaffold.FieldLocator$Factory);
    Code:
       0: aload_0
       1: invokespecial #38                 // Method java/lang/Object."<init>":()V
       4: aload_0
       5: aload_1
       6: putfield      #40                 // Field name:Ljava/lang/String;
       9: aload_0
      10: aload_2
      11: putfield      #42                 // Field fieldLocatorFactory:Lorg/modelmapper/internal/bytebuddy/dynamic/scaffold/FieldLocator$Factory;
      14: return

  public org.modelmapper.internal.bytebuddy.dynamic.scaffold.InstrumentedType prepare(org.modelmapper.internal.bytebuddy.dynamic.scaffold.InstrumentedType);
    Code:
       0: aload_1
       1: areturn

  public java.util.List<org.modelmapper.internal.bytebuddy.implementation.MethodCall$ArgumentLoader> make(org.modelmapper.internal.bytebuddy.description.type.TypeDescription, org.modelmapper.internal.bytebuddy.description.method.MethodDescription, org.modelmapper.internal.bytebuddy.description.method.MethodDescription);
    Code:
       0: aload_0
       1: getfield      #42                 // Field fieldLocatorFactory:Lorg/modelmapper/internal/bytebuddy/dynamic/scaffold/FieldLocator$Factory;
       4: aload_1
       5: invokeinterface #53,  2           // InterfaceMethod org/modelmapper/internal/bytebuddy/dynamic/scaffold/FieldLocator$Factory.make:(Lorg/modelmapper/internal/bytebuddy/description/type/TypeDescription;)Lorg/modelmapper/internal/bytebuddy/dynamic/scaffold/FieldLocator;
      10: aload_0
      11: getfield      #40                 // Field name:Ljava/lang/String;
      14: invokeinterface #57,  2           // InterfaceMethod org/modelmapper/internal/bytebuddy/dynamic/scaffold/FieldLocator.locate:(Ljava/lang/String;)Lorg/modelmapper/internal/bytebuddy/dynamic/scaffold/FieldLocator$Resolution;
      19: astore        4
      21: aload         4
      23: invokeinterface #61,  1           // InterfaceMethod org/modelmapper/internal/bytebuddy/dynamic/scaffold/FieldLocator$Resolution.isResolved:()Z
      28: ifne          70
      31: new           #63                 // class java/lang/IllegalStateException
      34: dup
      35: new           #65                 // class java/lang/StringBuilder
      38: dup
      39: invokespecial #66                 // Method java/lang/StringBuilder."<init>":()V
      42: ldc           #68                 // String Could not locate field \'
      44: invokevirtual #72                 // Method java/lang/StringBuilder.append:(Ljava/lang/String;)Ljava/lang/StringBuilder;
      47: aload_0
      48: getfield      #40                 // Field name:Ljava/lang/String;
      51: invokevirtual #72                 // Method java/lang/StringBuilder.append:(Ljava/lang/String;)Ljava/lang/StringBuilder;
      54: ldc           #74                 // String \' on
      56: invokevirtual #72                 // Method java/lang/StringBuilder.append:(Ljava/lang/String;)Ljava/lang/StringBuilder;
      59: aload_1
      60: invokevirtual #77                 // Method java/lang/StringBuilder.append:(Ljava/lang/Object;)Ljava/lang/StringBuilder;
      63: invokevirtual #81                 // Method java/lang/StringBuilder.toString:()Ljava/lang/String;
      66: invokespecial #84                 // Method java/lang/IllegalStateException."<init>":(Ljava/lang/String;)V
      69: athrow
      70: new           #20                 // class org/modelmapper/internal/bytebuddy/implementation/MethodCall$ArgumentLoader$ForField
      73: dup
      74: aload         4
      76: invokeinterface #88,  1           // InterfaceMethod org/modelmapper/internal/bytebuddy/dynamic/scaffold/FieldLocator$Resolution.getField:()Lorg/modelmapper/internal/bytebuddy/description/field/FieldDescription;
      81: aload_2
      82: invokespecial #91                 // Method org/modelmapper/internal/bytebuddy/implementation/MethodCall$ArgumentLoader$ForField."<init>":(Lorg/modelmapper/internal/bytebuddy/description/field/FieldDescription;Lorg/modelmapper/internal/bytebuddy/description/method/MethodDescription;)V
      85: invokestatic  #97                 // Method java/util/Collections.singletonList:(Ljava/lang/Object;)Ljava/util/List;
      88: areturn

  public boolean equals(java.lang.Object);
    Code:
       0: aload_0
       1: aload_1
       2: if_acmpne     7
       5: iconst_1
       6: ireturn
       7: aload_1
       8: ifnonnull     13
      11: iconst_0
      12: ireturn
      13: aload_0
      14: invokevirtual #109                // Method java/lang/Object.getClass:()Ljava/lang/Class;
      17: aload_1
      18: invokevirtual #109                // Method java/lang/Object.getClass:()Ljava/lang/Class;
      21: if_acmpeq     26
      24: iconst_0
      25: ireturn
      26: aload_0
      27: getfield      #40                 // Field name:Ljava/lang/String;
      30: aload_1
      31: checkcast     #2                  // class org/modelmapper/internal/bytebuddy/implementation/MethodCall$ArgumentLoader$ForField$Factory
      34: getfield      #40                 // Field name:Ljava/lang/String;
      37: invokevirtual #113                // Method java/lang/String.equals:(Ljava/lang/Object;)Z
      40: ifne          45
      43: iconst_0
      44: ireturn
      45: aload_0
      46: getfield      #42                 // Field fieldLocatorFactory:Lorg/modelmapper/internal/bytebuddy/dynamic/scaffold/FieldLocator$Factory;
      49: aload_1
      50: checkcast     #2                  // class org/modelmapper/internal/bytebuddy/implementation/MethodCall$ArgumentLoader$ForField$Factory
      53: getfield      #42                 // Field fieldLocatorFactory:Lorg/modelmapper/internal/bytebuddy/dynamic/scaffold/FieldLocator$Factory;
      56: invokeinterface #114,  2          // InterfaceMethod org/modelmapper/internal/bytebuddy/dynamic/scaffold/FieldLocator$Factory.equals:(Ljava/lang/Object;)Z
      61: ifne          66
      64: iconst_0
      65: ireturn
      66: iconst_1
      67: ireturn

  public int hashCode();
    Code:
       0: bipush        17
       2: bipush        31
       4: imul
       5: aload_0
       6: getfield      #40                 // Field name:Ljava/lang/String;
       9: invokevirtual #118                // Method java/lang/String.hashCode:()I
      12: iadd
      13: bipush        31
      15: imul
      16: aload_0
      17: getfield      #42                 // Field fieldLocatorFactory:Lorg/modelmapper/internal/bytebuddy/dynamic/scaffold/FieldLocator$Factory;
      20: invokeinterface #119,  1          // InterfaceMethod org/modelmapper/internal/bytebuddy/dynamic/scaffold/FieldLocator$Factory.hashCode:()I
      25: iadd
      26: ireturn
}
