Compiled from "SuperMethodCall.java"
public final class org.modelmapper.internal.bytebuddy.implementation.SuperMethodCall$WithoutReturn extends java.lang.Enum<org.modelmapper.internal.bytebuddy.implementation.SuperMethodCall$WithoutReturn> implements org.modelmapper.internal.bytebuddy.implementation.Implementation {
  public static final org.modelmapper.internal.bytebuddy.implementation.SuperMethodCall$WithoutReturn INSTANCE;

  private static final org.modelmapper.internal.bytebuddy.implementation.SuperMethodCall$WithoutReturn[] $VALUES;

  public static org.modelmapper.internal.bytebuddy.implementation.SuperMethodCall$WithoutReturn[] values();
    Code:
       0: getstatic     #28                 // Field $VALUES:[Lorg/modelmapper/internal/bytebuddy/implementation/SuperMethodCall$WithoutReturn;
       3: invokevirtual #33                 // Method "[Lorg/modelmapper/internal/bytebuddy/implementation/SuperMethodCall$WithoutReturn;".clone:()Ljava/lang/Object;
       6: checkcast     #29                 // class "[Lorg/modelmapper/internal/bytebuddy/implementation/SuperMethodCall$WithoutReturn;"
       9: areturn

  public static org.modelmapper.internal.bytebuddy.implementation.SuperMethodCall$WithoutReturn valueOf(java.lang.String);
    Code:
       0: ldc           #2                  // class org/modelmapper/internal/bytebuddy/implementation/SuperMethodCall$WithoutReturn
       2: aload_0
       3: invokestatic  #38                 // Method java/lang/Enum.valueOf:(Ljava/lang/Class;Ljava/lang/String;)Ljava/lang/Enum;
       6: checkcast     #2                  // class org/modelmapper/internal/bytebuddy/implementation/SuperMethodCall$WithoutReturn
       9: areturn

  private org.modelmapper.internal.bytebuddy.implementation.SuperMethodCall$WithoutReturn();
    Code:
       0: aload_0
       1: aload_1
       2: iload_2
       3: invokespecial #44                 // Method java/lang/Enum."<init>":(Ljava/lang/String;I)V
       6: return

  public org.modelmapper.internal.bytebuddy.dynamic.scaffold.InstrumentedType prepare(org.modelmapper.internal.bytebuddy.dynamic.scaffold.InstrumentedType);
    Code:
       0: aload_1
       1: areturn

  public org.modelmapper.internal.bytebuddy.implementation.bytecode.ByteCodeAppender appender(org.modelmapper.internal.bytebuddy.implementation.Implementation$Target);
    Code:
       0: new           #16                 // class org/modelmapper/internal/bytebuddy/implementation/SuperMethodCall$Appender
       3: dup
       4: aload_1
       5: getstatic     #55                 // Field org/modelmapper/internal/bytebuddy/implementation/SuperMethodCall$Appender$TerminationHandler.DROPPING:Lorg/modelmapper/internal/bytebuddy/implementation/SuperMethodCall$Appender$TerminationHandler;
       8: invokespecial #58                 // Method org/modelmapper/internal/bytebuddy/implementation/SuperMethodCall$Appender."<init>":(Lorg/modelmapper/internal/bytebuddy/implementation/Implementation$Target;Lorg/modelmapper/internal/bytebuddy/implementation/SuperMethodCall$Appender$TerminationHandler;)V
      11: areturn

  static {};
    Code:
       0: new           #2                  // class org/modelmapper/internal/bytebuddy/implementation/SuperMethodCall$WithoutReturn
       3: dup
       4: ldc           #63                 // String INSTANCE
       6: iconst_0
       7: invokespecial #64                 // Method "<init>":(Ljava/lang/String;I)V
      10: putstatic     #66                 // Field INSTANCE:Lorg/modelmapper/internal/bytebuddy/implementation/SuperMethodCall$WithoutReturn;
      13: iconst_1
      14: anewarray     #2                  // class org/modelmapper/internal/bytebuddy/implementation/SuperMethodCall$WithoutReturn
      17: dup
      18: iconst_0
      19: getstatic     #66                 // Field INSTANCE:Lorg/modelmapper/internal/bytebuddy/implementation/SuperMethodCall$WithoutReturn;
      22: aastore
      23: putstatic     #28                 // Field $VALUES:[Lorg/modelmapper/internal/bytebuddy/implementation/SuperMethodCall$WithoutReturn;
      26: return
}
