Compiled from "DnsNameResolver.java"
class io.netty.resolver.dns.DnsNameResolver$4 implements io.netty.channel.ChannelFutureListener {
  final io.netty.resolver.dns.DnsNameResolver this$0;

  io.netty.resolver.dns.DnsNameResolver$4(io.netty.resolver.dns.DnsNameResolver);
    Code:
       0: aload_0
       1: aload_1
       2: putfield      #1                  // Field this$0:Lio/netty/resolver/dns/DnsNameResolver;
       5: aload_0
       6: invokespecial #2                  // Method java/lang/Object."<init>":()V
       9: return

  public void operationComplete(io.netty.channel.ChannelFuture);
    Code:
       0: aload_1
       1: invokeinterface #3,  1            // InterfaceMethod io/netty/channel/ChannelFuture.cause:()Ljava/lang/Throwable;
       6: astore_2
       7: aload_2
       8: ifnull        25
      11: aload_0
      12: getfield      #1                  // Field this$0:Lio/netty/resolver/dns/DnsNameResolver;
      15: getfield      #4                  // Field io/netty/resolver/dns/DnsNameResolver.channelReadyPromise:Lio/netty/util/concurrent/Promise;
      18: aload_2
      19: invokeinterface #5,  2            // InterfaceMethod io/netty/util/concurrent/Promise.tryFailure:(Ljava/lang/Throwable;)Z
      24: pop
      25: return

  public void operationComplete(io.netty.util.concurrent.Future) throws java.lang.Exception;
    Code:
       0: aload_0
       1: aload_1
       2: checkcast     #6                  // class io/netty/channel/ChannelFuture
       5: invokevirtual #7                  // Method operationComplete:(Lio/netty/channel/ChannelFuture;)V
       8: return
}
