Compiled from "PointVectorValuePair.java"
class org.apache.commons.math3.optim.PointVectorValuePair$DataTransferObject implements java.io.Serializable {
  private static final long serialVersionUID;

  private final double[] point;

  private final double[] value;

  org.apache.commons.math3.optim.PointVectorValuePair$DataTransferObject(double[], double[]);
    Code:
       0: aload_0
       1: invokespecial #1                  // Method java/lang/Object."<init>":()V
       4: aload_0
       5: aload_1
       6: invokevirtual #2                  // Method "[D".clone:()Ljava/lang/Object;
       9: checkcast     #3                  // class "[D"
      12: putfield      #4                  // Field point:[D
      15: aload_0
      16: aload_2
      17: invokevirtual #5                  // Method "[D".clone:()Ljava/lang/Object;
      20: checkcast     #3                  // class "[D"
      23: putfield      #6                  // Field value:[D
      26: return

  private java.lang.Object readResolve();
    Code:
       0: new           #7                  // class org/apache/commons/math3/optim/PointVectorValuePair
       3: dup
       4: aload_0
       5: getfield      #4                  // Field point:[D
       8: aload_0
       9: getfield      #6                  // Field value:[D
      12: iconst_0
      13: invokespecial #8                  // Method org/apache/commons/math3/optim/PointVectorValuePair."<init>":([D[DZ)V
      16: areturn
}
