Compiled from "StaticManagedObject.java"
class org.jboss.as.naming.StaticManagedObject$1 implements org.jboss.as.naming.ManagedReference {
  final org.jboss.as.naming.StaticManagedObject this$0;

  org.jboss.as.naming.StaticManagedObject$1(org.jboss.as.naming.StaticManagedObject);
    Code:
       0: aload_0
       1: aload_1
       2: putfield      #1                  // Field this$0:Lorg/jboss/as/naming/StaticManagedObject;
       5: aload_0
       6: invokespecial #2                  // Method java/lang/Object."<init>":()V
       9: return

  public void release();
    Code:
       0: return

  public java.lang.Object getInstance();
    Code:
       0: aload_0
       1: getfield      #1                  // Field this$0:Lorg/jboss/as/naming/StaticManagedObject;
       4: invokestatic  #3                  // Method org/jboss/as/naming/StaticManagedObject.access$000:(Lorg/jboss/as/naming/StaticManagedObject;)Ljava/lang/Object;
       7: areturn
}
