Compiled from "ContextClassLoaderUtils.java"
public class org.ops4j.pax.swissbox.core.ContextClassLoaderUtils {
  private org.ops4j.pax.swissbox.core.ContextClassLoaderUtils();
    Code:
       0: aload_0
       1: invokespecial #1                  // Method java/lang/Object."<init>":()V
       4: return

  public static <V> V doWithClassLoader(java.lang.ClassLoader, java.util.concurrent.Callable<V>) throws java.lang.Exception;
    Code:
       0: aconst_null
       1: astore_2
       2: aconst_null
       3: astore_3
       4: aload_0
       5: ifnull        22
       8: invokestatic  #2                  // Method java/lang/Thread.currentThread:()Ljava/lang/Thread;
      11: astore_2
      12: aload_2
      13: invokevirtual #3                  // Method java/lang/Thread.getContextClassLoader:()Ljava/lang/ClassLoader;
      16: astore_3
      17: aload_2
      18: aload_0
      19: invokevirtual #4                  // Method java/lang/Thread.setContextClassLoader:(Ljava/lang/ClassLoader;)V
      22: aload_1
      23: invokeinterface #5,  1            // InterfaceMethod java/util/concurrent/Callable.call:()Ljava/lang/Object;
      28: astore        4
      30: aload_3
      31: ifnull        39
      34: aload_2
      35: aload_3
      36: invokevirtual #4                  // Method java/lang/Thread.setContextClassLoader:(Ljava/lang/ClassLoader;)V
      39: aload         4
      41: areturn
      42: astore        5
      44: aload_3
      45: ifnull        53
      48: aload_2
      49: aload_3
      50: invokevirtual #4                  // Method java/lang/Thread.setContextClassLoader:(Ljava/lang/ClassLoader;)V
      53: aload         5
      55: athrow
    Exception table:
       from    to  target type
           4    30    42   any
          42    44    42   any
}
