Compiled from "GeometryDecoderHelper.java"
final class com.mongodb.client.model.geojson.codecs.GeometryDecoderHelper {
  static <T extends com.mongodb.client.model.geojson.Geometry> T decodeGeometry(org.bson.BsonReader, java.lang.Class<T>);
    Code:
       0: aload_1
       1: ldc           #1                  // class com/mongodb/client/model/geojson/Point
       3: invokevirtual #2                  // Method java/lang/Object.equals:(Ljava/lang/Object;)Z
       6: ifeq          14
       9: aload_0
      10: invokestatic  #3                  // Method decodePoint:(Lorg/bson/BsonReader;)Lcom/mongodb/client/model/geojson/Point;
      13: areturn
      14: aload_1
      15: ldc           #4                  // class com/mongodb/client/model/geojson/MultiPoint
      17: invokevirtual #2                  // Method java/lang/Object.equals:(Ljava/lang/Object;)Z
      20: ifeq          28
      23: aload_0
      24: invokestatic  #5                  // Method decodeMultiPoint:(Lorg/bson/BsonReader;)Lcom/mongodb/client/model/geojson/MultiPoint;
      27: areturn
      28: aload_1
      29: ldc           #6                  // class com/mongodb/client/model/geojson/Polygon
      31: invokevirtual #2                  // Method java/lang/Object.equals:(Ljava/lang/Object;)Z
      34: ifeq          42
      37: aload_0
      38: invokestatic  #7                  // Method decodePolygon:(Lorg/bson/BsonReader;)Lcom/mongodb/client/model/geojson/Polygon;
      41: areturn
      42: aload_1
      43: ldc           #8                  // class com/mongodb/client/model/geojson/MultiPolygon
      45: invokevirtual #2                  // Method java/lang/Object.equals:(Ljava/lang/Object;)Z
      48: ifeq          56
      51: aload_0
      52: invokestatic  #9                  // Method decodeMultiPolygon:(Lorg/bson/BsonReader;)Lcom/mongodb/client/model/geojson/MultiPolygon;
      55: areturn
      56: aload_1
      57: ldc           #10                 // class com/mongodb/client/model/geojson/LineString
      59: invokevirtual #2                  // Method java/lang/Object.equals:(Ljava/lang/Object;)Z
      62: ifeq          70
      65: aload_0
      66: invokestatic  #11                 // Method decodeLineString:(Lorg/bson/BsonReader;)Lcom/mongodb/client/model/geojson/LineString;
      69: areturn
      70: aload_1
      71: ldc           #12                 // class com/mongodb/client/model/geojson/MultiLineString
      73: invokevirtual #2                  // Method java/lang/Object.equals:(Ljava/lang/Object;)Z
      76: ifeq          84
      79: aload_0
      80: invokestatic  #13                 // Method decodeMultiLineString:(Lorg/bson/BsonReader;)Lcom/mongodb/client/model/geojson/MultiLineString;
      83: areturn
      84: aload_1
      85: ldc           #14                 // class com/mongodb/client/model/geojson/GeometryCollection
      87: invokevirtual #2                  // Method java/lang/Object.equals:(Ljava/lang/Object;)Z
      90: ifeq          98
      93: aload_0
      94: invokestatic  #15                 // Method decodeGeometryCollection:(Lorg/bson/BsonReader;)Lcom/mongodb/client/model/geojson/GeometryCollection;
      97: areturn
      98: aload_1
      99: ldc           #16                 // class com/mongodb/client/model/geojson/Geometry
     101: invokevirtual #2                  // Method java/lang/Object.equals:(Ljava/lang/Object;)Z
     104: ifeq          112
     107: aload_0
     108: invokestatic  #17                 // Method decodeGeometry:(Lorg/bson/BsonReader;)Lcom/mongodb/client/model/geojson/Geometry;
     111: areturn
     112: new           #18                 // class org/bson/codecs/configuration/CodecConfigurationException
     115: dup
     116: ldc           #19                 // String Unsupported Geometry: %s
     118: iconst_1
     119: anewarray     #20                 // class java/lang/Object
     122: dup
     123: iconst_0
     124: aload_1
     125: aastore
     126: invokestatic  #21                 // Method java/lang/String.format:(Ljava/lang/String;[Ljava/lang/Object;)Ljava/lang/String;
     129: invokespecial #22                 // Method org/bson/codecs/configuration/CodecConfigurationException."<init>":(Ljava/lang/String;)V
     132: athrow

  private static com.mongodb.client.model.geojson.Point decodePoint(org.bson.BsonReader);
    Code:
       0: aconst_null
       1: astore_1
       2: aconst_null
       3: astore_2
       4: aconst_null
       5: astore_3
       6: aload_0
       7: invokeinterface #23,  1           // InterfaceMethod org/bson/BsonReader.readStartDocument:()V
      12: aload_0
      13: invokeinterface #24,  1           // InterfaceMethod org/bson/BsonReader.readBsonType:()Lorg/bson/BsonType;
      18: getstatic     #25                 // Field org/bson/BsonType.END_OF_DOCUMENT:Lorg/bson/BsonType;
      21: if_acmpeq     113
      24: aload_0
      25: invokeinterface #26,  1           // InterfaceMethod org/bson/BsonReader.readName:()Ljava/lang/String;
      30: astore        4
      32: aload         4
      34: ldc           #27                 // String type
      36: invokevirtual #28                 // Method java/lang/String.equals:(Ljava/lang/Object;)Z
      39: ifeq          52
      42: aload_0
      43: invokeinterface #29,  1           // InterfaceMethod org/bson/BsonReader.readString:()Ljava/lang/String;
      48: astore_1
      49: goto          110
      52: aload         4
      54: ldc           #30                 // String coordinates
      56: invokevirtual #28                 // Method java/lang/String.equals:(Ljava/lang/Object;)Z
      59: ifeq          70
      62: aload_0
      63: invokestatic  #31                 // Method decodePosition:(Lorg/bson/BsonReader;)Lcom/mongodb/client/model/geojson/Position;
      66: astore_2
      67: goto          110
      70: aload         4
      72: ldc           #32                 // String crs
      74: invokevirtual #28                 // Method java/lang/String.equals:(Ljava/lang/Object;)Z
      77: ifeq          88
      80: aload_0
      81: invokestatic  #33                 // Method decodeCoordinateReferenceSystem:(Lorg/bson/BsonReader;)Lcom/mongodb/client/model/geojson/CoordinateReferenceSystem;
      84: astore_3
      85: goto          110
      88: new           #18                 // class org/bson/codecs/configuration/CodecConfigurationException
      91: dup
      92: ldc           #34                 // String Unexpected key \'%s\' found when decoding a GeoJSON point
      94: iconst_1
      95: anewarray     #20                 // class java/lang/Object
      98: dup
      99: iconst_0
     100: aload         4
     102: aastore
     103: invokestatic  #21                 // Method java/lang/String.format:(Ljava/lang/String;[Ljava/lang/Object;)Ljava/lang/String;
     106: invokespecial #22                 // Method org/bson/codecs/configuration/CodecConfigurationException."<init>":(Ljava/lang/String;)V
     109: athrow
     110: goto          12
     113: aload_0
     114: invokeinterface #35,  1           // InterfaceMethod org/bson/BsonReader.readEndDocument:()V
     119: aload_1
     120: ifnonnull     133
     123: new           #18                 // class org/bson/codecs/configuration/CodecConfigurationException
     126: dup
     127: ldc           #36                 // String Invalid Point, document contained no type information.
     129: invokespecial #22                 // Method org/bson/codecs/configuration/CodecConfigurationException."<init>":(Ljava/lang/String;)V
     132: athrow
     133: aload_1
     134: ldc           #37                 // String Point
     136: invokevirtual #28                 // Method java/lang/String.equals:(Ljava/lang/Object;)Z
     139: ifne          163
     142: new           #18                 // class org/bson/codecs/configuration/CodecConfigurationException
     145: dup
     146: ldc           #38                 // String Invalid Point, found type \'%s\'.
     148: iconst_1
     149: anewarray     #20                 // class java/lang/Object
     152: dup
     153: iconst_0
     154: aload_1
     155: aastore
     156: invokestatic  #21                 // Method java/lang/String.format:(Ljava/lang/String;[Ljava/lang/Object;)Ljava/lang/String;
     159: invokespecial #22                 // Method org/bson/codecs/configuration/CodecConfigurationException."<init>":(Ljava/lang/String;)V
     162: athrow
     163: aload_2
     164: ifnonnull     177
     167: new           #18                 // class org/bson/codecs/configuration/CodecConfigurationException
     170: dup
     171: ldc           #39                 // String Invalid Point, missing position coordinates.
     173: invokespecial #22                 // Method org/bson/codecs/configuration/CodecConfigurationException."<init>":(Ljava/lang/String;)V
     176: athrow
     177: aload_3
     178: ifnull        193
     181: new           #1                  // class com/mongodb/client/model/geojson/Point
     184: dup
     185: aload_3
     186: aload_2
     187: invokespecial #40                 // Method com/mongodb/client/model/geojson/Point."<init>":(Lcom/mongodb/client/model/geojson/CoordinateReferenceSystem;Lcom/mongodb/client/model/geojson/Position;)V
     190: goto          201
     193: new           #1                  // class com/mongodb/client/model/geojson/Point
     196: dup
     197: aload_2
     198: invokespecial #41                 // Method com/mongodb/client/model/geojson/Point."<init>":(Lcom/mongodb/client/model/geojson/Position;)V
     201: areturn

  private static com.mongodb.client.model.geojson.MultiPoint decodeMultiPoint(org.bson.BsonReader);
    Code:
       0: aconst_null
       1: astore_1
       2: aconst_null
       3: astore_2
       4: aconst_null
       5: astore_3
       6: aload_0
       7: invokeinterface #23,  1           // InterfaceMethod org/bson/BsonReader.readStartDocument:()V
      12: aload_0
      13: invokeinterface #24,  1           // InterfaceMethod org/bson/BsonReader.readBsonType:()Lorg/bson/BsonType;
      18: getstatic     #25                 // Field org/bson/BsonType.END_OF_DOCUMENT:Lorg/bson/BsonType;
      21: if_acmpeq     113
      24: aload_0
      25: invokeinterface #26,  1           // InterfaceMethod org/bson/BsonReader.readName:()Ljava/lang/String;
      30: astore        4
      32: aload         4
      34: ldc           #27                 // String type
      36: invokevirtual #28                 // Method java/lang/String.equals:(Ljava/lang/Object;)Z
      39: ifeq          52
      42: aload_0
      43: invokeinterface #29,  1           // InterfaceMethod org/bson/BsonReader.readString:()Ljava/lang/String;
      48: astore_1
      49: goto          110
      52: aload         4
      54: ldc           #30                 // String coordinates
      56: invokevirtual #28                 // Method java/lang/String.equals:(Ljava/lang/Object;)Z
      59: ifeq          70
      62: aload_0
      63: invokestatic  #42                 // Method decodeCoordinates:(Lorg/bson/BsonReader;)Ljava/util/List;
      66: astore_2
      67: goto          110
      70: aload         4
      72: ldc           #32                 // String crs
      74: invokevirtual #28                 // Method java/lang/String.equals:(Ljava/lang/Object;)Z
      77: ifeq          88
      80: aload_0
      81: invokestatic  #33                 // Method decodeCoordinateReferenceSystem:(Lorg/bson/BsonReader;)Lcom/mongodb/client/model/geojson/CoordinateReferenceSystem;
      84: astore_3
      85: goto          110
      88: new           #18                 // class org/bson/codecs/configuration/CodecConfigurationException
      91: dup
      92: ldc           #34                 // String Unexpected key \'%s\' found when decoding a GeoJSON point
      94: iconst_1
      95: anewarray     #20                 // class java/lang/Object
      98: dup
      99: iconst_0
     100: aload         4
     102: aastore
     103: invokestatic  #21                 // Method java/lang/String.format:(Ljava/lang/String;[Ljava/lang/Object;)Ljava/lang/String;
     106: invokespecial #22                 // Method org/bson/codecs/configuration/CodecConfigurationException."<init>":(Ljava/lang/String;)V
     109: athrow
     110: goto          12
     113: aload_0
     114: invokeinterface #35,  1           // InterfaceMethod org/bson/BsonReader.readEndDocument:()V
     119: aload_1
     120: ifnonnull     133
     123: new           #18                 // class org/bson/codecs/configuration/CodecConfigurationException
     126: dup
     127: ldc           #43                 // String Invalid MultiPoint, document contained no type information.
     129: invokespecial #22                 // Method org/bson/codecs/configuration/CodecConfigurationException."<init>":(Ljava/lang/String;)V
     132: athrow
     133: aload_1
     134: ldc           #44                 // String MultiPoint
     136: invokevirtual #28                 // Method java/lang/String.equals:(Ljava/lang/Object;)Z
     139: ifne          163
     142: new           #18                 // class org/bson/codecs/configuration/CodecConfigurationException
     145: dup
     146: ldc           #45                 // String Invalid MultiPoint, found type \'%s\'.
     148: iconst_1
     149: anewarray     #20                 // class java/lang/Object
     152: dup
     153: iconst_0
     154: aload_1
     155: aastore
     156: invokestatic  #21                 // Method java/lang/String.format:(Ljava/lang/String;[Ljava/lang/Object;)Ljava/lang/String;
     159: invokespecial #22                 // Method org/bson/codecs/configuration/CodecConfigurationException."<init>":(Ljava/lang/String;)V
     162: athrow
     163: aload_2
     164: ifnonnull     177
     167: new           #18                 // class org/bson/codecs/configuration/CodecConfigurationException
     170: dup
     171: ldc           #46                 // String Invalid MultiPoint, missing position coordinates.
     173: invokespecial #22                 // Method org/bson/codecs/configuration/CodecConfigurationException."<init>":(Ljava/lang/String;)V
     176: athrow
     177: aload_3
     178: ifnull        193
     181: new           #4                  // class com/mongodb/client/model/geojson/MultiPoint
     184: dup
     185: aload_3
     186: aload_2
     187: invokespecial #47                 // Method com/mongodb/client/model/geojson/MultiPoint."<init>":(Lcom/mongodb/client/model/geojson/CoordinateReferenceSystem;Ljava/util/List;)V
     190: goto          201
     193: new           #4                  // class com/mongodb/client/model/geojson/MultiPoint
     196: dup
     197: aload_2
     198: invokespecial #48                 // Method com/mongodb/client/model/geojson/MultiPoint."<init>":(Ljava/util/List;)V
     201: areturn

  private static com.mongodb.client.model.geojson.Polygon decodePolygon(org.bson.BsonReader);
    Code:
       0: aconst_null
       1: astore_1
       2: aconst_null
       3: astore_2
       4: aconst_null
       5: astore_3
       6: aload_0
       7: invokeinterface #23,  1           // InterfaceMethod org/bson/BsonReader.readStartDocument:()V
      12: aload_0
      13: invokeinterface #24,  1           // InterfaceMethod org/bson/BsonReader.readBsonType:()Lorg/bson/BsonType;
      18: getstatic     #25                 // Field org/bson/BsonType.END_OF_DOCUMENT:Lorg/bson/BsonType;
      21: if_acmpeq     113
      24: aload_0
      25: invokeinterface #26,  1           // InterfaceMethod org/bson/BsonReader.readName:()Ljava/lang/String;
      30: astore        4
      32: aload         4
      34: ldc           #27                 // String type
      36: invokevirtual #28                 // Method java/lang/String.equals:(Ljava/lang/Object;)Z
      39: ifeq          52
      42: aload_0
      43: invokeinterface #29,  1           // InterfaceMethod org/bson/BsonReader.readString:()Ljava/lang/String;
      48: astore_1
      49: goto          110
      52: aload         4
      54: ldc           #30                 // String coordinates
      56: invokevirtual #28                 // Method java/lang/String.equals:(Ljava/lang/Object;)Z
      59: ifeq          70
      62: aload_0
      63: invokestatic  #49                 // Method decodePolygonCoordinates:(Lorg/bson/BsonReader;)Lcom/mongodb/client/model/geojson/PolygonCoordinates;
      66: astore_2
      67: goto          110
      70: aload         4
      72: ldc           #32                 // String crs
      74: invokevirtual #28                 // Method java/lang/String.equals:(Ljava/lang/Object;)Z
      77: ifeq          88
      80: aload_0
      81: invokestatic  #33                 // Method decodeCoordinateReferenceSystem:(Lorg/bson/BsonReader;)Lcom/mongodb/client/model/geojson/CoordinateReferenceSystem;
      84: astore_3
      85: goto          110
      88: new           #18                 // class org/bson/codecs/configuration/CodecConfigurationException
      91: dup
      92: ldc           #50                 // String Unexpected key \'%s\' found when decoding a GeoJSON Polygon
      94: iconst_1
      95: anewarray     #20                 // class java/lang/Object
      98: dup
      99: iconst_0
     100: aload         4
     102: aastore
     103: invokestatic  #21                 // Method java/lang/String.format:(Ljava/lang/String;[Ljava/lang/Object;)Ljava/lang/String;
     106: invokespecial #22                 // Method org/bson/codecs/configuration/CodecConfigurationException."<init>":(Ljava/lang/String;)V
     109: athrow
     110: goto          12
     113: aload_0
     114: invokeinterface #35,  1           // InterfaceMethod org/bson/BsonReader.readEndDocument:()V
     119: aload_1
     120: ifnonnull     133
     123: new           #18                 // class org/bson/codecs/configuration/CodecConfigurationException
     126: dup
     127: ldc           #51                 // String Invalid Polygon, document contained no type information.
     129: invokespecial #22                 // Method org/bson/codecs/configuration/CodecConfigurationException."<init>":(Ljava/lang/String;)V
     132: athrow
     133: aload_1
     134: ldc           #52                 // String Polygon
     136: invokevirtual #28                 // Method java/lang/String.equals:(Ljava/lang/Object;)Z
     139: ifne          163
     142: new           #18                 // class org/bson/codecs/configuration/CodecConfigurationException
     145: dup
     146: ldc           #53                 // String Invalid Polygon, found type \'%s\'.
     148: iconst_1
     149: anewarray     #20                 // class java/lang/Object
     152: dup
     153: iconst_0
     154: aload_1
     155: aastore
     156: invokestatic  #21                 // Method java/lang/String.format:(Ljava/lang/String;[Ljava/lang/Object;)Ljava/lang/String;
     159: invokespecial #22                 // Method org/bson/codecs/configuration/CodecConfigurationException."<init>":(Ljava/lang/String;)V
     162: athrow
     163: aload_2
     164: ifnonnull     177
     167: new           #18                 // class org/bson/codecs/configuration/CodecConfigurationException
     170: dup
     171: ldc           #54                 // String Invalid Polygon, missing coordinates.
     173: invokespecial #22                 // Method org/bson/codecs/configuration/CodecConfigurationException."<init>":(Ljava/lang/String;)V
     176: athrow
     177: aload_3
     178: ifnull        193
     181: new           #6                  // class com/mongodb/client/model/geojson/Polygon
     184: dup
     185: aload_3
     186: aload_2
     187: invokespecial #55                 // Method com/mongodb/client/model/geojson/Polygon."<init>":(Lcom/mongodb/client/model/geojson/CoordinateReferenceSystem;Lcom/mongodb/client/model/geojson/PolygonCoordinates;)V
     190: goto          201
     193: new           #6                  // class com/mongodb/client/model/geojson/Polygon
     196: dup
     197: aload_2
     198: invokespecial #56                 // Method com/mongodb/client/model/geojson/Polygon."<init>":(Lcom/mongodb/client/model/geojson/PolygonCoordinates;)V
     201: areturn

  private static com.mongodb.client.model.geojson.MultiPolygon decodeMultiPolygon(org.bson.BsonReader);
    Code:
       0: aconst_null
       1: astore_1
       2: aconst_null
       3: astore_2
       4: aconst_null
       5: astore_3
       6: aload_0
       7: invokeinterface #23,  1           // InterfaceMethod org/bson/BsonReader.readStartDocument:()V
      12: aload_0
      13: invokeinterface #24,  1           // InterfaceMethod org/bson/BsonReader.readBsonType:()Lorg/bson/BsonType;
      18: getstatic     #25                 // Field org/bson/BsonType.END_OF_DOCUMENT:Lorg/bson/BsonType;
      21: if_acmpeq     113
      24: aload_0
      25: invokeinterface #26,  1           // InterfaceMethod org/bson/BsonReader.readName:()Ljava/lang/String;
      30: astore        4
      32: aload         4
      34: ldc           #27                 // String type
      36: invokevirtual #28                 // Method java/lang/String.equals:(Ljava/lang/Object;)Z
      39: ifeq          52
      42: aload_0
      43: invokeinterface #29,  1           // InterfaceMethod org/bson/BsonReader.readString:()Ljava/lang/String;
      48: astore_1
      49: goto          110
      52: aload         4
      54: ldc           #30                 // String coordinates
      56: invokevirtual #28                 // Method java/lang/String.equals:(Ljava/lang/Object;)Z
      59: ifeq          70
      62: aload_0
      63: invokestatic  #57                 // Method decodeMultiPolygonCoordinates:(Lorg/bson/BsonReader;)Ljava/util/List;
      66: astore_2
      67: goto          110
      70: aload         4
      72: ldc           #32                 // String crs
      74: invokevirtual #28                 // Method java/lang/String.equals:(Ljava/lang/Object;)Z
      77: ifeq          88
      80: aload_0
      81: invokestatic  #33                 // Method decodeCoordinateReferenceSystem:(Lorg/bson/BsonReader;)Lcom/mongodb/client/model/geojson/CoordinateReferenceSystem;
      84: astore_3
      85: goto          110
      88: new           #18                 // class org/bson/codecs/configuration/CodecConfigurationException
      91: dup
      92: ldc           #50                 // String Unexpected key \'%s\' found when decoding a GeoJSON Polygon
      94: iconst_1
      95: anewarray     #20                 // class java/lang/Object
      98: dup
      99: iconst_0
     100: aload         4
     102: aastore
     103: invokestatic  #21                 // Method java/lang/String.format:(Ljava/lang/String;[Ljava/lang/Object;)Ljava/lang/String;
     106: invokespecial #22                 // Method org/bson/codecs/configuration/CodecConfigurationException."<init>":(Ljava/lang/String;)V
     109: athrow
     110: goto          12
     113: aload_0
     114: invokeinterface #35,  1           // InterfaceMethod org/bson/BsonReader.readEndDocument:()V
     119: aload_1
     120: ifnonnull     133
     123: new           #18                 // class org/bson/codecs/configuration/CodecConfigurationException
     126: dup
     127: ldc           #58                 // String Invalid MultiPolygon, document contained no type information.
     129: invokespecial #22                 // Method org/bson/codecs/configuration/CodecConfigurationException."<init>":(Ljava/lang/String;)V
     132: athrow
     133: aload_1
     134: ldc           #59                 // String MultiPolygon
     136: invokevirtual #28                 // Method java/lang/String.equals:(Ljava/lang/Object;)Z
     139: ifne          163
     142: new           #18                 // class org/bson/codecs/configuration/CodecConfigurationException
     145: dup
     146: ldc           #60                 // String Invalid MultiPolygon, found type \'%s\'.
     148: iconst_1
     149: anewarray     #20                 // class java/lang/Object
     152: dup
     153: iconst_0
     154: aload_1
     155: aastore
     156: invokestatic  #21                 // Method java/lang/String.format:(Ljava/lang/String;[Ljava/lang/Object;)Ljava/lang/String;
     159: invokespecial #22                 // Method org/bson/codecs/configuration/CodecConfigurationException."<init>":(Ljava/lang/String;)V
     162: athrow
     163: aload_2
     164: ifnonnull     177
     167: new           #18                 // class org/bson/codecs/configuration/CodecConfigurationException
     170: dup
     171: ldc           #61                 // String Invalid MultiPolygon, missing coordinates.
     173: invokespecial #22                 // Method org/bson/codecs/configuration/CodecConfigurationException."<init>":(Ljava/lang/String;)V
     176: athrow
     177: aload_3
     178: ifnull        193
     181: new           #8                  // class com/mongodb/client/model/geojson/MultiPolygon
     184: dup
     185: aload_3
     186: aload_2
     187: invokespecial #62                 // Method com/mongodb/client/model/geojson/MultiPolygon."<init>":(Lcom/mongodb/client/model/geojson/CoordinateReferenceSystem;Ljava/util/List;)V
     190: goto          201
     193: new           #8                  // class com/mongodb/client/model/geojson/MultiPolygon
     196: dup
     197: aload_2
     198: invokespecial #63                 // Method com/mongodb/client/model/geojson/MultiPolygon."<init>":(Ljava/util/List;)V
     201: areturn

  private static com.mongodb.client.model.geojson.LineString decodeLineString(org.bson.BsonReader);
    Code:
       0: aconst_null
       1: astore_1
       2: aconst_null
       3: astore_2
       4: aconst_null
       5: astore_3
       6: aload_0
       7: invokeinterface #23,  1           // InterfaceMethod org/bson/BsonReader.readStartDocument:()V
      12: aload_0
      13: invokeinterface #24,  1           // InterfaceMethod org/bson/BsonReader.readBsonType:()Lorg/bson/BsonType;
      18: getstatic     #25                 // Field org/bson/BsonType.END_OF_DOCUMENT:Lorg/bson/BsonType;
      21: if_acmpeq     113
      24: aload_0
      25: invokeinterface #26,  1           // InterfaceMethod org/bson/BsonReader.readName:()Ljava/lang/String;
      30: astore        4
      32: aload         4
      34: ldc           #27                 // String type
      36: invokevirtual #28                 // Method java/lang/String.equals:(Ljava/lang/Object;)Z
      39: ifeq          52
      42: aload_0
      43: invokeinterface #29,  1           // InterfaceMethod org/bson/BsonReader.readString:()Ljava/lang/String;
      48: astore_1
      49: goto          110
      52: aload         4
      54: ldc           #30                 // String coordinates
      56: invokevirtual #28                 // Method java/lang/String.equals:(Ljava/lang/Object;)Z
      59: ifeq          70
      62: aload_0
      63: invokestatic  #42                 // Method decodeCoordinates:(Lorg/bson/BsonReader;)Ljava/util/List;
      66: astore_2
      67: goto          110
      70: aload         4
      72: ldc           #32                 // String crs
      74: invokevirtual #28                 // Method java/lang/String.equals:(Ljava/lang/Object;)Z
      77: ifeq          88
      80: aload_0
      81: invokestatic  #33                 // Method decodeCoordinateReferenceSystem:(Lorg/bson/BsonReader;)Lcom/mongodb/client/model/geojson/CoordinateReferenceSystem;
      84: astore_3
      85: goto          110
      88: new           #18                 // class org/bson/codecs/configuration/CodecConfigurationException
      91: dup
      92: ldc           #50                 // String Unexpected key \'%s\' found when decoding a GeoJSON Polygon
      94: iconst_1
      95: anewarray     #20                 // class java/lang/Object
      98: dup
      99: iconst_0
     100: aload         4
     102: aastore
     103: invokestatic  #21                 // Method java/lang/String.format:(Ljava/lang/String;[Ljava/lang/Object;)Ljava/lang/String;
     106: invokespecial #22                 // Method org/bson/codecs/configuration/CodecConfigurationException."<init>":(Ljava/lang/String;)V
     109: athrow
     110: goto          12
     113: aload_0
     114: invokeinterface #35,  1           // InterfaceMethod org/bson/BsonReader.readEndDocument:()V
     119: aload_1
     120: ifnonnull     133
     123: new           #18                 // class org/bson/codecs/configuration/CodecConfigurationException
     126: dup
     127: ldc           #64                 // String Invalid LineString, document contained no type information.
     129: invokespecial #22                 // Method org/bson/codecs/configuration/CodecConfigurationException."<init>":(Ljava/lang/String;)V
     132: athrow
     133: aload_1
     134: ldc           #65                 // String LineString
     136: invokevirtual #28                 // Method java/lang/String.equals:(Ljava/lang/Object;)Z
     139: ifne          163
     142: new           #18                 // class org/bson/codecs/configuration/CodecConfigurationException
     145: dup
     146: ldc           #66                 // String Invalid LineString, found type \'%s\'.
     148: iconst_1
     149: anewarray     #20                 // class java/lang/Object
     152: dup
     153: iconst_0
     154: aload_1
     155: aastore
     156: invokestatic  #21                 // Method java/lang/String.format:(Ljava/lang/String;[Ljava/lang/Object;)Ljava/lang/String;
     159: invokespecial #22                 // Method org/bson/codecs/configuration/CodecConfigurationException."<init>":(Ljava/lang/String;)V
     162: athrow
     163: aload_2
     164: ifnonnull     177
     167: new           #18                 // class org/bson/codecs/configuration/CodecConfigurationException
     170: dup
     171: ldc           #67                 // String Invalid LineString, missing coordinates.
     173: invokespecial #22                 // Method org/bson/codecs/configuration/CodecConfigurationException."<init>":(Ljava/lang/String;)V
     176: athrow
     177: aload_3
     178: ifnull        193
     181: new           #10                 // class com/mongodb/client/model/geojson/LineString
     184: dup
     185: aload_3
     186: aload_2
     187: invokespecial #68                 // Method com/mongodb/client/model/geojson/LineString."<init>":(Lcom/mongodb/client/model/geojson/CoordinateReferenceSystem;Ljava/util/List;)V
     190: goto          201
     193: new           #10                 // class com/mongodb/client/model/geojson/LineString
     196: dup
     197: aload_2
     198: invokespecial #69                 // Method com/mongodb/client/model/geojson/LineString."<init>":(Ljava/util/List;)V
     201: areturn

  private static com.mongodb.client.model.geojson.MultiLineString decodeMultiLineString(org.bson.BsonReader);
    Code:
       0: aconst_null
       1: astore_1
       2: aconst_null
       3: astore_2
       4: aconst_null
       5: astore_3
       6: aload_0
       7: invokeinterface #23,  1           // InterfaceMethod org/bson/BsonReader.readStartDocument:()V
      12: aload_0
      13: invokeinterface #24,  1           // InterfaceMethod org/bson/BsonReader.readBsonType:()Lorg/bson/BsonType;
      18: getstatic     #25                 // Field org/bson/BsonType.END_OF_DOCUMENT:Lorg/bson/BsonType;
      21: if_acmpeq     113
      24: aload_0
      25: invokeinterface #26,  1           // InterfaceMethod org/bson/BsonReader.readName:()Ljava/lang/String;
      30: astore        4
      32: aload         4
      34: ldc           #27                 // String type
      36: invokevirtual #28                 // Method java/lang/String.equals:(Ljava/lang/Object;)Z
      39: ifeq          52
      42: aload_0
      43: invokeinterface #29,  1           // InterfaceMethod org/bson/BsonReader.readString:()Ljava/lang/String;
      48: astore_1
      49: goto          110
      52: aload         4
      54: ldc           #30                 // String coordinates
      56: invokevirtual #28                 // Method java/lang/String.equals:(Ljava/lang/Object;)Z
      59: ifeq          70
      62: aload_0
      63: invokestatic  #70                 // Method decodeMultiCoordinates:(Lorg/bson/BsonReader;)Ljava/util/List;
      66: astore_2
      67: goto          110
      70: aload         4
      72: ldc           #32                 // String crs
      74: invokevirtual #28                 // Method java/lang/String.equals:(Ljava/lang/Object;)Z
      77: ifeq          88
      80: aload_0
      81: invokestatic  #33                 // Method decodeCoordinateReferenceSystem:(Lorg/bson/BsonReader;)Lcom/mongodb/client/model/geojson/CoordinateReferenceSystem;
      84: astore_3
      85: goto          110
      88: new           #18                 // class org/bson/codecs/configuration/CodecConfigurationException
      91: dup
      92: ldc           #50                 // String Unexpected key \'%s\' found when decoding a GeoJSON Polygon
      94: iconst_1
      95: anewarray     #20                 // class java/lang/Object
      98: dup
      99: iconst_0
     100: aload         4
     102: aastore
     103: invokestatic  #21                 // Method java/lang/String.format:(Ljava/lang/String;[Ljava/lang/Object;)Ljava/lang/String;
     106: invokespecial #22                 // Method org/bson/codecs/configuration/CodecConfigurationException."<init>":(Ljava/lang/String;)V
     109: athrow
     110: goto          12
     113: aload_0
     114: invokeinterface #35,  1           // InterfaceMethod org/bson/BsonReader.readEndDocument:()V
     119: aload_1
     120: ifnonnull     133
     123: new           #18                 // class org/bson/codecs/configuration/CodecConfigurationException
     126: dup
     127: ldc           #71                 // String Invalid MultiLineString, document contained no type information.
     129: invokespecial #22                 // Method org/bson/codecs/configuration/CodecConfigurationException."<init>":(Ljava/lang/String;)V
     132: athrow
     133: aload_1
     134: ldc           #72                 // String MultiLineString
     136: invokevirtual #28                 // Method java/lang/String.equals:(Ljava/lang/Object;)Z
     139: ifne          163
     142: new           #18                 // class org/bson/codecs/configuration/CodecConfigurationException
     145: dup
     146: ldc           #73                 // String Invalid MultiLineString, found type \'%s\'.
     148: iconst_1
     149: anewarray     #20                 // class java/lang/Object
     152: dup
     153: iconst_0
     154: aload_1
     155: aastore
     156: invokestatic  #21                 // Method java/lang/String.format:(Ljava/lang/String;[Ljava/lang/Object;)Ljava/lang/String;
     159: invokespecial #22                 // Method org/bson/codecs/configuration/CodecConfigurationException."<init>":(Ljava/lang/String;)V
     162: athrow
     163: aload_2
     164: ifnonnull     177
     167: new           #18                 // class org/bson/codecs/configuration/CodecConfigurationException
     170: dup
     171: ldc           #74                 // String Invalid MultiLineString, missing coordinates.
     173: invokespecial #22                 // Method org/bson/codecs/configuration/CodecConfigurationException."<init>":(Ljava/lang/String;)V
     176: athrow
     177: aload_3
     178: ifnull        193
     181: new           #12                 // class com/mongodb/client/model/geojson/MultiLineString
     184: dup
     185: aload_3
     186: aload_2
     187: invokespecial #75                 // Method com/mongodb/client/model/geojson/MultiLineString."<init>":(Lcom/mongodb/client/model/geojson/CoordinateReferenceSystem;Ljava/util/List;)V
     190: goto          201
     193: new           #12                 // class com/mongodb/client/model/geojson/MultiLineString
     196: dup
     197: aload_2
     198: invokespecial #76                 // Method com/mongodb/client/model/geojson/MultiLineString."<init>":(Ljava/util/List;)V
     201: areturn

  private static com.mongodb.client.model.geojson.GeometryCollection decodeGeometryCollection(org.bson.BsonReader);
    Code:
       0: aconst_null
       1: astore_1
       2: aconst_null
       3: astore_2
       4: aconst_null
       5: astore_3
       6: aload_0
       7: invokeinterface #23,  1           // InterfaceMethod org/bson/BsonReader.readStartDocument:()V
      12: aload_0
      13: invokeinterface #24,  1           // InterfaceMethod org/bson/BsonReader.readBsonType:()Lorg/bson/BsonType;
      18: getstatic     #25                 // Field org/bson/BsonType.END_OF_DOCUMENT:Lorg/bson/BsonType;
      21: if_acmpeq     113
      24: aload_0
      25: invokeinterface #26,  1           // InterfaceMethod org/bson/BsonReader.readName:()Ljava/lang/String;
      30: astore        4
      32: aload         4
      34: ldc           #27                 // String type
      36: invokevirtual #28                 // Method java/lang/String.equals:(Ljava/lang/Object;)Z
      39: ifeq          52
      42: aload_0
      43: invokeinterface #29,  1           // InterfaceMethod org/bson/BsonReader.readString:()Ljava/lang/String;
      48: astore_1
      49: goto          110
      52: aload         4
      54: ldc           #77                 // String geometries
      56: invokevirtual #28                 // Method java/lang/String.equals:(Ljava/lang/Object;)Z
      59: ifeq          70
      62: aload_0
      63: invokestatic  #78                 // Method decodeGeometries:(Lorg/bson/BsonReader;)Ljava/util/List;
      66: astore_2
      67: goto          110
      70: aload         4
      72: ldc           #32                 // String crs
      74: invokevirtual #28                 // Method java/lang/String.equals:(Ljava/lang/Object;)Z
      77: ifeq          88
      80: aload_0
      81: invokestatic  #33                 // Method decodeCoordinateReferenceSystem:(Lorg/bson/BsonReader;)Lcom/mongodb/client/model/geojson/CoordinateReferenceSystem;
      84: astore_3
      85: goto          110
      88: new           #18                 // class org/bson/codecs/configuration/CodecConfigurationException
      91: dup
      92: ldc           #50                 // String Unexpected key \'%s\' found when decoding a GeoJSON Polygon
      94: iconst_1
      95: anewarray     #20                 // class java/lang/Object
      98: dup
      99: iconst_0
     100: aload         4
     102: aastore
     103: invokestatic  #21                 // Method java/lang/String.format:(Ljava/lang/String;[Ljava/lang/Object;)Ljava/lang/String;
     106: invokespecial #22                 // Method org/bson/codecs/configuration/CodecConfigurationException."<init>":(Ljava/lang/String;)V
     109: athrow
     110: goto          12
     113: aload_0
     114: invokeinterface #35,  1           // InterfaceMethod org/bson/BsonReader.readEndDocument:()V
     119: aload_1
     120: ifnonnull     133
     123: new           #18                 // class org/bson/codecs/configuration/CodecConfigurationException
     126: dup
     127: ldc           #79                 // String Invalid GeometryCollection, document contained no type information.
     129: invokespecial #22                 // Method org/bson/codecs/configuration/CodecConfigurationException."<init>":(Ljava/lang/String;)V
     132: athrow
     133: aload_1
     134: ldc           #80                 // String GeometryCollection
     136: invokevirtual #28                 // Method java/lang/String.equals:(Ljava/lang/Object;)Z
     139: ifne          163
     142: new           #18                 // class org/bson/codecs/configuration/CodecConfigurationException
     145: dup
     146: ldc           #81                 // String Invalid GeometryCollection, found type \'%s\'.
     148: iconst_1
     149: anewarray     #20                 // class java/lang/Object
     152: dup
     153: iconst_0
     154: aload_1
     155: aastore
     156: invokestatic  #21                 // Method java/lang/String.format:(Ljava/lang/String;[Ljava/lang/Object;)Ljava/lang/String;
     159: invokespecial #22                 // Method org/bson/codecs/configuration/CodecConfigurationException."<init>":(Ljava/lang/String;)V
     162: athrow
     163: aload_2
     164: ifnonnull     177
     167: new           #18                 // class org/bson/codecs/configuration/CodecConfigurationException
     170: dup
     171: ldc           #82                 // String Invalid GeometryCollection, missing geometries.
     173: invokespecial #22                 // Method org/bson/codecs/configuration/CodecConfigurationException."<init>":(Ljava/lang/String;)V
     176: athrow
     177: aload_3
     178: ifnull        193
     181: new           #14                 // class com/mongodb/client/model/geojson/GeometryCollection
     184: dup
     185: aload_3
     186: aload_2
     187: invokespecial #83                 // Method com/mongodb/client/model/geojson/GeometryCollection."<init>":(Lcom/mongodb/client/model/geojson/CoordinateReferenceSystem;Ljava/util/List;)V
     190: goto          201
     193: new           #14                 // class com/mongodb/client/model/geojson/GeometryCollection
     196: dup
     197: aload_2
     198: invokespecial #84                 // Method com/mongodb/client/model/geojson/GeometryCollection."<init>":(Ljava/util/List;)V
     201: areturn

  private static java.util.List<? extends com.mongodb.client.model.geojson.Geometry> decodeGeometries(org.bson.BsonReader);
    Code:
       0: aload_0
       1: invokestatic  #85                 // Method validateIsArray:(Lorg/bson/BsonReader;)V
       4: aload_0
       5: invokeinterface #86,  1           // InterfaceMethod org/bson/BsonReader.readStartArray:()V
      10: new           #87                 // class java/util/ArrayList
      13: dup
      14: invokespecial #88                 // Method java/util/ArrayList."<init>":()V
      17: astore_1
      18: aload_0
      19: invokeinterface #24,  1           // InterfaceMethod org/bson/BsonReader.readBsonType:()Lorg/bson/BsonType;
      24: getstatic     #25                 // Field org/bson/BsonType.END_OF_DOCUMENT:Lorg/bson/BsonType;
      27: if_acmpeq     46
      30: aload_0
      31: invokestatic  #17                 // Method decodeGeometry:(Lorg/bson/BsonReader;)Lcom/mongodb/client/model/geojson/Geometry;
      34: astore_2
      35: aload_1
      36: aload_2
      37: invokeinterface #89,  2           // InterfaceMethod java/util/List.add:(Ljava/lang/Object;)Z
      42: pop
      43: goto          18
      46: aload_0
      47: invokeinterface #90,  1           // InterfaceMethod org/bson/BsonReader.readEndArray:()V
      52: aload_1
      53: areturn

  private static com.mongodb.client.model.geojson.Geometry decodeGeometry(org.bson.BsonReader);
    Code:
       0: aconst_null
       1: astore_1
       2: aload_0
       3: invokeinterface #91,  1           // InterfaceMethod org/bson/BsonReader.getMark:()Lorg/bson/BsonReaderMark;
       8: astore_2
       9: aload_0
      10: invokestatic  #92                 // Method validateIsDocument:(Lorg/bson/BsonReader;)V
      13: aload_0
      14: invokeinterface #23,  1           // InterfaceMethod org/bson/BsonReader.readStartDocument:()V
      19: aload_0
      20: invokeinterface #24,  1           // InterfaceMethod org/bson/BsonReader.readBsonType:()Lorg/bson/BsonType;
      25: getstatic     #25                 // Field org/bson/BsonType.END_OF_DOCUMENT:Lorg/bson/BsonType;
      28: if_acmpeq     66
      31: aload_0
      32: invokeinterface #26,  1           // InterfaceMethod org/bson/BsonReader.readName:()Ljava/lang/String;
      37: astore_3
      38: aload_3
      39: ldc           #27                 // String type
      41: invokevirtual #28                 // Method java/lang/String.equals:(Ljava/lang/Object;)Z
      44: ifeq          57
      47: aload_0
      48: invokeinterface #29,  1           // InterfaceMethod org/bson/BsonReader.readString:()Ljava/lang/String;
      53: astore_1
      54: goto          66
      57: aload_0
      58: invokeinterface #93,  1           // InterfaceMethod org/bson/BsonReader.skipValue:()V
      63: goto          19
      66: aload_2
      67: invokeinterface #94,  1           // InterfaceMethod org/bson/BsonReaderMark.reset:()V
      72: aload_1
      73: ifnonnull     86
      76: new           #18                 // class org/bson/codecs/configuration/CodecConfigurationException
      79: dup
      80: ldc           #95                 // String Invalid Geometry item, document contained no type information.
      82: invokespecial #22                 // Method org/bson/codecs/configuration/CodecConfigurationException."<init>":(Ljava/lang/String;)V
      85: athrow
      86: aconst_null
      87: astore_3
      88: aload_1
      89: ldc           #37                 // String Point
      91: invokevirtual #28                 // Method java/lang/String.equals:(Ljava/lang/Object;)Z
      94: ifeq          105
      97: aload_0
      98: invokestatic  #3                  // Method decodePoint:(Lorg/bson/BsonReader;)Lcom/mongodb/client/model/geojson/Point;
     101: astore_3
     102: goto          228
     105: aload_1
     106: ldc           #44                 // String MultiPoint
     108: invokevirtual #28                 // Method java/lang/String.equals:(Ljava/lang/Object;)Z
     111: ifeq          122
     114: aload_0
     115: invokestatic  #5                  // Method decodeMultiPoint:(Lorg/bson/BsonReader;)Lcom/mongodb/client/model/geojson/MultiPoint;
     118: astore_3
     119: goto          228
     122: aload_1
     123: ldc           #52                 // String Polygon
     125: invokevirtual #28                 // Method java/lang/String.equals:(Ljava/lang/Object;)Z
     128: ifeq          139
     131: aload_0
     132: invokestatic  #7                  // Method decodePolygon:(Lorg/bson/BsonReader;)Lcom/mongodb/client/model/geojson/Polygon;
     135: astore_3
     136: goto          228
     139: aload_1
     140: ldc           #59                 // String MultiPolygon
     142: invokevirtual #28                 // Method java/lang/String.equals:(Ljava/lang/Object;)Z
     145: ifeq          156
     148: aload_0
     149: invokestatic  #9                  // Method decodeMultiPolygon:(Lorg/bson/BsonReader;)Lcom/mongodb/client/model/geojson/MultiPolygon;
     152: astore_3
     153: goto          228
     156: aload_1
     157: ldc           #65                 // String LineString
     159: invokevirtual #28                 // Method java/lang/String.equals:(Ljava/lang/Object;)Z
     162: ifeq          173
     165: aload_0
     166: invokestatic  #11                 // Method decodeLineString:(Lorg/bson/BsonReader;)Lcom/mongodb/client/model/geojson/LineString;
     169: astore_3
     170: goto          228
     173: aload_1
     174: ldc           #72                 // String MultiLineString
     176: invokevirtual #28                 // Method java/lang/String.equals:(Ljava/lang/Object;)Z
     179: ifeq          190
     182: aload_0
     183: invokestatic  #13                 // Method decodeMultiLineString:(Lorg/bson/BsonReader;)Lcom/mongodb/client/model/geojson/MultiLineString;
     186: astore_3
     187: goto          228
     190: aload_1
     191: ldc           #80                 // String GeometryCollection
     193: invokevirtual #28                 // Method java/lang/String.equals:(Ljava/lang/Object;)Z
     196: ifeq          207
     199: aload_0
     200: invokestatic  #15                 // Method decodeGeometryCollection:(Lorg/bson/BsonReader;)Lcom/mongodb/client/model/geojson/GeometryCollection;
     203: astore_3
     204: goto          228
     207: new           #18                 // class org/bson/codecs/configuration/CodecConfigurationException
     210: dup
     211: ldc           #96                 // String Invalid Geometry item, found type \'%s\'.
     213: iconst_1
     214: anewarray     #20                 // class java/lang/Object
     217: dup
     218: iconst_0
     219: aload_1
     220: aastore
     221: invokestatic  #21                 // Method java/lang/String.format:(Ljava/lang/String;[Ljava/lang/Object;)Ljava/lang/String;
     224: invokespecial #22                 // Method org/bson/codecs/configuration/CodecConfigurationException."<init>":(Ljava/lang/String;)V
     227: athrow
     228: aload_3
     229: areturn

  private static com.mongodb.client.model.geojson.PolygonCoordinates decodePolygonCoordinates(org.bson.BsonReader);
    Code:
       0: aload_0
       1: invokestatic  #85                 // Method validateIsArray:(Lorg/bson/BsonReader;)V
       4: aload_0
       5: invokeinterface #86,  1           // InterfaceMethod org/bson/BsonReader.readStartArray:()V
      10: new           #87                 // class java/util/ArrayList
      13: dup
      14: invokespecial #88                 // Method java/util/ArrayList."<init>":()V
      17: astore_1
      18: aload_0
      19: invokeinterface #24,  1           // InterfaceMethod org/bson/BsonReader.readBsonType:()Lorg/bson/BsonType;
      24: getstatic     #25                 // Field org/bson/BsonType.END_OF_DOCUMENT:Lorg/bson/BsonType;
      27: if_acmpeq     44
      30: aload_1
      31: aload_0
      32: invokestatic  #42                 // Method decodeCoordinates:(Lorg/bson/BsonReader;)Ljava/util/List;
      35: invokeinterface #89,  2           // InterfaceMethod java/util/List.add:(Ljava/lang/Object;)Z
      40: pop
      41: goto          18
      44: aload_0
      45: invokeinterface #90,  1           // InterfaceMethod org/bson/BsonReader.readEndArray:()V
      50: aload_1
      51: invokeinterface #97,  1           // InterfaceMethod java/util/List.isEmpty:()Z
      56: ifeq          69
      59: new           #18                 // class org/bson/codecs/configuration/CodecConfigurationException
      62: dup
      63: ldc           #98                 // String Invalid Polygon no coordinates.
      65: invokespecial #22                 // Method org/bson/codecs/configuration/CodecConfigurationException."<init>":(Ljava/lang/String;)V
      68: athrow
      69: aload_1
      70: iconst_0
      71: invokeinterface #99,  2           // InterfaceMethod java/util/List.remove:(I)Ljava/lang/Object;
      76: checkcast     #100                // class java/util/List
      79: astore_2
      80: aload_1
      81: aload_1
      82: invokeinterface #101,  1          // InterfaceMethod java/util/List.size:()I
      87: anewarray     #87                 // class java/util/ArrayList
      90: invokeinterface #102,  2          // InterfaceMethod java/util/List.toArray:([Ljava/lang/Object;)[Ljava/lang/Object;
      95: checkcast     #103                // class "[Ljava/util/ArrayList;"
      98: astore_3
      99: new           #104                // class com/mongodb/client/model/geojson/PolygonCoordinates
     102: dup
     103: aload_2
     104: aload_3
     105: invokespecial #105                // Method com/mongodb/client/model/geojson/PolygonCoordinates."<init>":(Ljava/util/List;[Ljava/util/List;)V
     108: areturn
     109: astore        4
     111: new           #18                 // class org/bson/codecs/configuration/CodecConfigurationException
     114: dup
     115: ldc           #107                // String Invalid Polygon: %s
     117: iconst_1
     118: anewarray     #20                 // class java/lang/Object
     121: dup
     122: iconst_0
     123: aload         4
     125: invokevirtual #108                // Method java/lang/IllegalArgumentException.getMessage:()Ljava/lang/String;
     128: aastore
     129: invokestatic  #21                 // Method java/lang/String.format:(Ljava/lang/String;[Ljava/lang/Object;)Ljava/lang/String;
     132: invokespecial #22                 // Method org/bson/codecs/configuration/CodecConfigurationException."<init>":(Ljava/lang/String;)V
     135: athrow
    Exception table:
       from    to  target type
          99   108   109   Class java/lang/IllegalArgumentException

  private static java.util.List<com.mongodb.client.model.geojson.PolygonCoordinates> decodeMultiPolygonCoordinates(org.bson.BsonReader);
    Code:
       0: aload_0
       1: invokestatic  #85                 // Method validateIsArray:(Lorg/bson/BsonReader;)V
       4: aload_0
       5: invokeinterface #86,  1           // InterfaceMethod org/bson/BsonReader.readStartArray:()V
      10: new           #87                 // class java/util/ArrayList
      13: dup
      14: invokespecial #88                 // Method java/util/ArrayList."<init>":()V
      17: astore_1
      18: aload_0
      19: invokeinterface #24,  1           // InterfaceMethod org/bson/BsonReader.readBsonType:()Lorg/bson/BsonType;
      24: getstatic     #25                 // Field org/bson/BsonType.END_OF_DOCUMENT:Lorg/bson/BsonType;
      27: if_acmpeq     44
      30: aload_1
      31: aload_0
      32: invokestatic  #49                 // Method decodePolygonCoordinates:(Lorg/bson/BsonReader;)Lcom/mongodb/client/model/geojson/PolygonCoordinates;
      35: invokeinterface #89,  2           // InterfaceMethod java/util/List.add:(Ljava/lang/Object;)Z
      40: pop
      41: goto          18
      44: aload_0
      45: invokeinterface #90,  1           // InterfaceMethod org/bson/BsonReader.readEndArray:()V
      50: aload_1
      51: invokeinterface #97,  1           // InterfaceMethod java/util/List.isEmpty:()Z
      56: ifeq          69
      59: new           #18                 // class org/bson/codecs/configuration/CodecConfigurationException
      62: dup
      63: ldc           #109                // String Invalid MultiPolygon no coordinates.
      65: invokespecial #22                 // Method org/bson/codecs/configuration/CodecConfigurationException."<init>":(Ljava/lang/String;)V
      68: athrow
      69: aload_1
      70: areturn

  private static java.util.List<com.mongodb.client.model.geojson.Position> decodeCoordinates(org.bson.BsonReader);
    Code:
       0: aload_0
       1: invokestatic  #85                 // Method validateIsArray:(Lorg/bson/BsonReader;)V
       4: aload_0
       5: invokeinterface #86,  1           // InterfaceMethod org/bson/BsonReader.readStartArray:()V
      10: new           #87                 // class java/util/ArrayList
      13: dup
      14: invokespecial #88                 // Method java/util/ArrayList."<init>":()V
      17: astore_1
      18: aload_0
      19: invokeinterface #24,  1           // InterfaceMethod org/bson/BsonReader.readBsonType:()Lorg/bson/BsonType;
      24: getstatic     #25                 // Field org/bson/BsonType.END_OF_DOCUMENT:Lorg/bson/BsonType;
      27: if_acmpeq     44
      30: aload_1
      31: aload_0
      32: invokestatic  #31                 // Method decodePosition:(Lorg/bson/BsonReader;)Lcom/mongodb/client/model/geojson/Position;
      35: invokeinterface #89,  2           // InterfaceMethod java/util/List.add:(Ljava/lang/Object;)Z
      40: pop
      41: goto          18
      44: aload_0
      45: invokeinterface #90,  1           // InterfaceMethod org/bson/BsonReader.readEndArray:()V
      50: aload_1
      51: areturn

  private static java.util.List<java.util.List<com.mongodb.client.model.geojson.Position>> decodeMultiCoordinates(org.bson.BsonReader);
    Code:
       0: aload_0
       1: invokestatic  #85                 // Method validateIsArray:(Lorg/bson/BsonReader;)V
       4: aload_0
       5: invokeinterface #86,  1           // InterfaceMethod org/bson/BsonReader.readStartArray:()V
      10: new           #87                 // class java/util/ArrayList
      13: dup
      14: invokespecial #88                 // Method java/util/ArrayList."<init>":()V
      17: astore_1
      18: aload_0
      19: invokeinterface #24,  1           // InterfaceMethod org/bson/BsonReader.readBsonType:()Lorg/bson/BsonType;
      24: getstatic     #25                 // Field org/bson/BsonType.END_OF_DOCUMENT:Lorg/bson/BsonType;
      27: if_acmpeq     44
      30: aload_1
      31: aload_0
      32: invokestatic  #42                 // Method decodeCoordinates:(Lorg/bson/BsonReader;)Ljava/util/List;
      35: invokeinterface #89,  2           // InterfaceMethod java/util/List.add:(Ljava/lang/Object;)Z
      40: pop
      41: goto          18
      44: aload_0
      45: invokeinterface #90,  1           // InterfaceMethod org/bson/BsonReader.readEndArray:()V
      50: aload_1
      51: areturn

  private static com.mongodb.client.model.geojson.Position decodePosition(org.bson.BsonReader);
    Code:
       0: aload_0
       1: invokestatic  #85                 // Method validateIsArray:(Lorg/bson/BsonReader;)V
       4: aload_0
       5: invokeinterface #86,  1           // InterfaceMethod org/bson/BsonReader.readStartArray:()V
      10: new           #87                 // class java/util/ArrayList
      13: dup
      14: invokespecial #88                 // Method java/util/ArrayList."<init>":()V
      17: astore_1
      18: aload_0
      19: invokeinterface #24,  1           // InterfaceMethod org/bson/BsonReader.readBsonType:()Lorg/bson/BsonType;
      24: getstatic     #25                 // Field org/bson/BsonType.END_OF_DOCUMENT:Lorg/bson/BsonType;
      27: if_acmpeq     71
      30: aload_0
      31: invokeinterface #110,  1          // InterfaceMethod org/bson/BsonReader.getCurrentBsonType:()Lorg/bson/BsonType;
      36: getstatic     #111                // Field org/bson/BsonType.DOUBLE:Lorg/bson/BsonType;
      39: if_acmpeq     52
      42: new           #18                 // class org/bson/codecs/configuration/CodecConfigurationException
      45: dup
      46: ldc           #112                // String Invalid position
      48: invokespecial #22                 // Method org/bson/codecs/configuration/CodecConfigurationException."<init>":(Ljava/lang/String;)V
      51: athrow
      52: aload_1
      53: aload_0
      54: invokeinterface #113,  1          // InterfaceMethod org/bson/BsonReader.readDouble:()D
      59: invokestatic  #114                // Method java/lang/Double.valueOf:(D)Ljava/lang/Double;
      62: invokeinterface #89,  2           // InterfaceMethod java/util/List.add:(Ljava/lang/Object;)Z
      67: pop
      68: goto          18
      71: aload_0
      72: invokeinterface #90,  1           // InterfaceMethod org/bson/BsonReader.readEndArray:()V
      77: new           #115                // class com/mongodb/client/model/geojson/Position
      80: dup
      81: aload_1
      82: invokespecial #116                // Method com/mongodb/client/model/geojson/Position."<init>":(Ljava/util/List;)V
      85: areturn
      86: astore_2
      87: new           #18                 // class org/bson/codecs/configuration/CodecConfigurationException
      90: dup
      91: ldc           #117                // String Invalid Position: %s
      93: iconst_1
      94: anewarray     #20                 // class java/lang/Object
      97: dup
      98: iconst_0
      99: aload_2
     100: invokevirtual #108                // Method java/lang/IllegalArgumentException.getMessage:()Ljava/lang/String;
     103: aastore
     104: invokestatic  #21                 // Method java/lang/String.format:(Ljava/lang/String;[Ljava/lang/Object;)Ljava/lang/String;
     107: invokespecial #22                 // Method org/bson/codecs/configuration/CodecConfigurationException."<init>":(Ljava/lang/String;)V
     110: athrow
    Exception table:
       from    to  target type
          77    85    86   Class java/lang/IllegalArgumentException

  static com.mongodb.client.model.geojson.CoordinateReferenceSystem decodeCoordinateReferenceSystem(org.bson.BsonReader);
    Code:
       0: aconst_null
       1: astore_1
       2: aload_0
       3: invokestatic  #92                 // Method validateIsDocument:(Lorg/bson/BsonReader;)V
       6: aload_0
       7: invokeinterface #23,  1           // InterfaceMethod org/bson/BsonReader.readStartDocument:()V
      12: aload_0
      13: invokeinterface #24,  1           // InterfaceMethod org/bson/BsonReader.readBsonType:()Lorg/bson/BsonType;
      18: getstatic     #25                 // Field org/bson/BsonType.END_OF_DOCUMENT:Lorg/bson/BsonType;
      21: if_acmpeq     121
      24: aload_0
      25: invokeinterface #26,  1           // InterfaceMethod org/bson/BsonReader.readName:()Ljava/lang/String;
      30: astore_2
      31: aload_2
      32: ldc           #27                 // String type
      34: invokevirtual #28                 // Method java/lang/String.equals:(Ljava/lang/Object;)Z
      37: ifeq          80
      40: aload_0
      41: invokeinterface #29,  1           // InterfaceMethod org/bson/BsonReader.readString:()Ljava/lang/String;
      46: astore_3
      47: aload_3
      48: ldc           #118                // String name
      50: invokevirtual #28                 // Method java/lang/String.equals:(Ljava/lang/Object;)Z
      53: ifne          77
      56: new           #18                 // class org/bson/codecs/configuration/CodecConfigurationException
      59: dup
      60: ldc           #119                // String Unsupported CoordinateReferenceSystem \'%s\'.
      62: iconst_1
      63: anewarray     #20                 // class java/lang/Object
      66: dup
      67: iconst_0
      68: aload_3
      69: aastore
      70: invokestatic  #21                 // Method java/lang/String.format:(Ljava/lang/String;[Ljava/lang/Object;)Ljava/lang/String;
      73: invokespecial #22                 // Method org/bson/codecs/configuration/CodecConfigurationException."<init>":(Ljava/lang/String;)V
      76: athrow
      77: goto          118
      80: aload_2
      81: ldc           #120                // String properties
      83: invokevirtual #28                 // Method java/lang/String.equals:(Ljava/lang/Object;)Z
      86: ifeq          97
      89: aload_0
      90: invokestatic  #121                // Method decodeCoordinateReferenceSystemProperties:(Lorg/bson/BsonReader;)Ljava/lang/String;
      93: astore_1
      94: goto          118
      97: new           #18                 // class org/bson/codecs/configuration/CodecConfigurationException
     100: dup
     101: ldc           #122                // String Found invalid key \'%s\' in the CoordinateReferenceSystem.
     103: iconst_1
     104: anewarray     #20                 // class java/lang/Object
     107: dup
     108: iconst_0
     109: aload_2
     110: aastore
     111: invokestatic  #21                 // Method java/lang/String.format:(Ljava/lang/String;[Ljava/lang/Object;)Ljava/lang/String;
     114: invokespecial #22                 // Method org/bson/codecs/configuration/CodecConfigurationException."<init>":(Ljava/lang/String;)V
     117: athrow
     118: goto          12
     121: aload_0
     122: invokeinterface #35,  1           // InterfaceMethod org/bson/BsonReader.readEndDocument:()V
     127: aload_1
     128: ifnull        142
     131: new           #123                // class com/mongodb/client/model/geojson/NamedCoordinateReferenceSystem
     134: dup
     135: aload_1
     136: invokespecial #124                // Method com/mongodb/client/model/geojson/NamedCoordinateReferenceSystem."<init>":(Ljava/lang/String;)V
     139: goto          143
     142: aconst_null
     143: areturn

  private static java.lang.String decodeCoordinateReferenceSystemProperties(org.bson.BsonReader);
    Code:
       0: aconst_null
       1: astore_1
       2: aload_0
       3: invokestatic  #92                 // Method validateIsDocument:(Lorg/bson/BsonReader;)V
       6: aload_0
       7: invokeinterface #23,  1           // InterfaceMethod org/bson/BsonReader.readStartDocument:()V
      12: aload_0
      13: invokeinterface #24,  1           // InterfaceMethod org/bson/BsonReader.readBsonType:()Lorg/bson/BsonType;
      18: getstatic     #25                 // Field org/bson/BsonType.END_OF_DOCUMENT:Lorg/bson/BsonType;
      21: if_acmpeq     74
      24: aload_0
      25: invokeinterface #26,  1           // InterfaceMethod org/bson/BsonReader.readName:()Ljava/lang/String;
      30: astore_2
      31: aload_2
      32: ldc           #118                // String name
      34: invokevirtual #28                 // Method java/lang/String.equals:(Ljava/lang/Object;)Z
      37: ifeq          50
      40: aload_0
      41: invokeinterface #29,  1           // InterfaceMethod org/bson/BsonReader.readString:()Ljava/lang/String;
      46: astore_1
      47: goto          71
      50: new           #18                 // class org/bson/codecs/configuration/CodecConfigurationException
      53: dup
      54: ldc           #122                // String Found invalid key \'%s\' in the CoordinateReferenceSystem.
      56: iconst_1
      57: anewarray     #20                 // class java/lang/Object
      60: dup
      61: iconst_0
      62: aload_2
      63: aastore
      64: invokestatic  #21                 // Method java/lang/String.format:(Ljava/lang/String;[Ljava/lang/Object;)Ljava/lang/String;
      67: invokespecial #22                 // Method org/bson/codecs/configuration/CodecConfigurationException."<init>":(Ljava/lang/String;)V
      70: athrow
      71: goto          12
      74: aload_0
      75: invokeinterface #35,  1           // InterfaceMethod org/bson/BsonReader.readEndDocument:()V
      80: aload_1
      81: ifnonnull     94
      84: new           #18                 // class org/bson/codecs/configuration/CodecConfigurationException
      87: dup
      88: ldc           #125                // String Found invalid properties in the CoordinateReferenceSystem.
      90: invokespecial #22                 // Method org/bson/codecs/configuration/CodecConfigurationException."<init>":(Ljava/lang/String;)V
      93: athrow
      94: aload_1
      95: areturn

  private static void validateIsDocument(org.bson.BsonReader);
    Code:
       0: aload_0
       1: invokeinterface #110,  1          // InterfaceMethod org/bson/BsonReader.getCurrentBsonType:()Lorg/bson/BsonType;
       6: astore_1
       7: aload_1
       8: ifnonnull     18
      11: aload_0
      12: invokeinterface #24,  1           // InterfaceMethod org/bson/BsonReader.readBsonType:()Lorg/bson/BsonType;
      17: astore_1
      18: aload_1
      19: getstatic     #126                // Field org/bson/BsonType.DOCUMENT:Lorg/bson/BsonType;
      22: invokevirtual #127                // Method org/bson/BsonType.equals:(Ljava/lang/Object;)Z
      25: ifne          38
      28: new           #18                 // class org/bson/codecs/configuration/CodecConfigurationException
      31: dup
      32: ldc           #128                // String Invalid BsonType expecting a Document
      34: invokespecial #22                 // Method org/bson/codecs/configuration/CodecConfigurationException."<init>":(Ljava/lang/String;)V
      37: athrow
      38: return

  private static void validateIsArray(org.bson.BsonReader);
    Code:
       0: aload_0
       1: invokeinterface #110,  1          // InterfaceMethod org/bson/BsonReader.getCurrentBsonType:()Lorg/bson/BsonType;
       6: getstatic     #129                // Field org/bson/BsonType.ARRAY:Lorg/bson/BsonType;
       9: if_acmpeq     22
      12: new           #18                 // class org/bson/codecs/configuration/CodecConfigurationException
      15: dup
      16: ldc           #130                // String Invalid BsonType expecting an Array
      18: invokespecial #22                 // Method org/bson/codecs/configuration/CodecConfigurationException."<init>":(Ljava/lang/String;)V
      21: athrow
      22: return

  private com.mongodb.client.model.geojson.codecs.GeometryDecoderHelper();
    Code:
       0: aload_0
       1: invokespecial #131                // Method java/lang/Object."<init>":()V
       4: return
}
