Compiled from "ApplyProjectInfo.java"
public class io.dekorate.project.ApplyProjectInfo extends io.dekorate.kubernetes.config.Configurator<io.dekorate.kubernetes.config.ConfigurationFluent> {
  private static final java.lang.String APP_NAME;

  private static final java.lang.String APP_VERSION;

  private final io.dekorate.project.Project project;

  public io.dekorate.project.ApplyProjectInfo(io.dekorate.project.Project);
    Code:
       0: aload_0
       1: invokespecial #1                  // Method io/dekorate/kubernetes/config/Configurator."<init>":()V
       4: aload_0
       5: aload_1
       6: putfield      #2                  // Field project:Lio/dekorate/project/Project;
       9: return

  public void visit(io.dekorate.kubernetes.config.ConfigurationFluent);
    Code:
       0: aload_1
       1: aload_0
       2: getfield      #2                  // Field project:Lio/dekorate/project/Project;
       5: invokeinterface #3,  2            // InterfaceMethod io/dekorate/kubernetes/config/ConfigurationFluent.withProject:(Lio/dekorate/project/Project;)Lio/dekorate/kubernetes/config/ConfigurationFluent;
      10: pop
      11: aload_1
      12: instanceof    #4                  // class io/dekorate/kubernetes/config/ApplicationConfigurationFluent
      15: ifeq          110
      18: aload_1
      19: checkcast     #4                  // class io/dekorate/kubernetes/config/ApplicationConfigurationFluent
      22: astore_2
      23: aload_2
      24: ldc           #6                  // String app.name
      26: aload_2
      27: invokeinterface #7,  1            // InterfaceMethod io/dekorate/kubernetes/config/ApplicationConfigurationFluent.getName:()Ljava/lang/String;
      32: invokestatic  #8                  // Method io/dekorate/utils/Strings.isNotNullOrEmpty:(Ljava/lang/String;)Z
      35: ifeq          47
      38: aload_2
      39: invokeinterface #7,  1            // InterfaceMethod io/dekorate/kubernetes/config/ApplicationConfigurationFluent.getName:()Ljava/lang/String;
      44: goto          57
      47: aload_0
      48: getfield      #2                  // Field project:Lio/dekorate/project/Project;
      51: invokevirtual #9                  // Method io/dekorate/project/Project.getBuildInfo:()Lio/dekorate/project/BuildInfo;
      54: invokevirtual #10                 // Method io/dekorate/project/BuildInfo.getName:()Ljava/lang/String;
      57: invokestatic  #11                 // Method java/lang/System.getProperty:(Ljava/lang/String;Ljava/lang/String;)Ljava/lang/String;
      60: invokeinterface #12,  2           // InterfaceMethod io/dekorate/kubernetes/config/ApplicationConfigurationFluent.withName:(Ljava/lang/String;)Lio/dekorate/kubernetes/config/ApplicationConfigurationFluent;
      65: ldc           #13                 // String app.version
      67: aload_2
      68: invokeinterface #14,  1           // InterfaceMethod io/dekorate/kubernetes/config/ApplicationConfigurationFluent.getVersion:()Ljava/lang/String;
      73: invokestatic  #8                  // Method io/dekorate/utils/Strings.isNotNullOrEmpty:(Ljava/lang/String;)Z
      76: ifeq          88
      79: aload_2
      80: invokeinterface #14,  1           // InterfaceMethod io/dekorate/kubernetes/config/ApplicationConfigurationFluent.getVersion:()Ljava/lang/String;
      85: goto          98
      88: aload_0
      89: getfield      #2                  // Field project:Lio/dekorate/project/Project;
      92: invokevirtual #9                  // Method io/dekorate/project/Project.getBuildInfo:()Lio/dekorate/project/BuildInfo;
      95: invokevirtual #15                 // Method io/dekorate/project/BuildInfo.getVersion:()Ljava/lang/String;
      98: invokestatic  #11                 // Method java/lang/System.getProperty:(Ljava/lang/String;Ljava/lang/String;)Ljava/lang/String;
     101: invokeinterface #16,  2           // InterfaceMethod io/dekorate/kubernetes/config/ApplicationConfigurationFluent.withVersion:(Ljava/lang/String;)Lio/dekorate/kubernetes/config/ApplicationConfigurationFluent;
     106: pop
     107: goto          206
     110: aload_1
     111: instanceof    #17                 // class io/dekorate/kubernetes/config/ImageConfigurationFluent
     114: ifeq          206
     117: aload_1
     118: checkcast     #17                 // class io/dekorate/kubernetes/config/ImageConfigurationFluent
     121: astore_2
     122: aload_2
     123: ldc           #6                  // String app.name
     125: aload_2
     126: invokeinterface #18,  1           // InterfaceMethod io/dekorate/kubernetes/config/ImageConfigurationFluent.getName:()Ljava/lang/String;
     131: invokestatic  #8                  // Method io/dekorate/utils/Strings.isNotNullOrEmpty:(Ljava/lang/String;)Z
     134: ifeq          146
     137: aload_2
     138: invokeinterface #18,  1           // InterfaceMethod io/dekorate/kubernetes/config/ImageConfigurationFluent.getName:()Ljava/lang/String;
     143: goto          156
     146: aload_0
     147: getfield      #2                  // Field project:Lio/dekorate/project/Project;
     150: invokevirtual #9                  // Method io/dekorate/project/Project.getBuildInfo:()Lio/dekorate/project/BuildInfo;
     153: invokevirtual #10                 // Method io/dekorate/project/BuildInfo.getName:()Ljava/lang/String;
     156: invokestatic  #11                 // Method java/lang/System.getProperty:(Ljava/lang/String;Ljava/lang/String;)Ljava/lang/String;
     159: invokeinterface #19,  2           // InterfaceMethod io/dekorate/kubernetes/config/ImageConfigurationFluent.withName:(Ljava/lang/String;)Lio/dekorate/kubernetes/config/ImageConfigurationFluent;
     164: ldc           #13                 // String app.version
     166: aload_2
     167: invokeinterface #20,  1           // InterfaceMethod io/dekorate/kubernetes/config/ImageConfigurationFluent.getVersion:()Ljava/lang/String;
     172: invokestatic  #8                  // Method io/dekorate/utils/Strings.isNotNullOrEmpty:(Ljava/lang/String;)Z
     175: ifeq          187
     178: aload_2
     179: invokeinterface #20,  1           // InterfaceMethod io/dekorate/kubernetes/config/ImageConfigurationFluent.getVersion:()Ljava/lang/String;
     184: goto          197
     187: aload_0
     188: getfield      #2                  // Field project:Lio/dekorate/project/Project;
     191: invokevirtual #9                  // Method io/dekorate/project/Project.getBuildInfo:()Lio/dekorate/project/BuildInfo;
     194: invokevirtual #15                 // Method io/dekorate/project/BuildInfo.getVersion:()Ljava/lang/String;
     197: invokestatic  #11                 // Method java/lang/System.getProperty:(Ljava/lang/String;Ljava/lang/String;)Ljava/lang/String;
     200: invokeinterface #21,  2           // InterfaceMethod io/dekorate/kubernetes/config/ImageConfigurationFluent.withVersion:(Ljava/lang/String;)Lio/dekorate/kubernetes/config/ImageConfigurationFluent;
     205: pop
     206: return

  public void visit(java.lang.Object);
    Code:
       0: aload_0
       1: aload_1
       2: checkcast     #22                 // class io/dekorate/kubernetes/config/ConfigurationFluent
       5: invokevirtual #23                 // Method visit:(Lio/dekorate/kubernetes/config/ConfigurationFluent;)V
       8: return
}
