Compiled from "CSVFileDataAdapter.java"
public class org.graylog2.lookup.adapters.CSVFileDataAdapter$Descriptor extends org.graylog2.plugin.lookup.LookupDataAdapter$Descriptor<org.graylog2.lookup.adapters.CSVFileDataAdapter$Config> {
  public org.graylog2.lookup.adapters.CSVFileDataAdapter$Descriptor();
    Code:
       0: aload_0
       1: ldc           #2                  // String csvfile
       3: ldc           #3                  // class org/graylog2/lookup/adapters/CSVFileDataAdapter$Config
       5: invokespecial #4                  // Method org/graylog2/plugin/lookup/LookupDataAdapter$Descriptor."<init>":(Ljava/lang/String;Ljava/lang/Class;)V
       8: return

  public org.graylog2.lookup.adapters.CSVFileDataAdapter$Config defaultConfiguration();
    Code:
       0: invokestatic  #5                  // Method org/graylog2/lookup/adapters/CSVFileDataAdapter$Config.builder:()Lorg/graylog2/lookup/adapters/CSVFileDataAdapter$Config$Builder;
       3: ldc           #2                  // String csvfile
       5: invokevirtual #6                  // Method org/graylog2/lookup/adapters/CSVFileDataAdapter$Config$Builder.type:(Ljava/lang/String;)Lorg/graylog2/lookup/adapters/CSVFileDataAdapter$Config$Builder;
       8: ldc           #7                  // String /etc/graylog/lookup-table.csv
      10: invokevirtual #8                  // Method org/graylog2/lookup/adapters/CSVFileDataAdapter$Config$Builder.path:(Ljava/lang/String;)Lorg/graylog2/lookup/adapters/CSVFileDataAdapter$Config$Builder;
      13: ldc           #9                  // String ,
      15: invokevirtual #10                 // Method org/graylog2/lookup/adapters/CSVFileDataAdapter$Config$Builder.separator:(Ljava/lang/String;)Lorg/graylog2/lookup/adapters/CSVFileDataAdapter$Config$Builder;
      18: ldc           #11                 // String \"
      20: invokevirtual #12                 // Method org/graylog2/lookup/adapters/CSVFileDataAdapter$Config$Builder.quotechar:(Ljava/lang/String;)Lorg/graylog2/lookup/adapters/CSVFileDataAdapter$Config$Builder;
      23: ldc           #13                 // String key
      25: invokevirtual #14                 // Method org/graylog2/lookup/adapters/CSVFileDataAdapter$Config$Builder.keyColumn:(Ljava/lang/String;)Lorg/graylog2/lookup/adapters/CSVFileDataAdapter$Config$Builder;
      28: ldc           #15                 // String value
      30: invokevirtual #16                 // Method org/graylog2/lookup/adapters/CSVFileDataAdapter$Config$Builder.valueColumn:(Ljava/lang/String;)Lorg/graylog2/lookup/adapters/CSVFileDataAdapter$Config$Builder;
      33: ldc2_w        #17                 // long 60l
      36: invokevirtual #19                 // Method org/graylog2/lookup/adapters/CSVFileDataAdapter$Config$Builder.checkInterval:(J)Lorg/graylog2/lookup/adapters/CSVFileDataAdapter$Config$Builder;
      39: iconst_0
      40: invokestatic  #20                 // Method java/lang/Boolean.valueOf:(Z)Ljava/lang/Boolean;
      43: invokevirtual #21                 // Method org/graylog2/lookup/adapters/CSVFileDataAdapter$Config$Builder.caseInsensitiveLookup:(Ljava/lang/Boolean;)Lorg/graylog2/lookup/adapters/CSVFileDataAdapter$Config$Builder;
      46: invokevirtual #22                 // Method org/graylog2/lookup/adapters/CSVFileDataAdapter$Config$Builder.build:()Lorg/graylog2/lookup/adapters/CSVFileDataAdapter$Config;
      49: areturn

  public org.graylog2.plugin.lookup.LookupDataAdapterConfiguration defaultConfiguration();
    Code:
       0: aload_0
       1: invokevirtual #23                 // Method defaultConfiguration:()Lorg/graylog2/lookup/adapters/CSVFileDataAdapter$Config;
       4: areturn
}
