Compiled from "CreateAcceleratorRequest.java"
final class software.amazon.awssdk.services.globalaccelerator.model.CreateAcceleratorRequest$BuilderImpl extends software.amazon.awssdk.services.globalaccelerator.model.GlobalAcceleratorRequest$BuilderImpl implements software.amazon.awssdk.services.globalaccelerator.model.CreateAcceleratorRequest$Builder {
  private java.lang.String name;

  private java.lang.String ipAddressType;

  private java.util.List<java.lang.String> ipAddresses;

  private java.lang.Boolean enabled;

  private java.lang.String idempotencyToken;

  private java.util.List<software.amazon.awssdk.services.globalaccelerator.model.Tag> tags;

  private software.amazon.awssdk.services.globalaccelerator.model.CreateAcceleratorRequest$BuilderImpl();
    Code:
       0: aload_0
       1: invokespecial #9                  // Method software/amazon/awssdk/services/globalaccelerator/model/GlobalAcceleratorRequest$BuilderImpl."<init>":()V
       4: aload_0
       5: invokestatic  #10                 // Method software/amazon/awssdk/core/util/DefaultSdkAutoConstructList.getInstance:()Lsoftware/amazon/awssdk/core/util/DefaultSdkAutoConstructList;
       8: putfield      #6                  // Field ipAddresses:Ljava/util/List;
      11: aload_0
      12: invokestatic  #10                 // Method software/amazon/awssdk/core/util/DefaultSdkAutoConstructList.getInstance:()Lsoftware/amazon/awssdk/core/util/DefaultSdkAutoConstructList;
      15: putfield      #3                  // Field tags:Ljava/util/List;
      18: return

  private software.amazon.awssdk.services.globalaccelerator.model.CreateAcceleratorRequest$BuilderImpl(software.amazon.awssdk.services.globalaccelerator.model.CreateAcceleratorRequest);
    Code:
       0: aload_0
       1: aload_1
       2: invokespecial #11                 // Method software/amazon/awssdk/services/globalaccelerator/model/GlobalAcceleratorRequest$BuilderImpl."<init>":(Lsoftware/amazon/awssdk/services/globalaccelerator/model/GlobalAcceleratorRequest;)V
       5: aload_0
       6: invokestatic  #10                 // Method software/amazon/awssdk/core/util/DefaultSdkAutoConstructList.getInstance:()Lsoftware/amazon/awssdk/core/util/DefaultSdkAutoConstructList;
       9: putfield      #6                  // Field ipAddresses:Ljava/util/List;
      12: aload_0
      13: invokestatic  #10                 // Method software/amazon/awssdk/core/util/DefaultSdkAutoConstructList.getInstance:()Lsoftware/amazon/awssdk/core/util/DefaultSdkAutoConstructList;
      16: putfield      #3                  // Field tags:Ljava/util/List;
      19: aload_0
      20: aload_1
      21: invokestatic  #12                 // Method software/amazon/awssdk/services/globalaccelerator/model/CreateAcceleratorRequest.access$800:(Lsoftware/amazon/awssdk/services/globalaccelerator/model/CreateAcceleratorRequest;)Ljava/lang/String;
      24: invokevirtual #13                 // Method name:(Ljava/lang/String;)Lsoftware/amazon/awssdk/services/globalaccelerator/model/CreateAcceleratorRequest$Builder;
      27: pop
      28: aload_0
      29: aload_1
      30: invokestatic  #14                 // Method software/amazon/awssdk/services/globalaccelerator/model/CreateAcceleratorRequest.access$900:(Lsoftware/amazon/awssdk/services/globalaccelerator/model/CreateAcceleratorRequest;)Ljava/lang/String;
      33: invokevirtual #15                 // Method ipAddressType:(Ljava/lang/String;)Lsoftware/amazon/awssdk/services/globalaccelerator/model/CreateAcceleratorRequest$Builder;
      36: pop
      37: aload_0
      38: aload_1
      39: invokestatic  #16                 // Method software/amazon/awssdk/services/globalaccelerator/model/CreateAcceleratorRequest.access$1000:(Lsoftware/amazon/awssdk/services/globalaccelerator/model/CreateAcceleratorRequest;)Ljava/util/List;
      42: invokevirtual #17                 // Method ipAddresses:(Ljava/util/Collection;)Lsoftware/amazon/awssdk/services/globalaccelerator/model/CreateAcceleratorRequest$Builder;
      45: pop
      46: aload_0
      47: aload_1
      48: invokestatic  #18                 // Method software/amazon/awssdk/services/globalaccelerator/model/CreateAcceleratorRequest.access$1100:(Lsoftware/amazon/awssdk/services/globalaccelerator/model/CreateAcceleratorRequest;)Ljava/lang/Boolean;
      51: invokevirtual #19                 // Method enabled:(Ljava/lang/Boolean;)Lsoftware/amazon/awssdk/services/globalaccelerator/model/CreateAcceleratorRequest$Builder;
      54: pop
      55: aload_0
      56: aload_1
      57: invokestatic  #20                 // Method software/amazon/awssdk/services/globalaccelerator/model/CreateAcceleratorRequest.access$1200:(Lsoftware/amazon/awssdk/services/globalaccelerator/model/CreateAcceleratorRequest;)Ljava/lang/String;
      60: invokevirtual #21                 // Method idempotencyToken:(Ljava/lang/String;)Lsoftware/amazon/awssdk/services/globalaccelerator/model/CreateAcceleratorRequest$Builder;
      63: pop
      64: aload_0
      65: aload_1
      66: invokestatic  #22                 // Method software/amazon/awssdk/services/globalaccelerator/model/CreateAcceleratorRequest.access$1300:(Lsoftware/amazon/awssdk/services/globalaccelerator/model/CreateAcceleratorRequest;)Ljava/util/List;
      69: invokevirtual #23                 // Method tags:(Ljava/util/Collection;)Lsoftware/amazon/awssdk/services/globalaccelerator/model/CreateAcceleratorRequest$Builder;
      72: pop
      73: return

  public final java.lang.String getName();
    Code:
       0: aload_0
       1: getfield      #8                  // Field name:Ljava/lang/String;
       4: areturn

  public final void setName(java.lang.String);
    Code:
       0: aload_0
       1: aload_1
       2: putfield      #8                  // Field name:Ljava/lang/String;
       5: return

  public final software.amazon.awssdk.services.globalaccelerator.model.CreateAcceleratorRequest$Builder name(java.lang.String);
    Code:
       0: aload_0
       1: aload_1
       2: putfield      #8                  // Field name:Ljava/lang/String;
       5: aload_0
       6: areturn

  public final java.lang.String getIpAddressType();
    Code:
       0: aload_0
       1: getfield      #7                  // Field ipAddressType:Ljava/lang/String;
       4: areturn

  public final void setIpAddressType(java.lang.String);
    Code:
       0: aload_0
       1: aload_1
       2: putfield      #7                  // Field ipAddressType:Ljava/lang/String;
       5: return

  public final software.amazon.awssdk.services.globalaccelerator.model.CreateAcceleratorRequest$Builder ipAddressType(java.lang.String);
    Code:
       0: aload_0
       1: aload_1
       2: putfield      #7                  // Field ipAddressType:Ljava/lang/String;
       5: aload_0
       6: areturn

  public final software.amazon.awssdk.services.globalaccelerator.model.CreateAcceleratorRequest$Builder ipAddressType(software.amazon.awssdk.services.globalaccelerator.model.IpAddressType);
    Code:
       0: aload_0
       1: aload_1
       2: ifnonnull     9
       5: aconst_null
       6: goto          13
       9: aload_1
      10: invokevirtual #24                 // Method software/amazon/awssdk/services/globalaccelerator/model/IpAddressType.toString:()Ljava/lang/String;
      13: invokevirtual #15                 // Method ipAddressType:(Ljava/lang/String;)Lsoftware/amazon/awssdk/services/globalaccelerator/model/CreateAcceleratorRequest$Builder;
      16: pop
      17: aload_0
      18: areturn

  public final java.util.Collection<java.lang.String> getIpAddresses();
    Code:
       0: aload_0
       1: getfield      #6                  // Field ipAddresses:Ljava/util/List;
       4: instanceof    #25                 // class software/amazon/awssdk/core/util/SdkAutoConstructList
       7: ifeq          12
      10: aconst_null
      11: areturn
      12: aload_0
      13: getfield      #6                  // Field ipAddresses:Ljava/util/List;
      16: areturn

  public final void setIpAddresses(java.util.Collection<java.lang.String>);
    Code:
       0: aload_0
       1: aload_1
       2: invokestatic  #26                 // Method software/amazon/awssdk/services/globalaccelerator/model/IpAddressesCopier.copy:(Ljava/util/Collection;)Ljava/util/List;
       5: putfield      #6                  // Field ipAddresses:Ljava/util/List;
       8: return

  public final software.amazon.awssdk.services.globalaccelerator.model.CreateAcceleratorRequest$Builder ipAddresses(java.util.Collection<java.lang.String>);
    Code:
       0: aload_0
       1: aload_1
       2: invokestatic  #26                 // Method software/amazon/awssdk/services/globalaccelerator/model/IpAddressesCopier.copy:(Ljava/util/Collection;)Ljava/util/List;
       5: putfield      #6                  // Field ipAddresses:Ljava/util/List;
       8: aload_0
       9: areturn

  public final software.amazon.awssdk.services.globalaccelerator.model.CreateAcceleratorRequest$Builder ipAddresses(java.lang.String...);
    Code:
       0: aload_0
       1: aload_1
       2: invokestatic  #27                 // Method java/util/Arrays.asList:([Ljava/lang/Object;)Ljava/util/List;
       5: invokevirtual #17                 // Method ipAddresses:(Ljava/util/Collection;)Lsoftware/amazon/awssdk/services/globalaccelerator/model/CreateAcceleratorRequest$Builder;
       8: pop
       9: aload_0
      10: areturn

  public final java.lang.Boolean getEnabled();
    Code:
       0: aload_0
       1: getfield      #5                  // Field enabled:Ljava/lang/Boolean;
       4: areturn

  public final void setEnabled(java.lang.Boolean);
    Code:
       0: aload_0
       1: aload_1
       2: putfield      #5                  // Field enabled:Ljava/lang/Boolean;
       5: return

  public final software.amazon.awssdk.services.globalaccelerator.model.CreateAcceleratorRequest$Builder enabled(java.lang.Boolean);
    Code:
       0: aload_0
       1: aload_1
       2: putfield      #5                  // Field enabled:Ljava/lang/Boolean;
       5: aload_0
       6: areturn

  public final java.lang.String getIdempotencyToken();
    Code:
       0: aload_0
       1: getfield      #4                  // Field idempotencyToken:Ljava/lang/String;
       4: areturn

  public final void setIdempotencyToken(java.lang.String);
    Code:
       0: aload_0
       1: aload_1
       2: putfield      #4                  // Field idempotencyToken:Ljava/lang/String;
       5: return

  public final software.amazon.awssdk.services.globalaccelerator.model.CreateAcceleratorRequest$Builder idempotencyToken(java.lang.String);
    Code:
       0: aload_0
       1: aload_1
       2: putfield      #4                  // Field idempotencyToken:Ljava/lang/String;
       5: aload_0
       6: areturn

  public final java.util.List<software.amazon.awssdk.services.globalaccelerator.model.Tag$Builder> getTags();
    Code:
       0: aload_0
       1: getfield      #3                  // Field tags:Ljava/util/List;
       4: invokestatic  #28                 // Method software/amazon/awssdk/services/globalaccelerator/model/TagsCopier.copyToBuilder:(Ljava/util/Collection;)Ljava/util/List;
       7: astore_1
       8: aload_1
       9: instanceof    #25                 // class software/amazon/awssdk/core/util/SdkAutoConstructList
      12: ifeq          17
      15: aconst_null
      16: areturn
      17: aload_1
      18: areturn

  public final void setTags(java.util.Collection<software.amazon.awssdk.services.globalaccelerator.model.Tag$BuilderImpl>);
    Code:
       0: aload_0
       1: aload_1
       2: invokestatic  #29                 // Method software/amazon/awssdk/services/globalaccelerator/model/TagsCopier.copyFromBuilder:(Ljava/util/Collection;)Ljava/util/List;
       5: putfield      #3                  // Field tags:Ljava/util/List;
       8: return

  public final software.amazon.awssdk.services.globalaccelerator.model.CreateAcceleratorRequest$Builder tags(java.util.Collection<software.amazon.awssdk.services.globalaccelerator.model.Tag>);
    Code:
       0: aload_0
       1: aload_1
       2: invokestatic  #30                 // Method software/amazon/awssdk/services/globalaccelerator/model/TagsCopier.copy:(Ljava/util/Collection;)Ljava/util/List;
       5: putfield      #3                  // Field tags:Ljava/util/List;
       8: aload_0
       9: areturn

  public final software.amazon.awssdk.services.globalaccelerator.model.CreateAcceleratorRequest$Builder tags(software.amazon.awssdk.services.globalaccelerator.model.Tag...);
    Code:
       0: aload_0
       1: aload_1
       2: invokestatic  #27                 // Method java/util/Arrays.asList:([Ljava/lang/Object;)Ljava/util/List;
       5: invokevirtual #23                 // Method tags:(Ljava/util/Collection;)Lsoftware/amazon/awssdk/services/globalaccelerator/model/CreateAcceleratorRequest$Builder;
       8: pop
       9: aload_0
      10: areturn

  public final software.amazon.awssdk.services.globalaccelerator.model.CreateAcceleratorRequest$Builder tags(java.util.function.Consumer<software.amazon.awssdk.services.globalaccelerator.model.Tag$Builder>...);
    Code:
       0: aload_0
       1: aload_1
       2: invokestatic  #31                 // InterfaceMethod java/util/stream/Stream.of:([Ljava/lang/Object;)Ljava/util/stream/Stream;
       5: invokedynamic #32,  0             // InvokeDynamic #0:apply:()Ljava/util/function/Function;
      10: invokeinterface #33,  2           // InterfaceMethod java/util/stream/Stream.map:(Ljava/util/function/Function;)Ljava/util/stream/Stream;
      15: invokestatic  #34                 // Method java/util/stream/Collectors.toList:()Ljava/util/stream/Collector;
      18: invokeinterface #35,  2           // InterfaceMethod java/util/stream/Stream.collect:(Ljava/util/stream/Collector;)Ljava/lang/Object;
      23: checkcast     #36                 // class java/util/Collection
      26: invokevirtual #23                 // Method tags:(Ljava/util/Collection;)Lsoftware/amazon/awssdk/services/globalaccelerator/model/CreateAcceleratorRequest$Builder;
      29: pop
      30: aload_0
      31: areturn

  public software.amazon.awssdk.services.globalaccelerator.model.CreateAcceleratorRequest$Builder overrideConfiguration(software.amazon.awssdk.awscore.AwsRequestOverrideConfiguration);
    Code:
       0: aload_0
       1: aload_1
       2: invokespecial #37                 // Method software/amazon/awssdk/services/globalaccelerator/model/GlobalAcceleratorRequest$BuilderImpl.overrideConfiguration:(Lsoftware/amazon/awssdk/awscore/AwsRequestOverrideConfiguration;)Lsoftware/amazon/awssdk/awscore/AwsRequest$Builder;
       5: pop
       6: aload_0
       7: areturn

  public software.amazon.awssdk.services.globalaccelerator.model.CreateAcceleratorRequest$Builder overrideConfiguration(java.util.function.Consumer<software.amazon.awssdk.awscore.AwsRequestOverrideConfiguration$Builder>);
    Code:
       0: aload_0
       1: aload_1
       2: invokespecial #38                 // Method software/amazon/awssdk/services/globalaccelerator/model/GlobalAcceleratorRequest$BuilderImpl.overrideConfiguration:(Ljava/util/function/Consumer;)Lsoftware/amazon/awssdk/awscore/AwsRequest$Builder;
       5: pop
       6: aload_0
       7: areturn

  public software.amazon.awssdk.services.globalaccelerator.model.CreateAcceleratorRequest build();
    Code:
       0: new           #39                 // class software/amazon/awssdk/services/globalaccelerator/model/CreateAcceleratorRequest
       3: dup
       4: aload_0
       5: aconst_null
       6: invokespecial #40                 // Method software/amazon/awssdk/services/globalaccelerator/model/CreateAcceleratorRequest."<init>":(Lsoftware/amazon/awssdk/services/globalaccelerator/model/CreateAcceleratorRequest$BuilderImpl;Lsoftware/amazon/awssdk/services/globalaccelerator/model/CreateAcceleratorRequest$1;)V
       9: areturn

  public java.util.List<software.amazon.awssdk.core.SdkField<?>> sdkFields();
    Code:
       0: invokestatic  #41                 // Method software/amazon/awssdk/services/globalaccelerator/model/CreateAcceleratorRequest.access$1500:()Ljava/util/List;
       3: areturn

  public software.amazon.awssdk.services.globalaccelerator.model.GlobalAcceleratorRequest build();
    Code:
       0: aload_0
       1: invokevirtual #42                 // Method build:()Lsoftware/amazon/awssdk/services/globalaccelerator/model/CreateAcceleratorRequest;
       4: areturn

  public software.amazon.awssdk.awscore.AwsRequest build();
    Code:
       0: aload_0
       1: invokevirtual #42                 // Method build:()Lsoftware/amazon/awssdk/services/globalaccelerator/model/CreateAcceleratorRequest;
       4: areturn

  public software.amazon.awssdk.awscore.AwsRequest$Builder overrideConfiguration(java.util.function.Consumer);
    Code:
       0: aload_0
       1: aload_1
       2: invokevirtual #43                 // Method overrideConfiguration:(Ljava/util/function/Consumer;)Lsoftware/amazon/awssdk/services/globalaccelerator/model/CreateAcceleratorRequest$Builder;
       5: areturn

  public software.amazon.awssdk.awscore.AwsRequest$Builder overrideConfiguration(software.amazon.awssdk.awscore.AwsRequestOverrideConfiguration);
    Code:
       0: aload_0
       1: aload_1
       2: invokevirtual #44                 // Method overrideConfiguration:(Lsoftware/amazon/awssdk/awscore/AwsRequestOverrideConfiguration;)Lsoftware/amazon/awssdk/services/globalaccelerator/model/CreateAcceleratorRequest$Builder;
       5: areturn

  public software.amazon.awssdk.core.SdkRequest build();
    Code:
       0: aload_0
       1: invokevirtual #42                 // Method build:()Lsoftware/amazon/awssdk/services/globalaccelerator/model/CreateAcceleratorRequest;
       4: areturn

  public java.lang.Object build();
    Code:
       0: aload_0
       1: invokevirtual #42                 // Method build:()Lsoftware/amazon/awssdk/services/globalaccelerator/model/CreateAcceleratorRequest;
       4: areturn

  private static software.amazon.awssdk.services.globalaccelerator.model.Tag lambda$tags$0(java.util.function.Consumer);
    Code:
       0: invokestatic  #45                 // Method software/amazon/awssdk/services/globalaccelerator/model/Tag.builder:()Lsoftware/amazon/awssdk/services/globalaccelerator/model/Tag$Builder;
       3: aload_0
       4: invokeinterface #46,  2           // InterfaceMethod software/amazon/awssdk/services/globalaccelerator/model/Tag$Builder.applyMutation:(Ljava/util/function/Consumer;)Lsoftware/amazon/awssdk/utils/builder/SdkBuilder;
       9: checkcast     #47                 // class software/amazon/awssdk/services/globalaccelerator/model/Tag$Builder
      12: invokeinterface #48,  1           // InterfaceMethod software/amazon/awssdk/services/globalaccelerator/model/Tag$Builder.build:()Ljava/lang/Object;
      17: checkcast     #49                 // class software/amazon/awssdk/services/globalaccelerator/model/Tag
      20: areturn

  static java.lang.String access$000(software.amazon.awssdk.services.globalaccelerator.model.CreateAcceleratorRequest$BuilderImpl);
    Code:
       0: aload_0
       1: getfield      #8                  // Field name:Ljava/lang/String;
       4: areturn

  static java.lang.String access$100(software.amazon.awssdk.services.globalaccelerator.model.CreateAcceleratorRequest$BuilderImpl);
    Code:
       0: aload_0
       1: getfield      #7                  // Field ipAddressType:Ljava/lang/String;
       4: areturn

  static java.util.List access$200(software.amazon.awssdk.services.globalaccelerator.model.CreateAcceleratorRequest$BuilderImpl);
    Code:
       0: aload_0
       1: getfield      #6                  // Field ipAddresses:Ljava/util/List;
       4: areturn

  static java.lang.Boolean access$300(software.amazon.awssdk.services.globalaccelerator.model.CreateAcceleratorRequest$BuilderImpl);
    Code:
       0: aload_0
       1: getfield      #5                  // Field enabled:Ljava/lang/Boolean;
       4: areturn

  static java.lang.String access$400(software.amazon.awssdk.services.globalaccelerator.model.CreateAcceleratorRequest$BuilderImpl);
    Code:
       0: aload_0
       1: getfield      #4                  // Field idempotencyToken:Ljava/lang/String;
       4: areturn

  static java.util.List access$500(software.amazon.awssdk.services.globalaccelerator.model.CreateAcceleratorRequest$BuilderImpl);
    Code:
       0: aload_0
       1: getfield      #3                  // Field tags:Ljava/util/List;
       4: areturn

  software.amazon.awssdk.services.globalaccelerator.model.CreateAcceleratorRequest$BuilderImpl(software.amazon.awssdk.services.globalaccelerator.model.CreateAcceleratorRequest, software.amazon.awssdk.services.globalaccelerator.model.CreateAcceleratorRequest$1);
    Code:
       0: aload_0
       1: aload_1
       2: invokespecial #2                  // Method "<init>":(Lsoftware/amazon/awssdk/services/globalaccelerator/model/CreateAcceleratorRequest;)V
       5: return

  software.amazon.awssdk.services.globalaccelerator.model.CreateAcceleratorRequest$BuilderImpl(software.amazon.awssdk.services.globalaccelerator.model.CreateAcceleratorRequest$1);
    Code:
       0: aload_0
       1: invokespecial #1                  // Method "<init>":()V
       4: return
}
