Compiled from "DescribeCustomRoutingAcceleratorResponse.java"
final class software.amazon.awssdk.services.globalaccelerator.model.DescribeCustomRoutingAcceleratorResponse$BuilderImpl extends software.amazon.awssdk.services.globalaccelerator.model.GlobalAcceleratorResponse$BuilderImpl implements software.amazon.awssdk.services.globalaccelerator.model.DescribeCustomRoutingAcceleratorResponse$Builder {
  private software.amazon.awssdk.services.globalaccelerator.model.CustomRoutingAccelerator accelerator;

  private software.amazon.awssdk.services.globalaccelerator.model.DescribeCustomRoutingAcceleratorResponse$BuilderImpl();
    Code:
       0: aload_0
       1: invokespecial #4                  // Method software/amazon/awssdk/services/globalaccelerator/model/GlobalAcceleratorResponse$BuilderImpl."<init>":()V
       4: return

  private software.amazon.awssdk.services.globalaccelerator.model.DescribeCustomRoutingAcceleratorResponse$BuilderImpl(software.amazon.awssdk.services.globalaccelerator.model.DescribeCustomRoutingAcceleratorResponse);
    Code:
       0: aload_0
       1: aload_1
       2: invokespecial #5                  // Method software/amazon/awssdk/services/globalaccelerator/model/GlobalAcceleratorResponse$BuilderImpl."<init>":(Lsoftware/amazon/awssdk/services/globalaccelerator/model/GlobalAcceleratorResponse;)V
       5: aload_0
       6: aload_1
       7: invokestatic  #6                  // Method software/amazon/awssdk/services/globalaccelerator/model/DescribeCustomRoutingAcceleratorResponse.access$300:(Lsoftware/amazon/awssdk/services/globalaccelerator/model/DescribeCustomRoutingAcceleratorResponse;)Lsoftware/amazon/awssdk/services/globalaccelerator/model/CustomRoutingAccelerator;
      10: invokevirtual #7                  // Method accelerator:(Lsoftware/amazon/awssdk/services/globalaccelerator/model/CustomRoutingAccelerator;)Lsoftware/amazon/awssdk/services/globalaccelerator/model/DescribeCustomRoutingAcceleratorResponse$Builder;
      13: pop
      14: return

  public final software.amazon.awssdk.services.globalaccelerator.model.CustomRoutingAccelerator$Builder getAccelerator();
    Code:
       0: aload_0
       1: getfield      #3                  // Field accelerator:Lsoftware/amazon/awssdk/services/globalaccelerator/model/CustomRoutingAccelerator;
       4: ifnull        17
       7: aload_0
       8: getfield      #3                  // Field accelerator:Lsoftware/amazon/awssdk/services/globalaccelerator/model/CustomRoutingAccelerator;
      11: invokevirtual #8                  // Method software/amazon/awssdk/services/globalaccelerator/model/CustomRoutingAccelerator.toBuilder:()Lsoftware/amazon/awssdk/services/globalaccelerator/model/CustomRoutingAccelerator$Builder;
      14: goto          18
      17: aconst_null
      18: areturn

  public final void setAccelerator(software.amazon.awssdk.services.globalaccelerator.model.CustomRoutingAccelerator$BuilderImpl);
    Code:
       0: aload_0
       1: aload_1
       2: ifnull        12
       5: aload_1
       6: invokevirtual #9                  // Method software/amazon/awssdk/services/globalaccelerator/model/CustomRoutingAccelerator$BuilderImpl.build:()Lsoftware/amazon/awssdk/services/globalaccelerator/model/CustomRoutingAccelerator;
       9: goto          13
      12: aconst_null
      13: putfield      #3                  // Field accelerator:Lsoftware/amazon/awssdk/services/globalaccelerator/model/CustomRoutingAccelerator;
      16: return

  public final software.amazon.awssdk.services.globalaccelerator.model.DescribeCustomRoutingAcceleratorResponse$Builder accelerator(software.amazon.awssdk.services.globalaccelerator.model.CustomRoutingAccelerator);
    Code:
       0: aload_0
       1: aload_1
       2: putfield      #3                  // Field accelerator:Lsoftware/amazon/awssdk/services/globalaccelerator/model/CustomRoutingAccelerator;
       5: aload_0
       6: areturn

  public software.amazon.awssdk.services.globalaccelerator.model.DescribeCustomRoutingAcceleratorResponse build();
    Code:
       0: new           #10                 // class software/amazon/awssdk/services/globalaccelerator/model/DescribeCustomRoutingAcceleratorResponse
       3: dup
       4: aload_0
       5: aconst_null
       6: invokespecial #11                 // Method software/amazon/awssdk/services/globalaccelerator/model/DescribeCustomRoutingAcceleratorResponse."<init>":(Lsoftware/amazon/awssdk/services/globalaccelerator/model/DescribeCustomRoutingAcceleratorResponse$BuilderImpl;Lsoftware/amazon/awssdk/services/globalaccelerator/model/DescribeCustomRoutingAcceleratorResponse$1;)V
       9: areturn

  public java.util.List<software.amazon.awssdk.core.SdkField<?>> sdkFields();
    Code:
       0: invokestatic  #12                 // Method software/amazon/awssdk/services/globalaccelerator/model/DescribeCustomRoutingAcceleratorResponse.access$500:()Ljava/util/List;
       3: areturn

  public software.amazon.awssdk.services.globalaccelerator.model.GlobalAcceleratorResponse build();
    Code:
       0: aload_0
       1: invokevirtual #13                 // Method build:()Lsoftware/amazon/awssdk/services/globalaccelerator/model/DescribeCustomRoutingAcceleratorResponse;
       4: areturn

  public software.amazon.awssdk.awscore.AwsResponse build();
    Code:
       0: aload_0
       1: invokevirtual #13                 // Method build:()Lsoftware/amazon/awssdk/services/globalaccelerator/model/DescribeCustomRoutingAcceleratorResponse;
       4: areturn

  public software.amazon.awssdk.core.SdkResponse build();
    Code:
       0: aload_0
       1: invokevirtual #13                 // Method build:()Lsoftware/amazon/awssdk/services/globalaccelerator/model/DescribeCustomRoutingAcceleratorResponse;
       4: areturn

  public java.lang.Object build();
    Code:
       0: aload_0
       1: invokevirtual #13                 // Method build:()Lsoftware/amazon/awssdk/services/globalaccelerator/model/DescribeCustomRoutingAcceleratorResponse;
       4: areturn

  static software.amazon.awssdk.services.globalaccelerator.model.CustomRoutingAccelerator access$000(software.amazon.awssdk.services.globalaccelerator.model.DescribeCustomRoutingAcceleratorResponse$BuilderImpl);
    Code:
       0: aload_0
       1: getfield      #3                  // Field accelerator:Lsoftware/amazon/awssdk/services/globalaccelerator/model/CustomRoutingAccelerator;
       4: areturn

  software.amazon.awssdk.services.globalaccelerator.model.DescribeCustomRoutingAcceleratorResponse$BuilderImpl(software.amazon.awssdk.services.globalaccelerator.model.DescribeCustomRoutingAcceleratorResponse, software.amazon.awssdk.services.globalaccelerator.model.DescribeCustomRoutingAcceleratorResponse$1);
    Code:
       0: aload_0
       1: aload_1
       2: invokespecial #2                  // Method "<init>":(Lsoftware/amazon/awssdk/services/globalaccelerator/model/DescribeCustomRoutingAcceleratorResponse;)V
       5: return

  software.amazon.awssdk.services.globalaccelerator.model.DescribeCustomRoutingAcceleratorResponse$BuilderImpl(software.amazon.awssdk.services.globalaccelerator.model.DescribeCustomRoutingAcceleratorResponse$1);
    Code:
       0: aload_0
       1: invokespecial #1                  // Method "<init>":()V
       4: return
}
