Compiled from "SocketAddress.java"
final class software.amazon.awssdk.services.globalaccelerator.model.SocketAddress$BuilderImpl implements software.amazon.awssdk.services.globalaccelerator.model.SocketAddress$Builder {
  private java.lang.String ipAddress;

  private java.lang.Integer port;

  private software.amazon.awssdk.services.globalaccelerator.model.SocketAddress$BuilderImpl();
    Code:
       0: aload_0
       1: invokespecial #5                  // Method java/lang/Object."<init>":()V
       4: return

  private software.amazon.awssdk.services.globalaccelerator.model.SocketAddress$BuilderImpl(software.amazon.awssdk.services.globalaccelerator.model.SocketAddress);
    Code:
       0: aload_0
       1: invokespecial #5                  // Method java/lang/Object."<init>":()V
       4: aload_0
       5: aload_1
       6: invokestatic  #6                  // Method software/amazon/awssdk/services/globalaccelerator/model/SocketAddress.access$400:(Lsoftware/amazon/awssdk/services/globalaccelerator/model/SocketAddress;)Ljava/lang/String;
       9: invokevirtual #7                  // Method ipAddress:(Ljava/lang/String;)Lsoftware/amazon/awssdk/services/globalaccelerator/model/SocketAddress$Builder;
      12: pop
      13: aload_0
      14: aload_1
      15: invokestatic  #8                  // Method software/amazon/awssdk/services/globalaccelerator/model/SocketAddress.access$500:(Lsoftware/amazon/awssdk/services/globalaccelerator/model/SocketAddress;)Ljava/lang/Integer;
      18: invokevirtual #9                  // Method port:(Ljava/lang/Integer;)Lsoftware/amazon/awssdk/services/globalaccelerator/model/SocketAddress$Builder;
      21: pop
      22: return

  public final java.lang.String getIpAddress();
    Code:
       0: aload_0
       1: getfield      #4                  // Field ipAddress:Ljava/lang/String;
       4: areturn

  public final void setIpAddress(java.lang.String);
    Code:
       0: aload_0
       1: aload_1
       2: putfield      #4                  // Field ipAddress:Ljava/lang/String;
       5: return

  public final software.amazon.awssdk.services.globalaccelerator.model.SocketAddress$Builder ipAddress(java.lang.String);
    Code:
       0: aload_0
       1: aload_1
       2: putfield      #4                  // Field ipAddress:Ljava/lang/String;
       5: aload_0
       6: areturn

  public final java.lang.Integer getPort();
    Code:
       0: aload_0
       1: getfield      #3                  // Field port:Ljava/lang/Integer;
       4: areturn

  public final void setPort(java.lang.Integer);
    Code:
       0: aload_0
       1: aload_1
       2: putfield      #3                  // Field port:Ljava/lang/Integer;
       5: return

  public final software.amazon.awssdk.services.globalaccelerator.model.SocketAddress$Builder port(java.lang.Integer);
    Code:
       0: aload_0
       1: aload_1
       2: putfield      #3                  // Field port:Ljava/lang/Integer;
       5: aload_0
       6: areturn

  public software.amazon.awssdk.services.globalaccelerator.model.SocketAddress build();
    Code:
       0: new           #10                 // class software/amazon/awssdk/services/globalaccelerator/model/SocketAddress
       3: dup
       4: aload_0
       5: aconst_null
       6: invokespecial #11                 // Method software/amazon/awssdk/services/globalaccelerator/model/SocketAddress."<init>":(Lsoftware/amazon/awssdk/services/globalaccelerator/model/SocketAddress$BuilderImpl;Lsoftware/amazon/awssdk/services/globalaccelerator/model/SocketAddress$1;)V
       9: areturn

  public java.util.List<software.amazon.awssdk.core.SdkField<?>> sdkFields();
    Code:
       0: invokestatic  #12                 // Method software/amazon/awssdk/services/globalaccelerator/model/SocketAddress.access$700:()Ljava/util/List;
       3: areturn

  public java.lang.Object build();
    Code:
       0: aload_0
       1: invokevirtual #13                 // Method build:()Lsoftware/amazon/awssdk/services/globalaccelerator/model/SocketAddress;
       4: areturn

  static java.lang.String access$000(software.amazon.awssdk.services.globalaccelerator.model.SocketAddress$BuilderImpl);
    Code:
       0: aload_0
       1: getfield      #4                  // Field ipAddress:Ljava/lang/String;
       4: areturn

  static java.lang.Integer access$100(software.amazon.awssdk.services.globalaccelerator.model.SocketAddress$BuilderImpl);
    Code:
       0: aload_0
       1: getfield      #3                  // Field port:Ljava/lang/Integer;
       4: areturn

  software.amazon.awssdk.services.globalaccelerator.model.SocketAddress$BuilderImpl(software.amazon.awssdk.services.globalaccelerator.model.SocketAddress, software.amazon.awssdk.services.globalaccelerator.model.SocketAddress$1);
    Code:
       0: aload_0
       1: aload_1
       2: invokespecial #2                  // Method "<init>":(Lsoftware/amazon/awssdk/services/globalaccelerator/model/SocketAddress;)V
       5: return

  software.amazon.awssdk.services.globalaccelerator.model.SocketAddress$BuilderImpl(software.amazon.awssdk.services.globalaccelerator.model.SocketAddress$1);
    Code:
       0: aload_0
       1: invokespecial #1                  // Method "<init>":()V
       4: return
}
