Compiled from "implicits.scala"
public final class io.udash.rest.FloatingPointRestImplicits$ implements io.udash.rest.FloatingPointRestImplicits {
  public static io.udash.rest.FloatingPointRestImplicits$ MODULE$;

  private final com.avsystem.commons.rpc.AsRawReal<io.udash.rest.raw.PlainValue, java.lang.Object> floatPlainValueAsRealRaw;

  private final com.avsystem.commons.rpc.AsRawReal<io.udash.rest.raw.PlainValue, java.lang.Object> doublePlainValueAsRealRaw;

  public static {};
    Code:
       0: new           #2                  // class io/udash/rest/FloatingPointRestImplicits$
       3: invokespecial #18                 // Method "<init>":()V
       6: return

  public final com.avsystem.commons.rpc.AsRawReal<io.udash.rest.raw.PlainValue, java.lang.Object> floatPlainValueAsRealRaw();
    Code:
       0: aload_0
       1: getfield      #22                 // Field floatPlainValueAsRealRaw:Lcom/avsystem/commons/rpc/AsRawReal;
       4: areturn

  public final com.avsystem.commons.rpc.AsRawReal<io.udash.rest.raw.PlainValue, java.lang.Object> doublePlainValueAsRealRaw();
    Code:
       0: aload_0
       1: getfield      #25                 // Field doublePlainValueAsRealRaw:Lcom/avsystem/commons/rpc/AsRawReal;
       4: areturn

  public final void io$udash$rest$FloatingPointRestImplicits$_setter_$floatPlainValueAsRealRaw_$eq(com.avsystem.commons.rpc.AsRawReal<io.udash.rest.raw.PlainValue, java.lang.Object>);
    Code:
       0: aload_0
       1: aload_1
       2: putfield      #22                 // Field floatPlainValueAsRealRaw:Lcom/avsystem/commons/rpc/AsRawReal;
       5: return

  public final void io$udash$rest$FloatingPointRestImplicits$_setter_$doublePlainValueAsRealRaw_$eq(com.avsystem.commons.rpc.AsRawReal<io.udash.rest.raw.PlainValue, java.lang.Object>);
    Code:
       0: aload_0
       1: aload_1
       2: putfield      #25                 // Field doublePlainValueAsRealRaw:Lcom/avsystem/commons/rpc/AsRawReal;
       5: return

  private io.udash.rest.FloatingPointRestImplicits$();
    Code:
       0: aload_0
       1: invokespecial #31                 // Method java/lang/Object."<init>":()V
       4: aload_0
       5: putstatic     #33                 // Field MODULE$:Lio/udash/rest/FloatingPointRestImplicits$;
       8: aload_0
       9: invokestatic  #37                 // InterfaceMethod io/udash/rest/FloatingPointRestImplicits.$init$:(Lio/udash/rest/FloatingPointRestImplicits;)V
      12: return
}
