Compiled from "implicits.scala"
public interface io.udash.rest.FutureRestImplicits {
  public static monix.execution.Scheduler clientScheduler$(io.udash.rest.FutureRestImplicits);
    Code:
       0: aload_0
       1: invokespecial #22                 // InterfaceMethod clientScheduler:()Lmonix/execution/Scheduler;
       4: areturn

  public default monix.execution.Scheduler clientScheduler();
    Code:
       0: getstatic     #29                 // Field monix/execution/Scheduler$.MODULE$:Lmonix/execution/Scheduler$;
       3: invokevirtual #32                 // Method monix/execution/Scheduler$.global:()Lmonix/execution/Scheduler;
       6: areturn

  public static io.udash.rest.raw.RawRest$FromTask futureFromTask$(io.udash.rest.FutureRestImplicits);
    Code:
       0: aload_0
       1: invokespecial #39                 // InterfaceMethod futureFromTask:()Lio/udash/rest/raw/RawRest$FromTask;
       4: areturn

  public default io.udash.rest.raw.RawRest$FromTask<scala.concurrent.Future> futureFromTask();
    Code:
       0: new           #10                 // class io/udash/rest/FutureRestImplicits$$anon$1
       3: dup
       4: aload_0
       5: invokespecial #44                 // Method io/udash/rest/FutureRestImplicits$$anon$1."<init>":(Lio/udash/rest/FutureRestImplicits;)V
       8: areturn

  public static com.avsystem.commons.misc.ImplicitNotFound httpResponseTypeNotFound$(io.udash.rest.FutureRestImplicits);
    Code:
       0: aload_0
       1: invokespecial #50                 // InterfaceMethod httpResponseTypeNotFound:()Lcom/avsystem/commons/misc/ImplicitNotFound;
       4: areturn

  public default <T> com.avsystem.commons.misc.ImplicitNotFound<io.udash.rest.raw.HttpResponseType<T>> httpResponseTypeNotFound();
    Code:
       0: getstatic     #56                 // Field com/avsystem/commons/misc/ImplicitNotFound$.MODULE$:Lcom/avsystem/commons/misc/ImplicitNotFound$;
       3: invokevirtual #59                 // Method com/avsystem/commons/misc/ImplicitNotFound$.apply:()Lcom/avsystem/commons/misc/ImplicitNotFound;
       6: areturn

  public static void $init$(io.udash.rest.FutureRestImplicits);
    Code:
       0: return
}
