Compiled from "annotations.scala"
public class io.udash.rest.PUT extends io.udash.rest.BodyMethodTag {
  private final java.lang.String path;

  public static java.lang.String $lessinit$greater$default$1();
    Code:
       0: getstatic     #18                 // Field io/udash/rest/PUT$.MODULE$:Lio/udash/rest/PUT$;
       3: invokevirtual #20                 // Method io/udash/rest/PUT$.$lessinit$greater$default$1:()Ljava/lang/String;
       6: areturn

  public java.lang.String path();
    Code:
       0: aload_0
       1: getfield      #22                 // Field path:Ljava/lang/String;
       4: areturn

  public final scala.collection.immutable.List<scala.annotation.StaticAnnotation> aggregated();
    Code:
       0: new           #29                 // class scala/collection/immutable/$colon$colon
       3: dup
       4: new           #31                 // class com/avsystem/commons/rpc/rpcNamePrefix
       7: dup
       8: ldc           #33                 // String put_
      10: iconst_1
      11: invokespecial #37                 // Method com/avsystem/commons/rpc/rpcNamePrefix."<init>":(Ljava/lang/String;Z)V
      14: getstatic     #42                 // Field scala/collection/immutable/Nil$.MODULE$:Lscala/collection/immutable/Nil$;
      17: invokespecial #45                 // Method scala/collection/immutable/$colon$colon."<init>":(Ljava/lang/Object;Lscala/collection/immutable/List;)V
      20: areturn

  public io.udash.rest.PUT(java.lang.String);
    Code:
       0: aload_0
       1: aload_1
       2: putfield      #22                 // Field path:Ljava/lang/String;
       5: aload_0
       6: getstatic     #51                 // Field io/udash/rest/raw/HttpMethod$.MODULE$:Lio/udash/rest/raw/HttpMethod$;
       9: invokevirtual #55                 // Method io/udash/rest/raw/HttpMethod$.PUT:()Lio/udash/rest/raw/HttpMethod;
      12: invokespecial #58                 // Method io/udash/rest/BodyMethodTag."<init>":(Lio/udash/rest/raw/HttpMethod;)V
      15: return
}
