Compiled from "RestDataCompanion.scala"
public abstract class io.udash.rest.RestDataCompanionWithDeps<D, T> {
  private com.avsystem.commons.serialization.GenCodec<T> codec;

  private io.udash.rest.openapi.RestStructure<T> restStructure;

  private io.udash.rest.openapi.RestSchema<T> restSchema;

  private final D deps;

  private final com.avsystem.commons.meta.MacroInstances<scala.Tuple2<io.udash.rest.DefaultRestImplicits, D>, io.udash.rest.CodecWithStructure<T>> instances;

  private volatile byte bitmap$0;

  private com.avsystem.commons.serialization.GenCodec<T> codec$lzycompute();
    Code:
       0: aload_0
       1: dup
       2: astore_1
       3: monitorenter
       4: aload_0
       5: getfield      #36                 // Field bitmap$0:B
       8: iconst_1
       9: iand
      10: i2b
      11: iconst_0
      12: if_icmpne     62
      15: aload_0
      16: aload_0
      17: getfield      #38                 // Field instances:Lcom/avsystem/commons/meta/MacroInstances;
      20: new           #40                 // class scala/Tuple2
      23: dup
      24: getstatic     #46                 // Field io/udash/rest/DefaultRestImplicits$.MODULE$:Lio/udash/rest/DefaultRestImplicits$;
      27: aload_0
      28: getfield      #48                 // Field deps:Ljava/lang/Object;
      31: invokespecial #52                 // Method scala/Tuple2."<init>":(Ljava/lang/Object;Ljava/lang/Object;)V
      34: aload_0
      35: invokeinterface #58,  3           // InterfaceMethod com/avsystem/commons/meta/MacroInstances.apply:(Ljava/lang/Object;Ljava/lang/Object;)Ljava/lang/Object;
      40: checkcast     #60                 // class io/udash/rest/CodecWithStructure
      43: invokeinterface #62,  1           // InterfaceMethod io/udash/rest/CodecWithStructure.codec:()Lcom/avsystem/commons/serialization/GenCodec;
      48: putfield      #64                 // Field codec:Lcom/avsystem/commons/serialization/GenCodec;
      51: aload_0
      52: aload_0
      53: getfield      #36                 // Field bitmap$0:B
      56: iconst_1
      57: ior
      58: i2b
      59: putfield      #36                 // Field bitmap$0:B
      62: aload_1
      63: monitorexit
      64: goto          70
      67: aload_1
      68: monitorexit
      69: athrow
      70: aload_0
      71: getfield      #64                 // Field codec:Lcom/avsystem/commons/serialization/GenCodec;
      74: areturn
    Exception table:
       from    to  target type
           4    62    67   any

  public com.avsystem.commons.serialization.GenCodec<T> codec();
    Code:
       0: aload_0
       1: getfield      #36                 // Field bitmap$0:B
       4: iconst_1
       5: iand
       6: i2b
       7: iconst_0
       8: if_icmpne     18
      11: aload_0
      12: invokespecial #70                 // Method codec$lzycompute:()Lcom/avsystem/commons/serialization/GenCodec;
      15: goto          22
      18: aload_0
      19: getfield      #64                 // Field codec:Lcom/avsystem/commons/serialization/GenCodec;
      22: areturn

  private io.udash.rest.openapi.RestStructure<T> restStructure$lzycompute();
    Code:
       0: aload_0
       1: dup
       2: astore_1
       3: monitorenter
       4: aload_0
       5: getfield      #36                 // Field bitmap$0:B
       8: iconst_2
       9: iand
      10: i2b
      11: iconst_0
      12: if_icmpne     62
      15: aload_0
      16: aload_0
      17: getfield      #38                 // Field instances:Lcom/avsystem/commons/meta/MacroInstances;
      20: new           #40                 // class scala/Tuple2
      23: dup
      24: getstatic     #46                 // Field io/udash/rest/DefaultRestImplicits$.MODULE$:Lio/udash/rest/DefaultRestImplicits$;
      27: aload_0
      28: getfield      #48                 // Field deps:Ljava/lang/Object;
      31: invokespecial #52                 // Method scala/Tuple2."<init>":(Ljava/lang/Object;Ljava/lang/Object;)V
      34: aload_0
      35: invokeinterface #58,  3           // InterfaceMethod com/avsystem/commons/meta/MacroInstances.apply:(Ljava/lang/Object;Ljava/lang/Object;)Ljava/lang/Object;
      40: checkcast     #60                 // class io/udash/rest/CodecWithStructure
      43: invokeinterface #78,  1           // InterfaceMethod io/udash/rest/CodecWithStructure.structure:()Lio/udash/rest/openapi/RestStructure;
      48: putfield      #80                 // Field restStructure:Lio/udash/rest/openapi/RestStructure;
      51: aload_0
      52: aload_0
      53: getfield      #36                 // Field bitmap$0:B
      56: iconst_2
      57: ior
      58: i2b
      59: putfield      #36                 // Field bitmap$0:B
      62: aload_1
      63: monitorexit
      64: goto          70
      67: aload_1
      68: monitorexit
      69: athrow
      70: aload_0
      71: getfield      #80                 // Field restStructure:Lio/udash/rest/openapi/RestStructure;
      74: areturn
    Exception table:
       from    to  target type
           4    62    67   any

  public io.udash.rest.openapi.RestStructure<T> restStructure();
    Code:
       0: aload_0
       1: getfield      #36                 // Field bitmap$0:B
       4: iconst_2
       5: iand
       6: i2b
       7: iconst_0
       8: if_icmpne     18
      11: aload_0
      12: invokespecial #82                 // Method restStructure$lzycompute:()Lio/udash/rest/openapi/RestStructure;
      15: goto          22
      18: aload_0
      19: getfield      #80                 // Field restStructure:Lio/udash/rest/openapi/RestStructure;
      22: areturn

  private io.udash.rest.openapi.RestSchema<T> restSchema$lzycompute();
    Code:
       0: aload_0
       1: dup
       2: astore_1
       3: monitorenter
       4: aload_0
       5: getfield      #36                 // Field bitmap$0:B
       8: iconst_4
       9: iand
      10: i2b
      11: iconst_0
      12: if_icmpne     42
      15: aload_0
      16: getstatic     #92                 // Field io/udash/rest/openapi/RestSchema$.MODULE$:Lio/udash/rest/openapi/RestSchema$;
      19: aload_0
      20: invokedynamic #114,  0            // InvokeDynamic #0:apply:(Lio/udash/rest/RestDataCompanionWithDeps;)Lscala/Function0;
      25: invokevirtual #118                // Method io/udash/rest/openapi/RestSchema$.lazySchema:(Lscala/Function0;)Lio/udash/rest/openapi/RestSchema;
      28: putfield      #120                // Field restSchema:Lio/udash/rest/openapi/RestSchema;
      31: aload_0
      32: aload_0
      33: getfield      #36                 // Field bitmap$0:B
      36: iconst_4
      37: ior
      38: i2b
      39: putfield      #36                 // Field bitmap$0:B
      42: aload_1
      43: monitorexit
      44: goto          50
      47: aload_1
      48: monitorexit
      49: athrow
      50: aload_0
      51: getfield      #120                // Field restSchema:Lio/udash/rest/openapi/RestSchema;
      54: areturn
    Exception table:
       from    to  target type
           4    42    47   any

  public io.udash.rest.openapi.RestSchema<T> restSchema();
    Code:
       0: aload_0
       1: getfield      #36                 // Field bitmap$0:B
       4: iconst_4
       5: iand
       6: i2b
       7: iconst_0
       8: if_icmpne     18
      11: aload_0
      12: invokespecial #122                // Method restSchema$lzycompute:()Lio/udash/rest/openapi/RestSchema;
      15: goto          22
      18: aload_0
      19: getfield      #120                // Field restSchema:Lio/udash/rest/openapi/RestSchema;
      22: areturn

  public static final io.udash.rest.openapi.RestSchema $anonfun$restSchema$2(io.udash.rest.RestDataCompanionWithDeps);
    Code:
       0: aload_0
       1: invokevirtual #127                // Method restStructure:()Lio/udash/rest/openapi/RestStructure;
       4: invokeinterface #130,  1          // InterfaceMethod io/udash/rest/openapi/RestStructure.standaloneSchema:()Lio/udash/rest/openapi/RestSchema;
       9: areturn

  public io.udash.rest.RestDataCompanionWithDeps(D, com.avsystem.commons.meta.MacroInstances<scala.Tuple2<io.udash.rest.DefaultRestImplicits, D>, io.udash.rest.CodecWithStructure<T>>);
    Code:
       0: aload_0
       1: aload_1
       2: putfield      #48                 // Field deps:Ljava/lang/Object;
       5: aload_0
       6: aload_2
       7: putfield      #38                 // Field instances:Lcom/avsystem/commons/meta/MacroInstances;
      10: aload_0
      11: invokespecial #135                // Method java/lang/Object."<init>":()V
      14: return

  private static java.lang.Object $deserializeLambda$(java.lang.invoke.SerializedLambda);
    Code:
       0: aload_0
       1: invokedynamic #147,  0            // InvokeDynamic #1:lambdaDeserialize:(Ljava/lang/invoke/SerializedLambda;)Ljava/lang/Object;
       6: areturn
}
