Compiled from "IndexExternalizer.java"
final class org.wildfly.clustering.marshalling.jboss.IndexExternalizer$2 extends org.wildfly.clustering.marshalling.jboss.IndexExternalizer {
  org.wildfly.clustering.marshalling.jboss.IndexExternalizer$2(java.lang.String, int);
    Code:
       0: aload_0
       1: aload_1
       2: iload_2
       3: aconst_null
       4: invokespecial #1                  // Method org/wildfly/clustering/marshalling/jboss/IndexExternalizer."<init>":(Ljava/lang/String;ILorg/wildfly/clustering/marshalling/jboss/IndexExternalizer$1;)V
       7: return

  public int readData(java.io.DataInput) throws java.io.IOException;
    Code:
       0: aload_1
       1: invokeinterface #2,  1            // InterfaceMethod java/io/DataInput.readUnsignedShort:()I
       6: ireturn

  public void writeData(java.io.DataOutput, int) throws java.io.IOException;
    Code:
       0: iload_2
       1: ldc           #4                  // int 65535
       3: if_icmple     18
       6: new           #5                  // class java/lang/IndexOutOfBoundsException
       9: dup
      10: iload_2
      11: invokestatic  #6                  // Method java/lang/Integer.toString:(I)Ljava/lang/String;
      14: invokespecial #7                  // Method java/lang/IndexOutOfBoundsException."<init>":(Ljava/lang/String;)V
      17: athrow
      18: aload_1
      19: iload_2
      20: invokeinterface #8,  2            // InterfaceMethod java/io/DataOutput.writeShort:(I)V
      25: return

  public java.lang.Object readObject(java.io.ObjectInput) throws java.io.IOException, java.lang.ClassNotFoundException;
    Code:
       0: aload_0
       1: aload_1
       2: invokespecial #9                  // Method org/wildfly/clustering/marshalling/jboss/IndexExternalizer.readObject:(Ljava/io/ObjectInput;)Ljava/lang/Integer;
       5: areturn

  public void writeObject(java.io.ObjectOutput, java.lang.Object) throws java.io.IOException;
    Code:
       0: aload_0
       1: aload_1
       2: aload_2
       3: checkcast     #10                 // class java/lang/Integer
       6: invokespecial #11                 // Method org/wildfly/clustering/marshalling/jboss/IndexExternalizer.writeObject:(Ljava/io/ObjectOutput;Ljava/lang/Integer;)V
       9: return
}
