Compiled from "xmlsplitter.java"
public class xmlsplitter {
  public static java.lang.String schema_location;

  public static java.lang.String xml_dir_name;

  public static net.sf.xsd2pgschema.PgSchemaOption option;

  public static net.sf.xsd2pgschema.XmlFileFilter xml_file_filter;

  public static java.io.File[] xml_files;

  public static java.lang.String xpath_doc_key;

  public static int shard_size;

  public static boolean verbose;

  public xmlsplitter();
    Code:
       0: aload_0
       1: invokespecial #1                  // Method java/lang/Object."<init>":()V
       4: return

  public static void main(java.lang.String[]);
    Code:
       0: new           #2                  // class java/util/HashSet
       3: dup
       4: invokespecial #3                  // Method java/util/HashSet."<init>":()V
       7: astore_1
       8: iconst_0
       9: istore_2
      10: iload_2
      11: aload_0
      12: arraylength
      13: if_icmpge     309
      16: aload_0
      17: iload_2
      18: aaload
      19: ldc           #4                  // String --xsd
      21: invokevirtual #5                  // Method java/lang/String.equals:(Ljava/lang/Object;)Z
      24: ifeq          39
      27: aload_0
      28: iinc          2, 1
      31: iload_2
      32: aaload
      33: putstatic     #6                  // Field schema_location:Ljava/lang/String;
      36: goto          303
      39: aload_0
      40: iload_2
      41: aaload
      42: ldc           #7                  // String --xml
      44: invokevirtual #5                  // Method java/lang/String.equals:(Ljava/lang/Object;)Z
      47: ifeq          84
      50: aload_0
      51: iinc          2, 1
      54: iload_2
      55: aaload
      56: astore_3
      57: aload_3
      58: invokevirtual #8                  // Method java/lang/String.isEmpty:()Z
      61: ifeq          75
      64: getstatic     #9                  // Field java/lang/System.err:Ljava/io/PrintStream;
      67: ldc           #10                 // String XML file name is empty.
      69: invokevirtual #11                 // Method java/io/PrintStream.println:(Ljava/lang/String;)V
      72: invokestatic  #12                 // Method showUsage:()V
      75: aload_1
      76: aload_3
      77: invokevirtual #13                 // Method java/util/HashSet.add:(Ljava/lang/Object;)Z
      80: pop
      81: goto          303
      84: aload_0
      85: iload_2
      86: aaload
      87: ldc           #14                 // String --xml-file-ext
      89: invokevirtual #5                  // Method java/lang/String.equals:(Ljava/lang/Object;)Z
      92: ifeq          116
      95: getstatic     #15                 // Field xml_file_filter:Lnet/sf/xsd2pgschema/XmlFileFilter;
      98: aload_0
      99: iinc          2, 1
     102: iload_2
     103: aaload
     104: invokevirtual #16                 // Method net/sf/xsd2pgschema/XmlFileFilter.setExt:(Ljava/lang/String;)Z
     107: ifne          303
     110: invokestatic  #12                 // Method showUsage:()V
     113: goto          303
     116: aload_0
     117: iload_2
     118: aaload
     119: ldc           #17                 // String --xml-dir
     121: invokevirtual #5                  // Method java/lang/String.equals:(Ljava/lang/Object;)Z
     124: ifeq          139
     127: aload_0
     128: iinc          2, 1
     131: iload_2
     132: aaload
     133: putstatic     #18                 // Field xml_dir_name:Ljava/lang/String;
     136: goto          303
     139: aload_0
     140: iload_2
     141: aaload
     142: ldc           #19                 // String --no-wild-card
     144: invokevirtual #5                  // Method java/lang/String.equals:(Ljava/lang/Object;)Z
     147: ifeq          160
     150: getstatic     #20                 // Field option:Lnet/sf/xsd2pgschema/PgSchemaOption;
     153: iconst_0
     154: putfield      #21                 // Field net/sf/xsd2pgschema/PgSchemaOption.wild_card:Z
     157: goto          303
     160: aload_0
     161: iload_2
     162: aaload
     163: ldc           #22                 // String --case-insensitive
     165: invokevirtual #5                  // Method java/lang/String.equals:(Ljava/lang/Object;)Z
     168: ifeq          181
     171: getstatic     #20                 // Field option:Lnet/sf/xsd2pgschema/PgSchemaOption;
     174: iconst_0
     175: putfield      #23                 // Field net/sf/xsd2pgschema/PgSchemaOption.case_sense:Z
     178: goto          303
     181: aload_0
     182: iload_2
     183: aaload
     184: ldc           #24                 // String --xpath-doc-key
     186: invokevirtual #5                  // Method java/lang/String.equals:(Ljava/lang/Object;)Z
     189: ifeq          204
     192: aload_0
     193: iinc          2, 1
     196: iload_2
     197: aaload
     198: putstatic     #25                 // Field xpath_doc_key:Ljava/lang/String;
     201: goto          303
     204: aload_0
     205: iload_2
     206: aaload
     207: ldc           #26                 // String --shard-size
     209: invokevirtual #5                  // Method java/lang/String.equals:(Ljava/lang/Object;)Z
     212: ifeq          250
     215: aload_0
     216: iinc          2, 1
     219: iload_2
     220: aaload
     221: invokestatic  #27                 // Method java/lang/Integer.valueOf:(Ljava/lang/String;)Ljava/lang/Integer;
     224: invokevirtual #28                 // Method java/lang/Integer.intValue:()I
     227: putstatic     #29                 // Field shard_size:I
     230: getstatic     #29                 // Field shard_size:I
     233: ifgt          303
     236: getstatic     #9                  // Field java/lang/System.err:Ljava/io/PrintStream;
     239: ldc           #30                 // String Out of range (shard-size).
     241: invokevirtual #11                 // Method java/io/PrintStream.println:(Ljava/lang/String;)V
     244: invokestatic  #12                 // Method showUsage:()V
     247: goto          303
     250: aload_0
     251: iload_2
     252: aaload
     253: ldc           #31                 // String --verbose
     255: invokevirtual #5                  // Method java/lang/String.equals:(Ljava/lang/Object;)Z
     258: ifeq          268
     261: iconst_1
     262: putstatic     #32                 // Field verbose:Z
     265: goto          303
     268: getstatic     #9                  // Field java/lang/System.err:Ljava/io/PrintStream;
     271: new           #33                 // class java/lang/StringBuilder
     274: dup
     275: invokespecial #34                 // Method java/lang/StringBuilder."<init>":()V
     278: ldc           #35                 // String Illegal option:
     280: invokevirtual #36                 // Method java/lang/StringBuilder.append:(Ljava/lang/String;)Ljava/lang/StringBuilder;
     283: aload_0
     284: iload_2
     285: aaload
     286: invokevirtual #36                 // Method java/lang/StringBuilder.append:(Ljava/lang/String;)Ljava/lang/StringBuilder;
     289: ldc           #37                 // String .
     291: invokevirtual #36                 // Method java/lang/StringBuilder.append:(Ljava/lang/String;)Ljava/lang/StringBuilder;
     294: invokevirtual #38                 // Method java/lang/StringBuilder.toString:()Ljava/lang/String;
     297: invokevirtual #11                 // Method java/io/PrintStream.println:(Ljava/lang/String;)V
     300: invokestatic  #12                 // Method showUsage:()V
     303: iinc          2, 1
     306: goto          10
     309: getstatic     #6                  // Field schema_location:Ljava/lang/String;
     312: invokevirtual #8                  // Method java/lang/String.isEmpty:()Z
     315: ifeq          329
     318: getstatic     #9                  // Field java/lang/System.err:Ljava/io/PrintStream;
     321: ldc           #39                 // String XSD schema location is empty.
     323: invokevirtual #11                 // Method java/io/PrintStream.println:(Ljava/lang/String;)V
     326: invokestatic  #12                 // Method showUsage:()V
     329: getstatic     #6                  // Field schema_location:Ljava/lang/String;
     332: aconst_null
     333: invokestatic  #40                 // Method net/sf/xsd2pgschema/PgSchemaUtil.getInputStream:(Ljava/lang/String;Ljava/lang/String;)Ljava/io/InputStream;
     336: astore_2
     337: aload_2
     338: ifnonnull     344
     341: invokestatic  #12                 // Method showUsage:()V
     344: aload_1
     345: invokevirtual #41                 // Method java/util/HashSet.size:()I
     348: ifne          362
     351: getstatic     #9                  // Field java/lang/System.err:Ljava/io/PrintStream;
     354: ldc           #10                 // String XML file name is empty.
     356: invokevirtual #11                 // Method java/io/PrintStream.println:(Ljava/lang/String;)V
     359: invokestatic  #12                 // Method showUsage:()V
     362: new           #42                 // class xmlsplitter$1
     365: dup
     366: invokespecial #43                 // Method xmlsplitter$1."<init>":()V
     369: astore_3
     370: aload_1
     371: aload_3
     372: invokestatic  #44                 // Method net/sf/xsd2pgschema/PgSchemaUtil.getTargetFiles:(Ljava/util/HashSet;Ljava/io/FilenameFilter;)[Ljava/io/File;
     375: putstatic     #45                 // Field xml_files:[Ljava/io/File;
     378: new           #46                 // class java/io/File
     381: dup
     382: getstatic     #18                 // Field xml_dir_name:Ljava/lang/String;
     385: invokespecial #47                 // Method java/io/File."<init>":(Ljava/lang/String;)V
     388: astore        4
     390: aload         4
     392: invokevirtual #48                 // Method java/io/File.isDirectory:()Z
     395: ifne          442
     398: aload         4
     400: invokevirtual #49                 // Method java/io/File.mkdir:()Z
     403: ifne          442
     406: getstatic     #9                  // Field java/lang/System.err:Ljava/io/PrintStream;
     409: new           #33                 // class java/lang/StringBuilder
     412: dup
     413: invokespecial #34                 // Method java/lang/StringBuilder."<init>":()V
     416: ldc           #50                 // String Couldn\'t create directory \'
     418: invokevirtual #36                 // Method java/lang/StringBuilder.append:(Ljava/lang/String;)Ljava/lang/StringBuilder;
     421: getstatic     #18                 // Field xml_dir_name:Ljava/lang/String;
     424: invokevirtual #36                 // Method java/lang/StringBuilder.append:(Ljava/lang/String;)Ljava/lang/StringBuilder;
     427: ldc           #51                 // String \'.
     429: invokevirtual #36                 // Method java/lang/StringBuilder.append:(Ljava/lang/String;)Ljava/lang/StringBuilder;
     432: invokevirtual #38                 // Method java/lang/StringBuilder.toString:()Ljava/lang/String;
     435: invokevirtual #11                 // Method java/io/PrintStream.println:(Ljava/lang/String;)V
     438: iconst_1
     439: invokestatic  #52                 // Method java/lang/System.exit:(I)V
     442: getstatic     #18                 // Field xml_dir_name:Ljava/lang/String;
     445: ldc           #53                 // String /$
     447: ldc           #54                 // String
     449: invokevirtual #55                 // Method java/lang/String.replaceFirst:(Ljava/lang/String;Ljava/lang/String;)Ljava/lang/String;
     452: putstatic     #18                 // Field xml_dir_name:Ljava/lang/String;
     455: new           #56                 // class XmlSplitterImpl
     458: dup
     459: getstatic     #29                 // Field shard_size:I
     462: aload_2
     463: getstatic     #20                 // Field option:Lnet/sf/xsd2pgschema/PgSchemaOption;
     466: getstatic     #25                 // Field xpath_doc_key:Ljava/lang/String;
     469: invokespecial #57                 // Method XmlSplitterImpl."<init>":(ILjava/io/InputStream;Lnet/sf/xsd2pgschema/PgSchemaOption;Ljava/lang/String;)V
     472: astore        5
     474: aload         5
     476: invokevirtual #58                 // Method XmlSplitterImpl.exec:()V
     479: goto          493
     482: astore        5
     484: aload         5
     486: invokevirtual #65                 // Method java/lang/Exception.printStackTrace:()V
     489: iconst_1
     490: invokestatic  #52                 // Method java/lang/System.exit:(I)V
     493: return
    Exception table:
       from    to  target type
         455   479   482   Class java/io/IOException
         455   479   482   Class java/security/NoSuchAlgorithmException
         455   479   482   Class javax/xml/parsers/ParserConfigurationException
         455   479   482   Class org/xml/sax/SAXException
         455   479   482   Class net/sf/xsd2pgschema/PgSchemaException
         455   479   482   Class com/github/antlr/grammars_v4/xpath/xpathListenerException

  private static void showUsage();
    Code:
       0: getstatic     #9                  // Field java/lang/System.err:Ljava/io/PrintStream;
       3: ldc           #66                 // String xmlsplitter: Split large XML into small XML files
       5: invokevirtual #11                 // Method java/io/PrintStream.println:(Ljava/lang/String;)V
       8: getstatic     #9                  // Field java/lang/System.err:Ljava/io/PrintStream;
      11: new           #33                 // class java/lang/StringBuilder
      14: dup
      15: invokespecial #34                 // Method java/lang/StringBuilder."<init>":()V
      18: ldc           #67                 // String Usage:  --xsd SCHEMA_LOCATION --xml SRC_XML_FILE_OR_DIRECTORY --xml-dir DST_DIRECTORY (default=\"
      20: invokevirtual #36                 // Method java/lang/StringBuilder.append:(Ljava/lang/String;)Ljava/lang/StringBuilder;
      23: getstatic     #18                 // Field xml_dir_name:Ljava/lang/String;
      26: invokevirtual #36                 // Method java/lang/StringBuilder.append:(Ljava/lang/String;)Ljava/lang/StringBuilder;
      29: ldc           #68                 // String \")
      31: invokevirtual #36                 // Method java/lang/StringBuilder.append:(Ljava/lang/String;)Ljava/lang/StringBuilder;
      34: invokevirtual #38                 // Method java/lang/StringBuilder.toString:()Ljava/lang/String;
      37: invokevirtual #11                 // Method java/io/PrintStream.println:(Ljava/lang/String;)V
      40: getstatic     #9                  // Field java/lang/System.err:Ljava/io/PrintStream;
      43: ldc           #69                 // String         --xml-file-ext SRC_FILE_EXTENSION [xml (default) | gz (indicates xml.gz suffix)]
      45: invokevirtual #11                 // Method java/io/PrintStream.println:(Ljava/lang/String;)V
      48: getstatic     #9                  // Field java/lang/System.err:Ljava/io/PrintStream;
      51: ldc           #70                 // String         --xpath-doc-key XPATH_EXPR_FOR_DOC_KEY
      53: invokevirtual #11                 // Method java/io/PrintStream.println:(Ljava/lang/String;)V
      56: getstatic     #9                  // Field java/lang/System.err:Ljava/io/PrintStream;
      59: ldc           #71                 // String         --no-wild-card (turn off wild card extension)
      61: invokevirtual #11                 // Method java/io/PrintStream.println:(Ljava/lang/String;)V
      64: getstatic     #9                  // Field java/lang/System.err:Ljava/io/PrintStream;
      67: ldc           #72                 // String         --case-insensitive (all table and column names are lowercase)
      69: invokevirtual #11                 // Method java/io/PrintStream.println:(Ljava/lang/String;)V
      72: getstatic     #9                  // Field java/lang/System.err:Ljava/io/PrintStream;
      75: ldc           #73                 // String         --shard-size SHARD_SIZE (default=1)
      77: invokevirtual #11                 // Method java/io/PrintStream.println:(Ljava/lang/String;)V
      80: getstatic     #9                  // Field java/lang/System.err:Ljava/io/PrintStream;
      83: ldc           #74                 // String Option: --verbose
      85: invokevirtual #11                 // Method java/io/PrintStream.println:(Ljava/lang/String;)V
      88: iconst_1
      89: invokestatic  #52                 // Method java/lang/System.exit:(I)V
      92: return

  static {};
    Code:
       0: ldc           #54                 // String
       2: putstatic     #6                  // Field schema_location:Ljava/lang/String;
       5: ldc           #75                 // String xml_work
       7: putstatic     #18                 // Field xml_dir_name:Ljava/lang/String;
      10: new           #76                 // class net/sf/xsd2pgschema/PgSchemaOption
      13: dup
      14: iconst_0
      15: invokespecial #77                 // Method net/sf/xsd2pgschema/PgSchemaOption."<init>":(Z)V
      18: putstatic     #20                 // Field option:Lnet/sf/xsd2pgschema/PgSchemaOption;
      21: new           #78                 // class net/sf/xsd2pgschema/XmlFileFilter
      24: dup
      25: invokespecial #79                 // Method net/sf/xsd2pgschema/XmlFileFilter."<init>":()V
      28: putstatic     #15                 // Field xml_file_filter:Lnet/sf/xsd2pgschema/XmlFileFilter;
      31: aconst_null
      32: putstatic     #45                 // Field xml_files:[Ljava/io/File;
      35: ldc           #54                 // String
      37: putstatic     #25                 // Field xpath_doc_key:Ljava/lang/String;
      40: iconst_1
      41: putstatic     #29                 // Field shard_size:I
      44: iconst_0
      45: putstatic     #32                 // Field verbose:Z
      48: return
}
