Compiled from "AtomEvent.java"
public class won.matcher.service.common.event.AtomEvent implements java.io.Serializable {
  private java.lang.String uri;

  private java.lang.String wonNodeUri;

  private java.lang.String serializedAtomResource;

  private java.lang.String serializationLangName;

  private java.lang.String serializationLangContentType;

  private long crawlDate;

  private won.matcher.service.common.event.AtomEvent$TYPE eventType;

  private won.matcher.service.common.event.Cause cause;

  public won.matcher.service.common.event.AtomEvent(java.lang.String, java.lang.String, won.matcher.service.common.event.AtomEvent$TYPE, long, java.lang.String, org.apache.jena.riot.Lang, won.matcher.service.common.event.Cause);
    Code:
       0: aload_0
       1: invokespecial #1                  // Method java/lang/Object."<init>":()V
       4: aload_0
       5: aload_1
       6: putfield      #2                  // Field uri:Ljava/lang/String;
       9: aload_0
      10: aload_2
      11: putfield      #3                  // Field wonNodeUri:Ljava/lang/String;
      14: aload_0
      15: aload_3
      16: putfield      #4                  // Field eventType:Lwon/matcher/service/common/event/AtomEvent$TYPE;
      19: aload_0
      20: lload         4
      22: putfield      #5                  // Field crawlDate:J
      25: aload_0
      26: aload         6
      28: putfield      #6                  // Field serializedAtomResource:Ljava/lang/String;
      31: aload_0
      32: aload         7
      34: invokevirtual #7                  // Method org/apache/jena/riot/Lang.getName:()Ljava/lang/String;
      37: putfield      #8                  // Field serializationLangName:Ljava/lang/String;
      40: aload_0
      41: aload         7
      43: invokevirtual #9                  // Method org/apache/jena/riot/Lang.getContentType:()Lorg/apache/jena/atlas/web/ContentType;
      46: invokevirtual #10                 // Method org/apache/jena/atlas/web/ContentType.getContentType:()Ljava/lang/String;
      49: putfield      #11                 // Field serializationLangContentType:Ljava/lang/String;
      52: aload_0
      53: aload         8
      55: putfield      #12                 // Field cause:Lwon/matcher/service/common/event/Cause;
      58: return

  public won.matcher.service.common.event.AtomEvent(java.lang.String, java.lang.String, won.matcher.service.common.event.AtomEvent$TYPE, long, org.apache.jena.query.Dataset, won.matcher.service.common.event.Cause);
    Code:
       0: aload_0
       1: invokespecial #1                  // Method java/lang/Object."<init>":()V
       4: aload_0
       5: aload_1
       6: putfield      #2                  // Field uri:Ljava/lang/String;
       9: aload_0
      10: aload_2
      11: putfield      #3                  // Field wonNodeUri:Ljava/lang/String;
      14: aload_0
      15: aload_3
      16: putfield      #4                  // Field eventType:Lwon/matcher/service/common/event/AtomEvent$TYPE;
      19: aload_0
      20: lload         4
      22: putfield      #5                  // Field crawlDate:J
      25: new           #13                 // class java/io/StringWriter
      28: dup
      29: invokespecial #14                 // Method java/io/StringWriter."<init>":()V
      32: astore        8
      34: aload         8
      36: aload         6
      38: getstatic     #15                 // Field org/apache/jena/riot/RDFFormat.TRIG:Lorg/apache/jena/riot/RDFFormat;
      41: invokevirtual #16                 // Method org/apache/jena/riot/RDFFormat.getLang:()Lorg/apache/jena/riot/Lang;
      44: invokestatic  #17                 // Method org/apache/jena/riot/RDFDataMgr.write:(Ljava/io/StringWriter;Lorg/apache/jena/query/Dataset;Lorg/apache/jena/riot/Lang;)V
      47: aload_0
      48: aload         8
      50: invokevirtual #18                 // Method java/io/StringWriter.toString:()Ljava/lang/String;
      53: putfield      #6                  // Field serializedAtomResource:Ljava/lang/String;
      56: aload_0
      57: getstatic     #15                 // Field org/apache/jena/riot/RDFFormat.TRIG:Lorg/apache/jena/riot/RDFFormat;
      60: invokevirtual #16                 // Method org/apache/jena/riot/RDFFormat.getLang:()Lorg/apache/jena/riot/Lang;
      63: invokevirtual #7                  // Method org/apache/jena/riot/Lang.getName:()Ljava/lang/String;
      66: putfield      #8                  // Field serializationLangName:Ljava/lang/String;
      69: aload_0
      70: getstatic     #15                 // Field org/apache/jena/riot/RDFFormat.TRIG:Lorg/apache/jena/riot/RDFFormat;
      73: invokevirtual #16                 // Method org/apache/jena/riot/RDFFormat.getLang:()Lorg/apache/jena/riot/Lang;
      76: invokevirtual #9                  // Method org/apache/jena/riot/Lang.getContentType:()Lorg/apache/jena/atlas/web/ContentType;
      79: invokevirtual #10                 // Method org/apache/jena/atlas/web/ContentType.getContentType:()Ljava/lang/String;
      82: putfield      #11                 // Field serializationLangContentType:Ljava/lang/String;
      85: aload_0
      86: aload         7
      88: putfield      #12                 // Field cause:Lwon/matcher/service/common/event/Cause;
      91: return

  public java.lang.String getUri();
    Code:
       0: aload_0
       1: getfield      #2                  // Field uri:Ljava/lang/String;
       4: areturn

  public java.lang.String getWonNodeUri();
    Code:
       0: aload_0
       1: getfield      #3                  // Field wonNodeUri:Ljava/lang/String;
       4: areturn

  public won.matcher.service.common.event.AtomEvent$TYPE getEventType();
    Code:
       0: aload_0
       1: getfield      #4                  // Field eventType:Lwon/matcher/service/common/event/AtomEvent$TYPE;
       4: areturn

  public won.matcher.service.common.event.Cause getCause();
    Code:
       0: aload_0
       1: getfield      #12                 // Field cause:Lwon/matcher/service/common/event/Cause;
       4: areturn

  public java.lang.String getSerializedAtomResource();
    Code:
       0: aload_0
       1: getfield      #6                  // Field serializedAtomResource:Ljava/lang/String;
       4: areturn

  public org.apache.jena.riot.Lang getSerializationFormat();
    Code:
       0: aload_0
       1: getfield      #8                  // Field serializationLangName:Ljava/lang/String;
       4: aload_0
       5: getfield      #11                 // Field serializationLangContentType:Ljava/lang/String;
       8: invokestatic  #19                 // Method org/apache/jena/riot/LangBuilder.create:(Ljava/lang/String;Ljava/lang/String;)Lorg/apache/jena/riot/LangBuilder;
      11: invokevirtual #20                 // Method org/apache/jena/riot/LangBuilder.build:()Lorg/apache/jena/riot/Lang;
      14: astore_1
      15: aload_1
      16: areturn

  public long getCrawlDate();
    Code:
       0: aload_0
       1: getfield      #5                  // Field crawlDate:J
       4: lreturn

  public org.apache.jena.query.Dataset deserializeAtomDataset() throws java.io.IOException;
    Code:
       0: aload_0
       1: getfield      #6                  // Field serializedAtomResource:Ljava/lang/String;
       4: aload_0
       5: invokevirtual #21                 // Method getSerializationFormat:()Lorg/apache/jena/riot/Lang;
       8: invokestatic  #22                 // Method won/matcher/service/common/service/sparql/SparqlService.deserializeDataset:(Ljava/lang/String;Lorg/apache/jena/riot/Lang;)Lorg/apache/jena/query/Dataset;
      11: areturn

  public won.matcher.service.common.event.AtomEvent clone();
    Code:
       0: new           #23                 // class won/matcher/service/common/event/AtomEvent
       3: dup
       4: aload_0
       5: getfield      #2                  // Field uri:Ljava/lang/String;
       8: aload_0
       9: getfield      #3                  // Field wonNodeUri:Ljava/lang/String;
      12: aload_0
      13: getfield      #4                  // Field eventType:Lwon/matcher/service/common/event/AtomEvent$TYPE;
      16: aload_0
      17: getfield      #5                  // Field crawlDate:J
      20: aload_0
      21: getfield      #6                  // Field serializedAtomResource:Ljava/lang/String;
      24: aload_0
      25: invokevirtual #21                 // Method getSerializationFormat:()Lorg/apache/jena/riot/Lang;
      28: aload_0
      29: getfield      #12                 // Field cause:Lwon/matcher/service/common/event/Cause;
      32: invokespecial #24                 // Method "<init>":(Ljava/lang/String;Ljava/lang/String;Lwon/matcher/service/common/event/AtomEvent$TYPE;JLjava/lang/String;Lorg/apache/jena/riot/Lang;Lwon/matcher/service/common/event/Cause;)V
      35: astore_1
      36: aload_1
      37: areturn

  public java.lang.String toString();
    Code:
       0: aload_0
       1: invokevirtual #25                 // Method getUri:()Ljava/lang/String;
       4: areturn

  public java.lang.Object clone() throws java.lang.CloneNotSupportedException;
    Code:
       0: aload_0
       1: invokevirtual #26                 // Method clone:()Lwon/matcher/service/common/event/AtomEvent;
       4: areturn
}
