Compiled from "WonNodeEvent.java"
public class won.matcher.service.common.event.WonNodeEvent implements java.io.Serializable {
  private java.lang.String wonNodeUri;

  private won.protocol.service.WonNodeInfo wonNodeInfo;

  private won.matcher.service.common.event.WonNodeEvent$STATUS status;

  public won.matcher.service.common.event.WonNodeEvent(java.lang.String, won.matcher.service.common.event.WonNodeEvent$STATUS);
    Code:
       0: aload_0
       1: invokespecial #1                  // Method java/lang/Object."<init>":()V
       4: aload_0
       5: aload_1
       6: putfield      #2                  // Field wonNodeUri:Ljava/lang/String;
       9: aload_0
      10: aload_2
      11: putfield      #3                  // Field status:Lwon/matcher/service/common/event/WonNodeEvent$STATUS;
      14: return

  public won.matcher.service.common.event.WonNodeEvent(java.lang.String, won.matcher.service.common.event.WonNodeEvent$STATUS, won.protocol.service.WonNodeInfo);
    Code:
       0: aload_0
       1: invokespecial #1                  // Method java/lang/Object."<init>":()V
       4: aload_0
       5: aload_1
       6: putfield      #2                  // Field wonNodeUri:Ljava/lang/String;
       9: aload_0
      10: aload_2
      11: putfield      #3                  // Field status:Lwon/matcher/service/common/event/WonNodeEvent$STATUS;
      14: aload_0
      15: aload_3
      16: putfield      #4                  // Field wonNodeInfo:Lwon/protocol/service/WonNodeInfo;
      19: return

  public java.lang.String getWonNodeUri();
    Code:
       0: aload_0
       1: getfield      #2                  // Field wonNodeUri:Ljava/lang/String;
       4: areturn

  public won.protocol.service.WonNodeInfo getWonNodeInfo();
    Code:
       0: aload_0
       1: getfield      #4                  // Field wonNodeInfo:Lwon/protocol/service/WonNodeInfo;
       4: areturn

  public won.matcher.service.common.event.WonNodeEvent$STATUS getStatus();
    Code:
       0: aload_0
       1: getfield      #3                  // Field status:Lwon/matcher/service/common/event/WonNodeEvent$STATUS;
       4: areturn
}
