class org.bouncycastle.jce.provider.RFC3281CertPathUtilities {
  private static final java.lang.String TARGET_INFORMATION;

  private static final java.lang.String NO_REV_AVAIL;

  private static final java.lang.String CRL_DISTRIBUTION_POINTS;

  private static final java.lang.String AUTHORITY_INFO_ACCESS;

  org.bouncycastle.jce.provider.RFC3281CertPathUtilities();
    Code:
       0: aload_0
       1: invokespecial #463                // Method java/lang/Object."<init>":()V
       4: return

  protected static void processAttrCert7(org.bouncycastle.x509.X509AttributeCertificate, java.security.cert.CertPath, java.security.cert.CertPath, org.bouncycastle.jcajce.PKIXExtendedParameters, java.util.Set) throws java.security.cert.CertPathValidatorException;
    Code:
       0: aload_0
       1: invokeinterface #566,  1          // InterfaceMethod org/bouncycastle/x509/X509AttributeCertificate.getCriticalExtensionOIDs:()Ljava/util/Set;
       6: astore        5
       8: aload         5
      10: getstatic     #462                // Field TARGET_INFORMATION:Ljava/lang/String;
      13: invokeinterface #559,  2          // InterfaceMethod java/util/Set.contains:(Ljava/lang/Object;)Z
      18: ifeq          63
      21: aload_0
      22: getstatic     #462                // Field TARGET_INFORMATION:Ljava/lang/String;
      25: invokestatic  #523                // Method org/bouncycastle/jce/provider/CertPathValidatorUtilities.getExtensionValue:(Ljava/security/cert/X509Extension;Ljava/lang/String;)Lorg/bouncycastle/asn1/ASN1Primitive;
      28: invokestatic  #501                // Method org/bouncycastle/asn1/x509/TargetInformation.getInstance:(Ljava/lang/Object;)Lorg/bouncycastle/asn1/x509/TargetInformation;
      31: pop
      32: goto          63
      35: astore        6
      37: new           #269                // class org/bouncycastle/jce/exception/ExtCertPathValidatorException
      40: dup
      41: ldc           #29                 // String Target information extension could not be read.
      43: aload         6
      45: invokespecial #518                // Method org/bouncycastle/jce/exception/ExtCertPathValidatorException."<init>":(Ljava/lang/String;Ljava/lang/Throwable;)V
      48: athrow
      49: astore        6
      51: new           #269                // class org/bouncycastle/jce/exception/ExtCertPathValidatorException
      54: dup
      55: ldc           #29                 // String Target information extension could not be read.
      57: aload         6
      59: invokespecial #518                // Method org/bouncycastle/jce/exception/ExtCertPathValidatorException."<init>":(Ljava/lang/String;Ljava/lang/Throwable;)V
      62: athrow
      63: aload         5
      65: getstatic     #462                // Field TARGET_INFORMATION:Ljava/lang/String;
      68: invokeinterface #560,  2          // InterfaceMethod java/util/Set.remove:(Ljava/lang/Object;)Z
      73: pop
      74: aload         4
      76: invokeinterface #562,  1          // InterfaceMethod java/util/Set.iterator:()Ljava/util/Iterator;
      81: astore        6
      83: aload         6
      85: invokeinterface #554,  1          // InterfaceMethod java/util/Iterator.hasNext:()Z
      90: ifeq          114
      93: aload         6
      95: invokeinterface #555,  1          // InterfaceMethod java/util/Iterator.next:()Ljava/lang/Object;
     100: checkcast     #279                // class org/bouncycastle/x509/PKIXAttrCertChecker
     103: aload_0
     104: aload_1
     105: aload_2
     106: aload         5
     108: invokevirtual #549                // Method org/bouncycastle/x509/PKIXAttrCertChecker.check:(Lorg/bouncycastle/x509/X509AttributeCertificate;Ljava/security/cert/CertPath;Ljava/security/cert/CertPath;Ljava/util/Collection;)V
     111: goto          83
     114: aload         5
     116: invokeinterface #558,  1          // InterfaceMethod java/util/Set.isEmpty:()Z
     121: ifne          152
     124: new           #238                // class java/security/cert/CertPathValidatorException
     127: dup
     128: new           #229                // class java/lang/StringBuilder
     131: dup
     132: invokespecial #466                // Method java/lang/StringBuilder."<init>":()V
     135: ldc           #4                  // String Attribute certificate contains unsupported critical extensions:
     137: invokevirtual #469                // Method java/lang/StringBuilder.append:(Ljava/lang/String;)Ljava/lang/StringBuilder;
     140: aload         5
     142: invokevirtual #468                // Method java/lang/StringBuilder.append:(Ljava/lang/Object;)Ljava/lang/StringBuilder;
     145: invokevirtual #467                // Method java/lang/StringBuilder.toString:()Ljava/lang/String;
     148: invokespecial #476                // Method java/security/cert/CertPathValidatorException."<init>":(Ljava/lang/String;)V
     151: athrow
     152: return
    Exception table:
       from    to  target type
          21    32    35   Class org/bouncycastle/jce/provider/AnnotatedException
          21    32    49   Class java/lang/IllegalArgumentException

  protected static void checkCRLs(org.bouncycastle.x509.X509AttributeCertificate, org.bouncycastle.jcajce.PKIXExtendedParameters, java.security.cert.X509Certificate, java.util.Date, java.util.List, org.bouncycastle.jcajce.util.JcaJceHelper) throws java.security.cert.CertPathValidatorException;
    Code:
       0: aload_1
       1: invokevirtual #508                // Method org/bouncycastle/jcajce/PKIXExtendedParameters.isRevocationEnabled:()Z
       4: ifeq          591
       7: aload_0
       8: getstatic     #461                // Field NO_REV_AVAIL:Ljava/lang/String;
      11: invokeinterface #563,  2          // InterfaceMethod org/bouncycastle/x509/X509AttributeCertificate.getExtensionValue:(Ljava/lang/String;)[B
      16: ifnonnull     557
      19: aconst_null
      20: astore        6
      22: aload_0
      23: getstatic     #460                // Field CRL_DISTRIBUTION_POINTS:Ljava/lang/String;
      26: invokestatic  #523                // Method org/bouncycastle/jce/provider/CertPathValidatorUtilities.getExtensionValue:(Ljava/security/cert/X509Extension;Ljava/lang/String;)Lorg/bouncycastle/asn1/ASN1Primitive;
      29: invokestatic  #496                // Method org/bouncycastle/asn1/x509/CRLDistPoint.getInstance:(Ljava/lang/Object;)Lorg/bouncycastle/asn1/x509/CRLDistPoint;
      32: astore        6
      34: goto          51
      37: astore        7
      39: new           #238                // class java/security/cert/CertPathValidatorException
      42: dup
      43: ldc           #13                 // String CRL distribution point extension could not be read.
      45: aload         7
      47: invokespecial #477                // Method java/security/cert/CertPathValidatorException."<init>":(Ljava/lang/String;Ljava/lang/Throwable;)V
      50: athrow
      51: new           #245                // class java/util/ArrayList
      54: dup
      55: invokespecial #488                // Method java/util/ArrayList."<init>":()V
      58: astore        7
      60: aload         7
      62: aload         6
      64: aload_1
      65: invokevirtual #513                // Method org/bouncycastle/jcajce/PKIXExtendedParameters.getNamedCRLStoreMap:()Ljava/util/Map;
      68: aload_3
      69: aload         5
      71: invokestatic  #524                // Method org/bouncycastle/jce/provider/CertPathValidatorUtilities.getAdditionalStoresFromCRLDistributionPoint:(Lorg/bouncycastle/asn1/x509/CRLDistPoint;Ljava/util/Map;Ljava/util/Date;Lorg/bouncycastle/jcajce/util/JcaJceHelper;)Ljava/util/List;
      74: invokeinterface #556,  2          // InterfaceMethod java/util/List.addAll:(Ljava/util/Collection;)Z
      79: pop
      80: goto          97
      83: astore        8
      85: new           #238                // class java/security/cert/CertPathValidatorException
      88: dup
      89: ldc           #18                 // String No additional CRL locations could be decoded from CRL distribution point extension.
      91: aload         8
      93: invokespecial #477                // Method java/security/cert/CertPathValidatorException."<init>":(Ljava/lang/String;Ljava/lang/Throwable;)V
      96: athrow
      97: new           #268                // class org/bouncycastle/jcajce/PKIXExtendedParameters$Builder
     100: dup
     101: aload_1
     102: invokespecial #515                // Method org/bouncycastle/jcajce/PKIXExtendedParameters$Builder."<init>":(Lorg/bouncycastle/jcajce/PKIXExtendedParameters;)V
     105: astore        8
     107: aload         7
     109: invokeinterface #557,  1          // InterfaceMethod java/util/List.iterator:()Ljava/util/Iterator;
     114: astore        9
     116: aload         9
     118: invokeinterface #554,  1          // InterfaceMethod java/util/Iterator.hasNext:()Z
     123: ifeq          140
     126: aload         8
     128: aload         7
     130: checkcast     #261                // class org/bouncycastle/jcajce/PKIXCRLStore
     133: invokevirtual #516                // Method org/bouncycastle/jcajce/PKIXExtendedParameters$Builder.addCRLStore:(Lorg/bouncycastle/jcajce/PKIXCRLStore;)Lorg/bouncycastle/jcajce/PKIXExtendedParameters$Builder;
     136: pop
     137: goto          116
     140: aload         8
     142: invokevirtual #514                // Method org/bouncycastle/jcajce/PKIXExtendedParameters$Builder.build:()Lorg/bouncycastle/jcajce/PKIXExtendedParameters;
     145: astore_1
     146: new           #272                // class org/bouncycastle/jce/provider/CertStatus
     149: dup
     150: invokespecial #528                // Method org/bouncycastle/jce/provider/CertStatus."<init>":()V
     153: astore        9
     155: new           #276                // class org/bouncycastle/jce/provider/ReasonsMask
     158: dup
     159: invokespecial #542                // Method org/bouncycastle/jce/provider/ReasonsMask."<init>":()V
     162: astore        10
     164: aconst_null
     165: astore        11
     167: iconst_0
     168: istore        12
     170: aload         6
     172: ifnull        288
     175: aconst_null
     176: astore        13
     178: aload         6
     180: invokevirtual #495                // Method org/bouncycastle/asn1/x509/CRLDistPoint.getDistributionPoints:()[Lorg/bouncycastle/asn1/x509/DistributionPoint;
     183: astore        13
     185: goto          202
     188: astore        14
     190: new           #269                // class org/bouncycastle/jce/exception/ExtCertPathValidatorException
     193: dup
     194: ldc           #16                 // String Distribution points could not be read.
     196: aload         14
     198: invokespecial #518                // Method org/bouncycastle/jce/exception/ExtCertPathValidatorException."<init>":(Ljava/lang/String;Ljava/lang/Throwable;)V
     201: athrow
     202: iconst_0
     203: istore        14
     205: iload         14
     207: aload         13
     209: arraylength
     210: if_icmpge     270
     213: aload         9
     215: invokevirtual #527                // Method org/bouncycastle/jce/provider/CertStatus.getCertStatus:()I
     218: bipush        11
     220: if_icmpne     270
     223: aload         10
     225: invokevirtual #543                // Method org/bouncycastle/jce/provider/ReasonsMask.isAllReasons:()Z
     228: ifne          270
     231: aload_1
     232: invokevirtual #510                // Method org/bouncycastle/jcajce/PKIXExtendedParameters.clone:()Ljava/lang/Object;
     235: checkcast     #267                // class org/bouncycastle/jcajce/PKIXExtendedParameters
     238: astore        15
     240: aload         13
     242: iload         14
     244: aaload
     245: aload_0
     246: aload         15
     248: aload_3
     249: aload_2
     250: aload         9
     252: aload         10
     254: aload         4
     256: aload         5
     258: invokestatic  #541                // Method checkCRL:(Lorg/bouncycastle/asn1/x509/DistributionPoint;Lorg/bouncycastle/x509/X509AttributeCertificate;Lorg/bouncycastle/jcajce/PKIXExtendedParameters;Ljava/util/Date;Ljava/security/cert/X509Certificate;Lorg/bouncycastle/jce/provider/CertStatus;Lorg/bouncycastle/jce/provider/ReasonsMask;Ljava/util/List;Lorg/bouncycastle/jcajce/util/JcaJceHelper;)V
     261: iconst_1
     262: istore        12
     264: iinc          14, 1
     267: goto          205
     270: goto          288
     273: astore        14
     275: new           #270                // class org/bouncycastle/jce/provider/AnnotatedException
     278: dup
     279: ldc           #21                 // String No valid CRL for distribution point found.
     281: aload         14
     283: invokespecial #520                // Method org/bouncycastle/jce/provider/AnnotatedException."<init>":(Ljava/lang/String;Ljava/lang/Throwable;)V
     286: astore        11
     288: aload         9
     290: invokevirtual #527                // Method org/bouncycastle/jce/provider/CertStatus.getCertStatus:()I
     293: bipush        11
     295: if_icmpne     413
     298: aload         10
     300: invokevirtual #543                // Method org/bouncycastle/jce/provider/ReasonsMask.isAllReasons:()Z
     303: ifne          413
     306: aload_0
     307: invokestatic  #531                // Method org/bouncycastle/jce/provider/PrincipalUtils.getEncodedIssuerPrincipal:(Ljava/lang/Object;)Lorg/bouncycastle/asn1/x500/X500Name;
     310: astore        13
     312: goto          329
     315: astore        14
     317: new           #270                // class org/bouncycastle/jce/provider/AnnotatedException
     320: dup
     321: ldc           #17                 // String Issuer from certificate for CRL could not be reencoded.
     323: aload         14
     325: invokespecial #520                // Method org/bouncycastle/jce/provider/AnnotatedException."<init>":(Ljava/lang/String;Ljava/lang/Throwable;)V
     328: athrow
     329: new           #254                // class org/bouncycastle/asn1/x509/DistributionPoint
     332: dup
     333: new           #255                // class org/bouncycastle/asn1/x509/DistributionPointName
     336: dup
     337: iconst_0
     338: new           #258                // class org/bouncycastle/asn1/x509/GeneralNames
     341: dup
     342: new           #257                // class org/bouncycastle/asn1/x509/GeneralName
     345: dup
     346: iconst_4
     347: aload         13
     349: invokespecial #499                // Method org/bouncycastle/asn1/x509/GeneralName."<init>":(ILorg/bouncycastle/asn1/ASN1Encodable;)V
     352: invokespecial #500                // Method org/bouncycastle/asn1/x509/GeneralNames."<init>":(Lorg/bouncycastle/asn1/x509/GeneralName;)V
     355: invokespecial #498                // Method org/bouncycastle/asn1/x509/DistributionPointName."<init>":(ILorg/bouncycastle/asn1/ASN1Encodable;)V
     358: aconst_null
     359: aconst_null
     360: invokespecial #497                // Method org/bouncycastle/asn1/x509/DistributionPoint."<init>":(Lorg/bouncycastle/asn1/x509/DistributionPointName;Lorg/bouncycastle/asn1/x509/ReasonFlags;Lorg/bouncycastle/asn1/x509/GeneralNames;)V
     363: astore        14
     365: aload_1
     366: invokevirtual #510                // Method org/bouncycastle/jcajce/PKIXExtendedParameters.clone:()Ljava/lang/Object;
     369: checkcast     #267                // class org/bouncycastle/jcajce/PKIXExtendedParameters
     372: astore        15
     374: aload         14
     376: aload_0
     377: aload         15
     379: aload_3
     380: aload_2
     381: aload         9
     383: aload         10
     385: aload         4
     387: aload         5
     389: invokestatic  #541                // Method checkCRL:(Lorg/bouncycastle/asn1/x509/DistributionPoint;Lorg/bouncycastle/x509/X509AttributeCertificate;Lorg/bouncycastle/jcajce/PKIXExtendedParameters;Ljava/util/Date;Ljava/security/cert/X509Certificate;Lorg/bouncycastle/jce/provider/CertStatus;Lorg/bouncycastle/jce/provider/ReasonsMask;Ljava/util/List;Lorg/bouncycastle/jcajce/util/JcaJceHelper;)V
     392: iconst_1
     393: istore        12
     395: goto          413
     398: astore        13
     400: new           #270                // class org/bouncycastle/jce/provider/AnnotatedException
     403: dup
     404: ldc           #21                 // String No valid CRL for distribution point found.
     406: aload         13
     408: invokespecial #520                // Method org/bouncycastle/jce/provider/AnnotatedException."<init>":(Ljava/lang/String;Ljava/lang/Throwable;)V
     411: astore        11
     413: iload         12
     415: ifne          430
     418: new           #269                // class org/bouncycastle/jce/exception/ExtCertPathValidatorException
     421: dup
     422: ldc           #22                 // String No valid CRL found.
     424: aload         11
     426: invokespecial #518                // Method org/bouncycastle/jce/exception/ExtCertPathValidatorException."<init>":(Ljava/lang/String;Ljava/lang/Throwable;)V
     429: athrow
     430: aload         9
     432: invokevirtual #527                // Method org/bouncycastle/jce/provider/CertStatus.getCertStatus:()I
     435: bipush        11
     437: if_icmpeq     509
     440: new           #229                // class java/lang/StringBuilder
     443: dup
     444: invokespecial #466                // Method java/lang/StringBuilder."<init>":()V
     447: ldc           #10                 // String Attribute certificate revocation after
     449: invokevirtual #469                // Method java/lang/StringBuilder.append:(Ljava/lang/String;)Ljava/lang/StringBuilder;
     452: aload         9
     454: invokevirtual #530                // Method org/bouncycastle/jce/provider/CertStatus.getRevocationDate:()Ljava/util/Date;
     457: invokevirtual #468                // Method java/lang/StringBuilder.append:(Ljava/lang/Object;)Ljava/lang/StringBuilder;
     460: invokevirtual #467                // Method java/lang/StringBuilder.toString:()Ljava/lang/String;
     463: astore        13
     465: new           #229                // class java/lang/StringBuilder
     468: dup
     469: invokespecial #466                // Method java/lang/StringBuilder."<init>":()V
     472: aload         13
     474: invokevirtual #469                // Method java/lang/StringBuilder.append:(Ljava/lang/String;)Ljava/lang/StringBuilder;
     477: ldc           #1                  // String , reason:
     479: invokevirtual #469                // Method java/lang/StringBuilder.append:(Ljava/lang/String;)Ljava/lang/StringBuilder;
     482: getstatic     #458                // Field org/bouncycastle/jce/provider/RFC3280CertPathUtilities.crlReasons:[Ljava/lang/String;
     485: aload         9
     487: invokevirtual #527                // Method org/bouncycastle/jce/provider/CertStatus.getCertStatus:()I
     490: aaload
     491: invokevirtual #469                // Method java/lang/StringBuilder.append:(Ljava/lang/String;)Ljava/lang/StringBuilder;
     494: invokevirtual #467                // Method java/lang/StringBuilder.toString:()Ljava/lang/String;
     497: astore        13
     499: new           #238                // class java/security/cert/CertPathValidatorException
     502: dup
     503: aload         13
     505: invokespecial #476                // Method java/security/cert/CertPathValidatorException."<init>":(Ljava/lang/String;)V
     508: athrow
     509: aload         10
     511: invokevirtual #543                // Method org/bouncycastle/jce/provider/ReasonsMask.isAllReasons:()Z
     514: ifne          534
     517: aload         9
     519: invokevirtual #527                // Method org/bouncycastle/jce/provider/CertStatus.getCertStatus:()I
     522: bipush        11
     524: if_icmpne     534
     527: aload         9
     529: bipush        12
     531: invokevirtual #529                // Method org/bouncycastle/jce/provider/CertStatus.setCertStatus:(I)V
     534: aload         9
     536: invokevirtual #527                // Method org/bouncycastle/jce/provider/CertStatus.getCertStatus:()I
     539: bipush        12
     541: if_icmpne     554
     544: new           #238                // class java/security/cert/CertPathValidatorException
     547: dup
     548: ldc           #11                 // String Attribute certificate status could not be determined.
     550: invokespecial #476                // Method java/security/cert/CertPathValidatorException."<init>":(Ljava/lang/String;)V
     553: athrow
     554: goto          591
     557: aload_0
     558: getstatic     #460                // Field CRL_DISTRIBUTION_POINTS:Ljava/lang/String;
     561: invokeinterface #563,  2          // InterfaceMethod org/bouncycastle/x509/X509AttributeCertificate.getExtensionValue:(Ljava/lang/String;)[B
     566: ifnonnull     581
     569: aload_0
     570: getstatic     #459                // Field AUTHORITY_INFO_ACCESS:Ljava/lang/String;
     573: invokeinterface #563,  2          // InterfaceMethod org/bouncycastle/x509/X509AttributeCertificate.getExtensionValue:(Ljava/lang/String;)[B
     578: ifnull        591
     581: new           #238                // class java/security/cert/CertPathValidatorException
     584: dup
     585: ldc           #19                 // String No rev avail extension is set, but also an AC revocation pointer.
     587: invokespecial #476                // Method java/security/cert/CertPathValidatorException."<init>":(Ljava/lang/String;)V
     590: athrow
     591: return
    Exception table:
       from    to  target type
          22    34    37   Class org/bouncycastle/jce/provider/AnnotatedException
          60    80    83   Class org/bouncycastle/jce/provider/AnnotatedException
         178   185   188   Class java/lang/Exception
         202   270   273   Class org/bouncycastle/jce/provider/AnnotatedException
         306   312   315   Class java/lang/Exception
         306   395   398   Class org/bouncycastle/jce/provider/AnnotatedException

  protected static void additionalChecks(org.bouncycastle.x509.X509AttributeCertificate, java.util.Set, java.util.Set) throws java.security.cert.CertPathValidatorException;
    Code:
       0: aload_1
       1: invokeinterface #562,  1          // InterfaceMethod java/util/Set.iterator:()Ljava/util/Iterator;
       6: astore_3
       7: aload_3
       8: invokeinterface #554,  1          // InterfaceMethod java/util/Iterator.hasNext:()Z
      13: ifeq          74
      16: aload_3
      17: invokeinterface #555,  1          // InterfaceMethod java/util/Iterator.next:()Ljava/lang/Object;
      22: checkcast     #228                // class java/lang/String
      25: astore        4
      27: aload_0
      28: aload         4
      30: invokeinterface #568,  2          // InterfaceMethod org/bouncycastle/x509/X509AttributeCertificate.getAttributes:(Ljava/lang/String;)[Lorg/bouncycastle/x509/X509Attribute;
      35: ifnull        71
      38: new           #238                // class java/security/cert/CertPathValidatorException
      41: dup
      42: new           #229                // class java/lang/StringBuilder
      45: dup
      46: invokespecial #466                // Method java/lang/StringBuilder."<init>":()V
      49: ldc           #3                  // String Attribute certificate contains prohibited attribute:
      51: invokevirtual #469                // Method java/lang/StringBuilder.append:(Ljava/lang/String;)Ljava/lang/StringBuilder;
      54: aload         4
      56: invokevirtual #469                // Method java/lang/StringBuilder.append:(Ljava/lang/String;)Ljava/lang/StringBuilder;
      59: ldc           #2                  // String .
      61: invokevirtual #469                // Method java/lang/StringBuilder.append:(Ljava/lang/String;)Ljava/lang/StringBuilder;
      64: invokevirtual #467                // Method java/lang/StringBuilder.toString:()Ljava/lang/String;
      67: invokespecial #476                // Method java/security/cert/CertPathValidatorException."<init>":(Ljava/lang/String;)V
      70: athrow
      71: goto          7
      74: aload_2
      75: invokeinterface #562,  1          // InterfaceMethod java/util/Set.iterator:()Ljava/util/Iterator;
      80: astore_3
      81: aload_3
      82: invokeinterface #554,  1          // InterfaceMethod java/util/Iterator.hasNext:()Z
      87: ifeq          148
      90: aload_3
      91: invokeinterface #555,  1          // InterfaceMethod java/util/Iterator.next:()Ljava/lang/Object;
      96: checkcast     #228                // class java/lang/String
      99: astore        4
     101: aload_0
     102: aload         4
     104: invokeinterface #568,  2          // InterfaceMethod org/bouncycastle/x509/X509AttributeCertificate.getAttributes:(Ljava/lang/String;)[Lorg/bouncycastle/x509/X509Attribute;
     109: ifnonnull     145
     112: new           #238                // class java/security/cert/CertPathValidatorException
     115: dup
     116: new           #229                // class java/lang/StringBuilder
     119: dup
     120: invokespecial #466                // Method java/lang/StringBuilder."<init>":()V
     123: ldc           #5                  // String Attribute certificate does not contain necessary attribute:
     125: invokevirtual #469                // Method java/lang/StringBuilder.append:(Ljava/lang/String;)Ljava/lang/StringBuilder;
     128: aload         4
     130: invokevirtual #469                // Method java/lang/StringBuilder.append:(Ljava/lang/String;)Ljava/lang/StringBuilder;
     133: ldc           #2                  // String .
     135: invokevirtual #469                // Method java/lang/StringBuilder.append:(Ljava/lang/String;)Ljava/lang/StringBuilder;
     138: invokevirtual #467                // Method java/lang/StringBuilder.toString:()Ljava/lang/String;
     141: invokespecial #476                // Method java/security/cert/CertPathValidatorException."<init>":(Ljava/lang/String;)V
     144: athrow
     145: goto          81
     148: return

  protected static void processAttrCert5(org.bouncycastle.x509.X509AttributeCertificate, org.bouncycastle.jcajce.PKIXExtendedParameters) throws java.security.cert.CertPathValidatorException;
    Code:
       0: aload_0
       1: aload_1
       2: invokestatic  #521                // Method org/bouncycastle/jce/provider/CertPathValidatorUtilities.getValidDate:(Lorg/bouncycastle/jcajce/PKIXExtendedParameters;)Ljava/util/Date;
       5: invokeinterface #565,  2          // InterfaceMethod org/bouncycastle/x509/X509AttributeCertificate.checkValidity:(Ljava/util/Date;)V
      10: goto          37
      13: astore_2
      14: new           #269                // class org/bouncycastle/jce/exception/ExtCertPathValidatorException
      17: dup
      18: ldc           #6                  // String Attribute certificate is not valid.
      20: aload_2
      21: invokespecial #518                // Method org/bouncycastle/jce/exception/ExtCertPathValidatorException."<init>":(Ljava/lang/String;Ljava/lang/Throwable;)V
      24: athrow
      25: astore_2
      26: new           #269                // class org/bouncycastle/jce/exception/ExtCertPathValidatorException
      29: dup
      30: ldc           #6                  // String Attribute certificate is not valid.
      32: aload_2
      33: invokespecial #518                // Method org/bouncycastle/jce/exception/ExtCertPathValidatorException."<init>":(Ljava/lang/String;Ljava/lang/Throwable;)V
      36: athrow
      37: return
    Exception table:
       from    to  target type
           0    10    13   Class java/security/cert/CertificateExpiredException
           0    10    25   Class java/security/cert/CertificateNotYetValidException

  protected static void processAttrCert4(java.security.cert.X509Certificate, java.util.Set) throws java.security.cert.CertPathValidatorException;
    Code:
       0: aload_1
       1: astore_2
       2: iconst_0
       3: istore_3
       4: aload_2
       5: invokeinterface #562,  1          // InterfaceMethod java/util/Set.iterator:()Ljava/util/Iterator;
      10: astore        4
      12: aload         4
      14: invokeinterface #554,  1          // InterfaceMethod java/util/Iterator.hasNext:()Z
      19: ifeq          71
      22: aload         4
      24: invokeinterface #555,  1          // InterfaceMethod java/util/Iterator.next:()Ljava/lang/Object;
      29: checkcast     #241                // class java/security/cert/TrustAnchor
      32: astore        5
      34: aload_0
      35: invokevirtual #487                // Method java/security/cert/X509Certificate.getSubjectX500Principal:()Ljavax/security/auth/x500/X500Principal;
      38: ldc           #27                 // String RFC2253
      40: invokevirtual #493                // Method javax/security/auth/x500/X500Principal.getName:(Ljava/lang/String;)Ljava/lang/String;
      43: aload         5
      45: invokevirtual #478                // Method java/security/cert/TrustAnchor.getCAName:()Ljava/lang/String;
      48: invokevirtual #465                // Method java/lang/String.equals:(Ljava/lang/Object;)Z
      51: ifne          66
      54: aload_0
      55: aload         5
      57: invokevirtual #479                // Method java/security/cert/TrustAnchor.getTrustedCert:()Ljava/security/cert/X509Certificate;
      60: invokevirtual #486                // Method java/security/cert/X509Certificate.equals:(Ljava/lang/Object;)Z
      63: ifeq          68
      66: iconst_1
      67: istore_3
      68: goto          12
      71: iload_3
      72: ifne          85
      75: new           #238                // class java/security/cert/CertPathValidatorException
      78: dup
      79: ldc           #8                  // String Attribute certificate issuer is not directly trusted.
      81: invokespecial #476                // Method java/security/cert/CertPathValidatorException."<init>":(Ljava/lang/String;)V
      84: athrow
      85: return

  protected static void processAttrCert3(java.security.cert.X509Certificate, org.bouncycastle.jcajce.PKIXExtendedParameters) throws java.security.cert.CertPathValidatorException;
    Code:
       0: aload_0
       1: invokevirtual #485                // Method java/security/cert/X509Certificate.getKeyUsage:()[Z
       4: astore_2
       5: aload_2
       6: ifnull        42
       9: aload_2
      10: arraylength
      11: ifle          20
      14: aload_2
      15: iconst_0
      16: baload
      17: ifne          42
      20: aload_2
      21: arraylength
      22: iconst_1
      23: if_icmple     32
      26: aload_2
      27: iconst_1
      28: baload
      29: ifne          42
      32: new           #238                // class java/security/cert/CertPathValidatorException
      35: dup
      36: ldc           #9                  // String Attribute certificate issuer public key cannot be used to validate digital signatures.
      38: invokespecial #476                // Method java/security/cert/CertPathValidatorException."<init>":(Ljava/lang/String;)V
      41: athrow
      42: aload_0
      43: invokevirtual #484                // Method java/security/cert/X509Certificate.getBasicConstraints:()I
      46: iconst_m1
      47: if_icmpeq     60
      50: new           #238                // class java/security/cert/CertPathValidatorException
      53: dup
      54: ldc           #7                  // String Attribute certificate issuer is also a public key certificate issuer.
      56: invokespecial #476                // Method java/security/cert/CertPathValidatorException."<init>":(Ljava/lang/String;)V
      59: athrow
      60: return

  protected static java.security.cert.CertPathValidatorResult processAttrCert2(java.security.cert.CertPath, org.bouncycastle.jcajce.PKIXExtendedParameters) throws java.security.cert.CertPathValidatorException;
    Code:
       0: aconst_null
       1: astore_2
       2: ldc           #23                 // String PKIX
       4: ldc           #12                 // String BC
       6: invokestatic  #474                // Method java/security/cert/CertPathValidator.getInstance:(Ljava/lang/String;Ljava/lang/String;)Ljava/security/cert/CertPathValidator;
       9: astore_2
      10: goto          37
      13: astore_3
      14: new           #269                // class org/bouncycastle/jce/exception/ExtCertPathValidatorException
      17: dup
      18: ldc           #28                 // String Support class could not be created.
      20: aload_3
      21: invokespecial #518                // Method org/bouncycastle/jce/exception/ExtCertPathValidatorException."<init>":(Ljava/lang/String;Ljava/lang/Throwable;)V
      24: athrow
      25: astore_3
      26: new           #269                // class org/bouncycastle/jce/exception/ExtCertPathValidatorException
      29: dup
      30: ldc           #28                 // String Support class could not be created.
      32: aload_3
      33: invokespecial #518                // Method org/bouncycastle/jce/exception/ExtCertPathValidatorException."<init>":(Ljava/lang/String;Ljava/lang/Throwable;)V
      36: athrow
      37: aload_2
      38: aload_0
      39: aload_1
      40: invokevirtual #475                // Method java/security/cert/CertPathValidator.validate:(Ljava/security/cert/CertPath;Ljava/security/cert/CertPathParameters;)Ljava/security/cert/CertPathValidatorResult;
      43: areturn
      44: astore_3
      45: new           #269                // class org/bouncycastle/jce/exception/ExtCertPathValidatorException
      48: dup
      49: ldc           #14                 // String Certification path for issuer certificate of attribute certificate could not be validated.
      51: aload_3
      52: invokespecial #518                // Method org/bouncycastle/jce/exception/ExtCertPathValidatorException."<init>":(Ljava/lang/String;Ljava/lang/Throwable;)V
      55: athrow
      56: astore_3
      57: new           #227                // class java/lang/RuntimeException
      60: dup
      61: aload_3
      62: invokevirtual #471                // Method java/security/InvalidAlgorithmParameterException.getMessage:()Ljava/lang/String;
      65: invokespecial #464                // Method java/lang/RuntimeException."<init>":(Ljava/lang/String;)V
      68: athrow
    Exception table:
       from    to  target type
           2    10    13   Class java/security/NoSuchProviderException
           2    10    25   Class java/security/NoSuchAlgorithmException
          37    43    44   Class java/security/cert/CertPathValidatorException
          37    43    56   Class java/security/InvalidAlgorithmParameterException

  protected static java.security.cert.CertPath processAttrCert1(org.bouncycastle.x509.X509AttributeCertificate, org.bouncycastle.jcajce.PKIXExtendedParameters) throws java.security.cert.CertPathValidatorException;
    Code:
       0: aconst_null
       1: astore_2
       2: new           #247                // class java/util/HashSet
       5: dup
       6: invokespecial #491                // Method java/util/HashSet."<init>":()V
       9: astore_3
      10: aload_0
      11: invokeinterface #567,  1          // InterfaceMethod org/bouncycastle/x509/X509AttributeCertificate.getHolder:()Lorg/bouncycastle/x509/AttributeCertificateHolder;
      16: invokevirtual #548                // Method org/bouncycastle/x509/AttributeCertificateHolder.getIssuer:()[Ljava/security/Principal;
      19: ifnull        176
      22: new           #243                // class java/security/cert/X509CertSelector
      25: dup
      26: invokespecial #481                // Method java/security/cert/X509CertSelector."<init>":()V
      29: astore        4
      31: aload         4
      33: aload_0
      34: invokeinterface #567,  1          // InterfaceMethod org/bouncycastle/x509/X509AttributeCertificate.getHolder:()Lorg/bouncycastle/x509/AttributeCertificateHolder;
      39: invokevirtual #546                // Method org/bouncycastle/x509/AttributeCertificateHolder.getSerialNumber:()Ljava/math/BigInteger;
      42: invokevirtual #483                // Method java/security/cert/X509CertSelector.setSerialNumber:(Ljava/math/BigInteger;)V
      45: aload_0
      46: invokeinterface #567,  1          // InterfaceMethod org/bouncycastle/x509/X509AttributeCertificate.getHolder:()Lorg/bouncycastle/x509/AttributeCertificateHolder;
      51: invokevirtual #548                // Method org/bouncycastle/x509/AttributeCertificateHolder.getIssuer:()[Ljava/security/Principal;
      54: astore        5
      56: iconst_0
      57: istore        6
      59: iload         6
      61: aload         5
      63: arraylength
      64: if_icmpge     157
      67: aload         5
      69: iload         6
      71: aaload
      72: instanceof    #251                // class javax/security/auth/x500/X500Principal
      75: ifeq          94
      78: aload         4
      80: aload         5
      82: iload         6
      84: aaload
      85: checkcast     #251                // class javax/security/auth/x500/X500Principal
      88: invokevirtual #492                // Method javax/security/auth/x500/X500Principal.getEncoded:()[B
      91: invokevirtual #482                // Method java/security/cert/X509CertSelector.setIssuer:([B)V
      94: aload_3
      95: new           #264                // class org/bouncycastle/jcajce/PKIXCertStoreSelector$Builder
      98: dup
      99: aload         4
     101: invokespecial #503                // Method org/bouncycastle/jcajce/PKIXCertStoreSelector$Builder."<init>":(Ljava/security/cert/CertSelector;)V
     104: invokevirtual #504                // Method org/bouncycastle/jcajce/PKIXCertStoreSelector$Builder.build:()Lorg/bouncycastle/jcajce/PKIXCertStoreSelector;
     107: aload_1
     108: invokevirtual #512                // Method org/bouncycastle/jcajce/PKIXExtendedParameters.getCertStores:()Ljava/util/List;
     111: invokestatic  #522                // Method org/bouncycastle/jce/provider/CertPathValidatorUtilities.findCertificates:(Lorg/bouncycastle/jcajce/PKIXCertStoreSelector;Ljava/util/List;)Ljava/util/Collection;
     114: invokeinterface #561,  2          // InterfaceMethod java/util/Set.addAll:(Ljava/util/Collection;)Z
     119: pop
     120: goto          151
     123: astore        7
     125: new           #269                // class org/bouncycastle/jce/exception/ExtCertPathValidatorException
     128: dup
     129: ldc           #24                 // String Public key certificate for attribute certificate cannot be searched.
     131: aload         7
     133: invokespecial #518                // Method org/bouncycastle/jce/exception/ExtCertPathValidatorException."<init>":(Ljava/lang/String;Ljava/lang/Throwable;)V
     136: athrow
     137: astore        7
     139: new           #269                // class org/bouncycastle/jce/exception/ExtCertPathValidatorException
     142: dup
     143: ldc           #30                 // String Unable to encode X500 principal.
     145: aload         7
     147: invokespecial #518                // Method org/bouncycastle/jce/exception/ExtCertPathValidatorException."<init>":(Ljava/lang/String;Ljava/lang/Throwable;)V
     150: athrow
     151: iinc          6, 1
     154: goto          59
     157: aload_3
     158: invokeinterface #558,  1          // InterfaceMethod java/util/Set.isEmpty:()Z
     163: ifeq          176
     166: new           #238                // class java/security/cert/CertPathValidatorException
     169: dup
     170: ldc           #25                 // String Public key certificate specified in base certificate ID for attribute certificate cannot be found.
     172: invokespecial #476                // Method java/security/cert/CertPathValidatorException."<init>":(Ljava/lang/String;)V
     175: athrow
     176: aload_0
     177: invokeinterface #567,  1          // InterfaceMethod org/bouncycastle/x509/X509AttributeCertificate.getHolder:()Lorg/bouncycastle/x509/AttributeCertificateHolder;
     182: invokevirtual #547                // Method org/bouncycastle/x509/AttributeCertificateHolder.getEntityNames:()[Ljava/security/Principal;
     185: ifnull        328
     188: new           #281                // class org/bouncycastle/x509/X509CertStoreSelector
     191: dup
     192: invokespecial #550                // Method org/bouncycastle/x509/X509CertStoreSelector."<init>":()V
     195: astore        4
     197: aload_0
     198: invokeinterface #567,  1          // InterfaceMethod org/bouncycastle/x509/X509AttributeCertificate.getHolder:()Lorg/bouncycastle/x509/AttributeCertificateHolder;
     203: invokevirtual #547                // Method org/bouncycastle/x509/AttributeCertificateHolder.getEntityNames:()[Ljava/security/Principal;
     206: astore        5
     208: iconst_0
     209: istore        6
     211: iload         6
     213: aload         5
     215: arraylength
     216: if_icmpge     309
     219: aload         5
     221: iload         6
     223: aaload
     224: instanceof    #251                // class javax/security/auth/x500/X500Principal
     227: ifeq          246
     230: aload         4
     232: aload         5
     234: iload         6
     236: aaload
     237: checkcast     #251                // class javax/security/auth/x500/X500Principal
     240: invokevirtual #492                // Method javax/security/auth/x500/X500Principal.getEncoded:()[B
     243: invokevirtual #551                // Method org/bouncycastle/x509/X509CertStoreSelector.setIssuer:([B)V
     246: aload_3
     247: new           #264                // class org/bouncycastle/jcajce/PKIXCertStoreSelector$Builder
     250: dup
     251: aload         4
     253: invokespecial #503                // Method org/bouncycastle/jcajce/PKIXCertStoreSelector$Builder."<init>":(Ljava/security/cert/CertSelector;)V
     256: invokevirtual #504                // Method org/bouncycastle/jcajce/PKIXCertStoreSelector$Builder.build:()Lorg/bouncycastle/jcajce/PKIXCertStoreSelector;
     259: aload_1
     260: invokevirtual #512                // Method org/bouncycastle/jcajce/PKIXExtendedParameters.getCertStores:()Ljava/util/List;
     263: invokestatic  #522                // Method org/bouncycastle/jce/provider/CertPathValidatorUtilities.findCertificates:(Lorg/bouncycastle/jcajce/PKIXCertStoreSelector;Ljava/util/List;)Ljava/util/Collection;
     266: invokeinterface #561,  2          // InterfaceMethod java/util/Set.addAll:(Ljava/util/Collection;)Z
     271: pop
     272: goto          303
     275: astore        7
     277: new           #269                // class org/bouncycastle/jce/exception/ExtCertPathValidatorException
     280: dup
     281: ldc           #24                 // String Public key certificate for attribute certificate cannot be searched.
     283: aload         7
     285: invokespecial #518                // Method org/bouncycastle/jce/exception/ExtCertPathValidatorException."<init>":(Ljava/lang/String;Ljava/lang/Throwable;)V
     288: athrow
     289: astore        7
     291: new           #269                // class org/bouncycastle/jce/exception/ExtCertPathValidatorException
     294: dup
     295: ldc           #30                 // String Unable to encode X500 principal.
     297: aload         7
     299: invokespecial #518                // Method org/bouncycastle/jce/exception/ExtCertPathValidatorException."<init>":(Ljava/lang/String;Ljava/lang/Throwable;)V
     302: athrow
     303: iinc          6, 1
     306: goto          211
     309: aload_3
     310: invokeinterface #558,  1          // InterfaceMethod java/util/Set.isEmpty:()Z
     315: ifeq          328
     318: new           #238                // class java/security/cert/CertPathValidatorException
     321: dup
     322: ldc           #26                 // String Public key certificate specified in entity name for attribute certificate cannot be found.
     324: invokespecial #476                // Method java/security/cert/CertPathValidatorException."<init>":(Ljava/lang/String;)V
     327: athrow
     328: new           #268                // class org/bouncycastle/jcajce/PKIXExtendedParameters$Builder
     331: dup
     332: aload_1
     333: invokespecial #515                // Method org/bouncycastle/jcajce/PKIXExtendedParameters$Builder."<init>":(Lorg/bouncycastle/jcajce/PKIXExtendedParameters;)V
     336: astore        4
     338: aconst_null
     339: astore        5
     341: aload_3
     342: invokeinterface #562,  1          // InterfaceMethod java/util/Set.iterator:()Ljava/util/Iterator;
     347: astore        6
     349: aload         6
     351: invokeinterface #554,  1          // InterfaceMethod java/util/Iterator.hasNext:()Z
     356: ifeq          504
     359: new           #281                // class org/bouncycastle/x509/X509CertStoreSelector
     362: dup
     363: invokespecial #550                // Method org/bouncycastle/x509/X509CertStoreSelector."<init>":()V
     366: astore        7
     368: aload         7
     370: aload         6
     372: invokeinterface #555,  1          // InterfaceMethod java/util/Iterator.next:()Ljava/lang/Object;
     377: checkcast     #244                // class java/security/cert/X509Certificate
     380: invokevirtual #552                // Method org/bouncycastle/x509/X509CertStoreSelector.setCertificate:(Ljava/security/cert/X509Certificate;)V
     383: aload         4
     385: new           #264                // class org/bouncycastle/jcajce/PKIXCertStoreSelector$Builder
     388: dup
     389: aload         7
     391: invokespecial #503                // Method org/bouncycastle/jcajce/PKIXCertStoreSelector$Builder."<init>":(Ljava/security/cert/CertSelector;)V
     394: invokevirtual #504                // Method org/bouncycastle/jcajce/PKIXCertStoreSelector$Builder.build:()Lorg/bouncycastle/jcajce/PKIXCertStoreSelector;
     397: invokevirtual #517                // Method org/bouncycastle/jcajce/PKIXExtendedParameters$Builder.setTargetConstraints:(Lorg/bouncycastle/jcajce/PKIXCertStoreSelector;)Lorg/bouncycastle/jcajce/PKIXExtendedParameters$Builder;
     400: pop
     401: aconst_null
     402: astore        8
     404: ldc           #23                 // String PKIX
     406: ldc           #12                 // String BC
     408: invokestatic  #473                // Method java/security/cert/CertPathBuilder.getInstance:(Ljava/lang/String;Ljava/lang/String;)Ljava/security/cert/CertPathBuilder;
     411: astore        8
     413: goto          444
     416: astore        9
     418: new           #269                // class org/bouncycastle/jce/exception/ExtCertPathValidatorException
     421: dup
     422: ldc           #28                 // String Support class could not be created.
     424: aload         9
     426: invokespecial #518                // Method org/bouncycastle/jce/exception/ExtCertPathValidatorException."<init>":(Ljava/lang/String;Ljava/lang/Throwable;)V
     429: athrow
     430: astore        9
     432: new           #269                // class org/bouncycastle/jce/exception/ExtCertPathValidatorException
     435: dup
     436: ldc           #28                 // String Support class could not be created.
     438: aload         9
     440: invokespecial #518                // Method org/bouncycastle/jce/exception/ExtCertPathValidatorException."<init>":(Ljava/lang/String;Ljava/lang/Throwable;)V
     443: athrow
     444: aload         8
     446: new           #266                // class org/bouncycastle/jcajce/PKIXExtendedBuilderParameters$Builder
     449: dup
     450: aload         4
     452: invokevirtual #514                // Method org/bouncycastle/jcajce/PKIXExtendedParameters$Builder.build:()Lorg/bouncycastle/jcajce/PKIXExtendedParameters;
     455: invokespecial #506                // Method org/bouncycastle/jcajce/PKIXExtendedBuilderParameters$Builder."<init>":(Lorg/bouncycastle/jcajce/PKIXExtendedParameters;)V
     458: invokevirtual #505                // Method org/bouncycastle/jcajce/PKIXExtendedBuilderParameters$Builder.build:()Lorg/bouncycastle/jcajce/PKIXExtendedBuilderParameters;
     461: invokevirtual #472                // Method java/security/cert/CertPathBuilder.build:(Ljava/security/cert/CertPathParameters;)Ljava/security/cert/CertPathBuilderResult;
     464: astore_2
     465: goto          501
     468: astore        9
     470: new           #269                // class org/bouncycastle/jce/exception/ExtCertPathValidatorException
     473: dup
     474: ldc           #15                 // String Certification path for public key certificate of attribute certificate could not be build.
     476: aload         9
     478: invokespecial #518                // Method org/bouncycastle/jce/exception/ExtCertPathValidatorException."<init>":(Ljava/lang/String;Ljava/lang/Throwable;)V
     481: astore        5
     483: goto          501
     486: astore        9
     488: new           #227                // class java/lang/RuntimeException
     491: dup
     492: aload         9
     494: invokevirtual #471                // Method java/security/InvalidAlgorithmParameterException.getMessage:()Ljava/lang/String;
     497: invokespecial #464                // Method java/lang/RuntimeException."<init>":(Ljava/lang/String;)V
     500: athrow
     501: goto          349
     504: aload         5
     506: ifnull        512
     509: aload         5
     511: athrow
     512: aload_2
     513: invokeinterface #553,  1          // InterfaceMethod java/security/cert/CertPathBuilderResult.getCertPath:()Ljava/security/cert/CertPath;
     518: areturn
    Exception table:
       from    to  target type
          67   120   123   Class org/bouncycastle/jce/provider/AnnotatedException
          67   120   137   Class java/io/IOException
         219   272   275   Class org/bouncycastle/jce/provider/AnnotatedException
         219   272   289   Class java/io/IOException
         404   413   416   Class java/security/NoSuchProviderException
         404   413   430   Class java/security/NoSuchAlgorithmException
         444   465   468   Class java/security/cert/CertPathBuilderException
         444   465   486   Class java/security/InvalidAlgorithmParameterException

  private static void checkCRL(org.bouncycastle.asn1.x509.DistributionPoint, org.bouncycastle.x509.X509AttributeCertificate, org.bouncycastle.jcajce.PKIXExtendedParameters, java.util.Date, java.security.cert.X509Certificate, org.bouncycastle.jce.provider.CertStatus, org.bouncycastle.jce.provider.ReasonsMask, java.util.List, org.bouncycastle.jcajce.util.JcaJceHelper) throws org.bouncycastle.jce.provider.AnnotatedException, org.bouncycastle.jce.provider.RecoverableCertPathValidatorException;
    Code:
       0: aload_1
       1: getstatic     #457                // Field org/bouncycastle/asn1/x509/X509Extensions.NoRevAvail:Lorg/bouncycastle/asn1/ASN1ObjectIdentifier;
       4: invokevirtual #494                // Method org/bouncycastle/asn1/ASN1ObjectIdentifier.getId:()Ljava/lang/String;
       7: invokeinterface #563,  2          // InterfaceMethod org/bouncycastle/x509/X509AttributeCertificate.getExtensionValue:(Ljava/lang/String;)[B
      12: ifnull        16
      15: return
      16: new           #246                // class java/util/Date
      19: dup
      20: invokestatic  #470                // Method java/lang/System.currentTimeMillis:()J
      23: invokespecial #490                // Method java/util/Date."<init>":(J)V
      26: astore        9
      28: aload_3
      29: invokevirtual #489                // Method java/util/Date.getTime:()J
      32: aload         9
      34: invokevirtual #489                // Method java/util/Date.getTime:()J
      37: lcmp
      38: ifle          51
      41: new           #270                // class org/bouncycastle/jce/provider/AnnotatedException
      44: dup
      45: ldc           #31                 // String Validation time is in future.
      47: invokespecial #519                // Method org/bouncycastle/jce/provider/AnnotatedException."<init>":(Ljava/lang/String;)V
      50: athrow
      51: new           #262                // class org/bouncycastle/jcajce/PKIXCertRevocationCheckerParameters
      54: dup
      55: aload_2
      56: aload_3
      57: aconst_null
      58: iconst_m1
      59: aload         4
      61: aconst_null
      62: invokespecial #502                // Method org/bouncycastle/jcajce/PKIXCertRevocationCheckerParameters."<init>":(Lorg/bouncycastle/jcajce/PKIXExtendedParameters;Ljava/util/Date;Ljava/security/cert/CertPath;ILjava/security/cert/X509Certificate;Ljava/security/PublicKey;)V
      65: astore        10
      67: aload         10
      69: aload_0
      70: aload_1
      71: aload         9
      73: aload_2
      74: invokestatic  #525                // Method org/bouncycastle/jce/provider/CertPathValidatorUtilities.getCompleteCRLs:(Lorg/bouncycastle/jcajce/PKIXCertRevocationCheckerParameters;Lorg/bouncycastle/asn1/x509/DistributionPoint;Ljava/lang/Object;Ljava/util/Date;Lorg/bouncycastle/jcajce/PKIXExtendedParameters;)Ljava/util/Set;
      77: astore        11
      79: iconst_0
      80: istore        12
      82: aconst_null
      83: astore        13
      85: aload         11
      87: invokeinterface #562,  1          // InterfaceMethod java/util/Set.iterator:()Ljava/util/Iterator;
      92: astore        14
      94: aload         14
      96: invokeinterface #554,  1          // InterfaceMethod java/util/Iterator.hasNext:()Z
     101: ifeq          336
     104: aload         5
     106: invokevirtual #527                // Method org/bouncycastle/jce/provider/CertStatus.getCertStatus:()I
     109: bipush        11
     111: if_icmpne     336
     114: aload         6
     116: invokevirtual #543                // Method org/bouncycastle/jce/provider/ReasonsMask.isAllReasons:()Z
     119: ifne          336
     122: aload         14
     124: invokeinterface #555,  1          // InterfaceMethod java/util/Iterator.next:()Ljava/lang/Object;
     129: checkcast     #242                // class java/security/cert/X509CRL
     132: astore        15
     134: aload         15
     136: aload_0
     137: invokestatic  #537                // Method org/bouncycastle/jce/provider/RFC3280CertPathUtilities.processCRLD:(Ljava/security/cert/X509CRL;Lorg/bouncycastle/asn1/x509/DistributionPoint;)Lorg/bouncycastle/jce/provider/ReasonsMask;
     140: astore        16
     142: aload         16
     144: aload         6
     146: invokevirtual #545                // Method org/bouncycastle/jce/provider/ReasonsMask.hasNewReasons:(Lorg/bouncycastle/jce/provider/ReasonsMask;)Z
     149: ifne          155
     152: goto          94
     155: aload         15
     157: aload_1
     158: aconst_null
     159: aconst_null
     160: aload_2
     161: aload         7
     163: aload         8
     165: invokestatic  #540                // Method org/bouncycastle/jce/provider/RFC3280CertPathUtilities.processCRLF:(Ljava/security/cert/X509CRL;Ljava/lang/Object;Ljava/security/cert/X509Certificate;Ljava/security/PublicKey;Lorg/bouncycastle/jcajce/PKIXExtendedParameters;Ljava/util/List;Lorg/bouncycastle/jcajce/util/JcaJceHelper;)Ljava/util/Set;
     168: astore        17
     170: aload         15
     172: aload         17
     174: invokestatic  #532                // Method org/bouncycastle/jce/provider/RFC3280CertPathUtilities.processCRLG:(Ljava/security/cert/X509CRL;Ljava/util/Set;)Ljava/security/PublicKey;
     177: astore        18
     179: aconst_null
     180: astore        19
     182: aload_2
     183: invokevirtual #509                // Method org/bouncycastle/jcajce/PKIXExtendedParameters.isUseDeltasEnabled:()Z
     186: ifeq          217
     189: aload         9
     191: aload         15
     193: aload_2
     194: invokevirtual #512                // Method org/bouncycastle/jcajce/PKIXExtendedParameters.getCertStores:()Ljava/util/List;
     197: aload_2
     198: invokevirtual #511                // Method org/bouncycastle/jcajce/PKIXExtendedParameters.getCRLStores:()Ljava/util/List;
     201: aload         8
     203: invokestatic  #526                // Method org/bouncycastle/jce/provider/CertPathValidatorUtilities.getDeltaCRLs:(Ljava/util/Date;Ljava/security/cert/X509CRL;Ljava/util/List;Ljava/util/List;Lorg/bouncycastle/jcajce/util/JcaJceHelper;)Ljava/util/Set;
     206: astore        20
     208: aload         20
     210: aload         18
     212: invokestatic  #535                // Method org/bouncycastle/jce/provider/RFC3280CertPathUtilities.processCRLH:(Ljava/util/Set;Ljava/security/PublicKey;)Ljava/security/cert/X509CRL;
     215: astore        19
     217: aload_2
     218: invokevirtual #507                // Method org/bouncycastle/jcajce/PKIXExtendedParameters.getValidityModel:()I
     221: iconst_1
     222: if_icmpeq     256
     225: aload_1
     226: invokeinterface #564,  1          // InterfaceMethod org/bouncycastle/x509/X509AttributeCertificate.getNotAfter:()Ljava/util/Date;
     231: invokevirtual #489                // Method java/util/Date.getTime:()J
     234: aload         15
     236: invokevirtual #480                // Method java/security/cert/X509CRL.getThisUpdate:()Ljava/util/Date;
     239: invokevirtual #489                // Method java/util/Date.getTime:()J
     242: lcmp
     243: ifge          256
     246: new           #270                // class org/bouncycastle/jce/provider/AnnotatedException
     249: dup
     250: ldc           #20                 // String No valid CRL for current time found.
     252: invokespecial #519                // Method org/bouncycastle/jce/provider/AnnotatedException."<init>":(Ljava/lang/String;)V
     255: athrow
     256: aload_0
     257: aload_1
     258: aload         15
     260: invokestatic  #533                // Method org/bouncycastle/jce/provider/RFC3280CertPathUtilities.processCRLB1:(Lorg/bouncycastle/asn1/x509/DistributionPoint;Ljava/lang/Object;Ljava/security/cert/X509CRL;)V
     263: aload_0
     264: aload_1
     265: aload         15
     267: invokestatic  #534                // Method org/bouncycastle/jce/provider/RFC3280CertPathUtilities.processCRLB2:(Lorg/bouncycastle/asn1/x509/DistributionPoint;Ljava/lang/Object;Ljava/security/cert/X509CRL;)V
     270: aload         19
     272: aload         15
     274: aload_2
     275: invokestatic  #536                // Method org/bouncycastle/jce/provider/RFC3280CertPathUtilities.processCRLC:(Ljava/security/cert/X509CRL;Ljava/security/cert/X509CRL;Lorg/bouncycastle/jcajce/PKIXExtendedParameters;)V
     278: aload_3
     279: aload         19
     281: aload_1
     282: aload         5
     284: aload_2
     285: invokestatic  #539                // Method org/bouncycastle/jce/provider/RFC3280CertPathUtilities.processCRLI:(Ljava/util/Date;Ljava/security/cert/X509CRL;Ljava/lang/Object;Lorg/bouncycastle/jce/provider/CertStatus;Lorg/bouncycastle/jcajce/PKIXExtendedParameters;)V
     288: aload_3
     289: aload         15
     291: aload_1
     292: aload         5
     294: invokestatic  #538                // Method org/bouncycastle/jce/provider/RFC3280CertPathUtilities.processCRLJ:(Ljava/util/Date;Ljava/security/cert/X509CRL;Ljava/lang/Object;Lorg/bouncycastle/jce/provider/CertStatus;)V
     297: aload         5
     299: invokevirtual #527                // Method org/bouncycastle/jce/provider/CertStatus.getCertStatus:()I
     302: bipush        8
     304: if_icmpne     314
     307: aload         5
     309: bipush        11
     311: invokevirtual #529                // Method org/bouncycastle/jce/provider/CertStatus.setCertStatus:(I)V
     314: aload         6
     316: aload         16
     318: invokevirtual #544                // Method org/bouncycastle/jce/provider/ReasonsMask.addReasons:(Lorg/bouncycastle/jce/provider/ReasonsMask;)V
     321: iconst_1
     322: istore        12
     324: goto          94
     327: astore        15
     329: aload         15
     331: astore        13
     333: goto          94
     336: iload         12
     338: ifne          344
     341: aload         13
     343: athrow
     344: return
    Exception table:
       from    to  target type
         122   152   327   Class org/bouncycastle/jce/provider/AnnotatedException
         155   324   327   Class org/bouncycastle/jce/provider/AnnotatedException

  static {};
    Code:
       0: getstatic     #456                // Field org/bouncycastle/asn1/x509/Extension.targetInformation:Lorg/bouncycastle/asn1/ASN1ObjectIdentifier;
       3: invokevirtual #494                // Method org/bouncycastle/asn1/ASN1ObjectIdentifier.getId:()Ljava/lang/String;
       6: putstatic     #462                // Field TARGET_INFORMATION:Ljava/lang/String;
       9: getstatic     #455                // Field org/bouncycastle/asn1/x509/Extension.noRevAvail:Lorg/bouncycastle/asn1/ASN1ObjectIdentifier;
      12: invokevirtual #494                // Method org/bouncycastle/asn1/ASN1ObjectIdentifier.getId:()Ljava/lang/String;
      15: putstatic     #461                // Field NO_REV_AVAIL:Ljava/lang/String;
      18: getstatic     #454                // Field org/bouncycastle/asn1/x509/Extension.cRLDistributionPoints:Lorg/bouncycastle/asn1/ASN1ObjectIdentifier;
      21: invokevirtual #494                // Method org/bouncycastle/asn1/ASN1ObjectIdentifier.getId:()Ljava/lang/String;
      24: putstatic     #460                // Field CRL_DISTRIBUTION_POINTS:Ljava/lang/String;
      27: getstatic     #453                // Field org/bouncycastle/asn1/x509/Extension.authorityInfoAccess:Lorg/bouncycastle/asn1/ASN1ObjectIdentifier;
      30: invokevirtual #494                // Method org/bouncycastle/asn1/ASN1ObjectIdentifier.getId:()Ljava/lang/String;
      33: putstatic     #459                // Field AUTHORITY_INFO_ACCESS:Ljava/lang/String;
      36: return
}
