Compiled from "DateConverterTests.java"
public final class org.pac4j.core.profile.converter.DateConverterTests {
  private static final java.lang.String FORMAT;

  private final org.pac4j.core.profile.converter.DateConverter converter;

  private static final java.lang.String GOOD_DATE;

  private static final java.lang.String BAD_DATE;

  public org.pac4j.core.profile.converter.DateConverterTests();
    Code:
       0: aload_0
       1: invokespecial #1                  // Method java/lang/Object."<init>":()V
       4: aload_0
       5: new           #2                  // class org/pac4j/core/profile/converter/DateConverter
       8: dup
       9: ldc           #4                  // String yyyy.MM.dd
      11: invokespecial #5                  // Method org/pac4j/core/profile/converter/DateConverter."<init>":(Ljava/lang/String;)V
      14: putfield      #6                  // Field converter:Lorg/pac4j/core/profile/converter/DateConverter;
      17: return

  public void testNull();
    Code:
       0: aload_0
       1: getfield      #6                  // Field converter:Lorg/pac4j/core/profile/converter/DateConverter;
       4: aconst_null
       5: invokevirtual #7                  // Method org/pac4j/core/profile/converter/DateConverter.convert:(Ljava/lang/Object;)Ljava/lang/Object;
       8: invokestatic  #8                  // Method org/junit/Assert.assertNull:(Ljava/lang/Object;)V
      11: return

  public void testNotAString();
    Code:
       0: aload_0
       1: getfield      #6                  // Field converter:Lorg/pac4j/core/profile/converter/DateConverter;
       4: getstatic     #9                  // Field java/lang/Boolean.TRUE:Ljava/lang/Boolean;
       7: invokevirtual #7                  // Method org/pac4j/core/profile/converter/DateConverter.convert:(Ljava/lang/Object;)Ljava/lang/Object;
      10: invokestatic  #8                  // Method org/junit/Assert.assertNull:(Ljava/lang/Object;)V
      13: return

  public void testGoodDate();
    Code:
       0: aload_0
       1: getfield      #6                  // Field converter:Lorg/pac4j/core/profile/converter/DateConverter;
       4: ldc           #10                 // String 2012.01.01
       6: invokevirtual #7                  // Method org/pac4j/core/profile/converter/DateConverter.convert:(Ljava/lang/Object;)Ljava/lang/Object;
       9: checkcast     #11                 // class java/util/Date
      12: astore_1
      13: new           #12                 // class java/text/SimpleDateFormat
      16: dup
      17: ldc           #4                  // String yyyy.MM.dd
      19: invokespecial #13                 // Method java/text/SimpleDateFormat."<init>":(Ljava/lang/String;)V
      22: astore_2
      23: ldc           #10                 // String 2012.01.01
      25: aload_2
      26: aload_1
      27: invokevirtual #14                 // Method java/text/SimpleDateFormat.format:(Ljava/util/Date;)Ljava/lang/String;
      30: invokestatic  #15                 // Method org/junit/Assert.assertEquals:(Ljava/lang/Object;Ljava/lang/Object;)V
      33: return

  public void testBadDate();
    Code:
       0: aload_0
       1: getfield      #6                  // Field converter:Lorg/pac4j/core/profile/converter/DateConverter;
       4: ldc           #16                 // String 2012/01/01
       6: invokevirtual #7                  // Method org/pac4j/core/profile/converter/DateConverter.convert:(Ljava/lang/Object;)Ljava/lang/Object;
       9: invokestatic  #8                  // Method org/junit/Assert.assertNull:(Ljava/lang/Object;)V
      12: return
}
