Compiled from "StringConverterTests.java"
public final class org.pac4j.core.profile.converter.StringConverterTests implements org.pac4j.core.util.TestsConstants {
  private final org.pac4j.core.profile.converter.StringConverter converter;

  public org.pac4j.core.profile.converter.StringConverterTests();
    Code:
       0: aload_0
       1: invokespecial #1                  // Method java/lang/Object."<init>":()V
       4: aload_0
       5: new           #2                  // class org/pac4j/core/profile/converter/StringConverter
       8: dup
       9: invokespecial #3                  // Method org/pac4j/core/profile/converter/StringConverter."<init>":()V
      12: putfield      #4                  // Field converter:Lorg/pac4j/core/profile/converter/StringConverter;
      15: return

  public void testNull();
    Code:
       0: aload_0
       1: getfield      #4                  // Field converter:Lorg/pac4j/core/profile/converter/StringConverter;
       4: aconst_null
       5: invokevirtual #5                  // Method org/pac4j/core/profile/converter/StringConverter.convert:(Ljava/lang/Object;)Ljava/lang/Object;
       8: invokestatic  #6                  // Method org/junit/Assert.assertNull:(Ljava/lang/Object;)V
      11: return

  public void testListNull();
    Code:
       0: aload_0
       1: getfield      #4                  // Field converter:Lorg/pac4j/core/profile/converter/StringConverter;
       4: new           #7                  // class java/util/ArrayList
       7: dup
       8: invokespecial #8                  // Method java/util/ArrayList."<init>":()V
      11: invokevirtual #5                  // Method org/pac4j/core/profile/converter/StringConverter.convert:(Ljava/lang/Object;)Ljava/lang/Object;
      14: invokestatic  #6                  // Method org/junit/Assert.assertNull:(Ljava/lang/Object;)V
      17: return

  public void testNotAString();
    Code:
       0: aload_0
       1: getfield      #4                  // Field converter:Lorg/pac4j/core/profile/converter/StringConverter;
       4: getstatic     #9                  // Field java/lang/Boolean.TRUE:Ljava/lang/Boolean;
       7: invokevirtual #5                  // Method org/pac4j/core/profile/converter/StringConverter.convert:(Ljava/lang/Object;)Ljava/lang/Object;
      10: invokestatic  #6                  // Method org/junit/Assert.assertNull:(Ljava/lang/Object;)V
      13: return

  public void testString();
    Code:
       0: ldc           #11                 // String value
       2: aload_0
       3: getfield      #4                  // Field converter:Lorg/pac4j/core/profile/converter/StringConverter;
       6: ldc           #11                 // String value
       8: invokevirtual #5                  // Method org/pac4j/core/profile/converter/StringConverter.convert:(Ljava/lang/Object;)Ljava/lang/Object;
      11: invokestatic  #12                 // Method org/junit/Assert.assertEquals:(Ljava/lang/Object;Ljava/lang/Object;)V
      14: return

  public void testListString();
    Code:
       0: ldc           #11                 // String value
       2: aload_0
       3: getfield      #4                  // Field converter:Lorg/pac4j/core/profile/converter/StringConverter;
       6: iconst_1
       7: anewarray     #13                 // class java/lang/String
      10: dup
      11: iconst_0
      12: ldc           #11                 // String value
      14: aastore
      15: invokestatic  #14                 // Method java/util/Arrays.asList:([Ljava/lang/Object;)Ljava/util/List;
      18: invokevirtual #5                  // Method org/pac4j/core/profile/converter/StringConverter.convert:(Ljava/lang/Object;)Ljava/lang/Object;
      21: invokestatic  #12                 // Method org/junit/Assert.assertEquals:(Ljava/lang/Object;Ljava/lang/Object;)V
      24: return
}
