Compiled from "DoneableIngressStatus.java"
class io.fabric8.kubernetes.api.model.networking.v1beta1.DoneableIngressStatus$1 implements io.fabric8.kubernetes.api.builder.Function<io.fabric8.kubernetes.api.model.networking.v1beta1.IngressStatus, io.fabric8.kubernetes.api.model.networking.v1beta1.IngressStatus> {
  final io.fabric8.kubernetes.api.model.networking.v1beta1.DoneableIngressStatus this$0;

  io.fabric8.kubernetes.api.model.networking.v1beta1.DoneableIngressStatus$1(io.fabric8.kubernetes.api.model.networking.v1beta1.DoneableIngressStatus);
    Code:
       0: aload_0
       1: aload_1
       2: putfield      #1                  // Field this$0:Lio/fabric8/kubernetes/api/model/networking/v1beta1/DoneableIngressStatus;
       5: aload_0
       6: invokespecial #2                  // Method java/lang/Object."<init>":()V
       9: return

  public io.fabric8.kubernetes.api.model.networking.v1beta1.IngressStatus apply(io.fabric8.kubernetes.api.model.networking.v1beta1.IngressStatus);
    Code:
       0: aload_1
       1: areturn

  public java.lang.Object apply(java.lang.Object);
    Code:
       0: aload_0
       1: aload_1
       2: checkcast     #3                  // class io/fabric8/kubernetes/api/model/networking/v1beta1/IngressStatus
       5: invokevirtual #4                  // Method apply:(Lio/fabric8/kubernetes/api/model/networking/v1beta1/IngressStatus;)Lio/fabric8/kubernetes/api/model/networking/v1beta1/IngressStatus;
       8: areturn
}
