Compiled from "RootEntityResultTransformer.java"
public final class org.hibernate.transform.RootEntityResultTransformer extends org.hibernate.transform.BasicTransformerAdapter implements org.hibernate.transform.TupleSubsetResultTransformer {
  public static final org.hibernate.transform.RootEntityResultTransformer INSTANCE;

  private org.hibernate.transform.RootEntityResultTransformer();
    Code:
       0: aload_0
       1: invokespecial #1                  // Method org/hibernate/transform/BasicTransformerAdapter."<init>":()V
       4: return

  public java.lang.Object transformTuple(java.lang.Object[], java.lang.String[]);
    Code:
       0: aload_1
       1: aload_1
       2: arraylength
       3: iconst_1
       4: isub
       5: aaload
       6: areturn

  public boolean isTransformedValueATupleElement(java.lang.String[], int);
    Code:
       0: iconst_1
       1: ireturn

  public boolean[] includeInTransform(java.lang.String[], int);
    Code:
       0: iload_2
       1: iconst_1
       2: if_icmpne     12
       5: getstatic     #2                  // Field org/hibernate/internal/util/collections/ArrayHelper.TRUE:[Z
       8: astore_3
       9: goto          22
      12: iload_2
      13: newarray       boolean
      15: astore_3
      16: aload_3
      17: iload_2
      18: iconst_1
      19: isub
      20: iconst_1
      21: bastore
      22: aload_3
      23: areturn

  private java.lang.Object readResolve();
    Code:
       0: getstatic     #3                  // Field INSTANCE:Lorg/hibernate/transform/RootEntityResultTransformer;
       3: areturn

  static {};
    Code:
       0: new           #4                  // class org/hibernate/transform/RootEntityResultTransformer
       3: dup
       4: invokespecial #5                  // Method "<init>":()V
       7: putstatic     #3                  // Field INSTANCE:Lorg/hibernate/transform/RootEntityResultTransformer;
      10: return
}
