Compiled from "DomainModelControllerService.java"
class org.jboss.as.host.controller.DomainModelControllerService$2 implements java.lang.Runnable {
  final org.jboss.as.host.controller.DomainModelControllerService this$0;

  org.jboss.as.host.controller.DomainModelControllerService$2(org.jboss.as.host.controller.DomainModelControllerService);
    Code:
       0: aload_0
       1: aload_1
       2: putfield      #1                  // Field this$0:Lorg/jboss/as/host/controller/DomainModelControllerService;
       5: aload_0
       6: invokespecial #2                  // Method java/lang/Object."<init>":()V
       9: return

  public void run();
    Code:
       0: aload_0
       1: getfield      #1                  // Field this$0:Lorg/jboss/as/host/controller/DomainModelControllerService;
       4: invokestatic  #3                  // Method org/jboss/as/host/controller/DomainModelControllerService.access$100:(Lorg/jboss/as/host/controller/DomainModelControllerService;)Lorg/jboss/as/host/controller/DomainSlaveHostRegistrations;
       7: invokevirtual #4                  // Method org/jboss/as/host/controller/DomainSlaveHostRegistrations.pruneExpired:()V
      10: goto          29
      13: astore_1
      14: getstatic     #6                  // Field org/jboss/as/host/controller/logging/HostControllerLogger.DOMAIN_LOGGER:Lorg/jboss/as/host/controller/logging/HostControllerLogger;
      17: aload_1
      18: ldc           #7                  // String failed to execute eviction task
      20: iconst_0
      21: anewarray     #8                  // class java/lang/Object
      24: invokeinterface #9,  4            // InterfaceMethod org/jboss/as/host/controller/logging/HostControllerLogger.debugf:(Ljava/lang/Throwable;Ljava/lang/String;[Ljava/lang/Object;)V
      29: return
    Exception table:
       from    to  target type
           0    10    13   Class java/lang/Exception
}
