Compiled from "JsonWriter.java"
final class net.minidev.json.reader.JsonWriter$5 implements net.minidev.json.reader.JsonWriterI<java.lang.Iterable<? extends java.lang.Object>> {
  net.minidev.json.reader.JsonWriter$5();
    Code:
       0: aload_0
       1: invokespecial #1                  // Method java/lang/Object."<init>":()V
       4: return

  public <E extends java.lang.Iterable<? extends java.lang.Object>> void writeJSONString(E, java.lang.Appendable, net.minidev.json.JSONStyle) throws java.io.IOException;
    Code:
       0: iconst_1
       1: istore        4
       3: aload_3
       4: aload_2
       5: invokevirtual #2                  // Method net/minidev/json/JSONStyle.arrayStart:(Ljava/lang/Appendable;)V
       8: aload_1
       9: invokeinterface #3,  1            // InterfaceMethod java/lang/Iterable.iterator:()Ljava/util/Iterator;
      14: astore        5
      16: aload         5
      18: invokeinterface #4,  1            // InterfaceMethod java/util/Iterator.hasNext:()Z
      23: ifeq          88
      26: aload         5
      28: invokeinterface #5,  1            // InterfaceMethod java/util/Iterator.next:()Ljava/lang/Object;
      33: astore        6
      35: iload         4
      37: ifeq          51
      40: iconst_0
      41: istore        4
      43: aload_3
      44: aload_2
      45: invokevirtual #6                  // Method net/minidev/json/JSONStyle.arrayfirstObject:(Ljava/lang/Appendable;)V
      48: goto          56
      51: aload_3
      52: aload_2
      53: invokevirtual #7                  // Method net/minidev/json/JSONStyle.arrayNextElm:(Ljava/lang/Appendable;)V
      56: aload         6
      58: ifnonnull     73
      61: aload_2
      62: ldc           #8                  // String null
      64: invokeinterface #9,  2            // InterfaceMethod java/lang/Appendable.append:(Ljava/lang/CharSequence;)Ljava/lang/Appendable;
      69: pop
      70: goto          80
      73: aload         6
      75: aload_2
      76: aload_3
      77: invokestatic  #10                 // Method net/minidev/json/JSONValue.writeJSONString:(Ljava/lang/Object;Ljava/lang/Appendable;Lnet/minidev/json/JSONStyle;)V
      80: aload_3
      81: aload_2
      82: invokevirtual #11                 // Method net/minidev/json/JSONStyle.arrayObjectEnd:(Ljava/lang/Appendable;)V
      85: goto          16
      88: aload_3
      89: aload_2
      90: invokevirtual #12                 // Method net/minidev/json/JSONStyle.arrayStop:(Ljava/lang/Appendable;)V
      93: return

  public void writeJSONString(java.lang.Object, java.lang.Appendable, net.minidev.json.JSONStyle) throws java.io.IOException;
    Code:
       0: aload_0
       1: aload_1
       2: checkcast     #13                 // class java/lang/Iterable
       5: aload_2
       6: aload_3
       7: invokevirtual #14                 // Method writeJSONString:(Ljava/lang/Iterable;Ljava/lang/Appendable;Lnet/minidev/json/JSONStyle;)V
      10: return
}
