Compiled from "ExamineResponse.java"
public class cn.sowjz.souwen.v1.query.response.ExamineResponse$FieldExamHit {
  cn.sowjz.souwen.v1.db.struct.FieldInfo finfo;

  long maxValue;

  long minValue;

  int type;

  final cn.sowjz.souwen.v1.query.response.ExamineResponse this$0;

  public cn.sowjz.souwen.v1.query.response.ExamineResponse$FieldExamHit(cn.sowjz.souwen.v1.query.response.ExamineResponse);
    Code:
       0: aload_0
       1: aload_1
       2: putfield      #1                  // Field this$0:Lcn/sowjz/souwen/v1/query/response/ExamineResponse;
       5: aload_0
       6: invokespecial #2                  // Method java/lang/Object."<init>":()V
       9: return

  public int bytes2Me(byte[], int);
    Code:
       0: iload_2
       1: istore_3
       2: aload_1
       3: iload_2
       4: invokestatic  #3                  // Method cn/sowjz/souwen/v1/util/VConvert.bytes2Int:([BI)I
       7: istore        4
       9: iinc          2, 4
      12: iload         4
      14: ifne          24
      17: ldc           #4                  // String
      19: astore        5
      21: goto          39
      24: new           #5                  // class java/lang/String
      27: dup
      28: aload_1
      29: iload_2
      30: iload         4
      32: iconst_1
      33: isub
      34: invokespecial #6                  // Method java/lang/String."<init>":([BII)V
      37: astore        5
      39: iload_2
      40: iload         4
      42: iadd
      43: istore_2
      44: aload_0
      45: aload_0
      46: getfield      #1                  // Field this$0:Lcn/sowjz/souwen/v1/query/response/ExamineResponse;
      49: getfield      #7                  // Field cn/sowjz/souwen/v1/query/response/ExamineResponse.searchSystem:Lcn/sowjz/souwen/v1/SouwenClient;
      52: invokevirtual #8                  // Method cn/sowjz/souwen/v1/SouwenClient.getInfos:()Lcn/sowjz/souwen/v1/db/struct/FieldInfos;
      55: aload         5
      57: invokevirtual #9                  // Method cn/sowjz/souwen/v1/db/struct/FieldInfos.find:(Ljava/lang/String;)Lcn/sowjz/souwen/v1/db/struct/FieldInfo;
      60: putfield      #10                 // Field finfo:Lcn/sowjz/souwen/v1/db/struct/FieldInfo;
      63: aload_0
      64: aload_1
      65: iload_2
      66: invokestatic  #11                 // Method cn/sowjz/souwen/v1/util/VConvert.bytes2Long:([BI)J
      69: putfield      #12                 // Field maxValue:J
      72: iinc          2, 8
      75: aload_0
      76: aload_1
      77: iload_2
      78: invokestatic  #11                 // Method cn/sowjz/souwen/v1/util/VConvert.bytes2Long:([BI)J
      81: putfield      #13                 // Field minValue:J
      84: iinc          2, 8
      87: aload_0
      88: aload_1
      89: iload_2
      90: invokestatic  #3                  // Method cn/sowjz/souwen/v1/util/VConvert.bytes2Int:([BI)I
      93: putfield      #14                 // Field type:I
      96: iinc          2, 4
      99: iload_2
     100: iload_3
     101: isub
     102: ireturn

  public java.lang.String toString();
    Code:
       0: new           #15                 // class java/lang/StringBuilder
       3: dup
       4: invokespecial #16                 // Method java/lang/StringBuilder."<init>":()V
       7: ldc           #17                 // String FieldExamHit [finfo=
       9: invokevirtual #18                 // Method java/lang/StringBuilder.append:(Ljava/lang/String;)Ljava/lang/StringBuilder;
      12: aload_0
      13: getfield      #10                 // Field finfo:Lcn/sowjz/souwen/v1/db/struct/FieldInfo;
      16: invokevirtual #19                 // Method cn/sowjz/souwen/v1/db/struct/FieldInfo.getName:()Ljava/lang/String;
      19: invokevirtual #18                 // Method java/lang/StringBuilder.append:(Ljava/lang/String;)Ljava/lang/StringBuilder;
      22: ldc           #20                 // String , maxValue=
      24: invokevirtual #18                 // Method java/lang/StringBuilder.append:(Ljava/lang/String;)Ljava/lang/StringBuilder;
      27: aload_0
      28: getfield      #12                 // Field maxValue:J
      31: invokevirtual #21                 // Method java/lang/StringBuilder.append:(J)Ljava/lang/StringBuilder;
      34: ldc           #22                 // String , minValue=
      36: invokevirtual #18                 // Method java/lang/StringBuilder.append:(Ljava/lang/String;)Ljava/lang/StringBuilder;
      39: aload_0
      40: getfield      #13                 // Field minValue:J
      43: invokevirtual #21                 // Method java/lang/StringBuilder.append:(J)Ljava/lang/StringBuilder;
      46: ldc           #23                 // String , type=
      48: invokevirtual #18                 // Method java/lang/StringBuilder.append:(Ljava/lang/String;)Ljava/lang/StringBuilder;
      51: getstatic     #24                 // Field cn/sowjz/souwen/v1/query/response/ExamineResponse.Types:[Ljava/lang/String;
      54: aload_0
      55: getfield      #14                 // Field type:I
      58: aaload
      59: invokevirtual #18                 // Method java/lang/StringBuilder.append:(Ljava/lang/String;)Ljava/lang/StringBuilder;
      62: ldc           #25                 // String ]
      64: invokevirtual #18                 // Method java/lang/StringBuilder.append:(Ljava/lang/String;)Ljava/lang/StringBuilder;
      67: invokevirtual #26                 // Method java/lang/StringBuilder.toString:()Ljava/lang/String;
      70: areturn

  public cn.sowjz.souwen.v1.db.struct.FieldInfo getFinfo();
    Code:
       0: aload_0
       1: getfield      #10                 // Field finfo:Lcn/sowjz/souwen/v1/db/struct/FieldInfo;
       4: areturn

  public long getMaxValue();
    Code:
       0: aload_0
       1: getfield      #12                 // Field maxValue:J
       4: lreturn

  public long getMinValue();
    Code:
       0: aload_0
       1: getfield      #13                 // Field minValue:J
       4: lreturn

  public int getType();
    Code:
       0: aload_0
       1: getfield      #14                 // Field type:I
       4: ireturn

  public java.lang.String getTypeName();
    Code:
       0: getstatic     #24                 // Field cn/sowjz/souwen/v1/query/response/ExamineResponse.Types:[Ljava/lang/String;
       3: aload_0
       4: getfield      #14                 // Field type:I
       7: aaload
       8: areturn
}
