Compiled from "ClusterVersionStatusFluentImpl.java"
public class io.dekorate.deps.openshift.api.model.ClusterVersionStatusFluentImpl$HistoryNestedImpl<N> extends io.dekorate.deps.openshift.api.model.UpdateHistoryFluentImpl<io.dekorate.deps.openshift.api.model.ClusterVersionStatusFluent$HistoryNested<N>> implements io.dekorate.deps.openshift.api.model.ClusterVersionStatusFluent$HistoryNested<N>, io.dekorate.deps.kubernetes.api.builder.Nested<N> {
  private final io.dekorate.deps.openshift.api.model.UpdateHistoryBuilder builder;

  private final int index;

  final io.dekorate.deps.openshift.api.model.ClusterVersionStatusFluentImpl this$0;

  io.dekorate.deps.openshift.api.model.ClusterVersionStatusFluentImpl$HistoryNestedImpl(io.dekorate.deps.openshift.api.model.ClusterVersionStatusFluentImpl, int, io.dekorate.deps.openshift.api.model.UpdateHistory);
    Code:
       0: aload_0
       1: aload_1
       2: putfield      #26                 // Field this$0:Lio/dekorate/deps/openshift/api/model/ClusterVersionStatusFluentImpl;
       5: aload_0
       6: invokespecial #29                 // Method io/dekorate/deps/openshift/api/model/UpdateHistoryFluentImpl."<init>":()V
       9: aload_0
      10: iload_2
      11: putfield      #31                 // Field index:I
      14: aload_0
      15: new           #33                 // class io/dekorate/deps/openshift/api/model/UpdateHistoryBuilder
      18: dup
      19: aload_0
      20: aload_3
      21: invokespecial #36                 // Method io/dekorate/deps/openshift/api/model/UpdateHistoryBuilder."<init>":(Lio/dekorate/deps/openshift/api/model/UpdateHistoryFluent;Lio/dekorate/deps/openshift/api/model/UpdateHistory;)V
      24: putfield      #38                 // Field builder:Lio/dekorate/deps/openshift/api/model/UpdateHistoryBuilder;
      27: return

  io.dekorate.deps.openshift.api.model.ClusterVersionStatusFluentImpl$HistoryNestedImpl(io.dekorate.deps.openshift.api.model.ClusterVersionStatusFluentImpl);
    Code:
       0: aload_0
       1: aload_1
       2: putfield      #26                 // Field this$0:Lio/dekorate/deps/openshift/api/model/ClusterVersionStatusFluentImpl;
       5: aload_0
       6: invokespecial #29                 // Method io/dekorate/deps/openshift/api/model/UpdateHistoryFluentImpl."<init>":()V
       9: aload_0
      10: iconst_m1
      11: putfield      #31                 // Field index:I
      14: aload_0
      15: new           #33                 // class io/dekorate/deps/openshift/api/model/UpdateHistoryBuilder
      18: dup
      19: aload_0
      20: invokespecial #47                 // Method io/dekorate/deps/openshift/api/model/UpdateHistoryBuilder."<init>":(Lio/dekorate/deps/openshift/api/model/UpdateHistoryFluent;)V
      23: putfield      #38                 // Field builder:Lio/dekorate/deps/openshift/api/model/UpdateHistoryBuilder;
      26: return

  public N and();
    Code:
       0: aload_0
       1: getfield      #26                 // Field this$0:Lio/dekorate/deps/openshift/api/model/ClusterVersionStatusFluentImpl;
       4: aload_0
       5: getfield      #31                 // Field index:I
       8: aload_0
       9: getfield      #38                 // Field builder:Lio/dekorate/deps/openshift/api/model/UpdateHistoryBuilder;
      12: invokevirtual #54                 // Method io/dekorate/deps/openshift/api/model/UpdateHistoryBuilder.build:()Lio/dekorate/deps/openshift/api/model/UpdateHistory;
      15: invokevirtual #58                 // Method io/dekorate/deps/openshift/api/model/ClusterVersionStatusFluentImpl.setToHistory:(ILio/dekorate/deps/openshift/api/model/UpdateHistory;)Lio/dekorate/deps/openshift/api/model/ClusterVersionStatusFluent;
      18: areturn

  public N endHistory();
    Code:
       0: aload_0
       1: invokevirtual #61                 // Method and:()Ljava/lang/Object;
       4: areturn
}
