Compiled from "DoneableStageInfo.java"
public class io.dekorate.deps.openshift.api.model.DoneableStageInfo extends io.dekorate.deps.openshift.api.model.StageInfoFluentImpl<io.dekorate.deps.openshift.api.model.DoneableStageInfo> implements io.dekorate.deps.kubernetes.api.model.Doneable<io.dekorate.deps.openshift.api.model.StageInfo> {
  private final io.dekorate.deps.openshift.api.model.StageInfoBuilder builder;

  private final io.dekorate.deps.kubernetes.api.builder.Function<io.dekorate.deps.openshift.api.model.StageInfo, io.dekorate.deps.openshift.api.model.StageInfo> function;

  public io.dekorate.deps.openshift.api.model.DoneableStageInfo(io.dekorate.deps.kubernetes.api.builder.Function<io.dekorate.deps.openshift.api.model.StageInfo, io.dekorate.deps.openshift.api.model.StageInfo>);
    Code:
       0: aload_0
       1: invokespecial #21                 // Method io/dekorate/deps/openshift/api/model/StageInfoFluentImpl."<init>":()V
       4: aload_0
       5: new           #23                 // class io/dekorate/deps/openshift/api/model/StageInfoBuilder
       8: dup
       9: aload_0
      10: invokespecial #26                 // Method io/dekorate/deps/openshift/api/model/StageInfoBuilder."<init>":(Lio/dekorate/deps/openshift/api/model/StageInfoFluent;)V
      13: putfield      #28                 // Field builder:Lio/dekorate/deps/openshift/api/model/StageInfoBuilder;
      16: aload_0
      17: aload_1
      18: putfield      #30                 // Field function:Lio/dekorate/deps/kubernetes/api/builder/Function;
      21: return

  public io.dekorate.deps.openshift.api.model.DoneableStageInfo(io.dekorate.deps.openshift.api.model.StageInfo, io.dekorate.deps.kubernetes.api.builder.Function<io.dekorate.deps.openshift.api.model.StageInfo, io.dekorate.deps.openshift.api.model.StageInfo>);
    Code:
       0: aload_0
       1: aload_1
       2: invokespecial #37                 // Method io/dekorate/deps/openshift/api/model/StageInfoFluentImpl."<init>":(Lio/dekorate/deps/openshift/api/model/StageInfo;)V
       5: aload_0
       6: new           #23                 // class io/dekorate/deps/openshift/api/model/StageInfoBuilder
       9: dup
      10: aload_0
      11: aload_1
      12: invokespecial #40                 // Method io/dekorate/deps/openshift/api/model/StageInfoBuilder."<init>":(Lio/dekorate/deps/openshift/api/model/StageInfoFluent;Lio/dekorate/deps/openshift/api/model/StageInfo;)V
      15: putfield      #28                 // Field builder:Lio/dekorate/deps/openshift/api/model/StageInfoBuilder;
      18: aload_0
      19: aload_2
      20: putfield      #30                 // Field function:Lio/dekorate/deps/kubernetes/api/builder/Function;
      23: return

  public io.dekorate.deps.openshift.api.model.DoneableStageInfo(io.dekorate.deps.openshift.api.model.StageInfo);
    Code:
       0: aload_0
       1: aload_1
       2: invokespecial #37                 // Method io/dekorate/deps/openshift/api/model/StageInfoFluentImpl."<init>":(Lio/dekorate/deps/openshift/api/model/StageInfo;)V
       5: aload_0
       6: new           #23                 // class io/dekorate/deps/openshift/api/model/StageInfoBuilder
       9: dup
      10: aload_0
      11: aload_1
      12: invokespecial #40                 // Method io/dekorate/deps/openshift/api/model/StageInfoBuilder."<init>":(Lio/dekorate/deps/openshift/api/model/StageInfoFluent;Lio/dekorate/deps/openshift/api/model/StageInfo;)V
      15: putfield      #28                 // Field builder:Lio/dekorate/deps/openshift/api/model/StageInfoBuilder;
      18: aload_0
      19: new           #10                 // class io/dekorate/deps/openshift/api/model/DoneableStageInfo$1
      22: dup
      23: aload_0
      24: invokespecial #45                 // Method io/dekorate/deps/openshift/api/model/DoneableStageInfo$1."<init>":(Lio/dekorate/deps/openshift/api/model/DoneableStageInfo;)V
      27: putfield      #30                 // Field function:Lio/dekorate/deps/kubernetes/api/builder/Function;
      30: return

  public io.dekorate.deps.openshift.api.model.StageInfo done();
    Code:
       0: aload_0
       1: getfield      #30                 // Field function:Lio/dekorate/deps/kubernetes/api/builder/Function;
       4: aload_0
       5: getfield      #28                 // Field builder:Lio/dekorate/deps/openshift/api/model/StageInfoBuilder;
       8: invokevirtual #50                 // Method io/dekorate/deps/openshift/api/model/StageInfoBuilder.build:()Lio/dekorate/deps/openshift/api/model/StageInfo;
      11: invokeinterface #56,  2           // InterfaceMethod io/dekorate/deps/kubernetes/api/builder/Function.apply:(Ljava/lang/Object;)Ljava/lang/Object;
      16: checkcast     #58                 // class io/dekorate/deps/openshift/api/model/StageInfo
      19: areturn

  public java.lang.Object done();
    Code:
       0: aload_0
       1: invokevirtual #61                 // Method done:()Lio/dekorate/deps/openshift/api/model/StageInfo;
       4: areturn
}
