Compiled from "GitSourceRevisionFluentImpl.java"
public class io.dekorate.deps.openshift.api.model.GitSourceRevisionFluentImpl<A extends io.dekorate.deps.openshift.api.model.GitSourceRevisionFluent<A>> extends io.dekorate.deps.kubernetes.api.builder.BaseFluent<A> implements io.dekorate.deps.openshift.api.model.GitSourceRevisionFluent<A> {
  private io.dekorate.deps.openshift.api.model.SourceControlUserBuilder author;

  private java.lang.String commit;

  private io.dekorate.deps.openshift.api.model.SourceControlUserBuilder committer;

  private java.lang.String message;

  public io.dekorate.deps.openshift.api.model.GitSourceRevisionFluentImpl();
    Code:
       0: aload_0
       1: invokespecial #30                 // Method io/dekorate/deps/kubernetes/api/builder/BaseFluent."<init>":()V
       4: return

  public io.dekorate.deps.openshift.api.model.GitSourceRevisionFluentImpl(io.dekorate.deps.openshift.api.model.GitSourceRevision);
    Code:
       0: aload_0
       1: invokespecial #30                 // Method io/dekorate/deps/kubernetes/api/builder/BaseFluent."<init>":()V
       4: aload_0
       5: aload_1
       6: invokevirtual #40                 // Method io/dekorate/deps/openshift/api/model/GitSourceRevision.getAuthor:()Lio/dekorate/deps/openshift/api/model/SourceControlUser;
       9: invokevirtual #44                 // Method withAuthor:(Lio/dekorate/deps/openshift/api/model/SourceControlUser;)Lio/dekorate/deps/openshift/api/model/GitSourceRevisionFluent;
      12: pop
      13: aload_0
      14: aload_1
      15: invokevirtual #48                 // Method io/dekorate/deps/openshift/api/model/GitSourceRevision.getCommit:()Ljava/lang/String;
      18: invokevirtual #52                 // Method withCommit:(Ljava/lang/String;)Lio/dekorate/deps/openshift/api/model/GitSourceRevisionFluent;
      21: pop
      22: aload_0
      23: aload_1
      24: invokevirtual #55                 // Method io/dekorate/deps/openshift/api/model/GitSourceRevision.getCommitter:()Lio/dekorate/deps/openshift/api/model/SourceControlUser;
      27: invokevirtual #58                 // Method withCommitter:(Lio/dekorate/deps/openshift/api/model/SourceControlUser;)Lio/dekorate/deps/openshift/api/model/GitSourceRevisionFluent;
      30: pop
      31: aload_0
      32: aload_1
      33: invokevirtual #61                 // Method io/dekorate/deps/openshift/api/model/GitSourceRevision.getMessage:()Ljava/lang/String;
      36: invokevirtual #64                 // Method withMessage:(Ljava/lang/String;)Lio/dekorate/deps/openshift/api/model/GitSourceRevisionFluent;
      39: pop
      40: return

  public io.dekorate.deps.openshift.api.model.SourceControlUser getAuthor();
    Code:
       0: aload_0
       1: getfield      #69                 // Field author:Lio/dekorate/deps/openshift/api/model/SourceControlUserBuilder;
       4: ifnull        17
       7: aload_0
       8: getfield      #69                 // Field author:Lio/dekorate/deps/openshift/api/model/SourceControlUserBuilder;
      11: invokevirtual #74                 // Method io/dekorate/deps/openshift/api/model/SourceControlUserBuilder.build:()Lio/dekorate/deps/openshift/api/model/SourceControlUser;
      14: goto          18
      17: aconst_null
      18: areturn

  public io.dekorate.deps.openshift.api.model.SourceControlUser buildAuthor();
    Code:
       0: aload_0
       1: getfield      #69                 // Field author:Lio/dekorate/deps/openshift/api/model/SourceControlUserBuilder;
       4: ifnull        17
       7: aload_0
       8: getfield      #69                 // Field author:Lio/dekorate/deps/openshift/api/model/SourceControlUserBuilder;
      11: invokevirtual #74                 // Method io/dekorate/deps/openshift/api/model/SourceControlUserBuilder.build:()Lio/dekorate/deps/openshift/api/model/SourceControlUser;
      14: goto          18
      17: aconst_null
      18: areturn

  public A withAuthor(io.dekorate.deps.openshift.api.model.SourceControlUser);
    Code:
       0: aload_0
       1: getfield      #82                 // Field _visitables:Lio/dekorate/deps/kubernetes/api/builder/VisitableMap;
       4: ldc           #83                 // String author
       6: invokevirtual #89                 // Method io/dekorate/deps/kubernetes/api/builder/VisitableMap.get:(Ljava/lang/Object;)Ljava/util/List;
       9: aload_0
      10: getfield      #69                 // Field author:Lio/dekorate/deps/openshift/api/model/SourceControlUserBuilder;
      13: invokeinterface #95,  2           // InterfaceMethod java/util/List.remove:(Ljava/lang/Object;)Z
      18: pop
      19: aload_1
      20: ifnull        54
      23: aload_0
      24: new           #71                 // class io/dekorate/deps/openshift/api/model/SourceControlUserBuilder
      27: dup
      28: aload_1
      29: invokespecial #98                 // Method io/dekorate/deps/openshift/api/model/SourceControlUserBuilder."<init>":(Lio/dekorate/deps/openshift/api/model/SourceControlUser;)V
      32: putfield      #69                 // Field author:Lio/dekorate/deps/openshift/api/model/SourceControlUserBuilder;
      35: aload_0
      36: getfield      #82                 // Field _visitables:Lio/dekorate/deps/kubernetes/api/builder/VisitableMap;
      39: ldc           #83                 // String author
      41: invokevirtual #89                 // Method io/dekorate/deps/kubernetes/api/builder/VisitableMap.get:(Ljava/lang/Object;)Ljava/util/List;
      44: aload_0
      45: getfield      #69                 // Field author:Lio/dekorate/deps/openshift/api/model/SourceControlUserBuilder;
      48: invokeinterface #101,  2          // InterfaceMethod java/util/List.add:(Ljava/lang/Object;)Z
      53: pop
      54: aload_0
      55: areturn

  public java.lang.Boolean hasAuthor();
    Code:
       0: aload_0
       1: getfield      #69                 // Field author:Lio/dekorate/deps/openshift/api/model/SourceControlUserBuilder;
       4: ifnull        11
       7: iconst_1
       8: goto          12
      11: iconst_0
      12: invokestatic  #110                // Method java/lang/Boolean.valueOf:(Z)Ljava/lang/Boolean;
      15: areturn

  public A withNewAuthor(java.lang.String, java.lang.String);
    Code:
       0: aload_0
       1: new           #76                 // class io/dekorate/deps/openshift/api/model/SourceControlUser
       4: dup
       5: aload_1
       6: aload_2
       7: invokespecial #116                // Method io/dekorate/deps/openshift/api/model/SourceControlUser."<init>":(Ljava/lang/String;Ljava/lang/String;)V
      10: invokevirtual #44                 // Method withAuthor:(Lio/dekorate/deps/openshift/api/model/SourceControlUser;)Lio/dekorate/deps/openshift/api/model/GitSourceRevisionFluent;
      13: areturn

  public io.dekorate.deps.openshift.api.model.GitSourceRevisionFluent$AuthorNested<A> withNewAuthor();
    Code:
       0: new           #13                 // class io/dekorate/deps/openshift/api/model/GitSourceRevisionFluentImpl$AuthorNestedImpl
       3: dup
       4: aload_0
       5: invokespecial #123                // Method io/dekorate/deps/openshift/api/model/GitSourceRevisionFluentImpl$AuthorNestedImpl."<init>":(Lio/dekorate/deps/openshift/api/model/GitSourceRevisionFluentImpl;)V
       8: areturn

  public io.dekorate.deps.openshift.api.model.GitSourceRevisionFluent$AuthorNested<A> withNewAuthorLike(io.dekorate.deps.openshift.api.model.SourceControlUser);
    Code:
       0: new           #13                 // class io/dekorate/deps/openshift/api/model/GitSourceRevisionFluentImpl$AuthorNestedImpl
       3: dup
       4: aload_0
       5: aload_1
       6: invokespecial #129                // Method io/dekorate/deps/openshift/api/model/GitSourceRevisionFluentImpl$AuthorNestedImpl."<init>":(Lio/dekorate/deps/openshift/api/model/GitSourceRevisionFluentImpl;Lio/dekorate/deps/openshift/api/model/SourceControlUser;)V
       9: areturn

  public io.dekorate.deps.openshift.api.model.GitSourceRevisionFluent$AuthorNested<A> editAuthor();
    Code:
       0: aload_0
       1: aload_0
       2: invokevirtual #132                // Method getAuthor:()Lio/dekorate/deps/openshift/api/model/SourceControlUser;
       5: invokevirtual #134                // Method withNewAuthorLike:(Lio/dekorate/deps/openshift/api/model/SourceControlUser;)Lio/dekorate/deps/openshift/api/model/GitSourceRevisionFluent$AuthorNested;
       8: areturn

  public io.dekorate.deps.openshift.api.model.GitSourceRevisionFluent$AuthorNested<A> editOrNewAuthor();
    Code:
       0: aload_0
       1: aload_0
       2: invokevirtual #132                // Method getAuthor:()Lio/dekorate/deps/openshift/api/model/SourceControlUser;
       5: ifnull        15
       8: aload_0
       9: invokevirtual #132                // Method getAuthor:()Lio/dekorate/deps/openshift/api/model/SourceControlUser;
      12: goto          25
      15: new           #71                 // class io/dekorate/deps/openshift/api/model/SourceControlUserBuilder
      18: dup
      19: invokespecial #136                // Method io/dekorate/deps/openshift/api/model/SourceControlUserBuilder."<init>":()V
      22: invokevirtual #74                 // Method io/dekorate/deps/openshift/api/model/SourceControlUserBuilder.build:()Lio/dekorate/deps/openshift/api/model/SourceControlUser;
      25: invokevirtual #134                // Method withNewAuthorLike:(Lio/dekorate/deps/openshift/api/model/SourceControlUser;)Lio/dekorate/deps/openshift/api/model/GitSourceRevisionFluent$AuthorNested;
      28: areturn

  public io.dekorate.deps.openshift.api.model.GitSourceRevisionFluent$AuthorNested<A> editOrNewAuthorLike(io.dekorate.deps.openshift.api.model.SourceControlUser);
    Code:
       0: aload_0
       1: aload_0
       2: invokevirtual #132                // Method getAuthor:()Lio/dekorate/deps/openshift/api/model/SourceControlUser;
       5: ifnull        15
       8: aload_0
       9: invokevirtual #132                // Method getAuthor:()Lio/dekorate/deps/openshift/api/model/SourceControlUser;
      12: goto          16
      15: aload_1
      16: invokevirtual #134                // Method withNewAuthorLike:(Lio/dekorate/deps/openshift/api/model/SourceControlUser;)Lio/dekorate/deps/openshift/api/model/GitSourceRevisionFluent$AuthorNested;
      19: areturn

  public java.lang.String getCommit();
    Code:
       0: aload_0
       1: getfield      #139                // Field commit:Ljava/lang/String;
       4: areturn

  public A withCommit(java.lang.String);
    Code:
       0: aload_0
       1: aload_1
       2: putfield      #139                // Field commit:Ljava/lang/String;
       5: aload_0
       6: areturn

  public java.lang.Boolean hasCommit();
    Code:
       0: aload_0
       1: getfield      #139                // Field commit:Ljava/lang/String;
       4: ifnull        11
       7: iconst_1
       8: goto          12
      11: iconst_0
      12: invokestatic  #110                // Method java/lang/Boolean.valueOf:(Z)Ljava/lang/Boolean;
      15: areturn

  public A withNewCommit(java.lang.String);
    Code:
       0: aload_0
       1: new           #144                // class java/lang/String
       4: dup
       5: aload_1
       6: invokespecial #147                // Method java/lang/String."<init>":(Ljava/lang/String;)V
       9: invokevirtual #52                 // Method withCommit:(Ljava/lang/String;)Lio/dekorate/deps/openshift/api/model/GitSourceRevisionFluent;
      12: areturn

  public A withNewCommit(java.lang.StringBuilder);
    Code:
       0: aload_0
       1: new           #144                // class java/lang/String
       4: dup
       5: aload_1
       6: invokespecial #153                // Method java/lang/String."<init>":(Ljava/lang/StringBuilder;)V
       9: invokevirtual #52                 // Method withCommit:(Ljava/lang/String;)Lio/dekorate/deps/openshift/api/model/GitSourceRevisionFluent;
      12: areturn

  public A withNewCommit(java.lang.StringBuffer);
    Code:
       0: aload_0
       1: new           #144                // class java/lang/String
       4: dup
       5: aload_1
       6: invokespecial #159                // Method java/lang/String."<init>":(Ljava/lang/StringBuffer;)V
       9: invokevirtual #52                 // Method withCommit:(Ljava/lang/String;)Lio/dekorate/deps/openshift/api/model/GitSourceRevisionFluent;
      12: areturn

  public io.dekorate.deps.openshift.api.model.SourceControlUser getCommitter();
    Code:
       0: aload_0
       1: getfield      #162                // Field committer:Lio/dekorate/deps/openshift/api/model/SourceControlUserBuilder;
       4: ifnull        17
       7: aload_0
       8: getfield      #162                // Field committer:Lio/dekorate/deps/openshift/api/model/SourceControlUserBuilder;
      11: invokevirtual #74                 // Method io/dekorate/deps/openshift/api/model/SourceControlUserBuilder.build:()Lio/dekorate/deps/openshift/api/model/SourceControlUser;
      14: goto          18
      17: aconst_null
      18: areturn

  public io.dekorate.deps.openshift.api.model.SourceControlUser buildCommitter();
    Code:
       0: aload_0
       1: getfield      #162                // Field committer:Lio/dekorate/deps/openshift/api/model/SourceControlUserBuilder;
       4: ifnull        17
       7: aload_0
       8: getfield      #162                // Field committer:Lio/dekorate/deps/openshift/api/model/SourceControlUserBuilder;
      11: invokevirtual #74                 // Method io/dekorate/deps/openshift/api/model/SourceControlUserBuilder.build:()Lio/dekorate/deps/openshift/api/model/SourceControlUser;
      14: goto          18
      17: aconst_null
      18: areturn

  public A withCommitter(io.dekorate.deps.openshift.api.model.SourceControlUser);
    Code:
       0: aload_0
       1: getfield      #82                 // Field _visitables:Lio/dekorate/deps/kubernetes/api/builder/VisitableMap;
       4: ldc           #164                // String committer
       6: invokevirtual #89                 // Method io/dekorate/deps/kubernetes/api/builder/VisitableMap.get:(Ljava/lang/Object;)Ljava/util/List;
       9: aload_0
      10: getfield      #162                // Field committer:Lio/dekorate/deps/openshift/api/model/SourceControlUserBuilder;
      13: invokeinterface #95,  2           // InterfaceMethod java/util/List.remove:(Ljava/lang/Object;)Z
      18: pop
      19: aload_1
      20: ifnull        54
      23: aload_0
      24: new           #71                 // class io/dekorate/deps/openshift/api/model/SourceControlUserBuilder
      27: dup
      28: aload_1
      29: invokespecial #98                 // Method io/dekorate/deps/openshift/api/model/SourceControlUserBuilder."<init>":(Lio/dekorate/deps/openshift/api/model/SourceControlUser;)V
      32: putfield      #162                // Field committer:Lio/dekorate/deps/openshift/api/model/SourceControlUserBuilder;
      35: aload_0
      36: getfield      #82                 // Field _visitables:Lio/dekorate/deps/kubernetes/api/builder/VisitableMap;
      39: ldc           #164                // String committer
      41: invokevirtual #89                 // Method io/dekorate/deps/kubernetes/api/builder/VisitableMap.get:(Ljava/lang/Object;)Ljava/util/List;
      44: aload_0
      45: getfield      #162                // Field committer:Lio/dekorate/deps/openshift/api/model/SourceControlUserBuilder;
      48: invokeinterface #101,  2          // InterfaceMethod java/util/List.add:(Ljava/lang/Object;)Z
      53: pop
      54: aload_0
      55: areturn

  public java.lang.Boolean hasCommitter();
    Code:
       0: aload_0
       1: getfield      #162                // Field committer:Lio/dekorate/deps/openshift/api/model/SourceControlUserBuilder;
       4: ifnull        11
       7: iconst_1
       8: goto          12
      11: iconst_0
      12: invokestatic  #110                // Method java/lang/Boolean.valueOf:(Z)Ljava/lang/Boolean;
      15: areturn

  public A withNewCommitter(java.lang.String, java.lang.String);
    Code:
       0: aload_0
       1: new           #76                 // class io/dekorate/deps/openshift/api/model/SourceControlUser
       4: dup
       5: aload_1
       6: aload_2
       7: invokespecial #116                // Method io/dekorate/deps/openshift/api/model/SourceControlUser."<init>":(Ljava/lang/String;Ljava/lang/String;)V
      10: invokevirtual #58                 // Method withCommitter:(Lio/dekorate/deps/openshift/api/model/SourceControlUser;)Lio/dekorate/deps/openshift/api/model/GitSourceRevisionFluent;
      13: areturn

  public io.dekorate.deps.openshift.api.model.GitSourceRevisionFluent$CommitterNested<A> withNewCommitter();
    Code:
       0: new           #10                 // class io/dekorate/deps/openshift/api/model/GitSourceRevisionFluentImpl$CommitterNestedImpl
       3: dup
       4: aload_0
       5: invokespecial #169                // Method io/dekorate/deps/openshift/api/model/GitSourceRevisionFluentImpl$CommitterNestedImpl."<init>":(Lio/dekorate/deps/openshift/api/model/GitSourceRevisionFluentImpl;)V
       8: areturn

  public io.dekorate.deps.openshift.api.model.GitSourceRevisionFluent$CommitterNested<A> withNewCommitterLike(io.dekorate.deps.openshift.api.model.SourceControlUser);
    Code:
       0: new           #10                 // class io/dekorate/deps/openshift/api/model/GitSourceRevisionFluentImpl$CommitterNestedImpl
       3: dup
       4: aload_0
       5: aload_1
       6: invokespecial #173                // Method io/dekorate/deps/openshift/api/model/GitSourceRevisionFluentImpl$CommitterNestedImpl."<init>":(Lio/dekorate/deps/openshift/api/model/GitSourceRevisionFluentImpl;Lio/dekorate/deps/openshift/api/model/SourceControlUser;)V
       9: areturn

  public io.dekorate.deps.openshift.api.model.GitSourceRevisionFluent$CommitterNested<A> editCommitter();
    Code:
       0: aload_0
       1: aload_0
       2: invokevirtual #175                // Method getCommitter:()Lio/dekorate/deps/openshift/api/model/SourceControlUser;
       5: invokevirtual #177                // Method withNewCommitterLike:(Lio/dekorate/deps/openshift/api/model/SourceControlUser;)Lio/dekorate/deps/openshift/api/model/GitSourceRevisionFluent$CommitterNested;
       8: areturn

  public io.dekorate.deps.openshift.api.model.GitSourceRevisionFluent$CommitterNested<A> editOrNewCommitter();
    Code:
       0: aload_0
       1: aload_0
       2: invokevirtual #175                // Method getCommitter:()Lio/dekorate/deps/openshift/api/model/SourceControlUser;
       5: ifnull        15
       8: aload_0
       9: invokevirtual #175                // Method getCommitter:()Lio/dekorate/deps/openshift/api/model/SourceControlUser;
      12: goto          25
      15: new           #71                 // class io/dekorate/deps/openshift/api/model/SourceControlUserBuilder
      18: dup
      19: invokespecial #136                // Method io/dekorate/deps/openshift/api/model/SourceControlUserBuilder."<init>":()V
      22: invokevirtual #74                 // Method io/dekorate/deps/openshift/api/model/SourceControlUserBuilder.build:()Lio/dekorate/deps/openshift/api/model/SourceControlUser;
      25: invokevirtual #177                // Method withNewCommitterLike:(Lio/dekorate/deps/openshift/api/model/SourceControlUser;)Lio/dekorate/deps/openshift/api/model/GitSourceRevisionFluent$CommitterNested;
      28: areturn

  public io.dekorate.deps.openshift.api.model.GitSourceRevisionFluent$CommitterNested<A> editOrNewCommitterLike(io.dekorate.deps.openshift.api.model.SourceControlUser);
    Code:
       0: aload_0
       1: aload_0
       2: invokevirtual #175                // Method getCommitter:()Lio/dekorate/deps/openshift/api/model/SourceControlUser;
       5: ifnull        15
       8: aload_0
       9: invokevirtual #175                // Method getCommitter:()Lio/dekorate/deps/openshift/api/model/SourceControlUser;
      12: goto          16
      15: aload_1
      16: invokevirtual #177                // Method withNewCommitterLike:(Lio/dekorate/deps/openshift/api/model/SourceControlUser;)Lio/dekorate/deps/openshift/api/model/GitSourceRevisionFluent$CommitterNested;
      19: areturn

  public java.lang.String getMessage();
    Code:
       0: aload_0
       1: getfield      #181                // Field message:Ljava/lang/String;
       4: areturn

  public A withMessage(java.lang.String);
    Code:
       0: aload_0
       1: aload_1
       2: putfield      #181                // Field message:Ljava/lang/String;
       5: aload_0
       6: areturn

  public java.lang.Boolean hasMessage();
    Code:
       0: aload_0
       1: getfield      #181                // Field message:Ljava/lang/String;
       4: ifnull        11
       7: iconst_1
       8: goto          12
      11: iconst_0
      12: invokestatic  #110                // Method java/lang/Boolean.valueOf:(Z)Ljava/lang/Boolean;
      15: areturn

  public A withNewMessage(java.lang.String);
    Code:
       0: aload_0
       1: new           #144                // class java/lang/String
       4: dup
       5: aload_1
       6: invokespecial #147                // Method java/lang/String."<init>":(Ljava/lang/String;)V
       9: invokevirtual #64                 // Method withMessage:(Ljava/lang/String;)Lio/dekorate/deps/openshift/api/model/GitSourceRevisionFluent;
      12: areturn

  public A withNewMessage(java.lang.StringBuilder);
    Code:
       0: aload_0
       1: new           #144                // class java/lang/String
       4: dup
       5: aload_1
       6: invokespecial #153                // Method java/lang/String."<init>":(Ljava/lang/StringBuilder;)V
       9: invokevirtual #64                 // Method withMessage:(Ljava/lang/String;)Lio/dekorate/deps/openshift/api/model/GitSourceRevisionFluent;
      12: areturn

  public A withNewMessage(java.lang.StringBuffer);
    Code:
       0: aload_0
       1: new           #144                // class java/lang/String
       4: dup
       5: aload_1
       6: invokespecial #159                // Method java/lang/String."<init>":(Ljava/lang/StringBuffer;)V
       9: invokevirtual #64                 // Method withMessage:(Ljava/lang/String;)Lio/dekorate/deps/openshift/api/model/GitSourceRevisionFluent;
      12: areturn

  public boolean equals(java.lang.Object);
    Code:
       0: aload_0
       1: aload_1
       2: if_acmpne     7
       5: iconst_1
       6: ireturn
       7: aload_1
       8: ifnull        22
      11: aload_0
      12: invokevirtual #190                // Method java/lang/Object.getClass:()Ljava/lang/Class;
      15: aload_1
      16: invokevirtual #190                // Method java/lang/Object.getClass:()Ljava/lang/Class;
      19: if_acmpeq     24
      22: iconst_0
      23: ireturn
      24: aload_1
      25: checkcast     #2                  // class io/dekorate/deps/openshift/api/model/GitSourceRevisionFluentImpl
      28: astore_2
      29: aload_0
      30: getfield      #69                 // Field author:Lio/dekorate/deps/openshift/api/model/SourceControlUserBuilder;
      33: ifnull        53
      36: aload_0
      37: getfield      #69                 // Field author:Lio/dekorate/deps/openshift/api/model/SourceControlUserBuilder;
      40: aload_2
      41: getfield      #69                 // Field author:Lio/dekorate/deps/openshift/api/model/SourceControlUserBuilder;
      44: invokevirtual #192                // Method io/dekorate/deps/openshift/api/model/SourceControlUserBuilder.equals:(Ljava/lang/Object;)Z
      47: ifne          62
      50: goto          60
      53: aload_2
      54: getfield      #69                 // Field author:Lio/dekorate/deps/openshift/api/model/SourceControlUserBuilder;
      57: ifnull        62
      60: iconst_0
      61: ireturn
      62: aload_0
      63: getfield      #139                // Field commit:Ljava/lang/String;
      66: ifnull        86
      69: aload_0
      70: getfield      #139                // Field commit:Ljava/lang/String;
      73: aload_2
      74: getfield      #139                // Field commit:Ljava/lang/String;
      77: invokevirtual #193                // Method java/lang/String.equals:(Ljava/lang/Object;)Z
      80: ifne          95
      83: goto          93
      86: aload_2
      87: getfield      #139                // Field commit:Ljava/lang/String;
      90: ifnull        95
      93: iconst_0
      94: ireturn
      95: aload_0
      96: getfield      #162                // Field committer:Lio/dekorate/deps/openshift/api/model/SourceControlUserBuilder;
      99: ifnull        119
     102: aload_0
     103: getfield      #162                // Field committer:Lio/dekorate/deps/openshift/api/model/SourceControlUserBuilder;
     106: aload_2
     107: getfield      #162                // Field committer:Lio/dekorate/deps/openshift/api/model/SourceControlUserBuilder;
     110: invokevirtual #192                // Method io/dekorate/deps/openshift/api/model/SourceControlUserBuilder.equals:(Ljava/lang/Object;)Z
     113: ifne          128
     116: goto          126
     119: aload_2
     120: getfield      #162                // Field committer:Lio/dekorate/deps/openshift/api/model/SourceControlUserBuilder;
     123: ifnull        128
     126: iconst_0
     127: ireturn
     128: aload_0
     129: getfield      #181                // Field message:Ljava/lang/String;
     132: ifnull        152
     135: aload_0
     136: getfield      #181                // Field message:Ljava/lang/String;
     139: aload_2
     140: getfield      #181                // Field message:Ljava/lang/String;
     143: invokevirtual #193                // Method java/lang/String.equals:(Ljava/lang/Object;)Z
     146: ifne          161
     149: goto          159
     152: aload_2
     153: getfield      #181                // Field message:Ljava/lang/String;
     156: ifnull        161
     159: iconst_0
     160: ireturn
     161: iconst_1
     162: ireturn
}
