Compiled from "GitSourceRevisionFluentImpl.java"
public class io.dekorate.deps.openshift.api.model.GitSourceRevisionFluentImpl$CommitterNestedImpl<N> extends io.dekorate.deps.openshift.api.model.SourceControlUserFluentImpl<io.dekorate.deps.openshift.api.model.GitSourceRevisionFluent$CommitterNested<N>> implements io.dekorate.deps.openshift.api.model.GitSourceRevisionFluent$CommitterNested<N>, io.dekorate.deps.kubernetes.api.builder.Nested<N> {
  private final io.dekorate.deps.openshift.api.model.SourceControlUserBuilder builder;

  final io.dekorate.deps.openshift.api.model.GitSourceRevisionFluentImpl this$0;

  io.dekorate.deps.openshift.api.model.GitSourceRevisionFluentImpl$CommitterNestedImpl(io.dekorate.deps.openshift.api.model.GitSourceRevisionFluentImpl, io.dekorate.deps.openshift.api.model.SourceControlUser);
    Code:
       0: aload_0
       1: aload_1
       2: putfield      #24                 // Field this$0:Lio/dekorate/deps/openshift/api/model/GitSourceRevisionFluentImpl;
       5: aload_0
       6: invokespecial #27                 // Method io/dekorate/deps/openshift/api/model/SourceControlUserFluentImpl."<init>":()V
       9: aload_0
      10: new           #29                 // class io/dekorate/deps/openshift/api/model/SourceControlUserBuilder
      13: dup
      14: aload_0
      15: aload_2
      16: invokespecial #32                 // Method io/dekorate/deps/openshift/api/model/SourceControlUserBuilder."<init>":(Lio/dekorate/deps/openshift/api/model/SourceControlUserFluent;Lio/dekorate/deps/openshift/api/model/SourceControlUser;)V
      19: putfield      #34                 // Field builder:Lio/dekorate/deps/openshift/api/model/SourceControlUserBuilder;
      22: return

  io.dekorate.deps.openshift.api.model.GitSourceRevisionFluentImpl$CommitterNestedImpl(io.dekorate.deps.openshift.api.model.GitSourceRevisionFluentImpl);
    Code:
       0: aload_0
       1: aload_1
       2: putfield      #24                 // Field this$0:Lio/dekorate/deps/openshift/api/model/GitSourceRevisionFluentImpl;
       5: aload_0
       6: invokespecial #27                 // Method io/dekorate/deps/openshift/api/model/SourceControlUserFluentImpl."<init>":()V
       9: aload_0
      10: new           #29                 // class io/dekorate/deps/openshift/api/model/SourceControlUserBuilder
      13: dup
      14: aload_0
      15: invokespecial #43                 // Method io/dekorate/deps/openshift/api/model/SourceControlUserBuilder."<init>":(Lio/dekorate/deps/openshift/api/model/SourceControlUserFluent;)V
      18: putfield      #34                 // Field builder:Lio/dekorate/deps/openshift/api/model/SourceControlUserBuilder;
      21: return

  public N and();
    Code:
       0: aload_0
       1: getfield      #24                 // Field this$0:Lio/dekorate/deps/openshift/api/model/GitSourceRevisionFluentImpl;
       4: aload_0
       5: getfield      #34                 // Field builder:Lio/dekorate/deps/openshift/api/model/SourceControlUserBuilder;
       8: invokevirtual #50                 // Method io/dekorate/deps/openshift/api/model/SourceControlUserBuilder.build:()Lio/dekorate/deps/openshift/api/model/SourceControlUser;
      11: invokevirtual #54                 // Method io/dekorate/deps/openshift/api/model/GitSourceRevisionFluentImpl.withCommitter:(Lio/dekorate/deps/openshift/api/model/SourceControlUser;)Lio/dekorate/deps/openshift/api/model/GitSourceRevisionFluent;
      14: areturn

  public N endCommitter();
    Code:
       0: aload_0
       1: invokevirtual #57                 // Method and:()Ljava/lang/Object;
       4: areturn
}
