Compiled from "ImageStreamTagFluentImpl.java"
public class io.dekorate.deps.openshift.api.model.ImageStreamTagFluentImpl$ConditionsNestedImpl<N> extends io.dekorate.deps.openshift.api.model.TagEventConditionFluentImpl<io.dekorate.deps.openshift.api.model.ImageStreamTagFluent$ConditionsNested<N>> implements io.dekorate.deps.openshift.api.model.ImageStreamTagFluent$ConditionsNested<N>, io.dekorate.deps.kubernetes.api.builder.Nested<N> {
  private final io.dekorate.deps.openshift.api.model.TagEventConditionBuilder builder;

  private final int index;

  final io.dekorate.deps.openshift.api.model.ImageStreamTagFluentImpl this$0;

  io.dekorate.deps.openshift.api.model.ImageStreamTagFluentImpl$ConditionsNestedImpl(io.dekorate.deps.openshift.api.model.ImageStreamTagFluentImpl, int, io.dekorate.deps.openshift.api.model.TagEventCondition);
    Code:
       0: aload_0
       1: aload_1
       2: putfield      #26                 // Field this$0:Lio/dekorate/deps/openshift/api/model/ImageStreamTagFluentImpl;
       5: aload_0
       6: invokespecial #29                 // Method io/dekorate/deps/openshift/api/model/TagEventConditionFluentImpl."<init>":()V
       9: aload_0
      10: iload_2
      11: putfield      #31                 // Field index:I
      14: aload_0
      15: new           #33                 // class io/dekorate/deps/openshift/api/model/TagEventConditionBuilder
      18: dup
      19: aload_0
      20: aload_3
      21: invokespecial #36                 // Method io/dekorate/deps/openshift/api/model/TagEventConditionBuilder."<init>":(Lio/dekorate/deps/openshift/api/model/TagEventConditionFluent;Lio/dekorate/deps/openshift/api/model/TagEventCondition;)V
      24: putfield      #38                 // Field builder:Lio/dekorate/deps/openshift/api/model/TagEventConditionBuilder;
      27: return

  io.dekorate.deps.openshift.api.model.ImageStreamTagFluentImpl$ConditionsNestedImpl(io.dekorate.deps.openshift.api.model.ImageStreamTagFluentImpl);
    Code:
       0: aload_0
       1: aload_1
       2: putfield      #26                 // Field this$0:Lio/dekorate/deps/openshift/api/model/ImageStreamTagFluentImpl;
       5: aload_0
       6: invokespecial #29                 // Method io/dekorate/deps/openshift/api/model/TagEventConditionFluentImpl."<init>":()V
       9: aload_0
      10: iconst_m1
      11: putfield      #31                 // Field index:I
      14: aload_0
      15: new           #33                 // class io/dekorate/deps/openshift/api/model/TagEventConditionBuilder
      18: dup
      19: aload_0
      20: invokespecial #47                 // Method io/dekorate/deps/openshift/api/model/TagEventConditionBuilder."<init>":(Lio/dekorate/deps/openshift/api/model/TagEventConditionFluent;)V
      23: putfield      #38                 // Field builder:Lio/dekorate/deps/openshift/api/model/TagEventConditionBuilder;
      26: return

  public N and();
    Code:
       0: aload_0
       1: getfield      #26                 // Field this$0:Lio/dekorate/deps/openshift/api/model/ImageStreamTagFluentImpl;
       4: aload_0
       5: getfield      #31                 // Field index:I
       8: aload_0
       9: getfield      #38                 // Field builder:Lio/dekorate/deps/openshift/api/model/TagEventConditionBuilder;
      12: invokevirtual #54                 // Method io/dekorate/deps/openshift/api/model/TagEventConditionBuilder.build:()Lio/dekorate/deps/openshift/api/model/TagEventCondition;
      15: invokevirtual #58                 // Method io/dekorate/deps/openshift/api/model/ImageStreamTagFluentImpl.setToConditions:(ILio/dekorate/deps/openshift/api/model/TagEventCondition;)Lio/dekorate/deps/openshift/api/model/ImageStreamTagFluent;
      18: areturn

  public N endCondition();
    Code:
       0: aload_0
       1: invokevirtual #61                 // Method and:()Ljava/lang/Object;
       4: areturn
}
