Compiled from "PolicyRuleFluentImpl.java"
public class io.dekorate.deps.openshift.api.model.PolicyRuleFluentImpl$GroupAttributeRestrictionsNestedImpl<N> extends io.dekorate.deps.openshift.api.model.GroupFluentImpl<io.dekorate.deps.openshift.api.model.PolicyRuleFluent$GroupAttributeRestrictionsNested<N>> implements io.dekorate.deps.openshift.api.model.PolicyRuleFluent$GroupAttributeRestrictionsNested<N>, io.dekorate.deps.kubernetes.api.builder.Nested<N> {
  private final io.dekorate.deps.openshift.api.model.GroupBuilder builder;

  final io.dekorate.deps.openshift.api.model.PolicyRuleFluentImpl this$0;

  io.dekorate.deps.openshift.api.model.PolicyRuleFluentImpl$GroupAttributeRestrictionsNestedImpl(io.dekorate.deps.openshift.api.model.PolicyRuleFluentImpl, io.dekorate.deps.openshift.api.model.Group);
    Code:
       0: aload_0
       1: aload_1
       2: putfield      #24                 // Field this$0:Lio/dekorate/deps/openshift/api/model/PolicyRuleFluentImpl;
       5: aload_0
       6: invokespecial #27                 // Method io/dekorate/deps/openshift/api/model/GroupFluentImpl."<init>":()V
       9: aload_0
      10: new           #29                 // class io/dekorate/deps/openshift/api/model/GroupBuilder
      13: dup
      14: aload_0
      15: aload_2
      16: invokespecial #32                 // Method io/dekorate/deps/openshift/api/model/GroupBuilder."<init>":(Lio/dekorate/deps/openshift/api/model/GroupFluent;Lio/dekorate/deps/openshift/api/model/Group;)V
      19: putfield      #34                 // Field builder:Lio/dekorate/deps/openshift/api/model/GroupBuilder;
      22: return

  io.dekorate.deps.openshift.api.model.PolicyRuleFluentImpl$GroupAttributeRestrictionsNestedImpl(io.dekorate.deps.openshift.api.model.PolicyRuleFluentImpl);
    Code:
       0: aload_0
       1: aload_1
       2: putfield      #24                 // Field this$0:Lio/dekorate/deps/openshift/api/model/PolicyRuleFluentImpl;
       5: aload_0
       6: invokespecial #27                 // Method io/dekorate/deps/openshift/api/model/GroupFluentImpl."<init>":()V
       9: aload_0
      10: new           #29                 // class io/dekorate/deps/openshift/api/model/GroupBuilder
      13: dup
      14: aload_0
      15: invokespecial #43                 // Method io/dekorate/deps/openshift/api/model/GroupBuilder."<init>":(Lio/dekorate/deps/openshift/api/model/GroupFluent;)V
      18: putfield      #34                 // Field builder:Lio/dekorate/deps/openshift/api/model/GroupBuilder;
      21: return

  public N and();
    Code:
       0: aload_0
       1: getfield      #24                 // Field this$0:Lio/dekorate/deps/openshift/api/model/PolicyRuleFluentImpl;
       4: aload_0
       5: getfield      #34                 // Field builder:Lio/dekorate/deps/openshift/api/model/GroupBuilder;
       8: invokevirtual #50                 // Method io/dekorate/deps/openshift/api/model/GroupBuilder.build:()Lio/dekorate/deps/openshift/api/model/Group;
      11: invokevirtual #54                 // Method io/dekorate/deps/openshift/api/model/PolicyRuleFluentImpl.withAttributeRestrictions:(Lio/dekorate/deps/kubernetes/api/model/HasMetadata;)Lio/dekorate/deps/openshift/api/model/PolicyRuleFluent;
      14: areturn

  public N endGroupAttributeRestrictions();
    Code:
       0: aload_0
       1: invokevirtual #57                 // Method and:()Ljava/lang/Object;
       4: areturn
}
