Compiled from "SourceBuildStrategyFluentImpl.java"
public class io.dekorate.deps.openshift.api.model.SourceBuildStrategyFluentImpl$PullSecretNestedImpl<N> extends io.dekorate.deps.kubernetes.api.model.LocalObjectReferenceFluentImpl<io.dekorate.deps.openshift.api.model.SourceBuildStrategyFluent$PullSecretNested<N>> implements io.dekorate.deps.openshift.api.model.SourceBuildStrategyFluent$PullSecretNested<N>, io.dekorate.deps.kubernetes.api.builder.Nested<N> {
  private final io.dekorate.deps.kubernetes.api.model.LocalObjectReferenceBuilder builder;

  final io.dekorate.deps.openshift.api.model.SourceBuildStrategyFluentImpl this$0;

  io.dekorate.deps.openshift.api.model.SourceBuildStrategyFluentImpl$PullSecretNestedImpl(io.dekorate.deps.openshift.api.model.SourceBuildStrategyFluentImpl, io.dekorate.deps.kubernetes.api.model.LocalObjectReference);
    Code:
       0: aload_0
       1: aload_1
       2: putfield      #24                 // Field this$0:Lio/dekorate/deps/openshift/api/model/SourceBuildStrategyFluentImpl;
       5: aload_0
       6: invokespecial #27                 // Method io/dekorate/deps/kubernetes/api/model/LocalObjectReferenceFluentImpl."<init>":()V
       9: aload_0
      10: new           #29                 // class io/dekorate/deps/kubernetes/api/model/LocalObjectReferenceBuilder
      13: dup
      14: aload_0
      15: aload_2
      16: invokespecial #32                 // Method io/dekorate/deps/kubernetes/api/model/LocalObjectReferenceBuilder."<init>":(Lio/dekorate/deps/kubernetes/api/model/LocalObjectReferenceFluent;Lio/dekorate/deps/kubernetes/api/model/LocalObjectReference;)V
      19: putfield      #34                 // Field builder:Lio/dekorate/deps/kubernetes/api/model/LocalObjectReferenceBuilder;
      22: return

  io.dekorate.deps.openshift.api.model.SourceBuildStrategyFluentImpl$PullSecretNestedImpl(io.dekorate.deps.openshift.api.model.SourceBuildStrategyFluentImpl);
    Code:
       0: aload_0
       1: aload_1
       2: putfield      #24                 // Field this$0:Lio/dekorate/deps/openshift/api/model/SourceBuildStrategyFluentImpl;
       5: aload_0
       6: invokespecial #27                 // Method io/dekorate/deps/kubernetes/api/model/LocalObjectReferenceFluentImpl."<init>":()V
       9: aload_0
      10: new           #29                 // class io/dekorate/deps/kubernetes/api/model/LocalObjectReferenceBuilder
      13: dup
      14: aload_0
      15: invokespecial #43                 // Method io/dekorate/deps/kubernetes/api/model/LocalObjectReferenceBuilder."<init>":(Lio/dekorate/deps/kubernetes/api/model/LocalObjectReferenceFluent;)V
      18: putfield      #34                 // Field builder:Lio/dekorate/deps/kubernetes/api/model/LocalObjectReferenceBuilder;
      21: return

  public N and();
    Code:
       0: aload_0
       1: getfield      #24                 // Field this$0:Lio/dekorate/deps/openshift/api/model/SourceBuildStrategyFluentImpl;
       4: aload_0
       5: getfield      #34                 // Field builder:Lio/dekorate/deps/kubernetes/api/model/LocalObjectReferenceBuilder;
       8: invokevirtual #50                 // Method io/dekorate/deps/kubernetes/api/model/LocalObjectReferenceBuilder.build:()Lio/dekorate/deps/kubernetes/api/model/LocalObjectReference;
      11: invokevirtual #54                 // Method io/dekorate/deps/openshift/api/model/SourceBuildStrategyFluentImpl.withPullSecret:(Lio/dekorate/deps/kubernetes/api/model/LocalObjectReference;)Lio/dekorate/deps/openshift/api/model/SourceBuildStrategyFluent;
      14: areturn

  public N endPullSecret();
    Code:
       0: aload_0
       1: invokevirtual #57                 // Method and:()Ljava/lang/Object;
       4: areturn
}
