Compiled from "StageInfoBuilder.java"
public class io.dekorate.deps.openshift.api.model.StageInfoBuilder extends io.dekorate.deps.openshift.api.model.StageInfoFluentImpl<io.dekorate.deps.openshift.api.model.StageInfoBuilder> implements io.dekorate.deps.kubernetes.api.builder.VisitableBuilder<io.dekorate.deps.openshift.api.model.StageInfo, io.dekorate.deps.openshift.api.model.StageInfoBuilder> {
  io.dekorate.deps.openshift.api.model.StageInfoFluent<?> fluent;

  java.lang.Boolean validationEnabled;

  public io.dekorate.deps.openshift.api.model.StageInfoBuilder();
    Code:
       0: aload_0
       1: iconst_1
       2: invokestatic  #21                 // Method java/lang/Boolean.valueOf:(Z)Ljava/lang/Boolean;
       5: invokespecial #24                 // Method "<init>":(Ljava/lang/Boolean;)V
       8: return

  public io.dekorate.deps.openshift.api.model.StageInfoBuilder(java.lang.Boolean);
    Code:
       0: aload_0
       1: new           #28                 // class io/dekorate/deps/openshift/api/model/StageInfo
       4: dup
       5: invokespecial #30                 // Method io/dekorate/deps/openshift/api/model/StageInfo."<init>":()V
       8: aload_1
       9: invokespecial #33                 // Method "<init>":(Lio/dekorate/deps/openshift/api/model/StageInfo;Ljava/lang/Boolean;)V
      12: return

  public io.dekorate.deps.openshift.api.model.StageInfoBuilder(io.dekorate.deps.openshift.api.model.StageInfoFluent<?>);
    Code:
       0: aload_0
       1: aload_1
       2: iconst_1
       3: invokestatic  #21                 // Method java/lang/Boolean.valueOf:(Z)Ljava/lang/Boolean;
       6: invokespecial #38                 // Method "<init>":(Lio/dekorate/deps/openshift/api/model/StageInfoFluent;Ljava/lang/Boolean;)V
       9: return

  public io.dekorate.deps.openshift.api.model.StageInfoBuilder(io.dekorate.deps.openshift.api.model.StageInfoFluent<?>, java.lang.Boolean);
    Code:
       0: aload_0
       1: aload_1
       2: new           #28                 // class io/dekorate/deps/openshift/api/model/StageInfo
       5: dup
       6: invokespecial #30                 // Method io/dekorate/deps/openshift/api/model/StageInfo."<init>":()V
       9: aload_2
      10: invokespecial #42                 // Method "<init>":(Lio/dekorate/deps/openshift/api/model/StageInfoFluent;Lio/dekorate/deps/openshift/api/model/StageInfo;Ljava/lang/Boolean;)V
      13: return

  public io.dekorate.deps.openshift.api.model.StageInfoBuilder(io.dekorate.deps.openshift.api.model.StageInfoFluent<?>, io.dekorate.deps.openshift.api.model.StageInfo);
    Code:
       0: aload_0
       1: aload_1
       2: aload_2
       3: iconst_1
       4: invokestatic  #21                 // Method java/lang/Boolean.valueOf:(Z)Ljava/lang/Boolean;
       7: invokespecial #42                 // Method "<init>":(Lio/dekorate/deps/openshift/api/model/StageInfoFluent;Lio/dekorate/deps/openshift/api/model/StageInfo;Ljava/lang/Boolean;)V
      10: return

  public io.dekorate.deps.openshift.api.model.StageInfoBuilder(io.dekorate.deps.openshift.api.model.StageInfoFluent<?>, io.dekorate.deps.openshift.api.model.StageInfo, java.lang.Boolean);
    Code:
       0: aload_0
       1: invokespecial #48                 // Method io/dekorate/deps/openshift/api/model/StageInfoFluentImpl."<init>":()V
       4: aload_0
       5: aload_1
       6: putfield      #50                 // Field fluent:Lio/dekorate/deps/openshift/api/model/StageInfoFluent;
       9: aload_1
      10: aload_2
      11: invokevirtual #54                 // Method io/dekorate/deps/openshift/api/model/StageInfo.getDurationMilliseconds:()Ljava/lang/Long;
      14: invokeinterface #60,  2           // InterfaceMethod io/dekorate/deps/openshift/api/model/StageInfoFluent.withDurationMilliseconds:(Ljava/lang/Long;)Lio/dekorate/deps/openshift/api/model/StageInfoFluent;
      19: pop
      20: aload_1
      21: aload_2
      22: invokevirtual #64                 // Method io/dekorate/deps/openshift/api/model/StageInfo.getName:()Ljava/lang/String;
      25: invokeinterface #68,  2           // InterfaceMethod io/dekorate/deps/openshift/api/model/StageInfoFluent.withName:(Ljava/lang/String;)Lio/dekorate/deps/openshift/api/model/StageInfoFluent;
      30: pop
      31: aload_1
      32: aload_2
      33: invokevirtual #71                 // Method io/dekorate/deps/openshift/api/model/StageInfo.getStartTime:()Ljava/lang/String;
      36: invokeinterface #74,  2           // InterfaceMethod io/dekorate/deps/openshift/api/model/StageInfoFluent.withStartTime:(Ljava/lang/String;)Lio/dekorate/deps/openshift/api/model/StageInfoFluent;
      41: pop
      42: aload_1
      43: aload_2
      44: invokevirtual #78                 // Method io/dekorate/deps/openshift/api/model/StageInfo.getSteps:()Ljava/util/List;
      47: invokeinterface #82,  2           // InterfaceMethod io/dekorate/deps/openshift/api/model/StageInfoFluent.withSteps:(Ljava/util/List;)Lio/dekorate/deps/openshift/api/model/StageInfoFluent;
      52: pop
      53: aload_0
      54: aload_3
      55: putfield      #84                 // Field validationEnabled:Ljava/lang/Boolean;
      58: return

  public io.dekorate.deps.openshift.api.model.StageInfoBuilder(io.dekorate.deps.openshift.api.model.StageInfo);
    Code:
       0: aload_0
       1: aload_1
       2: iconst_1
       3: invokestatic  #21                 // Method java/lang/Boolean.valueOf:(Z)Ljava/lang/Boolean;
       6: invokespecial #33                 // Method "<init>":(Lio/dekorate/deps/openshift/api/model/StageInfo;Ljava/lang/Boolean;)V
       9: return

  public io.dekorate.deps.openshift.api.model.StageInfoBuilder(io.dekorate.deps.openshift.api.model.StageInfo, java.lang.Boolean);
    Code:
       0: aload_0
       1: invokespecial #48                 // Method io/dekorate/deps/openshift/api/model/StageInfoFluentImpl."<init>":()V
       4: aload_0
       5: aload_0
       6: putfield      #50                 // Field fluent:Lio/dekorate/deps/openshift/api/model/StageInfoFluent;
       9: aload_0
      10: aload_1
      11: invokevirtual #54                 // Method io/dekorate/deps/openshift/api/model/StageInfo.getDurationMilliseconds:()Ljava/lang/Long;
      14: invokevirtual #86                 // Method withDurationMilliseconds:(Ljava/lang/Long;)Lio/dekorate/deps/openshift/api/model/StageInfoFluent;
      17: pop
      18: aload_0
      19: aload_1
      20: invokevirtual #64                 // Method io/dekorate/deps/openshift/api/model/StageInfo.getName:()Ljava/lang/String;
      23: invokevirtual #87                 // Method withName:(Ljava/lang/String;)Lio/dekorate/deps/openshift/api/model/StageInfoFluent;
      26: pop
      27: aload_0
      28: aload_1
      29: invokevirtual #71                 // Method io/dekorate/deps/openshift/api/model/StageInfo.getStartTime:()Ljava/lang/String;
      32: invokevirtual #88                 // Method withStartTime:(Ljava/lang/String;)Lio/dekorate/deps/openshift/api/model/StageInfoFluent;
      35: pop
      36: aload_0
      37: aload_1
      38: invokevirtual #78                 // Method io/dekorate/deps/openshift/api/model/StageInfo.getSteps:()Ljava/util/List;
      41: invokevirtual #89                 // Method withSteps:(Ljava/util/List;)Lio/dekorate/deps/openshift/api/model/StageInfoFluent;
      44: pop
      45: aload_0
      46: aload_2
      47: putfield      #84                 // Field validationEnabled:Ljava/lang/Boolean;
      50: return

  public io.dekorate.deps.openshift.api.model.StageInfo build();
    Code:
       0: new           #28                 // class io/dekorate/deps/openshift/api/model/StageInfo
       3: dup
       4: aload_0
       5: getfield      #50                 // Field fluent:Lio/dekorate/deps/openshift/api/model/StageInfoFluent;
       8: invokeinterface #92,  1           // InterfaceMethod io/dekorate/deps/openshift/api/model/StageInfoFluent.getDurationMilliseconds:()Ljava/lang/Long;
      13: aload_0
      14: getfield      #50                 // Field fluent:Lio/dekorate/deps/openshift/api/model/StageInfoFluent;
      17: invokeinterface #93,  1           // InterfaceMethod io/dekorate/deps/openshift/api/model/StageInfoFluent.getName:()Ljava/lang/String;
      22: aload_0
      23: getfield      #50                 // Field fluent:Lio/dekorate/deps/openshift/api/model/StageInfoFluent;
      26: invokeinterface #94,  1           // InterfaceMethod io/dekorate/deps/openshift/api/model/StageInfoFluent.getStartTime:()Ljava/lang/String;
      31: aload_0
      32: getfield      #50                 // Field fluent:Lio/dekorate/deps/openshift/api/model/StageInfoFluent;
      35: invokeinterface #95,  1           // InterfaceMethod io/dekorate/deps/openshift/api/model/StageInfoFluent.getSteps:()Ljava/util/List;
      40: invokespecial #98                 // Method io/dekorate/deps/openshift/api/model/StageInfo."<init>":(Ljava/lang/Long;Ljava/lang/String;Ljava/lang/String;Ljava/util/List;)V
      43: astore_1
      44: aload_1
      45: areturn

  public boolean equals(java.lang.Object);
    Code:
       0: aload_0
       1: aload_1
       2: if_acmpne     7
       5: iconst_1
       6: ireturn
       7: aload_1
       8: ifnull        22
      11: aload_0
      12: invokevirtual #107                // Method java/lang/Object.getClass:()Ljava/lang/Class;
      15: aload_1
      16: invokevirtual #107                // Method java/lang/Object.getClass:()Ljava/lang/Class;
      19: if_acmpeq     24
      22: iconst_0
      23: ireturn
      24: aload_0
      25: aload_1
      26: invokespecial #109                // Method io/dekorate/deps/openshift/api/model/StageInfoFluentImpl.equals:(Ljava/lang/Object;)Z
      29: ifne          34
      32: iconst_0
      33: ireturn
      34: aload_1
      35: checkcast     #2                  // class io/dekorate/deps/openshift/api/model/StageInfoBuilder
      38: astore_2
      39: aload_0
      40: getfield      #50                 // Field fluent:Lio/dekorate/deps/openshift/api/model/StageInfoFluent;
      43: ifnull        71
      46: aload_0
      47: getfield      #50                 // Field fluent:Lio/dekorate/deps/openshift/api/model/StageInfoFluent;
      50: aload_0
      51: if_acmpeq     71
      54: aload_0
      55: getfield      #50                 // Field fluent:Lio/dekorate/deps/openshift/api/model/StageInfoFluent;
      58: aload_2
      59: getfield      #50                 // Field fluent:Lio/dekorate/deps/openshift/api/model/StageInfoFluent;
      62: invokevirtual #110                // Method java/lang/Object.equals:(Ljava/lang/Object;)Z
      65: ifne          88
      68: goto          86
      71: aload_2
      72: getfield      #50                 // Field fluent:Lio/dekorate/deps/openshift/api/model/StageInfoFluent;
      75: ifnull        88
      78: aload_0
      79: getfield      #50                 // Field fluent:Lio/dekorate/deps/openshift/api/model/StageInfoFluent;
      82: aload_0
      83: if_acmpeq     88
      86: iconst_0
      87: ireturn
      88: aload_0
      89: getfield      #84                 // Field validationEnabled:Ljava/lang/Boolean;
      92: ifnull        112
      95: aload_0
      96: getfield      #84                 // Field validationEnabled:Ljava/lang/Boolean;
      99: aload_2
     100: getfield      #84                 // Field validationEnabled:Ljava/lang/Boolean;
     103: invokevirtual #111                // Method java/lang/Boolean.equals:(Ljava/lang/Object;)Z
     106: ifne          121
     109: goto          119
     112: aload_2
     113: getfield      #84                 // Field validationEnabled:Ljava/lang/Boolean;
     116: ifnull        121
     119: iconst_0
     120: ireturn
     121: iconst_1
     122: ireturn

  public java.lang.Object build();
    Code:
       0: aload_0
       1: invokevirtual #117                // Method build:()Lio/dekorate/deps/openshift/api/model/StageInfo;
       4: areturn
}
