Compiled from "JSON.java"
public class org.eclipse.jetty.util.ajax.JSON {
  static final org.eclipse.jetty.util.log.Logger LOG;

  public static final org.eclipse.jetty.util.ajax.JSON DEFAULT;

  private final java.util.Map<java.lang.String, org.eclipse.jetty.util.ajax.JSON$Convertor> _convertors;

  private int _stringBufferSize;

  private java.util.function.Function<java.util.List<?>, java.lang.Object> _arrayConverter;

  public org.eclipse.jetty.util.ajax.JSON();
    Code:
       0: aload_0
       1: invokespecial #2                  // Method java/lang/Object."<init>":()V
       4: aload_0
       5: new           #3                  // class java/util/concurrent/ConcurrentHashMap
       8: dup
       9: invokespecial #4                  // Method java/util/concurrent/ConcurrentHashMap."<init>":()V
      12: putfield      #5                  // Field _convertors:Ljava/util/Map;
      15: aload_0
      16: sipush        1024
      19: putfield      #6                  // Field _stringBufferSize:I
      22: aload_0
      23: aload_0
      24: invokedynamic #7,  0              // InvokeDynamic #0:apply:(Lorg/eclipse/jetty/util/ajax/JSON;)Ljava/util/function/Function;
      29: putfield      #8                  // Field _arrayConverter:Ljava/util/function/Function;
      32: return

  public static void reset();
    Code:
       0: getstatic     #9                  // Field DEFAULT:Lorg/eclipse/jetty/util/ajax/JSON;
       3: getfield      #5                  // Field _convertors:Ljava/util/Map;
       6: invokeinterface #10,  1           // InterfaceMethod java/util/Map.clear:()V
      11: getstatic     #9                  // Field DEFAULT:Lorg/eclipse/jetty/util/ajax/JSON;
      14: sipush        1024
      17: putfield      #6                  // Field _stringBufferSize:I
      20: return

  public int getStringBufferSize();
    Code:
       0: aload_0
       1: getfield      #6                  // Field _stringBufferSize:I
       4: ireturn

  public void setStringBufferSize(int);
    Code:
       0: aload_0
       1: iload_1
       2: putfield      #6                  // Field _stringBufferSize:I
       5: return

  public static void registerConvertor(java.lang.Class, org.eclipse.jetty.util.ajax.JSON$Convertor);
    Code:
       0: getstatic     #9                  // Field DEFAULT:Lorg/eclipse/jetty/util/ajax/JSON;
       3: aload_0
       4: aload_1
       5: invokevirtual #11                 // Method addConvertor:(Ljava/lang/Class;Lorg/eclipse/jetty/util/ajax/JSON$Convertor;)V
       8: return

  public static org.eclipse.jetty.util.ajax.JSON getDefault();
    Code:
       0: getstatic     #9                  // Field DEFAULT:Lorg/eclipse/jetty/util/ajax/JSON;
       3: areturn

  public static void setDefault(org.eclipse.jetty.util.ajax.JSON);
    Code:
       0: return

  public static java.lang.String toString(java.lang.Object);
    Code:
       0: new           #12                 // class java/lang/StringBuilder
       3: dup
       4: getstatic     #9                  // Field DEFAULT:Lorg/eclipse/jetty/util/ajax/JSON;
       7: invokevirtual #13                 // Method getStringBufferSize:()I
      10: invokespecial #14                 // Method java/lang/StringBuilder."<init>":(I)V
      13: astore_1
      14: getstatic     #9                  // Field DEFAULT:Lorg/eclipse/jetty/util/ajax/JSON;
      17: aload_1
      18: aload_0
      19: invokevirtual #15                 // Method append:(Ljava/lang/Appendable;Ljava/lang/Object;)V
      22: aload_1
      23: invokevirtual #16                 // Method java/lang/StringBuilder.toString:()Ljava/lang/String;
      26: areturn

  public static java.lang.String toString(java.util.Map);
    Code:
       0: new           #12                 // class java/lang/StringBuilder
       3: dup
       4: getstatic     #9                  // Field DEFAULT:Lorg/eclipse/jetty/util/ajax/JSON;
       7: invokevirtual #13                 // Method getStringBufferSize:()I
      10: invokespecial #14                 // Method java/lang/StringBuilder."<init>":(I)V
      13: astore_1
      14: getstatic     #9                  // Field DEFAULT:Lorg/eclipse/jetty/util/ajax/JSON;
      17: aload_1
      18: aload_0
      19: invokevirtual #17                 // Method appendMap:(Ljava/lang/Appendable;Ljava/util/Map;)V
      22: aload_1
      23: invokevirtual #16                 // Method java/lang/StringBuilder.toString:()Ljava/lang/String;
      26: areturn

  public static java.lang.String toString(java.lang.Object[]);
    Code:
       0: new           #12                 // class java/lang/StringBuilder
       3: dup
       4: getstatic     #9                  // Field DEFAULT:Lorg/eclipse/jetty/util/ajax/JSON;
       7: invokevirtual #13                 // Method getStringBufferSize:()I
      10: invokespecial #14                 // Method java/lang/StringBuilder."<init>":(I)V
      13: astore_1
      14: getstatic     #9                  // Field DEFAULT:Lorg/eclipse/jetty/util/ajax/JSON;
      17: aload_1
      18: aload_0
      19: invokevirtual #18                 // Method appendArray:(Ljava/lang/Appendable;Ljava/lang/Object;)V
      22: aload_1
      23: invokevirtual #16                 // Method java/lang/StringBuilder.toString:()Ljava/lang/String;
      26: areturn

  public static java.lang.Object parse(java.lang.String);
    Code:
       0: getstatic     #9                  // Field DEFAULT:Lorg/eclipse/jetty/util/ajax/JSON;
       3: new           #19                 // class org/eclipse/jetty/util/ajax/JSON$StringSource
       6: dup
       7: aload_0
       8: invokespecial #20                 // Method org/eclipse/jetty/util/ajax/JSON$StringSource."<init>":(Ljava/lang/String;)V
      11: iconst_0
      12: invokevirtual #21                 // Method parse:(Lorg/eclipse/jetty/util/ajax/JSON$Source;Z)Ljava/lang/Object;
      15: areturn

  public static java.lang.Object parse(java.lang.String, boolean);
    Code:
       0: getstatic     #9                  // Field DEFAULT:Lorg/eclipse/jetty/util/ajax/JSON;
       3: new           #19                 // class org/eclipse/jetty/util/ajax/JSON$StringSource
       6: dup
       7: aload_0
       8: invokespecial #20                 // Method org/eclipse/jetty/util/ajax/JSON$StringSource."<init>":(Ljava/lang/String;)V
      11: iload_1
      12: invokevirtual #21                 // Method parse:(Lorg/eclipse/jetty/util/ajax/JSON$Source;Z)Ljava/lang/Object;
      15: areturn

  public static java.lang.Object parse(java.io.Reader) throws java.io.IOException;
    Code:
       0: getstatic     #9                  // Field DEFAULT:Lorg/eclipse/jetty/util/ajax/JSON;
       3: new           #22                 // class org/eclipse/jetty/util/ajax/JSON$ReaderSource
       6: dup
       7: aload_0
       8: invokespecial #23                 // Method org/eclipse/jetty/util/ajax/JSON$ReaderSource."<init>":(Ljava/io/Reader;)V
      11: iconst_0
      12: invokevirtual #21                 // Method parse:(Lorg/eclipse/jetty/util/ajax/JSON$Source;Z)Ljava/lang/Object;
      15: areturn

  public static java.lang.Object parse(java.io.Reader, boolean) throws java.io.IOException;
    Code:
       0: getstatic     #9                  // Field DEFAULT:Lorg/eclipse/jetty/util/ajax/JSON;
       3: new           #22                 // class org/eclipse/jetty/util/ajax/JSON$ReaderSource
       6: dup
       7: aload_0
       8: invokespecial #23                 // Method org/eclipse/jetty/util/ajax/JSON$ReaderSource."<init>":(Ljava/io/Reader;)V
      11: iload_1
      12: invokevirtual #21                 // Method parse:(Lorg/eclipse/jetty/util/ajax/JSON$Source;Z)Ljava/lang/Object;
      15: areturn

  public static java.lang.Object parse(java.io.InputStream) throws java.io.IOException;
    Code:
       0: getstatic     #9                  // Field DEFAULT:Lorg/eclipse/jetty/util/ajax/JSON;
       3: new           #19                 // class org/eclipse/jetty/util/ajax/JSON$StringSource
       6: dup
       7: aload_0
       8: invokestatic  #24                 // Method org/eclipse/jetty/util/IO.toString:(Ljava/io/InputStream;)Ljava/lang/String;
      11: invokespecial #20                 // Method org/eclipse/jetty/util/ajax/JSON$StringSource."<init>":(Ljava/lang/String;)V
      14: iconst_0
      15: invokevirtual #21                 // Method parse:(Lorg/eclipse/jetty/util/ajax/JSON$Source;Z)Ljava/lang/Object;
      18: areturn

  public static java.lang.Object parse(java.io.InputStream, boolean) throws java.io.IOException;
    Code:
       0: getstatic     #9                  // Field DEFAULT:Lorg/eclipse/jetty/util/ajax/JSON;
       3: new           #19                 // class org/eclipse/jetty/util/ajax/JSON$StringSource
       6: dup
       7: aload_0
       8: invokestatic  #24                 // Method org/eclipse/jetty/util/IO.toString:(Ljava/io/InputStream;)Ljava/lang/String;
      11: invokespecial #20                 // Method org/eclipse/jetty/util/ajax/JSON$StringSource."<init>":(Ljava/lang/String;)V
      14: iload_1
      15: invokevirtual #21                 // Method parse:(Lorg/eclipse/jetty/util/ajax/JSON$Source;Z)Ljava/lang/Object;
      18: areturn

  private void quotedEscape(java.lang.Appendable, java.lang.String);
    Code:
       0: aload_1
       1: bipush        34
       3: invokeinterface #25,  2           // InterfaceMethod java/lang/Appendable.append:(C)Ljava/lang/Appendable;
       8: pop
       9: aload_2
      10: ifnull        26
      13: aload_2
      14: invokevirtual #26                 // Method java/lang/String.isEmpty:()Z
      17: ifne          26
      20: aload_0
      21: aload_1
      22: aload_2
      23: invokevirtual #27                 // Method escapeString:(Ljava/lang/Appendable;Ljava/lang/String;)V
      26: aload_1
      27: bipush        34
      29: invokeinterface #25,  2           // InterfaceMethod java/lang/Appendable.append:(C)Ljava/lang/Appendable;
      34: pop
      35: goto          48
      38: astore_3
      39: new           #29                 // class java/lang/RuntimeException
      42: dup
      43: aload_3
      44: invokespecial #30                 // Method java/lang/RuntimeException."<init>":(Ljava/lang/Throwable;)V
      47: athrow
      48: return
    Exception table:
       from    to  target type
           0    35    38   Class java/io/IOException

  public void escapeString(java.lang.Appendable, java.lang.String) throws java.io.IOException;
    Code:
       0: iconst_0
       1: istore_3
       2: iload_3
       3: aload_2
       4: invokevirtual #31                 // Method java/lang/String.length:()I
       7: if_icmpge     226
      10: aload_2
      11: iload_3
      12: invokevirtual #32                 // Method java/lang/String.charAt:(I)C
      15: istore        4
      17: iload         4
      19: bipush        32
      21: if_icmplt     76
      24: iload         4
      26: bipush        126
      28: if_icmpgt     76
      31: iload         4
      33: bipush        34
      35: if_icmpeq     45
      38: iload         4
      40: bipush        92
      42: if_icmpne     64
      45: aload_1
      46: bipush        92
      48: invokeinterface #25,  2           // InterfaceMethod java/lang/Appendable.append:(C)Ljava/lang/Appendable;
      53: iload         4
      55: invokeinterface #25,  2           // InterfaceMethod java/lang/Appendable.append:(C)Ljava/lang/Appendable;
      60: pop
      61: goto          220
      64: aload_1
      65: iload         4
      67: invokeinterface #25,  2           // InterfaceMethod java/lang/Appendable.append:(C)Ljava/lang/Appendable;
      72: pop
      73: goto          220
      76: iload         4
      78: bipush        8
      80: if_icmpne     95
      83: aload_1
      84: ldc           #33                 // String \\b
      86: invokeinterface #34,  2           // InterfaceMethod java/lang/Appendable.append:(Ljava/lang/CharSequence;)Ljava/lang/Appendable;
      91: pop
      92: goto          220
      95: iload         4
      97: bipush        12
      99: if_icmpne     114
     102: aload_1
     103: ldc           #35                 // String \\f
     105: invokeinterface #34,  2           // InterfaceMethod java/lang/Appendable.append:(Ljava/lang/CharSequence;)Ljava/lang/Appendable;
     110: pop
     111: goto          220
     114: iload         4
     116: bipush        10
     118: if_icmpne     133
     121: aload_1
     122: ldc           #36                 // String \\n
     124: invokeinterface #34,  2           // InterfaceMethod java/lang/Appendable.append:(Ljava/lang/CharSequence;)Ljava/lang/Appendable;
     129: pop
     130: goto          220
     133: iload         4
     135: bipush        13
     137: if_icmpne     152
     140: aload_1
     141: ldc           #37                 // String \\r
     143: invokeinterface #34,  2           // InterfaceMethod java/lang/Appendable.append:(Ljava/lang/CharSequence;)Ljava/lang/Appendable;
     148: pop
     149: goto          220
     152: iload         4
     154: bipush        9
     156: if_icmpne     171
     159: aload_1
     160: ldc           #38                 // String \\t
     162: invokeinterface #34,  2           // InterfaceMethod java/lang/Appendable.append:(Ljava/lang/CharSequence;)Ljava/lang/Appendable;
     167: pop
     168: goto          220
     171: iload         4
     173: bipush        32
     175: if_icmplt     185
     178: iload         4
     180: bipush        127
     182: if_icmpne     213
     185: aload_1
     186: ldc           #39                 // String \\u%04x
     188: iconst_1
     189: anewarray     #40                 // class java/lang/Object
     192: dup
     193: iconst_0
     194: iload         4
     196: i2s
     197: invokestatic  #41                 // Method java/lang/Short.valueOf:(S)Ljava/lang/Short;
     200: aastore
     201: invokestatic  #42                 // Method java/lang/String.format:(Ljava/lang/String;[Ljava/lang/Object;)Ljava/lang/String;
     204: invokeinterface #34,  2           // InterfaceMethod java/lang/Appendable.append:(Ljava/lang/CharSequence;)Ljava/lang/Appendable;
     209: pop
     210: goto          220
     213: aload_0
     214: aload_1
     215: iload         4
     217: invokevirtual #43                 // Method escapeUnicode:(Ljava/lang/Appendable;C)V
     220: iinc          3, 1
     223: goto          2
     226: return

  protected void escapeUnicode(java.lang.Appendable, char) throws java.io.IOException;
    Code:
       0: aload_1
       1: iload_2
       2: invokeinterface #25,  2           // InterfaceMethod java/lang/Appendable.append:(C)Ljava/lang/Appendable;
       7: pop
       8: return

  public java.lang.String toJSON(java.lang.Object);
    Code:
       0: new           #12                 // class java/lang/StringBuilder
       3: dup
       4: aload_0
       5: invokevirtual #13                 // Method getStringBufferSize:()I
       8: invokespecial #14                 // Method java/lang/StringBuilder."<init>":(I)V
      11: astore_2
      12: aload_0
      13: aload_2
      14: aload_1
      15: invokevirtual #15                 // Method append:(Ljava/lang/Appendable;Ljava/lang/Object;)V
      18: aload_2
      19: invokevirtual #16                 // Method java/lang/StringBuilder.toString:()Ljava/lang/String;
      22: areturn

  public java.lang.Object fromJSON(java.lang.String);
    Code:
       0: new           #19                 // class org/eclipse/jetty/util/ajax/JSON$StringSource
       3: dup
       4: aload_1
       5: invokespecial #20                 // Method org/eclipse/jetty/util/ajax/JSON$StringSource."<init>":(Ljava/lang/String;)V
       8: astore_2
       9: aload_0
      10: aload_2
      11: invokevirtual #44                 // Method parse:(Lorg/eclipse/jetty/util/ajax/JSON$Source;)Ljava/lang/Object;
      14: areturn

  public void append(java.lang.StringBuffer, java.lang.Object);
    Code:
       0: aload_0
       1: aload_1
       2: aload_2
       3: invokevirtual #15                 // Method append:(Ljava/lang/Appendable;Ljava/lang/Object;)V
       6: return

  public void append(java.lang.Appendable, java.lang.Object);
    Code:
       0: aload_2
       1: ifnonnull     16
       4: aload_1
       5: ldc           #45                 // String null
       7: invokeinterface #34,  2           // InterfaceMethod java/lang/Appendable.append:(Ljava/lang/CharSequence;)Ljava/lang/Appendable;
      12: pop
      13: goto          219
      16: aload_2
      17: instanceof    #46                 // class java/util/Map
      20: ifeq          35
      23: aload_0
      24: aload_1
      25: aload_2
      26: checkcast     #46                 // class java/util/Map
      29: invokevirtual #17                 // Method appendMap:(Ljava/lang/Appendable;Ljava/util/Map;)V
      32: goto          219
      35: aload_2
      36: instanceof    #47                 // class java/lang/String
      39: ifeq          54
      42: aload_0
      43: aload_1
      44: aload_2
      45: checkcast     #47                 // class java/lang/String
      48: invokevirtual #48                 // Method appendString:(Ljava/lang/Appendable;Ljava/lang/String;)V
      51: goto          219
      54: aload_2
      55: instanceof    #49                 // class java/lang/Number
      58: ifeq          73
      61: aload_0
      62: aload_1
      63: aload_2
      64: checkcast     #49                 // class java/lang/Number
      67: invokevirtual #50                 // Method appendNumber:(Ljava/lang/Appendable;Ljava/lang/Number;)V
      70: goto          219
      73: aload_2
      74: instanceof    #51                 // class java/lang/Boolean
      77: ifeq          92
      80: aload_0
      81: aload_1
      82: aload_2
      83: checkcast     #51                 // class java/lang/Boolean
      86: invokevirtual #52                 // Method appendBoolean:(Ljava/lang/Appendable;Ljava/lang/Boolean;)V
      89: goto          219
      92: aload_2
      93: invokevirtual #53                 // Method java/lang/Object.getClass:()Ljava/lang/Class;
      96: invokevirtual #54                 // Method java/lang/Class.isArray:()Z
      99: ifeq          111
     102: aload_0
     103: aload_1
     104: aload_2
     105: invokevirtual #18                 // Method appendArray:(Ljava/lang/Appendable;Ljava/lang/Object;)V
     108: goto          219
     111: aload_2
     112: instanceof    #55                 // class java/lang/Character
     115: ifeq          130
     118: aload_0
     119: aload_1
     120: aload_2
     121: invokevirtual #56                 // Method java/lang/Object.toString:()Ljava/lang/String;
     124: invokevirtual #48                 // Method appendString:(Ljava/lang/Appendable;Ljava/lang/String;)V
     127: goto          219
     130: aload_2
     131: instanceof    #57                 // class org/eclipse/jetty/util/ajax/JSON$Convertible
     134: ifeq          149
     137: aload_0
     138: aload_1
     139: aload_2
     140: checkcast     #57                 // class org/eclipse/jetty/util/ajax/JSON$Convertible
     143: invokevirtual #58                 // Method appendJSON:(Ljava/lang/Appendable;Lorg/eclipse/jetty/util/ajax/JSON$Convertible;)V
     146: goto          219
     149: aload_2
     150: instanceof    #59                 // class org/eclipse/jetty/util/ajax/JSON$Generator
     153: ifeq          168
     156: aload_0
     157: aload_1
     158: aload_2
     159: checkcast     #59                 // class org/eclipse/jetty/util/ajax/JSON$Generator
     162: invokevirtual #60                 // Method appendJSON:(Ljava/lang/Appendable;Lorg/eclipse/jetty/util/ajax/JSON$Generator;)V
     165: goto          219
     168: aload_0
     169: aload_2
     170: invokevirtual #53                 // Method java/lang/Object.getClass:()Ljava/lang/Class;
     173: invokevirtual #61                 // Method getConvertor:(Ljava/lang/Class;)Lorg/eclipse/jetty/util/ajax/JSON$Convertor;
     176: astore_3
     177: aload_3
     178: ifnull        191
     181: aload_0
     182: aload_1
     183: aload_3
     184: aload_2
     185: invokevirtual #62                 // Method appendJSON:(Ljava/lang/Appendable;Lorg/eclipse/jetty/util/ajax/JSON$Convertor;Ljava/lang/Object;)V
     188: goto          219
     191: aload_2
     192: instanceof    #63                 // class java/util/Collection
     195: ifeq          210
     198: aload_0
     199: aload_1
     200: aload_2
     201: checkcast     #63                 // class java/util/Collection
     204: invokevirtual #64                 // Method appendArray:(Ljava/lang/Appendable;Ljava/util/Collection;)V
     207: goto          219
     210: aload_0
     211: aload_1
     212: aload_2
     213: invokevirtual #56                 // Method java/lang/Object.toString:()Ljava/lang/String;
     216: invokevirtual #48                 // Method appendString:(Ljava/lang/Appendable;Ljava/lang/String;)V
     219: goto          232
     222: astore_3
     223: new           #29                 // class java/lang/RuntimeException
     226: dup
     227: aload_3
     228: invokespecial #30                 // Method java/lang/RuntimeException."<init>":(Ljava/lang/Throwable;)V
     231: athrow
     232: return
    Exception table:
       from    to  target type
           0   219   222   Class java/io/IOException

  public void appendNull(java.lang.StringBuffer);
    Code:
       0: aload_0
       1: aload_1
       2: invokevirtual #65                 // Method appendNull:(Ljava/lang/Appendable;)V
       5: return

  public void appendNull(java.lang.Appendable);
    Code:
       0: aload_1
       1: ldc           #45                 // String null
       3: invokeinterface #34,  2           // InterfaceMethod java/lang/Appendable.append:(Ljava/lang/CharSequence;)Ljava/lang/Appendable;
       8: pop
       9: goto          22
      12: astore_2
      13: new           #29                 // class java/lang/RuntimeException
      16: dup
      17: aload_2
      18: invokespecial #30                 // Method java/lang/RuntimeException."<init>":(Ljava/lang/Throwable;)V
      21: athrow
      22: return
    Exception table:
       from    to  target type
           0     9    12   Class java/io/IOException

  public void appendJSON(java.lang.StringBuffer, org.eclipse.jetty.util.ajax.JSON$Convertor, java.lang.Object);
    Code:
       0: aload_0
       1: aload_1
       2: aload_2
       3: aload_3
       4: invokevirtual #62                 // Method appendJSON:(Ljava/lang/Appendable;Lorg/eclipse/jetty/util/ajax/JSON$Convertor;Ljava/lang/Object;)V
       7: return

  public void appendJSON(java.lang.Appendable, org.eclipse.jetty.util.ajax.JSON$Convertor, java.lang.Object);
    Code:
       0: aload_0
       1: aload_1
       2: new           #66                 // class org/eclipse/jetty/util/ajax/JSON$1
       5: dup
       6: aload_0
       7: aload_2
       8: aload_3
       9: invokespecial #67                 // Method org/eclipse/jetty/util/ajax/JSON$1."<init>":(Lorg/eclipse/jetty/util/ajax/JSON;Lorg/eclipse/jetty/util/ajax/JSON$Convertor;Ljava/lang/Object;)V
      12: invokevirtual #58                 // Method appendJSON:(Ljava/lang/Appendable;Lorg/eclipse/jetty/util/ajax/JSON$Convertible;)V
      15: return

  public void appendJSON(java.lang.StringBuffer, org.eclipse.jetty.util.ajax.JSON$Convertible);
    Code:
       0: aload_0
       1: aload_1
       2: aload_2
       3: invokevirtual #58                 // Method appendJSON:(Ljava/lang/Appendable;Lorg/eclipse/jetty/util/ajax/JSON$Convertible;)V
       6: return

  public void appendJSON(java.lang.Appendable, org.eclipse.jetty.util.ajax.JSON$Convertible);
    Code:
       0: new           #68                 // class org/eclipse/jetty/util/ajax/JSON$ConvertableOutput
       3: dup
       4: aload_0
       5: aload_1
       6: aconst_null
       7: invokespecial #69                 // Method org/eclipse/jetty/util/ajax/JSON$ConvertableOutput."<init>":(Lorg/eclipse/jetty/util/ajax/JSON;Ljava/lang/Appendable;Lorg/eclipse/jetty/util/ajax/JSON$1;)V
      10: astore_3
      11: aload_2
      12: aload_3
      13: invokeinterface #70,  2           // InterfaceMethod org/eclipse/jetty/util/ajax/JSON$Convertible.toJSON:(Lorg/eclipse/jetty/util/ajax/JSON$Output;)V
      18: aload_3
      19: invokevirtual #71                 // Method org/eclipse/jetty/util/ajax/JSON$ConvertableOutput.complete:()V
      22: return

  public void appendJSON(java.lang.StringBuffer, org.eclipse.jetty.util.ajax.JSON$Generator);
    Code:
       0: aload_2
       1: aload_1
       2: invokeinterface #72,  2           // InterfaceMethod org/eclipse/jetty/util/ajax/JSON$Generator.addJSON:(Ljava/lang/Appendable;)V
       7: return

  public void appendJSON(java.lang.Appendable, org.eclipse.jetty.util.ajax.JSON$Generator);
    Code:
       0: aload_2
       1: aload_1
       2: invokeinterface #72,  2           // InterfaceMethod org/eclipse/jetty/util/ajax/JSON$Generator.addJSON:(Ljava/lang/Appendable;)V
       7: return

  public void appendMap(java.lang.StringBuffer, java.util.Map<?, ?>);
    Code:
       0: aload_0
       1: aload_1
       2: aload_2
       3: invokevirtual #17                 // Method appendMap:(Ljava/lang/Appendable;Ljava/util/Map;)V
       6: return

  public void appendMap(java.lang.Appendable, java.util.Map<?, ?>);
    Code:
       0: aload_2
       1: ifnonnull     10
       4: aload_0
       5: aload_1
       6: invokevirtual #65                 // Method appendNull:(Ljava/lang/Appendable;)V
       9: return
      10: aload_1
      11: bipush        123
      13: invokeinterface #25,  2           // InterfaceMethod java/lang/Appendable.append:(C)Ljava/lang/Appendable;
      18: pop
      19: aload_2
      20: invokeinterface #73,  1           // InterfaceMethod java/util/Map.entrySet:()Ljava/util/Set;
      25: invokeinterface #74,  1           // InterfaceMethod java/util/Set.iterator:()Ljava/util/Iterator;
      30: astore_3
      31: aload_3
      32: invokeinterface #75,  1           // InterfaceMethod java/util/Iterator.hasNext:()Z
      37: ifeq          108
      40: aload_3
      41: invokeinterface #76,  1           // InterfaceMethod java/util/Iterator.next:()Ljava/lang/Object;
      46: checkcast     #77                 // class java/util/Map$Entry
      49: astore        4
      51: aload_0
      52: aload_1
      53: aload         4
      55: invokeinterface #78,  1           // InterfaceMethod java/util/Map$Entry.getKey:()Ljava/lang/Object;
      60: invokevirtual #56                 // Method java/lang/Object.toString:()Ljava/lang/String;
      63: invokespecial #1                  // Method quotedEscape:(Ljava/lang/Appendable;Ljava/lang/String;)V
      66: aload_1
      67: bipush        58
      69: invokeinterface #25,  2           // InterfaceMethod java/lang/Appendable.append:(C)Ljava/lang/Appendable;
      74: pop
      75: aload_0
      76: aload_1
      77: aload         4
      79: invokeinterface #79,  1           // InterfaceMethod java/util/Map$Entry.getValue:()Ljava/lang/Object;
      84: invokevirtual #15                 // Method append:(Ljava/lang/Appendable;Ljava/lang/Object;)V
      87: aload_3
      88: invokeinterface #75,  1           // InterfaceMethod java/util/Iterator.hasNext:()Z
      93: ifeq          105
      96: aload_1
      97: bipush        44
      99: invokeinterface #25,  2           // InterfaceMethod java/lang/Appendable.append:(C)Ljava/lang/Appendable;
     104: pop
     105: goto          31
     108: aload_1
     109: bipush        125
     111: invokeinterface #25,  2           // InterfaceMethod java/lang/Appendable.append:(C)Ljava/lang/Appendable;
     116: pop
     117: goto          130
     120: astore_3
     121: new           #29                 // class java/lang/RuntimeException
     124: dup
     125: aload_3
     126: invokespecial #30                 // Method java/lang/RuntimeException."<init>":(Ljava/lang/Throwable;)V
     129: athrow
     130: return
    Exception table:
       from    to  target type
           0     9   120   Class java/io/IOException
          10   117   120   Class java/io/IOException

  public void appendArray(java.lang.StringBuffer, java.util.Collection);
    Code:
       0: aload_0
       1: aload_1
       2: aload_2
       3: invokevirtual #64                 // Method appendArray:(Ljava/lang/Appendable;Ljava/util/Collection;)V
       6: return

  public void appendArray(java.lang.Appendable, java.util.Collection);
    Code:
       0: aload_2
       1: ifnonnull     10
       4: aload_0
       5: aload_1
       6: invokevirtual #65                 // Method appendNull:(Ljava/lang/Appendable;)V
       9: return
      10: aload_1
      11: bipush        91
      13: invokeinterface #25,  2           // InterfaceMethod java/lang/Appendable.append:(C)Ljava/lang/Appendable;
      18: pop
      19: aload_2
      20: invokeinterface #80,  1           // InterfaceMethod java/util/Collection.iterator:()Ljava/util/Iterator;
      25: astore_3
      26: iconst_1
      27: istore        4
      29: aload_3
      30: invokeinterface #75,  1           // InterfaceMethod java/util/Iterator.hasNext:()Z
      35: ifeq          69
      38: iload         4
      40: ifne          52
      43: aload_1
      44: bipush        44
      46: invokeinterface #25,  2           // InterfaceMethod java/lang/Appendable.append:(C)Ljava/lang/Appendable;
      51: pop
      52: iconst_0
      53: istore        4
      55: aload_0
      56: aload_1
      57: aload_3
      58: invokeinterface #76,  1           // InterfaceMethod java/util/Iterator.next:()Ljava/lang/Object;
      63: invokevirtual #15                 // Method append:(Ljava/lang/Appendable;Ljava/lang/Object;)V
      66: goto          29
      69: aload_1
      70: bipush        93
      72: invokeinterface #25,  2           // InterfaceMethod java/lang/Appendable.append:(C)Ljava/lang/Appendable;
      77: pop
      78: goto          91
      81: astore_3
      82: new           #29                 // class java/lang/RuntimeException
      85: dup
      86: aload_3
      87: invokespecial #30                 // Method java/lang/RuntimeException."<init>":(Ljava/lang/Throwable;)V
      90: athrow
      91: return
    Exception table:
       from    to  target type
           0     9    81   Class java/io/IOException
          10    78    81   Class java/io/IOException

  public void appendArray(java.lang.StringBuffer, java.lang.Object);
    Code:
       0: aload_0
       1: aload_1
       2: aload_2
       3: invokevirtual #18                 // Method appendArray:(Ljava/lang/Appendable;Ljava/lang/Object;)V
       6: return

  public void appendArray(java.lang.Appendable, java.lang.Object);
    Code:
       0: aload_2
       1: ifnonnull     10
       4: aload_0
       5: aload_1
       6: invokevirtual #65                 // Method appendNull:(Ljava/lang/Appendable;)V
       9: return
      10: aload_1
      11: bipush        91
      13: invokeinterface #25,  2           // InterfaceMethod java/lang/Appendable.append:(C)Ljava/lang/Appendable;
      18: pop
      19: aload_2
      20: invokestatic  #81                 // Method java/lang/reflect/Array.getLength:(Ljava/lang/Object;)I
      23: istore_3
      24: iconst_0
      25: istore        4
      27: iload         4
      29: iload_3
      30: if_icmpge     64
      33: iload         4
      35: ifeq          47
      38: aload_1
      39: bipush        44
      41: invokeinterface #25,  2           // InterfaceMethod java/lang/Appendable.append:(C)Ljava/lang/Appendable;
      46: pop
      47: aload_0
      48: aload_1
      49: aload_2
      50: iload         4
      52: invokestatic  #82                 // Method java/lang/reflect/Array.get:(Ljava/lang/Object;I)Ljava/lang/Object;
      55: invokevirtual #15                 // Method append:(Ljava/lang/Appendable;Ljava/lang/Object;)V
      58: iinc          4, 1
      61: goto          27
      64: aload_1
      65: bipush        93
      67: invokeinterface #25,  2           // InterfaceMethod java/lang/Appendable.append:(C)Ljava/lang/Appendable;
      72: pop
      73: goto          86
      76: astore_3
      77: new           #29                 // class java/lang/RuntimeException
      80: dup
      81: aload_3
      82: invokespecial #30                 // Method java/lang/RuntimeException."<init>":(Ljava/lang/Throwable;)V
      85: athrow
      86: return
    Exception table:
       from    to  target type
           0     9    76   Class java/io/IOException
          10    73    76   Class java/io/IOException

  public void appendBoolean(java.lang.StringBuffer, java.lang.Boolean);
    Code:
       0: aload_0
       1: aload_1
       2: aload_2
       3: invokevirtual #52                 // Method appendBoolean:(Ljava/lang/Appendable;Ljava/lang/Boolean;)V
       6: return

  public void appendBoolean(java.lang.Appendable, java.lang.Boolean);
    Code:
       0: aload_2
       1: ifnonnull     10
       4: aload_0
       5: aload_1
       6: invokevirtual #65                 // Method appendNull:(Ljava/lang/Appendable;)V
       9: return
      10: aload_1
      11: aload_2
      12: invokevirtual #83                 // Method java/lang/Boolean.booleanValue:()Z
      15: ifeq          23
      18: ldc           #84                 // String true
      20: goto          25
      23: ldc           #85                 // String false
      25: invokeinterface #34,  2           // InterfaceMethod java/lang/Appendable.append:(Ljava/lang/CharSequence;)Ljava/lang/Appendable;
      30: pop
      31: goto          44
      34: astore_3
      35: new           #29                 // class java/lang/RuntimeException
      38: dup
      39: aload_3
      40: invokespecial #30                 // Method java/lang/RuntimeException."<init>":(Ljava/lang/Throwable;)V
      43: athrow
      44: return
    Exception table:
       from    to  target type
           0     9    34   Class java/io/IOException
          10    31    34   Class java/io/IOException

  public void appendNumber(java.lang.StringBuffer, java.lang.Number);
    Code:
       0: aload_0
       1: aload_1
       2: aload_2
       3: invokevirtual #50                 // Method appendNumber:(Ljava/lang/Appendable;Ljava/lang/Number;)V
       6: return

  public void appendNumber(java.lang.Appendable, java.lang.Number);
    Code:
       0: aload_2
       1: ifnonnull     10
       4: aload_0
       5: aload_1
       6: invokevirtual #65                 // Method appendNull:(Ljava/lang/Appendable;)V
       9: return
      10: aload_1
      11: aload_2
      12: invokestatic  #86                 // Method java/lang/String.valueOf:(Ljava/lang/Object;)Ljava/lang/String;
      15: invokeinterface #34,  2           // InterfaceMethod java/lang/Appendable.append:(Ljava/lang/CharSequence;)Ljava/lang/Appendable;
      20: pop
      21: goto          34
      24: astore_3
      25: new           #29                 // class java/lang/RuntimeException
      28: dup
      29: aload_3
      30: invokespecial #30                 // Method java/lang/RuntimeException."<init>":(Ljava/lang/Throwable;)V
      33: athrow
      34: return
    Exception table:
       from    to  target type
           0     9    24   Class java/io/IOException
          10    21    24   Class java/io/IOException

  public void appendString(java.lang.StringBuffer, java.lang.String);
    Code:
       0: aload_0
       1: aload_1
       2: aload_2
       3: invokevirtual #48                 // Method appendString:(Ljava/lang/Appendable;Ljava/lang/String;)V
       6: return

  public void appendString(java.lang.Appendable, java.lang.String);
    Code:
       0: aload_2
       1: ifnonnull     10
       4: aload_0
       5: aload_1
       6: invokevirtual #65                 // Method appendNull:(Ljava/lang/Appendable;)V
       9: return
      10: aload_0
      11: aload_1
      12: aload_2
      13: invokespecial #1                  // Method quotedEscape:(Ljava/lang/Appendable;Ljava/lang/String;)V
      16: return

  protected java.lang.String toString(char[], int, int);
    Code:
       0: new           #47                 // class java/lang/String
       3: dup
       4: aload_1
       5: iload_2
       6: iload_3
       7: invokespecial #87                 // Method java/lang/String."<init>":([CII)V
      10: areturn

  protected java.util.Map<java.lang.String, java.lang.Object> newMap();
    Code:
       0: new           #88                 // class java/util/HashMap
       3: dup
       4: invokespecial #89                 // Method java/util/HashMap."<init>":()V
       7: areturn

  protected java.lang.Object[] newArray(int);
    Code:
       0: iload_1
       1: anewarray     #40                 // class java/lang/Object
       4: areturn

  protected org.eclipse.jetty.util.ajax.JSON contextForArray();
    Code:
       0: aload_0
       1: areturn

  protected org.eclipse.jetty.util.ajax.JSON contextFor(java.lang.String);
    Code:
       0: aload_0
       1: areturn

  protected java.lang.Object convertTo(java.lang.Class, java.util.Map);
    Code:
       0: aload_1
       1: ifnull        51
       4: ldc           #57                 // class org/eclipse/jetty/util/ajax/JSON$Convertible
       6: aload_1
       7: invokevirtual #90                 // Method java/lang/Class.isAssignableFrom:(Ljava/lang/Class;)Z
      10: ifeq          51
      13: aload_1
      14: iconst_0
      15: anewarray     #91                 // class java/lang/Class
      18: invokevirtual #92                 // Method java/lang/Class.getDeclaredConstructor:([Ljava/lang/Class;)Ljava/lang/reflect/Constructor;
      21: iconst_0
      22: anewarray     #40                 // class java/lang/Object
      25: invokevirtual #93                 // Method java/lang/reflect/Constructor.newInstance:([Ljava/lang/Object;)Ljava/lang/Object;
      28: checkcast     #57                 // class org/eclipse/jetty/util/ajax/JSON$Convertible
      31: astore_3
      32: aload_3
      33: aload_2
      34: invokeinterface #94,  2           // InterfaceMethod org/eclipse/jetty/util/ajax/JSON$Convertible.fromJSON:(Ljava/util/Map;)V
      39: aload_3
      40: areturn
      41: astore_3
      42: new           #29                 // class java/lang/RuntimeException
      45: dup
      46: aload_3
      47: invokespecial #30                 // Method java/lang/RuntimeException."<init>":(Ljava/lang/Throwable;)V
      50: athrow
      51: aload_0
      52: aload_1
      53: invokevirtual #61                 // Method getConvertor:(Ljava/lang/Class;)Lorg/eclipse/jetty/util/ajax/JSON$Convertor;
      56: astore_3
      57: aload_3
      58: ifnull        69
      61: aload_3
      62: aload_2
      63: invokeinterface #96,  2           // InterfaceMethod org/eclipse/jetty/util/ajax/JSON$Convertor.fromJSON:(Ljava/util/Map;)Ljava/lang/Object;
      68: areturn
      69: aload_2
      70: areturn
    Exception table:
       from    to  target type
          13    40    41   Class java/lang/Exception

  public void addConvertor(java.lang.Class, org.eclipse.jetty.util.ajax.JSON$Convertor);
    Code:
       0: aload_0
       1: getfield      #5                  // Field _convertors:Ljava/util/Map;
       4: aload_1
       5: invokevirtual #97                 // Method java/lang/Class.getName:()Ljava/lang/String;
       8: aload_2
       9: invokeinterface #98,  3           // InterfaceMethod java/util/Map.put:(Ljava/lang/Object;Ljava/lang/Object;)Ljava/lang/Object;
      14: pop
      15: return

  protected org.eclipse.jetty.util.ajax.JSON$Convertor getConvertor(java.lang.Class);
    Code:
       0: aload_1
       1: astore_2
       2: aload_0
       3: getfield      #5                  // Field _convertors:Ljava/util/Map;
       6: aload_2
       7: invokevirtual #97                 // Method java/lang/Class.getName:()Ljava/lang/String;
      10: invokeinterface #99,  2           // InterfaceMethod java/util/Map.get:(Ljava/lang/Object;)Ljava/lang/Object;
      15: checkcast     #100                // class org/eclipse/jetty/util/ajax/JSON$Convertor
      18: astore_3
      19: aload_3
      20: ifnonnull     38
      23: aload_0
      24: getstatic     #9                  // Field DEFAULT:Lorg/eclipse/jetty/util/ajax/JSON;
      27: if_acmpeq     38
      30: getstatic     #9                  // Field DEFAULT:Lorg/eclipse/jetty/util/ajax/JSON;
      33: aload_2
      34: invokevirtual #61                 // Method getConvertor:(Ljava/lang/Class;)Lorg/eclipse/jetty/util/ajax/JSON$Convertor;
      37: astore_3
      38: aload_3
      39: ifnonnull     125
      42: aload_2
      43: ldc           #40                 // class java/lang/Object
      45: if_acmpeq     125
      48: aload_2
      49: invokevirtual #101                // Method java/lang/Class.getInterfaces:()[Ljava/lang/Class;
      52: astore        4
      54: iconst_0
      55: istore        5
      57: aload_3
      58: ifnonnull     96
      61: iload         5
      63: aload         4
      65: arraylength
      66: if_icmpge     96
      69: aload_0
      70: getfield      #5                  // Field _convertors:Ljava/util/Map;
      73: aload         4
      75: iload         5
      77: iinc          5, 1
      80: aaload
      81: invokevirtual #97                 // Method java/lang/Class.getName:()Ljava/lang/String;
      84: invokeinterface #99,  2           // InterfaceMethod java/util/Map.get:(Ljava/lang/Object;)Ljava/lang/Object;
      89: checkcast     #100                // class org/eclipse/jetty/util/ajax/JSON$Convertor
      92: astore_3
      93: goto          57
      96: aload_3
      97: ifnonnull     122
     100: aload_2
     101: invokevirtual #102                // Method java/lang/Class.getSuperclass:()Ljava/lang/Class;
     104: astore_2
     105: aload_0
     106: getfield      #5                  // Field _convertors:Ljava/util/Map;
     109: aload_2
     110: invokevirtual #97                 // Method java/lang/Class.getName:()Ljava/lang/String;
     113: invokeinterface #99,  2           // InterfaceMethod java/util/Map.get:(Ljava/lang/Object;)Ljava/lang/Object;
     118: checkcast     #100                // class org/eclipse/jetty/util/ajax/JSON$Convertor
     121: astore_3
     122: goto          38
     125: aload_3
     126: areturn

  public void addConvertorFor(java.lang.String, org.eclipse.jetty.util.ajax.JSON$Convertor);
    Code:
       0: aload_0
       1: getfield      #5                  // Field _convertors:Ljava/util/Map;
       4: aload_1
       5: aload_2
       6: invokeinterface #98,  3           // InterfaceMethod java/util/Map.put:(Ljava/lang/Object;Ljava/lang/Object;)Ljava/lang/Object;
      11: pop
      12: return

  public org.eclipse.jetty.util.ajax.JSON$Convertor removeConvertorFor(java.lang.String);
    Code:
       0: aload_0
       1: getfield      #5                  // Field _convertors:Ljava/util/Map;
       4: aload_1
       5: invokeinterface #103,  2          // InterfaceMethod java/util/Map.remove:(Ljava/lang/Object;)Ljava/lang/Object;
      10: checkcast     #100                // class org/eclipse/jetty/util/ajax/JSON$Convertor
      13: areturn

  public java.util.function.Function<java.util.List<?>, java.lang.Object> getArrayConverter();
    Code:
       0: aload_0
       1: getfield      #8                  // Field _arrayConverter:Ljava/util/function/Function;
       4: areturn

  public void setArrayConverter(java.util.function.Function<java.util.List<?>, java.lang.Object>);
    Code:
       0: aload_0
       1: aload_1
       2: invokestatic  #104                // Method java/util/Objects.requireNonNull:(Ljava/lang/Object;)Ljava/lang/Object;
       5: checkcast     #105                // class java/util/function/Function
       8: putfield      #8                  // Field _arrayConverter:Ljava/util/function/Function;
      11: return

  public org.eclipse.jetty.util.ajax.JSON$Convertor getConvertorFor(java.lang.String);
    Code:
       0: aload_0
       1: getfield      #5                  // Field _convertors:Ljava/util/Map;
       4: aload_1
       5: invokeinterface #99,  2           // InterfaceMethod java/util/Map.get:(Ljava/lang/Object;)Ljava/lang/Object;
      10: checkcast     #100                // class org/eclipse/jetty/util/ajax/JSON$Convertor
      13: astore_2
      14: aload_2
      15: ifnonnull     33
      18: aload_0
      19: getstatic     #9                  // Field DEFAULT:Lorg/eclipse/jetty/util/ajax/JSON;
      22: if_acmpeq     33
      25: getstatic     #9                  // Field DEFAULT:Lorg/eclipse/jetty/util/ajax/JSON;
      28: aload_1
      29: invokevirtual #106                // Method getConvertorFor:(Ljava/lang/String;)Lorg/eclipse/jetty/util/ajax/JSON$Convertor;
      32: astore_2
      33: aload_2
      34: areturn

  public java.lang.Object parse(org.eclipse.jetty.util.ajax.JSON$Source, boolean);
    Code:
       0: iconst_0
       1: istore_3
       2: iload_2
       3: ifne          12
       6: aload_0
       7: aload_1
       8: invokevirtual #44                 // Method parse:(Lorg/eclipse/jetty/util/ajax/JSON$Source;)Ljava/lang/Object;
      11: areturn
      12: iconst_1
      13: istore        4
      15: aconst_null
      16: astore        5
      18: aload_1
      19: invokeinterface #107,  1          // InterfaceMethod org/eclipse/jetty/util/ajax/JSON$Source.hasNext:()Z
      24: ifeq          253
      27: aload_1
      28: invokeinterface #108,  1          // InterfaceMethod org/eclipse/jetty/util/ajax/JSON$Source.peek:()C
      33: istore        6
      35: iload_3
      36: iconst_1
      37: if_icmpne     89
      40: iload         6
      42: lookupswitch  { // 2
                    42: 73
                    47: 68
               default: 86
          }
      68: iconst_m1
      69: istore_3
      70: goto          86
      73: iconst_2
      74: istore_3
      75: iload         4
      77: iconst_1
      78: if_icmpne     86
      81: iconst_0
      82: istore_3
      83: iconst_2
      84: istore        4
      86: goto          243
      89: iload_3
      90: iconst_1
      91: if_icmple     155
      94: iload         6
      96: lookupswitch  { // 2
                    42: 124
                    47: 129
               default: 150
          }
     124: iconst_3
     125: istore_3
     126: goto          243
     129: iload_3
     130: iconst_3
     131: if_icmpne     145
     134: iconst_0
     135: istore_3
     136: iload         4
     138: iconst_2
     139: if_icmpne     243
     142: aload         5
     144: areturn
     145: iconst_2
     146: istore_3
     147: goto          243
     150: iconst_2
     151: istore_3
     152: goto          243
     155: iload_3
     156: ifge          196
     159: iload         6
     161: lookupswitch  { // 2
                    10: 188
                    13: 188
               default: 193
          }
     188: iconst_0
     189: istore_3
     190: goto          243
     193: goto          243
     196: iload         6
     198: invokestatic  #109                // Method java/lang/Character.isWhitespace:(C)Z
     201: ifne          243
     204: iload         6
     206: bipush        47
     208: if_icmpne     216
     211: iconst_1
     212: istore_3
     213: goto          243
     216: iload         6
     218: bipush        42
     220: if_icmpne     228
     223: iconst_3
     224: istore_3
     225: goto          243
     228: aload         5
     230: ifnonnull     243
     233: aload_0
     234: aload_1
     235: invokevirtual #44                 // Method parse:(Lorg/eclipse/jetty/util/ajax/JSON$Source;)Ljava/lang/Object;
     238: astore        5
     240: goto          18
     243: aload_1
     244: invokeinterface #110,  1          // InterfaceMethod org/eclipse/jetty/util/ajax/JSON$Source.next:()C
     249: pop
     250: goto          18
     253: aload         5
     255: areturn

  public java.lang.Object parse(org.eclipse.jetty.util.ajax.JSON$Source);
    Code:
       0: iconst_0
       1: istore_2
       2: aload_1
       3: invokeinterface #107,  1          // InterfaceMethod org/eclipse/jetty/util/ajax/JSON$Source.hasNext:()Z
       8: ifeq          365
      11: aload_1
      12: invokeinterface #108,  1          // InterfaceMethod org/eclipse/jetty/util/ajax/JSON$Source.peek:()C
      17: istore_3
      18: iload_2
      19: iconst_1
      20: if_icmpne     62
      23: iload_3
      24: lookupswitch  { // 2
                    42: 57
                    47: 52
               default: 59
          }
      52: iconst_m1
      53: istore_2
      54: goto          59
      57: iconst_2
      58: istore_2
      59: goto          355
      62: iload_2
      63: iconst_1
      64: if_icmple     121
      67: iload_3
      68: lookupswitch  { // 2
                    42: 96
                    47: 101
               default: 116
          }
      96: iconst_3
      97: istore_2
      98: goto          355
     101: iload_2
     102: iconst_3
     103: if_icmpne     111
     106: iconst_0
     107: istore_2
     108: goto          355
     111: iconst_2
     112: istore_2
     113: goto          355
     116: iconst_2
     117: istore_2
     118: goto          355
     121: iload_2
     122: ifge          160
     125: iload_3
     126: lookupswitch  { // 2
                    10: 152
                    13: 152
               default: 157
          }
     152: iconst_0
     153: istore_2
     154: goto          355
     157: goto          355
     160: iload_3
     161: lookupswitch  { // 10
                    34: 264
                    45: 270
                    47: 320
                    78: 312
                    91: 258
                   102: 294
                   110: 276
                   116: 284
                   117: 304
                   123: 252
               default: 325
          }
     252: aload_0
     253: aload_1
     254: invokevirtual #111                // Method parseObject:(Lorg/eclipse/jetty/util/ajax/JSON$Source;)Ljava/lang/Object;
     257: areturn
     258: aload_0
     259: aload_1
     260: invokevirtual #112                // Method parseArray:(Lorg/eclipse/jetty/util/ajax/JSON$Source;)Ljava/lang/Object;
     263: areturn
     264: aload_0
     265: aload_1
     266: invokevirtual #113                // Method parseString:(Lorg/eclipse/jetty/util/ajax/JSON$Source;)Ljava/lang/String;
     269: areturn
     270: aload_0
     271: aload_1
     272: invokevirtual #114                // Method parseNumber:(Lorg/eclipse/jetty/util/ajax/JSON$Source;)Ljava/lang/Number;
     275: areturn
     276: ldc           #45                 // String null
     278: aload_1
     279: invokestatic  #115                // Method complete:(Ljava/lang/String;Lorg/eclipse/jetty/util/ajax/JSON$Source;)V
     282: aconst_null
     283: areturn
     284: ldc           #84                 // String true
     286: aload_1
     287: invokestatic  #115                // Method complete:(Ljava/lang/String;Lorg/eclipse/jetty/util/ajax/JSON$Source;)V
     290: getstatic     #116                // Field java/lang/Boolean.TRUE:Ljava/lang/Boolean;
     293: areturn
     294: ldc           #85                 // String false
     296: aload_1
     297: invokestatic  #115                // Method complete:(Ljava/lang/String;Lorg/eclipse/jetty/util/ajax/JSON$Source;)V
     300: getstatic     #117                // Field java/lang/Boolean.FALSE:Ljava/lang/Boolean;
     303: areturn
     304: ldc           #118                // String undefined
     306: aload_1
     307: invokestatic  #115                // Method complete:(Ljava/lang/String;Lorg/eclipse/jetty/util/ajax/JSON$Source;)V
     310: aconst_null
     311: areturn
     312: ldc           #119                // String NaN
     314: aload_1
     315: invokestatic  #115                // Method complete:(Ljava/lang/String;Lorg/eclipse/jetty/util/ajax/JSON$Source;)V
     318: aconst_null
     319: areturn
     320: iconst_1
     321: istore_2
     322: goto          355
     325: iload_3
     326: invokestatic  #120                // Method java/lang/Character.isDigit:(C)Z
     329: ifeq          338
     332: aload_0
     333: aload_1
     334: invokevirtual #114                // Method parseNumber:(Lorg/eclipse/jetty/util/ajax/JSON$Source;)Ljava/lang/Number;
     337: areturn
     338: iload_3
     339: invokestatic  #109                // Method java/lang/Character.isWhitespace:(C)Z
     342: ifeq          348
     345: goto          355
     348: aload_0
     349: aload_1
     350: iload_3
     351: invokevirtual #121                // Method handleUnknown:(Lorg/eclipse/jetty/util/ajax/JSON$Source;C)Ljava/lang/Object;
     354: areturn
     355: aload_1
     356: invokeinterface #110,  1          // InterfaceMethod org/eclipse/jetty/util/ajax/JSON$Source.next:()C
     361: pop
     362: goto          2
     365: aconst_null
     366: areturn

  protected java.lang.Object handleUnknown(org.eclipse.jetty.util.ajax.JSON$Source, char);
    Code:
       0: new           #122                // class java/lang/IllegalStateException
       3: dup
       4: new           #12                 // class java/lang/StringBuilder
       7: dup
       8: invokespecial #123                // Method java/lang/StringBuilder."<init>":()V
      11: ldc           #124                // String unknown char \'
      13: invokevirtual #125                // Method java/lang/StringBuilder.append:(Ljava/lang/String;)Ljava/lang/StringBuilder;
      16: iload_2
      17: invokevirtual #126                // Method java/lang/StringBuilder.append:(C)Ljava/lang/StringBuilder;
      20: ldc           #127                // String \'(
      22: invokevirtual #125                // Method java/lang/StringBuilder.append:(Ljava/lang/String;)Ljava/lang/StringBuilder;
      25: iload_2
      26: invokevirtual #128                // Method java/lang/StringBuilder.append:(I)Ljava/lang/StringBuilder;
      29: ldc           #129                // String ) in
      31: invokevirtual #125                // Method java/lang/StringBuilder.append:(Ljava/lang/String;)Ljava/lang/StringBuilder;
      34: aload_1
      35: invokevirtual #130                // Method java/lang/StringBuilder.append:(Ljava/lang/Object;)Ljava/lang/StringBuilder;
      38: invokevirtual #16                 // Method java/lang/StringBuilder.toString:()Ljava/lang/String;
      41: invokespecial #131                // Method java/lang/IllegalStateException."<init>":(Ljava/lang/String;)V
      44: athrow

  protected java.lang.Object parseObject(org.eclipse.jetty.util.ajax.JSON$Source);
    Code:
       0: aload_1
       1: invokeinterface #110,  1          // InterfaceMethod org/eclipse/jetty/util/ajax/JSON$Source.next:()C
       6: bipush        123
       8: if_icmpeq     19
      11: new           #122                // class java/lang/IllegalStateException
      14: dup
      15: invokespecial #132                // Method java/lang/IllegalStateException."<init>":()V
      18: athrow
      19: aload_0
      20: invokevirtual #133                // Method newMap:()Ljava/util/Map;
      23: astore_2
      24: aload_0
      25: ldc           #134                // String \"}
      27: aload_1
      28: invokevirtual #135                // Method seekTo:(Ljava/lang/String;Lorg/eclipse/jetty/util/ajax/JSON$Source;)C
      31: istore_3
      32: aload_1
      33: invokeinterface #107,  1          // InterfaceMethod org/eclipse/jetty/util/ajax/JSON$Source.hasNext:()Z
      38: ifeq          136
      41: iload_3
      42: bipush        125
      44: if_icmpne     57
      47: aload_1
      48: invokeinterface #110,  1          // InterfaceMethod org/eclipse/jetty/util/ajax/JSON$Source.next:()C
      53: pop
      54: goto          136
      57: aload_0
      58: aload_1
      59: invokevirtual #113                // Method parseString:(Lorg/eclipse/jetty/util/ajax/JSON$Source;)Ljava/lang/String;
      62: astore        4
      64: aload_0
      65: bipush        58
      67: aload_1
      68: invokevirtual #136                // Method seekTo:(CLorg/eclipse/jetty/util/ajax/JSON$Source;)V
      71: aload_1
      72: invokeinterface #110,  1          // InterfaceMethod org/eclipse/jetty/util/ajax/JSON$Source.next:()C
      77: pop
      78: aload_0
      79: aload         4
      81: invokevirtual #137                // Method contextFor:(Ljava/lang/String;)Lorg/eclipse/jetty/util/ajax/JSON;
      84: aload_1
      85: invokevirtual #44                 // Method parse:(Lorg/eclipse/jetty/util/ajax/JSON$Source;)Ljava/lang/Object;
      88: astore        5
      90: aload_2
      91: aload         4
      93: aload         5
      95: invokeinterface #98,  3           // InterfaceMethod java/util/Map.put:(Ljava/lang/Object;Ljava/lang/Object;)Ljava/lang/Object;
     100: pop
     101: aload_0
     102: ldc           #138                // String ,}
     104: aload_1
     105: invokevirtual #135                // Method seekTo:(Ljava/lang/String;Lorg/eclipse/jetty/util/ajax/JSON$Source;)C
     108: pop
     109: aload_1
     110: invokeinterface #110,  1          // InterfaceMethod org/eclipse/jetty/util/ajax/JSON$Source.next:()C
     115: istore_3
     116: iload_3
     117: bipush        125
     119: if_icmpne     125
     122: goto          136
     125: aload_0
     126: ldc           #134                // String \"}
     128: aload_1
     129: invokevirtual #135                // Method seekTo:(Ljava/lang/String;Lorg/eclipse/jetty/util/ajax/JSON$Source;)C
     132: istore_3
     133: goto          32
     136: aload_2
     137: ldc           #139                // String x-class
     139: invokeinterface #99,  2           // InterfaceMethod java/util/Map.get:(Ljava/lang/Object;)Ljava/lang/Object;
     144: checkcast     #47                 // class java/lang/String
     147: astore        4
     149: aload         4
     151: ifnull        195
     154: aload_0
     155: aload         4
     157: invokevirtual #106                // Method getConvertorFor:(Ljava/lang/String;)Lorg/eclipse/jetty/util/ajax/JSON$Convertor;
     160: astore        5
     162: aload         5
     164: ifnull        176
     167: aload         5
     169: aload_2
     170: invokeinterface #96,  2           // InterfaceMethod org/eclipse/jetty/util/ajax/JSON$Convertor.fromJSON:(Ljava/util/Map;)Ljava/lang/Object;
     175: areturn
     176: getstatic     #140                // Field LOG:Lorg/eclipse/jetty/util/log/Logger;
     179: ldc           #141                // String No Convertor for x-class \'{}\'
     181: iconst_1
     182: anewarray     #40                 // class java/lang/Object
     185: dup
     186: iconst_0
     187: aload         4
     189: aastore
     190: invokeinterface #142,  3          // InterfaceMethod org/eclipse/jetty/util/log/Logger.warn:(Ljava/lang/String;[Ljava/lang/Object;)V
     195: aload_2
     196: ldc           #143                // String class
     198: invokeinterface #99,  2           // InterfaceMethod java/util/Map.get:(Ljava/lang/Object;)Ljava/lang/Object;
     203: checkcast     #47                 // class java/lang/String
     206: astore        5
     208: aload         5
     210: ifnull        249
     213: aload         5
     215: invokestatic  #144                // Method org/eclipse/jetty/util/Loader.loadClass:(Ljava/lang/String;)Ljava/lang/Class;
     218: astore        6
     220: aload_0
     221: aload         6
     223: aload_2
     224: invokevirtual #145                // Method convertTo:(Ljava/lang/Class;Ljava/util/Map;)Ljava/lang/Object;
     227: areturn
     228: astore        6
     230: getstatic     #140                // Field LOG:Lorg/eclipse/jetty/util/log/Logger;
     233: ldc           #147                // String No Class for \'{}\'
     235: iconst_1
     236: anewarray     #40                 // class java/lang/Object
     239: dup
     240: iconst_0
     241: aload         5
     243: aastore
     244: invokeinterface #142,  3          // InterfaceMethod org/eclipse/jetty/util/log/Logger.warn:(Ljava/lang/String;[Ljava/lang/Object;)V
     249: aload_2
     250: areturn
    Exception table:
       from    to  target type
         213   227   228   Class java/lang/ClassNotFoundException

  private java.lang.Object defaultArrayConverter(java.util.List<?>);
    Code:
       0: aload_0
       1: aload_1
       2: invokeinterface #148,  1          // InterfaceMethod java/util/List.size:()I
       7: invokevirtual #149                // Method newArray:(I)[Ljava/lang/Object;
      10: astore_2
      11: iconst_0
      12: aload_1
      13: invokeinterface #148,  1          // InterfaceMethod java/util/List.size:()I
      18: invokestatic  #150                // InterfaceMethod java/util/stream/IntStream.range:(II)Ljava/util/stream/IntStream;
      21: aload_2
      22: aload_1
      23: invokedynamic #151,  0            // InvokeDynamic #1:accept:([Ljava/lang/Object;Ljava/util/List;)Ljava/util/function/IntConsumer;
      28: invokeinterface #152,  2          // InterfaceMethod java/util/stream/IntStream.forEach:(Ljava/util/function/IntConsumer;)V
      33: aload_2
      34: areturn

  protected java.lang.Object parseArray(org.eclipse.jetty.util.ajax.JSON$Source);
    Code:
       0: aload_1
       1: invokeinterface #110,  1          // InterfaceMethod org/eclipse/jetty/util/ajax/JSON$Source.next:()C
       6: bipush        91
       8: if_icmpeq     19
      11: new           #122                // class java/lang/IllegalStateException
      14: dup
      15: invokespecial #132                // Method java/lang/IllegalStateException."<init>":()V
      18: athrow
      19: iconst_0
      20: istore_2
      21: aconst_null
      22: astore_3
      23: aconst_null
      24: astore        4
      26: iconst_1
      27: istore        5
      29: aload_1
      30: invokeinterface #107,  1          // InterfaceMethod org/eclipse/jetty/util/ajax/JSON$Source.hasNext:()Z
      35: ifeq          277
      38: aload_1
      39: invokeinterface #108,  1          // InterfaceMethod org/eclipse/jetty/util/ajax/JSON$Source.peek:()C
      44: istore        6
      46: iload         6
      48: lookupswitch  { // 2
                    44: 139
                    93: 76
               default: 165
          }
      76: aload_1
      77: invokeinterface #110,  1          // InterfaceMethod org/eclipse/jetty/util/ajax/JSON$Source.next:()C
      82: pop
      83: iload_2
      84: lookupswitch  { // 2
                     0: 112
                     1: 119
               default: 128
          }
     112: invokestatic  #153                // Method java/util/Collections.emptyList:()Ljava/util/List;
     115: astore_3
     116: goto          128
     119: aload         4
     121: invokestatic  #154                // Method java/util/Collections.singletonList:(Ljava/lang/Object;)Ljava/util/List;
     124: astore_3
     125: goto          128
     128: aload_0
     129: invokevirtual #155                // Method getArrayConverter:()Ljava/util/function/Function;
     132: aload_3
     133: invokeinterface #156,  2          // InterfaceMethod java/util/function/Function.apply:(Ljava/lang/Object;)Ljava/lang/Object;
     138: areturn
     139: iload         5
     141: ifeq          152
     144: new           #122                // class java/lang/IllegalStateException
     147: dup
     148: invokespecial #132                // Method java/lang/IllegalStateException."<init>":()V
     151: athrow
     152: iconst_1
     153: istore        5
     155: aload_1
     156: invokeinterface #110,  1          // InterfaceMethod org/eclipse/jetty/util/ajax/JSON$Source.next:()C
     161: pop
     162: goto          274
     165: iload         6
     167: invokestatic  #109                // Method java/lang/Character.isWhitespace:(C)Z
     170: ifeq          183
     173: aload_1
     174: invokeinterface #110,  1          // InterfaceMethod org/eclipse/jetty/util/ajax/JSON$Source.next:()C
     179: pop
     180: goto          274
     183: iconst_0
     184: istore        5
     186: iload_2
     187: iinc          2, 1
     190: ifne          206
     193: aload_0
     194: invokevirtual #157                // Method contextForArray:()Lorg/eclipse/jetty/util/ajax/JSON;
     197: aload_1
     198: invokevirtual #44                 // Method parse:(Lorg/eclipse/jetty/util/ajax/JSON$Source;)Ljava/lang/Object;
     201: astore        4
     203: goto          274
     206: aload_3
     207: ifnonnull     252
     210: new           #158                // class java/util/ArrayList
     213: dup
     214: invokespecial #159                // Method java/util/ArrayList."<init>":()V
     217: astore_3
     218: aload_3
     219: aload         4
     221: invokeinterface #160,  2          // InterfaceMethod java/util/List.add:(Ljava/lang/Object;)Z
     226: pop
     227: aload_0
     228: invokevirtual #157                // Method contextForArray:()Lorg/eclipse/jetty/util/ajax/JSON;
     231: aload_1
     232: invokevirtual #44                 // Method parse:(Lorg/eclipse/jetty/util/ajax/JSON$Source;)Ljava/lang/Object;
     235: astore        4
     237: aload_3
     238: aload         4
     240: invokeinterface #160,  2          // InterfaceMethod java/util/List.add:(Ljava/lang/Object;)Z
     245: pop
     246: aconst_null
     247: astore        4
     249: goto          274
     252: aload_0
     253: invokevirtual #157                // Method contextForArray:()Lorg/eclipse/jetty/util/ajax/JSON;
     256: aload_1
     257: invokevirtual #44                 // Method parse:(Lorg/eclipse/jetty/util/ajax/JSON$Source;)Ljava/lang/Object;
     260: astore        4
     262: aload_3
     263: aload         4
     265: invokeinterface #160,  2          // InterfaceMethod java/util/List.add:(Ljava/lang/Object;)Z
     270: pop
     271: aconst_null
     272: astore        4
     274: goto          29
     277: new           #122                // class java/lang/IllegalStateException
     280: dup
     281: ldc           #161                // String unexpected end of array
     283: invokespecial #131                // Method java/lang/IllegalStateException."<init>":(Ljava/lang/String;)V
     286: athrow

  protected java.lang.String parseString(org.eclipse.jetty.util.ajax.JSON$Source);
    Code:
       0: aload_1
       1: invokeinterface #110,  1          // InterfaceMethod org/eclipse/jetty/util/ajax/JSON$Source.next:()C
       6: bipush        34
       8: if_icmpeq     19
      11: new           #122                // class java/lang/IllegalStateException
      14: dup
      15: invokespecial #132                // Method java/lang/IllegalStateException."<init>":()V
      18: athrow
      19: iconst_0
      20: istore_2
      21: aconst_null
      22: astore_3
      23: aload_1
      24: invokeinterface #162,  1          // InterfaceMethod org/eclipse/jetty/util/ajax/JSON$Source.scratchBuffer:()[C
      29: astore        4
      31: aload         4
      33: ifnull        423
      36: iconst_0
      37: istore        5
      39: aload_1
      40: invokeinterface #107,  1          // InterfaceMethod org/eclipse/jetty/util/ajax/JSON$Source.hasNext:()Z
      45: ifeq          406
      48: iload         5
      50: aload         4
      52: arraylength
      53: if_icmplt     82
      56: new           #12                 // class java/lang/StringBuilder
      59: dup
      60: aload         4
      62: arraylength
      63: iconst_2
      64: imul
      65: invokespecial #14                 // Method java/lang/StringBuilder."<init>":(I)V
      68: astore_3
      69: aload_3
      70: aload         4
      72: iconst_0
      73: iload         5
      75: invokevirtual #163                // Method java/lang/StringBuilder.append:([CII)Ljava/lang/StringBuilder;
      78: pop
      79: goto          406
      82: aload_1
      83: invokeinterface #110,  1          // InterfaceMethod org/eclipse/jetty/util/ajax/JSON$Source.next:()C
      88: istore        6
      90: iload_2
      91: ifeq          364
      94: iconst_0
      95: istore_2
      96: iload         6
      98: lookupswitch  { // 9
                    34: 180
                    47: 206
                    92: 193
                    98: 219
                   102: 232
                   110: 245
                   114: 258
                   116: 271
                   117: 284
               default: 351
          }
     180: aload         4
     182: iload         5
     184: iinc          5, 1
     187: bipush        34
     189: castore
     190: goto          403
     193: aload         4
     195: iload         5
     197: iinc          5, 1
     200: bipush        92
     202: castore
     203: goto          403
     206: aload         4
     208: iload         5
     210: iinc          5, 1
     213: bipush        47
     215: castore
     216: goto          403
     219: aload         4
     221: iload         5
     223: iinc          5, 1
     226: bipush        8
     228: castore
     229: goto          403
     232: aload         4
     234: iload         5
     236: iinc          5, 1
     239: bipush        12
     241: castore
     242: goto          403
     245: aload         4
     247: iload         5
     249: iinc          5, 1
     252: bipush        10
     254: castore
     255: goto          403
     258: aload         4
     260: iload         5
     262: iinc          5, 1
     265: bipush        13
     267: castore
     268: goto          403
     271: aload         4
     273: iload         5
     275: iinc          5, 1
     278: bipush        9
     280: castore
     281: goto          403
     284: aload_1
     285: invokeinterface #110,  1          // InterfaceMethod org/eclipse/jetty/util/ajax/JSON$Source.next:()C
     290: i2b
     291: invokestatic  #164                // Method org/eclipse/jetty/util/TypeUtil.convertHexDigit:(B)B
     294: bipush        12
     296: ishl
     297: aload_1
     298: invokeinterface #110,  1          // InterfaceMethod org/eclipse/jetty/util/ajax/JSON$Source.next:()C
     303: i2b
     304: invokestatic  #164                // Method org/eclipse/jetty/util/TypeUtil.convertHexDigit:(B)B
     307: bipush        8
     309: ishl
     310: iadd
     311: aload_1
     312: invokeinterface #110,  1          // InterfaceMethod org/eclipse/jetty/util/ajax/JSON$Source.next:()C
     317: i2b
     318: invokestatic  #164                // Method org/eclipse/jetty/util/TypeUtil.convertHexDigit:(B)B
     321: iconst_4
     322: ishl
     323: iadd
     324: aload_1
     325: invokeinterface #110,  1          // InterfaceMethod org/eclipse/jetty/util/ajax/JSON$Source.next:()C
     330: i2b
     331: invokestatic  #164                // Method org/eclipse/jetty/util/TypeUtil.convertHexDigit:(B)B
     334: iadd
     335: i2c
     336: istore        7
     338: aload         4
     340: iload         5
     342: iinc          5, 1
     345: iload         7
     347: castore
     348: goto          403
     351: aload         4
     353: iload         5
     355: iinc          5, 1
     358: iload         6
     360: castore
     361: goto          403
     364: iload         6
     366: bipush        92
     368: if_icmpne     376
     371: iconst_1
     372: istore_2
     373: goto          403
     376: iload         6
     378: bipush        34
     380: if_icmpne     393
     383: aload_0
     384: aload         4
     386: iconst_0
     387: iload         5
     389: invokevirtual #165                // Method toString:([CII)Ljava/lang/String;
     392: areturn
     393: aload         4
     395: iload         5
     397: iinc          5, 1
     400: iload         6
     402: castore
     403: goto          39
     406: aload_3
     407: ifnonnull     420
     410: aload_0
     411: aload         4
     413: iconst_0
     414: iload         5
     416: invokevirtual #165                // Method toString:([CII)Ljava/lang/String;
     419: areturn
     420: goto          435
     423: new           #12                 // class java/lang/StringBuilder
     426: dup
     427: aload_0
     428: invokevirtual #13                 // Method getStringBufferSize:()I
     431: invokespecial #14                 // Method java/lang/StringBuilder."<init>":(I)V
     434: astore_3
     435: aload_3
     436: astore        5
     438: aload_1
     439: invokeinterface #107,  1          // InterfaceMethod org/eclipse/jetty/util/ajax/JSON$Source.hasNext:()Z
     444: ifeq          741
     447: aload_1
     448: invokeinterface #110,  1          // InterfaceMethod org/eclipse/jetty/util/ajax/JSON$Source.next:()C
     453: istore        6
     455: iload_2
     456: ifeq          708
     459: iconst_0
     460: istore_2
     461: iload         6
     463: lookupswitch  { // 9
                    34: 544
                    47: 566
                    92: 555
                    98: 577
                   102: 588
                   110: 599
                   114: 610
                   116: 621
                   117: 632
               default: 697
          }
     544: aload         5
     546: bipush        34
     548: invokevirtual #126                // Method java/lang/StringBuilder.append:(C)Ljava/lang/StringBuilder;
     551: pop
     552: goto          738
     555: aload         5
     557: bipush        92
     559: invokevirtual #126                // Method java/lang/StringBuilder.append:(C)Ljava/lang/StringBuilder;
     562: pop
     563: goto          738
     566: aload         5
     568: bipush        47
     570: invokevirtual #126                // Method java/lang/StringBuilder.append:(C)Ljava/lang/StringBuilder;
     573: pop
     574: goto          738
     577: aload         5
     579: bipush        8
     581: invokevirtual #126                // Method java/lang/StringBuilder.append:(C)Ljava/lang/StringBuilder;
     584: pop
     585: goto          738
     588: aload         5
     590: bipush        12
     592: invokevirtual #126                // Method java/lang/StringBuilder.append:(C)Ljava/lang/StringBuilder;
     595: pop
     596: goto          738
     599: aload         5
     601: bipush        10
     603: invokevirtual #126                // Method java/lang/StringBuilder.append:(C)Ljava/lang/StringBuilder;
     606: pop
     607: goto          738
     610: aload         5
     612: bipush        13
     614: invokevirtual #126                // Method java/lang/StringBuilder.append:(C)Ljava/lang/StringBuilder;
     617: pop
     618: goto          738
     621: aload         5
     623: bipush        9
     625: invokevirtual #126                // Method java/lang/StringBuilder.append:(C)Ljava/lang/StringBuilder;
     628: pop
     629: goto          738
     632: aload_1
     633: invokeinterface #110,  1          // InterfaceMethod org/eclipse/jetty/util/ajax/JSON$Source.next:()C
     638: i2b
     639: invokestatic  #164                // Method org/eclipse/jetty/util/TypeUtil.convertHexDigit:(B)B
     642: bipush        12
     644: ishl
     645: aload_1
     646: invokeinterface #110,  1          // InterfaceMethod org/eclipse/jetty/util/ajax/JSON$Source.next:()C
     651: i2b
     652: invokestatic  #164                // Method org/eclipse/jetty/util/TypeUtil.convertHexDigit:(B)B
     655: bipush        8
     657: ishl
     658: iadd
     659: aload_1
     660: invokeinterface #110,  1          // InterfaceMethod org/eclipse/jetty/util/ajax/JSON$Source.next:()C
     665: i2b
     666: invokestatic  #164                // Method org/eclipse/jetty/util/TypeUtil.convertHexDigit:(B)B
     669: iconst_4
     670: ishl
     671: iadd
     672: aload_1
     673: invokeinterface #110,  1          // InterfaceMethod org/eclipse/jetty/util/ajax/JSON$Source.next:()C
     678: i2b
     679: invokestatic  #164                // Method org/eclipse/jetty/util/TypeUtil.convertHexDigit:(B)B
     682: iadd
     683: i2c
     684: istore        7
     686: aload         5
     688: iload         7
     690: invokevirtual #126                // Method java/lang/StringBuilder.append:(C)Ljava/lang/StringBuilder;
     693: pop
     694: goto          738
     697: aload         5
     699: iload         6
     701: invokevirtual #126                // Method java/lang/StringBuilder.append:(C)Ljava/lang/StringBuilder;
     704: pop
     705: goto          738
     708: iload         6
     710: bipush        92
     712: if_icmpne     720
     715: iconst_1
     716: istore_2
     717: goto          738
     720: iload         6
     722: bipush        34
     724: if_icmpne     730
     727: goto          741
     730: aload         5
     732: iload         6
     734: invokevirtual #126                // Method java/lang/StringBuilder.append:(C)Ljava/lang/StringBuilder;
     737: pop
     738: goto          438
     741: aload         5
     743: invokevirtual #16                 // Method java/lang/StringBuilder.toString:()Ljava/lang/String;
     746: areturn

  public java.lang.Number parseNumber(org.eclipse.jetty.util.ajax.JSON$Source);
    Code:
       0: iconst_0
       1: istore_2
       2: lconst_0
       3: lstore_3
       4: aconst_null
       5: astore        5
       7: aload_1
       8: invokeinterface #107,  1          // InterfaceMethod org/eclipse/jetty/util/ajax/JSON$Source.hasNext:()Z
      13: ifeq          381
      16: aload_1
      17: invokeinterface #108,  1          // InterfaceMethod org/eclipse/jetty/util/ajax/JSON$Source.peek:()C
      22: istore        6
      24: iload         6
      26: tableswitch   { // 43 to 101
                    43: 299
                    44: 375
                    45: 299
                    46: 327
                    47: 375
                    48: 276
                    49: 276
                    50: 276
                    51: 276
                    52: 276
                    53: 276
                    54: 276
                    55: 276
                    56: 276
                    57: 276
                    58: 375
                    59: 375
                    60: 375
                    61: 375
                    62: 375
                    63: 375
                    64: 375
                    65: 375
                    66: 375
                    67: 375
                    68: 375
                    69: 327
                    70: 375
                    71: 375
                    72: 375
                    73: 375
                    74: 375
                    75: 375
                    76: 375
                    77: 375
                    78: 375
                    79: 375
                    80: 375
                    81: 375
                    82: 375
                    83: 375
                    84: 375
                    85: 375
                    86: 375
                    87: 375
                    88: 375
                    89: 375
                    90: 375
                    91: 375
                    92: 375
                    93: 375
                    94: 375
                    95: 375
                    96: 375
                    97: 375
                    98: 375
                    99: 375
                   100: 375
                   101: 327
               default: 375
          }
     276: lload_3
     277: ldc2_w        #166                // long 10l
     280: lmul
     281: iload         6
     283: bipush        48
     285: isub
     286: i2l
     287: ladd
     288: lstore_3
     289: aload_1
     290: invokeinterface #110,  1          // InterfaceMethod org/eclipse/jetty/util/ajax/JSON$Source.next:()C
     295: pop
     296: goto          378
     299: lload_3
     300: lconst_0
     301: lcmp
     302: ifeq          315
     305: new           #122                // class java/lang/IllegalStateException
     308: dup
     309: ldc           #168                // String bad number
     311: invokespecial #131                // Method java/lang/IllegalStateException."<init>":(Ljava/lang/String;)V
     314: athrow
     315: iconst_1
     316: istore_2
     317: aload_1
     318: invokeinterface #110,  1          // InterfaceMethod org/eclipse/jetty/util/ajax/JSON$Source.next:()C
     323: pop
     324: goto          378
     327: new           #12                 // class java/lang/StringBuilder
     330: dup
     331: bipush        16
     333: invokespecial #14                 // Method java/lang/StringBuilder."<init>":(I)V
     336: astore        5
     338: iload_2
     339: ifeq          350
     342: aload         5
     344: bipush        45
     346: invokevirtual #126                // Method java/lang/StringBuilder.append:(C)Ljava/lang/StringBuilder;
     349: pop
     350: aload         5
     352: lload_3
     353: invokevirtual #169                // Method java/lang/StringBuilder.append:(J)Ljava/lang/StringBuilder;
     356: pop
     357: aload         5
     359: iload         6
     361: invokevirtual #126                // Method java/lang/StringBuilder.append:(C)Ljava/lang/StringBuilder;
     364: pop
     365: aload_1
     366: invokeinterface #110,  1          // InterfaceMethod org/eclipse/jetty/util/ajax/JSON$Source.next:()C
     371: pop
     372: goto          381
     375: goto          381
     378: goto          7
     381: aload         5
     383: ifnonnull     403
     386: iload_2
     387: ifeq          398
     390: ldc2_w        #170                // long -1l
     393: lload_3
     394: lmul
     395: goto          399
     398: lload_3
     399: invokestatic  #172                // Method java/lang/Long.valueOf:(J)Ljava/lang/Long;
     402: areturn
     403: aload_1
     404: invokeinterface #107,  1          // InterfaceMethod org/eclipse/jetty/util/ajax/JSON$Source.hasNext:()Z
     409: ifeq          696
     412: aload_1
     413: invokeinterface #108,  1          // InterfaceMethod org/eclipse/jetty/util/ajax/JSON$Source.peek:()C
     418: istore        6
     420: iload         6
     422: tableswitch   { // 43 to 101
                    43: 672
                    44: 690
                    45: 672
                    46: 672
                    47: 690
                    48: 672
                    49: 672
                    50: 672
                    51: 672
                    52: 672
                    53: 672
                    54: 672
                    55: 672
                    56: 672
                    57: 672
                    58: 690
                    59: 690
                    60: 690
                    61: 690
                    62: 690
                    63: 690
                    64: 690
                    65: 690
                    66: 690
                    67: 690
                    68: 690
                    69: 672
                    70: 690
                    71: 690
                    72: 690
                    73: 690
                    74: 690
                    75: 690
                    76: 690
                    77: 690
                    78: 690
                    79: 690
                    80: 690
                    81: 690
                    82: 690
                    83: 690
                    84: 690
                    85: 690
                    86: 690
                    87: 690
                    88: 690
                    89: 690
                    90: 690
                    91: 690
                    92: 690
                    93: 690
                    94: 690
                    95: 690
                    96: 690
                    97: 690
                    98: 690
                    99: 690
                   100: 690
                   101: 672
               default: 690
          }
     672: aload         5
     674: iload         6
     676: invokevirtual #126                // Method java/lang/StringBuilder.append:(C)Ljava/lang/StringBuilder;
     679: pop
     680: aload_1
     681: invokeinterface #110,  1          // InterfaceMethod org/eclipse/jetty/util/ajax/JSON$Source.next:()C
     686: pop
     687: goto          693
     690: goto          696
     693: goto          403
     696: aload         5
     698: invokevirtual #16                 // Method java/lang/StringBuilder.toString:()Ljava/lang/String;
     701: invokestatic  #173                // Method java/lang/Double.valueOf:(Ljava/lang/String;)Ljava/lang/Double;
     704: areturn

  protected void seekTo(char, org.eclipse.jetty.util.ajax.JSON$Source);
    Code:
       0: aload_2
       1: invokeinterface #107,  1          // InterfaceMethod org/eclipse/jetty/util/ajax/JSON$Source.hasNext:()Z
       6: ifeq          80
       9: aload_2
      10: invokeinterface #108,  1          // InterfaceMethod org/eclipse/jetty/util/ajax/JSON$Source.peek:()C
      15: istore_3
      16: iload_3
      17: iload_1
      18: if_icmpne     22
      21: return
      22: iload_3
      23: invokestatic  #109                // Method java/lang/Character.isWhitespace:(C)Z
      26: ifne          70
      29: new           #122                // class java/lang/IllegalStateException
      32: dup
      33: new           #12                 // class java/lang/StringBuilder
      36: dup
      37: invokespecial #123                // Method java/lang/StringBuilder."<init>":()V
      40: ldc           #174                // String Unexpected \'
      42: invokevirtual #125                // Method java/lang/StringBuilder.append:(Ljava/lang/String;)Ljava/lang/StringBuilder;
      45: iload_3
      46: invokevirtual #126                // Method java/lang/StringBuilder.append:(C)Ljava/lang/StringBuilder;
      49: ldc           #175                // String  while seeking \'
      51: invokevirtual #125                // Method java/lang/StringBuilder.append:(Ljava/lang/String;)Ljava/lang/StringBuilder;
      54: iload_1
      55: invokevirtual #126                // Method java/lang/StringBuilder.append:(C)Ljava/lang/StringBuilder;
      58: ldc           #176                // String \'
      60: invokevirtual #125                // Method java/lang/StringBuilder.append:(Ljava/lang/String;)Ljava/lang/StringBuilder;
      63: invokevirtual #16                 // Method java/lang/StringBuilder.toString:()Ljava/lang/String;
      66: invokespecial #131                // Method java/lang/IllegalStateException."<init>":(Ljava/lang/String;)V
      69: athrow
      70: aload_2
      71: invokeinterface #110,  1          // InterfaceMethod org/eclipse/jetty/util/ajax/JSON$Source.next:()C
      76: pop
      77: goto          0
      80: new           #122                // class java/lang/IllegalStateException
      83: dup
      84: new           #12                 // class java/lang/StringBuilder
      87: dup
      88: invokespecial #123                // Method java/lang/StringBuilder."<init>":()V
      91: ldc           #177                // String Expected \'
      93: invokevirtual #125                // Method java/lang/StringBuilder.append:(Ljava/lang/String;)Ljava/lang/StringBuilder;
      96: iload_1
      97: invokevirtual #126                // Method java/lang/StringBuilder.append:(C)Ljava/lang/StringBuilder;
     100: ldc           #176                // String \'
     102: invokevirtual #125                // Method java/lang/StringBuilder.append:(Ljava/lang/String;)Ljava/lang/StringBuilder;
     105: invokevirtual #16                 // Method java/lang/StringBuilder.toString:()Ljava/lang/String;
     108: invokespecial #131                // Method java/lang/IllegalStateException."<init>":(Ljava/lang/String;)V
     111: athrow

  protected char seekTo(java.lang.String, org.eclipse.jetty.util.ajax.JSON$Source);
    Code:
       0: aload_2
       1: invokeinterface #107,  1          // InterfaceMethod org/eclipse/jetty/util/ajax/JSON$Source.hasNext:()Z
       6: ifeq          84
       9: aload_2
      10: invokeinterface #108,  1          // InterfaceMethod org/eclipse/jetty/util/ajax/JSON$Source.peek:()C
      15: istore_3
      16: aload_1
      17: iload_3
      18: invokevirtual #178                // Method java/lang/String.indexOf:(I)I
      21: iflt          26
      24: iload_3
      25: ireturn
      26: iload_3
      27: invokestatic  #109                // Method java/lang/Character.isWhitespace:(C)Z
      30: ifne          74
      33: new           #122                // class java/lang/IllegalStateException
      36: dup
      37: new           #12                 // class java/lang/StringBuilder
      40: dup
      41: invokespecial #123                // Method java/lang/StringBuilder."<init>":()V
      44: ldc           #174                // String Unexpected \'
      46: invokevirtual #125                // Method java/lang/StringBuilder.append:(Ljava/lang/String;)Ljava/lang/StringBuilder;
      49: iload_3
      50: invokevirtual #126                // Method java/lang/StringBuilder.append:(C)Ljava/lang/StringBuilder;
      53: ldc           #179                // String \' while seeking one of \'
      55: invokevirtual #125                // Method java/lang/StringBuilder.append:(Ljava/lang/String;)Ljava/lang/StringBuilder;
      58: aload_1
      59: invokevirtual #125                // Method java/lang/StringBuilder.append:(Ljava/lang/String;)Ljava/lang/StringBuilder;
      62: ldc           #176                // String \'
      64: invokevirtual #125                // Method java/lang/StringBuilder.append:(Ljava/lang/String;)Ljava/lang/StringBuilder;
      67: invokevirtual #16                 // Method java/lang/StringBuilder.toString:()Ljava/lang/String;
      70: invokespecial #131                // Method java/lang/IllegalStateException."<init>":(Ljava/lang/String;)V
      73: athrow
      74: aload_2
      75: invokeinterface #110,  1          // InterfaceMethod org/eclipse/jetty/util/ajax/JSON$Source.next:()C
      80: pop
      81: goto          0
      84: new           #122                // class java/lang/IllegalStateException
      87: dup
      88: new           #12                 // class java/lang/StringBuilder
      91: dup
      92: invokespecial #123                // Method java/lang/StringBuilder."<init>":()V
      95: ldc           #180                // String Expected one of \'
      97: invokevirtual #125                // Method java/lang/StringBuilder.append:(Ljava/lang/String;)Ljava/lang/StringBuilder;
     100: aload_1
     101: invokevirtual #125                // Method java/lang/StringBuilder.append:(Ljava/lang/String;)Ljava/lang/StringBuilder;
     104: ldc           #176                // String \'
     106: invokevirtual #125                // Method java/lang/StringBuilder.append:(Ljava/lang/String;)Ljava/lang/StringBuilder;
     109: invokevirtual #16                 // Method java/lang/StringBuilder.toString:()Ljava/lang/String;
     112: invokespecial #131                // Method java/lang/IllegalStateException."<init>":(Ljava/lang/String;)V
     115: athrow

  protected static void complete(java.lang.String, org.eclipse.jetty.util.ajax.JSON$Source);
    Code:
       0: iconst_0
       1: istore_2
       2: aload_1
       3: invokeinterface #107,  1          // InterfaceMethod org/eclipse/jetty/util/ajax/JSON$Source.hasNext:()Z
       8: ifeq          82
      11: iload_2
      12: aload_0
      13: invokevirtual #31                 // Method java/lang/String.length:()I
      16: if_icmpge     82
      19: aload_1
      20: invokeinterface #110,  1          // InterfaceMethod org/eclipse/jetty/util/ajax/JSON$Source.next:()C
      25: istore_3
      26: iload_3
      27: aload_0
      28: iload_2
      29: iinc          2, 1
      32: invokevirtual #32                 // Method java/lang/String.charAt:(I)C
      35: if_icmpeq     79
      38: new           #122                // class java/lang/IllegalStateException
      41: dup
      42: new           #12                 // class java/lang/StringBuilder
      45: dup
      46: invokespecial #123                // Method java/lang/StringBuilder."<init>":()V
      49: ldc           #174                // String Unexpected \'
      51: invokevirtual #125                // Method java/lang/StringBuilder.append:(Ljava/lang/String;)Ljava/lang/StringBuilder;
      54: iload_3
      55: invokevirtual #126                // Method java/lang/StringBuilder.append:(C)Ljava/lang/StringBuilder;
      58: ldc           #181                // String  while seeking  \"
      60: invokevirtual #125                // Method java/lang/StringBuilder.append:(Ljava/lang/String;)Ljava/lang/StringBuilder;
      63: aload_0
      64: invokevirtual #125                // Method java/lang/StringBuilder.append:(Ljava/lang/String;)Ljava/lang/StringBuilder;
      67: ldc           #182                // String \"
      69: invokevirtual #125                // Method java/lang/StringBuilder.append:(Ljava/lang/String;)Ljava/lang/StringBuilder;
      72: invokevirtual #16                 // Method java/lang/StringBuilder.toString:()Ljava/lang/String;
      75: invokespecial #131                // Method java/lang/IllegalStateException."<init>":(Ljava/lang/String;)V
      78: athrow
      79: goto          2
      82: iload_2
      83: aload_0
      84: invokevirtual #31                 // Method java/lang/String.length:()I
      87: if_icmpge     122
      90: new           #122                // class java/lang/IllegalStateException
      93: dup
      94: new           #12                 // class java/lang/StringBuilder
      97: dup
      98: invokespecial #123                // Method java/lang/StringBuilder."<init>":()V
     101: ldc           #183                // String Expected \"
     103: invokevirtual #125                // Method java/lang/StringBuilder.append:(Ljava/lang/String;)Ljava/lang/StringBuilder;
     106: aload_0
     107: invokevirtual #125                // Method java/lang/StringBuilder.append:(Ljava/lang/String;)Ljava/lang/StringBuilder;
     110: ldc           #182                // String \"
     112: invokevirtual #125                // Method java/lang/StringBuilder.append:(Ljava/lang/String;)Ljava/lang/StringBuilder;
     115: invokevirtual #16                 // Method java/lang/StringBuilder.toString:()Ljava/lang/String;
     118: invokespecial #131                // Method java/lang/IllegalStateException."<init>":(Ljava/lang/String;)V
     121: athrow
     122: return

  private static void lambda$defaultArrayConverter$0(java.lang.Object[], java.util.List, int);
    Code:
       0: aload_0
       1: iload_2
       2: aload_1
       3: iload_2
       4: invokeinterface #184,  2          // InterfaceMethod java/util/List.get:(I)Ljava/lang/Object;
       9: aastore
      10: return

  static void access$100(org.eclipse.jetty.util.ajax.JSON, java.lang.Appendable, java.lang.String);
    Code:
       0: aload_0
       1: aload_1
       2: aload_2
       3: invokespecial #1                  // Method quotedEscape:(Ljava/lang/Appendable;Ljava/lang/String;)V
       6: return

  static {};
    Code:
       0: ldc           #185                // class org/eclipse/jetty/util/ajax/JSON
       2: invokestatic  #186                // Method org/eclipse/jetty/util/log/Log.getLogger:(Ljava/lang/Class;)Lorg/eclipse/jetty/util/log/Logger;
       5: putstatic     #140                // Field LOG:Lorg/eclipse/jetty/util/log/Logger;
       8: new           #185                // class org/eclipse/jetty/util/ajax/JSON
      11: dup
      12: invokespecial #187                // Method "<init>":()V
      15: putstatic     #9                  // Field DEFAULT:Lorg/eclipse/jetty/util/ajax/JSON;
      18: return
}
