Compiled from "DefaultInjector.java"
public class org.jboss.weld.injection.producer.DefaultInjector<T> implements org.jboss.weld.injection.producer.Injector<T> {
  private final java.util.List<java.util.Set<org.jboss.weld.injection.FieldInjectionPoint<?, ?>>> injectableFields;

  private final java.util.List<java.util.Set<org.jboss.weld.injection.MethodInjectionPoint<?, ?>>> initializerMethods;

  public static <T> org.jboss.weld.injection.producer.DefaultInjector<T> of(org.jboss.weld.annotated.enhanced.EnhancedAnnotatedType<T>, javax.enterprise.inject.spi.Bean<T>, org.jboss.weld.manager.BeanManagerImpl);
    Code:
       0: new           #3                  // class org/jboss/weld/injection/producer/DefaultInjector
       3: dup
       4: aload_0
       5: aload_1
       6: aload_2
       7: invokespecial #4                  // Method "<init>":(Lorg/jboss/weld/annotated/enhanced/EnhancedAnnotatedType;Ljavax/enterprise/inject/spi/Bean;Lorg/jboss/weld/manager/BeanManagerImpl;)V
      10: areturn

  public org.jboss.weld.injection.producer.DefaultInjector(org.jboss.weld.annotated.enhanced.EnhancedAnnotatedType<T>, javax.enterprise.inject.spi.Bean<T>, org.jboss.weld.manager.BeanManagerImpl);
    Code:
       0: aload_0
       1: invokespecial #5                  // Method java/lang/Object."<init>":()V
       4: aload_0
       5: invokestatic  #6                  // Method org/jboss/weld/injection/InjectionPointFactory.instance:()Lorg/jboss/weld/injection/InjectionPointFactory;
       8: aload_2
       9: aload_1
      10: aload_3
      11: invokevirtual #7                  // Method org/jboss/weld/injection/InjectionPointFactory.getFieldInjectionPoints:(Ljavax/enterprise/inject/spi/Bean;Lorg/jboss/weld/annotated/enhanced/EnhancedAnnotatedType;Lorg/jboss/weld/manager/BeanManagerImpl;)Ljava/util/List;
      14: putfield      #2                  // Field injectableFields:Ljava/util/List;
      17: aload_0
      18: aload_2
      19: aload_1
      20: aload_3
      21: invokestatic  #8                  // Method org/jboss/weld/util/BeanMethods.getInitializerMethods:(Ljavax/enterprise/inject/spi/Bean;Lorg/jboss/weld/annotated/enhanced/EnhancedAnnotatedType;Lorg/jboss/weld/manager/BeanManagerImpl;)Ljava/util/List;
      24: putfield      #1                  // Field initializerMethods:Ljava/util/List;
      27: return

  public void registerInjectionPoints(java.util.Set<javax.enterprise.inject.spi.InjectionPoint>);
    Code:
       0: aload_1
       1: aload_0
       2: getfield      #2                  // Field injectableFields:Ljava/util/List;
       5: invokestatic  #9                  // Method org/jboss/weld/util/InjectionPoints.flattenInjectionPoints:(Ljava/util/List;)Ljava/util/Set;
       8: invokeinterface #10,  2           // InterfaceMethod java/util/Set.addAll:(Ljava/util/Collection;)Z
      13: pop
      14: aload_1
      15: aload_0
      16: getfield      #1                  // Field initializerMethods:Ljava/util/List;
      19: invokestatic  #11                 // Method org/jboss/weld/util/InjectionPoints.flattenParameterInjectionPoints:(Ljava/util/List;)Ljava/util/Set;
      22: invokeinterface #10,  2           // InterfaceMethod java/util/Set.addAll:(Ljava/util/Collection;)Z
      27: pop
      28: return

  public void inject(T, javax.enterprise.context.spi.CreationalContext<T>, org.jboss.weld.manager.BeanManagerImpl, org.jboss.weld.annotated.slim.SlimAnnotatedType<T>, javax.enterprise.inject.spi.InjectionTarget<T>);
    Code:
       0: new           #12                 // class org/jboss/weld/injection/producer/DefaultInjector$1
       3: dup
       4: aload_0
       5: aload_3
       6: aload         5
       8: aload         4
      10: aload_1
      11: aload_1
      12: aload_2
      13: aload_3
      14: invokespecial #13                 // Method org/jboss/weld/injection/producer/DefaultInjector$1."<init>":(Lorg/jboss/weld/injection/producer/DefaultInjector;Lorg/jboss/weld/manager/BeanManagerImpl;Ljavax/enterprise/inject/spi/InjectionTarget;Ljavax/enterprise/inject/spi/AnnotatedType;Ljava/lang/Object;Ljava/lang/Object;Ljavax/enterprise/context/spi/CreationalContext;Lorg/jboss/weld/manager/BeanManagerImpl;)V
      17: invokevirtual #14                 // Method org/jboss/weld/injection/producer/DefaultInjector$1.run:()V
      20: return

  public java.util.List<java.util.Set<org.jboss.weld.injection.FieldInjectionPoint<?, ?>>> getInjectableFields();
    Code:
       0: aload_0
       1: getfield      #2                  // Field injectableFields:Ljava/util/List;
       4: areturn

  public java.util.List<java.util.Set<org.jboss.weld.injection.MethodInjectionPoint<?, ?>>> getInitializerMethods();
    Code:
       0: aload_0
       1: getfield      #1                  // Field initializerMethods:Ljava/util/List;
       4: areturn

  static java.util.List access$000(org.jboss.weld.injection.producer.DefaultInjector);
    Code:
       0: aload_0
       1: getfield      #2                  // Field injectableFields:Ljava/util/List;
       4: areturn

  static java.util.List access$100(org.jboss.weld.injection.producer.DefaultInjector);
    Code:
       0: aload_0
       1: getfield      #1                  // Field initializerMethods:Ljava/util/List;
       4: areturn
}
