Compiled from "ListPeripheralBysceneResponse.java"
public class cn.com.antcloud.api.provider.bot.v1_0_0.response.ListPeripheralBysceneResponse extends cn.com.antcloud.api.product.provider.AntCloudProdProviderResponse<cn.com.antcloud.api.provider.bot.v1_0_0.response.ListPeripheralBysceneResponse> {
  private java.util.List<cn.com.antcloud.api.provider.bot.v1_0_0.model.Peripheral> peripheralList;

  public cn.com.antcloud.api.provider.bot.v1_0_0.response.ListPeripheralBysceneResponse();
    Code:
       0: aload_0
       1: invokespecial #1                  // Method cn/com/antcloud/api/product/provider/AntCloudProdProviderResponse."<init>":()V
       4: return

  public java.util.List<cn.com.antcloud.api.provider.bot.v1_0_0.model.Peripheral> getPeripheralList();
    Code:
       0: aload_0
       1: getfield      #2                  // Field peripheralList:Ljava/util/List;
       4: areturn

  public void setPeripheralList(java.util.List<cn.com.antcloud.api.provider.bot.v1_0_0.model.Peripheral>);
    Code:
       0: aload_0
       1: aload_1
       2: putfield      #2                  // Field peripheralList:Ljava/util/List;
       5: return
}
