Compiled from "PagequerySceneResponse.java"
public class cn.com.antcloud.api.provider.bot.v1_0_0.response.PagequerySceneResponse extends cn.com.antcloud.api.product.provider.AntCloudProdProviderResponse<cn.com.antcloud.api.provider.bot.v1_0_0.response.PagequerySceneResponse> {
  private cn.com.antcloud.api.provider.bot.v1_0_0.model.ScenePageResponse data;

  public cn.com.antcloud.api.provider.bot.v1_0_0.response.PagequerySceneResponse();
    Code:
       0: aload_0
       1: invokespecial #1                  // Method cn/com/antcloud/api/product/provider/AntCloudProdProviderResponse."<init>":()V
       4: return

  public cn.com.antcloud.api.provider.bot.v1_0_0.model.ScenePageResponse getData();
    Code:
       0: aload_0
       1: getfield      #2                  // Field data:Lcn/com/antcloud/api/provider/bot/v1_0_0/model/ScenePageResponse;
       4: areturn

  public void setData(cn.com.antcloud.api.provider.bot.v1_0_0.model.ScenePageResponse);
    Code:
       0: aload_0
       1: aload_1
       2: putfield      #2                  // Field data:Lcn/com/antcloud/api/provider/bot/v1_0_0/model/ScenePageResponse;
       5: return
}
