Compiled from "EventDumpListener.java"
public class org.xwiki.rendering.wikimodel.EventDumpListener extends org.xwiki.rendering.wikimodel.PrintTextListener {
  private int fDepth;

  public org.xwiki.rendering.wikimodel.EventDumpListener(org.xwiki.rendering.wikimodel.IWikiPrinter);
    Code:
       0: aload_0
       1: aload_1
       2: invokespecial #1                  // Method org/xwiki/rendering/wikimodel/PrintTextListener."<init>":(Lorg/xwiki/rendering/wikimodel/IWikiPrinter;)V
       5: return

  public void beginDefinitionDescription();
    Code:
       0: aload_0
       1: ldc           #2                  // String beginDefinitionDescription()
       3: invokevirtual #3                  // Method println:(Ljava/lang/String;)V
       6: aload_0
       7: invokevirtual #4                  // Method inc:()V
      10: return

  public void beginDefinitionList(org.xwiki.rendering.wikimodel.WikiParameters);
    Code:
       0: aload_0
       1: aload_1
       2: invokedynamic #5,  0              // InvokeDynamic #0:makeConcatWithConstants:(Lorg/xwiki/rendering/wikimodel/WikiParameters;)Ljava/lang/String;
       7: invokevirtual #3                  // Method println:(Ljava/lang/String;)V
      10: aload_0
      11: invokevirtual #4                  // Method inc:()V
      14: return

  public void beginDefinitionTerm();
    Code:
       0: aload_0
       1: ldc           #6                  // String beginDefinitionTerm()
       3: invokevirtual #3                  // Method println:(Ljava/lang/String;)V
       6: aload_0
       7: invokevirtual #4                  // Method inc:()V
      10: return

  public void beginDocument(org.xwiki.rendering.wikimodel.WikiParameters);
    Code:
       0: aload_0
       1: aload_1
       2: invokedynamic #7,  0              // InvokeDynamic #1:makeConcatWithConstants:(Lorg/xwiki/rendering/wikimodel/WikiParameters;)Ljava/lang/String;
       7: invokevirtual #3                  // Method println:(Ljava/lang/String;)V
      10: aload_0
      11: invokevirtual #4                  // Method inc:()V
      14: return

  public void beginFormat(org.xwiki.rendering.wikimodel.WikiFormat);
    Code:
       0: aload_0
       1: aload_1
       2: invokedynamic #8,  0              // InvokeDynamic #2:makeConcatWithConstants:(Lorg/xwiki/rendering/wikimodel/WikiFormat;)Ljava/lang/String;
       7: invokevirtual #3                  // Method println:(Ljava/lang/String;)V
      10: aload_0
      11: invokevirtual #4                  // Method inc:()V
      14: return

  public void beginHeader(int, org.xwiki.rendering.wikimodel.WikiParameters);
    Code:
       0: aload_0
       1: iload_1
       2: aload_2
       3: invokedynamic #9,  0              // InvokeDynamic #3:makeConcatWithConstants:(ILorg/xwiki/rendering/wikimodel/WikiParameters;)Ljava/lang/String;
       8: invokevirtual #3                  // Method println:(Ljava/lang/String;)V
      11: aload_0
      12: invokevirtual #4                  // Method inc:()V
      15: return

  public void beginInfoBlock(java.lang.String, org.xwiki.rendering.wikimodel.WikiParameters);
    Code:
       0: aload_0
       1: aload_1
       2: aload_2
       3: invokedynamic #10,  0             // InvokeDynamic #4:makeConcatWithConstants:(Ljava/lang/String;Lorg/xwiki/rendering/wikimodel/WikiParameters;)Ljava/lang/String;
       8: invokevirtual #3                  // Method println:(Ljava/lang/String;)V
      11: aload_0
      12: invokevirtual #4                  // Method inc:()V
      15: return

  public void beginList(org.xwiki.rendering.wikimodel.WikiParameters, boolean);
    Code:
       0: aload_0
       1: aload_1
       2: iload_2
       3: invokedynamic #11,  0             // InvokeDynamic #5:makeConcatWithConstants:(Lorg/xwiki/rendering/wikimodel/WikiParameters;Z)Ljava/lang/String;
       8: invokevirtual #3                  // Method println:(Ljava/lang/String;)V
      11: aload_0
      12: invokevirtual #4                  // Method inc:()V
      15: return

  public void beginListItem();
    Code:
       0: aload_0
       1: ldc           #12                 // String beginListItem()
       3: invokevirtual #3                  // Method println:(Ljava/lang/String;)V
       6: aload_0
       7: invokevirtual #4                  // Method inc:()V
      10: return

  public void beginListItem(org.xwiki.rendering.wikimodel.WikiParameters);
    Code:
       0: aload_0
       1: aload_1
       2: invokedynamic #13,  0             // InvokeDynamic #6:makeConcatWithConstants:(Lorg/xwiki/rendering/wikimodel/WikiParameters;)Ljava/lang/String;
       7: invokevirtual #3                  // Method println:(Ljava/lang/String;)V
      10: aload_0
      11: invokevirtual #4                  // Method inc:()V
      14: return

  public void beginParagraph(org.xwiki.rendering.wikimodel.WikiParameters);
    Code:
       0: aload_0
       1: aload_1
       2: invokedynamic #14,  0             // InvokeDynamic #7:makeConcatWithConstants:(Lorg/xwiki/rendering/wikimodel/WikiParameters;)Ljava/lang/String;
       7: invokevirtual #3                  // Method println:(Ljava/lang/String;)V
      10: aload_0
      11: invokevirtual #4                  // Method inc:()V
      14: return

  public void beginPropertyBlock(java.lang.String, boolean);
    Code:
       0: aload_0
       1: aload_1
       2: iload_2
       3: invokedynamic #15,  0             // InvokeDynamic #8:makeConcatWithConstants:(Ljava/lang/String;Z)Ljava/lang/String;
       8: invokevirtual #3                  // Method println:(Ljava/lang/String;)V
      11: aload_0
      12: invokevirtual #4                  // Method inc:()V
      15: return

  public void beginPropertyInline(java.lang.String);
    Code:
       0: aload_0
       1: aload_1
       2: invokedynamic #16,  0             // InvokeDynamic #9:makeConcatWithConstants:(Ljava/lang/String;)Ljava/lang/String;
       7: invokevirtual #3                  // Method println:(Ljava/lang/String;)V
      10: aload_0
      11: invokevirtual #4                  // Method inc:()V
      14: return

  public void beginQuotation(org.xwiki.rendering.wikimodel.WikiParameters);
    Code:
       0: aload_0
       1: aload_1
       2: invokedynamic #17,  0             // InvokeDynamic #10:makeConcatWithConstants:(Lorg/xwiki/rendering/wikimodel/WikiParameters;)Ljava/lang/String;
       7: invokevirtual #3                  // Method println:(Ljava/lang/String;)V
      10: aload_0
      11: invokevirtual #4                  // Method inc:()V
      14: return

  public void beginQuotationLine();
    Code:
       0: aload_0
       1: ldc           #18                 // String beginQuotationLine()
       3: invokevirtual #3                  // Method println:(Ljava/lang/String;)V
       6: aload_0
       7: invokevirtual #4                  // Method inc:()V
      10: return

  public void beginSection(int, int, org.xwiki.rendering.wikimodel.WikiParameters);
    Code:
       0: aload_0
       1: iload_1
       2: invokedynamic #19,  0             // InvokeDynamic #11:makeConcatWithConstants:(I)Ljava/lang/String;
       7: invokevirtual #3                  // Method println:(Ljava/lang/String;)V
      10: aload_0
      11: invokevirtual #4                  // Method inc:()V
      14: return

  public void beginSectionContent(int, int, org.xwiki.rendering.wikimodel.WikiParameters);
    Code:
       0: aload_0
       1: iload_1
       2: invokedynamic #20,  0             // InvokeDynamic #12:makeConcatWithConstants:(I)Ljava/lang/String;
       7: invokevirtual #3                  // Method println:(Ljava/lang/String;)V
      10: aload_0
      11: invokevirtual #4                  // Method inc:()V
      14: return

  public void beginTable(org.xwiki.rendering.wikimodel.WikiParameters);
    Code:
       0: aload_0
       1: aload_1
       2: invokedynamic #21,  0             // InvokeDynamic #13:makeConcatWithConstants:(Lorg/xwiki/rendering/wikimodel/WikiParameters;)Ljava/lang/String;
       7: invokevirtual #3                  // Method println:(Ljava/lang/String;)V
      10: aload_0
      11: invokevirtual #4                  // Method inc:()V
      14: return

  public void beginTableCell(boolean, org.xwiki.rendering.wikimodel.WikiParameters);
    Code:
       0: aload_0
       1: iload_1
       2: aload_2
       3: invokedynamic #22,  0             // InvokeDynamic #14:makeConcatWithConstants:(ZLorg/xwiki/rendering/wikimodel/WikiParameters;)Ljava/lang/String;
       8: invokevirtual #3                  // Method println:(Ljava/lang/String;)V
      11: aload_0
      12: invokevirtual #4                  // Method inc:()V
      15: return

  public void beginTableRow(org.xwiki.rendering.wikimodel.WikiParameters);
    Code:
       0: aload_0
       1: aload_1
       2: invokedynamic #23,  0             // InvokeDynamic #15:makeConcatWithConstants:(Lorg/xwiki/rendering/wikimodel/WikiParameters;)Ljava/lang/String;
       7: invokevirtual #3                  // Method println:(Ljava/lang/String;)V
      10: aload_0
      11: invokevirtual #4                  // Method inc:()V
      14: return

  private void dec();
    Code:
       0: aload_0
       1: dup
       2: getfield      #24                 // Field fDepth:I
       5: iconst_1
       6: isub
       7: putfield      #24                 // Field fDepth:I
      10: return

  protected void endBlock();
    Code:
       0: aload_0
       1: invokevirtual #25                 // Method dec:()V
       4: aload_0
       5: ldc           #26                 // String endBlock()
       7: invokevirtual #3                  // Method println:(Ljava/lang/String;)V
      10: return

  public void endDefinitionDescription();
    Code:
       0: aload_0
       1: invokevirtual #25                 // Method dec:()V
       4: aload_0
       5: ldc           #27                 // String endDefinitionDescription()
       7: invokevirtual #3                  // Method println:(Ljava/lang/String;)V
      10: return

  public void endDefinitionList(org.xwiki.rendering.wikimodel.WikiParameters);
    Code:
       0: aload_0
       1: invokevirtual #25                 // Method dec:()V
       4: aload_0
       5: aload_1
       6: invokedynamic #28,  0             // InvokeDynamic #16:makeConcatWithConstants:(Lorg/xwiki/rendering/wikimodel/WikiParameters;)Ljava/lang/String;
      11: invokevirtual #3                  // Method println:(Ljava/lang/String;)V
      14: return

  public void endDefinitionTerm();
    Code:
       0: aload_0
       1: invokevirtual #25                 // Method dec:()V
       4: aload_0
       5: ldc           #29                 // String endDefinitionTerm()
       7: invokevirtual #3                  // Method println:(Ljava/lang/String;)V
      10: return

  public void endDocument(org.xwiki.rendering.wikimodel.WikiParameters);
    Code:
       0: aload_0
       1: invokevirtual #25                 // Method dec:()V
       4: aload_0
       5: aload_1
       6: invokedynamic #30,  0             // InvokeDynamic #17:makeConcatWithConstants:(Lorg/xwiki/rendering/wikimodel/WikiParameters;)Ljava/lang/String;
      11: invokevirtual #3                  // Method println:(Ljava/lang/String;)V
      14: return

  public void endFormat(org.xwiki.rendering.wikimodel.WikiFormat);
    Code:
       0: aload_0
       1: invokevirtual #25                 // Method dec:()V
       4: aload_0
       5: aload_1
       6: invokedynamic #31,  0             // InvokeDynamic #18:makeConcatWithConstants:(Lorg/xwiki/rendering/wikimodel/WikiFormat;)Ljava/lang/String;
      11: invokevirtual #3                  // Method println:(Ljava/lang/String;)V
      14: return

  public void endHeader(int, org.xwiki.rendering.wikimodel.WikiParameters);
    Code:
       0: aload_0
       1: invokevirtual #25                 // Method dec:()V
       4: aload_0
       5: iload_1
       6: aload_2
       7: invokedynamic #32,  0             // InvokeDynamic #19:makeConcatWithConstants:(ILorg/xwiki/rendering/wikimodel/WikiParameters;)Ljava/lang/String;
      12: invokevirtual #3                  // Method println:(Ljava/lang/String;)V
      15: return

  public void endInfoBlock(java.lang.String, org.xwiki.rendering.wikimodel.WikiParameters);
    Code:
       0: aload_0
       1: invokevirtual #25                 // Method dec:()V
       4: aload_0
       5: aload_1
       6: aload_2
       7: invokedynamic #33,  0             // InvokeDynamic #20:makeConcatWithConstants:(Ljava/lang/String;Lorg/xwiki/rendering/wikimodel/WikiParameters;)Ljava/lang/String;
      12: invokevirtual #3                  // Method println:(Ljava/lang/String;)V
      15: return

  public void endList(org.xwiki.rendering.wikimodel.WikiParameters, boolean);
    Code:
       0: aload_0
       1: invokevirtual #25                 // Method dec:()V
       4: aload_0
       5: aload_1
       6: iload_2
       7: invokedynamic #34,  0             // InvokeDynamic #21:makeConcatWithConstants:(Lorg/xwiki/rendering/wikimodel/WikiParameters;Z)Ljava/lang/String;
      12: invokevirtual #3                  // Method println:(Ljava/lang/String;)V
      15: return

  public void endListItem();
    Code:
       0: aload_0
       1: invokevirtual #25                 // Method dec:()V
       4: aload_0
       5: ldc           #35                 // String endListItem()
       7: invokevirtual #3                  // Method println:(Ljava/lang/String;)V
      10: return

  public void endListItem(org.xwiki.rendering.wikimodel.WikiParameters);
    Code:
       0: aload_0
       1: invokevirtual #25                 // Method dec:()V
       4: aload_0
       5: aload_1
       6: invokedynamic #36,  0             // InvokeDynamic #22:makeConcatWithConstants:(Lorg/xwiki/rendering/wikimodel/WikiParameters;)Ljava/lang/String;
      11: invokevirtual #3                  // Method println:(Ljava/lang/String;)V
      14: return

  public void endParagraph(org.xwiki.rendering.wikimodel.WikiParameters);
    Code:
       0: aload_0
       1: invokevirtual #25                 // Method dec:()V
       4: aload_0
       5: aload_1
       6: invokedynamic #37,  0             // InvokeDynamic #23:makeConcatWithConstants:(Lorg/xwiki/rendering/wikimodel/WikiParameters;)Ljava/lang/String;
      11: invokevirtual #3                  // Method println:(Ljava/lang/String;)V
      14: return

  public void endPropertyBlock(java.lang.String, boolean);
    Code:
       0: aload_0
       1: invokevirtual #25                 // Method dec:()V
       4: aload_0
       5: aload_1
       6: iload_2
       7: invokedynamic #38,  0             // InvokeDynamic #24:makeConcatWithConstants:(Ljava/lang/String;Z)Ljava/lang/String;
      12: invokevirtual #3                  // Method println:(Ljava/lang/String;)V
      15: return

  public void endPropertyInline(java.lang.String);
    Code:
       0: aload_0
       1: invokevirtual #25                 // Method dec:()V
       4: aload_0
       5: aload_1
       6: invokedynamic #39,  0             // InvokeDynamic #25:makeConcatWithConstants:(Ljava/lang/String;)Ljava/lang/String;
      11: invokevirtual #3                  // Method println:(Ljava/lang/String;)V
      14: return

  public void endQuotation(org.xwiki.rendering.wikimodel.WikiParameters);
    Code:
       0: aload_0
       1: invokevirtual #25                 // Method dec:()V
       4: aload_0
       5: aload_1
       6: invokedynamic #40,  0             // InvokeDynamic #26:makeConcatWithConstants:(Lorg/xwiki/rendering/wikimodel/WikiParameters;)Ljava/lang/String;
      11: invokevirtual #3                  // Method println:(Ljava/lang/String;)V
      14: return

  public void endQuotationLine();
    Code:
       0: aload_0
       1: invokevirtual #25                 // Method dec:()V
       4: aload_0
       5: ldc           #41                 // String endQuotationLine()
       7: invokevirtual #3                  // Method println:(Ljava/lang/String;)V
      10: return

  public void endSection(int, int, org.xwiki.rendering.wikimodel.WikiParameters);
    Code:
       0: aload_0
       1: invokevirtual #25                 // Method dec:()V
       4: aload_0
       5: iload_1
       6: invokedynamic #42,  0             // InvokeDynamic #27:makeConcatWithConstants:(I)Ljava/lang/String;
      11: invokevirtual #3                  // Method println:(Ljava/lang/String;)V
      14: return

  public void endSectionContent(int, int, org.xwiki.rendering.wikimodel.WikiParameters);
    Code:
       0: aload_0
       1: invokevirtual #25                 // Method dec:()V
       4: aload_0
       5: iload_1
       6: invokedynamic #43,  0             // InvokeDynamic #28:makeConcatWithConstants:(I)Ljava/lang/String;
      11: invokevirtual #3                  // Method println:(Ljava/lang/String;)V
      14: return

  public void endTable(org.xwiki.rendering.wikimodel.WikiParameters);
    Code:
       0: aload_0
       1: invokevirtual #25                 // Method dec:()V
       4: aload_0
       5: aload_1
       6: invokedynamic #44,  0             // InvokeDynamic #29:makeConcatWithConstants:(Lorg/xwiki/rendering/wikimodel/WikiParameters;)Ljava/lang/String;
      11: invokevirtual #3                  // Method println:(Ljava/lang/String;)V
      14: return

  public void endTableCell(boolean, org.xwiki.rendering.wikimodel.WikiParameters);
    Code:
       0: aload_0
       1: invokevirtual #25                 // Method dec:()V
       4: aload_0
       5: iload_1
       6: aload_2
       7: invokedynamic #45,  0             // InvokeDynamic #30:makeConcatWithConstants:(ZLorg/xwiki/rendering/wikimodel/WikiParameters;)Ljava/lang/String;
      12: invokevirtual #3                  // Method println:(Ljava/lang/String;)V
      15: return

  public void endTableRow(org.xwiki.rendering.wikimodel.WikiParameters);
    Code:
       0: aload_0
       1: invokevirtual #25                 // Method dec:()V
       4: aload_0
       5: aload_1
       6: invokedynamic #46,  0             // InvokeDynamic #31:makeConcatWithConstants:(Lorg/xwiki/rendering/wikimodel/WikiParameters;)Ljava/lang/String;
      11: invokevirtual #3                  // Method println:(Ljava/lang/String;)V
      14: return

  private void inc();
    Code:
       0: aload_0
       1: dup
       2: getfield      #24                 // Field fDepth:I
       5: iconst_1
       6: iadd
       7: putfield      #24                 // Field fDepth:I
      10: return

  public void onEmptyLines(int);
    Code:
       0: aload_0
       1: iload_1
       2: invokedynamic #47,  0             // InvokeDynamic #32:makeConcatWithConstants:(I)Ljava/lang/String;
       7: invokevirtual #3                  // Method println:(Ljava/lang/String;)V
      10: return

  public void onEscape(java.lang.String);
    Code:
       0: aload_0
       1: aload_1
       2: invokedynamic #48,  0             // InvokeDynamic #33:makeConcatWithConstants:(Ljava/lang/String;)Ljava/lang/String;
       7: invokevirtual #3                  // Method println:(Ljava/lang/String;)V
      10: return

  public void onExtensionBlock(java.lang.String, org.xwiki.rendering.wikimodel.WikiParameters);
    Code:
       0: aload_0
       1: aload_1
       2: aload_2
       3: invokedynamic #49,  0             // InvokeDynamic #34:makeConcatWithConstants:(Ljava/lang/String;Lorg/xwiki/rendering/wikimodel/WikiParameters;)Ljava/lang/String;
       8: invokevirtual #3                  // Method println:(Ljava/lang/String;)V
      11: return

  public void onExtensionInline(java.lang.String, org.xwiki.rendering.wikimodel.WikiParameters);
    Code:
       0: aload_0
       1: aload_1
       2: aload_2
       3: invokedynamic #50,  0             // InvokeDynamic #35:makeConcatWithConstants:(Ljava/lang/String;Lorg/xwiki/rendering/wikimodel/WikiParameters;)Ljava/lang/String;
       8: invokevirtual #3                  // Method println:(Ljava/lang/String;)V
      11: return

  public void onHorizontalLine(org.xwiki.rendering.wikimodel.WikiParameters);
    Code:
       0: aload_0
       1: aload_1
       2: invokedynamic #51,  0             // InvokeDynamic #36:makeConcatWithConstants:(Lorg/xwiki/rendering/wikimodel/WikiParameters;)Ljava/lang/String;
       7: invokevirtual #3                  // Method println:(Ljava/lang/String;)V
      10: return

  public void onLineBreak();
    Code:
       0: aload_0
       1: ldc           #52                 // String onLineBreak()
       3: invokevirtual #3                  // Method println:(Ljava/lang/String;)V
       6: return

  public void onMacroBlock(java.lang.String, org.xwiki.rendering.wikimodel.WikiParameters, java.lang.String);
    Code:
       0: aload_0
       1: aload_1
       2: aload_2
       3: aload_3
       4: invokedynamic #53,  0             // InvokeDynamic #37:makeConcatWithConstants:(Ljava/lang/String;Lorg/xwiki/rendering/wikimodel/WikiParameters;Ljava/lang/String;)Ljava/lang/String;
       9: invokevirtual #3                  // Method println:(Ljava/lang/String;)V
      12: return

  public void onMacroInline(java.lang.String, org.xwiki.rendering.wikimodel.WikiParameters, java.lang.String);
    Code:
       0: aload_0
       1: aload_1
       2: aload_2
       3: aload_3
       4: invokedynamic #54,  0             // InvokeDynamic #38:makeConcatWithConstants:(Ljava/lang/String;Lorg/xwiki/rendering/wikimodel/WikiParameters;Ljava/lang/String;)Ljava/lang/String;
       9: invokevirtual #3                  // Method println:(Ljava/lang/String;)V
      12: return

  public void onNewLine();
    Code:
       0: aload_0
       1: ldc           #55                 // String onNewLine()
       3: invokevirtual #3                  // Method println:(Ljava/lang/String;)V
       6: return

  public void onReference(java.lang.String);
    Code:
       0: aload_0
       1: aload_1
       2: invokedynamic #56,  0             // InvokeDynamic #39:makeConcatWithConstants:(Ljava/lang/String;)Ljava/lang/String;
       7: invokevirtual #3                  // Method println:(Ljava/lang/String;)V
      10: return

  public void onSpace(java.lang.String);
    Code:
       0: aload_0
       1: aload_1
       2: invokedynamic #57,  0             // InvokeDynamic #40:makeConcatWithConstants:(Ljava/lang/String;)Ljava/lang/String;
       7: invokevirtual #3                  // Method println:(Ljava/lang/String;)V
      10: return

  public void onSpecialSymbol(java.lang.String);
    Code:
       0: aload_0
       1: aload_1
       2: invokedynamic #58,  0             // InvokeDynamic #41:makeConcatWithConstants:(Ljava/lang/String;)Ljava/lang/String;
       7: invokevirtual #3                  // Method println:(Ljava/lang/String;)V
      10: return

  public void onTableCaption(java.lang.String);
    Code:
       0: aload_0
       1: aload_1
       2: invokedynamic #59,  0             // InvokeDynamic #42:makeConcatWithConstants:(Ljava/lang/String;)Ljava/lang/String;
       7: invokevirtual #3                  // Method println:(Ljava/lang/String;)V
      10: return

  public void onVerbatimBlock(java.lang.String, org.xwiki.rendering.wikimodel.WikiParameters);
    Code:
       0: aload_0
       1: aload_1
       2: invokedynamic #60,  0             // InvokeDynamic #43:makeConcatWithConstants:(Ljava/lang/String;)Ljava/lang/String;
       7: invokevirtual #3                  // Method println:(Ljava/lang/String;)V
      10: return

  public void onVerbatimInline(java.lang.String, org.xwiki.rendering.wikimodel.WikiParameters);
    Code:
       0: aload_0
       1: aload_1
       2: invokedynamic #61,  0             // InvokeDynamic #44:makeConcatWithConstants:(Ljava/lang/String;)Ljava/lang/String;
       7: invokevirtual #3                  // Method println:(Ljava/lang/String;)V
      10: return

  public void onWord(java.lang.String);
    Code:
       0: aload_0
       1: aload_1
       2: invokedynamic #62,  0             // InvokeDynamic #45:makeConcatWithConstants:(Ljava/lang/String;)Ljava/lang/String;
       7: invokevirtual #3                  // Method println:(Ljava/lang/String;)V
      10: return

  protected void println(java.lang.String);
    Code:
       0: iconst_0
       1: istore_2
       2: iload_2
       3: aload_0
       4: getfield      #24                 // Field fDepth:I
       7: if_icmpge     22
      10: aload_0
      11: ldc           #63                 // String
      13: invokespecial #64                 // Method org/xwiki/rendering/wikimodel/PrintTextListener.print:(Ljava/lang/String;)V
      16: iinc          2, 1
      19: goto          2
      22: aload_0
      23: aload_1
      24: invokespecial #65                 // Method org/xwiki/rendering/wikimodel/PrintTextListener.println:(Ljava/lang/String;)V
      27: return
}
