Compiled from "WikiReference.java"
public class org.xwiki.rendering.wikimodel.WikiReference {
  private final java.lang.String fLabel;

  private final java.lang.String fLink;

  private final org.xwiki.rendering.wikimodel.WikiParameters fParameters;

  private java.lang.String fString;

  static final boolean $assertionsDisabled;

  public org.xwiki.rendering.wikimodel.WikiReference(java.lang.String);
    Code:
       0: aload_0
       1: aload_1
       2: aconst_null
       3: aconst_null
       4: invokespecial #1                  // Method "<init>":(Ljava/lang/String;Ljava/lang/String;Lorg/xwiki/rendering/wikimodel/WikiParameters;)V
       7: return

  public org.xwiki.rendering.wikimodel.WikiReference(java.lang.String, java.lang.String);
    Code:
       0: aload_0
       1: aload_1
       2: aload_2
       3: aconst_null
       4: invokespecial #1                  // Method "<init>":(Ljava/lang/String;Ljava/lang/String;Lorg/xwiki/rendering/wikimodel/WikiParameters;)V
       7: return

  public org.xwiki.rendering.wikimodel.WikiReference(java.lang.String, java.lang.String, org.xwiki.rendering.wikimodel.WikiParameters);
    Code:
       0: aload_0
       1: invokespecial #2                  // Method java/lang/Object."<init>":()V
       4: getstatic     #3                  // Field $assertionsDisabled:Z
       7: ifne          24
      10: aload_1
      11: ifnonnull     24
      14: new           #4                  // class java/lang/AssertionError
      17: dup
      18: ldc           #5                  // String Link can not be null
      20: invokespecial #6                  // Method java/lang/AssertionError."<init>":(Ljava/lang/Object;)V
      23: athrow
      24: aload_0
      25: aload_1
      26: putfield      #7                  // Field fLink:Ljava/lang/String;
      29: aload_0
      30: aload_2
      31: putfield      #8                  // Field fLabel:Ljava/lang/String;
      34: aload_3
      35: ifnonnull     42
      38: getstatic     #9                  // Field org/xwiki/rendering/wikimodel/WikiParameters.EMPTY:Lorg/xwiki/rendering/wikimodel/WikiParameters;
      41: astore_3
      42: aload_0
      43: aload_3
      44: putfield      #10                 // Field fParameters:Lorg/xwiki/rendering/wikimodel/WikiParameters;
      47: return

  public org.xwiki.rendering.wikimodel.WikiReference(java.lang.String, org.xwiki.rendering.wikimodel.WikiParameters);
    Code:
       0: aload_0
       1: aload_1
       2: aconst_null
       3: aload_2
       4: invokespecial #1                  // Method "<init>":(Ljava/lang/String;Ljava/lang/String;Lorg/xwiki/rendering/wikimodel/WikiParameters;)V
       7: return

  public boolean equals(java.lang.Object);
    Code:
       0: aload_0
       1: aload_1
       2: if_acmpne     7
       5: iconst_1
       6: ireturn
       7: aload_1
       8: instanceof    #11                 // class org/xwiki/rendering/wikimodel/WikiReference
      11: ifne          16
      14: iconst_0
      15: ireturn
      16: aload_1
      17: checkcast     #11                 // class org/xwiki/rendering/wikimodel/WikiReference
      20: astore_2
      21: aload_0
      22: getfield      #7                  // Field fLink:Ljava/lang/String;
      25: aload_2
      26: getfield      #7                  // Field fLink:Ljava/lang/String;
      29: invokevirtual #12                 // Method java/lang/String.equals:(Ljava/lang/Object;)Z
      32: ifeq          85
      35: aload_0
      36: getfield      #8                  // Field fLabel:Ljava/lang/String;
      39: aload_2
      40: getfield      #8                  // Field fLabel:Ljava/lang/String;
      43: if_acmpeq     67
      46: aload_0
      47: getfield      #8                  // Field fLabel:Ljava/lang/String;
      50: ifnull        85
      53: aload_0
      54: getfield      #8                  // Field fLabel:Ljava/lang/String;
      57: aload_2
      58: getfield      #8                  // Field fLabel:Ljava/lang/String;
      61: invokevirtual #12                 // Method java/lang/String.equals:(Ljava/lang/Object;)Z
      64: ifeq          85
      67: aload_0
      68: getfield      #10                 // Field fParameters:Lorg/xwiki/rendering/wikimodel/WikiParameters;
      71: aload_2
      72: getfield      #10                 // Field fParameters:Lorg/xwiki/rendering/wikimodel/WikiParameters;
      75: invokevirtual #13                 // Method org/xwiki/rendering/wikimodel/WikiParameters.equals:(Ljava/lang/Object;)Z
      78: ifeq          85
      81: iconst_1
      82: goto          86
      85: iconst_0
      86: ireturn

  public java.lang.String getLabel();
    Code:
       0: aload_0
       1: getfield      #8                  // Field fLabel:Ljava/lang/String;
       4: areturn

  public java.lang.String getLink();
    Code:
       0: aload_0
       1: getfield      #7                  // Field fLink:Ljava/lang/String;
       4: areturn

  public org.xwiki.rendering.wikimodel.WikiParameters getParameters();
    Code:
       0: aload_0
       1: getfield      #10                 // Field fParameters:Lorg/xwiki/rendering/wikimodel/WikiParameters;
       4: areturn

  public int hashCode();
    Code:
       0: aload_0
       1: invokevirtual #14                 // Method toString:()Ljava/lang/String;
       4: invokevirtual #15                 // Method java/lang/String.hashCode:()I
       7: ireturn

  public java.lang.String toString();
    Code:
       0: aload_0
       1: getfield      #16                 // Field fString:Ljava/lang/String;
       4: ifnonnull     71
       7: new           #17                 // class java/lang/StringBuffer
      10: dup
      11: invokespecial #18                 // Method java/lang/StringBuffer."<init>":()V
      14: astore_1
      15: aload_1
      16: aload_0
      17: getfield      #7                  // Field fLink:Ljava/lang/String;
      20: invokevirtual #19                 // Method java/lang/StringBuffer.append:(Ljava/lang/String;)Ljava/lang/StringBuffer;
      23: pop
      24: aload_0
      25: getfield      #8                  // Field fLabel:Ljava/lang/String;
      28: ifnull        54
      31: aload_1
      32: bipush        40
      34: invokevirtual #20                 // Method java/lang/StringBuffer.append:(C)Ljava/lang/StringBuffer;
      37: pop
      38: aload_1
      39: aload_0
      40: getfield      #8                  // Field fLabel:Ljava/lang/String;
      43: invokevirtual #19                 // Method java/lang/StringBuffer.append:(Ljava/lang/String;)Ljava/lang/StringBuffer;
      46: pop
      47: aload_1
      48: bipush        41
      50: invokevirtual #20                 // Method java/lang/StringBuffer.append:(C)Ljava/lang/StringBuffer;
      53: pop
      54: aload_1
      55: aload_0
      56: getfield      #10                 // Field fParameters:Lorg/xwiki/rendering/wikimodel/WikiParameters;
      59: invokevirtual #21                 // Method java/lang/StringBuffer.append:(Ljava/lang/Object;)Ljava/lang/StringBuffer;
      62: pop
      63: aload_0
      64: aload_1
      65: invokevirtual #22                 // Method java/lang/StringBuffer.toString:()Ljava/lang/String;
      68: putfield      #16                 // Field fString:Ljava/lang/String;
      71: aload_0
      72: getfield      #16                 // Field fString:Ljava/lang/String;
      75: areturn

  static {};
    Code:
       0: ldc           #11                 // class org/xwiki/rendering/wikimodel/WikiReference
       2: invokevirtual #23                 // Method java/lang/Class.desiredAssertionStatus:()Z
       5: ifne          12
       8: iconst_1
       9: goto          13
      12: iconst_0
      13: putstatic     #3                  // Field $assertionsDisabled:Z
      16: return
}
