Compiled from "WikiParameter.java"
public class org.xwiki.rendering.wikimodel.WikiParameter {
  private java.lang.String fKey;

  private java.lang.String fStr;

  private java.lang.Boolean fValid;

  private java.lang.String fValue;

  public org.xwiki.rendering.wikimodel.WikiParameter(java.lang.String, java.lang.String);
    Code:
       0: aload_0
       1: invokespecial #1                  // Method java/lang/Object."<init>":()V
       4: aload_0
       5: aload_1
       6: putfield      #2                  // Field fKey:Ljava/lang/String;
       9: aload_0
      10: aload_2
      11: putfield      #3                  // Field fValue:Ljava/lang/String;
      14: return

  public org.xwiki.rendering.wikimodel.WikiParameter(org.xwiki.rendering.wikimodel.WikiParameter);
    Code:
       0: aload_0
       1: invokespecial #1                  // Method java/lang/Object."<init>":()V
       4: aload_0
       5: aload_1
       6: invokevirtual #4                  // Method getKey:()Ljava/lang/String;
       9: putfield      #2                  // Field fKey:Ljava/lang/String;
      12: aload_0
      13: aload_1
      14: invokevirtual #5                  // Method getValue:()Ljava/lang/String;
      17: putfield      #3                  // Field fValue:Ljava/lang/String;
      20: return

  public boolean equals(java.lang.Object);
    Code:
       0: aload_1
       1: aload_0
       2: if_acmpne     7
       5: iconst_1
       6: ireturn
       7: aload_1
       8: instanceof    #6                  // class org/xwiki/rendering/wikimodel/WikiParameter
      11: ifne          16
      14: iconst_0
      15: ireturn
      16: aload_1
      17: checkcast     #6                  // class org/xwiki/rendering/wikimodel/WikiParameter
      20: astore_2
      21: aload_0
      22: getfield      #2                  // Field fKey:Ljava/lang/String;
      25: aload_2
      26: getfield      #2                  // Field fKey:Ljava/lang/String;
      29: invokevirtual #7                  // Method java/lang/String.equals:(Ljava/lang/Object;)Z
      32: ifeq          71
      35: aload_0
      36: getfield      #3                  // Field fValue:Ljava/lang/String;
      39: aload_2
      40: getfield      #3                  // Field fValue:Ljava/lang/String;
      43: if_acmpeq     67
      46: aload_0
      47: getfield      #3                  // Field fValue:Ljava/lang/String;
      50: ifnull        71
      53: aload_0
      54: getfield      #3                  // Field fValue:Ljava/lang/String;
      57: aload_2
      58: getfield      #3                  // Field fValue:Ljava/lang/String;
      61: invokevirtual #7                  // Method java/lang/String.equals:(Ljava/lang/Object;)Z
      64: ifeq          71
      67: iconst_1
      68: goto          72
      71: iconst_0
      72: ireturn

  public java.lang.String getKey();
    Code:
       0: aload_0
       1: getfield      #2                  // Field fKey:Ljava/lang/String;
       4: areturn

  public java.lang.String getValue();
    Code:
       0: aload_0
       1: getfield      #3                  // Field fValue:Ljava/lang/String;
       4: areturn

  public int hashCode();
    Code:
       0: aload_0
       1: getfield      #2                  // Field fKey:Ljava/lang/String;
       4: invokevirtual #8                  // Method java/lang/String.hashCode:()I
       7: aload_0
       8: getfield      #3                  // Field fValue:Ljava/lang/String;
      11: ifnull        24
      14: aload_0
      15: getfield      #3                  // Field fValue:Ljava/lang/String;
      18: invokevirtual #8                  // Method java/lang/String.hashCode:()I
      21: goto          25
      24: iconst_0
      25: ixor
      26: ireturn

  public boolean isValid();
    Code:
       0: aload_0
       1: getfield      #9                  // Field fValid:Ljava/lang/Boolean;
       4: ifnonnull     185
       7: aload_0
       8: getfield      #2                  // Field fKey:Ljava/lang/String;
      11: ifnull        24
      14: aload_0
      15: getfield      #2                  // Field fKey:Ljava/lang/String;
      18: invokevirtual #10                 // Method java/lang/String.length:()I
      21: goto          25
      24: iconst_0
      25: istore_1
      26: iload_1
      27: ifle          34
      30: iconst_1
      31: goto          35
      34: iconst_0
      35: istore_2
      36: iconst_0
      37: istore_3
      38: iconst_0
      39: istore        4
      41: iload_2
      42: ifeq          168
      45: iload         4
      47: iload_1
      48: if_icmpge     168
      51: aload_0
      52: getfield      #2                  // Field fKey:Ljava/lang/String;
      55: iload         4
      57: invokevirtual #11                 // Method java/lang/String.charAt:(I)C
      60: istore        5
      62: iload         5
      64: bipush        58
      66: if_icmpne     97
      69: iload_3
      70: ifne          90
      73: iload         4
      75: ifle          90
      78: iload         4
      80: iload_1
      81: iconst_1
      82: isub
      83: if_icmpge     90
      86: iconst_1
      87: goto          91
      90: iconst_0
      91: istore_2
      92: iconst_1
      93: istore_3
      94: goto          162
      97: iload         5
      99: bipush        46
     101: if_icmpeq     111
     104: iload         5
     106: bipush        45
     108: if_icmpne     133
     111: iload         4
     113: ifle          128
     116: iload         4
     118: iload_1
     119: iconst_1
     120: isub
     121: if_icmpge     128
     124: iconst_1
     125: goto          129
     128: iconst_0
     129: istore_2
     130: goto          162
     133: iload_2
     134: iload         4
     136: ifne          147
     139: iload         5
     141: invokestatic  #12                 // Method java/lang/Character.isLetter:(C)Z
     144: ifne          155
     147: iload         5
     149: invokestatic  #13                 // Method java/lang/Character.isLetterOrDigit:(C)Z
     152: ifeq          159
     155: iconst_1
     156: goto          160
     159: iconst_0
     160: iand
     161: istore_2
     162: iinc          4, 1
     165: goto          41
     168: aload_0
     169: iload_2
     170: ifeq          179
     173: getstatic     #14                 // Field java/lang/Boolean.TRUE:Ljava/lang/Boolean;
     176: goto          182
     179: getstatic     #15                 // Field java/lang/Boolean.FALSE:Ljava/lang/Boolean;
     182: putfield      #9                  // Field fValid:Ljava/lang/Boolean;
     185: aload_0
     186: getfield      #9                  // Field fValid:Ljava/lang/Boolean;
     189: getstatic     #14                 // Field java/lang/Boolean.TRUE:Ljava/lang/Boolean;
     192: if_acmpne     199
     195: iconst_1
     196: goto          200
     199: iconst_0
     200: ireturn

  public java.lang.String toString();
    Code:
       0: aload_0
       1: getfield      #16                 // Field fStr:Ljava/lang/String;
       4: ifnonnull     27
       7: aload_0
       8: aload_0
       9: getfield      #2                  // Field fKey:Ljava/lang/String;
      12: aload_0
      13: getfield      #3                  // Field fValue:Ljava/lang/String;
      16: invokestatic  #17                 // Method org/xwiki/rendering/wikimodel/WikiPageUtil.escapeXmlAttribute:(Ljava/lang/String;)Ljava/lang/String;
      19: invokedynamic #18,  0             // InvokeDynamic #0:makeConcatWithConstants:(Ljava/lang/String;Ljava/lang/String;)Ljava/lang/String;
      24: putfield      #16                 // Field fStr:Ljava/lang/String;
      27: aload_0
      28: getfield      #16                 // Field fStr:Ljava/lang/String;
      31: areturn
}
