Compiled from "DatasetPrefixStorageInMemory.java"
public class org.apache.jena.sparql.core.mem.DatasetPrefixStorageInMemory implements org.apache.jena.sparql.core.DatasetPrefixStorage {
  private java.util.Map<java.lang.String, org.apache.jena.shared.PrefixMapping> prefixMappings;

  public org.apache.jena.sparql.core.mem.DatasetPrefixStorageInMemory();
    Code:
       0: aload_0
       1: invokespecial #1                  // Method java/lang/Object."<init>":()V
       4: aload_0
       5: new           #2                  // class java/util/concurrent/ConcurrentHashMap
       8: dup
       9: invokespecial #3                  // Method java/util/concurrent/ConcurrentHashMap."<init>":()V
      12: putfield      #4                  // Field prefixMappings:Ljava/util/Map;
      15: return

  private java.util.Map<java.lang.String, org.apache.jena.shared.PrefixMapping> prefixMappings();
    Code:
       0: aload_0
       1: getfield      #4                  // Field prefixMappings:Ljava/util/Map;
       4: areturn

  public void close();
    Code:
       0: aload_0
       1: aconst_null
       2: putfield      #4                  // Field prefixMappings:Ljava/util/Map;
       5: return

  public void sync();
    Code:
       0: return

  public java.util.Set<java.lang.String> graphNames();
    Code:
       0: aload_0
       1: invokespecial #5                  // Method prefixMappings:()Ljava/util/Map;
       4: invokeinterface #6,  1            // InterfaceMethod java/util/Map.keySet:()Ljava/util/Set;
       9: areturn

  public java.lang.String readPrefix(java.lang.String, java.lang.String);
    Code:
       0: aload_0
       1: aload_1
       2: invokevirtual #7                  // Method getPrefixMapping:(Ljava/lang/String;)Lorg/apache/jena/shared/PrefixMapping;
       5: aload_2
       6: invokeinterface #8,  2            // InterfaceMethod org/apache/jena/shared/PrefixMapping.getNsPrefixURI:(Ljava/lang/String;)Ljava/lang/String;
      11: areturn

  public java.lang.String readByURI(java.lang.String, java.lang.String);
    Code:
       0: aload_0
       1: aload_1
       2: invokevirtual #7                  // Method getPrefixMapping:(Ljava/lang/String;)Lorg/apache/jena/shared/PrefixMapping;
       5: aload_2
       6: invokeinterface #9,  2            // InterfaceMethod org/apache/jena/shared/PrefixMapping.getNsURIPrefix:(Ljava/lang/String;)Ljava/lang/String;
      11: areturn

  public java.util.Map<java.lang.String, java.lang.String> readPrefixMap(java.lang.String);
    Code:
       0: aload_0
       1: aload_1
       2: invokevirtual #7                  // Method getPrefixMapping:(Ljava/lang/String;)Lorg/apache/jena/shared/PrefixMapping;
       5: invokeinterface #10,  1           // InterfaceMethod org/apache/jena/shared/PrefixMapping.getNsPrefixMap:()Ljava/util/Map;
      10: areturn

  public void insertPrefix(java.lang.String, java.lang.String, java.lang.String);
    Code:
       0: aload_0
       1: aload_1
       2: invokevirtual #7                  // Method getPrefixMapping:(Ljava/lang/String;)Lorg/apache/jena/shared/PrefixMapping;
       5: aload_2
       6: aload_3
       7: invokeinterface #11,  3           // InterfaceMethod org/apache/jena/shared/PrefixMapping.setNsPrefix:(Ljava/lang/String;Ljava/lang/String;)Lorg/apache/jena/shared/PrefixMapping;
      12: pop
      13: return

  public void loadPrefixMapping(java.lang.String, org.apache.jena.shared.PrefixMapping);
    Code:
       0: aload_0
       1: aload_1
       2: invokevirtual #7                  // Method getPrefixMapping:(Ljava/lang/String;)Lorg/apache/jena/shared/PrefixMapping;
       5: aload_2
       6: invokeinterface #12,  2           // InterfaceMethod org/apache/jena/shared/PrefixMapping.setNsPrefixes:(Lorg/apache/jena/shared/PrefixMapping;)Lorg/apache/jena/shared/PrefixMapping;
      11: pop
      12: return

  public void removeFromPrefixMap(java.lang.String, java.lang.String);
    Code:
       0: aload_0
       1: aload_1
       2: invokevirtual #7                  // Method getPrefixMapping:(Ljava/lang/String;)Lorg/apache/jena/shared/PrefixMapping;
       5: aload_2
       6: invokeinterface #13,  2           // InterfaceMethod org/apache/jena/shared/PrefixMapping.removeNsPrefix:(Ljava/lang/String;)Lorg/apache/jena/shared/PrefixMapping;
      11: pop
      12: return

  public void removeAllFromPrefixMap(java.lang.String);
    Code:
       0: aload_0
       1: aload_1
       2: invokevirtual #7                  // Method getPrefixMapping:(Ljava/lang/String;)Lorg/apache/jena/shared/PrefixMapping;
       5: invokeinterface #14,  1           // InterfaceMethod org/apache/jena/shared/PrefixMapping.clearNsPrefixMap:()Lorg/apache/jena/shared/PrefixMapping;
      10: pop
      11: return

  public org.apache.jena.shared.PrefixMapping getPrefixMapping();
    Code:
       0: aload_0
       1: getstatic     #15                 // Field org/apache/jena/sparql/core/Quad.defaultGraphIRI:Lorg/apache/jena/graph/Node;
       4: invokevirtual #16                 // Method org/apache/jena/graph/Node.getURI:()Ljava/lang/String;
       7: invokevirtual #7                  // Method getPrefixMapping:(Ljava/lang/String;)Lorg/apache/jena/shared/PrefixMapping;
      10: areturn

  public org.apache.jena.shared.PrefixMapping getPrefixMapping(java.lang.String);
    Code:
       0: aload_0
       1: invokespecial #5                  // Method prefixMappings:()Ljava/util/Map;
       4: aload_1
       5: invokedynamic #17,  0             // InvokeDynamic #0:apply:()Ljava/util/function/Function;
      10: invokeinterface #18,  3           // InterfaceMethod java/util/Map.computeIfAbsent:(Ljava/lang/Object;Ljava/util/function/Function;)Ljava/lang/Object;
      15: checkcast     #19                 // class org/apache/jena/shared/PrefixMapping
      18: areturn

  private static org.apache.jena.shared.PrefixMapping lambda$getPrefixMapping$0(java.lang.String);
    Code:
       0: new           #20                 // class org/apache/jena/shared/impl/PrefixMappingImpl
       3: dup
       4: invokespecial #21                 // Method org/apache/jena/shared/impl/PrefixMappingImpl."<init>":()V
       7: areturn
}
