Compiled from "OrderedTupleTable.java"
public abstract class org.apache.jena.sparql.core.mem.OrderedTupleTable<TupleType, ConsumerType> implements org.apache.jena.sparql.core.mem.TupleTable<TupleType> {
  protected final org.apache.jena.atlas.lib.tuple.TupleMap order;

  protected final org.apache.jena.atlas.lib.tuple.TupleMap reverse;

  public org.apache.jena.sparql.core.mem.OrderedTupleTable(org.apache.jena.atlas.lib.tuple.TupleMap);
    Code:
       0: aload_0
       1: invokespecial #1                  // Method java/lang/Object."<init>":()V
       4: aload_0
       5: aload_1
       6: putfield      #2                  // Field order:Lorg/apache/jena/atlas/lib/tuple/TupleMap;
       9: aload_0
      10: aload_1
      11: invokevirtual #3                  // Method org/apache/jena/atlas/lib/tuple/TupleMap.reverse:()Lorg/apache/jena/atlas/lib/tuple/TupleMap;
      14: putfield      #4                  // Field reverse:Lorg/apache/jena/atlas/lib/tuple/TupleMap;
      17: return

  protected abstract ConsumerType add();

  protected abstract ConsumerType delete();

  protected java.util.function.Consumer<org.apache.jena.sparql.core.Quad> map(org.apache.jena.atlas.lib.tuple.TConsumer4<org.apache.jena.graph.Node>);
    Code:
       0: aload_0
       1: aload_1
       2: invokedynamic #5,  0              // InvokeDynamic #0:accept:(Lorg/apache/jena/sparql/core/mem/OrderedTupleTable;Lorg/apache/jena/atlas/lib/tuple/TConsumer4;)Ljava/util/function/Consumer;
       7: areturn

  protected <X> org.apache.jena.atlas.lib.tuple.TFunction4<org.apache.jena.graph.Node, X> map(org.apache.jena.atlas.lib.tuple.TFunction4<org.apache.jena.graph.Node, X>);
    Code:
       0: aload_0
       1: aload_1
       2: invokedynamic #6,  0              // InvokeDynamic #1:apply:(Lorg/apache/jena/sparql/core/mem/OrderedTupleTable;Lorg/apache/jena/atlas/lib/tuple/TFunction4;)Lorg/apache/jena/atlas/lib/tuple/TFunction4;
       7: areturn

  protected org.apache.jena.sparql.core.Quad unmap(org.apache.jena.graph.Node, org.apache.jena.graph.Node, org.apache.jena.graph.Node, org.apache.jena.graph.Node);
    Code:
       0: aload_0
       1: getfield      #4                  // Field reverse:Lorg/apache/jena/atlas/lib/tuple/TupleMap;
       4: aload_1
       5: aload_2
       6: aload_3
       7: aload         4
       9: invokedynamic #7,  0              // InvokeDynamic #2:apply:()Lorg/apache/jena/atlas/lib/tuple/TFunction4;
      14: invokestatic  #8                  // Method apply:(Lorg/apache/jena/atlas/lib/tuple/TupleMap;Ljava/lang/Object;Ljava/lang/Object;Ljava/lang/Object;Ljava/lang/Object;Lorg/apache/jena/atlas/lib/tuple/TFunction4;)Ljava/lang/Object;
      17: checkcast     #9                  // class org/apache/jena/sparql/core/Quad
      20: areturn

  protected java.util.function.Consumer<org.apache.jena.graph.Triple> map(org.apache.jena.atlas.lib.tuple.TConsumer3<org.apache.jena.graph.Node>);
    Code:
       0: aload_0
       1: aload_1
       2: invokedynamic #10,  0             // InvokeDynamic #3:accept:(Lorg/apache/jena/sparql/core/mem/OrderedTupleTable;Lorg/apache/jena/atlas/lib/tuple/TConsumer3;)Ljava/util/function/Consumer;
       7: areturn

  protected <T, X> org.apache.jena.atlas.lib.tuple.TFunction3<T, X> map(org.apache.jena.atlas.lib.tuple.TFunction3<T, X>);
    Code:
       0: aload_0
       1: aload_1
       2: invokedynamic #11,  0             // InvokeDynamic #4:apply:(Lorg/apache/jena/sparql/core/mem/OrderedTupleTable;Lorg/apache/jena/atlas/lib/tuple/TFunction3;)Lorg/apache/jena/atlas/lib/tuple/TFunction3;
       7: areturn

  protected org.apache.jena.graph.Triple unmap(org.apache.jena.graph.Node, org.apache.jena.graph.Node, org.apache.jena.graph.Node);
    Code:
       0: aload_0
       1: getfield      #4                  // Field reverse:Lorg/apache/jena/atlas/lib/tuple/TupleMap;
       4: aload_1
       5: aload_2
       6: aload_3
       7: invokedynamic #12,  0             // InvokeDynamic #5:apply:()Lorg/apache/jena/atlas/lib/tuple/TFunction3;
      12: invokestatic  #13                 // Method apply:(Lorg/apache/jena/atlas/lib/tuple/TupleMap;Ljava/lang/Object;Ljava/lang/Object;Ljava/lang/Object;Lorg/apache/jena/atlas/lib/tuple/TFunction3;)Ljava/lang/Object;
      15: checkcast     #14                 // class org/apache/jena/graph/Triple
      18: areturn

  private static <X> X get(int, X, X, X);
    Code:
       0: iload_0
       1: tableswitch   { // 0 to 2
                     0: 28
                     1: 30
                     2: 32
               default: 34
          }
      28: aload_1
      29: areturn
      30: aload_2
      31: areturn
      32: aload_3
      33: areturn
      34: new           #15                 // class java/lang/IndexOutOfBoundsException
      37: dup
      38: new           #16                 // class java/lang/StringBuilder
      41: dup
      42: invokespecial #17                 // Method java/lang/StringBuilder."<init>":()V
      45: ldc           #18                 // String Triples have components 0, 1, 2 but index =
      47: invokevirtual #19                 // Method java/lang/StringBuilder.append:(Ljava/lang/String;)Ljava/lang/StringBuilder;
      50: iload_0
      51: invokevirtual #20                 // Method java/lang/StringBuilder.append:(I)Ljava/lang/StringBuilder;
      54: ldc           #21                 // String !
      56: invokevirtual #19                 // Method java/lang/StringBuilder.append:(Ljava/lang/String;)Ljava/lang/StringBuilder;
      59: invokevirtual #22                 // Method java/lang/StringBuilder.toString:()Ljava/lang/String;
      62: invokespecial #23                 // Method java/lang/IndexOutOfBoundsException."<init>":(Ljava/lang/String;)V
      65: athrow

  private static <X> X get(int, X, X, X, X);
    Code:
       0: iload_0
       1: tableswitch   { // 0 to 3
                     0: 32
                     1: 34
                     2: 36
                     3: 38
               default: 41
          }
      32: aload_1
      33: areturn
      34: aload_2
      35: areturn
      36: aload_3
      37: areturn
      38: aload         4
      40: areturn
      41: new           #15                 // class java/lang/IndexOutOfBoundsException
      44: dup
      45: new           #16                 // class java/lang/StringBuilder
      48: dup
      49: invokespecial #17                 // Method java/lang/StringBuilder."<init>":()V
      52: ldc           #24                 // String Quads have components 0, 1, 2, 3 but index =
      54: invokevirtual #19                 // Method java/lang/StringBuilder.append:(Ljava/lang/String;)Ljava/lang/StringBuilder;
      57: iload_0
      58: invokevirtual #20                 // Method java/lang/StringBuilder.append:(I)Ljava/lang/StringBuilder;
      61: ldc           #21                 // String !
      63: invokevirtual #19                 // Method java/lang/StringBuilder.append:(Ljava/lang/String;)Ljava/lang/StringBuilder;
      66: invokevirtual #22                 // Method java/lang/StringBuilder.toString:()Ljava/lang/String;
      69: invokespecial #23                 // Method java/lang/IndexOutOfBoundsException."<init>":(Ljava/lang/String;)V
      72: athrow

  private static <X, Z> Z apply(org.apache.jena.atlas.lib.tuple.TupleMap, X, X, X, X, org.apache.jena.atlas.lib.tuple.TFunction4<X, Z>);
    Code:
       0: aload_0
       1: iconst_0
       2: invokevirtual #25                 // Method org/apache/jena/atlas/lib/tuple/TupleMap.mapIdx:(I)I
       5: aload_1
       6: aload_2
       7: aload_3
       8: aload         4
      10: invokestatic  #26                 // Method get:(ILjava/lang/Object;Ljava/lang/Object;Ljava/lang/Object;Ljava/lang/Object;)Ljava/lang/Object;
      13: astore        6
      15: aload_0
      16: iconst_1
      17: invokevirtual #25                 // Method org/apache/jena/atlas/lib/tuple/TupleMap.mapIdx:(I)I
      20: aload_1
      21: aload_2
      22: aload_3
      23: aload         4
      25: invokestatic  #26                 // Method get:(ILjava/lang/Object;Ljava/lang/Object;Ljava/lang/Object;Ljava/lang/Object;)Ljava/lang/Object;
      28: astore        7
      30: aload_0
      31: iconst_2
      32: invokevirtual #25                 // Method org/apache/jena/atlas/lib/tuple/TupleMap.mapIdx:(I)I
      35: aload_1
      36: aload_2
      37: aload_3
      38: aload         4
      40: invokestatic  #26                 // Method get:(ILjava/lang/Object;Ljava/lang/Object;Ljava/lang/Object;Ljava/lang/Object;)Ljava/lang/Object;
      43: astore        8
      45: aload_0
      46: iconst_3
      47: invokevirtual #25                 // Method org/apache/jena/atlas/lib/tuple/TupleMap.mapIdx:(I)I
      50: aload_1
      51: aload_2
      52: aload_3
      53: aload         4
      55: invokestatic  #26                 // Method get:(ILjava/lang/Object;Ljava/lang/Object;Ljava/lang/Object;Ljava/lang/Object;)Ljava/lang/Object;
      58: astore        9
      60: aload         5
      62: aload         6
      64: aload         7
      66: aload         8
      68: aload         9
      70: invokeinterface #27,  5           // InterfaceMethod org/apache/jena/atlas/lib/tuple/TFunction4.apply:(Ljava/lang/Object;Ljava/lang/Object;Ljava/lang/Object;Ljava/lang/Object;)Ljava/lang/Object;
      75: areturn

  private static <X, Z> Z apply(org.apache.jena.atlas.lib.tuple.TupleMap, X, X, X, org.apache.jena.atlas.lib.tuple.TFunction3<X, Z>);
    Code:
       0: aload_0
       1: iconst_0
       2: invokevirtual #25                 // Method org/apache/jena/atlas/lib/tuple/TupleMap.mapIdx:(I)I
       5: aload_1
       6: aload_2
       7: aload_3
       8: invokestatic  #28                 // Method get:(ILjava/lang/Object;Ljava/lang/Object;Ljava/lang/Object;)Ljava/lang/Object;
      11: astore        5
      13: aload_0
      14: iconst_1
      15: invokevirtual #25                 // Method org/apache/jena/atlas/lib/tuple/TupleMap.mapIdx:(I)I
      18: aload_1
      19: aload_2
      20: aload_3
      21: invokestatic  #28                 // Method get:(ILjava/lang/Object;Ljava/lang/Object;Ljava/lang/Object;)Ljava/lang/Object;
      24: astore        6
      26: aload_0
      27: iconst_2
      28: invokevirtual #25                 // Method org/apache/jena/atlas/lib/tuple/TupleMap.mapIdx:(I)I
      31: aload_1
      32: aload_2
      33: aload_3
      34: invokestatic  #28                 // Method get:(ILjava/lang/Object;Ljava/lang/Object;Ljava/lang/Object;)Ljava/lang/Object;
      37: astore        7
      39: aload         4
      41: aload         5
      43: aload         6
      45: aload         7
      47: invokeinterface #29,  4           // InterfaceMethod org/apache/jena/atlas/lib/tuple/TFunction3.apply:(Ljava/lang/Object;Ljava/lang/Object;Ljava/lang/Object;)Ljava/lang/Object;
      52: areturn

  private java.lang.Object lambda$map$3(org.apache.jena.atlas.lib.tuple.TFunction3, java.lang.Object, java.lang.Object, java.lang.Object);
    Code:
       0: aload_0
       1: getfield      #2                  // Field order:Lorg/apache/jena/atlas/lib/tuple/TupleMap;
       4: aload_2
       5: aload_3
       6: aload         4
       8: aload_1
       9: invokestatic  #13                 // Method apply:(Lorg/apache/jena/atlas/lib/tuple/TupleMap;Ljava/lang/Object;Ljava/lang/Object;Ljava/lang/Object;Lorg/apache/jena/atlas/lib/tuple/TFunction3;)Ljava/lang/Object;
      12: areturn

  private void lambda$map$2(org.apache.jena.atlas.lib.tuple.TConsumer3, org.apache.jena.graph.Triple);
    Code:
       0: aload_2
       1: invokevirtual #30                 // Method org/apache/jena/graph/Triple.getSubject:()Lorg/apache/jena/graph/Node;
       4: astore_3
       5: aload_2
       6: invokevirtual #31                 // Method org/apache/jena/graph/Triple.getPredicate:()Lorg/apache/jena/graph/Node;
       9: astore        4
      11: aload_2
      12: invokevirtual #32                 // Method org/apache/jena/graph/Triple.getObject:()Lorg/apache/jena/graph/Node;
      15: astore        5
      17: aload_0
      18: getfield      #2                  // Field order:Lorg/apache/jena/atlas/lib/tuple/TupleMap;
      21: iconst_0
      22: invokevirtual #25                 // Method org/apache/jena/atlas/lib/tuple/TupleMap.mapIdx:(I)I
      25: aload_3
      26: aload         4
      28: aload         5
      30: invokestatic  #28                 // Method get:(ILjava/lang/Object;Ljava/lang/Object;Ljava/lang/Object;)Ljava/lang/Object;
      33: checkcast     #33                 // class org/apache/jena/graph/Node
      36: astore        6
      38: aload_0
      39: getfield      #2                  // Field order:Lorg/apache/jena/atlas/lib/tuple/TupleMap;
      42: iconst_1
      43: invokevirtual #25                 // Method org/apache/jena/atlas/lib/tuple/TupleMap.mapIdx:(I)I
      46: aload_3
      47: aload         4
      49: aload         5
      51: invokestatic  #28                 // Method get:(ILjava/lang/Object;Ljava/lang/Object;Ljava/lang/Object;)Ljava/lang/Object;
      54: checkcast     #33                 // class org/apache/jena/graph/Node
      57: astore        7
      59: aload_0
      60: getfield      #2                  // Field order:Lorg/apache/jena/atlas/lib/tuple/TupleMap;
      63: iconst_2
      64: invokevirtual #25                 // Method org/apache/jena/atlas/lib/tuple/TupleMap.mapIdx:(I)I
      67: aload_3
      68: aload         4
      70: aload         5
      72: invokestatic  #28                 // Method get:(ILjava/lang/Object;Ljava/lang/Object;Ljava/lang/Object;)Ljava/lang/Object;
      75: checkcast     #33                 // class org/apache/jena/graph/Node
      78: astore        8
      80: aload_1
      81: aload         6
      83: aload         7
      85: aload         8
      87: invokeinterface #34,  4           // InterfaceMethod org/apache/jena/atlas/lib/tuple/TConsumer3.accept:(Ljava/lang/Object;Ljava/lang/Object;Ljava/lang/Object;)V
      92: return

  private java.lang.Object lambda$map$1(org.apache.jena.atlas.lib.tuple.TFunction4, org.apache.jena.graph.Node, org.apache.jena.graph.Node, org.apache.jena.graph.Node, org.apache.jena.graph.Node);
    Code:
       0: aload_0
       1: getfield      #2                  // Field order:Lorg/apache/jena/atlas/lib/tuple/TupleMap;
       4: aload_2
       5: aload_3
       6: aload         4
       8: aload         5
      10: aload_1
      11: invokestatic  #8                  // Method apply:(Lorg/apache/jena/atlas/lib/tuple/TupleMap;Ljava/lang/Object;Ljava/lang/Object;Ljava/lang/Object;Ljava/lang/Object;Lorg/apache/jena/atlas/lib/tuple/TFunction4;)Ljava/lang/Object;
      14: areturn

  private void lambda$map$0(org.apache.jena.atlas.lib.tuple.TConsumer4, org.apache.jena.sparql.core.Quad);
    Code:
       0: aload_2
       1: invokevirtual #35                 // Method org/apache/jena/sparql/core/Quad.getGraph:()Lorg/apache/jena/graph/Node;
       4: astore_3
       5: aload_2
       6: invokevirtual #36                 // Method org/apache/jena/sparql/core/Quad.getSubject:()Lorg/apache/jena/graph/Node;
       9: astore        4
      11: aload_2
      12: invokevirtual #37                 // Method org/apache/jena/sparql/core/Quad.getPredicate:()Lorg/apache/jena/graph/Node;
      15: astore        5
      17: aload_2
      18: invokevirtual #38                 // Method org/apache/jena/sparql/core/Quad.getObject:()Lorg/apache/jena/graph/Node;
      21: astore        6
      23: aload_0
      24: getfield      #2                  // Field order:Lorg/apache/jena/atlas/lib/tuple/TupleMap;
      27: iconst_0
      28: invokevirtual #25                 // Method org/apache/jena/atlas/lib/tuple/TupleMap.mapIdx:(I)I
      31: aload_3
      32: aload         4
      34: aload         5
      36: aload         6
      38: invokestatic  #26                 // Method get:(ILjava/lang/Object;Ljava/lang/Object;Ljava/lang/Object;Ljava/lang/Object;)Ljava/lang/Object;
      41: checkcast     #33                 // class org/apache/jena/graph/Node
      44: astore        7
      46: aload_0
      47: getfield      #2                  // Field order:Lorg/apache/jena/atlas/lib/tuple/TupleMap;
      50: iconst_1
      51: invokevirtual #25                 // Method org/apache/jena/atlas/lib/tuple/TupleMap.mapIdx:(I)I
      54: aload_3
      55: aload         4
      57: aload         5
      59: aload         6
      61: invokestatic  #26                 // Method get:(ILjava/lang/Object;Ljava/lang/Object;Ljava/lang/Object;Ljava/lang/Object;)Ljava/lang/Object;
      64: checkcast     #33                 // class org/apache/jena/graph/Node
      67: astore        8
      69: aload_0
      70: getfield      #2                  // Field order:Lorg/apache/jena/atlas/lib/tuple/TupleMap;
      73: iconst_2
      74: invokevirtual #25                 // Method org/apache/jena/atlas/lib/tuple/TupleMap.mapIdx:(I)I
      77: aload_3
      78: aload         4
      80: aload         5
      82: aload         6
      84: invokestatic  #26                 // Method get:(ILjava/lang/Object;Ljava/lang/Object;Ljava/lang/Object;Ljava/lang/Object;)Ljava/lang/Object;
      87: checkcast     #33                 // class org/apache/jena/graph/Node
      90: astore        9
      92: aload_0
      93: getfield      #2                  // Field order:Lorg/apache/jena/atlas/lib/tuple/TupleMap;
      96: iconst_3
      97: invokevirtual #25                 // Method org/apache/jena/atlas/lib/tuple/TupleMap.mapIdx:(I)I
     100: aload_3
     101: aload         4
     103: aload         5
     105: aload         6
     107: invokestatic  #26                 // Method get:(ILjava/lang/Object;Ljava/lang/Object;Ljava/lang/Object;Ljava/lang/Object;)Ljava/lang/Object;
     110: checkcast     #33                 // class org/apache/jena/graph/Node
     113: astore        10
     115: aload_1
     116: aload         7
     118: aload         8
     120: aload         9
     122: aload         10
     124: invokeinterface #39,  5           // InterfaceMethod org/apache/jena/atlas/lib/tuple/TConsumer4.accept:(Ljava/lang/Object;Ljava/lang/Object;Ljava/lang/Object;Ljava/lang/Object;)V
     129: return
}
