Compiled from "JpaParameters.java"
class org.springframework.data.jpa.repository.query.JpaParameters$JpaParameter extends org.springframework.data.repository.query.Parameter {
  private final org.springframework.data.jpa.repository.Temporal annotation;

  private javax.persistence.TemporalType temporalType;

  org.springframework.data.jpa.repository.query.JpaParameters$JpaParameter(org.springframework.core.MethodParameter);
    Code:
       0: aload_0
       1: aload_1
       2: invokespecial #1                  // Method org/springframework/data/repository/query/Parameter."<init>":(Lorg/springframework/core/MethodParameter;)V
       5: aload_0
       6: aload_1
       7: ldc           #2                  // class org/springframework/data/jpa/repository/Temporal
       9: invokevirtual #3                  // Method org/springframework/core/MethodParameter.getParameterAnnotation:(Ljava/lang/Class;)Ljava/lang/annotation/Annotation;
      12: checkcast     #2                  // class org/springframework/data/jpa/repository/Temporal
      15: putfield      #4                  // Field annotation:Lorg/springframework/data/jpa/repository/Temporal;
      18: aload_0
      19: aconst_null
      20: putfield      #5                  // Field temporalType:Ljavax/persistence/TemporalType;
      23: aload_0
      24: invokespecial #6                  // Method isDateParameter:()Z
      27: ifne          68
      30: aload_0
      31: invokespecial #7                  // Method hasTemporalParamAnnotation:()Z
      34: ifeq          68
      37: new           #8                  // class java/lang/IllegalArgumentException
      40: dup
      41: new           #9                  // class java/lang/StringBuilder
      44: dup
      45: invokespecial #10                 // Method java/lang/StringBuilder."<init>":()V
      48: ldc           #2                  // class org/springframework/data/jpa/repository/Temporal
      50: invokevirtual #11                 // Method java/lang/Class.getSimpleName:()Ljava/lang/String;
      53: invokevirtual #12                 // Method java/lang/StringBuilder.append:(Ljava/lang/String;)Ljava/lang/StringBuilder;
      56: ldc           #13                 // String  annotation is only allowed on Date parameter!
      58: invokevirtual #12                 // Method java/lang/StringBuilder.append:(Ljava/lang/String;)Ljava/lang/StringBuilder;
      61: invokevirtual #14                 // Method java/lang/StringBuilder.toString:()Ljava/lang/String;
      64: invokespecial #15                 // Method java/lang/IllegalArgumentException."<init>":(Ljava/lang/String;)V
      67: athrow
      68: return

  public boolean isBindable();
    Code:
       0: aload_0
       1: invokespecial #16                 // Method org/springframework/data/repository/query/Parameter.isBindable:()Z
       4: ifne          14
       7: aload_0
       8: invokevirtual #17                 // Method isTemporalParameter:()Z
      11: ifeq          18
      14: iconst_1
      15: goto          19
      18: iconst_0
      19: ireturn

  public boolean isTemporalParameter();
    Code:
       0: aload_0
       1: invokespecial #6                  // Method isDateParameter:()Z
       4: ifeq          18
       7: aload_0
       8: invokespecial #7                  // Method hasTemporalParamAnnotation:()Z
      11: ifeq          18
      14: iconst_1
      15: goto          19
      18: iconst_0
      19: ireturn

  public javax.persistence.TemporalType getTemporalType();
    Code:
       0: aload_0
       1: getfield      #5                  // Field temporalType:Ljavax/persistence/TemporalType;
       4: ifnonnull     31
       7: aload_0
       8: aload_0
       9: getfield      #4                  // Field annotation:Lorg/springframework/data/jpa/repository/Temporal;
      12: ifnonnull     19
      15: aconst_null
      16: goto          28
      19: aload_0
      20: getfield      #4                  // Field annotation:Lorg/springframework/data/jpa/repository/Temporal;
      23: invokeinterface #18,  1           // InterfaceMethod org/springframework/data/jpa/repository/Temporal.value:()Ljavax/persistence/TemporalType;
      28: putfield      #5                  // Field temporalType:Ljavax/persistence/TemporalType;
      31: aload_0
      32: getfield      #5                  // Field temporalType:Ljavax/persistence/TemporalType;
      35: areturn

  private boolean hasTemporalParamAnnotation();
    Code:
       0: aload_0
       1: getfield      #4                  // Field annotation:Lorg/springframework/data/jpa/repository/Temporal;
       4: ifnull        11
       7: iconst_1
       8: goto          12
      11: iconst_0
      12: ireturn

  private boolean isDateParameter();
    Code:
       0: aload_0
       1: invokevirtual #19                 // Method getType:()Ljava/lang/Class;
       4: ldc           #20                 // class java/util/Date
       6: invokevirtual #21                 // Method java/lang/Object.equals:(Ljava/lang/Object;)Z
       9: ireturn
}
