Compiled from "ListenerFactoryBeanManagerExtendedImpl.java"
public class org.hibernate.jpa.event.internal.jpa.ListenerFactoryBeanManagerExtendedImpl implements org.hibernate.jpa.event.spi.jpa.ListenerFactory,org.hibernate.jpa.event.spi.jpa.ExtendedBeanManager$LifecycleListener {
  private static final org.jboss.logging.Logger log;

  private final java.util.Map<java.lang.Class, org.hibernate.jpa.event.internal.jpa.ListenerFactoryBeanManagerExtendedImpl$ListenerImpl> listenerMap;

  public static org.hibernate.jpa.event.internal.jpa.ListenerFactoryBeanManagerExtendedImpl fromBeanManagerReference(java.lang.Object);
    Code:
       0: ldc           #1                  // class org/hibernate/jpa/event/spi/jpa/ExtendedBeanManager
       2: aload_0
       3: invokevirtual #2                  // Method java/lang/Class.isInstance:(Ljava/lang/Object;)Z
       6: ifne          36
       9: new           #3                  // class java/lang/IllegalArgumentException
      12: dup
      13: new           #4                  // class java/lang/StringBuilder
      16: dup
      17: invokespecial #5                  // Method java/lang/StringBuilder."<init>":()V
      20: ldc           #6                  // String Expecting BeanManager reference that implements optional ExtendedBeanManager contract :
      22: invokevirtual #7                  // Method java/lang/StringBuilder.append:(Ljava/lang/String;)Ljava/lang/StringBuilder;
      25: aload_0
      26: invokevirtual #8                  // Method java/lang/StringBuilder.append:(Ljava/lang/Object;)Ljava/lang/StringBuilder;
      29: invokevirtual #9                  // Method java/lang/StringBuilder.toString:()Ljava/lang/String;
      32: invokespecial #10                 // Method java/lang/IllegalArgumentException."<init>":(Ljava/lang/String;)V
      35: athrow
      36: new           #11                 // class org/hibernate/jpa/event/internal/jpa/ListenerFactoryBeanManagerExtendedImpl
      39: dup
      40: aload_0
      41: checkcast     #1                  // class org/hibernate/jpa/event/spi/jpa/ExtendedBeanManager
      44: invokespecial #12                 // Method "<init>":(Lorg/hibernate/jpa/event/spi/jpa/ExtendedBeanManager;)V
      47: areturn

  public org.hibernate.jpa.event.internal.jpa.ListenerFactoryBeanManagerExtendedImpl(org.hibernate.jpa.event.spi.jpa.ExtendedBeanManager);
    Code:
       0: aload_0
       1: invokespecial #13                 // Method java/lang/Object."<init>":()V
       4: aload_0
       5: new           #14                 // class java/util/concurrent/ConcurrentHashMap
       8: dup
       9: invokespecial #15                 // Method java/util/concurrent/ConcurrentHashMap."<init>":()V
      12: putfield      #16                 // Field listenerMap:Ljava/util/Map;
      15: aload_1
      16: aload_0
      17: invokeinterface #17,  2           // InterfaceMethod org/hibernate/jpa/event/spi/jpa/ExtendedBeanManager.registerLifecycleListener:(Lorg/hibernate/jpa/event/spi/jpa/ExtendedBeanManager$LifecycleListener;)V
      22: getstatic     #18                 // Field log:Lorg/jboss/logging/Logger;
      25: new           #4                  // class java/lang/StringBuilder
      28: dup
      29: invokespecial #5                  // Method java/lang/StringBuilder."<init>":()V
      32: ldc           #19                 // String ExtendedBeanManager access requested to CDI BeanManager :
      34: invokevirtual #7                  // Method java/lang/StringBuilder.append:(Ljava/lang/String;)Ljava/lang/StringBuilder;
      37: aload_1
      38: invokevirtual #8                  // Method java/lang/StringBuilder.append:(Ljava/lang/Object;)Ljava/lang/StringBuilder;
      41: invokevirtual #9                  // Method java/lang/StringBuilder.toString:()Ljava/lang/String;
      44: iconst_0
      45: anewarray     #20                 // class java/lang/Object
      48: invokevirtual #21                 // Method org/jboss/logging/Logger.debugf:(Ljava/lang/String;[Ljava/lang/Object;)V
      51: return

  public <T> org.hibernate.jpa.event.spi.jpa.Listener<T> buildListener(java.lang.Class<T>);
    Code:
       0: aload_0
       1: getfield      #16                 // Field listenerMap:Ljava/util/Map;
       4: aload_1
       5: invokeinterface #22,  2           // InterfaceMethod java/util/Map.get:(Ljava/lang/Object;)Ljava/lang/Object;
      10: checkcast     #23                 // class org/hibernate/jpa/event/internal/jpa/ListenerFactoryBeanManagerExtendedImpl$ListenerImpl
      13: astore_2
      14: aload_2
      15: ifnonnull     40
      18: new           #23                 // class org/hibernate/jpa/event/internal/jpa/ListenerFactoryBeanManagerExtendedImpl$ListenerImpl
      21: dup
      22: aload_1
      23: aconst_null
      24: invokespecial #24                 // Method org/hibernate/jpa/event/internal/jpa/ListenerFactoryBeanManagerExtendedImpl$ListenerImpl."<init>":(Ljava/lang/Class;Lorg/hibernate/jpa/event/internal/jpa/ListenerFactoryBeanManagerExtendedImpl$1;)V
      27: astore_2
      28: aload_0
      29: getfield      #16                 // Field listenerMap:Ljava/util/Map;
      32: aload_1
      33: aload_2
      34: invokeinterface #25,  3           // InterfaceMethod java/util/Map.put:(Ljava/lang/Object;Ljava/lang/Object;)Ljava/lang/Object;
      39: pop
      40: aload_2
      41: areturn

  public void release();
    Code:
       0: aload_0
       1: getfield      #16                 // Field listenerMap:Ljava/util/Map;
       4: invokeinterface #26,  1           // InterfaceMethod java/util/Map.values:()Ljava/util/Collection;
       9: invokeinterface #27,  1           // InterfaceMethod java/util/Collection.iterator:()Ljava/util/Iterator;
      14: astore_1
      15: aload_1
      16: invokeinterface #28,  1           // InterfaceMethod java/util/Iterator.hasNext:()Z
      21: ifeq          41
      24: aload_1
      25: invokeinterface #29,  1           // InterfaceMethod java/util/Iterator.next:()Ljava/lang/Object;
      30: checkcast     #23                 // class org/hibernate/jpa/event/internal/jpa/ListenerFactoryBeanManagerExtendedImpl$ListenerImpl
      33: astore_2
      34: aload_2
      35: invokevirtual #30                 // Method org/hibernate/jpa/event/internal/jpa/ListenerFactoryBeanManagerExtendedImpl$ListenerImpl.release:()V
      38: goto          15
      41: aload_0
      42: getfield      #16                 // Field listenerMap:Ljava/util/Map;
      45: invokeinterface #31,  1           // InterfaceMethod java/util/Map.clear:()V
      50: return

  public void beanManagerInitialized(javax.enterprise.inject.spi.BeanManager);
    Code:
       0: aload_0
       1: getfield      #16                 // Field listenerMap:Ljava/util/Map;
       4: invokeinterface #26,  1           // InterfaceMethod java/util/Map.values:()Ljava/util/Collection;
       9: invokeinterface #27,  1           // InterfaceMethod java/util/Collection.iterator:()Ljava/util/Iterator;
      14: astore_2
      15: aload_2
      16: invokeinterface #28,  1           // InterfaceMethod java/util/Iterator.hasNext:()Z
      21: ifeq          42
      24: aload_2
      25: invokeinterface #29,  1           // InterfaceMethod java/util/Iterator.next:()Ljava/lang/Object;
      30: checkcast     #23                 // class org/hibernate/jpa/event/internal/jpa/ListenerFactoryBeanManagerExtendedImpl$ListenerImpl
      33: astore_3
      34: aload_3
      35: aload_1
      36: invokevirtual #32                 // Method org/hibernate/jpa/event/internal/jpa/ListenerFactoryBeanManagerExtendedImpl$ListenerImpl.initialize:(Ljavax/enterprise/inject/spi/BeanManager;)V
      39: goto          15
      42: return

  static {};
    Code:
       0: ldc           #11                 // class org/hibernate/jpa/event/internal/jpa/ListenerFactoryBeanManagerExtendedImpl
       2: invokestatic  #33                 // Method org/jboss/logging/Logger.getLogger:(Ljava/lang/Class;)Lorg/jboss/logging/Logger;
       5: putstatic     #18                 // Field log:Lorg/jboss/logging/Logger;
       8: return
}
