Compiled from "WebApplicationExceptionMapper.java"
public class uk.gov.gchq.gaffer.rest.mapper.WebApplicationExceptionMapper implements javax.ws.rs.ext.ExceptionMapper<javax.ws.rs.WebApplicationException> {
  public uk.gov.gchq.gaffer.rest.mapper.WebApplicationExceptionMapper();
    Code:
       0: aload_0
       1: invokespecial #2                  // Method java/lang/Object."<init>":()V
       4: return

  public javax.ws.rs.core.Response toResponse(javax.ws.rs.WebApplicationException);
    Code:
       0: new           #3                  // class uk/gov/gchq/gaffer/core/exception/Error$ErrorBuilder
       3: dup
       4: invokespecial #4                  // Method uk/gov/gchq/gaffer/core/exception/Error$ErrorBuilder."<init>":()V
       7: aload_1
       8: invokevirtual #5                  // Method javax/ws/rs/WebApplicationException.getResponse:()Ljavax/ws/rs/core/Response;
      11: invokevirtual #6                  // Method javax/ws/rs/core/Response.getStatus:()I
      14: invokevirtual #7                  // Method uk/gov/gchq/gaffer/core/exception/Error$ErrorBuilder.statusCode:(I)Luk/gov/gchq/gaffer/core/exception/Error$ErrorBuilder;
      17: aload_1
      18: invokevirtual #8                  // Method javax/ws/rs/WebApplicationException.getMessage:()Ljava/lang/String;
      21: invokevirtual #9                  // Method uk/gov/gchq/gaffer/core/exception/Error$ErrorBuilder.simpleMessage:(Ljava/lang/String;)Luk/gov/gchq/gaffer/core/exception/Error$ErrorBuilder;
      24: aload_1
      25: invokestatic  #10                 // Method org/apache/commons/lang3/exception/ExceptionUtils.getStackTrace:(Ljava/lang/Throwable;)Ljava/lang/String;
      28: invokevirtual #11                 // Method uk/gov/gchq/gaffer/core/exception/Error$ErrorBuilder.detailMessage:(Ljava/lang/String;)Luk/gov/gchq/gaffer/core/exception/Error$ErrorBuilder;
      31: invokevirtual #12                 // Method uk/gov/gchq/gaffer/core/exception/Error$ErrorBuilder.build:()Luk/gov/gchq/gaffer/core/exception/Error;
      34: astore_2
      35: aload_1
      36: invokevirtual #5                  // Method javax/ws/rs/WebApplicationException.getResponse:()Ljavax/ws/rs/core/Response;
      39: invokevirtual #6                  // Method javax/ws/rs/core/Response.getStatus:()I
      42: invokestatic  #13                 // Method javax/ws/rs/core/Response.status:(I)Ljavax/ws/rs/core/Response$ResponseBuilder;
      45: ldc           #14                 // String X-Gaffer-Media-Type
      47: getstatic     #15                 // Field uk/gov/gchq/gaffer/rest/ServiceConstants.GAFFER_MEDIA_TYPE:Ljava/lang/String;
      50: invokevirtual #16                 // Method javax/ws/rs/core/Response$ResponseBuilder.header:(Ljava/lang/String;Ljava/lang/Object;)Ljavax/ws/rs/core/Response$ResponseBuilder;
      53: aload_2
      54: invokevirtual #17                 // Method javax/ws/rs/core/Response$ResponseBuilder.entity:(Ljava/lang/Object;)Ljavax/ws/rs/core/Response$ResponseBuilder;
      57: invokevirtual #18                 // Method javax/ws/rs/core/Response$ResponseBuilder.build:()Ljavax/ws/rs/core/Response;
      60: areturn

  public javax.ws.rs.core.Response toResponse(java.lang.Throwable);
    Code:
       0: aload_0
       1: aload_1
       2: checkcast     #19                 // class javax/ws/rs/WebApplicationException
       5: invokevirtual #20                 // Method toResponse:(Ljavax/ws/rs/WebApplicationException;)Ljavax/ws/rs/core/Response;
       8: areturn
}
