Compiled from "WSFException.java"
public class org.jboss.wsf.spi.WSFException extends java.lang.RuntimeException {
  public org.jboss.wsf.spi.WSFException();
    Code:
       0: aload_0
       1: invokespecial #1                  // Method java/lang/RuntimeException."<init>":()V
       4: return

  public org.jboss.wsf.spi.WSFException(java.lang.String);
    Code:
       0: aload_0
       1: aload_1
       2: invokespecial #2                  // Method java/lang/RuntimeException."<init>":(Ljava/lang/String;)V
       5: return

  public org.jboss.wsf.spi.WSFException(java.lang.String, java.lang.Throwable);
    Code:
       0: aload_0
       1: aload_1
       2: aload_2
       3: invokespecial #3                  // Method java/lang/RuntimeException."<init>":(Ljava/lang/String;Ljava/lang/Throwable;)V
       6: return

  public org.jboss.wsf.spi.WSFException(java.lang.Throwable);
    Code:
       0: aload_0
       1: aload_1
       2: invokespecial #4                  // Method java/lang/RuntimeException."<init>":(Ljava/lang/Throwable;)V
       5: return

  public static void rethrow(java.lang.String, java.lang.Throwable);
    Code:
       0: aload_1
       1: instanceof    #5                  // class org/jboss/wsf/spi/WSFException
       4: ifeq          12
       7: aload_1
       8: checkcast     #5                  // class org/jboss/wsf/spi/WSFException
      11: athrow
      12: new           #5                  // class org/jboss/wsf/spi/WSFException
      15: dup
      16: aload_0
      17: aload_1
      18: invokespecial #6                  // Method "<init>":(Ljava/lang/String;Ljava/lang/Throwable;)V
      21: athrow

  public static void rethrow(java.lang.Throwable);
    Code:
       0: aload_0
       1: instanceof    #5                  // class org/jboss/wsf/spi/WSFException
       4: ifeq          12
       7: aload_0
       8: checkcast     #5                  // class org/jboss/wsf/spi/WSFException
      11: athrow
      12: new           #5                  // class org/jboss/wsf/spi/WSFException
      15: dup
      16: aload_0
      17: invokespecial #7                  // Method "<init>":(Ljava/lang/Throwable;)V
      20: athrow
}
