Compiled from "SchemaManagementToolInitiator.java"
public class org.hibernate.tool.schema.internal.SchemaManagementToolInitiator implements org.hibernate.boot.registry.StandardServiceInitiator<org.hibernate.tool.schema.spi.SchemaManagementTool> {
  public static final org.hibernate.tool.schema.internal.SchemaManagementToolInitiator INSTANCE;

  public org.hibernate.tool.schema.internal.SchemaManagementToolInitiator();
    Code:
       0: aload_0
       1: invokespecial #1                  // Method java/lang/Object."<init>":()V
       4: return

  public org.hibernate.tool.schema.spi.SchemaManagementTool initiateService(java.util.Map, org.hibernate.service.spi.ServiceRegistryImplementor);
    Code:
       0: aload_1
       1: ldc           #3                  // String hibernate.schema_management_tool
       3: invokeinterface #4,  2            // InterfaceMethod java/util/Map.get:(Ljava/lang/Object;)Ljava/lang/Object;
       8: astore_3
       9: aload_2
      10: ldc           #5                  // class org/hibernate/boot/registry/selector/spi/StrategySelector
      12: invokeinterface #6,  2            // InterfaceMethod org/hibernate/service/spi/ServiceRegistryImplementor.getService:(Ljava/lang/Class;)Lorg/hibernate/service/Service;
      17: checkcast     #5                  // class org/hibernate/boot/registry/selector/spi/StrategySelector
      20: ldc           #7                  // class org/hibernate/tool/schema/spi/SchemaManagementTool
      22: aload_3
      23: invokeinterface #8,  3            // InterfaceMethod org/hibernate/boot/registry/selector/spi/StrategySelector.resolveStrategy:(Ljava/lang/Class;Ljava/lang/Object;)Ljava/lang/Object;
      28: checkcast     #7                  // class org/hibernate/tool/schema/spi/SchemaManagementTool
      31: astore        4
      33: aload         4
      35: ifnonnull     47
      38: new           #9                  // class org/hibernate/tool/schema/internal/HibernateSchemaManagementTool
      41: dup
      42: invokespecial #10                 // Method org/hibernate/tool/schema/internal/HibernateSchemaManagementTool."<init>":()V
      45: astore        4
      47: aload         4
      49: areturn

  public java.lang.Class<org.hibernate.tool.schema.spi.SchemaManagementTool> getServiceInitiated();
    Code:
       0: ldc           #7                  // class org/hibernate/tool/schema/spi/SchemaManagementTool
       2: areturn

  public org.hibernate.service.Service initiateService(java.util.Map, org.hibernate.service.spi.ServiceRegistryImplementor);
    Code:
       0: aload_0
       1: aload_1
       2: aload_2
       3: invokevirtual #11                 // Method initiateService:(Ljava/util/Map;Lorg/hibernate/service/spi/ServiceRegistryImplementor;)Lorg/hibernate/tool/schema/spi/SchemaManagementTool;
       6: areturn

  static {};
    Code:
       0: new           #12                 // class org/hibernate/tool/schema/internal/SchemaManagementToolInitiator
       3: dup
       4: invokespecial #13                 // Method "<init>":()V
       7: putstatic     #14                 // Field INSTANCE:Lorg/hibernate/tool/schema/internal/SchemaManagementToolInitiator;
      10: return
}
