Compiled from "DFUResultWrapper.java"
public class org.hpccsystems.ws.client.wrappers.wsdfu.DFUResultWrapper {
  private java.lang.String actionResult;

  private java.lang.Boolean failed;

  private java.lang.String fileName;

  private java.lang.String nodeGroup;

  public org.hpccsystems.ws.client.wrappers.wsdfu.DFUResultWrapper(org.hpccsystems.ws.client.gen.axis2.wsdfu.v1_57.DFUActionInfo);
    Code:
       0: aload_0
       1: invokespecial #1                  // Method java/lang/Object."<init>":()V
       4: aload_0
       5: aload_1
       6: invokevirtual #2                  // Method org/hpccsystems/ws/client/gen/axis2/wsdfu/v1_57/DFUActionInfo.getActionResult:()Ljava/lang/String;
       9: putfield      #3                  // Field actionResult:Ljava/lang/String;
      12: aload_0
      13: aload_1
      14: invokevirtual #4                  // Method org/hpccsystems/ws/client/gen/axis2/wsdfu/v1_57/DFUActionInfo.getFailed:()Z
      17: invokestatic  #5                  // Method java/lang/Boolean.valueOf:(Z)Ljava/lang/Boolean;
      20: putfield      #6                  // Field failed:Ljava/lang/Boolean;
      23: aload_0
      24: aload_1
      25: invokevirtual #7                  // Method org/hpccsystems/ws/client/gen/axis2/wsdfu/v1_57/DFUActionInfo.getFileName:()Ljava/lang/String;
      28: putfield      #8                  // Field fileName:Ljava/lang/String;
      31: aload_0
      32: aload_1
      33: invokevirtual #9                  // Method org/hpccsystems/ws/client/gen/axis2/wsdfu/v1_57/DFUActionInfo.getNodeGroup:()Ljava/lang/String;
      36: putfield      #10                 // Field nodeGroup:Ljava/lang/String;
      39: return

  public java.lang.String getActionResult();
    Code:
       0: aload_0
       1: getfield      #3                  // Field actionResult:Ljava/lang/String;
       4: areturn

  public void setActionResult(java.lang.String);
    Code:
       0: aload_0
       1: aload_1
       2: putfield      #3                  // Field actionResult:Ljava/lang/String;
       5: return

  public java.lang.Boolean getFailed();
    Code:
       0: aload_0
       1: getfield      #6                  // Field failed:Ljava/lang/Boolean;
       4: areturn

  public void setFailed(java.lang.Boolean);
    Code:
       0: aload_0
       1: aload_1
       2: putfield      #6                  // Field failed:Ljava/lang/Boolean;
       5: return

  public java.lang.String getFileName();
    Code:
       0: aload_0
       1: getfield      #8                  // Field fileName:Ljava/lang/String;
       4: areturn

  public void setFileName(java.lang.String);
    Code:
       0: aload_0
       1: aload_1
       2: putfield      #8                  // Field fileName:Ljava/lang/String;
       5: return

  public java.lang.String getNodeGroup();
    Code:
       0: aload_0
       1: getfield      #10                 // Field nodeGroup:Ljava/lang/String;
       4: areturn

  public void setNodeGroup(java.lang.String);
    Code:
       0: aload_0
       1: aload_1
       2: putfield      #10                 // Field nodeGroup:Ljava/lang/String;
       5: return
}
