Compiled from "FlowControlHandler.java"
final class io.netty.handler.flow.FlowControlHandler$RecyclableArrayDeque extends java.util.ArrayDeque<java.lang.Object> {
  private static final long serialVersionUID;

  private static final int DEFAULT_NUM_ELEMENTS;

  private static final io.netty.util.internal.ObjectPool<io.netty.handler.flow.FlowControlHandler$RecyclableArrayDeque> RECYCLER;

  private final io.netty.util.internal.ObjectPool$Handle<io.netty.handler.flow.FlowControlHandler$RecyclableArrayDeque> handle;

  public static io.netty.handler.flow.FlowControlHandler$RecyclableArrayDeque newInstance();
    Code:
       0: getstatic     #2                  // Field RECYCLER:Lio/netty/util/internal/ObjectPool;
       3: invokevirtual #3                  // Method io/netty/util/internal/ObjectPool.get:()Ljava/lang/Object;
       6: checkcast     #4                  // class io/netty/handler/flow/FlowControlHandler$RecyclableArrayDeque
       9: areturn

  private io.netty.handler.flow.FlowControlHandler$RecyclableArrayDeque(int, io.netty.util.internal.ObjectPool$Handle<io.netty.handler.flow.FlowControlHandler$RecyclableArrayDeque>);
    Code:
       0: aload_0
       1: iload_1
       2: invokespecial #5                  // Method java/util/ArrayDeque."<init>":(I)V
       5: aload_0
       6: aload_2
       7: putfield      #6                  // Field handle:Lio/netty/util/internal/ObjectPool$Handle;
      10: return

  public void recycle();
    Code:
       0: aload_0
       1: invokevirtual #7                  // Method clear:()V
       4: aload_0
       5: getfield      #6                  // Field handle:Lio/netty/util/internal/ObjectPool$Handle;
       8: aload_0
       9: invokeinterface #8,  2            // InterfaceMethod io/netty/util/internal/ObjectPool$Handle.recycle:(Ljava/lang/Object;)V
      14: return

  io.netty.handler.flow.FlowControlHandler$RecyclableArrayDeque(int, io.netty.util.internal.ObjectPool$Handle, io.netty.handler.flow.FlowControlHandler$1);
    Code:
       0: aload_0
       1: iload_1
       2: aload_2
       3: invokespecial #1                  // Method "<init>":(ILio/netty/util/internal/ObjectPool$Handle;)V
       6: return

  static {};
    Code:
       0: new           #9                  // class io/netty/handler/flow/FlowControlHandler$RecyclableArrayDeque$1
       3: dup
       4: invokespecial #10                 // Method io/netty/handler/flow/FlowControlHandler$RecyclableArrayDeque$1."<init>":()V
       7: invokestatic  #11                 // Method io/netty/util/internal/ObjectPool.newPool:(Lio/netty/util/internal/ObjectPool$ObjectCreator;)Lio/netty/util/internal/ObjectPool;
      10: putstatic     #2                  // Field RECYCLER:Lio/netty/util/internal/ObjectPool;
      13: return
}
