Compiled from "KQSelector.java"
class jnr.enxio.channels.KQSelector$Descriptor {
  private final int fd;

  private final java.util.Set<jnr.enxio.channels.KQSelectionKey> keys;

  private boolean write;

  private boolean read;

  public jnr.enxio.channels.KQSelector$Descriptor(int);
    Code:
       0: aload_0
       1: invokespecial #5                  // Method java/lang/Object."<init>":()V
       4: aload_0
       5: new           #6                  // class java/util/HashSet
       8: dup
       9: invokespecial #7                  // Method java/util/HashSet."<init>":()V
      12: putfield      #4                  // Field keys:Ljava/util/Set;
      15: aload_0
      16: iconst_0
      17: putfield      #2                  // Field write:Z
      20: aload_0
      21: iconst_0
      22: putfield      #3                  // Field read:Z
      25: aload_0
      26: iload_1
      27: putfield      #1                  // Field fd:I
      30: return

  static java.util.Set access$000(jnr.enxio.channels.KQSelector$Descriptor);
    Code:
       0: aload_0
       1: getfield      #4                  // Field keys:Ljava/util/Set;
       4: areturn

  static boolean access$100(jnr.enxio.channels.KQSelector$Descriptor);
    Code:
       0: aload_0
       1: getfield      #3                  // Field read:Z
       4: ireturn

  static boolean access$102(jnr.enxio.channels.KQSelector$Descriptor, boolean);
    Code:
       0: aload_0
       1: iload_1
       2: dup_x1
       3: putfield      #3                  // Field read:Z
       6: ireturn

  static boolean access$200(jnr.enxio.channels.KQSelector$Descriptor);
    Code:
       0: aload_0
       1: getfield      #2                  // Field write:Z
       4: ireturn

  static boolean access$202(jnr.enxio.channels.KQSelector$Descriptor, boolean);
    Code:
       0: aload_0
       1: iload_1
       2: dup_x1
       3: putfield      #2                  // Field write:Z
       6: ireturn

  static int access$300(jnr.enxio.channels.KQSelector$Descriptor);
    Code:
       0: aload_0
       1: getfield      #1                  // Field fd:I
       4: ireturn
}
