Compiled from "HelloHandler.java"
public class org.eclipse.jetty.demos.HelloHandler extends org.eclipse.jetty.server.handler.AbstractHandler {
  final java.lang.String greeting;

  final java.lang.String body;

  public org.eclipse.jetty.demos.HelloHandler();
    Code:
       0: aload_0
       1: ldc           #1                  // String Hello World
       3: invokespecial #3                  // Method "<init>":(Ljava/lang/String;)V
       6: return

  public org.eclipse.jetty.demos.HelloHandler(java.lang.String);
    Code:
       0: aload_0
       1: aload_1
       2: aconst_null
       3: invokespecial #9                  // Method "<init>":(Ljava/lang/String;Ljava/lang/String;)V
       6: return

  public org.eclipse.jetty.demos.HelloHandler(java.lang.String, java.lang.String);
    Code:
       0: aload_0
       1: invokespecial #12                 // Method org/eclipse/jetty/server/handler/AbstractHandler."<init>":()V
       4: aload_0
       5: aload_1
       6: putfield      #17                 // Field greeting:Ljava/lang/String;
       9: aload_0
      10: aload_2
      11: putfield      #21                 // Field body:Ljava/lang/String;
      14: return

  public void handle(java.lang.String, org.eclipse.jetty.server.Request, javax.servlet.http.HttpServletRequest, javax.servlet.http.HttpServletResponse) throws java.io.IOException, javax.servlet.ServletException;
    Code:
       0: aload         4
       2: ldc           #24                 // String text/html; charset=utf-8
       4: invokeinterface #26,  2           // InterfaceMethod javax/servlet/http/HttpServletResponse.setContentType:(Ljava/lang/String;)V
       9: aload         4
      11: sipush        200
      14: invokeinterface #31,  2           // InterfaceMethod javax/servlet/http/HttpServletResponse.setStatus:(I)V
      19: aload         4
      21: invokeinterface #35,  1           // InterfaceMethod javax/servlet/http/HttpServletResponse.getWriter:()Ljava/io/PrintWriter;
      26: astore        5
      28: aload         5
      30: aload_0
      31: getfield      #17                 // Field greeting:Ljava/lang/String;
      34: invokedynamic #39,  0             // InvokeDynamic #0:makeConcatWithConstants:(Ljava/lang/String;)Ljava/lang/String;
      39: invokevirtual #43                 // Method java/io/PrintWriter.println:(Ljava/lang/String;)V
      42: aload_0
      43: getfield      #21                 // Field body:Ljava/lang/String;
      46: ifnull        58
      49: aload         5
      51: aload_0
      52: getfield      #21                 // Field body:Ljava/lang/String;
      55: invokevirtual #43                 // Method java/io/PrintWriter.println:(Ljava/lang/String;)V
      58: aload_2
      59: iconst_1
      60: invokevirtual #48                 // Method org/eclipse/jetty/server/Request.setHandled:(Z)V
      63: return
}
