Compiled from "Http2Server.java"
class org.eclipse.jetty.demos.Http2Server$1 extends javax.servlet.http.HttpServlet {
  private static final long serialVersionUID;

  org.eclipse.jetty.demos.Http2Server$1();
    Code:
       0: aload_0
       1: invokespecial #1                  // Method javax/servlet/http/HttpServlet."<init>":()V
       4: return

  protected void service(javax.servlet.http.HttpServletRequest, javax.servlet.http.HttpServletResponse) throws java.io.IOException;
    Code:
       0: aload_1
       1: ldc           #7                  // String code
       3: invokeinterface #9,  2            // InterfaceMethod javax/servlet/http/HttpServletRequest.getParameter:(Ljava/lang/String;)Ljava/lang/String;
       8: astore_3
       9: aload_3
      10: ifnull        23
      13: aload_2
      14: aload_3
      15: invokestatic  #15                 // Method java/lang/Integer.parseInt:(Ljava/lang/String;)I
      18: invokeinterface #21,  2           // InterfaceMethod javax/servlet/http/HttpServletResponse.setStatus:(I)V
      23: aload_1
      24: iconst_1
      25: invokeinterface #27,  2           // InterfaceMethod javax/servlet/http/HttpServletRequest.getSession:(Z)Ljavax/servlet/http/HttpSession;
      30: astore        4
      32: aload         4
      34: invokeinterface #31,  1           // InterfaceMethod javax/servlet/http/HttpSession.isNew:()Z
      39: ifeq          72
      42: aload_2
      43: new           #37                 // class javax/servlet/http/Cookie
      46: dup
      47: ldc           #39                 // String bigcookie
      49: new           #41                 // class java/util/Date
      52: dup
      53: invokespecial #43                 // Method java/util/Date."<init>":()V
      56: invokestatic  #44                 // Method java/lang/String.valueOf:(Ljava/lang/Object;)Ljava/lang/String;
      59: invokedynamic #50,  0             // InvokeDynamic #0:makeConcatWithConstants:(Ljava/lang/String;)Ljava/lang/String;
      64: invokespecial #53                 // Method javax/servlet/http/Cookie."<init>":(Ljava/lang/String;Ljava/lang/String;)V
      67: invokeinterface #56,  2           // InterfaceMethod javax/servlet/http/HttpServletResponse.addCookie:(Ljavax/servlet/http/Cookie;)V
      72: aload_2
      73: ldc           #60                 // String Custom
      75: ldc           #62                 // String Value
      77: invokeinterface #64,  3           // InterfaceMethod javax/servlet/http/HttpServletResponse.setHeader:(Ljava/lang/String;Ljava/lang/String;)V
      82: aload_2
      83: ldc           #67                 // String text/plain
      85: invokeinterface #69,  2           // InterfaceMethod javax/servlet/http/HttpServletResponse.setContentType:(Ljava/lang/String;)V
      90: aload_1
      91: invokeinterface #73,  1           // InterfaceMethod javax/servlet/http/HttpServletRequest.getProtocol:()Ljava/lang/String;
      96: invokedynamic #77,  0             // InvokeDynamic #1:makeConcatWithConstants:(Ljava/lang/String;)Ljava/lang/String;
     101: astore        5
     103: aload         5
     105: aload_1
     106: invokeinterface #78,  1           // InterfaceMethod javax/servlet/http/HttpServletRequest.getRequestURI:()Ljava/lang/String;
     111: invokedynamic #81,  0             // InvokeDynamic #2:makeConcatWithConstants:(Ljava/lang/String;Ljava/lang/String;)Ljava/lang/String;
     116: astore        5
     118: aload         5
     120: aload         4
     122: invokeinterface #84,  1           // InterfaceMethod javax/servlet/http/HttpSession.getId:()Ljava/lang/String;
     127: aload         4
     129: invokeinterface #31,  1           // InterfaceMethod javax/servlet/http/HttpSession.isNew:()Z
     134: ifeq          142
     137: ldc           #87                 // String (New)\n
     139: goto          144
     142: ldc           #89                 // String \n
     144: invokedynamic #91,  0             // InvokeDynamic #3:makeConcatWithConstants:(Ljava/lang/String;Ljava/lang/String;Ljava/lang/String;)Ljava/lang/String;
     149: astore        5
     151: aload         5
     153: new           #41                 // class java/util/Date
     156: dup
     157: invokespecial #43                 // Method java/util/Date."<init>":()V
     160: invokestatic  #44                 // Method java/lang/String.valueOf:(Ljava/lang/Object;)Ljava/lang/String;
     163: invokedynamic #94,  0             // InvokeDynamic #4:makeConcatWithConstants:(Ljava/lang/String;Ljava/lang/String;)Ljava/lang/String;
     168: astore        5
     170: aload         5
     172: aload_1
     173: invokeinterface #95,  1           // InterfaceMethod javax/servlet/http/HttpServletRequest.getCookies:()[Ljavax/servlet/http/Cookie;
     178: invokestatic  #99                 // Method java/util/Optional.ofNullable:(Ljava/lang/Object;)Ljava/util/Optional;
     181: invokevirtual #105                // Method java/util/Optional.stream:()Ljava/util/stream/Stream;
     184: invokedynamic #109,  0            // InvokeDynamic #5:apply:()Ljava/util/function/Function;
     189: invokeinterface #113,  2          // InterfaceMethod java/util/stream/Stream.flatMap:(Ljava/util/function/Function;)Ljava/util/stream/Stream;
     194: invokedynamic #119,  0            // InvokeDynamic #6:apply:()Ljava/util/function/Function;
     199: invokeinterface #120,  2          // InterfaceMethod java/util/stream/Stream.map:(Ljava/util/function/Function;)Ljava/util/stream/Stream;
     204: invokestatic  #123                // Method java/lang/System.lineSeparator:()Ljava/lang/String;
     207: invokestatic  #128                // Method java/util/stream/Collectors.joining:(Ljava/lang/CharSequence;)Ljava/util/stream/Collector;
     210: invokeinterface #134,  2          // InterfaceMethod java/util/stream/Stream.collect:(Ljava/util/stream/Collector;)Ljava/lang/Object;
     215: checkcast     #45                 // class java/lang/String
     218: invokedynamic #138,  0            // InvokeDynamic #7:makeConcatWithConstants:(Ljava/lang/String;Ljava/lang/String;)Ljava/lang/String;
     223: astore        5
     225: aload_2
     226: aload         5
     228: invokevirtual #139                // Method java/lang/String.length:()I
     231: invokeinterface #143,  2          // InterfaceMethod javax/servlet/http/HttpServletResponse.setContentLength:(I)V
     236: aload_2
     237: invokeinterface #146,  1          // InterfaceMethod javax/servlet/http/HttpServletResponse.getOutputStream:()Ljavax/servlet/ServletOutputStream;
     242: aload         5
     244: invokevirtual #150                // Method javax/servlet/ServletOutputStream.print:(Ljava/lang/String;)V
     247: return

  private static java.lang.String lambda$service$0(javax.servlet.http.Cookie);
    Code:
       0: ldc           #155                // String cookie %s=%s
       2: iconst_2
       3: anewarray     #157                // class java/lang/Object
       6: dup
       7: iconst_0
       8: aload_0
       9: invokevirtual #159                // Method javax/servlet/http/Cookie.getName:()Ljava/lang/String;
      12: aastore
      13: dup
      14: iconst_1
      15: aload_0
      16: invokevirtual #162                // Method javax/servlet/http/Cookie.getValue:()Ljava/lang/String;
      19: aastore
      20: invokestatic  #165                // Method java/lang/String.format:(Ljava/lang/String;[Ljava/lang/Object;)Ljava/lang/String;
      23: areturn
}
