Compiled from "OneServletContext.java"
public class org.eclipse.jetty.demos.OneServletContext {
  public org.eclipse.jetty.demos.OneServletContext();
    Code:
       0: aload_0
       1: invokespecial #1                  // Method java/lang/Object."<init>":()V
       4: return

  public static org.eclipse.jetty.server.Server createServer(int, org.eclipse.jetty.util.resource.Resource);
    Code:
       0: new           #7                  // class org/eclipse/jetty/server/Server
       3: dup
       4: iload_0
       5: invokespecial #9                  // Method org/eclipse/jetty/server/Server."<init>":(I)V
       8: astore_2
       9: new           #12                 // class org/eclipse/jetty/servlet/ServletContextHandler
      12: dup
      13: iconst_1
      14: invokespecial #14                 // Method org/eclipse/jetty/servlet/ServletContextHandler."<init>":(I)V
      17: astore_3
      18: aload_3
      19: ldc           #15                 // String /
      21: invokevirtual #17                 // Method org/eclipse/jetty/servlet/ServletContextHandler.setContextPath:(Ljava/lang/String;)V
      24: aload_3
      25: aload_1
      26: invokevirtual #21                 // Method org/eclipse/jetty/servlet/ServletContextHandler.setBaseResource:(Lorg/eclipse/jetty/util/resource/Resource;)V
      29: aload_2
      30: aload_3
      31: invokevirtual #25                 // Method org/eclipse/jetty/server/Server.setHandler:(Lorg/eclipse/jetty/server/Handler;)V
      34: aload_3
      35: ldc           #29                 // class org/eclipse/jetty/demos/HelloServlet
      37: ldc           #31                 // String /hello/*
      39: invokevirtual #33                 // Method org/eclipse/jetty/servlet/ServletContextHandler.addServlet:(Ljava/lang/Class;Ljava/lang/String;)Lorg/eclipse/jetty/servlet/ServletHolder;
      42: pop
      43: new           #37                 // class org/eclipse/jetty/servlet/ServletHolder
      46: dup
      47: ldc           #39                 // String debug
      49: ldc           #41                 // class org/eclipse/jetty/demos/DumpServlet
      51: invokespecial #43                 // Method org/eclipse/jetty/servlet/ServletHolder."<init>":(Ljava/lang/String;Ljava/lang/Class;)V
      54: astore        4
      56: aload_3
      57: aload         4
      59: ldc           #46                 // String /dump/*
      61: invokevirtual #48                 // Method org/eclipse/jetty/servlet/ServletContextHandler.addServlet:(Lorg/eclipse/jetty/servlet/ServletHolder;Ljava/lang/String;)V
      64: aload_3
      65: aload         4
      67: ldc           #51                 // String *.dump
      69: invokevirtual #48                 // Method org/eclipse/jetty/servlet/ServletContextHandler.addServlet:(Lorg/eclipse/jetty/servlet/ServletHolder;Ljava/lang/String;)V
      72: aload_3
      73: ldc           #53                 // class org/eclipse/jetty/servlet/DefaultServlet
      75: ldc           #15                 // String /
      77: invokevirtual #33                 // Method org/eclipse/jetty/servlet/ServletContextHandler.addServlet:(Ljava/lang/Class;Ljava/lang/String;)Lorg/eclipse/jetty/servlet/ServletHolder;
      80: pop
      81: aload_3
      82: ldc           #55                 // class org/eclipse/jetty/demos/OneServletContext$TestFilter
      84: ldc           #57                 // String /test/*
      86: getstatic     #59                 // Field javax/servlet/DispatcherType.REQUEST:Ljavax/servlet/DispatcherType;
      89: invokestatic  #65                 // Method java/util/EnumSet.of:(Ljava/lang/Enum;)Ljava/util/EnumSet;
      92: invokevirtual #71                 // Method org/eclipse/jetty/servlet/ServletContextHandler.addFilter:(Ljava/lang/Class;Ljava/lang/String;Ljava/util/EnumSet;)Lorg/eclipse/jetty/servlet/FilterHolder;
      95: pop
      96: aload_3
      97: ldc           #55                 // class org/eclipse/jetty/demos/OneServletContext$TestFilter
      99: ldc           #75                 // String *.test
     101: getstatic     #59                 // Field javax/servlet/DispatcherType.REQUEST:Ljavax/servlet/DispatcherType;
     104: getstatic     #77                 // Field javax/servlet/DispatcherType.ASYNC:Ljavax/servlet/DispatcherType;
     107: invokestatic  #80                 // Method java/util/EnumSet.of:(Ljava/lang/Enum;Ljava/lang/Enum;)Ljava/util/EnumSet;
     110: invokevirtual #71                 // Method org/eclipse/jetty/servlet/ServletContextHandler.addFilter:(Ljava/lang/Class;Ljava/lang/String;Ljava/util/EnumSet;)Lorg/eclipse/jetty/servlet/FilterHolder;
     113: pop
     114: aload_3
     115: invokevirtual #83                 // Method org/eclipse/jetty/servlet/ServletContextHandler.getServletHandler:()Lorg/eclipse/jetty/servlet/ServletHandler;
     118: new           #87                 // class org/eclipse/jetty/servlet/ListenerHolder
     121: dup
     122: ldc           #89                 // class org/eclipse/jetty/demos/OneServletContext$InitListener
     124: invokespecial #91                 // Method org/eclipse/jetty/servlet/ListenerHolder."<init>":(Ljava/lang/Class;)V
     127: invokevirtual #94                 // Method org/eclipse/jetty/servlet/ServletHandler.addListener:(Lorg/eclipse/jetty/servlet/ListenerHolder;)V
     130: aload_3
     131: invokevirtual #83                 // Method org/eclipse/jetty/servlet/ServletContextHandler.getServletHandler:()Lorg/eclipse/jetty/servlet/ServletHandler;
     134: new           #87                 // class org/eclipse/jetty/servlet/ListenerHolder
     137: dup
     138: ldc           #100                // class org/eclipse/jetty/demos/OneServletContext$RequestListener
     140: invokespecial #91                 // Method org/eclipse/jetty/servlet/ListenerHolder."<init>":(Ljava/lang/Class;)V
     143: invokevirtual #94                 // Method org/eclipse/jetty/servlet/ServletHandler.addListener:(Lorg/eclipse/jetty/servlet/ListenerHolder;)V
     146: aload_2
     147: areturn

  public static void main(java.lang.String[]) throws java.lang.Exception;
    Code:
       0: aload_0
       1: ldc           #102                // String jetty.http.port
       3: sipush        8080
       6: invokestatic  #104                // Method org/eclipse/jetty/demos/ExampleUtil.getPort:([Ljava/lang/String;Ljava/lang/String;I)I
       9: istore_1
      10: ldc           #110                // String java.io.tmpdir
      12: invokestatic  #112                // Method java/lang/System.getProperty:(Ljava/lang/String;)Ljava/lang/String;
      15: iconst_0
      16: anewarray     #118                // class java/lang/String
      19: invokestatic  #120                // Method java/nio/file/Paths.get:(Ljava/lang/String;[Ljava/lang/String;)Ljava/nio/file/Path;
      22: astore_2
      23: iload_1
      24: new           #126                // class org/eclipse/jetty/util/resource/PathResource
      27: dup
      28: aload_2
      29: invokespecial #128                // Method org/eclipse/jetty/util/resource/PathResource."<init>":(Ljava/nio/file/Path;)V
      32: invokestatic  #131                // Method createServer:(ILorg/eclipse/jetty/util/resource/Resource;)Lorg/eclipse/jetty/server/Server;
      35: astore_3
      36: aload_3
      37: invokevirtual #137                // Method org/eclipse/jetty/server/Server.start:()V
      40: aload_3
      41: invokevirtual #140                // Method org/eclipse/jetty/server/Server.dumpStdErr:()V
      44: aload_3
      45: invokevirtual #143                // Method org/eclipse/jetty/server/Server.join:()V
      48: return
}
