Compiled from "AUtils.java"
public final class cn.omisheep.authz.core.util.AUtils {
  private static final org.slf4j.Logger log;

  private static org.springframework.context.ApplicationContext ctx;

  private cn.omisheep.authz.core.util.AUtils();
    Code:
       0: aload_0
       1: invokespecial #1                  // Method java/lang/Object."<init>":()V
       4: return

  public static <T> T getBean(java.lang.Class<T>);
    Code:
       0: getstatic     #2                  // Field ctx:Lorg/springframework/context/ApplicationContext;
       3: aload_0
       4: invokeinterface #3,  2            // InterfaceMethod org/springframework/context/ApplicationContext.getBean:(Ljava/lang/Class;)Ljava/lang/Object;
       9: areturn

  public static <T> T getBean(java.lang.String, java.lang.Class<T>);
    Code:
       0: getstatic     #2                  // Field ctx:Lorg/springframework/context/ApplicationContext;
       3: aload_0
       4: aload_1
       5: invokeinterface #4,  3            // InterfaceMethod org/springframework/context/ApplicationContext.getBean:(Ljava/lang/String;Ljava/lang/Class;)Ljava/lang/Object;
      10: areturn

  public static <T> java.util.Map<java.lang.String, T> getBeansOfType(java.lang.Class<T>);
    Code:
       0: getstatic     #2                  // Field ctx:Lorg/springframework/context/ApplicationContext;
       3: aload_0
       4: invokeinterface #5,  2            // InterfaceMethod org/springframework/context/ApplicationContext.getBeansOfType:(Ljava/lang/Class;)Ljava/util/Map;
       9: areturn

  public static void init(org.springframework.context.ApplicationContext);
    Code:
       0: aload_0
       1: putstatic     #2                  // Field ctx:Lorg/springframework/context/ApplicationContext;
       4: return

  public static cn.omisheep.authz.core.auth.ipf.HttpMeta getCurrentHttpMeta() throws cn.omisheep.authz.core.ThreadWebEnvironmentException;
    Code:
       0: invokestatic  #6                  // Method cn/omisheep/web/utils/HttpUtils.getCurrentRequest:()Ljavax/servlet/http/HttpServletRequest;
       3: ldc           #8                  // String AU_HTTP_META
       5: invokeinterface #9,  2            // InterfaceMethod javax/servlet/http/HttpServletRequest.getAttribute:(Ljava/lang/String;)Ljava/lang/Object;
      10: checkcast     #10                 // class cn/omisheep/authz/core/auth/ipf/HttpMeta
      13: astore_0
      14: aload_0
      15: ifnonnull     26
      18: new           #11                 // class cn/omisheep/authz/core/ThreadWebEnvironmentException
      21: dup
      22: invokespecial #12                 // Method cn/omisheep/authz/core/ThreadWebEnvironmentException."<init>":()V
      25: athrow
      26: aload_0
      27: areturn
      28: astore_0
      29: new           #11                 // class cn/omisheep/authz/core/ThreadWebEnvironmentException
      32: dup
      33: invokespecial #12                 // Method cn/omisheep/authz/core/ThreadWebEnvironmentException."<init>":()V
      36: athrow
    Exception table:
       from    to  target type
           0    27    28   Class java/lang/Exception

  public static cn.omisheep.authz.core.tk.Token getCurrentToken() throws cn.omisheep.authz.core.NotLoginException;
    Code:
       0: invokestatic  #14                 // Method getCurrentHttpMeta:()Lcn/omisheep/authz/core/auth/ipf/HttpMeta;
       3: invokevirtual #15                 // Method cn/omisheep/authz/core/auth/ipf/HttpMeta.getToken:()Lcn/omisheep/authz/core/tk/Token;
       6: astore_0
       7: aload_0
       8: ifnonnull     19
      11: new           #16                 // class cn/omisheep/authz/core/NotLoginException
      14: dup
      15: invokespecial #17                 // Method cn/omisheep/authz/core/NotLoginException."<init>":()V
      18: athrow
      19: aload_0
      20: areturn
      21: astore_0
      22: new           #16                 // class cn/omisheep/authz/core/NotLoginException
      25: dup
      26: invokespecial #17                 // Method cn/omisheep/authz/core/NotLoginException."<init>":()V
      29: athrow
    Exception table:
       from    to  target type
           0    20    21   Class java/lang/Exception

  static {};
    Code:
       0: ldc           #18                 // class cn/omisheep/authz/core/util/AUtils
       2: invokestatic  #19                 // Method org/slf4j/LoggerFactory.getLogger:(Ljava/lang/Class;)Lorg/slf4j/Logger;
       5: putstatic     #20                 // Field log:Lorg/slf4j/Logger;
       8: return
}
