Compiled from "DefaultSpdySynReplyFrame.java"
public class io.netty.handler.codec.spdy.DefaultSpdySynReplyFrame extends io.netty.handler.codec.spdy.DefaultSpdyHeadersFrame implements io.netty.handler.codec.spdy.SpdySynReplyFrame {
  public io.netty.handler.codec.spdy.DefaultSpdySynReplyFrame(int);
    Code:
       0: aload_0
       1: iload_1
       2: invokespecial #1                  // Method io/netty/handler/codec/spdy/DefaultSpdyHeadersFrame."<init>":(I)V
       5: return

  public io.netty.handler.codec.spdy.DefaultSpdySynReplyFrame(int, boolean);
    Code:
       0: aload_0
       1: iload_1
       2: iload_2
       3: invokespecial #2                  // Method io/netty/handler/codec/spdy/DefaultSpdyHeadersFrame."<init>":(IZ)V
       6: return

  public io.netty.handler.codec.spdy.SpdySynReplyFrame setStreamId(int);
    Code:
       0: aload_0
       1: iload_1
       2: invokespecial #3                  // Method io/netty/handler/codec/spdy/DefaultSpdyHeadersFrame.setStreamId:(I)Lio/netty/handler/codec/spdy/SpdyHeadersFrame;
       5: pop
       6: aload_0
       7: areturn

  public io.netty.handler.codec.spdy.SpdySynReplyFrame setLast(boolean);
    Code:
       0: aload_0
       1: iload_1
       2: invokespecial #4                  // Method io/netty/handler/codec/spdy/DefaultSpdyHeadersFrame.setLast:(Z)Lio/netty/handler/codec/spdy/SpdyHeadersFrame;
       5: pop
       6: aload_0
       7: areturn

  public io.netty.handler.codec.spdy.SpdySynReplyFrame setInvalid();
    Code:
       0: aload_0
       1: invokespecial #5                  // Method io/netty/handler/codec/spdy/DefaultSpdyHeadersFrame.setInvalid:()Lio/netty/handler/codec/spdy/SpdyHeadersFrame;
       4: pop
       5: aload_0
       6: areturn

  public java.lang.String toString();
    Code:
       0: new           #6                  // class java/lang/StringBuilder
       3: dup
       4: invokespecial #7                  // Method java/lang/StringBuilder."<init>":()V
       7: aload_0
       8: invokestatic  #8                  // Method io/netty/util/internal/StringUtil.simpleClassName:(Ljava/lang/Object;)Ljava/lang/String;
      11: invokevirtual #9                  // Method java/lang/StringBuilder.append:(Ljava/lang/String;)Ljava/lang/StringBuilder;
      14: ldc           #10                 // String (last:
      16: invokevirtual #9                  // Method java/lang/StringBuilder.append:(Ljava/lang/String;)Ljava/lang/StringBuilder;
      19: aload_0
      20: invokevirtual #11                 // Method isLast:()Z
      23: invokevirtual #12                 // Method java/lang/StringBuilder.append:(Z)Ljava/lang/StringBuilder;
      26: bipush        41
      28: invokevirtual #13                 // Method java/lang/StringBuilder.append:(C)Ljava/lang/StringBuilder;
      31: getstatic     #14                 // Field io/netty/util/internal/StringUtil.NEWLINE:Ljava/lang/String;
      34: invokevirtual #9                  // Method java/lang/StringBuilder.append:(Ljava/lang/String;)Ljava/lang/StringBuilder;
      37: ldc           #15                 // String --> Stream-ID =
      39: invokevirtual #9                  // Method java/lang/StringBuilder.append:(Ljava/lang/String;)Ljava/lang/StringBuilder;
      42: aload_0
      43: invokevirtual #16                 // Method streamId:()I
      46: invokevirtual #17                 // Method java/lang/StringBuilder.append:(I)Ljava/lang/StringBuilder;
      49: getstatic     #14                 // Field io/netty/util/internal/StringUtil.NEWLINE:Ljava/lang/String;
      52: invokevirtual #9                  // Method java/lang/StringBuilder.append:(Ljava/lang/String;)Ljava/lang/StringBuilder;
      55: ldc           #18                 // String --> Headers:
      57: invokevirtual #9                  // Method java/lang/StringBuilder.append:(Ljava/lang/String;)Ljava/lang/StringBuilder;
      60: getstatic     #14                 // Field io/netty/util/internal/StringUtil.NEWLINE:Ljava/lang/String;
      63: invokevirtual #9                  // Method java/lang/StringBuilder.append:(Ljava/lang/String;)Ljava/lang/StringBuilder;
      66: astore_1
      67: aload_0
      68: aload_1
      69: invokevirtual #19                 // Method appendHeaders:(Ljava/lang/StringBuilder;)V
      72: aload_1
      73: aload_1
      74: invokevirtual #20                 // Method java/lang/StringBuilder.length:()I
      77: getstatic     #14                 // Field io/netty/util/internal/StringUtil.NEWLINE:Ljava/lang/String;
      80: invokevirtual #21                 // Method java/lang/String.length:()I
      83: isub
      84: invokevirtual #22                 // Method java/lang/StringBuilder.setLength:(I)V
      87: aload_1
      88: invokevirtual #23                 // Method java/lang/StringBuilder.toString:()Ljava/lang/String;
      91: areturn

  public io.netty.handler.codec.spdy.SpdyHeadersFrame setInvalid();
    Code:
       0: aload_0
       1: invokevirtual #24                 // Method setInvalid:()Lio/netty/handler/codec/spdy/SpdySynReplyFrame;
       4: areturn

  public io.netty.handler.codec.spdy.SpdyHeadersFrame setLast(boolean);
    Code:
       0: aload_0
       1: iload_1
       2: invokevirtual #25                 // Method setLast:(Z)Lio/netty/handler/codec/spdy/SpdySynReplyFrame;
       5: areturn

  public io.netty.handler.codec.spdy.SpdyHeadersFrame setStreamId(int);
    Code:
       0: aload_0
       1: iload_1
       2: invokevirtual #26                 // Method setStreamId:(I)Lio/netty/handler/codec/spdy/SpdySynReplyFrame;
       5: areturn

  public io.netty.handler.codec.spdy.SpdyStreamFrame setLast(boolean);
    Code:
       0: aload_0
       1: iload_1
       2: invokevirtual #25                 // Method setLast:(Z)Lio/netty/handler/codec/spdy/SpdySynReplyFrame;
       5: areturn

  public io.netty.handler.codec.spdy.SpdyStreamFrame setStreamId(int);
    Code:
       0: aload_0
       1: iload_1
       2: invokevirtual #26                 // Method setStreamId:(I)Lio/netty/handler/codec/spdy/SpdySynReplyFrame;
       5: areturn
}
