Compiled from "DefaultSpdyHeaders.java"
final class io.netty.handler.codec.spdy.DefaultSpdyHeaders$1 implements io.netty.handler.codec.DefaultHeaders$NameValidator<java.lang.CharSequence> {
  io.netty.handler.codec.spdy.DefaultSpdyHeaders$1();
    Code:
       0: aload_0
       1: invokespecial #1                  // Method java/lang/Object."<init>":()V
       4: return

  public void validateName(java.lang.CharSequence);
    Code:
       0: aload_1
       1: invokestatic  #2                  // Method io/netty/handler/codec/spdy/SpdyCodecUtil.validateHeaderName:(Ljava/lang/CharSequence;)V
       4: return

  public void validateName(java.lang.Object);
    Code:
       0: aload_0
       1: aload_1
       2: checkcast     #3                  // class java/lang/CharSequence
       5: invokevirtual #4                  // Method validateName:(Ljava/lang/CharSequence;)V
       8: return
}
