Compiled from "SpdyFrameCodec.java"
public class io.netty.handler.codec.spdy.SpdyFrameCodec extends io.netty.handler.codec.ByteToMessageDecoder implements io.netty.handler.codec.spdy.SpdyFrameDecoderDelegate,io.netty.channel.ChannelOutboundHandler {
  private static final io.netty.handler.codec.spdy.SpdyProtocolException INVALID_FRAME;

  private final io.netty.handler.codec.spdy.SpdyFrameDecoder spdyFrameDecoder;

  private final io.netty.handler.codec.spdy.SpdyFrameEncoder spdyFrameEncoder;

  private final io.netty.handler.codec.spdy.SpdyHeaderBlockDecoder spdyHeaderBlockDecoder;

  private final io.netty.handler.codec.spdy.SpdyHeaderBlockEncoder spdyHeaderBlockEncoder;

  private io.netty.handler.codec.spdy.SpdyHeadersFrame spdyHeadersFrame;

  private io.netty.handler.codec.spdy.SpdySettingsFrame spdySettingsFrame;

  private io.netty.channel.ChannelHandlerContext ctx;

  private boolean read;

  private final boolean validateHeaders;

  public io.netty.handler.codec.spdy.SpdyFrameCodec(io.netty.handler.codec.spdy.SpdyVersion);
    Code:
       0: aload_0
       1: aload_1
       2: iconst_1
       3: invokespecial #3                  // Method "<init>":(Lio/netty/handler/codec/spdy/SpdyVersion;Z)V
       6: return

  public io.netty.handler.codec.spdy.SpdyFrameCodec(io.netty.handler.codec.spdy.SpdyVersion, boolean);
    Code:
       0: aload_0
       1: aload_1
       2: sipush        8192
       5: sipush        16384
       8: bipush        6
      10: bipush        15
      12: bipush        8
      14: iload_2
      15: invokespecial #4                  // Method "<init>":(Lio/netty/handler/codec/spdy/SpdyVersion;IIIIIZ)V
      18: return

  public io.netty.handler.codec.spdy.SpdyFrameCodec(io.netty.handler.codec.spdy.SpdyVersion, int, int, int, int, int);
    Code:
       0: aload_0
       1: aload_1
       2: iload_2
       3: iload_3
       4: iload         4
       6: iload         5
       8: iload         6
      10: iconst_1
      11: invokespecial #4                  // Method "<init>":(Lio/netty/handler/codec/spdy/SpdyVersion;IIIIIZ)V
      14: return

  public io.netty.handler.codec.spdy.SpdyFrameCodec(io.netty.handler.codec.spdy.SpdyVersion, int, int, int, int, int, boolean);
    Code:
       0: aload_0
       1: aload_1
       2: iload_2
       3: aload_1
       4: iload_3
       5: invokestatic  #5                  // Method io/netty/handler/codec/spdy/SpdyHeaderBlockDecoder.newInstance:(Lio/netty/handler/codec/spdy/SpdyVersion;I)Lio/netty/handler/codec/spdy/SpdyHeaderBlockDecoder;
       8: aload_1
       9: iload         4
      11: iload         5
      13: iload         6
      15: invokestatic  #6                  // Method io/netty/handler/codec/spdy/SpdyHeaderBlockEncoder.newInstance:(Lio/netty/handler/codec/spdy/SpdyVersion;III)Lio/netty/handler/codec/spdy/SpdyHeaderBlockEncoder;
      18: iload         7
      20: invokespecial #7                  // Method "<init>":(Lio/netty/handler/codec/spdy/SpdyVersion;ILio/netty/handler/codec/spdy/SpdyHeaderBlockDecoder;Lio/netty/handler/codec/spdy/SpdyHeaderBlockEncoder;Z)V
      23: return

  protected io.netty.handler.codec.spdy.SpdyFrameCodec(io.netty.handler.codec.spdy.SpdyVersion, int, io.netty.handler.codec.spdy.SpdyHeaderBlockDecoder, io.netty.handler.codec.spdy.SpdyHeaderBlockEncoder, boolean);
    Code:
       0: aload_0
       1: invokespecial #8                  // Method io/netty/handler/codec/ByteToMessageDecoder."<init>":()V
       4: aload_0
       5: new           #9                  // class io/netty/handler/codec/spdy/SpdyFrameDecoder
       8: dup
       9: aload_1
      10: aload_0
      11: iload_2
      12: invokespecial #10                 // Method io/netty/handler/codec/spdy/SpdyFrameDecoder."<init>":(Lio/netty/handler/codec/spdy/SpdyVersion;Lio/netty/handler/codec/spdy/SpdyFrameDecoderDelegate;I)V
      15: putfield      #11                 // Field spdyFrameDecoder:Lio/netty/handler/codec/spdy/SpdyFrameDecoder;
      18: aload_0
      19: new           #12                 // class io/netty/handler/codec/spdy/SpdyFrameEncoder
      22: dup
      23: aload_1
      24: invokespecial #13                 // Method io/netty/handler/codec/spdy/SpdyFrameEncoder."<init>":(Lio/netty/handler/codec/spdy/SpdyVersion;)V
      27: putfield      #14                 // Field spdyFrameEncoder:Lio/netty/handler/codec/spdy/SpdyFrameEncoder;
      30: aload_0
      31: aload_3
      32: putfield      #2                  // Field spdyHeaderBlockDecoder:Lio/netty/handler/codec/spdy/SpdyHeaderBlockDecoder;
      35: aload_0
      36: aload         4
      38: putfield      #1                  // Field spdyHeaderBlockEncoder:Lio/netty/handler/codec/spdy/SpdyHeaderBlockEncoder;
      41: aload_0
      42: iload         5
      44: putfield      #15                 // Field validateHeaders:Z
      47: return

  public void handlerAdded(io.netty.channel.ChannelHandlerContext) throws java.lang.Exception;
    Code:
       0: aload_0
       1: aload_1
       2: invokespecial #16                 // Method io/netty/handler/codec/ByteToMessageDecoder.handlerAdded:(Lio/netty/channel/ChannelHandlerContext;)V
       5: aload_0
       6: aload_1
       7: putfield      #17                 // Field ctx:Lio/netty/channel/ChannelHandlerContext;
      10: aload_1
      11: invokeinterface #18,  1           // InterfaceMethod io/netty/channel/ChannelHandlerContext.channel:()Lio/netty/channel/Channel;
      16: invokeinterface #19,  1           // InterfaceMethod io/netty/channel/Channel.closeFuture:()Lio/netty/channel/ChannelFuture;
      21: new           #20                 // class io/netty/handler/codec/spdy/SpdyFrameCodec$1
      24: dup
      25: aload_0
      26: invokespecial #21                 // Method io/netty/handler/codec/spdy/SpdyFrameCodec$1."<init>":(Lio/netty/handler/codec/spdy/SpdyFrameCodec;)V
      29: invokeinterface #22,  2           // InterfaceMethod io/netty/channel/ChannelFuture.addListener:(Lio/netty/util/concurrent/GenericFutureListener;)Lio/netty/channel/ChannelFuture;
      34: pop
      35: return

  protected void decode(io.netty.channel.ChannelHandlerContext, io.netty.buffer.ByteBuf, java.util.List<java.lang.Object>) throws java.lang.Exception;
    Code:
       0: aload_0
       1: getfield      #11                 // Field spdyFrameDecoder:Lio/netty/handler/codec/spdy/SpdyFrameDecoder;
       4: aload_2
       5: invokevirtual #23                 // Method io/netty/handler/codec/spdy/SpdyFrameDecoder.decode:(Lio/netty/buffer/ByteBuf;)V
       8: return

  public void channelReadComplete(io.netty.channel.ChannelHandlerContext) throws java.lang.Exception;
    Code:
       0: aload_0
       1: getfield      #24                 // Field read:Z
       4: ifne          33
       7: aload_1
       8: invokeinterface #18,  1           // InterfaceMethod io/netty/channel/ChannelHandlerContext.channel:()Lio/netty/channel/Channel;
      13: invokeinterface #25,  1           // InterfaceMethod io/netty/channel/Channel.config:()Lio/netty/channel/ChannelConfig;
      18: invokeinterface #26,  1           // InterfaceMethod io/netty/channel/ChannelConfig.isAutoRead:()Z
      23: ifne          33
      26: aload_1
      27: invokeinterface #27,  1           // InterfaceMethod io/netty/channel/ChannelHandlerContext.read:()Lio/netty/channel/ChannelHandlerContext;
      32: pop
      33: aload_0
      34: iconst_0
      35: putfield      #24                 // Field read:Z
      38: aload_0
      39: aload_1
      40: invokespecial #28                 // Method io/netty/handler/codec/ByteToMessageDecoder.channelReadComplete:(Lio/netty/channel/ChannelHandlerContext;)V
      43: return

  public void bind(io.netty.channel.ChannelHandlerContext, java.net.SocketAddress, io.netty.channel.ChannelPromise) throws java.lang.Exception;
    Code:
       0: aload_1
       1: aload_2
       2: aload_3
       3: invokeinterface #29,  3           // InterfaceMethod io/netty/channel/ChannelHandlerContext.bind:(Ljava/net/SocketAddress;Lio/netty/channel/ChannelPromise;)Lio/netty/channel/ChannelFuture;
       8: pop
       9: return

  public void connect(io.netty.channel.ChannelHandlerContext, java.net.SocketAddress, java.net.SocketAddress, io.netty.channel.ChannelPromise) throws java.lang.Exception;
    Code:
       0: aload_1
       1: aload_2
       2: aload_3
       3: aload         4
       5: invokeinterface #30,  4           // InterfaceMethod io/netty/channel/ChannelHandlerContext.connect:(Ljava/net/SocketAddress;Ljava/net/SocketAddress;Lio/netty/channel/ChannelPromise;)Lio/netty/channel/ChannelFuture;
      10: pop
      11: return

  public void disconnect(io.netty.channel.ChannelHandlerContext, io.netty.channel.ChannelPromise) throws java.lang.Exception;
    Code:
       0: aload_1
       1: aload_2
       2: invokeinterface #31,  2           // InterfaceMethod io/netty/channel/ChannelHandlerContext.disconnect:(Lio/netty/channel/ChannelPromise;)Lio/netty/channel/ChannelFuture;
       7: pop
       8: return

  public void close(io.netty.channel.ChannelHandlerContext, io.netty.channel.ChannelPromise) throws java.lang.Exception;
    Code:
       0: aload_1
       1: aload_2
       2: invokeinterface #32,  2           // InterfaceMethod io/netty/channel/ChannelHandlerContext.close:(Lio/netty/channel/ChannelPromise;)Lio/netty/channel/ChannelFuture;
       7: pop
       8: return

  public void deregister(io.netty.channel.ChannelHandlerContext, io.netty.channel.ChannelPromise) throws java.lang.Exception;
    Code:
       0: aload_1
       1: aload_2
       2: invokeinterface #33,  2           // InterfaceMethod io/netty/channel/ChannelHandlerContext.deregister:(Lio/netty/channel/ChannelPromise;)Lio/netty/channel/ChannelFuture;
       7: pop
       8: return

  public void read(io.netty.channel.ChannelHandlerContext) throws java.lang.Exception;
    Code:
       0: aload_1
       1: invokeinterface #27,  1           // InterfaceMethod io/netty/channel/ChannelHandlerContext.read:()Lio/netty/channel/ChannelHandlerContext;
       6: pop
       7: return

  public void flush(io.netty.channel.ChannelHandlerContext) throws java.lang.Exception;
    Code:
       0: aload_1
       1: invokeinterface #34,  1           // InterfaceMethod io/netty/channel/ChannelHandlerContext.flush:()Lio/netty/channel/ChannelHandlerContext;
       6: pop
       7: return

  public void write(io.netty.channel.ChannelHandlerContext, java.lang.Object, io.netty.channel.ChannelPromise) throws java.lang.Exception;
    Code:
       0: aload_2
       1: instanceof    #35                 // class io/netty/handler/codec/spdy/SpdyDataFrame
       4: ifeq          70
       7: aload_2
       8: checkcast     #35                 // class io/netty/handler/codec/spdy/SpdyDataFrame
      11: astore        5
      13: aload_0
      14: getfield      #14                 // Field spdyFrameEncoder:Lio/netty/handler/codec/spdy/SpdyFrameEncoder;
      17: aload_1
      18: invokeinterface #36,  1           // InterfaceMethod io/netty/channel/ChannelHandlerContext.alloc:()Lio/netty/buffer/ByteBufAllocator;
      23: aload         5
      25: invokeinterface #37,  1           // InterfaceMethod io/netty/handler/codec/spdy/SpdyDataFrame.streamId:()I
      30: aload         5
      32: invokeinterface #38,  1           // InterfaceMethod io/netty/handler/codec/spdy/SpdyDataFrame.isLast:()Z
      37: aload         5
      39: invokeinterface #39,  1           // InterfaceMethod io/netty/handler/codec/spdy/SpdyDataFrame.content:()Lio/netty/buffer/ByteBuf;
      44: invokevirtual #40                 // Method io/netty/handler/codec/spdy/SpdyFrameEncoder.encodeDataFrame:(Lio/netty/buffer/ByteBufAllocator;IZLio/netty/buffer/ByteBuf;)Lio/netty/buffer/ByteBuf;
      47: astore        4
      49: aload         5
      51: invokeinterface #41,  1           // InterfaceMethod io/netty/handler/codec/spdy/SpdyDataFrame.release:()Z
      56: pop
      57: aload_1
      58: aload         4
      60: aload_3
      61: invokeinterface #42,  3           // InterfaceMethod io/netty/channel/ChannelHandlerContext.write:(Ljava/lang/Object;Lio/netty/channel/ChannelPromise;)Lio/netty/channel/ChannelFuture;
      66: pop
      67: goto          648
      70: aload_2
      71: instanceof    #43                 // class io/netty/handler/codec/spdy/SpdySynStreamFrame
      74: ifeq          185
      77: aload_2
      78: checkcast     #43                 // class io/netty/handler/codec/spdy/SpdySynStreamFrame
      81: astore        5
      83: aload_0
      84: getfield      #1                  // Field spdyHeaderBlockEncoder:Lio/netty/handler/codec/spdy/SpdyHeaderBlockEncoder;
      87: aload_1
      88: invokeinterface #36,  1           // InterfaceMethod io/netty/channel/ChannelHandlerContext.alloc:()Lio/netty/buffer/ByteBufAllocator;
      93: aload         5
      95: invokevirtual #44                 // Method io/netty/handler/codec/spdy/SpdyHeaderBlockEncoder.encode:(Lio/netty/buffer/ByteBufAllocator;Lio/netty/handler/codec/spdy/SpdyHeadersFrame;)Lio/netty/buffer/ByteBuf;
      98: astore        6
     100: aload_0
     101: getfield      #14                 // Field spdyFrameEncoder:Lio/netty/handler/codec/spdy/SpdyFrameEncoder;
     104: aload_1
     105: invokeinterface #36,  1           // InterfaceMethod io/netty/channel/ChannelHandlerContext.alloc:()Lio/netty/buffer/ByteBufAllocator;
     110: aload         5
     112: invokeinterface #45,  1           // InterfaceMethod io/netty/handler/codec/spdy/SpdySynStreamFrame.streamId:()I
     117: aload         5
     119: invokeinterface #46,  1           // InterfaceMethod io/netty/handler/codec/spdy/SpdySynStreamFrame.associatedStreamId:()I
     124: aload         5
     126: invokeinterface #47,  1           // InterfaceMethod io/netty/handler/codec/spdy/SpdySynStreamFrame.priority:()B
     131: aload         5
     133: invokeinterface #48,  1           // InterfaceMethod io/netty/handler/codec/spdy/SpdySynStreamFrame.isLast:()Z
     138: aload         5
     140: invokeinterface #49,  1           // InterfaceMethod io/netty/handler/codec/spdy/SpdySynStreamFrame.isUnidirectional:()Z
     145: aload         6
     147: invokevirtual #50                 // Method io/netty/handler/codec/spdy/SpdyFrameEncoder.encodeSynStreamFrame:(Lio/netty/buffer/ByteBufAllocator;IIBZZLio/netty/buffer/ByteBuf;)Lio/netty/buffer/ByteBuf;
     150: astore        4
     152: aload         6
     154: invokevirtual #51                 // Method io/netty/buffer/ByteBuf.release:()Z
     157: pop
     158: goto          172
     161: astore        7
     163: aload         6
     165: invokevirtual #51                 // Method io/netty/buffer/ByteBuf.release:()Z
     168: pop
     169: aload         7
     171: athrow
     172: aload_1
     173: aload         4
     175: aload_3
     176: invokeinterface #42,  3           // InterfaceMethod io/netty/channel/ChannelHandlerContext.write:(Ljava/lang/Object;Lio/netty/channel/ChannelPromise;)Lio/netty/channel/ChannelFuture;
     181: pop
     182: goto          648
     185: aload_2
     186: instanceof    #52                 // class io/netty/handler/codec/spdy/SpdySynReplyFrame
     189: ifeq          279
     192: aload_2
     193: checkcast     #52                 // class io/netty/handler/codec/spdy/SpdySynReplyFrame
     196: astore        5
     198: aload_0
     199: getfield      #1                  // Field spdyHeaderBlockEncoder:Lio/netty/handler/codec/spdy/SpdyHeaderBlockEncoder;
     202: aload_1
     203: invokeinterface #36,  1           // InterfaceMethod io/netty/channel/ChannelHandlerContext.alloc:()Lio/netty/buffer/ByteBufAllocator;
     208: aload         5
     210: invokevirtual #44                 // Method io/netty/handler/codec/spdy/SpdyHeaderBlockEncoder.encode:(Lio/netty/buffer/ByteBufAllocator;Lio/netty/handler/codec/spdy/SpdyHeadersFrame;)Lio/netty/buffer/ByteBuf;
     213: astore        6
     215: aload_0
     216: getfield      #14                 // Field spdyFrameEncoder:Lio/netty/handler/codec/spdy/SpdyFrameEncoder;
     219: aload_1
     220: invokeinterface #36,  1           // InterfaceMethod io/netty/channel/ChannelHandlerContext.alloc:()Lio/netty/buffer/ByteBufAllocator;
     225: aload         5
     227: invokeinterface #53,  1           // InterfaceMethod io/netty/handler/codec/spdy/SpdySynReplyFrame.streamId:()I
     232: aload         5
     234: invokeinterface #54,  1           // InterfaceMethod io/netty/handler/codec/spdy/SpdySynReplyFrame.isLast:()Z
     239: aload         6
     241: invokevirtual #55                 // Method io/netty/handler/codec/spdy/SpdyFrameEncoder.encodeSynReplyFrame:(Lio/netty/buffer/ByteBufAllocator;IZLio/netty/buffer/ByteBuf;)Lio/netty/buffer/ByteBuf;
     244: astore        4
     246: aload         6
     248: invokevirtual #51                 // Method io/netty/buffer/ByteBuf.release:()Z
     251: pop
     252: goto          266
     255: astore        8
     257: aload         6
     259: invokevirtual #51                 // Method io/netty/buffer/ByteBuf.release:()Z
     262: pop
     263: aload         8
     265: athrow
     266: aload_1
     267: aload         4
     269: aload_3
     270: invokeinterface #42,  3           // InterfaceMethod io/netty/channel/ChannelHandlerContext.write:(Ljava/lang/Object;Lio/netty/channel/ChannelPromise;)Lio/netty/channel/ChannelFuture;
     275: pop
     276: goto          648
     279: aload_2
     280: instanceof    #56                 // class io/netty/handler/codec/spdy/SpdyRstStreamFrame
     283: ifeq          337
     286: aload_2
     287: checkcast     #56                 // class io/netty/handler/codec/spdy/SpdyRstStreamFrame
     290: astore        5
     292: aload_0
     293: getfield      #14                 // Field spdyFrameEncoder:Lio/netty/handler/codec/spdy/SpdyFrameEncoder;
     296: aload_1
     297: invokeinterface #36,  1           // InterfaceMethod io/netty/channel/ChannelHandlerContext.alloc:()Lio/netty/buffer/ByteBufAllocator;
     302: aload         5
     304: invokeinterface #57,  1           // InterfaceMethod io/netty/handler/codec/spdy/SpdyRstStreamFrame.streamId:()I
     309: aload         5
     311: invokeinterface #58,  1           // InterfaceMethod io/netty/handler/codec/spdy/SpdyRstStreamFrame.status:()Lio/netty/handler/codec/spdy/SpdyStreamStatus;
     316: invokevirtual #59                 // Method io/netty/handler/codec/spdy/SpdyStreamStatus.code:()I
     319: invokevirtual #60                 // Method io/netty/handler/codec/spdy/SpdyFrameEncoder.encodeRstStreamFrame:(Lio/netty/buffer/ByteBufAllocator;II)Lio/netty/buffer/ByteBuf;
     322: astore        4
     324: aload_1
     325: aload         4
     327: aload_3
     328: invokeinterface #42,  3           // InterfaceMethod io/netty/channel/ChannelHandlerContext.write:(Ljava/lang/Object;Lio/netty/channel/ChannelPromise;)Lio/netty/channel/ChannelFuture;
     333: pop
     334: goto          648
     337: aload_2
     338: instanceof    #61                 // class io/netty/handler/codec/spdy/SpdySettingsFrame
     341: ifeq          380
     344: aload_2
     345: checkcast     #61                 // class io/netty/handler/codec/spdy/SpdySettingsFrame
     348: astore        5
     350: aload_0
     351: getfield      #14                 // Field spdyFrameEncoder:Lio/netty/handler/codec/spdy/SpdyFrameEncoder;
     354: aload_1
     355: invokeinterface #36,  1           // InterfaceMethod io/netty/channel/ChannelHandlerContext.alloc:()Lio/netty/buffer/ByteBufAllocator;
     360: aload         5
     362: invokevirtual #62                 // Method io/netty/handler/codec/spdy/SpdyFrameEncoder.encodeSettingsFrame:(Lio/netty/buffer/ByteBufAllocator;Lio/netty/handler/codec/spdy/SpdySettingsFrame;)Lio/netty/buffer/ByteBuf;
     365: astore        4
     367: aload_1
     368: aload         4
     370: aload_3
     371: invokeinterface #42,  3           // InterfaceMethod io/netty/channel/ChannelHandlerContext.write:(Ljava/lang/Object;Lio/netty/channel/ChannelPromise;)Lio/netty/channel/ChannelFuture;
     376: pop
     377: goto          648
     380: aload_2
     381: instanceof    #63                 // class io/netty/handler/codec/spdy/SpdyPingFrame
     384: ifeq          428
     387: aload_2
     388: checkcast     #63                 // class io/netty/handler/codec/spdy/SpdyPingFrame
     391: astore        5
     393: aload_0
     394: getfield      #14                 // Field spdyFrameEncoder:Lio/netty/handler/codec/spdy/SpdyFrameEncoder;
     397: aload_1
     398: invokeinterface #36,  1           // InterfaceMethod io/netty/channel/ChannelHandlerContext.alloc:()Lio/netty/buffer/ByteBufAllocator;
     403: aload         5
     405: invokeinterface #64,  1           // InterfaceMethod io/netty/handler/codec/spdy/SpdyPingFrame.id:()I
     410: invokevirtual #65                 // Method io/netty/handler/codec/spdy/SpdyFrameEncoder.encodePingFrame:(Lio/netty/buffer/ByteBufAllocator;I)Lio/netty/buffer/ByteBuf;
     413: astore        4
     415: aload_1
     416: aload         4
     418: aload_3
     419: invokeinterface #42,  3           // InterfaceMethod io/netty/channel/ChannelHandlerContext.write:(Ljava/lang/Object;Lio/netty/channel/ChannelPromise;)Lio/netty/channel/ChannelFuture;
     424: pop
     425: goto          648
     428: aload_2
     429: instanceof    #66                 // class io/netty/handler/codec/spdy/SpdyGoAwayFrame
     432: ifeq          486
     435: aload_2
     436: checkcast     #66                 // class io/netty/handler/codec/spdy/SpdyGoAwayFrame
     439: astore        5
     441: aload_0
     442: getfield      #14                 // Field spdyFrameEncoder:Lio/netty/handler/codec/spdy/SpdyFrameEncoder;
     445: aload_1
     446: invokeinterface #36,  1           // InterfaceMethod io/netty/channel/ChannelHandlerContext.alloc:()Lio/netty/buffer/ByteBufAllocator;
     451: aload         5
     453: invokeinterface #67,  1           // InterfaceMethod io/netty/handler/codec/spdy/SpdyGoAwayFrame.lastGoodStreamId:()I
     458: aload         5
     460: invokeinterface #68,  1           // InterfaceMethod io/netty/handler/codec/spdy/SpdyGoAwayFrame.status:()Lio/netty/handler/codec/spdy/SpdySessionStatus;
     465: invokevirtual #69                 // Method io/netty/handler/codec/spdy/SpdySessionStatus.code:()I
     468: invokevirtual #70                 // Method io/netty/handler/codec/spdy/SpdyFrameEncoder.encodeGoAwayFrame:(Lio/netty/buffer/ByteBufAllocator;II)Lio/netty/buffer/ByteBuf;
     471: astore        4
     473: aload_1
     474: aload         4
     476: aload_3
     477: invokeinterface #42,  3           // InterfaceMethod io/netty/channel/ChannelHandlerContext.write:(Ljava/lang/Object;Lio/netty/channel/ChannelPromise;)Lio/netty/channel/ChannelFuture;
     482: pop
     483: goto          648
     486: aload_2
     487: instanceof    #71                 // class io/netty/handler/codec/spdy/SpdyHeadersFrame
     490: ifeq          580
     493: aload_2
     494: checkcast     #71                 // class io/netty/handler/codec/spdy/SpdyHeadersFrame
     497: astore        5
     499: aload_0
     500: getfield      #1                  // Field spdyHeaderBlockEncoder:Lio/netty/handler/codec/spdy/SpdyHeaderBlockEncoder;
     503: aload_1
     504: invokeinterface #36,  1           // InterfaceMethod io/netty/channel/ChannelHandlerContext.alloc:()Lio/netty/buffer/ByteBufAllocator;
     509: aload         5
     511: invokevirtual #44                 // Method io/netty/handler/codec/spdy/SpdyHeaderBlockEncoder.encode:(Lio/netty/buffer/ByteBufAllocator;Lio/netty/handler/codec/spdy/SpdyHeadersFrame;)Lio/netty/buffer/ByteBuf;
     514: astore        6
     516: aload_0
     517: getfield      #14                 // Field spdyFrameEncoder:Lio/netty/handler/codec/spdy/SpdyFrameEncoder;
     520: aload_1
     521: invokeinterface #36,  1           // InterfaceMethod io/netty/channel/ChannelHandlerContext.alloc:()Lio/netty/buffer/ByteBufAllocator;
     526: aload         5
     528: invokeinterface #72,  1           // InterfaceMethod io/netty/handler/codec/spdy/SpdyHeadersFrame.streamId:()I
     533: aload         5
     535: invokeinterface #73,  1           // InterfaceMethod io/netty/handler/codec/spdy/SpdyHeadersFrame.isLast:()Z
     540: aload         6
     542: invokevirtual #74                 // Method io/netty/handler/codec/spdy/SpdyFrameEncoder.encodeHeadersFrame:(Lio/netty/buffer/ByteBufAllocator;IZLio/netty/buffer/ByteBuf;)Lio/netty/buffer/ByteBuf;
     545: astore        4
     547: aload         6
     549: invokevirtual #51                 // Method io/netty/buffer/ByteBuf.release:()Z
     552: pop
     553: goto          567
     556: astore        9
     558: aload         6
     560: invokevirtual #51                 // Method io/netty/buffer/ByteBuf.release:()Z
     563: pop
     564: aload         9
     566: athrow
     567: aload_1
     568: aload         4
     570: aload_3
     571: invokeinterface #42,  3           // InterfaceMethod io/netty/channel/ChannelHandlerContext.write:(Ljava/lang/Object;Lio/netty/channel/ChannelPromise;)Lio/netty/channel/ChannelFuture;
     576: pop
     577: goto          648
     580: aload_2
     581: instanceof    #75                 // class io/netty/handler/codec/spdy/SpdyWindowUpdateFrame
     584: ifeq          635
     587: aload_2
     588: checkcast     #75                 // class io/netty/handler/codec/spdy/SpdyWindowUpdateFrame
     591: astore        5
     593: aload_0
     594: getfield      #14                 // Field spdyFrameEncoder:Lio/netty/handler/codec/spdy/SpdyFrameEncoder;
     597: aload_1
     598: invokeinterface #36,  1           // InterfaceMethod io/netty/channel/ChannelHandlerContext.alloc:()Lio/netty/buffer/ByteBufAllocator;
     603: aload         5
     605: invokeinterface #76,  1           // InterfaceMethod io/netty/handler/codec/spdy/SpdyWindowUpdateFrame.streamId:()I
     610: aload         5
     612: invokeinterface #77,  1           // InterfaceMethod io/netty/handler/codec/spdy/SpdyWindowUpdateFrame.deltaWindowSize:()I
     617: invokevirtual #78                 // Method io/netty/handler/codec/spdy/SpdyFrameEncoder.encodeWindowUpdateFrame:(Lio/netty/buffer/ByteBufAllocator;II)Lio/netty/buffer/ByteBuf;
     620: astore        4
     622: aload_1
     623: aload         4
     625: aload_3
     626: invokeinterface #42,  3           // InterfaceMethod io/netty/channel/ChannelHandlerContext.write:(Ljava/lang/Object;Lio/netty/channel/ChannelPromise;)Lio/netty/channel/ChannelFuture;
     631: pop
     632: goto          648
     635: new           #79                 // class io/netty/handler/codec/UnsupportedMessageTypeException
     638: dup
     639: aload_2
     640: iconst_0
     641: anewarray     #80                 // class java/lang/Class
     644: invokespecial #81                 // Method io/netty/handler/codec/UnsupportedMessageTypeException."<init>":(Ljava/lang/Object;[Ljava/lang/Class;)V
     647: athrow
     648: return
    Exception table:
       from    to  target type
         100   152   161   any
         161   163   161   any
         215   246   255   any
         255   257   255   any
         516   547   556   any
         556   558   556   any

  public void readDataFrame(int, boolean, io.netty.buffer.ByteBuf);
    Code:
       0: aload_0
       1: iconst_1
       2: putfield      #24                 // Field read:Z
       5: new           #82                 // class io/netty/handler/codec/spdy/DefaultSpdyDataFrame
       8: dup
       9: iload_1
      10: aload_3
      11: invokespecial #83                 // Method io/netty/handler/codec/spdy/DefaultSpdyDataFrame."<init>":(ILio/netty/buffer/ByteBuf;)V
      14: astore        4
      16: aload         4
      18: iload_2
      19: invokeinterface #84,  2           // InterfaceMethod io/netty/handler/codec/spdy/SpdyDataFrame.setLast:(Z)Lio/netty/handler/codec/spdy/SpdyDataFrame;
      24: pop
      25: aload_0
      26: getfield      #17                 // Field ctx:Lio/netty/channel/ChannelHandlerContext;
      29: aload         4
      31: invokeinterface #85,  2           // InterfaceMethod io/netty/channel/ChannelHandlerContext.fireChannelRead:(Ljava/lang/Object;)Lio/netty/channel/ChannelHandlerContext;
      36: pop
      37: return

  public void readSynStreamFrame(int, int, byte, boolean, boolean);
    Code:
       0: new           #86                 // class io/netty/handler/codec/spdy/DefaultSpdySynStreamFrame
       3: dup
       4: iload_1
       5: iload_2
       6: iload_3
       7: aload_0
       8: getfield      #15                 // Field validateHeaders:Z
      11: invokespecial #87                 // Method io/netty/handler/codec/spdy/DefaultSpdySynStreamFrame."<init>":(IIBZ)V
      14: astore        6
      16: aload         6
      18: iload         4
      20: invokeinterface #88,  2           // InterfaceMethod io/netty/handler/codec/spdy/SpdySynStreamFrame.setLast:(Z)Lio/netty/handler/codec/spdy/SpdySynStreamFrame;
      25: pop
      26: aload         6
      28: iload         5
      30: invokeinterface #89,  2           // InterfaceMethod io/netty/handler/codec/spdy/SpdySynStreamFrame.setUnidirectional:(Z)Lio/netty/handler/codec/spdy/SpdySynStreamFrame;
      35: pop
      36: aload_0
      37: aload         6
      39: putfield      #90                 // Field spdyHeadersFrame:Lio/netty/handler/codec/spdy/SpdyHeadersFrame;
      42: return

  public void readSynReplyFrame(int, boolean);
    Code:
       0: new           #91                 // class io/netty/handler/codec/spdy/DefaultSpdySynReplyFrame
       3: dup
       4: iload_1
       5: aload_0
       6: getfield      #15                 // Field validateHeaders:Z
       9: invokespecial #92                 // Method io/netty/handler/codec/spdy/DefaultSpdySynReplyFrame."<init>":(IZ)V
      12: astore_3
      13: aload_3
      14: iload_2
      15: invokeinterface #93,  2           // InterfaceMethod io/netty/handler/codec/spdy/SpdySynReplyFrame.setLast:(Z)Lio/netty/handler/codec/spdy/SpdySynReplyFrame;
      20: pop
      21: aload_0
      22: aload_3
      23: putfield      #90                 // Field spdyHeadersFrame:Lio/netty/handler/codec/spdy/SpdyHeadersFrame;
      26: return

  public void readRstStreamFrame(int, int);
    Code:
       0: aload_0
       1: iconst_1
       2: putfield      #24                 // Field read:Z
       5: new           #94                 // class io/netty/handler/codec/spdy/DefaultSpdyRstStreamFrame
       8: dup
       9: iload_1
      10: iload_2
      11: invokespecial #95                 // Method io/netty/handler/codec/spdy/DefaultSpdyRstStreamFrame."<init>":(II)V
      14: astore_3
      15: aload_0
      16: getfield      #17                 // Field ctx:Lio/netty/channel/ChannelHandlerContext;
      19: aload_3
      20: invokeinterface #85,  2           // InterfaceMethod io/netty/channel/ChannelHandlerContext.fireChannelRead:(Ljava/lang/Object;)Lio/netty/channel/ChannelHandlerContext;
      25: pop
      26: return

  public void readSettingsFrame(boolean);
    Code:
       0: aload_0
       1: iconst_1
       2: putfield      #24                 // Field read:Z
       5: aload_0
       6: new           #96                 // class io/netty/handler/codec/spdy/DefaultSpdySettingsFrame
       9: dup
      10: invokespecial #97                 // Method io/netty/handler/codec/spdy/DefaultSpdySettingsFrame."<init>":()V
      13: putfield      #98                 // Field spdySettingsFrame:Lio/netty/handler/codec/spdy/SpdySettingsFrame;
      16: aload_0
      17: getfield      #98                 // Field spdySettingsFrame:Lio/netty/handler/codec/spdy/SpdySettingsFrame;
      20: iload_1
      21: invokeinterface #99,  2           // InterfaceMethod io/netty/handler/codec/spdy/SpdySettingsFrame.setClearPreviouslyPersistedSettings:(Z)Lio/netty/handler/codec/spdy/SpdySettingsFrame;
      26: pop
      27: return

  public void readSetting(int, int, boolean, boolean);
    Code:
       0: aload_0
       1: getfield      #98                 // Field spdySettingsFrame:Lio/netty/handler/codec/spdy/SpdySettingsFrame;
       4: iload_1
       5: iload_2
       6: iload_3
       7: iload         4
       9: invokeinterface #100,  5          // InterfaceMethod io/netty/handler/codec/spdy/SpdySettingsFrame.setValue:(IIZZ)Lio/netty/handler/codec/spdy/SpdySettingsFrame;
      14: pop
      15: return

  public void readSettingsEnd();
    Code:
       0: aload_0
       1: iconst_1
       2: putfield      #24                 // Field read:Z
       5: aload_0
       6: getfield      #98                 // Field spdySettingsFrame:Lio/netty/handler/codec/spdy/SpdySettingsFrame;
       9: astore_1
      10: aload_0
      11: aconst_null
      12: putfield      #98                 // Field spdySettingsFrame:Lio/netty/handler/codec/spdy/SpdySettingsFrame;
      15: aload_0
      16: getfield      #17                 // Field ctx:Lio/netty/channel/ChannelHandlerContext;
      19: aload_1
      20: invokeinterface #85,  2           // InterfaceMethod io/netty/channel/ChannelHandlerContext.fireChannelRead:(Ljava/lang/Object;)Lio/netty/channel/ChannelHandlerContext;
      25: pop
      26: return

  public void readPingFrame(int);
    Code:
       0: aload_0
       1: iconst_1
       2: putfield      #24                 // Field read:Z
       5: new           #101                // class io/netty/handler/codec/spdy/DefaultSpdyPingFrame
       8: dup
       9: iload_1
      10: invokespecial #102                // Method io/netty/handler/codec/spdy/DefaultSpdyPingFrame."<init>":(I)V
      13: astore_2
      14: aload_0
      15: getfield      #17                 // Field ctx:Lio/netty/channel/ChannelHandlerContext;
      18: aload_2
      19: invokeinterface #85,  2           // InterfaceMethod io/netty/channel/ChannelHandlerContext.fireChannelRead:(Ljava/lang/Object;)Lio/netty/channel/ChannelHandlerContext;
      24: pop
      25: return

  public void readGoAwayFrame(int, int);
    Code:
       0: aload_0
       1: iconst_1
       2: putfield      #24                 // Field read:Z
       5: new           #103                // class io/netty/handler/codec/spdy/DefaultSpdyGoAwayFrame
       8: dup
       9: iload_1
      10: iload_2
      11: invokespecial #104                // Method io/netty/handler/codec/spdy/DefaultSpdyGoAwayFrame."<init>":(II)V
      14: astore_3
      15: aload_0
      16: getfield      #17                 // Field ctx:Lio/netty/channel/ChannelHandlerContext;
      19: aload_3
      20: invokeinterface #85,  2           // InterfaceMethod io/netty/channel/ChannelHandlerContext.fireChannelRead:(Ljava/lang/Object;)Lio/netty/channel/ChannelHandlerContext;
      25: pop
      26: return

  public void readHeadersFrame(int, boolean);
    Code:
       0: aload_0
       1: new           #105                // class io/netty/handler/codec/spdy/DefaultSpdyHeadersFrame
       4: dup
       5: iload_1
       6: aload_0
       7: getfield      #15                 // Field validateHeaders:Z
      10: invokespecial #106                // Method io/netty/handler/codec/spdy/DefaultSpdyHeadersFrame."<init>":(IZ)V
      13: putfield      #90                 // Field spdyHeadersFrame:Lio/netty/handler/codec/spdy/SpdyHeadersFrame;
      16: aload_0
      17: getfield      #90                 // Field spdyHeadersFrame:Lio/netty/handler/codec/spdy/SpdyHeadersFrame;
      20: iload_2
      21: invokeinterface #107,  2          // InterfaceMethod io/netty/handler/codec/spdy/SpdyHeadersFrame.setLast:(Z)Lio/netty/handler/codec/spdy/SpdyHeadersFrame;
      26: pop
      27: return

  public void readWindowUpdateFrame(int, int);
    Code:
       0: aload_0
       1: iconst_1
       2: putfield      #24                 // Field read:Z
       5: new           #108                // class io/netty/handler/codec/spdy/DefaultSpdyWindowUpdateFrame
       8: dup
       9: iload_1
      10: iload_2
      11: invokespecial #109                // Method io/netty/handler/codec/spdy/DefaultSpdyWindowUpdateFrame."<init>":(II)V
      14: astore_3
      15: aload_0
      16: getfield      #17                 // Field ctx:Lio/netty/channel/ChannelHandlerContext;
      19: aload_3
      20: invokeinterface #85,  2           // InterfaceMethod io/netty/channel/ChannelHandlerContext.fireChannelRead:(Ljava/lang/Object;)Lio/netty/channel/ChannelHandlerContext;
      25: pop
      26: return

  public void readHeaderBlock(io.netty.buffer.ByteBuf);
    Code:
       0: aload_0
       1: getfield      #2                  // Field spdyHeaderBlockDecoder:Lio/netty/handler/codec/spdy/SpdyHeaderBlockDecoder;
       4: aload_0
       5: getfield      #17                 // Field ctx:Lio/netty/channel/ChannelHandlerContext;
       8: invokeinterface #36,  1           // InterfaceMethod io/netty/channel/ChannelHandlerContext.alloc:()Lio/netty/buffer/ByteBufAllocator;
      13: aload_1
      14: aload_0
      15: getfield      #90                 // Field spdyHeadersFrame:Lio/netty/handler/codec/spdy/SpdyHeadersFrame;
      18: invokevirtual #110                // Method io/netty/handler/codec/spdy/SpdyHeaderBlockDecoder.decode:(Lio/netty/buffer/ByteBufAllocator;Lio/netty/buffer/ByteBuf;Lio/netty/handler/codec/spdy/SpdyHeadersFrame;)V
      21: aload_1
      22: invokevirtual #51                 // Method io/netty/buffer/ByteBuf.release:()Z
      25: pop
      26: goto          57
      29: astore_2
      30: aload_0
      31: getfield      #17                 // Field ctx:Lio/netty/channel/ChannelHandlerContext;
      34: aload_2
      35: invokeinterface #112,  2          // InterfaceMethod io/netty/channel/ChannelHandlerContext.fireExceptionCaught:(Ljava/lang/Throwable;)Lio/netty/channel/ChannelHandlerContext;
      40: pop
      41: aload_1
      42: invokevirtual #51                 // Method io/netty/buffer/ByteBuf.release:()Z
      45: pop
      46: goto          57
      49: astore_3
      50: aload_1
      51: invokevirtual #51                 // Method io/netty/buffer/ByteBuf.release:()Z
      54: pop
      55: aload_3
      56: athrow
      57: return
    Exception table:
       from    to  target type
           0    21    29   Class java/lang/Exception
           0    21    49   any
          29    41    49   any

  public void readHeaderBlockEnd();
    Code:
       0: aconst_null
       1: astore_1
       2: aload_0
       3: getfield      #2                  // Field spdyHeaderBlockDecoder:Lio/netty/handler/codec/spdy/SpdyHeaderBlockDecoder;
       6: aload_0
       7: getfield      #90                 // Field spdyHeadersFrame:Lio/netty/handler/codec/spdy/SpdyHeadersFrame;
      10: invokevirtual #113                // Method io/netty/handler/codec/spdy/SpdyHeaderBlockDecoder.endHeaderBlock:(Lio/netty/handler/codec/spdy/SpdyHeadersFrame;)V
      13: aload_0
      14: getfield      #90                 // Field spdyHeadersFrame:Lio/netty/handler/codec/spdy/SpdyHeadersFrame;
      17: astore_1
      18: aload_0
      19: aconst_null
      20: putfield      #90                 // Field spdyHeadersFrame:Lio/netty/handler/codec/spdy/SpdyHeadersFrame;
      23: goto          38
      26: astore_2
      27: aload_0
      28: getfield      #17                 // Field ctx:Lio/netty/channel/ChannelHandlerContext;
      31: aload_2
      32: invokeinterface #112,  2          // InterfaceMethod io/netty/channel/ChannelHandlerContext.fireExceptionCaught:(Ljava/lang/Throwable;)Lio/netty/channel/ChannelHandlerContext;
      37: pop
      38: aload_1
      39: ifnull        58
      42: aload_0
      43: iconst_1
      44: putfield      #24                 // Field read:Z
      47: aload_0
      48: getfield      #17                 // Field ctx:Lio/netty/channel/ChannelHandlerContext;
      51: aload_1
      52: invokeinterface #85,  2           // InterfaceMethod io/netty/channel/ChannelHandlerContext.fireChannelRead:(Ljava/lang/Object;)Lio/netty/channel/ChannelHandlerContext;
      57: pop
      58: return
    Exception table:
       from    to  target type
           2    23    26   Class java/lang/Exception

  public void readFrameError(java.lang.String);
    Code:
       0: aload_0
       1: getfield      #17                 // Field ctx:Lio/netty/channel/ChannelHandlerContext;
       4: getstatic     #114                // Field INVALID_FRAME:Lio/netty/handler/codec/spdy/SpdyProtocolException;
       7: invokeinterface #112,  2          // InterfaceMethod io/netty/channel/ChannelHandlerContext.fireExceptionCaught:(Ljava/lang/Throwable;)Lio/netty/channel/ChannelHandlerContext;
      12: pop
      13: return

  static io.netty.handler.codec.spdy.SpdyHeaderBlockDecoder access$000(io.netty.handler.codec.spdy.SpdyFrameCodec);
    Code:
       0: aload_0
       1: getfield      #2                  // Field spdyHeaderBlockDecoder:Lio/netty/handler/codec/spdy/SpdyHeaderBlockDecoder;
       4: areturn

  static io.netty.handler.codec.spdy.SpdyHeaderBlockEncoder access$100(io.netty.handler.codec.spdy.SpdyFrameCodec);
    Code:
       0: aload_0
       1: getfield      #1                  // Field spdyHeaderBlockEncoder:Lio/netty/handler/codec/spdy/SpdyHeaderBlockEncoder;
       4: areturn

  static {};
    Code:
       0: new           #115                // class io/netty/handler/codec/spdy/SpdyProtocolException
       3: dup
       4: ldc           #116                // String Received invalid frame
       6: invokespecial #117                // Method io/netty/handler/codec/spdy/SpdyProtocolException."<init>":(Ljava/lang/String;)V
       9: putstatic     #114                // Field INVALID_FRAME:Lio/netty/handler/codec/spdy/SpdyProtocolException;
      12: return
}
