Compiled from "JFileChooserConfirmOverwrite.java"
public class org.antlr.v4.gui.JFileChooserConfirmOverwrite extends javax.swing.JFileChooser {
  public org.antlr.v4.gui.JFileChooserConfirmOverwrite();
    Code:
       0: aload_0
       1: invokespecial #1                  // Method javax/swing/JFileChooser."<init>":()V
       4: aload_0
       5: iconst_0
       6: invokevirtual #2                  // Method setMultiSelectionEnabled:(Z)V
       9: return

  public void approveSelection();
    Code:
       0: aload_0
       1: invokevirtual #3                  // Method getSelectedFile:()Ljava/io/File;
       4: astore_1
       5: aload_1
       6: invokevirtual #4                  // Method java/io/File.exists:()Z
       9: ifeq          27
      12: aload_0
      13: ldc           #5                  // String Overwrite existing file?
      15: ldc           #6                  // String Overwrite?
      17: iconst_0
      18: invokestatic  #7                  // Method javax/swing/JOptionPane.showConfirmDialog:(Ljava/awt/Component;Ljava/lang/Object;Ljava/lang/String;I)I
      21: istore_2
      22: iload_2
      23: ifeq          27
      26: return
      27: aload_0
      28: invokespecial #8                  // Method javax/swing/JFileChooser.approveSelection:()V
      31: return
}
