Compiled from "TreeViewer.java"
class org.antlr.v4.gui.TreeViewer$TreeNodeWrapper extends javax.swing.tree.DefaultMutableTreeNode {
  final org.antlr.v4.gui.TreeViewer viewer;

  org.antlr.v4.gui.TreeViewer$TreeNodeWrapper(org.antlr.v4.runtime.tree.Tree, org.antlr.v4.gui.TreeViewer);
    Code:
       0: aload_0
       1: aload_1
       2: invokespecial #1                  // Method javax/swing/tree/DefaultMutableTreeNode."<init>":(Ljava/lang/Object;)V
       5: aload_0
       6: aload_2
       7: putfield      #2                  // Field viewer:Lorg/antlr/v4/gui/TreeViewer;
      10: return

  public java.lang.String toString();
    Code:
       0: aload_0
       1: getfield      #2                  // Field viewer:Lorg/antlr/v4/gui/TreeViewer;
       4: aload_0
       5: invokevirtual #3                  // Method getUserObject:()Ljava/lang/Object;
       8: checkcast     #4                  // class org/antlr/v4/runtime/tree/Tree
      11: invokevirtual #5                  // Method org/antlr/v4/gui/TreeViewer.getText:(Lorg/antlr/v4/runtime/tree/Tree;)Ljava/lang/String;
      14: areturn
}
