Compiled from "TimeWindowQuantiles.java"
class io.prometheus.client.TimeWindowQuantiles {
  private final io.prometheus.client.CKMSQuantiles$Quantile[] quantiles;

  private final io.prometheus.client.CKMSQuantiles[] ringBuffer;

  private int currentBucket;

  private long lastRotateTimestampMillis;

  private final long durationBetweenRotatesMillis;

  public io.prometheus.client.TimeWindowQuantiles(io.prometheus.client.CKMSQuantiles$Quantile[], long, int);
    Code:
       0: aload_0
       1: invokespecial #1                  // Method java/lang/Object."<init>":()V
       4: aload_0
       5: aload_1
       6: putfield      #2                  // Field quantiles:[Lio/prometheus/client/CKMSQuantiles$Quantile;
       9: aload_0
      10: iload         4
      12: anewarray     #3                  // class io/prometheus/client/CKMSQuantiles
      15: putfield      #4                  // Field ringBuffer:[Lio/prometheus/client/CKMSQuantiles;
      18: iconst_0
      19: istore        5
      21: iload         5
      23: iload         4
      25: if_icmpge     49
      28: aload_0
      29: getfield      #4                  // Field ringBuffer:[Lio/prometheus/client/CKMSQuantiles;
      32: iload         5
      34: new           #3                  // class io/prometheus/client/CKMSQuantiles
      37: dup
      38: aload_1
      39: invokespecial #5                  // Method io/prometheus/client/CKMSQuantiles."<init>":([Lio/prometheus/client/CKMSQuantiles$Quantile;)V
      42: aastore
      43: iinc          5, 1
      46: goto          21
      49: aload_0
      50: iconst_0
      51: putfield      #6                  // Field currentBucket:I
      54: aload_0
      55: invokestatic  #7                  // Method java/lang/System.currentTimeMillis:()J
      58: putfield      #8                  // Field lastRotateTimestampMillis:J
      61: aload_0
      62: getstatic     #9                  // Field java/util/concurrent/TimeUnit.SECONDS:Ljava/util/concurrent/TimeUnit;
      65: lload_2
      66: invokevirtual #10                 // Method java/util/concurrent/TimeUnit.toMillis:(J)J
      69: iload         4
      71: i2l
      72: ldiv
      73: putfield      #11                 // Field durationBetweenRotatesMillis:J
      76: return

  public double get(double);
    Code:
       0: aload_0
       1: invokespecial #12                 // Method rotate:()Lio/prometheus/client/CKMSQuantiles;
       4: astore_3
       5: aload_3
       6: dload_1
       7: invokevirtual #13                 // Method io/prometheus/client/CKMSQuantiles.get:(D)D
      10: dreturn

  public void insert(double);
    Code:
       0: aload_0
       1: invokespecial #12                 // Method rotate:()Lio/prometheus/client/CKMSQuantiles;
       4: pop
       5: aload_0
       6: getfield      #4                  // Field ringBuffer:[Lio/prometheus/client/CKMSQuantiles;
       9: astore_3
      10: aload_3
      11: arraylength
      12: istore        4
      14: iconst_0
      15: istore        5
      17: iload         5
      19: iload         4
      21: if_icmpge     42
      24: aload_3
      25: iload         5
      27: aaload
      28: astore        6
      30: aload         6
      32: dload_1
      33: invokevirtual #14                 // Method io/prometheus/client/CKMSQuantiles.insert:(D)V
      36: iinc          5, 1
      39: goto          17
      42: return

  private synchronized io.prometheus.client.CKMSQuantiles rotate();
    Code:
       0: invokestatic  #7                  // Method java/lang/System.currentTimeMillis:()J
       3: aload_0
       4: getfield      #8                  // Field lastRotateTimestampMillis:J
       7: lsub
       8: lstore_1
       9: lload_1
      10: aload_0
      11: getfield      #11                 // Field durationBetweenRotatesMillis:J
      14: lcmp
      15: ifle          85
      18: aload_0
      19: getfield      #4                  // Field ringBuffer:[Lio/prometheus/client/CKMSQuantiles;
      22: aload_0
      23: getfield      #6                  // Field currentBucket:I
      26: new           #3                  // class io/prometheus/client/CKMSQuantiles
      29: dup
      30: aload_0
      31: getfield      #2                  // Field quantiles:[Lio/prometheus/client/CKMSQuantiles$Quantile;
      34: invokespecial #5                  // Method io/prometheus/client/CKMSQuantiles."<init>":([Lio/prometheus/client/CKMSQuantiles$Quantile;)V
      37: aastore
      38: aload_0
      39: dup
      40: getfield      #6                  // Field currentBucket:I
      43: iconst_1
      44: iadd
      45: dup_x1
      46: putfield      #6                  // Field currentBucket:I
      49: aload_0
      50: getfield      #4                  // Field ringBuffer:[Lio/prometheus/client/CKMSQuantiles;
      53: arraylength
      54: if_icmplt     62
      57: aload_0
      58: iconst_0
      59: putfield      #6                  // Field currentBucket:I
      62: lload_1
      63: aload_0
      64: getfield      #11                 // Field durationBetweenRotatesMillis:J
      67: lsub
      68: lstore_1
      69: aload_0
      70: dup
      71: getfield      #8                  // Field lastRotateTimestampMillis:J
      74: aload_0
      75: getfield      #11                 // Field durationBetweenRotatesMillis:J
      78: ladd
      79: putfield      #8                  // Field lastRotateTimestampMillis:J
      82: goto          9
      85: aload_0
      86: getfield      #4                  // Field ringBuffer:[Lio/prometheus/client/CKMSQuantiles;
      89: aload_0
      90: getfield      #6                  // Field currentBucket:I
      93: aaload
      94: areturn
}
