Compiled from "CompressionException.java"
public class io.netty.handler.codec.compression.CompressionException extends io.netty.handler.codec.EncoderException {
  private static final long serialVersionUID;

  public io.netty.handler.codec.compression.CompressionException();
    Code:
       0: aload_0
       1: invokespecial #1                  // Method io/netty/handler/codec/EncoderException."<init>":()V
       4: return

  public io.netty.handler.codec.compression.CompressionException(java.lang.String, java.lang.Throwable);
    Code:
       0: aload_0
       1: aload_1
       2: aload_2
       3: invokespecial #2                  // Method io/netty/handler/codec/EncoderException."<init>":(Ljava/lang/String;Ljava/lang/Throwable;)V
       6: return

  public io.netty.handler.codec.compression.CompressionException(java.lang.String);
    Code:
       0: aload_0
       1: aload_1
       2: invokespecial #3                  // Method io/netty/handler/codec/EncoderException."<init>":(Ljava/lang/String;)V
       5: return

  public io.netty.handler.codec.compression.CompressionException(java.lang.Throwable);
    Code:
       0: aload_0
       1: aload_1
       2: invokespecial #4                  // Method io/netty/handler/codec/EncoderException."<init>":(Ljava/lang/Throwable;)V
       5: return
}
