Compiled from "SizeValidator.java"
public class org.jboss.as.domain.management.audit.validators.SizeValidator extends org.jboss.as.controller.operations.validation.ModelTypeValidator {
  private static final java.util.regex.Pattern SIZE_PATTERN;

  public org.jboss.as.domain.management.audit.validators.SizeValidator();
    Code:
       0: aload_0
       1: iconst_0
       2: invokespecial #1                  // Method "<init>":(Z)V
       5: return

  public org.jboss.as.domain.management.audit.validators.SizeValidator(boolean);
    Code:
       0: aload_0
       1: getstatic     #2                  // Field org/jboss/dmr/ModelType.STRING:Lorg/jboss/dmr/ModelType;
       4: iload_1
       5: invokespecial #3                  // Method org/jboss/as/controller/operations/validation/ModelTypeValidator."<init>":(Lorg/jboss/dmr/ModelType;Z)V
       8: return

  public void validateParameter(java.lang.String, org.jboss.dmr.ModelNode) throws org.jboss.as.controller.OperationFailedException;
    Code:
       0: aload_0
       1: aload_1
       2: aload_2
       3: invokespecial #4                  // Method org/jboss/as/controller/operations/validation/ModelTypeValidator.validateParameter:(Ljava/lang/String;Lorg/jboss/dmr/ModelNode;)V
       6: aload_2
       7: invokevirtual #5                  // Method org/jboss/dmr/ModelNode.isDefined:()Z
      10: ifeq          18
      13: aload_2
      14: invokestatic  #6                  // Method parseSize:(Lorg/jboss/dmr/ModelNode;)J
      17: pop2
      18: return

  public static long parseSize(org.jboss.dmr.ModelNode) throws org.jboss.as.controller.OperationFailedException;
    Code:
       0: getstatic     #7                  // Field SIZE_PATTERN:Ljava/util/regex/Pattern;
       3: aload_0
       4: invokevirtual #8                  // Method org/jboss/dmr/ModelNode.asString:()Ljava/lang/String;
       7: invokevirtual #9                  // Method java/util/regex/Pattern.matcher:(Ljava/lang/CharSequence;)Ljava/util/regex/Matcher;
      10: astore_1
      11: aload_1
      12: invokevirtual #10                 // Method java/util/regex/Matcher.matches:()Z
      15: ifne          31
      18: getstatic     #11                 // Field org/jboss/as/domain/management/logging/DomainManagementLogger.ROOT_LOGGER:Lorg/jboss/as/domain/management/logging/DomainManagementLogger;
      21: aload_0
      22: invokevirtual #8                  // Method org/jboss/dmr/ModelNode.asString:()Ljava/lang/String;
      25: invokeinterface #12,  2           // InterfaceMethod org/jboss/as/domain/management/logging/DomainManagementLogger.invalidSize:(Ljava/lang/String;)Lorg/jboss/as/controller/OperationFailedException;
      30: athrow
      31: aload_1
      32: iconst_1
      33: invokevirtual #13                 // Method java/util/regex/Matcher.group:(I)Ljava/lang/String;
      36: bipush        10
      38: invokestatic  #14                 // Method java/lang/Long.parseLong:(Ljava/lang/String;I)J
      41: lstore_2
      42: aload_1
      43: iconst_2
      44: invokevirtual #13                 // Method java/util/regex/Matcher.group:(I)Ljava/lang/String;
      47: astore        4
      49: aload         4
      51: ifnull        200
      54: aload         4
      56: iconst_0
      57: invokevirtual #15                 // Method java/lang/String.charAt:(I)C
      60: lookupswitch  { // 10
                    66: 152
                    71: 171
                    75: 155
                    77: 163
                    84: 179
                    98: 152
                   103: 171
                   107: 155
                   109: 163
                   116: 179
               default: 187
          }
     152: goto          200
     155: lload_2
     156: bipush        10
     158: lshl
     159: lstore_2
     160: goto          200
     163: lload_2
     164: bipush        20
     166: lshl
     167: lstore_2
     168: goto          200
     171: lload_2
     172: bipush        30
     174: lshl
     175: lstore_2
     176: goto          200
     179: lload_2
     180: bipush        40
     182: lshl
     183: lstore_2
     184: goto          200
     187: getstatic     #11                 // Field org/jboss/as/domain/management/logging/DomainManagementLogger.ROOT_LOGGER:Lorg/jboss/as/domain/management/logging/DomainManagementLogger;
     190: aload_0
     191: invokevirtual #8                  // Method org/jboss/dmr/ModelNode.asString:()Ljava/lang/String;
     194: invokeinterface #12,  2           // InterfaceMethod org/jboss/as/domain/management/logging/DomainManagementLogger.invalidSize:(Ljava/lang/String;)Lorg/jboss/as/controller/OperationFailedException;
     199: athrow
     200: lload_2
     201: lreturn

  static {};
    Code:
       0: ldc           #16                 // String (\\d+)([kKmMgGbBtT])?
       2: invokestatic  #17                 // Method java/util/regex/Pattern.compile:(Ljava/lang/String;)Ljava/util/regex/Pattern;
       5: putstatic     #7                  // Field SIZE_PATTERN:Ljava/util/regex/Pattern;
       8: return
}
