Compiled from "StandardServiceRegistryBuilder.java"
final class org.hibernate.boot.registry.StandardServiceRegistryBuilder$2 extends org.hibernate.boot.registry.StandardServiceRegistryBuilder {
  org.hibernate.boot.registry.StandardServiceRegistryBuilder$2(org.hibernate.boot.registry.BootstrapServiceRegistry, java.util.Map, org.hibernate.boot.cfgxml.spi.LoadedConfig);
    Code:
       0: aload_0
       1: aload_1
       2: aload_2
       3: aload_3
       4: aconst_null
       5: invokespecial #1                  // Method org/hibernate/boot/registry/StandardServiceRegistryBuilder."<init>":(Lorg/hibernate/boot/registry/BootstrapServiceRegistry;Ljava/util/Map;Lorg/hibernate/boot/cfgxml/spi/LoadedConfig;Lorg/hibernate/boot/registry/StandardServiceRegistryBuilder$1;)V
       8: return

  public org.hibernate.boot.registry.StandardServiceRegistryBuilder configure(org.hibernate.boot.cfgxml.spi.LoadedConfig);
    Code:
       0: aload_0
       1: invokevirtual #2                  // Method getAggregatedCfgXml:()Lorg/hibernate/boot/cfgxml/spi/LoadedConfig;
       4: aload_1
       5: invokevirtual #3                  // Method org/hibernate/boot/cfgxml/spi/LoadedConfig.merge:(Lorg/hibernate/boot/cfgxml/spi/LoadedConfig;)V
       8: aload_0
       9: areturn
}
