Compiled from "ClassEmitter.java"
class org.springframework.cglib.core.ClassEmitter$1 extends org.springframework.cglib.core.ClassInfo {
  final org.springframework.asm.Type val$classType;

  final org.springframework.asm.Type val$superType;

  final org.springframework.asm.Type[] val$interfaces;

  final int val$access;

  final org.springframework.cglib.core.ClassEmitter this$0;

  org.springframework.cglib.core.ClassEmitter$1(org.springframework.cglib.core.ClassEmitter, org.springframework.asm.Type, org.springframework.asm.Type, org.springframework.asm.Type[], int);
    Code:
       0: aload_0
       1: aload_1
       2: putfield      #23                 // Field this$0:Lorg/springframework/cglib/core/ClassEmitter;
       5: aload_0
       6: aload_2
       7: putfield      #25                 // Field val$classType:Lorg/springframework/asm/Type;
      10: aload_0
      11: aload_3
      12: putfield      #27                 // Field val$superType:Lorg/springframework/asm/Type;
      15: aload_0
      16: aload         4
      18: putfield      #29                 // Field val$interfaces:[Lorg/springframework/asm/Type;
      21: aload_0
      22: iload         5
      24: putfield      #31                 // Field val$access:I
      27: aload_0
      28: invokespecial #34                 // Method org/springframework/cglib/core/ClassInfo."<init>":()V
      31: return

  public org.springframework.asm.Type getType();
    Code:
       0: aload_0
       1: getfield      #25                 // Field val$classType:Lorg/springframework/asm/Type;
       4: areturn

  public org.springframework.asm.Type getSuperType();
    Code:
       0: aload_0
       1: getfield      #27                 // Field val$superType:Lorg/springframework/asm/Type;
       4: ifnull        14
       7: aload_0
       8: getfield      #27                 // Field val$superType:Lorg/springframework/asm/Type;
      11: goto          17
      14: getstatic     #44                 // Field org/springframework/cglib/core/Constants.TYPE_OBJECT:Lorg/springframework/asm/Type;
      17: areturn

  public org.springframework.asm.Type[] getInterfaces();
    Code:
       0: aload_0
       1: getfield      #29                 // Field val$interfaces:[Lorg/springframework/asm/Type;
       4: areturn

  public int getModifiers();
    Code:
       0: aload_0
       1: getfield      #31                 // Field val$access:I
       4: ireturn
}
