Compiled from "VmComponent.java"
public class org.apache.camel.component.vm.VmComponent extends org.apache.camel.component.seda.SedaComponent {
  protected static final java.util.Map<java.lang.String, org.apache.camel.component.seda.QueueReference> QUEUES;

  private static final java.util.concurrent.atomic.AtomicInteger START_COUNTER;

  public org.apache.camel.component.vm.VmComponent();
    Code:
       0: aload_0
       1: invokespecial #14                 // Method org/apache/camel/component/seda/SedaComponent."<init>":()V
       4: return

  public java.util.Map<java.lang.String, org.apache.camel.component.seda.QueueReference> getQueues();
    Code:
       0: getstatic     #20                 // Field QUEUES:Ljava/util/Map;
       3: areturn

  public org.apache.camel.component.seda.QueueReference getQueueReference(java.lang.String);
    Code:
       0: getstatic     #20                 // Field QUEUES:Ljava/util/Map;
       3: aload_1
       4: invokeinterface #28,  2           // InterfaceMethod java/util/Map.get:(Ljava/lang/Object;)Ljava/lang/Object;
       9: checkcast     #30                 // class org/apache/camel/component/seda/QueueReference
      12: areturn

  protected void doStart() throws java.lang.Exception;
    Code:
       0: aload_0
       1: invokespecial #37                 // Method org/apache/camel/component/seda/SedaComponent.doStart:()V
       4: getstatic     #39                 // Field START_COUNTER:Ljava/util/concurrent/atomic/AtomicInteger;
       7: invokevirtual #45                 // Method java/util/concurrent/atomic/AtomicInteger.incrementAndGet:()I
      10: pop
      11: return

  protected void doStop() throws java.lang.Exception;
    Code:
       0: getstatic     #39                 // Field START_COUNTER:Ljava/util/concurrent/atomic/AtomicInteger;
       3: invokevirtual #49                 // Method java/util/concurrent/atomic/AtomicInteger.decrementAndGet:()I
       6: ifgt          18
       9: aload_0
      10: invokevirtual #51                 // Method getQueues:()Ljava/util/Map;
      13: invokeinterface #54,  1           // InterfaceMethod java/util/Map.clear:()V
      18: return

  static {};
    Code:
       0: new           #57                 // class java/util/HashMap
       3: dup
       4: invokespecial #58                 // Method java/util/HashMap."<init>":()V
       7: putstatic     #20                 // Field QUEUES:Ljava/util/Map;
      10: new           #41                 // class java/util/concurrent/atomic/AtomicInteger
      13: dup
      14: invokespecial #59                 // Method java/util/concurrent/atomic/AtomicInteger."<init>":()V
      17: putstatic     #39                 // Field START_COUNTER:Ljava/util/concurrent/atomic/AtomicInteger;
      20: return
}
