Compiled from "SafeWritableConverter.java"
class org.elasticsearch.hadoop.mr.SafeWritableConverter {
  public org.elasticsearch.hadoop.mr.SafeWritableConverter();
    Code:
       0: aload_0
       1: invokespecial #1                  // Method java/lang/Object."<init>":()V
       4: ldc           #7                  // class org/apache/hadoop/io/Text
       6: invokevirtual #9                  // Method java/lang/Class.getName:()Ljava/lang/String;
       9: pop
      10: return

  public void invoke(java.lang.Object, org.elasticsearch.hadoop.util.BytesArray);
    Code:
       0: aload_1
       1: instanceof    #7                  // class org/apache/hadoop/io/Text
       4: ifeq          24
       7: aload_1
       8: checkcast     #7                  // class org/apache/hadoop/io/Text
      11: astore_3
      12: aload_2
      13: aload_3
      14: invokevirtual #15                 // Method org/apache/hadoop/io/Text.getBytes:()[B
      17: aload_3
      18: invokevirtual #19                 // Method org/apache/hadoop/io/Text.getLength:()I
      21: invokevirtual #23                 // Method org/elasticsearch/hadoop/util/BytesArray.bytes:([BI)V
      24: aload_1
      25: instanceof    #29                 // class org/apache/hadoop/io/BytesWritable
      28: ifeq          48
      31: aload_1
      32: checkcast     #29                 // class org/apache/hadoop/io/BytesWritable
      35: astore_3
      36: aload_2
      37: aload_3
      38: invokevirtual #31                 // Method org/apache/hadoop/io/BytesWritable.getBytes:()[B
      41: aload_3
      42: invokevirtual #32                 // Method org/apache/hadoop/io/BytesWritable.getLength:()I
      45: invokevirtual #23                 // Method org/elasticsearch/hadoop/util/BytesArray.bytes:([BI)V
      48: return
}
