Compiled from "EmbeddedChannel.java"
final class io.netty.channel.embedded.EmbeddedChannel$EmbeddedUnsafe extends io.netty.channel.AbstractChannel$AbstractUnsafe {
  final io.netty.channel.Channel$Unsafe wrapped;

  final io.netty.channel.embedded.EmbeddedChannel this$0;

  private io.netty.channel.embedded.EmbeddedChannel$EmbeddedUnsafe(io.netty.channel.embedded.EmbeddedChannel);
    Code:
       0: aload_0
       1: aload_1
       2: putfield      #2                  // Field this$0:Lio/netty/channel/embedded/EmbeddedChannel;
       5: aload_0
       6: aload_1
       7: invokespecial #3                  // Method io/netty/channel/AbstractChannel$AbstractUnsafe."<init>":(Lio/netty/channel/AbstractChannel;)V
      10: aload_0
      11: new           #4                  // class io/netty/channel/embedded/EmbeddedChannel$EmbeddedUnsafe$1
      14: dup
      15: aload_0
      16: invokespecial #5                  // Method io/netty/channel/embedded/EmbeddedChannel$EmbeddedUnsafe$1."<init>":(Lio/netty/channel/embedded/EmbeddedChannel$EmbeddedUnsafe;)V
      19: putfield      #6                  // Field wrapped:Lio/netty/channel/Channel$Unsafe;
      22: return

  public void connect(java.net.SocketAddress, java.net.SocketAddress, io.netty.channel.ChannelPromise);
    Code:
       0: aload_0
       1: aload_3
       2: invokevirtual #7                  // Method safeSetSuccess:(Lio/netty/channel/ChannelPromise;)V
       5: return

  io.netty.channel.embedded.EmbeddedChannel$EmbeddedUnsafe(io.netty.channel.embedded.EmbeddedChannel, io.netty.channel.embedded.EmbeddedChannel$1);
    Code:
       0: aload_0
       1: aload_1
       2: invokespecial #1                  // Method "<init>":(Lio/netty/channel/embedded/EmbeddedChannel;)V
       5: return
}
