Compiled from "Http1ExchangeCodec.kt"
final class okhttp3.internal.http1.Http1ExchangeCodec$ChunkedSource extends okhttp3.internal.http1.Http1ExchangeCodec$AbstractSource {
  private long bytesRemainingInChunk;

  private boolean hasMoreChunks;

  private final okhttp3.HttpUrl url;

  final okhttp3.internal.http1.Http1ExchangeCodec this$0;

  public long read(okio.Buffer, long);
    Code:
       0: aload_1
       1: ldc           #13                 // String sink
       3: invokestatic  #19                 // Method kotlin/jvm/internal/Intrinsics.checkNotNullParameter:(Ljava/lang/Object;Ljava/lang/String;)V
       6: lload_2
       7: lconst_0
       8: lcmp
       9: iflt          16
      12: iconst_1
      13: goto          17
      16: iconst_0
      17: istore        4
      19: iconst_0
      20: istore        5
      22: iconst_0
      23: istore        6
      25: iload         4
      27: ifne          70
      30: iconst_0
      31: istore        7
      33: new           #21                 // class java/lang/StringBuilder
      36: dup
      37: invokespecial #25                 // Method java/lang/StringBuilder."<init>":()V
      40: ldc           #27                 // String byteCount < 0:
      42: invokevirtual #31                 // Method java/lang/StringBuilder.append:(Ljava/lang/String;)Ljava/lang/StringBuilder;
      45: lload_2
      46: invokevirtual #34                 // Method java/lang/StringBuilder.append:(J)Ljava/lang/StringBuilder;
      49: invokevirtual #38                 // Method java/lang/StringBuilder.toString:()Ljava/lang/String;
      52: astore        6
      54: new           #40                 // class java/lang/IllegalArgumentException
      57: dup
      58: aload         6
      60: invokevirtual #43                 // Method java/lang/Object.toString:()Ljava/lang/String;
      63: invokespecial #46                 // Method java/lang/IllegalArgumentException."<init>":(Ljava/lang/String;)V
      66: checkcast     #48                 // class java/lang/Throwable
      69: athrow
      70: aload_0
      71: invokevirtual #52                 // Method getClosed:()Z
      74: ifne          81
      77: iconst_1
      78: goto          82
      81: iconst_0
      82: istore        4
      84: iconst_0
      85: istore        5
      87: iconst_0
      88: istore        6
      90: iload         4
      92: ifne          118
      95: iconst_0
      96: istore        7
      98: ldc           #54                 // String closed
     100: astore        6
     102: new           #56                 // class java/lang/IllegalStateException
     105: dup
     106: aload         6
     108: invokevirtual #43                 // Method java/lang/Object.toString:()Ljava/lang/String;
     111: invokespecial #57                 // Method java/lang/IllegalStateException."<init>":(Ljava/lang/String;)V
     114: checkcast     #48                 // class java/lang/Throwable
     117: athrow
     118: aload_0
     119: getfield      #59                 // Field hasMoreChunks:Z
     122: ifne          129
     125: ldc2_w        #60                 // long -1l
     128: lreturn
     129: aload_0
     130: getfield      #63                 // Field bytesRemainingInChunk:J
     133: lconst_0
     134: lcmp
     135: ifeq          149
     138: aload_0
     139: getfield      #63                 // Field bytesRemainingInChunk:J
     142: ldc2_w        #60                 // long -1l
     145: lcmp
     146: ifne          164
     149: aload_0
     150: invokespecial #66                 // Method readChunkSize:()V
     153: aload_0
     154: getfield      #59                 // Field hasMoreChunks:Z
     157: ifne          164
     160: ldc2_w        #60                 // long -1l
     163: lreturn
     164: aload_0
     165: aload_1
     166: aload_0
     167: getfield      #63                 // Field bytesRemainingInChunk:J
     170: lstore        6
     172: iconst_0
     173: istore        8
     175: lload_2
     176: lload         6
     178: invokestatic  #72                 // Method java/lang/Math.min:(JJ)J
     181: invokespecial #74                 // Method okhttp3/internal/http1/Http1ExchangeCodec$AbstractSource.read:(Lokio/Buffer;J)J
     184: lstore        4
     186: lload         4
     188: ldc2_w        #60                 // long -1l
     191: lcmp
     192: ifne          226
     195: aload_0
     196: getfield      #78                 // Field this$0:Lokhttp3/internal/http1/Http1ExchangeCodec;
     199: invokevirtual #84                 // Method okhttp3/internal/http1/Http1ExchangeCodec.getConnection:()Lokhttp3/internal/connection/RealConnection;
     202: invokevirtual #89                 // Method okhttp3/internal/connection/RealConnection.noNewExchanges$okhttp:()V
     205: new           #91                 // class java/net/ProtocolException
     208: dup
     209: ldc           #93                 // String unexpected end of stream
     211: invokespecial #94                 // Method java/net/ProtocolException."<init>":(Ljava/lang/String;)V
     214: astore        6
     216: aload_0
     217: invokevirtual #97                 // Method responseBodyComplete:()V
     220: aload         6
     222: checkcast     #48                 // class java/lang/Throwable
     225: athrow
     226: aload_0
     227: dup
     228: getfield      #63                 // Field bytesRemainingInChunk:J
     231: lload         4
     233: lsub
     234: putfield      #63                 // Field bytesRemainingInChunk:J
     237: lload         4
     239: lreturn

  private final void readChunkSize();
    Code:
       0: aload_0
       1: getfield      #63                 // Field bytesRemainingInChunk:J
       4: ldc2_w        #60                 // long -1l
       7: lcmp
       8: ifeq          24
      11: aload_0
      12: getfield      #78                 // Field this$0:Lokhttp3/internal/http1/Http1ExchangeCodec;
      15: invokestatic  #114                // Method okhttp3/internal/http1/Http1ExchangeCodec.access$getSource$p:(Lokhttp3/internal/http1/Http1ExchangeCodec;)Lokio/BufferedSource;
      18: invokeinterface #119,  1          // InterfaceMethod okio/BufferedSource.readUtf8LineStrict:()Ljava/lang/String;
      23: pop
      24: nop
      25: aload_0
      26: aload_0
      27: getfield      #78                 // Field this$0:Lokhttp3/internal/http1/Http1ExchangeCodec;
      30: invokestatic  #114                // Method okhttp3/internal/http1/Http1ExchangeCodec.access$getSource$p:(Lokhttp3/internal/http1/Http1ExchangeCodec;)Lokio/BufferedSource;
      33: invokeinterface #123,  1          // InterfaceMethod okio/BufferedSource.readHexadecimalUnsignedLong:()J
      38: putfield      #63                 // Field bytesRemainingInChunk:J
      41: aload_0
      42: getfield      #78                 // Field this$0:Lokhttp3/internal/http1/Http1ExchangeCodec;
      45: invokestatic  #114                // Method okhttp3/internal/http1/Http1ExchangeCodec.access$getSource$p:(Lokhttp3/internal/http1/Http1ExchangeCodec;)Lokio/BufferedSource;
      48: invokeinterface #119,  1          // InterfaceMethod okio/BufferedSource.readUtf8LineStrict:()Ljava/lang/String;
      53: astore_2
      54: iconst_0
      55: istore_3
      56: aload_2
      57: dup
      58: ifnonnull     71
      61: new           #125                // class java/lang/NullPointerException
      64: dup
      65: ldc           #127                // String null cannot be cast to non-null type kotlin.CharSequence
      67: invokespecial #128                // Method java/lang/NullPointerException."<init>":(Ljava/lang/String;)V
      70: athrow
      71: checkcast     #130                // class java/lang/CharSequence
      74: invokestatic  #136                // Method kotlin/text/StringsKt.trim:(Ljava/lang/CharSequence;)Ljava/lang/CharSequence;
      77: invokevirtual #43                 // Method java/lang/Object.toString:()Ljava/lang/String;
      80: astore_1
      81: aload_0
      82: getfield      #63                 // Field bytesRemainingInChunk:J
      85: lconst_0
      86: lcmp
      87: iflt          126
      90: aload_1
      91: checkcast     #130                // class java/lang/CharSequence
      94: astore_2
      95: iconst_0
      96: istore_3
      97: aload_2
      98: invokeinterface #140,  1          // InterfaceMethod java/lang/CharSequence.length:()I
     103: ifle          110
     106: iconst_1
     107: goto          111
     110: iconst_0
     111: ifeq          189
     114: aload_1
     115: ldc           #142                // String ;
     117: iconst_0
     118: iconst_2
     119: aconst_null
     120: invokestatic  #146                // Method kotlin/text/StringsKt.startsWith$default:(Ljava/lang/String;Ljava/lang/String;ZILjava/lang/Object;)Z
     123: ifne          189
     126: new           #91                 // class java/net/ProtocolException
     129: dup
     130: new           #21                 // class java/lang/StringBuilder
     133: dup
     134: invokespecial #25                 // Method java/lang/StringBuilder."<init>":()V
     137: ldc           #148                // String expected chunk size and optional extensions
     139: invokevirtual #31                 // Method java/lang/StringBuilder.append:(Ljava/lang/String;)Ljava/lang/StringBuilder;
     142: ldc           #150                // String  but was \"
     144: invokevirtual #31                 // Method java/lang/StringBuilder.append:(Ljava/lang/String;)Ljava/lang/StringBuilder;
     147: aload_0
     148: getfield      #63                 // Field bytesRemainingInChunk:J
     151: invokevirtual #34                 // Method java/lang/StringBuilder.append:(J)Ljava/lang/StringBuilder;
     154: aload_1
     155: invokevirtual #31                 // Method java/lang/StringBuilder.append:(Ljava/lang/String;)Ljava/lang/StringBuilder;
     158: bipush        34
     160: invokevirtual #153                // Method java/lang/StringBuilder.append:(C)Ljava/lang/StringBuilder;
     163: invokevirtual #38                 // Method java/lang/StringBuilder.toString:()Ljava/lang/String;
     166: invokespecial #94                 // Method java/net/ProtocolException."<init>":(Ljava/lang/String;)V
     169: checkcast     #48                 // class java/lang/Throwable
     172: athrow
     173: astore_1
     174: new           #91                 // class java/net/ProtocolException
     177: dup
     178: aload_1
     179: invokevirtual #156                // Method java/lang/NumberFormatException.getMessage:()Ljava/lang/String;
     182: invokespecial #94                 // Method java/net/ProtocolException."<init>":(Ljava/lang/String;)V
     185: checkcast     #48                 // class java/lang/Throwable
     188: athrow
     189: aload_0
     190: getfield      #63                 // Field bytesRemainingInChunk:J
     193: lconst_0
     194: lcmp
     195: ifne          256
     198: aload_0
     199: iconst_0
     200: putfield      #59                 // Field hasMoreChunks:Z
     203: aload_0
     204: getfield      #78                 // Field this$0:Lokhttp3/internal/http1/Http1ExchangeCodec;
     207: aload_0
     208: getfield      #78                 // Field this$0:Lokhttp3/internal/http1/Http1ExchangeCodec;
     211: invokestatic  #160                // Method okhttp3/internal/http1/Http1ExchangeCodec.access$getHeadersReader$p:(Lokhttp3/internal/http1/Http1ExchangeCodec;)Lokhttp3/internal/http1/HeadersReader;
     214: invokevirtual #166                // Method okhttp3/internal/http1/HeadersReader.readHeaders:()Lokhttp3/Headers;
     217: invokestatic  #170                // Method okhttp3/internal/http1/Http1ExchangeCodec.access$setTrailers$p:(Lokhttp3/internal/http1/Http1ExchangeCodec;Lokhttp3/Headers;)V
     220: aload_0
     221: getfield      #78                 // Field this$0:Lokhttp3/internal/http1/Http1ExchangeCodec;
     224: invokestatic  #174                // Method okhttp3/internal/http1/Http1ExchangeCodec.access$getClient$p:(Lokhttp3/internal/http1/Http1ExchangeCodec;)Lokhttp3/OkHttpClient;
     227: dup
     228: invokestatic  #178                // Method kotlin/jvm/internal/Intrinsics.checkNotNull:(Ljava/lang/Object;)V
     231: invokevirtual #184                // Method okhttp3/OkHttpClient.cookieJar:()Lokhttp3/CookieJar;
     234: aload_0
     235: getfield      #188                // Field url:Lokhttp3/HttpUrl;
     238: aload_0
     239: getfield      #78                 // Field this$0:Lokhttp3/internal/http1/Http1ExchangeCodec;
     242: invokestatic  #192                // Method okhttp3/internal/http1/Http1ExchangeCodec.access$getTrailers$p:(Lokhttp3/internal/http1/Http1ExchangeCodec;)Lokhttp3/Headers;
     245: dup
     246: invokestatic  #178                // Method kotlin/jvm/internal/Intrinsics.checkNotNull:(Ljava/lang/Object;)V
     249: invokestatic  #198                // Method okhttp3/internal/http/HttpHeaders.receiveHeaders:(Lokhttp3/CookieJar;Lokhttp3/HttpUrl;Lokhttp3/Headers;)V
     252: aload_0
     253: invokevirtual #97                 // Method responseBodyComplete:()V
     256: return
    Exception table:
       from    to  target type
          24   173   173   Class java/lang/NumberFormatException

  public void close();
    Code:
       0: aload_0
       1: invokevirtual #52                 // Method getClosed:()Z
       4: ifeq          8
       7: return
       8: aload_0
       9: getfield      #59                 // Field hasMoreChunks:Z
      12: ifeq          41
      15: aload_0
      16: bipush        100
      18: getstatic     #210                // Field java/util/concurrent/TimeUnit.MILLISECONDS:Ljava/util/concurrent/TimeUnit;
      21: invokestatic  #216                // Method okhttp3/internal/Util.discard:(Lokio/Source;ILjava/util/concurrent/TimeUnit;)Z
      24: ifne          41
      27: aload_0
      28: getfield      #78                 // Field this$0:Lokhttp3/internal/http1/Http1ExchangeCodec;
      31: invokevirtual #84                 // Method okhttp3/internal/http1/Http1ExchangeCodec.getConnection:()Lokhttp3/internal/connection/RealConnection;
      34: invokevirtual #89                 // Method okhttp3/internal/connection/RealConnection.noNewExchanges$okhttp:()V
      37: aload_0
      38: invokevirtual #97                 // Method responseBodyComplete:()V
      41: aload_0
      42: iconst_1
      43: invokevirtual #220                // Method setClosed:(Z)V
      46: return

  public okhttp3.internal.http1.Http1ExchangeCodec$ChunkedSource(okhttp3.HttpUrl);
    Code:
       0: aload_2
       1: ldc           #223                // String url
       3: invokestatic  #19                 // Method kotlin/jvm/internal/Intrinsics.checkNotNullParameter:(Ljava/lang/Object;Ljava/lang/String;)V
       6: aload_0
       7: aload_1
       8: putfield      #78                 // Field this$0:Lokhttp3/internal/http1/Http1ExchangeCodec;
      11: aload_0
      12: aload_1
      13: invokespecial #226                // Method okhttp3/internal/http1/Http1ExchangeCodec$AbstractSource."<init>":(Lokhttp3/internal/http1/Http1ExchangeCodec;)V
      16: aload_0
      17: aload_2
      18: putfield      #188                // Field url:Lokhttp3/HttpUrl;
      21: aload_0
      22: ldc2_w        #60                 // long -1l
      25: putfield      #63                 // Field bytesRemainingInChunk:J
      28: aload_0
      29: iconst_1
      30: putfield      #59                 // Field hasMoreChunks:Z
      33: return
}
