Compiled from "MyFacesLifecycleProvider.java"
public class org.jboss.as.jsf.injection.MyFacesLifecycleProvider implements org.apache.myfaces.config.annotation.LifecycleProvider2 {
  private final org.jboss.as.web.common.WebInjectionContainer injectionContainer;

  public org.jboss.as.jsf.injection.MyFacesLifecycleProvider();
    Code:
       0: aload_0
       1: invokespecial #1                  // Method java/lang/Object."<init>":()V
       4: aload_0
       5: invokestatic  #2                  // Method org/jboss/as/web/common/StartupContext.getInjectionContainer:()Lorg/jboss/as/web/common/WebInjectionContainer;
       8: putfield      #3                  // Field injectionContainer:Lorg/jboss/as/web/common/WebInjectionContainer;
      11: return

  public java.lang.Object newInstance(java.lang.String) throws java.lang.ClassNotFoundException, java.lang.IllegalAccessException, java.lang.InstantiationException, javax.naming.NamingException, java.lang.reflect.InvocationTargetException;
    Code:
       0: invokestatic  #4                  // Method org/wildfly/security/manager/WildFlySecurityManager.getCurrentContextClassLoaderPrivileged:()Ljava/lang/ClassLoader;
       3: aload_1
       4: invokevirtual #5                  // Method java/lang/ClassLoader.loadClass:(Ljava/lang/String;)Ljava/lang/Class;
       7: astore_2
       8: invokestatic  #6                  // Method java/lang/System.getSecurityManager:()Ljava/lang/SecurityManager;
      11: ifnonnull     19
      14: aload_2
      15: invokevirtual #7                  // Method java/lang/Class.newInstance:()Ljava/lang/Object;
      18: areturn
      19: new           #8                  // class org/jboss/as/jsf/injection/MyFacesLifecycleProvider$1
      22: dup
      23: aload_0
      24: aload_2
      25: invokespecial #9                  // Method org/jboss/as/jsf/injection/MyFacesLifecycleProvider$1."<init>":(Lorg/jboss/as/jsf/injection/MyFacesLifecycleProvider;Ljava/lang/Class;)V
      28: invokestatic  #10                 // Method java/security/AccessController.doPrivileged:(Ljava/security/PrivilegedExceptionAction;)Ljava/lang/Object;
      31: areturn
      32: astore_3
      33: aload_3
      34: invokevirtual #12                 // Method java/security/PrivilegedActionException.getException:()Ljava/lang/Exception;
      37: astore        4
      39: aload         4
      41: instanceof    #13                 // class java/lang/IllegalAccessException
      44: ifeq          53
      47: aload         4
      49: checkcast     #13                 // class java/lang/IllegalAccessException
      52: athrow
      53: aload         4
      55: instanceof    #14                 // class java/lang/InstantiationException
      58: ifeq          67
      61: aload         4
      63: checkcast     #14                 // class java/lang/InstantiationException
      66: athrow
      67: new           #15                 // class javax/faces/FacesException
      70: dup
      71: aload         4
      73: invokespecial #16                 // Method javax/faces/FacesException."<init>":(Ljava/lang/Throwable;)V
      76: athrow
    Exception table:
       from    to  target type
          19    31    32   Class java/security/PrivilegedActionException

  public void postConstruct(java.lang.Object) throws java.lang.IllegalAccessException, java.lang.reflect.InvocationTargetException;
    Code:
       0: aload_0
       1: getfield      #3                  // Field injectionContainer:Lorg/jboss/as/web/common/WebInjectionContainer;
       4: aload_1
       5: invokevirtual #17                 // Method org/jboss/as/web/common/WebInjectionContainer.newInstance:(Ljava/lang/Object;)V
       8: goto          21
      11: astore_2
      12: new           #15                 // class javax/faces/FacesException
      15: dup
      16: aload_2
      17: invokespecial #16                 // Method javax/faces/FacesException."<init>":(Ljava/lang/Throwable;)V
      20: athrow
      21: return
    Exception table:
       from    to  target type
           0     8    11   Class javax/naming/NamingException

  public void destroyInstance(java.lang.Object) throws java.lang.IllegalAccessException, java.lang.reflect.InvocationTargetException;
    Code:
       0: aload_0
       1: getfield      #3                  // Field injectionContainer:Lorg/jboss/as/web/common/WebInjectionContainer;
       4: aload_1
       5: invokevirtual #19                 // Method org/jboss/as/web/common/WebInjectionContainer.destroyInstance:(Ljava/lang/Object;)V
       8: return
}
