Compiled from "ActiveMQServerImpl.java"
class org.apache.activemq.artemis.core.server.impl.ActiveMQServerImpl$4 implements java.lang.Runnable {
  final org.apache.activemq.artemis.core.server.impl.ServerInfo val$dumper;

  final org.apache.activemq.artemis.core.server.impl.ActiveMQServerImpl this$0;

  org.apache.activemq.artemis.core.server.impl.ActiveMQServerImpl$4(org.apache.activemq.artemis.core.server.impl.ActiveMQServerImpl, org.apache.activemq.artemis.core.server.impl.ServerInfo);
    Code:
       0: aload_0
       1: aload_1
       2: putfield      #1                  // Field this$0:Lorg/apache/activemq/artemis/core/server/impl/ActiveMQServerImpl;
       5: aload_0
       6: aload_2
       7: putfield      #2                  // Field val$dumper:Lorg/apache/activemq/artemis/core/server/impl/ServerInfo;
      10: aload_0
      11: invokespecial #3                  // Method java/lang/Object."<init>":()V
      14: return

  public void run();
    Code:
       0: getstatic     #4                  // Field org/apache/activemq/artemis/core/server/ActiveMQServerLogger.LOGGER:Lorg/apache/activemq/artemis/core/server/ActiveMQServerLogger;
       3: aload_0
       4: getfield      #2                  // Field val$dumper:Lorg/apache/activemq/artemis/core/server/impl/ServerInfo;
       7: invokevirtual #5                  // Method org/apache/activemq/artemis/core/server/impl/ServerInfo.dump:()Ljava/lang/String;
      10: invokeinterface #6,  2            // InterfaceMethod org/apache/activemq/artemis/core/server/ActiveMQServerLogger.dumpServerInfo:(Ljava/lang/String;)V
      15: return
}
