Compiled from "LastValueQueue.java"
class org.apache.activemq.artemis.core.server.impl.LastValueQueue$HolderReference implements org.apache.activemq.artemis.core.server.MessageReference {
  private final org.apache.activemq.artemis.api.core.SimpleString prop;

  private volatile org.apache.activemq.artemis.core.server.MessageReference ref;

  private java.lang.Long consumerId;

  final org.apache.activemq.artemis.core.server.impl.LastValueQueue this$0;

  org.apache.activemq.artemis.core.server.impl.LastValueQueue$HolderReference(org.apache.activemq.artemis.core.server.impl.LastValueQueue, org.apache.activemq.artemis.api.core.SimpleString, org.apache.activemq.artemis.core.server.MessageReference);
    Code:
       0: aload_0
       1: aload_1
       2: putfield      #1                  // Field this$0:Lorg/apache/activemq/artemis/core/server/impl/LastValueQueue;
       5: aload_0
       6: invokespecial #2                  // Method java/lang/Object."<init>":()V
       9: aload_0
      10: aload_2
      11: putfield      #3                  // Field prop:Lorg/apache/activemq/artemis/api/core/SimpleString;
      14: aload_0
      15: aload_3
      16: putfield      #4                  // Field ref:Lorg/apache/activemq/artemis/core/server/MessageReference;
      19: return

  org.apache.activemq.artemis.core.server.MessageReference getReference();
    Code:
       0: aload_0
       1: getfield      #4                  // Field ref:Lorg/apache/activemq/artemis/core/server/MessageReference;
       4: areturn

  public void handled();
    Code:
       0: aload_0
       1: getfield      #4                  // Field ref:Lorg/apache/activemq/artemis/core/server/MessageReference;
       4: invokeinterface #5,  1            // InterfaceMethod org/apache/activemq/artemis/core/server/MessageReference.handled:()V
       9: aload_0
      10: getfield      #1                  // Field this$0:Lorg/apache/activemq/artemis/core/server/impl/LastValueQueue;
      13: invokestatic  #6                  // Method org/apache/activemq/artemis/core/server/impl/LastValueQueue.access$000:(Lorg/apache/activemq/artemis/core/server/impl/LastValueQueue;)Ljava/util/Map;
      16: aload_0
      17: getfield      #3                  // Field prop:Lorg/apache/activemq/artemis/api/core/SimpleString;
      20: invokeinterface #7,  2            // InterfaceMethod java/util/Map.remove:(Ljava/lang/Object;)Ljava/lang/Object;
      25: pop
      26: return

  public void setAlreadyAcked();
    Code:
       0: aload_0
       1: getfield      #4                  // Field ref:Lorg/apache/activemq/artemis/core/server/MessageReference;
       4: invokeinterface #8,  1            // InterfaceMethod org/apache/activemq/artemis/core/server/MessageReference.setAlreadyAcked:()V
       9: return

  public boolean isAlreadyAcked();
    Code:
       0: aload_0
       1: getfield      #4                  // Field ref:Lorg/apache/activemq/artemis/core/server/MessageReference;
       4: invokeinterface #9,  1            // InterfaceMethod org/apache/activemq/artemis/core/server/MessageReference.isAlreadyAcked:()Z
       9: ireturn

  void setReference(org.apache.activemq.artemis.core.server.MessageReference);
    Code:
       0: aload_0
       1: aload_1
       2: putfield      #4                  // Field ref:Lorg/apache/activemq/artemis/core/server/MessageReference;
       5: return

  public org.apache.activemq.artemis.core.server.MessageReference copy(org.apache.activemq.artemis.core.server.Queue);
    Code:
       0: aload_0
       1: getfield      #4                  // Field ref:Lorg/apache/activemq/artemis/core/server/MessageReference;
       4: aload_1
       5: invokeinterface #10,  2           // InterfaceMethod org/apache/activemq/artemis/core/server/MessageReference.copy:(Lorg/apache/activemq/artemis/core/server/Queue;)Lorg/apache/activemq/artemis/core/server/MessageReference;
      10: areturn

  public void decrementDeliveryCount();
    Code:
       0: aload_0
       1: getfield      #4                  // Field ref:Lorg/apache/activemq/artemis/core/server/MessageReference;
       4: invokeinterface #11,  1           // InterfaceMethod org/apache/activemq/artemis/core/server/MessageReference.decrementDeliveryCount:()V
       9: return

  public int getDeliveryCount();
    Code:
       0: aload_0
       1: getfield      #4                  // Field ref:Lorg/apache/activemq/artemis/core/server/MessageReference;
       4: invokeinterface #12,  1           // InterfaceMethod org/apache/activemq/artemis/core/server/MessageReference.getDeliveryCount:()I
       9: ireturn

  public org.apache.activemq.artemis.core.server.ServerMessage getMessage();
    Code:
       0: aload_0
       1: getfield      #4                  // Field ref:Lorg/apache/activemq/artemis/core/server/MessageReference;
       4: invokeinterface #13,  1           // InterfaceMethod org/apache/activemq/artemis/core/server/MessageReference.getMessage:()Lorg/apache/activemq/artemis/core/server/ServerMessage;
       9: areturn

  public org.apache.activemq.artemis.core.server.Queue getQueue();
    Code:
       0: aload_0
       1: getfield      #4                  // Field ref:Lorg/apache/activemq/artemis/core/server/MessageReference;
       4: invokeinterface #14,  1           // InterfaceMethod org/apache/activemq/artemis/core/server/MessageReference.getQueue:()Lorg/apache/activemq/artemis/core/server/Queue;
       9: areturn

  public long getScheduledDeliveryTime();
    Code:
       0: aload_0
       1: getfield      #4                  // Field ref:Lorg/apache/activemq/artemis/core/server/MessageReference;
       4: invokeinterface #15,  1           // InterfaceMethod org/apache/activemq/artemis/core/server/MessageReference.getScheduledDeliveryTime:()J
       9: lreturn

  public void incrementDeliveryCount();
    Code:
       0: aload_0
       1: getfield      #4                  // Field ref:Lorg/apache/activemq/artemis/core/server/MessageReference;
       4: invokeinterface #16,  1           // InterfaceMethod org/apache/activemq/artemis/core/server/MessageReference.incrementDeliveryCount:()V
       9: return

  public void setDeliveryCount(int);
    Code:
       0: aload_0
       1: getfield      #4                  // Field ref:Lorg/apache/activemq/artemis/core/server/MessageReference;
       4: iload_1
       5: invokeinterface #17,  2           // InterfaceMethod org/apache/activemq/artemis/core/server/MessageReference.setDeliveryCount:(I)V
      10: return

  public void setScheduledDeliveryTime(long);
    Code:
       0: aload_0
       1: getfield      #4                  // Field ref:Lorg/apache/activemq/artemis/core/server/MessageReference;
       4: lload_1
       5: invokeinterface #18,  3           // InterfaceMethod org/apache/activemq/artemis/core/server/MessageReference.setScheduledDeliveryTime:(J)V
      10: return

  public void setPersistedCount(int);
    Code:
       0: aload_0
       1: getfield      #4                  // Field ref:Lorg/apache/activemq/artemis/core/server/MessageReference;
       4: iload_1
       5: invokeinterface #19,  2           // InterfaceMethod org/apache/activemq/artemis/core/server/MessageReference.setPersistedCount:(I)V
      10: return

  public int getPersistedCount();
    Code:
       0: aload_0
       1: getfield      #4                  // Field ref:Lorg/apache/activemq/artemis/core/server/MessageReference;
       4: invokeinterface #20,  1           // InterfaceMethod org/apache/activemq/artemis/core/server/MessageReference.getPersistedCount:()I
       9: ireturn

  public boolean isPaged();
    Code:
       0: iconst_0
       1: ireturn

  public void acknowledge() throws java.lang.Exception;
    Code:
       0: aload_0
       1: getfield      #4                  // Field ref:Lorg/apache/activemq/artemis/core/server/MessageReference;
       4: invokeinterface #14,  1           // InterfaceMethod org/apache/activemq/artemis/core/server/MessageReference.getQueue:()Lorg/apache/activemq/artemis/core/server/Queue;
       9: aload_0
      10: invokeinterface #21,  2           // InterfaceMethod org/apache/activemq/artemis/core/server/Queue.acknowledge:(Lorg/apache/activemq/artemis/core/server/MessageReference;)V
      15: return

  public int getMessageMemoryEstimate();
    Code:
       0: aload_0
       1: getfield      #4                  // Field ref:Lorg/apache/activemq/artemis/core/server/MessageReference;
       4: invokeinterface #13,  1           // InterfaceMethod org/apache/activemq/artemis/core/server/MessageReference.getMessage:()Lorg/apache/activemq/artemis/core/server/ServerMessage;
       9: invokeinterface #22,  1           // InterfaceMethod org/apache/activemq/artemis/core/server/ServerMessage.getMemoryEstimate:()I
      14: ireturn

  public void setConsumerId(java.lang.Long);
    Code:
       0: aload_0
       1: aload_1
       2: putfield      #23                 // Field consumerId:Ljava/lang/Long;
       5: return

  public java.lang.Long getConsumerId();
    Code:
       0: aload_0
       1: getfield      #23                 // Field consumerId:Ljava/lang/Long;
       4: areturn
}
