Compiled from "PostOfficeJournalLoader.java"
public class org.apache.activemq.artemis.core.server.impl.PostOfficeJournalLoader implements org.apache.activemq.artemis.core.server.impl.JournalLoader {
  protected final org.apache.activemq.artemis.core.postoffice.PostOffice postOffice;

  protected final org.apache.activemq.artemis.core.paging.PagingManager pagingManager;

  private org.apache.activemq.artemis.core.persistence.StorageManager storageManager;

  private final org.apache.activemq.artemis.core.server.QueueFactory queueFactory;

  protected final org.apache.activemq.artemis.core.server.NodeManager nodeManager;

  private final org.apache.activemq.artemis.core.server.management.ManagementService managementService;

  private final org.apache.activemq.artemis.core.server.group.GroupingHandler groupingHandler;

  private org.apache.activemq.artemis.core.config.Configuration configuration;

  private java.util.Map<java.lang.Long, org.apache.activemq.artemis.core.server.Queue> queues;

  static final boolean $assertionsDisabled;

  public org.apache.activemq.artemis.core.server.impl.PostOfficeJournalLoader(org.apache.activemq.artemis.core.postoffice.PostOffice, org.apache.activemq.artemis.core.paging.PagingManager, org.apache.activemq.artemis.core.persistence.StorageManager, org.apache.activemq.artemis.core.server.QueueFactory, org.apache.activemq.artemis.core.server.NodeManager, org.apache.activemq.artemis.core.server.management.ManagementService, org.apache.activemq.artemis.core.server.group.GroupingHandler, org.apache.activemq.artemis.core.config.Configuration);
    Code:
       0: aload_0
       1: invokespecial #1                  // Method java/lang/Object."<init>":()V
       4: aload_0
       5: aload_1
       6: putfield      #2                  // Field postOffice:Lorg/apache/activemq/artemis/core/postoffice/PostOffice;
       9: aload_0
      10: aload_2
      11: putfield      #3                  // Field pagingManager:Lorg/apache/activemq/artemis/core/paging/PagingManager;
      14: aload_0
      15: aload_3
      16: putfield      #4                  // Field storageManager:Lorg/apache/activemq/artemis/core/persistence/StorageManager;
      19: aload_0
      20: aload         4
      22: putfield      #5                  // Field queueFactory:Lorg/apache/activemq/artemis/core/server/QueueFactory;
      25: aload_0
      26: aload         5
      28: putfield      #6                  // Field nodeManager:Lorg/apache/activemq/artemis/core/server/NodeManager;
      31: aload_0
      32: aload         6
      34: putfield      #7                  // Field managementService:Lorg/apache/activemq/artemis/core/server/management/ManagementService;
      37: aload_0
      38: aload         7
      40: putfield      #8                  // Field groupingHandler:Lorg/apache/activemq/artemis/core/server/group/GroupingHandler;
      43: aload_0
      44: aload         8
      46: putfield      #9                  // Field configuration:Lorg/apache/activemq/artemis/core/config/Configuration;
      49: aload_0
      50: new           #10                 // class java/util/HashMap
      53: dup
      54: invokespecial #11                 // Method java/util/HashMap."<init>":()V
      57: putfield      #12                 // Field queues:Ljava/util/Map;
      60: return

  public org.apache.activemq.artemis.core.server.impl.PostOfficeJournalLoader(org.apache.activemq.artemis.core.postoffice.PostOffice, org.apache.activemq.artemis.core.paging.PagingManager, org.apache.activemq.artemis.core.persistence.StorageManager, org.apache.activemq.artemis.core.server.QueueFactory, org.apache.activemq.artemis.core.server.NodeManager, org.apache.activemq.artemis.core.server.management.ManagementService, org.apache.activemq.artemis.core.server.group.GroupingHandler, org.apache.activemq.artemis.core.config.Configuration, java.util.Map<java.lang.Long, org.apache.activemq.artemis.core.server.Queue>);
    Code:
       0: aload_0
       1: aload_1
       2: aload_2
       3: aload_3
       4: aload         4
       6: aload         5
       8: aload         6
      10: aload         7
      12: aload         8
      14: invokespecial #13                 // Method "<init>":(Lorg/apache/activemq/artemis/core/postoffice/PostOffice;Lorg/apache/activemq/artemis/core/paging/PagingManager;Lorg/apache/activemq/artemis/core/persistence/StorageManager;Lorg/apache/activemq/artemis/core/server/QueueFactory;Lorg/apache/activemq/artemis/core/server/NodeManager;Lorg/apache/activemq/artemis/core/server/management/ManagementService;Lorg/apache/activemq/artemis/core/server/group/GroupingHandler;Lorg/apache/activemq/artemis/core/config/Configuration;)V
      17: aload_0
      18: aload         9
      20: putfield      #12                 // Field queues:Ljava/util/Map;
      23: return

  public void initQueues(java.util.Map<java.lang.Long, org.apache.activemq.artemis.core.persistence.QueueBindingInfo>, java.util.List<org.apache.activemq.artemis.core.persistence.QueueBindingInfo>) throws java.lang.Exception;
    Code:
       0: iconst_0
       1: istore_3
       2: aload_2
       3: invokeinterface #14,  1           // InterfaceMethod java/util/List.iterator:()Ljava/util/Iterator;
       8: astore        4
      10: aload         4
      12: invokeinterface #15,  1           // InterfaceMethod java/util/Iterator.hasNext:()Z
      17: ifeq          474
      20: aload         4
      22: invokeinterface #16,  1           // InterfaceMethod java/util/Iterator.next:()Ljava/lang/Object;
      27: checkcast     #17                 // class org/apache/activemq/artemis/core/persistence/QueueBindingInfo
      30: astore        5
      32: aload_1
      33: aload         5
      35: invokeinterface #18,  1           // InterfaceMethod org/apache/activemq/artemis/core/persistence/QueueBindingInfo.getId:()J
      40: invokestatic  #19                 // Method java/lang/Long.valueOf:(J)Ljava/lang/Long;
      43: aload         5
      45: invokeinterface #20,  3           // InterfaceMethod java/util/Map.put:(Ljava/lang/Object;Ljava/lang/Object;)Ljava/lang/Object;
      50: pop
      51: aload         5
      53: invokeinterface #21,  1           // InterfaceMethod org/apache/activemq/artemis/core/persistence/QueueBindingInfo.getFilterString:()Lorg/apache/activemq/artemis/api/core/SimpleString;
      58: invokestatic  #22                 // Method org/apache/activemq/artemis/core/filter/impl/FilterImpl.createFilter:(Lorg/apache/activemq/artemis/api/core/SimpleString;)Lorg/apache/activemq/artemis/core/filter/Filter;
      61: astore        6
      63: aload         6
      65: ifnull        100
      68: aload         6
      70: invokeinterface #23,  1           // InterfaceMethod org/apache/activemq/artemis/core/filter/Filter.getFilterString:()Lorg/apache/activemq/artemis/api/core/SimpleString;
      75: ifnull        100
      78: aload         6
      80: invokeinterface #23,  1           // InterfaceMethod org/apache/activemq/artemis/core/filter/Filter.getFilterString:()Lorg/apache/activemq/artemis/api/core/SimpleString;
      85: invokevirtual #24                 // Method org/apache/activemq/artemis/api/core/SimpleString.toString:()Ljava/lang/String;
      88: ldc           #26                 // String __AMQX=-1
      90: invokevirtual #27                 // Method java/lang/String.equals:(Ljava/lang/Object;)Z
      93: ifeq          100
      96: iconst_1
      97: goto          101
     100: iconst_0
     101: istore        7
     103: aload_0
     104: getfield      #2                  // Field postOffice:Lorg/apache/activemq/artemis/core/postoffice/PostOffice;
     107: aload         5
     109: invokeinterface #28,  1           // InterfaceMethod org/apache/activemq/artemis/core/persistence/QueueBindingInfo.getQueueName:()Lorg/apache/activemq/artemis/api/core/SimpleString;
     114: invokeinterface #29,  2           // InterfaceMethod org/apache/activemq/artemis/core/postoffice/PostOffice.getBinding:(Lorg/apache/activemq/artemis/api/core/SimpleString;)Lorg/apache/activemq/artemis/core/postoffice/Binding;
     119: ifnull        236
     122: iload         7
     124: ifeq          170
     127: aload_0
     128: getfield      #4                  // Field storageManager:Lorg/apache/activemq/artemis/core/persistence/StorageManager;
     131: invokeinterface #30,  1           // InterfaceMethod org/apache/activemq/artemis/core/persistence/StorageManager.generateID:()J
     136: lstore        8
     138: aload_0
     139: getfield      #4                  // Field storageManager:Lorg/apache/activemq/artemis/core/persistence/StorageManager;
     142: lload         8
     144: aload         5
     146: invokeinterface #18,  1           // InterfaceMethod org/apache/activemq/artemis/core/persistence/QueueBindingInfo.getId:()J
     151: invokeinterface #31,  5           // InterfaceMethod org/apache/activemq/artemis/core/persistence/StorageManager.deleteQueueBinding:(JJ)V
     156: aload_0
     157: getfield      #4                  // Field storageManager:Lorg/apache/activemq/artemis/core/persistence/StorageManager;
     160: lload         8
     162: invokeinterface #32,  3           // InterfaceMethod org/apache/activemq/artemis/core/persistence/StorageManager.commitBindings:(J)V
     167: goto          10
     170: aload         5
     172: invokeinterface #28,  1           // InterfaceMethod org/apache/activemq/artemis/core/persistence/QueueBindingInfo.getQueueName:()Lorg/apache/activemq/artemis/api/core/SimpleString;
     177: new           #33                 // class java/lang/StringBuilder
     180: dup
     181: invokespecial #34                 // Method java/lang/StringBuilder."<init>":()V
     184: ldc           #35                 // String -
     186: invokevirtual #36                 // Method java/lang/StringBuilder.append:(Ljava/lang/String;)Ljava/lang/StringBuilder;
     189: iload_3
     190: iinc          3, 1
     193: invokevirtual #37                 // Method java/lang/StringBuilder.append:(I)Ljava/lang/StringBuilder;
     196: invokevirtual #38                 // Method java/lang/StringBuilder.toString:()Ljava/lang/String;
     199: invokevirtual #39                 // Method org/apache/activemq/artemis/api/core/SimpleString.concat:(Ljava/lang/String;)Lorg/apache/activemq/artemis/api/core/SimpleString;
     202: astore        8
     204: getstatic     #40                 // Field org/apache/activemq/artemis/core/server/ActiveMQServerLogger.LOGGER:Lorg/apache/activemq/artemis/core/server/ActiveMQServerLogger;
     207: aload         5
     209: invokeinterface #28,  1           // InterfaceMethod org/apache/activemq/artemis/core/persistence/QueueBindingInfo.getQueueName:()Lorg/apache/activemq/artemis/api/core/SimpleString;
     214: invokevirtual #24                 // Method org/apache/activemq/artemis/api/core/SimpleString.toString:()Ljava/lang/String;
     217: aload         8
     219: invokevirtual #24                 // Method org/apache/activemq/artemis/api/core/SimpleString.toString:()Ljava/lang/String;
     222: invokeinterface #41,  3           // InterfaceMethod org/apache/activemq/artemis/core/server/ActiveMQServerLogger.queueDuplicatedRenaming:(Ljava/lang/String;Ljava/lang/String;)V
     227: aload         5
     229: aload         8
     231: invokeinterface #42,  2           // InterfaceMethod org/apache/activemq/artemis/core/persistence/QueueBindingInfo.replaceQueueName:(Lorg/apache/activemq/artemis/api/core/SimpleString;)V
     236: aconst_null
     237: astore        8
     239: iload         7
     241: ifne          282
     244: aload_0
     245: getfield      #3                  // Field pagingManager:Lorg/apache/activemq/artemis/core/paging/PagingManager;
     248: aload         5
     250: invokeinterface #43,  1           // InterfaceMethod org/apache/activemq/artemis/core/persistence/QueueBindingInfo.getAddress:()Lorg/apache/activemq/artemis/api/core/SimpleString;
     255: invokeinterface #44,  2           // InterfaceMethod org/apache/activemq/artemis/core/paging/PagingManager.getPageStore:(Lorg/apache/activemq/artemis/api/core/SimpleString;)Lorg/apache/activemq/artemis/core/paging/PagingStore;
     260: invokeinterface #45,  1           // InterfaceMethod org/apache/activemq/artemis/core/paging/PagingStore.getCursorProvider:()Lorg/apache/activemq/artemis/core/paging/cursor/PageCursorProvider;
     265: aload         5
     267: invokeinterface #18,  1           // InterfaceMethod org/apache/activemq/artemis/core/persistence/QueueBindingInfo.getId:()J
     272: aload         6
     274: iconst_1
     275: invokeinterface #46,  5           // InterfaceMethod org/apache/activemq/artemis/core/paging/cursor/PageCursorProvider.createSubscription:(JLorg/apache/activemq/artemis/core/filter/Filter;Z)Lorg/apache/activemq/artemis/core/paging/cursor/PageSubscription;
     280: astore        8
     282: aload_0
     283: getfield      #5                  // Field queueFactory:Lorg/apache/activemq/artemis/core/server/QueueFactory;
     286: aload         5
     288: invokeinterface #18,  1           // InterfaceMethod org/apache/activemq/artemis/core/persistence/QueueBindingInfo.getId:()J
     293: aload         5
     295: invokeinterface #43,  1           // InterfaceMethod org/apache/activemq/artemis/core/persistence/QueueBindingInfo.getAddress:()Lorg/apache/activemq/artemis/api/core/SimpleString;
     300: aload         5
     302: invokeinterface #28,  1           // InterfaceMethod org/apache/activemq/artemis/core/persistence/QueueBindingInfo.getQueueName:()Lorg/apache/activemq/artemis/api/core/SimpleString;
     307: aload         6
     309: aload         8
     311: aload         5
     313: invokeinterface #47,  1           // InterfaceMethod org/apache/activemq/artemis/core/persistence/QueueBindingInfo.getUser:()Lorg/apache/activemq/artemis/api/core/SimpleString;
     318: iconst_1
     319: iconst_0
     320: aload         5
     322: invokeinterface #48,  1           // InterfaceMethod org/apache/activemq/artemis/core/persistence/QueueBindingInfo.isAutoCreated:()Z
     327: invokeinterface #49,  11          // InterfaceMethod org/apache/activemq/artemis/core/server/QueueFactory.createQueue:(JLorg/apache/activemq/artemis/api/core/SimpleString;Lorg/apache/activemq/artemis/api/core/SimpleString;Lorg/apache/activemq/artemis/core/filter/Filter;Lorg/apache/activemq/artemis/core/paging/cursor/PageSubscription;Lorg/apache/activemq/artemis/api/core/SimpleString;ZZZ)Lorg/apache/activemq/artemis/core/server/Queue;
     332: astore        9
     334: aload         5
     336: invokeinterface #48,  1           // InterfaceMethod org/apache/activemq/artemis/core/persistence/QueueBindingInfo.isAutoCreated:()Z
     341: ifeq          375
     344: aload         9
     346: new           #50                 // class org/apache/activemq/artemis/core/server/impl/AutoCreatedQueueManagerImpl
     349: dup
     350: aload_0
     351: getfield      #2                  // Field postOffice:Lorg/apache/activemq/artemis/core/postoffice/PostOffice;
     354: checkcast     #51                 // class org/apache/activemq/artemis/core/postoffice/impl/PostOfficeImpl
     357: invokevirtual #52                 // Method org/apache/activemq/artemis/core/postoffice/impl/PostOfficeImpl.getServer:()Lorg/apache/activemq/artemis/core/server/ActiveMQServer;
     360: aload         5
     362: invokeinterface #28,  1           // InterfaceMethod org/apache/activemq/artemis/core/persistence/QueueBindingInfo.getQueueName:()Lorg/apache/activemq/artemis/api/core/SimpleString;
     367: invokespecial #53                 // Method org/apache/activemq/artemis/core/server/impl/AutoCreatedQueueManagerImpl."<init>":(Lorg/apache/activemq/artemis/core/server/ActiveMQServer;Lorg/apache/activemq/artemis/api/core/SimpleString;)V
     370: invokeinterface #54,  2           // InterfaceMethod org/apache/activemq/artemis/core/server/Queue.setConsumersRefCount:(Lorg/apache/activemq/artemis/utils/ReferenceCounter;)V
     375: new           #55                 // class org/apache/activemq/artemis/core/postoffice/impl/LocalQueueBinding
     378: dup
     379: aload         5
     381: invokeinterface #43,  1           // InterfaceMethod org/apache/activemq/artemis/core/persistence/QueueBindingInfo.getAddress:()Lorg/apache/activemq/artemis/api/core/SimpleString;
     386: aload         9
     388: aload_0
     389: getfield      #6                  // Field nodeManager:Lorg/apache/activemq/artemis/core/server/NodeManager;
     392: invokevirtual #56                 // Method org/apache/activemq/artemis/core/server/NodeManager.getNodeId:()Lorg/apache/activemq/artemis/api/core/SimpleString;
     395: invokespecial #57                 // Method org/apache/activemq/artemis/core/postoffice/impl/LocalQueueBinding."<init>":(Lorg/apache/activemq/artemis/api/core/SimpleString;Lorg/apache/activemq/artemis/core/server/Queue;Lorg/apache/activemq/artemis/api/core/SimpleString;)V
     398: astore        10
     400: aload_0
     401: getfield      #12                 // Field queues:Ljava/util/Map;
     404: aload         5
     406: invokeinterface #18,  1           // InterfaceMethod org/apache/activemq/artemis/core/persistence/QueueBindingInfo.getId:()J
     411: invokestatic  #19                 // Method java/lang/Long.valueOf:(J)Ljava/lang/Long;
     414: aload         9
     416: invokeinterface #20,  3           // InterfaceMethod java/util/Map.put:(Ljava/lang/Object;Ljava/lang/Object;)Ljava/lang/Object;
     421: pop
     422: aload_0
     423: getfield      #2                  // Field postOffice:Lorg/apache/activemq/artemis/core/postoffice/PostOffice;
     426: aload         10
     428: invokeinterface #58,  2           // InterfaceMethod org/apache/activemq/artemis/core/postoffice/PostOffice.addBinding:(Lorg/apache/activemq/artemis/core/postoffice/Binding;)V
     433: aload_0
     434: getfield      #7                  // Field managementService:Lorg/apache/activemq/artemis/core/server/management/ManagementService;
     437: aload         5
     439: invokeinterface #43,  1           // InterfaceMethod org/apache/activemq/artemis/core/persistence/QueueBindingInfo.getAddress:()Lorg/apache/activemq/artemis/api/core/SimpleString;
     444: invokeinterface #59,  2           // InterfaceMethod org/apache/activemq/artemis/core/server/management/ManagementService.registerAddress:(Lorg/apache/activemq/artemis/api/core/SimpleString;)V
     449: aload_0
     450: getfield      #7                  // Field managementService:Lorg/apache/activemq/artemis/core/server/management/ManagementService;
     453: aload         9
     455: aload         5
     457: invokeinterface #43,  1           // InterfaceMethod org/apache/activemq/artemis/core/persistence/QueueBindingInfo.getAddress:()Lorg/apache/activemq/artemis/api/core/SimpleString;
     462: aload_0
     463: getfield      #4                  // Field storageManager:Lorg/apache/activemq/artemis/core/persistence/StorageManager;
     466: invokeinterface #60,  4           // InterfaceMethod org/apache/activemq/artemis/core/server/management/ManagementService.registerQueue:(Lorg/apache/activemq/artemis/core/server/Queue;Lorg/apache/activemq/artemis/api/core/SimpleString;Lorg/apache/activemq/artemis/core/persistence/StorageManager;)V
     471: goto          10
     474: return

  public void handleAddMessage(java.util.Map<java.lang.Long, java.util.Map<java.lang.Long, org.apache.activemq.artemis.core.persistence.impl.journal.AddMessageRecord>>) throws java.lang.Exception;
    Code:
       0: aload_1
       1: invokeinterface #61,  1           // InterfaceMethod java/util/Map.entrySet:()Ljava/util/Set;
       6: invokeinterface #62,  1           // InterfaceMethod java/util/Set.iterator:()Ljava/util/Iterator;
      11: astore_2
      12: aload_2
      13: invokeinterface #15,  1           // InterfaceMethod java/util/Iterator.hasNext:()Z
      18: ifeq          283
      21: aload_2
      22: invokeinterface #16,  1           // InterfaceMethod java/util/Iterator.next:()Ljava/lang/Object;
      27: checkcast     #63                 // class java/util/Map$Entry
      30: astore_3
      31: aload_3
      32: invokeinterface #64,  1           // InterfaceMethod java/util/Map$Entry.getKey:()Ljava/lang/Object;
      37: checkcast     #65                 // class java/lang/Long
      40: invokevirtual #66                 // Method java/lang/Long.longValue:()J
      43: lstore        4
      45: aload_3
      46: invokeinterface #67,  1           // InterfaceMethod java/util/Map$Entry.getValue:()Ljava/lang/Object;
      51: checkcast     #68                 // class java/util/Map
      54: astore        6
      56: aload_0
      57: getfield      #12                 // Field queues:Ljava/util/Map;
      60: lload         4
      62: invokestatic  #19                 // Method java/lang/Long.valueOf:(J)Ljava/lang/Long;
      65: invokeinterface #69,  2           // InterfaceMethod java/util/Map.get:(Ljava/lang/Object;)Ljava/lang/Object;
      70: checkcast     #70                 // class org/apache/activemq/artemis/core/server/Queue
      73: astore        7
      75: aload         7
      77: ifnonnull     111
      80: aload         6
      82: invokeinterface #71,  1           // InterfaceMethod java/util/Map.values:()Ljava/util/Collection;
      87: invokeinterface #72,  1           // InterfaceMethod java/util/Collection.size:()I
      92: ifeq          12
      95: getstatic     #40                 // Field org/apache/activemq/artemis/core/server/ActiveMQServerLogger.LOGGER:Lorg/apache/activemq/artemis/core/server/ActiveMQServerLogger;
      98: lload         4
     100: invokestatic  #19                 // Method java/lang/Long.valueOf:(J)Ljava/lang/Long;
     103: invokeinterface #73,  2           // InterfaceMethod org/apache/activemq/artemis/core/server/ActiveMQServerLogger.journalCannotFindQueueForMessage:(Ljava/lang/Long;)V
     108: goto          12
     111: aload         7
     113: invokeinterface #74,  1           // InterfaceMethod org/apache/activemq/artemis/core/server/Queue.pause:()V
     118: aload         6
     120: invokeinterface #71,  1           // InterfaceMethod java/util/Map.values:()Ljava/util/Collection;
     125: astore        8
     127: invokestatic  #75                 // Method java/lang/System.currentTimeMillis:()J
     130: lstore        9
     132: aload         8
     134: invokeinterface #76,  1           // InterfaceMethod java/util/Collection.iterator:()Ljava/util/Iterator;
     139: astore        11
     141: aload         11
     143: invokeinterface #15,  1           // InterfaceMethod java/util/Iterator.hasNext:()Z
     148: ifeq          280
     151: aload         11
     153: invokeinterface #16,  1           // InterfaceMethod java/util/Iterator.next:()Ljava/lang/Object;
     158: checkcast     #77                 // class org/apache/activemq/artemis/core/persistence/impl/journal/AddMessageRecord
     161: astore        12
     163: aload         12
     165: invokevirtual #78                 // Method org/apache/activemq/artemis/core/persistence/impl/journal/AddMessageRecord.getScheduledDeliveryTime:()J
     168: lstore        13
     170: lload         13
     172: lconst_0
     173: lcmp
     174: ifeq          202
     177: lload         13
     179: lload         9
     181: lcmp
     182: ifgt          202
     185: lconst_0
     186: lstore        13
     188: aload         12
     190: invokevirtual #79                 // Method org/apache/activemq/artemis/core/persistence/impl/journal/AddMessageRecord.getMessage:()Lorg/apache/activemq/artemis/core/server/ServerMessage;
     193: getstatic     #80                 // Field org/apache/activemq/artemis/api/core/Message.HDR_SCHEDULED_DELIVERY_TIME:Lorg/apache/activemq/artemis/api/core/SimpleString;
     196: invokeinterface #81,  2           // InterfaceMethod org/apache/activemq/artemis/core/server/ServerMessage.removeProperty:(Lorg/apache/activemq/artemis/api/core/SimpleString;)Ljava/lang/Object;
     201: pop
     202: lload         13
     204: lconst_0
     205: lcmp
     206: ifeq          225
     209: aload         12
     211: invokevirtual #79                 // Method org/apache/activemq/artemis/core/persistence/impl/journal/AddMessageRecord.getMessage:()Lorg/apache/activemq/artemis/core/server/ServerMessage;
     214: getstatic     #80                 // Field org/apache/activemq/artemis/api/core/Message.HDR_SCHEDULED_DELIVERY_TIME:Lorg/apache/activemq/artemis/api/core/SimpleString;
     217: lload         13
     219: invokeinterface #82,  4           // InterfaceMethod org/apache/activemq/artemis/core/server/ServerMessage.putLongProperty:(Lorg/apache/activemq/artemis/api/core/SimpleString;J)Lorg/apache/activemq/artemis/api/core/Message;
     224: pop
     225: aload_0
     226: getfield      #2                  // Field postOffice:Lorg/apache/activemq/artemis/core/postoffice/PostOffice;
     229: aload         12
     231: invokevirtual #79                 // Method org/apache/activemq/artemis/core/persistence/impl/journal/AddMessageRecord.getMessage:()Lorg/apache/activemq/artemis/core/server/ServerMessage;
     234: aload         7
     236: aconst_null
     237: invokeinterface #83,  4           // InterfaceMethod org/apache/activemq/artemis/core/postoffice/PostOffice.reroute:(Lorg/apache/activemq/artemis/core/server/ServerMessage;Lorg/apache/activemq/artemis/core/server/Queue;Lorg/apache/activemq/artemis/core/transaction/Transaction;)Lorg/apache/activemq/artemis/core/server/MessageReference;
     242: astore        15
     244: aload         15
     246: aload         12
     248: invokevirtual #84                 // Method org/apache/activemq/artemis/core/persistence/impl/journal/AddMessageRecord.getDeliveryCount:()I
     251: invokeinterface #85,  2           // InterfaceMethod org/apache/activemq/artemis/core/server/MessageReference.setDeliveryCount:(I)V
     256: lload         13
     258: lconst_0
     259: lcmp
     260: ifeq          277
     263: aload         12
     265: invokevirtual #79                 // Method org/apache/activemq/artemis/core/persistence/impl/journal/AddMessageRecord.getMessage:()Lorg/apache/activemq/artemis/core/server/ServerMessage;
     268: getstatic     #80                 // Field org/apache/activemq/artemis/api/core/Message.HDR_SCHEDULED_DELIVERY_TIME:Lorg/apache/activemq/artemis/api/core/SimpleString;
     271: invokeinterface #81,  2           // InterfaceMethod org/apache/activemq/artemis/core/server/ServerMessage.removeProperty:(Lorg/apache/activemq/artemis/api/core/SimpleString;)Ljava/lang/Object;
     276: pop
     277: goto          141
     280: goto          12
     283: return

  public void handleNoMessageReferences(java.util.Map<java.lang.Long, org.apache.activemq.artemis.core.server.ServerMessage>);
    Code:
       0: aload_1
       1: invokeinterface #71,  1           // InterfaceMethod java/util/Map.values:()Ljava/util/Collection;
       6: invokeinterface #76,  1           // InterfaceMethod java/util/Collection.iterator:()Ljava/util/Iterator;
      11: astore_2
      12: aload_2
      13: invokeinterface #15,  1           // InterfaceMethod java/util/Iterator.hasNext:()Z
      18: ifeq          99
      21: aload_2
      22: invokeinterface #16,  1           // InterfaceMethod java/util/Iterator.next:()Ljava/lang/Object;
      27: checkcast     #86                 // class org/apache/activemq/artemis/core/server/ServerMessage
      30: astore_3
      31: aload_3
      32: invokeinterface #87,  1           // InterfaceMethod org/apache/activemq/artemis/core/server/ServerMessage.getRefCount:()I
      37: ifne          96
      40: getstatic     #40                 // Field org/apache/activemq/artemis/core/server/ActiveMQServerLogger.LOGGER:Lorg/apache/activemq/artemis/core/server/ActiveMQServerLogger;
      43: aload_3
      44: invokeinterface #88,  1           // InterfaceMethod org/apache/activemq/artemis/core/server/ServerMessage.getMessageID:()J
      49: invokestatic  #19                 // Method java/lang/Long.valueOf:(J)Ljava/lang/Long;
      52: invokeinterface #89,  2           // InterfaceMethod org/apache/activemq/artemis/core/server/ActiveMQServerLogger.journalUnreferencedMessage:(Ljava/lang/Long;)V
      57: aload_0
      58: getfield      #4                  // Field storageManager:Lorg/apache/activemq/artemis/core/persistence/StorageManager;
      61: aload_3
      62: invokeinterface #88,  1           // InterfaceMethod org/apache/activemq/artemis/core/server/ServerMessage.getMessageID:()J
      67: invokeinterface #90,  3           // InterfaceMethod org/apache/activemq/artemis/core/persistence/StorageManager.deleteMessage:(J)V
      72: goto          96
      75: astore        4
      77: getstatic     #40                 // Field org/apache/activemq/artemis/core/server/ActiveMQServerLogger.LOGGER:Lorg/apache/activemq/artemis/core/server/ActiveMQServerLogger;
      80: aload         4
      82: aload_3
      83: invokeinterface #88,  1           // InterfaceMethod org/apache/activemq/artemis/core/server/ServerMessage.getMessageID:()J
      88: invokestatic  #19                 // Method java/lang/Long.valueOf:(J)Ljava/lang/Long;
      91: invokeinterface #92,  3           // InterfaceMethod org/apache/activemq/artemis/core/server/ActiveMQServerLogger.journalErrorDeletingMessage:(Ljava/lang/Exception;Ljava/lang/Long;)V
      96: goto          12
      99: return
    Exception table:
       from    to  target type
          57    72    75   Class java/lang/Exception

  public void handleGroupingBindings(java.util.List<org.apache.activemq.artemis.core.persistence.GroupingInfo>);
    Code:
       0: aload_1
       1: invokeinterface #14,  1           // InterfaceMethod java/util/List.iterator:()Ljava/util/Iterator;
       6: astore_2
       7: aload_2
       8: invokeinterface #15,  1           // InterfaceMethod java/util/Iterator.hasNext:()Z
      13: ifeq          70
      16: aload_2
      17: invokeinterface #16,  1           // InterfaceMethod java/util/Iterator.next:()Ljava/lang/Object;
      22: checkcast     #93                 // class org/apache/activemq/artemis/core/persistence/GroupingInfo
      25: astore_3
      26: aload_0
      27: getfield      #8                  // Field groupingHandler:Lorg/apache/activemq/artemis/core/server/group/GroupingHandler;
      30: ifnull        67
      33: aload_0
      34: getfield      #8                  // Field groupingHandler:Lorg/apache/activemq/artemis/core/server/group/GroupingHandler;
      37: new           #94                 // class org/apache/activemq/artemis/core/server/group/impl/GroupBinding
      40: dup
      41: aload_3
      42: invokeinterface #95,  1           // InterfaceMethod org/apache/activemq/artemis/core/persistence/GroupingInfo.getId:()J
      47: aload_3
      48: invokeinterface #96,  1           // InterfaceMethod org/apache/activemq/artemis/core/persistence/GroupingInfo.getGroupId:()Lorg/apache/activemq/artemis/api/core/SimpleString;
      53: aload_3
      54: invokeinterface #97,  1           // InterfaceMethod org/apache/activemq/artemis/core/persistence/GroupingInfo.getClusterName:()Lorg/apache/activemq/artemis/api/core/SimpleString;
      59: invokespecial #98                 // Method org/apache/activemq/artemis/core/server/group/impl/GroupBinding."<init>":(JLorg/apache/activemq/artemis/api/core/SimpleString;Lorg/apache/activemq/artemis/api/core/SimpleString;)V
      62: invokeinterface #99,  2           // InterfaceMethod org/apache/activemq/artemis/core/server/group/GroupingHandler.addGroupBinding:(Lorg/apache/activemq/artemis/core/server/group/impl/GroupBinding;)V
      67: goto          7
      70: return

  public void handleDuplicateIds(java.util.Map<org.apache.activemq.artemis.api.core.SimpleString, java.util.List<org.apache.activemq.artemis.api.core.Pair<byte[], java.lang.Long>>>) throws java.lang.Exception;
    Code:
       0: aload_1
       1: invokeinterface #61,  1           // InterfaceMethod java/util/Map.entrySet:()Ljava/util/Set;
       6: invokeinterface #62,  1           // InterfaceMethod java/util/Set.iterator:()Ljava/util/Iterator;
      11: astore_2
      12: aload_2
      13: invokeinterface #15,  1           // InterfaceMethod java/util/Iterator.hasNext:()Z
      18: ifeq          86
      21: aload_2
      22: invokeinterface #16,  1           // InterfaceMethod java/util/Iterator.next:()Ljava/lang/Object;
      27: checkcast     #63                 // class java/util/Map$Entry
      30: astore_3
      31: aload_3
      32: invokeinterface #64,  1           // InterfaceMethod java/util/Map$Entry.getKey:()Ljava/lang/Object;
      37: checkcast     #100                // class org/apache/activemq/artemis/api/core/SimpleString
      40: astore        4
      42: aload_0
      43: getfield      #2                  // Field postOffice:Lorg/apache/activemq/artemis/core/postoffice/PostOffice;
      46: aload         4
      48: invokeinterface #101,  2          // InterfaceMethod org/apache/activemq/artemis/core/postoffice/PostOffice.getDuplicateIDCache:(Lorg/apache/activemq/artemis/api/core/SimpleString;)Lorg/apache/activemq/artemis/core/postoffice/DuplicateIDCache;
      53: astore        5
      55: aload_0
      56: getfield      #9                  // Field configuration:Lorg/apache/activemq/artemis/core/config/Configuration;
      59: invokeinterface #102,  1          // InterfaceMethod org/apache/activemq/artemis/core/config/Configuration.isPersistIDCache:()Z
      64: ifeq          83
      67: aload         5
      69: aload_3
      70: invokeinterface #67,  1           // InterfaceMethod java/util/Map$Entry.getValue:()Ljava/lang/Object;
      75: checkcast     #103                // class java/util/List
      78: invokeinterface #104,  2          // InterfaceMethod org/apache/activemq/artemis/core/postoffice/DuplicateIDCache.load:(Ljava/util/List;)V
      83: goto          12
      86: return

  public void postLoad(org.apache.activemq.artemis.core.journal.Journal, org.apache.activemq.artemis.core.transaction.ResourceManager, java.util.Map<org.apache.activemq.artemis.api.core.SimpleString, java.util.List<org.apache.activemq.artemis.api.core.Pair<byte[], java.lang.Long>>>) throws java.lang.Exception;
    Code:
       0: aload_0
       1: getfield      #12                 // Field queues:Ljava/util/Map;
       4: invokeinterface #71,  1           // InterfaceMethod java/util/Map.values:()Ljava/util/Collection;
       9: invokeinterface #76,  1           // InterfaceMethod java/util/Collection.iterator:()Ljava/util/Iterator;
      14: astore        4
      16: aload         4
      18: invokeinterface #15,  1           // InterfaceMethod java/util/Iterator.hasNext:()Z
      23: ifeq          48
      26: aload         4
      28: invokeinterface #16,  1           // InterfaceMethod java/util/Iterator.next:()Ljava/lang/Object;
      33: checkcast     #70                 // class org/apache/activemq/artemis/core/server/Queue
      36: astore        5
      38: aload         5
      40: invokeinterface #105,  1          // InterfaceMethod org/apache/activemq/artemis/core/server/Queue.resume:()V
      45: goto          16
      48: ldc           #106                // String org.apache.activemq.opt.directblast
      50: invokestatic  #107                // Method java/lang/System.getProperty:(Ljava/lang/String;)Ljava/lang/String;
      53: ifnull        62
      56: aload_1
      57: invokeinterface #108,  1          // InterfaceMethod org/apache/activemq/artemis/core/journal/Journal.runDirectJournalBlast:()V
      62: return

  public void handlePreparedSendMessage(org.apache.activemq.artemis.core.server.ServerMessage, org.apache.activemq.artemis.core.transaction.Transaction, long) throws java.lang.Exception;
    Code:
       0: aload_0
       1: getfield      #12                 // Field queues:Ljava/util/Map;
       4: lload_3
       5: invokestatic  #19                 // Method java/lang/Long.valueOf:(J)Ljava/lang/Long;
       8: invokeinterface #69,  2           // InterfaceMethod java/util/Map.get:(Ljava/lang/Object;)Ljava/lang/Object;
      13: checkcast     #70                 // class org/apache/activemq/artemis/core/server/Queue
      16: astore        5
      18: aload         5
      20: ifnonnull     36
      23: getstatic     #40                 // Field org/apache/activemq/artemis/core/server/ActiveMQServerLogger.LOGGER:Lorg/apache/activemq/artemis/core/server/ActiveMQServerLogger;
      26: lload_3
      27: invokestatic  #19                 // Method java/lang/Long.valueOf:(J)Ljava/lang/Long;
      30: invokeinterface #109,  2          // InterfaceMethod org/apache/activemq/artemis/core/server/ActiveMQServerLogger.journalMessageInPreparedTX:(Ljava/lang/Long;)V
      35: return
      36: aload_0
      37: getfield      #2                  // Field postOffice:Lorg/apache/activemq/artemis/core/postoffice/PostOffice;
      40: aload_1
      41: aload         5
      43: aload_2
      44: invokeinterface #83,  4           // InterfaceMethod org/apache/activemq/artemis/core/postoffice/PostOffice.reroute:(Lorg/apache/activemq/artemis/core/server/ServerMessage;Lorg/apache/activemq/artemis/core/server/Queue;Lorg/apache/activemq/artemis/core/transaction/Transaction;)Lorg/apache/activemq/artemis/core/server/MessageReference;
      49: pop
      50: return

  public void handlePreparedAcknowledge(long, java.util.List<org.apache.activemq.artemis.core.server.MessageReference>, long) throws java.lang.Exception;
    Code:
       0: aload_0
       1: getfield      #12                 // Field queues:Ljava/util/Map;
       4: lload         4
       6: invokestatic  #19                 // Method java/lang/Long.valueOf:(J)Ljava/lang/Long;
       9: invokeinterface #69,  2           // InterfaceMethod java/util/Map.get:(Ljava/lang/Object;)Ljava/lang/Object;
      14: checkcast     #70                 // class org/apache/activemq/artemis/core/server/Queue
      17: astore        6
      19: aload         6
      21: ifnonnull     52
      24: new           #110                // class java/lang/IllegalStateException
      27: dup
      28: new           #33                 // class java/lang/StringBuilder
      31: dup
      32: invokespecial #34                 // Method java/lang/StringBuilder."<init>":()V
      35: ldc           #111                // String Cannot find queue with id
      37: invokevirtual #36                 // Method java/lang/StringBuilder.append:(Ljava/lang/String;)Ljava/lang/StringBuilder;
      40: lload         4
      42: invokevirtual #112                // Method java/lang/StringBuilder.append:(J)Ljava/lang/StringBuilder;
      45: invokevirtual #38                 // Method java/lang/StringBuilder.toString:()Ljava/lang/String;
      48: invokespecial #113                // Method java/lang/IllegalStateException."<init>":(Ljava/lang/String;)V
      51: athrow
      52: aload         6
      54: lload_1
      55: invokeinterface #114,  3          // InterfaceMethod org/apache/activemq/artemis/core/server/Queue.removeReferenceWithID:(J)Lorg/apache/activemq/artemis/core/server/MessageReference;
      60: astore        7
      62: aload         7
      64: ifnonnull     82
      67: getstatic     #40                 // Field org/apache/activemq/artemis/core/server/ActiveMQServerLogger.LOGGER:Lorg/apache/activemq/artemis/core/server/ActiveMQServerLogger;
      70: lload_1
      71: invokestatic  #19                 // Method java/lang/Long.valueOf:(J)Ljava/lang/Long;
      74: invokeinterface #115,  2          // InterfaceMethod org/apache/activemq/artemis/core/server/ActiveMQServerLogger.journalErrorRemovingRef:(Ljava/lang/Long;)V
      79: goto          91
      82: aload_3
      83: aload         7
      85: invokeinterface #116,  2          // InterfaceMethod java/util/List.add:(Ljava/lang/Object;)Z
      90: pop
      91: return

  public void handlePreparedTransaction(org.apache.activemq.artemis.core.transaction.Transaction, java.util.List<org.apache.activemq.artemis.core.server.MessageReference>, javax.transaction.xa.Xid, org.apache.activemq.artemis.core.transaction.ResourceManager) throws java.lang.Exception;
    Code:
       0: aload_2
       1: invokeinterface #14,  1           // InterfaceMethod java/util/List.iterator:()Ljava/util/Iterator;
       6: astore        5
       8: aload         5
      10: invokeinterface #15,  1           // InterfaceMethod java/util/Iterator.hasNext:()Z
      15: ifeq          48
      18: aload         5
      20: invokeinterface #16,  1           // InterfaceMethod java/util/Iterator.next:()Ljava/lang/Object;
      25: checkcast     #117                // class org/apache/activemq/artemis/core/server/MessageReference
      28: astore        6
      30: aload         6
      32: invokeinterface #118,  1          // InterfaceMethod org/apache/activemq/artemis/core/server/MessageReference.getQueue:()Lorg/apache/activemq/artemis/core/server/Queue;
      37: aload_1
      38: aload         6
      40: invokeinterface #119,  3          // InterfaceMethod org/apache/activemq/artemis/core/server/Queue.reacknowledge:(Lorg/apache/activemq/artemis/core/transaction/Transaction;Lorg/apache/activemq/artemis/core/server/MessageReference;)V
      45: goto          8
      48: aload_1
      49: getstatic     #120                // Field org/apache/activemq/artemis/core/transaction/Transaction$State.PREPARED:Lorg/apache/activemq/artemis/core/transaction/Transaction$State;
      52: invokeinterface #121,  2          // InterfaceMethod org/apache/activemq/artemis/core/transaction/Transaction.setState:(Lorg/apache/activemq/artemis/core/transaction/Transaction$State;)V
      57: aload         4
      59: aload_3
      60: aload_1
      61: invokeinterface #122,  3          // InterfaceMethod org/apache/activemq/artemis/core/transaction/ResourceManager.putTransaction:(Ljavax/transaction/xa/Xid;Lorg/apache/activemq/artemis/core/transaction/Transaction;)Z
      66: pop
      67: return

  public void recoverPendingPageCounters(java.util.List<org.apache.activemq.artemis.core.persistence.impl.PageCountPending>) throws java.lang.Exception;
    Code:
       0: new           #123                // class org/apache/activemq/artemis/core/transaction/impl/TransactionImpl
       3: dup
       4: aload_0
       5: getfield      #4                  // Field storageManager:Lorg/apache/activemq/artemis/core/persistence/StorageManager;
       8: invokespecial #124                // Method org/apache/activemq/artemis/core/transaction/impl/TransactionImpl."<init>":(Lorg/apache/activemq/artemis/core/persistence/StorageManager;)V
      11: astore_2
      12: aload_0
      13: aload_0
      14: getfield      #12                 // Field queues:Ljava/util/Map;
      17: aload_1
      18: aload_2
      19: invokespecial #125                // Method generateMapsOnPendingCount:(Ljava/util/Map;Ljava/util/List;Lorg/apache/activemq/artemis/core/transaction/Transaction;)Ljava/util/Map;
      22: astore_3
      23: aload_3
      24: invokeinterface #126,  1          // InterfaceMethod java/util/Map.keySet:()Ljava/util/Set;
      29: invokeinterface #62,  1           // InterfaceMethod java/util/Set.iterator:()Ljava/util/Iterator;
      34: astore        4
      36: aload         4
      38: invokeinterface #15,  1           // InterfaceMethod java/util/Iterator.hasNext:()Z
      43: ifeq          825
      46: aload         4
      48: invokeinterface #16,  1           // InterfaceMethod java/util/Iterator.next:()Ljava/lang/Object;
      53: checkcast     #100                // class org/apache/activemq/artemis/api/core/SimpleString
      56: astore        5
      58: aload_0
      59: getfield      #3                  // Field pagingManager:Lorg/apache/activemq/artemis/core/paging/PagingManager;
      62: aload         5
      64: invokeinterface #44,  2           // InterfaceMethod org/apache/activemq/artemis/core/paging/PagingManager.getPageStore:(Lorg/apache/activemq/artemis/api/core/SimpleString;)Lorg/apache/activemq/artemis/core/paging/PagingStore;
      69: astore        6
      71: aload_3
      72: aload         5
      74: invokeinterface #69,  2           // InterfaceMethod java/util/Map.get:(Ljava/lang/Object;)Ljava/lang/Object;
      79: checkcast     #68                 // class java/util/Map
      82: astore        7
      84: getstatic     #127                // Field $assertionsDisabled:Z
      87: ifne          103
      90: aload         7
      92: ifnonnull     103
      95: new           #128                // class java/lang/AssertionError
      98: dup
      99: invokespecial #129                // Method java/lang/AssertionError."<init>":()V
     102: athrow
     103: aload         7
     105: invokeinterface #126,  1          // InterfaceMethod java/util/Map.keySet:()Ljava/util/Set;
     110: invokeinterface #62,  1           // InterfaceMethod java/util/Set.iterator:()Ljava/util/Iterator;
     115: astore        8
     117: aload         8
     119: invokeinterface #15,  1           // InterfaceMethod java/util/Iterator.hasNext:()Z
     124: ifeq          822
     127: aload         8
     129: invokeinterface #16,  1           // InterfaceMethod java/util/Iterator.next:()Ljava/lang/Object;
     134: checkcast     #65                 // class java/lang/Long
     137: astore        9
     139: aload         7
     141: aload         9
     143: invokeinterface #69,  2           // InterfaceMethod java/util/Map.get:(Ljava/lang/Object;)Ljava/lang/Object;
     148: checkcast     #68                 // class java/util/Map
     151: astore        10
     153: getstatic     #127                // Field $assertionsDisabled:Z
     156: ifne          172
     159: aload         10
     161: ifnonnull     172
     164: new           #128                // class java/lang/AssertionError
     167: dup
     168: invokespecial #129                // Method java/lang/AssertionError."<init>":()V
     171: athrow
     172: aload         6
     174: aload         9
     176: invokevirtual #130                // Method java/lang/Long.intValue:()I
     179: invokeinterface #131,  2          // InterfaceMethod org/apache/activemq/artemis/core/paging/PagingStore.checkPageFileExists:(I)Z
     184: ifeq          642
     187: aload         6
     189: aload         9
     191: invokevirtual #130                // Method java/lang/Long.intValue:()I
     194: invokeinterface #132,  2          // InterfaceMethod org/apache/activemq/artemis/core/paging/PagingStore.createPage:(I)Lorg/apache/activemq/artemis/core/paging/impl/Page;
     199: astore        11
     201: aload         11
     203: invokevirtual #133                // Method org/apache/activemq/artemis/core/paging/impl/Page.open:()V
     206: aload         11
     208: aload_0
     209: getfield      #4                  // Field storageManager:Lorg/apache/activemq/artemis/core/persistence/StorageManager;
     212: invokevirtual #134                // Method org/apache/activemq/artemis/core/paging/impl/Page.read:(Lorg/apache/activemq/artemis/core/persistence/StorageManager;)Ljava/util/List;
     215: astore        12
     217: new           #10                 // class java/util/HashMap
     220: dup
     221: invokespecial #11                 // Method java/util/HashMap."<init>":()V
     224: astore        13
     226: aload         12
     228: invokeinterface #14,  1           // InterfaceMethod java/util/List.iterator:()Ljava/util/Iterator;
     233: astore        14
     235: aload         14
     237: invokeinterface #15,  1           // InterfaceMethod java/util/Iterator.hasNext:()Z
     242: ifeq          362
     245: aload         14
     247: invokeinterface #16,  1           // InterfaceMethod java/util/Iterator.next:()Ljava/lang/Object;
     252: checkcast     #135                // class org/apache/activemq/artemis/core/paging/PagedMessage
     255: astore        15
     257: aload         15
     259: invokeinterface #136,  1          // InterfaceMethod org/apache/activemq/artemis/core/paging/PagedMessage.getTransactionID:()J
     264: lconst_0
     265: lcmp
     266: ifgt          359
     269: aload         15
     271: invokeinterface #137,  1          // InterfaceMethod org/apache/activemq/artemis/core/paging/PagedMessage.getQueueIDs:()[J
     276: astore        16
     278: aload         16
     280: arraylength
     281: istore        17
     283: iconst_0
     284: istore        18
     286: iload         18
     288: iload         17
     290: if_icmpge     359
     293: aload         16
     295: iload         18
     297: laload
     298: lstore        19
     300: aload         13
     302: lload         19
     304: invokestatic  #19                 // Method java/lang/Long.valueOf:(J)Ljava/lang/Long;
     307: invokeinterface #69,  2           // InterfaceMethod java/util/Map.get:(Ljava/lang/Object;)Ljava/lang/Object;
     312: checkcast     #138                // class java/util/concurrent/atomic/AtomicInteger
     315: astore        21
     317: aload         21
     319: ifnonnull     347
     322: new           #138                // class java/util/concurrent/atomic/AtomicInteger
     325: dup
     326: iconst_0
     327: invokespecial #139                // Method java/util/concurrent/atomic/AtomicInteger."<init>":(I)V
     330: astore        21
     332: aload         13
     334: lload         19
     336: invokestatic  #19                 // Method java/lang/Long.valueOf:(J)Ljava/lang/Long;
     339: aload         21
     341: invokeinterface #20,  3           // InterfaceMethod java/util/Map.put:(Ljava/lang/Object;Ljava/lang/Object;)Ljava/lang/Object;
     346: pop
     347: aload         21
     349: invokevirtual #140                // Method java/util/concurrent/atomic/AtomicInteger.incrementAndGet:()I
     352: pop
     353: iinc          18, 1
     356: goto          286
     359: goto          235
     362: aload         10
     364: invokeinterface #61,  1           // InterfaceMethod java/util/Map.entrySet:()Ljava/util/Set;
     369: invokeinterface #62,  1           // InterfaceMethod java/util/Set.iterator:()Ljava/util/Iterator;
     374: astore        14
     376: aload         14
     378: invokeinterface #15,  1           // InterfaceMethod java/util/Iterator.hasNext:()Z
     383: ifeq          639
     386: aload         14
     388: invokeinterface #16,  1           // InterfaceMethod java/util/Iterator.next:()Ljava/lang/Object;
     393: checkcast     #63                 // class java/util/Map$Entry
     396: astore        15
     398: aload         15
     400: invokeinterface #67,  1           // InterfaceMethod java/util/Map$Entry.getValue:()Ljava/lang/Object;
     405: checkcast     #103                // class java/util/List
     408: invokeinterface #14,  1           // InterfaceMethod java/util/List.iterator:()Ljava/util/Iterator;
     413: astore        16
     415: aload         16
     417: invokeinterface #15,  1           // InterfaceMethod java/util/Iterator.hasNext:()Z
     422: ifeq          495
     425: aload         16
     427: invokeinterface #16,  1           // InterfaceMethod java/util/Iterator.next:()Ljava/lang/Object;
     432: checkcast     #141                // class org/apache/activemq/artemis/core/persistence/impl/PageCountPending
     435: astore        17
     437: getstatic     #40                 // Field org/apache/activemq/artemis/core/server/ActiveMQServerLogger.LOGGER:Lorg/apache/activemq/artemis/core/server/ActiveMQServerLogger;
     440: new           #33                 // class java/lang/StringBuilder
     443: dup
     444: invokespecial #34                 // Method java/lang/StringBuilder."<init>":()V
     447: ldc           #142                // String Deleting pg tempCount
     449: invokevirtual #36                 // Method java/lang/StringBuilder.append:(Ljava/lang/String;)Ljava/lang/StringBuilder;
     452: aload         17
     454: invokeinterface #143,  1          // InterfaceMethod org/apache/activemq/artemis/core/persistence/impl/PageCountPending.getID:()J
     459: invokevirtual #112                // Method java/lang/StringBuilder.append:(J)Ljava/lang/StringBuilder;
     462: invokevirtual #38                 // Method java/lang/StringBuilder.toString:()Ljava/lang/String;
     465: invokeinterface #144,  2          // InterfaceMethod org/apache/activemq/artemis/core/server/ActiveMQServerLogger.debug:(Ljava/lang/Object;)V
     470: aload_0
     471: getfield      #4                  // Field storageManager:Lorg/apache/activemq/artemis/core/persistence/StorageManager;
     474: aload_2
     475: invokeinterface #145,  1          // InterfaceMethod org/apache/activemq/artemis/core/transaction/Transaction.getID:()J
     480: aload         17
     482: invokeinterface #143,  1          // InterfaceMethod org/apache/activemq/artemis/core/persistence/impl/PageCountPending.getID:()J
     487: invokeinterface #146,  5          // InterfaceMethod org/apache/activemq/artemis/core/persistence/StorageManager.deletePendingPageCounter:(JJ)V
     492: goto          415
     495: aload         6
     497: invokeinterface #45,  1           // InterfaceMethod org/apache/activemq/artemis/core/paging/PagingStore.getCursorProvider:()Lorg/apache/activemq/artemis/core/paging/cursor/PageCursorProvider;
     502: aload         15
     504: invokeinterface #64,  1           // InterfaceMethod java/util/Map$Entry.getKey:()Ljava/lang/Object;
     509: checkcast     #65                 // class java/lang/Long
     512: invokevirtual #66                 // Method java/lang/Long.longValue:()J
     515: invokeinterface #147,  3          // InterfaceMethod org/apache/activemq/artemis/core/paging/cursor/PageCursorProvider.getSubscription:(J)Lorg/apache/activemq/artemis/core/paging/cursor/PageSubscription;
     520: invokeinterface #148,  1          // InterfaceMethod org/apache/activemq/artemis/core/paging/cursor/PageSubscription.getCounter:()Lorg/apache/activemq/artemis/core/paging/cursor/PageSubscriptionCounter;
     525: astore        16
     527: aload         13
     529: aload         15
     531: invokeinterface #64,  1           // InterfaceMethod java/util/Map$Entry.getKey:()Ljava/lang/Object;
     536: invokeinterface #69,  2           // InterfaceMethod java/util/Map.get:(Ljava/lang/Object;)Ljava/lang/Object;
     541: checkcast     #138                // class java/util/concurrent/atomic/AtomicInteger
     544: astore        17
     546: aload         17
     548: ifnonnull     592
     551: getstatic     #40                 // Field org/apache/activemq/artemis/core/server/ActiveMQServerLogger.LOGGER:Lorg/apache/activemq/artemis/core/server/ActiveMQServerLogger;
     554: new           #33                 // class java/lang/StringBuilder
     557: dup
     558: invokespecial #34                 // Method java/lang/StringBuilder."<init>":()V
     561: ldc           #149                // String Page
     563: invokevirtual #36                 // Method java/lang/StringBuilder.append:(Ljava/lang/String;)Ljava/lang/StringBuilder;
     566: aload         15
     568: invokeinterface #64,  1           // InterfaceMethod java/util/Map$Entry.getKey:()Ljava/lang/Object;
     573: invokevirtual #150                // Method java/lang/StringBuilder.append:(Ljava/lang/Object;)Ljava/lang/StringBuilder;
     576: ldc           #151                // String  wasn\'t open, so we will just ignore
     578: invokevirtual #36                 // Method java/lang/StringBuilder.append:(Ljava/lang/String;)Ljava/lang/StringBuilder;
     581: invokevirtual #38                 // Method java/lang/StringBuilder.toString:()Ljava/lang/String;
     584: invokeinterface #144,  2          // InterfaceMethod org/apache/activemq/artemis/core/server/ActiveMQServerLogger.debug:(Ljava/lang/Object;)V
     589: goto          636
     592: getstatic     #40                 // Field org/apache/activemq/artemis/core/server/ActiveMQServerLogger.LOGGER:Lorg/apache/activemq/artemis/core/server/ActiveMQServerLogger;
     595: new           #33                 // class java/lang/StringBuilder
     598: dup
     599: invokespecial #34                 // Method java/lang/StringBuilder."<init>":()V
     602: ldc           #152                // String Replacing counter
     604: invokevirtual #36                 // Method java/lang/StringBuilder.append:(Ljava/lang/String;)Ljava/lang/StringBuilder;
     607: aload         17
     609: invokevirtual #153                // Method java/util/concurrent/atomic/AtomicInteger.get:()I
     612: invokevirtual #37                 // Method java/lang/StringBuilder.append:(I)Ljava/lang/StringBuilder;
     615: invokevirtual #38                 // Method java/lang/StringBuilder.toString:()Ljava/lang/String;
     618: invokeinterface #144,  2          // InterfaceMethod org/apache/activemq/artemis/core/server/ActiveMQServerLogger.debug:(Ljava/lang/Object;)V
     623: aload         16
     625: aload_2
     626: aload         17
     628: invokevirtual #153                // Method java/util/concurrent/atomic/AtomicInteger.get:()I
     631: invokeinterface #154,  3          // InterfaceMethod org/apache/activemq/artemis/core/paging/cursor/PageSubscriptionCounter.increment:(Lorg/apache/activemq/artemis/core/transaction/Transaction;I)V
     636: goto          376
     639: goto          819
     642: getstatic     #40                 // Field org/apache/activemq/artemis/core/server/ActiveMQServerLogger.LOGGER:Lorg/apache/activemq/artemis/core/server/ActiveMQServerLogger;
     645: new           #33                 // class java/lang/StringBuilder
     648: dup
     649: invokespecial #34                 // Method java/lang/StringBuilder."<init>":()V
     652: ldc           #149                // String Page
     654: invokevirtual #36                 // Method java/lang/StringBuilder.append:(Ljava/lang/String;)Ljava/lang/StringBuilder;
     657: aload         9
     659: invokevirtual #150                // Method java/lang/StringBuilder.append:(Ljava/lang/Object;)Ljava/lang/StringBuilder;
     662: ldc           #155                // String  didn\'t exist on address
     664: invokevirtual #36                 // Method java/lang/StringBuilder.append:(Ljava/lang/String;)Ljava/lang/StringBuilder;
     667: aload         5
     669: invokevirtual #150                // Method java/lang/StringBuilder.append:(Ljava/lang/Object;)Ljava/lang/StringBuilder;
     672: ldc           #156                // String , so we are just removing records
     674: invokevirtual #36                 // Method java/lang/StringBuilder.append:(Ljava/lang/String;)Ljava/lang/StringBuilder;
     677: invokevirtual #38                 // Method java/lang/StringBuilder.toString:()Ljava/lang/String;
     680: invokeinterface #144,  2          // InterfaceMethod org/apache/activemq/artemis/core/server/ActiveMQServerLogger.debug:(Ljava/lang/Object;)V
     685: aload         10
     687: invokeinterface #71,  1           // InterfaceMethod java/util/Map.values:()Ljava/util/Collection;
     692: invokeinterface #76,  1           // InterfaceMethod java/util/Collection.iterator:()Ljava/util/Iterator;
     697: astore        11
     699: aload         11
     701: invokeinterface #15,  1           // InterfaceMethod java/util/Iterator.hasNext:()Z
     706: ifeq          819
     709: aload         11
     711: invokeinterface #16,  1           // InterfaceMethod java/util/Iterator.next:()Ljava/lang/Object;
     716: checkcast     #103                // class java/util/List
     719: astore        12
     721: aload         12
     723: invokeinterface #14,  1           // InterfaceMethod java/util/List.iterator:()Ljava/util/Iterator;
     728: astore        13
     730: aload         13
     732: invokeinterface #15,  1           // InterfaceMethod java/util/Iterator.hasNext:()Z
     737: ifeq          816
     740: aload         13
     742: invokeinterface #16,  1           // InterfaceMethod java/util/Iterator.next:()Ljava/lang/Object;
     747: checkcast     #141                // class org/apache/activemq/artemis/core/persistence/impl/PageCountPending
     750: astore        14
     752: getstatic     #40                 // Field org/apache/activemq/artemis/core/server/ActiveMQServerLogger.LOGGER:Lorg/apache/activemq/artemis/core/server/ActiveMQServerLogger;
     755: new           #33                 // class java/lang/StringBuilder
     758: dup
     759: invokespecial #34                 // Method java/lang/StringBuilder."<init>":()V
     762: ldc           #157                // String Removing pending page counter
     764: invokevirtual #36                 // Method java/lang/StringBuilder.append:(Ljava/lang/String;)Ljava/lang/StringBuilder;
     767: aload         14
     769: invokeinterface #143,  1          // InterfaceMethod org/apache/activemq/artemis/core/persistence/impl/PageCountPending.getID:()J
     774: invokevirtual #112                // Method java/lang/StringBuilder.append:(J)Ljava/lang/StringBuilder;
     777: invokevirtual #38                 // Method java/lang/StringBuilder.toString:()Ljava/lang/String;
     780: invokeinterface #144,  2          // InterfaceMethod org/apache/activemq/artemis/core/server/ActiveMQServerLogger.debug:(Ljava/lang/Object;)V
     785: aload_0
     786: getfield      #4                  // Field storageManager:Lorg/apache/activemq/artemis/core/persistence/StorageManager;
     789: aload_2
     790: invokeinterface #145,  1          // InterfaceMethod org/apache/activemq/artemis/core/transaction/Transaction.getID:()J
     795: aload         14
     797: invokeinterface #143,  1          // InterfaceMethod org/apache/activemq/artemis/core/persistence/impl/PageCountPending.getID:()J
     802: invokeinterface #146,  5          // InterfaceMethod org/apache/activemq/artemis/core/persistence/StorageManager.deletePendingPageCounter:(JJ)V
     807: aload_2
     808: invokeinterface #158,  1          // InterfaceMethod org/apache/activemq/artemis/core/transaction/Transaction.setContainsPersistent:()V
     813: goto          730
     816: goto          699
     819: goto          117
     822: goto          36
     825: aload_2
     826: invokeinterface #159,  1          // InterfaceMethod org/apache/activemq/artemis/core/transaction/Transaction.commit:()V
     831: return

  public void cleanUp();
    Code:
       0: aload_0
       1: getfield      #12                 // Field queues:Ljava/util/Map;
       4: invokeinterface #160,  1          // InterfaceMethod java/util/Map.clear:()V
       9: return

  private java.util.Map<org.apache.activemq.artemis.api.core.SimpleString, java.util.Map<java.lang.Long, java.util.Map<java.lang.Long, java.util.List<org.apache.activemq.artemis.core.persistence.impl.PageCountPending>>>> generateMapsOnPendingCount(java.util.Map<java.lang.Long, org.apache.activemq.artemis.core.server.Queue>, java.util.List<org.apache.activemq.artemis.core.persistence.impl.PageCountPending>, org.apache.activemq.artemis.core.transaction.Transaction) throws java.lang.Exception;
    Code:
       0: new           #10                 // class java/util/HashMap
       3: dup
       4: invokespecial #11                 // Method java/util/HashMap."<init>":()V
       7: astore        4
       9: aload_2
      10: invokeinterface #14,  1           // InterfaceMethod java/util/List.iterator:()Ljava/util/Iterator;
      15: astore        5
      17: aload         5
      19: invokeinterface #15,  1           // InterfaceMethod java/util/Iterator.hasNext:()Z
      24: ifeq          331
      27: aload         5
      29: invokeinterface #16,  1           // InterfaceMethod java/util/Iterator.next:()Ljava/lang/Object;
      34: checkcast     #141                // class org/apache/activemq/artemis/core/persistence/impl/PageCountPending
      37: astore        6
      39: aload         6
      41: invokeinterface #161,  1          // InterfaceMethod org/apache/activemq/artemis/core/persistence/impl/PageCountPending.getQueueID:()J
      46: lstore        7
      48: aload         6
      50: invokeinterface #162,  1          // InterfaceMethod org/apache/activemq/artemis/core/persistence/impl/PageCountPending.getPageID:()J
      55: lstore        9
      57: aload_1
      58: lload         7
      60: invokestatic  #19                 // Method java/lang/Long.valueOf:(J)Ljava/lang/Long;
      63: invokeinterface #69,  2           // InterfaceMethod java/util/Map.get:(Ljava/lang/Object;)Ljava/lang/Object;
      68: checkcast     #70                 // class org/apache/activemq/artemis/core/server/Queue
      71: astore        11
      73: aload         11
      75: ifnonnull     162
      78: getstatic     #40                 // Field org/apache/activemq/artemis/core/server/ActiveMQServerLogger.LOGGER:Lorg/apache/activemq/artemis/core/server/ActiveMQServerLogger;
      81: new           #33                 // class java/lang/StringBuilder
      84: dup
      85: invokespecial #34                 // Method java/lang/StringBuilder."<init>":()V
      88: ldc           #163                // String removing pending page counter id =
      90: invokevirtual #36                 // Method java/lang/StringBuilder.append:(Ljava/lang/String;)Ljava/lang/StringBuilder;
      93: aload         6
      95: invokeinterface #143,  1          // InterfaceMethod org/apache/activemq/artemis/core/persistence/impl/PageCountPending.getID:()J
     100: invokevirtual #112                // Method java/lang/StringBuilder.append:(J)Ljava/lang/StringBuilder;
     103: ldc           #164                // String  as queueID=
     105: invokevirtual #36                 // Method java/lang/StringBuilder.append:(Ljava/lang/String;)Ljava/lang/StringBuilder;
     108: aload         6
     110: invokeinterface #143,  1          // InterfaceMethod org/apache/activemq/artemis/core/persistence/impl/PageCountPending.getID:()J
     115: invokevirtual #112                // Method java/lang/StringBuilder.append:(J)Ljava/lang/StringBuilder;
     118: ldc           #165                // String  no longer exists
     120: invokevirtual #36                 // Method java/lang/StringBuilder.append:(Ljava/lang/String;)Ljava/lang/StringBuilder;
     123: invokevirtual #38                 // Method java/lang/StringBuilder.toString:()Ljava/lang/String;
     126: invokeinterface #144,  2          // InterfaceMethod org/apache/activemq/artemis/core/server/ActiveMQServerLogger.debug:(Ljava/lang/Object;)V
     131: aload_0
     132: getfield      #4                  // Field storageManager:Lorg/apache/activemq/artemis/core/persistence/StorageManager;
     135: aload_3
     136: invokeinterface #145,  1          // InterfaceMethod org/apache/activemq/artemis/core/transaction/Transaction.getID:()J
     141: aload         6
     143: invokeinterface #143,  1          // InterfaceMethod org/apache/activemq/artemis/core/persistence/impl/PageCountPending.getID:()J
     148: invokeinterface #146,  5          // InterfaceMethod org/apache/activemq/artemis/core/persistence/StorageManager.deletePendingPageCounter:(JJ)V
     153: aload_3
     154: invokeinterface #158,  1          // InterfaceMethod org/apache/activemq/artemis/core/transaction/Transaction.setContainsPersistent:()V
     159: goto          17
     162: aload         11
     164: invokeinterface #166,  1          // InterfaceMethod org/apache/activemq/artemis/core/server/Queue.getAddress:()Lorg/apache/activemq/artemis/api/core/SimpleString;
     169: astore        12
     171: aload         4
     173: aload         12
     175: invokeinterface #69,  2           // InterfaceMethod java/util/Map.get:(Ljava/lang/Object;)Ljava/lang/Object;
     180: checkcast     #68                 // class java/util/Map
     183: astore        13
     185: aload         13
     187: ifnonnull     211
     190: new           #10                 // class java/util/HashMap
     193: dup
     194: invokespecial #11                 // Method java/util/HashMap."<init>":()V
     197: astore        13
     199: aload         4
     201: aload         12
     203: aload         13
     205: invokeinterface #20,  3           // InterfaceMethod java/util/Map.put:(Ljava/lang/Object;Ljava/lang/Object;)Ljava/lang/Object;
     210: pop
     211: aload         13
     213: lload         9
     215: invokestatic  #19                 // Method java/lang/Long.valueOf:(J)Ljava/lang/Long;
     218: invokeinterface #69,  2           // InterfaceMethod java/util/Map.get:(Ljava/lang/Object;)Ljava/lang/Object;
     223: checkcast     #68                 // class java/util/Map
     226: astore        14
     228: aload         14
     230: ifnonnull     257
     233: new           #10                 // class java/util/HashMap
     236: dup
     237: invokespecial #11                 // Method java/util/HashMap."<init>":()V
     240: astore        14
     242: aload         13
     244: lload         9
     246: invokestatic  #19                 // Method java/lang/Long.valueOf:(J)Ljava/lang/Long;
     249: aload         14
     251: invokeinterface #20,  3           // InterfaceMethod java/util/Map.put:(Ljava/lang/Object;Ljava/lang/Object;)Ljava/lang/Object;
     256: pop
     257: aload         14
     259: lload         7
     261: invokestatic  #19                 // Method java/lang/Long.valueOf:(J)Ljava/lang/Long;
     264: invokeinterface #69,  2           // InterfaceMethod java/util/Map.get:(Ljava/lang/Object;)Ljava/lang/Object;
     269: checkcast     #103                // class java/util/List
     272: astore        15
     274: aload         15
     276: ifnonnull     303
     279: new           #167                // class java/util/LinkedList
     282: dup
     283: invokespecial #168                // Method java/util/LinkedList."<init>":()V
     286: astore        15
     288: aload         14
     290: lload         7
     292: invokestatic  #19                 // Method java/lang/Long.valueOf:(J)Ljava/lang/Long;
     295: aload         15
     297: invokeinterface #20,  3           // InterfaceMethod java/util/Map.put:(Ljava/lang/Object;Ljava/lang/Object;)Ljava/lang/Object;
     302: pop
     303: aload         15
     305: aload         6
     307: invokeinterface #116,  2          // InterfaceMethod java/util/List.add:(Ljava/lang/Object;)Z
     312: pop
     313: aload         14
     315: lload         7
     317: invokestatic  #19                 // Method java/lang/Long.valueOf:(J)Ljava/lang/Long;
     320: aload         15
     322: invokeinterface #20,  3           // InterfaceMethod java/util/Map.put:(Ljava/lang/Object;Ljava/lang/Object;)Ljava/lang/Object;
     327: pop
     328: goto          17
     331: aload         4
     333: areturn

  static {};
    Code:
       0: ldc           #169                // class org/apache/activemq/artemis/core/server/impl/PostOfficeJournalLoader
       2: invokevirtual #170                // Method java/lang/Class.desiredAssertionStatus:()Z
       5: ifne          12
       8: iconst_1
       9: goto          13
      12: iconst_0
      13: putstatic     #127                // Field $assertionsDisabled:Z
      16: return
}
