Compiled from "ServerSessionImpl.java"
public class org.apache.activemq.artemis.core.server.impl.ServerSessionImpl implements org.apache.activemq.artemis.core.server.ServerSession,org.apache.activemq.artemis.core.remoting.FailureListener {
  private static final boolean isTrace;

  protected final java.lang.String username;

  protected final java.lang.String password;

  private final int minLargeMessageSize;

  protected boolean autoCommitSends;

  protected boolean autoCommitAcks;

  protected final boolean preAcknowledge;

  protected final boolean strictUpdateDeliveryCount;

  protected final org.apache.activemq.artemis.spi.core.protocol.RemotingConnection remotingConnection;

  protected final java.util.Map<java.lang.Long, org.apache.activemq.artemis.core.server.ServerConsumer> consumers;

  protected org.apache.activemq.artemis.core.transaction.Transaction tx;

  protected boolean xa;

  protected final org.apache.activemq.artemis.core.persistence.StorageManager storageManager;

  private final org.apache.activemq.artemis.core.transaction.ResourceManager resourceManager;

  public final org.apache.activemq.artemis.core.postoffice.PostOffice postOffice;

  private final org.apache.activemq.artemis.core.security.SecurityStore securityStore;

  protected final org.apache.activemq.artemis.core.server.management.ManagementService managementService;

  protected volatile boolean started;

  protected final java.util.Map<org.apache.activemq.artemis.api.core.SimpleString, org.apache.activemq.artemis.core.server.impl.ServerSessionImpl$TempQueueCleanerUpper> tempQueueCleannerUppers;

  protected final java.lang.String name;

  protected final org.apache.activemq.artemis.core.server.ActiveMQServer server;

  private final org.apache.activemq.artemis.api.core.SimpleString managementAddress;

  private volatile org.apache.activemq.artemis.core.server.LargeServerMessage currentLargeMessage;

  protected final org.apache.activemq.artemis.core.server.RoutingContext routingContext;

  protected final org.apache.activemq.artemis.spi.core.protocol.SessionCallback callback;

  private volatile org.apache.activemq.artemis.api.core.SimpleString defaultAddress;

  private volatile int timeoutSeconds;

  private java.util.Map<java.lang.String, java.lang.String> metaData;

  private final org.apache.activemq.artemis.core.persistence.OperationContext context;

  private org.apache.activemq.artemis.core.server.QueueCreator queueCreator;

  protected final java.util.Map<org.apache.activemq.artemis.api.core.SimpleString, org.apache.activemq.artemis.api.core.Pair<org.apache.activemq.artemis.utils.UUID, java.util.concurrent.atomic.AtomicLong>> targetAddressInfos;

  private final long creationTime;

  private volatile boolean closed;

  private final org.apache.activemq.artemis.core.transaction.TransactionFactory transactionFactory;

  public org.apache.activemq.artemis.core.server.impl.ServerSessionImpl(java.lang.String, java.lang.String, java.lang.String, int, boolean, boolean, boolean, boolean, boolean, org.apache.activemq.artemis.spi.core.protocol.RemotingConnection, org.apache.activemq.artemis.core.persistence.StorageManager, org.apache.activemq.artemis.core.postoffice.PostOffice, org.apache.activemq.artemis.core.transaction.ResourceManager, org.apache.activemq.artemis.core.security.SecurityStore, org.apache.activemq.artemis.core.server.management.ManagementService, org.apache.activemq.artemis.core.server.ActiveMQServer, org.apache.activemq.artemis.api.core.SimpleString, org.apache.activemq.artemis.api.core.SimpleString, org.apache.activemq.artemis.spi.core.protocol.SessionCallback, org.apache.activemq.artemis.core.persistence.OperationContext, org.apache.activemq.artemis.core.server.QueueCreator) throws java.lang.Exception;
    Code:
       0: aload_0
       1: aload_1
       2: aload_2
       3: aload_3
       4: iload         4
       6: iload         5
       8: iload         6
      10: iload         7
      12: iload         8
      14: iload         9
      16: aload         10
      18: aload         11
      20: aload         12
      22: aload         13
      24: aload         14
      26: aload         15
      28: aload         16
      30: aload         17
      32: aload         18
      34: aload         19
      36: aload         20
      38: aconst_null
      39: aload         21
      41: invokespecial #1                  // Method "<init>":(Ljava/lang/String;Ljava/lang/String;Ljava/lang/String;IZZZZZLorg/apache/activemq/artemis/spi/core/protocol/RemotingConnection;Lorg/apache/activemq/artemis/core/persistence/StorageManager;Lorg/apache/activemq/artemis/core/postoffice/PostOffice;Lorg/apache/activemq/artemis/core/transaction/ResourceManager;Lorg/apache/activemq/artemis/core/security/SecurityStore;Lorg/apache/activemq/artemis/core/server/management/ManagementService;Lorg/apache/activemq/artemis/core/server/ActiveMQServer;Lorg/apache/activemq/artemis/api/core/SimpleString;Lorg/apache/activemq/artemis/api/core/SimpleString;Lorg/apache/activemq/artemis/spi/core/protocol/SessionCallback;Lorg/apache/activemq/artemis/core/persistence/OperationContext;Lorg/apache/activemq/artemis/core/transaction/TransactionFactory;Lorg/apache/activemq/artemis/core/server/QueueCreator;)V
      44: return

  public org.apache.activemq.artemis.core.server.impl.ServerSessionImpl(java.lang.String, java.lang.String, java.lang.String, int, boolean, boolean, boolean, boolean, boolean, org.apache.activemq.artemis.spi.core.protocol.RemotingConnection, org.apache.activemq.artemis.core.persistence.StorageManager, org.apache.activemq.artemis.core.postoffice.PostOffice, org.apache.activemq.artemis.core.transaction.ResourceManager, org.apache.activemq.artemis.core.security.SecurityStore, org.apache.activemq.artemis.core.server.management.ManagementService, org.apache.activemq.artemis.core.server.ActiveMQServer, org.apache.activemq.artemis.api.core.SimpleString, org.apache.activemq.artemis.api.core.SimpleString, org.apache.activemq.artemis.spi.core.protocol.SessionCallback, org.apache.activemq.artemis.core.persistence.OperationContext, org.apache.activemq.artemis.core.transaction.TransactionFactory, org.apache.activemq.artemis.core.server.QueueCreator) throws java.lang.Exception;
    Code:
       0: aload_0
       1: invokespecial #2                  // Method java/lang/Object."<init>":()V
       4: aload_0
       5: new           #3                  // class java/util/concurrent/ConcurrentHashMap
       8: dup
       9: invokespecial #4                  // Method java/util/concurrent/ConcurrentHashMap."<init>":()V
      12: putfield      #5                  // Field consumers:Ljava/util/Map;
      15: aload_0
      16: iconst_0
      17: putfield      #6                  // Field started:Z
      20: aload_0
      21: new           #7                  // class java/util/HashMap
      24: dup
      25: invokespecial #8                  // Method java/util/HashMap."<init>":()V
      28: putfield      #9                  // Field tempQueueCleannerUppers:Ljava/util/Map;
      31: aload_0
      32: new           #10                 // class org/apache/activemq/artemis/core/server/impl/RoutingContextImpl
      35: dup
      36: aconst_null
      37: invokespecial #11                 // Method org/apache/activemq/artemis/core/server/impl/RoutingContextImpl."<init>":(Lorg/apache/activemq/artemis/core/transaction/Transaction;)V
      40: putfield      #12                 // Field routingContext:Lorg/apache/activemq/artemis/core/server/RoutingContext;
      43: aload_0
      44: new           #7                  // class java/util/HashMap
      47: dup
      48: invokespecial #8                  // Method java/util/HashMap."<init>":()V
      51: putfield      #13                 // Field targetAddressInfos:Ljava/util/Map;
      54: aload_0
      55: invokestatic  #14                 // Method java/lang/System.currentTimeMillis:()J
      58: putfield      #15                 // Field creationTime:J
      61: aload_0
      62: iconst_0
      63: putfield      #16                 // Field closed:Z
      66: aload_0
      67: aload_2
      68: putfield      #17                 // Field username:Ljava/lang/String;
      71: aload_0
      72: aload_3
      73: putfield      #18                 // Field password:Ljava/lang/String;
      76: aload_0
      77: iload         4
      79: putfield      #19                 // Field minLargeMessageSize:I
      82: aload_0
      83: iload         5
      85: putfield      #20                 // Field autoCommitSends:Z
      88: aload_0
      89: iload         6
      91: putfield      #21                 // Field autoCommitAcks:Z
      94: aload_0
      95: iload         7
      97: putfield      #22                 // Field preAcknowledge:Z
     100: aload_0
     101: aload         10
     103: putfield      #23                 // Field remotingConnection:Lorg/apache/activemq/artemis/spi/core/protocol/RemotingConnection;
     106: aload_0
     107: aload         11
     109: putfield      #24                 // Field storageManager:Lorg/apache/activemq/artemis/core/persistence/StorageManager;
     112: aload_0
     113: aload         12
     115: putfield      #25                 // Field postOffice:Lorg/apache/activemq/artemis/core/postoffice/PostOffice;
     118: aload_0
     119: aload         13
     121: putfield      #26                 // Field resourceManager:Lorg/apache/activemq/artemis/core/transaction/ResourceManager;
     124: aload_0
     125: aload         14
     127: putfield      #27                 // Field securityStore:Lorg/apache/activemq/artemis/core/security/SecurityStore;
     130: aload_0
     131: aload         13
     133: invokeinterface #28,  1           // InterfaceMethod org/apache/activemq/artemis/core/transaction/ResourceManager.getTimeoutSeconds:()I
     138: putfield      #29                 // Field timeoutSeconds:I
     141: aload_0
     142: iload         9
     144: putfield      #30                 // Field xa:Z
     147: aload_0
     148: iload         8
     150: putfield      #31                 // Field strictUpdateDeliveryCount:Z
     153: aload_0
     154: aload         15
     156: putfield      #32                 // Field managementService:Lorg/apache/activemq/artemis/core/server/management/ManagementService;
     159: aload_0
     160: aload_1
     161: putfield      #33                 // Field name:Ljava/lang/String;
     164: aload_0
     165: aload         16
     167: putfield      #34                 // Field server:Lorg/apache/activemq/artemis/core/server/ActiveMQServer;
     170: aload_0
     171: aload         17
     173: putfield      #35                 // Field managementAddress:Lorg/apache/activemq/artemis/api/core/SimpleString;
     176: aload_0
     177: aload         19
     179: putfield      #36                 // Field callback:Lorg/apache/activemq/artemis/spi/core/protocol/SessionCallback;
     182: aload_0
     183: aload         18
     185: putfield      #37                 // Field defaultAddress:Lorg/apache/activemq/artemis/api/core/SimpleString;
     188: aload         10
     190: aload_0
     191: invokeinterface #38,  2           // InterfaceMethod org/apache/activemq/artemis/spi/core/protocol/RemotingConnection.addFailureListener:(Lorg/apache/activemq/artemis/core/remoting/FailureListener;)V
     196: aload_0
     197: aload         20
     199: putfield      #39                 // Field context:Lorg/apache/activemq/artemis/core/persistence/OperationContext;
     202: aload_0
     203: aload         22
     205: putfield      #40                 // Field queueCreator:Lorg/apache/activemq/artemis/core/server/QueueCreator;
     208: aload         21
     210: ifnonnull     228
     213: aload_0
     214: new           #41                 // class org/apache/activemq/artemis/core/server/impl/ServerSessionImpl$DefaultTransactionFactory
     217: dup
     218: aconst_null
     219: invokespecial #42                 // Method org/apache/activemq/artemis/core/server/impl/ServerSessionImpl$DefaultTransactionFactory."<init>":(Lorg/apache/activemq/artemis/core/server/impl/ServerSessionImpl$1;)V
     222: putfield      #43                 // Field transactionFactory:Lorg/apache/activemq/artemis/core/transaction/TransactionFactory;
     225: goto          234
     228: aload_0
     229: aload         21
     231: putfield      #43                 // Field transactionFactory:Lorg/apache/activemq/artemis/core/transaction/TransactionFactory;
     234: iload         9
     236: ifne          247
     239: aload_0
     240: aload_0
     241: invokevirtual #44                 // Method newTransaction:()Lorg/apache/activemq/artemis/core/transaction/Transaction;
     244: putfield      #45                 // Field tx:Lorg/apache/activemq/artemis/core/transaction/Transaction;
     247: return

  public org.apache.activemq.artemis.core.persistence.OperationContext getSessionContext();
    Code:
       0: aload_0
       1: getfield      #39                 // Field context:Lorg/apache/activemq/artemis/core/persistence/OperationContext;
       4: areturn

  public java.lang.String getUsername();
    Code:
       0: aload_0
       1: getfield      #17                 // Field username:Ljava/lang/String;
       4: areturn

  public java.lang.String getPassword();
    Code:
       0: aload_0
       1: getfield      #18                 // Field password:Ljava/lang/String;
       4: areturn

  public int getMinLargeMessageSize();
    Code:
       0: aload_0
       1: getfield      #19                 // Field minLargeMessageSize:I
       4: ireturn

  public java.lang.String getName();
    Code:
       0: aload_0
       1: getfield      #33                 // Field name:Ljava/lang/String;
       4: areturn

  public java.lang.Object getConnectionID();
    Code:
       0: aload_0
       1: getfield      #23                 // Field remotingConnection:Lorg/apache/activemq/artemis/spi/core/protocol/RemotingConnection;
       4: invokeinterface #46,  1           // InterfaceMethod org/apache/activemq/artemis/spi/core/protocol/RemotingConnection.getID:()Ljava/lang/Object;
       9: areturn

  public java.util.Set<org.apache.activemq.artemis.core.server.ServerConsumer> getServerConsumers();
    Code:
       0: new           #47                 // class java/util/HashSet
       3: dup
       4: aload_0
       5: getfield      #5                  // Field consumers:Ljava/util/Map;
       8: invokeinterface #48,  1           // InterfaceMethod java/util/Map.values:()Ljava/util/Collection;
      13: invokespecial #49                 // Method java/util/HashSet."<init>":(Ljava/util/Collection;)V
      16: astore_1
      17: aload_1
      18: invokestatic  #50                 // Method java/util/Collections.unmodifiableSet:(Ljava/util/Set;)Ljava/util/Set;
      21: areturn

  public void markTXFailed(java.lang.Throwable);
    Code:
       0: aload_0
       1: getfield      #45                 // Field tx:Lorg/apache/activemq/artemis/core/transaction/Transaction;
       4: astore_2
       5: aload_2
       6: ifnull        54
       9: aload_1
      10: instanceof    #51                 // class org/apache/activemq/artemis/api/core/ActiveMQException
      13: ifeq          29
      16: aload_2
      17: aload_1
      18: checkcast     #51                 // class org/apache/activemq/artemis/api/core/ActiveMQException
      21: invokeinterface #52,  2           // InterfaceMethod org/apache/activemq/artemis/core/transaction/Transaction.markAsRollbackOnly:(Lorg/apache/activemq/artemis/api/core/ActiveMQException;)V
      26: goto          54
      29: new           #51                 // class org/apache/activemq/artemis/api/core/ActiveMQException
      32: dup
      33: aload_1
      34: invokevirtual #53                 // Method java/lang/Throwable.getMessage:()Ljava/lang/String;
      37: invokespecial #54                 // Method org/apache/activemq/artemis/api/core/ActiveMQException."<init>":(Ljava/lang/String;)V
      40: astore_3
      41: aload_3
      42: aload_1
      43: invokevirtual #55                 // Method org/apache/activemq/artemis/api/core/ActiveMQException.initCause:(Ljava/lang/Throwable;)Ljava/lang/Throwable;
      46: pop
      47: aload_2
      48: aload_3
      49: invokeinterface #52,  2           // InterfaceMethod org/apache/activemq/artemis/core/transaction/Transaction.markAsRollbackOnly:(Lorg/apache/activemq/artemis/api/core/ActiveMQException;)V
      54: return

  public boolean removeConsumer(long) throws java.lang.Exception;
    Code:
       0: aload_0
       1: getfield      #5                  // Field consumers:Ljava/util/Map;
       4: lload_1
       5: invokestatic  #56                 // Method java/lang/Long.valueOf:(J)Ljava/lang/Long;
       8: invokeinterface #57,  2           // InterfaceMethod java/util/Map.remove:(Ljava/lang/Object;)Ljava/lang/Object;
      13: ifnull        20
      16: iconst_1
      17: goto          21
      20: iconst_0
      21: ireturn

  protected void doClose(boolean) throws java.lang.Exception;
    Code:
       0: aload_0
       1: dup
       2: astore_2
       3: monitorenter
       4: aload_0
       5: getfield      #16                 // Field closed:Z
       8: ifeq          14
      11: aload_2
      12: monitorexit
      13: return
      14: aload_0
      15: getfield      #45                 // Field tx:Lorg/apache/activemq/artemis/core/transaction/Transaction;
      18: ifnull        56
      21: aload_0
      22: getfield      #45                 // Field tx:Lorg/apache/activemq/artemis/core/transaction/Transaction;
      25: invokeinterface #58,  1           // InterfaceMethod org/apache/activemq/artemis/core/transaction/Transaction.getXid:()Ljavax/transaction/xa/Xid;
      30: ifnonnull     56
      33: aload_0
      34: iload_1
      35: iconst_0
      36: invokespecial #59                 // Method rollback:(ZZ)V
      39: goto          56
      42: astore_3
      43: getstatic     #61                 // Field org/apache/activemq/artemis/core/server/ActiveMQServerLogger.LOGGER:Lorg/apache/activemq/artemis/core/server/ActiveMQServerLogger;
      46: aload_3
      47: invokevirtual #62                 // Method java/lang/Exception.getMessage:()Ljava/lang/String;
      50: aload_3
      51: invokeinterface #63,  3           // InterfaceMethod org/apache/activemq/artemis/core/server/ActiveMQServerLogger.warn:(Ljava/lang/Object;Ljava/lang/Throwable;)V
      56: aload_2
      57: monitorexit
      58: goto          68
      61: astore        4
      63: aload_2
      64: monitorexit
      65: aload         4
      67: athrow
      68: new           #47                 // class java/util/HashSet
      71: dup
      72: aload_0
      73: getfield      #5                  // Field consumers:Ljava/util/Map;
      76: invokeinterface #48,  1           // InterfaceMethod java/util/Map.values:()Ljava/util/Collection;
      81: invokespecial #49                 // Method java/util/HashSet."<init>":(Ljava/util/Collection;)V
      84: astore_2
      85: aload_2
      86: invokeinterface #64,  1           // InterfaceMethod java/util/Set.iterator:()Ljava/util/Iterator;
      91: astore_3
      92: aload_3
      93: invokeinterface #65,  1           // InterfaceMethod java/util/Iterator.hasNext:()Z
      98: ifeq          170
     101: aload_3
     102: invokeinterface #66,  1           // InterfaceMethod java/util/Iterator.next:()Ljava/lang/Object;
     107: checkcast     #67                 // class org/apache/activemq/artemis/core/server/ServerConsumer
     110: astore        4
     112: aload         4
     114: iload_1
     115: invokeinterface #68,  2           // InterfaceMethod org/apache/activemq/artemis/core/server/ServerConsumer.close:(Z)V
     120: goto          167
     123: astore        5
     125: getstatic     #61                 // Field org/apache/activemq/artemis/core/server/ActiveMQServerLogger.LOGGER:Lorg/apache/activemq/artemis/core/server/ActiveMQServerLogger;
     128: aload         5
     130: invokevirtual #53                 // Method java/lang/Throwable.getMessage:()Ljava/lang/String;
     133: aload         5
     135: invokeinterface #63,  3           // InterfaceMethod org/apache/activemq/artemis/core/server/ActiveMQServerLogger.warn:(Ljava/lang/Object;Ljava/lang/Throwable;)V
     140: aload         4
     142: invokeinterface #70,  1           // InterfaceMethod org/apache/activemq/artemis/core/server/ServerConsumer.removeItself:()V
     147: goto          167
     150: astore        6
     152: getstatic     #61                 // Field org/apache/activemq/artemis/core/server/ActiveMQServerLogger.LOGGER:Lorg/apache/activemq/artemis/core/server/ActiveMQServerLogger;
     155: aload         6
     157: invokevirtual #53                 // Method java/lang/Throwable.getMessage:()Ljava/lang/String;
     160: aload         6
     162: invokeinterface #63,  3           // InterfaceMethod org/apache/activemq/artemis/core/server/ActiveMQServerLogger.warn:(Ljava/lang/Object;Ljava/lang/Throwable;)V
     167: goto          92
     170: aload_0
     171: getfield      #5                  // Field consumers:Ljava/util/Map;
     174: invokeinterface #71,  1           // InterfaceMethod java/util/Map.clear:()V
     179: aload_0
     180: getfield      #72                 // Field currentLargeMessage:Lorg/apache/activemq/artemis/core/server/LargeServerMessage;
     183: ifnull        208
     186: aload_0
     187: getfield      #72                 // Field currentLargeMessage:Lorg/apache/activemq/artemis/core/server/LargeServerMessage;
     190: invokeinterface #73,  1           // InterfaceMethod org/apache/activemq/artemis/core/server/LargeServerMessage.deleteFile:()V
     195: goto          208
     198: astore_3
     199: getstatic     #61                 // Field org/apache/activemq/artemis/core/server/ActiveMQServerLogger.LOGGER:Lorg/apache/activemq/artemis/core/server/ActiveMQServerLogger;
     202: aload_3
     203: invokeinterface #74,  2           // InterfaceMethod org/apache/activemq/artemis/core/server/ActiveMQServerLogger.errorDeletingLargeMessageFile:(Ljava/lang/Throwable;)V
     208: aload_0
     209: dup
     210: astore_3
     211: monitorenter
     212: aload_0
     213: getfield      #34                 // Field server:Lorg/apache/activemq/artemis/core/server/ActiveMQServer;
     216: aload_0
     217: getfield      #33                 // Field name:Ljava/lang/String;
     220: invokeinterface #75,  2           // InterfaceMethod org/apache/activemq/artemis/core/server/ActiveMQServer.removeSession:(Ljava/lang/String;)V
     225: aload_0
     226: getfield      #23                 // Field remotingConnection:Lorg/apache/activemq/artemis/spi/core/protocol/RemotingConnection;
     229: aload_0
     230: invokeinterface #76,  2           // InterfaceMethod org/apache/activemq/artemis/spi/core/protocol/RemotingConnection.removeFailureListener:(Lorg/apache/activemq/artemis/core/remoting/FailureListener;)Z
     235: pop
     236: aload_0
     237: getfield      #36                 // Field callback:Lorg/apache/activemq/artemis/spi/core/protocol/SessionCallback;
     240: invokeinterface #77,  1           // InterfaceMethod org/apache/activemq/artemis/spi/core/protocol/SessionCallback.closed:()V
     245: aload_0
     246: iconst_1
     247: putfield      #16                 // Field closed:Z
     250: aload_3
     251: monitorexit
     252: goto          262
     255: astore        7
     257: aload_3
     258: monitorexit
     259: aload         7
     261: athrow
     262: return
    Exception table:
       from    to  target type
          33    39    42   Class java/lang/Exception
           4    13    61   any
          14    58    61   any
          61    65    61   any
         112   120   123   Class java/lang/Throwable
         140   147   150   Class java/lang/Throwable
         186   195   198   Class java/lang/Throwable
         212   252   255   any
         255   259   255   any

  public org.apache.activemq.artemis.core.server.QueueCreator getQueueCreator();
    Code:
       0: aload_0
       1: getfield      #40                 // Field queueCreator:Lorg/apache/activemq/artemis/core/server/QueueCreator;
       4: areturn

  public org.apache.activemq.artemis.core.server.ServerConsumer createConsumer(long, org.apache.activemq.artemis.api.core.SimpleString, org.apache.activemq.artemis.api.core.SimpleString, boolean) throws java.lang.Exception;
    Code:
       0: aload_0
       1: lload_1
       2: aload_3
       3: aload         4
       5: iload         5
       7: iconst_1
       8: aconst_null
       9: invokevirtual #78                 // Method createConsumer:(JLorg/apache/activemq/artemis/api/core/SimpleString;Lorg/apache/activemq/artemis/api/core/SimpleString;ZZLjava/lang/Integer;)Lorg/apache/activemq/artemis/core/server/ServerConsumer;
      12: areturn

  public org.apache.activemq.artemis.core.server.ServerConsumer createConsumer(long, org.apache.activemq.artemis.api.core.SimpleString, org.apache.activemq.artemis.api.core.SimpleString, boolean, boolean, java.lang.Integer) throws java.lang.Exception;
    Code:
       0: aload_0
       1: getfield      #25                 // Field postOffice:Lorg/apache/activemq/artemis/core/postoffice/PostOffice;
       4: aload_3
       5: invokeinterface #79,  2           // InterfaceMethod org/apache/activemq/artemis/core/postoffice/PostOffice.getBinding:(Lorg/apache/activemq/artemis/api/core/SimpleString;)Lorg/apache/activemq/artemis/core/postoffice/Binding;
      10: astore        8
      12: aload         8
      14: ifnull        30
      17: aload         8
      19: invokeinterface #80,  1           // InterfaceMethod org/apache/activemq/artemis/core/postoffice/Binding.getType:()Lorg/apache/activemq/artemis/core/postoffice/BindingType;
      24: getstatic     #81                 // Field org/apache/activemq/artemis/core/postoffice/BindingType.LOCAL_QUEUE:Lorg/apache/activemq/artemis/core/postoffice/BindingType;
      27: if_acmpeq     40
      30: getstatic     #82                 // Field org/apache/activemq/artemis/core/server/ActiveMQMessageBundle.BUNDLE:Lorg/apache/activemq/artemis/core/server/ActiveMQMessageBundle;
      33: aload_3
      34: invokeinterface #83,  2           // InterfaceMethod org/apache/activemq/artemis/core/server/ActiveMQMessageBundle.noSuchQueue:(Lorg/apache/activemq/artemis/api/core/SimpleString;)Lorg/apache/activemq/artemis/api/core/ActiveMQNonExistentQueueException;
      39: athrow
      40: aload_0
      41: getfield      #27                 // Field securityStore:Lorg/apache/activemq/artemis/core/security/SecurityStore;
      44: aload         8
      46: invokeinterface #84,  1           // InterfaceMethod org/apache/activemq/artemis/core/postoffice/Binding.getAddress:()Lorg/apache/activemq/artemis/api/core/SimpleString;
      51: getstatic     #85                 // Field org/apache/activemq/artemis/core/security/CheckType.CONSUME:Lorg/apache/activemq/artemis/core/security/CheckType;
      54: aload_0
      55: invokeinterface #86,  4           // InterfaceMethod org/apache/activemq/artemis/core/security/SecurityStore.check:(Lorg/apache/activemq/artemis/api/core/SimpleString;Lorg/apache/activemq/artemis/core/security/CheckType;Lorg/apache/activemq/artemis/core/security/SecurityAuth;)V
      60: aload         4
      62: invokestatic  #87                 // Method org/apache/activemq/artemis/core/filter/impl/FilterImpl.createFilter:(Lorg/apache/activemq/artemis/api/core/SimpleString;)Lorg/apache/activemq/artemis/core/filter/Filter;
      65: astore        9
      67: aload_0
      68: lload_1
      69: aload_0
      70: aload         8
      72: checkcast     #88                 // class org/apache/activemq/artemis/core/postoffice/QueueBinding
      75: aload         9
      77: aload_0
      78: getfield      #6                  // Field started:Z
      81: iload         5
      83: aload_0
      84: getfield      #24                 // Field storageManager:Lorg/apache/activemq/artemis/core/persistence/StorageManager;
      87: aload_0
      88: getfield      #36                 // Field callback:Lorg/apache/activemq/artemis/spi/core/protocol/SessionCallback;
      91: aload_0
      92: getfield      #22                 // Field preAcknowledge:Z
      95: aload_0
      96: getfield      #31                 // Field strictUpdateDeliveryCount:Z
      99: aload_0
     100: getfield      #32                 // Field managementService:Lorg/apache/activemq/artemis/core/server/management/ManagementService;
     103: iload         6
     105: aload         7
     107: invokevirtual #89                 // Method newConsumer:(JLorg/apache/activemq/artemis/core/server/impl/ServerSessionImpl;Lorg/apache/activemq/artemis/core/postoffice/QueueBinding;Lorg/apache/activemq/artemis/core/filter/Filter;ZZLorg/apache/activemq/artemis/core/persistence/StorageManager;Lorg/apache/activemq/artemis/spi/core/protocol/SessionCallback;ZZLorg/apache/activemq/artemis/core/server/management/ManagementService;ZLjava/lang/Integer;)Lorg/apache/activemq/artemis/core/server/ServerConsumer;
     110: astore        10
     112: aload_0
     113: getfield      #5                  // Field consumers:Ljava/util/Map;
     116: aload         10
     118: invokeinterface #90,  1           // InterfaceMethod org/apache/activemq/artemis/core/server/ServerConsumer.getID:()J
     123: invokestatic  #56                 // Method java/lang/Long.valueOf:(J)Ljava/lang/Long;
     126: aload         10
     128: invokeinterface #91,  3           // InterfaceMethod java/util/Map.put:(Ljava/lang/Object;Ljava/lang/Object;)Ljava/lang/Object;
     133: pop
     134: iload         5
     136: ifne          398
     139: new           #92                 // class org/apache/activemq/artemis/utils/TypedProperties
     142: dup
     143: invokespecial #93                 // Method org/apache/activemq/artemis/utils/TypedProperties."<init>":()V
     146: astore        11
     148: aload         11
     150: getstatic     #94                 // Field org/apache/activemq/artemis/api/core/management/ManagementHelper.HDR_ADDRESS:Lorg/apache/activemq/artemis/api/core/SimpleString;
     153: aload         8
     155: invokeinterface #84,  1           // InterfaceMethod org/apache/activemq/artemis/core/postoffice/Binding.getAddress:()Lorg/apache/activemq/artemis/api/core/SimpleString;
     160: invokevirtual #95                 // Method org/apache/activemq/artemis/utils/TypedProperties.putSimpleStringProperty:(Lorg/apache/activemq/artemis/api/core/SimpleString;Lorg/apache/activemq/artemis/api/core/SimpleString;)V
     163: aload         11
     165: getstatic     #96                 // Field org/apache/activemq/artemis/api/core/management/ManagementHelper.HDR_CLUSTER_NAME:Lorg/apache/activemq/artemis/api/core/SimpleString;
     168: aload         8
     170: invokeinterface #97,  1           // InterfaceMethod org/apache/activemq/artemis/core/postoffice/Binding.getClusterName:()Lorg/apache/activemq/artemis/api/core/SimpleString;
     175: invokevirtual #95                 // Method org/apache/activemq/artemis/utils/TypedProperties.putSimpleStringProperty:(Lorg/apache/activemq/artemis/api/core/SimpleString;Lorg/apache/activemq/artemis/api/core/SimpleString;)V
     178: aload         11
     180: getstatic     #98                 // Field org/apache/activemq/artemis/api/core/management/ManagementHelper.HDR_ROUTING_NAME:Lorg/apache/activemq/artemis/api/core/SimpleString;
     183: aload         8
     185: invokeinterface #99,  1           // InterfaceMethod org/apache/activemq/artemis/core/postoffice/Binding.getRoutingName:()Lorg/apache/activemq/artemis/api/core/SimpleString;
     190: invokevirtual #95                 // Method org/apache/activemq/artemis/utils/TypedProperties.putSimpleStringProperty:(Lorg/apache/activemq/artemis/api/core/SimpleString;Lorg/apache/activemq/artemis/api/core/SimpleString;)V
     193: aload         11
     195: getstatic     #100                // Field org/apache/activemq/artemis/api/core/management/ManagementHelper.HDR_DISTANCE:Lorg/apache/activemq/artemis/api/core/SimpleString;
     198: aload         8
     200: invokeinterface #101,  1          // InterfaceMethod org/apache/activemq/artemis/core/postoffice/Binding.getDistance:()I
     205: invokevirtual #102                // Method org/apache/activemq/artemis/utils/TypedProperties.putIntProperty:(Lorg/apache/activemq/artemis/api/core/SimpleString;I)V
     208: aload         8
     210: invokeinterface #103,  1          // InterfaceMethod org/apache/activemq/artemis/core/postoffice/Binding.getBindable:()Lorg/apache/activemq/artemis/core/server/Bindable;
     215: checkcast     #104                // class org/apache/activemq/artemis/core/server/Queue
     218: astore        12
     220: aload         11
     222: getstatic     #105                // Field org/apache/activemq/artemis/api/core/management/ManagementHelper.HDR_CONSUMER_COUNT:Lorg/apache/activemq/artemis/api/core/SimpleString;
     225: aload         12
     227: invokeinterface #106,  1          // InterfaceMethod org/apache/activemq/artemis/core/server/Queue.getConsumerCount:()I
     232: invokevirtual #102                // Method org/apache/activemq/artemis/utils/TypedProperties.putIntProperty:(Lorg/apache/activemq/artemis/api/core/SimpleString;I)V
     235: aload         11
     237: getstatic     #107                // Field org/apache/activemq/artemis/api/core/management/ManagementHelper.HDR_USER:Lorg/apache/activemq/artemis/api/core/SimpleString;
     240: aload_0
     241: getfield      #17                 // Field username:Ljava/lang/String;
     244: invokestatic  #108                // Method org/apache/activemq/artemis/api/core/SimpleString.toSimpleString:(Ljava/lang/String;)Lorg/apache/activemq/artemis/api/core/SimpleString;
     247: invokevirtual #95                 // Method org/apache/activemq/artemis/utils/TypedProperties.putSimpleStringProperty:(Lorg/apache/activemq/artemis/api/core/SimpleString;Lorg/apache/activemq/artemis/api/core/SimpleString;)V
     250: aload         11
     252: getstatic     #109                // Field org/apache/activemq/artemis/api/core/management/ManagementHelper.HDR_REMOTE_ADDRESS:Lorg/apache/activemq/artemis/api/core/SimpleString;
     255: aload_0
     256: getfield      #23                 // Field remotingConnection:Lorg/apache/activemq/artemis/spi/core/protocol/RemotingConnection;
     259: invokeinterface #110,  1          // InterfaceMethod org/apache/activemq/artemis/spi/core/protocol/RemotingConnection.getRemoteAddress:()Ljava/lang/String;
     264: invokestatic  #108                // Method org/apache/activemq/artemis/api/core/SimpleString.toSimpleString:(Ljava/lang/String;)Lorg/apache/activemq/artemis/api/core/SimpleString;
     267: invokevirtual #95                 // Method org/apache/activemq/artemis/utils/TypedProperties.putSimpleStringProperty:(Lorg/apache/activemq/artemis/api/core/SimpleString;Lorg/apache/activemq/artemis/api/core/SimpleString;)V
     270: aload         11
     272: getstatic     #111                // Field org/apache/activemq/artemis/api/core/management/ManagementHelper.HDR_SESSION_NAME:Lorg/apache/activemq/artemis/api/core/SimpleString;
     275: aload_0
     276: getfield      #33                 // Field name:Ljava/lang/String;
     279: invokestatic  #108                // Method org/apache/activemq/artemis/api/core/SimpleString.toSimpleString:(Ljava/lang/String;)Lorg/apache/activemq/artemis/api/core/SimpleString;
     282: invokevirtual #95                 // Method org/apache/activemq/artemis/utils/TypedProperties.putSimpleStringProperty:(Lorg/apache/activemq/artemis/api/core/SimpleString;Lorg/apache/activemq/artemis/api/core/SimpleString;)V
     285: aload         4
     287: ifnull        300
     290: aload         11
     292: getstatic     #112                // Field org/apache/activemq/artemis/api/core/management/ManagementHelper.HDR_FILTERSTRING:Lorg/apache/activemq/artemis/api/core/SimpleString;
     295: aload         4
     297: invokevirtual #95                 // Method org/apache/activemq/artemis/utils/TypedProperties.putSimpleStringProperty:(Lorg/apache/activemq/artemis/api/core/SimpleString;Lorg/apache/activemq/artemis/api/core/SimpleString;)V
     300: new           #113                // class org/apache/activemq/artemis/core/server/management/Notification
     303: dup
     304: aconst_null
     305: getstatic     #114                // Field org/apache/activemq/artemis/api/core/management/CoreNotificationType.CONSUMER_CREATED:Lorg/apache/activemq/artemis/api/core/management/CoreNotificationType;
     308: aload         11
     310: invokespecial #115                // Method org/apache/activemq/artemis/core/server/management/Notification."<init>":(Ljava/lang/String;Lorg/apache/activemq/artemis/api/core/management/NotificationType;Lorg/apache/activemq/artemis/utils/TypedProperties;)V
     313: astore        13
     315: getstatic     #61                 // Field org/apache/activemq/artemis/core/server/ActiveMQServerLogger.LOGGER:Lorg/apache/activemq/artemis/core/server/ActiveMQServerLogger;
     318: invokeinterface #116,  1          // InterfaceMethod org/apache/activemq/artemis/core/server/ActiveMQServerLogger.isDebugEnabled:()Z
     323: ifeq          387
     326: getstatic     #61                 // Field org/apache/activemq/artemis/core/server/ActiveMQServerLogger.LOGGER:Lorg/apache/activemq/artemis/core/server/ActiveMQServerLogger;
     329: new           #117                // class java/lang/StringBuilder
     332: dup
     333: invokespecial #118                // Method java/lang/StringBuilder."<init>":()V
     336: ldc           #119                // String Session with user=
     338: invokevirtual #120                // Method java/lang/StringBuilder.append:(Ljava/lang/String;)Ljava/lang/StringBuilder;
     341: aload_0
     342: getfield      #17                 // Field username:Ljava/lang/String;
     345: invokevirtual #120                // Method java/lang/StringBuilder.append:(Ljava/lang/String;)Ljava/lang/StringBuilder;
     348: ldc           #121                // String , connection=
     350: invokevirtual #120                // Method java/lang/StringBuilder.append:(Ljava/lang/String;)Ljava/lang/StringBuilder;
     353: aload_0
     354: getfield      #23                 // Field remotingConnection:Lorg/apache/activemq/artemis/spi/core/protocol/RemotingConnection;
     357: invokevirtual #122                // Method java/lang/StringBuilder.append:(Ljava/lang/Object;)Ljava/lang/StringBuilder;
     360: ldc           #123                // String  created a consumer on queue
     362: invokevirtual #120                // Method java/lang/StringBuilder.append:(Ljava/lang/String;)Ljava/lang/StringBuilder;
     365: aload_3
     366: invokevirtual #122                // Method java/lang/StringBuilder.append:(Ljava/lang/Object;)Ljava/lang/StringBuilder;
     369: ldc           #124                // String , filter =
     371: invokevirtual #120                // Method java/lang/StringBuilder.append:(Ljava/lang/String;)Ljava/lang/StringBuilder;
     374: aload         4
     376: invokevirtual #122                // Method java/lang/StringBuilder.append:(Ljava/lang/Object;)Ljava/lang/StringBuilder;
     379: invokevirtual #125                // Method java/lang/StringBuilder.toString:()Ljava/lang/String;
     382: invokeinterface #126,  2          // InterfaceMethod org/apache/activemq/artemis/core/server/ActiveMQServerLogger.debug:(Ljava/lang/Object;)V
     387: aload_0
     388: getfield      #32                 // Field managementService:Lorg/apache/activemq/artemis/core/server/management/ManagementService;
     391: aload         13
     393: invokeinterface #127,  2          // InterfaceMethod org/apache/activemq/artemis/core/server/management/ManagementService.sendNotification:(Lorg/apache/activemq/artemis/core/server/management/Notification;)V
     398: aload         10
     400: areturn

  protected org.apache.activemq.artemis.core.server.ServerConsumer newConsumer(long, org.apache.activemq.artemis.core.server.impl.ServerSessionImpl, org.apache.activemq.artemis.core.postoffice.QueueBinding, org.apache.activemq.artemis.core.filter.Filter, boolean, boolean, org.apache.activemq.artemis.core.persistence.StorageManager, org.apache.activemq.artemis.spi.core.protocol.SessionCallback, boolean, boolean, org.apache.activemq.artemis.core.server.management.ManagementService, boolean, java.lang.Integer) throws java.lang.Exception;
    Code:
       0: new           #128                // class org/apache/activemq/artemis/core/server/impl/ServerConsumerImpl
       3: dup
       4: lload_1
       5: aload_0
       6: aload         4
       8: aload         5
      10: aload_0
      11: getfield      #6                  // Field started:Z
      14: iload         7
      16: aload_0
      17: getfield      #24                 // Field storageManager:Lorg/apache/activemq/artemis/core/persistence/StorageManager;
      20: aload_0
      21: getfield      #36                 // Field callback:Lorg/apache/activemq/artemis/spi/core/protocol/SessionCallback;
      24: aload_0
      25: getfield      #22                 // Field preAcknowledge:Z
      28: aload_0
      29: getfield      #31                 // Field strictUpdateDeliveryCount:Z
      32: aload_0
      33: getfield      #32                 // Field managementService:Lorg/apache/activemq/artemis/core/server/management/ManagementService;
      36: iload         13
      38: aload         14
      40: invokespecial #129                // Method org/apache/activemq/artemis/core/server/impl/ServerConsumerImpl."<init>":(JLorg/apache/activemq/artemis/core/server/ServerSession;Lorg/apache/activemq/artemis/core/postoffice/QueueBinding;Lorg/apache/activemq/artemis/core/filter/Filter;ZZLorg/apache/activemq/artemis/core/persistence/StorageManager;Lorg/apache/activemq/artemis/spi/core/protocol/SessionCallback;ZZLorg/apache/activemq/artemis/core/server/management/ManagementService;ZLjava/lang/Integer;)V
      43: areturn

  public org.apache.activemq.artemis.core.server.Queue createQueue(org.apache.activemq.artemis.api.core.SimpleString, org.apache.activemq.artemis.api.core.SimpleString, org.apache.activemq.artemis.api.core.SimpleString, boolean, boolean) throws java.lang.Exception;
    Code:
       0: iload         5
       2: ifeq          22
       5: aload_0
       6: getfield      #27                 // Field securityStore:Lorg/apache/activemq/artemis/core/security/SecurityStore;
       9: aload_1
      10: getstatic     #130                // Field org/apache/activemq/artemis/core/security/CheckType.CREATE_DURABLE_QUEUE:Lorg/apache/activemq/artemis/core/security/CheckType;
      13: aload_0
      14: invokeinterface #86,  4           // InterfaceMethod org/apache/activemq/artemis/core/security/SecurityStore.check:(Lorg/apache/activemq/artemis/api/core/SimpleString;Lorg/apache/activemq/artemis/core/security/CheckType;Lorg/apache/activemq/artemis/core/security/SecurityAuth;)V
      19: goto          36
      22: aload_0
      23: getfield      #27                 // Field securityStore:Lorg/apache/activemq/artemis/core/security/SecurityStore;
      26: aload_1
      27: getstatic     #131                // Field org/apache/activemq/artemis/core/security/CheckType.CREATE_NON_DURABLE_QUEUE:Lorg/apache/activemq/artemis/core/security/CheckType;
      30: aload_0
      31: invokeinterface #86,  4           // InterfaceMethod org/apache/activemq/artemis/core/security/SecurityStore.check:(Lorg/apache/activemq/artemis/api/core/SimpleString;Lorg/apache/activemq/artemis/core/security/CheckType;Lorg/apache/activemq/artemis/core/security/SecurityAuth;)V
      36: aload_0
      37: getfield      #34                 // Field server:Lorg/apache/activemq/artemis/core/server/ActiveMQServer;
      40: aload_0
      41: invokevirtual #132                // Method getUsername:()Ljava/lang/String;
      44: invokeinterface #133,  2          // InterfaceMethod org/apache/activemq/artemis/core/server/ActiveMQServer.checkQueueCreationLimit:(Ljava/lang/String;)V
      49: iload         4
      51: ifne          103
      54: aload_1
      55: invokevirtual #134                // Method org/apache/activemq/artemis/api/core/SimpleString.toString:()Ljava/lang/String;
      58: ldc           #136                // String jms.queue.
      60: invokevirtual #137                // Method java/lang/String.startsWith:(Ljava/lang/String;)Z
      63: ifeq          103
      66: aload_1
      67: aload_2
      68: invokevirtual #138                // Method org/apache/activemq/artemis/api/core/SimpleString.equals:(Ljava/lang/Object;)Z
      71: ifeq          103
      74: aload_0
      75: getfield      #34                 // Field server:Lorg/apache/activemq/artemis/core/server/ActiveMQServer;
      78: aload_1
      79: aload_2
      80: aload_3
      81: aload_0
      82: invokevirtual #132                // Method getUsername:()Ljava/lang/String;
      85: invokestatic  #108                // Method org/apache/activemq/artemis/api/core/SimpleString.toSimpleString:(Ljava/lang/String;)Lorg/apache/activemq/artemis/api/core/SimpleString;
      88: iload         5
      90: iload         4
      92: iconst_1
      93: invokeinterface #139,  8          // InterfaceMethod org/apache/activemq/artemis/core/server/ActiveMQServer.createQueue:(Lorg/apache/activemq/artemis/api/core/SimpleString;Lorg/apache/activemq/artemis/api/core/SimpleString;Lorg/apache/activemq/artemis/api/core/SimpleString;Lorg/apache/activemq/artemis/api/core/SimpleString;ZZZ)Lorg/apache/activemq/artemis/core/server/Queue;
      98: astore        6
     100: goto          128
     103: aload_0
     104: getfield      #34                 // Field server:Lorg/apache/activemq/artemis/core/server/ActiveMQServer;
     107: aload_1
     108: aload_2
     109: aload_3
     110: aload_0
     111: invokevirtual #132                // Method getUsername:()Ljava/lang/String;
     114: invokestatic  #108                // Method org/apache/activemq/artemis/api/core/SimpleString.toSimpleString:(Ljava/lang/String;)Lorg/apache/activemq/artemis/api/core/SimpleString;
     117: iload         5
     119: iload         4
     121: invokeinterface #140,  7          // InterfaceMethod org/apache/activemq/artemis/core/server/ActiveMQServer.createQueue:(Lorg/apache/activemq/artemis/api/core/SimpleString;Lorg/apache/activemq/artemis/api/core/SimpleString;Lorg/apache/activemq/artemis/api/core/SimpleString;Lorg/apache/activemq/artemis/api/core/SimpleString;ZZ)Lorg/apache/activemq/artemis/core/server/Queue;
     126: astore        6
     128: iload         4
     130: ifeq          182
     133: new           #141                // class org/apache/activemq/artemis/core/server/impl/ServerSessionImpl$TempQueueCleanerUpper
     136: dup
     137: aload_0
     138: getfield      #34                 // Field server:Lorg/apache/activemq/artemis/core/server/ActiveMQServer;
     141: aload_2
     142: invokespecial #142                // Method org/apache/activemq/artemis/core/server/impl/ServerSessionImpl$TempQueueCleanerUpper."<init>":(Lorg/apache/activemq/artemis/core/server/ActiveMQServer;Lorg/apache/activemq/artemis/api/core/SimpleString;)V
     145: astore        7
     147: aload_0
     148: getfield      #23                 // Field remotingConnection:Lorg/apache/activemq/artemis/spi/core/protocol/RemotingConnection;
     151: aload         7
     153: invokeinterface #143,  2          // InterfaceMethod org/apache/activemq/artemis/spi/core/protocol/RemotingConnection.addCloseListener:(Lorg/apache/activemq/artemis/core/remoting/CloseListener;)V
     158: aload_0
     159: getfield      #23                 // Field remotingConnection:Lorg/apache/activemq/artemis/spi/core/protocol/RemotingConnection;
     162: aload         7
     164: invokeinterface #38,  2           // InterfaceMethod org/apache/activemq/artemis/spi/core/protocol/RemotingConnection.addFailureListener:(Lorg/apache/activemq/artemis/core/remoting/FailureListener;)V
     169: aload_0
     170: getfield      #9                  // Field tempQueueCleannerUppers:Ljava/util/Map;
     173: aload_2
     174: aload         7
     176: invokeinterface #91,  3           // InterfaceMethod java/util/Map.put:(Ljava/lang/Object;Ljava/lang/Object;)Ljava/lang/Object;
     181: pop
     182: getstatic     #61                 // Field org/apache/activemq/artemis/core/server/ActiveMQServerLogger.LOGGER:Lorg/apache/activemq/artemis/core/server/ActiveMQServerLogger;
     185: invokeinterface #116,  1          // InterfaceMethod org/apache/activemq/artemis/core/server/ActiveMQServerLogger.isDebugEnabled:()Z
     190: ifeq          282
     193: getstatic     #61                 // Field org/apache/activemq/artemis/core/server/ActiveMQServerLogger.LOGGER:Lorg/apache/activemq/artemis/core/server/ActiveMQServerLogger;
     196: new           #117                // class java/lang/StringBuilder
     199: dup
     200: invokespecial #118                // Method java/lang/StringBuilder."<init>":()V
     203: ldc           #144                // String Queue
     205: invokevirtual #120                // Method java/lang/StringBuilder.append:(Ljava/lang/String;)Ljava/lang/StringBuilder;
     208: aload_2
     209: invokevirtual #122                // Method java/lang/StringBuilder.append:(Ljava/lang/Object;)Ljava/lang/StringBuilder;
     212: ldc           #145                // String  created on address
     214: invokevirtual #120                // Method java/lang/StringBuilder.append:(Ljava/lang/String;)Ljava/lang/StringBuilder;
     217: aload_1
     218: invokevirtual #122                // Method java/lang/StringBuilder.append:(Ljava/lang/Object;)Ljava/lang/StringBuilder;
     221: ldc           #146                // String  with filter=
     223: invokevirtual #120                // Method java/lang/StringBuilder.append:(Ljava/lang/String;)Ljava/lang/StringBuilder;
     226: aload_3
     227: invokevirtual #122                // Method java/lang/StringBuilder.append:(Ljava/lang/Object;)Ljava/lang/StringBuilder;
     230: ldc           #147                // String  temporary =
     232: invokevirtual #120                // Method java/lang/StringBuilder.append:(Ljava/lang/String;)Ljava/lang/StringBuilder;
     235: iload         4
     237: invokevirtual #148                // Method java/lang/StringBuilder.append:(Z)Ljava/lang/StringBuilder;
     240: ldc           #149                // String  durable=
     242: invokevirtual #120                // Method java/lang/StringBuilder.append:(Ljava/lang/String;)Ljava/lang/StringBuilder;
     245: iload         5
     247: invokevirtual #148                // Method java/lang/StringBuilder.append:(Z)Ljava/lang/StringBuilder;
     250: ldc           #150                // String  on session user=
     252: invokevirtual #120                // Method java/lang/StringBuilder.append:(Ljava/lang/String;)Ljava/lang/StringBuilder;
     255: aload_0
     256: getfield      #17                 // Field username:Ljava/lang/String;
     259: invokevirtual #120                // Method java/lang/StringBuilder.append:(Ljava/lang/String;)Ljava/lang/StringBuilder;
     262: ldc           #121                // String , connection=
     264: invokevirtual #120                // Method java/lang/StringBuilder.append:(Ljava/lang/String;)Ljava/lang/StringBuilder;
     267: aload_0
     268: getfield      #23                 // Field remotingConnection:Lorg/apache/activemq/artemis/spi/core/protocol/RemotingConnection;
     271: invokevirtual #122                // Method java/lang/StringBuilder.append:(Ljava/lang/Object;)Ljava/lang/StringBuilder;
     274: invokevirtual #125                // Method java/lang/StringBuilder.toString:()Ljava/lang/String;
     277: invokeinterface #126,  2          // InterfaceMethod org/apache/activemq/artemis/core/server/ActiveMQServerLogger.debug:(Ljava/lang/Object;)V
     282: aload         6
     284: areturn

  public void createSharedQueue(org.apache.activemq.artemis.api.core.SimpleString, org.apache.activemq.artemis.api.core.SimpleString, boolean, org.apache.activemq.artemis.api.core.SimpleString) throws java.lang.Exception;
    Code:
       0: aload_0
       1: getfield      #27                 // Field securityStore:Lorg/apache/activemq/artemis/core/security/SecurityStore;
       4: aload_1
       5: getstatic     #131                // Field org/apache/activemq/artemis/core/security/CheckType.CREATE_NON_DURABLE_QUEUE:Lorg/apache/activemq/artemis/core/security/CheckType;
       8: aload_0
       9: invokeinterface #86,  4           // InterfaceMethod org/apache/activemq/artemis/core/security/SecurityStore.check:(Lorg/apache/activemq/artemis/api/core/SimpleString;Lorg/apache/activemq/artemis/core/security/CheckType;Lorg/apache/activemq/artemis/core/security/SecurityAuth;)V
      14: aload_0
      15: getfield      #34                 // Field server:Lorg/apache/activemq/artemis/core/server/ActiveMQServer;
      18: aload_0
      19: invokevirtual #132                // Method getUsername:()Ljava/lang/String;
      22: invokeinterface #133,  2          // InterfaceMethod org/apache/activemq/artemis/core/server/ActiveMQServer.checkQueueCreationLimit:(Ljava/lang/String;)V
      27: aload_0
      28: getfield      #34                 // Field server:Lorg/apache/activemq/artemis/core/server/ActiveMQServer;
      31: aload_1
      32: aload_2
      33: aload         4
      35: aload_0
      36: invokevirtual #132                // Method getUsername:()Ljava/lang/String;
      39: invokestatic  #108                // Method org/apache/activemq/artemis/api/core/SimpleString.toSimpleString:(Ljava/lang/String;)Lorg/apache/activemq/artemis/api/core/SimpleString;
      42: iload_3
      43: invokeinterface #151,  6          // InterfaceMethod org/apache/activemq/artemis/core/server/ActiveMQServer.createSharedQueue:(Lorg/apache/activemq/artemis/api/core/SimpleString;Lorg/apache/activemq/artemis/api/core/SimpleString;Lorg/apache/activemq/artemis/api/core/SimpleString;Lorg/apache/activemq/artemis/api/core/SimpleString;Z)V
      48: return

  public org.apache.activemq.artemis.spi.core.protocol.RemotingConnection getRemotingConnection();
    Code:
       0: aload_0
       1: getfield      #23                 // Field remotingConnection:Lorg/apache/activemq/artemis/spi/core/protocol/RemotingConnection;
       4: areturn

  public void deleteQueue(org.apache.activemq.artemis.api.core.SimpleString) throws java.lang.Exception;
    Code:
       0: aload_0
       1: getfield      #25                 // Field postOffice:Lorg/apache/activemq/artemis/core/postoffice/PostOffice;
       4: aload_1
       5: invokeinterface #79,  2           // InterfaceMethod org/apache/activemq/artemis/core/postoffice/PostOffice.getBinding:(Lorg/apache/activemq/artemis/api/core/SimpleString;)Lorg/apache/activemq/artemis/core/postoffice/Binding;
      10: astore_2
      11: aload_2
      12: ifnull        27
      15: aload_2
      16: invokeinterface #80,  1           // InterfaceMethod org/apache/activemq/artemis/core/postoffice/Binding.getType:()Lorg/apache/activemq/artemis/core/postoffice/BindingType;
      21: getstatic     #81                 // Field org/apache/activemq/artemis/core/postoffice/BindingType.LOCAL_QUEUE:Lorg/apache/activemq/artemis/core/postoffice/BindingType;
      24: if_acmpeq     35
      27: new           #152                // class org/apache/activemq/artemis/api/core/ActiveMQNonExistentQueueException
      30: dup
      31: invokespecial #153                // Method org/apache/activemq/artemis/api/core/ActiveMQNonExistentQueueException."<init>":()V
      34: athrow
      35: aload_0
      36: getfield      #34                 // Field server:Lorg/apache/activemq/artemis/core/server/ActiveMQServer;
      39: aload_1
      40: aload_0
      41: iconst_1
      42: invokeinterface #154,  4          // InterfaceMethod org/apache/activemq/artemis/core/server/ActiveMQServer.destroyQueue:(Lorg/apache/activemq/artemis/api/core/SimpleString;Lorg/apache/activemq/artemis/core/security/SecurityAuth;Z)V
      47: aload_0
      48: getfield      #9                  // Field tempQueueCleannerUppers:Ljava/util/Map;
      51: aload_1
      52: invokeinterface #57,  2           // InterfaceMethod java/util/Map.remove:(Ljava/lang/Object;)Ljava/lang/Object;
      57: checkcast     #141                // class org/apache/activemq/artemis/core/server/impl/ServerSessionImpl$TempQueueCleanerUpper
      60: astore_3
      61: aload_3
      62: ifnull        87
      65: aload_0
      66: getfield      #23                 // Field remotingConnection:Lorg/apache/activemq/artemis/spi/core/protocol/RemotingConnection;
      69: aload_3
      70: invokeinterface #155,  2          // InterfaceMethod org/apache/activemq/artemis/spi/core/protocol/RemotingConnection.removeCloseListener:(Lorg/apache/activemq/artemis/core/remoting/CloseListener;)Z
      75: pop
      76: aload_0
      77: getfield      #23                 // Field remotingConnection:Lorg/apache/activemq/artemis/spi/core/protocol/RemotingConnection;
      80: aload_3
      81: invokeinterface #76,  2           // InterfaceMethod org/apache/activemq/artemis/spi/core/protocol/RemotingConnection.removeFailureListener:(Lorg/apache/activemq/artemis/core/remoting/FailureListener;)Z
      86: pop
      87: return

  public org.apache.activemq.artemis.core.server.QueueQueryResult executeQueueQuery(org.apache.activemq.artemis.api.core.SimpleString) throws java.lang.Exception;
    Code:
       0: aload_1
       1: invokevirtual #134                // Method org/apache/activemq/artemis/api/core/SimpleString.toString:()Ljava/lang/String;
       4: ldc           #136                // String jms.queue.
       6: invokevirtual #137                // Method java/lang/String.startsWith:(Ljava/lang/String;)Z
       9: ifeq          43
      12: aload_0
      13: getfield      #34                 // Field server:Lorg/apache/activemq/artemis/core/server/ActiveMQServer;
      16: invokeinterface #156,  1          // InterfaceMethod org/apache/activemq/artemis/core/server/ActiveMQServer.getAddressSettingsRepository:()Lorg/apache/activemq/artemis/core/settings/HierarchicalRepository;
      21: aload_1
      22: invokevirtual #134                // Method org/apache/activemq/artemis/api/core/SimpleString.toString:()Ljava/lang/String;
      25: invokeinterface #157,  2          // InterfaceMethod org/apache/activemq/artemis/core/settings/HierarchicalRepository.getMatch:(Ljava/lang/String;)Ljava/lang/Object;
      30: checkcast     #158                // class org/apache/activemq/artemis/core/settings/impl/AddressSettings
      33: invokevirtual #159                // Method org/apache/activemq/artemis/core/settings/impl/AddressSettings.isAutoCreateJmsQueues:()Z
      36: ifeq          43
      39: iconst_1
      40: goto          44
      43: iconst_0
      44: istore_2
      45: aload_1
      46: ifnonnull     58
      49: getstatic     #82                 // Field org/apache/activemq/artemis/core/server/ActiveMQMessageBundle.BUNDLE:Lorg/apache/activemq/artemis/core/server/ActiveMQMessageBundle;
      52: invokeinterface #160,  1          // InterfaceMethod org/apache/activemq/artemis/core/server/ActiveMQMessageBundle.queueNameIsNull:()Ljava/lang/IllegalArgumentException;
      57: athrow
      58: aload_0
      59: getfield      #25                 // Field postOffice:Lorg/apache/activemq/artemis/core/postoffice/PostOffice;
      62: aload_1
      63: invokeinterface #79,  2           // InterfaceMethod org/apache/activemq/artemis/core/postoffice/PostOffice.getBinding:(Lorg/apache/activemq/artemis/api/core/SimpleString;)Lorg/apache/activemq/artemis/core/postoffice/Binding;
      68: astore        4
      70: aload         4
      72: ifnull        177
      75: aload         4
      77: invokeinterface #80,  1           // InterfaceMethod org/apache/activemq/artemis/core/postoffice/Binding.getType:()Lorg/apache/activemq/artemis/core/postoffice/BindingType;
      82: getstatic     #81                 // Field org/apache/activemq/artemis/core/postoffice/BindingType.LOCAL_QUEUE:Lorg/apache/activemq/artemis/core/postoffice/BindingType;
      85: if_acmpne     177
      88: aload         4
      90: invokeinterface #103,  1          // InterfaceMethod org/apache/activemq/artemis/core/postoffice/Binding.getBindable:()Lorg/apache/activemq/artemis/core/server/Bindable;
      95: checkcast     #104                // class org/apache/activemq/artemis/core/server/Queue
      98: astore        5
     100: aload         5
     102: invokeinterface #161,  1          // InterfaceMethod org/apache/activemq/artemis/core/server/Queue.getFilter:()Lorg/apache/activemq/artemis/core/filter/Filter;
     107: astore        6
     109: aload         6
     111: ifnonnull     118
     114: aconst_null
     115: goto          125
     118: aload         6
     120: invokeinterface #162,  1          // InterfaceMethod org/apache/activemq/artemis/core/filter/Filter.getFilterString:()Lorg/apache/activemq/artemis/api/core/SimpleString;
     125: astore        7
     127: new           #163                // class org/apache/activemq/artemis/core/server/QueueQueryResult
     130: dup
     131: aload_1
     132: aload         4
     134: invokeinterface #84,  1           // InterfaceMethod org/apache/activemq/artemis/core/postoffice/Binding.getAddress:()Lorg/apache/activemq/artemis/api/core/SimpleString;
     139: aload         5
     141: invokeinterface #164,  1          // InterfaceMethod org/apache/activemq/artemis/core/server/Queue.isDurable:()Z
     146: aload         5
     148: invokeinterface #165,  1          // InterfaceMethod org/apache/activemq/artemis/core/server/Queue.isTemporary:()Z
     153: aload         7
     155: aload         5
     157: invokeinterface #106,  1          // InterfaceMethod org/apache/activemq/artemis/core/server/Queue.getConsumerCount:()I
     162: aload         5
     164: invokeinterface #166,  1          // InterfaceMethod org/apache/activemq/artemis/core/server/Queue.getMessageCount:()J
     169: iload_2
     170: invokespecial #167                // Method org/apache/activemq/artemis/core/server/QueueQueryResult."<init>":(Lorg/apache/activemq/artemis/api/core/SimpleString;Lorg/apache/activemq/artemis/api/core/SimpleString;ZZLorg/apache/activemq/artemis/api/core/SimpleString;IJZ)V
     173: astore_3
     174: goto          253
     177: aload_1
     178: aload_0
     179: getfield      #35                 // Field managementAddress:Lorg/apache/activemq/artemis/api/core/SimpleString;
     182: invokevirtual #138                // Method org/apache/activemq/artemis/api/core/SimpleString.equals:(Ljava/lang/Object;)Z
     185: ifeq          212
     188: new           #163                // class org/apache/activemq/artemis/core/server/QueueQueryResult
     191: dup
     192: aload_1
     193: aload_0
     194: getfield      #35                 // Field managementAddress:Lorg/apache/activemq/artemis/api/core/SimpleString;
     197: iconst_1
     198: iconst_0
     199: aconst_null
     200: iconst_m1
     201: ldc2_w        #168                // long -1l
     204: iload_2
     205: invokespecial #167                // Method org/apache/activemq/artemis/core/server/QueueQueryResult."<init>":(Lorg/apache/activemq/artemis/api/core/SimpleString;Lorg/apache/activemq/artemis/api/core/SimpleString;ZZLorg/apache/activemq/artemis/api/core/SimpleString;IJZ)V
     208: astore_3
     209: goto          253
     212: iload_2
     213: ifeq          236
     216: new           #163                // class org/apache/activemq/artemis/core/server/QueueQueryResult
     219: dup
     220: aload_1
     221: aload_1
     222: iconst_1
     223: iconst_0
     224: aconst_null
     225: iconst_0
     226: lconst_0
     227: iconst_1
     228: iconst_0
     229: invokespecial #170                // Method org/apache/activemq/artemis/core/server/QueueQueryResult."<init>":(Lorg/apache/activemq/artemis/api/core/SimpleString;Lorg/apache/activemq/artemis/api/core/SimpleString;ZZLorg/apache/activemq/artemis/api/core/SimpleString;IJZZ)V
     232: astore_3
     233: goto          253
     236: new           #163                // class org/apache/activemq/artemis/core/server/QueueQueryResult
     239: dup
     240: aconst_null
     241: aconst_null
     242: iconst_0
     243: iconst_0
     244: aconst_null
     245: iconst_0
     246: lconst_0
     247: iconst_0
     248: iconst_0
     249: invokespecial #170                // Method org/apache/activemq/artemis/core/server/QueueQueryResult."<init>":(Lorg/apache/activemq/artemis/api/core/SimpleString;Lorg/apache/activemq/artemis/api/core/SimpleString;ZZLorg/apache/activemq/artemis/api/core/SimpleString;IJZZ)V
     252: astore_3
     253: aload_3
     254: areturn

  public org.apache.activemq.artemis.core.server.BindingQueryResult executeBindingQuery(org.apache.activemq.artemis.api.core.SimpleString) throws java.lang.Exception;
    Code:
       0: aload_1
       1: invokevirtual #134                // Method org/apache/activemq/artemis/api/core/SimpleString.toString:()Ljava/lang/String;
       4: ldc           #136                // String jms.queue.
       6: invokevirtual #137                // Method java/lang/String.startsWith:(Ljava/lang/String;)Z
       9: ifeq          43
      12: aload_0
      13: getfield      #34                 // Field server:Lorg/apache/activemq/artemis/core/server/ActiveMQServer;
      16: invokeinterface #156,  1          // InterfaceMethod org/apache/activemq/artemis/core/server/ActiveMQServer.getAddressSettingsRepository:()Lorg/apache/activemq/artemis/core/settings/HierarchicalRepository;
      21: aload_1
      22: invokevirtual #134                // Method org/apache/activemq/artemis/api/core/SimpleString.toString:()Ljava/lang/String;
      25: invokeinterface #157,  2          // InterfaceMethod org/apache/activemq/artemis/core/settings/HierarchicalRepository.getMatch:(Ljava/lang/String;)Ljava/lang/Object;
      30: checkcast     #158                // class org/apache/activemq/artemis/core/settings/impl/AddressSettings
      33: invokevirtual #159                // Method org/apache/activemq/artemis/core/settings/impl/AddressSettings.isAutoCreateJmsQueues:()Z
      36: ifeq          43
      39: iconst_1
      40: goto          44
      43: iconst_0
      44: istore_2
      45: aload_1
      46: ifnonnull     58
      49: getstatic     #82                 // Field org/apache/activemq/artemis/core/server/ActiveMQMessageBundle.BUNDLE:Lorg/apache/activemq/artemis/core/server/ActiveMQMessageBundle;
      52: invokeinterface #171,  1          // InterfaceMethod org/apache/activemq/artemis/core/server/ActiveMQMessageBundle.addressIsNull:()Ljava/lang/IllegalArgumentException;
      57: athrow
      58: new           #172                // class java/util/ArrayList
      61: dup
      62: invokespecial #173                // Method java/util/ArrayList."<init>":()V
      65: astore_3
      66: aload_1
      67: aload_0
      68: getfield      #35                 // Field managementAddress:Lorg/apache/activemq/artemis/api/core/SimpleString;
      71: invokevirtual #138                // Method org/apache/activemq/artemis/api/core/SimpleString.equals:(Ljava/lang/Object;)Z
      74: ifeq          88
      77: new           #174                // class org/apache/activemq/artemis/core/server/BindingQueryResult
      80: dup
      81: iconst_1
      82: aload_3
      83: iload_2
      84: invokespecial #175                // Method org/apache/activemq/artemis/core/server/BindingQueryResult."<init>":(ZLjava/util/List;Z)V
      87: areturn
      88: aload_0
      89: getfield      #25                 // Field postOffice:Lorg/apache/activemq/artemis/core/postoffice/PostOffice;
      92: aload_1
      93: invokeinterface #176,  2          // InterfaceMethod org/apache/activemq/artemis/core/postoffice/PostOffice.getMatchingBindings:(Lorg/apache/activemq/artemis/api/core/SimpleString;)Lorg/apache/activemq/artemis/core/postoffice/Bindings;
      98: astore        4
     100: aload         4
     102: invokeinterface #177,  1          // InterfaceMethod org/apache/activemq/artemis/core/postoffice/Bindings.getBindings:()Ljava/util/Collection;
     107: invokeinterface #178,  1          // InterfaceMethod java/util/Collection.iterator:()Ljava/util/Iterator;
     112: astore        5
     114: aload         5
     116: invokeinterface #65,  1           // InterfaceMethod java/util/Iterator.hasNext:()Z
     121: ifeq          179
     124: aload         5
     126: invokeinterface #66,  1           // InterfaceMethod java/util/Iterator.next:()Ljava/lang/Object;
     131: checkcast     #179                // class org/apache/activemq/artemis/core/postoffice/Binding
     134: astore        6
     136: aload         6
     138: invokeinterface #80,  1           // InterfaceMethod org/apache/activemq/artemis/core/postoffice/Binding.getType:()Lorg/apache/activemq/artemis/core/postoffice/BindingType;
     143: getstatic     #81                 // Field org/apache/activemq/artemis/core/postoffice/BindingType.LOCAL_QUEUE:Lorg/apache/activemq/artemis/core/postoffice/BindingType;
     146: if_acmpeq     162
     149: aload         6
     151: invokeinterface #80,  1           // InterfaceMethod org/apache/activemq/artemis/core/postoffice/Binding.getType:()Lorg/apache/activemq/artemis/core/postoffice/BindingType;
     156: getstatic     #180                // Field org/apache/activemq/artemis/core/postoffice/BindingType.REMOTE_QUEUE:Lorg/apache/activemq/artemis/core/postoffice/BindingType;
     159: if_acmpne     176
     162: aload_3
     163: aload         6
     165: invokeinterface #181,  1          // InterfaceMethod org/apache/activemq/artemis/core/postoffice/Binding.getUniqueName:()Lorg/apache/activemq/artemis/api/core/SimpleString;
     170: invokeinterface #182,  2          // InterfaceMethod java/util/List.add:(Ljava/lang/Object;)Z
     175: pop
     176: goto          114
     179: new           #174                // class org/apache/activemq/artemis/core/server/BindingQueryResult
     182: dup
     183: aload_3
     184: invokeinterface #183,  1          // InterfaceMethod java/util/List.isEmpty:()Z
     189: ifne          196
     192: iconst_1
     193: goto          197
     196: iconst_0
     197: aload_3
     198: iload_2
     199: invokespecial #175                // Method org/apache/activemq/artemis/core/server/BindingQueryResult."<init>":(ZLjava/util/List;Z)V
     202: areturn

  public void forceConsumerDelivery(long, long) throws java.lang.Exception;
    Code:
       0: aload_0
       1: getfield      #5                  // Field consumers:Ljava/util/Map;
       4: lload_1
       5: invokestatic  #56                 // Method java/lang/Long.valueOf:(J)Ljava/lang/Long;
       8: invokeinterface #184,  2          // InterfaceMethod java/util/Map.get:(Ljava/lang/Object;)Ljava/lang/Object;
      13: checkcast     #67                 // class org/apache/activemq/artemis/core/server/ServerConsumer
      16: astore        5
      18: aload         5
      20: ifnull        31
      23: aload         5
      25: lload_3
      26: invokeinterface #185,  3          // InterfaceMethod org/apache/activemq/artemis/core/server/ServerConsumer.forceDelivery:(J)V
      31: return

  public void promptDelivery(long);
    Code:
       0: aload_0
       1: getfield      #5                  // Field consumers:Ljava/util/Map;
       4: lload_1
       5: invokestatic  #56                 // Method java/lang/Long.valueOf:(J)Ljava/lang/Long;
       8: invokeinterface #184,  2          // InterfaceMethod java/util/Map.get:(Ljava/lang/Object;)Ljava/lang/Object;
      13: checkcast     #67                 // class org/apache/activemq/artemis/core/server/ServerConsumer
      16: astore_3
      17: aload_3
      18: ifnull        27
      21: aload_3
      22: invokeinterface #186,  1          // InterfaceMethod org/apache/activemq/artemis/core/server/ServerConsumer.promptDelivery:()V
      27: return

  public void acknowledge(long, long) throws java.lang.Exception;
    Code:
       0: aload_0
       1: lload_1
       2: invokespecial #187                // Method findConsumer:(J)Lorg/apache/activemq/artemis/core/server/ServerConsumer;
       5: astore        5
       7: aload_0
       8: getfield      #45                 // Field tx:Lorg/apache/activemq/artemis/core/transaction/Transaction;
      11: ifnull        94
      14: aload_0
      15: getfield      #45                 // Field tx:Lorg/apache/activemq/artemis/core/transaction/Transaction;
      18: invokeinterface #188,  1          // InterfaceMethod org/apache/activemq/artemis/core/transaction/Transaction.getState:()Lorg/apache/activemq/artemis/core/transaction/Transaction$State;
      23: getstatic     #189                // Field org/apache/activemq/artemis/core/transaction/Transaction$State.ROLLEDBACK:Lorg/apache/activemq/artemis/core/transaction/Transaction$State;
      26: if_acmpne     94
      29: aload_0
      30: invokevirtual #44                 // Method newTransaction:()Lorg/apache/activemq/artemis/core/transaction/Transaction;
      33: astore        6
      35: aload         5
      37: aload         6
      39: lload_3
      40: invokeinterface #190,  4          // InterfaceMethod org/apache/activemq/artemis/core/server/ServerConsumer.acknowledge:(Lorg/apache/activemq/artemis/core/transaction/Transaction;J)V
      45: goto          84
      48: astore        7
      50: getstatic     #61                 // Field org/apache/activemq/artemis/core/server/ActiveMQServerLogger.LOGGER:Lorg/apache/activemq/artemis/core/server/ActiveMQServerLogger;
      53: new           #117                // class java/lang/StringBuilder
      56: dup
      57: invokespecial #118                // Method java/lang/StringBuilder."<init>":()V
      60: ldc           #191                // String Ignored exception while acking messageID
      62: invokevirtual #120                // Method java/lang/StringBuilder.append:(Ljava/lang/String;)Ljava/lang/StringBuilder;
      65: lload_3
      66: invokevirtual #192                // Method java/lang/StringBuilder.append:(J)Ljava/lang/StringBuilder;
      69: ldc           #193                // String  on a rolledback TX
      71: invokevirtual #120                // Method java/lang/StringBuilder.append:(Ljava/lang/String;)Ljava/lang/StringBuilder;
      74: invokevirtual #125                // Method java/lang/StringBuilder.toString:()Ljava/lang/String;
      77: aload         7
      79: invokeinterface #194,  3          // InterfaceMethod org/apache/activemq/artemis/core/server/ActiveMQServerLogger.debug:(Ljava/lang/Object;Ljava/lang/Throwable;)V
      84: aload         6
      86: invokeinterface #195,  1          // InterfaceMethod org/apache/activemq/artemis/core/transaction/Transaction.rollback:()V
      91: goto          117
      94: aload         5
      96: aload_0
      97: getfield      #21                 // Field autoCommitAcks:Z
     100: ifeq          107
     103: aconst_null
     104: goto          111
     107: aload_0
     108: getfield      #45                 // Field tx:Lorg/apache/activemq/artemis/core/transaction/Transaction;
     111: lload_3
     112: invokeinterface #190,  4          // InterfaceMethod org/apache/activemq/artemis/core/server/ServerConsumer.acknowledge:(Lorg/apache/activemq/artemis/core/transaction/Transaction;J)V
     117: return
    Exception table:
       from    to  target type
          35    45    48   Class java/lang/Exception

  private org.apache.activemq.artemis.core.server.ServerConsumer findConsumer(long) throws java.lang.Exception;
    Code:
       0: aload_0
       1: getfield      #5                  // Field consumers:Ljava/util/Map;
       4: lload_1
       5: invokestatic  #56                 // Method java/lang/Long.valueOf:(J)Ljava/lang/Long;
       8: invokeinterface #184,  2          // InterfaceMethod java/util/Map.get:(Ljava/lang/Object;)Ljava/lang/Object;
      13: checkcast     #67                 // class org/apache/activemq/artemis/core/server/ServerConsumer
      16: astore_3
      17: aload_3
      18: ifnonnull     55
      21: aload_0
      22: getfield      #45                 // Field tx:Lorg/apache/activemq/artemis/core/transaction/Transaction;
      25: astore        4
      27: getstatic     #82                 // Field org/apache/activemq/artemis/core/server/ActiveMQMessageBundle.BUNDLE:Lorg/apache/activemq/artemis/core/server/ActiveMQMessageBundle;
      30: lload_1
      31: invokeinterface #196,  3          // InterfaceMethod org/apache/activemq/artemis/core/server/ActiveMQMessageBundle.consumerDoesntExist:(J)Lorg/apache/activemq/artemis/api/core/ActiveMQIllegalStateException;
      36: astore        5
      38: aload         4
      40: ifnull        52
      43: aload         4
      45: aload         5
      47: invokeinterface #52,  2           // InterfaceMethod org/apache/activemq/artemis/core/transaction/Transaction.markAsRollbackOnly:(Lorg/apache/activemq/artemis/api/core/ActiveMQException;)V
      52: aload         5
      54: athrow
      55: aload_3
      56: areturn

  public void individualAcknowledge(long, long) throws java.lang.Exception;
    Code:
       0: aload_0
       1: lload_1
       2: invokespecial #187                // Method findConsumer:(J)Lorg/apache/activemq/artemis/core/server/ServerConsumer;
       5: astore        5
       7: aload_0
       8: getfield      #45                 // Field tx:Lorg/apache/activemq/artemis/core/transaction/Transaction;
      11: ifnull        57
      14: aload_0
      15: getfield      #45                 // Field tx:Lorg/apache/activemq/artemis/core/transaction/Transaction;
      18: invokeinterface #188,  1          // InterfaceMethod org/apache/activemq/artemis/core/transaction/Transaction.getState:()Lorg/apache/activemq/artemis/core/transaction/Transaction$State;
      23: getstatic     #189                // Field org/apache/activemq/artemis/core/transaction/Transaction$State.ROLLEDBACK:Lorg/apache/activemq/artemis/core/transaction/Transaction$State;
      26: if_acmpne     57
      29: aload_0
      30: invokevirtual #44                 // Method newTransaction:()Lorg/apache/activemq/artemis/core/transaction/Transaction;
      33: astore        6
      35: aload         5
      37: aload_0
      38: getfield      #45                 // Field tx:Lorg/apache/activemq/artemis/core/transaction/Transaction;
      41: lload_3
      42: invokeinterface #197,  4          // InterfaceMethod org/apache/activemq/artemis/core/server/ServerConsumer.individualAcknowledge:(Lorg/apache/activemq/artemis/core/transaction/Transaction;J)V
      47: aload         6
      49: invokeinterface #195,  1          // InterfaceMethod org/apache/activemq/artemis/core/transaction/Transaction.rollback:()V
      54: goto          80
      57: aload         5
      59: aload_0
      60: getfield      #21                 // Field autoCommitAcks:Z
      63: ifeq          70
      66: aconst_null
      67: goto          74
      70: aload_0
      71: getfield      #45                 // Field tx:Lorg/apache/activemq/artemis/core/transaction/Transaction;
      74: lload_3
      75: invokeinterface #197,  4          // InterfaceMethod org/apache/activemq/artemis/core/server/ServerConsumer.individualAcknowledge:(Lorg/apache/activemq/artemis/core/transaction/Transaction;J)V
      80: return

  public void individualCancel(long, long, boolean) throws java.lang.Exception;
    Code:
       0: aload_0
       1: getfield      #5                  // Field consumers:Ljava/util/Map;
       4: lload_1
       5: invokestatic  #56                 // Method java/lang/Long.valueOf:(J)Ljava/lang/Long;
       8: invokeinterface #184,  2          // InterfaceMethod java/util/Map.get:(Ljava/lang/Object;)Ljava/lang/Object;
      13: checkcast     #67                 // class org/apache/activemq/artemis/core/server/ServerConsumer
      16: astore        6
      18: aload         6
      20: ifnull        33
      23: aload         6
      25: lload_3
      26: iload         5
      28: invokeinterface #198,  4          // InterfaceMethod org/apache/activemq/artemis/core/server/ServerConsumer.individualCancel:(JZ)V
      33: return

  public void expire(long, long) throws java.lang.Exception;
    Code:
       0: aload_0
       1: getfield      #5                  // Field consumers:Ljava/util/Map;
       4: lload_1
       5: invokestatic  #56                 // Method java/lang/Long.valueOf:(J)Ljava/lang/Long;
       8: invokeinterface #184,  2          // InterfaceMethod java/util/Map.get:(Ljava/lang/Object;)Ljava/lang/Object;
      13: checkcast     #67                 // class org/apache/activemq/artemis/core/server/ServerConsumer
      16: lload_3
      17: invokeinterface #199,  3          // InterfaceMethod org/apache/activemq/artemis/core/server/ServerConsumer.removeReferenceByID:(J)Lorg/apache/activemq/artemis/core/server/MessageReference;
      22: astore        5
      24: aload         5
      26: ifnull        43
      29: aload         5
      31: invokeinterface #200,  1          // InterfaceMethod org/apache/activemq/artemis/core/server/MessageReference.getQueue:()Lorg/apache/activemq/artemis/core/server/Queue;
      36: aload         5
      38: invokeinterface #201,  2          // InterfaceMethod org/apache/activemq/artemis/core/server/Queue.expire:(Lorg/apache/activemq/artemis/core/server/MessageReference;)V
      43: return

  public synchronized void commit() throws java.lang.Exception;
    Code:
       0: getstatic     #202                // Field isTrace:Z
       3: ifeq          16
       6: getstatic     #61                 // Field org/apache/activemq/artemis/core/server/ActiveMQServerLogger.LOGGER:Lorg/apache/activemq/artemis/core/server/ActiveMQServerLogger;
       9: ldc           #203                // String Calling commit
      11: invokeinterface #204,  2          // InterfaceMethod org/apache/activemq/artemis/core/server/ActiveMQServerLogger.trace:(Ljava/lang/Object;)V
      16: aload_0
      17: getfield      #45                 // Field tx:Lorg/apache/activemq/artemis/core/transaction/Transaction;
      20: ifnull        32
      23: aload_0
      24: getfield      #45                 // Field tx:Lorg/apache/activemq/artemis/core/transaction/Transaction;
      27: invokeinterface #205,  1          // InterfaceMethod org/apache/activemq/artemis/core/transaction/Transaction.commit:()V
      32: aload_0
      33: getfield      #30                 // Field xa:Z
      36: ifeq          47
      39: aload_0
      40: aconst_null
      41: putfield      #45                 // Field tx:Lorg/apache/activemq/artemis/core/transaction/Transaction;
      44: goto          84
      47: aload_0
      48: aload_0
      49: invokevirtual #44                 // Method newTransaction:()Lorg/apache/activemq/artemis/core/transaction/Transaction;
      52: putfield      #45                 // Field tx:Lorg/apache/activemq/artemis/core/transaction/Transaction;
      55: goto          84
      58: astore_1
      59: aload_0
      60: getfield      #30                 // Field xa:Z
      63: ifeq          74
      66: aload_0
      67: aconst_null
      68: putfield      #45                 // Field tx:Lorg/apache/activemq/artemis/core/transaction/Transaction;
      71: goto          82
      74: aload_0
      75: aload_0
      76: invokevirtual #44                 // Method newTransaction:()Lorg/apache/activemq/artemis/core/transaction/Transaction;
      79: putfield      #45                 // Field tx:Lorg/apache/activemq/artemis/core/transaction/Transaction;
      82: aload_1
      83: athrow
      84: return
    Exception table:
       from    to  target type
          16    32    58   any

  public void rollback(boolean) throws java.lang.Exception;
    Code:
       0: aload_0
       1: iconst_0
       2: iload_1
       3: invokespecial #59                 // Method rollback:(ZZ)V
       6: return

  private synchronized void rollback(boolean, boolean) throws java.lang.Exception;
    Code:
       0: aload_0
       1: getfield      #45                 // Field tx:Lorg/apache/activemq/artemis/core/transaction/Transaction;
       4: ifnonnull     15
       7: aload_0
       8: aload_0
       9: invokevirtual #44                 // Method newTransaction:()Lorg/apache/activemq/artemis/core/transaction/Transaction;
      12: putfield      #45                 // Field tx:Lorg/apache/activemq/artemis/core/transaction/Transaction;
      15: aload_0
      16: iload_1
      17: iload_2
      18: aload_0
      19: getfield      #45                 // Field tx:Lorg/apache/activemq/artemis/core/transaction/Transaction;
      22: invokespecial #206                // Method doRollback:(ZZLorg/apache/activemq/artemis/core/transaction/Transaction;)V
      25: aload_0
      26: getfield      #30                 // Field xa:Z
      29: ifeq          40
      32: aload_0
      33: aconst_null
      34: putfield      #45                 // Field tx:Lorg/apache/activemq/artemis/core/transaction/Transaction;
      37: goto          48
      40: aload_0
      41: aload_0
      42: invokevirtual #44                 // Method newTransaction:()Lorg/apache/activemq/artemis/core/transaction/Transaction;
      45: putfield      #45                 // Field tx:Lorg/apache/activemq/artemis/core/transaction/Transaction;
      48: return

  protected org.apache.activemq.artemis.core.transaction.Transaction newTransaction();
    Code:
       0: aload_0
       1: getfield      #43                 // Field transactionFactory:Lorg/apache/activemq/artemis/core/transaction/TransactionFactory;
       4: aconst_null
       5: aload_0
       6: getfield      #24                 // Field storageManager:Lorg/apache/activemq/artemis/core/persistence/StorageManager;
       9: aload_0
      10: getfield      #29                 // Field timeoutSeconds:I
      13: invokeinterface #207,  4          // InterfaceMethod org/apache/activemq/artemis/core/transaction/TransactionFactory.newTransaction:(Ljavax/transaction/xa/Xid;Lorg/apache/activemq/artemis/core/persistence/StorageManager;I)Lorg/apache/activemq/artemis/core/transaction/Transaction;
      18: areturn

  private org.apache.activemq.artemis.core.transaction.Transaction newTransaction(javax.transaction.xa.Xid);
    Code:
       0: aload_0
       1: getfield      #43                 // Field transactionFactory:Lorg/apache/activemq/artemis/core/transaction/TransactionFactory;
       4: aload_1
       5: aload_0
       6: getfield      #24                 // Field storageManager:Lorg/apache/activemq/artemis/core/persistence/StorageManager;
       9: aload_0
      10: getfield      #29                 // Field timeoutSeconds:I
      13: invokeinterface #207,  4          // InterfaceMethod org/apache/activemq/artemis/core/transaction/TransactionFactory.newTransaction:(Ljavax/transaction/xa/Xid;Lorg/apache/activemq/artemis/core/persistence/StorageManager;I)Lorg/apache/activemq/artemis/core/transaction/Transaction;
      18: areturn

  public synchronized void xaCommit(javax.transaction.xa.Xid, boolean) throws java.lang.Exception;
    Code:
       0: aload_0
       1: getfield      #45                 // Field tx:Lorg/apache/activemq/artemis/core/transaction/Transaction;
       4: ifnull        62
       7: aload_0
       8: getfield      #45                 // Field tx:Lorg/apache/activemq/artemis/core/transaction/Transaction;
      11: invokeinterface #58,  1           // InterfaceMethod org/apache/activemq/artemis/core/transaction/Transaction.getXid:()Ljavax/transaction/xa/Xid;
      16: aload_1
      17: invokevirtual #208                // Method java/lang/Object.equals:(Ljava/lang/Object;)Z
      20: ifeq          62
      23: new           #117                // class java/lang/StringBuilder
      26: dup
      27: invokespecial #118                // Method java/lang/StringBuilder."<init>":()V
      30: ldc           #209                // String Cannot commit, session is currently doing work in transaction
      32: invokevirtual #120                // Method java/lang/StringBuilder.append:(Ljava/lang/String;)Ljava/lang/StringBuilder;
      35: aload_0
      36: getfield      #45                 // Field tx:Lorg/apache/activemq/artemis/core/transaction/Transaction;
      39: invokeinterface #58,  1           // InterfaceMethod org/apache/activemq/artemis/core/transaction/Transaction.getXid:()Ljavax/transaction/xa/Xid;
      44: invokevirtual #122                // Method java/lang/StringBuilder.append:(Ljava/lang/Object;)Ljava/lang/StringBuilder;
      47: invokevirtual #125                // Method java/lang/StringBuilder.toString:()Ljava/lang/String;
      50: astore_3
      51: new           #210                // class org/apache/activemq/artemis/core/exception/ActiveMQXAException
      54: dup
      55: bipush        -6
      57: aload_3
      58: invokespecial #212                // Method org/apache/activemq/artemis/core/exception/ActiveMQXAException."<init>":(ILjava/lang/String;)V
      61: athrow
      62: aload_0
      63: getfield      #26                 // Field resourceManager:Lorg/apache/activemq/artemis/core/transaction/ResourceManager;
      66: aload_1
      67: invokeinterface #213,  2          // InterfaceMethod org/apache/activemq/artemis/core/transaction/ResourceManager.removeTransaction:(Ljavax/transaction/xa/Xid;)Lorg/apache/activemq/artemis/core/transaction/Transaction;
      72: astore_3
      73: getstatic     #202                // Field isTrace:Z
      76: ifeq          115
      79: getstatic     #61                 // Field org/apache/activemq/artemis/core/server/ActiveMQServerLogger.LOGGER:Lorg/apache/activemq/artemis/core/server/ActiveMQServerLogger;
      82: new           #117                // class java/lang/StringBuilder
      85: dup
      86: invokespecial #118                // Method java/lang/StringBuilder."<init>":()V
      89: ldc           #214                // String XAcommit into
      91: invokevirtual #120                // Method java/lang/StringBuilder.append:(Ljava/lang/String;)Ljava/lang/StringBuilder;
      94: aload_3
      95: invokevirtual #122                // Method java/lang/StringBuilder.append:(Ljava/lang/Object;)Ljava/lang/StringBuilder;
      98: ldc           #215                // String , xid=
     100: invokevirtual #120                // Method java/lang/StringBuilder.append:(Ljava/lang/String;)Ljava/lang/StringBuilder;
     103: aload_1
     104: invokevirtual #122                // Method java/lang/StringBuilder.append:(Ljava/lang/Object;)Ljava/lang/StringBuilder;
     107: invokevirtual #125                // Method java/lang/StringBuilder.toString:()Ljava/lang/String;
     110: invokeinterface #204,  2          // InterfaceMethod org/apache/activemq/artemis/core/server/ActiveMQServerLogger.trace:(Ljava/lang/Object;)V
     115: aload_3
     116: ifnonnull     289
     119: aload_0
     120: getfield      #26                 // Field resourceManager:Lorg/apache/activemq/artemis/core/transaction/ResourceManager;
     123: invokeinterface #216,  1          // InterfaceMethod org/apache/activemq/artemis/core/transaction/ResourceManager.getHeuristicCommittedTransactions:()Ljava/util/List;
     128: aload_1
     129: invokeinterface #217,  2          // InterfaceMethod java/util/List.contains:(Ljava/lang/Object;)Z
     134: ifeq          166
     137: new           #210                // class org/apache/activemq/artemis/core/exception/ActiveMQXAException
     140: dup
     141: bipush        7
     143: new           #117                // class java/lang/StringBuilder
     146: dup
     147: invokespecial #118                // Method java/lang/StringBuilder."<init>":()V
     150: ldc           #218                // String transaction has been heuristically committed:
     152: invokevirtual #120                // Method java/lang/StringBuilder.append:(Ljava/lang/String;)Ljava/lang/StringBuilder;
     155: aload_1
     156: invokevirtual #122                // Method java/lang/StringBuilder.append:(Ljava/lang/Object;)Ljava/lang/StringBuilder;
     159: invokevirtual #125                // Method java/lang/StringBuilder.toString:()Ljava/lang/String;
     162: invokespecial #212                // Method org/apache/activemq/artemis/core/exception/ActiveMQXAException."<init>":(ILjava/lang/String;)V
     165: athrow
     166: aload_0
     167: getfield      #26                 // Field resourceManager:Lorg/apache/activemq/artemis/core/transaction/ResourceManager;
     170: invokeinterface #219,  1          // InterfaceMethod org/apache/activemq/artemis/core/transaction/ResourceManager.getHeuristicRolledbackTransactions:()Ljava/util/List;
     175: aload_1
     176: invokeinterface #217,  2          // InterfaceMethod java/util/List.contains:(Ljava/lang/Object;)Z
     181: ifeq          213
     184: new           #210                // class org/apache/activemq/artemis/core/exception/ActiveMQXAException
     187: dup
     188: bipush        6
     190: new           #117                // class java/lang/StringBuilder
     193: dup
     194: invokespecial #118                // Method java/lang/StringBuilder."<init>":()V
     197: ldc           #220                // String transaction has been heuristically rolled back:
     199: invokevirtual #120                // Method java/lang/StringBuilder.append:(Ljava/lang/String;)Ljava/lang/StringBuilder;
     202: aload_1
     203: invokevirtual #122                // Method java/lang/StringBuilder.append:(Ljava/lang/Object;)Ljava/lang/StringBuilder;
     206: invokevirtual #125                // Method java/lang/StringBuilder.toString:()Ljava/lang/String;
     209: invokespecial #212                // Method org/apache/activemq/artemis/core/exception/ActiveMQXAException."<init>":(ILjava/lang/String;)V
     212: athrow
     213: getstatic     #202                // Field isTrace:Z
     216: ifeq          260
     219: getstatic     #61                 // Field org/apache/activemq/artemis/core/server/ActiveMQServerLogger.LOGGER:Lorg/apache/activemq/artemis/core/server/ActiveMQServerLogger;
     222: new           #117                // class java/lang/StringBuilder
     225: dup
     226: invokespecial #118                // Method java/lang/StringBuilder."<init>":()V
     229: ldc           #214                // String XAcommit into
     231: invokevirtual #120                // Method java/lang/StringBuilder.append:(Ljava/lang/String;)Ljava/lang/StringBuilder;
     234: aload_3
     235: invokevirtual #122                // Method java/lang/StringBuilder.append:(Ljava/lang/Object;)Ljava/lang/StringBuilder;
     238: ldc           #215                // String , xid=
     240: invokevirtual #120                // Method java/lang/StringBuilder.append:(Ljava/lang/String;)Ljava/lang/StringBuilder;
     243: aload_1
     244: invokevirtual #122                // Method java/lang/StringBuilder.append:(Ljava/lang/Object;)Ljava/lang/StringBuilder;
     247: ldc           #221                // String  cannot find it
     249: invokevirtual #120                // Method java/lang/StringBuilder.append:(Ljava/lang/String;)Ljava/lang/StringBuilder;
     252: invokevirtual #125                // Method java/lang/StringBuilder.toString:()Ljava/lang/String;
     255: invokeinterface #204,  2          // InterfaceMethod org/apache/activemq/artemis/core/server/ActiveMQServerLogger.trace:(Ljava/lang/Object;)V
     260: new           #210                // class org/apache/activemq/artemis/core/exception/ActiveMQXAException
     263: dup
     264: bipush        -4
     266: new           #117                // class java/lang/StringBuilder
     269: dup
     270: invokespecial #118                // Method java/lang/StringBuilder."<init>":()V
     273: ldc           #222                // String Cannot find xid in resource manager:
     275: invokevirtual #120                // Method java/lang/StringBuilder.append:(Ljava/lang/String;)Ljava/lang/StringBuilder;
     278: aload_1
     279: invokevirtual #122                // Method java/lang/StringBuilder.append:(Ljava/lang/Object;)Ljava/lang/StringBuilder;
     282: invokevirtual #125                // Method java/lang/StringBuilder.toString:()Ljava/lang/String;
     285: invokespecial #212                // Method org/apache/activemq/artemis/core/exception/ActiveMQXAException."<init>":(ILjava/lang/String;)V
     288: athrow
     289: aload_3
     290: invokeinterface #188,  1          // InterfaceMethod org/apache/activemq/artemis/core/transaction/Transaction.getState:()Lorg/apache/activemq/artemis/core/transaction/Transaction$State;
     295: getstatic     #223                // Field org/apache/activemq/artemis/core/transaction/Transaction$State.SUSPENDED:Lorg/apache/activemq/artemis/core/transaction/Transaction$State;
     298: if_acmpne     342
     301: aload_0
     302: getfield      #26                 // Field resourceManager:Lorg/apache/activemq/artemis/core/transaction/ResourceManager;
     305: aload_1
     306: aload_3
     307: invokeinterface #224,  3          // InterfaceMethod org/apache/activemq/artemis/core/transaction/ResourceManager.putTransaction:(Ljavax/transaction/xa/Xid;Lorg/apache/activemq/artemis/core/transaction/Transaction;)Z
     312: pop
     313: new           #210                // class org/apache/activemq/artemis/core/exception/ActiveMQXAException
     316: dup
     317: bipush        -6
     319: new           #117                // class java/lang/StringBuilder
     322: dup
     323: invokespecial #118                // Method java/lang/StringBuilder."<init>":()V
     326: ldc           #225                // String Cannot commit transaction, it is suspended
     328: invokevirtual #120                // Method java/lang/StringBuilder.append:(Ljava/lang/String;)Ljava/lang/StringBuilder;
     331: aload_1
     332: invokevirtual #122                // Method java/lang/StringBuilder.append:(Ljava/lang/Object;)Ljava/lang/StringBuilder;
     335: invokevirtual #125                // Method java/lang/StringBuilder.toString:()Ljava/lang/String;
     338: invokespecial #212                // Method org/apache/activemq/artemis/core/exception/ActiveMQXAException."<init>":(ILjava/lang/String;)V
     341: athrow
     342: aload_3
     343: iload_2
     344: invokeinterface #226,  2          // InterfaceMethod org/apache/activemq/artemis/core/transaction/Transaction.commit:(Z)V
     349: return

  public synchronized void xaEnd(javax.transaction.xa.Xid) throws java.lang.Exception;
    Code:
       0: aload_0
       1: getfield      #45                 // Field tx:Lorg/apache/activemq/artemis/core/transaction/Transaction;
       4: ifnull        96
       7: aload_0
       8: getfield      #45                 // Field tx:Lorg/apache/activemq/artemis/core/transaction/Transaction;
      11: invokeinterface #58,  1           // InterfaceMethod org/apache/activemq/artemis/core/transaction/Transaction.getXid:()Ljavax/transaction/xa/Xid;
      16: aload_1
      17: invokevirtual #208                // Method java/lang/Object.equals:(Ljava/lang/Object;)Z
      20: ifeq          96
      23: aload_0
      24: getfield      #45                 // Field tx:Lorg/apache/activemq/artemis/core/transaction/Transaction;
      27: invokeinterface #188,  1          // InterfaceMethod org/apache/activemq/artemis/core/transaction/Transaction.getState:()Lorg/apache/activemq/artemis/core/transaction/Transaction$State;
      32: getstatic     #223                // Field org/apache/activemq/artemis/core/transaction/Transaction$State.SUSPENDED:Lorg/apache/activemq/artemis/core/transaction/Transaction$State;
      35: if_acmpne     53
      38: ldc           #227                // String Cannot end, transaction is suspended
      40: astore_2
      41: new           #210                // class org/apache/activemq/artemis/core/exception/ActiveMQXAException
      44: dup
      45: bipush        -6
      47: ldc           #227                // String Cannot end, transaction is suspended
      49: invokespecial #212                // Method org/apache/activemq/artemis/core/exception/ActiveMQXAException."<init>":(ILjava/lang/String;)V
      52: athrow
      53: aload_0
      54: getfield      #45                 // Field tx:Lorg/apache/activemq/artemis/core/transaction/Transaction;
      57: invokeinterface #188,  1          // InterfaceMethod org/apache/activemq/artemis/core/transaction/Transaction.getState:()Lorg/apache/activemq/artemis/core/transaction/Transaction$State;
      62: getstatic     #189                // Field org/apache/activemq/artemis/core/transaction/Transaction$State.ROLLEDBACK:Lorg/apache/activemq/artemis/core/transaction/Transaction$State;
      65: if_acmpne     88
      68: ldc           #228                // String Cannot end, transaction is rolled back
      70: astore_2
      71: aload_0
      72: aconst_null
      73: putfield      #45                 // Field tx:Lorg/apache/activemq/artemis/core/transaction/Transaction;
      76: new           #210                // class org/apache/activemq/artemis/core/exception/ActiveMQXAException
      79: dup
      80: bipush        -6
      82: ldc           #228                // String Cannot end, transaction is rolled back
      84: invokespecial #212                // Method org/apache/activemq/artemis/core/exception/ActiveMQXAException."<init>":(ILjava/lang/String;)V
      87: athrow
      88: aload_0
      89: aconst_null
      90: putfield      #45                 // Field tx:Lorg/apache/activemq/artemis/core/transaction/Transaction;
      93: goto          191
      96: aload_0
      97: getfield      #26                 // Field resourceManager:Lorg/apache/activemq/artemis/core/transaction/ResourceManager;
     100: aload_1
     101: invokeinterface #229,  2          // InterfaceMethod org/apache/activemq/artemis/core/transaction/ResourceManager.getTransaction:(Ljavax/transaction/xa/Xid;)Lorg/apache/activemq/artemis/core/transaction/Transaction;
     106: astore_2
     107: aload_2
     108: ifnonnull     142
     111: new           #117                // class java/lang/StringBuilder
     114: dup
     115: invokespecial #118                // Method java/lang/StringBuilder."<init>":()V
     118: ldc           #230                // String Cannot find suspended transaction to end
     120: invokevirtual #120                // Method java/lang/StringBuilder.append:(Ljava/lang/String;)Ljava/lang/StringBuilder;
     123: aload_1
     124: invokevirtual #122                // Method java/lang/StringBuilder.append:(Ljava/lang/Object;)Ljava/lang/StringBuilder;
     127: invokevirtual #125                // Method java/lang/StringBuilder.toString:()Ljava/lang/String;
     130: astore_3
     131: new           #210                // class org/apache/activemq/artemis/core/exception/ActiveMQXAException
     134: dup
     135: bipush        -4
     137: aload_3
     138: invokespecial #212                // Method org/apache/activemq/artemis/core/exception/ActiveMQXAException."<init>":(ILjava/lang/String;)V
     141: athrow
     142: aload_2
     143: invokeinterface #188,  1          // InterfaceMethod org/apache/activemq/artemis/core/transaction/Transaction.getState:()Lorg/apache/activemq/artemis/core/transaction/Transaction$State;
     148: getstatic     #223                // Field org/apache/activemq/artemis/core/transaction/Transaction$State.SUSPENDED:Lorg/apache/activemq/artemis/core/transaction/Transaction$State;
     151: if_acmpeq     185
     154: new           #117                // class java/lang/StringBuilder
     157: dup
     158: invokespecial #118                // Method java/lang/StringBuilder."<init>":()V
     161: ldc           #231                // String Transaction is not suspended
     163: invokevirtual #120                // Method java/lang/StringBuilder.append:(Ljava/lang/String;)Ljava/lang/StringBuilder;
     166: aload_1
     167: invokevirtual #122                // Method java/lang/StringBuilder.append:(Ljava/lang/Object;)Ljava/lang/StringBuilder;
     170: invokevirtual #125                // Method java/lang/StringBuilder.toString:()Ljava/lang/String;
     173: astore_3
     174: new           #210                // class org/apache/activemq/artemis/core/exception/ActiveMQXAException
     177: dup
     178: bipush        -6
     180: aload_3
     181: invokespecial #212                // Method org/apache/activemq/artemis/core/exception/ActiveMQXAException."<init>":(ILjava/lang/String;)V
     184: athrow
     185: aload_2
     186: invokeinterface #232,  1          // InterfaceMethod org/apache/activemq/artemis/core/transaction/Transaction.resume:()V
     191: return

  public synchronized void xaForget(javax.transaction.xa.Xid) throws java.lang.Exception;
    Code:
       0: aload_0
       1: getfield      #26                 // Field resourceManager:Lorg/apache/activemq/artemis/core/transaction/ResourceManager;
       4: aload_1
       5: invokeinterface #233,  2          // InterfaceMethod org/apache/activemq/artemis/core/transaction/ResourceManager.removeHeuristicCompletion:(Ljavax/transaction/xa/Xid;)J
      10: lstore_2
      11: lload_2
      12: ldc2_w        #168                // long -1l
      15: lcmp
      16: ifeq          49
      19: aload_0
      20: getfield      #24                 // Field storageManager:Lorg/apache/activemq/artemis/core/persistence/StorageManager;
      23: lload_2
      24: invokeinterface #234,  3          // InterfaceMethod org/apache/activemq/artemis/core/persistence/StorageManager.deleteHeuristicCompletion:(J)V
      29: goto          59
      32: astore        4
      34: aload         4
      36: invokevirtual #235                // Method java/lang/Exception.printStackTrace:()V
      39: new           #210                // class org/apache/activemq/artemis/core/exception/ActiveMQXAException
      42: dup
      43: bipush        -7
      45: invokespecial #236                // Method org/apache/activemq/artemis/core/exception/ActiveMQXAException."<init>":(I)V
      48: athrow
      49: new           #210                // class org/apache/activemq/artemis/core/exception/ActiveMQXAException
      52: dup
      53: bipush        -4
      55: invokespecial #236                // Method org/apache/activemq/artemis/core/exception/ActiveMQXAException."<init>":(I)V
      58: athrow
      59: return
    Exception table:
       from    to  target type
          19    29    32   Class java/lang/Exception

  public synchronized void xaJoin(javax.transaction.xa.Xid) throws java.lang.Exception;
    Code:
       0: aload_0
       1: getfield      #26                 // Field resourceManager:Lorg/apache/activemq/artemis/core/transaction/ResourceManager;
       4: aload_1
       5: invokeinterface #229,  2          // InterfaceMethod org/apache/activemq/artemis/core/transaction/ResourceManager.getTransaction:(Ljavax/transaction/xa/Xid;)Lorg/apache/activemq/artemis/core/transaction/Transaction;
      10: astore_2
      11: aload_2
      12: ifnonnull     46
      15: new           #117                // class java/lang/StringBuilder
      18: dup
      19: invokespecial #118                // Method java/lang/StringBuilder."<init>":()V
      22: ldc           #222                // String Cannot find xid in resource manager:
      24: invokevirtual #120                // Method java/lang/StringBuilder.append:(Ljava/lang/String;)Ljava/lang/StringBuilder;
      27: aload_1
      28: invokevirtual #122                // Method java/lang/StringBuilder.append:(Ljava/lang/Object;)Ljava/lang/StringBuilder;
      31: invokevirtual #125                // Method java/lang/StringBuilder.toString:()Ljava/lang/String;
      34: astore_3
      35: new           #210                // class org/apache/activemq/artemis/core/exception/ActiveMQXAException
      38: dup
      39: bipush        -4
      41: aload_3
      42: invokespecial #212                // Method org/apache/activemq/artemis/core/exception/ActiveMQXAException."<init>":(ILjava/lang/String;)V
      45: athrow
      46: aload_2
      47: invokeinterface #188,  1          // InterfaceMethod org/apache/activemq/artemis/core/transaction/Transaction.getState:()Lorg/apache/activemq/artemis/core/transaction/Transaction$State;
      52: getstatic     #223                // Field org/apache/activemq/artemis/core/transaction/Transaction$State.SUSPENDED:Lorg/apache/activemq/artemis/core/transaction/Transaction$State;
      55: if_acmpne     87
      58: new           #210                // class org/apache/activemq/artemis/core/exception/ActiveMQXAException
      61: dup
      62: bipush        -6
      64: new           #117                // class java/lang/StringBuilder
      67: dup
      68: invokespecial #118                // Method java/lang/StringBuilder."<init>":()V
      71: ldc           #237                // String Cannot join tx, it is suspended
      73: invokevirtual #120                // Method java/lang/StringBuilder.append:(Ljava/lang/String;)Ljava/lang/StringBuilder;
      76: aload_1
      77: invokevirtual #122                // Method java/lang/StringBuilder.append:(Ljava/lang/Object;)Ljava/lang/StringBuilder;
      80: invokevirtual #125                // Method java/lang/StringBuilder.toString:()Ljava/lang/String;
      83: invokespecial #212                // Method org/apache/activemq/artemis/core/exception/ActiveMQXAException."<init>":(ILjava/lang/String;)V
      86: athrow
      87: aload_0
      88: aload_2
      89: putfield      #45                 // Field tx:Lorg/apache/activemq/artemis/core/transaction/Transaction;
      92: return

  public synchronized void xaResume(javax.transaction.xa.Xid) throws java.lang.Exception;
    Code:
       0: aload_0
       1: getfield      #45                 // Field tx:Lorg/apache/activemq/artemis/core/transaction/Transaction;
       4: ifnull        46
       7: new           #117                // class java/lang/StringBuilder
      10: dup
      11: invokespecial #118                // Method java/lang/StringBuilder."<init>":()V
      14: ldc           #238                // String Cannot resume, session is currently doing work in a transaction
      16: invokevirtual #120                // Method java/lang/StringBuilder.append:(Ljava/lang/String;)Ljava/lang/StringBuilder;
      19: aload_0
      20: getfield      #45                 // Field tx:Lorg/apache/activemq/artemis/core/transaction/Transaction;
      23: invokeinterface #58,  1           // InterfaceMethod org/apache/activemq/artemis/core/transaction/Transaction.getXid:()Ljavax/transaction/xa/Xid;
      28: invokevirtual #122                // Method java/lang/StringBuilder.append:(Ljava/lang/Object;)Ljava/lang/StringBuilder;
      31: invokevirtual #125                // Method java/lang/StringBuilder.toString:()Ljava/lang/String;
      34: astore_2
      35: new           #210                // class org/apache/activemq/artemis/core/exception/ActiveMQXAException
      38: dup
      39: bipush        -6
      41: aload_2
      42: invokespecial #212                // Method org/apache/activemq/artemis/core/exception/ActiveMQXAException."<init>":(ILjava/lang/String;)V
      45: athrow
      46: aload_0
      47: getfield      #26                 // Field resourceManager:Lorg/apache/activemq/artemis/core/transaction/ResourceManager;
      50: aload_1
      51: invokeinterface #229,  2          // InterfaceMethod org/apache/activemq/artemis/core/transaction/ResourceManager.getTransaction:(Ljavax/transaction/xa/Xid;)Lorg/apache/activemq/artemis/core/transaction/Transaction;
      56: astore_2
      57: aload_2
      58: ifnonnull     92
      61: new           #117                // class java/lang/StringBuilder
      64: dup
      65: invokespecial #118                // Method java/lang/StringBuilder."<init>":()V
      68: ldc           #222                // String Cannot find xid in resource manager:
      70: invokevirtual #120                // Method java/lang/StringBuilder.append:(Ljava/lang/String;)Ljava/lang/StringBuilder;
      73: aload_1
      74: invokevirtual #122                // Method java/lang/StringBuilder.append:(Ljava/lang/Object;)Ljava/lang/StringBuilder;
      77: invokevirtual #125                // Method java/lang/StringBuilder.toString:()Ljava/lang/String;
      80: astore_3
      81: new           #210                // class org/apache/activemq/artemis/core/exception/ActiveMQXAException
      84: dup
      85: bipush        -4
      87: aload_3
      88: invokespecial #212                // Method org/apache/activemq/artemis/core/exception/ActiveMQXAException."<init>":(ILjava/lang/String;)V
      91: athrow
      92: aload_2
      93: invokeinterface #188,  1          // InterfaceMethod org/apache/activemq/artemis/core/transaction/Transaction.getState:()Lorg/apache/activemq/artemis/core/transaction/Transaction$State;
      98: getstatic     #223                // Field org/apache/activemq/artemis/core/transaction/Transaction$State.SUSPENDED:Lorg/apache/activemq/artemis/core/transaction/Transaction$State;
     101: if_acmpeq     133
     104: new           #210                // class org/apache/activemq/artemis/core/exception/ActiveMQXAException
     107: dup
     108: bipush        -6
     110: new           #117                // class java/lang/StringBuilder
     113: dup
     114: invokespecial #118                // Method java/lang/StringBuilder."<init>":()V
     117: ldc           #239                // String Cannot resume transaction, it is not suspended
     119: invokevirtual #120                // Method java/lang/StringBuilder.append:(Ljava/lang/String;)Ljava/lang/StringBuilder;
     122: aload_1
     123: invokevirtual #122                // Method java/lang/StringBuilder.append:(Ljava/lang/Object;)Ljava/lang/StringBuilder;
     126: invokevirtual #125                // Method java/lang/StringBuilder.toString:()Ljava/lang/String;
     129: invokespecial #212                // Method org/apache/activemq/artemis/core/exception/ActiveMQXAException."<init>":(ILjava/lang/String;)V
     132: athrow
     133: aload_0
     134: aload_2
     135: putfield      #45                 // Field tx:Lorg/apache/activemq/artemis/core/transaction/Transaction;
     138: aload_0
     139: getfield      #45                 // Field tx:Lorg/apache/activemq/artemis/core/transaction/Transaction;
     142: invokeinterface #232,  1          // InterfaceMethod org/apache/activemq/artemis/core/transaction/Transaction.resume:()V
     147: return

  public synchronized void xaRollback(javax.transaction.xa.Xid) throws java.lang.Exception;
    Code:
       0: aload_0
       1: getfield      #45                 // Field tx:Lorg/apache/activemq/artemis/core/transaction/Transaction;
       4: ifnull        62
       7: aload_0
       8: getfield      #45                 // Field tx:Lorg/apache/activemq/artemis/core/transaction/Transaction;
      11: invokeinterface #58,  1           // InterfaceMethod org/apache/activemq/artemis/core/transaction/Transaction.getXid:()Ljavax/transaction/xa/Xid;
      16: aload_1
      17: invokevirtual #208                // Method java/lang/Object.equals:(Ljava/lang/Object;)Z
      20: ifeq          62
      23: new           #117                // class java/lang/StringBuilder
      26: dup
      27: invokespecial #118                // Method java/lang/StringBuilder."<init>":()V
      30: ldc           #240                // String Cannot roll back, session is currently doing work in a transaction
      32: invokevirtual #120                // Method java/lang/StringBuilder.append:(Ljava/lang/String;)Ljava/lang/StringBuilder;
      35: aload_0
      36: getfield      #45                 // Field tx:Lorg/apache/activemq/artemis/core/transaction/Transaction;
      39: invokeinterface #58,  1           // InterfaceMethod org/apache/activemq/artemis/core/transaction/Transaction.getXid:()Ljavax/transaction/xa/Xid;
      44: invokevirtual #122                // Method java/lang/StringBuilder.append:(Ljava/lang/Object;)Ljava/lang/StringBuilder;
      47: invokevirtual #125                // Method java/lang/StringBuilder.toString:()Ljava/lang/String;
      50: astore_2
      51: new           #210                // class org/apache/activemq/artemis/core/exception/ActiveMQXAException
      54: dup
      55: bipush        -6
      57: aload_2
      58: invokespecial #212                // Method org/apache/activemq/artemis/core/exception/ActiveMQXAException."<init>":(ILjava/lang/String;)V
      61: athrow
      62: aload_0
      63: getfield      #26                 // Field resourceManager:Lorg/apache/activemq/artemis/core/transaction/ResourceManager;
      66: aload_1
      67: invokeinterface #213,  2          // InterfaceMethod org/apache/activemq/artemis/core/transaction/ResourceManager.removeTransaction:(Ljavax/transaction/xa/Xid;)Lorg/apache/activemq/artemis/core/transaction/Transaction;
      72: astore_2
      73: getstatic     #202                // Field isTrace:Z
      76: ifeq          106
      79: getstatic     #61                 // Field org/apache/activemq/artemis/core/server/ActiveMQServerLogger.LOGGER:Lorg/apache/activemq/artemis/core/server/ActiveMQServerLogger;
      82: new           #117                // class java/lang/StringBuilder
      85: dup
      86: invokespecial #118                // Method java/lang/StringBuilder."<init>":()V
      89: ldc           #241                // String xarollback into
      91: invokevirtual #120                // Method java/lang/StringBuilder.append:(Ljava/lang/String;)Ljava/lang/StringBuilder;
      94: aload_2
      95: invokevirtual #122                // Method java/lang/StringBuilder.append:(Ljava/lang/Object;)Ljava/lang/StringBuilder;
      98: invokevirtual #125                // Method java/lang/StringBuilder.toString:()Ljava/lang/String;
     101: invokeinterface #204,  2          // InterfaceMethod org/apache/activemq/artemis/core/server/ActiveMQServerLogger.trace:(Ljava/lang/Object;)V
     106: aload_2
     107: ifnonnull     302
     110: aload_0
     111: getfield      #26                 // Field resourceManager:Lorg/apache/activemq/artemis/core/transaction/ResourceManager;
     114: invokeinterface #216,  1          // InterfaceMethod org/apache/activemq/artemis/core/transaction/ResourceManager.getHeuristicCommittedTransactions:()Ljava/util/List;
     119: aload_1
     120: invokeinterface #217,  2          // InterfaceMethod java/util/List.contains:(Ljava/lang/Object;)Z
     125: ifeq          157
     128: new           #210                // class org/apache/activemq/artemis/core/exception/ActiveMQXAException
     131: dup
     132: bipush        7
     134: new           #117                // class java/lang/StringBuilder
     137: dup
     138: invokespecial #118                // Method java/lang/StringBuilder."<init>":()V
     141: ldc           #242                // String transaction has ben heuristically committed:
     143: invokevirtual #120                // Method java/lang/StringBuilder.append:(Ljava/lang/String;)Ljava/lang/StringBuilder;
     146: aload_1
     147: invokevirtual #122                // Method java/lang/StringBuilder.append:(Ljava/lang/Object;)Ljava/lang/StringBuilder;
     150: invokevirtual #125                // Method java/lang/StringBuilder.toString:()Ljava/lang/String;
     153: invokespecial #212                // Method org/apache/activemq/artemis/core/exception/ActiveMQXAException."<init>":(ILjava/lang/String;)V
     156: athrow
     157: aload_0
     158: getfield      #26                 // Field resourceManager:Lorg/apache/activemq/artemis/core/transaction/ResourceManager;
     161: invokeinterface #219,  1          // InterfaceMethod org/apache/activemq/artemis/core/transaction/ResourceManager.getHeuristicRolledbackTransactions:()Ljava/util/List;
     166: aload_1
     167: invokeinterface #217,  2          // InterfaceMethod java/util/List.contains:(Ljava/lang/Object;)Z
     172: ifeq          204
     175: new           #210                // class org/apache/activemq/artemis/core/exception/ActiveMQXAException
     178: dup
     179: bipush        6
     181: new           #117                // class java/lang/StringBuilder
     184: dup
     185: invokespecial #118                // Method java/lang/StringBuilder."<init>":()V
     188: ldc           #243                // String transaction has ben heuristically rolled back:
     190: invokevirtual #120                // Method java/lang/StringBuilder.append:(Ljava/lang/String;)Ljava/lang/StringBuilder;
     193: aload_1
     194: invokevirtual #122                // Method java/lang/StringBuilder.append:(Ljava/lang/Object;)Ljava/lang/StringBuilder;
     197: invokevirtual #125                // Method java/lang/StringBuilder.toString:()Ljava/lang/String;
     200: invokespecial #212                // Method org/apache/activemq/artemis/core/exception/ActiveMQXAException."<init>":(ILjava/lang/String;)V
     203: athrow
     204: getstatic     #202                // Field isTrace:Z
     207: ifeq          251
     210: getstatic     #61                 // Field org/apache/activemq/artemis/core/server/ActiveMQServerLogger.LOGGER:Lorg/apache/activemq/artemis/core/server/ActiveMQServerLogger;
     213: new           #117                // class java/lang/StringBuilder
     216: dup
     217: invokespecial #118                // Method java/lang/StringBuilder."<init>":()V
     220: ldc           #241                // String xarollback into
     222: invokevirtual #120                // Method java/lang/StringBuilder.append:(Ljava/lang/String;)Ljava/lang/StringBuilder;
     225: aload_2
     226: invokevirtual #122                // Method java/lang/StringBuilder.append:(Ljava/lang/Object;)Ljava/lang/StringBuilder;
     229: ldc           #215                // String , xid=
     231: invokevirtual #120                // Method java/lang/StringBuilder.append:(Ljava/lang/String;)Ljava/lang/StringBuilder;
     234: aload_1
     235: invokevirtual #122                // Method java/lang/StringBuilder.append:(Ljava/lang/Object;)Ljava/lang/StringBuilder;
     238: ldc           #244                // String  forcing a rollback regular
     240: invokevirtual #120                // Method java/lang/StringBuilder.append:(Ljava/lang/String;)Ljava/lang/StringBuilder;
     243: invokevirtual #125                // Method java/lang/StringBuilder.toString:()Ljava/lang/String;
     246: invokeinterface #204,  2          // InterfaceMethod org/apache/activemq/artemis/core/server/ActiveMQServerLogger.trace:(Ljava/lang/Object;)V
     251: aload_0
     252: iconst_0
     253: invokevirtual #245                // Method rollback:(Z)V
     256: goto          273
     259: astore_3
     260: getstatic     #61                 // Field org/apache/activemq/artemis/core/server/ActiveMQServerLogger.LOGGER:Lorg/apache/activemq/artemis/core/server/ActiveMQServerLogger;
     263: aload_3
     264: invokevirtual #62                 // Method java/lang/Exception.getMessage:()Ljava/lang/String;
     267: aload_3
     268: invokeinterface #63,  3           // InterfaceMethod org/apache/activemq/artemis/core/server/ActiveMQServerLogger.warn:(Ljava/lang/Object;Ljava/lang/Throwable;)V
     273: new           #210                // class org/apache/activemq/artemis/core/exception/ActiveMQXAException
     276: dup
     277: bipush        -4
     279: new           #117                // class java/lang/StringBuilder
     282: dup
     283: invokespecial #118                // Method java/lang/StringBuilder."<init>":()V
     286: ldc           #222                // String Cannot find xid in resource manager:
     288: invokevirtual #120                // Method java/lang/StringBuilder.append:(Ljava/lang/String;)Ljava/lang/StringBuilder;
     291: aload_1
     292: invokevirtual #122                // Method java/lang/StringBuilder.append:(Ljava/lang/Object;)Ljava/lang/StringBuilder;
     295: invokevirtual #125                // Method java/lang/StringBuilder.toString:()Ljava/lang/String;
     298: invokespecial #212                // Method org/apache/activemq/artemis/core/exception/ActiveMQXAException."<init>":(ILjava/lang/String;)V
     301: athrow
     302: aload_2
     303: invokeinterface #188,  1          // InterfaceMethod org/apache/activemq/artemis/core/transaction/Transaction.getState:()Lorg/apache/activemq/artemis/core/transaction/Transaction$State;
     308: getstatic     #223                // Field org/apache/activemq/artemis/core/transaction/Transaction$State.SUSPENDED:Lorg/apache/activemq/artemis/core/transaction/Transaction$State;
     311: if_acmpne     396
     314: getstatic     #202                // Field isTrace:Z
     317: ifeq          352
     320: getstatic     #61                 // Field org/apache/activemq/artemis/core/server/ActiveMQServerLogger.LOGGER:Lorg/apache/activemq/artemis/core/server/ActiveMQServerLogger;
     323: new           #117                // class java/lang/StringBuilder
     326: dup
     327: invokespecial #118                // Method java/lang/StringBuilder."<init>":()V
     330: ldc           #241                // String xarollback into
     332: invokevirtual #120                // Method java/lang/StringBuilder.append:(Ljava/lang/String;)Ljava/lang/StringBuilder;
     335: aload_2
     336: invokevirtual #122                // Method java/lang/StringBuilder.append:(Ljava/lang/Object;)Ljava/lang/StringBuilder;
     339: ldc           #246                // String  sending tx back as it was suspended
     341: invokevirtual #120                // Method java/lang/StringBuilder.append:(Ljava/lang/String;)Ljava/lang/StringBuilder;
     344: invokevirtual #125                // Method java/lang/StringBuilder.toString:()Ljava/lang/String;
     347: invokeinterface #204,  2          // InterfaceMethod org/apache/activemq/artemis/core/server/ActiveMQServerLogger.trace:(Ljava/lang/Object;)V
     352: aload_0
     353: getfield      #26                 // Field resourceManager:Lorg/apache/activemq/artemis/core/transaction/ResourceManager;
     356: aload_1
     357: aload_0
     358: getfield      #45                 // Field tx:Lorg/apache/activemq/artemis/core/transaction/Transaction;
     361: invokeinterface #224,  3          // InterfaceMethod org/apache/activemq/artemis/core/transaction/ResourceManager.putTransaction:(Ljavax/transaction/xa/Xid;Lorg/apache/activemq/artemis/core/transaction/Transaction;)Z
     366: pop
     367: new           #210                // class org/apache/activemq/artemis/core/exception/ActiveMQXAException
     370: dup
     371: bipush        -6
     373: new           #117                // class java/lang/StringBuilder
     376: dup
     377: invokespecial #118                // Method java/lang/StringBuilder."<init>":()V
     380: ldc           #247                // String Cannot rollback transaction, it is suspended
     382: invokevirtual #120                // Method java/lang/StringBuilder.append:(Ljava/lang/String;)Ljava/lang/StringBuilder;
     385: aload_1
     386: invokevirtual #122                // Method java/lang/StringBuilder.append:(Ljava/lang/Object;)Ljava/lang/StringBuilder;
     389: invokevirtual #125                // Method java/lang/StringBuilder.toString:()Ljava/lang/String;
     392: invokespecial #212                // Method org/apache/activemq/artemis/core/exception/ActiveMQXAException."<init>":(ILjava/lang/String;)V
     395: athrow
     396: aload_0
     397: iconst_0
     398: iconst_0
     399: aload_2
     400: invokespecial #206                // Method doRollback:(ZZLorg/apache/activemq/artemis/core/transaction/Transaction;)V
     403: return
    Exception table:
       from    to  target type
         251   256   259   Class java/lang/Exception

  public synchronized void xaStart(javax.transaction.xa.Xid) throws java.lang.Exception;
    Code:
       0: aload_0
       1: getfield      #45                 // Field tx:Lorg/apache/activemq/artemis/core/transaction/Transaction;
       4: ifnull        101
       7: getstatic     #61                 // Field org/apache/activemq/artemis/core/server/ActiveMQServerLogger.LOGGER:Lorg/apache/activemq/artemis/core/server/ActiveMQServerLogger;
      10: aload_0
      11: getfield      #45                 // Field tx:Lorg/apache/activemq/artemis/core/transaction/Transaction;
      14: invokeinterface #58,  1           // InterfaceMethod org/apache/activemq/artemis/core/transaction/Transaction.getXid:()Ljavax/transaction/xa/Xid;
      19: invokevirtual #248                // Method java/lang/Object.toString:()Ljava/lang/String;
      22: aload_1
      23: invokevirtual #248                // Method java/lang/Object.toString:()Ljava/lang/String;
      26: invokeinterface #249,  3          // InterfaceMethod org/apache/activemq/artemis/core/server/ActiveMQServerLogger.xidReplacedOnXStart:(Ljava/lang/String;Ljava/lang/String;)V
      31: aload_0
      32: getfield      #45                 // Field tx:Lorg/apache/activemq/artemis/core/transaction/Transaction;
      35: invokeinterface #188,  1          // InterfaceMethod org/apache/activemq/artemis/core/transaction/Transaction.getState:()Lorg/apache/activemq/artemis/core/transaction/Transaction$State;
      40: getstatic     #250                // Field org/apache/activemq/artemis/core/transaction/Transaction$State.PREPARED:Lorg/apache/activemq/artemis/core/transaction/Transaction$State;
      43: if_acmpeq     86
      46: aload_0
      47: getfield      #45                 // Field tx:Lorg/apache/activemq/artemis/core/transaction/Transaction;
      50: invokeinterface #58,  1           // InterfaceMethod org/apache/activemq/artemis/core/transaction/Transaction.getXid:()Ljavax/transaction/xa/Xid;
      55: ifnull        77
      58: aload_0
      59: getfield      #26                 // Field resourceManager:Lorg/apache/activemq/artemis/core/transaction/ResourceManager;
      62: aload_0
      63: getfield      #45                 // Field tx:Lorg/apache/activemq/artemis/core/transaction/Transaction;
      66: invokeinterface #58,  1           // InterfaceMethod org/apache/activemq/artemis/core/transaction/Transaction.getXid:()Ljavax/transaction/xa/Xid;
      71: invokeinterface #213,  2          // InterfaceMethod org/apache/activemq/artemis/core/transaction/ResourceManager.removeTransaction:(Ljavax/transaction/xa/Xid;)Lorg/apache/activemq/artemis/core/transaction/Transaction;
      76: pop
      77: aload_0
      78: getfield      #45                 // Field tx:Lorg/apache/activemq/artemis/core/transaction/Transaction;
      81: invokeinterface #195,  1          // InterfaceMethod org/apache/activemq/artemis/core/transaction/Transaction.rollback:()V
      86: goto          101
      89: astore_2
      90: getstatic     #61                 // Field org/apache/activemq/artemis/core/server/ActiveMQServerLogger.LOGGER:Lorg/apache/activemq/artemis/core/server/ActiveMQServerLogger;
      93: ldc           #251                // String An exception happened while we tried to debug the previous tx, we can ignore this exception
      95: aload_2
      96: invokeinterface #194,  3          // InterfaceMethod org/apache/activemq/artemis/core/server/ActiveMQServerLogger.debug:(Ljava/lang/Object;Ljava/lang/Throwable;)V
     101: aload_0
     102: aload_0
     103: aload_1
     104: invokespecial #252                // Method newTransaction:(Ljavax/transaction/xa/Xid;)Lorg/apache/activemq/artemis/core/transaction/Transaction;
     107: putfield      #45                 // Field tx:Lorg/apache/activemq/artemis/core/transaction/Transaction;
     110: getstatic     #202                // Field isTrace:Z
     113: ifeq          146
     116: getstatic     #61                 // Field org/apache/activemq/artemis/core/server/ActiveMQServerLogger.LOGGER:Lorg/apache/activemq/artemis/core/server/ActiveMQServerLogger;
     119: new           #117                // class java/lang/StringBuilder
     122: dup
     123: invokespecial #118                // Method java/lang/StringBuilder."<init>":()V
     126: ldc           #253                // String xastart into tx=
     128: invokevirtual #120                // Method java/lang/StringBuilder.append:(Ljava/lang/String;)Ljava/lang/StringBuilder;
     131: aload_0
     132: getfield      #45                 // Field tx:Lorg/apache/activemq/artemis/core/transaction/Transaction;
     135: invokevirtual #122                // Method java/lang/StringBuilder.append:(Ljava/lang/Object;)Ljava/lang/StringBuilder;
     138: invokevirtual #125                // Method java/lang/StringBuilder.toString:()Ljava/lang/String;
     141: invokeinterface #204,  2          // InterfaceMethod org/apache/activemq/artemis/core/server/ActiveMQServerLogger.trace:(Ljava/lang/Object;)V
     146: aload_0
     147: getfield      #26                 // Field resourceManager:Lorg/apache/activemq/artemis/core/transaction/ResourceManager;
     150: aload_1
     151: aload_0
     152: getfield      #45                 // Field tx:Lorg/apache/activemq/artemis/core/transaction/Transaction;
     155: invokeinterface #224,  3          // InterfaceMethod org/apache/activemq/artemis/core/transaction/ResourceManager.putTransaction:(Ljavax/transaction/xa/Xid;Lorg/apache/activemq/artemis/core/transaction/Transaction;)Z
     160: istore_2
     161: iload_2
     162: ifne          204
     165: new           #117                // class java/lang/StringBuilder
     168: dup
     169: invokespecial #118                // Method java/lang/StringBuilder."<init>":()V
     172: ldc           #254                // String Cannot start, there is already a xid
     174: invokevirtual #120                // Method java/lang/StringBuilder.append:(Ljava/lang/String;)Ljava/lang/StringBuilder;
     177: aload_0
     178: getfield      #45                 // Field tx:Lorg/apache/activemq/artemis/core/transaction/Transaction;
     181: invokeinterface #58,  1           // InterfaceMethod org/apache/activemq/artemis/core/transaction/Transaction.getXid:()Ljavax/transaction/xa/Xid;
     186: invokevirtual #122                // Method java/lang/StringBuilder.append:(Ljava/lang/Object;)Ljava/lang/StringBuilder;
     189: invokevirtual #125                // Method java/lang/StringBuilder.toString:()Ljava/lang/String;
     192: astore_3
     193: new           #210                // class org/apache/activemq/artemis/core/exception/ActiveMQXAException
     196: dup
     197: bipush        -8
     199: aload_3
     200: invokespecial #212                // Method org/apache/activemq/artemis/core/exception/ActiveMQXAException."<init>":(ILjava/lang/String;)V
     203: athrow
     204: return
    Exception table:
       from    to  target type
          31    86    89   Class java/lang/Exception

  public synchronized void xaFailed(javax.transaction.xa.Xid) throws java.lang.Exception;
    Code:
       0: aload_0
       1: getfield      #26                 // Field resourceManager:Lorg/apache/activemq/artemis/core/transaction/ResourceManager;
       4: aload_1
       5: invokeinterface #229,  2          // InterfaceMethod org/apache/activemq/artemis/core/transaction/ResourceManager.getTransaction:(Ljavax/transaction/xa/Xid;)Lorg/apache/activemq/artemis/core/transaction/Transaction;
      10: astore_2
      11: aload_2
      12: ifnonnull     33
      15: aload_0
      16: aload_1
      17: invokespecial #252                // Method newTransaction:(Ljavax/transaction/xa/Xid;)Lorg/apache/activemq/artemis/core/transaction/Transaction;
      20: astore_2
      21: aload_0
      22: getfield      #26                 // Field resourceManager:Lorg/apache/activemq/artemis/core/transaction/ResourceManager;
      25: aload_1
      26: aload_2
      27: invokeinterface #224,  3          // InterfaceMethod org/apache/activemq/artemis/core/transaction/ResourceManager.putTransaction:(Ljavax/transaction/xa/Xid;Lorg/apache/activemq/artemis/core/transaction/Transaction;)Z
      32: pop
      33: aload_2
      34: invokeinterface #255,  1          // InterfaceMethod org/apache/activemq/artemis/core/transaction/Transaction.isEffective:()Z
      39: ifeq          93
      42: getstatic     #61                 // Field org/apache/activemq/artemis/core/server/ActiveMQServerLogger.LOGGER:Lorg/apache/activemq/artemis/core/server/ActiveMQServerLogger;
      45: new           #117                // class java/lang/StringBuilder
      48: dup
      49: invokespecial #118                // Method java/lang/StringBuilder."<init>":()V
      52: ldc_w         #256                // String Client failed with Xid
      55: invokevirtual #120                // Method java/lang/StringBuilder.append:(Ljava/lang/String;)Ljava/lang/StringBuilder;
      58: aload_1
      59: invokevirtual #122                // Method java/lang/StringBuilder.append:(Ljava/lang/Object;)Ljava/lang/StringBuilder;
      62: ldc_w         #257                // String  but the server already had it
      65: invokevirtual #120                // Method java/lang/StringBuilder.append:(Ljava/lang/String;)Ljava/lang/StringBuilder;
      68: aload_2
      69: invokeinterface #188,  1          // InterfaceMethod org/apache/activemq/artemis/core/transaction/Transaction.getState:()Lorg/apache/activemq/artemis/core/transaction/Transaction$State;
      74: invokevirtual #122                // Method java/lang/StringBuilder.append:(Ljava/lang/Object;)Ljava/lang/StringBuilder;
      77: invokevirtual #125                // Method java/lang/StringBuilder.toString:()Ljava/lang/String;
      80: invokeinterface #126,  2          // InterfaceMethod org/apache/activemq/artemis/core/server/ActiveMQServerLogger.debug:(Ljava/lang/Object;)V
      85: aload_0
      86: aconst_null
      87: putfield      #45                 // Field tx:Lorg/apache/activemq/artemis/core/transaction/Transaction;
      90: goto          114
      93: aload_2
      94: new           #51                 // class org/apache/activemq/artemis/api/core/ActiveMQException
      97: dup
      98: ldc_w         #258                // String Can\'t commit as a Failover happened during the operation
     101: invokespecial #54                 // Method org/apache/activemq/artemis/api/core/ActiveMQException."<init>":(Ljava/lang/String;)V
     104: invokeinterface #52,  2           // InterfaceMethod org/apache/activemq/artemis/core/transaction/Transaction.markAsRollbackOnly:(Lorg/apache/activemq/artemis/api/core/ActiveMQException;)V
     109: aload_0
     110: aload_2
     111: putfield      #45                 // Field tx:Lorg/apache/activemq/artemis/core/transaction/Transaction;
     114: getstatic     #202                // Field isTrace:Z
     117: ifeq          150
     120: getstatic     #61                 // Field org/apache/activemq/artemis/core/server/ActiveMQServerLogger.LOGGER:Lorg/apache/activemq/artemis/core/server/ActiveMQServerLogger;
     123: new           #117                // class java/lang/StringBuilder
     126: dup
     127: invokespecial #118                // Method java/lang/StringBuilder."<init>":()V
     130: ldc           #253                // String xastart into tx=
     132: invokevirtual #120                // Method java/lang/StringBuilder.append:(Ljava/lang/String;)Ljava/lang/StringBuilder;
     135: aload_0
     136: getfield      #45                 // Field tx:Lorg/apache/activemq/artemis/core/transaction/Transaction;
     139: invokevirtual #122                // Method java/lang/StringBuilder.append:(Ljava/lang/Object;)Ljava/lang/StringBuilder;
     142: invokevirtual #125                // Method java/lang/StringBuilder.toString:()Ljava/lang/String;
     145: invokeinterface #204,  2          // InterfaceMethod org/apache/activemq/artemis/core/server/ActiveMQServerLogger.trace:(Ljava/lang/Object;)V
     150: return

  public synchronized void xaSuspend() throws java.lang.Exception;
    Code:
       0: getstatic     #202                // Field isTrace:Z
       3: ifeq          37
       6: getstatic     #61                 // Field org/apache/activemq/artemis/core/server/ActiveMQServerLogger.LOGGER:Lorg/apache/activemq/artemis/core/server/ActiveMQServerLogger;
       9: new           #117                // class java/lang/StringBuilder
      12: dup
      13: invokespecial #118                // Method java/lang/StringBuilder."<init>":()V
      16: ldc_w         #259                // String xasuspend on
      19: invokevirtual #120                // Method java/lang/StringBuilder.append:(Ljava/lang/String;)Ljava/lang/StringBuilder;
      22: aload_0
      23: getfield      #45                 // Field tx:Lorg/apache/activemq/artemis/core/transaction/Transaction;
      26: invokevirtual #122                // Method java/lang/StringBuilder.append:(Ljava/lang/Object;)Ljava/lang/StringBuilder;
      29: invokevirtual #125                // Method java/lang/StringBuilder.toString:()Ljava/lang/String;
      32: invokeinterface #204,  2          // InterfaceMethod org/apache/activemq/artemis/core/server/ActiveMQServerLogger.trace:(Ljava/lang/Object;)V
      37: aload_0
      38: getfield      #45                 // Field tx:Lorg/apache/activemq/artemis/core/transaction/Transaction;
      41: ifnonnull     61
      44: ldc_w         #260                // String Cannot suspend, session is not doing work in a transaction
      47: astore_1
      48: new           #210                // class org/apache/activemq/artemis/core/exception/ActiveMQXAException
      51: dup
      52: bipush        -6
      54: ldc_w         #260                // String Cannot suspend, session is not doing work in a transaction
      57: invokespecial #212                // Method org/apache/activemq/artemis/core/exception/ActiveMQXAException."<init>":(ILjava/lang/String;)V
      60: athrow
      61: aload_0
      62: getfield      #45                 // Field tx:Lorg/apache/activemq/artemis/core/transaction/Transaction;
      65: invokeinterface #188,  1          // InterfaceMethod org/apache/activemq/artemis/core/transaction/Transaction.getState:()Lorg/apache/activemq/artemis/core/transaction/Transaction$State;
      70: getstatic     #223                // Field org/apache/activemq/artemis/core/transaction/Transaction$State.SUSPENDED:Lorg/apache/activemq/artemis/core/transaction/Transaction$State;
      73: if_acmpne     116
      76: new           #117                // class java/lang/StringBuilder
      79: dup
      80: invokespecial #118                // Method java/lang/StringBuilder."<init>":()V
      83: ldc_w         #261                // String Cannot suspend, transaction is already suspended
      86: invokevirtual #120                // Method java/lang/StringBuilder.append:(Ljava/lang/String;)Ljava/lang/StringBuilder;
      89: aload_0
      90: getfield      #45                 // Field tx:Lorg/apache/activemq/artemis/core/transaction/Transaction;
      93: invokeinterface #58,  1           // InterfaceMethod org/apache/activemq/artemis/core/transaction/Transaction.getXid:()Ljavax/transaction/xa/Xid;
      98: invokevirtual #122                // Method java/lang/StringBuilder.append:(Ljava/lang/Object;)Ljava/lang/StringBuilder;
     101: invokevirtual #125                // Method java/lang/StringBuilder.toString:()Ljava/lang/String;
     104: astore_1
     105: new           #210                // class org/apache/activemq/artemis/core/exception/ActiveMQXAException
     108: dup
     109: bipush        -6
     111: aload_1
     112: invokespecial #212                // Method org/apache/activemq/artemis/core/exception/ActiveMQXAException."<init>":(ILjava/lang/String;)V
     115: athrow
     116: aload_0
     117: getfield      #45                 // Field tx:Lorg/apache/activemq/artemis/core/transaction/Transaction;
     120: invokeinterface #262,  1          // InterfaceMethod org/apache/activemq/artemis/core/transaction/Transaction.suspend:()V
     125: aload_0
     126: aconst_null
     127: putfield      #45                 // Field tx:Lorg/apache/activemq/artemis/core/transaction/Transaction;
     130: return

  public synchronized void xaPrepare(javax.transaction.xa.Xid) throws java.lang.Exception;
    Code:
       0: aload_0
       1: getfield      #45                 // Field tx:Lorg/apache/activemq/artemis/core/transaction/Transaction;
       4: ifnull        63
       7: aload_0
       8: getfield      #45                 // Field tx:Lorg/apache/activemq/artemis/core/transaction/Transaction;
      11: invokeinterface #58,  1           // InterfaceMethod org/apache/activemq/artemis/core/transaction/Transaction.getXid:()Ljavax/transaction/xa/Xid;
      16: aload_1
      17: invokevirtual #208                // Method java/lang/Object.equals:(Ljava/lang/Object;)Z
      20: ifeq          63
      23: new           #117                // class java/lang/StringBuilder
      26: dup
      27: invokespecial #118                // Method java/lang/StringBuilder."<init>":()V
      30: ldc_w         #263                // String Cannot commit, session is currently doing work in a transaction
      33: invokevirtual #120                // Method java/lang/StringBuilder.append:(Ljava/lang/String;)Ljava/lang/StringBuilder;
      36: aload_0
      37: getfield      #45                 // Field tx:Lorg/apache/activemq/artemis/core/transaction/Transaction;
      40: invokeinterface #58,  1           // InterfaceMethod org/apache/activemq/artemis/core/transaction/Transaction.getXid:()Ljavax/transaction/xa/Xid;
      45: invokevirtual #122                // Method java/lang/StringBuilder.append:(Ljava/lang/Object;)Ljava/lang/StringBuilder;
      48: invokevirtual #125                // Method java/lang/StringBuilder.toString:()Ljava/lang/String;
      51: astore_2
      52: new           #210                // class org/apache/activemq/artemis/core/exception/ActiveMQXAException
      55: dup
      56: bipush        -6
      58: aload_2
      59: invokespecial #212                // Method org/apache/activemq/artemis/core/exception/ActiveMQXAException."<init>":(ILjava/lang/String;)V
      62: athrow
      63: aload_0
      64: getfield      #26                 // Field resourceManager:Lorg/apache/activemq/artemis/core/transaction/ResourceManager;
      67: aload_1
      68: invokeinterface #229,  2          // InterfaceMethod org/apache/activemq/artemis/core/transaction/ResourceManager.getTransaction:(Ljavax/transaction/xa/Xid;)Lorg/apache/activemq/artemis/core/transaction/Transaction;
      73: astore_2
      74: getstatic     #202                // Field isTrace:Z
      77: ifeq          121
      80: getstatic     #61                 // Field org/apache/activemq/artemis/core/server/ActiveMQServerLogger.LOGGER:Lorg/apache/activemq/artemis/core/server/ActiveMQServerLogger;
      83: new           #117                // class java/lang/StringBuilder
      86: dup
      87: invokespecial #118                // Method java/lang/StringBuilder."<init>":()V
      90: ldc_w         #264                // String xaprepare into , xid=
      93: invokevirtual #120                // Method java/lang/StringBuilder.append:(Ljava/lang/String;)Ljava/lang/StringBuilder;
      96: aload_1
      97: invokevirtual #122                // Method java/lang/StringBuilder.append:(Ljava/lang/Object;)Ljava/lang/StringBuilder;
     100: ldc_w         #265                // String , tx=
     103: invokevirtual #120                // Method java/lang/StringBuilder.append:(Ljava/lang/String;)Ljava/lang/StringBuilder;
     106: aload_0
     107: getfield      #45                 // Field tx:Lorg/apache/activemq/artemis/core/transaction/Transaction;
     110: invokevirtual #122                // Method java/lang/StringBuilder.append:(Ljava/lang/Object;)Ljava/lang/StringBuilder;
     113: invokevirtual #125                // Method java/lang/StringBuilder.toString:()Ljava/lang/String;
     116: invokeinterface #204,  2          // InterfaceMethod org/apache/activemq/artemis/core/server/ActiveMQServerLogger.trace:(Ljava/lang/Object;)V
     121: aload_2
     122: ifnonnull     156
     125: new           #117                // class java/lang/StringBuilder
     128: dup
     129: invokespecial #118                // Method java/lang/StringBuilder."<init>":()V
     132: ldc           #222                // String Cannot find xid in resource manager:
     134: invokevirtual #120                // Method java/lang/StringBuilder.append:(Ljava/lang/String;)Ljava/lang/StringBuilder;
     137: aload_1
     138: invokevirtual #122                // Method java/lang/StringBuilder.append:(Ljava/lang/Object;)Ljava/lang/StringBuilder;
     141: invokevirtual #125                // Method java/lang/StringBuilder.toString:()Ljava/lang/String;
     144: astore_3
     145: new           #210                // class org/apache/activemq/artemis/core/exception/ActiveMQXAException
     148: dup
     149: bipush        -4
     151: aload_3
     152: invokespecial #212                // Method org/apache/activemq/artemis/core/exception/ActiveMQXAException."<init>":(ILjava/lang/String;)V
     155: athrow
     156: aload_2
     157: invokeinterface #188,  1          // InterfaceMethod org/apache/activemq/artemis/core/transaction/Transaction.getState:()Lorg/apache/activemq/artemis/core/transaction/Transaction$State;
     162: getstatic     #223                // Field org/apache/activemq/artemis/core/transaction/Transaction$State.SUSPENDED:Lorg/apache/activemq/artemis/core/transaction/Transaction$State;
     165: if_acmpne     198
     168: new           #210                // class org/apache/activemq/artemis/core/exception/ActiveMQXAException
     171: dup
     172: bipush        -6
     174: new           #117                // class java/lang/StringBuilder
     177: dup
     178: invokespecial #118                // Method java/lang/StringBuilder."<init>":()V
     181: ldc_w         #266                // String Cannot prepare transaction, it is suspended
     184: invokevirtual #120                // Method java/lang/StringBuilder.append:(Ljava/lang/String;)Ljava/lang/StringBuilder;
     187: aload_1
     188: invokevirtual #122                // Method java/lang/StringBuilder.append:(Ljava/lang/Object;)Ljava/lang/StringBuilder;
     191: invokevirtual #125                // Method java/lang/StringBuilder.toString:()Ljava/lang/String;
     194: invokespecial #212                // Method org/apache/activemq/artemis/core/exception/ActiveMQXAException."<init>":(ILjava/lang/String;)V
     197: athrow
     198: aload_2
     199: invokeinterface #188,  1          // InterfaceMethod org/apache/activemq/artemis/core/transaction/Transaction.getState:()Lorg/apache/activemq/artemis/core/transaction/Transaction$State;
     204: getstatic     #250                // Field org/apache/activemq/artemis/core/transaction/Transaction$State.PREPARED:Lorg/apache/activemq/artemis/core/transaction/Transaction$State;
     207: if_acmpne     241
     210: getstatic     #61                 // Field org/apache/activemq/artemis/core/server/ActiveMQServerLogger.LOGGER:Lorg/apache/activemq/artemis/core/server/ActiveMQServerLogger;
     213: new           #117                // class java/lang/StringBuilder
     216: dup
     217: invokespecial #118                // Method java/lang/StringBuilder."<init>":()V
     220: ldc_w         #267                // String ignoring prepare on xid as already called :
     223: invokevirtual #120                // Method java/lang/StringBuilder.append:(Ljava/lang/String;)Ljava/lang/StringBuilder;
     226: aload_1
     227: invokevirtual #122                // Method java/lang/StringBuilder.append:(Ljava/lang/Object;)Ljava/lang/StringBuilder;
     230: invokevirtual #125                // Method java/lang/StringBuilder.toString:()Ljava/lang/String;
     233: invokeinterface #268,  2          // InterfaceMethod org/apache/activemq/artemis/core/server/ActiveMQServerLogger.info:(Ljava/lang/Object;)V
     238: goto          247
     241: aload_2
     242: invokeinterface #269,  1          // InterfaceMethod org/apache/activemq/artemis/core/transaction/Transaction.prepare:()V
     247: return

  public java.util.List<javax.transaction.xa.Xid> xaGetInDoubtXids();
    Code:
       0: new           #172                // class java/util/ArrayList
       3: dup
       4: invokespecial #173                // Method java/util/ArrayList."<init>":()V
       7: astore_1
       8: aload_1
       9: aload_0
      10: getfield      #26                 // Field resourceManager:Lorg/apache/activemq/artemis/core/transaction/ResourceManager;
      13: invokeinterface #270,  1          // InterfaceMethod org/apache/activemq/artemis/core/transaction/ResourceManager.getPreparedTransactions:()Ljava/util/List;
      18: invokeinterface #271,  2          // InterfaceMethod java/util/List.addAll:(Ljava/util/Collection;)Z
      23: pop
      24: aload_1
      25: aload_0
      26: getfield      #26                 // Field resourceManager:Lorg/apache/activemq/artemis/core/transaction/ResourceManager;
      29: invokeinterface #216,  1          // InterfaceMethod org/apache/activemq/artemis/core/transaction/ResourceManager.getHeuristicCommittedTransactions:()Ljava/util/List;
      34: invokeinterface #271,  2          // InterfaceMethod java/util/List.addAll:(Ljava/util/Collection;)Z
      39: pop
      40: aload_1
      41: aload_0
      42: getfield      #26                 // Field resourceManager:Lorg/apache/activemq/artemis/core/transaction/ResourceManager;
      45: invokeinterface #219,  1          // InterfaceMethod org/apache/activemq/artemis/core/transaction/ResourceManager.getHeuristicRolledbackTransactions:()Ljava/util/List;
      50: invokeinterface #271,  2          // InterfaceMethod java/util/List.addAll:(Ljava/util/Collection;)Z
      55: pop
      56: aload_1
      57: areturn

  public int xaGetTimeout();
    Code:
       0: aload_0
       1: getfield      #26                 // Field resourceManager:Lorg/apache/activemq/artemis/core/transaction/ResourceManager;
       4: invokeinterface #28,  1           // InterfaceMethod org/apache/activemq/artemis/core/transaction/ResourceManager.getTimeoutSeconds:()I
       9: ireturn

  public void xaSetTimeout(int);
    Code:
       0: aload_0
       1: iload_1
       2: putfield      #29                 // Field timeoutSeconds:I
       5: aload_0
       6: getfield      #45                 // Field tx:Lorg/apache/activemq/artemis/core/transaction/Transaction;
       9: ifnull        22
      12: aload_0
      13: getfield      #45                 // Field tx:Lorg/apache/activemq/artemis/core/transaction/Transaction;
      16: iload_1
      17: invokeinterface #272,  2          // InterfaceMethod org/apache/activemq/artemis/core/transaction/Transaction.setTimeout:(I)V
      22: return

  public void start();
    Code:
       0: aload_0
       1: iconst_1
       2: invokespecial #273                // Method setStarted:(Z)V
       5: return

  public void stop();
    Code:
       0: aload_0
       1: iconst_0
       2: invokespecial #273                // Method setStarted:(Z)V
       5: return

  public void waitContextCompletion();
    Code:
       0: aload_0
       1: getfield      #39                 // Field context:Lorg/apache/activemq/artemis/core/persistence/OperationContext;
       4: ldc2_w        #274                // long 10000l
       7: invokeinterface #276,  3          // InterfaceMethod org/apache/activemq/artemis/core/persistence/OperationContext.waitCompletion:(J)Z
      12: ifne          33
      15: getstatic     #61                 // Field org/apache/activemq/artemis/core/server/ActiveMQServerLogger.LOGGER:Lorg/apache/activemq/artemis/core/server/ActiveMQServerLogger;
      18: new           #60                 // class java/lang/Exception
      21: dup
      22: ldc_w         #277                // String warning
      25: invokespecial #278                // Method java/lang/Exception."<init>":(Ljava/lang/String;)V
      28: invokeinterface #279,  2          // InterfaceMethod org/apache/activemq/artemis/core/server/ActiveMQServerLogger.errorCompletingContext:(Ljava/lang/Exception;)V
      33: goto          50
      36: astore_1
      37: getstatic     #61                 // Field org/apache/activemq/artemis/core/server/ActiveMQServerLogger.LOGGER:Lorg/apache/activemq/artemis/core/server/ActiveMQServerLogger;
      40: aload_1
      41: invokevirtual #62                 // Method java/lang/Exception.getMessage:()Ljava/lang/String;
      44: aload_1
      45: invokeinterface #63,  3           // InterfaceMethod org/apache/activemq/artemis/core/server/ActiveMQServerLogger.warn:(Ljava/lang/Object;Ljava/lang/Throwable;)V
      50: return
    Exception table:
       from    to  target type
           0    33    36   Class java/lang/Exception

  public void close(boolean);
    Code:
       0: aload_0
       1: getfield      #16                 // Field closed:Z
       4: ifeq          8
       7: return
       8: aload_0
       9: getfield      #39                 // Field context:Lorg/apache/activemq/artemis/core/persistence/OperationContext;
      12: new           #280                // class org/apache/activemq/artemis/core/server/impl/ServerSessionImpl$1
      15: dup
      16: aload_0
      17: iload_1
      18: invokespecial #281                // Method org/apache/activemq/artemis/core/server/impl/ServerSessionImpl$1."<init>":(Lorg/apache/activemq/artemis/core/server/impl/ServerSessionImpl;Z)V
      21: invokeinterface #282,  2          // InterfaceMethod org/apache/activemq/artemis/core/persistence/OperationContext.executeOnCompletion:(Lorg/apache/activemq/artemis/core/io/IOCallback;)V
      26: return

  public void closeConsumer(long) throws java.lang.Exception;
    Code:
       0: aload_0
       1: getfield      #5                  // Field consumers:Ljava/util/Map;
       4: lload_1
       5: invokestatic  #56                 // Method java/lang/Long.valueOf:(J)Ljava/lang/Long;
       8: invokeinterface #184,  2          // InterfaceMethod java/util/Map.get:(Ljava/lang/Object;)Ljava/lang/Object;
      13: checkcast     #67                 // class org/apache/activemq/artemis/core/server/ServerConsumer
      16: astore_3
      17: aload_3
      18: ifnull        31
      21: aload_3
      22: iconst_0
      23: invokeinterface #68,  2           // InterfaceMethod org/apache/activemq/artemis/core/server/ServerConsumer.close:(Z)V
      28: goto          40
      31: getstatic     #61                 // Field org/apache/activemq/artemis/core/server/ActiveMQServerLogger.LOGGER:Lorg/apache/activemq/artemis/core/server/ActiveMQServerLogger;
      34: lload_1
      35: invokeinterface #283,  3          // InterfaceMethod org/apache/activemq/artemis/core/server/ActiveMQServerLogger.cannotFindConsumer:(J)V
      40: return

  public void receiveConsumerCredits(long, int) throws java.lang.Exception;
    Code:
       0: aload_0
       1: getfield      #5                  // Field consumers:Ljava/util/Map;
       4: lload_1
       5: invokestatic  #56                 // Method java/lang/Long.valueOf:(J)Ljava/lang/Long;
       8: invokeinterface #184,  2          // InterfaceMethod java/util/Map.get:(Ljava/lang/Object;)Ljava/lang/Object;
      13: checkcast     #67                 // class org/apache/activemq/artemis/core/server/ServerConsumer
      16: astore        4
      18: aload         4
      20: ifnonnull     52
      23: getstatic     #61                 // Field org/apache/activemq/artemis/core/server/ActiveMQServerLogger.LOGGER:Lorg/apache/activemq/artemis/core/server/ActiveMQServerLogger;
      26: new           #117                // class java/lang/StringBuilder
      29: dup
      30: invokespecial #118                // Method java/lang/StringBuilder."<init>":()V
      33: ldc_w         #284                // String There is no consumer with id
      36: invokevirtual #120                // Method java/lang/StringBuilder.append:(Ljava/lang/String;)Ljava/lang/StringBuilder;
      39: lload_1
      40: invokevirtual #192                // Method java/lang/StringBuilder.append:(J)Ljava/lang/StringBuilder;
      43: invokevirtual #125                // Method java/lang/StringBuilder.toString:()Ljava/lang/String;
      46: invokeinterface #126,  2          // InterfaceMethod org/apache/activemq/artemis/core/server/ActiveMQServerLogger.debug:(Ljava/lang/Object;)V
      51: return
      52: aload         4
      54: iload_3
      55: invokeinterface #285,  2          // InterfaceMethod org/apache/activemq/artemis/core/server/ServerConsumer.receiveCredits:(I)V
      60: return

  public org.apache.activemq.artemis.core.transaction.Transaction getCurrentTransaction();
    Code:
       0: aload_0
       1: getfield      #45                 // Field tx:Lorg/apache/activemq/artemis/core/transaction/Transaction;
       4: ifnonnull     15
       7: aload_0
       8: aload_0
       9: invokevirtual #44                 // Method newTransaction:()Lorg/apache/activemq/artemis/core/transaction/Transaction;
      12: putfield      #45                 // Field tx:Lorg/apache/activemq/artemis/core/transaction/Transaction;
      15: aload_0
      16: getfield      #45                 // Field tx:Lorg/apache/activemq/artemis/core/transaction/Transaction;
      19: areturn

  public void sendLarge(org.apache.activemq.artemis.core.message.impl.MessageInternal) throws java.lang.Exception;
    Code:
       0: aload_0
       1: getfield      #24                 // Field storageManager:Lorg/apache/activemq/artemis/core/persistence/StorageManager;
       4: invokeinterface #286,  1          // InterfaceMethod org/apache/activemq/artemis/core/persistence/StorageManager.generateID:()J
       9: lstore_2
      10: aload_0
      11: getfield      #24                 // Field storageManager:Lorg/apache/activemq/artemis/core/persistence/StorageManager;
      14: lload_2
      15: aload_1
      16: invokeinterface #287,  4          // InterfaceMethod org/apache/activemq/artemis/core/persistence/StorageManager.createLargeMessage:(JLorg/apache/activemq/artemis/core/message/impl/MessageInternal;)Lorg/apache/activemq/artemis/core/server/LargeServerMessage;
      21: astore        4
      23: getstatic     #61                 // Field org/apache/activemq/artemis/core/server/ActiveMQServerLogger.LOGGER:Lorg/apache/activemq/artemis/core/server/ActiveMQServerLogger;
      26: invokeinterface #288,  1          // InterfaceMethod org/apache/activemq/artemis/core/server/ActiveMQServerLogger.isTraceEnabled:()Z
      31: ifeq          63
      34: getstatic     #61                 // Field org/apache/activemq/artemis/core/server/ActiveMQServerLogger.LOGGER:Lorg/apache/activemq/artemis/core/server/ActiveMQServerLogger;
      37: new           #117                // class java/lang/StringBuilder
      40: dup
      41: invokespecial #118                // Method java/lang/StringBuilder."<init>":()V
      44: ldc_w         #289                // String sendLarge::
      47: invokevirtual #120                // Method java/lang/StringBuilder.append:(Ljava/lang/String;)Ljava/lang/StringBuilder;
      50: aload         4
      52: invokevirtual #122                // Method java/lang/StringBuilder.append:(Ljava/lang/Object;)Ljava/lang/StringBuilder;
      55: invokevirtual #125                // Method java/lang/StringBuilder.toString:()Ljava/lang/String;
      58: invokeinterface #204,  2          // InterfaceMethod org/apache/activemq/artemis/core/server/ActiveMQServerLogger.trace:(Ljava/lang/Object;)V
      63: aload_0
      64: getfield      #72                 // Field currentLargeMessage:Lorg/apache/activemq/artemis/core/server/LargeServerMessage;
      67: ifnull        90
      70: getstatic     #61                 // Field org/apache/activemq/artemis/core/server/ActiveMQServerLogger.LOGGER:Lorg/apache/activemq/artemis/core/server/ActiveMQServerLogger;
      73: aload_0
      74: getfield      #72                 // Field currentLargeMessage:Lorg/apache/activemq/artemis/core/server/LargeServerMessage;
      77: invokeinterface #290,  1          // InterfaceMethod org/apache/activemq/artemis/core/server/LargeServerMessage.getMessageID:()J
      82: invokestatic  #56                 // Method java/lang/Long.valueOf:(J)Ljava/lang/Long;
      85: invokeinterface #291,  2          // InterfaceMethod org/apache/activemq/artemis/core/server/ActiveMQServerLogger.replacingIncompleteLargeMessage:(Ljava/lang/Long;)V
      90: aload_0
      91: aload         4
      93: putfield      #72                 // Field currentLargeMessage:Lorg/apache/activemq/artemis/core/server/LargeServerMessage;
      96: return

  public void send(org.apache.activemq.artemis.core.server.ServerMessage, boolean) throws java.lang.Exception;
    Code:
       0: aload_1
       1: invokeinterface #292,  1          // InterfaceMethod org/apache/activemq/artemis/core/server/ServerMessage.isLargeMessage:()Z
       6: ifne          33
       9: aload_0
      10: getfield      #24                 // Field storageManager:Lorg/apache/activemq/artemis/core/persistence/StorageManager;
      13: invokeinterface #286,  1          // InterfaceMethod org/apache/activemq/artemis/core/persistence/StorageManager.generateID:()J
      18: lstore_3
      19: aload_1
      20: lload_3
      21: invokeinterface #293,  3          // InterfaceMethod org/apache/activemq/artemis/core/server/ServerMessage.setMessageID:(J)Lorg/apache/activemq/artemis/core/server/ServerMessage;
      26: pop
      27: aload_1
      28: invokeinterface #294,  1          // InterfaceMethod org/apache/activemq/artemis/core/server/ServerMessage.encodeMessageIDToBuffer:()V
      33: aload_1
      34: invokeinterface #295,  1          // InterfaceMethod org/apache/activemq/artemis/core/server/ServerMessage.getAddress:()Lorg/apache/activemq/artemis/api/core/SimpleString;
      39: astore_3
      40: aload_0
      41: getfield      #37                 // Field defaultAddress:Lorg/apache/activemq/artemis/api/core/SimpleString;
      44: ifnonnull     56
      47: aload_3
      48: ifnull        56
      51: aload_0
      52: aload_3
      53: putfield      #37                 // Field defaultAddress:Lorg/apache/activemq/artemis/api/core/SimpleString;
      56: aload_3
      57: ifnonnull     93
      60: aload_1
      61: invokeinterface #296,  1          // InterfaceMethod org/apache/activemq/artemis/core/server/ServerMessage.isDurable:()Z
      66: ifeq          83
      69: aload_1
      70: aload_0
      71: getfield      #37                 // Field defaultAddress:Lorg/apache/activemq/artemis/api/core/SimpleString;
      74: invokeinterface #297,  2          // InterfaceMethod org/apache/activemq/artemis/core/server/ServerMessage.setAddress:(Lorg/apache/activemq/artemis/api/core/SimpleString;)Lorg/apache/activemq/artemis/api/core/Message;
      79: pop
      80: goto          93
      83: aload_1
      84: aload_0
      85: getfield      #37                 // Field defaultAddress:Lorg/apache/activemq/artemis/api/core/SimpleString;
      88: invokeinterface #298,  2          // InterfaceMethod org/apache/activemq/artemis/core/server/ServerMessage.setAddressTransient:(Lorg/apache/activemq/artemis/api/core/SimpleString;)V
      93: getstatic     #202                // Field isTrace:Z
      96: ifeq          143
      99: getstatic     #61                 // Field org/apache/activemq/artemis/core/server/ActiveMQServerLogger.LOGGER:Lorg/apache/activemq/artemis/core/server/ActiveMQServerLogger;
     102: new           #117                // class java/lang/StringBuilder
     105: dup
     106: invokespecial #118                // Method java/lang/StringBuilder."<init>":()V
     109: ldc_w         #299                // String send(message=
     112: invokevirtual #120                // Method java/lang/StringBuilder.append:(Ljava/lang/String;)Ljava/lang/StringBuilder;
     115: aload_1
     116: invokevirtual #122                // Method java/lang/StringBuilder.append:(Ljava/lang/Object;)Ljava/lang/StringBuilder;
     119: ldc_w         #300                // String , direct=
     122: invokevirtual #120                // Method java/lang/StringBuilder.append:(Ljava/lang/String;)Ljava/lang/StringBuilder;
     125: iload_2
     126: invokevirtual #148                // Method java/lang/StringBuilder.append:(Z)Ljava/lang/StringBuilder;
     129: ldc_w         #301                // String ) being called
     132: invokevirtual #120                // Method java/lang/StringBuilder.append:(Ljava/lang/String;)Ljava/lang/StringBuilder;
     135: invokevirtual #125                // Method java/lang/StringBuilder.toString:()Ljava/lang/String;
     138: invokeinterface #204,  2          // InterfaceMethod org/apache/activemq/artemis/core/server/ActiveMQServerLogger.trace:(Ljava/lang/Object;)V
     143: aload_1
     144: invokeinterface #295,  1          // InterfaceMethod org/apache/activemq/artemis/core/server/ServerMessage.getAddress:()Lorg/apache/activemq/artemis/api/core/SimpleString;
     149: ifnonnull     161
     152: getstatic     #82                 // Field org/apache/activemq/artemis/core/server/ActiveMQMessageBundle.BUNDLE:Lorg/apache/activemq/artemis/core/server/ActiveMQMessageBundle;
     155: invokeinterface #302,  1          // InterfaceMethod org/apache/activemq/artemis/core/server/ActiveMQMessageBundle.noAddress:()Lorg/apache/activemq/artemis/api/core/ActiveMQIllegalStateException;
     160: athrow
     161: aload_1
     162: invokeinterface #295,  1          // InterfaceMethod org/apache/activemq/artemis/core/server/ServerMessage.getAddress:()Lorg/apache/activemq/artemis/api/core/SimpleString;
     167: aload_0
     168: getfield      #35                 // Field managementAddress:Lorg/apache/activemq/artemis/api/core/SimpleString;
     171: invokevirtual #138                // Method org/apache/activemq/artemis/api/core/SimpleString.equals:(Ljava/lang/Object;)Z
     174: ifeq          186
     177: aload_0
     178: aload_1
     179: iload_2
     180: invokespecial #303                // Method handleManagementMessage:(Lorg/apache/activemq/artemis/core/server/ServerMessage;Z)V
     183: goto          192
     186: aload_0
     187: aload_1
     188: iload_2
     189: invokevirtual #304                // Method doSend:(Lorg/apache/activemq/artemis/core/server/ServerMessage;Z)V
     192: return

  public void sendContinuations(int, long, byte[], boolean) throws java.lang.Exception;
    Code:
       0: aload_0
       1: getfield      #72                 // Field currentLargeMessage:Lorg/apache/activemq/artemis/core/server/LargeServerMessage;
       4: ifnonnull     16
       7: getstatic     #82                 // Field org/apache/activemq/artemis/core/server/ActiveMQMessageBundle.BUNDLE:Lorg/apache/activemq/artemis/core/server/ActiveMQMessageBundle;
      10: invokeinterface #305,  1          // InterfaceMethod org/apache/activemq/artemis/core/server/ActiveMQMessageBundle.largeMessageNotInitialised:()Lorg/apache/activemq/artemis/api/core/ActiveMQIllegalStateException;
      15: athrow
      16: aload_0
      17: getfield      #72                 // Field currentLargeMessage:Lorg/apache/activemq/artemis/core/server/LargeServerMessage;
      20: aload         4
      22: invokeinterface #306,  2          // InterfaceMethod org/apache/activemq/artemis/core/server/LargeServerMessage.addBytes:([B)V
      27: iload         5
      29: ifne          75
      32: aload_0
      33: getfield      #72                 // Field currentLargeMessage:Lorg/apache/activemq/artemis/core/server/LargeServerMessage;
      36: invokeinterface #307,  1          // InterfaceMethod org/apache/activemq/artemis/core/server/LargeServerMessage.releaseResources:()V
      41: lload_2
      42: lconst_0
      43: lcmp
      44: iflt          61
      47: aload_0
      48: getfield      #72                 // Field currentLargeMessage:Lorg/apache/activemq/artemis/core/server/LargeServerMessage;
      51: getstatic     #308                // Field org/apache/activemq/artemis/api/core/Message.HDR_LARGE_BODY_SIZE:Lorg/apache/activemq/artemis/api/core/SimpleString;
      54: lload_2
      55: invokeinterface #309,  4          // InterfaceMethod org/apache/activemq/artemis/core/server/LargeServerMessage.putLongProperty:(Lorg/apache/activemq/artemis/api/core/SimpleString;J)Lorg/apache/activemq/artemis/api/core/Message;
      60: pop
      61: aload_0
      62: aload_0
      63: getfield      #72                 // Field currentLargeMessage:Lorg/apache/activemq/artemis/core/server/LargeServerMessage;
      66: iconst_0
      67: invokevirtual #304                // Method doSend:(Lorg/apache/activemq/artemis/core/server/ServerMessage;Z)V
      70: aload_0
      71: aconst_null
      72: putfield      #72                 // Field currentLargeMessage:Lorg/apache/activemq/artemis/core/server/LargeServerMessage;
      75: return

  public void requestProducerCredits(org.apache.activemq.artemis.api.core.SimpleString, int) throws java.lang.Exception;
    Code:
       0: aload_0
       1: getfield      #34                 // Field server:Lorg/apache/activemq/artemis/core/server/ActiveMQServer;
       4: invokeinterface #310,  1          // InterfaceMethod org/apache/activemq/artemis/core/server/ActiveMQServer.getPagingManager:()Lorg/apache/activemq/artemis/core/paging/PagingManager;
       9: aload_1
      10: invokeinterface #311,  2          // InterfaceMethod org/apache/activemq/artemis/core/paging/PagingManager.getPageStore:(Lorg/apache/activemq/artemis/api/core/SimpleString;)Lorg/apache/activemq/artemis/core/paging/PagingStore;
      15: astore_3
      16: aload_3
      17: new           #312                // class org/apache/activemq/artemis/core/server/impl/ServerSessionImpl$2
      20: dup
      21: aload_0
      22: iload_2
      23: aload_1
      24: invokespecial #313                // Method org/apache/activemq/artemis/core/server/impl/ServerSessionImpl$2."<init>":(Lorg/apache/activemq/artemis/core/server/impl/ServerSessionImpl;ILorg/apache/activemq/artemis/api/core/SimpleString;)V
      27: invokeinterface #314,  2          // InterfaceMethod org/apache/activemq/artemis/core/paging/PagingStore.checkMemory:(Ljava/lang/Runnable;)Z
      32: ifne          46
      35: aload_0
      36: getfield      #36                 // Field callback:Lorg/apache/activemq/artemis/spi/core/protocol/SessionCallback;
      39: iload_2
      40: aload_1
      41: invokeinterface #315,  3          // InterfaceMethod org/apache/activemq/artemis/spi/core/protocol/SessionCallback.sendProducerCreditsFailMessage:(ILorg/apache/activemq/artemis/api/core/SimpleString;)V
      46: return

  public void setTransferring(boolean);
    Code:
       0: new           #47                 // class java/util/HashSet
       3: dup
       4: aload_0
       5: getfield      #5                  // Field consumers:Ljava/util/Map;
       8: invokeinterface #48,  1           // InterfaceMethod java/util/Map.values:()Ljava/util/Collection;
      13: invokespecial #49                 // Method java/util/HashSet."<init>":(Ljava/util/Collection;)V
      16: astore_2
      17: aload_2
      18: invokeinterface #64,  1           // InterfaceMethod java/util/Set.iterator:()Ljava/util/Iterator;
      23: astore_3
      24: aload_3
      25: invokeinterface #65,  1           // InterfaceMethod java/util/Iterator.hasNext:()Z
      30: ifeq          55
      33: aload_3
      34: invokeinterface #66,  1           // InterfaceMethod java/util/Iterator.next:()Ljava/lang/Object;
      39: checkcast     #67                 // class org/apache/activemq/artemis/core/server/ServerConsumer
      42: astore        4
      44: aload         4
      46: iload_1
      47: invokeinterface #316,  2          // InterfaceMethod org/apache/activemq/artemis/core/server/ServerConsumer.setTransferring:(Z)V
      52: goto          24
      55: return

  public void addMetaData(java.lang.String, java.lang.String);
    Code:
       0: aload_0
       1: getfield      #317                // Field metaData:Ljava/util/Map;
       4: ifnonnull     18
       7: aload_0
       8: new           #7                  // class java/util/HashMap
      11: dup
      12: invokespecial #8                  // Method java/util/HashMap."<init>":()V
      15: putfield      #317                // Field metaData:Ljava/util/Map;
      18: aload_0
      19: getfield      #317                // Field metaData:Ljava/util/Map;
      22: aload_1
      23: aload_2
      24: invokeinterface #91,  3           // InterfaceMethod java/util/Map.put:(Ljava/lang/Object;Ljava/lang/Object;)Ljava/lang/Object;
      29: pop
      30: return

  public boolean addUniqueMetaData(java.lang.String, java.lang.String);
    Code:
       0: aload_0
       1: getfield      #34                 // Field server:Lorg/apache/activemq/artemis/core/server/ActiveMQServer;
       4: aload_1
       5: aload_2
       6: invokeinterface #318,  3          // InterfaceMethod org/apache/activemq/artemis/core/server/ActiveMQServer.lookupSession:(Ljava/lang/String;Ljava/lang/String;)Lorg/apache/activemq/artemis/core/server/ServerSession;
      11: astore_3
      12: aload_3
      13: ifnull        23
      16: aload_3
      17: aload_0
      18: if_acmpeq     23
      21: iconst_0
      22: ireturn
      23: aload_0
      24: aload_1
      25: aload_2
      26: invokevirtual #319                // Method addMetaData:(Ljava/lang/String;Ljava/lang/String;)V
      29: iconst_1
      30: ireturn

  public java.lang.String getMetaData(java.lang.String);
    Code:
       0: aconst_null
       1: astore_2
       2: aload_0
       3: getfield      #317                // Field metaData:Ljava/util/Map;
       6: ifnull        23
       9: aload_0
      10: getfield      #317                // Field metaData:Ljava/util/Map;
      13: aload_1
      14: invokeinterface #184,  2          // InterfaceMethod java/util/Map.get:(Ljava/lang/Object;)Ljava/lang/Object;
      19: checkcast     #320                // class java/lang/String
      22: astore_2
      23: aload_1
      24: ldc_w         #322                // String jms-client-id
      27: invokevirtual #323                // Method java/lang/String.equals:(Ljava/lang/Object;)Z
      30: ifeq          37
      33: aload_0
      34: invokespecial #324                // Method installJMSHooks:()V
      37: aload_2
      38: areturn

  public java.lang.String[] getTargetAddresses();
    Code:
       0: aload_0
       1: invokespecial #325                // Method cloneTargetAddresses:()Ljava/util/Map;
       4: astore_1
       5: aload_1
       6: invokeinterface #326,  1          // InterfaceMethod java/util/Map.keySet:()Ljava/util/Set;
      11: invokeinterface #64,  1           // InterfaceMethod java/util/Set.iterator:()Ljava/util/Iterator;
      16: astore_2
      17: aload_1
      18: invokeinterface #326,  1          // InterfaceMethod java/util/Map.keySet:()Ljava/util/Set;
      23: invokeinterface #327,  1          // InterfaceMethod java/util/Set.size:()I
      28: istore_3
      29: iload_3
      30: anewarray     #320                // class java/lang/String
      33: astore        4
      35: iconst_0
      36: istore        5
      38: aload_2
      39: invokeinterface #65,  1           // InterfaceMethod java/util/Iterator.hasNext:()Z
      44: ifeq          70
      47: aload         4
      49: iload         5
      51: aload_2
      52: invokeinterface #66,  1           // InterfaceMethod java/util/Iterator.next:()Ljava/lang/Object;
      57: checkcast     #328                // class org/apache/activemq/artemis/api/core/SimpleString
      60: invokevirtual #134                // Method org/apache/activemq/artemis/api/core/SimpleString.toString:()Ljava/lang/String;
      63: aastore
      64: iinc          5, 1
      67: goto          38
      70: aload         4
      72: areturn

  public java.lang.String getLastSentMessageID(java.lang.String);
    Code:
       0: aload_0
       1: getfield      #13                 // Field targetAddressInfos:Ljava/util/Map;
       4: aload_1
       5: invokestatic  #108                // Method org/apache/activemq/artemis/api/core/SimpleString.toSimpleString:(Ljava/lang/String;)Lorg/apache/activemq/artemis/api/core/SimpleString;
       8: invokeinterface #184,  2          // InterfaceMethod java/util/Map.get:(Ljava/lang/Object;)Ljava/lang/Object;
      13: checkcast     #329                // class org/apache/activemq/artemis/api/core/Pair
      16: astore_2
      17: aload_2
      18: ifnull        32
      21: aload_2
      22: invokevirtual #330                // Method org/apache/activemq/artemis/api/core/Pair.getA:()Ljava/lang/Object;
      25: checkcast     #331                // class org/apache/activemq/artemis/utils/UUID
      28: invokevirtual #332                // Method org/apache/activemq/artemis/utils/UUID.toString:()Ljava/lang/String;
      31: areturn
      32: aconst_null
      33: areturn

  public long getCreationTime();
    Code:
       0: aload_0
       1: getfield      #15                 // Field creationTime:J
       4: lreturn

  public org.apache.activemq.artemis.core.persistence.StorageManager getStorageManager();
    Code:
       0: aload_0
       1: getfield      #24                 // Field storageManager:Lorg/apache/activemq/artemis/core/persistence/StorageManager;
       4: areturn

  public void describeProducersInfo(org.apache.activemq.artemis.utils.json.JSONArray) throws java.lang.Exception;
    Code:
       0: aload_0
       1: invokespecial #325                // Method cloneTargetAddresses:()Ljava/util/Map;
       4: astore_2
       5: aload_2
       6: invokeinterface #333,  1          // InterfaceMethod java/util/Map.entrySet:()Ljava/util/Set;
      11: invokeinterface #64,  1           // InterfaceMethod java/util/Set.iterator:()Ljava/util/Iterator;
      16: astore_3
      17: aload_3
      18: invokeinterface #65,  1           // InterfaceMethod java/util/Iterator.hasNext:()Z
      23: ifeq          157
      26: aload_3
      27: invokeinterface #66,  1           // InterfaceMethod java/util/Iterator.next:()Ljava/lang/Object;
      32: checkcast     #334                // class java/util/Map$Entry
      35: astore        4
      37: new           #335                // class org/apache/activemq/artemis/utils/json/JSONObject
      40: dup
      41: invokespecial #336                // Method org/apache/activemq/artemis/utils/json/JSONObject."<init>":()V
      44: astore        5
      46: aload         5
      48: ldc_w         #337                // String connectionID
      51: aload_0
      52: invokevirtual #338                // Method getConnectionID:()Ljava/lang/Object;
      55: invokevirtual #248                // Method java/lang/Object.toString:()Ljava/lang/String;
      58: invokevirtual #339                // Method org/apache/activemq/artemis/utils/json/JSONObject.put:(Ljava/lang/String;Ljava/lang/Object;)Lorg/apache/activemq/artemis/utils/json/JSONObject;
      61: pop
      62: aload         5
      64: ldc_w         #340                // String sessionID
      67: aload_0
      68: invokevirtual #341                // Method getName:()Ljava/lang/String;
      71: invokevirtual #339                // Method org/apache/activemq/artemis/utils/json/JSONObject.put:(Ljava/lang/String;Ljava/lang/Object;)Lorg/apache/activemq/artemis/utils/json/JSONObject;
      74: pop
      75: aload         5
      77: ldc_w         #342                // String destination
      80: aload         4
      82: invokeinterface #343,  1          // InterfaceMethod java/util/Map$Entry.getKey:()Ljava/lang/Object;
      87: checkcast     #328                // class org/apache/activemq/artemis/api/core/SimpleString
      90: invokevirtual #134                // Method org/apache/activemq/artemis/api/core/SimpleString.toString:()Ljava/lang/String;
      93: invokevirtual #339                // Method org/apache/activemq/artemis/utils/json/JSONObject.put:(Ljava/lang/String;Ljava/lang/Object;)Lorg/apache/activemq/artemis/utils/json/JSONObject;
      96: pop
      97: aload         5
      99: ldc_w         #344                // String lastUUIDSent
     102: aload         4
     104: invokeinterface #345,  1          // InterfaceMethod java/util/Map$Entry.getValue:()Ljava/lang/Object;
     109: checkcast     #329                // class org/apache/activemq/artemis/api/core/Pair
     112: invokevirtual #330                // Method org/apache/activemq/artemis/api/core/Pair.getA:()Ljava/lang/Object;
     115: invokevirtual #339                // Method org/apache/activemq/artemis/utils/json/JSONObject.put:(Ljava/lang/String;Ljava/lang/Object;)Lorg/apache/activemq/artemis/utils/json/JSONObject;
     118: pop
     119: aload         5
     121: ldc_w         #346                // String msgSent
     124: aload         4
     126: invokeinterface #345,  1          // InterfaceMethod java/util/Map$Entry.getValue:()Ljava/lang/Object;
     131: checkcast     #329                // class org/apache/activemq/artemis/api/core/Pair
     134: invokevirtual #347                // Method org/apache/activemq/artemis/api/core/Pair.getB:()Ljava/lang/Object;
     137: checkcast     #348                // class java/util/concurrent/atomic/AtomicLong
     140: invokevirtual #349                // Method java/util/concurrent/atomic/AtomicLong.longValue:()J
     143: invokevirtual #350                // Method org/apache/activemq/artemis/utils/json/JSONObject.put:(Ljava/lang/String;J)Lorg/apache/activemq/artemis/utils/json/JSONObject;
     146: pop
     147: aload_1
     148: aload         5
     150: invokevirtual #351                // Method org/apache/activemq/artemis/utils/json/JSONArray.put:(Ljava/lang/Object;)Lorg/apache/activemq/artemis/utils/json/JSONArray;
     153: pop
     154: goto          17
     157: return

  public java.lang.String toString();
    Code:
       0: new           #352                // class java/lang/StringBuffer
       3: dup
       4: invokespecial #353                // Method java/lang/StringBuffer."<init>":()V
       7: astore_1
       8: aload_0
       9: getfield      #317                // Field metaData:Ljava/util/Map;
      12: ifnull        165
      15: aload_0
      16: getfield      #317                // Field metaData:Ljava/util/Map;
      19: invokeinterface #333,  1          // InterfaceMethod java/util/Map.entrySet:()Ljava/util/Set;
      24: invokeinterface #64,  1           // InterfaceMethod java/util/Set.iterator:()Ljava/util/Iterator;
      29: astore_2
      30: aload_2
      31: invokeinterface #65,  1           // InterfaceMethod java/util/Iterator.hasNext:()Z
      36: ifeq          165
      39: aload_2
      40: invokeinterface #66,  1           // InterfaceMethod java/util/Iterator.next:()Ljava/lang/Object;
      45: checkcast     #334                // class java/util/Map$Entry
      48: astore_3
      49: aload_1
      50: invokevirtual #354                // Method java/lang/StringBuffer.length:()I
      53: ifeq          64
      56: aload_1
      57: ldc_w         #355                // String ,
      60: invokevirtual #356                // Method java/lang/StringBuffer.append:(Ljava/lang/String;)Ljava/lang/StringBuffer;
      63: pop
      64: aload_3
      65: invokeinterface #345,  1          // InterfaceMethod java/util/Map$Entry.getValue:()Ljava/lang/Object;
      70: astore        4
      72: aload         4
      74: ifnull        88
      77: aload         4
      79: invokevirtual #248                // Method java/lang/Object.toString:()Ljava/lang/String;
      82: invokevirtual #357                // Method java/lang/String.isEmpty:()Z
      85: ifeq          124
      88: aload_1
      89: new           #117                // class java/lang/StringBuilder
      92: dup
      93: invokespecial #118                // Method java/lang/StringBuilder."<init>":()V
      96: aload_3
      97: invokeinterface #343,  1          // InterfaceMethod java/util/Map$Entry.getKey:()Ljava/lang/Object;
     102: checkcast     #320                // class java/lang/String
     105: invokevirtual #120                // Method java/lang/StringBuilder.append:(Ljava/lang/String;)Ljava/lang/StringBuilder;
     108: ldc_w         #358                // String =*N/A*
     111: invokevirtual #120                // Method java/lang/StringBuilder.append:(Ljava/lang/String;)Ljava/lang/StringBuilder;
     114: invokevirtual #125                // Method java/lang/StringBuilder.toString:()Ljava/lang/String;
     117: invokevirtual #356                // Method java/lang/StringBuffer.append:(Ljava/lang/String;)Ljava/lang/StringBuffer;
     120: pop
     121: goto          162
     124: aload_1
     125: new           #117                // class java/lang/StringBuilder
     128: dup
     129: invokespecial #118                // Method java/lang/StringBuilder."<init>":()V
     132: aload_3
     133: invokeinterface #343,  1          // InterfaceMethod java/util/Map$Entry.getKey:()Ljava/lang/Object;
     138: checkcast     #320                // class java/lang/String
     141: invokevirtual #120                // Method java/lang/StringBuilder.append:(Ljava/lang/String;)Ljava/lang/StringBuilder;
     144: ldc_w         #359                // String =
     147: invokevirtual #120                // Method java/lang/StringBuilder.append:(Ljava/lang/String;)Ljava/lang/StringBuilder;
     150: aload         4
     152: invokevirtual #122                // Method java/lang/StringBuilder.append:(Ljava/lang/Object;)Ljava/lang/StringBuilder;
     155: invokevirtual #125                // Method java/lang/StringBuilder.toString:()Ljava/lang/String;
     158: invokevirtual #356                // Method java/lang/StringBuffer.append:(Ljava/lang/String;)Ljava/lang/StringBuffer;
     161: pop
     162: goto          30
     165: new           #117                // class java/lang/StringBuilder
     168: dup
     169: invokespecial #118                // Method java/lang/StringBuilder."<init>":()V
     172: ldc_w         #360                // String ServerSessionImpl(
     175: invokevirtual #120                // Method java/lang/StringBuilder.append:(Ljava/lang/String;)Ljava/lang/StringBuilder;
     178: aload_1
     179: invokevirtual #361                // Method java/lang/StringBuffer.toString:()Ljava/lang/String;
     182: invokevirtual #120                // Method java/lang/StringBuilder.append:(Ljava/lang/String;)Ljava/lang/StringBuilder;
     185: ldc_w         #362                // String )
     188: invokevirtual #120                // Method java/lang/StringBuilder.append:(Ljava/lang/String;)Ljava/lang/StringBuilder;
     191: invokevirtual #125                // Method java/lang/StringBuilder.toString:()Ljava/lang/String;
     194: areturn

  public void connectionFailed(org.apache.activemq.artemis.api.core.ActiveMQException, boolean);
    Code:
       0: getstatic     #61                 // Field org/apache/activemq/artemis/core/server/ActiveMQServerLogger.LOGGER:Lorg/apache/activemq/artemis/core/server/ActiveMQServerLogger;
       3: aload_0
       4: getfield      #33                 // Field name:Ljava/lang/String;
       7: invokeinterface #363,  2          // InterfaceMethod org/apache/activemq/artemis/core/server/ActiveMQServerLogger.clientConnectionFailed:(Ljava/lang/String;)V
      12: aload_0
      13: iconst_1
      14: invokevirtual #364                // Method close:(Z)V
      17: getstatic     #61                 // Field org/apache/activemq/artemis/core/server/ActiveMQServerLogger.LOGGER:Lorg/apache/activemq/artemis/core/server/ActiveMQServerLogger;
      20: aload_0
      21: getfield      #33                 // Field name:Ljava/lang/String;
      24: invokeinterface #365,  2          // InterfaceMethod org/apache/activemq/artemis/core/server/ActiveMQServerLogger.clientConnectionFailedClearingSession:(Ljava/lang/String;)V
      29: goto          42
      32: astore_3
      33: getstatic     #61                 // Field org/apache/activemq/artemis/core/server/ActiveMQServerLogger.LOGGER:Lorg/apache/activemq/artemis/core/server/ActiveMQServerLogger;
      36: aload_0
      37: invokeinterface #366,  2          // InterfaceMethod org/apache/activemq/artemis/core/server/ActiveMQServerLogger.errorClosingConnection:(Lorg/apache/activemq/artemis/core/server/impl/ServerSessionImpl;)V
      42: return
    Exception table:
       from    to  target type
           0    29    32   Class java/lang/Throwable

  public void connectionFailed(org.apache.activemq.artemis.api.core.ActiveMQException, boolean, java.lang.String);
    Code:
       0: aload_0
       1: aload_1
       2: iload_2
       3: invokevirtual #367                // Method connectionFailed:(Lorg/apache/activemq/artemis/api/core/ActiveMQException;Z)V
       6: return

  public void clearLargeMessage();
    Code:
       0: aload_0
       1: aconst_null
       2: putfield      #72                 // Field currentLargeMessage:Lorg/apache/activemq/artemis/core/server/LargeServerMessage;
       5: return

  private void installJMSHooks();
    Code:
       0: aload_0
       1: aload_0
       2: getfield      #34                 // Field server:Lorg/apache/activemq/artemis/core/server/ActiveMQServer;
       5: invokeinterface #368,  1          // InterfaceMethod org/apache/activemq/artemis/core/server/ActiveMQServer.getJMSQueueCreator:()Lorg/apache/activemq/artemis/core/server/QueueCreator;
      10: putfield      #40                 // Field queueCreator:Lorg/apache/activemq/artemis/core/server/QueueCreator;
      13: return

  private java.util.Map<org.apache.activemq.artemis.api.core.SimpleString, org.apache.activemq.artemis.api.core.Pair<org.apache.activemq.artemis.utils.UUID, java.util.concurrent.atomic.AtomicLong>> cloneTargetAddresses();
    Code:
       0: new           #7                  // class java/util/HashMap
       3: dup
       4: aload_0
       5: getfield      #13                 // Field targetAddressInfos:Ljava/util/Map;
       8: invokespecial #369                // Method java/util/HashMap."<init>":(Ljava/util/Map;)V
      11: areturn

  private void setStarted(boolean);
    Code:
       0: new           #47                 // class java/util/HashSet
       3: dup
       4: aload_0
       5: getfield      #5                  // Field consumers:Ljava/util/Map;
       8: invokeinterface #48,  1           // InterfaceMethod java/util/Map.values:()Ljava/util/Collection;
      13: invokespecial #49                 // Method java/util/HashSet."<init>":(Ljava/util/Collection;)V
      16: astore_2
      17: aload_2
      18: invokeinterface #64,  1           // InterfaceMethod java/util/Set.iterator:()Ljava/util/Iterator;
      23: astore_3
      24: aload_3
      25: invokeinterface #65,  1           // InterfaceMethod java/util/Iterator.hasNext:()Z
      30: ifeq          55
      33: aload_3
      34: invokeinterface #66,  1           // InterfaceMethod java/util/Iterator.next:()Ljava/lang/Object;
      39: checkcast     #67                 // class org/apache/activemq/artemis/core/server/ServerConsumer
      42: astore        4
      44: aload         4
      46: iload_1
      47: invokeinterface #370,  2          // InterfaceMethod org/apache/activemq/artemis/core/server/ServerConsumer.setStarted:(Z)V
      52: goto          24
      55: aload_0
      56: iload_1
      57: putfield      #6                  // Field started:Z
      60: return

  private void handleManagementMessage(org.apache.activemq.artemis.core.server.ServerMessage, boolean) throws java.lang.Exception;
    Code:
       0: aload_0
       1: getfield      #27                 // Field securityStore:Lorg/apache/activemq/artemis/core/security/SecurityStore;
       4: aload_1
       5: invokeinterface #295,  1          // InterfaceMethod org/apache/activemq/artemis/core/server/ServerMessage.getAddress:()Lorg/apache/activemq/artemis/api/core/SimpleString;
      10: getstatic     #371                // Field org/apache/activemq/artemis/core/security/CheckType.MANAGE:Lorg/apache/activemq/artemis/core/security/CheckType;
      13: aload_0
      14: invokeinterface #86,  4           // InterfaceMethod org/apache/activemq/artemis/core/security/SecurityStore.check:(Lorg/apache/activemq/artemis/api/core/SimpleString;Lorg/apache/activemq/artemis/core/security/CheckType;Lorg/apache/activemq/artemis/core/security/SecurityAuth;)V
      19: goto          42
      22: astore_3
      23: aload_0
      24: getfield      #20                 // Field autoCommitSends:Z
      27: ifne          40
      30: aload_0
      31: getfield      #45                 // Field tx:Lorg/apache/activemq/artemis/core/transaction/Transaction;
      34: aload_3
      35: invokeinterface #52,  2           // InterfaceMethod org/apache/activemq/artemis/core/transaction/Transaction.markAsRollbackOnly:(Lorg/apache/activemq/artemis/api/core/ActiveMQException;)V
      40: aload_3
      41: athrow
      42: aload_0
      43: getfield      #32                 // Field managementService:Lorg/apache/activemq/artemis/core/server/management/ManagementService;
      46: aload_1
      47: invokeinterface #372,  2          // InterfaceMethod org/apache/activemq/artemis/core/server/management/ManagementService.handleMessage:(Lorg/apache/activemq/artemis/core/server/ServerMessage;)Lorg/apache/activemq/artemis/core/server/ServerMessage;
      52: astore_3
      53: aload_1
      54: getstatic     #373                // Field org/apache/activemq/artemis/core/client/impl/ClientMessageImpl.REPLYTO_HEADER_NAME:Lorg/apache/activemq/artemis/api/core/SimpleString;
      57: invokeinterface #374,  2          // InterfaceMethod org/apache/activemq/artemis/core/server/ServerMessage.getSimpleStringProperty:(Lorg/apache/activemq/artemis/api/core/SimpleString;)Lorg/apache/activemq/artemis/api/core/SimpleString;
      62: astore        4
      64: aload         4
      66: ifnull        84
      69: aload_3
      70: aload         4
      72: invokeinterface #297,  2          // InterfaceMethod org/apache/activemq/artemis/core/server/ServerMessage.setAddress:(Lorg/apache/activemq/artemis/api/core/SimpleString;)Lorg/apache/activemq/artemis/api/core/Message;
      77: pop
      78: aload_0
      79: aload_3
      80: iload_2
      81: invokevirtual #304                // Method doSend:(Lorg/apache/activemq/artemis/core/server/ServerMessage;Z)V
      84: return
    Exception table:
       from    to  target type
           0    19    22   Class org/apache/activemq/artemis/api/core/ActiveMQException

  private void doRollback(boolean, boolean, org.apache.activemq.artemis.core.transaction.Transaction) throws java.lang.Exception;
    Code:
       0: aload_0
       1: getfield      #6                  // Field started:Z
       4: istore        4
       6: new           #172                // class java/util/ArrayList
       9: dup
      10: invokespecial #173                // Method java/util/ArrayList."<init>":()V
      13: astore        5
      15: aload_0
      16: getfield      #5                  // Field consumers:Ljava/util/Map;
      19: invokeinterface #48,  1           // InterfaceMethod java/util/Map.values:()Ljava/util/Collection;
      24: invokeinterface #178,  1          // InterfaceMethod java/util/Collection.iterator:()Ljava/util/Iterator;
      29: astore        6
      31: aload         6
      33: invokeinterface #65,  1           // InterfaceMethod java/util/Iterator.hasNext:()Z
      38: ifeq          87
      41: aload         6
      43: invokeinterface #66,  1           // InterfaceMethod java/util/Iterator.next:()Ljava/lang/Object;
      48: checkcast     #67                 // class org/apache/activemq/artemis/core/server/ServerConsumer
      51: astore        7
      53: iload         4
      55: ifeq          66
      58: aload         7
      60: iconst_0
      61: invokeinterface #370,  2          // InterfaceMethod org/apache/activemq/artemis/core/server/ServerConsumer.setStarted:(Z)V
      66: aload         5
      68: aload         7
      70: iload_1
      71: iload_2
      72: aload_3
      73: invokeinterface #375,  4          // InterfaceMethod org/apache/activemq/artemis/core/server/ServerConsumer.cancelRefs:(ZZLorg/apache/activemq/artemis/core/transaction/Transaction;)Ljava/util/List;
      78: invokeinterface #271,  2          // InterfaceMethod java/util/List.addAll:(Ljava/util/Collection;)Z
      83: pop
      84: goto          31
      87: aload_3
      88: invokeinterface #188,  1          // InterfaceMethod org/apache/activemq/artemis/core/transaction/Transaction.getState:()Lorg/apache/activemq/artemis/core/transaction/Transaction$State;
      93: getstatic     #189                // Field org/apache/activemq/artemis/core/transaction/Transaction$State.ROLLEDBACK:Lorg/apache/activemq/artemis/core/transaction/Transaction$State;
      96: if_acmpne     119
      99: aload_0
     100: invokevirtual #44                 // Method newTransaction:()Lorg/apache/activemq/artemis/core/transaction/Transaction;
     103: astore        6
     105: aload_0
     106: iload_1
     107: aload         6
     109: iload         4
     111: aload         5
     113: invokespecial #376                // Method cancelAndRollback:(ZLorg/apache/activemq/artemis/core/transaction/Transaction;ZLjava/util/List;)V
     116: goto          129
     119: aload_0
     120: iload_1
     121: aload_3
     122: iload         4
     124: aload         5
     126: invokespecial #376                // Method cancelAndRollback:(ZLorg/apache/activemq/artemis/core/transaction/Transaction;ZLjava/util/List;)V
     129: return

  private void cancelAndRollback(boolean, org.apache.activemq.artemis.core.transaction.Transaction, boolean, java.util.List<org.apache.activemq.artemis.core.server.MessageReference>) throws java.lang.Exception;
    Code:
       0: aload         4
       2: invokeinterface #377,  1          // InterfaceMethod java/util/List.iterator:()Ljava/util/Iterator;
       7: astore        5
       9: aload         5
      11: invokeinterface #65,  1           // InterfaceMethod java/util/Iterator.hasNext:()Z
      16: ifeq          49
      19: aload         5
      21: invokeinterface #66,  1           // InterfaceMethod java/util/Iterator.next:()Ljava/lang/Object;
      26: checkcast     #378                // class org/apache/activemq/artemis/core/server/MessageReference
      29: astore        6
      31: aload         6
      33: invokeinterface #200,  1          // InterfaceMethod org/apache/activemq/artemis/core/server/MessageReference.getQueue:()Lorg/apache/activemq/artemis/core/server/Queue;
      38: aload_2
      39: aload         6
      41: invokeinterface #379,  3          // InterfaceMethod org/apache/activemq/artemis/core/server/Queue.cancel:(Lorg/apache/activemq/artemis/core/transaction/Transaction;Lorg/apache/activemq/artemis/core/server/MessageReference;)V
      46: goto          9
      49: iload_3
      50: ifeq          71
      53: iload_1
      54: ifne          71
      57: aload_2
      58: new           #380                // class org/apache/activemq/artemis/core/server/impl/ServerSessionImpl$3
      61: dup
      62: aload_0
      63: invokespecial #381                // Method org/apache/activemq/artemis/core/server/impl/ServerSessionImpl$3."<init>":(Lorg/apache/activemq/artemis/core/server/impl/ServerSessionImpl;)V
      66: invokeinterface #382,  2          // InterfaceMethod org/apache/activemq/artemis/core/transaction/Transaction.addOperation:(Lorg/apache/activemq/artemis/core/transaction/TransactionOperation;)V
      71: aload_2
      72: invokeinterface #195,  1          // InterfaceMethod org/apache/activemq/artemis/core/transaction/Transaction.rollback:()V
      77: return

  protected void doSend(org.apache.activemq.artemis.core.server.ServerMessage, boolean) throws java.lang.Exception;
    Code:
       0: aload_0
       1: getfield      #27                 // Field securityStore:Lorg/apache/activemq/artemis/core/security/SecurityStore;
       4: aload_1
       5: invokeinterface #295,  1          // InterfaceMethod org/apache/activemq/artemis/core/server/ServerMessage.getAddress:()Lorg/apache/activemq/artemis/api/core/SimpleString;
      10: getstatic     #383                // Field org/apache/activemq/artemis/core/security/CheckType.SEND:Lorg/apache/activemq/artemis/core/security/CheckType;
      13: aload_0
      14: invokeinterface #86,  4           // InterfaceMethod org/apache/activemq/artemis/core/security/SecurityStore.check:(Lorg/apache/activemq/artemis/api/core/SimpleString;Lorg/apache/activemq/artemis/core/security/CheckType;Lorg/apache/activemq/artemis/core/security/SecurityAuth;)V
      19: goto          49
      22: astore_3
      23: aload_0
      24: getfield      #20                 // Field autoCommitSends:Z
      27: ifne          47
      30: aload_0
      31: getfield      #45                 // Field tx:Lorg/apache/activemq/artemis/core/transaction/Transaction;
      34: ifnull        47
      37: aload_0
      38: getfield      #45                 // Field tx:Lorg/apache/activemq/artemis/core/transaction/Transaction;
      41: aload_3
      42: invokeinterface #52,  2           // InterfaceMethod org/apache/activemq/artemis/core/transaction/Transaction.markAsRollbackOnly:(Lorg/apache/activemq/artemis/api/core/ActiveMQException;)V
      47: aload_3
      48: athrow
      49: aload_0
      50: getfield      #45                 // Field tx:Lorg/apache/activemq/artemis/core/transaction/Transaction;
      53: ifnull        79
      56: aload_0
      57: getfield      #20                 // Field autoCommitSends:Z
      60: ifeq          66
      63: goto          79
      66: aload_0
      67: getfield      #12                 // Field routingContext:Lorg/apache/activemq/artemis/core/server/RoutingContext;
      70: aload_0
      71: getfield      #45                 // Field tx:Lorg/apache/activemq/artemis/core/transaction/Transaction;
      74: invokeinterface #384,  2          // InterfaceMethod org/apache/activemq/artemis/core/server/RoutingContext.setTransaction:(Lorg/apache/activemq/artemis/core/transaction/Transaction;)V
      79: aload_0
      80: getfield      #25                 // Field postOffice:Lorg/apache/activemq/artemis/core/postoffice/PostOffice;
      83: aload_1
      84: aload_0
      85: getfield      #40                 // Field queueCreator:Lorg/apache/activemq/artemis/core/server/QueueCreator;
      88: aload_0
      89: getfield      #12                 // Field routingContext:Lorg/apache/activemq/artemis/core/server/RoutingContext;
      92: iload_2
      93: invokeinterface #385,  5          // InterfaceMethod org/apache/activemq/artemis/core/postoffice/PostOffice.route:(Lorg/apache/activemq/artemis/core/server/ServerMessage;Lorg/apache/activemq/artemis/core/server/QueueCreator;Lorg/apache/activemq/artemis/core/server/RoutingContext;Z)V
      98: aload_0
      99: getfield      #13                 // Field targetAddressInfos:Ljava/util/Map;
     102: aload_1
     103: invokeinterface #295,  1          // InterfaceMethod org/apache/activemq/artemis/core/server/ServerMessage.getAddress:()Lorg/apache/activemq/artemis/api/core/SimpleString;
     108: invokeinterface #184,  2          // InterfaceMethod java/util/Map.get:(Ljava/lang/Object;)Ljava/lang/Object;
     113: checkcast     #329                // class org/apache/activemq/artemis/api/core/Pair
     116: astore_3
     117: aload_3
     118: ifnonnull     161
     121: aload_0
     122: getfield      #13                 // Field targetAddressInfos:Ljava/util/Map;
     125: aload_1
     126: invokeinterface #295,  1          // InterfaceMethod org/apache/activemq/artemis/core/server/ServerMessage.getAddress:()Lorg/apache/activemq/artemis/api/core/SimpleString;
     131: new           #329                // class org/apache/activemq/artemis/api/core/Pair
     134: dup
     135: aload_1
     136: invokeinterface #386,  1          // InterfaceMethod org/apache/activemq/artemis/core/server/ServerMessage.getUserID:()Lorg/apache/activemq/artemis/utils/UUID;
     141: new           #348                // class java/util/concurrent/atomic/AtomicLong
     144: dup
     145: lconst_1
     146: invokespecial #387                // Method java/util/concurrent/atomic/AtomicLong."<init>":(J)V
     149: invokespecial #388                // Method org/apache/activemq/artemis/api/core/Pair."<init>":(Ljava/lang/Object;Ljava/lang/Object;)V
     152: invokeinterface #91,  3           // InterfaceMethod java/util/Map.put:(Ljava/lang/Object;Ljava/lang/Object;)Ljava/lang/Object;
     157: pop
     158: goto          182
     161: aload_3
     162: aload_1
     163: invokeinterface #386,  1          // InterfaceMethod org/apache/activemq/artemis/core/server/ServerMessage.getUserID:()Lorg/apache/activemq/artemis/utils/UUID;
     168: invokevirtual #389                // Method org/apache/activemq/artemis/api/core/Pair.setA:(Ljava/lang/Object;)V
     171: aload_3
     172: invokevirtual #347                // Method org/apache/activemq/artemis/api/core/Pair.getB:()Ljava/lang/Object;
     175: checkcast     #348                // class java/util/concurrent/atomic/AtomicLong
     178: invokevirtual #390                // Method java/util/concurrent/atomic/AtomicLong.incrementAndGet:()J
     181: pop2
     182: aload_0
     183: getfield      #12                 // Field routingContext:Lorg/apache/activemq/artemis/core/server/RoutingContext;
     186: invokeinterface #391,  1          // InterfaceMethod org/apache/activemq/artemis/core/server/RoutingContext.clear:()V
     191: goto          208
     194: astore        4
     196: aload_0
     197: getfield      #12                 // Field routingContext:Lorg/apache/activemq/artemis/core/server/RoutingContext;
     200: invokeinterface #391,  1          // InterfaceMethod org/apache/activemq/artemis/core/server/RoutingContext.clear:()V
     205: aload         4
     207: athrow
     208: return
    Exception table:
       from    to  target type
           0    19    22   Class org/apache/activemq/artemis/api/core/ActiveMQException
          79   182   194   any
         194   196   194   any

  public java.util.List<org.apache.activemq.artemis.core.server.MessageReference> getInTXMessagesForConsumer(long);
    Code:
       0: aload_0
       1: getfield      #45                 // Field tx:Lorg/apache/activemq/artemis/core/transaction/Transaction;
       4: ifnull        36
       7: aload_0
       8: getfield      #45                 // Field tx:Lorg/apache/activemq/artemis/core/transaction/Transaction;
      11: bipush        6
      13: invokeinterface #393,  2          // InterfaceMethod org/apache/activemq/artemis/core/transaction/Transaction.getProperty:(I)Ljava/lang/Object;
      18: checkcast     #394                // class org/apache/activemq/artemis/core/server/impl/RefsOperation
      21: astore_3
      22: aload_3
      23: ifnonnull     30
      26: invokestatic  #395                // Method java/util/Collections.emptyList:()Ljava/util/List;
      29: areturn
      30: aload_3
      31: lload_1
      32: invokevirtual #396                // Method org/apache/activemq/artemis/core/server/impl/RefsOperation.getListOnConsumer:(J)Ljava/util/List;
      35: areturn
      36: invokestatic  #395                // Method java/util/Collections.emptyList:()Ljava/util/List;
      39: areturn

  static {};
    Code:
       0: getstatic     #61                 // Field org/apache/activemq/artemis/core/server/ActiveMQServerLogger.LOGGER:Lorg/apache/activemq/artemis/core/server/ActiveMQServerLogger;
       3: invokeinterface #288,  1          // InterfaceMethod org/apache/activemq/artemis/core/server/ActiveMQServerLogger.isTraceEnabled:()Z
       8: putstatic     #202                // Field isTrace:Z
      11: return
}
