Compiled from "ServerConsumerImpl.java"
final class org.apache.activemq.artemis.core.server.impl.ServerConsumerImpl$LargeMessageDeliverer {
  private long sizePendingLargeMessage;

  private org.apache.activemq.artemis.core.server.LargeServerMessage largeMessage;

  private final org.apache.activemq.artemis.core.server.MessageReference ref;

  private boolean sentInitialPacket;

  private long positionPendingLargeMessage;

  private org.apache.activemq.artemis.core.message.BodyEncoder context;

  final org.apache.activemq.artemis.core.server.impl.ServerConsumerImpl this$0;

  public org.apache.activemq.artemis.core.server.impl.ServerConsumerImpl$LargeMessageDeliverer(org.apache.activemq.artemis.core.server.impl.ServerConsumerImpl, org.apache.activemq.artemis.core.server.LargeServerMessage, org.apache.activemq.artemis.core.server.MessageReference) throws java.lang.Exception;
    Code:
       0: aload_0
       1: aload_1
       2: putfield      #1                  // Field this$0:Lorg/apache/activemq/artemis/core/server/impl/ServerConsumerImpl;
       5: aload_0
       6: invokespecial #2                  // Method java/lang/Object."<init>":()V
       9: aload_0
      10: iconst_0
      11: putfield      #3                  // Field sentInitialPacket:Z
      14: aload_0
      15: aload_2
      16: putfield      #4                  // Field largeMessage:Lorg/apache/activemq/artemis/core/server/LargeServerMessage;
      19: aload_0
      20: getfield      #4                  // Field largeMessage:Lorg/apache/activemq/artemis/core/server/LargeServerMessage;
      23: invokeinterface #5,  1            // InterfaceMethod org/apache/activemq/artemis/core/server/LargeServerMessage.incrementDelayDeletionCount:()V
      28: aload_0
      29: aload_3
      30: putfield      #6                  // Field ref:Lorg/apache/activemq/artemis/core/server/MessageReference;
      33: return

  public boolean deliver() throws java.lang.Exception;
    Code:
       0: aload_0
       1: getfield      #1                  // Field this$0:Lorg/apache/activemq/artemis/core/server/impl/ServerConsumerImpl;
       4: invokestatic  #7                  // Method org/apache/activemq/artemis/core/server/impl/ServerConsumerImpl.access$600:(Lorg/apache/activemq/artemis/core/server/impl/ServerConsumerImpl;)Ljava/util/concurrent/locks/ReadWriteLock;
       7: invokeinterface #8,  1            // InterfaceMethod java/util/concurrent/locks/ReadWriteLock.readLock:()Ljava/util/concurrent/locks/Lock;
      12: invokeinterface #9,  1            // InterfaceMethod java/util/concurrent/locks/Lock.lock:()V
      17: aload_0
      18: getfield      #4                  // Field largeMessage:Lorg/apache/activemq/artemis/core/server/LargeServerMessage;
      21: astore_1
      22: aload_1
      23: ifnonnull     47
      26: iconst_1
      27: istore_2
      28: aload_0
      29: getfield      #1                  // Field this$0:Lorg/apache/activemq/artemis/core/server/impl/ServerConsumerImpl;
      32: invokestatic  #7                  // Method org/apache/activemq/artemis/core/server/impl/ServerConsumerImpl.access$600:(Lorg/apache/activemq/artemis/core/server/impl/ServerConsumerImpl;)Ljava/util/concurrent/locks/ReadWriteLock;
      35: invokeinterface #8,  1            // InterfaceMethod java/util/concurrent/locks/ReadWriteLock.readLock:()Ljava/util/concurrent/locks/Lock;
      40: invokeinterface #10,  1           // InterfaceMethod java/util/concurrent/locks/Lock.unlock:()V
      45: iload_2
      46: ireturn
      47: aload_0
      48: getfield      #1                  // Field this$0:Lorg/apache/activemq/artemis/core/server/impl/ServerConsumerImpl;
      51: invokestatic  #11                 // Method org/apache/activemq/artemis/core/server/impl/ServerConsumerImpl.access$700:(Lorg/apache/activemq/artemis/core/server/impl/ServerConsumerImpl;)Ljava/util/concurrent/atomic/AtomicInteger;
      54: ifnull        139
      57: aload_0
      58: getfield      #1                  // Field this$0:Lorg/apache/activemq/artemis/core/server/impl/ServerConsumerImpl;
      61: invokestatic  #11                 // Method org/apache/activemq/artemis/core/server/impl/ServerConsumerImpl.access$700:(Lorg/apache/activemq/artemis/core/server/impl/ServerConsumerImpl;)Ljava/util/concurrent/atomic/AtomicInteger;
      64: invokevirtual #12                 // Method java/util/concurrent/atomic/AtomicInteger.get:()I
      67: ifgt          139
      70: getstatic     #13                 // Field org/apache/activemq/artemis/core/server/ActiveMQServerLogger.LOGGER:Lorg/apache/activemq/artemis/core/server/ActiveMQServerLogger;
      73: invokeinterface #14,  1           // InterfaceMethod org/apache/activemq/artemis/core/server/ActiveMQServerLogger.isTraceEnabled:()Z
      78: ifeq          118
      81: getstatic     #13                 // Field org/apache/activemq/artemis/core/server/ActiveMQServerLogger.LOGGER:Lorg/apache/activemq/artemis/core/server/ActiveMQServerLogger;
      84: new           #15                 // class java/lang/StringBuilder
      87: dup
      88: invokespecial #16                 // Method java/lang/StringBuilder."<init>":()V
      91: aload_0
      92: invokevirtual #17                 // Method java/lang/StringBuilder.append:(Ljava/lang/Object;)Ljava/lang/StringBuilder;
      95: ldc           #18                 // String ::FlowControl::delivery largeMessage interrupting as there are no more credits, available=
      97: invokevirtual #19                 // Method java/lang/StringBuilder.append:(Ljava/lang/String;)Ljava/lang/StringBuilder;
     100: aload_0
     101: getfield      #1                  // Field this$0:Lorg/apache/activemq/artemis/core/server/impl/ServerConsumerImpl;
     104: invokestatic  #11                 // Method org/apache/activemq/artemis/core/server/impl/ServerConsumerImpl.access$700:(Lorg/apache/activemq/artemis/core/server/impl/ServerConsumerImpl;)Ljava/util/concurrent/atomic/AtomicInteger;
     107: invokevirtual #17                 // Method java/lang/StringBuilder.append:(Ljava/lang/Object;)Ljava/lang/StringBuilder;
     110: invokevirtual #20                 // Method java/lang/StringBuilder.toString:()Ljava/lang/String;
     113: invokeinterface #21,  2           // InterfaceMethod org/apache/activemq/artemis/core/server/ActiveMQServerLogger.trace:(Ljava/lang/Object;)V
     118: iconst_0
     119: istore_2
     120: aload_0
     121: getfield      #1                  // Field this$0:Lorg/apache/activemq/artemis/core/server/impl/ServerConsumerImpl;
     124: invokestatic  #7                  // Method org/apache/activemq/artemis/core/server/impl/ServerConsumerImpl.access$600:(Lorg/apache/activemq/artemis/core/server/impl/ServerConsumerImpl;)Ljava/util/concurrent/locks/ReadWriteLock;
     127: invokeinterface #8,  1            // InterfaceMethod java/util/concurrent/locks/ReadWriteLock.readLock:()Ljava/util/concurrent/locks/Lock;
     132: invokeinterface #10,  1           // InterfaceMethod java/util/concurrent/locks/Lock.unlock:()V
     137: iload_2
     138: ireturn
     139: aload_0
     140: getfield      #3                  // Field sentInitialPacket:Z
     143: ifne          332
     146: aload_0
     147: aload_1
     148: invokeinterface #22,  1           // InterfaceMethod org/apache/activemq/artemis/core/server/LargeServerMessage.getBodyEncoder:()Lorg/apache/activemq/artemis/core/message/BodyEncoder;
     153: putfield      #23                 // Field context:Lorg/apache/activemq/artemis/core/message/BodyEncoder;
     156: aload_0
     157: aload_0
     158: getfield      #23                 // Field context:Lorg/apache/activemq/artemis/core/message/BodyEncoder;
     161: invokeinterface #24,  1           // InterfaceMethod org/apache/activemq/artemis/core/message/BodyEncoder.getLargeBodySize:()J
     166: putfield      #25                 // Field sizePendingLargeMessage:J
     169: aload_0
     170: getfield      #23                 // Field context:Lorg/apache/activemq/artemis/core/message/BodyEncoder;
     173: invokeinterface #26,  1           // InterfaceMethod org/apache/activemq/artemis/core/message/BodyEncoder.open:()V
     178: aload_0
     179: iconst_1
     180: putfield      #3                  // Field sentInitialPacket:Z
     183: aload_0
     184: getfield      #1                  // Field this$0:Lorg/apache/activemq/artemis/core/server/impl/ServerConsumerImpl;
     187: invokestatic  #27                 // Method org/apache/activemq/artemis/core/server/impl/ServerConsumerImpl.access$300:(Lorg/apache/activemq/artemis/core/server/impl/ServerConsumerImpl;)Lorg/apache/activemq/artemis/spi/core/protocol/SessionCallback;
     190: aload_1
     191: aload_0
     192: getfield      #1                  // Field this$0:Lorg/apache/activemq/artemis/core/server/impl/ServerConsumerImpl;
     195: aload_0
     196: getfield      #23                 // Field context:Lorg/apache/activemq/artemis/core/message/BodyEncoder;
     199: invokeinterface #24,  1           // InterfaceMethod org/apache/activemq/artemis/core/message/BodyEncoder.getLargeBodySize:()J
     204: aload_0
     205: getfield      #6                  // Field ref:Lorg/apache/activemq/artemis/core/server/MessageReference;
     208: invokeinterface #28,  1           // InterfaceMethod org/apache/activemq/artemis/core/server/MessageReference.getDeliveryCount:()I
     213: invokeinterface #29,  6           // InterfaceMethod org/apache/activemq/artemis/spi/core/protocol/SessionCallback.sendLargeMessage:(Lorg/apache/activemq/artemis/core/server/ServerMessage;Lorg/apache/activemq/artemis/core/server/ServerConsumer;JI)I
     218: istore_2
     219: aload_0
     220: getfield      #1                  // Field this$0:Lorg/apache/activemq/artemis/core/server/impl/ServerConsumerImpl;
     223: invokestatic  #11                 // Method org/apache/activemq/artemis/core/server/impl/ServerConsumerImpl.access$700:(Lorg/apache/activemq/artemis/core/server/impl/ServerConsumerImpl;)Ljava/util/concurrent/atomic/AtomicInteger;
     226: ifnull        304
     229: aload_0
     230: getfield      #1                  // Field this$0:Lorg/apache/activemq/artemis/core/server/impl/ServerConsumerImpl;
     233: invokestatic  #11                 // Method org/apache/activemq/artemis/core/server/impl/ServerConsumerImpl.access$700:(Lorg/apache/activemq/artemis/core/server/impl/ServerConsumerImpl;)Ljava/util/concurrent/atomic/AtomicInteger;
     236: iload_2
     237: ineg
     238: invokevirtual #30                 // Method java/util/concurrent/atomic/AtomicInteger.addAndGet:(I)I
     241: pop
     242: getstatic     #13                 // Field org/apache/activemq/artemis/core/server/ActiveMQServerLogger.LOGGER:Lorg/apache/activemq/artemis/core/server/ActiveMQServerLogger;
     245: invokeinterface #14,  1           // InterfaceMethod org/apache/activemq/artemis/core/server/ActiveMQServerLogger.isTraceEnabled:()Z
     250: ifeq          304
     253: getstatic     #13                 // Field org/apache/activemq/artemis/core/server/ActiveMQServerLogger.LOGGER:Lorg/apache/activemq/artemis/core/server/ActiveMQServerLogger;
     256: new           #15                 // class java/lang/StringBuilder
     259: dup
     260: invokespecial #16                 // Method java/lang/StringBuilder."<init>":()V
     263: aload_0
     264: invokevirtual #17                 // Method java/lang/StringBuilder.append:(Ljava/lang/Object;)Ljava/lang/StringBuilder;
     267: ldc           #31                 // String ::FlowControl::
     269: invokevirtual #19                 // Method java/lang/StringBuilder.append:(Ljava/lang/String;)Ljava/lang/StringBuilder;
     272: ldc           #32                 // String  deliver initialpackage with
     274: invokevirtual #19                 // Method java/lang/StringBuilder.append:(Ljava/lang/String;)Ljava/lang/StringBuilder;
     277: iload_2
     278: invokevirtual #33                 // Method java/lang/StringBuilder.append:(I)Ljava/lang/StringBuilder;
     281: ldc           #34                 // String  delivered, available now =
     283: invokevirtual #19                 // Method java/lang/StringBuilder.append:(Ljava/lang/String;)Ljava/lang/StringBuilder;
     286: aload_0
     287: getfield      #1                  // Field this$0:Lorg/apache/activemq/artemis/core/server/impl/ServerConsumerImpl;
     290: invokestatic  #11                 // Method org/apache/activemq/artemis/core/server/impl/ServerConsumerImpl.access$700:(Lorg/apache/activemq/artemis/core/server/impl/ServerConsumerImpl;)Ljava/util/concurrent/atomic/AtomicInteger;
     293: invokevirtual #17                 // Method java/lang/StringBuilder.append:(Ljava/lang/Object;)Ljava/lang/StringBuilder;
     296: invokevirtual #20                 // Method java/lang/StringBuilder.toString:()Ljava/lang/String;
     299: invokeinterface #21,  2           // InterfaceMethod org/apache/activemq/artemis/core/server/ActiveMQServerLogger.trace:(Ljava/lang/Object;)V
     304: aload_0
     305: getfield      #1                  // Field this$0:Lorg/apache/activemq/artemis/core/server/impl/ServerConsumerImpl;
     308: invokestatic  #35                 // Method org/apache/activemq/artemis/core/server/impl/ServerConsumerImpl.access$800:(Lorg/apache/activemq/artemis/core/server/impl/ServerConsumerImpl;)V
     311: iconst_0
     312: istore_3
     313: aload_0
     314: getfield      #1                  // Field this$0:Lorg/apache/activemq/artemis/core/server/impl/ServerConsumerImpl;
     317: invokestatic  #7                  // Method org/apache/activemq/artemis/core/server/impl/ServerConsumerImpl.access$600:(Lorg/apache/activemq/artemis/core/server/impl/ServerConsumerImpl;)Ljava/util/concurrent/locks/ReadWriteLock;
     320: invokeinterface #8,  1            // InterfaceMethod java/util/concurrent/locks/ReadWriteLock.readLock:()Ljava/util/concurrent/locks/Lock;
     325: invokeinterface #10,  1           // InterfaceMethod java/util/concurrent/locks/Lock.unlock:()V
     330: iload_3
     331: ireturn
     332: aload_0
     333: getfield      #1                  // Field this$0:Lorg/apache/activemq/artemis/core/server/impl/ServerConsumerImpl;
     336: invokestatic  #11                 // Method org/apache/activemq/artemis/core/server/impl/ServerConsumerImpl.access$700:(Lorg/apache/activemq/artemis/core/server/impl/ServerConsumerImpl;)Ljava/util/concurrent/atomic/AtomicInteger;
     339: ifnull        419
     342: aload_0
     343: getfield      #1                  // Field this$0:Lorg/apache/activemq/artemis/core/server/impl/ServerConsumerImpl;
     346: invokestatic  #11                 // Method org/apache/activemq/artemis/core/server/impl/ServerConsumerImpl.access$700:(Lorg/apache/activemq/artemis/core/server/impl/ServerConsumerImpl;)Ljava/util/concurrent/atomic/AtomicInteger;
     349: invokevirtual #12                 // Method java/util/concurrent/atomic/AtomicInteger.get:()I
     352: ifgt          419
     355: invokestatic  #36                 // Method org/apache/activemq/artemis/core/server/impl/ServerConsumerImpl.access$900:()Z
     358: ifeq          398
     361: getstatic     #13                 // Field org/apache/activemq/artemis/core/server/ActiveMQServerLogger.LOGGER:Lorg/apache/activemq/artemis/core/server/ActiveMQServerLogger;
     364: new           #15                 // class java/lang/StringBuilder
     367: dup
     368: invokespecial #16                 // Method java/lang/StringBuilder."<init>":()V
     371: aload_0
     372: invokevirtual #17                 // Method java/lang/StringBuilder.append:(Ljava/lang/Object;)Ljava/lang/StringBuilder;
     375: ldc           #37                 // String ::FlowControl::deliverLargeMessage Leaving loop of send LargeMessage because of credits, available=
     377: invokevirtual #19                 // Method java/lang/StringBuilder.append:(Ljava/lang/String;)Ljava/lang/StringBuilder;
     380: aload_0
     381: getfield      #1                  // Field this$0:Lorg/apache/activemq/artemis/core/server/impl/ServerConsumerImpl;
     384: invokestatic  #11                 // Method org/apache/activemq/artemis/core/server/impl/ServerConsumerImpl.access$700:(Lorg/apache/activemq/artemis/core/server/impl/ServerConsumerImpl;)Ljava/util/concurrent/atomic/AtomicInteger;
     387: invokevirtual #17                 // Method java/lang/StringBuilder.append:(Ljava/lang/Object;)Ljava/lang/StringBuilder;
     390: invokevirtual #20                 // Method java/lang/StringBuilder.toString:()Ljava/lang/String;
     393: invokeinterface #21,  2           // InterfaceMethod org/apache/activemq/artemis/core/server/ActiveMQServerLogger.trace:(Ljava/lang/Object;)V
     398: iconst_0
     399: istore_2
     400: aload_0
     401: getfield      #1                  // Field this$0:Lorg/apache/activemq/artemis/core/server/impl/ServerConsumerImpl;
     404: invokestatic  #7                  // Method org/apache/activemq/artemis/core/server/impl/ServerConsumerImpl.access$600:(Lorg/apache/activemq/artemis/core/server/impl/ServerConsumerImpl;)Ljava/util/concurrent/locks/ReadWriteLock;
     407: invokeinterface #8,  1            // InterfaceMethod java/util/concurrent/locks/ReadWriteLock.readLock:()Ljava/util/concurrent/locks/Lock;
     412: invokeinterface #10,  1           // InterfaceMethod java/util/concurrent/locks/Lock.unlock:()V
     417: iload_2
     418: ireturn
     419: iconst_0
     420: istore_2
     421: aload_0
     422: getfield      #25                 // Field sizePendingLargeMessage:J
     425: aload_0
     426: getfield      #38                 // Field positionPendingLargeMessage:J
     429: lsub
     430: aload_0
     431: getfield      #1                  // Field this$0:Lorg/apache/activemq/artemis/core/server/impl/ServerConsumerImpl;
     434: invokestatic  #39                 // Method org/apache/activemq/artemis/core/server/impl/ServerConsumerImpl.access$1000:(Lorg/apache/activemq/artemis/core/server/impl/ServerConsumerImpl;)I
     437: i2l
     438: invokestatic  #40                 // Method java/lang/Math.min:(JJ)J
     441: l2i
     442: istore_2
     443: iload_2
     444: invokestatic  #41                 // Method org/apache/activemq/artemis/api/core/ActiveMQBuffers.fixedBuffer:(I)Lorg/apache/activemq/artemis/api/core/ActiveMQBuffer;
     447: astore_3
     448: aload_0
     449: getfield      #23                 // Field context:Lorg/apache/activemq/artemis/core/message/BodyEncoder;
     452: aload_3
     453: iload_2
     454: invokeinterface #42,  3           // InterfaceMethod org/apache/activemq/artemis/core/message/BodyEncoder.encode:(Lorg/apache/activemq/artemis/api/core/ActiveMQBuffer;I)I
     459: pop
     460: aload_3
     461: invokeinterface #43,  1           // InterfaceMethod org/apache/activemq/artemis/api/core/ActiveMQBuffer.toByteBuffer:()Ljava/nio/ByteBuffer;
     466: invokevirtual #44                 // Method java/nio/ByteBuffer.hasArray:()Z
     469: ifeq          486
     472: aload_3
     473: invokeinterface #43,  1           // InterfaceMethod org/apache/activemq/artemis/api/core/ActiveMQBuffer.toByteBuffer:()Ljava/nio/ByteBuffer;
     478: invokevirtual #45                 // Method java/nio/ByteBuffer.array:()[B
     481: astore        4
     483: goto          491
     486: iconst_0
     487: newarray       byte
     489: astore        4
     491: aload_0
     492: getfield      #1                  // Field this$0:Lorg/apache/activemq/artemis/core/server/impl/ServerConsumerImpl;
     495: invokestatic  #27                 // Method org/apache/activemq/artemis/core/server/impl/ServerConsumerImpl.access$300:(Lorg/apache/activemq/artemis/core/server/impl/ServerConsumerImpl;)Lorg/apache/activemq/artemis/spi/core/protocol/SessionCallback;
     498: aload_0
     499: getfield      #1                  // Field this$0:Lorg/apache/activemq/artemis/core/server/impl/ServerConsumerImpl;
     502: aload         4
     504: aload_0
     505: getfield      #38                 // Field positionPendingLargeMessage:J
     508: iload_2
     509: i2l
     510: ladd
     511: aload_0
     512: getfield      #25                 // Field sizePendingLargeMessage:J
     515: lcmp
     516: ifge          523
     519: iconst_1
     520: goto          524
     523: iconst_0
     524: iconst_0
     525: invokeinterface #46,  5           // InterfaceMethod org/apache/activemq/artemis/spi/core/protocol/SessionCallback.sendLargeMessageContinuation:(Lorg/apache/activemq/artemis/core/server/ServerConsumer;[BZZ)I
     530: istore        5
     532: aload         4
     534: arraylength
     535: istore        6
     537: aload_0
     538: getfield      #1                  // Field this$0:Lorg/apache/activemq/artemis/core/server/impl/ServerConsumerImpl;
     541: invokestatic  #11                 // Method org/apache/activemq/artemis/core/server/impl/ServerConsumerImpl.access$700:(Lorg/apache/activemq/artemis/core/server/impl/ServerConsumerImpl;)Ljava/util/concurrent/atomic/AtomicInteger;
     544: ifnull        619
     547: aload_0
     548: getfield      #1                  // Field this$0:Lorg/apache/activemq/artemis/core/server/impl/ServerConsumerImpl;
     551: invokestatic  #11                 // Method org/apache/activemq/artemis/core/server/impl/ServerConsumerImpl.access$700:(Lorg/apache/activemq/artemis/core/server/impl/ServerConsumerImpl;)Ljava/util/concurrent/atomic/AtomicInteger;
     554: iload         5
     556: ineg
     557: invokevirtual #30                 // Method java/util/concurrent/atomic/AtomicInteger.addAndGet:(I)I
     560: pop
     561: getstatic     #13                 // Field org/apache/activemq/artemis/core/server/ActiveMQServerLogger.LOGGER:Lorg/apache/activemq/artemis/core/server/ActiveMQServerLogger;
     564: invokeinterface #14,  1           // InterfaceMethod org/apache/activemq/artemis/core/server/ActiveMQServerLogger.isTraceEnabled:()Z
     569: ifeq          619
     572: getstatic     #13                 // Field org/apache/activemq/artemis/core/server/ActiveMQServerLogger.LOGGER:Lorg/apache/activemq/artemis/core/server/ActiveMQServerLogger;
     575: new           #15                 // class java/lang/StringBuilder
     578: dup
     579: invokespecial #16                 // Method java/lang/StringBuilder."<init>":()V
     582: aload_0
     583: invokevirtual #17                 // Method java/lang/StringBuilder.append:(Ljava/lang/Object;)Ljava/lang/StringBuilder;
     586: ldc           #47                 // String ::FlowControl::largeMessage deliver continuation, packetSize=
     588: invokevirtual #19                 // Method java/lang/StringBuilder.append:(Ljava/lang/String;)Ljava/lang/StringBuilder;
     591: iload         5
     593: invokevirtual #33                 // Method java/lang/StringBuilder.append:(I)Ljava/lang/StringBuilder;
     596: ldc           #48                 // String  available now=
     598: invokevirtual #19                 // Method java/lang/StringBuilder.append:(Ljava/lang/String;)Ljava/lang/StringBuilder;
     601: aload_0
     602: getfield      #1                  // Field this$0:Lorg/apache/activemq/artemis/core/server/impl/ServerConsumerImpl;
     605: invokestatic  #11                 // Method org/apache/activemq/artemis/core/server/impl/ServerConsumerImpl.access$700:(Lorg/apache/activemq/artemis/core/server/impl/ServerConsumerImpl;)Ljava/util/concurrent/atomic/AtomicInteger;
     608: invokevirtual #17                 // Method java/lang/StringBuilder.append:(Ljava/lang/Object;)Ljava/lang/StringBuilder;
     611: invokevirtual #20                 // Method java/lang/StringBuilder.toString:()Ljava/lang/String;
     614: invokeinterface #21,  2           // InterfaceMethod org/apache/activemq/artemis/core/server/ActiveMQServerLogger.trace:(Ljava/lang/Object;)V
     619: aload_0
     620: dup
     621: getfield      #38                 // Field positionPendingLargeMessage:J
     624: iload         6
     626: i2l
     627: ladd
     628: putfield      #38                 // Field positionPendingLargeMessage:J
     631: aload_0
     632: getfield      #38                 // Field positionPendingLargeMessage:J
     635: aload_0
     636: getfield      #25                 // Field sizePendingLargeMessage:J
     639: lcmp
     640: ifge          673
     643: aload_0
     644: getfield      #1                  // Field this$0:Lorg/apache/activemq/artemis/core/server/impl/ServerConsumerImpl;
     647: invokestatic  #35                 // Method org/apache/activemq/artemis/core/server/impl/ServerConsumerImpl.access$800:(Lorg/apache/activemq/artemis/core/server/impl/ServerConsumerImpl;)V
     650: iconst_0
     651: istore        7
     653: aload_0
     654: getfield      #1                  // Field this$0:Lorg/apache/activemq/artemis/core/server/impl/ServerConsumerImpl;
     657: invokestatic  #7                  // Method org/apache/activemq/artemis/core/server/impl/ServerConsumerImpl.access$600:(Lorg/apache/activemq/artemis/core/server/impl/ServerConsumerImpl;)Ljava/util/concurrent/locks/ReadWriteLock;
     660: invokeinterface #8,  1            // InterfaceMethod java/util/concurrent/locks/ReadWriteLock.readLock:()Ljava/util/concurrent/locks/Lock;
     665: invokeinterface #10,  1           // InterfaceMethod java/util/concurrent/locks/Lock.unlock:()V
     670: iload         7
     672: ireturn
     673: invokestatic  #36                 // Method org/apache/activemq/artemis/core/server/impl/ServerConsumerImpl.access$900:()Z
     676: ifeq          689
     679: getstatic     #13                 // Field org/apache/activemq/artemis/core/server/ActiveMQServerLogger.LOGGER:Lorg/apache/activemq/artemis/core/server/ActiveMQServerLogger;
     682: ldc           #49                 // String Finished deliverLargeMessage
     684: invokeinterface #21,  2           // InterfaceMethod org/apache/activemq/artemis/core/server/ActiveMQServerLogger.trace:(Ljava/lang/Object;)V
     689: aload_0
     690: invokevirtual #50                 // Method finish:()V
     693: iconst_1
     694: istore_2
     695: aload_0
     696: getfield      #1                  // Field this$0:Lorg/apache/activemq/artemis/core/server/impl/ServerConsumerImpl;
     699: invokestatic  #7                  // Method org/apache/activemq/artemis/core/server/impl/ServerConsumerImpl.access$600:(Lorg/apache/activemq/artemis/core/server/impl/ServerConsumerImpl;)Ljava/util/concurrent/locks/ReadWriteLock;
     702: invokeinterface #8,  1            // InterfaceMethod java/util/concurrent/locks/ReadWriteLock.readLock:()Ljava/util/concurrent/locks/Lock;
     707: invokeinterface #10,  1           // InterfaceMethod java/util/concurrent/locks/Lock.unlock:()V
     712: iload_2
     713: ireturn
     714: astore        8
     716: aload_0
     717: getfield      #1                  // Field this$0:Lorg/apache/activemq/artemis/core/server/impl/ServerConsumerImpl;
     720: invokestatic  #7                  // Method org/apache/activemq/artemis/core/server/impl/ServerConsumerImpl.access$600:(Lorg/apache/activemq/artemis/core/server/impl/ServerConsumerImpl;)Ljava/util/concurrent/locks/ReadWriteLock;
     723: invokeinterface #8,  1            // InterfaceMethod java/util/concurrent/locks/ReadWriteLock.readLock:()Ljava/util/concurrent/locks/Lock;
     728: invokeinterface #10,  1           // InterfaceMethod java/util/concurrent/locks/Lock.unlock:()V
     733: aload         8
     735: athrow
    Exception table:
       from    to  target type
          17    28   714   any
          47   120   714   any
         139   313   714   any
         332   400   714   any
         419   653   714   any
         673   695   714   any
         714   716   714   any

  public void finish() throws java.lang.Exception;
    Code:
       0: aload_0
       1: getfield      #1                  // Field this$0:Lorg/apache/activemq/artemis/core/server/impl/ServerConsumerImpl;
       4: invokestatic  #51                 // Method org/apache/activemq/artemis/core/server/impl/ServerConsumerImpl.access$000:(Lorg/apache/activemq/artemis/core/server/impl/ServerConsumerImpl;)Ljava/lang/Object;
       7: dup
       8: astore_1
       9: monitorenter
      10: aload_0
      11: getfield      #4                  // Field largeMessage:Lorg/apache/activemq/artemis/core/server/LargeServerMessage;
      14: ifnonnull     20
      17: aload_1
      18: monitorexit
      19: return
      20: aload_0
      21: getfield      #23                 // Field context:Lorg/apache/activemq/artemis/core/message/BodyEncoder;
      24: ifnull        36
      27: aload_0
      28: getfield      #23                 // Field context:Lorg/apache/activemq/artemis/core/message/BodyEncoder;
      31: invokeinterface #52,  1           // InterfaceMethod org/apache/activemq/artemis/core/message/BodyEncoder.close:()V
      36: aload_0
      37: getfield      #4                  // Field largeMessage:Lorg/apache/activemq/artemis/core/server/LargeServerMessage;
      40: invokeinterface #53,  1           // InterfaceMethod org/apache/activemq/artemis/core/server/LargeServerMessage.releaseResources:()V
      45: aload_0
      46: getfield      #4                  // Field largeMessage:Lorg/apache/activemq/artemis/core/server/LargeServerMessage;
      49: invokeinterface #54,  1           // InterfaceMethod org/apache/activemq/artemis/core/server/LargeServerMessage.decrementDelayDeletionCount:()V
      54: aload_0
      55: getfield      #1                  // Field this$0:Lorg/apache/activemq/artemis/core/server/impl/ServerConsumerImpl;
      58: invokestatic  #55                 // Method org/apache/activemq/artemis/core/server/impl/ServerConsumerImpl.access$1100:(Lorg/apache/activemq/artemis/core/server/impl/ServerConsumerImpl;)Z
      61: ifeq          83
      64: aload_0
      65: getfield      #1                  // Field this$0:Lorg/apache/activemq/artemis/core/server/impl/ServerConsumerImpl;
      68: invokestatic  #56                 // Method org/apache/activemq/artemis/core/server/impl/ServerConsumerImpl.access$1200:(Lorg/apache/activemq/artemis/core/server/impl/ServerConsumerImpl;)Z
      71: ifne          83
      74: aload_0
      75: getfield      #4                  // Field largeMessage:Lorg/apache/activemq/artemis/core/server/LargeServerMessage;
      78: invokeinterface #54,  1           // InterfaceMethod org/apache/activemq/artemis/core/server/LargeServerMessage.decrementDelayDeletionCount:()V
      83: aload_0
      84: getfield      #1                  // Field this$0:Lorg/apache/activemq/artemis/core/server/impl/ServerConsumerImpl;
      87: aconst_null
      88: invokestatic  #57                 // Method org/apache/activemq/artemis/core/server/impl/ServerConsumerImpl.access$402:(Lorg/apache/activemq/artemis/core/server/impl/ServerConsumerImpl;Lorg/apache/activemq/artemis/core/server/impl/ServerConsumerImpl$LargeMessageDeliverer;)Lorg/apache/activemq/artemis/core/server/impl/ServerConsumerImpl$LargeMessageDeliverer;
      91: pop
      92: aload_0
      93: aconst_null
      94: putfield      #4                  // Field largeMessage:Lorg/apache/activemq/artemis/core/server/LargeServerMessage;
      97: aload_1
      98: monitorexit
      99: goto          107
     102: astore_2
     103: aload_1
     104: monitorexit
     105: aload_2
     106: athrow
     107: return
    Exception table:
       from    to  target type
          10    19   102   any
          20    99   102   any
         102   105   102   any
}
