Compiled from "JsonFormatTypes.java"
public final class com.fasterxml.jackson.databind.jsonFormatVisitors.JsonFormatTypes extends java.lang.Enum<com.fasterxml.jackson.databind.jsonFormatVisitors.JsonFormatTypes> {
  public static final com.fasterxml.jackson.databind.jsonFormatVisitors.JsonFormatTypes STRING;

  public static final com.fasterxml.jackson.databind.jsonFormatVisitors.JsonFormatTypes NUMBER;

  public static final com.fasterxml.jackson.databind.jsonFormatVisitors.JsonFormatTypes INTEGER;

  public static final com.fasterxml.jackson.databind.jsonFormatVisitors.JsonFormatTypes BOOLEAN;

  public static final com.fasterxml.jackson.databind.jsonFormatVisitors.JsonFormatTypes OBJECT;

  public static final com.fasterxml.jackson.databind.jsonFormatVisitors.JsonFormatTypes ARRAY;

  public static final com.fasterxml.jackson.databind.jsonFormatVisitors.JsonFormatTypes NULL;

  public static final com.fasterxml.jackson.databind.jsonFormatVisitors.JsonFormatTypes ANY;

  private static final java.util.Map<java.lang.String, com.fasterxml.jackson.databind.jsonFormatVisitors.JsonFormatTypes> _byLCName;

  private static final com.fasterxml.jackson.databind.jsonFormatVisitors.JsonFormatTypes[] $VALUES;

  public static com.fasterxml.jackson.databind.jsonFormatVisitors.JsonFormatTypes[] values();
    Code:
       0: getstatic     #1                  // Field $VALUES:[Lcom/fasterxml/jackson/databind/jsonFormatVisitors/JsonFormatTypes;
       3: invokevirtual #2                  // Method "[Lcom/fasterxml/jackson/databind/jsonFormatVisitors/JsonFormatTypes;".clone:()Ljava/lang/Object;
       6: checkcast     #3                  // class "[Lcom/fasterxml/jackson/databind/jsonFormatVisitors/JsonFormatTypes;"
       9: areturn

  public static com.fasterxml.jackson.databind.jsonFormatVisitors.JsonFormatTypes valueOf(java.lang.String);
    Code:
       0: ldc           #4                  // class com/fasterxml/jackson/databind/jsonFormatVisitors/JsonFormatTypes
       2: aload_0
       3: invokestatic  #5                  // Method java/lang/Enum.valueOf:(Ljava/lang/Class;Ljava/lang/String;)Ljava/lang/Enum;
       6: checkcast     #4                  // class com/fasterxml/jackson/databind/jsonFormatVisitors/JsonFormatTypes
       9: areturn

  private com.fasterxml.jackson.databind.jsonFormatVisitors.JsonFormatTypes();
    Code:
       0: aload_0
       1: aload_1
       2: iload_2
       3: invokespecial #6                  // Method java/lang/Enum."<init>":(Ljava/lang/String;I)V
       6: return

  public java.lang.String value();
    Code:
       0: aload_0
       1: invokevirtual #7                  // Method name:()Ljava/lang/String;
       4: invokevirtual #8                  // Method java/lang/String.toLowerCase:()Ljava/lang/String;
       7: areturn

  public static com.fasterxml.jackson.databind.jsonFormatVisitors.JsonFormatTypes forValue(java.lang.String);
    Code:
       0: getstatic     #9                  // Field _byLCName:Ljava/util/Map;
       3: aload_0
       4: invokeinterface #10,  2           // InterfaceMethod java/util/Map.get:(Ljava/lang/Object;)Ljava/lang/Object;
       9: checkcast     #4                  // class com/fasterxml/jackson/databind/jsonFormatVisitors/JsonFormatTypes
      12: areturn

  static {};
    Code:
       0: new           #4                  // class com/fasterxml/jackson/databind/jsonFormatVisitors/JsonFormatTypes
       3: dup
       4: ldc           #11                 // String STRING
       6: iconst_0
       7: invokespecial #12                 // Method "<init>":(Ljava/lang/String;I)V
      10: putstatic     #13                 // Field STRING:Lcom/fasterxml/jackson/databind/jsonFormatVisitors/JsonFormatTypes;
      13: new           #4                  // class com/fasterxml/jackson/databind/jsonFormatVisitors/JsonFormatTypes
      16: dup
      17: ldc           #14                 // String NUMBER
      19: iconst_1
      20: invokespecial #12                 // Method "<init>":(Ljava/lang/String;I)V
      23: putstatic     #15                 // Field NUMBER:Lcom/fasterxml/jackson/databind/jsonFormatVisitors/JsonFormatTypes;
      26: new           #4                  // class com/fasterxml/jackson/databind/jsonFormatVisitors/JsonFormatTypes
      29: dup
      30: ldc           #16                 // String INTEGER
      32: iconst_2
      33: invokespecial #12                 // Method "<init>":(Ljava/lang/String;I)V
      36: putstatic     #17                 // Field INTEGER:Lcom/fasterxml/jackson/databind/jsonFormatVisitors/JsonFormatTypes;
      39: new           #4                  // class com/fasterxml/jackson/databind/jsonFormatVisitors/JsonFormatTypes
      42: dup
      43: ldc           #18                 // String BOOLEAN
      45: iconst_3
      46: invokespecial #12                 // Method "<init>":(Ljava/lang/String;I)V
      49: putstatic     #19                 // Field BOOLEAN:Lcom/fasterxml/jackson/databind/jsonFormatVisitors/JsonFormatTypes;
      52: new           #4                  // class com/fasterxml/jackson/databind/jsonFormatVisitors/JsonFormatTypes
      55: dup
      56: ldc           #20                 // String OBJECT
      58: iconst_4
      59: invokespecial #12                 // Method "<init>":(Ljava/lang/String;I)V
      62: putstatic     #21                 // Field OBJECT:Lcom/fasterxml/jackson/databind/jsonFormatVisitors/JsonFormatTypes;
      65: new           #4                  // class com/fasterxml/jackson/databind/jsonFormatVisitors/JsonFormatTypes
      68: dup
      69: ldc           #22                 // String ARRAY
      71: iconst_5
      72: invokespecial #12                 // Method "<init>":(Ljava/lang/String;I)V
      75: putstatic     #23                 // Field ARRAY:Lcom/fasterxml/jackson/databind/jsonFormatVisitors/JsonFormatTypes;
      78: new           #4                  // class com/fasterxml/jackson/databind/jsonFormatVisitors/JsonFormatTypes
      81: dup
      82: ldc           #24                 // String NULL
      84: bipush        6
      86: invokespecial #12                 // Method "<init>":(Ljava/lang/String;I)V
      89: putstatic     #25                 // Field NULL:Lcom/fasterxml/jackson/databind/jsonFormatVisitors/JsonFormatTypes;
      92: new           #4                  // class com/fasterxml/jackson/databind/jsonFormatVisitors/JsonFormatTypes
      95: dup
      96: ldc           #26                 // String ANY
      98: bipush        7
     100: invokespecial #12                 // Method "<init>":(Ljava/lang/String;I)V
     103: putstatic     #27                 // Field ANY:Lcom/fasterxml/jackson/databind/jsonFormatVisitors/JsonFormatTypes;
     106: bipush        8
     108: anewarray     #4                  // class com/fasterxml/jackson/databind/jsonFormatVisitors/JsonFormatTypes
     111: dup
     112: iconst_0
     113: getstatic     #13                 // Field STRING:Lcom/fasterxml/jackson/databind/jsonFormatVisitors/JsonFormatTypes;
     116: aastore
     117: dup
     118: iconst_1
     119: getstatic     #15                 // Field NUMBER:Lcom/fasterxml/jackson/databind/jsonFormatVisitors/JsonFormatTypes;
     122: aastore
     123: dup
     124: iconst_2
     125: getstatic     #17                 // Field INTEGER:Lcom/fasterxml/jackson/databind/jsonFormatVisitors/JsonFormatTypes;
     128: aastore
     129: dup
     130: iconst_3
     131: getstatic     #19                 // Field BOOLEAN:Lcom/fasterxml/jackson/databind/jsonFormatVisitors/JsonFormatTypes;
     134: aastore
     135: dup
     136: iconst_4
     137: getstatic     #21                 // Field OBJECT:Lcom/fasterxml/jackson/databind/jsonFormatVisitors/JsonFormatTypes;
     140: aastore
     141: dup
     142: iconst_5
     143: getstatic     #23                 // Field ARRAY:Lcom/fasterxml/jackson/databind/jsonFormatVisitors/JsonFormatTypes;
     146: aastore
     147: dup
     148: bipush        6
     150: getstatic     #25                 // Field NULL:Lcom/fasterxml/jackson/databind/jsonFormatVisitors/JsonFormatTypes;
     153: aastore
     154: dup
     155: bipush        7
     157: getstatic     #27                 // Field ANY:Lcom/fasterxml/jackson/databind/jsonFormatVisitors/JsonFormatTypes;
     160: aastore
     161: putstatic     #1                  // Field $VALUES:[Lcom/fasterxml/jackson/databind/jsonFormatVisitors/JsonFormatTypes;
     164: new           #28                 // class java/util/HashMap
     167: dup
     168: invokespecial #29                 // Method java/util/HashMap."<init>":()V
     171: putstatic     #9                  // Field _byLCName:Ljava/util/Map;
     174: invokestatic  #30                 // Method values:()[Lcom/fasterxml/jackson/databind/jsonFormatVisitors/JsonFormatTypes;
     177: astore_0
     178: aload_0
     179: arraylength
     180: istore_1
     181: iconst_0
     182: istore_2
     183: iload_2
     184: iload_1
     185: if_icmpge     215
     188: aload_0
     189: iload_2
     190: aaload
     191: astore_3
     192: getstatic     #9                  // Field _byLCName:Ljava/util/Map;
     195: aload_3
     196: invokevirtual #7                  // Method name:()Ljava/lang/String;
     199: invokevirtual #8                  // Method java/lang/String.toLowerCase:()Ljava/lang/String;
     202: aload_3
     203: invokeinterface #31,  3           // InterfaceMethod java/util/Map.put:(Ljava/lang/Object;Ljava/lang/Object;)Ljava/lang/Object;
     208: pop
     209: iinc          2, 1
     212: goto          183
     215: return
}
