Compiled from "Annotation.java"
public abstract class io.opencensus.trace.Annotation {
  private static final java.util.Map<java.lang.String, io.opencensus.trace.AttributeValue> EMPTY_ATTRIBUTES;

  public static io.opencensus.trace.Annotation fromDescription(java.lang.String);
    Code:
       0: new           #1                  // class io/opencensus/trace/AutoValue_Annotation
       3: dup
       4: aload_0
       5: getstatic     #2                  // Field EMPTY_ATTRIBUTES:Ljava/util/Map;
       8: invokespecial #3                  // Method io/opencensus/trace/AutoValue_Annotation."<init>":(Ljava/lang/String;Ljava/util/Map;)V
      11: areturn

  public static io.opencensus.trace.Annotation fromDescriptionAndAttributes(java.lang.String, java.util.Map<java.lang.String, io.opencensus.trace.AttributeValue>);
    Code:
       0: new           #1                  // class io/opencensus/trace/AutoValue_Annotation
       3: dup
       4: aload_0
       5: new           #4                  // class java/util/HashMap
       8: dup
       9: aload_1
      10: ldc           #5                  // String attributes
      12: invokestatic  #6                  // Method io/opencensus/internal/Utils.checkNotNull:(Ljava/lang/Object;Ljava/lang/Object;)Ljava/lang/Object;
      15: checkcast     #7                  // class java/util/Map
      18: invokespecial #8                  // Method java/util/HashMap."<init>":(Ljava/util/Map;)V
      21: invokestatic  #9                  // Method java/util/Collections.unmodifiableMap:(Ljava/util/Map;)Ljava/util/Map;
      24: invokespecial #3                  // Method io/opencensus/trace/AutoValue_Annotation."<init>":(Ljava/lang/String;Ljava/util/Map;)V
      27: areturn

  public abstract java.lang.String getDescription();

  public abstract java.util.Map<java.lang.String, io.opencensus.trace.AttributeValue> getAttributes();

  io.opencensus.trace.Annotation();
    Code:
       0: aload_0
       1: invokespecial #10                 // Method java/lang/Object."<init>":()V
       4: return

  static {};
    Code:
       0: invokestatic  #11                 // Method java/util/Collections.emptyMap:()Ljava/util/Map;
       3: invokestatic  #9                  // Method java/util/Collections.unmodifiableMap:(Ljava/util/Map;)Ljava/util/Map;
       6: putstatic     #2                  // Field EMPTY_ATTRIBUTES:Ljava/util/Map;
       9: return
}
