Compiled from "SpanBuilder.java"
public abstract class io.opencensus.trace.SpanBuilder {
  public io.opencensus.trace.SpanBuilder();
    Code:
       0: aload_0
       1: invokespecial #1                  // Method java/lang/Object."<init>":()V
       4: return

  public abstract io.opencensus.trace.SpanBuilder setSampler(io.opencensus.trace.Sampler);

  public abstract io.opencensus.trace.SpanBuilder setParentLinks(java.util.List<io.opencensus.trace.Span>);

  public abstract io.opencensus.trace.SpanBuilder setRecordEvents(boolean);

  public io.opencensus.trace.SpanBuilder setSpanKind(io.opencensus.trace.Span$Kind);
    Code:
       0: aload_0
       1: areturn

  public abstract io.opencensus.trace.Span startSpan();

  public final io.opencensus.common.Scope startScopedSpan();
    Code:
       0: aload_0
       1: invokevirtual #2                  // Method startSpan:()Lio/opencensus/trace/Span;
       4: iconst_1
       5: invokestatic  #3                  // Method io/opencensus/trace/CurrentSpanUtils.withSpan:(Lio/opencensus/trace/Span;Z)Lio/opencensus/common/Scope;
       8: areturn

  public final void startSpanAndRun(java.lang.Runnable);
    Code:
       0: aload_0
       1: invokevirtual #2                  // Method startSpan:()Lio/opencensus/trace/Span;
       4: astore_2
       5: aload_2
       6: iconst_1
       7: aload_1
       8: invokestatic  #4                  // Method io/opencensus/trace/CurrentSpanUtils.withSpan:(Lio/opencensus/trace/Span;ZLjava/lang/Runnable;)Ljava/lang/Runnable;
      11: invokeinterface #5,  1            // InterfaceMethod java/lang/Runnable.run:()V
      16: return

  public final <V> V startSpanAndCall(java.util.concurrent.Callable<V>) throws java.lang.Exception;
    Code:
       0: aload_0
       1: invokevirtual #2                  // Method startSpan:()Lio/opencensus/trace/Span;
       4: astore_2
       5: aload_2
       6: iconst_1
       7: aload_1
       8: invokestatic  #6                  // Method io/opencensus/trace/CurrentSpanUtils.withSpan:(Lio/opencensus/trace/Span;ZLjava/util/concurrent/Callable;)Ljava/util/concurrent/Callable;
      11: invokeinterface #7,  1            // InterfaceMethod java/util/concurrent/Callable.call:()Ljava/lang/Object;
      16: areturn
}
