Compiled from "PreauthHandler.java"
public class org.apache.kerby.kerberos.kerb.server.preauth.PreauthHandler {
  private java.util.List<org.apache.kerby.kerberos.kerb.server.preauth.KdcPreauth> preauths;

  public org.apache.kerby.kerberos.kerb.server.preauth.PreauthHandler();
    Code:
       0: aload_0
       1: invokespecial #1                  // Method java/lang/Object."<init>":()V
       4: return

  public void init();
    Code:
       0: aload_0
       1: invokespecial #2                  // Method loadPreauthPlugins:()V
       4: return

  private void loadPreauthPlugins();
    Code:
       0: aload_0
       1: new           #3                  // class java/util/ArrayList
       4: dup
       5: invokespecial #4                  // Method java/util/ArrayList."<init>":()V
       8: putfield      #5                  // Field preauths:Ljava/util/List;
      11: new           #6                  // class org/apache/kerby/kerberos/kerb/server/preauth/builtin/EncTsPreauth
      14: dup
      15: invokespecial #7                  // Method org/apache/kerby/kerberos/kerb/server/preauth/builtin/EncTsPreauth."<init>":()V
      18: astore_1
      19: aload_0
      20: getfield      #5                  // Field preauths:Ljava/util/List;
      23: aload_1
      24: invokeinterface #8,  2            // InterfaceMethod java/util/List.add:(Ljava/lang/Object;)Z
      29: pop
      30: new           #9                  // class org/apache/kerby/kerberos/kerb/server/preauth/builtin/TgtPreauth
      33: dup
      34: invokespecial #10                 // Method org/apache/kerby/kerberos/kerb/server/preauth/builtin/TgtPreauth."<init>":()V
      37: astore_1
      38: aload_0
      39: getfield      #5                  // Field preauths:Ljava/util/List;
      42: aload_1
      43: invokeinterface #8,  2            // InterfaceMethod java/util/List.add:(Ljava/lang/Object;)Z
      48: pop
      49: new           #11                 // class org/apache/kerby/kerberos/kerb/server/preauth/token/TokenPreauth
      52: dup
      53: invokespecial #12                 // Method org/apache/kerby/kerberos/kerb/server/preauth/token/TokenPreauth."<init>":()V
      56: astore_1
      57: aload_0
      58: getfield      #5                  // Field preauths:Ljava/util/List;
      61: aload_1
      62: invokeinterface #8,  2            // InterfaceMethod java/util/List.add:(Ljava/lang/Object;)Z
      67: pop
      68: new           #13                 // class org/apache/kerby/kerberos/kerb/server/preauth/pkinit/PkinitPreauth
      71: dup
      72: invokespecial #14                 // Method org/apache/kerby/kerberos/kerb/server/preauth/pkinit/PkinitPreauth."<init>":()V
      75: astore_1
      76: aload_0
      77: getfield      #5                  // Field preauths:Ljava/util/List;
      80: aload_1
      81: invokeinterface #8,  2            // InterfaceMethod java/util/List.add:(Ljava/lang/Object;)Z
      86: pop
      87: return

  public void initWith(org.apache.kerby.kerberos.kerb.server.KdcContext);
    Code:
       0: aload_0
       1: getfield      #5                  // Field preauths:Ljava/util/List;
       4: invokeinterface #15,  1           // InterfaceMethod java/util/List.iterator:()Ljava/util/Iterator;
       9: astore_2
      10: aload_2
      11: invokeinterface #16,  1           // InterfaceMethod java/util/Iterator.hasNext:()Z
      16: ifeq          39
      19: aload_2
      20: invokeinterface #17,  1           // InterfaceMethod java/util/Iterator.next:()Ljava/lang/Object;
      25: checkcast     #18                 // class org/apache/kerby/kerberos/kerb/server/preauth/KdcPreauth
      28: astore_3
      29: aload_3
      30: aload_1
      31: invokeinterface #19,  2           // InterfaceMethod org/apache/kerby/kerberos/kerb/server/preauth/KdcPreauth.initWith:(Lorg/apache/kerby/kerberos/kerb/server/KdcContext;)V
      36: goto          10
      39: return

  public org.apache.kerby.kerberos.kerb.server.preauth.PreauthContext preparePreauthContext(org.apache.kerby.kerberos.kerb.server.request.KdcRequest);
    Code:
       0: new           #20                 // class org/apache/kerby/kerberos/kerb/server/preauth/PreauthContext
       3: dup
       4: invokespecial #21                 // Method org/apache/kerby/kerberos/kerb/server/preauth/PreauthContext."<init>":()V
       7: astore_2
       8: aload_1
       9: invokevirtual #22                 // Method org/apache/kerby/kerberos/kerb/server/request/KdcRequest.getKdcContext:()Lorg/apache/kerby/kerberos/kerb/server/KdcContext;
      12: astore_3
      13: aload_0
      14: aload_3
      15: invokevirtual #23                 // Method initWith:(Lorg/apache/kerby/kerberos/kerb/server/KdcContext;)V
      18: aload_2
      19: aload_3
      20: invokevirtual #24                 // Method org/apache/kerby/kerberos/kerb/server/KdcContext.getConfig:()Lorg/apache/kerby/kerberos/kerb/server/KdcConfig;
      23: invokevirtual #25                 // Method org/apache/kerby/kerberos/kerb/server/KdcConfig.isPreauthRequired:()Z
      26: invokevirtual #26                 // Method org/apache/kerby/kerberos/kerb/server/preauth/PreauthContext.setPreauthRequired:(Z)V
      29: aload_0
      30: getfield      #5                  // Field preauths:Ljava/util/List;
      33: invokeinterface #15,  1           // InterfaceMethod java/util/List.iterator:()Ljava/util/Iterator;
      38: astore        4
      40: aload         4
      42: invokeinterface #16,  1           // InterfaceMethod java/util/Iterator.hasNext:()Z
      47: ifeq          94
      50: aload         4
      52: invokeinterface #17,  1           // InterfaceMethod java/util/Iterator.next:()Ljava/lang/Object;
      57: checkcast     #18                 // class org/apache/kerby/kerberos/kerb/server/preauth/KdcPreauth
      60: astore        5
      62: new           #27                 // class org/apache/kerby/kerberos/kerb/server/preauth/PreauthHandle
      65: dup
      66: aload         5
      68: invokespecial #28                 // Method org/apache/kerby/kerberos/kerb/server/preauth/PreauthHandle."<init>":(Lorg/apache/kerby/kerberos/kerb/server/preauth/KdcPreauth;)V
      71: astore        6
      73: aload         6
      75: aload_1
      76: invokevirtual #29                 // Method org/apache/kerby/kerberos/kerb/server/preauth/PreauthHandle.initRequestContext:(Lorg/apache/kerby/kerberos/kerb/server/request/KdcRequest;)V
      79: aload_2
      80: invokevirtual #30                 // Method org/apache/kerby/kerberos/kerb/server/preauth/PreauthContext.getHandles:()Ljava/util/List;
      83: aload         6
      85: invokeinterface #8,  2            // InterfaceMethod java/util/List.add:(Ljava/lang/Object;)Z
      90: pop
      91: goto          40
      94: aload_2
      95: areturn

  public void provideEdata(org.apache.kerby.kerberos.kerb.server.request.KdcRequest, org.apache.kerby.kerberos.kerb.type.pa.PaData) throws org.apache.kerby.kerberos.kerb.KrbException;
    Code:
       0: aload_1
       1: invokevirtual #31                 // Method org/apache/kerby/kerberos/kerb/server/request/KdcRequest.getPreauthContext:()Lorg/apache/kerby/kerberos/kerb/server/preauth/PreauthContext;
       4: astore_3
       5: aload_3
       6: invokevirtual #30                 // Method org/apache/kerby/kerberos/kerb/server/preauth/PreauthContext.getHandles:()Ljava/util/List;
       9: invokeinterface #15,  1           // InterfaceMethod java/util/List.iterator:()Ljava/util/Iterator;
      14: astore        4
      16: aload         4
      18: invokeinterface #16,  1           // InterfaceMethod java/util/Iterator.hasNext:()Z
      23: ifeq          48
      26: aload         4
      28: invokeinterface #17,  1           // InterfaceMethod java/util/Iterator.next:()Ljava/lang/Object;
      33: checkcast     #27                 // class org/apache/kerby/kerberos/kerb/server/preauth/PreauthHandle
      36: astore        5
      38: aload         5
      40: aload_1
      41: aload_2
      42: invokevirtual #32                 // Method org/apache/kerby/kerberos/kerb/server/preauth/PreauthHandle.provideEdata:(Lorg/apache/kerby/kerberos/kerb/server/request/KdcRequest;Lorg/apache/kerby/kerberos/kerb/type/pa/PaData;)V
      45: goto          16
      48: return

  public void verify(org.apache.kerby.kerberos.kerb.server.request.KdcRequest, org.apache.kerby.kerberos.kerb.type.pa.PaData) throws org.apache.kerby.kerberos.kerb.KrbException;
    Code:
       0: aload_2
       1: invokevirtual #33                 // Method org/apache/kerby/kerberos/kerb/type/pa/PaData.getElements:()Ljava/util/List;
       4: invokeinterface #15,  1           // InterfaceMethod java/util/List.iterator:()Ljava/util/Iterator;
       9: astore_3
      10: aload_3
      11: invokeinterface #16,  1           // InterfaceMethod java/util/Iterator.hasNext:()Z
      16: ifeq          58
      19: aload_3
      20: invokeinterface #17,  1           // InterfaceMethod java/util/Iterator.next:()Ljava/lang/Object;
      25: checkcast     #34                 // class org/apache/kerby/kerberos/kerb/type/pa/PaDataEntry
      28: astore        4
      30: aload_0
      31: aload_1
      32: aload         4
      34: invokevirtual #35                 // Method org/apache/kerby/kerberos/kerb/type/pa/PaDataEntry.getPaDataType:()Lorg/apache/kerby/kerberos/kerb/type/pa/PaDataType;
      37: invokespecial #36                 // Method findHandle:(Lorg/apache/kerby/kerberos/kerb/server/request/KdcRequest;Lorg/apache/kerby/kerberos/kerb/type/pa/PaDataType;)Lorg/apache/kerby/kerberos/kerb/server/preauth/PreauthHandle;
      40: astore        5
      42: aload         5
      44: ifnull        55
      47: aload         5
      49: aload_1
      50: aload         4
      52: invokevirtual #37                 // Method org/apache/kerby/kerberos/kerb/server/preauth/PreauthHandle.verify:(Lorg/apache/kerby/kerberos/kerb/server/request/KdcRequest;Lorg/apache/kerby/kerberos/kerb/type/pa/PaDataEntry;)V
      55: goto          10
      58: return

  public void providePaData(org.apache.kerby.kerberos.kerb.server.request.KdcRequest, org.apache.kerby.kerberos.kerb.type.pa.PaData);
    Code:
       0: aload_1
       1: invokevirtual #31                 // Method org/apache/kerby/kerberos/kerb/server/request/KdcRequest.getPreauthContext:()Lorg/apache/kerby/kerberos/kerb/server/preauth/PreauthContext;
       4: astore_3
       5: aload_3
       6: invokevirtual #30                 // Method org/apache/kerby/kerberos/kerb/server/preauth/PreauthContext.getHandles:()Ljava/util/List;
       9: invokeinterface #15,  1           // InterfaceMethod java/util/List.iterator:()Ljava/util/Iterator;
      14: astore        4
      16: aload         4
      18: invokeinterface #16,  1           // InterfaceMethod java/util/Iterator.hasNext:()Z
      23: ifeq          48
      26: aload         4
      28: invokeinterface #17,  1           // InterfaceMethod java/util/Iterator.next:()Ljava/lang/Object;
      33: checkcast     #27                 // class org/apache/kerby/kerberos/kerb/server/preauth/PreauthHandle
      36: astore        5
      38: aload         5
      40: aload_1
      41: aload_2
      42: invokevirtual #38                 // Method org/apache/kerby/kerberos/kerb/server/preauth/PreauthHandle.providePaData:(Lorg/apache/kerby/kerberos/kerb/server/request/KdcRequest;Lorg/apache/kerby/kerberos/kerb/type/pa/PaData;)V
      45: goto          16
      48: return

  private org.apache.kerby.kerberos.kerb.server.preauth.PreauthHandle findHandle(org.apache.kerby.kerberos.kerb.server.request.KdcRequest, org.apache.kerby.kerberos.kerb.type.pa.PaDataType);
    Code:
       0: aload_1
       1: invokevirtual #31                 // Method org/apache/kerby/kerberos/kerb/server/request/KdcRequest.getPreauthContext:()Lorg/apache/kerby/kerberos/kerb/server/preauth/PreauthContext;
       4: astore_3
       5: aload_3
       6: invokevirtual #30                 // Method org/apache/kerby/kerberos/kerb/server/preauth/PreauthContext.getHandles:()Ljava/util/List;
       9: invokeinterface #15,  1           // InterfaceMethod java/util/List.iterator:()Ljava/util/Iterator;
      14: astore        4
      16: aload         4
      18: invokeinterface #16,  1           // InterfaceMethod java/util/Iterator.hasNext:()Z
      23: ifeq          90
      26: aload         4
      28: invokeinterface #17,  1           // InterfaceMethod java/util/Iterator.next:()Ljava/lang/Object;
      33: checkcast     #27                 // class org/apache/kerby/kerberos/kerb/server/preauth/PreauthHandle
      36: astore        5
      38: aload         5
      40: getfield      #39                 // Field org/apache/kerby/kerberos/kerb/server/preauth/PreauthHandle.preauth:Lorg/apache/kerby/kerberos/kerb/server/preauth/KdcPreauth;
      43: invokeinterface #40,  1           // InterfaceMethod org/apache/kerby/kerberos/kerb/server/preauth/KdcPreauth.getPaTypes:()[Lorg/apache/kerby/kerberos/kerb/type/pa/PaDataType;
      48: astore        6
      50: aload         6
      52: arraylength
      53: istore        7
      55: iconst_0
      56: istore        8
      58: iload         8
      60: iload         7
      62: if_icmpge     87
      65: aload         6
      67: iload         8
      69: aaload
      70: astore        9
      72: aload         9
      74: aload_2
      75: if_acmpne     81
      78: aload         5
      80: areturn
      81: iinc          8, 1
      84: goto          58
      87: goto          16
      90: aconst_null
      91: areturn

  public void destroy();
    Code:
       0: aload_0
       1: getfield      #5                  // Field preauths:Ljava/util/List;
       4: invokeinterface #15,  1           // InterfaceMethod java/util/List.iterator:()Ljava/util/Iterator;
       9: astore_1
      10: aload_1
      11: invokeinterface #16,  1           // InterfaceMethod java/util/Iterator.hasNext:()Z
      16: ifeq          38
      19: aload_1
      20: invokeinterface #17,  1           // InterfaceMethod java/util/Iterator.next:()Ljava/lang/Object;
      25: checkcast     #18                 // class org/apache/kerby/kerberos/kerb/server/preauth/KdcPreauth
      28: astore_2
      29: aload_2
      30: invokeinterface #41,  1           // InterfaceMethod org/apache/kerby/kerberos/kerb/server/preauth/KdcPreauth.destroy:()V
      35: goto          10
      38: return

  public static boolean isToken(org.apache.kerby.kerberos.kerb.type.pa.PaData);
    Code:
       0: aload_0
       1: ifnull        48
       4: aload_0
       5: invokevirtual #33                 // Method org/apache/kerby/kerberos/kerb/type/pa/PaData.getElements:()Ljava/util/List;
       8: invokeinterface #15,  1           // InterfaceMethod java/util/List.iterator:()Ljava/util/Iterator;
      13: astore_1
      14: aload_1
      15: invokeinterface #16,  1           // InterfaceMethod java/util/Iterator.hasNext:()Z
      20: ifeq          48
      23: aload_1
      24: invokeinterface #17,  1           // InterfaceMethod java/util/Iterator.next:()Ljava/lang/Object;
      29: checkcast     #34                 // class org/apache/kerby/kerberos/kerb/type/pa/PaDataEntry
      32: astore_2
      33: aload_2
      34: invokevirtual #35                 // Method org/apache/kerby/kerberos/kerb/type/pa/PaDataEntry.getPaDataType:()Lorg/apache/kerby/kerberos/kerb/type/pa/PaDataType;
      37: getstatic     #42                 // Field org/apache/kerby/kerberos/kerb/type/pa/PaDataType.TOKEN_REQUEST:Lorg/apache/kerby/kerberos/kerb/type/pa/PaDataType;
      40: if_acmpne     45
      43: iconst_1
      44: ireturn
      45: goto          14
      48: iconst_0
      49: ireturn

  public static boolean isPkinit(org.apache.kerby.kerberos.kerb.type.pa.PaData);
    Code:
       0: aload_0
       1: ifnull        48
       4: aload_0
       5: invokevirtual #33                 // Method org/apache/kerby/kerberos/kerb/type/pa/PaData.getElements:()Ljava/util/List;
       8: invokeinterface #15,  1           // InterfaceMethod java/util/List.iterator:()Ljava/util/Iterator;
      13: astore_1
      14: aload_1
      15: invokeinterface #16,  1           // InterfaceMethod java/util/Iterator.hasNext:()Z
      20: ifeq          48
      23: aload_1
      24: invokeinterface #17,  1           // InterfaceMethod java/util/Iterator.next:()Ljava/lang/Object;
      29: checkcast     #34                 // class org/apache/kerby/kerberos/kerb/type/pa/PaDataEntry
      32: astore_2
      33: aload_2
      34: invokevirtual #35                 // Method org/apache/kerby/kerberos/kerb/type/pa/PaDataEntry.getPaDataType:()Lorg/apache/kerby/kerberos/kerb/type/pa/PaDataType;
      37: getstatic     #43                 // Field org/apache/kerby/kerberos/kerb/type/pa/PaDataType.PK_AS_REQ:Lorg/apache/kerby/kerberos/kerb/type/pa/PaDataType;
      40: if_acmpne     45
      43: iconst_1
      44: ireturn
      45: goto          14
      48: iconst_0
      49: ireturn
}
