Compiled from "AnnotationJmxAttributeSource.java"
public class org.springframework.jmx.export.annotation.AnnotationJmxAttributeSource implements org.springframework.jmx.export.metadata.JmxAttributeSource,org.springframework.beans.factory.BeanFactoryAware {
  private org.springframework.util.StringValueResolver embeddedValueResolver;

  public org.springframework.jmx.export.annotation.AnnotationJmxAttributeSource();
    Code:
       0: aload_0
       1: invokespecial #1                  // Method java/lang/Object."<init>":()V
       4: return

  public void setBeanFactory(org.springframework.beans.factory.BeanFactory);
    Code:
       0: aload_1
       1: instanceof    #2                  // class org/springframework/beans/factory/config/ConfigurableBeanFactory
       4: ifeq          22
       7: aload_0
       8: new           #3                  // class org/springframework/beans/factory/config/EmbeddedValueResolver
      11: dup
      12: aload_1
      13: checkcast     #2                  // class org/springframework/beans/factory/config/ConfigurableBeanFactory
      16: invokespecial #4                  // Method org/springframework/beans/factory/config/EmbeddedValueResolver."<init>":(Lorg/springframework/beans/factory/config/ConfigurableBeanFactory;)V
      19: putfield      #5                  // Field embeddedValueResolver:Lorg/springframework/util/StringValueResolver;
      22: return

  public org.springframework.jmx.export.metadata.ManagedResource getManagedResource(java.lang.Class<?>) throws org.springframework.jmx.export.metadata.InvalidMetadataException;
    Code:
       0: aload_1
       1: ldc           #6                  // class org/springframework/jmx/export/annotation/ManagedResource
       3: invokestatic  #7                  // Method org/springframework/core/annotation/AnnotationUtils.findAnnotation:(Ljava/lang/Class;Ljava/lang/Class;)Ljava/lang/annotation/Annotation;
       6: checkcast     #6                  // class org/springframework/jmx/export/annotation/ManagedResource
       9: astore_2
      10: aload_2
      11: ifnonnull     16
      14: aconst_null
      15: areturn
      16: ldc           #6                  // class org/springframework/jmx/export/annotation/ManagedResource
      18: aload_1
      19: invokestatic  #8                  // Method org/springframework/core/annotation/AnnotationUtils.findAnnotationDeclaringClass:(Ljava/lang/Class;Ljava/lang/Class;)Ljava/lang/Class;
      22: astore_3
      23: aload_3
      24: ifnull        38
      27: aload_3
      28: invokevirtual #9                  // Method java/lang/Class.isInterface:()Z
      31: ifne          38
      34: aload_3
      35: goto          39
      38: aload_1
      39: astore        4
      41: aload         4
      43: invokevirtual #10                 // Method java/lang/Class.getModifiers:()I
      46: invokestatic  #11                 // Method java/lang/reflect/Modifier.isPublic:(I)Z
      49: ifne          88
      52: new           #12                 // class org/springframework/jmx/export/metadata/InvalidMetadataException
      55: dup
      56: new           #13                 // class java/lang/StringBuilder
      59: dup
      60: invokespecial #14                 // Method java/lang/StringBuilder."<init>":()V
      63: ldc           #15                 // String @ManagedResource class \'
      65: invokevirtual #16                 // Method java/lang/StringBuilder.append:(Ljava/lang/String;)Ljava/lang/StringBuilder;
      68: aload         4
      70: invokevirtual #17                 // Method java/lang/Class.getName:()Ljava/lang/String;
      73: invokevirtual #16                 // Method java/lang/StringBuilder.append:(Ljava/lang/String;)Ljava/lang/StringBuilder;
      76: ldc           #18                 // String \' must be public
      78: invokevirtual #16                 // Method java/lang/StringBuilder.append:(Ljava/lang/String;)Ljava/lang/StringBuilder;
      81: invokevirtual #19                 // Method java/lang/StringBuilder.toString:()Ljava/lang/String;
      84: invokespecial #20                 // Method org/springframework/jmx/export/metadata/InvalidMetadataException."<init>":(Ljava/lang/String;)V
      87: athrow
      88: new           #21                 // class org/springframework/jmx/export/metadata/ManagedResource
      91: dup
      92: invokespecial #22                 // Method org/springframework/jmx/export/metadata/ManagedResource."<init>":()V
      95: astore        5
      97: aload_2
      98: aload         5
     100: aload_0
     101: getfield      #5                  // Field embeddedValueResolver:Lorg/springframework/util/StringValueResolver;
     104: iconst_0
     105: anewarray     #23                 // class java/lang/String
     108: invokestatic  #24                 // Method org/springframework/beans/annotation/AnnotationBeanUtils.copyPropertiesToBean:(Ljava/lang/annotation/Annotation;Ljava/lang/Object;Lorg/springframework/util/StringValueResolver;[Ljava/lang/String;)V
     111: aload         5
     113: areturn

  public org.springframework.jmx.export.metadata.ManagedAttribute getManagedAttribute(java.lang.reflect.Method) throws org.springframework.jmx.export.metadata.InvalidMetadataException;
    Code:
       0: aload_1
       1: ldc           #25                 // class org/springframework/jmx/export/annotation/ManagedAttribute
       3: invokestatic  #26                 // Method org/springframework/core/annotation/AnnotationUtils.findAnnotation:(Ljava/lang/reflect/Method;Ljava/lang/Class;)Ljava/lang/annotation/Annotation;
       6: checkcast     #25                 // class org/springframework/jmx/export/annotation/ManagedAttribute
       9: astore_2
      10: aload_2
      11: ifnonnull     16
      14: aconst_null
      15: areturn
      16: new           #27                 // class org/springframework/jmx/export/metadata/ManagedAttribute
      19: dup
      20: invokespecial #28                 // Method org/springframework/jmx/export/metadata/ManagedAttribute."<init>":()V
      23: astore_3
      24: aload_2
      25: aload_3
      26: iconst_1
      27: anewarray     #23                 // class java/lang/String
      30: dup
      31: iconst_0
      32: ldc           #29                 // String defaultValue
      34: aastore
      35: invokestatic  #30                 // Method org/springframework/beans/annotation/AnnotationBeanUtils.copyPropertiesToBean:(Ljava/lang/annotation/Annotation;Ljava/lang/Object;[Ljava/lang/String;)V
      38: aload_2
      39: invokeinterface #31,  1           // InterfaceMethod org/springframework/jmx/export/annotation/ManagedAttribute.defaultValue:()Ljava/lang/String;
      44: invokevirtual #32                 // Method java/lang/String.length:()I
      47: ifle          60
      50: aload_3
      51: aload_2
      52: invokeinterface #31,  1           // InterfaceMethod org/springframework/jmx/export/annotation/ManagedAttribute.defaultValue:()Ljava/lang/String;
      57: invokevirtual #33                 // Method org/springframework/jmx/export/metadata/ManagedAttribute.setDefaultValue:(Ljava/lang/Object;)V
      60: aload_3
      61: areturn

  public org.springframework.jmx.export.metadata.ManagedMetric getManagedMetric(java.lang.reflect.Method) throws org.springframework.jmx.export.metadata.InvalidMetadataException;
    Code:
       0: aload_1
       1: ldc           #34                 // class org/springframework/jmx/export/annotation/ManagedMetric
       3: invokestatic  #26                 // Method org/springframework/core/annotation/AnnotationUtils.findAnnotation:(Ljava/lang/reflect/Method;Ljava/lang/Class;)Ljava/lang/annotation/Annotation;
       6: checkcast     #34                 // class org/springframework/jmx/export/annotation/ManagedMetric
       9: astore_2
      10: aload_2
      11: ldc           #35                 // class org/springframework/jmx/export/metadata/ManagedMetric
      13: invokestatic  #36                 // Method copyPropertiesToBean:(Ljava/lang/annotation/Annotation;Ljava/lang/Class;)Ljava/lang/Object;
      16: checkcast     #35                 // class org/springframework/jmx/export/metadata/ManagedMetric
      19: areturn

  public org.springframework.jmx.export.metadata.ManagedOperation getManagedOperation(java.lang.reflect.Method) throws org.springframework.jmx.export.metadata.InvalidMetadataException;
    Code:
       0: aload_1
       1: ldc           #37                 // class org/springframework/jmx/export/annotation/ManagedOperation
       3: invokestatic  #26                 // Method org/springframework/core/annotation/AnnotationUtils.findAnnotation:(Ljava/lang/reflect/Method;Ljava/lang/Class;)Ljava/lang/annotation/Annotation;
       6: checkcast     #37                 // class org/springframework/jmx/export/annotation/ManagedOperation
       9: astore_2
      10: aload_2
      11: ldc           #38                 // class org/springframework/jmx/export/metadata/ManagedOperation
      13: invokestatic  #36                 // Method copyPropertiesToBean:(Ljava/lang/annotation/Annotation;Ljava/lang/Class;)Ljava/lang/Object;
      16: checkcast     #38                 // class org/springframework/jmx/export/metadata/ManagedOperation
      19: areturn

  public org.springframework.jmx.export.metadata.ManagedOperationParameter[] getManagedOperationParameters(java.lang.reflect.Method) throws org.springframework.jmx.export.metadata.InvalidMetadataException;
    Code:
       0: aload_1
       1: ldc           #39                 // class org/springframework/jmx/export/annotation/ManagedOperationParameter
       3: ldc           #40                 // class org/springframework/jmx/export/annotation/ManagedOperationParameters
       5: invokestatic  #41                 // Method org/springframework/core/annotation/AnnotationUtils.getRepeatableAnnotations:(Ljava/lang/reflect/AnnotatedElement;Ljava/lang/Class;Ljava/lang/Class;)Ljava/util/Set;
       8: astore_2
       9: aload_2
      10: ldc           #42                 // class org/springframework/jmx/export/metadata/ManagedOperationParameter
      12: invokestatic  #43                 // Method copyPropertiesToBeanArray:(Ljava/util/Collection;Ljava/lang/Class;)[Ljava/lang/Object;
      15: checkcast     #44                 // class "[Lorg/springframework/jmx/export/metadata/ManagedOperationParameter;"
      18: areturn

  public org.springframework.jmx.export.metadata.ManagedNotification[] getManagedNotifications(java.lang.Class<?>) throws org.springframework.jmx.export.metadata.InvalidMetadataException;
    Code:
       0: aload_1
       1: ldc           #45                 // class org/springframework/jmx/export/annotation/ManagedNotification
       3: ldc           #46                 // class org/springframework/jmx/export/annotation/ManagedNotifications
       5: invokestatic  #41                 // Method org/springframework/core/annotation/AnnotationUtils.getRepeatableAnnotations:(Ljava/lang/reflect/AnnotatedElement;Ljava/lang/Class;Ljava/lang/Class;)Ljava/util/Set;
       8: astore_2
       9: aload_2
      10: ldc           #47                 // class org/springframework/jmx/export/metadata/ManagedNotification
      12: invokestatic  #43                 // Method copyPropertiesToBeanArray:(Ljava/util/Collection;Ljava/lang/Class;)[Ljava/lang/Object;
      15: checkcast     #48                 // class "[Lorg/springframework/jmx/export/metadata/ManagedNotification;"
      18: areturn

  private static <T> T[] copyPropertiesToBeanArray(java.util.Collection<? extends java.lang.annotation.Annotation>, java.lang.Class<T>);
    Code:
       0: aload_1
       1: aload_0
       2: invokeinterface #49,  1           // InterfaceMethod java/util/Collection.size:()I
       7: invokestatic  #50                 // Method java/lang/reflect/Array.newInstance:(Ljava/lang/Class;I)Ljava/lang/Object;
      10: checkcast     #51                 // class "[Ljava/lang/Object;"
      13: checkcast     #51                 // class "[Ljava/lang/Object;"
      16: astore_2
      17: iconst_0
      18: istore_3
      19: aload_0
      20: invokeinterface #52,  1           // InterfaceMethod java/util/Collection.iterator:()Ljava/util/Iterator;
      25: astore        4
      27: aload         4
      29: invokeinterface #53,  1           // InterfaceMethod java/util/Iterator.hasNext:()Z
      34: ifeq          64
      37: aload         4
      39: invokeinterface #54,  1           // InterfaceMethod java/util/Iterator.next:()Ljava/lang/Object;
      44: checkcast     #55                 // class java/lang/annotation/Annotation
      47: astore        5
      49: aload_2
      50: iload_3
      51: iinc          3, 1
      54: aload         5
      56: aload_1
      57: invokestatic  #36                 // Method copyPropertiesToBean:(Ljava/lang/annotation/Annotation;Ljava/lang/Class;)Ljava/lang/Object;
      60: aastore
      61: goto          27
      64: aload_2
      65: areturn

  private static <T> T copyPropertiesToBean(java.lang.annotation.Annotation, java.lang.Class<T>);
    Code:
       0: aload_0
       1: ifnonnull     6
       4: aconst_null
       5: areturn
       6: aload_1
       7: invokestatic  #56                 // Method org/springframework/beans/BeanUtils.instantiateClass:(Ljava/lang/Class;)Ljava/lang/Object;
      10: astore_2
      11: aload_0
      12: aload_2
      13: iconst_0
      14: anewarray     #23                 // class java/lang/String
      17: invokestatic  #30                 // Method org/springframework/beans/annotation/AnnotationBeanUtils.copyPropertiesToBean:(Ljava/lang/annotation/Annotation;Ljava/lang/Object;[Ljava/lang/String;)V
      20: aload_2
      21: areturn
}
