Compiled from "FastConstructor.java"
public class org.springframework.cglib.reflect.FastConstructor extends org.springframework.cglib.reflect.FastMember {
  org.springframework.cglib.reflect.FastConstructor(org.springframework.cglib.reflect.FastClass, java.lang.reflect.Constructor);
    Code:
       0: aload_0
       1: aload_1
       2: aload_2
       3: aload_1
       4: aload_2
       5: invokevirtual #13                 // Method java/lang/reflect/Constructor.getParameterTypes:()[Ljava/lang/Class;
       8: invokevirtual #19                 // Method org/springframework/cglib/reflect/FastClass.getIndex:([Ljava/lang/Class;)I
      11: invokespecial #22                 // Method org/springframework/cglib/reflect/FastMember."<init>":(Lorg/springframework/cglib/reflect/FastClass;Ljava/lang/reflect/Member;I)V
      14: return

  public java.lang.Class[] getParameterTypes();
    Code:
       0: aload_0
       1: getfield      #32                 // Field member:Ljava/lang/reflect/Member;
       4: checkcast     #9                  // class java/lang/reflect/Constructor
       7: invokevirtual #13                 // Method java/lang/reflect/Constructor.getParameterTypes:()[Ljava/lang/Class;
      10: areturn

  public java.lang.Class[] getExceptionTypes();
    Code:
       0: aload_0
       1: getfield      #32                 // Field member:Ljava/lang/reflect/Member;
       4: checkcast     #9                  // class java/lang/reflect/Constructor
       7: invokevirtual #35                 // Method java/lang/reflect/Constructor.getExceptionTypes:()[Ljava/lang/Class;
      10: areturn

  public java.lang.Object newInstance() throws java.lang.reflect.InvocationTargetException;
    Code:
       0: aload_0
       1: getfield      #41                 // Field fc:Lorg/springframework/cglib/reflect/FastClass;
       4: aload_0
       5: getfield      #45                 // Field index:I
       8: aconst_null
       9: invokevirtual #48                 // Method org/springframework/cglib/reflect/FastClass.newInstance:(I[Ljava/lang/Object;)Ljava/lang/Object;
      12: areturn

  public java.lang.Object newInstance(java.lang.Object[]) throws java.lang.reflect.InvocationTargetException;
    Code:
       0: aload_0
       1: getfield      #41                 // Field fc:Lorg/springframework/cglib/reflect/FastClass;
       4: aload_0
       5: getfield      #45                 // Field index:I
       8: aload_1
       9: invokevirtual #48                 // Method org/springframework/cglib/reflect/FastClass.newInstance:(I[Ljava/lang/Object;)Ljava/lang/Object;
      12: areturn

  public java.lang.reflect.Constructor getJavaConstructor();
    Code:
       0: aload_0
       1: getfield      #32                 // Field member:Ljava/lang/reflect/Member;
       4: checkcast     #9                  // class java/lang/reflect/Constructor
       7: areturn
}
