Compiled from "StatusManager.java"
class org.eclipse.ui.statushandlers.StatusManager$StatusManagerLogListener implements org.eclipse.core.runtime.ILogListener {
  final org.eclipse.ui.statushandlers.StatusManager this$0;

  private org.eclipse.ui.statushandlers.StatusManager$StatusManagerLogListener(org.eclipse.ui.statushandlers.StatusManager);
    Code:
       0: aload_0
       1: aload_1
       2: putfield      #39                 // Field this$0:Lorg/eclipse/ui/statushandlers/StatusManager;
       5: aload_0
       6: invokespecial #40                 // Method java/lang/Object."<init>":()V
       9: return

  public void logging(org.eclipse.core.runtime.IStatus, java.lang.String);
    Code:
       0: aload_0
       1: getfield      #39                 // Field this$0:Lorg/eclipse/ui/statushandlers/StatusManager;
       4: getfield      #38                 // Field org/eclipse/ui/statushandlers/StatusManager.loggedStatuses:Ljava/util/List;
       7: aload_1
       8: invokeinterface #42,  2           // InterfaceMethod java/util/List.contains:(Ljava/lang/Object;)Z
      13: ifne          28
      16: aload_0
      17: getfield      #39                 // Field this$0:Lorg/eclipse/ui/statushandlers/StatusManager;
      20: aload_1
      21: iconst_0
      22: invokevirtual #41                 // Method org/eclipse/ui/statushandlers/StatusManager.handle:(Lorg/eclipse/core/runtime/IStatus;I)V
      25: goto          42
      28: aload_0
      29: getfield      #39                 // Field this$0:Lorg/eclipse/ui/statushandlers/StatusManager;
      32: getfield      #38                 // Field org/eclipse/ui/statushandlers/StatusManager.loggedStatuses:Ljava/util/List;
      35: aload_1
      36: invokeinterface #43,  2           // InterfaceMethod java/util/List.remove:(Ljava/lang/Object;)Z
      41: pop
      42: return
}
