Compiled from "MessageSecurityMetadataSourceRegistry.java"
public class org.springframework.security.config.annotation.web.messaging.MessageSecurityMetadataSourceRegistry$Constraint {
  private final java.util.List<? extends org.springframework.security.config.annotation.web.messaging.MessageSecurityMetadataSourceRegistry$MatcherBuilder> messageMatchers;

  final org.springframework.security.config.annotation.web.messaging.MessageSecurityMetadataSourceRegistry this$0;

  private org.springframework.security.config.annotation.web.messaging.MessageSecurityMetadataSourceRegistry$Constraint(java.util.List<? extends org.springframework.security.config.annotation.web.messaging.MessageSecurityMetadataSourceRegistry$MatcherBuilder>);
    Code:
       0: aload_0
       1: aload_1
       2: putfield      #3                  // Field this$0:Lorg/springframework/security/config/annotation/web/messaging/MessageSecurityMetadataSourceRegistry;
       5: aload_0
       6: invokespecial #4                  // Method java/lang/Object."<init>":()V
       9: aload_2
      10: ldc           #5                  // String messageMatchers cannot be null or empty
      12: invokestatic  #6                  // Method org/springframework/util/Assert.notEmpty:(Ljava/util/Collection;Ljava/lang/String;)V
      15: aload_0
      16: aload_2
      17: putfield      #7                  // Field messageMatchers:Ljava/util/List;
      20: return

  public org.springframework.security.config.annotation.web.messaging.MessageSecurityMetadataSourceRegistry hasRole(java.lang.String);
    Code:
       0: aload_0
       1: aload_1
       2: invokestatic  #8                  // Method org/springframework/security/config/annotation/web/messaging/MessageSecurityMetadataSourceRegistry.access$300:(Ljava/lang/String;)Ljava/lang/String;
       5: invokevirtual #9                  // Method access:(Ljava/lang/String;)Lorg/springframework/security/config/annotation/web/messaging/MessageSecurityMetadataSourceRegistry;
       8: areturn

  public org.springframework.security.config.annotation.web.messaging.MessageSecurityMetadataSourceRegistry hasAnyRole(java.lang.String...);
    Code:
       0: aload_0
       1: aload_1
       2: invokestatic  #10                 // Method org/springframework/security/config/annotation/web/messaging/MessageSecurityMetadataSourceRegistry.access$400:([Ljava/lang/String;)Ljava/lang/String;
       5: invokevirtual #9                  // Method access:(Ljava/lang/String;)Lorg/springframework/security/config/annotation/web/messaging/MessageSecurityMetadataSourceRegistry;
       8: areturn

  public org.springframework.security.config.annotation.web.messaging.MessageSecurityMetadataSourceRegistry hasAuthority(java.lang.String);
    Code:
       0: aload_0
       1: aload_1
       2: invokestatic  #11                 // Method org/springframework/security/config/annotation/web/messaging/MessageSecurityMetadataSourceRegistry.access$500:(Ljava/lang/String;)Ljava/lang/String;
       5: invokevirtual #9                  // Method access:(Ljava/lang/String;)Lorg/springframework/security/config/annotation/web/messaging/MessageSecurityMetadataSourceRegistry;
       8: areturn

  public org.springframework.security.config.annotation.web.messaging.MessageSecurityMetadataSourceRegistry hasAnyAuthority(java.lang.String...);
    Code:
       0: aload_0
       1: aload_1
       2: invokestatic  #12                 // Method org/springframework/security/config/annotation/web/messaging/MessageSecurityMetadataSourceRegistry.access$600:([Ljava/lang/String;)Ljava/lang/String;
       5: invokevirtual #9                  // Method access:(Ljava/lang/String;)Lorg/springframework/security/config/annotation/web/messaging/MessageSecurityMetadataSourceRegistry;
       8: areturn

  public org.springframework.security.config.annotation.web.messaging.MessageSecurityMetadataSourceRegistry permitAll();
    Code:
       0: aload_0
       1: ldc           #13                 // String permitAll
       3: invokevirtual #9                  // Method access:(Ljava/lang/String;)Lorg/springframework/security/config/annotation/web/messaging/MessageSecurityMetadataSourceRegistry;
       6: areturn

  public org.springframework.security.config.annotation.web.messaging.MessageSecurityMetadataSourceRegistry anonymous();
    Code:
       0: aload_0
       1: ldc           #14                 // String anonymous
       3: invokevirtual #9                  // Method access:(Ljava/lang/String;)Lorg/springframework/security/config/annotation/web/messaging/MessageSecurityMetadataSourceRegistry;
       6: areturn

  public org.springframework.security.config.annotation.web.messaging.MessageSecurityMetadataSourceRegistry rememberMe();
    Code:
       0: aload_0
       1: ldc           #15                 // String rememberMe
       3: invokevirtual #9                  // Method access:(Ljava/lang/String;)Lorg/springframework/security/config/annotation/web/messaging/MessageSecurityMetadataSourceRegistry;
       6: areturn

  public org.springframework.security.config.annotation.web.messaging.MessageSecurityMetadataSourceRegistry denyAll();
    Code:
       0: aload_0
       1: ldc           #16                 // String denyAll
       3: invokevirtual #9                  // Method access:(Ljava/lang/String;)Lorg/springframework/security/config/annotation/web/messaging/MessageSecurityMetadataSourceRegistry;
       6: areturn

  public org.springframework.security.config.annotation.web.messaging.MessageSecurityMetadataSourceRegistry authenticated();
    Code:
       0: aload_0
       1: ldc           #17                 // String authenticated
       3: invokevirtual #9                  // Method access:(Ljava/lang/String;)Lorg/springframework/security/config/annotation/web/messaging/MessageSecurityMetadataSourceRegistry;
       6: areturn

  public org.springframework.security.config.annotation.web.messaging.MessageSecurityMetadataSourceRegistry fullyAuthenticated();
    Code:
       0: aload_0
       1: ldc           #18                 // String fullyAuthenticated
       3: invokevirtual #9                  // Method access:(Ljava/lang/String;)Lorg/springframework/security/config/annotation/web/messaging/MessageSecurityMetadataSourceRegistry;
       6: areturn

  public org.springframework.security.config.annotation.web.messaging.MessageSecurityMetadataSourceRegistry access(java.lang.String);
    Code:
       0: aload_0
       1: getfield      #7                  // Field messageMatchers:Ljava/util/List;
       4: invokeinterface #19,  1           // InterfaceMethod java/util/List.iterator:()Ljava/util/Iterator;
       9: astore_2
      10: aload_2
      11: invokeinterface #20,  1           // InterfaceMethod java/util/Iterator.hasNext:()Z
      16: ifeq          45
      19: aload_2
      20: invokeinterface #21,  1           // InterfaceMethod java/util/Iterator.next:()Ljava/lang/Object;
      25: checkcast     #22                 // class org/springframework/security/config/annotation/web/messaging/MessageSecurityMetadataSourceRegistry$MatcherBuilder
      28: astore_3
      29: aload_0
      30: getfield      #3                  // Field this$0:Lorg/springframework/security/config/annotation/web/messaging/MessageSecurityMetadataSourceRegistry;
      33: invokestatic  #23                 // Method org/springframework/security/config/annotation/web/messaging/MessageSecurityMetadataSourceRegistry.access$700:(Lorg/springframework/security/config/annotation/web/messaging/MessageSecurityMetadataSourceRegistry;)Ljava/util/LinkedHashMap;
      36: aload_3
      37: aload_1
      38: invokevirtual #24                 // Method java/util/LinkedHashMap.put:(Ljava/lang/Object;Ljava/lang/Object;)Ljava/lang/Object;
      41: pop
      42: goto          10
      45: aload_0
      46: getfield      #3                  // Field this$0:Lorg/springframework/security/config/annotation/web/messaging/MessageSecurityMetadataSourceRegistry;
      49: areturn

  org.springframework.security.config.annotation.web.messaging.MessageSecurityMetadataSourceRegistry$Constraint(org.springframework.security.config.annotation.web.messaging.MessageSecurityMetadataSourceRegistry, java.util.List, org.springframework.security.config.annotation.web.messaging.MessageSecurityMetadataSourceRegistry$1);
    Code:
       0: aload_0
       1: aload_1
       2: aload_2
       3: invokespecial #2                  // Method "<init>":(Lorg/springframework/security/config/annotation/web/messaging/MessageSecurityMetadataSourceRegistry;Ljava/util/List;)V
       6: return
}
