Compiled from "HibernateDaoSupport.java"
public abstract class org.springframework.orm.hibernate4.support.HibernateDaoSupport extends org.springframework.dao.support.DaoSupport {
  private org.springframework.orm.hibernate4.HibernateTemplate hibernateTemplate;

  public org.springframework.orm.hibernate4.support.HibernateDaoSupport();
    Code:
       0: aload_0
       1: invokespecial #1                  // Method org/springframework/dao/support/DaoSupport."<init>":()V
       4: return

  public final void setSessionFactory(org.hibernate.SessionFactory);
    Code:
       0: aload_0
       1: getfield      #2                  // Field hibernateTemplate:Lorg/springframework/orm/hibernate4/HibernateTemplate;
       4: ifnull        18
       7: aload_1
       8: aload_0
       9: getfield      #2                  // Field hibernateTemplate:Lorg/springframework/orm/hibernate4/HibernateTemplate;
      12: invokevirtual #3                  // Method org/springframework/orm/hibernate4/HibernateTemplate.getSessionFactory:()Lorg/hibernate/SessionFactory;
      15: if_acmpeq     27
      18: aload_0
      19: aload_0
      20: aload_1
      21: invokevirtual #4                  // Method createHibernateTemplate:(Lorg/hibernate/SessionFactory;)Lorg/springframework/orm/hibernate4/HibernateTemplate;
      24: putfield      #2                  // Field hibernateTemplate:Lorg/springframework/orm/hibernate4/HibernateTemplate;
      27: return

  protected org.springframework.orm.hibernate4.HibernateTemplate createHibernateTemplate(org.hibernate.SessionFactory);
    Code:
       0: new           #5                  // class org/springframework/orm/hibernate4/HibernateTemplate
       3: dup
       4: aload_1
       5: invokespecial #6                  // Method org/springframework/orm/hibernate4/HibernateTemplate."<init>":(Lorg/hibernate/SessionFactory;)V
       8: areturn

  public final org.hibernate.SessionFactory getSessionFactory();
    Code:
       0: aload_0
       1: getfield      #2                  // Field hibernateTemplate:Lorg/springframework/orm/hibernate4/HibernateTemplate;
       4: ifnull        17
       7: aload_0
       8: getfield      #2                  // Field hibernateTemplate:Lorg/springframework/orm/hibernate4/HibernateTemplate;
      11: invokevirtual #3                  // Method org/springframework/orm/hibernate4/HibernateTemplate.getSessionFactory:()Lorg/hibernate/SessionFactory;
      14: goto          18
      17: aconst_null
      18: areturn

  public final void setHibernateTemplate(org.springframework.orm.hibernate4.HibernateTemplate);
    Code:
       0: aload_0
       1: aload_1
       2: putfield      #2                  // Field hibernateTemplate:Lorg/springframework/orm/hibernate4/HibernateTemplate;
       5: return

  public final org.springframework.orm.hibernate4.HibernateTemplate getHibernateTemplate();
    Code:
       0: aload_0
       1: getfield      #2                  // Field hibernateTemplate:Lorg/springframework/orm/hibernate4/HibernateTemplate;
       4: areturn

  protected final void checkDaoConfig();
    Code:
       0: aload_0
       1: getfield      #2                  // Field hibernateTemplate:Lorg/springframework/orm/hibernate4/HibernateTemplate;
       4: ifnonnull     17
       7: new           #7                  // class java/lang/IllegalArgumentException
      10: dup
      11: ldc           #8                  // String \'sessionFactory\' or \'hibernateTemplate\' is required
      13: invokespecial #9                  // Method java/lang/IllegalArgumentException."<init>":(Ljava/lang/String;)V
      16: athrow
      17: return

  protected final org.hibernate.Session currentSession() throws org.springframework.dao.DataAccessResourceFailureException;
    Code:
       0: aload_0
       1: invokevirtual #10                 // Method getSessionFactory:()Lorg/hibernate/SessionFactory;
       4: invokeinterface #11,  1           // InterfaceMethod org/hibernate/SessionFactory.getCurrentSession:()Lorg/hibernate/Session;
       9: areturn
}
