Compiled from "BlockAwareReader.java"
abstract class org.thymeleaf.templateparser.reader.BlockAwareReader extends java.io.Reader {
  private final java.io.Reader reader;

  private final org.thymeleaf.templateparser.reader.BlockAwareReader$BlockAction action;

  private final char[] prefix;

  private final char[] suffix;

  private final char p0;

  private final char s0;

  private char[] overflowBuffer;

  private int overflowBufferLen;

  private boolean insideComment;

  private int index;

  private int discardFrom;

  protected org.thymeleaf.templateparser.reader.BlockAwareReader(java.io.Reader, org.thymeleaf.templateparser.reader.BlockAwareReader$BlockAction, char[], char[]);
    Code:
       0: aload_0
       1: invokespecial #1                  // Method java/io/Reader."<init>":()V
       4: aload_0
       5: aconst_null
       6: putfield      #2                  // Field overflowBuffer:[C
       9: aload_0
      10: iconst_0
      11: putfield      #3                  // Field overflowBufferLen:I
      14: aload_0
      15: iconst_0
      16: putfield      #4                  // Field insideComment:Z
      19: aload_0
      20: iconst_0
      21: putfield      #5                  // Field index:I
      24: aload_0
      25: iconst_m1
      26: putfield      #6                  // Field discardFrom:I
      29: aload_0
      30: aload_1
      31: putfield      #7                  // Field reader:Ljava/io/Reader;
      34: aload_0
      35: aload_2
      36: putfield      #8                  // Field action:Lorg/thymeleaf/templateparser/reader/BlockAwareReader$BlockAction;
      39: aload_0
      40: aload_3
      41: putfield      #9                  // Field prefix:[C
      44: aload_0
      45: aload         4
      47: putfield      #10                 // Field suffix:[C
      50: aload_0
      51: aload_0
      52: getfield      #9                  // Field prefix:[C
      55: iconst_0
      56: caload
      57: putfield      #11                 // Field p0:C
      60: aload_0
      61: aload_0
      62: getfield      #10                 // Field suffix:[C
      65: iconst_0
      66: caload
      67: putfield      #12                 // Field s0:C
      70: return

  public int read(char[], int, int) throws java.io.IOException;
    Code:
       0: aload_0
       1: aload_1
       2: iload_2
       3: iload_3
       4: invokespecial #13                 // Method readBytes:([CII)I
       7: istore        4
       9: iload         4
      11: ifgt          85
      14: iload         4
      16: ifge          82
      19: aload_0
      20: getfield      #4                  // Field insideComment:Z
      23: ifeq          82
      26: new           #14                 // class java/io/IOException
      29: dup
      30: new           #15                 // class java/lang/StringBuilder
      33: dup
      34: invokespecial #16                 // Method java/lang/StringBuilder."<init>":()V
      37: ldc           #17                 // String Unfinished block structure
      39: invokevirtual #18                 // Method java/lang/StringBuilder.append:(Ljava/lang/String;)Ljava/lang/StringBuilder;
      42: new           #19                 // class java/lang/String
      45: dup
      46: aload_0
      47: getfield      #9                  // Field prefix:[C
      50: invokespecial #20                 // Method java/lang/String."<init>":([C)V
      53: invokevirtual #18                 // Method java/lang/StringBuilder.append:(Ljava/lang/String;)Ljava/lang/StringBuilder;
      56: ldc           #21                 // String ...
      58: invokevirtual #18                 // Method java/lang/StringBuilder.append:(Ljava/lang/String;)Ljava/lang/StringBuilder;
      61: new           #19                 // class java/lang/String
      64: dup
      65: aload_0
      66: getfield      #10                 // Field suffix:[C
      69: invokespecial #20                 // Method java/lang/String."<init>":([C)V
      72: invokevirtual #18                 // Method java/lang/StringBuilder.append:(Ljava/lang/String;)Ljava/lang/StringBuilder;
      75: invokevirtual #22                 // Method java/lang/StringBuilder.toString:()Ljava/lang/String;
      78: invokespecial #23                 // Method java/io/IOException."<init>":(Ljava/lang/String;)V
      81: athrow
      82: iload         4
      84: ireturn
      85: aload_0
      86: aload_0
      87: getfield      #6                  // Field discardFrom:I
      90: ifge          100
      93: aload_0
      94: getfield      #6                  // Field discardFrom:I
      97: goto          108
     100: iload_2
     101: aload_0
     102: getfield      #6                  // Field discardFrom:I
     105: invokestatic  #24                 // Method java/lang/Math.max:(II)I
     108: putfield      #6                  // Field discardFrom:I
     111: iload_2
     112: iload         4
     114: iadd
     115: istore        5
     117: iload_2
     118: istore        7
     120: iload         7
     122: iload         5
     124: if_icmpge     516
     127: aload_1
     128: iload         7
     130: iinc          7, 1
     133: caload
     134: istore        6
     136: aload_0
     137: getfield      #5                  // Field index:I
     140: ifne          164
     143: iload         6
     145: aload_0
     146: getfield      #11                 // Field p0:C
     149: if_icmpeq     164
     152: iload         6
     154: aload_0
     155: getfield      #12                 // Field s0:C
     158: if_icmpeq     164
     161: goto          120
     164: aload_0
     165: getfield      #4                  // Field insideComment:Z
     168: ifne          321
     171: iload         6
     173: aload_0
     174: getfield      #9                  // Field prefix:[C
     177: aload_0
     178: getfield      #5                  // Field index:I
     181: caload
     182: if_icmpne     297
     185: aload_0
     186: dup
     187: getfield      #5                  // Field index:I
     190: iconst_1
     191: iadd
     192: putfield      #5                  // Field index:I
     195: aload_0
     196: getfield      #5                  // Field index:I
     199: aload_0
     200: getfield      #9                  // Field prefix:[C
     203: arraylength
     204: if_icmpne     120
     207: iload         7
     209: iload         5
     211: if_icmpge     234
     214: aload_1
     215: iload         7
     217: aload_1
     218: iload         7
     220: aload_0
     221: getfield      #9                  // Field prefix:[C
     224: arraylength
     225: isub
     226: iload         5
     228: iload         7
     230: isub
     231: invokestatic  #25                 // Method java/lang/System.arraycopy:(Ljava/lang/Object;ILjava/lang/Object;II)V
     234: aload_0
     235: iconst_1
     236: putfield      #4                  // Field insideComment:Z
     239: aload_0
     240: iconst_0
     241: putfield      #5                  // Field index:I
     244: iload         4
     246: aload_0
     247: getfield      #9                  // Field prefix:[C
     250: arraylength
     251: isub
     252: istore        4
     254: iload         5
     256: aload_0
     257: getfield      #9                  // Field prefix:[C
     260: arraylength
     261: isub
     262: istore        5
     264: iload         7
     266: aload_0
     267: getfield      #9                  // Field prefix:[C
     270: arraylength
     271: isub
     272: istore        7
     274: aload_0
     275: aload_0
     276: getfield      #8                  // Field action:Lorg/thymeleaf/templateparser/reader/BlockAwareReader$BlockAction;
     279: getstatic     #26                 // Field org/thymeleaf/templateparser/reader/BlockAwareReader$BlockAction.DISCARD_ALL:Lorg/thymeleaf/templateparser/reader/BlockAwareReader$BlockAction;
     282: if_acmpne     290
     285: iload         7
     287: goto          291
     290: iconst_m1
     291: putfield      #6                  // Field discardFrom:I
     294: goto          120
     297: aload_0
     298: getfield      #5                  // Field index:I
     301: ifle          313
     304: iload         7
     306: aload_0
     307: getfield      #5                  // Field index:I
     310: isub
     311: istore        7
     313: aload_0
     314: iconst_0
     315: putfield      #5                  // Field index:I
     318: goto          120
     321: iload         6
     323: aload_0
     324: getfield      #10                 // Field suffix:[C
     327: aload_0
     328: getfield      #5                  // Field index:I
     331: caload
     332: if_icmpne     492
     335: aload_0
     336: dup
     337: getfield      #5                  // Field index:I
     340: iconst_1
     341: iadd
     342: putfield      #5                  // Field index:I
     345: aload_0
     346: getfield      #5                  // Field index:I
     349: aload_0
     350: getfield      #10                 // Field suffix:[C
     353: arraylength
     354: if_icmpne     120
     357: iload         7
     359: iload         5
     361: if_icmpge     384
     364: aload_1
     365: iload         7
     367: aload_1
     368: iload         7
     370: aload_0
     371: getfield      #10                 // Field suffix:[C
     374: arraylength
     375: isub
     376: iload         5
     378: iload         7
     380: isub
     381: invokestatic  #25                 // Method java/lang/System.arraycopy:(Ljava/lang/Object;ILjava/lang/Object;II)V
     384: aload_0
     385: iconst_0
     386: putfield      #4                  // Field insideComment:Z
     389: aload_0
     390: iconst_0
     391: putfield      #5                  // Field index:I
     394: iload         4
     396: aload_0
     397: getfield      #10                 // Field suffix:[C
     400: arraylength
     401: isub
     402: istore        4
     404: iload         5
     406: aload_0
     407: getfield      #10                 // Field suffix:[C
     410: arraylength
     411: isub
     412: istore        5
     414: iload         7
     416: aload_0
     417: getfield      #10                 // Field suffix:[C
     420: arraylength
     421: isub
     422: istore        7
     424: aload_0
     425: getfield      #6                  // Field discardFrom:I
     428: iflt          120
     431: iload         7
     433: iload         5
     435: if_icmpge     454
     438: aload_1
     439: iload         7
     441: aload_1
     442: aload_0
     443: getfield      #6                  // Field discardFrom:I
     446: iload         5
     448: iload         7
     450: isub
     451: invokestatic  #25                 // Method java/lang/System.arraycopy:(Ljava/lang/Object;ILjava/lang/Object;II)V
     454: iload         4
     456: iload         7
     458: aload_0
     459: getfield      #6                  // Field discardFrom:I
     462: isub
     463: isub
     464: istore        4
     466: iload         5
     468: iload         7
     470: aload_0
     471: getfield      #6                  // Field discardFrom:I
     474: isub
     475: isub
     476: istore        5
     478: aload_0
     479: getfield      #6                  // Field discardFrom:I
     482: istore        7
     484: aload_0
     485: iconst_m1
     486: putfield      #6                  // Field discardFrom:I
     489: goto          120
     492: aload_0
     493: getfield      #5                  // Field index:I
     496: ifle          508
     499: iload         7
     501: aload_0
     502: getfield      #5                  // Field index:I
     505: isub
     506: istore        7
     508: aload_0
     509: iconst_0
     510: putfield      #5                  // Field index:I
     513: goto          120
     516: aload_0
     517: getfield      #5                  // Field index:I
     520: ifle          669
     523: aload_0
     524: aload_1
     525: iload         5
     527: aload_0
     528: getfield      #5                  // Field index:I
     531: invokespecial #27                 // Method overflowLastBytes:([CII)V
     534: iload         4
     536: aload_0
     537: getfield      #5                  // Field index:I
     540: isub
     541: istore        4
     543: iload         5
     545: aload_0
     546: getfield      #5                  // Field index:I
     549: isub
     550: istore        5
     552: aload_0
     553: getfield      #4                  // Field insideComment:Z
     556: ifeq          566
     559: aload_0
     560: getfield      #10                 // Field suffix:[C
     563: goto          570
     566: aload_0
     567: getfield      #9                  // Field prefix:[C
     570: astore        8
     572: aload_0
     573: aload         8
     575: invokespecial #28                 // Method matchOverflow:([C)Z
     578: ifeq          617
     581: aload_0
     582: aload_0
     583: getfield      #4                  // Field insideComment:Z
     586: ifne          593
     589: iconst_1
     590: goto          594
     593: iconst_0
     594: putfield      #4                  // Field insideComment:Z
     597: aload_0
     598: dup
     599: getfield      #3                  // Field overflowBufferLen:I
     602: aload         8
     604: arraylength
     605: isub
     606: putfield      #3                  // Field overflowBufferLen:I
     609: aload_0
     610: iconst_0
     611: putfield      #5                  // Field index:I
     614: goto          669
     617: aload_0
     618: getfield      #2                  // Field overflowBuffer:[C
     621: iconst_0
     622: aload_1
     623: iload         5
     625: iconst_1
     626: invokestatic  #25                 // Method java/lang/System.arraycopy:(Ljava/lang/Object;ILjava/lang/Object;II)V
     629: iinc          4, 1
     632: iinc          5, 1
     635: aload_0
     636: getfield      #2                  // Field overflowBuffer:[C
     639: iconst_1
     640: aload_0
     641: getfield      #2                  // Field overflowBuffer:[C
     644: iconst_0
     645: aload_0
     646: getfield      #3                  // Field overflowBufferLen:I
     649: iconst_1
     650: isub
     651: invokestatic  #25                 // Method java/lang/System.arraycopy:(Ljava/lang/Object;ILjava/lang/Object;II)V
     654: aload_0
     655: dup
     656: getfield      #3                  // Field overflowBufferLen:I
     659: iconst_1
     660: isub
     661: putfield      #3                  // Field overflowBufferLen:I
     664: aload_0
     665: iconst_0
     666: putfield      #5                  // Field index:I
     669: aload_0
     670: getfield      #6                  // Field discardFrom:I
     673: iflt          693
     676: iload         4
     678: iload         5
     680: aload_0
     681: getfield      #6                  // Field discardFrom:I
     684: isub
     685: isub
     686: istore        4
     688: aload_0
     689: iconst_0
     690: putfield      #6                  // Field discardFrom:I
     693: aload_0
     694: aload_0
     695: getfield      #4                  // Field insideComment:Z
     698: ifeq          715
     701: aload_0
     702: getfield      #8                  // Field action:Lorg/thymeleaf/templateparser/reader/BlockAwareReader$BlockAction;
     705: getstatic     #26                 // Field org/thymeleaf/templateparser/reader/BlockAwareReader$BlockAction.DISCARD_ALL:Lorg/thymeleaf/templateparser/reader/BlockAwareReader$BlockAction;
     708: if_acmpne     715
     711: iconst_0
     712: goto          716
     715: iconst_m1
     716: putfield      #6                  // Field discardFrom:I
     719: iload         4
     721: ireturn

  private int readBytes(char[], int, int) throws java.io.IOException;
    Code:
       0: iload_3
       1: ifne          6
       4: iconst_0
       5: ireturn
       6: aload_0
       7: getfield      #3                  // Field overflowBufferLen:I
      10: ifne          24
      13: aload_0
      14: getfield      #7                  // Field reader:Ljava/io/Reader;
      17: aload_1
      18: iload_2
      19: iload_3
      20: invokevirtual #29                 // Method java/io/Reader.read:([CII)I
      23: ireturn
      24: aload_0
      25: getfield      #3                  // Field overflowBufferLen:I
      28: iload_3
      29: if_icmpgt     96
      32: aload_0
      33: getfield      #2                  // Field overflowBuffer:[C
      36: iconst_0
      37: aload_1
      38: iload_2
      39: aload_0
      40: getfield      #3                  // Field overflowBufferLen:I
      43: invokestatic  #25                 // Method java/lang/System.arraycopy:(Ljava/lang/Object;ILjava/lang/Object;II)V
      46: aload_0
      47: getfield      #3                  // Field overflowBufferLen:I
      50: istore        4
      52: aload_0
      53: iconst_0
      54: putfield      #3                  // Field overflowBufferLen:I
      57: iload         4
      59: iload_3
      60: if_icmpge     93
      63: aload_0
      64: getfield      #7                  // Field reader:Ljava/io/Reader;
      67: aload_1
      68: iload_2
      69: iload         4
      71: iadd
      72: iload_3
      73: iload         4
      75: isub
      76: invokevirtual #29                 // Method java/io/Reader.read:([CII)I
      79: istore        5
      81: iload         5
      83: ifle          93
      86: iload         4
      88: iload         5
      90: iadd
      91: istore        4
      93: iload         4
      95: ireturn
      96: aload_0
      97: getfield      #2                  // Field overflowBuffer:[C
     100: iconst_0
     101: aload_1
     102: iload_2
     103: iload_3
     104: invokestatic  #25                 // Method java/lang/System.arraycopy:(Ljava/lang/Object;ILjava/lang/Object;II)V
     107: iload_3
     108: aload_0
     109: getfield      #3                  // Field overflowBufferLen:I
     112: if_icmpge     134
     115: aload_0
     116: getfield      #2                  // Field overflowBuffer:[C
     119: iload_3
     120: aload_0
     121: getfield      #2                  // Field overflowBuffer:[C
     124: iconst_0
     125: aload_0
     126: getfield      #3                  // Field overflowBufferLen:I
     129: iload_3
     130: isub
     131: invokestatic  #25                 // Method java/lang/System.arraycopy:(Ljava/lang/Object;ILjava/lang/Object;II)V
     134: aload_0
     135: dup
     136: getfield      #3                  // Field overflowBufferLen:I
     139: iload_3
     140: isub
     141: putfield      #3                  // Field overflowBufferLen:I
     144: iload_3
     145: ireturn

  private void overflowLastBytes(char[], int, int);
    Code:
       0: aload_0
       1: getfield      #2                  // Field overflowBuffer:[C
       4: ifnonnull     26
       7: aload_0
       8: aload_0
       9: getfield      #9                  // Field prefix:[C
      12: arraylength
      13: aload_0
      14: getfield      #10                 // Field suffix:[C
      17: arraylength
      18: invokestatic  #24                 // Method java/lang/Math.max:(II)I
      21: newarray       char
      23: putfield      #2                  // Field overflowBuffer:[C
      26: aload_0
      27: getfield      #3                  // Field overflowBufferLen:I
      30: ifle          50
      33: aload_0
      34: getfield      #2                  // Field overflowBuffer:[C
      37: iconst_0
      38: aload_0
      39: getfield      #2                  // Field overflowBuffer:[C
      42: iload_3
      43: aload_0
      44: getfield      #3                  // Field overflowBufferLen:I
      47: invokestatic  #25                 // Method java/lang/System.arraycopy:(Ljava/lang/Object;ILjava/lang/Object;II)V
      50: aload_1
      51: iload_2
      52: iload_3
      53: isub
      54: aload_0
      55: getfield      #2                  // Field overflowBuffer:[C
      58: iconst_0
      59: iload_3
      60: invokestatic  #25                 // Method java/lang/System.arraycopy:(Ljava/lang/Object;ILjava/lang/Object;II)V
      63: aload_0
      64: dup
      65: getfield      #3                  // Field overflowBufferLen:I
      68: iload_3
      69: iadd
      70: putfield      #3                  // Field overflowBufferLen:I
      73: return

  private boolean matchOverflow(char[]) throws java.io.IOException;
    Code:
       0: aload_0
       1: getfield      #3                  // Field overflowBufferLen:I
       4: ifle          37
       7: iconst_0
       8: istore_2
       9: iload_2
      10: aload_0
      11: getfield      #3                  // Field overflowBufferLen:I
      14: if_icmpge     37
      17: aload_0
      18: getfield      #2                  // Field overflowBuffer:[C
      21: iload_2
      22: caload
      23: aload_1
      24: iload_2
      25: caload
      26: if_icmpeq     31
      29: iconst_0
      30: ireturn
      31: iinc          2, 1
      34: goto          9
      37: iconst_0
      38: istore_2
      39: iload_2
      40: iflt          107
      43: aload_0
      44: getfield      #3                  // Field overflowBufferLen:I
      47: aload_1
      48: arraylength
      49: if_icmpge     107
      52: aload_0
      53: getfield      #7                  // Field reader:Ljava/io/Reader;
      56: aload_0
      57: getfield      #2                  // Field overflowBuffer:[C
      60: aload_0
      61: getfield      #3                  // Field overflowBufferLen:I
      64: iconst_1
      65: invokevirtual #29                 // Method java/io/Reader.read:([CII)I
      68: istore_2
      69: iload_2
      70: ifle          39
      73: aload_0
      74: dup
      75: getfield      #3                  // Field overflowBufferLen:I
      78: iconst_1
      79: iadd
      80: putfield      #3                  // Field overflowBufferLen:I
      83: aload_0
      84: getfield      #2                  // Field overflowBuffer:[C
      87: aload_0
      88: getfield      #3                  // Field overflowBufferLen:I
      91: iconst_1
      92: isub
      93: caload
      94: aload_1
      95: aload_0
      96: getfield      #3                  // Field overflowBufferLen:I
      99: iconst_1
     100: isub
     101: caload
     102: if_icmpeq     39
     105: iconst_0
     106: ireturn
     107: aload_0
     108: getfield      #3                  // Field overflowBufferLen:I
     111: aload_1
     112: arraylength
     113: if_icmpne     120
     116: iconst_1
     117: goto          121
     120: iconst_0
     121: ireturn

  public void close() throws java.io.IOException;
    Code:
       0: aload_0
       1: getfield      #7                  // Field reader:Ljava/io/Reader;
       4: invokevirtual #30                 // Method java/io/Reader.close:()V
       7: return
}
