Compiled from "TypesJVM.kt"
final class kotlin.reflect.TypesJVMKt$typeToString$unwrap$1 extends kotlin.jvm.internal.FunctionReferenceImpl implements kotlin.jvm.functions.Function1<java.lang.Class<?>, java.lang.Class<?>> {
  public static final kotlin.reflect.TypesJVMKt$typeToString$unwrap$1 INSTANCE;

  kotlin.reflect.TypesJVMKt$typeToString$unwrap$1();
    Code:
       0: aload_0
       1: iconst_1
       2: ldc           #11                 // class java/lang/Class
       4: ldc           #13                 // String getComponentType
       6: ldc           #15                 // String getComponentType()Ljava/lang/Class;
       8: iconst_0
       9: invokespecial #18                 // Method kotlin/jvm/internal/FunctionReferenceImpl."<init>":(ILjava/lang/Class;Ljava/lang/String;Ljava/lang/String;I)V
      12: return

  public final java.lang.Class<?> invoke(java.lang.Class<?>);
    Code:
       0: aload_1
       1: ldc           #26                 // String p0
       3: invokestatic  #32                 // Method kotlin/jvm/internal/Intrinsics.checkNotNullParameter:(Ljava/lang/Object;Ljava/lang/String;)V
       6: aload_1
       7: invokevirtual #35                 // Method java/lang/Class.getComponentType:()Ljava/lang/Class;
      10: areturn

  public java.lang.Object invoke(java.lang.Object);
    Code:
       0: aload_0
       1: aload_1
       2: checkcast     #11                 // class java/lang/Class
       5: invokevirtual #39                 // Method invoke:(Ljava/lang/Class;)Ljava/lang/Class;
       8: areturn

  static {};
    Code:
       0: new           #2                  // class kotlin/reflect/TypesJVMKt$typeToString$unwrap$1
       3: dup
       4: invokespecial #44                 // Method "<init>":()V
       7: putstatic     #47                 // Field INSTANCE:Lkotlin/reflect/TypesJVMKt$typeToString$unwrap$1;
      10: return
}
