Compiled from "AuthorizationPreInitializer.java"
public class cloud.piranha.security.exousia.AuthorizationPreInitializer implements javax.servlet.ServletContainerInitializer {
  public static final java.lang.String AUTHZ_SERVICE;

  public static final java.lang.String AUTHZ_FACTORY_CLASS;

  public static final java.lang.String AUTHZ_POLICY_CLASS;

  public static final java.lang.String UNCHECKED_PERMISSIONS;

  public static final java.lang.String PERROLE_PERMISSIONS;

  public static final java.lang.String CONSTRAINTS;

  public static final java.lang.String SECURITY_ELEMENTS;

  public static final java.lang.String SECURITY_ANNOTATIONS;

  public cloud.piranha.security.exousia.AuthorizationPreInitializer();
    Code:
       0: aload_0
       1: invokespecial #1                  // Method java/lang/Object."<init>":()V
       4: return

  public void onStartup(java.util.Set<java.lang.Class<?>>, javax.servlet.ServletContext) throws javax.servlet.ServletException;
    Code:
       0: aload_2
       1: checkcast     #2                  // class cloud/piranha/api/WebApplication
       4: astore_3
       5: aload_0
       6: aload_2
       7: getstatic     #3                  // Field AUTHZ_FACTORY_CLASS:Ljava/lang/String;
      10: invokevirtual #4                  // Method getAttribute:(Ljavax/servlet/ServletContext;Ljava/lang/String;)Ljava/lang/Object;
      13: checkcast     #5                  // class java/lang/Class
      16: astore        4
      18: aload_0
      19: aload_2
      20: getstatic     #6                  // Field AUTHZ_POLICY_CLASS:Ljava/lang/String;
      23: invokevirtual #4                  // Method getAttribute:(Ljavax/servlet/ServletContext;Ljava/lang/String;)Ljava/lang/Object;
      26: checkcast     #5                  // class java/lang/Class
      29: astore        5
      31: new           #7                  // class org/omnifaces/exousia/AuthorizationService
      34: dup
      35: aload         4
      37: aload         5
      39: aload_3
      40: invokeinterface #8,  1            // InterfaceMethod cloud/piranha/api/WebApplication.getServletContextId:()Ljava/lang/String;
      45: invokedynamic #9,  0              // InvokeDynamic #0:get:()Ljava/util/function/Supplier;
      50: invokedynamic #10,  0             // InvokeDynamic #1:get:()Ljava/util/function/Supplier;
      55: new           #11                 // class cloud/piranha/security/exousia/PiranhaPrincipalMapper
      58: dup
      59: invokespecial #12                 // Method cloud/piranha/security/exousia/PiranhaPrincipalMapper."<init>":()V
      62: invokespecial #13                 // Method org/omnifaces/exousia/AuthorizationService."<init>":(Ljava/lang/Class;Ljava/lang/Class;Ljava/lang/String;Ljava/util/function/Supplier;Ljava/util/function/Supplier;Lorg/omnifaces/exousia/spi/PrincipalMapper;)V
      65: astore        6
      67: aload_0
      68: aload_0
      69: aload_2
      70: aload         6
      72: invokevirtual #14                 // Method getConstraintsFromSecurityElements:(Ljavax/servlet/ServletContext;Lorg/omnifaces/exousia/AuthorizationService;)Ljava/util/List;
      75: aload_0
      76: aload_2
      77: aload         6
      79: invokevirtual #15                 // Method getConstraintsFromSecurityAnnotations:(Ljavax/servlet/ServletContext;Lorg/omnifaces/exousia/AuthorizationService;)Ljava/util/List;
      82: aload_0
      83: aload_2
      84: getstatic     #16                 // Field CONSTRAINTS:Ljava/lang/String;
      87: invokevirtual #17                 // Method getOptionalAttribute:(Ljavax/servlet/ServletContext;Ljava/lang/String;)Ljava/lang/Object;
      90: checkcast     #18                 // class java/util/List
      93: aload_0
      94: aload_3
      95: invokevirtual #19                 // Method getConstraintsFromWebXMl:(Lcloud/piranha/api/WebApplication;)Ljava/util/List;
      98: invokevirtual #20                 // Method join:(Ljava/util/List;Ljava/util/List;Ljava/util/List;Ljava/util/List;)Ljava/util/List;
     101: astore        7
     103: aload_0
     104: aload_3
     105: invokevirtual #21                 // Method hasPermissionsSet:(Ljavax/servlet/ServletContext;)Z
     108: ifeq          121
     111: aload_0
     112: aload_3
     113: aload         6
     115: invokevirtual #22                 // Method setPermissions:(Ljavax/servlet/ServletContext;Lorg/omnifaces/exousia/AuthorizationService;)V
     118: goto          158
     121: aload         6
     123: aload         7
     125: ifnull        133
     128: aload         7
     130: goto          136
     133: invokestatic  #23                 // Method java/util/Collections.emptyList:()Ljava/util/List;
     136: invokestatic  #24                 // Method java/util/Collections.emptySet:()Ljava/util/Set;
     139: aload_0
     140: aload_3
     141: invokespecial #25                 // Method isDenyUncoveredHttpMethods:(Lcloud/piranha/api/WebApplication;)Z
     144: aload_3
     145: invokeinterface #26,  1           // InterfaceMethod cloud/piranha/api/WebApplication.getServletRegistrations:()Ljava/util/Map;
     150: invokeinterface #27,  1           // InterfaceMethod java/util/Map.keySet:()Ljava/util/Set;
     155: invokevirtual #28                 // Method org/omnifaces/exousia/AuthorizationService.addConstraintsToPolicy:(Ljava/util/List;Ljava/util/Set;ZLjava/util/Collection;)V
     158: aload_2
     159: getstatic     #29                 // Field AUTHZ_SERVICE:Ljava/lang/String;
     162: aload         6
     164: invokeinterface #30,  3           // InterfaceMethod javax/servlet/ServletContext.setAttribute:(Ljava/lang/String;Ljava/lang/Object;)V
     169: aload_2
     170: ldc           #31                 // class cloud/piranha/security/exousia/AuthorizationPreFilter
     172: invokevirtual #32                 // Method java/lang/Class.getSimpleName:()Ljava/lang/String;
     175: ldc           #31                 // class cloud/piranha/security/exousia/AuthorizationPreFilter
     177: invokeinterface #33,  3           // InterfaceMethod javax/servlet/ServletContext.addFilter:(Ljava/lang/String;Ljava/lang/Class;)Ljavax/servlet/FilterRegistration$Dynamic;
     182: pop
     183: aload_3
     184: ldc           #31                 // class cloud/piranha/security/exousia/AuthorizationPreFilter
     186: invokevirtual #32                 // Method java/lang/Class.getSimpleName:()Ljava/lang/String;
     189: iconst_1
     190: anewarray     #34                 // class java/lang/String
     193: dup
     194: iconst_0
     195: ldc           #35                 // String /*
     197: aastore
     198: invokeinterface #36,  3           // InterfaceMethod cloud/piranha/api/WebApplication.addFilterMapping:(Ljava/lang/String;[Ljava/lang/String;)Ljava/util/Set;
     203: pop
     204: return

  private boolean isDenyUncoveredHttpMethods(cloud.piranha.api.WebApplication) throws javax.servlet.ServletException;
    Code:
       0: aload_1
       1: invokeinterface #37,  1           // InterfaceMethod cloud/piranha/api/WebApplication.getDenyUncoveredHttpMethods:()Z
       6: ireturn

  public static void addToRole(javax.security.jacc.PolicyConfiguration, java.lang.String, java.security.Permission);
    Code:
       0: aload_0
       1: aload_1
       2: aload_2
       3: invokeinterface #38,  3           // InterfaceMethod javax/security/jacc/PolicyConfiguration.addToRole:(Ljava/lang/String;Ljava/security/Permission;)V
       8: goto          21
      11: astore_3
      12: new           #40                 // class java/lang/IllegalStateException
      15: dup
      16: aload_3
      17: invokespecial #41                 // Method java/lang/IllegalStateException."<init>":(Ljava/lang/Throwable;)V
      20: athrow
      21: return
    Exception table:
       from    to  target type
           0     8    11   Class javax/security/jacc/PolicyContextException

  public <T> T getAttribute(javax.servlet.ServletContext, java.lang.String) throws javax.servlet.ServletException;
    Code:
       0: aload_0
       1: aload_1
       2: aload_2
       3: invokevirtual #17                 // Method getOptionalAttribute:(Ljavax/servlet/ServletContext;Ljava/lang/String;)Ljava/lang/Object;
       6: astore_3
       7: aload_3
       8: ifnonnull     25
      11: new           #42                 // class javax/servlet/ServletException
      14: dup
      15: aload_2
      16: invokedynamic #43,  0             // InvokeDynamic #2:makeConcatWithConstants:(Ljava/lang/String;)Ljava/lang/String;
      21: invokespecial #44                 // Method javax/servlet/ServletException."<init>":(Ljava/lang/String;)V
      24: athrow
      25: aload_3
      26: areturn

  public <T> T getOptionalAttribute(javax.servlet.ServletContext, java.lang.String) throws javax.servlet.ServletException;
    Code:
       0: aload_1
       1: aload_2
       2: invokeinterface #45,  2           // InterfaceMethod javax/servlet/ServletContext.getAttribute:(Ljava/lang/String;)Ljava/lang/Object;
       7: astore_3
       8: aload_3
       9: areturn

  public java.util.List<org.omnifaces.exousia.constraints.SecurityConstraint> getConstraintsFromSecurityElements(javax.servlet.ServletContext, org.omnifaces.exousia.AuthorizationService) throws javax.servlet.ServletException;
    Code:
       0: aload_0
       1: aload_1
       2: getstatic     #46                 // Field SECURITY_ELEMENTS:Ljava/lang/String;
       5: invokevirtual #17                 // Method getOptionalAttribute:(Ljavax/servlet/ServletContext;Ljava/lang/String;)Ljava/lang/Object;
       8: checkcast     #18                 // class java/util/List
      11: astore_3
      12: aload_3
      13: ifnonnull     18
      16: aconst_null
      17: areturn
      18: new           #47                 // class java/util/ArrayList
      21: dup
      22: invokespecial #48                 // Method java/util/ArrayList."<init>":()V
      25: astore        4
      27: aload_3
      28: invokeinterface #49,  1           // InterfaceMethod java/util/List.iterator:()Ljava/util/Iterator;
      33: astore        5
      35: aload         5
      37: invokeinterface #50,  1           // InterfaceMethod java/util/Iterator.hasNext:()Z
      42: ifeq          98
      45: aload         5
      47: invokeinterface #51,  1           // InterfaceMethod java/util/Iterator.next:()Ljava/lang/Object;
      52: checkcast     #52                 // class java/util/Map$Entry
      55: astore        6
      57: aload         4
      59: new           #53                 // class java/util/HashSet
      62: dup
      63: aload         6
      65: invokeinterface #54,  1           // InterfaceMethod java/util/Map$Entry.getKey:()Ljava/lang/Object;
      70: checkcast     #55                 // class java/util/Collection
      73: invokespecial #56                 // Method java/util/HashSet."<init>":(Ljava/util/Collection;)V
      76: aload         6
      78: invokeinterface #57,  1           // InterfaceMethod java/util/Map$Entry.getValue:()Ljava/lang/Object;
      83: checkcast     #58                 // class javax/servlet/ServletSecurityElement
      86: invokestatic  #59                 // Method org/omnifaces/exousia/constraints/transformer/ElementsToConstraintsTransformer.createConstraints:(Ljava/util/Set;Ljavax/servlet/ServletSecurityElement;)Ljava/util/List;
      89: invokeinterface #60,  2           // InterfaceMethod java/util/List.addAll:(Ljava/util/Collection;)Z
      94: pop
      95: goto          35
      98: aload         4
     100: areturn

  public java.util.List<org.omnifaces.exousia.constraints.SecurityConstraint> getConstraintsFromSecurityAnnotations(javax.servlet.ServletContext, org.omnifaces.exousia.AuthorizationService) throws javax.servlet.ServletException;
    Code:
       0: aload_0
       1: aload_1
       2: getstatic     #61                 // Field SECURITY_ANNOTATIONS:Ljava/lang/String;
       5: invokevirtual #17                 // Method getOptionalAttribute:(Ljavax/servlet/ServletContext;Ljava/lang/String;)Ljava/lang/Object;
       8: checkcast     #18                 // class java/util/List
      11: astore_3
      12: aload_3
      13: ifnonnull     18
      16: aconst_null
      17: areturn
      18: new           #47                 // class java/util/ArrayList
      21: dup
      22: invokespecial #48                 // Method java/util/ArrayList."<init>":()V
      25: astore        4
      27: aload_3
      28: invokeinterface #49,  1           // InterfaceMethod java/util/List.iterator:()Ljava/util/Iterator;
      33: astore        5
      35: aload         5
      37: invokeinterface #50,  1           // InterfaceMethod java/util/Iterator.hasNext:()Z
      42: ifeq          98
      45: aload         5
      47: invokeinterface #51,  1           // InterfaceMethod java/util/Iterator.next:()Ljava/lang/Object;
      52: checkcast     #52                 // class java/util/Map$Entry
      55: astore        6
      57: aload         4
      59: new           #53                 // class java/util/HashSet
      62: dup
      63: aload         6
      65: invokeinterface #54,  1           // InterfaceMethod java/util/Map$Entry.getKey:()Ljava/lang/Object;
      70: checkcast     #55                 // class java/util/Collection
      73: invokespecial #56                 // Method java/util/HashSet."<init>":(Ljava/util/Collection;)V
      76: aload         6
      78: invokeinterface #57,  1           // InterfaceMethod java/util/Map$Entry.getValue:()Ljava/lang/Object;
      83: checkcast     #62                 // class javax/servlet/annotation/ServletSecurity
      86: invokestatic  #63                 // Method org/omnifaces/exousia/constraints/transformer/ElementsToConstraintsTransformer.createConstraints:(Ljava/util/Set;Ljavax/servlet/annotation/ServletSecurity;)Ljava/util/List;
      89: invokeinterface #60,  2           // InterfaceMethod java/util/List.addAll:(Ljava/util/Collection;)Z
      94: pop
      95: goto          35
      98: aload         4
     100: areturn

  public java.util.List<org.omnifaces.exousia.constraints.SecurityConstraint> getConstraintsFromWebXMl(cloud.piranha.api.WebApplication) throws javax.servlet.ServletException;
    Code:
       0: aload_1
       1: getstatic     #64                 // Field cloud/piranha/servlet/webxml/WebXmlManager.KEY:Ljava/lang/String;
       4: invokeinterface #65,  2           // InterfaceMethod cloud/piranha/api/WebApplication.getAttribute:(Ljava/lang/String;)Ljava/lang/Object;
       9: checkcast     #66                 // class cloud/piranha/servlet/webxml/WebXmlManager
      12: astore_2
      13: aload_2
      14: invokevirtual #67                 // Method cloud/piranha/servlet/webxml/WebXmlManager.getWebXml:()Lcloud/piranha/servlet/webxml/WebXml;
      17: astore_3
      18: aload_3
      19: ifnull        29
      22: aload_3
      23: getfield      #68                 // Field cloud/piranha/servlet/webxml/WebXml.securityConstraints:Ljava/util/List;
      26: ifnonnull     31
      29: aconst_null
      30: areturn
      31: new           #47                 // class java/util/ArrayList
      34: dup
      35: invokespecial #48                 // Method java/util/ArrayList."<init>":()V
      38: astore        4
      40: aload_3
      41: getfield      #68                 // Field cloud/piranha/servlet/webxml/WebXml.securityConstraints:Ljava/util/List;
      44: invokeinterface #49,  1           // InterfaceMethod java/util/List.iterator:()Ljava/util/Iterator;
      49: astore        5
      51: aload         5
      53: invokeinterface #50,  1           // InterfaceMethod java/util/Iterator.hasNext:()Z
      58: ifeq          203
      61: aload         5
      63: invokeinterface #51,  1           // InterfaceMethod java/util/Iterator.next:()Ljava/lang/Object;
      68: checkcast     #69                 // class cloud/piranha/servlet/webxml/WebXml$SecurityConstraint
      71: astore        6
      73: new           #47                 // class java/util/ArrayList
      76: dup
      77: invokespecial #48                 // Method java/util/ArrayList."<init>":()V
      80: astore        7
      82: aload         6
      84: getfield      #70                 // Field cloud/piranha/servlet/webxml/WebXml$SecurityConstraint.webResourceCollections:Ljava/util/List;
      87: invokeinterface #49,  1           // InterfaceMethod java/util/List.iterator:()Ljava/util/Iterator;
      92: astore        8
      94: aload         8
      96: invokeinterface #50,  1           // InterfaceMethod java/util/Iterator.hasNext:()Z
     101: ifeq          149
     104: aload         8
     106: invokeinterface #51,  1           // InterfaceMethod java/util/Iterator.next:()Ljava/lang/Object;
     111: checkcast     #71                 // class cloud/piranha/servlet/webxml/WebXml$SecurityConstraint$WebResourceCollection
     114: astore        9
     116: aload         7
     118: new           #72                 // class org/omnifaces/exousia/constraints/WebResourceCollection
     121: dup
     122: aload         9
     124: getfield      #73                 // Field cloud/piranha/servlet/webxml/WebXml$SecurityConstraint$WebResourceCollection.urlPatterns:Ljava/util/List;
     127: aload         9
     129: getfield      #74                 // Field cloud/piranha/servlet/webxml/WebXml$SecurityConstraint$WebResourceCollection.httpMethods:Ljava/util/List;
     132: aload         9
     134: getfield      #75                 // Field cloud/piranha/servlet/webxml/WebXml$SecurityConstraint$WebResourceCollection.httpMethodOmissions:Ljava/util/List;
     137: invokespecial #76                 // Method org/omnifaces/exousia/constraints/WebResourceCollection."<init>":(Ljava/util/List;Ljava/util/List;Ljava/util/List;)V
     140: invokeinterface #77,  2           // InterfaceMethod java/util/List.add:(Ljava/lang/Object;)Z
     145: pop
     146: goto          94
     149: aload         4
     151: new           #78                 // class org/omnifaces/exousia/constraints/SecurityConstraint
     154: dup
     155: aload         7
     157: new           #53                 // class java/util/HashSet
     160: dup
     161: aload         6
     163: getfield      #79                 // Field cloud/piranha/servlet/webxml/WebXml$SecurityConstraint.roleNames:Ljava/util/List;
     166: invokespecial #56                 // Method java/util/HashSet."<init>":(Ljava/util/Collection;)V
     169: ldc           #80                 // String confidential
     171: aload         6
     173: getfield      #81                 // Field cloud/piranha/servlet/webxml/WebXml$SecurityConstraint.transportGuarantee:Ljava/lang/String;
     176: invokevirtual #82                 // Method java/lang/String.equalsIgnoreCase:(Ljava/lang/String;)Z
     179: ifeq          188
     182: getstatic     #83                 // Field javax/servlet/annotation/ServletSecurity$TransportGuarantee.CONFIDENTIAL:Ljavax/servlet/annotation/ServletSecurity$TransportGuarantee;
     185: goto          191
     188: getstatic     #84                 // Field javax/servlet/annotation/ServletSecurity$TransportGuarantee.NONE:Ljavax/servlet/annotation/ServletSecurity$TransportGuarantee;
     191: invokespecial #85                 // Method org/omnifaces/exousia/constraints/SecurityConstraint."<init>":(Ljava/util/List;Ljava/util/Set;Ljavax/servlet/annotation/ServletSecurity$TransportGuarantee;)V
     194: invokeinterface #77,  2           // InterfaceMethod java/util/List.add:(Ljava/lang/Object;)Z
     199: pop
     200: goto          51
     203: aload         4
     205: areturn

  public java.util.List<org.omnifaces.exousia.constraints.SecurityConstraint> join(java.util.List<org.omnifaces.exousia.constraints.SecurityConstraint>, java.util.List<org.omnifaces.exousia.constraints.SecurityConstraint>, java.util.List<org.omnifaces.exousia.constraints.SecurityConstraint>, java.util.List<org.omnifaces.exousia.constraints.SecurityConstraint>);
    Code:
       0: aload_0
       1: aload_0
       2: aload_1
       3: aload_2
       4: aload_3
       5: invokevirtual #86                 // Method join:(Ljava/util/List;Ljava/util/List;Ljava/util/List;)Ljava/util/List;
       8: aload         4
      10: invokevirtual #87                 // Method join:(Ljava/util/List;Ljava/util/List;)Ljava/util/List;
      13: areturn

  public java.util.List<org.omnifaces.exousia.constraints.SecurityConstraint> join(java.util.List<org.omnifaces.exousia.constraints.SecurityConstraint>, java.util.List<org.omnifaces.exousia.constraints.SecurityConstraint>, java.util.List<org.omnifaces.exousia.constraints.SecurityConstraint>);
    Code:
       0: aload_0
       1: aload_0
       2: aload_1
       3: aload_2
       4: invokevirtual #87                 // Method join:(Ljava/util/List;Ljava/util/List;)Ljava/util/List;
       7: aload_3
       8: invokevirtual #87                 // Method join:(Ljava/util/List;Ljava/util/List;)Ljava/util/List;
      11: areturn

  public java.util.List<org.omnifaces.exousia.constraints.SecurityConstraint> join(java.util.List<org.omnifaces.exousia.constraints.SecurityConstraint>, java.util.List<org.omnifaces.exousia.constraints.SecurityConstraint>);
    Code:
       0: aload_1
       1: ifnonnull     10
       4: aload_2
       5: ifnonnull     10
       8: aconst_null
       9: areturn
      10: aload_1
      11: ifnull        45
      14: aload_2
      15: ifnull        45
      18: aload_1
      19: invokeinterface #88,  1           // InterfaceMethod java/util/List.stream:()Ljava/util/stream/Stream;
      24: aload_2
      25: invokeinterface #88,  1           // InterfaceMethod java/util/List.stream:()Ljava/util/stream/Stream;
      30: invokestatic  #89                 // InterfaceMethod java/util/stream/Stream.concat:(Ljava/util/stream/Stream;Ljava/util/stream/Stream;)Ljava/util/stream/Stream;
      33: invokestatic  #90                 // Method java/util/stream/Collectors.toList:()Ljava/util/stream/Collector;
      36: invokeinterface #91,  2           // InterfaceMethod java/util/stream/Stream.collect:(Ljava/util/stream/Collector;)Ljava/lang/Object;
      41: checkcast     #18                 // class java/util/List
      44: areturn
      45: aload_1
      46: ifnull        51
      49: aload_1
      50: areturn
      51: aload_2
      52: areturn

  public boolean hasPermissionsSet(javax.servlet.ServletContext) throws javax.servlet.ServletException;
    Code:
       0: aload_0
       1: aload_1
       2: getstatic     #92                 // Field UNCHECKED_PERMISSIONS:Ljava/lang/String;
       5: invokevirtual #17                 // Method getOptionalAttribute:(Ljavax/servlet/ServletContext;Ljava/lang/String;)Ljava/lang/Object;
       8: ifnonnull     22
      11: aload_0
      12: aload_1
      13: getstatic     #93                 // Field PERROLE_PERMISSIONS:Ljava/lang/String;
      16: invokevirtual #17                 // Method getOptionalAttribute:(Ljavax/servlet/ServletContext;Ljava/lang/String;)Ljava/lang/Object;
      19: ifnull        26
      22: iconst_1
      23: goto          27
      26: iconst_0
      27: ireturn

  public void setPermissions(javax.servlet.ServletContext, org.omnifaces.exousia.AuthorizationService) throws javax.servlet.ServletException;
    Code:
       0: aload_2
       1: invokevirtual #94                 // Method org/omnifaces/exousia/AuthorizationService.getPolicyConfiguration:()Ljavax/security/jacc/PolicyConfiguration;
       4: astore_3
       5: aload_0
       6: aload_1
       7: getstatic     #92                 // Field UNCHECKED_PERMISSIONS:Ljava/lang/String;
      10: invokevirtual #17                 // Method getOptionalAttribute:(Ljavax/servlet/ServletContext;Ljava/lang/String;)Ljava/lang/Object;
      13: checkcast     #18                 // class java/util/List
      16: astore        4
      18: aload         4
      20: ifnull        65
      23: aload         4
      25: invokeinterface #49,  1           // InterfaceMethod java/util/List.iterator:()Ljava/util/Iterator;
      30: astore        5
      32: aload         5
      34: invokeinterface #50,  1           // InterfaceMethod java/util/Iterator.hasNext:()Z
      39: ifeq          65
      42: aload         5
      44: invokeinterface #51,  1           // InterfaceMethod java/util/Iterator.next:()Ljava/lang/Object;
      49: checkcast     #95                 // class java/security/Permission
      52: astore        6
      54: aload_3
      55: aload         6
      57: invokeinterface #96,  2           // InterfaceMethod javax/security/jacc/PolicyConfiguration.addToUncheckedPolicy:(Ljava/security/Permission;)V
      62: goto          32
      65: aload_0
      66: aload_1
      67: getstatic     #93                 // Field PERROLE_PERMISSIONS:Ljava/lang/String;
      70: invokevirtual #17                 // Method getOptionalAttribute:(Ljavax/servlet/ServletContext;Ljava/lang/String;)Ljava/lang/Object;
      73: checkcast     #18                 // class java/util/List
      76: astore        5
      78: aload         5
      80: ifnull        143
      83: aload         5
      85: invokeinterface #49,  1           // InterfaceMethod java/util/List.iterator:()Ljava/util/Iterator;
      90: astore        6
      92: aload         6
      94: invokeinterface #50,  1           // InterfaceMethod java/util/Iterator.hasNext:()Z
      99: ifeq          143
     102: aload         6
     104: invokeinterface #51,  1           // InterfaceMethod java/util/Iterator.next:()Ljava/lang/Object;
     109: checkcast     #52                 // class java/util/Map$Entry
     112: astore        7
     114: aload_3
     115: aload         7
     117: invokeinterface #54,  1           // InterfaceMethod java/util/Map$Entry.getKey:()Ljava/lang/Object;
     122: checkcast     #34                 // class java/lang/String
     125: aload         7
     127: invokeinterface #57,  1           // InterfaceMethod java/util/Map$Entry.getValue:()Ljava/lang/Object;
     132: checkcast     #95                 // class java/security/Permission
     135: invokeinterface #38,  3           // InterfaceMethod javax/security/jacc/PolicyConfiguration.addToRole:(Ljava/lang/String;Ljava/security/Permission;)V
     140: goto          92
     143: aload_3
     144: invokeinterface #97,  1           // InterfaceMethod javax/security/jacc/PolicyConfiguration.commit:()V
     149: goto          164
     152: astore        4
     154: new           #40                 // class java/lang/IllegalStateException
     157: dup
     158: aload         4
     160: invokespecial #41                 // Method java/lang/IllegalStateException."<init>":(Ljava/lang/Throwable;)V
     163: athrow
     164: return
    Exception table:
       from    to  target type
           5   149   152   Class javax/security/jacc/PolicyContextException

  private static javax.security.auth.Subject lambda$onStartup$1();
    Code:
       0: invokestatic  #98                 // Method cloud/piranha/DefaultAuthenticatedIdentity.getCurrentSubject:()Ljavax/security/auth/Subject;
       3: areturn

  private static javax.servlet.http.HttpServletRequest lambda$onStartup$0();
    Code:
       0: getstatic     #99                 // Field cloud/piranha/security/exousia/AuthorizationPreFilter.localServletRequest:Ljava/lang/ThreadLocal;
       3: invokevirtual #100                // Method java/lang/ThreadLocal.get:()Ljava/lang/Object;
       6: checkcast     #101                // class javax/servlet/http/HttpServletRequest
       9: areturn

  static {};
    Code:
       0: ldc           #102                // class cloud/piranha/security/exousia/AuthorizationPreInitializer
       2: invokevirtual #103                // Method java/lang/Class.getName:()Ljava/lang/String;
       5: invokedynamic #104,  0            // InvokeDynamic #3:makeConcatWithConstants:(Ljava/lang/String;)Ljava/lang/String;
      10: putstatic     #29                 // Field AUTHZ_SERVICE:Ljava/lang/String;
      13: ldc           #102                // class cloud/piranha/security/exousia/AuthorizationPreInitializer
      15: invokevirtual #103                // Method java/lang/Class.getName:()Ljava/lang/String;
      18: invokedynamic #105,  0            // InvokeDynamic #4:makeConcatWithConstants:(Ljava/lang/String;)Ljava/lang/String;
      23: putstatic     #3                  // Field AUTHZ_FACTORY_CLASS:Ljava/lang/String;
      26: ldc           #102                // class cloud/piranha/security/exousia/AuthorizationPreInitializer
      28: invokevirtual #103                // Method java/lang/Class.getName:()Ljava/lang/String;
      31: invokedynamic #106,  0            // InvokeDynamic #5:makeConcatWithConstants:(Ljava/lang/String;)Ljava/lang/String;
      36: putstatic     #6                  // Field AUTHZ_POLICY_CLASS:Ljava/lang/String;
      39: ldc           #102                // class cloud/piranha/security/exousia/AuthorizationPreInitializer
      41: invokevirtual #103                // Method java/lang/Class.getName:()Ljava/lang/String;
      44: invokedynamic #107,  0            // InvokeDynamic #6:makeConcatWithConstants:(Ljava/lang/String;)Ljava/lang/String;
      49: putstatic     #92                 // Field UNCHECKED_PERMISSIONS:Ljava/lang/String;
      52: ldc           #102                // class cloud/piranha/security/exousia/AuthorizationPreInitializer
      54: invokevirtual #103                // Method java/lang/Class.getName:()Ljava/lang/String;
      57: invokedynamic #108,  0            // InvokeDynamic #7:makeConcatWithConstants:(Ljava/lang/String;)Ljava/lang/String;
      62: putstatic     #93                 // Field PERROLE_PERMISSIONS:Ljava/lang/String;
      65: ldc           #102                // class cloud/piranha/security/exousia/AuthorizationPreInitializer
      67: invokevirtual #103                // Method java/lang/Class.getName:()Ljava/lang/String;
      70: invokedynamic #109,  0            // InvokeDynamic #8:makeConcatWithConstants:(Ljava/lang/String;)Ljava/lang/String;
      75: putstatic     #16                 // Field CONSTRAINTS:Ljava/lang/String;
      78: ldc           #102                // class cloud/piranha/security/exousia/AuthorizationPreInitializer
      80: invokevirtual #103                // Method java/lang/Class.getName:()Ljava/lang/String;
      83: invokedynamic #110,  0            // InvokeDynamic #9:makeConcatWithConstants:(Ljava/lang/String;)Ljava/lang/String;
      88: putstatic     #46                 // Field SECURITY_ELEMENTS:Ljava/lang/String;
      91: ldc           #102                // class cloud/piranha/security/exousia/AuthorizationPreInitializer
      93: invokevirtual #103                // Method java/lang/Class.getName:()Ljava/lang/String;
      96: invokedynamic #111,  0            // InvokeDynamic #10:makeConcatWithConstants:(Ljava/lang/String;)Ljava/lang/String;
     101: putstatic     #61                 // Field SECURITY_ANNOTATIONS:Ljava/lang/String;
     104: return
}
