Compiled from "ApplicationSpecFluentImpl.java"
public class io.dekorate.deps.applicationcrd.api.model.ApplicationSpecFluentImpl<A extends io.dekorate.deps.applicationcrd.api.model.ApplicationSpecFluent<A>> extends io.dekorate.deps.kubernetes.api.builder.BaseFluent<A> implements io.dekorate.deps.applicationcrd.api.model.ApplicationSpecFluent<A> {
  private java.lang.String assemblyPhase;

  private java.util.List<io.dekorate.deps.applicationcrd.api.model.GroupKindBuilder> componentKinds;

  private io.dekorate.deps.applicationcrd.api.model.DescriptorBuilder descriptor;

  private java.util.List<io.dekorate.deps.applicationcrd.api.model.InfoItemBuilder> info;

  private io.dekorate.deps.kubernetes.api.model.LabelSelectorBuilder selector;

  public io.dekorate.deps.applicationcrd.api.model.ApplicationSpecFluentImpl();
    Code:
       0: aload_0
       1: invokespecial #47                 // Method io/dekorate/deps/kubernetes/api/builder/BaseFluent."<init>":()V
       4: return

  public io.dekorate.deps.applicationcrd.api.model.ApplicationSpecFluentImpl(io.dekorate.deps.applicationcrd.api.model.ApplicationSpec);
    Code:
       0: aload_0
       1: invokespecial #47                 // Method io/dekorate/deps/kubernetes/api/builder/BaseFluent."<init>":()V
       4: aload_0
       5: aload_1
       6: invokevirtual #57                 // Method io/dekorate/deps/applicationcrd/api/model/ApplicationSpec.getAssemblyPhase:()Ljava/lang/String;
       9: invokevirtual #61                 // Method withAssemblyPhase:(Ljava/lang/String;)Lio/dekorate/deps/applicationcrd/api/model/ApplicationSpecFluent;
      12: pop
      13: aload_0
      14: aload_1
      15: invokevirtual #65                 // Method io/dekorate/deps/applicationcrd/api/model/ApplicationSpec.getComponentKinds:()Ljava/util/List;
      18: invokevirtual #69                 // Method withComponentKinds:(Ljava/util/List;)Lio/dekorate/deps/applicationcrd/api/model/ApplicationSpecFluent;
      21: pop
      22: aload_0
      23: aload_1
      24: invokevirtual #73                 // Method io/dekorate/deps/applicationcrd/api/model/ApplicationSpec.getDescriptor:()Lio/dekorate/deps/applicationcrd/api/model/Descriptor;
      27: invokevirtual #77                 // Method withDescriptor:(Lio/dekorate/deps/applicationcrd/api/model/Descriptor;)Lio/dekorate/deps/applicationcrd/api/model/ApplicationSpecFluent;
      30: pop
      31: aload_0
      32: aload_1
      33: invokevirtual #80                 // Method io/dekorate/deps/applicationcrd/api/model/ApplicationSpec.getInfo:()Ljava/util/List;
      36: invokevirtual #83                 // Method withInfo:(Ljava/util/List;)Lio/dekorate/deps/applicationcrd/api/model/ApplicationSpecFluent;
      39: pop
      40: aload_0
      41: aload_1
      42: invokevirtual #87                 // Method io/dekorate/deps/applicationcrd/api/model/ApplicationSpec.getSelector:()Lio/dekorate/deps/kubernetes/api/model/LabelSelector;
      45: invokevirtual #91                 // Method withSelector:(Lio/dekorate/deps/kubernetes/api/model/LabelSelector;)Lio/dekorate/deps/applicationcrd/api/model/ApplicationSpecFluent;
      48: pop
      49: return

  public java.lang.String getAssemblyPhase();
    Code:
       0: aload_0
       1: getfield      #95                 // Field assemblyPhase:Ljava/lang/String;
       4: areturn

  public A withAssemblyPhase(java.lang.String);
    Code:
       0: aload_0
       1: aload_1
       2: putfield      #95                 // Field assemblyPhase:Ljava/lang/String;
       5: aload_0
       6: areturn

  public java.lang.Boolean hasAssemblyPhase();
    Code:
       0: aload_0
       1: getfield      #95                 // Field assemblyPhase:Ljava/lang/String;
       4: ifnull        11
       7: iconst_1
       8: goto          12
      11: iconst_0
      12: invokestatic  #104                // Method java/lang/Boolean.valueOf:(Z)Ljava/lang/Boolean;
      15: areturn

  public A withNewAssemblyPhase(java.lang.String);
    Code:
       0: aload_0
       1: new           #107                // class java/lang/String
       4: dup
       5: aload_1
       6: invokespecial #110                // Method java/lang/String."<init>":(Ljava/lang/String;)V
       9: invokevirtual #61                 // Method withAssemblyPhase:(Ljava/lang/String;)Lio/dekorate/deps/applicationcrd/api/model/ApplicationSpecFluent;
      12: areturn

  public A withNewAssemblyPhase(java.lang.StringBuilder);
    Code:
       0: aload_0
       1: new           #107                // class java/lang/String
       4: dup
       5: aload_1
       6: invokespecial #116                // Method java/lang/String."<init>":(Ljava/lang/StringBuilder;)V
       9: invokevirtual #61                 // Method withAssemblyPhase:(Ljava/lang/String;)Lio/dekorate/deps/applicationcrd/api/model/ApplicationSpecFluent;
      12: areturn

  public A withNewAssemblyPhase(java.lang.StringBuffer);
    Code:
       0: aload_0
       1: new           #107                // class java/lang/String
       4: dup
       5: aload_1
       6: invokespecial #122                // Method java/lang/String."<init>":(Ljava/lang/StringBuffer;)V
       9: invokevirtual #61                 // Method withAssemblyPhase:(Ljava/lang/String;)Lio/dekorate/deps/applicationcrd/api/model/ApplicationSpecFluent;
      12: areturn

  public A addToComponentKinds(int, io.dekorate.deps.applicationcrd.api.model.GroupKind);
    Code:
       0: aload_0
       1: getfield      #128                // Field componentKinds:Ljava/util/List;
       4: ifnonnull     18
       7: aload_0
       8: new           #130                // class java/util/ArrayList
      11: dup
      12: invokespecial #131                // Method java/util/ArrayList."<init>":()V
      15: putfield      #128                // Field componentKinds:Ljava/util/List;
      18: new           #133                // class io/dekorate/deps/applicationcrd/api/model/GroupKindBuilder
      21: dup
      22: aload_2
      23: invokespecial #136                // Method io/dekorate/deps/applicationcrd/api/model/GroupKindBuilder."<init>":(Lio/dekorate/deps/applicationcrd/api/model/GroupKind;)V
      26: astore_3
      27: aload_0
      28: getfield      #140                // Field _visitables:Lio/dekorate/deps/kubernetes/api/builder/VisitableMap;
      31: ldc           #141                // String componentKinds
      33: invokevirtual #147                // Method io/dekorate/deps/kubernetes/api/builder/VisitableMap.get:(Ljava/lang/Object;)Ljava/util/List;
      36: iload_1
      37: iflt          44
      40: iload_1
      41: goto          58
      44: aload_0
      45: getfield      #140                // Field _visitables:Lio/dekorate/deps/kubernetes/api/builder/VisitableMap;
      48: ldc           #141                // String componentKinds
      50: invokevirtual #147                // Method io/dekorate/deps/kubernetes/api/builder/VisitableMap.get:(Ljava/lang/Object;)Ljava/util/List;
      53: invokeinterface #155,  1          // InterfaceMethod java/util/List.size:()I
      58: aload_3
      59: invokeinterface #159,  3          // InterfaceMethod java/util/List.add:(ILjava/lang/Object;)V
      64: aload_0
      65: getfield      #128                // Field componentKinds:Ljava/util/List;
      68: iload_1
      69: iflt          76
      72: iload_1
      73: goto          85
      76: aload_0
      77: getfield      #128                // Field componentKinds:Ljava/util/List;
      80: invokeinterface #155,  1          // InterfaceMethod java/util/List.size:()I
      85: aload_3
      86: invokeinterface #159,  3          // InterfaceMethod java/util/List.add:(ILjava/lang/Object;)V
      91: aload_0
      92: areturn

  public A setToComponentKinds(int, io.dekorate.deps.applicationcrd.api.model.GroupKind);
    Code:
       0: aload_0
       1: getfield      #128                // Field componentKinds:Ljava/util/List;
       4: ifnonnull     18
       7: aload_0
       8: new           #130                // class java/util/ArrayList
      11: dup
      12: invokespecial #131                // Method java/util/ArrayList."<init>":()V
      15: putfield      #128                // Field componentKinds:Ljava/util/List;
      18: new           #133                // class io/dekorate/deps/applicationcrd/api/model/GroupKindBuilder
      21: dup
      22: aload_2
      23: invokespecial #136                // Method io/dekorate/deps/applicationcrd/api/model/GroupKindBuilder."<init>":(Lio/dekorate/deps/applicationcrd/api/model/GroupKind;)V
      26: astore_3
      27: iload_1
      28: iflt          49
      31: iload_1
      32: aload_0
      33: getfield      #140                // Field _visitables:Lio/dekorate/deps/kubernetes/api/builder/VisitableMap;
      36: ldc           #141                // String componentKinds
      38: invokevirtual #147                // Method io/dekorate/deps/kubernetes/api/builder/VisitableMap.get:(Ljava/lang/Object;)Ljava/util/List;
      41: invokeinterface #155,  1          // InterfaceMethod java/util/List.size:()I
      46: if_icmplt     68
      49: aload_0
      50: getfield      #140                // Field _visitables:Lio/dekorate/deps/kubernetes/api/builder/VisitableMap;
      53: ldc           #141                // String componentKinds
      55: invokevirtual #147                // Method io/dekorate/deps/kubernetes/api/builder/VisitableMap.get:(Ljava/lang/Object;)Ljava/util/List;
      58: aload_3
      59: invokeinterface #169,  2          // InterfaceMethod java/util/List.add:(Ljava/lang/Object;)Z
      64: pop
      65: goto          85
      68: aload_0
      69: getfield      #140                // Field _visitables:Lio/dekorate/deps/kubernetes/api/builder/VisitableMap;
      72: ldc           #141                // String componentKinds
      74: invokevirtual #147                // Method io/dekorate/deps/kubernetes/api/builder/VisitableMap.get:(Ljava/lang/Object;)Ljava/util/List;
      77: iload_1
      78: aload_3
      79: invokeinterface #173,  3          // InterfaceMethod java/util/List.set:(ILjava/lang/Object;)Ljava/lang/Object;
      84: pop
      85: iload_1
      86: iflt          102
      89: iload_1
      90: aload_0
      91: getfield      #128                // Field componentKinds:Ljava/util/List;
      94: invokeinterface #155,  1          // InterfaceMethod java/util/List.size:()I
      99: if_icmplt     116
     102: aload_0
     103: getfield      #128                // Field componentKinds:Ljava/util/List;
     106: aload_3
     107: invokeinterface #169,  2          // InterfaceMethod java/util/List.add:(Ljava/lang/Object;)Z
     112: pop
     113: goto          128
     116: aload_0
     117: getfield      #128                // Field componentKinds:Ljava/util/List;
     120: iload_1
     121: aload_3
     122: invokeinterface #173,  3          // InterfaceMethod java/util/List.set:(ILjava/lang/Object;)Ljava/lang/Object;
     127: pop
     128: aload_0
     129: areturn

  public A addToComponentKinds(io.dekorate.deps.applicationcrd.api.model.GroupKind...);
    Code:
       0: aload_0
       1: getfield      #128                // Field componentKinds:Ljava/util/List;
       4: ifnonnull     18
       7: aload_0
       8: new           #130                // class java/util/ArrayList
      11: dup
      12: invokespecial #131                // Method java/util/ArrayList."<init>":()V
      15: putfield      #128                // Field componentKinds:Ljava/util/List;
      18: aload_1
      19: astore_2
      20: aload_2
      21: arraylength
      22: istore_3
      23: iconst_0
      24: istore        4
      26: iload         4
      28: iload_3
      29: if_icmpge     84
      32: aload_2
      33: iload         4
      35: aaload
      36: astore        5
      38: new           #133                // class io/dekorate/deps/applicationcrd/api/model/GroupKindBuilder
      41: dup
      42: aload         5
      44: invokespecial #136                // Method io/dekorate/deps/applicationcrd/api/model/GroupKindBuilder."<init>":(Lio/dekorate/deps/applicationcrd/api/model/GroupKind;)V
      47: astore        6
      49: aload_0
      50: getfield      #140                // Field _visitables:Lio/dekorate/deps/kubernetes/api/builder/VisitableMap;
      53: ldc           #141                // String componentKinds
      55: invokevirtual #147                // Method io/dekorate/deps/kubernetes/api/builder/VisitableMap.get:(Ljava/lang/Object;)Ljava/util/List;
      58: aload         6
      60: invokeinterface #169,  2          // InterfaceMethod java/util/List.add:(Ljava/lang/Object;)Z
      65: pop
      66: aload_0
      67: getfield      #128                // Field componentKinds:Ljava/util/List;
      70: aload         6
      72: invokeinterface #169,  2          // InterfaceMethod java/util/List.add:(Ljava/lang/Object;)Z
      77: pop
      78: iinc          4, 1
      81: goto          26
      84: aload_0
      85: areturn

  public A addAllToComponentKinds(java.util.Collection<io.dekorate.deps.applicationcrd.api.model.GroupKind>);
    Code:
       0: aload_0
       1: getfield      #128                // Field componentKinds:Ljava/util/List;
       4: ifnonnull     18
       7: aload_0
       8: new           #130                // class java/util/ArrayList
      11: dup
      12: invokespecial #131                // Method java/util/ArrayList."<init>":()V
      15: putfield      #128                // Field componentKinds:Ljava/util/List;
      18: aload_1
      19: invokeinterface #187,  1          // InterfaceMethod java/util/Collection.iterator:()Ljava/util/Iterator;
      24: astore_2
      25: aload_2
      26: invokeinterface #193,  1          // InterfaceMethod java/util/Iterator.hasNext:()Z
      31: ifeq          86
      34: aload_2
      35: invokeinterface #197,  1          // InterfaceMethod java/util/Iterator.next:()Ljava/lang/Object;
      40: checkcast     #149                // class io/dekorate/deps/applicationcrd/api/model/GroupKind
      43: astore_3
      44: new           #133                // class io/dekorate/deps/applicationcrd/api/model/GroupKindBuilder
      47: dup
      48: aload_3
      49: invokespecial #136                // Method io/dekorate/deps/applicationcrd/api/model/GroupKindBuilder."<init>":(Lio/dekorate/deps/applicationcrd/api/model/GroupKind;)V
      52: astore        4
      54: aload_0
      55: getfield      #140                // Field _visitables:Lio/dekorate/deps/kubernetes/api/builder/VisitableMap;
      58: ldc           #141                // String componentKinds
      60: invokevirtual #147                // Method io/dekorate/deps/kubernetes/api/builder/VisitableMap.get:(Ljava/lang/Object;)Ljava/util/List;
      63: aload         4
      65: invokeinterface #169,  2          // InterfaceMethod java/util/List.add:(Ljava/lang/Object;)Z
      70: pop
      71: aload_0
      72: getfield      #128                // Field componentKinds:Ljava/util/List;
      75: aload         4
      77: invokeinterface #169,  2          // InterfaceMethod java/util/List.add:(Ljava/lang/Object;)Z
      82: pop
      83: goto          25
      86: aload_0
      87: areturn

  public A removeFromComponentKinds(io.dekorate.deps.applicationcrd.api.model.GroupKind...);
    Code:
       0: aload_1
       1: astore_2
       2: aload_2
       3: arraylength
       4: istore_3
       5: iconst_0
       6: istore        4
       8: iload         4
      10: iload_3
      11: if_icmpge     73
      14: aload_2
      15: iload         4
      17: aaload
      18: astore        5
      20: new           #133                // class io/dekorate/deps/applicationcrd/api/model/GroupKindBuilder
      23: dup
      24: aload         5
      26: invokespecial #136                // Method io/dekorate/deps/applicationcrd/api/model/GroupKindBuilder."<init>":(Lio/dekorate/deps/applicationcrd/api/model/GroupKind;)V
      29: astore        6
      31: aload_0
      32: getfield      #140                // Field _visitables:Lio/dekorate/deps/kubernetes/api/builder/VisitableMap;
      35: ldc           #141                // String componentKinds
      37: invokevirtual #147                // Method io/dekorate/deps/kubernetes/api/builder/VisitableMap.get:(Ljava/lang/Object;)Ljava/util/List;
      40: aload         6
      42: invokeinterface #203,  2          // InterfaceMethod java/util/List.remove:(Ljava/lang/Object;)Z
      47: pop
      48: aload_0
      49: getfield      #128                // Field componentKinds:Ljava/util/List;
      52: ifnull        67
      55: aload_0
      56: getfield      #128                // Field componentKinds:Ljava/util/List;
      59: aload         6
      61: invokeinterface #203,  2          // InterfaceMethod java/util/List.remove:(Ljava/lang/Object;)Z
      66: pop
      67: iinc          4, 1
      70: goto          8
      73: aload_0
      74: areturn

  public A removeAllFromComponentKinds(java.util.Collection<io.dekorate.deps.applicationcrd.api.model.GroupKind>);
    Code:
       0: aload_1
       1: invokeinterface #187,  1          // InterfaceMethod java/util/Collection.iterator:()Ljava/util/Iterator;
       6: astore_2
       7: aload_2
       8: invokeinterface #193,  1          // InterfaceMethod java/util/Iterator.hasNext:()Z
      13: ifeq          75
      16: aload_2
      17: invokeinterface #197,  1          // InterfaceMethod java/util/Iterator.next:()Ljava/lang/Object;
      22: checkcast     #149                // class io/dekorate/deps/applicationcrd/api/model/GroupKind
      25: astore_3
      26: new           #133                // class io/dekorate/deps/applicationcrd/api/model/GroupKindBuilder
      29: dup
      30: aload_3
      31: invokespecial #136                // Method io/dekorate/deps/applicationcrd/api/model/GroupKindBuilder."<init>":(Lio/dekorate/deps/applicationcrd/api/model/GroupKind;)V
      34: astore        4
      36: aload_0
      37: getfield      #140                // Field _visitables:Lio/dekorate/deps/kubernetes/api/builder/VisitableMap;
      40: ldc           #141                // String componentKinds
      42: invokevirtual #147                // Method io/dekorate/deps/kubernetes/api/builder/VisitableMap.get:(Ljava/lang/Object;)Ljava/util/List;
      45: aload         4
      47: invokeinterface #203,  2          // InterfaceMethod java/util/List.remove:(Ljava/lang/Object;)Z
      52: pop
      53: aload_0
      54: getfield      #128                // Field componentKinds:Ljava/util/List;
      57: ifnull        72
      60: aload_0
      61: getfield      #128                // Field componentKinds:Ljava/util/List;
      64: aload         4
      66: invokeinterface #203,  2          // InterfaceMethod java/util/List.remove:(Ljava/lang/Object;)Z
      71: pop
      72: goto          7
      75: aload_0
      76: areturn

  public java.util.List<io.dekorate.deps.applicationcrd.api.model.GroupKind> getComponentKinds();
    Code:
       0: aload_0
       1: getfield      #128                // Field componentKinds:Ljava/util/List;
       4: invokestatic  #210                // Method build:(Ljava/util/List;)Ljava/util/ArrayList;
       7: areturn

  public java.util.List<io.dekorate.deps.applicationcrd.api.model.GroupKind> buildComponentKinds();
    Code:
       0: aload_0
       1: getfield      #128                // Field componentKinds:Ljava/util/List;
       4: invokestatic  #210                // Method build:(Ljava/util/List;)Ljava/util/ArrayList;
       7: areturn

  public io.dekorate.deps.applicationcrd.api.model.GroupKind buildComponentKind(int);
    Code:
       0: aload_0
       1: getfield      #128                // Field componentKinds:Ljava/util/List;
       4: iload_1
       5: invokeinterface #216,  2          // InterfaceMethod java/util/List.get:(I)Ljava/lang/Object;
      10: checkcast     #133                // class io/dekorate/deps/applicationcrd/api/model/GroupKindBuilder
      13: invokevirtual #219                // Method io/dekorate/deps/applicationcrd/api/model/GroupKindBuilder.build:()Lio/dekorate/deps/applicationcrd/api/model/GroupKind;
      16: areturn

  public io.dekorate.deps.applicationcrd.api.model.GroupKind buildFirstComponentKind();
    Code:
       0: aload_0
       1: getfield      #128                // Field componentKinds:Ljava/util/List;
       4: iconst_0
       5: invokeinterface #216,  2          // InterfaceMethod java/util/List.get:(I)Ljava/lang/Object;
      10: checkcast     #133                // class io/dekorate/deps/applicationcrd/api/model/GroupKindBuilder
      13: invokevirtual #219                // Method io/dekorate/deps/applicationcrd/api/model/GroupKindBuilder.build:()Lio/dekorate/deps/applicationcrd/api/model/GroupKind;
      16: areturn

  public io.dekorate.deps.applicationcrd.api.model.GroupKind buildLastComponentKind();
    Code:
       0: aload_0
       1: getfield      #128                // Field componentKinds:Ljava/util/List;
       4: aload_0
       5: getfield      #128                // Field componentKinds:Ljava/util/List;
       8: invokeinterface #155,  1          // InterfaceMethod java/util/List.size:()I
      13: iconst_1
      14: isub
      15: invokeinterface #216,  2          // InterfaceMethod java/util/List.get:(I)Ljava/lang/Object;
      20: checkcast     #133                // class io/dekorate/deps/applicationcrd/api/model/GroupKindBuilder
      23: invokevirtual #219                // Method io/dekorate/deps/applicationcrd/api/model/GroupKindBuilder.build:()Lio/dekorate/deps/applicationcrd/api/model/GroupKind;
      26: areturn

  public io.dekorate.deps.applicationcrd.api.model.GroupKind buildMatchingComponentKind(io.dekorate.deps.kubernetes.api.builder.Predicate<io.dekorate.deps.applicationcrd.api.model.GroupKindBuilder>);
    Code:
       0: aload_0
       1: getfield      #128                // Field componentKinds:Ljava/util/List;
       4: invokeinterface #225,  1          // InterfaceMethod java/util/List.iterator:()Ljava/util/Iterator;
       9: astore_2
      10: aload_2
      11: invokeinterface #193,  1          // InterfaceMethod java/util/Iterator.hasNext:()Z
      16: ifeq          50
      19: aload_2
      20: invokeinterface #197,  1          // InterfaceMethod java/util/Iterator.next:()Ljava/lang/Object;
      25: checkcast     #133                // class io/dekorate/deps/applicationcrd/api/model/GroupKindBuilder
      28: astore_3
      29: aload_1
      30: aload_3
      31: invokeinterface #231,  2          // InterfaceMethod io/dekorate/deps/kubernetes/api/builder/Predicate.apply:(Ljava/lang/Object;)Ljava/lang/Boolean;
      36: invokevirtual #234                // Method java/lang/Boolean.booleanValue:()Z
      39: ifeq          47
      42: aload_3
      43: invokevirtual #219                // Method io/dekorate/deps/applicationcrd/api/model/GroupKindBuilder.build:()Lio/dekorate/deps/applicationcrd/api/model/GroupKind;
      46: areturn
      47: goto          10
      50: aconst_null
      51: areturn

  public java.lang.Boolean hasMatchingComponentKind(io.dekorate.deps.kubernetes.api.builder.Predicate<io.dekorate.deps.applicationcrd.api.model.GroupKindBuilder>);
    Code:
       0: aload_0
       1: getfield      #128                // Field componentKinds:Ljava/util/List;
       4: invokeinterface #225,  1          // InterfaceMethod java/util/List.iterator:()Ljava/util/Iterator;
       9: astore_2
      10: aload_2
      11: invokeinterface #193,  1          // InterfaceMethod java/util/Iterator.hasNext:()Z
      16: ifeq          50
      19: aload_2
      20: invokeinterface #197,  1          // InterfaceMethod java/util/Iterator.next:()Ljava/lang/Object;
      25: checkcast     #133                // class io/dekorate/deps/applicationcrd/api/model/GroupKindBuilder
      28: astore_3
      29: aload_1
      30: aload_3
      31: invokeinterface #231,  2          // InterfaceMethod io/dekorate/deps/kubernetes/api/builder/Predicate.apply:(Ljava/lang/Object;)Ljava/lang/Boolean;
      36: invokevirtual #234                // Method java/lang/Boolean.booleanValue:()Z
      39: ifeq          47
      42: iconst_1
      43: invokestatic  #104                // Method java/lang/Boolean.valueOf:(Z)Ljava/lang/Boolean;
      46: areturn
      47: goto          10
      50: iconst_0
      51: invokestatic  #104                // Method java/lang/Boolean.valueOf:(Z)Ljava/lang/Boolean;
      54: areturn

  public A withComponentKinds(java.util.List<io.dekorate.deps.applicationcrd.api.model.GroupKind>);
    Code:
       0: aload_0
       1: getfield      #128                // Field componentKinds:Ljava/util/List;
       4: ifnull        26
       7: aload_0
       8: getfield      #140                // Field _visitables:Lio/dekorate/deps/kubernetes/api/builder/VisitableMap;
      11: ldc           #141                // String componentKinds
      13: invokevirtual #147                // Method io/dekorate/deps/kubernetes/api/builder/VisitableMap.get:(Ljava/lang/Object;)Ljava/util/List;
      16: aload_0
      17: getfield      #128                // Field componentKinds:Ljava/util/List;
      20: invokeinterface #245,  2          // InterfaceMethod java/util/List.removeAll:(Ljava/util/Collection;)Z
      25: pop
      26: aload_1
      27: ifnull        86
      30: aload_0
      31: new           #130                // class java/util/ArrayList
      34: dup
      35: invokespecial #131                // Method java/util/ArrayList."<init>":()V
      38: putfield      #128                // Field componentKinds:Ljava/util/List;
      41: aload_1
      42: invokeinterface #225,  1          // InterfaceMethod java/util/List.iterator:()Ljava/util/Iterator;
      47: astore_2
      48: aload_2
      49: invokeinterface #193,  1          // InterfaceMethod java/util/Iterator.hasNext:()Z
      54: ifeq          83
      57: aload_2
      58: invokeinterface #197,  1          // InterfaceMethod java/util/Iterator.next:()Ljava/lang/Object;
      63: checkcast     #149                // class io/dekorate/deps/applicationcrd/api/model/GroupKind
      66: astore_3
      67: aload_0
      68: iconst_1
      69: anewarray     #149                // class io/dekorate/deps/applicationcrd/api/model/GroupKind
      72: dup
      73: iconst_0
      74: aload_3
      75: aastore
      76: invokevirtual #247                // Method addToComponentKinds:([Lio/dekorate/deps/applicationcrd/api/model/GroupKind;)Lio/dekorate/deps/applicationcrd/api/model/ApplicationSpecFluent;
      79: pop
      80: goto          48
      83: goto          91
      86: aload_0
      87: aconst_null
      88: putfield      #128                // Field componentKinds:Ljava/util/List;
      91: aload_0
      92: areturn

  public A withComponentKinds(io.dekorate.deps.applicationcrd.api.model.GroupKind...);
    Code:
       0: aload_0
       1: getfield      #128                // Field componentKinds:Ljava/util/List;
       4: ifnull        16
       7: aload_0
       8: getfield      #128                // Field componentKinds:Ljava/util/List;
      11: invokeinterface #251,  1          // InterfaceMethod java/util/List.clear:()V
      16: aload_1
      17: ifnull        60
      20: aload_1
      21: astore_2
      22: aload_2
      23: arraylength
      24: istore_3
      25: iconst_0
      26: istore        4
      28: iload         4
      30: iload_3
      31: if_icmpge     60
      34: aload_2
      35: iload         4
      37: aaload
      38: astore        5
      40: aload_0
      41: iconst_1
      42: anewarray     #149                // class io/dekorate/deps/applicationcrd/api/model/GroupKind
      45: dup
      46: iconst_0
      47: aload         5
      49: aastore
      50: invokevirtual #247                // Method addToComponentKinds:([Lio/dekorate/deps/applicationcrd/api/model/GroupKind;)Lio/dekorate/deps/applicationcrd/api/model/ApplicationSpecFluent;
      53: pop
      54: iinc          4, 1
      57: goto          28
      60: aload_0
      61: areturn

  public java.lang.Boolean hasComponentKinds();
    Code:
       0: aload_0
       1: getfield      #128                // Field componentKinds:Ljava/util/List;
       4: ifnull        23
       7: aload_0
       8: getfield      #128                // Field componentKinds:Ljava/util/List;
      11: invokeinterface #255,  1          // InterfaceMethod java/util/List.isEmpty:()Z
      16: ifne          23
      19: iconst_1
      20: goto          24
      23: iconst_0
      24: invokestatic  #104                // Method java/lang/Boolean.valueOf:(Z)Ljava/lang/Boolean;
      27: areturn

  public A addNewComponentKind(java.lang.String, java.lang.String);
    Code:
       0: aload_0
       1: iconst_1
       2: anewarray     #149                // class io/dekorate/deps/applicationcrd/api/model/GroupKind
       5: dup
       6: iconst_0
       7: new           #149                // class io/dekorate/deps/applicationcrd/api/model/GroupKind
      10: dup
      11: aload_1
      12: aload_2
      13: invokespecial #261                // Method io/dekorate/deps/applicationcrd/api/model/GroupKind."<init>":(Ljava/lang/String;Ljava/lang/String;)V
      16: aastore
      17: invokevirtual #247                // Method addToComponentKinds:([Lio/dekorate/deps/applicationcrd/api/model/GroupKind;)Lio/dekorate/deps/applicationcrd/api/model/ApplicationSpecFluent;
      20: areturn

  public io.dekorate.deps.applicationcrd.api.model.ApplicationSpecFluent$ComponentKindsNested<A> addNewComponentKind();
    Code:
       0: new           #19                 // class io/dekorate/deps/applicationcrd/api/model/ApplicationSpecFluentImpl$ComponentKindsNestedImpl
       3: dup
       4: aload_0
       5: invokespecial #268                // Method io/dekorate/deps/applicationcrd/api/model/ApplicationSpecFluentImpl$ComponentKindsNestedImpl."<init>":(Lio/dekorate/deps/applicationcrd/api/model/ApplicationSpecFluentImpl;)V
       8: areturn

  public io.dekorate.deps.applicationcrd.api.model.ApplicationSpecFluent$ComponentKindsNested<A> addNewComponentKindLike(io.dekorate.deps.applicationcrd.api.model.GroupKind);
    Code:
       0: new           #19                 // class io/dekorate/deps/applicationcrd/api/model/ApplicationSpecFluentImpl$ComponentKindsNestedImpl
       3: dup
       4: aload_0
       5: iconst_m1
       6: aload_1
       7: invokespecial #274                // Method io/dekorate/deps/applicationcrd/api/model/ApplicationSpecFluentImpl$ComponentKindsNestedImpl."<init>":(Lio/dekorate/deps/applicationcrd/api/model/ApplicationSpecFluentImpl;ILio/dekorate/deps/applicationcrd/api/model/GroupKind;)V
      10: areturn

  public io.dekorate.deps.applicationcrd.api.model.ApplicationSpecFluent$ComponentKindsNested<A> setNewComponentKindLike(int, io.dekorate.deps.applicationcrd.api.model.GroupKind);
    Code:
       0: new           #19                 // class io/dekorate/deps/applicationcrd/api/model/ApplicationSpecFluentImpl$ComponentKindsNestedImpl
       3: dup
       4: aload_0
       5: iload_1
       6: aload_2
       7: invokespecial #274                // Method io/dekorate/deps/applicationcrd/api/model/ApplicationSpecFluentImpl$ComponentKindsNestedImpl."<init>":(Lio/dekorate/deps/applicationcrd/api/model/ApplicationSpecFluentImpl;ILio/dekorate/deps/applicationcrd/api/model/GroupKind;)V
      10: areturn

  public io.dekorate.deps.applicationcrd.api.model.ApplicationSpecFluent$ComponentKindsNested<A> editComponentKind(int);
    Code:
       0: aload_0
       1: getfield      #128                // Field componentKinds:Ljava/util/List;
       4: invokeinterface #155,  1          // InterfaceMethod java/util/List.size:()I
       9: iload_1
      10: if_icmpgt     24
      13: new           #282                // class java/lang/RuntimeException
      16: dup
      17: ldc_w         #284                // String Can\'t edit componentKinds. Index exceeds size.
      20: invokespecial #285                // Method java/lang/RuntimeException."<init>":(Ljava/lang/String;)V
      23: athrow
      24: aload_0
      25: iload_1
      26: aload_0
      27: iload_1
      28: invokevirtual #287                // Method buildComponentKind:(I)Lio/dekorate/deps/applicationcrd/api/model/GroupKind;
      31: invokevirtual #289                // Method setNewComponentKindLike:(ILio/dekorate/deps/applicationcrd/api/model/GroupKind;)Lio/dekorate/deps/applicationcrd/api/model/ApplicationSpecFluent$ComponentKindsNested;
      34: areturn

  public io.dekorate.deps.applicationcrd.api.model.ApplicationSpecFluent$ComponentKindsNested<A> editFirstComponentKind();
    Code:
       0: aload_0
       1: getfield      #128                // Field componentKinds:Ljava/util/List;
       4: invokeinterface #155,  1          // InterfaceMethod java/util/List.size:()I
       9: ifne          23
      12: new           #282                // class java/lang/RuntimeException
      15: dup
      16: ldc_w         #292                // String Can\'t edit first componentKinds. The list is empty.
      19: invokespecial #285                // Method java/lang/RuntimeException."<init>":(Ljava/lang/String;)V
      22: athrow
      23: aload_0
      24: iconst_0
      25: aload_0
      26: iconst_0
      27: invokevirtual #287                // Method buildComponentKind:(I)Lio/dekorate/deps/applicationcrd/api/model/GroupKind;
      30: invokevirtual #289                // Method setNewComponentKindLike:(ILio/dekorate/deps/applicationcrd/api/model/GroupKind;)Lio/dekorate/deps/applicationcrd/api/model/ApplicationSpecFluent$ComponentKindsNested;
      33: areturn

  public io.dekorate.deps.applicationcrd.api.model.ApplicationSpecFluent$ComponentKindsNested<A> editLastComponentKind();
    Code:
       0: aload_0
       1: getfield      #128                // Field componentKinds:Ljava/util/List;
       4: invokeinterface #155,  1          // InterfaceMethod java/util/List.size:()I
       9: iconst_1
      10: isub
      11: istore_1
      12: iload_1
      13: ifge          27
      16: new           #282                // class java/lang/RuntimeException
      19: dup
      20: ldc_w         #295                // String Can\'t edit last componentKinds. The list is empty.
      23: invokespecial #285                // Method java/lang/RuntimeException."<init>":(Ljava/lang/String;)V
      26: athrow
      27: aload_0
      28: iload_1
      29: aload_0
      30: iload_1
      31: invokevirtual #287                // Method buildComponentKind:(I)Lio/dekorate/deps/applicationcrd/api/model/GroupKind;
      34: invokevirtual #289                // Method setNewComponentKindLike:(ILio/dekorate/deps/applicationcrd/api/model/GroupKind;)Lio/dekorate/deps/applicationcrd/api/model/ApplicationSpecFluent$ComponentKindsNested;
      37: areturn

  public io.dekorate.deps.applicationcrd.api.model.ApplicationSpecFluent$ComponentKindsNested<A> editMatchingComponentKind(io.dekorate.deps.kubernetes.api.builder.Predicate<io.dekorate.deps.applicationcrd.api.model.GroupKindBuilder>);
    Code:
       0: iconst_m1
       1: istore_2
       2: iconst_0
       3: istore_3
       4: iload_3
       5: aload_0
       6: getfield      #128                // Field componentKinds:Ljava/util/List;
       9: invokeinterface #155,  1          // InterfaceMethod java/util/List.size:()I
      14: if_icmpge     50
      17: aload_1
      18: aload_0
      19: getfield      #128                // Field componentKinds:Ljava/util/List;
      22: iload_3
      23: invokeinterface #216,  2          // InterfaceMethod java/util/List.get:(I)Ljava/lang/Object;
      28: invokeinterface #231,  2          // InterfaceMethod io/dekorate/deps/kubernetes/api/builder/Predicate.apply:(Ljava/lang/Object;)Ljava/lang/Boolean;
      33: invokevirtual #234                // Method java/lang/Boolean.booleanValue:()Z
      36: ifeq          44
      39: iload_3
      40: istore_2
      41: goto          50
      44: iinc          3, 1
      47: goto          4
      50: iload_2
      51: ifge          65
      54: new           #282                // class java/lang/RuntimeException
      57: dup
      58: ldc_w         #300                // String Can\'t edit matching componentKinds. No match found.
      61: invokespecial #285                // Method java/lang/RuntimeException."<init>":(Ljava/lang/String;)V
      64: athrow
      65: aload_0
      66: iload_2
      67: aload_0
      68: iload_2
      69: invokevirtual #287                // Method buildComponentKind:(I)Lio/dekorate/deps/applicationcrd/api/model/GroupKind;
      72: invokevirtual #289                // Method setNewComponentKindLike:(ILio/dekorate/deps/applicationcrd/api/model/GroupKind;)Lio/dekorate/deps/applicationcrd/api/model/ApplicationSpecFluent$ComponentKindsNested;
      75: areturn

  public io.dekorate.deps.applicationcrd.api.model.Descriptor getDescriptor();
    Code:
       0: aload_0
       1: getfield      #303                // Field descriptor:Lio/dekorate/deps/applicationcrd/api/model/DescriptorBuilder;
       4: ifnull        17
       7: aload_0
       8: getfield      #303                // Field descriptor:Lio/dekorate/deps/applicationcrd/api/model/DescriptorBuilder;
      11: invokevirtual #307                // Method io/dekorate/deps/applicationcrd/api/model/DescriptorBuilder.build:()Lio/dekorate/deps/applicationcrd/api/model/Descriptor;
      14: goto          18
      17: aconst_null
      18: areturn

  public io.dekorate.deps.applicationcrd.api.model.Descriptor buildDescriptor();
    Code:
       0: aload_0
       1: getfield      #303                // Field descriptor:Lio/dekorate/deps/applicationcrd/api/model/DescriptorBuilder;
       4: ifnull        17
       7: aload_0
       8: getfield      #303                // Field descriptor:Lio/dekorate/deps/applicationcrd/api/model/DescriptorBuilder;
      11: invokevirtual #307                // Method io/dekorate/deps/applicationcrd/api/model/DescriptorBuilder.build:()Lio/dekorate/deps/applicationcrd/api/model/Descriptor;
      14: goto          18
      17: aconst_null
      18: areturn

  public A withDescriptor(io.dekorate.deps.applicationcrd.api.model.Descriptor);
    Code:
       0: aload_0
       1: getfield      #140                // Field _visitables:Lio/dekorate/deps/kubernetes/api/builder/VisitableMap;
       4: ldc_w         #312                // String descriptor
       7: invokevirtual #147                // Method io/dekorate/deps/kubernetes/api/builder/VisitableMap.get:(Ljava/lang/Object;)Ljava/util/List;
      10: aload_0
      11: getfield      #303                // Field descriptor:Lio/dekorate/deps/applicationcrd/api/model/DescriptorBuilder;
      14: invokeinterface #203,  2          // InterfaceMethod java/util/List.remove:(Ljava/lang/Object;)Z
      19: pop
      20: aload_1
      21: ifnull        56
      24: aload_0
      25: new           #305                // class io/dekorate/deps/applicationcrd/api/model/DescriptorBuilder
      28: dup
      29: aload_1
      30: invokespecial #315                // Method io/dekorate/deps/applicationcrd/api/model/DescriptorBuilder."<init>":(Lio/dekorate/deps/applicationcrd/api/model/Descriptor;)V
      33: putfield      #303                // Field descriptor:Lio/dekorate/deps/applicationcrd/api/model/DescriptorBuilder;
      36: aload_0
      37: getfield      #140                // Field _visitables:Lio/dekorate/deps/kubernetes/api/builder/VisitableMap;
      40: ldc_w         #312                // String descriptor
      43: invokevirtual #147                // Method io/dekorate/deps/kubernetes/api/builder/VisitableMap.get:(Ljava/lang/Object;)Ljava/util/List;
      46: aload_0
      47: getfield      #303                // Field descriptor:Lio/dekorate/deps/applicationcrd/api/model/DescriptorBuilder;
      50: invokeinterface #169,  2          // InterfaceMethod java/util/List.add:(Ljava/lang/Object;)Z
      55: pop
      56: aload_0
      57: areturn

  public java.lang.Boolean hasDescriptor();
    Code:
       0: aload_0
       1: getfield      #303                // Field descriptor:Lio/dekorate/deps/applicationcrd/api/model/DescriptorBuilder;
       4: ifnull        11
       7: iconst_1
       8: goto          12
      11: iconst_0
      12: invokestatic  #104                // Method java/lang/Boolean.valueOf:(Z)Ljava/lang/Boolean;
      15: areturn

  public io.dekorate.deps.applicationcrd.api.model.ApplicationSpecFluent$DescriptorNested<A> withNewDescriptor();
    Code:
       0: new           #16                 // class io/dekorate/deps/applicationcrd/api/model/ApplicationSpecFluentImpl$DescriptorNestedImpl
       3: dup
       4: aload_0
       5: invokespecial #321                // Method io/dekorate/deps/applicationcrd/api/model/ApplicationSpecFluentImpl$DescriptorNestedImpl."<init>":(Lio/dekorate/deps/applicationcrd/api/model/ApplicationSpecFluentImpl;)V
       8: areturn

  public io.dekorate.deps.applicationcrd.api.model.ApplicationSpecFluent$DescriptorNested<A> withNewDescriptorLike(io.dekorate.deps.applicationcrd.api.model.Descriptor);
    Code:
       0: new           #16                 // class io/dekorate/deps/applicationcrd/api/model/ApplicationSpecFluentImpl$DescriptorNestedImpl
       3: dup
       4: aload_0
       5: aload_1
       6: invokespecial #327                // Method io/dekorate/deps/applicationcrd/api/model/ApplicationSpecFluentImpl$DescriptorNestedImpl."<init>":(Lio/dekorate/deps/applicationcrd/api/model/ApplicationSpecFluentImpl;Lio/dekorate/deps/applicationcrd/api/model/Descriptor;)V
       9: areturn

  public io.dekorate.deps.applicationcrd.api.model.ApplicationSpecFluent$DescriptorNested<A> editDescriptor();
    Code:
       0: aload_0
       1: aload_0
       2: invokevirtual #329                // Method getDescriptor:()Lio/dekorate/deps/applicationcrd/api/model/Descriptor;
       5: invokevirtual #331                // Method withNewDescriptorLike:(Lio/dekorate/deps/applicationcrd/api/model/Descriptor;)Lio/dekorate/deps/applicationcrd/api/model/ApplicationSpecFluent$DescriptorNested;
       8: areturn

  public io.dekorate.deps.applicationcrd.api.model.ApplicationSpecFluent$DescriptorNested<A> editOrNewDescriptor();
    Code:
       0: aload_0
       1: aload_0
       2: invokevirtual #329                // Method getDescriptor:()Lio/dekorate/deps/applicationcrd/api/model/Descriptor;
       5: ifnull        15
       8: aload_0
       9: invokevirtual #329                // Method getDescriptor:()Lio/dekorate/deps/applicationcrd/api/model/Descriptor;
      12: goto          25
      15: new           #305                // class io/dekorate/deps/applicationcrd/api/model/DescriptorBuilder
      18: dup
      19: invokespecial #333                // Method io/dekorate/deps/applicationcrd/api/model/DescriptorBuilder."<init>":()V
      22: invokevirtual #307                // Method io/dekorate/deps/applicationcrd/api/model/DescriptorBuilder.build:()Lio/dekorate/deps/applicationcrd/api/model/Descriptor;
      25: invokevirtual #331                // Method withNewDescriptorLike:(Lio/dekorate/deps/applicationcrd/api/model/Descriptor;)Lio/dekorate/deps/applicationcrd/api/model/ApplicationSpecFluent$DescriptorNested;
      28: areturn

  public io.dekorate.deps.applicationcrd.api.model.ApplicationSpecFluent$DescriptorNested<A> editOrNewDescriptorLike(io.dekorate.deps.applicationcrd.api.model.Descriptor);
    Code:
       0: aload_0
       1: aload_0
       2: invokevirtual #329                // Method getDescriptor:()Lio/dekorate/deps/applicationcrd/api/model/Descriptor;
       5: ifnull        15
       8: aload_0
       9: invokevirtual #329                // Method getDescriptor:()Lio/dekorate/deps/applicationcrd/api/model/Descriptor;
      12: goto          16
      15: aload_1
      16: invokevirtual #331                // Method withNewDescriptorLike:(Lio/dekorate/deps/applicationcrd/api/model/Descriptor;)Lio/dekorate/deps/applicationcrd/api/model/ApplicationSpecFluent$DescriptorNested;
      19: areturn

  public A addToInfo(int, io.dekorate.deps.applicationcrd.api.model.InfoItem);
    Code:
       0: aload_0
       1: getfield      #339                // Field info:Ljava/util/List;
       4: ifnonnull     18
       7: aload_0
       8: new           #130                // class java/util/ArrayList
      11: dup
      12: invokespecial #131                // Method java/util/ArrayList."<init>":()V
      15: putfield      #339                // Field info:Ljava/util/List;
      18: new           #341                // class io/dekorate/deps/applicationcrd/api/model/InfoItemBuilder
      21: dup
      22: aload_2
      23: invokespecial #344                // Method io/dekorate/deps/applicationcrd/api/model/InfoItemBuilder."<init>":(Lio/dekorate/deps/applicationcrd/api/model/InfoItem;)V
      26: astore_3
      27: aload_0
      28: getfield      #140                // Field _visitables:Lio/dekorate/deps/kubernetes/api/builder/VisitableMap;
      31: ldc_w         #345                // String info
      34: invokevirtual #147                // Method io/dekorate/deps/kubernetes/api/builder/VisitableMap.get:(Ljava/lang/Object;)Ljava/util/List;
      37: iload_1
      38: iflt          45
      41: iload_1
      42: goto          60
      45: aload_0
      46: getfield      #140                // Field _visitables:Lio/dekorate/deps/kubernetes/api/builder/VisitableMap;
      49: ldc_w         #345                // String info
      52: invokevirtual #147                // Method io/dekorate/deps/kubernetes/api/builder/VisitableMap.get:(Ljava/lang/Object;)Ljava/util/List;
      55: invokeinterface #155,  1          // InterfaceMethod java/util/List.size:()I
      60: aload_3
      61: invokeinterface #159,  3          // InterfaceMethod java/util/List.add:(ILjava/lang/Object;)V
      66: aload_0
      67: getfield      #339                // Field info:Ljava/util/List;
      70: iload_1
      71: iflt          78
      74: iload_1
      75: goto          87
      78: aload_0
      79: getfield      #339                // Field info:Ljava/util/List;
      82: invokeinterface #155,  1          // InterfaceMethod java/util/List.size:()I
      87: aload_3
      88: invokeinterface #159,  3          // InterfaceMethod java/util/List.add:(ILjava/lang/Object;)V
      93: aload_0
      94: areturn

  public A setToInfo(int, io.dekorate.deps.applicationcrd.api.model.InfoItem);
    Code:
       0: aload_0
       1: getfield      #339                // Field info:Ljava/util/List;
       4: ifnonnull     18
       7: aload_0
       8: new           #130                // class java/util/ArrayList
      11: dup
      12: invokespecial #131                // Method java/util/ArrayList."<init>":()V
      15: putfield      #339                // Field info:Ljava/util/List;
      18: new           #341                // class io/dekorate/deps/applicationcrd/api/model/InfoItemBuilder
      21: dup
      22: aload_2
      23: invokespecial #344                // Method io/dekorate/deps/applicationcrd/api/model/InfoItemBuilder."<init>":(Lio/dekorate/deps/applicationcrd/api/model/InfoItem;)V
      26: astore_3
      27: iload_1
      28: iflt          50
      31: iload_1
      32: aload_0
      33: getfield      #140                // Field _visitables:Lio/dekorate/deps/kubernetes/api/builder/VisitableMap;
      36: ldc_w         #345                // String info
      39: invokevirtual #147                // Method io/dekorate/deps/kubernetes/api/builder/VisitableMap.get:(Ljava/lang/Object;)Ljava/util/List;
      42: invokeinterface #155,  1          // InterfaceMethod java/util/List.size:()I
      47: if_icmplt     70
      50: aload_0
      51: getfield      #140                // Field _visitables:Lio/dekorate/deps/kubernetes/api/builder/VisitableMap;
      54: ldc_w         #345                // String info
      57: invokevirtual #147                // Method io/dekorate/deps/kubernetes/api/builder/VisitableMap.get:(Ljava/lang/Object;)Ljava/util/List;
      60: aload_3
      61: invokeinterface #169,  2          // InterfaceMethod java/util/List.add:(Ljava/lang/Object;)Z
      66: pop
      67: goto          88
      70: aload_0
      71: getfield      #140                // Field _visitables:Lio/dekorate/deps/kubernetes/api/builder/VisitableMap;
      74: ldc_w         #345                // String info
      77: invokevirtual #147                // Method io/dekorate/deps/kubernetes/api/builder/VisitableMap.get:(Ljava/lang/Object;)Ljava/util/List;
      80: iload_1
      81: aload_3
      82: invokeinterface #173,  3          // InterfaceMethod java/util/List.set:(ILjava/lang/Object;)Ljava/lang/Object;
      87: pop
      88: iload_1
      89: iflt          105
      92: iload_1
      93: aload_0
      94: getfield      #339                // Field info:Ljava/util/List;
      97: invokeinterface #155,  1          // InterfaceMethod java/util/List.size:()I
     102: if_icmplt     119
     105: aload_0
     106: getfield      #339                // Field info:Ljava/util/List;
     109: aload_3
     110: invokeinterface #169,  2          // InterfaceMethod java/util/List.add:(Ljava/lang/Object;)Z
     115: pop
     116: goto          131
     119: aload_0
     120: getfield      #339                // Field info:Ljava/util/List;
     123: iload_1
     124: aload_3
     125: invokeinterface #173,  3          // InterfaceMethod java/util/List.set:(ILjava/lang/Object;)Ljava/lang/Object;
     130: pop
     131: aload_0
     132: areturn

  public A addToInfo(io.dekorate.deps.applicationcrd.api.model.InfoItem...);
    Code:
       0: aload_0
       1: getfield      #339                // Field info:Ljava/util/List;
       4: ifnonnull     18
       7: aload_0
       8: new           #130                // class java/util/ArrayList
      11: dup
      12: invokespecial #131                // Method java/util/ArrayList."<init>":()V
      15: putfield      #339                // Field info:Ljava/util/List;
      18: aload_1
      19: astore_2
      20: aload_2
      21: arraylength
      22: istore_3
      23: iconst_0
      24: istore        4
      26: iload         4
      28: iload_3
      29: if_icmpge     85
      32: aload_2
      33: iload         4
      35: aaload
      36: astore        5
      38: new           #341                // class io/dekorate/deps/applicationcrd/api/model/InfoItemBuilder
      41: dup
      42: aload         5
      44: invokespecial #344                // Method io/dekorate/deps/applicationcrd/api/model/InfoItemBuilder."<init>":(Lio/dekorate/deps/applicationcrd/api/model/InfoItem;)V
      47: astore        6
      49: aload_0
      50: getfield      #140                // Field _visitables:Lio/dekorate/deps/kubernetes/api/builder/VisitableMap;
      53: ldc_w         #345                // String info
      56: invokevirtual #147                // Method io/dekorate/deps/kubernetes/api/builder/VisitableMap.get:(Ljava/lang/Object;)Ljava/util/List;
      59: aload         6
      61: invokeinterface #169,  2          // InterfaceMethod java/util/List.add:(Ljava/lang/Object;)Z
      66: pop
      67: aload_0
      68: getfield      #339                // Field info:Ljava/util/List;
      71: aload         6
      73: invokeinterface #169,  2          // InterfaceMethod java/util/List.add:(Ljava/lang/Object;)Z
      78: pop
      79: iinc          4, 1
      82: goto          26
      85: aload_0
      86: areturn

  public A addAllToInfo(java.util.Collection<io.dekorate.deps.applicationcrd.api.model.InfoItem>);
    Code:
       0: aload_0
       1: getfield      #339                // Field info:Ljava/util/List;
       4: ifnonnull     18
       7: aload_0
       8: new           #130                // class java/util/ArrayList
      11: dup
      12: invokespecial #131                // Method java/util/ArrayList."<init>":()V
      15: putfield      #339                // Field info:Ljava/util/List;
      18: aload_1
      19: invokeinterface #187,  1          // InterfaceMethod java/util/Collection.iterator:()Ljava/util/Iterator;
      24: astore_2
      25: aload_2
      26: invokeinterface #193,  1          // InterfaceMethod java/util/Iterator.hasNext:()Z
      31: ifeq          87
      34: aload_2
      35: invokeinterface #197,  1          // InterfaceMethod java/util/Iterator.next:()Ljava/lang/Object;
      40: checkcast     #347                // class io/dekorate/deps/applicationcrd/api/model/InfoItem
      43: astore_3
      44: new           #341                // class io/dekorate/deps/applicationcrd/api/model/InfoItemBuilder
      47: dup
      48: aload_3
      49: invokespecial #344                // Method io/dekorate/deps/applicationcrd/api/model/InfoItemBuilder."<init>":(Lio/dekorate/deps/applicationcrd/api/model/InfoItem;)V
      52: astore        4
      54: aload_0
      55: getfield      #140                // Field _visitables:Lio/dekorate/deps/kubernetes/api/builder/VisitableMap;
      58: ldc_w         #345                // String info
      61: invokevirtual #147                // Method io/dekorate/deps/kubernetes/api/builder/VisitableMap.get:(Ljava/lang/Object;)Ljava/util/List;
      64: aload         4
      66: invokeinterface #169,  2          // InterfaceMethod java/util/List.add:(Ljava/lang/Object;)Z
      71: pop
      72: aload_0
      73: getfield      #339                // Field info:Ljava/util/List;
      76: aload         4
      78: invokeinterface #169,  2          // InterfaceMethod java/util/List.add:(Ljava/lang/Object;)Z
      83: pop
      84: goto          25
      87: aload_0
      88: areturn

  public A removeFromInfo(io.dekorate.deps.applicationcrd.api.model.InfoItem...);
    Code:
       0: aload_1
       1: astore_2
       2: aload_2
       3: arraylength
       4: istore_3
       5: iconst_0
       6: istore        4
       8: iload         4
      10: iload_3
      11: if_icmpge     74
      14: aload_2
      15: iload         4
      17: aaload
      18: astore        5
      20: new           #341                // class io/dekorate/deps/applicationcrd/api/model/InfoItemBuilder
      23: dup
      24: aload         5
      26: invokespecial #344                // Method io/dekorate/deps/applicationcrd/api/model/InfoItemBuilder."<init>":(Lio/dekorate/deps/applicationcrd/api/model/InfoItem;)V
      29: astore        6
      31: aload_0
      32: getfield      #140                // Field _visitables:Lio/dekorate/deps/kubernetes/api/builder/VisitableMap;
      35: ldc_w         #345                // String info
      38: invokevirtual #147                // Method io/dekorate/deps/kubernetes/api/builder/VisitableMap.get:(Ljava/lang/Object;)Ljava/util/List;
      41: aload         6
      43: invokeinterface #203,  2          // InterfaceMethod java/util/List.remove:(Ljava/lang/Object;)Z
      48: pop
      49: aload_0
      50: getfield      #339                // Field info:Ljava/util/List;
      53: ifnull        68
      56: aload_0
      57: getfield      #339                // Field info:Ljava/util/List;
      60: aload         6
      62: invokeinterface #203,  2          // InterfaceMethod java/util/List.remove:(Ljava/lang/Object;)Z
      67: pop
      68: iinc          4, 1
      71: goto          8
      74: aload_0
      75: areturn

  public A removeAllFromInfo(java.util.Collection<io.dekorate.deps.applicationcrd.api.model.InfoItem>);
    Code:
       0: aload_1
       1: invokeinterface #187,  1          // InterfaceMethod java/util/Collection.iterator:()Ljava/util/Iterator;
       6: astore_2
       7: aload_2
       8: invokeinterface #193,  1          // InterfaceMethod java/util/Iterator.hasNext:()Z
      13: ifeq          76
      16: aload_2
      17: invokeinterface #197,  1          // InterfaceMethod java/util/Iterator.next:()Ljava/lang/Object;
      22: checkcast     #347                // class io/dekorate/deps/applicationcrd/api/model/InfoItem
      25: astore_3
      26: new           #341                // class io/dekorate/deps/applicationcrd/api/model/InfoItemBuilder
      29: dup
      30: aload_3
      31: invokespecial #344                // Method io/dekorate/deps/applicationcrd/api/model/InfoItemBuilder."<init>":(Lio/dekorate/deps/applicationcrd/api/model/InfoItem;)V
      34: astore        4
      36: aload_0
      37: getfield      #140                // Field _visitables:Lio/dekorate/deps/kubernetes/api/builder/VisitableMap;
      40: ldc_w         #345                // String info
      43: invokevirtual #147                // Method io/dekorate/deps/kubernetes/api/builder/VisitableMap.get:(Ljava/lang/Object;)Ljava/util/List;
      46: aload         4
      48: invokeinterface #203,  2          // InterfaceMethod java/util/List.remove:(Ljava/lang/Object;)Z
      53: pop
      54: aload_0
      55: getfield      #339                // Field info:Ljava/util/List;
      58: ifnull        73
      61: aload_0
      62: getfield      #339                // Field info:Ljava/util/List;
      65: aload         4
      67: invokeinterface #203,  2          // InterfaceMethod java/util/List.remove:(Ljava/lang/Object;)Z
      72: pop
      73: goto          7
      76: aload_0
      77: areturn

  public java.util.List<io.dekorate.deps.applicationcrd.api.model.InfoItem> getInfo();
    Code:
       0: aload_0
       1: getfield      #339                // Field info:Ljava/util/List;
       4: invokestatic  #210                // Method build:(Ljava/util/List;)Ljava/util/ArrayList;
       7: areturn

  public java.util.List<io.dekorate.deps.applicationcrd.api.model.InfoItem> buildInfo();
    Code:
       0: aload_0
       1: getfield      #339                // Field info:Ljava/util/List;
       4: invokestatic  #210                // Method build:(Ljava/util/List;)Ljava/util/ArrayList;
       7: areturn

  public io.dekorate.deps.applicationcrd.api.model.InfoItem buildInfo(int);
    Code:
       0: aload_0
       1: getfield      #339                // Field info:Ljava/util/List;
       4: iload_1
       5: invokeinterface #216,  2          // InterfaceMethod java/util/List.get:(I)Ljava/lang/Object;
      10: checkcast     #341                // class io/dekorate/deps/applicationcrd/api/model/InfoItemBuilder
      13: invokevirtual #365                // Method io/dekorate/deps/applicationcrd/api/model/InfoItemBuilder.build:()Lio/dekorate/deps/applicationcrd/api/model/InfoItem;
      16: areturn

  public io.dekorate.deps.applicationcrd.api.model.InfoItem buildFirstInfo();
    Code:
       0: aload_0
       1: getfield      #339                // Field info:Ljava/util/List;
       4: iconst_0
       5: invokeinterface #216,  2          // InterfaceMethod java/util/List.get:(I)Ljava/lang/Object;
      10: checkcast     #341                // class io/dekorate/deps/applicationcrd/api/model/InfoItemBuilder
      13: invokevirtual #365                // Method io/dekorate/deps/applicationcrd/api/model/InfoItemBuilder.build:()Lio/dekorate/deps/applicationcrd/api/model/InfoItem;
      16: areturn

  public io.dekorate.deps.applicationcrd.api.model.InfoItem buildLastInfo();
    Code:
       0: aload_0
       1: getfield      #339                // Field info:Ljava/util/List;
       4: aload_0
       5: getfield      #339                // Field info:Ljava/util/List;
       8: invokeinterface #155,  1          // InterfaceMethod java/util/List.size:()I
      13: iconst_1
      14: isub
      15: invokeinterface #216,  2          // InterfaceMethod java/util/List.get:(I)Ljava/lang/Object;
      20: checkcast     #341                // class io/dekorate/deps/applicationcrd/api/model/InfoItemBuilder
      23: invokevirtual #365                // Method io/dekorate/deps/applicationcrd/api/model/InfoItemBuilder.build:()Lio/dekorate/deps/applicationcrd/api/model/InfoItem;
      26: areturn

  public io.dekorate.deps.applicationcrd.api.model.InfoItem buildMatchingInfo(io.dekorate.deps.kubernetes.api.builder.Predicate<io.dekorate.deps.applicationcrd.api.model.InfoItemBuilder>);
    Code:
       0: aload_0
       1: getfield      #339                // Field info:Ljava/util/List;
       4: invokeinterface #225,  1          // InterfaceMethod java/util/List.iterator:()Ljava/util/Iterator;
       9: astore_2
      10: aload_2
      11: invokeinterface #193,  1          // InterfaceMethod java/util/Iterator.hasNext:()Z
      16: ifeq          50
      19: aload_2
      20: invokeinterface #197,  1          // InterfaceMethod java/util/Iterator.next:()Ljava/lang/Object;
      25: checkcast     #341                // class io/dekorate/deps/applicationcrd/api/model/InfoItemBuilder
      28: astore_3
      29: aload_1
      30: aload_3
      31: invokeinterface #231,  2          // InterfaceMethod io/dekorate/deps/kubernetes/api/builder/Predicate.apply:(Ljava/lang/Object;)Ljava/lang/Boolean;
      36: invokevirtual #234                // Method java/lang/Boolean.booleanValue:()Z
      39: ifeq          47
      42: aload_3
      43: invokevirtual #365                // Method io/dekorate/deps/applicationcrd/api/model/InfoItemBuilder.build:()Lio/dekorate/deps/applicationcrd/api/model/InfoItem;
      46: areturn
      47: goto          10
      50: aconst_null
      51: areturn

  public java.lang.Boolean hasMatchingInfo(io.dekorate.deps.kubernetes.api.builder.Predicate<io.dekorate.deps.applicationcrd.api.model.InfoItemBuilder>);
    Code:
       0: aload_0
       1: getfield      #339                // Field info:Ljava/util/List;
       4: invokeinterface #225,  1          // InterfaceMethod java/util/List.iterator:()Ljava/util/Iterator;
       9: astore_2
      10: aload_2
      11: invokeinterface #193,  1          // InterfaceMethod java/util/Iterator.hasNext:()Z
      16: ifeq          50
      19: aload_2
      20: invokeinterface #197,  1          // InterfaceMethod java/util/Iterator.next:()Ljava/lang/Object;
      25: checkcast     #341                // class io/dekorate/deps/applicationcrd/api/model/InfoItemBuilder
      28: astore_3
      29: aload_1
      30: aload_3
      31: invokeinterface #231,  2          // InterfaceMethod io/dekorate/deps/kubernetes/api/builder/Predicate.apply:(Ljava/lang/Object;)Ljava/lang/Boolean;
      36: invokevirtual #234                // Method java/lang/Boolean.booleanValue:()Z
      39: ifeq          47
      42: iconst_1
      43: invokestatic  #104                // Method java/lang/Boolean.valueOf:(Z)Ljava/lang/Boolean;
      46: areturn
      47: goto          10
      50: iconst_0
      51: invokestatic  #104                // Method java/lang/Boolean.valueOf:(Z)Ljava/lang/Boolean;
      54: areturn

  public A withInfo(java.util.List<io.dekorate.deps.applicationcrd.api.model.InfoItem>);
    Code:
       0: aload_0
       1: getfield      #339                // Field info:Ljava/util/List;
       4: ifnull        27
       7: aload_0
       8: getfield      #140                // Field _visitables:Lio/dekorate/deps/kubernetes/api/builder/VisitableMap;
      11: ldc_w         #345                // String info
      14: invokevirtual #147                // Method io/dekorate/deps/kubernetes/api/builder/VisitableMap.get:(Ljava/lang/Object;)Ljava/util/List;
      17: aload_0
      18: getfield      #339                // Field info:Ljava/util/List;
      21: invokeinterface #245,  2          // InterfaceMethod java/util/List.removeAll:(Ljava/util/Collection;)Z
      26: pop
      27: aload_1
      28: ifnull        87
      31: aload_0
      32: new           #130                // class java/util/ArrayList
      35: dup
      36: invokespecial #131                // Method java/util/ArrayList."<init>":()V
      39: putfield      #339                // Field info:Ljava/util/List;
      42: aload_1
      43: invokeinterface #225,  1          // InterfaceMethod java/util/List.iterator:()Ljava/util/Iterator;
      48: astore_2
      49: aload_2
      50: invokeinterface #193,  1          // InterfaceMethod java/util/Iterator.hasNext:()Z
      55: ifeq          84
      58: aload_2
      59: invokeinterface #197,  1          // InterfaceMethod java/util/Iterator.next:()Ljava/lang/Object;
      64: checkcast     #347                // class io/dekorate/deps/applicationcrd/api/model/InfoItem
      67: astore_3
      68: aload_0
      69: iconst_1
      70: anewarray     #347                // class io/dekorate/deps/applicationcrd/api/model/InfoItem
      73: dup
      74: iconst_0
      75: aload_3
      76: aastore
      77: invokevirtual #376                // Method addToInfo:([Lio/dekorate/deps/applicationcrd/api/model/InfoItem;)Lio/dekorate/deps/applicationcrd/api/model/ApplicationSpecFluent;
      80: pop
      81: goto          49
      84: goto          92
      87: aload_0
      88: aconst_null
      89: putfield      #339                // Field info:Ljava/util/List;
      92: aload_0
      93: areturn

  public A withInfo(io.dekorate.deps.applicationcrd.api.model.InfoItem...);
    Code:
       0: aload_0
       1: getfield      #339                // Field info:Ljava/util/List;
       4: ifnull        16
       7: aload_0
       8: getfield      #339                // Field info:Ljava/util/List;
      11: invokeinterface #251,  1          // InterfaceMethod java/util/List.clear:()V
      16: aload_1
      17: ifnull        60
      20: aload_1
      21: astore_2
      22: aload_2
      23: arraylength
      24: istore_3
      25: iconst_0
      26: istore        4
      28: iload         4
      30: iload_3
      31: if_icmpge     60
      34: aload_2
      35: iload         4
      37: aaload
      38: astore        5
      40: aload_0
      41: iconst_1
      42: anewarray     #347                // class io/dekorate/deps/applicationcrd/api/model/InfoItem
      45: dup
      46: iconst_0
      47: aload         5
      49: aastore
      50: invokevirtual #376                // Method addToInfo:([Lio/dekorate/deps/applicationcrd/api/model/InfoItem;)Lio/dekorate/deps/applicationcrd/api/model/ApplicationSpecFluent;
      53: pop
      54: iinc          4, 1
      57: goto          28
      60: aload_0
      61: areturn

  public java.lang.Boolean hasInfo();
    Code:
       0: aload_0
       1: getfield      #339                // Field info:Ljava/util/List;
       4: ifnull        23
       7: aload_0
       8: getfield      #339                // Field info:Ljava/util/List;
      11: invokeinterface #255,  1          // InterfaceMethod java/util/List.isEmpty:()Z
      16: ifne          23
      19: iconst_1
      20: goto          24
      23: iconst_0
      24: invokestatic  #104                // Method java/lang/Boolean.valueOf:(Z)Ljava/lang/Boolean;
      27: areturn

  public io.dekorate.deps.applicationcrd.api.model.ApplicationSpecFluent$InfoNested<A> addNewInfo();
    Code:
       0: new           #13                 // class io/dekorate/deps/applicationcrd/api/model/ApplicationSpecFluentImpl$InfoNestedImpl
       3: dup
       4: aload_0
       5: invokespecial #382                // Method io/dekorate/deps/applicationcrd/api/model/ApplicationSpecFluentImpl$InfoNestedImpl."<init>":(Lio/dekorate/deps/applicationcrd/api/model/ApplicationSpecFluentImpl;)V
       8: areturn

  public io.dekorate.deps.applicationcrd.api.model.ApplicationSpecFluent$InfoNested<A> addNewInfoLike(io.dekorate.deps.applicationcrd.api.model.InfoItem);
    Code:
       0: new           #13                 // class io/dekorate/deps/applicationcrd/api/model/ApplicationSpecFluentImpl$InfoNestedImpl
       3: dup
       4: aload_0
       5: iconst_m1
       6: aload_1
       7: invokespecial #388                // Method io/dekorate/deps/applicationcrd/api/model/ApplicationSpecFluentImpl$InfoNestedImpl."<init>":(Lio/dekorate/deps/applicationcrd/api/model/ApplicationSpecFluentImpl;ILio/dekorate/deps/applicationcrd/api/model/InfoItem;)V
      10: areturn

  public io.dekorate.deps.applicationcrd.api.model.ApplicationSpecFluent$InfoNested<A> setNewInfoLike(int, io.dekorate.deps.applicationcrd.api.model.InfoItem);
    Code:
       0: new           #13                 // class io/dekorate/deps/applicationcrd/api/model/ApplicationSpecFluentImpl$InfoNestedImpl
       3: dup
       4: aload_0
       5: iload_1
       6: aload_2
       7: invokespecial #388                // Method io/dekorate/deps/applicationcrd/api/model/ApplicationSpecFluentImpl$InfoNestedImpl."<init>":(Lio/dekorate/deps/applicationcrd/api/model/ApplicationSpecFluentImpl;ILio/dekorate/deps/applicationcrd/api/model/InfoItem;)V
      10: areturn

  public io.dekorate.deps.applicationcrd.api.model.ApplicationSpecFluent$InfoNested<A> editInfo(int);
    Code:
       0: aload_0
       1: getfield      #339                // Field info:Ljava/util/List;
       4: invokeinterface #155,  1          // InterfaceMethod java/util/List.size:()I
       9: iload_1
      10: if_icmpgt     24
      13: new           #282                // class java/lang/RuntimeException
      16: dup
      17: ldc_w         #396                // String Can\'t edit info. Index exceeds size.
      20: invokespecial #285                // Method java/lang/RuntimeException."<init>":(Ljava/lang/String;)V
      23: athrow
      24: aload_0
      25: iload_1
      26: aload_0
      27: iload_1
      28: invokevirtual #398                // Method buildInfo:(I)Lio/dekorate/deps/applicationcrd/api/model/InfoItem;
      31: invokevirtual #400                // Method setNewInfoLike:(ILio/dekorate/deps/applicationcrd/api/model/InfoItem;)Lio/dekorate/deps/applicationcrd/api/model/ApplicationSpecFluent$InfoNested;
      34: areturn

  public io.dekorate.deps.applicationcrd.api.model.ApplicationSpecFluent$InfoNested<A> editFirstInfo();
    Code:
       0: aload_0
       1: getfield      #339                // Field info:Ljava/util/List;
       4: invokeinterface #155,  1          // InterfaceMethod java/util/List.size:()I
       9: ifne          23
      12: new           #282                // class java/lang/RuntimeException
      15: dup
      16: ldc_w         #403                // String Can\'t edit first info. The list is empty.
      19: invokespecial #285                // Method java/lang/RuntimeException."<init>":(Ljava/lang/String;)V
      22: athrow
      23: aload_0
      24: iconst_0
      25: aload_0
      26: iconst_0
      27: invokevirtual #398                // Method buildInfo:(I)Lio/dekorate/deps/applicationcrd/api/model/InfoItem;
      30: invokevirtual #400                // Method setNewInfoLike:(ILio/dekorate/deps/applicationcrd/api/model/InfoItem;)Lio/dekorate/deps/applicationcrd/api/model/ApplicationSpecFluent$InfoNested;
      33: areturn

  public io.dekorate.deps.applicationcrd.api.model.ApplicationSpecFluent$InfoNested<A> editLastInfo();
    Code:
       0: aload_0
       1: getfield      #339                // Field info:Ljava/util/List;
       4: invokeinterface #155,  1          // InterfaceMethod java/util/List.size:()I
       9: iconst_1
      10: isub
      11: istore_1
      12: iload_1
      13: ifge          27
      16: new           #282                // class java/lang/RuntimeException
      19: dup
      20: ldc_w         #406                // String Can\'t edit last info. The list is empty.
      23: invokespecial #285                // Method java/lang/RuntimeException."<init>":(Ljava/lang/String;)V
      26: athrow
      27: aload_0
      28: iload_1
      29: aload_0
      30: iload_1
      31: invokevirtual #398                // Method buildInfo:(I)Lio/dekorate/deps/applicationcrd/api/model/InfoItem;
      34: invokevirtual #400                // Method setNewInfoLike:(ILio/dekorate/deps/applicationcrd/api/model/InfoItem;)Lio/dekorate/deps/applicationcrd/api/model/ApplicationSpecFluent$InfoNested;
      37: areturn

  public io.dekorate.deps.applicationcrd.api.model.ApplicationSpecFluent$InfoNested<A> editMatchingInfo(io.dekorate.deps.kubernetes.api.builder.Predicate<io.dekorate.deps.applicationcrd.api.model.InfoItemBuilder>);
    Code:
       0: iconst_m1
       1: istore_2
       2: iconst_0
       3: istore_3
       4: iload_3
       5: aload_0
       6: getfield      #339                // Field info:Ljava/util/List;
       9: invokeinterface #155,  1          // InterfaceMethod java/util/List.size:()I
      14: if_icmpge     50
      17: aload_1
      18: aload_0
      19: getfield      #339                // Field info:Ljava/util/List;
      22: iload_3
      23: invokeinterface #216,  2          // InterfaceMethod java/util/List.get:(I)Ljava/lang/Object;
      28: invokeinterface #231,  2          // InterfaceMethod io/dekorate/deps/kubernetes/api/builder/Predicate.apply:(Ljava/lang/Object;)Ljava/lang/Boolean;
      33: invokevirtual #234                // Method java/lang/Boolean.booleanValue:()Z
      36: ifeq          44
      39: iload_3
      40: istore_2
      41: goto          50
      44: iinc          3, 1
      47: goto          4
      50: iload_2
      51: ifge          65
      54: new           #282                // class java/lang/RuntimeException
      57: dup
      58: ldc_w         #411                // String Can\'t edit matching info. No match found.
      61: invokespecial #285                // Method java/lang/RuntimeException."<init>":(Ljava/lang/String;)V
      64: athrow
      65: aload_0
      66: iload_2
      67: aload_0
      68: iload_2
      69: invokevirtual #398                // Method buildInfo:(I)Lio/dekorate/deps/applicationcrd/api/model/InfoItem;
      72: invokevirtual #400                // Method setNewInfoLike:(ILio/dekorate/deps/applicationcrd/api/model/InfoItem;)Lio/dekorate/deps/applicationcrd/api/model/ApplicationSpecFluent$InfoNested;
      75: areturn

  public io.dekorate.deps.kubernetes.api.model.LabelSelector getSelector();
    Code:
       0: aload_0
       1: getfield      #413                // Field selector:Lio/dekorate/deps/kubernetes/api/model/LabelSelectorBuilder;
       4: ifnull        17
       7: aload_0
       8: getfield      #413                // Field selector:Lio/dekorate/deps/kubernetes/api/model/LabelSelectorBuilder;
      11: invokevirtual #417                // Method io/dekorate/deps/kubernetes/api/model/LabelSelectorBuilder.build:()Lio/dekorate/deps/kubernetes/api/model/LabelSelector;
      14: goto          18
      17: aconst_null
      18: areturn

  public io.dekorate.deps.kubernetes.api.model.LabelSelector buildSelector();
    Code:
       0: aload_0
       1: getfield      #413                // Field selector:Lio/dekorate/deps/kubernetes/api/model/LabelSelectorBuilder;
       4: ifnull        17
       7: aload_0
       8: getfield      #413                // Field selector:Lio/dekorate/deps/kubernetes/api/model/LabelSelectorBuilder;
      11: invokevirtual #417                // Method io/dekorate/deps/kubernetes/api/model/LabelSelectorBuilder.build:()Lio/dekorate/deps/kubernetes/api/model/LabelSelector;
      14: goto          18
      17: aconst_null
      18: areturn

  public A withSelector(io.dekorate.deps.kubernetes.api.model.LabelSelector);
    Code:
       0: aload_0
       1: getfield      #140                // Field _visitables:Lio/dekorate/deps/kubernetes/api/builder/VisitableMap;
       4: ldc_w         #422                // String selector
       7: invokevirtual #147                // Method io/dekorate/deps/kubernetes/api/builder/VisitableMap.get:(Ljava/lang/Object;)Ljava/util/List;
      10: aload_0
      11: getfield      #413                // Field selector:Lio/dekorate/deps/kubernetes/api/model/LabelSelectorBuilder;
      14: invokeinterface #203,  2          // InterfaceMethod java/util/List.remove:(Ljava/lang/Object;)Z
      19: pop
      20: aload_1
      21: ifnull        56
      24: aload_0
      25: new           #415                // class io/dekorate/deps/kubernetes/api/model/LabelSelectorBuilder
      28: dup
      29: aload_1
      30: invokespecial #425                // Method io/dekorate/deps/kubernetes/api/model/LabelSelectorBuilder."<init>":(Lio/dekorate/deps/kubernetes/api/model/LabelSelector;)V
      33: putfield      #413                // Field selector:Lio/dekorate/deps/kubernetes/api/model/LabelSelectorBuilder;
      36: aload_0
      37: getfield      #140                // Field _visitables:Lio/dekorate/deps/kubernetes/api/builder/VisitableMap;
      40: ldc_w         #422                // String selector
      43: invokevirtual #147                // Method io/dekorate/deps/kubernetes/api/builder/VisitableMap.get:(Ljava/lang/Object;)Ljava/util/List;
      46: aload_0
      47: getfield      #413                // Field selector:Lio/dekorate/deps/kubernetes/api/model/LabelSelectorBuilder;
      50: invokeinterface #169,  2          // InterfaceMethod java/util/List.add:(Ljava/lang/Object;)Z
      55: pop
      56: aload_0
      57: areturn

  public java.lang.Boolean hasSelector();
    Code:
       0: aload_0
       1: getfield      #413                // Field selector:Lio/dekorate/deps/kubernetes/api/model/LabelSelectorBuilder;
       4: ifnull        11
       7: iconst_1
       8: goto          12
      11: iconst_0
      12: invokestatic  #104                // Method java/lang/Boolean.valueOf:(Z)Ljava/lang/Boolean;
      15: areturn

  public io.dekorate.deps.applicationcrd.api.model.ApplicationSpecFluent$SelectorNested<A> withNewSelector();
    Code:
       0: new           #10                 // class io/dekorate/deps/applicationcrd/api/model/ApplicationSpecFluentImpl$SelectorNestedImpl
       3: dup
       4: aload_0
       5: invokespecial #431                // Method io/dekorate/deps/applicationcrd/api/model/ApplicationSpecFluentImpl$SelectorNestedImpl."<init>":(Lio/dekorate/deps/applicationcrd/api/model/ApplicationSpecFluentImpl;)V
       8: areturn

  public io.dekorate.deps.applicationcrd.api.model.ApplicationSpecFluent$SelectorNested<A> withNewSelectorLike(io.dekorate.deps.kubernetes.api.model.LabelSelector);
    Code:
       0: new           #10                 // class io/dekorate/deps/applicationcrd/api/model/ApplicationSpecFluentImpl$SelectorNestedImpl
       3: dup
       4: aload_0
       5: aload_1
       6: invokespecial #437                // Method io/dekorate/deps/applicationcrd/api/model/ApplicationSpecFluentImpl$SelectorNestedImpl."<init>":(Lio/dekorate/deps/applicationcrd/api/model/ApplicationSpecFluentImpl;Lio/dekorate/deps/kubernetes/api/model/LabelSelector;)V
       9: areturn

  public io.dekorate.deps.applicationcrd.api.model.ApplicationSpecFluent$SelectorNested<A> editSelector();
    Code:
       0: aload_0
       1: aload_0
       2: invokevirtual #439                // Method getSelector:()Lio/dekorate/deps/kubernetes/api/model/LabelSelector;
       5: invokevirtual #441                // Method withNewSelectorLike:(Lio/dekorate/deps/kubernetes/api/model/LabelSelector;)Lio/dekorate/deps/applicationcrd/api/model/ApplicationSpecFluent$SelectorNested;
       8: areturn

  public io.dekorate.deps.applicationcrd.api.model.ApplicationSpecFluent$SelectorNested<A> editOrNewSelector();
    Code:
       0: aload_0
       1: aload_0
       2: invokevirtual #439                // Method getSelector:()Lio/dekorate/deps/kubernetes/api/model/LabelSelector;
       5: ifnull        15
       8: aload_0
       9: invokevirtual #439                // Method getSelector:()Lio/dekorate/deps/kubernetes/api/model/LabelSelector;
      12: goto          25
      15: new           #415                // class io/dekorate/deps/kubernetes/api/model/LabelSelectorBuilder
      18: dup
      19: invokespecial #443                // Method io/dekorate/deps/kubernetes/api/model/LabelSelectorBuilder."<init>":()V
      22: invokevirtual #417                // Method io/dekorate/deps/kubernetes/api/model/LabelSelectorBuilder.build:()Lio/dekorate/deps/kubernetes/api/model/LabelSelector;
      25: invokevirtual #441                // Method withNewSelectorLike:(Lio/dekorate/deps/kubernetes/api/model/LabelSelector;)Lio/dekorate/deps/applicationcrd/api/model/ApplicationSpecFluent$SelectorNested;
      28: areturn

  public io.dekorate.deps.applicationcrd.api.model.ApplicationSpecFluent$SelectorNested<A> editOrNewSelectorLike(io.dekorate.deps.kubernetes.api.model.LabelSelector);
    Code:
       0: aload_0
       1: aload_0
       2: invokevirtual #439                // Method getSelector:()Lio/dekorate/deps/kubernetes/api/model/LabelSelector;
       5: ifnull        15
       8: aload_0
       9: invokevirtual #439                // Method getSelector:()Lio/dekorate/deps/kubernetes/api/model/LabelSelector;
      12: goto          16
      15: aload_1
      16: invokevirtual #441                // Method withNewSelectorLike:(Lio/dekorate/deps/kubernetes/api/model/LabelSelector;)Lio/dekorate/deps/applicationcrd/api/model/ApplicationSpecFluent$SelectorNested;
      19: areturn

  public boolean equals(java.lang.Object);
    Code:
       0: aload_0
       1: aload_1
       2: if_acmpne     7
       5: iconst_1
       6: ireturn
       7: aload_1
       8: ifnull        22
      11: aload_0
      12: invokevirtual #451                // Method java/lang/Object.getClass:()Ljava/lang/Class;
      15: aload_1
      16: invokevirtual #451                // Method java/lang/Object.getClass:()Ljava/lang/Class;
      19: if_acmpeq     24
      22: iconst_0
      23: ireturn
      24: aload_0
      25: aload_1
      26: invokespecial #453                // Method java/lang/Object.equals:(Ljava/lang/Object;)Z
      29: ifne          34
      32: iconst_0
      33: ireturn
      34: aload_1
      35: checkcast     #2                  // class io/dekorate/deps/applicationcrd/api/model/ApplicationSpecFluentImpl
      38: astore_2
      39: aload_0
      40: getfield      #95                 // Field assemblyPhase:Ljava/lang/String;
      43: ifnull        63
      46: aload_0
      47: getfield      #95                 // Field assemblyPhase:Ljava/lang/String;
      50: aload_2
      51: getfield      #95                 // Field assemblyPhase:Ljava/lang/String;
      54: invokevirtual #454                // Method java/lang/String.equals:(Ljava/lang/Object;)Z
      57: ifne          72
      60: goto          70
      63: aload_2
      64: getfield      #95                 // Field assemblyPhase:Ljava/lang/String;
      67: ifnull        72
      70: iconst_0
      71: ireturn
      72: aload_0
      73: getfield      #128                // Field componentKinds:Ljava/util/List;
      76: ifnull        98
      79: aload_0
      80: getfield      #128                // Field componentKinds:Ljava/util/List;
      83: aload_2
      84: getfield      #128                // Field componentKinds:Ljava/util/List;
      87: invokeinterface #455,  2          // InterfaceMethod java/util/List.equals:(Ljava/lang/Object;)Z
      92: ifne          107
      95: goto          105
      98: aload_2
      99: getfield      #128                // Field componentKinds:Ljava/util/List;
     102: ifnull        107
     105: iconst_0
     106: ireturn
     107: aload_0
     108: getfield      #303                // Field descriptor:Lio/dekorate/deps/applicationcrd/api/model/DescriptorBuilder;
     111: ifnull        131
     114: aload_0
     115: getfield      #303                // Field descriptor:Lio/dekorate/deps/applicationcrd/api/model/DescriptorBuilder;
     118: aload_2
     119: getfield      #303                // Field descriptor:Lio/dekorate/deps/applicationcrd/api/model/DescriptorBuilder;
     122: invokevirtual #456                // Method io/dekorate/deps/applicationcrd/api/model/DescriptorBuilder.equals:(Ljava/lang/Object;)Z
     125: ifne          140
     128: goto          138
     131: aload_2
     132: getfield      #303                // Field descriptor:Lio/dekorate/deps/applicationcrd/api/model/DescriptorBuilder;
     135: ifnull        140
     138: iconst_0
     139: ireturn
     140: aload_0
     141: getfield      #339                // Field info:Ljava/util/List;
     144: ifnull        166
     147: aload_0
     148: getfield      #339                // Field info:Ljava/util/List;
     151: aload_2
     152: getfield      #339                // Field info:Ljava/util/List;
     155: invokeinterface #455,  2          // InterfaceMethod java/util/List.equals:(Ljava/lang/Object;)Z
     160: ifne          175
     163: goto          173
     166: aload_2
     167: getfield      #339                // Field info:Ljava/util/List;
     170: ifnull        175
     173: iconst_0
     174: ireturn
     175: aload_0
     176: getfield      #413                // Field selector:Lio/dekorate/deps/kubernetes/api/model/LabelSelectorBuilder;
     179: ifnull        199
     182: aload_0
     183: getfield      #413                // Field selector:Lio/dekorate/deps/kubernetes/api/model/LabelSelectorBuilder;
     186: aload_2
     187: getfield      #413                // Field selector:Lio/dekorate/deps/kubernetes/api/model/LabelSelectorBuilder;
     190: invokevirtual #457                // Method io/dekorate/deps/kubernetes/api/model/LabelSelectorBuilder.equals:(Ljava/lang/Object;)Z
     193: ifne          208
     196: goto          206
     199: aload_2
     200: getfield      #413                // Field selector:Lio/dekorate/deps/kubernetes/api/model/LabelSelectorBuilder;
     203: ifnull        208
     206: iconst_0
     207: ireturn
     208: iconst_1
     209: ireturn
}
