Compiled from "DoneableInfoItem.java"
public class io.dekorate.deps.applicationcrd.api.model.DoneableInfoItem extends io.dekorate.deps.applicationcrd.api.model.InfoItemFluentImpl<io.dekorate.deps.applicationcrd.api.model.DoneableInfoItem> implements io.dekorate.deps.kubernetes.api.model.Doneable<io.dekorate.deps.applicationcrd.api.model.InfoItem> {
  private final io.dekorate.deps.applicationcrd.api.model.InfoItemBuilder builder;

  private final io.dekorate.deps.kubernetes.api.builder.Function<io.dekorate.deps.applicationcrd.api.model.InfoItem, io.dekorate.deps.applicationcrd.api.model.InfoItem> function;

  public io.dekorate.deps.applicationcrd.api.model.DoneableInfoItem(io.dekorate.deps.kubernetes.api.builder.Function<io.dekorate.deps.applicationcrd.api.model.InfoItem, io.dekorate.deps.applicationcrd.api.model.InfoItem>);
    Code:
       0: aload_0
       1: invokespecial #21                 // Method io/dekorate/deps/applicationcrd/api/model/InfoItemFluentImpl."<init>":()V
       4: aload_0
       5: new           #23                 // class io/dekorate/deps/applicationcrd/api/model/InfoItemBuilder
       8: dup
       9: aload_0
      10: invokespecial #26                 // Method io/dekorate/deps/applicationcrd/api/model/InfoItemBuilder."<init>":(Lio/dekorate/deps/applicationcrd/api/model/InfoItemFluent;)V
      13: putfield      #28                 // Field builder:Lio/dekorate/deps/applicationcrd/api/model/InfoItemBuilder;
      16: aload_0
      17: aload_1
      18: putfield      #30                 // Field function:Lio/dekorate/deps/kubernetes/api/builder/Function;
      21: return

  public io.dekorate.deps.applicationcrd.api.model.DoneableInfoItem(io.dekorate.deps.applicationcrd.api.model.InfoItem, io.dekorate.deps.kubernetes.api.builder.Function<io.dekorate.deps.applicationcrd.api.model.InfoItem, io.dekorate.deps.applicationcrd.api.model.InfoItem>);
    Code:
       0: aload_0
       1: aload_1
       2: invokespecial #37                 // Method io/dekorate/deps/applicationcrd/api/model/InfoItemFluentImpl."<init>":(Lio/dekorate/deps/applicationcrd/api/model/InfoItem;)V
       5: aload_0
       6: new           #23                 // class io/dekorate/deps/applicationcrd/api/model/InfoItemBuilder
       9: dup
      10: aload_0
      11: aload_1
      12: invokespecial #40                 // Method io/dekorate/deps/applicationcrd/api/model/InfoItemBuilder."<init>":(Lio/dekorate/deps/applicationcrd/api/model/InfoItemFluent;Lio/dekorate/deps/applicationcrd/api/model/InfoItem;)V
      15: putfield      #28                 // Field builder:Lio/dekorate/deps/applicationcrd/api/model/InfoItemBuilder;
      18: aload_0
      19: aload_2
      20: putfield      #30                 // Field function:Lio/dekorate/deps/kubernetes/api/builder/Function;
      23: return

  public io.dekorate.deps.applicationcrd.api.model.DoneableInfoItem(io.dekorate.deps.applicationcrd.api.model.InfoItem);
    Code:
       0: aload_0
       1: aload_1
       2: invokespecial #37                 // Method io/dekorate/deps/applicationcrd/api/model/InfoItemFluentImpl."<init>":(Lio/dekorate/deps/applicationcrd/api/model/InfoItem;)V
       5: aload_0
       6: new           #23                 // class io/dekorate/deps/applicationcrd/api/model/InfoItemBuilder
       9: dup
      10: aload_0
      11: aload_1
      12: invokespecial #40                 // Method io/dekorate/deps/applicationcrd/api/model/InfoItemBuilder."<init>":(Lio/dekorate/deps/applicationcrd/api/model/InfoItemFluent;Lio/dekorate/deps/applicationcrd/api/model/InfoItem;)V
      15: putfield      #28                 // Field builder:Lio/dekorate/deps/applicationcrd/api/model/InfoItemBuilder;
      18: aload_0
      19: new           #10                 // class io/dekorate/deps/applicationcrd/api/model/DoneableInfoItem$1
      22: dup
      23: aload_0
      24: invokespecial #45                 // Method io/dekorate/deps/applicationcrd/api/model/DoneableInfoItem$1."<init>":(Lio/dekorate/deps/applicationcrd/api/model/DoneableInfoItem;)V
      27: putfield      #30                 // Field function:Lio/dekorate/deps/kubernetes/api/builder/Function;
      30: return

  public io.dekorate.deps.applicationcrd.api.model.InfoItem done();
    Code:
       0: aload_0
       1: getfield      #30                 // Field function:Lio/dekorate/deps/kubernetes/api/builder/Function;
       4: aload_0
       5: getfield      #28                 // Field builder:Lio/dekorate/deps/applicationcrd/api/model/InfoItemBuilder;
       8: invokevirtual #50                 // Method io/dekorate/deps/applicationcrd/api/model/InfoItemBuilder.build:()Lio/dekorate/deps/applicationcrd/api/model/InfoItem;
      11: invokeinterface #56,  2           // InterfaceMethod io/dekorate/deps/kubernetes/api/builder/Function.apply:(Ljava/lang/Object;)Ljava/lang/Object;
      16: checkcast     #58                 // class io/dekorate/deps/applicationcrd/api/model/InfoItem
      19: areturn

  public java.lang.Object done();
    Code:
       0: aload_0
       1: invokevirtual #61                 // Method done:()Lio/dekorate/deps/applicationcrd/api/model/InfoItem;
       4: areturn
}
