Compiled from "ThreadsParser2_0.java"
public class org.jboss.as.threads.ThreadsParser2_0 extends org.jboss.as.controller.PersistentResourceXMLParser {
  static final org.jboss.as.threads.ThreadsParser2_0 INSTANCE;

  public static final org.jboss.as.controller.PersistentResourceXMLDescription$PersistentResourceXMLBuilder THREAD_FACTORY_PARSER;

  private static final org.jboss.as.controller.PersistentResourceXMLDescription xmlDescription;

  public org.jboss.as.threads.ThreadsParser2_0();
    Code:
       0: aload_0
       1: invokespecial #1                  // Method org/jboss/as/controller/PersistentResourceXMLParser."<init>":()V
       4: return

  public org.jboss.as.controller.PersistentResourceXMLDescription getParserDescription();
    Code:
       0: getstatic     #2                  // Field xmlDescription:Lorg/jboss/as/controller/PersistentResourceXMLDescription;
       3: areturn

  public static org.jboss.as.controller.PersistentResourceXMLDescription$PersistentResourceXMLBuilder getThreadFactoryParser(org.jboss.as.threads.ThreadFactoryResourceDefinition);
    Code:
       0: aload_0
       1: invokestatic  #3                  // Method org/jboss/as/controller/PersistentResourceXMLDescription.builder:(Lorg/jboss/as/controller/PersistentResourceDefinition;)Lorg/jboss/as/controller/PersistentResourceXMLDescription$PersistentResourceXMLBuilder;
       4: iconst_3
       5: anewarray     #4                  // class org/jboss/as/controller/AttributeDefinition
       8: dup
       9: iconst_0
      10: getstatic     #5                  // Field org/jboss/as/threads/PoolAttributeDefinitions.GROUP_NAME:Lorg/jboss/as/controller/SimpleAttributeDefinition;
      13: aastore
      14: dup
      15: iconst_1
      16: getstatic     #6                  // Field org/jboss/as/threads/PoolAttributeDefinitions.THREAD_NAME_PATTERN:Lorg/jboss/as/controller/SimpleAttributeDefinition;
      19: aastore
      20: dup
      21: iconst_2
      22: getstatic     #7                  // Field org/jboss/as/threads/PoolAttributeDefinitions.PRIORITY:Lorg/jboss/as/controller/SimpleAttributeDefinition;
      25: aastore
      26: invokevirtual #8                  // Method org/jboss/as/controller/PersistentResourceXMLDescription$PersistentResourceXMLBuilder.addAttributes:([Lorg/jboss/as/controller/AttributeDefinition;)Lorg/jboss/as/controller/PersistentResourceXMLDescription$PersistentResourceXMLBuilder;
      29: areturn

  public static org.jboss.as.controller.PersistentResourceXMLDescription$PersistentResourceXMLBuilder getUnboundedQueueThreadPoolParser(org.jboss.as.threads.UnboundedQueueThreadPoolResourceDefinition);
    Code:
       0: aload_0
       1: invokestatic  #3                  // Method org/jboss/as/controller/PersistentResourceXMLDescription.builder:(Lorg/jboss/as/controller/PersistentResourceDefinition;)Lorg/jboss/as/controller/PersistentResourceXMLDescription$PersistentResourceXMLBuilder;
       4: iconst_3
       5: anewarray     #4                  // class org/jboss/as/controller/AttributeDefinition
       8: dup
       9: iconst_0
      10: getstatic     #9                  // Field org/jboss/as/threads/PoolAttributeDefinitions.KEEPALIVE_TIME:Lorg/jboss/as/threads/KeepAliveTimeAttributeDefinition;
      13: aastore
      14: dup
      15: iconst_1
      16: getstatic     #10                 // Field org/jboss/as/threads/PoolAttributeDefinitions.MAX_THREADS:Lorg/jboss/as/controller/SimpleAttributeDefinition;
      19: aastore
      20: dup
      21: iconst_2
      22: getstatic     #11                 // Field org/jboss/as/threads/PoolAttributeDefinitions.THREAD_FACTORY:Lorg/jboss/as/controller/SimpleAttributeDefinition;
      25: aastore
      26: invokevirtual #8                  // Method org/jboss/as/controller/PersistentResourceXMLDescription$PersistentResourceXMLBuilder.addAttributes:([Lorg/jboss/as/controller/AttributeDefinition;)Lorg/jboss/as/controller/PersistentResourceXMLDescription$PersistentResourceXMLBuilder;
      29: areturn

  public static org.jboss.as.controller.PersistentResourceXMLDescription$PersistentResourceXMLBuilder getScheduledThreadPoolParser(org.jboss.as.threads.ScheduledThreadPoolResourceDefinition);
    Code:
       0: aload_0
       1: invokestatic  #3                  // Method org/jboss/as/controller/PersistentResourceXMLDescription.builder:(Lorg/jboss/as/controller/PersistentResourceDefinition;)Lorg/jboss/as/controller/PersistentResourceXMLDescription$PersistentResourceXMLBuilder;
       4: iconst_3
       5: anewarray     #4                  // class org/jboss/as/controller/AttributeDefinition
       8: dup
       9: iconst_0
      10: getstatic     #9                  // Field org/jboss/as/threads/PoolAttributeDefinitions.KEEPALIVE_TIME:Lorg/jboss/as/threads/KeepAliveTimeAttributeDefinition;
      13: aastore
      14: dup
      15: iconst_1
      16: getstatic     #10                 // Field org/jboss/as/threads/PoolAttributeDefinitions.MAX_THREADS:Lorg/jboss/as/controller/SimpleAttributeDefinition;
      19: aastore
      20: dup
      21: iconst_2
      22: getstatic     #11                 // Field org/jboss/as/threads/PoolAttributeDefinitions.THREAD_FACTORY:Lorg/jboss/as/controller/SimpleAttributeDefinition;
      25: aastore
      26: invokevirtual #8                  // Method org/jboss/as/controller/PersistentResourceXMLDescription$PersistentResourceXMLBuilder.addAttributes:([Lorg/jboss/as/controller/AttributeDefinition;)Lorg/jboss/as/controller/PersistentResourceXMLDescription$PersistentResourceXMLBuilder;
      29: areturn

  public static org.jboss.as.controller.PersistentResourceXMLDescription$PersistentResourceXMLBuilder getQueuelessThreadPoolParser(org.jboss.as.threads.QueuelessThreadPoolResourceDefinition);
    Code:
       0: aload_0
       1: invokestatic  #3                  // Method org/jboss/as/controller/PersistentResourceXMLDescription.builder:(Lorg/jboss/as/controller/PersistentResourceDefinition;)Lorg/jboss/as/controller/PersistentResourceXMLDescription$PersistentResourceXMLBuilder;
       4: iconst_3
       5: anewarray     #4                  // class org/jboss/as/controller/AttributeDefinition
       8: dup
       9: iconst_0
      10: getstatic     #9                  // Field org/jboss/as/threads/PoolAttributeDefinitions.KEEPALIVE_TIME:Lorg/jboss/as/threads/KeepAliveTimeAttributeDefinition;
      13: aastore
      14: dup
      15: iconst_1
      16: getstatic     #10                 // Field org/jboss/as/threads/PoolAttributeDefinitions.MAX_THREADS:Lorg/jboss/as/controller/SimpleAttributeDefinition;
      19: aastore
      20: dup
      21: iconst_2
      22: getstatic     #11                 // Field org/jboss/as/threads/PoolAttributeDefinitions.THREAD_FACTORY:Lorg/jboss/as/controller/SimpleAttributeDefinition;
      25: aastore
      26: invokevirtual #8                  // Method org/jboss/as/controller/PersistentResourceXMLDescription$PersistentResourceXMLBuilder.addAttributes:([Lorg/jboss/as/controller/AttributeDefinition;)Lorg/jboss/as/controller/PersistentResourceXMLDescription$PersistentResourceXMLBuilder;
      29: astore_1
      30: aload_0
      31: invokevirtual #12                 // Method org/jboss/as/threads/QueuelessThreadPoolResourceDefinition.isBlocking:()Z
      34: ifne          45
      37: aload_1
      38: getstatic     #13                 // Field org/jboss/as/threads/PoolAttributeDefinitions.HANDOFF_EXECUTOR:Lorg/jboss/as/controller/SimpleAttributeDefinition;
      41: invokevirtual #14                 // Method org/jboss/as/controller/PersistentResourceXMLDescription$PersistentResourceXMLBuilder.addAttribute:(Lorg/jboss/as/controller/AttributeDefinition;)Lorg/jboss/as/controller/PersistentResourceXMLDescription$PersistentResourceXMLBuilder;
      44: pop
      45: aload_1
      46: areturn

  public static org.jboss.as.controller.PersistentResourceXMLDescription$PersistentResourceXMLBuilder getBoundedQueueThreadPoolParser(org.jboss.as.threads.BoundedQueueThreadPoolResourceDefinition);
    Code:
       0: aload_0
       1: invokestatic  #3                  // Method org/jboss/as/controller/PersistentResourceXMLDescription.builder:(Lorg/jboss/as/controller/PersistentResourceDefinition;)Lorg/jboss/as/controller/PersistentResourceXMLDescription$PersistentResourceXMLBuilder;
       4: bipush        6
       6: anewarray     #4                  // class org/jboss/as/controller/AttributeDefinition
       9: dup
      10: iconst_0
      11: getstatic     #9                  // Field org/jboss/as/threads/PoolAttributeDefinitions.KEEPALIVE_TIME:Lorg/jboss/as/threads/KeepAliveTimeAttributeDefinition;
      14: aastore
      15: dup
      16: iconst_1
      17: getstatic     #10                 // Field org/jboss/as/threads/PoolAttributeDefinitions.MAX_THREADS:Lorg/jboss/as/controller/SimpleAttributeDefinition;
      20: aastore
      21: dup
      22: iconst_2
      23: getstatic     #11                 // Field org/jboss/as/threads/PoolAttributeDefinitions.THREAD_FACTORY:Lorg/jboss/as/controller/SimpleAttributeDefinition;
      26: aastore
      27: dup
      28: iconst_3
      29: getstatic     #15                 // Field org/jboss/as/threads/PoolAttributeDefinitions.CORE_THREADS:Lorg/jboss/as/controller/SimpleAttributeDefinition;
      32: aastore
      33: dup
      34: iconst_4
      35: getstatic     #16                 // Field org/jboss/as/threads/PoolAttributeDefinitions.QUEUE_LENGTH:Lorg/jboss/as/controller/SimpleAttributeDefinition;
      38: aastore
      39: dup
      40: iconst_5
      41: getstatic     #17                 // Field org/jboss/as/threads/PoolAttributeDefinitions.ALLOW_CORE_TIMEOUT:Lorg/jboss/as/controller/SimpleAttributeDefinition;
      44: aastore
      45: invokevirtual #8                  // Method org/jboss/as/controller/PersistentResourceXMLDescription$PersistentResourceXMLBuilder.addAttributes:([Lorg/jboss/as/controller/AttributeDefinition;)Lorg/jboss/as/controller/PersistentResourceXMLDescription$PersistentResourceXMLBuilder;
      48: astore_1
      49: aload_0
      50: invokevirtual #18                 // Method org/jboss/as/threads/BoundedQueueThreadPoolResourceDefinition.isBlocking:()Z
      53: ifne          64
      56: aload_1
      57: getstatic     #13                 // Field org/jboss/as/threads/PoolAttributeDefinitions.HANDOFF_EXECUTOR:Lorg/jboss/as/controller/SimpleAttributeDefinition;
      60: invokevirtual #14                 // Method org/jboss/as/controller/PersistentResourceXMLDescription$PersistentResourceXMLBuilder.addAttribute:(Lorg/jboss/as/controller/AttributeDefinition;)Lorg/jboss/as/controller/PersistentResourceXMLDescription$PersistentResourceXMLBuilder;
      63: pop
      64: aload_1
      65: areturn

  static {};
    Code:
       0: new           #19                 // class org/jboss/as/threads/ThreadsParser2_0
       3: dup
       4: invokespecial #20                 // Method "<init>":()V
       7: putstatic     #21                 // Field INSTANCE:Lorg/jboss/as/threads/ThreadsParser2_0;
      10: getstatic     #22                 // Field org/jboss/as/threads/ThreadFactoryResourceDefinition.DEFAULT_INSTANCE:Lorg/jboss/as/threads/ThreadFactoryResourceDefinition;
      13: invokestatic  #23                 // Method getThreadFactoryParser:(Lorg/jboss/as/threads/ThreadFactoryResourceDefinition;)Lorg/jboss/as/controller/PersistentResourceXMLDescription$PersistentResourceXMLBuilder;
      16: putstatic     #24                 // Field THREAD_FACTORY_PARSER:Lorg/jboss/as/controller/PersistentResourceXMLDescription$PersistentResourceXMLBuilder;
      19: new           #25                 // class org/jboss/as/threads/ThreadSubsystemResourceDefinition
      22: dup
      23: iconst_0
      24: invokespecial #26                 // Method org/jboss/as/threads/ThreadSubsystemResourceDefinition."<init>":(Z)V
      27: getstatic     #27                 // Field org/jboss/as/threads/Namespace.CURRENT:Lorg/jboss/as/threads/Namespace;
      30: invokevirtual #28                 // Method org/jboss/as/threads/Namespace.getUriString:()Ljava/lang/String;
      33: invokestatic  #29                 // Method org/jboss/as/controller/PersistentResourceXMLDescription.builder:(Lorg/jboss/as/controller/PersistentResourceDefinition;Ljava/lang/String;)Lorg/jboss/as/controller/PersistentResourceXMLDescription$PersistentResourceXMLBuilder;
      36: getstatic     #24                 // Field THREAD_FACTORY_PARSER:Lorg/jboss/as/controller/PersistentResourceXMLDescription$PersistentResourceXMLBuilder;
      39: invokevirtual #30                 // Method org/jboss/as/controller/PersistentResourceXMLDescription$PersistentResourceXMLBuilder.addChild:(Lorg/jboss/as/controller/PersistentResourceXMLDescription$PersistentResourceXMLBuilder;)Lorg/jboss/as/controller/PersistentResourceXMLDescription$PersistentResourceXMLBuilder;
      42: iconst_0
      43: invokestatic  #31                 // Method org/jboss/as/threads/UnboundedQueueThreadPoolResourceDefinition.create:(Z)Lorg/jboss/as/threads/UnboundedQueueThreadPoolResourceDefinition;
      46: invokestatic  #32                 // Method getUnboundedQueueThreadPoolParser:(Lorg/jboss/as/threads/UnboundedQueueThreadPoolResourceDefinition;)Lorg/jboss/as/controller/PersistentResourceXMLDescription$PersistentResourceXMLBuilder;
      49: invokevirtual #30                 // Method org/jboss/as/controller/PersistentResourceXMLDescription$PersistentResourceXMLBuilder.addChild:(Lorg/jboss/as/controller/PersistentResourceXMLDescription$PersistentResourceXMLBuilder;)Lorg/jboss/as/controller/PersistentResourceXMLDescription$PersistentResourceXMLBuilder;
      52: iconst_0
      53: iconst_0
      54: invokestatic  #33                 // Method org/jboss/as/threads/BoundedQueueThreadPoolResourceDefinition.create:(ZZ)Lorg/jboss/as/threads/BoundedQueueThreadPoolResourceDefinition;
      57: invokestatic  #34                 // Method getBoundedQueueThreadPoolParser:(Lorg/jboss/as/threads/BoundedQueueThreadPoolResourceDefinition;)Lorg/jboss/as/controller/PersistentResourceXMLDescription$PersistentResourceXMLBuilder;
      60: invokevirtual #30                 // Method org/jboss/as/controller/PersistentResourceXMLDescription$PersistentResourceXMLBuilder.addChild:(Lorg/jboss/as/controller/PersistentResourceXMLDescription$PersistentResourceXMLBuilder;)Lorg/jboss/as/controller/PersistentResourceXMLDescription$PersistentResourceXMLBuilder;
      63: iconst_1
      64: iconst_0
      65: invokestatic  #33                 // Method org/jboss/as/threads/BoundedQueueThreadPoolResourceDefinition.create:(ZZ)Lorg/jboss/as/threads/BoundedQueueThreadPoolResourceDefinition;
      68: invokestatic  #34                 // Method getBoundedQueueThreadPoolParser:(Lorg/jboss/as/threads/BoundedQueueThreadPoolResourceDefinition;)Lorg/jboss/as/controller/PersistentResourceXMLDescription$PersistentResourceXMLBuilder;
      71: invokevirtual #30                 // Method org/jboss/as/controller/PersistentResourceXMLDescription$PersistentResourceXMLBuilder.addChild:(Lorg/jboss/as/controller/PersistentResourceXMLDescription$PersistentResourceXMLBuilder;)Lorg/jboss/as/controller/PersistentResourceXMLDescription$PersistentResourceXMLBuilder;
      74: iconst_0
      75: iconst_0
      76: invokestatic  #35                 // Method org/jboss/as/threads/QueuelessThreadPoolResourceDefinition.create:(ZZ)Lorg/jboss/as/threads/QueuelessThreadPoolResourceDefinition;
      79: invokestatic  #36                 // Method getQueuelessThreadPoolParser:(Lorg/jboss/as/threads/QueuelessThreadPoolResourceDefinition;)Lorg/jboss/as/controller/PersistentResourceXMLDescription$PersistentResourceXMLBuilder;
      82: invokevirtual #30                 // Method org/jboss/as/controller/PersistentResourceXMLDescription$PersistentResourceXMLBuilder.addChild:(Lorg/jboss/as/controller/PersistentResourceXMLDescription$PersistentResourceXMLBuilder;)Lorg/jboss/as/controller/PersistentResourceXMLDescription$PersistentResourceXMLBuilder;
      85: iconst_1
      86: iconst_0
      87: invokestatic  #35                 // Method org/jboss/as/threads/QueuelessThreadPoolResourceDefinition.create:(ZZ)Lorg/jboss/as/threads/QueuelessThreadPoolResourceDefinition;
      90: invokestatic  #36                 // Method getQueuelessThreadPoolParser:(Lorg/jboss/as/threads/QueuelessThreadPoolResourceDefinition;)Lorg/jboss/as/controller/PersistentResourceXMLDescription$PersistentResourceXMLBuilder;
      93: invokevirtual #30                 // Method org/jboss/as/controller/PersistentResourceXMLDescription$PersistentResourceXMLBuilder.addChild:(Lorg/jboss/as/controller/PersistentResourceXMLDescription$PersistentResourceXMLBuilder;)Lorg/jboss/as/controller/PersistentResourceXMLDescription$PersistentResourceXMLBuilder;
      96: iconst_0
      97: invokestatic  #37                 // Method org/jboss/as/threads/ScheduledThreadPoolResourceDefinition.create:(Z)Lorg/jboss/as/threads/ScheduledThreadPoolResourceDefinition;
     100: invokestatic  #38                 // Method getScheduledThreadPoolParser:(Lorg/jboss/as/threads/ScheduledThreadPoolResourceDefinition;)Lorg/jboss/as/controller/PersistentResourceXMLDescription$PersistentResourceXMLBuilder;
     103: invokevirtual #30                 // Method org/jboss/as/controller/PersistentResourceXMLDescription$PersistentResourceXMLBuilder.addChild:(Lorg/jboss/as/controller/PersistentResourceXMLDescription$PersistentResourceXMLBuilder;)Lorg/jboss/as/controller/PersistentResourceXMLDescription$PersistentResourceXMLBuilder;
     106: invokevirtual #39                 // Method org/jboss/as/controller/PersistentResourceXMLDescription$PersistentResourceXMLBuilder.build:()Lorg/jboss/as/controller/PersistentResourceXMLDescription;
     109: putstatic     #2                  // Field xmlDescription:Lorg/jboss/as/controller/PersistentResourceXMLDescription;
     112: return
}
