Compiled from "Adjuster.scala"
public class io.udash.rest.openapi.adjusters.adjustParameter extends scala.annotation.Annotation implements io.udash.rest.openapi.adjusters.ParameterAdjuster {
  private final scala.Function1<io.udash.rest.openapi.Parameter, io.udash.rest.openapi.Parameter> f;

  public io.udash.rest.openapi.Parameter adjustParameter(io.udash.rest.openapi.Parameter);
    Code:
       0: aload_0
       1: getfield      #18                 // Field f:Lscala/Function1;
       4: aload_1
       5: invokeinterface #24,  2           // InterfaceMethod scala/Function1.apply:(Ljava/lang/Object;)Ljava/lang/Object;
      10: checkcast     #26                 // class io/udash/rest/openapi/Parameter
      13: areturn

  public io.udash.rest.openapi.adjusters.adjustParameter(scala.Function1<io.udash.rest.openapi.Parameter, io.udash.rest.openapi.Parameter>);
    Code:
       0: aload_0
       1: aload_1
       2: putfield      #18                 // Field f:Lscala/Function1;
       5: aload_0
       6: invokespecial #35                 // Method scala/annotation/Annotation."<init>":()V
       9: return
}
