Compiled from "NodeValueLang.java"
public class org.apache.jena.sparql.expr.nodevalue.NodeValueLang extends org.apache.jena.sparql.expr.NodeValue {
  private final java.lang.String string;

  private final java.lang.String lang;

  public org.apache.jena.sparql.expr.nodevalue.NodeValueLang(java.lang.String, java.lang.String);
    Code:
       0: aload_0
       1: invokespecial #1                  // Method org/apache/jena/sparql/expr/NodeValue."<init>":()V
       4: aload_0
       5: aload_1
       6: invokestatic  #2                  // Method java/util/Objects.requireNonNull:(Ljava/lang/Object;)Ljava/lang/Object;
       9: checkcast     #3                  // class java/lang/String
      12: putfield      #4                  // Field string:Ljava/lang/String;
      15: aload_0
      16: aload_2
      17: invokestatic  #2                  // Method java/util/Objects.requireNonNull:(Ljava/lang/Object;)Ljava/lang/Object;
      20: checkcast     #3                  // class java/lang/String
      23: putfield      #5                  // Field lang:Ljava/lang/String;
      26: aload_2
      27: invokevirtual #6                  // Method java/lang/String.isEmpty:()Z
      30: ifeq          43
      33: new           #7                  // class java/lang/IllegalArgumentException
      36: dup
      37: ldc           #8                  // String lang is the empty string
      39: invokespecial #9                  // Method java/lang/IllegalArgumentException."<init>":(Ljava/lang/String;)V
      42: athrow
      43: return

  public org.apache.jena.sparql.expr.nodevalue.NodeValueLang(org.apache.jena.graph.Node);
    Code:
       0: aload_0
       1: aload_1
       2: invokestatic  #2                  // Method java/util/Objects.requireNonNull:(Ljava/lang/Object;)Ljava/lang/Object;
       5: checkcast     #10                 // class org/apache/jena/graph/Node
       8: invokespecial #11                 // Method org/apache/jena/sparql/expr/NodeValue."<init>":(Lorg/apache/jena/graph/Node;)V
      11: aload_0
      12: aload_1
      13: invokevirtual #12                 // Method org/apache/jena/graph/Node.getLiteralLexicalForm:()Ljava/lang/String;
      16: putfield      #4                  // Field string:Ljava/lang/String;
      19: aload_0
      20: aload_1
      21: invokevirtual #13                 // Method org/apache/jena/graph/Node.getLiteralLanguage:()Ljava/lang/String;
      24: putfield      #5                  // Field lang:Ljava/lang/String;
      27: return

  public boolean isLangString();
    Code:
       0: iconst_1
       1: ireturn

  public java.lang.String getString();
    Code:
       0: aload_0
       1: getfield      #4                  // Field string:Ljava/lang/String;
       4: areturn

  public java.lang.String getLang();
    Code:
       0: aload_0
       1: getfield      #5                  // Field lang:Ljava/lang/String;
       4: areturn

  public java.lang.String asString();
    Code:
       0: aload_0
       1: getfield      #4                  // Field string:Ljava/lang/String;
       4: areturn

  protected org.apache.jena.graph.Node makeNode();
    Code:
       0: aload_0
       1: getfield      #4                  // Field string:Ljava/lang/String;
       4: aload_0
       5: getfield      #5                  // Field lang:Ljava/lang/String;
       8: invokestatic  #14                 // Method org/apache/jena/graph/NodeFactory.createLiteral:(Ljava/lang/String;Ljava/lang/String;)Lorg/apache/jena/graph/Node;
      11: areturn

  public java.lang.String toString();
    Code:
       0: aload_0
       1: invokevirtual #15                 // Method getNode:()Lorg/apache/jena/graph/Node;
       4: ifnull        15
       7: aload_0
       8: invokevirtual #15                 // Method getNode:()Lorg/apache/jena/graph/Node;
      11: invokestatic  #16                 // Method org/apache/jena/sparql/util/FmtUtils.stringForNode:(Lorg/apache/jena/graph/Node;)Ljava/lang/String;
      14: areturn
      15: new           #17                 // class java/lang/StringBuilder
      18: dup
      19: invokespecial #18                 // Method java/lang/StringBuilder."<init>":()V
      22: ldc           #19                 // String \'
      24: invokevirtual #20                 // Method java/lang/StringBuilder.append:(Ljava/lang/String;)Ljava/lang/StringBuilder;
      27: aload_0
      28: invokevirtual #21                 // Method getString:()Ljava/lang/String;
      31: invokevirtual #20                 // Method java/lang/StringBuilder.append:(Ljava/lang/String;)Ljava/lang/StringBuilder;
      34: ldc           #22                 // String \'@
      36: invokevirtual #20                 // Method java/lang/StringBuilder.append:(Ljava/lang/String;)Ljava/lang/StringBuilder;
      39: aload_0
      40: getfield      #5                  // Field lang:Ljava/lang/String;
      43: invokevirtual #20                 // Method java/lang/StringBuilder.append:(Ljava/lang/String;)Ljava/lang/StringBuilder;
      46: invokevirtual #23                 // Method java/lang/StringBuilder.toString:()Ljava/lang/String;
      49: areturn

  public void visit(org.apache.jena.sparql.expr.nodevalue.NodeValueVisitor);
    Code:
       0: aload_1
       1: aload_0
       2: invokeinterface #24,  2           // InterfaceMethod org/apache/jena/sparql/expr/nodevalue/NodeValueVisitor.visit:(Lorg/apache/jena/sparql/expr/nodevalue/NodeValueLang;)V
       7: return
}
