Compiled from "package.scala"
public final class morphir.ir.fuzzer.package$ {
  public static final morphir.ir.fuzzer.package$ MODULE$;

  private static final zio.test.Gen$ Fuzzer;

  private static volatile byte bitmap$init$0;

  public static {};
    Code:
       0: new           #2                  // class morphir/ir/fuzzer/package$
       3: dup
       4: invokespecial #16                 // Method "<init>":()V
       7: putstatic     #18                 // Field MODULE$:Lmorphir/ir/fuzzer/package$;
      10: getstatic     #22                 // Field zio/test/Gen$.MODULE$:Lzio/test/Gen$;
      13: putstatic     #24                 // Field Fuzzer:Lzio/test/Gen$;
      16: getstatic     #26                 // Field bitmap$init$0:B
      19: iconst_1
      20: ior
      21: i2b
      22: putstatic     #26                 // Field bitmap$init$0:B
      25: return

  public zio.test.Gen$ Fuzzer();
    Code:
       0: getstatic     #26                 // Field bitmap$init$0:B
       3: iconst_1
       4: iand
       5: i2b
       6: iconst_0
       7: if_icmpeq     16
      10: getstatic     #24                 // Field Fuzzer:Lzio/test/Gen$;
      13: goto          26
      16: new           #29                 // class scala/UninitializedFieldError
      19: dup
      20: ldc           #31                 // String Uninitialized field: /home/runner/work/morphir-jvm/morphir-jvm/morphir/ir/src/morphir/ir/fuzzer/package.scala: 25
      22: invokespecial #34                 // Method scala/UninitializedFieldError."<init>":(Ljava/lang/String;)V
      25: athrow
      26: pop
      27: getstatic     #24                 // Field Fuzzer:Lzio/test/Gen$;
      30: areturn

  private morphir.ir.fuzzer.package$();
    Code:
       0: aload_0
       1: invokespecial #36                 // Method java/lang/Object."<init>":()V
       4: return
}
