Compiled from "LegacyHierarchicalLedgerManager.java"
class org.apache.bookkeeper.meta.LegacyHierarchicalLedgerManager$2$1 implements org.apache.bookkeeper.proto.BookkeeperInternalCallbacks$Processor<java.lang.String> {
  final java.lang.String val$l1Node;

  final org.apache.bookkeeper.meta.LegacyHierarchicalLedgerManager$2 this$1;

  org.apache.bookkeeper.meta.LegacyHierarchicalLedgerManager$2$1(org.apache.bookkeeper.meta.LegacyHierarchicalLedgerManager$2, java.lang.String);
    Code:
       0: aload_0
       1: aload_1
       2: putfield      #1                  // Field this$1:Lorg/apache/bookkeeper/meta/LegacyHierarchicalLedgerManager$2;
       5: aload_0
       6: aload_2
       7: putfield      #2                  // Field val$l1Node:Ljava/lang/String;
      10: aload_0
      11: invokespecial #3                  // Method java/lang/Object."<init>":()V
      14: return

  public void process(java.lang.String, org.apache.zookeeper.AsyncCallback$VoidCallback);
    Code:
       0: new           #4                  // class java/lang/StringBuilder
       3: dup
       4: invokespecial #5                  // Method java/lang/StringBuilder."<init>":()V
       7: aload_0
       8: getfield      #1                  // Field this$1:Lorg/apache/bookkeeper/meta/LegacyHierarchicalLedgerManager$2;
      11: getfield      #6                  // Field org/apache/bookkeeper/meta/LegacyHierarchicalLedgerManager$2.this$0:Lorg/apache/bookkeeper/meta/LegacyHierarchicalLedgerManager;
      14: getfield      #7                  // Field org/apache/bookkeeper/meta/LegacyHierarchicalLedgerManager.ledgerRootPath:Ljava/lang/String;
      17: invokevirtual #8                  // Method java/lang/StringBuilder.append:(Ljava/lang/String;)Ljava/lang/StringBuilder;
      20: ldc           #9                  // String /
      22: invokevirtual #8                  // Method java/lang/StringBuilder.append:(Ljava/lang/String;)Ljava/lang/StringBuilder;
      25: aload_0
      26: getfield      #2                  // Field val$l1Node:Ljava/lang/String;
      29: invokevirtual #8                  // Method java/lang/StringBuilder.append:(Ljava/lang/String;)Ljava/lang/StringBuilder;
      32: ldc           #9                  // String /
      34: invokevirtual #8                  // Method java/lang/StringBuilder.append:(Ljava/lang/String;)Ljava/lang/StringBuilder;
      37: aload_1
      38: invokevirtual #8                  // Method java/lang/StringBuilder.append:(Ljava/lang/String;)Ljava/lang/StringBuilder;
      41: invokevirtual #10                 // Method java/lang/StringBuilder.toString:()Ljava/lang/String;
      44: astore_3
      45: aload_0
      46: getfield      #1                  // Field this$1:Lorg/apache/bookkeeper/meta/LegacyHierarchicalLedgerManager$2;
      49: getfield      #6                  // Field org/apache/bookkeeper/meta/LegacyHierarchicalLedgerManager$2.this$0:Lorg/apache/bookkeeper/meta/LegacyHierarchicalLedgerManager;
      52: aload_3
      53: aload_0
      54: getfield      #1                  // Field this$1:Lorg/apache/bookkeeper/meta/LegacyHierarchicalLedgerManager$2;
      57: getfield      #11                 // Field org/apache/bookkeeper/meta/LegacyHierarchicalLedgerManager$2.val$processor:Lorg/apache/bookkeeper/proto/BookkeeperInternalCallbacks$Processor;
      60: aload_2
      61: aload_0
      62: getfield      #1                  // Field this$1:Lorg/apache/bookkeeper/meta/LegacyHierarchicalLedgerManager$2;
      65: getfield      #12                 // Field org/apache/bookkeeper/meta/LegacyHierarchicalLedgerManager$2.val$context:Ljava/lang/Object;
      68: aload_0
      69: getfield      #1                  // Field this$1:Lorg/apache/bookkeeper/meta/LegacyHierarchicalLedgerManager$2;
      72: getfield      #13                 // Field org/apache/bookkeeper/meta/LegacyHierarchicalLedgerManager$2.val$successRc:I
      75: aload_0
      76: getfield      #1                  // Field this$1:Lorg/apache/bookkeeper/meta/LegacyHierarchicalLedgerManager$2;
      79: getfield      #14                 // Field org/apache/bookkeeper/meta/LegacyHierarchicalLedgerManager$2.val$failureRc:I
      82: invokevirtual #15                 // Method org/apache/bookkeeper/meta/LegacyHierarchicalLedgerManager.asyncProcessLedgersInSingleNode:(Ljava/lang/String;Lorg/apache/bookkeeper/proto/BookkeeperInternalCallbacks$Processor;Lorg/apache/zookeeper/AsyncCallback$VoidCallback;Ljava/lang/Object;II)V
      85: return

  public void process(java.lang.Object, org.apache.zookeeper.AsyncCallback$VoidCallback);
    Code:
       0: aload_0
       1: aload_1
       2: checkcast     #16                 // class java/lang/String
       5: aload_2
       6: invokevirtual #17                 // Method process:(Ljava/lang/String;Lorg/apache/zookeeper/AsyncCallback$VoidCallback;)V
       9: return
}
