class nu.xom.jaxen.expr.DefaultDivExpr extends nu.xom.jaxen.expr.DefaultMultiplicativeExpr {
  private static final long serialVersionUID;

  nu.xom.jaxen.expr.DefaultDivExpr(nu.xom.jaxen.expr.Expr, nu.xom.jaxen.expr.Expr);
    Code:
       0: aload_0
       1: aload_1
       2: aload_2
       3: invokespecial #12                 // Method nu/xom/jaxen/expr/DefaultMultiplicativeExpr."<init>":(Lnu/xom/jaxen/expr/Expr;Lnu/xom/jaxen/expr/Expr;)V
       6: return

  public java.lang.String getOperator();
    Code:
       0: ldc           #16                 // String div
       2: areturn

  public java.lang.Object evaluate(nu.xom.jaxen.Context) throws nu.xom.jaxen.JaxenException;
    Code:
       0: aload_0
       1: invokevirtual #24                 // Method getLHS:()Lnu/xom/jaxen/expr/Expr;
       4: aload_1
       5: invokeinterface #28,  2           // InterfaceMethod nu/xom/jaxen/expr/Expr.evaluate:(Lnu/xom/jaxen/Context;)Ljava/lang/Object;
      10: aload_1
      11: invokevirtual #34                 // Method nu/xom/jaxen/Context.getNavigator:()Lnu/xom/jaxen/Navigator;
      14: invokestatic  #39                 // Method nu/xom/jaxen/function/NumberFunction.evaluate:(Ljava/lang/Object;Lnu/xom/jaxen/Navigator;)Ljava/lang/Double;
      17: astore_2
      18: aload_0
      19: invokevirtual #42                 // Method getRHS:()Lnu/xom/jaxen/expr/Expr;
      22: aload_1
      23: invokeinterface #28,  2           // InterfaceMethod nu/xom/jaxen/expr/Expr.evaluate:(Lnu/xom/jaxen/Context;)Ljava/lang/Object;
      28: aload_1
      29: invokevirtual #34                 // Method nu/xom/jaxen/Context.getNavigator:()Lnu/xom/jaxen/Navigator;
      32: invokestatic  #39                 // Method nu/xom/jaxen/function/NumberFunction.evaluate:(Ljava/lang/Object;Lnu/xom/jaxen/Navigator;)Ljava/lang/Double;
      35: astore_3
      36: aload_2
      37: invokevirtual #48                 // Method java/lang/Number.doubleValue:()D
      40: aload_3
      41: invokevirtual #48                 // Method java/lang/Number.doubleValue:()D
      44: ddiv
      45: dstore        4
      47: new           #50                 // class java/lang/Double
      50: dup
      51: dload         4
      53: invokespecial #53                 // Method java/lang/Double."<init>":(D)V
      56: areturn
}
