Compiled from "CacheControl.kt"
public final class okhttp3.CacheControl$Companion {
  public final okhttp3.CacheControl parse(okhttp3.Headers);
    Code:
       0: aload_1
       1: ldc           #10                 // String headers
       3: invokestatic  #16                 // Method kotlin/jvm/internal/Intrinsics.checkNotNullParameter:(Ljava/lang/Object;Ljava/lang/String;)V
       6: iconst_0
       7: istore_2
       8: iconst_0
       9: istore_3
      10: iconst_m1
      11: istore        4
      13: iconst_m1
      14: istore        5
      16: iconst_0
      17: istore        6
      19: iconst_0
      20: istore        7
      22: iconst_0
      23: istore        8
      25: iconst_m1
      26: istore        9
      28: iconst_m1
      29: istore        10
      31: iconst_0
      32: istore        11
      34: iconst_0
      35: istore        12
      37: iconst_0
      38: istore        13
      40: iconst_1
      41: istore        14
      43: aconst_null
      44: checkcast     #18                 // class java/lang/String
      47: astore        15
      49: iconst_0
      50: istore        16
      52: aload_1
      53: invokevirtual #24                 // Method okhttp3/Headers.size:()I
      56: istore        17
      58: iload         16
      60: iload         17
      62: if_icmpge     702
      65: aload_1
      66: iload         16
      68: invokevirtual #28                 // Method okhttp3/Headers.name:(I)Ljava/lang/String;
      71: astore        18
      73: aload_1
      74: iload         16
      76: invokevirtual #31                 // Method okhttp3/Headers.value:(I)Ljava/lang/String;
      79: astore        19
      81: nop
      82: aload         18
      84: ldc           #33                 // String Cache-Control
      86: iconst_1
      87: invokestatic  #39                 // Method kotlin/text/StringsKt.equals:(Ljava/lang/String;Ljava/lang/String;Z)Z
      90: ifeq          111
      93: aload         15
      95: ifnull        104
      98: iconst_0
      99: istore        14
     101: goto          131
     104: aload         19
     106: astore        15
     108: goto          131
     111: aload         18
     113: ldc           #41                 // String Pragma
     115: iconst_1
     116: invokestatic  #39                 // Method kotlin/text/StringsKt.equals:(Ljava/lang/String;Ljava/lang/String;Z)Z
     119: ifeq          128
     122: iconst_0
     123: istore        14
     125: goto          131
     128: goto          696
     131: iconst_0
     132: istore        20
     134: iload         20
     136: aload         19
     138: invokevirtual #44                 // Method java/lang/String.length:()I
     141: if_icmpge     696
     144: iload         20
     146: istore        21
     148: aload_0
     149: checkcast     #2                  // class okhttp3/CacheControl$Companion
     152: aload         19
     154: ldc           #46                 // String =,;
     156: iload         20
     158: invokespecial #50                 // Method indexOfElement:(Ljava/lang/String;Ljava/lang/String;I)I
     161: istore        20
     163: aload         19
     165: astore        23
     167: iconst_0
     168: istore        24
     170: aload         23
     172: dup
     173: ifnonnull     186
     176: new           #52                 // class java/lang/NullPointerException
     179: dup
     180: ldc           #54                 // String null cannot be cast to non-null type java.lang.String
     182: invokespecial #58                 // Method java/lang/NullPointerException."<init>":(Ljava/lang/String;)V
     185: athrow
     186: iload         21
     188: iload         20
     190: invokevirtual #62                 // Method java/lang/String.substring:(II)Ljava/lang/String;
     193: dup
     194: ldc           #64                 // String (this as java.lang.Strin…ing(startIndex, endIndex)
     196: invokestatic  #67                 // Method kotlin/jvm/internal/Intrinsics.checkNotNullExpressionValue:(Ljava/lang/Object;Ljava/lang/String;)V
     199: astore        23
     201: iconst_0
     202: istore        24
     204: aload         23
     206: dup
     207: ifnonnull     220
     210: new           #52                 // class java/lang/NullPointerException
     213: dup
     214: ldc           #69                 // String null cannot be cast to non-null type kotlin.CharSequence
     216: invokespecial #58                 // Method java/lang/NullPointerException."<init>":(Ljava/lang/String;)V
     219: athrow
     220: checkcast     #71                 // class java/lang/CharSequence
     223: invokestatic  #75                 // Method kotlin/text/StringsKt.trim:(Ljava/lang/CharSequence;)Ljava/lang/CharSequence;
     226: invokevirtual #79                 // Method java/lang/Object.toString:()Ljava/lang/String;
     229: astore        22
     231: aconst_null
     232: astore        23
     234: iload         20
     236: aload         19
     238: invokevirtual #44                 // Method java/lang/String.length:()I
     241: if_icmpeq     268
     244: aload         19
     246: iload         20
     248: invokevirtual #83                 // Method java/lang/String.charAt:(I)C
     251: bipush        44
     253: if_icmpeq     268
     256: aload         19
     258: iload         20
     260: invokevirtual #83                 // Method java/lang/String.charAt:(I)C
     263: bipush        59
     265: if_icmpne     280
     268: iinc          20, 1
     271: aconst_null
     272: checkcast     #18                 // class java/lang/String
     275: astore        23
     277: goto          469
     280: iinc          20, 1
     283: aload         19
     285: iload         20
     287: invokestatic  #89                 // Method okhttp3/internal/Util.indexOfNonWhitespace:(Ljava/lang/String;I)I
     290: istore        20
     292: iload         20
     294: aload         19
     296: invokevirtual #44                 // Method java/lang/String.length:()I
     299: if_icmpge     382
     302: aload         19
     304: iload         20
     306: invokevirtual #83                 // Method java/lang/String.charAt:(I)C
     309: bipush        34
     311: if_icmpne     382
     314: iinc          20, 1
     317: iload         20
     319: istore        24
     321: aload         19
     323: checkcast     #71                 // class java/lang/CharSequence
     326: bipush        34
     328: iload         20
     330: iconst_0
     331: iconst_4
     332: aconst_null
     333: invokestatic  #93                 // Method kotlin/text/StringsKt.indexOf$default:(Ljava/lang/CharSequence;CIZILjava/lang/Object;)I
     336: istore        20
     338: aload         19
     340: astore        25
     342: iconst_0
     343: istore        26
     345: aload         25
     347: dup
     348: ifnonnull     361
     351: new           #52                 // class java/lang/NullPointerException
     354: dup
     355: ldc           #54                 // String null cannot be cast to non-null type java.lang.String
     357: invokespecial #58                 // Method java/lang/NullPointerException."<init>":(Ljava/lang/String;)V
     360: athrow
     361: iload         24
     363: iload         20
     365: invokevirtual #62                 // Method java/lang/String.substring:(II)Ljava/lang/String;
     368: dup
     369: ldc           #64                 // String (this as java.lang.Strin…ing(startIndex, endIndex)
     371: invokestatic  #67                 // Method kotlin/jvm/internal/Intrinsics.checkNotNullExpressionValue:(Ljava/lang/Object;Ljava/lang/String;)V
     374: astore        23
     376: iinc          20, 1
     379: goto          469
     382: iload         20
     384: istore        24
     386: aload_0
     387: checkcast     #2                  // class okhttp3/CacheControl$Companion
     390: aload         19
     392: ldc           #95                 // String ,;
     394: iload         20
     396: invokespecial #50                 // Method indexOfElement:(Ljava/lang/String;Ljava/lang/String;I)I
     399: istore        20
     401: aload         19
     403: astore        25
     405: iconst_0
     406: istore        26
     408: aload         25
     410: dup
     411: ifnonnull     424
     414: new           #52                 // class java/lang/NullPointerException
     417: dup
     418: ldc           #54                 // String null cannot be cast to non-null type java.lang.String
     420: invokespecial #58                 // Method java/lang/NullPointerException."<init>":(Ljava/lang/String;)V
     423: athrow
     424: iload         24
     426: iload         20
     428: invokevirtual #62                 // Method java/lang/String.substring:(II)Ljava/lang/String;
     431: dup
     432: ldc           #64                 // String (this as java.lang.Strin…ing(startIndex, endIndex)
     434: invokestatic  #67                 // Method kotlin/jvm/internal/Intrinsics.checkNotNullExpressionValue:(Ljava/lang/Object;Ljava/lang/String;)V
     437: astore        25
     439: iconst_0
     440: istore        26
     442: aload         25
     444: dup
     445: ifnonnull     458
     448: new           #52                 // class java/lang/NullPointerException
     451: dup
     452: ldc           #69                 // String null cannot be cast to non-null type kotlin.CharSequence
     454: invokespecial #58                 // Method java/lang/NullPointerException."<init>":(Ljava/lang/String;)V
     457: athrow
     458: checkcast     #71                 // class java/lang/CharSequence
     461: invokestatic  #75                 // Method kotlin/text/StringsKt.trim:(Ljava/lang/CharSequence;)Ljava/lang/CharSequence;
     464: invokevirtual #79                 // Method java/lang/Object.toString:()Ljava/lang/String;
     467: astore        23
     469: nop
     470: ldc           #97                 // String no-cache
     472: aload         22
     474: iconst_1
     475: invokestatic  #39                 // Method kotlin/text/StringsKt.equals:(Ljava/lang/String;Ljava/lang/String;Z)Z
     478: ifeq          486
     481: iconst_1
     482: istore_2
     483: goto          693
     486: ldc           #99                 // String no-store
     488: aload         22
     490: iconst_1
     491: invokestatic  #39                 // Method kotlin/text/StringsKt.equals:(Ljava/lang/String;Ljava/lang/String;Z)Z
     494: ifeq          502
     497: iconst_1
     498: istore_3
     499: goto          693
     502: ldc           #101                // String max-age
     504: aload         22
     506: iconst_1
     507: invokestatic  #39                 // Method kotlin/text/StringsKt.equals:(Ljava/lang/String;Ljava/lang/String;Z)Z
     510: ifeq          524
     513: aload         23
     515: iconst_m1
     516: invokestatic  #104                // Method okhttp3/internal/Util.toNonNegativeInt:(Ljava/lang/String;I)I
     519: istore        4
     521: goto          693
     524: ldc           #106                // String s-maxage
     526: aload         22
     528: iconst_1
     529: invokestatic  #39                 // Method kotlin/text/StringsKt.equals:(Ljava/lang/String;Ljava/lang/String;Z)Z
     532: ifeq          546
     535: aload         23
     537: iconst_m1
     538: invokestatic  #104                // Method okhttp3/internal/Util.toNonNegativeInt:(Ljava/lang/String;I)I
     541: istore        5
     543: goto          693
     546: ldc           #108                // String private
     548: aload         22
     550: iconst_1
     551: invokestatic  #39                 // Method kotlin/text/StringsKt.equals:(Ljava/lang/String;Ljava/lang/String;Z)Z
     554: ifeq          563
     557: iconst_1
     558: istore        6
     560: goto          693
     563: ldc           #110                // String public
     565: aload         22
     567: iconst_1
     568: invokestatic  #39                 // Method kotlin/text/StringsKt.equals:(Ljava/lang/String;Ljava/lang/String;Z)Z
     571: ifeq          580
     574: iconst_1
     575: istore        7
     577: goto          693
     580: ldc           #112                // String must-revalidate
     582: aload         22
     584: iconst_1
     585: invokestatic  #39                 // Method kotlin/text/StringsKt.equals:(Ljava/lang/String;Ljava/lang/String;Z)Z
     588: ifeq          597
     591: iconst_1
     592: istore        8
     594: goto          693
     597: ldc           #114                // String max-stale
     599: aload         22
     601: iconst_1
     602: invokestatic  #39                 // Method kotlin/text/StringsKt.equals:(Ljava/lang/String;Ljava/lang/String;Z)Z
     605: ifeq          620
     608: aload         23
     610: ldc           #115                // int 2147483647
     612: invokestatic  #104                // Method okhttp3/internal/Util.toNonNegativeInt:(Ljava/lang/String;I)I
     615: istore        9
     617: goto          693
     620: ldc           #117                // String min-fresh
     622: aload         22
     624: iconst_1
     625: invokestatic  #39                 // Method kotlin/text/StringsKt.equals:(Ljava/lang/String;Ljava/lang/String;Z)Z
     628: ifeq          642
     631: aload         23
     633: iconst_m1
     634: invokestatic  #104                // Method okhttp3/internal/Util.toNonNegativeInt:(Ljava/lang/String;I)I
     637: istore        10
     639: goto          693
     642: ldc           #119                // String only-if-cached
     644: aload         22
     646: iconst_1
     647: invokestatic  #39                 // Method kotlin/text/StringsKt.equals:(Ljava/lang/String;Ljava/lang/String;Z)Z
     650: ifeq          659
     653: iconst_1
     654: istore        11
     656: goto          693
     659: ldc           #121                // String no-transform
     661: aload         22
     663: iconst_1
     664: invokestatic  #39                 // Method kotlin/text/StringsKt.equals:(Ljava/lang/String;Ljava/lang/String;Z)Z
     667: ifeq          676
     670: iconst_1
     671: istore        12
     673: goto          693
     676: ldc           #123                // String immutable
     678: aload         22
     680: iconst_1
     681: invokestatic  #39                 // Method kotlin/text/StringsKt.equals:(Ljava/lang/String;Ljava/lang/String;Z)Z
     684: ifeq          693
     687: iconst_1
     688: istore        13
     690: goto          693
     693: goto          134
     696: iinc          16, 1
     699: goto          58
     702: iload         14
     704: ifne          713
     707: aconst_null
     708: checkcast     #18                 // class java/lang/String
     711: astore        15
     713: new           #125                // class okhttp3/CacheControl
     716: dup
     717: iload_2
     718: iload_3
     719: iload         4
     721: iload         5
     723: iload         6
     725: iload         7
     727: iload         8
     729: iload         9
     731: iload         10
     733: iload         11
     735: iload         12
     737: iload         13
     739: aload         15
     741: aconst_null
     742: invokespecial #128                // Method okhttp3/CacheControl."<init>":(ZZIIZZZIIZZZLjava/lang/String;Lkotlin/jvm/internal/DefaultConstructorMarker;)V
     745: areturn

  private final int indexOfElement(java.lang.String, java.lang.String, int);
    Code:
       0: iload_3
       1: istore        4
       3: aload_1
       4: invokevirtual #44                 // Method java/lang/String.length:()I
       7: istore        5
       9: iload         4
      11: iload         5
      13: if_icmpge     44
      16: aload_2
      17: checkcast     #71                 // class java/lang/CharSequence
      20: aload_1
      21: iload         4
      23: invokevirtual #83                 // Method java/lang/String.charAt:(I)C
      26: iconst_0
      27: iconst_2
      28: aconst_null
      29: invokestatic  #157                // Method kotlin/text/StringsKt.contains$default:(Ljava/lang/CharSequence;CZILjava/lang/Object;)Z
      32: ifeq          38
      35: iload         4
      37: ireturn
      38: iinc          4, 1
      41: goto          9
      44: aload_1
      45: invokevirtual #44                 // Method java/lang/String.length:()I
      48: ireturn

  static int indexOfElement$default(okhttp3.CacheControl$Companion, java.lang.String, java.lang.String, int, int, java.lang.Object);
    Code:
       0: iload         4
       2: iconst_2
       3: iand
       4: ifeq          9
       7: iconst_0
       8: istore_3
       9: aload_0
      10: aload_1
      11: aload_2
      12: iload_3
      13: invokespecial #50                 // Method indexOfElement:(Ljava/lang/String;Ljava/lang/String;I)I
      16: ireturn

  private okhttp3.CacheControl$Companion();
    Code:
       0: aload_0
       1: invokespecial #165                // Method java/lang/Object."<init>":()V
       4: return

  public okhttp3.CacheControl$Companion(kotlin.jvm.internal.DefaultConstructorMarker);
    Code:
       0: aload_0
       1: invokespecial #167                // Method "<init>":()V
       4: return
}
