Compiled from "ProxyConnection.java"
class org.apache.activemq.proxy.ProxyConnection$1 extends org.apache.activemq.transport.DefaultTransportListener {
  final org.apache.activemq.proxy.ProxyConnection this$0;

  org.apache.activemq.proxy.ProxyConnection$1(org.apache.activemq.proxy.ProxyConnection);
    Code:
       0: aload_0
       1: aload_1
       2: putfield      #1                  // Field this$0:Lorg/apache/activemq/proxy/ProxyConnection;
       5: aload_0
       6: invokespecial #2                  // Method org/apache/activemq/transport/DefaultTransportListener."<init>":()V
       9: return

  public void onCommand(java.lang.Object);
    Code:
       0: iconst_0
       1: istore_2
       2: aload_1
       3: invokevirtual #3                  // Method java/lang/Object.getClass:()Ljava/lang/Class;
       6: ldc_w         #4                  // class org/apache/activemq/command/ShutdownInfo
       9: if_acmpne     25
      12: aload_0
      13: getfield      #1                  // Field this$0:Lorg/apache/activemq/proxy/ProxyConnection;
      16: invokestatic  #5                  // Method org/apache/activemq/proxy/ProxyConnection.access$000:(Lorg/apache/activemq/proxy/ProxyConnection;)Ljava/util/concurrent/atomic/AtomicBoolean;
      19: iconst_1
      20: invokevirtual #6                  // Method java/util/concurrent/atomic/AtomicBoolean.set:(Z)V
      23: iconst_1
      24: istore_2
      25: aload_1
      26: invokevirtual #3                  // Method java/lang/Object.getClass:()Ljava/lang/Class;
      29: ldc_w         #7                  // class org/apache/activemq/command/WireFormatInfo
      32: if_acmpne     36
      35: return
      36: aload_0
      37: getfield      #1                  // Field this$0:Lorg/apache/activemq/proxy/ProxyConnection;
      40: getfield      #8                  // Field org/apache/activemq/proxy/ProxyConnection.remoteTransport:Lorg/apache/activemq/transport/Transport;
      43: aload_1
      44: invokeinterface #9,  2            // InterfaceMethod org/apache/activemq/transport/Transport.oneway:(Ljava/lang/Object;)V
      49: iload_2
      50: ifeq          60
      53: aload_0
      54: getfield      #1                  // Field this$0:Lorg/apache/activemq/proxy/ProxyConnection;
      57: invokevirtual #10                 // Method org/apache/activemq/proxy/ProxyConnection.stop:()V
      60: goto          87
      63: astore_3
      64: aload_0
      65: getfield      #1                  // Field this$0:Lorg/apache/activemq/proxy/ProxyConnection;
      68: aload_3
      69: invokevirtual #12                 // Method org/apache/activemq/proxy/ProxyConnection.onFailure:(Ljava/io/IOException;)V
      72: goto          87
      75: astore_3
      76: aload_0
      77: getfield      #1                  // Field this$0:Lorg/apache/activemq/proxy/ProxyConnection;
      80: aload_3
      81: invokestatic  #14                 // Method org/apache/activemq/util/IOExceptionSupport.create:(Ljava/lang/Exception;)Ljava/io/IOException;
      84: invokevirtual #12                 // Method org/apache/activemq/proxy/ProxyConnection.onFailure:(Ljava/io/IOException;)V
      87: return
    Exception table:
       from    to  target type
          36    60    63   Class java/io/IOException
          36    60    75   Class java/lang/Exception

  public void onException(java.io.IOException);
    Code:
       0: aload_0
       1: getfield      #1                  // Field this$0:Lorg/apache/activemq/proxy/ProxyConnection;
       4: aload_1
       5: invokevirtual #12                 // Method org/apache/activemq/proxy/ProxyConnection.onFailure:(Ljava/io/IOException;)V
       8: return
}
