Compiled from "ExtendedCertificateInfo.java"
public final class org.apache.kerby.cms.type.ExtendedCertificateInfo$ExtendedCertificateInfoField extends java.lang.Enum<org.apache.kerby.cms.type.ExtendedCertificateInfo$ExtendedCertificateInfoField> implements org.apache.kerby.asn1.EnumType {
  public static final org.apache.kerby.cms.type.ExtendedCertificateInfo$ExtendedCertificateInfoField CMS_VERSION;

  public static final org.apache.kerby.cms.type.ExtendedCertificateInfo$ExtendedCertificateInfoField CERTIFICATE;

  public static final org.apache.kerby.cms.type.ExtendedCertificateInfo$ExtendedCertificateInfoField ATTRIBUTES;

  private static final org.apache.kerby.cms.type.ExtendedCertificateInfo$ExtendedCertificateInfoField[] $VALUES;

  public static org.apache.kerby.cms.type.ExtendedCertificateInfo$ExtendedCertificateInfoField[] values();
    Code:
       0: getstatic     #1                  // Field $VALUES:[Lorg/apache/kerby/cms/type/ExtendedCertificateInfo$ExtendedCertificateInfoField;
       3: invokevirtual #2                  // Method "[Lorg/apache/kerby/cms/type/ExtendedCertificateInfo$ExtendedCertificateInfoField;".clone:()Ljava/lang/Object;
       6: checkcast     #3                  // class "[Lorg/apache/kerby/cms/type/ExtendedCertificateInfo$ExtendedCertificateInfoField;"
       9: areturn

  public static org.apache.kerby.cms.type.ExtendedCertificateInfo$ExtendedCertificateInfoField valueOf(java.lang.String);
    Code:
       0: ldc_w         #4                  // class org/apache/kerby/cms/type/ExtendedCertificateInfo$ExtendedCertificateInfoField
       3: aload_0
       4: invokestatic  #5                  // Method java/lang/Enum.valueOf:(Ljava/lang/Class;Ljava/lang/String;)Ljava/lang/Enum;
       7: checkcast     #4                  // class org/apache/kerby/cms/type/ExtendedCertificateInfo$ExtendedCertificateInfoField
      10: areturn

  private org.apache.kerby.cms.type.ExtendedCertificateInfo$ExtendedCertificateInfoField();
    Code:
       0: aload_0
       1: aload_1
       2: iload_2
       3: invokespecial #6                  // Method java/lang/Enum."<init>":(Ljava/lang/String;I)V
       6: return

  public int getValue();
    Code:
       0: aload_0
       1: invokevirtual #7                  // Method ordinal:()I
       4: ireturn

  public java.lang.String getName();
    Code:
       0: aload_0
       1: invokevirtual #8                  // Method name:()Ljava/lang/String;
       4: areturn

  static {};
    Code:
       0: new           #4                  // class org/apache/kerby/cms/type/ExtendedCertificateInfo$ExtendedCertificateInfoField
       3: dup
       4: ldc           #9                  // String CMS_VERSION
       6: iconst_0
       7: invokespecial #10                 // Method "<init>":(Ljava/lang/String;I)V
      10: putstatic     #11                 // Field CMS_VERSION:Lorg/apache/kerby/cms/type/ExtendedCertificateInfo$ExtendedCertificateInfoField;
      13: new           #4                  // class org/apache/kerby/cms/type/ExtendedCertificateInfo$ExtendedCertificateInfoField
      16: dup
      17: ldc           #12                 // String CERTIFICATE
      19: iconst_1
      20: invokespecial #10                 // Method "<init>":(Ljava/lang/String;I)V
      23: putstatic     #13                 // Field CERTIFICATE:Lorg/apache/kerby/cms/type/ExtendedCertificateInfo$ExtendedCertificateInfoField;
      26: new           #4                  // class org/apache/kerby/cms/type/ExtendedCertificateInfo$ExtendedCertificateInfoField
      29: dup
      30: ldc           #14                 // String ATTRIBUTES
      32: iconst_2
      33: invokespecial #10                 // Method "<init>":(Ljava/lang/String;I)V
      36: putstatic     #15                 // Field ATTRIBUTES:Lorg/apache/kerby/cms/type/ExtendedCertificateInfo$ExtendedCertificateInfoField;
      39: iconst_3
      40: anewarray     #4                  // class org/apache/kerby/cms/type/ExtendedCertificateInfo$ExtendedCertificateInfoField
      43: dup
      44: iconst_0
      45: getstatic     #11                 // Field CMS_VERSION:Lorg/apache/kerby/cms/type/ExtendedCertificateInfo$ExtendedCertificateInfoField;
      48: aastore
      49: dup
      50: iconst_1
      51: getstatic     #13                 // Field CERTIFICATE:Lorg/apache/kerby/cms/type/ExtendedCertificateInfo$ExtendedCertificateInfoField;
      54: aastore
      55: dup
      56: iconst_2
      57: getstatic     #15                 // Field ATTRIBUTES:Lorg/apache/kerby/cms/type/ExtendedCertificateInfo$ExtendedCertificateInfoField;
      60: aastore
      61: putstatic     #1                  // Field $VALUES:[Lorg/apache/kerby/cms/type/ExtendedCertificateInfo$ExtendedCertificateInfoField;
      64: return
}
