Compiled from "RecipientInfo.java"
public final class org.apache.kerby.cms.type.RecipientInfo$RecipientInfoField extends java.lang.Enum<org.apache.kerby.cms.type.RecipientInfo$RecipientInfoField> implements org.apache.kerby.asn1.EnumType {
  public static final org.apache.kerby.cms.type.RecipientInfo$RecipientInfoField KTRI;

  public static final org.apache.kerby.cms.type.RecipientInfo$RecipientInfoField KARI;

  public static final org.apache.kerby.cms.type.RecipientInfo$RecipientInfoField KEKRI;

  public static final org.apache.kerby.cms.type.RecipientInfo$RecipientInfoField PWRI;

  public static final org.apache.kerby.cms.type.RecipientInfo$RecipientInfoField ORI;

  private static final org.apache.kerby.cms.type.RecipientInfo$RecipientInfoField[] $VALUES;

  public static org.apache.kerby.cms.type.RecipientInfo$RecipientInfoField[] values();
    Code:
       0: getstatic     #1                  // Field $VALUES:[Lorg/apache/kerby/cms/type/RecipientInfo$RecipientInfoField;
       3: invokevirtual #2                  // Method "[Lorg/apache/kerby/cms/type/RecipientInfo$RecipientInfoField;".clone:()Ljava/lang/Object;
       6: checkcast     #3                  // class "[Lorg/apache/kerby/cms/type/RecipientInfo$RecipientInfoField;"
       9: areturn

  public static org.apache.kerby.cms.type.RecipientInfo$RecipientInfoField valueOf(java.lang.String);
    Code:
       0: ldc_w         #4                  // class org/apache/kerby/cms/type/RecipientInfo$RecipientInfoField
       3: aload_0
       4: invokestatic  #5                  // Method java/lang/Enum.valueOf:(Ljava/lang/Class;Ljava/lang/String;)Ljava/lang/Enum;
       7: checkcast     #4                  // class org/apache/kerby/cms/type/RecipientInfo$RecipientInfoField
      10: areturn

  private org.apache.kerby.cms.type.RecipientInfo$RecipientInfoField();
    Code:
       0: aload_0
       1: aload_1
       2: iload_2
       3: invokespecial #6                  // Method java/lang/Enum."<init>":(Ljava/lang/String;I)V
       6: return

  public int getValue();
    Code:
       0: aload_0
       1: invokevirtual #7                  // Method ordinal:()I
       4: ireturn

  public java.lang.String getName();
    Code:
       0: aload_0
       1: invokevirtual #8                  // Method name:()Ljava/lang/String;
       4: areturn

  static {};
    Code:
       0: new           #4                  // class org/apache/kerby/cms/type/RecipientInfo$RecipientInfoField
       3: dup
       4: ldc           #9                  // String KTRI
       6: iconst_0
       7: invokespecial #10                 // Method "<init>":(Ljava/lang/String;I)V
      10: putstatic     #11                 // Field KTRI:Lorg/apache/kerby/cms/type/RecipientInfo$RecipientInfoField;
      13: new           #4                  // class org/apache/kerby/cms/type/RecipientInfo$RecipientInfoField
      16: dup
      17: ldc           #12                 // String KARI
      19: iconst_1
      20: invokespecial #10                 // Method "<init>":(Ljava/lang/String;I)V
      23: putstatic     #13                 // Field KARI:Lorg/apache/kerby/cms/type/RecipientInfo$RecipientInfoField;
      26: new           #4                  // class org/apache/kerby/cms/type/RecipientInfo$RecipientInfoField
      29: dup
      30: ldc           #14                 // String KEKRI
      32: iconst_2
      33: invokespecial #10                 // Method "<init>":(Ljava/lang/String;I)V
      36: putstatic     #15                 // Field KEKRI:Lorg/apache/kerby/cms/type/RecipientInfo$RecipientInfoField;
      39: new           #4                  // class org/apache/kerby/cms/type/RecipientInfo$RecipientInfoField
      42: dup
      43: ldc           #16                 // String PWRI
      45: iconst_3
      46: invokespecial #10                 // Method "<init>":(Ljava/lang/String;I)V
      49: putstatic     #17                 // Field PWRI:Lorg/apache/kerby/cms/type/RecipientInfo$RecipientInfoField;
      52: new           #4                  // class org/apache/kerby/cms/type/RecipientInfo$RecipientInfoField
      55: dup
      56: ldc           #18                 // String ORI
      58: iconst_4
      59: invokespecial #10                 // Method "<init>":(Ljava/lang/String;I)V
      62: putstatic     #19                 // Field ORI:Lorg/apache/kerby/cms/type/RecipientInfo$RecipientInfoField;
      65: iconst_5
      66: anewarray     #4                  // class org/apache/kerby/cms/type/RecipientInfo$RecipientInfoField
      69: dup
      70: iconst_0
      71: getstatic     #11                 // Field KTRI:Lorg/apache/kerby/cms/type/RecipientInfo$RecipientInfoField;
      74: aastore
      75: dup
      76: iconst_1
      77: getstatic     #13                 // Field KARI:Lorg/apache/kerby/cms/type/RecipientInfo$RecipientInfoField;
      80: aastore
      81: dup
      82: iconst_2
      83: getstatic     #15                 // Field KEKRI:Lorg/apache/kerby/cms/type/RecipientInfo$RecipientInfoField;
      86: aastore
      87: dup
      88: iconst_3
      89: getstatic     #17                 // Field PWRI:Lorg/apache/kerby/cms/type/RecipientInfo$RecipientInfoField;
      92: aastore
      93: dup
      94: iconst_4
      95: getstatic     #19                 // Field ORI:Lorg/apache/kerby/cms/type/RecipientInfo$RecipientInfoField;
      98: aastore
      99: putstatic     #1                  // Field $VALUES:[Lorg/apache/kerby/cms/type/RecipientInfo$RecipientInfoField;
     102: return
}
