Compiled from "ResolvedType.java"
public abstract class com.fasterxml.classmate.ResolvedType implements java.lang.reflect.Type {
  public static final com.fasterxml.classmate.ResolvedType[] NO_TYPES;

  protected static final com.fasterxml.classmate.members.RawConstructor[] NO_CONSTRUCTORS;

  protected static final com.fasterxml.classmate.members.RawField[] NO_FIELDS;

  protected static final com.fasterxml.classmate.members.RawMethod[] NO_METHODS;

  protected final java.lang.Class<?> _erasedType;

  protected final com.fasterxml.classmate.TypeBindings _typeBindings;

  protected com.fasterxml.classmate.ResolvedType(java.lang.Class<?>, com.fasterxml.classmate.TypeBindings);
    Code:
       0: aload_0
       1: invokespecial #1                  // Method java/lang/Object."<init>":()V
       4: aload_0
       5: aload_1
       6: putfield      #2                  // Field _erasedType:Ljava/lang/Class;
       9: aload_0
      10: aload_2
      11: ifnonnull     20
      14: invokestatic  #3                  // Method com/fasterxml/classmate/TypeBindings.emptyBindings:()Lcom/fasterxml/classmate/TypeBindings;
      17: goto          21
      20: aload_2
      21: putfield      #4                  // Field _typeBindings:Lcom/fasterxml/classmate/TypeBindings;
      24: return

  public abstract boolean canCreateSubtypes();

  public final boolean canCreateSubtype(java.lang.Class<?>);
    Code:
       0: aload_0
       1: invokevirtual #5                  // Method canCreateSubtypes:()Z
       4: ifeq          22
       7: aload_0
       8: getfield      #2                  // Field _erasedType:Ljava/lang/Class;
      11: aload_1
      12: invokevirtual #6                  // Method java/lang/Class.isAssignableFrom:(Ljava/lang/Class;)Z
      15: ifeq          22
      18: iconst_1
      19: goto          23
      22: iconst_0
      23: ireturn

  public java.lang.Class<?> getErasedType();
    Code:
       0: aload_0
       1: getfield      #2                  // Field _erasedType:Ljava/lang/Class;
       4: areturn

  public abstract com.fasterxml.classmate.ResolvedType getParentClass();

  public abstract com.fasterxml.classmate.ResolvedType getSelfReferencedType();

  public abstract com.fasterxml.classmate.ResolvedType getArrayElementType();

  public abstract java.util.List<com.fasterxml.classmate.ResolvedType> getImplementedInterfaces();

  public java.util.List<com.fasterxml.classmate.ResolvedType> getTypeParameters();
    Code:
       0: aload_0
       1: getfield      #4                  // Field _typeBindings:Lcom/fasterxml/classmate/TypeBindings;
       4: invokevirtual #7                  // Method com/fasterxml/classmate/TypeBindings.getTypeParameters:()Ljava/util/List;
       7: areturn

  public com.fasterxml.classmate.TypeBindings getTypeBindings();
    Code:
       0: aload_0
       1: getfield      #4                  // Field _typeBindings:Lcom/fasterxml/classmate/TypeBindings;
       4: areturn

  public java.util.List<com.fasterxml.classmate.ResolvedType> typeParametersFor(java.lang.Class<?>);
    Code:
       0: aload_0
       1: aload_1
       2: invokevirtual #8                  // Method findSupertype:(Ljava/lang/Class;)Lcom/fasterxml/classmate/ResolvedType;
       5: astore_2
       6: aload_2
       7: ifnull        15
      10: aload_2
      11: invokevirtual #9                  // Method getTypeParameters:()Ljava/util/List;
      14: areturn
      15: aconst_null
      16: areturn

  public com.fasterxml.classmate.ResolvedType findSupertype(java.lang.Class<?>);
    Code:
       0: aload_1
       1: aload_0
       2: getfield      #2                  // Field _erasedType:Ljava/lang/Class;
       5: if_acmpne     10
       8: aload_0
       9: areturn
      10: aload_1
      11: invokevirtual #10                 // Method java/lang/Class.isInterface:()Z
      14: ifeq          64
      17: aload_0
      18: invokevirtual #11                 // Method getImplementedInterfaces:()Ljava/util/List;
      21: invokeinterface #12,  1           // InterfaceMethod java/util/List.iterator:()Ljava/util/Iterator;
      26: astore_2
      27: aload_2
      28: invokeinterface #13,  1           // InterfaceMethod java/util/Iterator.hasNext:()Z
      33: ifeq          64
      36: aload_2
      37: invokeinterface #14,  1           // InterfaceMethod java/util/Iterator.next:()Ljava/lang/Object;
      42: checkcast     #15                 // class com/fasterxml/classmate/ResolvedType
      45: astore_3
      46: aload_3
      47: aload_1
      48: invokevirtual #8                  // Method findSupertype:(Ljava/lang/Class;)Lcom/fasterxml/classmate/ResolvedType;
      51: astore        4
      53: aload         4
      55: ifnull        61
      58: aload         4
      60: areturn
      61: goto          27
      64: aload_0
      65: invokevirtual #16                 // Method getParentClass:()Lcom/fasterxml/classmate/ResolvedType;
      68: astore_2
      69: aload_2
      70: ifnull        85
      73: aload_2
      74: aload_1
      75: invokevirtual #8                  // Method findSupertype:(Ljava/lang/Class;)Lcom/fasterxml/classmate/ResolvedType;
      78: astore_3
      79: aload_3
      80: ifnull        85
      83: aload_3
      84: areturn
      85: aconst_null
      86: areturn

  public abstract boolean isInterface();

  public final boolean isConcrete();
    Code:
       0: aload_0
       1: invokevirtual #17                 // Method isAbstract:()Z
       4: ifne          11
       7: iconst_1
       8: goto          12
      11: iconst_0
      12: ireturn

  public abstract boolean isAbstract();

  public abstract boolean isArray();

  public abstract boolean isPrimitive();

  public final boolean isInstanceOf(java.lang.Class<?>);
    Code:
       0: aload_1
       1: aload_0
       2: getfield      #2                  // Field _erasedType:Ljava/lang/Class;
       5: invokevirtual #6                  // Method java/lang/Class.isAssignableFrom:(Ljava/lang/Class;)Z
       8: ireturn

  public java.util.List<com.fasterxml.classmate.members.RawConstructor> getConstructors();
    Code:
       0: invokestatic  #18                 // Method java/util/Collections.emptyList:()Ljava/util/List;
       3: areturn

  public java.util.List<com.fasterxml.classmate.members.RawField> getMemberFields();
    Code:
       0: invokestatic  #18                 // Method java/util/Collections.emptyList:()Ljava/util/List;
       3: areturn

  public java.util.List<com.fasterxml.classmate.members.RawMethod> getMemberMethods();
    Code:
       0: invokestatic  #18                 // Method java/util/Collections.emptyList:()Ljava/util/List;
       3: areturn

  public java.util.List<com.fasterxml.classmate.members.RawField> getStaticFields();
    Code:
       0: invokestatic  #18                 // Method java/util/Collections.emptyList:()Ljava/util/List;
       3: areturn

  public java.util.List<com.fasterxml.classmate.members.RawMethod> getStaticMethods();
    Code:
       0: invokestatic  #18                 // Method java/util/Collections.emptyList:()Ljava/util/List;
       3: areturn

  public java.lang.String getSignature();
    Code:
       0: new           #19                 // class java/lang/StringBuilder
       3: dup
       4: invokespecial #20                 // Method java/lang/StringBuilder."<init>":()V
       7: astore_1
       8: aload_0
       9: aload_1
      10: invokevirtual #21                 // Method appendSignature:(Ljava/lang/StringBuilder;)Ljava/lang/StringBuilder;
      13: invokevirtual #22                 // Method java/lang/StringBuilder.toString:()Ljava/lang/String;
      16: areturn

  public java.lang.String getErasedSignature();
    Code:
       0: new           #19                 // class java/lang/StringBuilder
       3: dup
       4: invokespecial #20                 // Method java/lang/StringBuilder."<init>":()V
       7: astore_1
       8: aload_0
       9: aload_1
      10: invokevirtual #23                 // Method appendErasedSignature:(Ljava/lang/StringBuilder;)Ljava/lang/StringBuilder;
      13: invokevirtual #22                 // Method java/lang/StringBuilder.toString:()Ljava/lang/String;
      16: areturn

  public java.lang.String getFullDescription();
    Code:
       0: new           #19                 // class java/lang/StringBuilder
       3: dup
       4: invokespecial #20                 // Method java/lang/StringBuilder."<init>":()V
       7: astore_1
       8: aload_0
       9: aload_1
      10: invokevirtual #24                 // Method appendFullDescription:(Ljava/lang/StringBuilder;)Ljava/lang/StringBuilder;
      13: invokevirtual #22                 // Method java/lang/StringBuilder.toString:()Ljava/lang/String;
      16: areturn

  public java.lang.String getBriefDescription();
    Code:
       0: new           #19                 // class java/lang/StringBuilder
       3: dup
       4: invokespecial #20                 // Method java/lang/StringBuilder."<init>":()V
       7: astore_1
       8: aload_0
       9: aload_1
      10: invokevirtual #25                 // Method appendBriefDescription:(Ljava/lang/StringBuilder;)Ljava/lang/StringBuilder;
      13: invokevirtual #22                 // Method java/lang/StringBuilder.toString:()Ljava/lang/String;
      16: areturn

  public abstract java.lang.StringBuilder appendBriefDescription(java.lang.StringBuilder);

  public abstract java.lang.StringBuilder appendFullDescription(java.lang.StringBuilder);

  public abstract java.lang.StringBuilder appendSignature(java.lang.StringBuilder);

  public abstract java.lang.StringBuilder appendErasedSignature(java.lang.StringBuilder);

  public java.lang.String toString();
    Code:
       0: aload_0
       1: invokevirtual #26                 // Method getBriefDescription:()Ljava/lang/String;
       4: areturn

  public int hashCode();
    Code:
       0: aload_0
       1: getfield      #2                  // Field _erasedType:Ljava/lang/Class;
       4: invokevirtual #27                 // Method java/lang/Class.getName:()Ljava/lang/String;
       7: invokevirtual #28                 // Method java/lang/String.hashCode:()I
      10: aload_0
      11: getfield      #4                  // Field _typeBindings:Lcom/fasterxml/classmate/TypeBindings;
      14: invokevirtual #29                 // Method com/fasterxml/classmate/TypeBindings.hashCode:()I
      17: iadd
      18: ireturn

  public boolean equals(java.lang.Object);
    Code:
       0: aload_1
       1: aload_0
       2: if_acmpne     7
       5: iconst_1
       6: ireturn
       7: aload_1
       8: ifnull        22
      11: aload_1
      12: invokevirtual #30                 // Method java/lang/Object.getClass:()Ljava/lang/Class;
      15: aload_0
      16: invokevirtual #30                 // Method java/lang/Object.getClass:()Ljava/lang/Class;
      19: if_acmpeq     24
      22: iconst_0
      23: ireturn
      24: aload_1
      25: checkcast     #15                 // class com/fasterxml/classmate/ResolvedType
      28: astore_2
      29: aload_2
      30: getfield      #2                  // Field _erasedType:Ljava/lang/Class;
      33: aload_0
      34: getfield      #2                  // Field _erasedType:Ljava/lang/Class;
      37: if_acmpeq     42
      40: iconst_0
      41: ireturn
      42: aload_0
      43: getfield      #4                  // Field _typeBindings:Lcom/fasterxml/classmate/TypeBindings;
      46: aload_2
      47: getfield      #4                  // Field _typeBindings:Lcom/fasterxml/classmate/TypeBindings;
      50: invokevirtual #31                 // Method com/fasterxml/classmate/TypeBindings.equals:(Ljava/lang/Object;)Z
      53: ireturn

  protected java.lang.StringBuilder _appendClassSignature(java.lang.StringBuilder);
    Code:
       0: aload_1
       1: bipush        76
       3: invokevirtual #32                 // Method java/lang/StringBuilder.append:(C)Ljava/lang/StringBuilder;
       6: pop
       7: aload_0
       8: aload_1
       9: invokevirtual #33                 // Method _appendClassName:(Ljava/lang/StringBuilder;)Ljava/lang/StringBuilder;
      12: astore_1
      13: aload_0
      14: getfield      #4                  // Field _typeBindings:Lcom/fasterxml/classmate/TypeBindings;
      17: invokevirtual #34                 // Method com/fasterxml/classmate/TypeBindings.size:()I
      20: istore_2
      21: iload_2
      22: ifle          65
      25: aload_1
      26: bipush        60
      28: invokevirtual #32                 // Method java/lang/StringBuilder.append:(C)Ljava/lang/StringBuilder;
      31: pop
      32: iconst_0
      33: istore_3
      34: iload_3
      35: iload_2
      36: if_icmpge     58
      39: aload_0
      40: getfield      #4                  // Field _typeBindings:Lcom/fasterxml/classmate/TypeBindings;
      43: iload_3
      44: invokevirtual #35                 // Method com/fasterxml/classmate/TypeBindings.getBoundType:(I)Lcom/fasterxml/classmate/ResolvedType;
      47: aload_1
      48: invokevirtual #23                 // Method appendErasedSignature:(Ljava/lang/StringBuilder;)Ljava/lang/StringBuilder;
      51: astore_1
      52: iinc          3, 1
      55: goto          34
      58: aload_1
      59: bipush        62
      61: invokevirtual #32                 // Method java/lang/StringBuilder.append:(C)Ljava/lang/StringBuilder;
      64: pop
      65: aload_1
      66: bipush        59
      68: invokevirtual #32                 // Method java/lang/StringBuilder.append:(C)Ljava/lang/StringBuilder;
      71: pop
      72: aload_1
      73: areturn

  protected java.lang.StringBuilder _appendErasedClassSignature(java.lang.StringBuilder);
    Code:
       0: aload_1
       1: bipush        76
       3: invokevirtual #32                 // Method java/lang/StringBuilder.append:(C)Ljava/lang/StringBuilder;
       6: pop
       7: aload_0
       8: aload_1
       9: invokevirtual #33                 // Method _appendClassName:(Ljava/lang/StringBuilder;)Ljava/lang/StringBuilder;
      12: astore_1
      13: aload_1
      14: bipush        59
      16: invokevirtual #32                 // Method java/lang/StringBuilder.append:(C)Ljava/lang/StringBuilder;
      19: pop
      20: aload_1
      21: areturn

  protected java.lang.StringBuilder _appendClassDescription(java.lang.StringBuilder);
    Code:
       0: aload_1
       1: aload_0
       2: getfield      #2                  // Field _erasedType:Ljava/lang/Class;
       5: invokevirtual #27                 // Method java/lang/Class.getName:()Ljava/lang/String;
       8: invokevirtual #36                 // Method java/lang/StringBuilder.append:(Ljava/lang/String;)Ljava/lang/StringBuilder;
      11: pop
      12: aload_0
      13: getfield      #4                  // Field _typeBindings:Lcom/fasterxml/classmate/TypeBindings;
      16: invokevirtual #34                 // Method com/fasterxml/classmate/TypeBindings.size:()I
      19: istore_2
      20: iload_2
      21: ifle          75
      24: aload_1
      25: bipush        60
      27: invokevirtual #32                 // Method java/lang/StringBuilder.append:(C)Ljava/lang/StringBuilder;
      30: pop
      31: iconst_0
      32: istore_3
      33: iload_3
      34: iload_2
      35: if_icmpge     68
      38: iload_3
      39: ifle          49
      42: aload_1
      43: bipush        44
      45: invokevirtual #32                 // Method java/lang/StringBuilder.append:(C)Ljava/lang/StringBuilder;
      48: pop
      49: aload_0
      50: getfield      #4                  // Field _typeBindings:Lcom/fasterxml/classmate/TypeBindings;
      53: iload_3
      54: invokevirtual #35                 // Method com/fasterxml/classmate/TypeBindings.getBoundType:(I)Lcom/fasterxml/classmate/ResolvedType;
      57: aload_1
      58: invokevirtual #25                 // Method appendBriefDescription:(Ljava/lang/StringBuilder;)Ljava/lang/StringBuilder;
      61: astore_1
      62: iinc          3, 1
      65: goto          33
      68: aload_1
      69: bipush        62
      71: invokevirtual #32                 // Method java/lang/StringBuilder.append:(C)Ljava/lang/StringBuilder;
      74: pop
      75: aload_1
      76: areturn

  protected java.lang.StringBuilder _appendClassName(java.lang.StringBuilder);
    Code:
       0: aload_0
       1: getfield      #2                  // Field _erasedType:Ljava/lang/Class;
       4: invokevirtual #27                 // Method java/lang/Class.getName:()Ljava/lang/String;
       7: astore_2
       8: iconst_0
       9: istore_3
      10: aload_2
      11: invokevirtual #37                 // Method java/lang/String.length:()I
      14: istore        4
      16: iload_3
      17: iload         4
      19: if_icmpge     53
      22: aload_2
      23: iload_3
      24: invokevirtual #38                 // Method java/lang/String.charAt:(I)C
      27: istore        5
      29: iload         5
      31: bipush        46
      33: if_icmpne     40
      36: bipush        47
      38: istore        5
      40: aload_1
      41: iload         5
      43: invokevirtual #32                 // Method java/lang/StringBuilder.append:(C)Ljava/lang/StringBuilder;
      46: pop
      47: iinc          3, 1
      50: goto          16
      53: aload_1
      54: areturn

  protected com.fasterxml.classmate.members.RawField[] _getFields(boolean);
    Code:
       0: new           #39                 // class java/util/ArrayList
       3: dup
       4: invokespecial #40                 // Method java/util/ArrayList."<init>":()V
       7: astore_2
       8: aload_0
       9: getfield      #2                  // Field _erasedType:Ljava/lang/Class;
      12: invokevirtual #41                 // Method java/lang/Class.getDeclaredFields:()[Ljava/lang/reflect/Field;
      15: astore_3
      16: aload_3
      17: arraylength
      18: istore        4
      20: iconst_0
      21: istore        5
      23: iload         5
      25: iload         4
      27: if_icmpge     77
      30: aload_3
      31: iload         5
      33: aaload
      34: astore        6
      36: aload         6
      38: invokevirtual #42                 // Method java/lang/reflect/Field.isSynthetic:()Z
      41: ifne          71
      44: aload         6
      46: invokevirtual #43                 // Method java/lang/reflect/Field.getModifiers:()I
      49: invokestatic  #44                 // Method java/lang/reflect/Modifier.isStatic:(I)Z
      52: iload_1
      53: if_icmpne     71
      56: aload_2
      57: new           #45                 // class com/fasterxml/classmate/members/RawField
      60: dup
      61: aload_0
      62: aload         6
      64: invokespecial #46                 // Method com/fasterxml/classmate/members/RawField."<init>":(Lcom/fasterxml/classmate/ResolvedType;Ljava/lang/reflect/Field;)V
      67: invokevirtual #47                 // Method java/util/ArrayList.add:(Ljava/lang/Object;)Z
      70: pop
      71: iinc          5, 1
      74: goto          23
      77: aload_2
      78: invokevirtual #48                 // Method java/util/ArrayList.isEmpty:()Z
      81: ifeq          88
      84: getstatic     #49                 // Field NO_FIELDS:[Lcom/fasterxml/classmate/members/RawField;
      87: areturn
      88: aload_2
      89: aload_2
      90: invokevirtual #50                 // Method java/util/ArrayList.size:()I
      93: anewarray     #45                 // class com/fasterxml/classmate/members/RawField
      96: invokevirtual #51                 // Method java/util/ArrayList.toArray:([Ljava/lang/Object;)[Ljava/lang/Object;
      99: checkcast     #52                 // class "[Lcom/fasterxml/classmate/members/RawField;"
     102: areturn

  protected com.fasterxml.classmate.members.RawMethod[] _getMethods(boolean);
    Code:
       0: new           #39                 // class java/util/ArrayList
       3: dup
       4: invokespecial #40                 // Method java/util/ArrayList."<init>":()V
       7: astore_2
       8: aload_0
       9: getfield      #2                  // Field _erasedType:Ljava/lang/Class;
      12: invokevirtual #53                 // Method java/lang/Class.getDeclaredMethods:()[Ljava/lang/reflect/Method;
      15: astore_3
      16: aload_3
      17: arraylength
      18: istore        4
      20: iconst_0
      21: istore        5
      23: iload         5
      25: iload         4
      27: if_icmpge     77
      30: aload_3
      31: iload         5
      33: aaload
      34: astore        6
      36: aload         6
      38: invokevirtual #54                 // Method java/lang/reflect/Method.isSynthetic:()Z
      41: ifne          71
      44: aload         6
      46: invokevirtual #55                 // Method java/lang/reflect/Method.getModifiers:()I
      49: invokestatic  #44                 // Method java/lang/reflect/Modifier.isStatic:(I)Z
      52: iload_1
      53: if_icmpne     71
      56: aload_2
      57: new           #56                 // class com/fasterxml/classmate/members/RawMethod
      60: dup
      61: aload_0
      62: aload         6
      64: invokespecial #57                 // Method com/fasterxml/classmate/members/RawMethod."<init>":(Lcom/fasterxml/classmate/ResolvedType;Ljava/lang/reflect/Method;)V
      67: invokevirtual #47                 // Method java/util/ArrayList.add:(Ljava/lang/Object;)Z
      70: pop
      71: iinc          5, 1
      74: goto          23
      77: aload_2
      78: invokevirtual #48                 // Method java/util/ArrayList.isEmpty:()Z
      81: ifeq          88
      84: getstatic     #58                 // Field NO_METHODS:[Lcom/fasterxml/classmate/members/RawMethod;
      87: areturn
      88: aload_2
      89: aload_2
      90: invokevirtual #50                 // Method java/util/ArrayList.size:()I
      93: anewarray     #56                 // class com/fasterxml/classmate/members/RawMethod
      96: invokevirtual #51                 // Method java/util/ArrayList.toArray:([Ljava/lang/Object;)[Ljava/lang/Object;
      99: checkcast     #59                 // class "[Lcom/fasterxml/classmate/members/RawMethod;"
     102: areturn

  protected com.fasterxml.classmate.members.RawConstructor[] _getConstructors();
    Code:
       0: new           #39                 // class java/util/ArrayList
       3: dup
       4: invokespecial #40                 // Method java/util/ArrayList."<init>":()V
       7: astore_1
       8: aload_0
       9: getfield      #2                  // Field _erasedType:Ljava/lang/Class;
      12: invokevirtual #60                 // Method java/lang/Class.getDeclaredConstructors:()[Ljava/lang/reflect/Constructor;
      15: astore_2
      16: aload_2
      17: arraylength
      18: istore_3
      19: iconst_0
      20: istore        4
      22: iload         4
      24: iload_3
      25: if_icmpge     63
      28: aload_2
      29: iload         4
      31: aaload
      32: astore        5
      34: aload         5
      36: invokevirtual #61                 // Method java/lang/reflect/Constructor.isSynthetic:()Z
      39: ifne          57
      42: aload_1
      43: new           #62                 // class com/fasterxml/classmate/members/RawConstructor
      46: dup
      47: aload_0
      48: aload         5
      50: invokespecial #63                 // Method com/fasterxml/classmate/members/RawConstructor."<init>":(Lcom/fasterxml/classmate/ResolvedType;Ljava/lang/reflect/Constructor;)V
      53: invokevirtual #47                 // Method java/util/ArrayList.add:(Ljava/lang/Object;)Z
      56: pop
      57: iinc          4, 1
      60: goto          22
      63: aload_1
      64: invokevirtual #48                 // Method java/util/ArrayList.isEmpty:()Z
      67: ifeq          74
      70: getstatic     #64                 // Field NO_CONSTRUCTORS:[Lcom/fasterxml/classmate/members/RawConstructor;
      73: areturn
      74: aload_1
      75: aload_1
      76: invokevirtual #50                 // Method java/util/ArrayList.size:()I
      79: anewarray     #62                 // class com/fasterxml/classmate/members/RawConstructor
      82: invokevirtual #51                 // Method java/util/ArrayList.toArray:([Ljava/lang/Object;)[Ljava/lang/Object;
      85: checkcast     #65                 // class "[Lcom/fasterxml/classmate/members/RawConstructor;"
      88: areturn

  static {};
    Code:
       0: iconst_0
       1: anewarray     #15                 // class com/fasterxml/classmate/ResolvedType
       4: putstatic     #66                 // Field NO_TYPES:[Lcom/fasterxml/classmate/ResolvedType;
       7: iconst_0
       8: anewarray     #62                 // class com/fasterxml/classmate/members/RawConstructor
      11: putstatic     #64                 // Field NO_CONSTRUCTORS:[Lcom/fasterxml/classmate/members/RawConstructor;
      14: iconst_0
      15: anewarray     #45                 // class com/fasterxml/classmate/members/RawField
      18: putstatic     #49                 // Field NO_FIELDS:[Lcom/fasterxml/classmate/members/RawField;
      21: iconst_0
      22: anewarray     #56                 // class com/fasterxml/classmate/members/RawMethod
      25: putstatic     #58                 // Field NO_METHODS:[Lcom/fasterxml/classmate/members/RawMethod;
      28: return
}
