Compiled from "SslConduit.java"
class io.undertow.protocols.ssl.SslConduit$AccumulativeOrBoolean {
  private boolean value;

  private io.undertow.protocols.ssl.SslConduit$AccumulativeOrBoolean();
    Code:
       0: aload_0
       1: invokespecial #1                  // Method java/lang/Object."<init>":()V
       4: aload_0
       5: iconst_0
       6: putfield      #2                  // Field value:Z
       9: return

  public void add(boolean);
    Code:
       0: aload_0
       1: aload_0
       2: getfield      #2                  // Field value:Z
       5: ifne          12
       8: iload_1
       9: ifeq          16
      12: iconst_1
      13: goto          17
      16: iconst_0
      17: putfield      #2                  // Field value:Z
      20: return

  public boolean get();
    Code:
       0: aload_0
       1: getfield      #2                  // Field value:Z
       4: ireturn
}
