Compiled from "SslConduit.java"
class io.undertow.protocols.ssl.SslConduit$1 implements java.lang.Runnable {
  final io.undertow.protocols.ssl.SslConduit this$0;

  io.undertow.protocols.ssl.SslConduit$1(io.undertow.protocols.ssl.SslConduit);
    Code:
       0: aload_0
       1: aload_1
       2: putfield      #1                  // Field this$0:Lio/undertow/protocols/ssl/SslConduit;
       5: aload_0
       6: invokespecial #2                  // Method java/lang/Object."<init>":()V
       9: return

  public void run();
    Code:
       0: aload_0
       1: getfield      #1                  // Field this$0:Lio/undertow/protocols/ssl/SslConduit;
       4: getfield      #3                  // Field io/undertow/protocols/ssl/SslConduit.readListenerInvocationCount:I
       7: istore_1
       8: aload_0
       9: getfield      #1                  // Field this$0:Lio/undertow/protocols/ssl/SslConduit;
      12: getfield      #4                  // Field io/undertow/protocols/ssl/SslConduit.readReadyHandler:Lio/undertow/protocols/ssl/SslConduit$SslReadReadyHandler;
      15: invokevirtual #5                  // Method io/undertow/protocols/ssl/SslConduit$SslReadReadyHandler.readReady:()V
      18: iload_1
      19: aload_0
      20: getfield      #1                  // Field this$0:Lio/undertow/protocols/ssl/SslConduit;
      23: getfield      #3                  // Field io/undertow/protocols/ssl/SslConduit.readListenerInvocationCount:I
      26: if_icmpne     62
      29: aload_0
      30: getfield      #1                  // Field this$0:Lio/undertow/protocols/ssl/SslConduit;
      33: iconst_0
      34: putfield      #3                  // Field io/undertow/protocols/ssl/SslConduit.readListenerInvocationCount:I
      37: goto          62
      40: astore_2
      41: iload_1
      42: aload_0
      43: getfield      #1                  // Field this$0:Lio/undertow/protocols/ssl/SslConduit;
      46: getfield      #3                  // Field io/undertow/protocols/ssl/SslConduit.readListenerInvocationCount:I
      49: if_icmpne     60
      52: aload_0
      53: getfield      #1                  // Field this$0:Lio/undertow/protocols/ssl/SslConduit;
      56: iconst_0
      57: putfield      #3                  // Field io/undertow/protocols/ssl/SslConduit.readListenerInvocationCount:I
      60: aload_2
      61: athrow
      62: return
    Exception table:
       from    to  target type
           8    18    40   any
}
