class org.bouncycastle.jcajce.provider.symmetric.GcmSpecUtil {
  static final java.lang.Class gcmSpecClass;

  org.bouncycastle.jcajce.provider.symmetric.GcmSpecUtil();
    Code:
       0: aload_0
       1: invokespecial #119                // Method java/lang/Object."<init>":()V
       4: return

  static boolean gcmSpecExists();
    Code:
       0: getstatic     #111                // Field gcmSpecClass:Ljava/lang/Class;
       3: ifnull        10
       6: iconst_1
       7: goto          11
      10: iconst_0
      11: ireturn

  static boolean isGcmSpec(java.security.spec.AlgorithmParameterSpec);
    Code:
       0: getstatic     #111                // Field gcmSpecClass:Ljava/lang/Class;
       3: ifnull        20
       6: getstatic     #111                // Field gcmSpecClass:Ljava/lang/Class;
       9: aload_0
      10: invokevirtual #113                // Method java/lang/Class.isInstance:(Ljava/lang/Object;)Z
      13: ifeq          20
      16: iconst_1
      17: goto          21
      20: iconst_0
      21: ireturn

  static boolean isGcmSpec(java.lang.Class);
    Code:
       0: getstatic     #111                // Field gcmSpecClass:Ljava/lang/Class;
       3: aload_0
       4: if_acmpne     11
       7: iconst_1
       8: goto          12
      11: iconst_0
      12: ireturn

  static java.security.spec.AlgorithmParameterSpec extractGcmSpec(org.bouncycastle.asn1.ASN1Primitive) throws java.security.spec.InvalidParameterSpecException;
    Code:
       0: aload_0
       1: invokestatic  #129                // Method org/bouncycastle/asn1/cms/GCMParameters.getInstance:(Ljava/lang/Object;)Lorg/bouncycastle/asn1/cms/GCMParameters;
       4: astore_1
       5: getstatic     #111                // Field gcmSpecClass:Ljava/lang/Class;
       8: iconst_2
       9: anewarray     #58                 // class java/lang/Class
      12: dup
      13: iconst_0
      14: getstatic     #110                // Field java/lang/Integer.TYPE:Ljava/lang/Class;
      17: aastore
      18: dup
      19: iconst_1
      20: ldc_w         #57                 // class "[B"
      23: aastore
      24: invokevirtual #114                // Method java/lang/Class.getConstructor:([Ljava/lang/Class;)Ljava/lang/reflect/Constructor;
      27: astore_2
      28: aload_2
      29: iconst_2
      30: anewarray     #63                 // class java/lang/Object
      33: dup
      34: iconst_0
      35: aload_1
      36: invokevirtual #126                // Method org/bouncycastle/asn1/cms/GCMParameters.getIcvLen:()I
      39: bipush        8
      41: imul
      42: invokestatic  #131                // Method org/bouncycastle/util/Integers.valueOf:(I)Ljava/lang/Integer;
      45: aastore
      46: dup
      47: iconst_1
      48: aload_1
      49: invokevirtual #127                // Method org/bouncycastle/asn1/cms/GCMParameters.getNonce:()[B
      52: aastore
      53: invokevirtual #123                // Method java/lang/reflect/Constructor.newInstance:([Ljava/lang/Object;)Ljava/lang/Object;
      56: checkcast     #67                 // class java/security/spec/AlgorithmParameterSpec
      59: areturn
      60: astore_1
      61: new           #68                 // class java/security/spec/InvalidParameterSpecException
      64: dup
      65: ldc           #3                  // String No constructor found!
      67: invokespecial #125                // Method java/security/spec/InvalidParameterSpecException."<init>":(Ljava/lang/String;)V
      70: athrow
      71: astore_1
      72: new           #68                 // class java/security/spec/InvalidParameterSpecException
      75: dup
      76: new           #64                 // class java/lang/StringBuilder
      79: dup
      80: invokespecial #120                // Method java/lang/StringBuilder."<init>":()V
      83: ldc           #2                  // String Construction failed:
      85: invokevirtual #122                // Method java/lang/StringBuilder.append:(Ljava/lang/String;)Ljava/lang/StringBuilder;
      88: aload_1
      89: invokevirtual #117                // Method java/lang/Exception.getMessage:()Ljava/lang/String;
      92: invokevirtual #122                // Method java/lang/StringBuilder.append:(Ljava/lang/String;)Ljava/lang/StringBuilder;
      95: invokevirtual #121                // Method java/lang/StringBuilder.toString:()Ljava/lang/String;
      98: invokespecial #125                // Method java/security/spec/InvalidParameterSpecException."<init>":(Ljava/lang/String;)V
     101: athrow
    Exception table:
       from    to  target type
           0    59    60   Class java/lang/NoSuchMethodException
           0    59    71   Class java/lang/Exception

  static org.bouncycastle.asn1.cms.GCMParameters extractGcmParameters(java.security.spec.AlgorithmParameterSpec) throws java.security.spec.InvalidParameterSpecException;
    Code:
       0: getstatic     #111                // Field gcmSpecClass:Ljava/lang/Class;
       3: ldc           #5                  // String getTLen
       5: iconst_0
       6: anewarray     #58                 // class java/lang/Class
       9: invokevirtual #115                // Method java/lang/Class.getDeclaredMethod:(Ljava/lang/String;[Ljava/lang/Class;)Ljava/lang/reflect/Method;
      12: astore_1
      13: getstatic     #111                // Field gcmSpecClass:Ljava/lang/Class;
      16: ldc           #4                  // String getIV
      18: iconst_0
      19: anewarray     #58                 // class java/lang/Class
      22: invokevirtual #115                // Method java/lang/Class.getDeclaredMethod:(Ljava/lang/String;[Ljava/lang/Class;)Ljava/lang/reflect/Method;
      25: astore_2
      26: new           #69                 // class org/bouncycastle/asn1/cms/GCMParameters
      29: dup
      30: aload_2
      31: aload_0
      32: iconst_0
      33: anewarray     #63                 // class java/lang/Object
      36: invokevirtual #124                // Method java/lang/reflect/Method.invoke:(Ljava/lang/Object;[Ljava/lang/Object;)Ljava/lang/Object;
      39: checkcast     #57                 // class "[B"
      42: checkcast     #57                 // class "[B"
      45: aload_1
      46: aload_0
      47: iconst_0
      48: anewarray     #63                 // class java/lang/Object
      51: invokevirtual #124                // Method java/lang/reflect/Method.invoke:(Ljava/lang/Object;[Ljava/lang/Object;)Ljava/lang/Object;
      54: checkcast     #61                 // class java/lang/Integer
      57: invokevirtual #118                // Method java/lang/Integer.intValue:()I
      60: bipush        8
      62: idiv
      63: invokespecial #128                // Method org/bouncycastle/asn1/cms/GCMParameters."<init>":([BI)V
      66: areturn
      67: astore_1
      68: new           #68                 // class java/security/spec/InvalidParameterSpecException
      71: dup
      72: ldc           #1                  // String Cannot process GCMParameterSpec
      74: invokespecial #125                // Method java/security/spec/InvalidParameterSpecException."<init>":(Ljava/lang/String;)V
      77: athrow
    Exception table:
       from    to  target type
           0    66    67   Class java/lang/Exception

  private static java.lang.Class lookup(java.lang.String);
    Code:
       0: ldc_w         #70                 // class org/bouncycastle/jcajce/provider/symmetric/GcmSpecUtil
       3: invokevirtual #112                // Method java/lang/Class.getClassLoader:()Ljava/lang/ClassLoader;
       6: aload_0
       7: invokevirtual #116                // Method java/lang/ClassLoader.loadClass:(Ljava/lang/String;)Ljava/lang/Class;
      10: areturn
      11: astore_1
      12: aconst_null
      13: areturn
    Exception table:
       from    to  target type
           0    10    11   Class java/lang/Exception

  static {};
    Code:
       0: ldc           #6                  // String javax.crypto.spec.GCMParameterSpec
       2: invokestatic  #130                // Method lookup:(Ljava/lang/String;)Ljava/lang/Class;
       5: putstatic     #111                // Field gcmSpecClass:Ljava/lang/Class;
       8: return
}
