public class org.bouncycastle.jcajce.provider.symmetric.Skipjack$Mac extends org.bouncycastle.jcajce.provider.symmetric.util.BaseMac {
  public org.bouncycastle.jcajce.provider.symmetric.Skipjack$Mac();
    Code:
       0: aload_0
       1: new           #9                  // class org/bouncycastle/crypto/macs/CBCBlockCipherMac
       4: dup
       5: new           #8                  // class org/bouncycastle/crypto/engines/SkipjackEngine
       8: dup
       9: invokespecial #18                 // Method org/bouncycastle/crypto/engines/SkipjackEngine."<init>":()V
      12: invokespecial #19                 // Method org/bouncycastle/crypto/macs/CBCBlockCipherMac."<init>":(Lorg/bouncycastle/crypto/BlockCipher;)V
      15: invokespecial #20                 // Method org/bouncycastle/jcajce/provider/symmetric/util/BaseMac."<init>":(Lorg/bouncycastle/crypto/Mac;)V
      18: return
}
