Compiled from "Documentation.java"
public final class com.google.api.Documentation extends com.google.protobuf.GeneratedMessageV3 implements com.google.api.DocumentationOrBuilder {
  private static final long serialVersionUID;

  public static final int SUMMARY_FIELD_NUMBER;

  private volatile java.lang.Object summary_;

  public static final int PAGES_FIELD_NUMBER;

  private java.util.List<com.google.api.Page> pages_;

  public static final int RULES_FIELD_NUMBER;

  private java.util.List<com.google.api.DocumentationRule> rules_;

  public static final int DOCUMENTATION_ROOT_URL_FIELD_NUMBER;

  private volatile java.lang.Object documentationRootUrl_;

  public static final int SERVICE_ROOT_URL_FIELD_NUMBER;

  private volatile java.lang.Object serviceRootUrl_;

  public static final int OVERVIEW_FIELD_NUMBER;

  private volatile java.lang.Object overview_;

  private byte memoizedIsInitialized;

  private static final com.google.api.Documentation DEFAULT_INSTANCE;

  private static final com.google.protobuf.Parser<com.google.api.Documentation> PARSER;

  private com.google.api.Documentation(com.google.protobuf.GeneratedMessageV3$Builder<?>);
    Code:
       0: aload_0
       1: aload_1
       2: invokespecial #13                 // Method com/google/protobuf/GeneratedMessageV3."<init>":(Lcom/google/protobuf/GeneratedMessageV3$Builder;)V
       5: aload_0
       6: iconst_m1
       7: putfield      #14                 // Field memoizedIsInitialized:B
      10: return

  private com.google.api.Documentation();
    Code:
       0: aload_0
       1: invokespecial #15                 // Method com/google/protobuf/GeneratedMessageV3."<init>":()V
       4: aload_0
       5: iconst_m1
       6: putfield      #14                 // Field memoizedIsInitialized:B
       9: aload_0
      10: ldc           #16                 // String
      12: putfield      #11                 // Field summary_:Ljava/lang/Object;
      15: aload_0
      16: invokestatic  #17                 // Method java/util/Collections.emptyList:()Ljava/util/List;
      19: putfield      #10                 // Field pages_:Ljava/util/List;
      22: aload_0
      23: invokestatic  #17                 // Method java/util/Collections.emptyList:()Ljava/util/List;
      26: putfield      #9                  // Field rules_:Ljava/util/List;
      29: aload_0
      30: ldc           #16                 // String
      32: putfield      #8                  // Field documentationRootUrl_:Ljava/lang/Object;
      35: aload_0
      36: ldc           #16                 // String
      38: putfield      #7                  // Field serviceRootUrl_:Ljava/lang/Object;
      41: aload_0
      42: ldc           #16                 // String
      44: putfield      #6                  // Field overview_:Ljava/lang/Object;
      47: return

  protected java.lang.Object newInstance(com.google.protobuf.GeneratedMessageV3$UnusedPrivateParameter);
    Code:
       0: new           #18                 // class com/google/api/Documentation
       3: dup
       4: invokespecial #19                 // Method "<init>":()V
       7: areturn

  public final com.google.protobuf.UnknownFieldSet getUnknownFields();
    Code:
       0: aload_0
       1: getfield      #4                  // Field unknownFields:Lcom/google/protobuf/UnknownFieldSet;
       4: areturn

  private com.google.api.Documentation(com.google.protobuf.CodedInputStream, com.google.protobuf.ExtensionRegistryLite) throws com.google.protobuf.InvalidProtocolBufferException;
    Code:
       0: aload_0
       1: invokespecial #19                 // Method "<init>":()V
       4: aload_2
       5: ifnonnull     16
       8: new           #20                 // class java/lang/NullPointerException
      11: dup
      12: invokespecial #21                 // Method java/lang/NullPointerException."<init>":()V
      15: athrow
      16: iconst_0
      17: istore_3
      18: invokestatic  #22                 // Method com/google/protobuf/UnknownFieldSet.newBuilder:()Lcom/google/protobuf/UnknownFieldSet$Builder;
      21: astore        4
      23: iconst_0
      24: istore        5
      26: iload         5
      28: ifne          273
      31: aload_1
      32: invokevirtual #23                 // Method com/google/protobuf/CodedInputStream.readTag:()I
      35: istore        6
      37: iload         6
      39: lookupswitch  { // 7
                     0: 104
                    10: 110
                    18: 125
                    26: 140
                    34: 182
                    42: 197
                    50: 239
               default: 254
          }
     104: iconst_1
     105: istore        5
     107: goto          270
     110: aload_1
     111: invokevirtual #24                 // Method com/google/protobuf/CodedInputStream.readStringRequireUtf8:()Ljava/lang/String;
     114: astore        7
     116: aload_0
     117: aload         7
     119: putfield      #11                 // Field summary_:Ljava/lang/Object;
     122: goto          270
     125: aload_1
     126: invokevirtual #24                 // Method com/google/protobuf/CodedInputStream.readStringRequireUtf8:()Ljava/lang/String;
     129: astore        7
     131: aload_0
     132: aload         7
     134: putfield      #6                  // Field overview_:Ljava/lang/Object;
     137: goto          270
     140: iload_3
     141: iconst_2
     142: iand
     143: ifne          161
     146: aload_0
     147: new           #25                 // class java/util/ArrayList
     150: dup
     151: invokespecial #26                 // Method java/util/ArrayList."<init>":()V
     154: putfield      #9                  // Field rules_:Ljava/util/List;
     157: iload_3
     158: iconst_2
     159: ior
     160: istore_3
     161: aload_0
     162: getfield      #9                  // Field rules_:Ljava/util/List;
     165: aload_1
     166: invokestatic  #27                 // Method com/google/api/DocumentationRule.parser:()Lcom/google/protobuf/Parser;
     169: aload_2
     170: invokevirtual #28                 // Method com/google/protobuf/CodedInputStream.readMessage:(Lcom/google/protobuf/Parser;Lcom/google/protobuf/ExtensionRegistryLite;)Lcom/google/protobuf/MessageLite;
     173: invokeinterface #29,  2           // InterfaceMethod java/util/List.add:(Ljava/lang/Object;)Z
     178: pop
     179: goto          270
     182: aload_1
     183: invokevirtual #24                 // Method com/google/protobuf/CodedInputStream.readStringRequireUtf8:()Ljava/lang/String;
     186: astore        7
     188: aload_0
     189: aload         7
     191: putfield      #8                  // Field documentationRootUrl_:Ljava/lang/Object;
     194: goto          270
     197: iload_3
     198: iconst_1
     199: iand
     200: ifne          218
     203: aload_0
     204: new           #25                 // class java/util/ArrayList
     207: dup
     208: invokespecial #26                 // Method java/util/ArrayList."<init>":()V
     211: putfield      #10                 // Field pages_:Ljava/util/List;
     214: iload_3
     215: iconst_1
     216: ior
     217: istore_3
     218: aload_0
     219: getfield      #10                 // Field pages_:Ljava/util/List;
     222: aload_1
     223: invokestatic  #30                 // Method com/google/api/Page.parser:()Lcom/google/protobuf/Parser;
     226: aload_2
     227: invokevirtual #28                 // Method com/google/protobuf/CodedInputStream.readMessage:(Lcom/google/protobuf/Parser;Lcom/google/protobuf/ExtensionRegistryLite;)Lcom/google/protobuf/MessageLite;
     230: invokeinterface #29,  2           // InterfaceMethod java/util/List.add:(Ljava/lang/Object;)Z
     235: pop
     236: goto          270
     239: aload_1
     240: invokevirtual #24                 // Method com/google/protobuf/CodedInputStream.readStringRequireUtf8:()Ljava/lang/String;
     243: astore        7
     245: aload_0
     246: aload         7
     248: putfield      #7                  // Field serviceRootUrl_:Ljava/lang/Object;
     251: goto          270
     254: aload_0
     255: aload_1
     256: aload         4
     258: aload_2
     259: iload         6
     261: invokevirtual #31                 // Method parseUnknownField:(Lcom/google/protobuf/CodedInputStream;Lcom/google/protobuf/UnknownFieldSet$Builder;Lcom/google/protobuf/ExtensionRegistryLite;I)Z
     264: ifne          270
     267: iconst_1
     268: istore        5
     270: goto          26
     273: iload_3
     274: iconst_2
     275: iand
     276: ifeq          290
     279: aload_0
     280: aload_0
     281: getfield      #9                  // Field rules_:Ljava/util/List;
     284: invokestatic  #32                 // Method java/util/Collections.unmodifiableList:(Ljava/util/List;)Ljava/util/List;
     287: putfield      #9                  // Field rules_:Ljava/util/List;
     290: iload_3
     291: iconst_1
     292: iand
     293: ifeq          307
     296: aload_0
     297: aload_0
     298: getfield      #10                 // Field pages_:Ljava/util/List;
     301: invokestatic  #32                 // Method java/util/Collections.unmodifiableList:(Ljava/util/List;)Ljava/util/List;
     304: putfield      #10                 // Field pages_:Ljava/util/List;
     307: aload_0
     308: aload         4
     310: invokevirtual #33                 // Method com/google/protobuf/UnknownFieldSet$Builder.build:()Lcom/google/protobuf/UnknownFieldSet;
     313: putfield      #4                  // Field unknownFields:Lcom/google/protobuf/UnknownFieldSet;
     316: aload_0
     317: invokevirtual #34                 // Method makeExtensionsImmutable:()V
     320: goto          400
     323: astore        5
     325: aload         5
     327: aload_0
     328: invokevirtual #36                 // Method com/google/protobuf/InvalidProtocolBufferException.setUnfinishedMessage:(Lcom/google/protobuf/MessageLite;)Lcom/google/protobuf/InvalidProtocolBufferException;
     331: athrow
     332: astore        5
     334: new           #35                 // class com/google/protobuf/InvalidProtocolBufferException
     337: dup
     338: aload         5
     340: invokespecial #38                 // Method com/google/protobuf/InvalidProtocolBufferException."<init>":(Ljava/io/IOException;)V
     343: aload_0
     344: invokevirtual #36                 // Method com/google/protobuf/InvalidProtocolBufferException.setUnfinishedMessage:(Lcom/google/protobuf/MessageLite;)Lcom/google/protobuf/InvalidProtocolBufferException;
     347: athrow
     348: astore        8
     350: iload_3
     351: iconst_2
     352: iand
     353: ifeq          367
     356: aload_0
     357: aload_0
     358: getfield      #9                  // Field rules_:Ljava/util/List;
     361: invokestatic  #32                 // Method java/util/Collections.unmodifiableList:(Ljava/util/List;)Ljava/util/List;
     364: putfield      #9                  // Field rules_:Ljava/util/List;
     367: iload_3
     368: iconst_1
     369: iand
     370: ifeq          384
     373: aload_0
     374: aload_0
     375: getfield      #10                 // Field pages_:Ljava/util/List;
     378: invokestatic  #32                 // Method java/util/Collections.unmodifiableList:(Ljava/util/List;)Ljava/util/List;
     381: putfield      #10                 // Field pages_:Ljava/util/List;
     384: aload_0
     385: aload         4
     387: invokevirtual #33                 // Method com/google/protobuf/UnknownFieldSet$Builder.build:()Lcom/google/protobuf/UnknownFieldSet;
     390: putfield      #4                  // Field unknownFields:Lcom/google/protobuf/UnknownFieldSet;
     393: aload_0
     394: invokevirtual #34                 // Method makeExtensionsImmutable:()V
     397: aload         8
     399: athrow
     400: return
    Exception table:
       from    to  target type
          23   273   323   Class com/google/protobuf/InvalidProtocolBufferException
          23   273   332   Class java/io/IOException
          23   273   348   any
         323   350   348   any

  public static final com.google.protobuf.Descriptors$Descriptor getDescriptor();
    Code:
       0: getstatic     #39                 // Field com/google/api/DocumentationProto.internal_static_google_api_Documentation_descriptor:Lcom/google/protobuf/Descriptors$Descriptor;
       3: areturn

  protected com.google.protobuf.GeneratedMessageV3$FieldAccessorTable internalGetFieldAccessorTable();
    Code:
       0: getstatic     #40                 // Field com/google/api/DocumentationProto.internal_static_google_api_Documentation_fieldAccessorTable:Lcom/google/protobuf/GeneratedMessageV3$FieldAccessorTable;
       3: ldc           #18                 // class com/google/api/Documentation
       5: ldc           #41                 // class com/google/api/Documentation$Builder
       7: invokevirtual #42                 // Method com/google/protobuf/GeneratedMessageV3$FieldAccessorTable.ensureFieldAccessorsInitialized:(Ljava/lang/Class;Ljava/lang/Class;)Lcom/google/protobuf/GeneratedMessageV3$FieldAccessorTable;
      10: areturn

  public java.lang.String getSummary();
    Code:
       0: aload_0
       1: getfield      #11                 // Field summary_:Ljava/lang/Object;
       4: astore_1
       5: aload_1
       6: instanceof    #43                 // class java/lang/String
       9: ifeq          17
      12: aload_1
      13: checkcast     #43                 // class java/lang/String
      16: areturn
      17: aload_1
      18: checkcast     #44                 // class com/google/protobuf/ByteString
      21: astore_2
      22: aload_2
      23: invokevirtual #45                 // Method com/google/protobuf/ByteString.toStringUtf8:()Ljava/lang/String;
      26: astore_3
      27: aload_0
      28: aload_3
      29: putfield      #11                 // Field summary_:Ljava/lang/Object;
      32: aload_3
      33: areturn

  public com.google.protobuf.ByteString getSummaryBytes();
    Code:
       0: aload_0
       1: getfield      #11                 // Field summary_:Ljava/lang/Object;
       4: astore_1
       5: aload_1
       6: instanceof    #43                 // class java/lang/String
       9: ifeq          27
      12: aload_1
      13: checkcast     #43                 // class java/lang/String
      16: invokestatic  #46                 // Method com/google/protobuf/ByteString.copyFromUtf8:(Ljava/lang/String;)Lcom/google/protobuf/ByteString;
      19: astore_2
      20: aload_0
      21: aload_2
      22: putfield      #11                 // Field summary_:Ljava/lang/Object;
      25: aload_2
      26: areturn
      27: aload_1
      28: checkcast     #44                 // class com/google/protobuf/ByteString
      31: areturn

  public java.util.List<com.google.api.Page> getPagesList();
    Code:
       0: aload_0
       1: getfield      #10                 // Field pages_:Ljava/util/List;
       4: areturn

  public java.util.List<? extends com.google.api.PageOrBuilder> getPagesOrBuilderList();
    Code:
       0: aload_0
       1: getfield      #10                 // Field pages_:Ljava/util/List;
       4: areturn

  public int getPagesCount();
    Code:
       0: aload_0
       1: getfield      #10                 // Field pages_:Ljava/util/List;
       4: invokeinterface #47,  1           // InterfaceMethod java/util/List.size:()I
       9: ireturn

  public com.google.api.Page getPages(int);
    Code:
       0: aload_0
       1: getfield      #10                 // Field pages_:Ljava/util/List;
       4: iload_1
       5: invokeinterface #48,  2           // InterfaceMethod java/util/List.get:(I)Ljava/lang/Object;
      10: checkcast     #49                 // class com/google/api/Page
      13: areturn

  public com.google.api.PageOrBuilder getPagesOrBuilder(int);
    Code:
       0: aload_0
       1: getfield      #10                 // Field pages_:Ljava/util/List;
       4: iload_1
       5: invokeinterface #48,  2           // InterfaceMethod java/util/List.get:(I)Ljava/lang/Object;
      10: checkcast     #50                 // class com/google/api/PageOrBuilder
      13: areturn

  public java.util.List<com.google.api.DocumentationRule> getRulesList();
    Code:
       0: aload_0
       1: getfield      #9                  // Field rules_:Ljava/util/List;
       4: areturn

  public java.util.List<? extends com.google.api.DocumentationRuleOrBuilder> getRulesOrBuilderList();
    Code:
       0: aload_0
       1: getfield      #9                  // Field rules_:Ljava/util/List;
       4: areturn

  public int getRulesCount();
    Code:
       0: aload_0
       1: getfield      #9                  // Field rules_:Ljava/util/List;
       4: invokeinterface #47,  1           // InterfaceMethod java/util/List.size:()I
       9: ireturn

  public com.google.api.DocumentationRule getRules(int);
    Code:
       0: aload_0
       1: getfield      #9                  // Field rules_:Ljava/util/List;
       4: iload_1
       5: invokeinterface #48,  2           // InterfaceMethod java/util/List.get:(I)Ljava/lang/Object;
      10: checkcast     #51                 // class com/google/api/DocumentationRule
      13: areturn

  public com.google.api.DocumentationRuleOrBuilder getRulesOrBuilder(int);
    Code:
       0: aload_0
       1: getfield      #9                  // Field rules_:Ljava/util/List;
       4: iload_1
       5: invokeinterface #48,  2           // InterfaceMethod java/util/List.get:(I)Ljava/lang/Object;
      10: checkcast     #52                 // class com/google/api/DocumentationRuleOrBuilder
      13: areturn

  public java.lang.String getDocumentationRootUrl();
    Code:
       0: aload_0
       1: getfield      #8                  // Field documentationRootUrl_:Ljava/lang/Object;
       4: astore_1
       5: aload_1
       6: instanceof    #43                 // class java/lang/String
       9: ifeq          17
      12: aload_1
      13: checkcast     #43                 // class java/lang/String
      16: areturn
      17: aload_1
      18: checkcast     #44                 // class com/google/protobuf/ByteString
      21: astore_2
      22: aload_2
      23: invokevirtual #45                 // Method com/google/protobuf/ByteString.toStringUtf8:()Ljava/lang/String;
      26: astore_3
      27: aload_0
      28: aload_3
      29: putfield      #8                  // Field documentationRootUrl_:Ljava/lang/Object;
      32: aload_3
      33: areturn

  public com.google.protobuf.ByteString getDocumentationRootUrlBytes();
    Code:
       0: aload_0
       1: getfield      #8                  // Field documentationRootUrl_:Ljava/lang/Object;
       4: astore_1
       5: aload_1
       6: instanceof    #43                 // class java/lang/String
       9: ifeq          27
      12: aload_1
      13: checkcast     #43                 // class java/lang/String
      16: invokestatic  #46                 // Method com/google/protobuf/ByteString.copyFromUtf8:(Ljava/lang/String;)Lcom/google/protobuf/ByteString;
      19: astore_2
      20: aload_0
      21: aload_2
      22: putfield      #8                  // Field documentationRootUrl_:Ljava/lang/Object;
      25: aload_2
      26: areturn
      27: aload_1
      28: checkcast     #44                 // class com/google/protobuf/ByteString
      31: areturn

  public java.lang.String getServiceRootUrl();
    Code:
       0: aload_0
       1: getfield      #7                  // Field serviceRootUrl_:Ljava/lang/Object;
       4: astore_1
       5: aload_1
       6: instanceof    #43                 // class java/lang/String
       9: ifeq          17
      12: aload_1
      13: checkcast     #43                 // class java/lang/String
      16: areturn
      17: aload_1
      18: checkcast     #44                 // class com/google/protobuf/ByteString
      21: astore_2
      22: aload_2
      23: invokevirtual #45                 // Method com/google/protobuf/ByteString.toStringUtf8:()Ljava/lang/String;
      26: astore_3
      27: aload_0
      28: aload_3
      29: putfield      #7                  // Field serviceRootUrl_:Ljava/lang/Object;
      32: aload_3
      33: areturn

  public com.google.protobuf.ByteString getServiceRootUrlBytes();
    Code:
       0: aload_0
       1: getfield      #7                  // Field serviceRootUrl_:Ljava/lang/Object;
       4: astore_1
       5: aload_1
       6: instanceof    #43                 // class java/lang/String
       9: ifeq          27
      12: aload_1
      13: checkcast     #43                 // class java/lang/String
      16: invokestatic  #46                 // Method com/google/protobuf/ByteString.copyFromUtf8:(Ljava/lang/String;)Lcom/google/protobuf/ByteString;
      19: astore_2
      20: aload_0
      21: aload_2
      22: putfield      #7                  // Field serviceRootUrl_:Ljava/lang/Object;
      25: aload_2
      26: areturn
      27: aload_1
      28: checkcast     #44                 // class com/google/protobuf/ByteString
      31: areturn

  public java.lang.String getOverview();
    Code:
       0: aload_0
       1: getfield      #6                  // Field overview_:Ljava/lang/Object;
       4: astore_1
       5: aload_1
       6: instanceof    #43                 // class java/lang/String
       9: ifeq          17
      12: aload_1
      13: checkcast     #43                 // class java/lang/String
      16: areturn
      17: aload_1
      18: checkcast     #44                 // class com/google/protobuf/ByteString
      21: astore_2
      22: aload_2
      23: invokevirtual #45                 // Method com/google/protobuf/ByteString.toStringUtf8:()Ljava/lang/String;
      26: astore_3
      27: aload_0
      28: aload_3
      29: putfield      #6                  // Field overview_:Ljava/lang/Object;
      32: aload_3
      33: areturn

  public com.google.protobuf.ByteString getOverviewBytes();
    Code:
       0: aload_0
       1: getfield      #6                  // Field overview_:Ljava/lang/Object;
       4: astore_1
       5: aload_1
       6: instanceof    #43                 // class java/lang/String
       9: ifeq          27
      12: aload_1
      13: checkcast     #43                 // class java/lang/String
      16: invokestatic  #46                 // Method com/google/protobuf/ByteString.copyFromUtf8:(Ljava/lang/String;)Lcom/google/protobuf/ByteString;
      19: astore_2
      20: aload_0
      21: aload_2
      22: putfield      #6                  // Field overview_:Ljava/lang/Object;
      25: aload_2
      26: areturn
      27: aload_1
      28: checkcast     #44                 // class com/google/protobuf/ByteString
      31: areturn

  public final boolean isInitialized();
    Code:
       0: aload_0
       1: getfield      #14                 // Field memoizedIsInitialized:B
       4: istore_1
       5: iload_1
       6: iconst_1
       7: if_icmpne     12
      10: iconst_1
      11: ireturn
      12: iload_1
      13: ifne          18
      16: iconst_0
      17: ireturn
      18: aload_0
      19: iconst_1
      20: putfield      #14                 // Field memoizedIsInitialized:B
      23: iconst_1
      24: ireturn

  public void writeTo(com.google.protobuf.CodedOutputStream) throws java.io.IOException;
    Code:
       0: aload_0
       1: invokevirtual #53                 // Method getSummaryBytes:()Lcom/google/protobuf/ByteString;
       4: invokevirtual #54                 // Method com/google/protobuf/ByteString.isEmpty:()Z
       7: ifne          19
      10: aload_1
      11: iconst_1
      12: aload_0
      13: getfield      #11                 // Field summary_:Ljava/lang/Object;
      16: invokestatic  #55                 // Method com/google/protobuf/GeneratedMessageV3.writeString:(Lcom/google/protobuf/CodedOutputStream;ILjava/lang/Object;)V
      19: aload_0
      20: invokevirtual #56                 // Method getOverviewBytes:()Lcom/google/protobuf/ByteString;
      23: invokevirtual #54                 // Method com/google/protobuf/ByteString.isEmpty:()Z
      26: ifne          38
      29: aload_1
      30: iconst_2
      31: aload_0
      32: getfield      #6                  // Field overview_:Ljava/lang/Object;
      35: invokestatic  #55                 // Method com/google/protobuf/GeneratedMessageV3.writeString:(Lcom/google/protobuf/CodedOutputStream;ILjava/lang/Object;)V
      38: iconst_0
      39: istore_2
      40: iload_2
      41: aload_0
      42: getfield      #9                  // Field rules_:Ljava/util/List;
      45: invokeinterface #47,  1           // InterfaceMethod java/util/List.size:()I
      50: if_icmpge     77
      53: aload_1
      54: iconst_3
      55: aload_0
      56: getfield      #9                  // Field rules_:Ljava/util/List;
      59: iload_2
      60: invokeinterface #48,  2           // InterfaceMethod java/util/List.get:(I)Ljava/lang/Object;
      65: checkcast     #57                 // class com/google/protobuf/MessageLite
      68: invokevirtual #58                 // Method com/google/protobuf/CodedOutputStream.writeMessage:(ILcom/google/protobuf/MessageLite;)V
      71: iinc          2, 1
      74: goto          40
      77: aload_0
      78: invokevirtual #59                 // Method getDocumentationRootUrlBytes:()Lcom/google/protobuf/ByteString;
      81: invokevirtual #54                 // Method com/google/protobuf/ByteString.isEmpty:()Z
      84: ifne          96
      87: aload_1
      88: iconst_4
      89: aload_0
      90: getfield      #8                  // Field documentationRootUrl_:Ljava/lang/Object;
      93: invokestatic  #55                 // Method com/google/protobuf/GeneratedMessageV3.writeString:(Lcom/google/protobuf/CodedOutputStream;ILjava/lang/Object;)V
      96: iconst_0
      97: istore_2
      98: iload_2
      99: aload_0
     100: getfield      #10                 // Field pages_:Ljava/util/List;
     103: invokeinterface #47,  1           // InterfaceMethod java/util/List.size:()I
     108: if_icmpge     135
     111: aload_1
     112: iconst_5
     113: aload_0
     114: getfield      #10                 // Field pages_:Ljava/util/List;
     117: iload_2
     118: invokeinterface #48,  2           // InterfaceMethod java/util/List.get:(I)Ljava/lang/Object;
     123: checkcast     #57                 // class com/google/protobuf/MessageLite
     126: invokevirtual #58                 // Method com/google/protobuf/CodedOutputStream.writeMessage:(ILcom/google/protobuf/MessageLite;)V
     129: iinc          2, 1
     132: goto          98
     135: aload_0
     136: invokevirtual #60                 // Method getServiceRootUrlBytes:()Lcom/google/protobuf/ByteString;
     139: invokevirtual #54                 // Method com/google/protobuf/ByteString.isEmpty:()Z
     142: ifne          155
     145: aload_1
     146: bipush        6
     148: aload_0
     149: getfield      #7                  // Field serviceRootUrl_:Ljava/lang/Object;
     152: invokestatic  #55                 // Method com/google/protobuf/GeneratedMessageV3.writeString:(Lcom/google/protobuf/CodedOutputStream;ILjava/lang/Object;)V
     155: aload_0
     156: getfield      #4                  // Field unknownFields:Lcom/google/protobuf/UnknownFieldSet;
     159: aload_1
     160: invokevirtual #61                 // Method com/google/protobuf/UnknownFieldSet.writeTo:(Lcom/google/protobuf/CodedOutputStream;)V
     163: return

  public int getSerializedSize();
    Code:
       0: aload_0
       1: getfield      #62                 // Field memoizedSize:I
       4: istore_1
       5: iload_1
       6: iconst_m1
       7: if_icmpeq     12
      10: iload_1
      11: ireturn
      12: iconst_0
      13: istore_1
      14: aload_0
      15: invokevirtual #53                 // Method getSummaryBytes:()Lcom/google/protobuf/ByteString;
      18: invokevirtual #54                 // Method com/google/protobuf/ByteString.isEmpty:()Z
      21: ifne          35
      24: iload_1
      25: iconst_1
      26: aload_0
      27: getfield      #11                 // Field summary_:Ljava/lang/Object;
      30: invokestatic  #63                 // Method com/google/protobuf/GeneratedMessageV3.computeStringSize:(ILjava/lang/Object;)I
      33: iadd
      34: istore_1
      35: aload_0
      36: invokevirtual #56                 // Method getOverviewBytes:()Lcom/google/protobuf/ByteString;
      39: invokevirtual #54                 // Method com/google/protobuf/ByteString.isEmpty:()Z
      42: ifne          56
      45: iload_1
      46: iconst_2
      47: aload_0
      48: getfield      #6                  // Field overview_:Ljava/lang/Object;
      51: invokestatic  #63                 // Method com/google/protobuf/GeneratedMessageV3.computeStringSize:(ILjava/lang/Object;)I
      54: iadd
      55: istore_1
      56: iconst_0
      57: istore_2
      58: iload_2
      59: aload_0
      60: getfield      #9                  // Field rules_:Ljava/util/List;
      63: invokeinterface #47,  1           // InterfaceMethod java/util/List.size:()I
      68: if_icmpge     97
      71: iload_1
      72: iconst_3
      73: aload_0
      74: getfield      #9                  // Field rules_:Ljava/util/List;
      77: iload_2
      78: invokeinterface #48,  2           // InterfaceMethod java/util/List.get:(I)Ljava/lang/Object;
      83: checkcast     #57                 // class com/google/protobuf/MessageLite
      86: invokestatic  #64                 // Method com/google/protobuf/CodedOutputStream.computeMessageSize:(ILcom/google/protobuf/MessageLite;)I
      89: iadd
      90: istore_1
      91: iinc          2, 1
      94: goto          58
      97: aload_0
      98: invokevirtual #59                 // Method getDocumentationRootUrlBytes:()Lcom/google/protobuf/ByteString;
     101: invokevirtual #54                 // Method com/google/protobuf/ByteString.isEmpty:()Z
     104: ifne          118
     107: iload_1
     108: iconst_4
     109: aload_0
     110: getfield      #8                  // Field documentationRootUrl_:Ljava/lang/Object;
     113: invokestatic  #63                 // Method com/google/protobuf/GeneratedMessageV3.computeStringSize:(ILjava/lang/Object;)I
     116: iadd
     117: istore_1
     118: iconst_0
     119: istore_2
     120: iload_2
     121: aload_0
     122: getfield      #10                 // Field pages_:Ljava/util/List;
     125: invokeinterface #47,  1           // InterfaceMethod java/util/List.size:()I
     130: if_icmpge     159
     133: iload_1
     134: iconst_5
     135: aload_0
     136: getfield      #10                 // Field pages_:Ljava/util/List;
     139: iload_2
     140: invokeinterface #48,  2           // InterfaceMethod java/util/List.get:(I)Ljava/lang/Object;
     145: checkcast     #57                 // class com/google/protobuf/MessageLite
     148: invokestatic  #64                 // Method com/google/protobuf/CodedOutputStream.computeMessageSize:(ILcom/google/protobuf/MessageLite;)I
     151: iadd
     152: istore_1
     153: iinc          2, 1
     156: goto          120
     159: aload_0
     160: invokevirtual #60                 // Method getServiceRootUrlBytes:()Lcom/google/protobuf/ByteString;
     163: invokevirtual #54                 // Method com/google/protobuf/ByteString.isEmpty:()Z
     166: ifne          181
     169: iload_1
     170: bipush        6
     172: aload_0
     173: getfield      #7                  // Field serviceRootUrl_:Ljava/lang/Object;
     176: invokestatic  #63                 // Method com/google/protobuf/GeneratedMessageV3.computeStringSize:(ILjava/lang/Object;)I
     179: iadd
     180: istore_1
     181: iload_1
     182: aload_0
     183: getfield      #4                  // Field unknownFields:Lcom/google/protobuf/UnknownFieldSet;
     186: invokevirtual #65                 // Method com/google/protobuf/UnknownFieldSet.getSerializedSize:()I
     189: iadd
     190: istore_1
     191: aload_0
     192: iload_1
     193: putfield      #62                 // Field memoizedSize:I
     196: iload_1
     197: ireturn

  public boolean equals(java.lang.Object);
    Code:
       0: aload_1
       1: aload_0
       2: if_acmpne     7
       5: iconst_1
       6: ireturn
       7: aload_1
       8: instanceof    #18                 // class com/google/api/Documentation
      11: ifne          20
      14: aload_0
      15: aload_1
      16: invokespecial #66                 // Method com/google/protobuf/GeneratedMessageV3.equals:(Ljava/lang/Object;)Z
      19: ireturn
      20: aload_1
      21: checkcast     #18                 // class com/google/api/Documentation
      24: astore_2
      25: aload_0
      26: invokevirtual #67                 // Method getSummary:()Ljava/lang/String;
      29: aload_2
      30: invokevirtual #67                 // Method getSummary:()Ljava/lang/String;
      33: invokevirtual #68                 // Method java/lang/String.equals:(Ljava/lang/Object;)Z
      36: ifne          41
      39: iconst_0
      40: ireturn
      41: aload_0
      42: invokevirtual #69                 // Method getPagesList:()Ljava/util/List;
      45: aload_2
      46: invokevirtual #69                 // Method getPagesList:()Ljava/util/List;
      49: invokeinterface #70,  2           // InterfaceMethod java/util/List.equals:(Ljava/lang/Object;)Z
      54: ifne          59
      57: iconst_0
      58: ireturn
      59: aload_0
      60: invokevirtual #71                 // Method getRulesList:()Ljava/util/List;
      63: aload_2
      64: invokevirtual #71                 // Method getRulesList:()Ljava/util/List;
      67: invokeinterface #70,  2           // InterfaceMethod java/util/List.equals:(Ljava/lang/Object;)Z
      72: ifne          77
      75: iconst_0
      76: ireturn
      77: aload_0
      78: invokevirtual #72                 // Method getDocumentationRootUrl:()Ljava/lang/String;
      81: aload_2
      82: invokevirtual #72                 // Method getDocumentationRootUrl:()Ljava/lang/String;
      85: invokevirtual #68                 // Method java/lang/String.equals:(Ljava/lang/Object;)Z
      88: ifne          93
      91: iconst_0
      92: ireturn
      93: aload_0
      94: invokevirtual #73                 // Method getServiceRootUrl:()Ljava/lang/String;
      97: aload_2
      98: invokevirtual #73                 // Method getServiceRootUrl:()Ljava/lang/String;
     101: invokevirtual #68                 // Method java/lang/String.equals:(Ljava/lang/Object;)Z
     104: ifne          109
     107: iconst_0
     108: ireturn
     109: aload_0
     110: invokevirtual #74                 // Method getOverview:()Ljava/lang/String;
     113: aload_2
     114: invokevirtual #74                 // Method getOverview:()Ljava/lang/String;
     117: invokevirtual #68                 // Method java/lang/String.equals:(Ljava/lang/Object;)Z
     120: ifne          125
     123: iconst_0
     124: ireturn
     125: aload_0
     126: getfield      #4                  // Field unknownFields:Lcom/google/protobuf/UnknownFieldSet;
     129: aload_2
     130: getfield      #4                  // Field unknownFields:Lcom/google/protobuf/UnknownFieldSet;
     133: invokevirtual #75                 // Method com/google/protobuf/UnknownFieldSet.equals:(Ljava/lang/Object;)Z
     136: ifne          141
     139: iconst_0
     140: ireturn
     141: iconst_1
     142: ireturn

  public int hashCode();
    Code:
       0: aload_0
       1: getfield      #76                 // Field memoizedHashCode:I
       4: ifeq          12
       7: aload_0
       8: getfield      #76                 // Field memoizedHashCode:I
      11: ireturn
      12: bipush        41
      14: istore_1
      15: bipush        19
      17: iload_1
      18: imul
      19: invokestatic  #77                 // Method getDescriptor:()Lcom/google/protobuf/Descriptors$Descriptor;
      22: invokevirtual #78                 // Method java/lang/Object.hashCode:()I
      25: iadd
      26: istore_1
      27: bipush        37
      29: iload_1
      30: imul
      31: iconst_1
      32: iadd
      33: istore_1
      34: bipush        53
      36: iload_1
      37: imul
      38: aload_0
      39: invokevirtual #67                 // Method getSummary:()Ljava/lang/String;
      42: invokevirtual #79                 // Method java/lang/String.hashCode:()I
      45: iadd
      46: istore_1
      47: aload_0
      48: invokevirtual #80                 // Method getPagesCount:()I
      51: ifle          76
      54: bipush        37
      56: iload_1
      57: imul
      58: iconst_5
      59: iadd
      60: istore_1
      61: bipush        53
      63: iload_1
      64: imul
      65: aload_0
      66: invokevirtual #69                 // Method getPagesList:()Ljava/util/List;
      69: invokeinterface #81,  1           // InterfaceMethod java/util/List.hashCode:()I
      74: iadd
      75: istore_1
      76: aload_0
      77: invokevirtual #82                 // Method getRulesCount:()I
      80: ifle          105
      83: bipush        37
      85: iload_1
      86: imul
      87: iconst_3
      88: iadd
      89: istore_1
      90: bipush        53
      92: iload_1
      93: imul
      94: aload_0
      95: invokevirtual #71                 // Method getRulesList:()Ljava/util/List;
      98: invokeinterface #81,  1           // InterfaceMethod java/util/List.hashCode:()I
     103: iadd
     104: istore_1
     105: bipush        37
     107: iload_1
     108: imul
     109: iconst_4
     110: iadd
     111: istore_1
     112: bipush        53
     114: iload_1
     115: imul
     116: aload_0
     117: invokevirtual #72                 // Method getDocumentationRootUrl:()Ljava/lang/String;
     120: invokevirtual #79                 // Method java/lang/String.hashCode:()I
     123: iadd
     124: istore_1
     125: bipush        37
     127: iload_1
     128: imul
     129: bipush        6
     131: iadd
     132: istore_1
     133: bipush        53
     135: iload_1
     136: imul
     137: aload_0
     138: invokevirtual #73                 // Method getServiceRootUrl:()Ljava/lang/String;
     141: invokevirtual #79                 // Method java/lang/String.hashCode:()I
     144: iadd
     145: istore_1
     146: bipush        37
     148: iload_1
     149: imul
     150: iconst_2
     151: iadd
     152: istore_1
     153: bipush        53
     155: iload_1
     156: imul
     157: aload_0
     158: invokevirtual #74                 // Method getOverview:()Ljava/lang/String;
     161: invokevirtual #79                 // Method java/lang/String.hashCode:()I
     164: iadd
     165: istore_1
     166: bipush        29
     168: iload_1
     169: imul
     170: aload_0
     171: getfield      #4                  // Field unknownFields:Lcom/google/protobuf/UnknownFieldSet;
     174: invokevirtual #83                 // Method com/google/protobuf/UnknownFieldSet.hashCode:()I
     177: iadd
     178: istore_1
     179: aload_0
     180: iload_1
     181: putfield      #76                 // Field memoizedHashCode:I
     184: iload_1
     185: ireturn

  public static com.google.api.Documentation parseFrom(java.nio.ByteBuffer) throws com.google.protobuf.InvalidProtocolBufferException;
    Code:
       0: getstatic     #3                  // Field PARSER:Lcom/google/protobuf/Parser;
       3: aload_0
       4: invokeinterface #84,  2           // InterfaceMethod com/google/protobuf/Parser.parseFrom:(Ljava/nio/ByteBuffer;)Ljava/lang/Object;
       9: checkcast     #18                 // class com/google/api/Documentation
      12: areturn

  public static com.google.api.Documentation parseFrom(java.nio.ByteBuffer, com.google.protobuf.ExtensionRegistryLite) throws com.google.protobuf.InvalidProtocolBufferException;
    Code:
       0: getstatic     #3                  // Field PARSER:Lcom/google/protobuf/Parser;
       3: aload_0
       4: aload_1
       5: invokeinterface #85,  3           // InterfaceMethod com/google/protobuf/Parser.parseFrom:(Ljava/nio/ByteBuffer;Lcom/google/protobuf/ExtensionRegistryLite;)Ljava/lang/Object;
      10: checkcast     #18                 // class com/google/api/Documentation
      13: areturn

  public static com.google.api.Documentation parseFrom(com.google.protobuf.ByteString) throws com.google.protobuf.InvalidProtocolBufferException;
    Code:
       0: getstatic     #3                  // Field PARSER:Lcom/google/protobuf/Parser;
       3: aload_0
       4: invokeinterface #86,  2           // InterfaceMethod com/google/protobuf/Parser.parseFrom:(Lcom/google/protobuf/ByteString;)Ljava/lang/Object;
       9: checkcast     #18                 // class com/google/api/Documentation
      12: areturn

  public static com.google.api.Documentation parseFrom(com.google.protobuf.ByteString, com.google.protobuf.ExtensionRegistryLite) throws com.google.protobuf.InvalidProtocolBufferException;
    Code:
       0: getstatic     #3                  // Field PARSER:Lcom/google/protobuf/Parser;
       3: aload_0
       4: aload_1
       5: invokeinterface #87,  3           // InterfaceMethod com/google/protobuf/Parser.parseFrom:(Lcom/google/protobuf/ByteString;Lcom/google/protobuf/ExtensionRegistryLite;)Ljava/lang/Object;
      10: checkcast     #18                 // class com/google/api/Documentation
      13: areturn

  public static com.google.api.Documentation parseFrom(byte[]) throws com.google.protobuf.InvalidProtocolBufferException;
    Code:
       0: getstatic     #3                  // Field PARSER:Lcom/google/protobuf/Parser;
       3: aload_0
       4: invokeinterface #88,  2           // InterfaceMethod com/google/protobuf/Parser.parseFrom:([B)Ljava/lang/Object;
       9: checkcast     #18                 // class com/google/api/Documentation
      12: areturn

  public static com.google.api.Documentation parseFrom(byte[], com.google.protobuf.ExtensionRegistryLite) throws com.google.protobuf.InvalidProtocolBufferException;
    Code:
       0: getstatic     #3                  // Field PARSER:Lcom/google/protobuf/Parser;
       3: aload_0
       4: aload_1
       5: invokeinterface #89,  3           // InterfaceMethod com/google/protobuf/Parser.parseFrom:([BLcom/google/protobuf/ExtensionRegistryLite;)Ljava/lang/Object;
      10: checkcast     #18                 // class com/google/api/Documentation
      13: areturn

  public static com.google.api.Documentation parseFrom(java.io.InputStream) throws java.io.IOException;
    Code:
       0: getstatic     #3                  // Field PARSER:Lcom/google/protobuf/Parser;
       3: aload_0
       4: invokestatic  #90                 // Method com/google/protobuf/GeneratedMessageV3.parseWithIOException:(Lcom/google/protobuf/Parser;Ljava/io/InputStream;)Lcom/google/protobuf/Message;
       7: checkcast     #18                 // class com/google/api/Documentation
      10: areturn

  public static com.google.api.Documentation parseFrom(java.io.InputStream, com.google.protobuf.ExtensionRegistryLite) throws java.io.IOException;
    Code:
       0: getstatic     #3                  // Field PARSER:Lcom/google/protobuf/Parser;
       3: aload_0
       4: aload_1
       5: invokestatic  #91                 // Method com/google/protobuf/GeneratedMessageV3.parseWithIOException:(Lcom/google/protobuf/Parser;Ljava/io/InputStream;Lcom/google/protobuf/ExtensionRegistryLite;)Lcom/google/protobuf/Message;
       8: checkcast     #18                 // class com/google/api/Documentation
      11: areturn

  public static com.google.api.Documentation parseDelimitedFrom(java.io.InputStream) throws java.io.IOException;
    Code:
       0: getstatic     #3                  // Field PARSER:Lcom/google/protobuf/Parser;
       3: aload_0
       4: invokestatic  #92                 // Method com/google/protobuf/GeneratedMessageV3.parseDelimitedWithIOException:(Lcom/google/protobuf/Parser;Ljava/io/InputStream;)Lcom/google/protobuf/Message;
       7: checkcast     #18                 // class com/google/api/Documentation
      10: areturn

  public static com.google.api.Documentation parseDelimitedFrom(java.io.InputStream, com.google.protobuf.ExtensionRegistryLite) throws java.io.IOException;
    Code:
       0: getstatic     #3                  // Field PARSER:Lcom/google/protobuf/Parser;
       3: aload_0
       4: aload_1
       5: invokestatic  #93                 // Method com/google/protobuf/GeneratedMessageV3.parseDelimitedWithIOException:(Lcom/google/protobuf/Parser;Ljava/io/InputStream;Lcom/google/protobuf/ExtensionRegistryLite;)Lcom/google/protobuf/Message;
       8: checkcast     #18                 // class com/google/api/Documentation
      11: areturn

  public static com.google.api.Documentation parseFrom(com.google.protobuf.CodedInputStream) throws java.io.IOException;
    Code:
       0: getstatic     #3                  // Field PARSER:Lcom/google/protobuf/Parser;
       3: aload_0
       4: invokestatic  #94                 // Method com/google/protobuf/GeneratedMessageV3.parseWithIOException:(Lcom/google/protobuf/Parser;Lcom/google/protobuf/CodedInputStream;)Lcom/google/protobuf/Message;
       7: checkcast     #18                 // class com/google/api/Documentation
      10: areturn

  public static com.google.api.Documentation parseFrom(com.google.protobuf.CodedInputStream, com.google.protobuf.ExtensionRegistryLite) throws java.io.IOException;
    Code:
       0: getstatic     #3                  // Field PARSER:Lcom/google/protobuf/Parser;
       3: aload_0
       4: aload_1
       5: invokestatic  #95                 // Method com/google/protobuf/GeneratedMessageV3.parseWithIOException:(Lcom/google/protobuf/Parser;Lcom/google/protobuf/CodedInputStream;Lcom/google/protobuf/ExtensionRegistryLite;)Lcom/google/protobuf/Message;
       8: checkcast     #18                 // class com/google/api/Documentation
      11: areturn

  public com.google.api.Documentation$Builder newBuilderForType();
    Code:
       0: invokestatic  #96                 // Method newBuilder:()Lcom/google/api/Documentation$Builder;
       3: areturn

  public static com.google.api.Documentation$Builder newBuilder();
    Code:
       0: getstatic     #97                 // Field DEFAULT_INSTANCE:Lcom/google/api/Documentation;
       3: invokevirtual #98                 // Method toBuilder:()Lcom/google/api/Documentation$Builder;
       6: areturn

  public static com.google.api.Documentation$Builder newBuilder(com.google.api.Documentation);
    Code:
       0: getstatic     #97                 // Field DEFAULT_INSTANCE:Lcom/google/api/Documentation;
       3: invokevirtual #98                 // Method toBuilder:()Lcom/google/api/Documentation$Builder;
       6: aload_0
       7: invokevirtual #99                 // Method com/google/api/Documentation$Builder.mergeFrom:(Lcom/google/api/Documentation;)Lcom/google/api/Documentation$Builder;
      10: areturn

  public com.google.api.Documentation$Builder toBuilder();
    Code:
       0: aload_0
       1: getstatic     #97                 // Field DEFAULT_INSTANCE:Lcom/google/api/Documentation;
       4: if_acmpne     18
       7: new           #41                 // class com/google/api/Documentation$Builder
      10: dup
      11: aconst_null
      12: invokespecial #100                // Method com/google/api/Documentation$Builder."<init>":(Lcom/google/api/Documentation$1;)V
      15: goto          30
      18: new           #41                 // class com/google/api/Documentation$Builder
      21: dup
      22: aconst_null
      23: invokespecial #100                // Method com/google/api/Documentation$Builder."<init>":(Lcom/google/api/Documentation$1;)V
      26: aload_0
      27: invokevirtual #99                 // Method com/google/api/Documentation$Builder.mergeFrom:(Lcom/google/api/Documentation;)Lcom/google/api/Documentation$Builder;
      30: areturn

  protected com.google.api.Documentation$Builder newBuilderForType(com.google.protobuf.GeneratedMessageV3$BuilderParent);
    Code:
       0: new           #41                 // class com/google/api/Documentation$Builder
       3: dup
       4: aload_1
       5: aconst_null
       6: invokespecial #101                // Method com/google/api/Documentation$Builder."<init>":(Lcom/google/protobuf/GeneratedMessageV3$BuilderParent;Lcom/google/api/Documentation$1;)V
       9: astore_2
      10: aload_2
      11: areturn

  public static com.google.api.Documentation getDefaultInstance();
    Code:
       0: getstatic     #97                 // Field DEFAULT_INSTANCE:Lcom/google/api/Documentation;
       3: areturn

  public static com.google.protobuf.Parser<com.google.api.Documentation> parser();
    Code:
       0: getstatic     #3                  // Field PARSER:Lcom/google/protobuf/Parser;
       3: areturn

  public com.google.protobuf.Parser<com.google.api.Documentation> getParserForType();
    Code:
       0: getstatic     #3                  // Field PARSER:Lcom/google/protobuf/Parser;
       3: areturn

  public com.google.api.Documentation getDefaultInstanceForType();
    Code:
       0: getstatic     #97                 // Field DEFAULT_INSTANCE:Lcom/google/api/Documentation;
       3: areturn

  protected com.google.protobuf.Message$Builder newBuilderForType(com.google.protobuf.GeneratedMessageV3$BuilderParent);
    Code:
       0: aload_0
       1: aload_1
       2: invokevirtual #102                // Method newBuilderForType:(Lcom/google/protobuf/GeneratedMessageV3$BuilderParent;)Lcom/google/api/Documentation$Builder;
       5: areturn

  public com.google.protobuf.Message$Builder toBuilder();
    Code:
       0: aload_0
       1: invokevirtual #98                 // Method toBuilder:()Lcom/google/api/Documentation$Builder;
       4: areturn

  public com.google.protobuf.Message$Builder newBuilderForType();
    Code:
       0: aload_0
       1: invokevirtual #103                // Method newBuilderForType:()Lcom/google/api/Documentation$Builder;
       4: areturn

  public com.google.protobuf.MessageLite$Builder toBuilder();
    Code:
       0: aload_0
       1: invokevirtual #98                 // Method toBuilder:()Lcom/google/api/Documentation$Builder;
       4: areturn

  public com.google.protobuf.MessageLite$Builder newBuilderForType();
    Code:
       0: aload_0
       1: invokevirtual #103                // Method newBuilderForType:()Lcom/google/api/Documentation$Builder;
       4: areturn

  public com.google.protobuf.MessageLite getDefaultInstanceForType();
    Code:
       0: aload_0
       1: invokevirtual #104                // Method getDefaultInstanceForType:()Lcom/google/api/Documentation;
       4: areturn

  public com.google.protobuf.Message getDefaultInstanceForType();
    Code:
       0: aload_0
       1: invokevirtual #104                // Method getDefaultInstanceForType:()Lcom/google/api/Documentation;
       4: areturn

  static boolean access$200();
    Code:
       0: getstatic     #5                  // Field alwaysUseFieldBuilders:Z
       3: ireturn

  com.google.api.Documentation(com.google.protobuf.GeneratedMessageV3$Builder, com.google.api.Documentation$1);
    Code:
       0: aload_0
       1: aload_1
       2: invokespecial #12                 // Method "<init>":(Lcom/google/protobuf/GeneratedMessageV3$Builder;)V
       5: return

  static java.lang.Object access$402(com.google.api.Documentation, java.lang.Object);
    Code:
       0: aload_0
       1: aload_1
       2: dup_x1
       3: putfield      #11                 // Field summary_:Ljava/lang/Object;
       6: areturn

  static java.util.List access$502(com.google.api.Documentation, java.util.List);
    Code:
       0: aload_0
       1: aload_1
       2: dup_x1
       3: putfield      #10                 // Field pages_:Ljava/util/List;
       6: areturn

  static java.util.List access$602(com.google.api.Documentation, java.util.List);
    Code:
       0: aload_0
       1: aload_1
       2: dup_x1
       3: putfield      #9                  // Field rules_:Ljava/util/List;
       6: areturn

  static java.lang.Object access$702(com.google.api.Documentation, java.lang.Object);
    Code:
       0: aload_0
       1: aload_1
       2: dup_x1
       3: putfield      #8                  // Field documentationRootUrl_:Ljava/lang/Object;
       6: areturn

  static java.lang.Object access$802(com.google.api.Documentation, java.lang.Object);
    Code:
       0: aload_0
       1: aload_1
       2: dup_x1
       3: putfield      #7                  // Field serviceRootUrl_:Ljava/lang/Object;
       6: areturn

  static java.lang.Object access$902(com.google.api.Documentation, java.lang.Object);
    Code:
       0: aload_0
       1: aload_1
       2: dup_x1
       3: putfield      #6                  // Field overview_:Ljava/lang/Object;
       6: areturn

  static java.lang.Object access$400(com.google.api.Documentation);
    Code:
       0: aload_0
       1: getfield      #11                 // Field summary_:Ljava/lang/Object;
       4: areturn

  static java.util.List access$500(com.google.api.Documentation);
    Code:
       0: aload_0
       1: getfield      #10                 // Field pages_:Ljava/util/List;
       4: areturn

  static boolean access$1000();
    Code:
       0: getstatic     #5                  // Field alwaysUseFieldBuilders:Z
       3: ireturn

  static java.util.List access$600(com.google.api.Documentation);
    Code:
       0: aload_0
       1: getfield      #9                  // Field rules_:Ljava/util/List;
       4: areturn

  static boolean access$1100();
    Code:
       0: getstatic     #5                  // Field alwaysUseFieldBuilders:Z
       3: ireturn

  static java.lang.Object access$700(com.google.api.Documentation);
    Code:
       0: aload_0
       1: getfield      #8                  // Field documentationRootUrl_:Ljava/lang/Object;
       4: areturn

  static java.lang.Object access$800(com.google.api.Documentation);
    Code:
       0: aload_0
       1: getfield      #7                  // Field serviceRootUrl_:Ljava/lang/Object;
       4: areturn

  static java.lang.Object access$900(com.google.api.Documentation);
    Code:
       0: aload_0
       1: getfield      #6                  // Field overview_:Ljava/lang/Object;
       4: areturn

  static com.google.protobuf.UnknownFieldSet access$1200(com.google.api.Documentation);
    Code:
       0: aload_0
       1: getfield      #4                  // Field unknownFields:Lcom/google/protobuf/UnknownFieldSet;
       4: areturn

  static com.google.protobuf.Parser access$1300();
    Code:
       0: getstatic     #3                  // Field PARSER:Lcom/google/protobuf/Parser;
       3: areturn

  static void access$1400(com.google.protobuf.ByteString) throws java.lang.IllegalArgumentException;
    Code:
       0: aload_0
       1: invokestatic  #2                  // Method checkByteStringIsUtf8:(Lcom/google/protobuf/ByteString;)V
       4: return

  static void access$1500(com.google.protobuf.ByteString) throws java.lang.IllegalArgumentException;
    Code:
       0: aload_0
       1: invokestatic  #2                  // Method checkByteStringIsUtf8:(Lcom/google/protobuf/ByteString;)V
       4: return

  static void access$1600(com.google.protobuf.ByteString) throws java.lang.IllegalArgumentException;
    Code:
       0: aload_0
       1: invokestatic  #2                  // Method checkByteStringIsUtf8:(Lcom/google/protobuf/ByteString;)V
       4: return

  static void access$1700(com.google.protobuf.ByteString) throws java.lang.IllegalArgumentException;
    Code:
       0: aload_0
       1: invokestatic  #2                  // Method checkByteStringIsUtf8:(Lcom/google/protobuf/ByteString;)V
       4: return

  com.google.api.Documentation(com.google.protobuf.CodedInputStream, com.google.protobuf.ExtensionRegistryLite, com.google.api.Documentation$1) throws com.google.protobuf.InvalidProtocolBufferException;
    Code:
       0: aload_0
       1: aload_1
       2: aload_2
       3: invokespecial #1                  // Method "<init>":(Lcom/google/protobuf/CodedInputStream;Lcom/google/protobuf/ExtensionRegistryLite;)V
       6: return

  static {};
    Code:
       0: new           #18                 // class com/google/api/Documentation
       3: dup
       4: invokespecial #19                 // Method "<init>":()V
       7: putstatic     #97                 // Field DEFAULT_INSTANCE:Lcom/google/api/Documentation;
      10: new           #105                // class com/google/api/Documentation$1
      13: dup
      14: invokespecial #106                // Method com/google/api/Documentation$1."<init>":()V
      17: putstatic     #3                  // Field PARSER:Lcom/google/protobuf/Parser;
      20: return
}
