Compiled from "MultipartEntity.java"
public class org.apache.http.entity.mime.MultipartEntity implements org.apache.http.HttpEntity {
  private static final char[] MULTIPART_CHARS;

  private final org.apache.http.entity.mime.MultipartEntityBuilder builder;

  private volatile org.apache.http.entity.mime.MultipartFormEntity entity;

  public org.apache.http.entity.mime.MultipartEntity(org.apache.http.entity.mime.HttpMultipartMode, java.lang.String, java.nio.charset.Charset);
    Code:
       0: aload_0
       1: invokespecial #1                  // Method java/lang/Object."<init>":()V
       4: aload_0
       5: new           #2                  // class org/apache/http/entity/mime/MultipartEntityBuilder
       8: dup
       9: invokespecial #3                  // Method org/apache/http/entity/mime/MultipartEntityBuilder."<init>":()V
      12: aload_1
      13: invokevirtual #4                  // Method org/apache/http/entity/mime/MultipartEntityBuilder.setMode:(Lorg/apache/http/entity/mime/HttpMultipartMode;)Lorg/apache/http/entity/mime/MultipartEntityBuilder;
      16: aload_3
      17: invokevirtual #5                  // Method org/apache/http/entity/mime/MultipartEntityBuilder.setCharset:(Ljava/nio/charset/Charset;)Lorg/apache/http/entity/mime/MultipartEntityBuilder;
      20: aload_2
      21: invokevirtual #6                  // Method org/apache/http/entity/mime/MultipartEntityBuilder.setBoundary:(Ljava/lang/String;)Lorg/apache/http/entity/mime/MultipartEntityBuilder;
      24: putfield      #7                  // Field builder:Lorg/apache/http/entity/mime/MultipartEntityBuilder;
      27: aload_0
      28: aconst_null
      29: putfield      #8                  // Field entity:Lorg/apache/http/entity/mime/MultipartFormEntity;
      32: return

  public org.apache.http.entity.mime.MultipartEntity(org.apache.http.entity.mime.HttpMultipartMode);
    Code:
       0: aload_0
       1: aload_1
       2: aconst_null
       3: aconst_null
       4: invokespecial #9                  // Method "<init>":(Lorg/apache/http/entity/mime/HttpMultipartMode;Ljava/lang/String;Ljava/nio/charset/Charset;)V
       7: return

  public org.apache.http.entity.mime.MultipartEntity();
    Code:
       0: aload_0
       1: getstatic     #10                 // Field org/apache/http/entity/mime/HttpMultipartMode.STRICT:Lorg/apache/http/entity/mime/HttpMultipartMode;
       4: aconst_null
       5: aconst_null
       6: invokespecial #9                  // Method "<init>":(Lorg/apache/http/entity/mime/HttpMultipartMode;Ljava/lang/String;Ljava/nio/charset/Charset;)V
       9: return

  protected java.lang.String generateContentType(java.lang.String, java.nio.charset.Charset);
    Code:
       0: new           #11                 // class java/lang/StringBuilder
       3: dup
       4: invokespecial #12                 // Method java/lang/StringBuilder."<init>":()V
       7: astore_3
       8: aload_3
       9: ldc           #13                 // String multipart/form-data; boundary=
      11: invokevirtual #14                 // Method java/lang/StringBuilder.append:(Ljava/lang/String;)Ljava/lang/StringBuilder;
      14: pop
      15: aload_3
      16: aload_1
      17: invokevirtual #14                 // Method java/lang/StringBuilder.append:(Ljava/lang/String;)Ljava/lang/StringBuilder;
      20: pop
      21: aload_2
      22: ifnull        41
      25: aload_3
      26: ldc           #15                 // String ; charset=
      28: invokevirtual #14                 // Method java/lang/StringBuilder.append:(Ljava/lang/String;)Ljava/lang/StringBuilder;
      31: pop
      32: aload_3
      33: aload_2
      34: invokevirtual #16                 // Method java/nio/charset/Charset.name:()Ljava/lang/String;
      37: invokevirtual #14                 // Method java/lang/StringBuilder.append:(Ljava/lang/String;)Ljava/lang/StringBuilder;
      40: pop
      41: aload_3
      42: invokevirtual #17                 // Method java/lang/StringBuilder.toString:()Ljava/lang/String;
      45: areturn

  protected java.lang.String generateBoundary();
    Code:
       0: new           #11                 // class java/lang/StringBuilder
       3: dup
       4: invokespecial #12                 // Method java/lang/StringBuilder."<init>":()V
       7: astore_1
       8: new           #18                 // class java/util/Random
      11: dup
      12: invokespecial #19                 // Method java/util/Random."<init>":()V
      15: astore_2
      16: aload_2
      17: bipush        11
      19: invokevirtual #20                 // Method java/util/Random.nextInt:(I)I
      22: bipush        30
      24: iadd
      25: istore_3
      26: iconst_0
      27: istore        4
      29: iload         4
      31: iload_3
      32: if_icmpge     58
      35: aload_1
      36: getstatic     #21                 // Field MULTIPART_CHARS:[C
      39: aload_2
      40: getstatic     #21                 // Field MULTIPART_CHARS:[C
      43: arraylength
      44: invokevirtual #20                 // Method java/util/Random.nextInt:(I)I
      47: caload
      48: invokevirtual #22                 // Method java/lang/StringBuilder.append:(C)Ljava/lang/StringBuilder;
      51: pop
      52: iinc          4, 1
      55: goto          29
      58: aload_1
      59: invokevirtual #17                 // Method java/lang/StringBuilder.toString:()Ljava/lang/String;
      62: areturn

  private org.apache.http.entity.mime.MultipartFormEntity getEntity();
    Code:
       0: aload_0
       1: getfield      #8                  // Field entity:Lorg/apache/http/entity/mime/MultipartFormEntity;
       4: ifnonnull     18
       7: aload_0
       8: aload_0
       9: getfield      #7                  // Field builder:Lorg/apache/http/entity/mime/MultipartEntityBuilder;
      12: invokevirtual #23                 // Method org/apache/http/entity/mime/MultipartEntityBuilder.buildEntity:()Lorg/apache/http/entity/mime/MultipartFormEntity;
      15: putfield      #8                  // Field entity:Lorg/apache/http/entity/mime/MultipartFormEntity;
      18: aload_0
      19: getfield      #8                  // Field entity:Lorg/apache/http/entity/mime/MultipartFormEntity;
      22: areturn

  public void addPart(org.apache.http.entity.mime.FormBodyPart);
    Code:
       0: aload_0
       1: getfield      #7                  // Field builder:Lorg/apache/http/entity/mime/MultipartEntityBuilder;
       4: aload_1
       5: invokevirtual #24                 // Method org/apache/http/entity/mime/MultipartEntityBuilder.addPart:(Lorg/apache/http/entity/mime/FormBodyPart;)Lorg/apache/http/entity/mime/MultipartEntityBuilder;
       8: pop
       9: aload_0
      10: aconst_null
      11: putfield      #8                  // Field entity:Lorg/apache/http/entity/mime/MultipartFormEntity;
      14: return

  public void addPart(java.lang.String, org.apache.http.entity.mime.content.ContentBody);
    Code:
       0: aload_0
       1: new           #25                 // class org/apache/http/entity/mime/FormBodyPart
       4: dup
       5: aload_1
       6: aload_2
       7: invokespecial #26                 // Method org/apache/http/entity/mime/FormBodyPart."<init>":(Ljava/lang/String;Lorg/apache/http/entity/mime/content/ContentBody;)V
      10: invokevirtual #27                 // Method addPart:(Lorg/apache/http/entity/mime/FormBodyPart;)V
      13: return

  public boolean isRepeatable();
    Code:
       0: aload_0
       1: invokespecial #28                 // Method getEntity:()Lorg/apache/http/entity/mime/MultipartFormEntity;
       4: invokevirtual #29                 // Method org/apache/http/entity/mime/MultipartFormEntity.isRepeatable:()Z
       7: ireturn

  public boolean isChunked();
    Code:
       0: aload_0
       1: invokespecial #28                 // Method getEntity:()Lorg/apache/http/entity/mime/MultipartFormEntity;
       4: invokevirtual #30                 // Method org/apache/http/entity/mime/MultipartFormEntity.isChunked:()Z
       7: ireturn

  public boolean isStreaming();
    Code:
       0: aload_0
       1: invokespecial #28                 // Method getEntity:()Lorg/apache/http/entity/mime/MultipartFormEntity;
       4: invokevirtual #31                 // Method org/apache/http/entity/mime/MultipartFormEntity.isStreaming:()Z
       7: ireturn

  public long getContentLength();
    Code:
       0: aload_0
       1: invokespecial #28                 // Method getEntity:()Lorg/apache/http/entity/mime/MultipartFormEntity;
       4: invokevirtual #32                 // Method org/apache/http/entity/mime/MultipartFormEntity.getContentLength:()J
       7: lreturn

  public org.apache.http.Header getContentType();
    Code:
       0: aload_0
       1: invokespecial #28                 // Method getEntity:()Lorg/apache/http/entity/mime/MultipartFormEntity;
       4: invokevirtual #33                 // Method org/apache/http/entity/mime/MultipartFormEntity.getContentType:()Lorg/apache/http/Header;
       7: areturn

  public org.apache.http.Header getContentEncoding();
    Code:
       0: aload_0
       1: invokespecial #28                 // Method getEntity:()Lorg/apache/http/entity/mime/MultipartFormEntity;
       4: invokevirtual #34                 // Method org/apache/http/entity/mime/MultipartFormEntity.getContentEncoding:()Lorg/apache/http/Header;
       7: areturn

  public void consumeContent() throws java.io.IOException, java.lang.UnsupportedOperationException;
    Code:
       0: aload_0
       1: invokevirtual #35                 // Method isStreaming:()Z
       4: ifeq          17
       7: new           #36                 // class java/lang/UnsupportedOperationException
      10: dup
      11: ldc           #37                 // String Streaming entity does not implement #consumeContent()
      13: invokespecial #38                 // Method java/lang/UnsupportedOperationException."<init>":(Ljava/lang/String;)V
      16: athrow
      17: return

  public java.io.InputStream getContent() throws java.io.IOException, java.lang.UnsupportedOperationException;
    Code:
       0: new           #36                 // class java/lang/UnsupportedOperationException
       3: dup
       4: ldc           #39                 // String Multipart form entity does not implement #getContent()
       6: invokespecial #38                 // Method java/lang/UnsupportedOperationException."<init>":(Ljava/lang/String;)V
       9: athrow

  public void writeTo(java.io.OutputStream) throws java.io.IOException;
    Code:
       0: aload_0
       1: invokespecial #28                 // Method getEntity:()Lorg/apache/http/entity/mime/MultipartFormEntity;
       4: aload_1
       5: invokevirtual #40                 // Method org/apache/http/entity/mime/MultipartFormEntity.writeTo:(Ljava/io/OutputStream;)V
       8: return

  static {};
    Code:
       0: ldc           #41                 // String -_1234567890abcdefghijklmnopqrstuvwxyzABCDEFGHIJKLMNOPQRSTUVWXYZ
       2: invokevirtual #42                 // Method java/lang/String.toCharArray:()[C
       5: putstatic     #21                 // Field MULTIPART_CHARS:[C
       8: return
}
