Compiled from "FramedSnappyCompressorOutputStream.java"
public class io.dekorate.deps.commons.compress.compressors.snappy.FramedSnappyCompressorOutputStream extends io.dekorate.deps.commons.compress.compressors.CompressorOutputStream {
  private static final int MAX_COMPRESSED_BUFFER_SIZE;

  private final java.io.OutputStream out;

  private final io.dekorate.deps.commons.compress.compressors.lz77support.Parameters params;

  private final io.dekorate.deps.commons.compress.compressors.snappy.PureJavaCrc32C checksum;

  private final byte[] oneByte;

  private final byte[] buffer;

  private int currentIndex;

  private final io.dekorate.deps.commons.compress.utils.ByteUtils$ByteConsumer consumer;

  public io.dekorate.deps.commons.compress.compressors.snappy.FramedSnappyCompressorOutputStream(java.io.OutputStream) throws java.io.IOException;
    Code:
       0: aload_0
       1: aload_1
       2: ldc           #38                 // int 32768
       4: invokestatic  #44                 // Method io/dekorate/deps/commons/compress/compressors/snappy/SnappyCompressorOutputStream.createParameterBuilder:(I)Lio/dekorate/deps/commons/compress/compressors/lz77support/Parameters$Builder;
       7: invokevirtual #48                 // Method io/dekorate/deps/commons/compress/compressors/lz77support/Parameters$Builder.build:()Lio/dekorate/deps/commons/compress/compressors/lz77support/Parameters;
      10: invokespecial #51                 // Method "<init>":(Ljava/io/OutputStream;Lio/dekorate/deps/commons/compress/compressors/lz77support/Parameters;)V
      13: return

  public io.dekorate.deps.commons.compress.compressors.snappy.FramedSnappyCompressorOutputStream(java.io.OutputStream, io.dekorate.deps.commons.compress.compressors.lz77support.Parameters) throws java.io.IOException;
    Code:
       0: aload_0
       1: invokespecial #56                 // Method io/dekorate/deps/commons/compress/compressors/CompressorOutputStream."<init>":()V
       4: aload_0
       5: new           #58                 // class io/dekorate/deps/commons/compress/compressors/snappy/PureJavaCrc32C
       8: dup
       9: invokespecial #59                 // Method io/dekorate/deps/commons/compress/compressors/snappy/PureJavaCrc32C."<init>":()V
      12: putfield      #61                 // Field checksum:Lio/dekorate/deps/commons/compress/compressors/snappy/PureJavaCrc32C;
      15: aload_0
      16: iconst_1
      17: newarray       byte
      19: putfield      #63                 // Field oneByte:[B
      22: aload_0
      23: ldc           #21                 // int 65536
      25: newarray       byte
      27: putfield      #65                 // Field buffer:[B
      30: aload_0
      31: iconst_0
      32: putfield      #67                 // Field currentIndex:I
      35: aload_0
      36: aload_1
      37: putfield      #69                 // Field out:Ljava/io/OutputStream;
      40: aload_0
      41: aload_2
      42: putfield      #71                 // Field params:Lio/dekorate/deps/commons/compress/compressors/lz77support/Parameters;
      45: aload_0
      46: new           #12                 // class io/dekorate/deps/commons/compress/utils/ByteUtils$OutputStreamByteConsumer
      49: dup
      50: aload_1
      51: invokespecial #73                 // Method io/dekorate/deps/commons/compress/utils/ByteUtils$OutputStreamByteConsumer."<init>":(Ljava/io/OutputStream;)V
      54: putfield      #75                 // Field consumer:Lio/dekorate/deps/commons/compress/utils/ByteUtils$ByteConsumer;
      57: aload_1
      58: getstatic     #80                 // Field io/dekorate/deps/commons/compress/compressors/snappy/FramedSnappyCompressorInputStream.SZ_SIGNATURE:[B
      61: invokevirtual #86                 // Method java/io/OutputStream.write:([B)V
      64: return

  public void write(int) throws java.io.IOException;
    Code:
       0: aload_0
       1: getfield      #63                 // Field oneByte:[B
       4: iconst_0
       5: iload_1
       6: sipush        255
       9: iand
      10: i2b
      11: bastore
      12: aload_0
      13: aload_0
      14: getfield      #63                 // Field oneByte:[B
      17: invokevirtual #88                 // Method write:([B)V
      20: return

  public void write(byte[], int, int) throws java.io.IOException;
    Code:
       0: aload_0
       1: getfield      #67                 // Field currentIndex:I
       4: iload_3
       5: iadd
       6: ldc           #21                 // int 65536
       8: if_icmple     56
      11: aload_0
      12: invokespecial #93                 // Method flushBuffer:()V
      15: iload_3
      16: ldc           #21                 // int 65536
      18: if_icmple     56
      21: aload_1
      22: iload_2
      23: aload_0
      24: getfield      #65                 // Field buffer:[B
      27: iconst_0
      28: ldc           #21                 // int 65536
      30: invokestatic  #99                 // Method java/lang/System.arraycopy:(Ljava/lang/Object;ILjava/lang/Object;II)V
      33: iload_2
      34: ldc           #21                 // int 65536
      36: iadd
      37: istore_2
      38: iload_3
      39: ldc           #21                 // int 65536
      41: isub
      42: istore_3
      43: aload_0
      44: ldc           #21                 // int 65536
      46: putfield      #67                 // Field currentIndex:I
      49: aload_0
      50: invokespecial #93                 // Method flushBuffer:()V
      53: goto          15
      56: aload_1
      57: iload_2
      58: aload_0
      59: getfield      #65                 // Field buffer:[B
      62: aload_0
      63: getfield      #67                 // Field currentIndex:I
      66: iload_3
      67: invokestatic  #99                 // Method java/lang/System.arraycopy:(Ljava/lang/Object;ILjava/lang/Object;II)V
      70: aload_0
      71: dup
      72: getfield      #67                 // Field currentIndex:I
      75: iload_3
      76: iadd
      77: putfield      #67                 // Field currentIndex:I
      80: return

  public void close() throws java.io.IOException;
    Code:
       0: aload_0
       1: invokevirtual #106                // Method finish:()V
       4: aload_0
       5: getfield      #69                 // Field out:Ljava/io/OutputStream;
       8: invokevirtual #108                // Method java/io/OutputStream.close:()V
      11: goto          24
      14: astore_1
      15: aload_0
      16: getfield      #69                 // Field out:Ljava/io/OutputStream;
      19: invokevirtual #108                // Method java/io/OutputStream.close:()V
      22: aload_1
      23: athrow
      24: return
    Exception table:
       from    to  target type
           0     4    14   any

  public void finish() throws java.io.IOException;
    Code:
       0: aload_0
       1: getfield      #67                 // Field currentIndex:I
       4: ifle          11
       7: aload_0
       8: invokespecial #93                 // Method flushBuffer:()V
      11: return

  private void flushBuffer() throws java.io.IOException;
    Code:
       0: aload_0
       1: getfield      #69                 // Field out:Ljava/io/OutputStream;
       4: iconst_0
       5: invokevirtual #112                // Method java/io/OutputStream.write:(I)V
       8: new           #114                // class java/io/ByteArrayOutputStream
      11: dup
      12: invokespecial #115                // Method java/io/ByteArrayOutputStream."<init>":()V
      15: astore_1
      16: new           #40                 // class io/dekorate/deps/commons/compress/compressors/snappy/SnappyCompressorOutputStream
      19: dup
      20: aload_1
      21: aload_0
      22: getfield      #67                 // Field currentIndex:I
      25: i2l
      26: aload_0
      27: getfield      #71                 // Field params:Lio/dekorate/deps/commons/compress/compressors/lz77support/Parameters;
      30: invokespecial #118                // Method io/dekorate/deps/commons/compress/compressors/snappy/SnappyCompressorOutputStream."<init>":(Ljava/io/OutputStream;JLio/dekorate/deps/commons/compress/compressors/lz77support/Parameters;)V
      33: astore_2
      34: aconst_null
      35: astore_3
      36: aload_2
      37: aload_0
      38: getfield      #65                 // Field buffer:[B
      41: iconst_0
      42: aload_0
      43: getfield      #67                 // Field currentIndex:I
      46: invokevirtual #120                // Method java/io/OutputStream.write:([BII)V
      49: aload_2
      50: ifnull        125
      53: aload_3
      54: ifnull        75
      57: aload_2
      58: invokevirtual #108                // Method java/io/OutputStream.close:()V
      61: goto          125
      64: astore        4
      66: aload_3
      67: aload         4
      69: invokevirtual #124                // Method java/lang/Throwable.addSuppressed:(Ljava/lang/Throwable;)V
      72: goto          125
      75: aload_2
      76: invokevirtual #108                // Method java/io/OutputStream.close:()V
      79: goto          125
      82: astore        4
      84: aload         4
      86: astore_3
      87: aload         4
      89: athrow
      90: astore        5
      92: aload_2
      93: ifnull        122
      96: aload_3
      97: ifnull        118
     100: aload_2
     101: invokevirtual #108                // Method java/io/OutputStream.close:()V
     104: goto          122
     107: astore        6
     109: aload_3
     110: aload         6
     112: invokevirtual #124                // Method java/lang/Throwable.addSuppressed:(Ljava/lang/Throwable;)V
     115: goto          122
     118: aload_2
     119: invokevirtual #108                // Method java/io/OutputStream.close:()V
     122: aload         5
     124: athrow
     125: aload_1
     126: invokevirtual #128                // Method java/io/ByteArrayOutputStream.toByteArray:()[B
     129: astore_2
     130: aload_0
     131: iconst_3
     132: aload_2
     133: arraylength
     134: i2l
     135: ldc2_w        #129                // long 4l
     138: ladd
     139: invokespecial #134                // Method writeLittleEndian:(IJ)V
     142: aload_0
     143: invokespecial #137                // Method writeCrc:()V
     146: aload_0
     147: getfield      #69                 // Field out:Ljava/io/OutputStream;
     150: aload_2
     151: invokevirtual #86                 // Method java/io/OutputStream.write:([B)V
     154: aload_0
     155: iconst_0
     156: putfield      #67                 // Field currentIndex:I
     159: return
    Exception table:
       from    to  target type
          57    61    64   Class java/lang/Throwable
          36    49    82   Class java/lang/Throwable
          36    49    90   any
         100   104   107   Class java/lang/Throwable
          82    92    90   any

  private void writeLittleEndian(int, long) throws java.io.IOException;
    Code:
       0: aload_0
       1: getfield      #75                 // Field consumer:Lio/dekorate/deps/commons/compress/utils/ByteUtils$ByteConsumer;
       4: lload_2
       5: iload_1
       6: invokestatic  #144                // Method io/dekorate/deps/commons/compress/utils/ByteUtils.toLittleEndian:(Lio/dekorate/deps/commons/compress/utils/ByteUtils$ByteConsumer;JI)V
       9: return

  private void writeCrc() throws java.io.IOException;
    Code:
       0: aload_0
       1: getfield      #61                 // Field checksum:Lio/dekorate/deps/commons/compress/compressors/snappy/PureJavaCrc32C;
       4: aload_0
       5: getfield      #65                 // Field buffer:[B
       8: iconst_0
       9: aload_0
      10: getfield      #67                 // Field currentIndex:I
      13: invokevirtual #150                // Method io/dekorate/deps/commons/compress/compressors/snappy/PureJavaCrc32C.update:([BII)V
      16: aload_0
      17: iconst_4
      18: aload_0
      19: getfield      #61                 // Field checksum:Lio/dekorate/deps/commons/compress/compressors/snappy/PureJavaCrc32C;
      22: invokevirtual #154                // Method io/dekorate/deps/commons/compress/compressors/snappy/PureJavaCrc32C.getValue:()J
      25: invokestatic  #158                // Method mask:(J)J
      28: invokespecial #134                // Method writeLittleEndian:(IJ)V
      31: aload_0
      32: getfield      #61                 // Field checksum:Lio/dekorate/deps/commons/compress/compressors/snappy/PureJavaCrc32C;
      35: invokevirtual #161                // Method io/dekorate/deps/commons/compress/compressors/snappy/PureJavaCrc32C.reset:()V
      38: return

  static long mask(long);
    Code:
       0: lload_0
       1: bipush        15
       3: lshr
       4: lload_0
       5: bipush        17
       7: lshl
       8: lor
       9: lstore_0
      10: lload_0
      11: ldc2_w        #162                // long 2726488792l
      14: ladd
      15: lstore_0
      16: lload_0
      17: ldc2_w        #164                // long 4294967295l
      20: land
      21: lstore_0
      22: lload_0
      23: lreturn
}
