Compiled from "ServiceManager.java"
class com.google.common.util.concurrent.ServiceManager$ServiceManagerState$5 extends com.google.common.util.concurrent.ListenerCallQueue$Callback<com.google.common.util.concurrent.ServiceManager$Listener> {
  final com.google.common.util.concurrent.Service val$service;

  final com.google.common.util.concurrent.ServiceManager$ServiceManagerState this$0;

  com.google.common.util.concurrent.ServiceManager$ServiceManagerState$5(com.google.common.util.concurrent.ServiceManager$ServiceManagerState, java.lang.String, com.google.common.util.concurrent.Service);
    Code:
       0: aload_0
       1: aload_1
       2: putfield      #1                  // Field this$0:Lcom/google/common/util/concurrent/ServiceManager$ServiceManagerState;
       5: aload_0
       6: aload_3
       7: putfield      #2                  // Field val$service:Lcom/google/common/util/concurrent/Service;
      10: aload_0
      11: aload_2
      12: invokespecial #3                  // Method com/google/common/util/concurrent/ListenerCallQueue$Callback."<init>":(Ljava/lang/String;)V
      15: return

  void call(com.google.common.util.concurrent.ServiceManager$Listener);
    Code:
       0: aload_1
       1: aload_0
       2: getfield      #2                  // Field val$service:Lcom/google/common/util/concurrent/Service;
       5: invokevirtual #4                  // Method com/google/common/util/concurrent/ServiceManager$Listener.failure:(Lcom/google/common/util/concurrent/Service;)V
       8: return

  void call(java.lang.Object);
    Code:
       0: aload_0
       1: aload_1
       2: checkcast     #5                  // class com/google/common/util/concurrent/ServiceManager$Listener
       5: invokevirtual #6                  // Method call:(Lcom/google/common/util/concurrent/ServiceManager$Listener;)V
       8: return
}
