Compiled from "Balancer.java"
public class org.wildfly.swarm.config.undertow.configuration.mod_cluster.Balancer<T extends org.wildfly.swarm.config.undertow.configuration.mod_cluster.Balancer<T>> extends java.util.HashMap {
  private java.lang.String key;

  private java.beans.PropertyChangeSupport pcs;

  private org.wildfly.swarm.config.undertow.configuration.mod_cluster.Balancer$BalancerResources subresources;

  private java.lang.Integer maxAttempts;

  private java.lang.Boolean stickySession;

  private java.lang.String stickySessionCookie;

  private java.lang.Boolean stickySessionForce;

  private java.lang.String stickySessionPath;

  private java.lang.Boolean stickySessionRemove;

  private java.lang.Integer waitWorker;

  public org.wildfly.swarm.config.undertow.configuration.mod_cluster.Balancer(java.lang.String);
    Code:
       0: aload_0
       1: invokespecial #1                  // Method java/util/HashMap."<init>":()V
       4: aload_0
       5: new           #2                  // class org/wildfly/swarm/config/undertow/configuration/mod_cluster/Balancer$BalancerResources
       8: dup
       9: invokespecial #3                  // Method org/wildfly/swarm/config/undertow/configuration/mod_cluster/Balancer$BalancerResources."<init>":()V
      12: putfield      #4                  // Field subresources:Lorg/wildfly/swarm/config/undertow/configuration/mod_cluster/Balancer$BalancerResources;
      15: aload_0
      16: aload_1
      17: putfield      #5                  // Field key:Ljava/lang/String;
      20: return

  public java.lang.String getKey();
    Code:
       0: aload_0
       1: getfield      #5                  // Field key:Ljava/lang/String;
       4: areturn

  public void addPropertyChangeListener(java.beans.PropertyChangeListener);
    Code:
       0: aconst_null
       1: aload_0
       2: getfield      #6                  // Field pcs:Ljava/beans/PropertyChangeSupport;
       5: if_acmpne     20
       8: aload_0
       9: new           #7                  // class java/beans/PropertyChangeSupport
      12: dup
      13: aload_0
      14: invokespecial #8                  // Method java/beans/PropertyChangeSupport."<init>":(Ljava/lang/Object;)V
      17: putfield      #6                  // Field pcs:Ljava/beans/PropertyChangeSupport;
      20: aload_0
      21: getfield      #6                  // Field pcs:Ljava/beans/PropertyChangeSupport;
      24: aload_1
      25: invokevirtual #9                  // Method java/beans/PropertyChangeSupport.addPropertyChangeListener:(Ljava/beans/PropertyChangeListener;)V
      28: return

  public void removePropertyChangeListener(java.beans.PropertyChangeListener);
    Code:
       0: aload_0
       1: getfield      #6                  // Field pcs:Ljava/beans/PropertyChangeSupport;
       4: ifnull        15
       7: aload_0
       8: getfield      #6                  // Field pcs:Ljava/beans/PropertyChangeSupport;
      11: aload_1
      12: invokevirtual #10                 // Method java/beans/PropertyChangeSupport.removePropertyChangeListener:(Ljava/beans/PropertyChangeListener;)V
      15: return

  public org.wildfly.swarm.config.undertow.configuration.mod_cluster.Balancer$BalancerResources subresources();
    Code:
       0: aload_0
       1: getfield      #4                  // Field subresources:Lorg/wildfly/swarm/config/undertow/configuration/mod_cluster/Balancer$BalancerResources;
       4: areturn

  public T nodes(java.util.List<org.wildfly.swarm.config.undertow.configuration.mod_cluster.balancer.Node>);
    Code:
       0: aload_0
       1: getfield      #4                  // Field subresources:Lorg/wildfly/swarm/config/undertow/configuration/mod_cluster/Balancer$BalancerResources;
       4: aload_1
       5: invokestatic  #11                 // Method org/wildfly/swarm/config/undertow/configuration/mod_cluster/Balancer$BalancerResources.access$002:(Lorg/wildfly/swarm/config/undertow/configuration/mod_cluster/Balancer$BalancerResources;Ljava/util/List;)Ljava/util/List;
       8: pop
       9: aload_0
      10: areturn

  public T node(org.wildfly.swarm.config.undertow.configuration.mod_cluster.balancer.Node);
    Code:
       0: aload_0
       1: getfield      #4                  // Field subresources:Lorg/wildfly/swarm/config/undertow/configuration/mod_cluster/Balancer$BalancerResources;
       4: invokestatic  #12                 // Method org/wildfly/swarm/config/undertow/configuration/mod_cluster/Balancer$BalancerResources.access$000:(Lorg/wildfly/swarm/config/undertow/configuration/mod_cluster/Balancer$BalancerResources;)Ljava/util/List;
       7: aload_1
       8: invokeinterface #13,  2           // InterfaceMethod java/util/List.add:(Ljava/lang/Object;)Z
      13: pop
      14: aload_0
      15: areturn

  public T node(java.lang.String, org.wildfly.swarm.config.undertow.configuration.mod_cluster.balancer.NodeConsumer);
    Code:
       0: new           #14                 // class org/wildfly/swarm/config/undertow/configuration/mod_cluster/balancer/Node
       3: dup
       4: aload_1
       5: invokespecial #15                 // Method org/wildfly/swarm/config/undertow/configuration/mod_cluster/balancer/Node."<init>":(Ljava/lang/String;)V
       8: astore_3
       9: aload_2
      10: ifnull        20
      13: aload_2
      14: aload_3
      15: invokeinterface #16,  2           // InterfaceMethod org/wildfly/swarm/config/undertow/configuration/mod_cluster/balancer/NodeConsumer.accept:(Lorg/wildfly/swarm/config/undertow/configuration/mod_cluster/balancer/Node;)V
      20: aload_0
      21: aload_3
      22: invokevirtual #17                 // Method node:(Lorg/wildfly/swarm/config/undertow/configuration/mod_cluster/balancer/Node;)Lorg/wildfly/swarm/config/undertow/configuration/mod_cluster/Balancer;
      25: pop
      26: aload_0
      27: areturn

  public T node(java.lang.String);
    Code:
       0: aload_0
       1: aload_1
       2: aconst_null
       3: invokevirtual #18                 // Method node:(Ljava/lang/String;Lorg/wildfly/swarm/config/undertow/configuration/mod_cluster/balancer/NodeConsumer;)Lorg/wildfly/swarm/config/undertow/configuration/mod_cluster/Balancer;
       6: pop
       7: aload_0
       8: areturn

  public T node(org.wildfly.swarm.config.undertow.configuration.mod_cluster.balancer.NodeSupplier);
    Code:
       0: aload_0
       1: aload_1
       2: invokeinterface #19,  1           // InterfaceMethod org/wildfly/swarm/config/undertow/configuration/mod_cluster/balancer/NodeSupplier.get:()Lorg/wildfly/swarm/config/undertow/configuration/mod_cluster/balancer/Node;
       7: invokevirtual #17                 // Method node:(Lorg/wildfly/swarm/config/undertow/configuration/mod_cluster/balancer/Node;)Lorg/wildfly/swarm/config/undertow/configuration/mod_cluster/Balancer;
      10: pop
      11: aload_0
      12: areturn

  public T loadBalancingGroups(java.util.List<org.wildfly.swarm.config.undertow.configuration.mod_cluster.balancer.LoadBalancingGroup>);
    Code:
       0: aload_0
       1: getfield      #4                  // Field subresources:Lorg/wildfly/swarm/config/undertow/configuration/mod_cluster/Balancer$BalancerResources;
       4: aload_1
       5: invokestatic  #20                 // Method org/wildfly/swarm/config/undertow/configuration/mod_cluster/Balancer$BalancerResources.access$102:(Lorg/wildfly/swarm/config/undertow/configuration/mod_cluster/Balancer$BalancerResources;Ljava/util/List;)Ljava/util/List;
       8: pop
       9: aload_0
      10: areturn

  public T loadBalancingGroup(org.wildfly.swarm.config.undertow.configuration.mod_cluster.balancer.LoadBalancingGroup);
    Code:
       0: aload_0
       1: getfield      #4                  // Field subresources:Lorg/wildfly/swarm/config/undertow/configuration/mod_cluster/Balancer$BalancerResources;
       4: invokestatic  #21                 // Method org/wildfly/swarm/config/undertow/configuration/mod_cluster/Balancer$BalancerResources.access$100:(Lorg/wildfly/swarm/config/undertow/configuration/mod_cluster/Balancer$BalancerResources;)Ljava/util/List;
       7: aload_1
       8: invokeinterface #13,  2           // InterfaceMethod java/util/List.add:(Ljava/lang/Object;)Z
      13: pop
      14: aload_0
      15: areturn

  public T loadBalancingGroup(java.lang.String, org.wildfly.swarm.config.undertow.configuration.mod_cluster.balancer.LoadBalancingGroupConsumer);
    Code:
       0: new           #22                 // class org/wildfly/swarm/config/undertow/configuration/mod_cluster/balancer/LoadBalancingGroup
       3: dup
       4: aload_1
       5: invokespecial #23                 // Method org/wildfly/swarm/config/undertow/configuration/mod_cluster/balancer/LoadBalancingGroup."<init>":(Ljava/lang/String;)V
       8: astore_3
       9: aload_2
      10: ifnull        20
      13: aload_2
      14: aload_3
      15: invokeinterface #24,  2           // InterfaceMethod org/wildfly/swarm/config/undertow/configuration/mod_cluster/balancer/LoadBalancingGroupConsumer.accept:(Lorg/wildfly/swarm/config/undertow/configuration/mod_cluster/balancer/LoadBalancingGroup;)V
      20: aload_0
      21: aload_3
      22: invokevirtual #25                 // Method loadBalancingGroup:(Lorg/wildfly/swarm/config/undertow/configuration/mod_cluster/balancer/LoadBalancingGroup;)Lorg/wildfly/swarm/config/undertow/configuration/mod_cluster/Balancer;
      25: pop
      26: aload_0
      27: areturn

  public T loadBalancingGroup(java.lang.String);
    Code:
       0: aload_0
       1: aload_1
       2: aconst_null
       3: invokevirtual #26                 // Method loadBalancingGroup:(Ljava/lang/String;Lorg/wildfly/swarm/config/undertow/configuration/mod_cluster/balancer/LoadBalancingGroupConsumer;)Lorg/wildfly/swarm/config/undertow/configuration/mod_cluster/Balancer;
       6: pop
       7: aload_0
       8: areturn

  public T loadBalancingGroup(org.wildfly.swarm.config.undertow.configuration.mod_cluster.balancer.LoadBalancingGroupSupplier);
    Code:
       0: aload_0
       1: aload_1
       2: invokeinterface #27,  1           // InterfaceMethod org/wildfly/swarm/config/undertow/configuration/mod_cluster/balancer/LoadBalancingGroupSupplier.get:()Lorg/wildfly/swarm/config/undertow/configuration/mod_cluster/balancer/LoadBalancingGroup;
       7: invokevirtual #25                 // Method loadBalancingGroup:(Lorg/wildfly/swarm/config/undertow/configuration/mod_cluster/balancer/LoadBalancingGroup;)Lorg/wildfly/swarm/config/undertow/configuration/mod_cluster/Balancer;
      10: pop
      11: aload_0
      12: areturn

  public java.lang.Integer maxAttempts();
    Code:
       0: aload_0
       1: getfield      #28                 // Field maxAttempts:Ljava/lang/Integer;
       4: areturn

  public T maxAttempts(java.lang.Integer);
    Code:
       0: aload_0
       1: getfield      #28                 // Field maxAttempts:Ljava/lang/Integer;
       4: astore_2
       5: aload_0
       6: aload_1
       7: putfield      #28                 // Field maxAttempts:Ljava/lang/Integer;
      10: aload_0
      11: getfield      #6                  // Field pcs:Ljava/beans/PropertyChangeSupport;
      14: ifnull        28
      17: aload_0
      18: getfield      #6                  // Field pcs:Ljava/beans/PropertyChangeSupport;
      21: ldc           #29                 // String maxAttempts
      23: aload_2
      24: aload_1
      25: invokevirtual #30                 // Method java/beans/PropertyChangeSupport.firePropertyChange:(Ljava/lang/String;Ljava/lang/Object;Ljava/lang/Object;)V
      28: aload_0
      29: areturn

  public java.lang.Boolean stickySession();
    Code:
       0: aload_0
       1: getfield      #31                 // Field stickySession:Ljava/lang/Boolean;
       4: areturn

  public T stickySession(java.lang.Boolean);
    Code:
       0: aload_0
       1: getfield      #31                 // Field stickySession:Ljava/lang/Boolean;
       4: astore_2
       5: aload_0
       6: aload_1
       7: putfield      #31                 // Field stickySession:Ljava/lang/Boolean;
      10: aload_0
      11: getfield      #6                  // Field pcs:Ljava/beans/PropertyChangeSupport;
      14: ifnull        28
      17: aload_0
      18: getfield      #6                  // Field pcs:Ljava/beans/PropertyChangeSupport;
      21: ldc           #32                 // String stickySession
      23: aload_2
      24: aload_1
      25: invokevirtual #30                 // Method java/beans/PropertyChangeSupport.firePropertyChange:(Ljava/lang/String;Ljava/lang/Object;Ljava/lang/Object;)V
      28: aload_0
      29: areturn

  public java.lang.String stickySessionCookie();
    Code:
       0: aload_0
       1: getfield      #33                 // Field stickySessionCookie:Ljava/lang/String;
       4: areturn

  public T stickySessionCookie(java.lang.String);
    Code:
       0: aload_0
       1: getfield      #33                 // Field stickySessionCookie:Ljava/lang/String;
       4: astore_2
       5: aload_0
       6: aload_1
       7: putfield      #33                 // Field stickySessionCookie:Ljava/lang/String;
      10: aload_0
      11: getfield      #6                  // Field pcs:Ljava/beans/PropertyChangeSupport;
      14: ifnull        28
      17: aload_0
      18: getfield      #6                  // Field pcs:Ljava/beans/PropertyChangeSupport;
      21: ldc           #34                 // String stickySessionCookie
      23: aload_2
      24: aload_1
      25: invokevirtual #30                 // Method java/beans/PropertyChangeSupport.firePropertyChange:(Ljava/lang/String;Ljava/lang/Object;Ljava/lang/Object;)V
      28: aload_0
      29: areturn

  public java.lang.Boolean stickySessionForce();
    Code:
       0: aload_0
       1: getfield      #35                 // Field stickySessionForce:Ljava/lang/Boolean;
       4: areturn

  public T stickySessionForce(java.lang.Boolean);
    Code:
       0: aload_0
       1: getfield      #35                 // Field stickySessionForce:Ljava/lang/Boolean;
       4: astore_2
       5: aload_0
       6: aload_1
       7: putfield      #35                 // Field stickySessionForce:Ljava/lang/Boolean;
      10: aload_0
      11: getfield      #6                  // Field pcs:Ljava/beans/PropertyChangeSupport;
      14: ifnull        28
      17: aload_0
      18: getfield      #6                  // Field pcs:Ljava/beans/PropertyChangeSupport;
      21: ldc           #36                 // String stickySessionForce
      23: aload_2
      24: aload_1
      25: invokevirtual #30                 // Method java/beans/PropertyChangeSupport.firePropertyChange:(Ljava/lang/String;Ljava/lang/Object;Ljava/lang/Object;)V
      28: aload_0
      29: areturn

  public java.lang.String stickySessionPath();
    Code:
       0: aload_0
       1: getfield      #37                 // Field stickySessionPath:Ljava/lang/String;
       4: areturn

  public T stickySessionPath(java.lang.String);
    Code:
       0: aload_0
       1: getfield      #37                 // Field stickySessionPath:Ljava/lang/String;
       4: astore_2
       5: aload_0
       6: aload_1
       7: putfield      #37                 // Field stickySessionPath:Ljava/lang/String;
      10: aload_0
      11: getfield      #6                  // Field pcs:Ljava/beans/PropertyChangeSupport;
      14: ifnull        28
      17: aload_0
      18: getfield      #6                  // Field pcs:Ljava/beans/PropertyChangeSupport;
      21: ldc           #38                 // String stickySessionPath
      23: aload_2
      24: aload_1
      25: invokevirtual #30                 // Method java/beans/PropertyChangeSupport.firePropertyChange:(Ljava/lang/String;Ljava/lang/Object;Ljava/lang/Object;)V
      28: aload_0
      29: areturn

  public java.lang.Boolean stickySessionRemove();
    Code:
       0: aload_0
       1: getfield      #39                 // Field stickySessionRemove:Ljava/lang/Boolean;
       4: areturn

  public T stickySessionRemove(java.lang.Boolean);
    Code:
       0: aload_0
       1: getfield      #39                 // Field stickySessionRemove:Ljava/lang/Boolean;
       4: astore_2
       5: aload_0
       6: aload_1
       7: putfield      #39                 // Field stickySessionRemove:Ljava/lang/Boolean;
      10: aload_0
      11: getfield      #6                  // Field pcs:Ljava/beans/PropertyChangeSupport;
      14: ifnull        28
      17: aload_0
      18: getfield      #6                  // Field pcs:Ljava/beans/PropertyChangeSupport;
      21: ldc           #40                 // String stickySessionRemove
      23: aload_2
      24: aload_1
      25: invokevirtual #30                 // Method java/beans/PropertyChangeSupport.firePropertyChange:(Ljava/lang/String;Ljava/lang/Object;Ljava/lang/Object;)V
      28: aload_0
      29: areturn

  public java.lang.Integer waitWorker();
    Code:
       0: aload_0
       1: getfield      #41                 // Field waitWorker:Ljava/lang/Integer;
       4: areturn

  public T waitWorker(java.lang.Integer);
    Code:
       0: aload_0
       1: getfield      #41                 // Field waitWorker:Ljava/lang/Integer;
       4: astore_2
       5: aload_0
       6: aload_1
       7: putfield      #41                 // Field waitWorker:Ljava/lang/Integer;
      10: aload_0
      11: getfield      #6                  // Field pcs:Ljava/beans/PropertyChangeSupport;
      14: ifnull        28
      17: aload_0
      18: getfield      #6                  // Field pcs:Ljava/beans/PropertyChangeSupport;
      21: ldc           #42                 // String waitWorker
      23: aload_2
      24: aload_1
      25: invokevirtual #30                 // Method java/beans/PropertyChangeSupport.firePropertyChange:(Ljava/lang/String;Ljava/lang/Object;Ljava/lang/Object;)V
      28: aload_0
      29: areturn
}
