Compiled from "DoneablePodList.java"
public class io.fabric8.kubernetes.api.model.DoneablePodList extends io.fabric8.kubernetes.api.model.PodListFluentImpl<io.fabric8.kubernetes.api.model.DoneablePodList> implements io.fabric8.kubernetes.api.model.Doneable<io.fabric8.kubernetes.api.model.PodList> {
  private final io.fabric8.kubernetes.api.model.PodListBuilder builder;

  private final io.fabric8.kubernetes.api.builder.Function<io.fabric8.kubernetes.api.model.PodList, io.fabric8.kubernetes.api.model.PodList> function;

  public io.fabric8.kubernetes.api.model.DoneablePodList(io.fabric8.kubernetes.api.builder.Function<io.fabric8.kubernetes.api.model.PodList, io.fabric8.kubernetes.api.model.PodList>);
    Code:
       0: aload_0
       1: invokespecial #1                  // Method io/fabric8/kubernetes/api/model/PodListFluentImpl."<init>":()V
       4: aload_0
       5: new           #2                  // class io/fabric8/kubernetes/api/model/PodListBuilder
       8: dup
       9: aload_0
      10: invokespecial #3                  // Method io/fabric8/kubernetes/api/model/PodListBuilder."<init>":(Lio/fabric8/kubernetes/api/model/PodListFluent;)V
      13: putfield      #4                  // Field builder:Lio/fabric8/kubernetes/api/model/PodListBuilder;
      16: aload_0
      17: aload_1
      18: putfield      #5                  // Field function:Lio/fabric8/kubernetes/api/builder/Function;
      21: return

  public io.fabric8.kubernetes.api.model.DoneablePodList(io.fabric8.kubernetes.api.model.PodList, io.fabric8.kubernetes.api.builder.Function<io.fabric8.kubernetes.api.model.PodList, io.fabric8.kubernetes.api.model.PodList>);
    Code:
       0: aload_0
       1: aload_1
       2: invokespecial #6                  // Method io/fabric8/kubernetes/api/model/PodListFluentImpl."<init>":(Lio/fabric8/kubernetes/api/model/PodList;)V
       5: aload_0
       6: new           #2                  // class io/fabric8/kubernetes/api/model/PodListBuilder
       9: dup
      10: aload_0
      11: aload_1
      12: invokespecial #7                  // Method io/fabric8/kubernetes/api/model/PodListBuilder."<init>":(Lio/fabric8/kubernetes/api/model/PodListFluent;Lio/fabric8/kubernetes/api/model/PodList;)V
      15: putfield      #4                  // Field builder:Lio/fabric8/kubernetes/api/model/PodListBuilder;
      18: aload_0
      19: aload_2
      20: putfield      #5                  // Field function:Lio/fabric8/kubernetes/api/builder/Function;
      23: return

  public io.fabric8.kubernetes.api.model.DoneablePodList(io.fabric8.kubernetes.api.model.PodList);
    Code:
       0: aload_0
       1: aload_1
       2: invokespecial #6                  // Method io/fabric8/kubernetes/api/model/PodListFluentImpl."<init>":(Lio/fabric8/kubernetes/api/model/PodList;)V
       5: aload_0
       6: new           #2                  // class io/fabric8/kubernetes/api/model/PodListBuilder
       9: dup
      10: aload_0
      11: aload_1
      12: invokespecial #7                  // Method io/fabric8/kubernetes/api/model/PodListBuilder."<init>":(Lio/fabric8/kubernetes/api/model/PodListFluent;Lio/fabric8/kubernetes/api/model/PodList;)V
      15: putfield      #4                  // Field builder:Lio/fabric8/kubernetes/api/model/PodListBuilder;
      18: aload_0
      19: new           #8                  // class io/fabric8/kubernetes/api/model/DoneablePodList$1
      22: dup
      23: aload_0
      24: invokespecial #9                  // Method io/fabric8/kubernetes/api/model/DoneablePodList$1."<init>":(Lio/fabric8/kubernetes/api/model/DoneablePodList;)V
      27: putfield      #5                  // Field function:Lio/fabric8/kubernetes/api/builder/Function;
      30: return

  public io.fabric8.kubernetes.api.model.PodList done();
    Code:
       0: aload_0
       1: getfield      #5                  // Field function:Lio/fabric8/kubernetes/api/builder/Function;
       4: aload_0
       5: getfield      #4                  // Field builder:Lio/fabric8/kubernetes/api/model/PodListBuilder;
       8: invokevirtual #10                 // Method io/fabric8/kubernetes/api/model/PodListBuilder.build:()Lio/fabric8/kubernetes/api/model/PodList;
      11: invokeinterface #11,  2           // InterfaceMethod io/fabric8/kubernetes/api/builder/Function.apply:(Ljava/lang/Object;)Ljava/lang/Object;
      16: checkcast     #12                 // class io/fabric8/kubernetes/api/model/PodList
      19: areturn

  public java.lang.Object done();
    Code:
       0: aload_0
       1: invokevirtual #13                 // Method done:()Lio/fabric8/kubernetes/api/model/PodList;
       4: areturn
}
