Compiled from "DoneableAWSElasticBlockStoreVolumeSource.java"
public class io.fabric8.kubernetes.api.model.DoneableAWSElasticBlockStoreVolumeSource extends io.fabric8.kubernetes.api.model.AWSElasticBlockStoreVolumeSourceFluentImpl<io.fabric8.kubernetes.api.model.DoneableAWSElasticBlockStoreVolumeSource> implements io.fabric8.kubernetes.api.model.Doneable<io.fabric8.kubernetes.api.model.AWSElasticBlockStoreVolumeSource> {
  private final io.fabric8.kubernetes.api.model.AWSElasticBlockStoreVolumeSourceBuilder builder;

  private final io.fabric8.kubernetes.api.builder.Function<io.fabric8.kubernetes.api.model.AWSElasticBlockStoreVolumeSource, io.fabric8.kubernetes.api.model.AWSElasticBlockStoreVolumeSource> function;

  public io.fabric8.kubernetes.api.model.DoneableAWSElasticBlockStoreVolumeSource(io.fabric8.kubernetes.api.builder.Function<io.fabric8.kubernetes.api.model.AWSElasticBlockStoreVolumeSource, io.fabric8.kubernetes.api.model.AWSElasticBlockStoreVolumeSource>);
    Code:
       0: aload_0
       1: invokespecial #1                  // Method io/fabric8/kubernetes/api/model/AWSElasticBlockStoreVolumeSourceFluentImpl."<init>":()V
       4: aload_0
       5: new           #2                  // class io/fabric8/kubernetes/api/model/AWSElasticBlockStoreVolumeSourceBuilder
       8: dup
       9: aload_0
      10: invokespecial #3                  // Method io/fabric8/kubernetes/api/model/AWSElasticBlockStoreVolumeSourceBuilder."<init>":(Lio/fabric8/kubernetes/api/model/AWSElasticBlockStoreVolumeSourceFluent;)V
      13: putfield      #4                  // Field builder:Lio/fabric8/kubernetes/api/model/AWSElasticBlockStoreVolumeSourceBuilder;
      16: aload_0
      17: aload_1
      18: putfield      #5                  // Field function:Lio/fabric8/kubernetes/api/builder/Function;
      21: return

  public io.fabric8.kubernetes.api.model.DoneableAWSElasticBlockStoreVolumeSource(io.fabric8.kubernetes.api.model.AWSElasticBlockStoreVolumeSource, io.fabric8.kubernetes.api.builder.Function<io.fabric8.kubernetes.api.model.AWSElasticBlockStoreVolumeSource, io.fabric8.kubernetes.api.model.AWSElasticBlockStoreVolumeSource>);
    Code:
       0: aload_0
       1: aload_1
       2: invokespecial #6                  // Method io/fabric8/kubernetes/api/model/AWSElasticBlockStoreVolumeSourceFluentImpl."<init>":(Lio/fabric8/kubernetes/api/model/AWSElasticBlockStoreVolumeSource;)V
       5: aload_0
       6: new           #2                  // class io/fabric8/kubernetes/api/model/AWSElasticBlockStoreVolumeSourceBuilder
       9: dup
      10: aload_0
      11: aload_1
      12: invokespecial #7                  // Method io/fabric8/kubernetes/api/model/AWSElasticBlockStoreVolumeSourceBuilder."<init>":(Lio/fabric8/kubernetes/api/model/AWSElasticBlockStoreVolumeSourceFluent;Lio/fabric8/kubernetes/api/model/AWSElasticBlockStoreVolumeSource;)V
      15: putfield      #4                  // Field builder:Lio/fabric8/kubernetes/api/model/AWSElasticBlockStoreVolumeSourceBuilder;
      18: aload_0
      19: aload_2
      20: putfield      #5                  // Field function:Lio/fabric8/kubernetes/api/builder/Function;
      23: return

  public io.fabric8.kubernetes.api.model.DoneableAWSElasticBlockStoreVolumeSource(io.fabric8.kubernetes.api.model.AWSElasticBlockStoreVolumeSource);
    Code:
       0: aload_0
       1: aload_1
       2: invokespecial #6                  // Method io/fabric8/kubernetes/api/model/AWSElasticBlockStoreVolumeSourceFluentImpl."<init>":(Lio/fabric8/kubernetes/api/model/AWSElasticBlockStoreVolumeSource;)V
       5: aload_0
       6: new           #2                  // class io/fabric8/kubernetes/api/model/AWSElasticBlockStoreVolumeSourceBuilder
       9: dup
      10: aload_0
      11: aload_1
      12: invokespecial #7                  // Method io/fabric8/kubernetes/api/model/AWSElasticBlockStoreVolumeSourceBuilder."<init>":(Lio/fabric8/kubernetes/api/model/AWSElasticBlockStoreVolumeSourceFluent;Lio/fabric8/kubernetes/api/model/AWSElasticBlockStoreVolumeSource;)V
      15: putfield      #4                  // Field builder:Lio/fabric8/kubernetes/api/model/AWSElasticBlockStoreVolumeSourceBuilder;
      18: aload_0
      19: new           #8                  // class io/fabric8/kubernetes/api/model/DoneableAWSElasticBlockStoreVolumeSource$1
      22: dup
      23: aload_0
      24: invokespecial #9                  // Method io/fabric8/kubernetes/api/model/DoneableAWSElasticBlockStoreVolumeSource$1."<init>":(Lio/fabric8/kubernetes/api/model/DoneableAWSElasticBlockStoreVolumeSource;)V
      27: putfield      #5                  // Field function:Lio/fabric8/kubernetes/api/builder/Function;
      30: return

  public io.fabric8.kubernetes.api.model.AWSElasticBlockStoreVolumeSource done();
    Code:
       0: aload_0
       1: getfield      #5                  // Field function:Lio/fabric8/kubernetes/api/builder/Function;
       4: aload_0
       5: getfield      #4                  // Field builder:Lio/fabric8/kubernetes/api/model/AWSElasticBlockStoreVolumeSourceBuilder;
       8: invokevirtual #10                 // Method io/fabric8/kubernetes/api/model/AWSElasticBlockStoreVolumeSourceBuilder.build:()Lio/fabric8/kubernetes/api/model/AWSElasticBlockStoreVolumeSource;
      11: invokeinterface #11,  2           // InterfaceMethod io/fabric8/kubernetes/api/builder/Function.apply:(Ljava/lang/Object;)Ljava/lang/Object;
      16: checkcast     #12                 // class io/fabric8/kubernetes/api/model/AWSElasticBlockStoreVolumeSource
      19: areturn

  public java.lang.Object done();
    Code:
       0: aload_0
       1: invokevirtual #13                 // Method done:()Lio/fabric8/kubernetes/api/model/AWSElasticBlockStoreVolumeSource;
       4: areturn
}
