Compiled from "DoneableFCVolumeSource.java"
public class io.fabric8.kubernetes.api.model.DoneableFCVolumeSource extends io.fabric8.kubernetes.api.model.FCVolumeSourceFluentImpl<io.fabric8.kubernetes.api.model.DoneableFCVolumeSource> implements io.fabric8.kubernetes.api.model.Doneable<io.fabric8.kubernetes.api.model.FCVolumeSource> {
  private final io.fabric8.kubernetes.api.model.FCVolumeSourceBuilder builder;

  private final io.fabric8.kubernetes.api.builder.Function<io.fabric8.kubernetes.api.model.FCVolumeSource, io.fabric8.kubernetes.api.model.FCVolumeSource> function;

  public io.fabric8.kubernetes.api.model.DoneableFCVolumeSource(io.fabric8.kubernetes.api.builder.Function<io.fabric8.kubernetes.api.model.FCVolumeSource, io.fabric8.kubernetes.api.model.FCVolumeSource>);
    Code:
       0: aload_0
       1: invokespecial #1                  // Method io/fabric8/kubernetes/api/model/FCVolumeSourceFluentImpl."<init>":()V
       4: aload_0
       5: new           #2                  // class io/fabric8/kubernetes/api/model/FCVolumeSourceBuilder
       8: dup
       9: aload_0
      10: invokespecial #3                  // Method io/fabric8/kubernetes/api/model/FCVolumeSourceBuilder."<init>":(Lio/fabric8/kubernetes/api/model/FCVolumeSourceFluent;)V
      13: putfield      #4                  // Field builder:Lio/fabric8/kubernetes/api/model/FCVolumeSourceBuilder;
      16: aload_0
      17: aload_1
      18: putfield      #5                  // Field function:Lio/fabric8/kubernetes/api/builder/Function;
      21: return

  public io.fabric8.kubernetes.api.model.DoneableFCVolumeSource(io.fabric8.kubernetes.api.model.FCVolumeSource, io.fabric8.kubernetes.api.builder.Function<io.fabric8.kubernetes.api.model.FCVolumeSource, io.fabric8.kubernetes.api.model.FCVolumeSource>);
    Code:
       0: aload_0
       1: aload_1
       2: invokespecial #6                  // Method io/fabric8/kubernetes/api/model/FCVolumeSourceFluentImpl."<init>":(Lio/fabric8/kubernetes/api/model/FCVolumeSource;)V
       5: aload_0
       6: new           #2                  // class io/fabric8/kubernetes/api/model/FCVolumeSourceBuilder
       9: dup
      10: aload_0
      11: aload_1
      12: invokespecial #7                  // Method io/fabric8/kubernetes/api/model/FCVolumeSourceBuilder."<init>":(Lio/fabric8/kubernetes/api/model/FCVolumeSourceFluent;Lio/fabric8/kubernetes/api/model/FCVolumeSource;)V
      15: putfield      #4                  // Field builder:Lio/fabric8/kubernetes/api/model/FCVolumeSourceBuilder;
      18: aload_0
      19: aload_2
      20: putfield      #5                  // Field function:Lio/fabric8/kubernetes/api/builder/Function;
      23: return

  public io.fabric8.kubernetes.api.model.DoneableFCVolumeSource(io.fabric8.kubernetes.api.model.FCVolumeSource);
    Code:
       0: aload_0
       1: aload_1
       2: invokespecial #6                  // Method io/fabric8/kubernetes/api/model/FCVolumeSourceFluentImpl."<init>":(Lio/fabric8/kubernetes/api/model/FCVolumeSource;)V
       5: aload_0
       6: new           #2                  // class io/fabric8/kubernetes/api/model/FCVolumeSourceBuilder
       9: dup
      10: aload_0
      11: aload_1
      12: invokespecial #7                  // Method io/fabric8/kubernetes/api/model/FCVolumeSourceBuilder."<init>":(Lio/fabric8/kubernetes/api/model/FCVolumeSourceFluent;Lio/fabric8/kubernetes/api/model/FCVolumeSource;)V
      15: putfield      #4                  // Field builder:Lio/fabric8/kubernetes/api/model/FCVolumeSourceBuilder;
      18: aload_0
      19: new           #8                  // class io/fabric8/kubernetes/api/model/DoneableFCVolumeSource$1
      22: dup
      23: aload_0
      24: invokespecial #9                  // Method io/fabric8/kubernetes/api/model/DoneableFCVolumeSource$1."<init>":(Lio/fabric8/kubernetes/api/model/DoneableFCVolumeSource;)V
      27: putfield      #5                  // Field function:Lio/fabric8/kubernetes/api/builder/Function;
      30: return

  public io.fabric8.kubernetes.api.model.FCVolumeSource done();
    Code:
       0: aload_0
       1: getfield      #5                  // Field function:Lio/fabric8/kubernetes/api/builder/Function;
       4: aload_0
       5: getfield      #4                  // Field builder:Lio/fabric8/kubernetes/api/model/FCVolumeSourceBuilder;
       8: invokevirtual #10                 // Method io/fabric8/kubernetes/api/model/FCVolumeSourceBuilder.build:()Lio/fabric8/kubernetes/api/model/FCVolumeSource;
      11: invokeinterface #11,  2           // InterfaceMethod io/fabric8/kubernetes/api/builder/Function.apply:(Ljava/lang/Object;)Ljava/lang/Object;
      16: checkcast     #12                 // class io/fabric8/kubernetes/api/model/FCVolumeSource
      19: areturn

  public java.lang.Object done();
    Code:
       0: aload_0
       1: invokevirtual #13                 // Method done:()Lio/fabric8/kubernetes/api/model/FCVolumeSource;
       4: areturn
}
