Compiled from "IntOrString.java"
public class io.fabric8.kubernetes.api.model.IntOrString$Deserializer extends com.fasterxml.jackson.databind.JsonDeserializer<io.fabric8.kubernetes.api.model.IntOrString> {
  public io.fabric8.kubernetes.api.model.IntOrString$Deserializer();
    Code:
       0: aload_0
       1: invokespecial #1                  // Method com/fasterxml/jackson/databind/JsonDeserializer."<init>":()V
       4: return

  public io.fabric8.kubernetes.api.model.IntOrString deserialize(com.fasterxml.jackson.core.JsonParser, com.fasterxml.jackson.databind.DeserializationContext) throws java.io.IOException, com.fasterxml.jackson.core.JsonProcessingException;
    Code:
       0: aload_1
       1: invokevirtual #2                  // Method com/fasterxml/jackson/core/JsonParser.getCodec:()Lcom/fasterxml/jackson/core/ObjectCodec;
       4: astore_3
       5: aload_3
       6: aload_1
       7: invokevirtual #3                  // Method com/fasterxml/jackson/core/ObjectCodec.readTree:(Lcom/fasterxml/jackson/core/JsonParser;)Lcom/fasterxml/jackson/core/TreeNode;
      10: checkcast     #4                  // class com/fasterxml/jackson/databind/JsonNode
      13: astore        4
      15: aload         4
      17: invokevirtual #5                  // Method com/fasterxml/jackson/databind/JsonNode.isInt:()Z
      20: ifeq          43
      23: new           #6                  // class io/fabric8/kubernetes/api/model/IntOrString
      26: dup
      27: aload         4
      29: invokevirtual #7                  // Method com/fasterxml/jackson/databind/JsonNode.asInt:()I
      32: invokestatic  #8                  // Method java/lang/Integer.valueOf:(I)Ljava/lang/Integer;
      35: invokespecial #9                  // Method io/fabric8/kubernetes/api/model/IntOrString."<init>":(Ljava/lang/Integer;)V
      38: astore        5
      40: goto          57
      43: new           #6                  // class io/fabric8/kubernetes/api/model/IntOrString
      46: dup
      47: aload         4
      49: invokevirtual #10                 // Method com/fasterxml/jackson/databind/JsonNode.asText:()Ljava/lang/String;
      52: invokespecial #11                 // Method io/fabric8/kubernetes/api/model/IntOrString."<init>":(Ljava/lang/String;)V
      55: astore        5
      57: aload         5
      59: areturn

  public java.lang.Object deserialize(com.fasterxml.jackson.core.JsonParser, com.fasterxml.jackson.databind.DeserializationContext) throws java.io.IOException, com.fasterxml.jackson.core.JsonProcessingException;
    Code:
       0: aload_0
       1: aload_1
       2: aload_2
       3: invokevirtual #12                 // Method deserialize:(Lcom/fasterxml/jackson/core/JsonParser;Lcom/fasterxml/jackson/databind/DeserializationContext;)Lio/fabric8/kubernetes/api/model/IntOrString;
       6: areturn
}
