Compiled from "LabelSelectorFluentImpl.java"
public class io.fabric8.kubernetes.api.model.LabelSelectorFluentImpl$MatchExpressionsNestedImpl<N> extends io.fabric8.kubernetes.api.model.LabelSelectorRequirementFluentImpl<io.fabric8.kubernetes.api.model.LabelSelectorFluent$MatchExpressionsNested<N>> implements io.fabric8.kubernetes.api.model.LabelSelectorFluent$MatchExpressionsNested<N>, io.fabric8.kubernetes.api.builder.Nested<N> {
  private final io.fabric8.kubernetes.api.model.LabelSelectorRequirementBuilder builder;

  private final int index;

  final io.fabric8.kubernetes.api.model.LabelSelectorFluentImpl this$0;

  io.fabric8.kubernetes.api.model.LabelSelectorFluentImpl$MatchExpressionsNestedImpl(io.fabric8.kubernetes.api.model.LabelSelectorFluentImpl, int, io.fabric8.kubernetes.api.model.LabelSelectorRequirement);
    Code:
       0: aload_0
       1: aload_1
       2: putfield      #1                  // Field this$0:Lio/fabric8/kubernetes/api/model/LabelSelectorFluentImpl;
       5: aload_0
       6: invokespecial #2                  // Method io/fabric8/kubernetes/api/model/LabelSelectorRequirementFluentImpl."<init>":()V
       9: aload_0
      10: iload_2
      11: putfield      #3                  // Field index:I
      14: aload_0
      15: new           #4                  // class io/fabric8/kubernetes/api/model/LabelSelectorRequirementBuilder
      18: dup
      19: aload_0
      20: aload_3
      21: invokespecial #5                  // Method io/fabric8/kubernetes/api/model/LabelSelectorRequirementBuilder."<init>":(Lio/fabric8/kubernetes/api/model/LabelSelectorRequirementFluent;Lio/fabric8/kubernetes/api/model/LabelSelectorRequirement;)V
      24: putfield      #6                  // Field builder:Lio/fabric8/kubernetes/api/model/LabelSelectorRequirementBuilder;
      27: return

  io.fabric8.kubernetes.api.model.LabelSelectorFluentImpl$MatchExpressionsNestedImpl(io.fabric8.kubernetes.api.model.LabelSelectorFluentImpl);
    Code:
       0: aload_0
       1: aload_1
       2: putfield      #1                  // Field this$0:Lio/fabric8/kubernetes/api/model/LabelSelectorFluentImpl;
       5: aload_0
       6: invokespecial #2                  // Method io/fabric8/kubernetes/api/model/LabelSelectorRequirementFluentImpl."<init>":()V
       9: aload_0
      10: iconst_m1
      11: putfield      #3                  // Field index:I
      14: aload_0
      15: new           #4                  // class io/fabric8/kubernetes/api/model/LabelSelectorRequirementBuilder
      18: dup
      19: aload_0
      20: invokespecial #7                  // Method io/fabric8/kubernetes/api/model/LabelSelectorRequirementBuilder."<init>":(Lio/fabric8/kubernetes/api/model/LabelSelectorRequirementFluent;)V
      23: putfield      #6                  // Field builder:Lio/fabric8/kubernetes/api/model/LabelSelectorRequirementBuilder;
      26: return

  public N and();
    Code:
       0: aload_0
       1: getfield      #1                  // Field this$0:Lio/fabric8/kubernetes/api/model/LabelSelectorFluentImpl;
       4: aload_0
       5: getfield      #3                  // Field index:I
       8: aload_0
       9: getfield      #6                  // Field builder:Lio/fabric8/kubernetes/api/model/LabelSelectorRequirementBuilder;
      12: invokevirtual #8                  // Method io/fabric8/kubernetes/api/model/LabelSelectorRequirementBuilder.build:()Lio/fabric8/kubernetes/api/model/LabelSelectorRequirement;
      15: invokevirtual #9                  // Method io/fabric8/kubernetes/api/model/LabelSelectorFluentImpl.setToMatchExpressions:(ILio/fabric8/kubernetes/api/model/LabelSelectorRequirement;)Lio/fabric8/kubernetes/api/model/LabelSelectorFluent;
      18: areturn

  public N endMatchExpression();
    Code:
       0: aload_0
       1: invokevirtual #10                 // Method and:()Ljava/lang/Object;
       4: areturn
}
