Compiled from "PodStatusFluentImpl.java"
public class io.fabric8.kubernetes.api.model.PodStatusFluentImpl$InitContainerStatusesNestedImpl<N> extends io.fabric8.kubernetes.api.model.ContainerStatusFluentImpl<io.fabric8.kubernetes.api.model.PodStatusFluent$InitContainerStatusesNested<N>> implements io.fabric8.kubernetes.api.model.PodStatusFluent$InitContainerStatusesNested<N>, io.fabric8.kubernetes.api.builder.Nested<N> {
  private final io.fabric8.kubernetes.api.model.ContainerStatusBuilder builder;

  private final int index;

  final io.fabric8.kubernetes.api.model.PodStatusFluentImpl this$0;

  io.fabric8.kubernetes.api.model.PodStatusFluentImpl$InitContainerStatusesNestedImpl(io.fabric8.kubernetes.api.model.PodStatusFluentImpl, int, io.fabric8.kubernetes.api.model.ContainerStatus);
    Code:
       0: aload_0
       1: aload_1
       2: putfield      #1                  // Field this$0:Lio/fabric8/kubernetes/api/model/PodStatusFluentImpl;
       5: aload_0
       6: invokespecial #2                  // Method io/fabric8/kubernetes/api/model/ContainerStatusFluentImpl."<init>":()V
       9: aload_0
      10: iload_2
      11: putfield      #3                  // Field index:I
      14: aload_0
      15: new           #4                  // class io/fabric8/kubernetes/api/model/ContainerStatusBuilder
      18: dup
      19: aload_0
      20: aload_3
      21: invokespecial #5                  // Method io/fabric8/kubernetes/api/model/ContainerStatusBuilder."<init>":(Lio/fabric8/kubernetes/api/model/ContainerStatusFluent;Lio/fabric8/kubernetes/api/model/ContainerStatus;)V
      24: putfield      #6                  // Field builder:Lio/fabric8/kubernetes/api/model/ContainerStatusBuilder;
      27: return

  io.fabric8.kubernetes.api.model.PodStatusFluentImpl$InitContainerStatusesNestedImpl(io.fabric8.kubernetes.api.model.PodStatusFluentImpl);
    Code:
       0: aload_0
       1: aload_1
       2: putfield      #1                  // Field this$0:Lio/fabric8/kubernetes/api/model/PodStatusFluentImpl;
       5: aload_0
       6: invokespecial #2                  // Method io/fabric8/kubernetes/api/model/ContainerStatusFluentImpl."<init>":()V
       9: aload_0
      10: iconst_m1
      11: putfield      #3                  // Field index:I
      14: aload_0
      15: new           #4                  // class io/fabric8/kubernetes/api/model/ContainerStatusBuilder
      18: dup
      19: aload_0
      20: invokespecial #7                  // Method io/fabric8/kubernetes/api/model/ContainerStatusBuilder."<init>":(Lio/fabric8/kubernetes/api/model/ContainerStatusFluent;)V
      23: putfield      #6                  // Field builder:Lio/fabric8/kubernetes/api/model/ContainerStatusBuilder;
      26: return

  public N and();
    Code:
       0: aload_0
       1: getfield      #1                  // Field this$0:Lio/fabric8/kubernetes/api/model/PodStatusFluentImpl;
       4: aload_0
       5: getfield      #3                  // Field index:I
       8: aload_0
       9: getfield      #6                  // Field builder:Lio/fabric8/kubernetes/api/model/ContainerStatusBuilder;
      12: invokevirtual #8                  // Method io/fabric8/kubernetes/api/model/ContainerStatusBuilder.build:()Lio/fabric8/kubernetes/api/model/ContainerStatus;
      15: invokevirtual #9                  // Method io/fabric8/kubernetes/api/model/PodStatusFluentImpl.setToInitContainerStatuses:(ILio/fabric8/kubernetes/api/model/ContainerStatus;)Lio/fabric8/kubernetes/api/model/PodStatusFluent;
      18: areturn

  public N endInitContainerStatus();
    Code:
       0: aload_0
       1: invokevirtual #10                 // Method and:()Ljava/lang/Object;
       4: areturn
}
