Compiled from "SecurityContextFluentImpl.java"
public class io.fabric8.kubernetes.api.model.SecurityContextFluentImpl$WindowsOptionsNestedImpl<N> extends io.fabric8.kubernetes.api.model.WindowsSecurityContextOptionsFluentImpl<io.fabric8.kubernetes.api.model.SecurityContextFluent$WindowsOptionsNested<N>> implements io.fabric8.kubernetes.api.model.SecurityContextFluent$WindowsOptionsNested<N>, io.fabric8.kubernetes.api.builder.Nested<N> {
  private final io.fabric8.kubernetes.api.model.WindowsSecurityContextOptionsBuilder builder;

  final io.fabric8.kubernetes.api.model.SecurityContextFluentImpl this$0;

  io.fabric8.kubernetes.api.model.SecurityContextFluentImpl$WindowsOptionsNestedImpl(io.fabric8.kubernetes.api.model.SecurityContextFluentImpl, io.fabric8.kubernetes.api.model.WindowsSecurityContextOptions);
    Code:
       0: aload_0
       1: aload_1
       2: putfield      #1                  // Field this$0:Lio/fabric8/kubernetes/api/model/SecurityContextFluentImpl;
       5: aload_0
       6: invokespecial #2                  // Method io/fabric8/kubernetes/api/model/WindowsSecurityContextOptionsFluentImpl."<init>":()V
       9: aload_0
      10: new           #3                  // class io/fabric8/kubernetes/api/model/WindowsSecurityContextOptionsBuilder
      13: dup
      14: aload_0
      15: aload_2
      16: invokespecial #4                  // Method io/fabric8/kubernetes/api/model/WindowsSecurityContextOptionsBuilder."<init>":(Lio/fabric8/kubernetes/api/model/WindowsSecurityContextOptionsFluent;Lio/fabric8/kubernetes/api/model/WindowsSecurityContextOptions;)V
      19: putfield      #5                  // Field builder:Lio/fabric8/kubernetes/api/model/WindowsSecurityContextOptionsBuilder;
      22: return

  io.fabric8.kubernetes.api.model.SecurityContextFluentImpl$WindowsOptionsNestedImpl(io.fabric8.kubernetes.api.model.SecurityContextFluentImpl);
    Code:
       0: aload_0
       1: aload_1
       2: putfield      #1                  // Field this$0:Lio/fabric8/kubernetes/api/model/SecurityContextFluentImpl;
       5: aload_0
       6: invokespecial #2                  // Method io/fabric8/kubernetes/api/model/WindowsSecurityContextOptionsFluentImpl."<init>":()V
       9: aload_0
      10: new           #3                  // class io/fabric8/kubernetes/api/model/WindowsSecurityContextOptionsBuilder
      13: dup
      14: aload_0
      15: invokespecial #6                  // Method io/fabric8/kubernetes/api/model/WindowsSecurityContextOptionsBuilder."<init>":(Lio/fabric8/kubernetes/api/model/WindowsSecurityContextOptionsFluent;)V
      18: putfield      #5                  // Field builder:Lio/fabric8/kubernetes/api/model/WindowsSecurityContextOptionsBuilder;
      21: return

  public N and();
    Code:
       0: aload_0
       1: getfield      #1                  // Field this$0:Lio/fabric8/kubernetes/api/model/SecurityContextFluentImpl;
       4: aload_0
       5: getfield      #5                  // Field builder:Lio/fabric8/kubernetes/api/model/WindowsSecurityContextOptionsBuilder;
       8: invokevirtual #7                  // Method io/fabric8/kubernetes/api/model/WindowsSecurityContextOptionsBuilder.build:()Lio/fabric8/kubernetes/api/model/WindowsSecurityContextOptions;
      11: invokevirtual #8                  // Method io/fabric8/kubernetes/api/model/SecurityContextFluentImpl.withWindowsOptions:(Lio/fabric8/kubernetes/api/model/WindowsSecurityContextOptions;)Lio/fabric8/kubernetes/api/model/SecurityContextFluent;
      14: areturn

  public N endWindowsOptions();
    Code:
       0: aload_0
       1: invokevirtual #9                  // Method and:()Ljava/lang/Object;
       4: areturn
}
