Compiled from "WatchEventFluentImpl.java"
public class io.fabric8.kubernetes.api.model.WatchEventFluentImpl$PersistentVolumeClaimConditionObjectNestedImpl<N> extends io.fabric8.kubernetes.api.model.PersistentVolumeClaimConditionFluentImpl<io.fabric8.kubernetes.api.model.WatchEventFluent$PersistentVolumeClaimConditionObjectNested<N>> implements io.fabric8.kubernetes.api.model.WatchEventFluent$PersistentVolumeClaimConditionObjectNested<N>, io.fabric8.kubernetes.api.builder.Nested<N> {
  private final io.fabric8.kubernetes.api.model.PersistentVolumeClaimConditionBuilder builder;

  final io.fabric8.kubernetes.api.model.WatchEventFluentImpl this$0;

  io.fabric8.kubernetes.api.model.WatchEventFluentImpl$PersistentVolumeClaimConditionObjectNestedImpl(io.fabric8.kubernetes.api.model.WatchEventFluentImpl, io.fabric8.kubernetes.api.model.PersistentVolumeClaimCondition);
    Code:
       0: aload_0
       1: aload_1
       2: putfield      #1                  // Field this$0:Lio/fabric8/kubernetes/api/model/WatchEventFluentImpl;
       5: aload_0
       6: invokespecial #2                  // Method io/fabric8/kubernetes/api/model/PersistentVolumeClaimConditionFluentImpl."<init>":()V
       9: aload_0
      10: new           #3                  // class io/fabric8/kubernetes/api/model/PersistentVolumeClaimConditionBuilder
      13: dup
      14: aload_0
      15: aload_2
      16: invokespecial #4                  // Method io/fabric8/kubernetes/api/model/PersistentVolumeClaimConditionBuilder."<init>":(Lio/fabric8/kubernetes/api/model/PersistentVolumeClaimConditionFluent;Lio/fabric8/kubernetes/api/model/PersistentVolumeClaimCondition;)V
      19: putfield      #5                  // Field builder:Lio/fabric8/kubernetes/api/model/PersistentVolumeClaimConditionBuilder;
      22: return

  io.fabric8.kubernetes.api.model.WatchEventFluentImpl$PersistentVolumeClaimConditionObjectNestedImpl(io.fabric8.kubernetes.api.model.WatchEventFluentImpl);
    Code:
       0: aload_0
       1: aload_1
       2: putfield      #1                  // Field this$0:Lio/fabric8/kubernetes/api/model/WatchEventFluentImpl;
       5: aload_0
       6: invokespecial #2                  // Method io/fabric8/kubernetes/api/model/PersistentVolumeClaimConditionFluentImpl."<init>":()V
       9: aload_0
      10: new           #3                  // class io/fabric8/kubernetes/api/model/PersistentVolumeClaimConditionBuilder
      13: dup
      14: aload_0
      15: invokespecial #6                  // Method io/fabric8/kubernetes/api/model/PersistentVolumeClaimConditionBuilder."<init>":(Lio/fabric8/kubernetes/api/model/PersistentVolumeClaimConditionFluent;)V
      18: putfield      #5                  // Field builder:Lio/fabric8/kubernetes/api/model/PersistentVolumeClaimConditionBuilder;
      21: return

  public N and();
    Code:
       0: aload_0
       1: getfield      #1                  // Field this$0:Lio/fabric8/kubernetes/api/model/WatchEventFluentImpl;
       4: aload_0
       5: getfield      #5                  // Field builder:Lio/fabric8/kubernetes/api/model/PersistentVolumeClaimConditionBuilder;
       8: invokevirtual #7                  // Method io/fabric8/kubernetes/api/model/PersistentVolumeClaimConditionBuilder.build:()Lio/fabric8/kubernetes/api/model/PersistentVolumeClaimCondition;
      11: invokevirtual #8                  // Method io/fabric8/kubernetes/api/model/WatchEventFluentImpl.withObject:(Lio/fabric8/kubernetes/api/model/KubernetesResource;)Lio/fabric8/kubernetes/api/model/WatchEventFluent;
      14: areturn

  public N endPersistentVolumeClaimConditionObject();
    Code:
       0: aload_0
       1: invokevirtual #9                  // Method and:()Ljava/lang/Object;
       4: areturn
}
