Compiled from "WatchEventFluentImpl.java"
public class io.fabric8.kubernetes.api.model.WatchEventFluentImpl$NamedExtensionObjectNestedImpl<N> extends io.fabric8.kubernetes.api.model.NamedExtensionFluentImpl<io.fabric8.kubernetes.api.model.WatchEventFluent$NamedExtensionObjectNested<N>> implements io.fabric8.kubernetes.api.model.WatchEventFluent$NamedExtensionObjectNested<N>, io.fabric8.kubernetes.api.builder.Nested<N> {
  private final io.fabric8.kubernetes.api.model.NamedExtensionBuilder builder;

  final io.fabric8.kubernetes.api.model.WatchEventFluentImpl this$0;

  io.fabric8.kubernetes.api.model.WatchEventFluentImpl$NamedExtensionObjectNestedImpl(io.fabric8.kubernetes.api.model.WatchEventFluentImpl, io.fabric8.kubernetes.api.model.NamedExtension);
    Code:
       0: aload_0
       1: aload_1
       2: putfield      #1                  // Field this$0:Lio/fabric8/kubernetes/api/model/WatchEventFluentImpl;
       5: aload_0
       6: invokespecial #2                  // Method io/fabric8/kubernetes/api/model/NamedExtensionFluentImpl."<init>":()V
       9: aload_0
      10: new           #3                  // class io/fabric8/kubernetes/api/model/NamedExtensionBuilder
      13: dup
      14: aload_0
      15: aload_2
      16: invokespecial #4                  // Method io/fabric8/kubernetes/api/model/NamedExtensionBuilder."<init>":(Lio/fabric8/kubernetes/api/model/NamedExtensionFluent;Lio/fabric8/kubernetes/api/model/NamedExtension;)V
      19: putfield      #5                  // Field builder:Lio/fabric8/kubernetes/api/model/NamedExtensionBuilder;
      22: return

  io.fabric8.kubernetes.api.model.WatchEventFluentImpl$NamedExtensionObjectNestedImpl(io.fabric8.kubernetes.api.model.WatchEventFluentImpl);
    Code:
       0: aload_0
       1: aload_1
       2: putfield      #1                  // Field this$0:Lio/fabric8/kubernetes/api/model/WatchEventFluentImpl;
       5: aload_0
       6: invokespecial #2                  // Method io/fabric8/kubernetes/api/model/NamedExtensionFluentImpl."<init>":()V
       9: aload_0
      10: new           #3                  // class io/fabric8/kubernetes/api/model/NamedExtensionBuilder
      13: dup
      14: aload_0
      15: invokespecial #6                  // Method io/fabric8/kubernetes/api/model/NamedExtensionBuilder."<init>":(Lio/fabric8/kubernetes/api/model/NamedExtensionFluent;)V
      18: putfield      #5                  // Field builder:Lio/fabric8/kubernetes/api/model/NamedExtensionBuilder;
      21: return

  public N and();
    Code:
       0: aload_0
       1: getfield      #1                  // Field this$0:Lio/fabric8/kubernetes/api/model/WatchEventFluentImpl;
       4: aload_0
       5: getfield      #5                  // Field builder:Lio/fabric8/kubernetes/api/model/NamedExtensionBuilder;
       8: invokevirtual #7                  // Method io/fabric8/kubernetes/api/model/NamedExtensionBuilder.build:()Lio/fabric8/kubernetes/api/model/NamedExtension;
      11: invokevirtual #8                  // Method io/fabric8/kubernetes/api/model/WatchEventFluentImpl.withObject:(Lio/fabric8/kubernetes/api/model/KubernetesResource;)Lio/fabric8/kubernetes/api/model/WatchEventFluent;
      14: areturn

  public N endNamedExtensionObject();
    Code:
       0: aload_0
       1: invokevirtual #9                  // Method and:()Ljava/lang/Object;
       4: areturn
}
