Compiled from "SpringPropertiesHolder.java"
public interface io.dekorate.spring.SpringPropertiesHolder extends io.dekorate.WithProject {
  public static final java.util.concurrent.atomic.AtomicReference<java.util.Map<java.lang.String, java.lang.Object>> springProperties;

  public default java.util.Map<java.lang.String, java.lang.Object> getSpringProperties();
    Code:
       0: getstatic     #1                  // Field springProperties:Ljava/util/concurrent/atomic/AtomicReference;
       3: invokevirtual #2                  // Method java/util/concurrent/atomic/AtomicReference.get:()Ljava/lang/Object;
       6: ifnonnull     75
       9: new           #3                  // class java/util/HashMap
      12: dup
      13: invokespecial #4                  // Method java/util/HashMap."<init>":()V
      16: astore_1
      17: aload_1
      18: aload_0
      19: invokeinterface #5,  1            // InterfaceMethod getProject:()Lio/dekorate/project/Project;
      24: ldc           #6                  // String application.properties
      26: invokevirtual #7                  // Method io/dekorate/project/Project.parseResourceFile:(Ljava/lang/String;)Ljava/util/Map;
      29: invokeinterface #8,  2            // InterfaceMethod java/util/Map.putAll:(Ljava/util/Map;)V
      34: aload_1
      35: aload_0
      36: invokeinterface #5,  1            // InterfaceMethod getProject:()Lio/dekorate/project/Project;
      41: ldc           #9                  // String application.yaml
      43: invokevirtual #7                  // Method io/dekorate/project/Project.parseResourceFile:(Ljava/lang/String;)Ljava/util/Map;
      46: invokeinterface #8,  2            // InterfaceMethod java/util/Map.putAll:(Ljava/util/Map;)V
      51: aload_1
      52: aload_0
      53: invokeinterface #5,  1            // InterfaceMethod getProject:()Lio/dekorate/project/Project;
      58: ldc           #10                 // String application.yml
      60: invokevirtual #7                  // Method io/dekorate/project/Project.parseResourceFile:(Ljava/lang/String;)Ljava/util/Map;
      63: invokeinterface #8,  2            // InterfaceMethod java/util/Map.putAll:(Ljava/util/Map;)V
      68: getstatic     #1                  // Field springProperties:Ljava/util/concurrent/atomic/AtomicReference;
      71: aload_1
      72: invokevirtual #11                 // Method java/util/concurrent/atomic/AtomicReference.set:(Ljava/lang/Object;)V
      75: getstatic     #1                  // Field springProperties:Ljava/util/concurrent/atomic/AtomicReference;
      78: invokevirtual #2                  // Method java/util/concurrent/atomic/AtomicReference.get:()Ljava/lang/Object;
      81: checkcast     #12                 // class java/util/Map
      84: areturn

  static {};
    Code:
       0: new           #13                 // class java/util/concurrent/atomic/AtomicReference
       3: dup
       4: aconst_null
       5: invokespecial #14                 // Method java/util/concurrent/atomic/AtomicReference."<init>":(Ljava/lang/Object;)V
       8: putstatic     #1                  // Field springProperties:Ljava/util/concurrent/atomic/AtomicReference;
      11: return
}
