Compiled from "ServiceFinder.java"
public final class org.glassfish.jersey.internal.ServiceFinder$DefaultServiceIteratorProvider extends org.glassfish.jersey.internal.ServiceFinder$ServiceIteratorProvider {
  public org.glassfish.jersey.internal.ServiceFinder$DefaultServiceIteratorProvider();
    Code:
       0: aload_0
       1: invokespecial #1                  // Method org/glassfish/jersey/internal/ServiceFinder$ServiceIteratorProvider."<init>":()V
       4: return

  public <T> java.util.Iterator<T> createIterator(java.lang.Class<T>, java.lang.String, java.lang.ClassLoader, boolean);
    Code:
       0: new           #2                  // class org/glassfish/jersey/internal/ServiceFinder$LazyObjectIterator
       3: dup
       4: aload_1
       5: aload_2
       6: aload_3
       7: iload         4
       9: aconst_null
      10: invokespecial #3                  // Method org/glassfish/jersey/internal/ServiceFinder$LazyObjectIterator."<init>":(Ljava/lang/Class;Ljava/lang/String;Ljava/lang/ClassLoader;ZLorg/glassfish/jersey/internal/ServiceFinder$1;)V
      13: areturn

  public <T> java.util.Iterator<java.lang.Class<T>> createClassIterator(java.lang.Class<T>, java.lang.String, java.lang.ClassLoader, boolean);
    Code:
       0: new           #4                  // class org/glassfish/jersey/internal/ServiceFinder$LazyClassIterator
       3: dup
       4: aload_1
       5: aload_2
       6: aload_3
       7: iload         4
       9: aconst_null
      10: invokespecial #5                  // Method org/glassfish/jersey/internal/ServiceFinder$LazyClassIterator."<init>":(Ljava/lang/Class;Ljava/lang/String;Ljava/lang/ClassLoader;ZLorg/glassfish/jersey/internal/ServiceFinder$1;)V
      13: areturn
}
