Compiled from "ServerZkReceiptOperations.java"
public class org.signal.libsignal.zkgroup.receipts.ServerZkReceiptOperations {
  private final org.signal.libsignal.zkgroup.ServerSecretParams serverSecretParams;

  public org.signal.libsignal.zkgroup.receipts.ServerZkReceiptOperations(org.signal.libsignal.zkgroup.ServerSecretParams);
    Code:
       0: aload_0
       1: invokespecial #2                  // Method java/lang/Object."<init>":()V
       4: aload_0
       5: aload_1
       6: putfield      #3                  // Field serverSecretParams:Lorg/signal/libsignal/zkgroup/ServerSecretParams;
       9: return

  public org.signal.libsignal.zkgroup.receipts.ReceiptCredentialResponse issueReceiptCredential(org.signal.libsignal.zkgroup.receipts.ReceiptCredentialRequest, long, long) throws org.signal.libsignal.zkgroup.VerificationFailedException;
    Code:
       0: aload_0
       1: new           #4                  // class java/security/SecureRandom
       4: dup
       5: invokespecial #5                  // Method java/security/SecureRandom."<init>":()V
       8: aload_1
       9: lload_2
      10: lload         4
      12: invokevirtual #6                  // Method issueReceiptCredential:(Ljava/security/SecureRandom;Lorg/signal/libsignal/zkgroup/receipts/ReceiptCredentialRequest;JJ)Lorg/signal/libsignal/zkgroup/receipts/ReceiptCredentialResponse;
      15: areturn

  public org.signal.libsignal.zkgroup.receipts.ReceiptCredentialResponse issueReceiptCredential(java.security.SecureRandom, org.signal.libsignal.zkgroup.receipts.ReceiptCredentialRequest, long, long) throws org.signal.libsignal.zkgroup.VerificationFailedException;
    Code:
       0: bipush        32
       2: newarray       byte
       4: astore        7
       6: aload_1
       7: aload         7
       9: invokevirtual #7                  // Method java/security/SecureRandom.nextBytes:([B)V
      12: aload_0
      13: getfield      #3                  // Field serverSecretParams:Lorg/signal/libsignal/zkgroup/ServerSecretParams;
      16: invokevirtual #8                  // Method org/signal/libsignal/zkgroup/ServerSecretParams.getInternalContentsForJNI:()[B
      19: aload         7
      21: aload_2
      22: invokevirtual #9                  // Method org/signal/libsignal/zkgroup/receipts/ReceiptCredentialRequest.getInternalContentsForJNI:()[B
      25: lload_3
      26: lload         5
      28: invokestatic  #10                 // Method org/signal/libsignal/internal/Native.ServerSecretParams_IssueReceiptCredentialDeterministic:([B[B[BJJ)[B
      31: astore        8
      33: new           #11                 // class org/signal/libsignal/zkgroup/receipts/ReceiptCredentialResponse
      36: dup
      37: aload         8
      39: invokespecial #12                 // Method org/signal/libsignal/zkgroup/receipts/ReceiptCredentialResponse."<init>":([B)V
      42: areturn
      43: astore        9
      45: new           #14                 // class java/lang/AssertionError
      48: dup
      49: aload         9
      51: invokespecial #15                 // Method java/lang/AssertionError."<init>":(Ljava/lang/Object;)V
      54: athrow
    Exception table:
       from    to  target type
          33    42    43   Class org/signal/libsignal/zkgroup/InvalidInputException

  public void verifyReceiptCredentialPresentation(org.signal.libsignal.zkgroup.receipts.ReceiptCredentialPresentation) throws org.signal.libsignal.zkgroup.VerificationFailedException;
    Code:
       0: aload_0
       1: getfield      #3                  // Field serverSecretParams:Lorg/signal/libsignal/zkgroup/ServerSecretParams;
       4: invokevirtual #8                  // Method org/signal/libsignal/zkgroup/ServerSecretParams.getInternalContentsForJNI:()[B
       7: aload_1
       8: invokevirtual #16                 // Method org/signal/libsignal/zkgroup/receipts/ReceiptCredentialPresentation.getInternalContentsForJNI:()[B
      11: invokestatic  #17                 // Method org/signal/libsignal/internal/Native.ServerSecretParams_VerifyReceiptCredentialPresentation:([B[B)V
      14: return
}
