Compiled from "ManagedThroughputLogger.java"
public class org.apache.camel.management.mbean.ManagedThroughputLogger extends org.apache.camel.management.mbean.ManagedProcessor implements org.apache.camel.api.management.mbean.ManagedThroughputLoggerMBean {
  private final org.apache.camel.processor.ThroughputLogger logger;

  public org.apache.camel.management.mbean.ManagedThroughputLogger(org.apache.camel.CamelContext, org.apache.camel.processor.ThroughputLogger, org.apache.camel.model.ProcessorDefinition<?>);
    Code:
       0: aload_0
       1: aload_1
       2: aload_2
       3: aload_3
       4: invokespecial #17                 // Method org/apache/camel/management/mbean/ManagedProcessor."<init>":(Lorg/apache/camel/CamelContext;Lorg/apache/camel/Processor;Lorg/apache/camel/model/ProcessorDefinition;)V
       7: aload_0
       8: aload_2
       9: putfield      #19                 // Field logger:Lorg/apache/camel/processor/ThroughputLogger;
      12: return

  public org.apache.camel.processor.ThroughputLogger getLogger();
    Code:
       0: aload_0
       1: getfield      #19                 // Field logger:Lorg/apache/camel/processor/ThroughputLogger;
       4: areturn

  public synchronized void reset();
    Code:
       0: aload_0
       1: invokespecial #32                 // Method org/apache/camel/management/mbean/ManagedProcessor.reset:()V
       4: aload_0
       5: getfield      #19                 // Field logger:Lorg/apache/camel/processor/ThroughputLogger;
       8: invokevirtual #35                 // Method org/apache/camel/processor/ThroughputLogger.reset:()V
      11: return

  public int getReceivedCounter();
    Code:
       0: aload_0
       1: getfield      #19                 // Field logger:Lorg/apache/camel/processor/ThroughputLogger;
       4: invokevirtual #39                 // Method org/apache/camel/processor/ThroughputLogger.getReceivedCounter:()I
       7: ireturn

  public double getAverage();
    Code:
       0: aload_0
       1: getfield      #19                 // Field logger:Lorg/apache/camel/processor/ThroughputLogger;
       4: invokevirtual #43                 // Method org/apache/camel/processor/ThroughputLogger.getAverage:()D
       7: dreturn

  public double getRate();
    Code:
       0: aload_0
       1: getfield      #19                 // Field logger:Lorg/apache/camel/processor/ThroughputLogger;
       4: invokevirtual #46                 // Method org/apache/camel/processor/ThroughputLogger.getRate:()D
       7: dreturn

  public java.lang.String getLastLogMessage();
    Code:
       0: aload_0
       1: getfield      #19                 // Field logger:Lorg/apache/camel/processor/ThroughputLogger;
       4: invokevirtual #50                 // Method org/apache/camel/processor/ThroughputLogger.getLastLogMessage:()Ljava/lang/String;
       7: areturn

  public void resetThroughputLogger();
    Code:
       0: aload_0
       1: getfield      #19                 // Field logger:Lorg/apache/camel/processor/ThroughputLogger;
       4: invokevirtual #35                 // Method org/apache/camel/processor/ThroughputLogger.reset:()V
       7: return
}
