Compiled from "ManagedSetExchangePattern.java"
public class org.apache.camel.management.mbean.ManagedSetExchangePattern extends org.apache.camel.management.mbean.ManagedProcessor implements org.apache.camel.api.management.mbean.ManagedSetExchangePatternMBean {
  private final org.apache.camel.processor.ExchangePatternProcessor processor;

  public org.apache.camel.management.mbean.ManagedSetExchangePattern(org.apache.camel.CamelContext, org.apache.camel.processor.ExchangePatternProcessor, org.apache.camel.model.ProcessorDefinition<?>);
    Code:
       0: aload_0
       1: aload_1
       2: aload_2
       3: aload_3
       4: invokespecial #17                 // Method org/apache/camel/management/mbean/ManagedProcessor."<init>":(Lorg/apache/camel/CamelContext;Lorg/apache/camel/Processor;Lorg/apache/camel/model/ProcessorDefinition;)V
       7: aload_0
       8: aload_2
       9: putfield      #19                 // Field processor:Lorg/apache/camel/processor/ExchangePatternProcessor;
      12: return

  public java.lang.String getPattern();
    Code:
       0: aload_0
       1: getfield      #19                 // Field processor:Lorg/apache/camel/processor/ExchangePatternProcessor;
       4: invokevirtual #34                 // Method org/apache/camel/processor/ExchangePatternProcessor.getExchangePattern:()Lorg/apache/camel/ExchangePattern;
       7: invokevirtual #39                 // Method org/apache/camel/ExchangePattern.name:()Ljava/lang/String;
      10: areturn
}
