Compiled from "Api.scala"
public abstract class ai.chronon.online.Api implements java.io.Serializable {
  private ai.chronon.online.Fetcher fetcher;

  private ai.chronon.online.Fetcher fetcherObj;

  private long timeoutMillis;

  private volatile boolean bitmap$0;

  private ai.chronon.online.Fetcher fetcher$lzycompute();
    Code:
       0: aload_0
       1: dup
       2: astore_1
       3: monitorenter
       4: aload_0
       5: getfield      #23                 // Field bitmap$0:Z
       8: ifne          46
      11: aload_0
      12: aload_0
      13: invokespecial #25                 // Method fetcherObj:()Lai/chronon/online/Fetcher;
      16: ifnonnull     34
      19: aload_0
      20: aload_0
      21: aload_0
      22: invokevirtual #29                 // Method buildFetcher$default$1:()Z
      25: invokevirtual #33                 // Method buildFetcher:(Z)Lai/chronon/online/Fetcher;
      28: invokespecial #37                 // Method fetcherObj_$eq:(Lai/chronon/online/Fetcher;)V
      31: goto          34
      34: aload_0
      35: invokespecial #25                 // Method fetcherObj:()Lai/chronon/online/Fetcher;
      38: putfield      #39                 // Field fetcher:Lai/chronon/online/Fetcher;
      41: aload_0
      42: iconst_1
      43: putfield      #23                 // Field bitmap$0:Z
      46: aload_1
      47: monitorexit
      48: goto          54
      51: aload_1
      52: monitorexit
      53: athrow
      54: aload_0
      55: getfield      #39                 // Field fetcher:Lai/chronon/online/Fetcher;
      58: areturn
    Exception table:
       from    to  target type
           4    46    51   any

  public ai.chronon.online.Fetcher fetcher();
    Code:
       0: aload_0
       1: getfield      #23                 // Field bitmap$0:Z
       4: ifne          14
       7: aload_0
       8: invokespecial #45                 // Method fetcher$lzycompute:()Lai/chronon/online/Fetcher;
      11: goto          18
      14: aload_0
      15: getfield      #39                 // Field fetcher:Lai/chronon/online/Fetcher;
      18: areturn

  private ai.chronon.online.Fetcher fetcherObj();
    Code:
       0: aload_0
       1: getfield      #49                 // Field fetcherObj:Lai/chronon/online/Fetcher;
       4: areturn

  private void fetcherObj_$eq(ai.chronon.online.Fetcher);
    Code:
       0: aload_0
       1: aload_1
       2: putfield      #49                 // Field fetcherObj:Lai/chronon/online/Fetcher;
       5: return

  public abstract ai.chronon.online.StreamDecoder streamDecoder(ai.chronon.online.GroupByServingInfoParsed);

  public abstract ai.chronon.online.KVStore genKvStore();

  public abstract ai.chronon.online.ExternalSourceRegistry externalRegistry();

  private long timeoutMillis();
    Code:
       0: aload_0
       1: getfield      #60                 // Field timeoutMillis:J
       4: lreturn

  private void timeoutMillis_$eq(long);
    Code:
       0: aload_0
       1: lload_1
       2: putfield      #60                 // Field timeoutMillis:J
       5: return

  public void setTimeout(long);
    Code:
       0: aload_0
       1: lload_1
       2: invokespecial #66                 // Method timeoutMillis_$eq:(J)V
       5: return

  public abstract void logResponse(ai.chronon.online.LoggableResponse);

  public final ai.chronon.online.Fetcher buildFetcher(boolean);
    Code:
       0: aload_0
       1: invokevirtual #72                 // Method genKvStore:()Lai/chronon/online/KVStore;
       4: astore_2
       5: getstatic     #78                 // Field ai/chronon/api/Constants$.MODULE$:Lai/chronon/api/Constants$;
       8: invokevirtual #82                 // Method ai/chronon/api/Constants$.ChrononMetadataKey:()Ljava/lang/String;
      11: astore_3
      12: aload_0
      13: invokespecial #86                 // Method responseConsumer:()Ljava/util/function/Consumer;
      16: astore        4
      18: iload_1
      19: istore        5
      21: aload_0
      22: invokevirtual #88                 // Method externalRegistry:()Lai/chronon/online/ExternalSourceRegistry;
      25: astore        6
      27: aload_0
      28: invokespecial #90                 // Method timeoutMillis:()J
      31: lstore        7
      33: new           #47                 // class ai/chronon/online/Fetcher
      36: dup
      37: aload_2
      38: aload_3
      39: lload         7
      41: aload         4
      43: iload         5
      45: aload         6
      47: invokespecial #94                 // Method ai/chronon/online/Fetcher."<init>":(Lai/chronon/online/KVStore;Ljava/lang/String;JLjava/util/function/Consumer;ZLai/chronon/online/ExternalSourceRegistry;)V
      50: areturn

  public final boolean buildFetcher$default$1();
    Code:
       0: iconst_0
       1: ireturn

  public final ai.chronon.online.JavaFetcher buildJavaFetcher();
    Code:
       0: new           #107                // class ai/chronon/online/JavaFetcher
       3: dup
       4: aload_0
       5: invokevirtual #72                 // Method genKvStore:()Lai/chronon/online/KVStore;
       8: getstatic     #78                 // Field ai/chronon/api/Constants$.MODULE$:Lai/chronon/api/Constants$;
      11: invokevirtual #82                 // Method ai/chronon/api/Constants$.ChrononMetadataKey:()Ljava/lang/String;
      14: getstatic     #112                // Field scala/Predef$.MODULE$:Lscala/Predef$;
      17: aload_0
      18: invokespecial #90                 // Method timeoutMillis:()J
      21: invokevirtual #116                // Method scala/Predef$.long2Long:(J)Ljava/lang/Long;
      24: aload_0
      25: invokespecial #86                 // Method responseConsumer:()Ljava/util/function/Consumer;
      28: aload_0
      29: invokevirtual #88                 // Method externalRegistry:()Lai/chronon/online/ExternalSourceRegistry;
      32: invokespecial #119                // Method ai/chronon/online/JavaFetcher."<init>":(Lai/chronon/online/KVStore;Ljava/lang/String;Ljava/lang/Long;Ljava/util/function/Consumer;Lai/chronon/online/ExternalSourceRegistry;)V
      35: areturn

  private java.util.function.Consumer<ai.chronon.online.LoggableResponse> responseConsumer();
    Code:
       0: new           #12                 // class ai/chronon/online/Api$$anon$1
       3: dup
       4: aload_0
       5: invokespecial #123                // Method ai/chronon/online/Api$$anon$1."<init>":(Lai/chronon/online/Api;)V
       8: areturn

  public ai.chronon.online.Api(scala.collection.immutable.Map<java.lang.String, java.lang.String>);
    Code:
       0: aload_0
       1: invokespecial #129                // Method java/lang/Object."<init>":()V
       4: aload_0
       5: aconst_null
       6: putfield      #49                 // Field fetcherObj:Lai/chronon/online/Fetcher;
       9: aload_0
      10: ldc2_w        #130                // long 10000l
      13: putfield      #60                 // Field timeoutMillis:J
      16: return
}
