Compiled from "AvroCodec.scala"
public final class ai.chronon.online.ArrayRow$ {
  public static final ai.chronon.online.ArrayRow$ MODULE$;

  public static {};
    Code:
       0: new           #2                  // class ai/chronon/online/ArrayRow$
       3: dup
       4: invokespecial #12                 // Method "<init>":()V
       7: putstatic     #14                 // Field MODULE$:Lai/chronon/online/ArrayRow$;
      10: return

  public boolean $lessinit$greater$default$3();
    Code:
       0: iconst_0
       1: ireturn

  private ai.chronon.online.ArrayRow$();
    Code:
       0: aload_0
       1: invokespecial #18                 // Method java/lang/Object."<init>":()V
       4: return
}
