Compiled from "BaseFetcher.scala"
public final class ai.chronon.online.BaseFetcher$$anonfun$$nestedInanonfun$fetchJoin$13$1 extends scala.runtime.AbstractPartialFunction<java.lang.Throwable, scala.collection.immutable.Map<java.lang.String, java.lang.String>> implements java.io.Serializable {
  private static final long serialVersionUID;

  private final ai.chronon.online.BaseFetcher $outer;

  private final ai.chronon.online.Fetcher$Request groupByRequest$1;

  public final <A1 extends java.lang.Throwable, B1> B1 applyOrElse(A1, scala.Function1<A1, B1>);
    Code:
       0: aload_1
       1: astore        4
       3: aload         4
       5: ifnull        163
       8: aload         4
      10: astore        5
      12: aload_0
      13: getfield      #43                 // Field $outer:Lai/chronon/online/BaseFetcher;
      16: getfield      #47                 // Field ai/chronon/online/BaseFetcher.ai$chronon$online$BaseFetcher$$debug:Z
      19: ifne          32
      22: invokestatic  #53                 // Method java/lang/Math.random:()D
      25: ldc2_w        #54                 // double 0.001d
      28: dcmpg
      29: ifge          84
      32: getstatic     #61                 // Field scala/Predef$.MODULE$:Lscala/Predef$;
      35: new           #63                 // class java/lang/StringBuilder
      38: dup
      39: ldc           #64                 // int 23
      41: invokespecial #68                 // Method java/lang/StringBuilder."<init>":(I)V
      44: ldc           #70                 // String Failed to fetch
      46: invokevirtual #74                 // Method java/lang/StringBuilder.append:(Ljava/lang/String;)Ljava/lang/StringBuilder;
      49: aload_0
      50: getfield      #76                 // Field groupByRequest$1:Lai/chronon/online/Fetcher$Request;
      53: invokevirtual #79                 // Method java/lang/StringBuilder.append:(Ljava/lang/Object;)Ljava/lang/StringBuilder;
      56: ldc           #81                 // String  with \n
      58: invokevirtual #74                 // Method java/lang/StringBuilder.append:(Ljava/lang/String;)Ljava/lang/StringBuilder;
      61: getstatic     #86                 // Field ai/chronon/api/Extensions$.MODULE$:Lai/chronon/api/Extensions$;
      64: aload         5
      66: invokevirtual #89                 // Method ai/chronon/api/Extensions$.ThrowableOps:(Ljava/lang/Throwable;)Lai/chronon/api/Extensions$ThrowableOps;
      69: invokevirtual #93                 // Method ai/chronon/api/Extensions$ThrowableOps.traceString:()Ljava/lang/String;
      72: invokevirtual #74                 // Method java/lang/StringBuilder.append:(Ljava/lang/String;)Ljava/lang/StringBuilder;
      75: invokevirtual #96                 // Method java/lang/StringBuilder.toString:()Ljava/lang/String;
      78: invokevirtual #100                // Method scala/Predef$.println:(Ljava/lang/Object;)V
      81: goto          84
      84: getstatic     #61                 // Field scala/Predef$.MODULE$:Lscala/Predef$;
      87: invokevirtual #104                // Method scala/Predef$.Map:()Lscala/collection/immutable/Map$;
      90: getstatic     #109                // Field scala/runtime/ScalaRunTime$.MODULE$:Lscala/runtime/ScalaRunTime$;
      93: iconst_1
      94: anewarray     #111                // class scala/Tuple2
      97: dup
      98: iconst_0
      99: getstatic     #114                // Field scala/Predef$ArrowAssoc$.MODULE$:Lscala/Predef$ArrowAssoc$;
     102: getstatic     #61                 // Field scala/Predef$.MODULE$:Lscala/Predef$;
     105: new           #63                 // class java/lang/StringBuilder
     108: dup
     109: ldc           #115                // int 10
     111: invokespecial #68                 // Method java/lang/StringBuilder."<init>":(I)V
     114: aload_0
     115: getfield      #76                 // Field groupByRequest$1:Lai/chronon/online/Fetcher$Request;
     118: invokevirtual #118                // Method ai/chronon/online/Fetcher$Request.name:()Ljava/lang/String;
     121: invokevirtual #74                 // Method java/lang/StringBuilder.append:(Ljava/lang/String;)Ljava/lang/StringBuilder;
     124: ldc           #120                // String _exception
     126: invokevirtual #74                 // Method java/lang/StringBuilder.append:(Ljava/lang/String;)Ljava/lang/StringBuilder;
     129: invokevirtual #96                 // Method java/lang/StringBuilder.toString:()Ljava/lang/String;
     132: invokevirtual #124                // Method scala/Predef$.ArrowAssoc:(Ljava/lang/Object;)Ljava/lang/Object;
     135: getstatic     #86                 // Field ai/chronon/api/Extensions$.MODULE$:Lai/chronon/api/Extensions$;
     138: aload         5
     140: invokevirtual #89                 // Method ai/chronon/api/Extensions$.ThrowableOps:(Ljava/lang/Throwable;)Lai/chronon/api/Extensions$ThrowableOps;
     143: invokevirtual #93                 // Method ai/chronon/api/Extensions$ThrowableOps.traceString:()Ljava/lang/String;
     146: invokevirtual #128                // Method scala/Predef$ArrowAssoc$.$minus$greater$extension:(Ljava/lang/Object;Ljava/lang/Object;)Lscala/Tuple2;
     149: aastore
     150: checkcast     #130                // class "[Ljava/lang/Object;"
     153: invokevirtual #134                // Method scala/runtime/ScalaRunTime$.wrapRefArray:([Ljava/lang/Object;)Lscala/collection/immutable/ArraySeq;
     156: invokevirtual #140                // Method scala/collection/immutable/Map$.apply:(Lscala/collection/immutable/Seq;)Ljava/lang/Object;
     159: astore_3
     160: goto          177
     163: goto          166
     166: aload_2
     167: aload_1
     168: invokeinterface #144,  2          // InterfaceMethod scala/Function1.apply:(Ljava/lang/Object;)Ljava/lang/Object;
     173: astore_3
     174: goto          177
     177: aload_3
     178: areturn

  public final boolean isDefinedAt(java.lang.Throwable);
    Code:
       0: aload_1
       1: astore_3
       2: aload_3
       3: ifnull        11
       6: iconst_1
       7: istore_2
       8: goto          19
      11: goto          14
      14: iconst_0
      15: istore_2
      16: goto          19
      19: iload_2
      20: ireturn

  public final boolean isDefinedAt(java.lang.Object);
    Code:
       0: aload_0
       1: aload_1
       2: checkcast     #150                // class java/lang/Throwable
       5: invokevirtual #158                // Method isDefinedAt:(Ljava/lang/Throwable;)Z
       8: ireturn

  public final java.lang.Object applyOrElse(java.lang.Object, scala.Function1);
    Code:
       0: aload_0
       1: aload_1
       2: checkcast     #150                // class java/lang/Throwable
       5: aload_2
       6: invokevirtual #162                // Method applyOrElse:(Ljava/lang/Throwable;Lscala/Function1;)Ljava/lang/Object;
       9: areturn

  public ai.chronon.online.BaseFetcher$$anonfun$$nestedInanonfun$fetchJoin$13$1(ai.chronon.online.BaseFetcher, ai.chronon.online.Fetcher$Request);
    Code:
       0: aload_1
       1: ifnonnull     6
       4: aconst_null
       5: athrow
       6: aload_0
       7: aload_1
       8: putfield      #43                 // Field $outer:Lai/chronon/online/BaseFetcher;
      11: aload_0
      12: aload_2
      13: putfield      #76                 // Field groupByRequest$1:Lai/chronon/online/Fetcher$Request;
      16: aload_0
      17: invokespecial #166                // Method scala/runtime/AbstractPartialFunction."<init>":()V
      20: return
}
