Compiled from "CatalystUtil.scala"
public class ai.chronon.online.CatalystUtil {
  private transient org.apache.spark.sql.types.StructType inputSparkSchema;

  private final ai.chronon.api.StructType inputSchema;

  private final java.lang.String selectClauses;

  private final java.lang.String sessionTable;

  private final java.lang.String query;

  private final ai.chronon.online.CatalystUtil$IteratorWrapper<org.apache.spark.sql.catalyst.InternalRow> iteratorWrapper;

  private final scala.Tuple2 x$1;

  private final org.apache.spark.sql.execution.BufferedRowIterator sparkSQLTransformerBuffer;

  private final org.apache.spark.sql.types.StructType outputSparkSchema;

  private final scala.Function1<java.lang.Object, java.lang.Object> outputDecoder;

  private final scala.Function1<java.lang.Object, java.lang.Object> inputEncoder;

  private volatile transient boolean bitmap$trans$0;

  public static org.apache.spark.sql.SparkSession session();
    Code:
       0: getstatic     #56                 // Field ai/chronon/online/CatalystUtil$.MODULE$:Lai/chronon/online/CatalystUtil$;
       3: invokevirtual #58                 // Method ai/chronon/online/CatalystUtil$.session:()Lorg/apache/spark/sql/SparkSession;
       6: areturn

  public static java.lang.String inputTable();
    Code:
       0: getstatic     #56                 // Field ai/chronon/online/CatalystUtil$.MODULE$:Lai/chronon/online/CatalystUtil$;
       3: invokevirtual #62                 // Method ai/chronon/online/CatalystUtil$.inputTable:()Ljava/lang/String;
       6: areturn

  private java.lang.String selectClauses();
    Code:
       0: aload_0
       1: getfield      #64                 // Field selectClauses:Ljava/lang/String;
       4: areturn

  private java.lang.String sessionTable();
    Code:
       0: aload_0
       1: getfield      #68                 // Field sessionTable:Ljava/lang/String;
       4: areturn

  private java.lang.String query();
    Code:
       0: aload_0
       1: getfield      #70                 // Field query:Ljava/lang/String;
       4: areturn

  private ai.chronon.online.CatalystUtil$IteratorWrapper<org.apache.spark.sql.catalyst.InternalRow> iteratorWrapper();
    Code:
       0: aload_0
       1: getfield      #74                 // Field iteratorWrapper:Lai/chronon/online/CatalystUtil$IteratorWrapper;
       4: areturn

  private org.apache.spark.sql.execution.BufferedRowIterator sparkSQLTransformerBuffer();
    Code:
       0: aload_0
       1: getfield      #77                 // Field sparkSQLTransformerBuffer:Lorg/apache/spark/sql/execution/BufferedRowIterator;
       4: areturn

  private org.apache.spark.sql.types.StructType outputSparkSchema();
    Code:
       0: aload_0
       1: getfield      #80                 // Field outputSparkSchema:Lorg/apache/spark/sql/types/StructType;
       4: areturn

  private scala.Function1<java.lang.Object, java.lang.Object> outputDecoder();
    Code:
       0: aload_0
       1: getfield      #84                 // Field outputDecoder:Lscala/Function1;
       4: areturn

  private org.apache.spark.sql.types.StructType inputSparkSchema$lzycompute();
    Code:
       0: aload_0
       1: dup
       2: astore_1
       3: monitorenter
       4: aload_0
       5: getfield      #87                 // Field bitmap$trans$0:Z
       8: ifne          30
      11: aload_0
      12: getstatic     #92                 // Field ai/chronon/online/SparkConversions$.MODULE$:Lai/chronon/online/SparkConversions$;
      15: aload_0
      16: getfield      #94                 // Field inputSchema:Lai/chronon/api/StructType;
      19: invokevirtual #98                 // Method ai/chronon/online/SparkConversions$.fromChrononSchema:(Lai/chronon/api/StructType;)Lorg/apache/spark/sql/types/StructType;
      22: putfield      #100                // Field inputSparkSchema:Lorg/apache/spark/sql/types/StructType;
      25: aload_0
      26: iconst_1
      27: putfield      #87                 // Field bitmap$trans$0:Z
      30: aload_1
      31: monitorexit
      32: goto          38
      35: aload_1
      36: monitorexit
      37: athrow
      38: aload_0
      39: getfield      #100                // Field inputSparkSchema:Lorg/apache/spark/sql/types/StructType;
      42: areturn
    Exception table:
       from    to  target type
           4    30    35   any

  public org.apache.spark.sql.types.StructType inputSparkSchema();
    Code:
       0: aload_0
       1: getfield      #87                 // Field bitmap$trans$0:Z
       4: ifne          14
       7: aload_0
       8: invokespecial #104                // Method inputSparkSchema$lzycompute:()Lorg/apache/spark/sql/types/StructType;
      11: goto          18
      14: aload_0
      15: getfield      #100                // Field inputSparkSchema:Lorg/apache/spark/sql/types/StructType;
      18: areturn

  private scala.Function1<java.lang.Object, java.lang.Object> inputEncoder();
    Code:
       0: aload_0
       1: getfield      #108                // Field inputEncoder:Lscala/Function1;
       4: areturn

  public scala.collection.immutable.Map<java.lang.String, java.lang.Object> performSql(scala.collection.immutable.Map<java.lang.String, java.lang.Object>);
    Code:
       0: aload_0
       1: invokespecial #114                // Method inputEncoder:()Lscala/Function1;
       4: aload_1
       5: invokeinterface #120,  2          // InterfaceMethod scala/Function1.apply:(Ljava/lang/Object;)Ljava/lang/Object;
      10: checkcast     #122                // class org/apache/spark/sql/catalyst/InternalRow
      13: astore_2
      14: aload_0
      15: invokespecial #124                // Method iteratorWrapper:()Lai/chronon/online/CatalystUtil$IteratorWrapper;
      18: aload_2
      19: invokevirtual #128                // Method ai/chronon/online/CatalystUtil$IteratorWrapper.put:(Ljava/lang/Object;)V
      22: aload_0
      23: invokespecial #130                // Method sparkSQLTransformerBuffer:()Lorg/apache/spark/sql/execution/BufferedRowIterator;
      26: invokevirtual #136                // Method org/apache/spark/sql/execution/BufferedRowIterator.hasNext:()Z
      29: ifeq          81
      32: aload_0
      33: invokespecial #130                // Method sparkSQLTransformerBuffer:()Lorg/apache/spark/sql/execution/BufferedRowIterator;
      36: invokevirtual #140                // Method org/apache/spark/sql/execution/BufferedRowIterator.next:()Lorg/apache/spark/sql/catalyst/InternalRow;
      39: astore_3
      40: aload_0
      41: invokespecial #142                // Method outputDecoder:()Lscala/Function1;
      44: aload_3
      45: invokeinterface #120,  2          // InterfaceMethod scala/Function1.apply:(Ljava/lang/Object;)Ljava/lang/Object;
      50: astore        4
      52: getstatic     #147                // Field scala/Option$.MODULE$:Lscala/Option$;
      55: aload         4
      57: invokevirtual #150                // Method scala/Option$.apply:(Ljava/lang/Object;)Lscala/Option;
      60: invokedynamic #168,  0            // InvokeDynamic #0:apply:()Lscala/Function1;
      65: invokevirtual #174                // Method scala/Option.map:(Lscala/Function1;)Lscala/Option;
      68: getstatic     #179                // Field scala/$less$colon$less$.MODULE$:Lscala/$less$colon$less$;
      71: invokevirtual #183                // Method scala/$less$colon$less$.refl:()Lscala/$eq$colon$eq;
      74: invokevirtual #187                // Method scala/Option.orNull:(Lscala/$less$colon$less;)Ljava/lang/Object;
      77: checkcast     #189                // class scala/collection/immutable/Map
      80: areturn
      81: aconst_null
      82: areturn

  private scala.Tuple2<org.apache.spark.sql.execution.BufferedRowIterator, org.apache.spark.sql.types.StructType> initializeIterator(ai.chronon.online.CatalystUtil$IteratorWrapper<org.apache.spark.sql.catalyst.InternalRow>);
    Code:
       0: getstatic     #56                 // Field ai/chronon/online/CatalystUtil$.MODULE$:Lai/chronon/online/CatalystUtil$;
       3: invokevirtual #58                 // Method ai/chronon/online/CatalystUtil$.session:()Lorg/apache/spark/sql/SparkSession;
       6: astore        4
       8: aload         4
      10: invokevirtual #204                // Method org/apache/spark/sql/SparkSession.emptyDataFrame:()Lorg/apache/spark/sql/Dataset;
      13: invokevirtual #210                // Method org/apache/spark/sql/Dataset.rdd:()Lorg/apache/spark/rdd/RDD;
      16: astore        5
      18: getstatic     #92                 // Field ai/chronon/online/SparkConversions$.MODULE$:Lai/chronon/online/SparkConversions$;
      21: aload_0
      22: getfield      #94                 // Field inputSchema:Lai/chronon/api/StructType;
      25: invokevirtual #98                 // Method ai/chronon/online/SparkConversions$.fromChrononSchema:(Lai/chronon/api/StructType;)Lorg/apache/spark/sql/types/StructType;
      28: astore        6
      30: aload         4
      32: aload         5
      34: aload         6
      36: invokevirtual #214                // Method org/apache/spark/sql/SparkSession.createDataFrame:(Lorg/apache/spark/rdd/RDD;Lorg/apache/spark/sql/types/StructType;)Lorg/apache/spark/sql/Dataset;
      39: astore        7
      41: aload         7
      43: aload_0
      44: invokespecial #216                // Method sessionTable:()Ljava/lang/String;
      47: invokevirtual #220                // Method org/apache/spark/sql/Dataset.createOrReplaceTempView:(Ljava/lang/String;)V
      50: aload         4
      52: aload_0
      53: invokespecial #222                // Method query:()Ljava/lang/String;
      56: invokevirtual #226                // Method org/apache/spark/sql/SparkSession.sql:(Ljava/lang/String;)Lorg/apache/spark/sql/Dataset;
      59: invokevirtual #229                // Method org/apache/spark/sql/Dataset.schema:()Lorg/apache/spark/sql/types/StructType;
      62: astore        8
      64: aload         4
      66: invokevirtual #233                // Method org/apache/spark/sql/SparkSession.sessionState:()Lorg/apache/spark/sql/internal/SessionState;
      69: invokevirtual #239                // Method org/apache/spark/sql/internal/SessionState.sqlParser:()Lorg/apache/spark/sql/catalyst/parser/ParserInterface;
      72: aload_0
      73: invokespecial #222                // Method query:()Ljava/lang/String;
      76: invokeinterface #245,  2          // InterfaceMethod org/apache/spark/sql/catalyst/parser/ParserInterface.parsePlan:(Ljava/lang/String;)Lorg/apache/spark/sql/catalyst/plans/logical/LogicalPlan;
      81: astore        9
      83: aload         4
      85: invokevirtual #233                // Method org/apache/spark/sql/SparkSession.sessionState:()Lorg/apache/spark/sql/internal/SessionState;
      88: aload         9
      90: aload         4
      92: invokevirtual #233                // Method org/apache/spark/sql/SparkSession.sessionState:()Lorg/apache/spark/sql/internal/SessionState;
      95: invokevirtual #249                // Method org/apache/spark/sql/internal/SessionState.executePlan$default$2:()Lscala/Enumeration$Value;
      98: invokevirtual #253                // Method org/apache/spark/sql/internal/SessionState.executePlan:(Lorg/apache/spark/sql/catalyst/plans/logical/LogicalPlan;Lscala/Enumeration$Value;)Lorg/apache/spark/sql/execution/QueryExecution;
     101: astore        10
     103: aload         10
     105: invokevirtual #259                // Method org/apache/spark/sql/execution/QueryExecution.executedPlan:()Lorg/apache/spark/sql/execution/SparkPlan;
     108: astore        11
     110: aload         11
     112: checkcast     #261                // class org/apache/spark/sql/execution/WholeStageCodegenExec
     115: astore        12
     117: aload         12
     119: invokevirtual #265                // Method org/apache/spark/sql/execution/WholeStageCodegenExec.doCodeGen:()Lscala/Tuple2;
     122: astore        14
     124: aload         14
     126: ifnull        164
     129: aload         14
     131: invokevirtual #271                // Method scala/Tuple2._1:()Ljava/lang/Object;
     134: checkcast     #273                // class org/apache/spark/sql/catalyst/expressions/codegen/CodegenContext
     137: astore        15
     139: aload         14
     141: invokevirtual #276                // Method scala/Tuple2._2:()Ljava/lang/Object;
     144: checkcast     #278                // class org/apache/spark/sql/catalyst/expressions/codegen/CodeAndComment
     147: astore        16
     149: new           #267                // class scala/Tuple2
     152: dup
     153: aload         15
     155: aload         16
     157: invokespecial #282                // Method scala/Tuple2."<init>":(Ljava/lang/Object;Ljava/lang/Object;)V
     160: astore_3
     161: goto          177
     164: goto          167
     167: new           #284                // class scala/MatchError
     170: dup
     171: aload         14
     173: invokespecial #286                // Method scala/MatchError."<init>":(Ljava/lang/Object;)V
     176: athrow
     177: aload_3
     178: astore        13
     180: aload         13
     182: invokevirtual #271                // Method scala/Tuple2._1:()Ljava/lang/Object;
     185: checkcast     #273                // class org/apache/spark/sql/catalyst/expressions/codegen/CodegenContext
     188: astore        17
     190: aload         13
     192: invokevirtual #276                // Method scala/Tuple2._2:()Ljava/lang/Object;
     195: checkcast     #278                // class org/apache/spark/sql/catalyst/expressions/codegen/CodeAndComment
     198: astore        18
     200: getstatic     #291                // Field org/apache/spark/sql/catalyst/expressions/codegen/CodeGenerator$.MODULE$:Lorg/apache/spark/sql/catalyst/expressions/codegen/CodeGenerator$;
     203: aload         18
     205: invokevirtual #295                // Method org/apache/spark/sql/catalyst/expressions/codegen/CodeGenerator$.compile:(Lorg/apache/spark/sql/catalyst/expressions/codegen/CodeAndComment;)Lscala/Tuple2;
     208: astore        20
     210: aload         20
     212: ifnull        231
     215: aload         20
     217: invokevirtual #271                // Method scala/Tuple2._1:()Ljava/lang/Object;
     220: checkcast     #297                // class org/apache/spark/sql/catalyst/expressions/codegen/GeneratedClass
     223: astore        21
     225: aload         21
     227: astore_2
     228: goto          244
     231: goto          234
     234: new           #284                // class scala/MatchError
     237: dup
     238: aload         20
     240: invokespecial #286                // Method scala/MatchError."<init>":(Ljava/lang/Object;)V
     243: athrow
     244: aload_2
     245: astore        19
     247: aload         17
     249: invokevirtual #301                // Method org/apache/spark/sql/catalyst/expressions/codegen/CodegenContext.references:()Lscala/collection/mutable/ArrayBuffer;
     252: getstatic     #306                // Field scala/reflect/ClassTag$.MODULE$:Lscala/reflect/ClassTag$;
     255: invokevirtual #310                // Method scala/reflect/ClassTag$.Any:()Lscala/reflect/ClassTag;
     258: invokevirtual #316                // Method scala/collection/mutable/ArrayBuffer.toArray:(Lscala/reflect/ClassTag;)Ljava/lang/Object;
     261: checkcast     #318                // class "[Ljava/lang/Object;"
     264: astore        22
     266: aload         19
     268: aload         22
     270: invokevirtual #322                // Method org/apache/spark/sql/catalyst/expressions/codegen/GeneratedClass.generate:([Ljava/lang/Object;)Ljava/lang/Object;
     273: checkcast     #132                // class org/apache/spark/sql/execution/BufferedRowIterator
     276: astore        23
     278: aload         23
     280: iconst_0
     281: iconst_1
     282: anewarray     #324                // class scala/collection/Iterator
     285: dup
     286: iconst_0
     287: aload_1
     288: aastore
     289: checkcast     #318                // class "[Ljava/lang/Object;"
     292: checkcast     #326                // class "[Lscala/collection/Iterator;"
     295: invokevirtual #330                // Method org/apache/spark/sql/execution/BufferedRowIterator.init:(I[Lscala/collection/Iterator;)V
     298: new           #267                // class scala/Tuple2
     301: dup
     302: aload         23
     304: aload         8
     306: invokespecial #282                // Method scala/Tuple2."<init>":(Ljava/lang/Object;Ljava/lang/Object;)V
     309: areturn

  public static final java.lang.String $anonfun$selectClauses$1(scala.Tuple2);
    Code:
       0: aload_0
       1: astore_2
       2: aload_2
       3: ifnull        55
       6: aload_2
       7: invokevirtual #271                // Method scala/Tuple2._1:()Ljava/lang/Object;
      10: checkcast     #361                // class java/lang/String
      13: astore_3
      14: aload_2
      15: invokevirtual #276                // Method scala/Tuple2._2:()Ljava/lang/Object;
      18: checkcast     #361                // class java/lang/String
      21: astore        4
      23: new           #363                // class java/lang/StringBuilder
      26: dup
      27: ldc_w         #364                // int 4
      30: invokespecial #367                // Method java/lang/StringBuilder."<init>":(I)V
      33: aload         4
      35: invokevirtual #371                // Method java/lang/StringBuilder.append:(Ljava/lang/String;)Ljava/lang/StringBuilder;
      38: ldc_w         #373                // String  as
      41: invokevirtual #371                // Method java/lang/StringBuilder.append:(Ljava/lang/String;)Ljava/lang/StringBuilder;
      44: aload_3
      45: invokevirtual #371                // Method java/lang/StringBuilder.append:(Ljava/lang/String;)Ljava/lang/StringBuilder;
      48: invokevirtual #376                // Method java/lang/StringBuilder.toString:()Ljava/lang/String;
      51: astore_1
      52: goto          67
      55: goto          58
      58: new           #284                // class scala/MatchError
      61: dup
      62: aload_2
      63: invokespecial #286                // Method scala/MatchError."<init>":(Ljava/lang/Object;)V
      66: athrow
      67: aload_1
      68: areturn

  public static final scala.collection.immutable.Map $anonfun$performSql$1(java.lang.Object);
    Code:
       0: aload_0
       1: checkcast     #189                // class scala/collection/immutable/Map
       4: areturn

  public ai.chronon.online.CatalystUtil(scala.collection.immutable.Map<java.lang.String, java.lang.String>, ai.chronon.api.StructType);
    Code:
       0: aload_0
       1: aload_2
       2: putfield      #94                 // Field inputSchema:Lai/chronon/api/StructType;
       5: aload_0
       6: invokespecial #385                // Method java/lang/Object."<init>":()V
       9: aload_0
      10: aload_1
      11: invokedynamic #390,  0            // InvokeDynamic #1:apply:()Lscala/Function1;
      16: invokeinterface #393,  2          // InterfaceMethod scala/collection/immutable/Map.map:(Lscala/Function1;)Ljava/lang/Object;
      21: checkcast     #395                // class scala/collection/IterableOnceOps
      24: ldc_w         #397                // String ,
      27: invokeinterface #401,  2          // InterfaceMethod scala/collection/IterableOnceOps.mkString:(Ljava/lang/String;)Ljava/lang/String;
      32: putfield      #64                 // Field selectClauses:Ljava/lang/String;
      35: aload_0
      36: new           #363                // class java/lang/StringBuilder
      39: dup
      40: ldc_w         #402                // int 3
      43: invokespecial #367                // Method java/lang/StringBuilder."<init>":(I)V
      46: ldc_w         #404                // String q
      49: invokevirtual #371                // Method java/lang/StringBuilder.append:(Ljava/lang/String;)Ljava/lang/StringBuilder;
      52: getstatic     #409                // Field scala/math/package$.MODULE$:Lscala/math/package$;
      55: aload_0
      56: invokespecial #411                // Method selectClauses:()Ljava/lang/String;
      59: invokevirtual #415                // Method java/lang/String.hashCode:()I
      62: invokevirtual #419                // Method scala/math/package$.abs:(I)I
      65: invokevirtual #422                // Method java/lang/StringBuilder.append:(I)Ljava/lang/StringBuilder;
      68: ldc_w         #424                // String _f
      71: invokevirtual #371                // Method java/lang/StringBuilder.append:(Ljava/lang/String;)Ljava/lang/StringBuilder;
      74: getstatic     #409                // Field scala/math/package$.MODULE$:Lscala/math/package$;
      77: getstatic     #429                // Field ai/chronon/online/Extensions$.MODULE$:Lai/chronon/online/Extensions$;
      80: aload_0
      81: invokevirtual #431                // Method inputSparkSchema:()Lorg/apache/spark/sql/types/StructType;
      84: invokevirtual #434                // Method ai/chronon/online/Extensions$.StructTypeOps:(Lorg/apache/spark/sql/types/StructType;)Lai/chronon/online/Extensions$StructTypeOps;
      87: invokevirtual #437                // Method ai/chronon/online/Extensions$StructTypeOps.pretty:()Ljava/lang/String;
      90: invokevirtual #415                // Method java/lang/String.hashCode:()I
      93: invokevirtual #419                // Method scala/math/package$.abs:(I)I
      96: invokevirtual #422                // Method java/lang/StringBuilder.append:(I)Ljava/lang/StringBuilder;
      99: invokevirtual #376                // Method java/lang/StringBuilder.toString:()Ljava/lang/String;
     102: putfield      #68                 // Field sessionTable:Ljava/lang/String;
     105: aload_0
     106: new           #363                // class java/lang/StringBuilder
     109: dup
     110: ldc_w         #438                // int 13
     113: invokespecial #367                // Method java/lang/StringBuilder."<init>":(I)V
     116: ldc_w         #440                // String SELECT
     119: invokevirtual #371                // Method java/lang/StringBuilder.append:(Ljava/lang/String;)Ljava/lang/StringBuilder;
     122: aload_0
     123: invokespecial #411                // Method selectClauses:()Ljava/lang/String;
     126: invokevirtual #371                // Method java/lang/StringBuilder.append:(Ljava/lang/String;)Ljava/lang/StringBuilder;
     129: ldc_w         #442                // String  FROM
     132: invokevirtual #371                // Method java/lang/StringBuilder.append:(Ljava/lang/String;)Ljava/lang/StringBuilder;
     135: aload_0
     136: invokespecial #216                // Method sessionTable:()Ljava/lang/String;
     139: invokevirtual #371                // Method java/lang/StringBuilder.append:(Ljava/lang/String;)Ljava/lang/StringBuilder;
     142: invokevirtual #376                // Method java/lang/StringBuilder.toString:()Ljava/lang/String;
     145: putfield      #70                 // Field query:Ljava/lang/String;
     148: aload_0
     149: new           #10                 // class ai/chronon/online/CatalystUtil$IteratorWrapper
     152: dup
     153: invokespecial #443                // Method ai/chronon/online/CatalystUtil$IteratorWrapper."<init>":()V
     156: putfield      #74                 // Field iteratorWrapper:Lai/chronon/online/CatalystUtil$IteratorWrapper;
     159: aload_0
     160: aload_0
     161: aload_0
     162: invokespecial #124                // Method iteratorWrapper:()Lai/chronon/online/CatalystUtil$IteratorWrapper;
     165: invokespecial #445                // Method initializeIterator:(Lai/chronon/online/CatalystUtil$IteratorWrapper;)Lscala/Tuple2;
     168: astore        4
     170: aload         4
     172: ifnull        234
     175: aload         4
     177: invokevirtual #271                // Method scala/Tuple2._1:()Ljava/lang/Object;
     180: checkcast     #132                // class org/apache/spark/sql/execution/BufferedRowIterator
     183: astore        5
     185: aload         4
     187: invokevirtual #276                // Method scala/Tuple2._2:()Ljava/lang/Object;
     190: checkcast     #106                // class org/apache/spark/sql/types/StructType
     193: astore        6
     195: aload         5
     197: ifnull        231
     200: aload         5
     202: astore        7
     204: aload         6
     206: ifnull        228
     209: aload         6
     211: astore        8
     213: new           #267                // class scala/Tuple2
     216: dup
     217: aload         7
     219: aload         8
     221: invokespecial #282                // Method scala/Tuple2."<init>":(Ljava/lang/Object;Ljava/lang/Object;)V
     224: astore_3
     225: goto          247
     228: goto          237
     231: goto          237
     234: goto          237
     237: new           #284                // class scala/MatchError
     240: dup
     241: aload         4
     243: invokespecial #286                // Method scala/MatchError."<init>":(Ljava/lang/Object;)V
     246: athrow
     247: aload_3
     248: putfield      #447                // Field x$1:Lscala/Tuple2;
     251: aload_0
     252: aload_0
     253: getfield      #447                // Field x$1:Lscala/Tuple2;
     256: invokevirtual #271                // Method scala/Tuple2._1:()Ljava/lang/Object;
     259: checkcast     #132                // class org/apache/spark/sql/execution/BufferedRowIterator
     262: putfield      #77                 // Field sparkSQLTransformerBuffer:Lorg/apache/spark/sql/execution/BufferedRowIterator;
     265: aload_0
     266: aload_0
     267: getfield      #447                // Field x$1:Lscala/Tuple2;
     270: invokevirtual #276                // Method scala/Tuple2._2:()Ljava/lang/Object;
     273: checkcast     #106                // class org/apache/spark/sql/types/StructType
     276: putfield      #80                 // Field outputSparkSchema:Lorg/apache/spark/sql/types/StructType;
     279: aload_0
     280: getstatic     #452                // Field ai/chronon/online/SparkInternalRowConversions$.MODULE$:Lai/chronon/online/SparkInternalRowConversions$;
     283: aload_0
     284: invokespecial #454                // Method outputSparkSchema:()Lorg/apache/spark/sql/types/StructType;
     287: invokevirtual #458                // Method ai/chronon/online/SparkInternalRowConversions$.from:(Lorg/apache/spark/sql/types/DataType;)Lscala/Function1;
     290: putfield      #84                 // Field outputDecoder:Lscala/Function1;
     293: aload_0
     294: getstatic     #452                // Field ai/chronon/online/SparkInternalRowConversions$.MODULE$:Lai/chronon/online/SparkInternalRowConversions$;
     297: getstatic     #92                 // Field ai/chronon/online/SparkConversions$.MODULE$:Lai/chronon/online/SparkConversions$;
     300: aload_2
     301: invokevirtual #98                 // Method ai/chronon/online/SparkConversions$.fromChrononSchema:(Lai/chronon/api/StructType;)Lorg/apache/spark/sql/types/StructType;
     304: invokevirtual #461                // Method ai/chronon/online/SparkInternalRowConversions$.to:(Lorg/apache/spark/sql/types/DataType;)Lscala/Function1;
     307: putfield      #108                // Field inputEncoder:Lscala/Function1;
     310: return

  private static java.lang.Object $deserializeLambda$(java.lang.invoke.SerializedLambda);
    Code:
       0: aload_0
       1: invokedynamic #475,  0            // InvokeDynamic #2:lambdaDeserialize:(Ljava/lang/invoke/SerializedLambda;)Ljava/lang/Object;
       6: areturn
}
