Compiled from "CompatParColls.scala"
public final class ai.chronon.online.CompatParColls$ {
  public static final ai.chronon.online.CompatParColls$ MODULE$;

  private static final ai.chronon.online.CompatParColls$Compat$CollectionConverters$ Converters;

  public static {};
    Code:
       0: new           #2                  // class ai/chronon/online/CompatParColls$
       3: dup
       4: invokespecial #22                 // Method "<init>":()V
       7: putstatic     #24                 // Field MODULE$:Lai/chronon/online/CompatParColls$;
      10: getstatic     #26                 // Field ai/chronon/online/CompatParColls$Compat$CollectionConverters$.MODULE$:Lai/chronon/online/CompatParColls$Compat$CollectionConverters$;
      13: putstatic     #28                 // Field Converters:Lai/chronon/online/CompatParColls$Compat$CollectionConverters$;
      16: return

  public ai.chronon.online.CompatParColls$Compat$CollectionConverters$ Converters();
    Code:
       0: getstatic     #28                 // Field Converters:Lai/chronon/online/CompatParColls$Compat$CollectionConverters$;
       3: areturn

  private ai.chronon.online.CompatParColls$();
    Code:
       0: aload_0
       1: invokespecial #31                 // Method java/lang/Object."<init>":()V
       4: return
}
