Compiled from "Fetcher.scala"
public class ai.chronon.online.Fetcher$Request implements scala.Product,java.io.Serializable {
  private final java.lang.String name;

  private final scala.collection.immutable.Map<java.lang.String, java.lang.Object> keys;

  private final scala.Option<java.lang.Object> atMillis;

  private final scala.Option<ai.chronon.online.Metrics$Context> context;

  public scala.collection.Iterator<java.lang.String> productElementNames();
    Code:
       0: aload_0
       1: invokestatic  #34                 // InterfaceMethod scala/Product.productElementNames$:(Lscala/Product;)Lscala/collection/Iterator;
       4: areturn

  public java.lang.String name();
    Code:
       0: aload_0
       1: getfield      #39                 // Field name:Ljava/lang/String;
       4: areturn

  public scala.collection.immutable.Map<java.lang.String, java.lang.Object> keys();
    Code:
       0: aload_0
       1: getfield      #43                 // Field keys:Lscala/collection/immutable/Map;
       4: areturn

  public scala.Option<java.lang.Object> atMillis();
    Code:
       0: aload_0
       1: getfield      #47                 // Field atMillis:Lscala/Option;
       4: areturn

  public scala.Option<ai.chronon.online.Metrics$Context> context();
    Code:
       0: aload_0
       1: getfield      #50                 // Field context:Lscala/Option;
       4: areturn

  public ai.chronon.online.Fetcher$Request copy(java.lang.String, scala.collection.immutable.Map<java.lang.String, java.lang.Object>, scala.Option<java.lang.Object>, scala.Option<ai.chronon.online.Metrics$Context>);
    Code:
       0: new           #2                  // class ai/chronon/online/Fetcher$Request
       3: dup
       4: aload_1
       5: aload_2
       6: aload_3
       7: aload         4
       9: invokespecial #57                 // Method "<init>":(Ljava/lang/String;Lscala/collection/immutable/Map;Lscala/Option;Lscala/Option;)V
      12: areturn

  public java.lang.String copy$default$1();
    Code:
       0: aload_0
       1: invokevirtual #60                 // Method name:()Ljava/lang/String;
       4: areturn

  public scala.collection.immutable.Map<java.lang.String, java.lang.Object> copy$default$2();
    Code:
       0: aload_0
       1: invokevirtual #63                 // Method keys:()Lscala/collection/immutable/Map;
       4: areturn

  public scala.Option<java.lang.Object> copy$default$3();
    Code:
       0: aload_0
       1: invokevirtual #66                 // Method atMillis:()Lscala/Option;
       4: areturn

  public scala.Option<ai.chronon.online.Metrics$Context> copy$default$4();
    Code:
       0: aload_0
       1: invokevirtual #69                 // Method context:()Lscala/Option;
       4: areturn

  public java.lang.String productPrefix();
    Code:
       0: ldc           #71                 // String Request
       2: areturn

  public int productArity();
    Code:
       0: iconst_4
       1: ireturn

  public java.lang.Object productElement(int);
    Code:
       0: iload_1
       1: istore_2
       2: iload_2
       3: tableswitch   { // 0 to 3
                     0: 32
                     1: 39
                     2: 46
                     3: 53
               default: 60
          }
      32: aload_0
      33: invokevirtual #60                 // Method name:()Ljava/lang/String;
      36: goto          67
      39: aload_0
      40: invokevirtual #63                 // Method keys:()Lscala/collection/immutable/Map;
      43: goto          67
      46: aload_0
      47: invokevirtual #66                 // Method atMillis:()Lscala/Option;
      50: goto          67
      53: aload_0
      54: invokevirtual #69                 // Method context:()Lscala/Option;
      57: goto          67
      60: iload_1
      61: invokestatic  #81                 // Method scala/runtime/Statics.ioobe:(I)Ljava/lang/Object;
      64: goto          67
      67: areturn

  public scala.collection.Iterator<java.lang.Object> productIterator();
    Code:
       0: getstatic     #90                 // Field scala/runtime/ScalaRunTime$.MODULE$:Lscala/runtime/ScalaRunTime$;
       3: aload_0
       4: invokevirtual #93                 // Method scala/runtime/ScalaRunTime$.typedProductIterator:(Lscala/Product;)Lscala/collection/Iterator;
       7: areturn

  public boolean canEqual(java.lang.Object);
    Code:
       0: aload_1
       1: instanceof    #2                  // class ai/chronon/online/Fetcher$Request
       4: ireturn

  public java.lang.String productElementName(int);
    Code:
       0: iload_1
       1: istore_2
       2: iload_2
       3: tableswitch   { // 0 to 3
                     0: 32
                     1: 37
                     2: 42
                     3: 47
               default: 52
          }
      32: ldc           #99                 // String name
      34: goto          62
      37: ldc           #100                // String keys
      39: goto          62
      42: ldc           #101                // String atMillis
      44: goto          62
      47: ldc           #102                // String context
      49: goto          62
      52: iload_1
      53: invokestatic  #81                 // Method scala/runtime/Statics.ioobe:(I)Ljava/lang/Object;
      56: checkcast     #104                // class java/lang/String
      59: goto          62
      62: areturn

  public int hashCode();
    Code:
       0: getstatic     #90                 // Field scala/runtime/ScalaRunTime$.MODULE$:Lscala/runtime/ScalaRunTime$;
       3: aload_0
       4: invokevirtual #109                // Method scala/runtime/ScalaRunTime$._hashCode:(Lscala/Product;)I
       7: ireturn

  public java.lang.String toString();
    Code:
       0: getstatic     #90                 // Field scala/runtime/ScalaRunTime$.MODULE$:Lscala/runtime/ScalaRunTime$;
       3: aload_0
       4: invokevirtual #114                // Method scala/runtime/ScalaRunTime$._toString:(Lscala/Product;)Ljava/lang/String;
       7: areturn

  public boolean equals(java.lang.Object);
    Code:
       0: aload_0
       1: aload_1
       2: if_acmpeq     182
       5: aload_1
       6: astore_3
       7: aload_3
       8: instanceof    #2                  // class ai/chronon/online/Fetcher$Request
      11: ifeq          19
      14: iconst_1
      15: istore_2
      16: goto          27
      19: goto          22
      22: iconst_0
      23: istore_2
      24: goto          27
      27: iload_2
      28: ifeq          186
      31: aload_1
      32: checkcast     #2                  // class ai/chronon/online/Fetcher$Request
      35: astore        4
      37: aload_0
      38: invokevirtual #60                 // Method name:()Ljava/lang/String;
      41: aload         4
      43: invokevirtual #60                 // Method name:()Ljava/lang/String;
      46: astore        5
      48: dup
      49: ifnonnull     61
      52: pop
      53: aload         5
      55: ifnull        69
      58: goto          178
      61: aload         5
      63: invokevirtual #117                // Method java/lang/Object.equals:(Ljava/lang/Object;)Z
      66: ifeq          178
      69: aload_0
      70: invokevirtual #63                 // Method keys:()Lscala/collection/immutable/Map;
      73: aload         4
      75: invokevirtual #63                 // Method keys:()Lscala/collection/immutable/Map;
      78: astore        6
      80: dup
      81: ifnonnull     93
      84: pop
      85: aload         6
      87: ifnull        101
      90: goto          178
      93: aload         6
      95: invokevirtual #117                // Method java/lang/Object.equals:(Ljava/lang/Object;)Z
      98: ifeq          178
     101: aload_0
     102: invokevirtual #66                 // Method atMillis:()Lscala/Option;
     105: aload         4
     107: invokevirtual #66                 // Method atMillis:()Lscala/Option;
     110: astore        7
     112: dup
     113: ifnonnull     125
     116: pop
     117: aload         7
     119: ifnull        133
     122: goto          178
     125: aload         7
     127: invokevirtual #117                // Method java/lang/Object.equals:(Ljava/lang/Object;)Z
     130: ifeq          178
     133: aload_0
     134: invokevirtual #69                 // Method context:()Lscala/Option;
     137: aload         4
     139: invokevirtual #69                 // Method context:()Lscala/Option;
     142: astore        8
     144: dup
     145: ifnonnull     157
     148: pop
     149: aload         8
     151: ifnull        165
     154: goto          178
     157: aload         8
     159: invokevirtual #117                // Method java/lang/Object.equals:(Ljava/lang/Object;)Z
     162: ifeq          178
     165: aload         4
     167: aload_0
     168: invokevirtual #119                // Method canEqual:(Ljava/lang/Object;)Z
     171: ifeq          178
     174: iconst_1
     175: goto          179
     178: iconst_0
     179: ifeq          186
     182: iconst_1
     183: goto          187
     186: iconst_0
     187: ireturn

  public ai.chronon.online.Fetcher$Request(java.lang.String, scala.collection.immutable.Map<java.lang.String, java.lang.Object>, scala.Option<java.lang.Object>, scala.Option<ai.chronon.online.Metrics$Context>);
    Code:
       0: aload_0
       1: aload_1
       2: putfield      #39                 // Field name:Ljava/lang/String;
       5: aload_0
       6: aload_2
       7: putfield      #43                 // Field keys:Lscala/collection/immutable/Map;
      10: aload_0
      11: aload_3
      12: putfield      #47                 // Field atMillis:Lscala/Option;
      15: aload_0
      16: aload         4
      18: putfield      #50                 // Field context:Lscala/Option;
      21: aload_0
      22: invokespecial #127                // Method java/lang/Object."<init>":()V
      25: aload_0
      26: invokestatic  #131                // InterfaceMethod scala/Product.$init$:(Lscala/Product;)V
      29: return
}
