Compiled from "Fetcher.scala"
public class ai.chronon.online.Fetcher$ExternalToJoinRequest implements scala.Product,java.io.Serializable {
  private ai.chronon.online.Metrics$Context context;

  private final scala.util.Either<ai.chronon.online.Fetcher$Request, ai.chronon.api.KeyMissingException> externalRequest;

  private final ai.chronon.online.Fetcher$Request joinRequest;

  private final ai.chronon.api.ExternalPart part;

  private volatile boolean bitmap$0;

  public final ai.chronon.online.Fetcher $outer;

  public scala.collection.Iterator<java.lang.String> productElementNames();
    Code:
       0: aload_0
       1: invokestatic  #51                 // InterfaceMethod scala/Product.productElementNames$:(Lscala/Product;)Lscala/collection/Iterator;
       4: areturn

  public scala.util.Either<ai.chronon.online.Fetcher$Request, ai.chronon.api.KeyMissingException> externalRequest();
    Code:
       0: aload_0
       1: getfield      #57                 // Field externalRequest:Lscala/util/Either;
       4: areturn

  public ai.chronon.online.Fetcher$Request joinRequest();
    Code:
       0: aload_0
       1: getfield      #60                 // Field joinRequest:Lai/chronon/online/Fetcher$Request;
       4: areturn

  public ai.chronon.api.ExternalPart part();
    Code:
       0: aload_0
       1: getfield      #63                 // Field part:Lai/chronon/api/ExternalPart;
       4: areturn

  private ai.chronon.online.Metrics$Context context$lzycompute();
    Code:
       0: aload_0
       1: dup
       2: astore_1
       3: monitorenter
       4: aload_0
       5: getfield      #67                 // Field bitmap$0:Z
       8: ifne          89
      11: aload_0
      12: new           #22                 // class ai/chronon/online/Metrics$Context
      15: dup
      16: getstatic     #71                 // Field ai/chronon/online/Metrics$Environment$.MODULE$:Lai/chronon/online/Metrics$Environment$;
      19: invokevirtual #75                 // Method ai/chronon/online/Metrics$Environment$.JoinFetching:()Ljava/lang/String;
      22: aload_0
      23: invokevirtual #77                 // Method joinRequest:()Lai/chronon/online/Fetcher$Request;
      26: invokevirtual #80                 // Method ai/chronon/online/Fetcher$Request.name:()Ljava/lang/String;
      29: getstatic     #85                 // Field ai/chronon/api/Extensions$.MODULE$:Lai/chronon/api/Extensions$;
      32: aload_0
      33: invokevirtual #87                 // Method part:()Lai/chronon/api/ExternalPart;
      36: invokevirtual #90                 // Method ai/chronon/api/Extensions$.ExternalPartOps:(Lai/chronon/api/ExternalPart;)Lai/chronon/api/Extensions$ExternalPartOps;
      39: invokevirtual #93                 // Method ai/chronon/api/Extensions$ExternalPartOps.fullName:()Ljava/lang/String;
      42: getstatic     #96                 // Field ai/chronon/online/Metrics$Context$.MODULE$:Lai/chronon/online/Metrics$Context$;
      45: invokevirtual #99                 // Method ai/chronon/online/Metrics$Context$.apply$default$4:()Ljava/lang/String;
      48: getstatic     #96                 // Field ai/chronon/online/Metrics$Context$.MODULE$:Lai/chronon/online/Metrics$Context$;
      51: invokevirtual #103                // Method ai/chronon/online/Metrics$Context$.apply$default$5:()Z
      54: getstatic     #96                 // Field ai/chronon/online/Metrics$Context$.MODULE$:Lai/chronon/online/Metrics$Context$;
      57: invokevirtual #107                // Method ai/chronon/online/Metrics$Context$.apply$default$6:()Lai/chronon/api/Accuracy;
      60: getstatic     #96                 // Field ai/chronon/online/Metrics$Context$.MODULE$:Lai/chronon/online/Metrics$Context$;
      63: invokevirtual #110                // Method ai/chronon/online/Metrics$Context$.apply$default$7:()Ljava/lang/String;
      66: getstatic     #96                 // Field ai/chronon/online/Metrics$Context$.MODULE$:Lai/chronon/online/Metrics$Context$;
      69: invokevirtual #113                // Method ai/chronon/online/Metrics$Context$.apply$default$8:()Ljava/lang/String;
      72: getstatic     #96                 // Field ai/chronon/online/Metrics$Context$.MODULE$:Lai/chronon/online/Metrics$Context$;
      75: invokevirtual #116                // Method ai/chronon/online/Metrics$Context$.apply$default$9:()Ljava/lang/String;
      78: invokespecial #120                // Method ai/chronon/online/Metrics$Context."<init>":(Ljava/lang/String;Ljava/lang/String;Ljava/lang/String;Ljava/lang/String;ZLai/chronon/api/Accuracy;Ljava/lang/String;Ljava/lang/String;Ljava/lang/String;)V
      81: putfield      #122                // Field context:Lai/chronon/online/Metrics$Context;
      84: aload_0
      85: iconst_1
      86: putfield      #67                 // Field bitmap$0:Z
      89: aload_1
      90: monitorexit
      91: goto          97
      94: aload_1
      95: monitorexit
      96: athrow
      97: aload_0
      98: getfield      #122                // Field context:Lai/chronon/online/Metrics$Context;
     101: areturn
    Exception table:
       from    to  target type
           4    89    94   any

  public ai.chronon.online.Metrics$Context context();
    Code:
       0: aload_0
       1: getfield      #67                 // Field bitmap$0:Z
       4: ifne          14
       7: aload_0
       8: invokespecial #126                // Method context$lzycompute:()Lai/chronon/online/Metrics$Context;
      11: goto          18
      14: aload_0
      15: getfield      #122                // Field context:Lai/chronon/online/Metrics$Context;
      18: areturn

  public ai.chronon.online.Fetcher$ExternalToJoinRequest copy(scala.util.Either<ai.chronon.online.Fetcher$Request, ai.chronon.api.KeyMissingException>, ai.chronon.online.Fetcher$Request, ai.chronon.api.ExternalPart);
    Code:
       0: new           #2                  // class ai/chronon/online/Fetcher$ExternalToJoinRequest
       3: dup
       4: aload_0
       5: invokevirtual #133                // Method ai$chronon$online$Fetcher$ExternalToJoinRequest$$$outer:()Lai/chronon/online/Fetcher;
       8: aload_1
       9: aload_2
      10: aload_3
      11: invokespecial #136                // Method "<init>":(Lai/chronon/online/Fetcher;Lscala/util/Either;Lai/chronon/online/Fetcher$Request;Lai/chronon/api/ExternalPart;)V
      14: areturn

  public scala.util.Either<ai.chronon.online.Fetcher$Request, ai.chronon.api.KeyMissingException> copy$default$1();
    Code:
       0: aload_0
       1: invokevirtual #139                // Method externalRequest:()Lscala/util/Either;
       4: areturn

  public ai.chronon.online.Fetcher$Request copy$default$2();
    Code:
       0: aload_0
       1: invokevirtual #77                 // Method joinRequest:()Lai/chronon/online/Fetcher$Request;
       4: areturn

  public ai.chronon.api.ExternalPart copy$default$3();
    Code:
       0: aload_0
       1: invokevirtual #87                 // Method part:()Lai/chronon/api/ExternalPart;
       4: areturn

  public java.lang.String productPrefix();
    Code:
       0: ldc           #143                // String ExternalToJoinRequest
       2: areturn

  public int productArity();
    Code:
       0: iconst_3
       1: ireturn

  public java.lang.Object productElement(int);
    Code:
       0: iload_1
       1: istore_2
       2: iload_2
       3: tableswitch   { // 0 to 2
                     0: 28
                     1: 35
                     2: 42
               default: 49
          }
      28: aload_0
      29: invokevirtual #139                // Method externalRequest:()Lscala/util/Either;
      32: goto          56
      35: aload_0
      36: invokevirtual #77                 // Method joinRequest:()Lai/chronon/online/Fetcher$Request;
      39: goto          56
      42: aload_0
      43: invokevirtual #87                 // Method part:()Lai/chronon/api/ExternalPart;
      46: goto          56
      49: iload_1
      50: invokestatic  #153                // Method scala/runtime/Statics.ioobe:(I)Ljava/lang/Object;
      53: goto          56
      56: areturn

  public scala.collection.Iterator<java.lang.Object> productIterator();
    Code:
       0: getstatic     #161                // Field scala/runtime/ScalaRunTime$.MODULE$:Lscala/runtime/ScalaRunTime$;
       3: aload_0
       4: invokevirtual #164                // Method scala/runtime/ScalaRunTime$.typedProductIterator:(Lscala/Product;)Lscala/collection/Iterator;
       7: areturn

  public boolean canEqual(java.lang.Object);
    Code:
       0: aload_1
       1: instanceof    #2                  // class ai/chronon/online/Fetcher$ExternalToJoinRequest
       4: ireturn

  public java.lang.String productElementName(int);
    Code:
       0: iload_1
       1: istore_2
       2: iload_2
       3: tableswitch   { // 0 to 2
                     0: 28
                     1: 33
                     2: 38
               default: 43
          }
      28: ldc           #170                // String externalRequest
      30: goto          53
      33: ldc           #171                // String joinRequest
      35: goto          53
      38: ldc           #172                // String part
      40: goto          53
      43: iload_1
      44: invokestatic  #153                // Method scala/runtime/Statics.ioobe:(I)Ljava/lang/Object;
      47: checkcast     #174                // class java/lang/String
      50: goto          53
      53: areturn

  public int hashCode();
    Code:
       0: getstatic     #161                // Field scala/runtime/ScalaRunTime$.MODULE$:Lscala/runtime/ScalaRunTime$;
       3: aload_0
       4: invokevirtual #179                // Method scala/runtime/ScalaRunTime$._hashCode:(Lscala/Product;)I
       7: ireturn

  public java.lang.String toString();
    Code:
       0: getstatic     #161                // Field scala/runtime/ScalaRunTime$.MODULE$:Lscala/runtime/ScalaRunTime$;
       3: aload_0
       4: invokevirtual #184                // Method scala/runtime/ScalaRunTime$._toString:(Lscala/Product;)Ljava/lang/String;
       7: areturn

  public boolean equals(java.lang.Object);
    Code:
       0: aload_0
       1: aload_1
       2: if_acmpeq     164
       5: aload_1
       6: astore_3
       7: aload_3
       8: instanceof    #2                  // class ai/chronon/online/Fetcher$ExternalToJoinRequest
      11: ifeq          33
      14: aload_3
      15: checkcast     #2                  // class ai/chronon/online/Fetcher$ExternalToJoinRequest
      18: invokevirtual #133                // Method ai$chronon$online$Fetcher$ExternalToJoinRequest$$$outer:()Lai/chronon/online/Fetcher;
      21: aload_0
      22: invokevirtual #133                // Method ai$chronon$online$Fetcher$ExternalToJoinRequest$$$outer:()Lai/chronon/online/Fetcher;
      25: if_acmpne     33
      28: iconst_1
      29: istore_2
      30: goto          41
      33: goto          36
      36: iconst_0
      37: istore_2
      38: goto          41
      41: iload_2
      42: ifeq          168
      45: aload_1
      46: checkcast     #2                  // class ai/chronon/online/Fetcher$ExternalToJoinRequest
      49: astore        4
      51: aload_0
      52: invokevirtual #139                // Method externalRequest:()Lscala/util/Either;
      55: aload         4
      57: invokevirtual #139                // Method externalRequest:()Lscala/util/Either;
      60: astore        5
      62: dup
      63: ifnonnull     75
      66: pop
      67: aload         5
      69: ifnull        83
      72: goto          160
      75: aload         5
      77: invokevirtual #187                // Method java/lang/Object.equals:(Ljava/lang/Object;)Z
      80: ifeq          160
      83: aload_0
      84: invokevirtual #77                 // Method joinRequest:()Lai/chronon/online/Fetcher$Request;
      87: aload         4
      89: invokevirtual #77                 // Method joinRequest:()Lai/chronon/online/Fetcher$Request;
      92: astore        6
      94: dup
      95: ifnonnull     107
      98: pop
      99: aload         6
     101: ifnull        115
     104: goto          160
     107: aload         6
     109: invokevirtual #187                // Method java/lang/Object.equals:(Ljava/lang/Object;)Z
     112: ifeq          160
     115: aload_0
     116: invokevirtual #87                 // Method part:()Lai/chronon/api/ExternalPart;
     119: aload         4
     121: invokevirtual #87                 // Method part:()Lai/chronon/api/ExternalPart;
     124: astore        7
     126: dup
     127: ifnonnull     139
     130: pop
     131: aload         7
     133: ifnull        147
     136: goto          160
     139: aload         7
     141: invokevirtual #187                // Method java/lang/Object.equals:(Ljava/lang/Object;)Z
     144: ifeq          160
     147: aload         4
     149: aload_0
     150: invokevirtual #189                // Method canEqual:(Ljava/lang/Object;)Z
     153: ifeq          160
     156: iconst_1
     157: goto          161
     160: iconst_0
     161: ifeq          168
     164: iconst_1
     165: goto          169
     168: iconst_0
     169: ireturn

  public ai.chronon.online.Fetcher ai$chronon$online$Fetcher$ExternalToJoinRequest$$$outer();
    Code:
       0: aload_0
       1: getfield      #195                // Field $outer:Lai/chronon/online/Fetcher;
       4: areturn

  public ai.chronon.online.Fetcher$ExternalToJoinRequest(scala.util.Either<ai.chronon.online.Fetcher$Request, ai.chronon.api.KeyMissingException>, ai.chronon.online.Fetcher$Request, ai.chronon.api.ExternalPart);
    Code:
       0: aload_0
       1: aload_2
       2: putfield      #57                 // Field externalRequest:Lscala/util/Either;
       5: aload_0
       6: aload_3
       7: putfield      #60                 // Field joinRequest:Lai/chronon/online/Fetcher$Request;
      10: aload_0
      11: aload         4
      13: putfield      #63                 // Field part:Lai/chronon/api/ExternalPart;
      16: aload_1
      17: ifnonnull     22
      20: aconst_null
      21: athrow
      22: aload_0
      23: aload_1
      24: putfield      #195                // Field $outer:Lai/chronon/online/Fetcher;
      27: aload_0
      28: invokespecial #199                // Method java/lang/Object."<init>":()V
      31: aload_0
      32: invokestatic  #203                // InterfaceMethod scala/Product.$init$:(Lscala/Product;)V
      35: return
}
