Compiled from "Metrics.scala"
public class ai.chronon.online.Metrics$Tag$ {
  public static final ai.chronon.online.Metrics$Tag$ MODULE$;

  private static final java.lang.String GroupBy;

  private static final java.lang.String Join;

  private static final java.lang.String JoinPartPrefix;

  private static final java.lang.String StagingQuery;

  private static final java.lang.String Environment;

  private static final java.lang.String Production;

  private static final java.lang.String Accuracy;

  private static final java.lang.String Team;

  public static {};
    Code:
       0: new           #2                  // class ai/chronon/online/Metrics$Tag$
       3: dup
       4: invokespecial #24                 // Method "<init>":()V
       7: putstatic     #26                 // Field MODULE$:Lai/chronon/online/Metrics$Tag$;
      10: ldc           #28                 // String group_by
      12: putstatic     #30                 // Field GroupBy:Ljava/lang/String;
      15: ldc           #32                 // String join
      17: putstatic     #34                 // Field Join:Ljava/lang/String;
      20: ldc           #36                 // String join_part_prefix
      22: putstatic     #38                 // Field JoinPartPrefix:Ljava/lang/String;
      25: ldc           #40                 // String staging_query
      27: putstatic     #42                 // Field StagingQuery:Ljava/lang/String;
      30: ldc           #44                 // String environment
      32: putstatic     #46                 // Field Environment:Ljava/lang/String;
      35: ldc           #48                 // String production
      37: putstatic     #50                 // Field Production:Ljava/lang/String;
      40: ldc           #52                 // String accuracy
      42: putstatic     #54                 // Field Accuracy:Ljava/lang/String;
      45: ldc           #56                 // String team
      47: putstatic     #58                 // Field Team:Ljava/lang/String;
      50: return

  public java.lang.String GroupBy();
    Code:
       0: getstatic     #30                 // Field GroupBy:Ljava/lang/String;
       3: areturn

  public java.lang.String Join();
    Code:
       0: getstatic     #34                 // Field Join:Ljava/lang/String;
       3: areturn

  public java.lang.String JoinPartPrefix();
    Code:
       0: getstatic     #38                 // Field JoinPartPrefix:Ljava/lang/String;
       3: areturn

  public java.lang.String StagingQuery();
    Code:
       0: getstatic     #42                 // Field StagingQuery:Ljava/lang/String;
       3: areturn

  public java.lang.String Environment();
    Code:
       0: getstatic     #46                 // Field Environment:Ljava/lang/String;
       3: areturn

  public java.lang.String Production();
    Code:
       0: getstatic     #50                 // Field Production:Ljava/lang/String;
       3: areturn

  public java.lang.String Accuracy();
    Code:
       0: getstatic     #54                 // Field Accuracy:Ljava/lang/String;
       3: areturn

  public java.lang.String Team();
    Code:
       0: getstatic     #58                 // Field Team:Ljava/lang/String;
       3: areturn

  public ai.chronon.online.Metrics$Tag$();
    Code:
       0: aload_0
       1: invokespecial #61                 // Method java/lang/Object."<init>":()V
       4: return
}
