Compiled from "Api.scala"
public class ai.chronon.online.Mutation implements scala.Product,java.io.Serializable {
  private final ai.chronon.api.StructType schema;

  private final java.lang.Object[] before;

  private final java.lang.Object[] after;

  public static java.lang.Object[] $lessinit$greater$default$3();
    Code:
       0: getstatic     #25                 // Field ai/chronon/online/Mutation$.MODULE$:Lai/chronon/online/Mutation$;
       3: invokevirtual #27                 // Method ai/chronon/online/Mutation$.$lessinit$greater$default$3:()[Ljava/lang/Object;
       6: areturn

  public static java.lang.Object[] $lessinit$greater$default$2();
    Code:
       0: getstatic     #25                 // Field ai/chronon/online/Mutation$.MODULE$:Lai/chronon/online/Mutation$;
       3: invokevirtual #30                 // Method ai/chronon/online/Mutation$.$lessinit$greater$default$2:()[Ljava/lang/Object;
       6: areturn

  public static ai.chronon.api.StructType $lessinit$greater$default$1();
    Code:
       0: getstatic     #25                 // Field ai/chronon/online/Mutation$.MODULE$:Lai/chronon/online/Mutation$;
       3: invokevirtual #34                 // Method ai/chronon/online/Mutation$.$lessinit$greater$default$1:()Lai/chronon/api/StructType;
       6: areturn

  public static scala.Option<scala.Tuple3<ai.chronon.api.StructType, java.lang.Object[], java.lang.Object[]>> unapply(ai.chronon.online.Mutation);
    Code:
       0: getstatic     #25                 // Field ai/chronon/online/Mutation$.MODULE$:Lai/chronon/online/Mutation$;
       3: aload_0
       4: invokevirtual #40                 // Method ai/chronon/online/Mutation$.unapply:(Lai/chronon/online/Mutation;)Lscala/Option;
       7: areturn

  public static java.lang.Object[] apply$default$3();
    Code:
       0: getstatic     #25                 // Field ai/chronon/online/Mutation$.MODULE$:Lai/chronon/online/Mutation$;
       3: invokevirtual #44                 // Method ai/chronon/online/Mutation$.apply$default$3:()[Ljava/lang/Object;
       6: areturn

  public static java.lang.Object[] apply$default$2();
    Code:
       0: getstatic     #25                 // Field ai/chronon/online/Mutation$.MODULE$:Lai/chronon/online/Mutation$;
       3: invokevirtual #47                 // Method ai/chronon/online/Mutation$.apply$default$2:()[Ljava/lang/Object;
       6: areturn

  public static ai.chronon.api.StructType apply$default$1();
    Code:
       0: getstatic     #25                 // Field ai/chronon/online/Mutation$.MODULE$:Lai/chronon/online/Mutation$;
       3: invokevirtual #50                 // Method ai/chronon/online/Mutation$.apply$default$1:()Lai/chronon/api/StructType;
       6: areturn

  public static ai.chronon.online.Mutation apply(ai.chronon.api.StructType, java.lang.Object[], java.lang.Object[]);
    Code:
       0: getstatic     #25                 // Field ai/chronon/online/Mutation$.MODULE$:Lai/chronon/online/Mutation$;
       3: aload_0
       4: aload_1
       5: aload_2
       6: invokevirtual #54                 // Method ai/chronon/online/Mutation$.apply:(Lai/chronon/api/StructType;[Ljava/lang/Object;[Ljava/lang/Object;)Lai/chronon/online/Mutation;
       9: areturn

  public static scala.Function1<scala.Tuple3<ai.chronon.api.StructType, java.lang.Object[], java.lang.Object[]>, ai.chronon.online.Mutation> tupled();
    Code:
       0: getstatic     #25                 // Field ai/chronon/online/Mutation$.MODULE$:Lai/chronon/online/Mutation$;
       3: invokevirtual #59                 // Method ai/chronon/online/Mutation$.tupled:()Lscala/Function1;
       6: areturn

  public static scala.Function1<ai.chronon.api.StructType, scala.Function1<java.lang.Object[], scala.Function1<java.lang.Object[], ai.chronon.online.Mutation>>> curried();
    Code:
       0: getstatic     #25                 // Field ai/chronon/online/Mutation$.MODULE$:Lai/chronon/online/Mutation$;
       3: invokevirtual #63                 // Method ai/chronon/online/Mutation$.curried:()Lscala/Function1;
       6: areturn

  public scala.collection.Iterator<java.lang.String> productElementNames();
    Code:
       0: aload_0
       1: invokestatic  #70                 // InterfaceMethod scala/Product.productElementNames$:(Lscala/Product;)Lscala/collection/Iterator;
       4: areturn

  public ai.chronon.api.StructType schema();
    Code:
       0: aload_0
       1: getfield      #73                 // Field schema:Lai/chronon/api/StructType;
       4: areturn

  public java.lang.Object[] before();
    Code:
       0: aload_0
       1: getfield      #75                 // Field before:[Ljava/lang/Object;
       4: areturn

  public java.lang.Object[] after();
    Code:
       0: aload_0
       1: getfield      #77                 // Field after:[Ljava/lang/Object;
       4: areturn

  public ai.chronon.online.Mutation copy(ai.chronon.api.StructType, java.lang.Object[], java.lang.Object[]);
    Code:
       0: new           #2                  // class ai/chronon/online/Mutation
       3: dup
       4: aload_1
       5: aload_2
       6: aload_3
       7: invokespecial #82                 // Method "<init>":(Lai/chronon/api/StructType;[Ljava/lang/Object;[Ljava/lang/Object;)V
      10: areturn

  public ai.chronon.api.StructType copy$default$1();
    Code:
       0: aload_0
       1: invokevirtual #85                 // Method schema:()Lai/chronon/api/StructType;
       4: areturn

  public java.lang.Object[] copy$default$2();
    Code:
       0: aload_0
       1: invokevirtual #88                 // Method before:()[Ljava/lang/Object;
       4: areturn

  public java.lang.Object[] copy$default$3();
    Code:
       0: aload_0
       1: invokevirtual #91                 // Method after:()[Ljava/lang/Object;
       4: areturn

  public java.lang.String productPrefix();
    Code:
       0: ldc           #95                 // String Mutation
       2: areturn

  public int productArity();
    Code:
       0: iconst_3
       1: ireturn

  public java.lang.Object productElement(int);
    Code:
       0: iload_1
       1: istore_2
       2: iload_2
       3: tableswitch   { // 0 to 2
                     0: 28
                     1: 35
                     2: 42
               default: 49
          }
      28: aload_0
      29: invokevirtual #85                 // Method schema:()Lai/chronon/api/StructType;
      32: goto          56
      35: aload_0
      36: invokevirtual #88                 // Method before:()[Ljava/lang/Object;
      39: goto          56
      42: aload_0
      43: invokevirtual #91                 // Method after:()[Ljava/lang/Object;
      46: goto          56
      49: iload_1
      50: invokestatic  #105                // Method scala/runtime/Statics.ioobe:(I)Ljava/lang/Object;
      53: goto          56
      56: areturn

  public scala.collection.Iterator<java.lang.Object> productIterator();
    Code:
       0: getstatic     #113                // Field scala/runtime/ScalaRunTime$.MODULE$:Lscala/runtime/ScalaRunTime$;
       3: aload_0
       4: invokevirtual #116                // Method scala/runtime/ScalaRunTime$.typedProductIterator:(Lscala/Product;)Lscala/collection/Iterator;
       7: areturn

  public boolean canEqual(java.lang.Object);
    Code:
       0: aload_1
       1: instanceof    #2                  // class ai/chronon/online/Mutation
       4: ireturn

  public java.lang.String productElementName(int);
    Code:
       0: iload_1
       1: istore_2
       2: iload_2
       3: tableswitch   { // 0 to 2
                     0: 28
                     1: 33
                     2: 38
               default: 43
          }
      28: ldc           #122                // String schema
      30: goto          53
      33: ldc           #123                // String before
      35: goto          53
      38: ldc           #124                // String after
      40: goto          53
      43: iload_1
      44: invokestatic  #105                // Method scala/runtime/Statics.ioobe:(I)Ljava/lang/Object;
      47: checkcast     #126                // class java/lang/String
      50: goto          53
      53: areturn

  public int hashCode();
    Code:
       0: getstatic     #113                // Field scala/runtime/ScalaRunTime$.MODULE$:Lscala/runtime/ScalaRunTime$;
       3: aload_0
       4: invokevirtual #131                // Method scala/runtime/ScalaRunTime$._hashCode:(Lscala/Product;)I
       7: ireturn

  public java.lang.String toString();
    Code:
       0: getstatic     #113                // Field scala/runtime/ScalaRunTime$.MODULE$:Lscala/runtime/ScalaRunTime$;
       3: aload_0
       4: invokevirtual #136                // Method scala/runtime/ScalaRunTime$._toString:(Lscala/Product;)Ljava/lang/String;
       7: areturn

  public boolean equals(java.lang.Object);
    Code:
       0: aload_0
       1: aload_1
       2: if_acmpeq     110
       5: aload_1
       6: astore_3
       7: aload_3
       8: instanceof    #2                  // class ai/chronon/online/Mutation
      11: ifeq          19
      14: iconst_1
      15: istore_2
      16: goto          27
      19: goto          22
      22: iconst_0
      23: istore_2
      24: goto          27
      27: iload_2
      28: ifeq          114
      31: aload_1
      32: checkcast     #2                  // class ai/chronon/online/Mutation
      35: astore        4
      37: aload_0
      38: invokevirtual #85                 // Method schema:()Lai/chronon/api/StructType;
      41: aload         4
      43: invokevirtual #85                 // Method schema:()Lai/chronon/api/StructType;
      46: astore        5
      48: dup
      49: ifnonnull     61
      52: pop
      53: aload         5
      55: ifnull        69
      58: goto          106
      61: aload         5
      63: invokevirtual #139                // Method java/lang/Object.equals:(Ljava/lang/Object;)Z
      66: ifeq          106
      69: aload_0
      70: invokevirtual #88                 // Method before:()[Ljava/lang/Object;
      73: aload         4
      75: invokevirtual #88                 // Method before:()[Ljava/lang/Object;
      78: if_acmpne     106
      81: aload_0
      82: invokevirtual #91                 // Method after:()[Ljava/lang/Object;
      85: aload         4
      87: invokevirtual #91                 // Method after:()[Ljava/lang/Object;
      90: if_acmpne     106
      93: aload         4
      95: aload_0
      96: invokevirtual #141                // Method canEqual:(Ljava/lang/Object;)Z
      99: ifeq          106
     102: iconst_1
     103: goto          107
     106: iconst_0
     107: ifeq          114
     110: iconst_1
     111: goto          115
     114: iconst_0
     115: ireturn

  public ai.chronon.online.Mutation(ai.chronon.api.StructType, java.lang.Object[], java.lang.Object[]);
    Code:
       0: aload_0
       1: aload_1
       2: putfield      #73                 // Field schema:Lai/chronon/api/StructType;
       5: aload_0
       6: aload_2
       7: putfield      #75                 // Field before:[Ljava/lang/Object;
      10: aload_0
      11: aload_3
      12: putfield      #77                 // Field after:[Ljava/lang/Object;
      15: aload_0
      16: invokespecial #146                // Method java/lang/Object."<init>":()V
      19: aload_0
      20: invokestatic  #150                // InterfaceMethod scala/Product.$init$:(Lscala/Product;)V
      23: return
}
