Compiled from "AbstractNonStreamingHashFunction.java"
final class org.sonar.api.internal.google.common.hash.AbstractNonStreamingHashFunction$ExposedByteArrayOutputStream extends java.io.ByteArrayOutputStream {
  org.sonar.api.internal.google.common.hash.AbstractNonStreamingHashFunction$ExposedByteArrayOutputStream(int);
    Code:
       0: aload_0
       1: iload_1
       2: invokespecial #12                 // Method java/io/ByteArrayOutputStream."<init>":(I)V
       5: return

  byte[] byteArray();
    Code:
       0: aload_0
       1: getfield      #22                 // Field buf:[B
       4: areturn

  int length();
    Code:
       0: aload_0
       1: getfield      #27                 // Field count:I
       4: ireturn
}
