Compiled from "LocalEjbReceiver.java"
final class org.jboss.as.ejb3.remote.LocalEjbReceiver$3 implements java.security.PrivilegedExceptionAction<java.lang.Object> {
  final org.jboss.marshalling.cloner.ObjectCloner val$cloner;

  final java.lang.Object val$object;

  org.jboss.as.ejb3.remote.LocalEjbReceiver$3(org.jboss.marshalling.cloner.ObjectCloner, java.lang.Object);
    Code:
       0: aload_0
       1: aload_1
       2: putfield      #1                  // Field val$cloner:Lorg/jboss/marshalling/cloner/ObjectCloner;
       5: aload_0
       6: aload_2
       7: putfield      #2                  // Field val$object:Ljava/lang/Object;
      10: aload_0
      11: invokespecial #3                  // Method java/lang/Object."<init>":()V
      14: return

  public java.lang.Object run() throws java.io.IOException, java.lang.ClassNotFoundException;
    Code:
       0: aload_0
       1: getfield      #1                  // Field val$cloner:Lorg/jboss/marshalling/cloner/ObjectCloner;
       4: aload_0
       5: getfield      #2                  // Field val$object:Ljava/lang/Object;
       8: invokeinterface #4,  2            // InterfaceMethod org/jboss/marshalling/cloner/ObjectCloner.clone:(Ljava/lang/Object;)Ljava/lang/Object;
      13: areturn
}
