Compiled from "LocalEJBReceiverPreferringDeploymentNodeSelector.java"
public class org.jboss.as.ejb3.remote.LocalEJBReceiverPreferringDeploymentNodeSelector implements org.jboss.ejb.client.DeploymentNodeSelector {
  private final java.lang.String localNodeName;

  public org.jboss.as.ejb3.remote.LocalEJBReceiverPreferringDeploymentNodeSelector();
    Code:
       0: aload_0
       1: invokespecial #1                  // Method java/lang/Object."<init>":()V
       4: aload_0
       5: ldc           #3                  // String jboss.node.name
       7: aconst_null
       8: invokestatic  #4                  // Method org/wildfly/security/manager/WildFlySecurityManager.getPropertyPrivileged:(Ljava/lang/String;Ljava/lang/String;)Ljava/lang/String;
      11: putfield      #5                  // Field localNodeName:Ljava/lang/String;
      14: return

  public java.lang.String selectNode(java.lang.String[], java.lang.String, java.lang.String, java.lang.String);
    Code:
       0: aload_1
       1: arraylength
       2: iconst_1
       3: if_icmpne     10
       6: aload_1
       7: iconst_0
       8: aaload
       9: areturn
      10: aload_1
      11: astore        5
      13: aload         5
      15: arraylength
      16: istore        6
      18: iconst_0
      19: istore        7
      21: iload         7
      23: iload         6
      25: if_icmpge     90
      28: aload         5
      30: iload         7
      32: aaload
      33: astore        8
      35: aload_0
      36: getfield      #5                  // Field localNodeName:Ljava/lang/String;
      39: aload         8
      41: invokevirtual #6                  // Method java/lang/String.equals:(Ljava/lang/Object;)Z
      44: ifeq          84
      47: getstatic     #7                  // Field org/jboss/as/ejb3/logging/EjbLogger.REMOTE_LOGGER:Lorg/jboss/as/ejb3/logging/EjbLogger;
      50: ldc           #8                  // String Selected local node %s for [app: %s, module: %s,  distinctname: %s]
      52: iconst_4
      53: anewarray     #9                  // class java/lang/Object
      56: dup
      57: iconst_0
      58: aload_0
      59: getfield      #5                  // Field localNodeName:Ljava/lang/String;
      62: aastore
      63: dup
      64: iconst_1
      65: aload_2
      66: aastore
      67: dup
      68: iconst_2
      69: aload_3
      70: aastore
      71: dup
      72: iconst_3
      73: aload         4
      75: aastore
      76: invokeinterface #10,  3           // InterfaceMethod org/jboss/as/ejb3/logging/EjbLogger.debugf:(Ljava/lang/String;[Ljava/lang/Object;)V
      81: aload         8
      83: areturn
      84: iinc          7, 1
      87: goto          21
      90: new           #11                 // class java/util/Random
      93: dup
      94: invokespecial #12                 // Method java/util/Random."<init>":()V
      97: astore        5
      99: aload         5
     101: aload_1
     102: arraylength
     103: invokevirtual #13                 // Method java/util/Random.nextInt:(I)I
     106: istore        6
     108: aload_1
     109: iload         6
     111: aaload
     112: areturn
}
