Compiled from "RemotingConnectionClusterNodeManager.java"
class org.jboss.as.ejb3.remote.RemotingConnectionClusterNodeManager implements org.jboss.ejb.client.ClusterNodeManager {
  private final java.lang.String nodeName;

  private final org.jboss.ejb.client.ClusterContext clusterContext;

  private final java.lang.String destinationHost;

  private final int destinationPort;

  private final java.lang.String destinationProtocol;

  private final org.jboss.remoting3.Endpoint endpoint;

  org.jboss.as.ejb3.remote.RemotingConnectionClusterNodeManager(org.jboss.ejb.client.ClusterContext, org.jboss.remoting3.Endpoint, java.lang.String, java.lang.String, int, java.lang.String);
    Code:
       0: aload_0
       1: invokespecial #3                  // Method java/lang/Object."<init>":()V
       4: aload_0
       5: aload_3
       6: putfield      #4                  // Field nodeName:Ljava/lang/String;
       9: aload_0
      10: aload_1
      11: putfield      #1                  // Field clusterContext:Lorg/jboss/ejb/client/ClusterContext;
      14: aload_0
      15: aload         4
      17: putfield      #5                  // Field destinationHost:Ljava/lang/String;
      20: aload_0
      21: iload         5
      23: putfield      #6                  // Field destinationPort:I
      26: aload_0
      27: aload_2
      28: putfield      #2                  // Field endpoint:Lorg/jboss/remoting3/Endpoint;
      31: aload_0
      32: aload         6
      34: putfield      #7                  // Field destinationProtocol:Ljava/lang/String;
      37: return

  public java.lang.String getNodeName();
    Code:
       0: aload_0
       1: getfield      #4                  // Field nodeName:Ljava/lang/String;
       4: areturn

  public org.jboss.ejb.client.EJBReceiver getEJBReceiver();
    Code:
       0: getstatic     #8                  // Field org/xnio/OptionMap.EMPTY:Lorg/xnio/OptionMap;
       3: astore_3
       4: aload_0
       5: getfield      #1                  // Field clusterContext:Lorg/jboss/ejb/client/ClusterContext;
       8: invokevirtual #9                  // Method org/jboss/ejb/client/ClusterContext.getEJBClientContext:()Lorg/jboss/ejb/client/EJBClientContext;
      11: invokevirtual #10                 // Method org/jboss/ejb/client/EJBClientContext.getEJBClientConfiguration:()Lorg/jboss/ejb/client/EJBClientConfiguration;
      14: astore        4
      16: aload         4
      18: ifnull        302
      21: aload         4
      23: aload_0
      24: getfield      #1                  // Field clusterContext:Lorg/jboss/ejb/client/ClusterContext;
      27: invokevirtual #11                 // Method org/jboss/ejb/client/ClusterContext.getClusterName:()Ljava/lang/String;
      30: invokeinterface #12,  2           // InterfaceMethod org/jboss/ejb/client/EJBClientConfiguration.getClusterConfiguration:(Ljava/lang/String;)Lorg/jboss/ejb/client/EJBClientConfiguration$ClusterConfiguration;
      35: astore        5
      37: aload         5
      39: ifnonnull     126
      42: getstatic     #8                  // Field org/xnio/OptionMap.EMPTY:Lorg/xnio/OptionMap;
      45: astore        6
      47: aload         4
      49: invokeinterface #13,  1           // InterfaceMethod org/jboss/ejb/client/EJBClientConfiguration.getCallbackHandler:()Ljavax/security/auth/callback/CallbackHandler;
      54: astore        7
      56: aload_0
      57: getfield      #2                  // Field endpoint:Lorg/jboss/remoting3/Endpoint;
      60: aload_0
      61: getfield      #7                  // Field destinationProtocol:Ljava/lang/String;
      64: aload_0
      65: getfield      #5                  // Field destinationHost:Ljava/lang/String;
      68: aload_0
      69: getfield      #6                  // Field destinationPort:I
      72: aconst_null
      73: aload         6
      75: aload         7
      77: aconst_null
      78: invokestatic  #14                 // Method org/jboss/ejb/client/remoting/NetworkUtil.connect:(Lorg/jboss/remoting3/Endpoint;Ljava/lang/String;Ljava/lang/String;ILjava/net/InetSocketAddress;Lorg/xnio/OptionMap;Ljavax/security/auth/callback/CallbackHandler;Ljavax/net/ssl/SSLContext;)Lorg/xnio/IoFuture;
      81: astore        8
      83: aload         8
      85: ldc2_w        #15                 // long 5000l
      88: getstatic     #17                 // Field java/util/concurrent/TimeUnit.MILLISECONDS:Ljava/util/concurrent/TimeUnit;
      91: invokestatic  #18                 // Method org/jboss/ejb/client/remoting/IoFutureHelper.get:(Lorg/xnio/IoFuture;JLjava/util/concurrent/TimeUnit;)Ljava/lang/Object;
      94: checkcast     #19                 // class org/jboss/remoting3/Connection
      97: astore_1
      98: new           #20                 // class org/jboss/as/ejb3/remote/RemotingConnectionClusterNodeManager$ClusterNodeReconnectHandler
     101: dup
     102: aload_0
     103: aload_0
     104: getfield      #5                  // Field destinationHost:Ljava/lang/String;
     107: aload_0
     108: getfield      #6                  // Field destinationPort:I
     111: aload         6
     113: aload         7
     115: aload_3
     116: ldc2_w        #15                 // long 5000l
     119: invokespecial #21                 // Method org/jboss/as/ejb3/remote/RemotingConnectionClusterNodeManager$ClusterNodeReconnectHandler."<init>":(Lorg/jboss/as/ejb3/remote/RemotingConnectionClusterNodeManager;Ljava/lang/String;ILorg/xnio/OptionMap;Ljavax/security/auth/callback/CallbackHandler;Lorg/xnio/OptionMap;J)V
     122: astore_2
     123: goto          299
     126: aload         5
     128: aload_0
     129: invokevirtual #22                 // Method getNodeName:()Ljava/lang/String;
     132: invokeinterface #23,  2           // InterfaceMethod org/jboss/ejb/client/EJBClientConfiguration$ClusterConfiguration.getNodeConfiguration:(Ljava/lang/String;)Lorg/jboss/ejb/client/EJBClientConfiguration$ClusterNodeConfiguration;
     137: astore        6
     139: aload         6
     141: ifnonnull     154
     144: aload         5
     146: invokeinterface #24,  1           // InterfaceMethod org/jboss/ejb/client/EJBClientConfiguration$ClusterConfiguration.getChannelCreationOptions:()Lorg/xnio/OptionMap;
     151: goto          161
     154: aload         6
     156: invokeinterface #25,  1           // InterfaceMethod org/jboss/ejb/client/EJBClientConfiguration$ClusterNodeConfiguration.getChannelCreationOptions:()Lorg/xnio/OptionMap;
     161: astore_3
     162: aload         6
     164: ifnonnull     177
     167: aload         5
     169: invokeinterface #26,  1           // InterfaceMethod org/jboss/ejb/client/EJBClientConfiguration$ClusterConfiguration.getConnectionCreationOptions:()Lorg/xnio/OptionMap;
     174: goto          184
     177: aload         6
     179: invokeinterface #27,  1           // InterfaceMethod org/jboss/ejb/client/EJBClientConfiguration$ClusterNodeConfiguration.getConnectionCreationOptions:()Lorg/xnio/OptionMap;
     184: astore        7
     186: aload         6
     188: ifnonnull     201
     191: aload         5
     193: invokeinterface #28,  1           // InterfaceMethod org/jboss/ejb/client/EJBClientConfiguration$ClusterConfiguration.getCallbackHandler:()Ljavax/security/auth/callback/CallbackHandler;
     198: goto          208
     201: aload         6
     203: invokeinterface #29,  1           // InterfaceMethod org/jboss/ejb/client/EJBClientConfiguration$ClusterNodeConfiguration.getCallbackHandler:()Ljavax/security/auth/callback/CallbackHandler;
     208: astore        8
     210: aload_0
     211: getfield      #2                  // Field endpoint:Lorg/jboss/remoting3/Endpoint;
     214: aload_0
     215: getfield      #7                  // Field destinationProtocol:Ljava/lang/String;
     218: aload_0
     219: getfield      #5                  // Field destinationHost:Ljava/lang/String;
     222: aload_0
     223: getfield      #6                  // Field destinationPort:I
     226: aconst_null
     227: aload         7
     229: aload         8
     231: aconst_null
     232: invokestatic  #14                 // Method org/jboss/ejb/client/remoting/NetworkUtil.connect:(Lorg/jboss/remoting3/Endpoint;Ljava/lang/String;Ljava/lang/String;ILjava/net/InetSocketAddress;Lorg/xnio/OptionMap;Ljavax/security/auth/callback/CallbackHandler;Ljavax/net/ssl/SSLContext;)Lorg/xnio/IoFuture;
     235: astore        9
     237: aload         6
     239: ifnonnull     252
     242: aload         5
     244: invokeinterface #30,  1           // InterfaceMethod org/jboss/ejb/client/EJBClientConfiguration$ClusterConfiguration.getConnectionTimeout:()J
     249: goto          259
     252: aload         6
     254: invokeinterface #31,  1           // InterfaceMethod org/jboss/ejb/client/EJBClientConfiguration$ClusterNodeConfiguration.getConnectionTimeout:()J
     259: lstore        10
     261: aload         9
     263: lload         10
     265: getstatic     #17                 // Field java/util/concurrent/TimeUnit.MILLISECONDS:Ljava/util/concurrent/TimeUnit;
     268: invokestatic  #18                 // Method org/jboss/ejb/client/remoting/IoFutureHelper.get:(Lorg/xnio/IoFuture;JLjava/util/concurrent/TimeUnit;)Ljava/lang/Object;
     271: checkcast     #19                 // class org/jboss/remoting3/Connection
     274: astore_1
     275: new           #20                 // class org/jboss/as/ejb3/remote/RemotingConnectionClusterNodeManager$ClusterNodeReconnectHandler
     278: dup
     279: aload_0
     280: aload_0
     281: getfield      #5                  // Field destinationHost:Ljava/lang/String;
     284: aload_0
     285: getfield      #6                  // Field destinationPort:I
     288: aload         7
     290: aload         8
     292: aload_3
     293: lload         10
     295: invokespecial #21                 // Method org/jboss/as/ejb3/remote/RemotingConnectionClusterNodeManager$ClusterNodeReconnectHandler."<init>":(Lorg/jboss/as/ejb3/remote/RemotingConnectionClusterNodeManager;Ljava/lang/String;ILorg/xnio/OptionMap;Ljavax/security/auth/callback/CallbackHandler;Lorg/xnio/OptionMap;J)V
     298: astore_2
     299: goto          383
     302: getstatic     #8                  // Field org/xnio/OptionMap.EMPTY:Lorg/xnio/OptionMap;
     305: astore        5
     307: new           #32                 // class org/jboss/as/ejb3/remote/AnonymousCallbackHandler
     310: dup
     311: invokespecial #33                 // Method org/jboss/as/ejb3/remote/AnonymousCallbackHandler."<init>":()V
     314: astore        6
     316: aload_0
     317: getfield      #2                  // Field endpoint:Lorg/jboss/remoting3/Endpoint;
     320: aload_0
     321: getfield      #7                  // Field destinationProtocol:Ljava/lang/String;
     324: aload_0
     325: getfield      #5                  // Field destinationHost:Ljava/lang/String;
     328: aload_0
     329: getfield      #6                  // Field destinationPort:I
     332: aconst_null
     333: aload         5
     335: aload         6
     337: aconst_null
     338: invokestatic  #14                 // Method org/jboss/ejb/client/remoting/NetworkUtil.connect:(Lorg/jboss/remoting3/Endpoint;Ljava/lang/String;Ljava/lang/String;ILjava/net/InetSocketAddress;Lorg/xnio/OptionMap;Ljavax/security/auth/callback/CallbackHandler;Ljavax/net/ssl/SSLContext;)Lorg/xnio/IoFuture;
     341: astore        7
     343: aload         7
     345: ldc2_w        #15                 // long 5000l
     348: getstatic     #17                 // Field java/util/concurrent/TimeUnit.MILLISECONDS:Ljava/util/concurrent/TimeUnit;
     351: invokestatic  #18                 // Method org/jboss/ejb/client/remoting/IoFutureHelper.get:(Lorg/xnio/IoFuture;JLjava/util/concurrent/TimeUnit;)Ljava/lang/Object;
     354: checkcast     #19                 // class org/jboss/remoting3/Connection
     357: astore_1
     358: new           #20                 // class org/jboss/as/ejb3/remote/RemotingConnectionClusterNodeManager$ClusterNodeReconnectHandler
     361: dup
     362: aload_0
     363: aload_0
     364: getfield      #5                  // Field destinationHost:Ljava/lang/String;
     367: aload_0
     368: getfield      #6                  // Field destinationPort:I
     371: aload         5
     373: aload         6
     375: aload_3
     376: ldc2_w        #15                 // long 5000l
     379: invokespecial #21                 // Method org/jboss/as/ejb3/remote/RemotingConnectionClusterNodeManager$ClusterNodeReconnectHandler."<init>":(Lorg/jboss/as/ejb3/remote/RemotingConnectionClusterNodeManager;Ljava/lang/String;ILorg/xnio/OptionMap;Ljavax/security/auth/callback/CallbackHandler;Lorg/xnio/OptionMap;J)V
     382: astore_2
     383: goto          411
     386: astore        5
     388: getstatic     #35                 // Field org/jboss/as/ejb3/logging/EjbLogger.REMOTE_LOGGER:Lorg/jboss/as/ejb3/logging/EjbLogger;
     391: aload         5
     393: aload_0
     394: getfield      #4                  // Field nodeName:Ljava/lang/String;
     397: aload_0
     398: getfield      #1                  // Field clusterContext:Lorg/jboss/ejb/client/ClusterContext;
     401: invokevirtual #11                 // Method org/jboss/ejb/client/ClusterContext.getClusterName:()Ljava/lang/String;
     404: invokeinterface #36,  4           // InterfaceMethod org/jboss/as/ejb3/logging/EjbLogger.couldNotCreateClusterConnection:(Ljava/lang/Throwable;Ljava/lang/String;Ljava/lang/String;)V
     409: aconst_null
     410: areturn
     411: new           #37                 // class org/jboss/ejb/client/remoting/RemotingConnectionEJBReceiver
     414: dup
     415: aload_1
     416: aload_2
     417: aload_3
     418: aload_0
     419: getfield      #7                  // Field destinationProtocol:Ljava/lang/String;
     422: invokespecial #38                 // Method org/jboss/ejb/client/remoting/RemotingConnectionEJBReceiver."<init>":(Lorg/jboss/remoting3/Connection;Lorg/jboss/ejb/client/remoting/ReconnectHandler;Lorg/xnio/OptionMap;Ljava/lang/String;)V
     425: areturn
    Exception table:
       from    to  target type
          16   383   386   Class java/lang/Exception

  static org.jboss.remoting3.Endpoint access$000(org.jboss.as.ejb3.remote.RemotingConnectionClusterNodeManager);
    Code:
       0: aload_0
       1: getfield      #2                  // Field endpoint:Lorg/jboss/remoting3/Endpoint;
       4: areturn

  static org.jboss.ejb.client.ClusterContext access$100(org.jboss.as.ejb3.remote.RemotingConnectionClusterNodeManager);
    Code:
       0: aload_0
       1: getfield      #1                  // Field clusterContext:Lorg/jboss/ejb/client/ClusterContext;
       4: areturn
}
