Compiled from "ThreadLocalRandom.java"
final class scala.concurrent.forkjoin.ThreadLocalRandom$1 extends java.lang.ThreadLocal<scala.concurrent.forkjoin.ThreadLocalRandom> {
  scala.concurrent.forkjoin.ThreadLocalRandom$1();
    Code:
       0: aload_0
       1: invokespecial #1                  // Method java/lang/ThreadLocal."<init>":()V
       4: return

  protected scala.concurrent.forkjoin.ThreadLocalRandom initialValue();
    Code:
       0: new           #2                  // class scala/concurrent/forkjoin/ThreadLocalRandom
       3: dup
       4: invokespecial #3                  // Method scala/concurrent/forkjoin/ThreadLocalRandom."<init>":()V
       7: areturn

  protected java.lang.Object initialValue();
    Code:
       0: aload_0
       1: invokevirtual #4                  // Method initialValue:()Lscala/concurrent/forkjoin/ThreadLocalRandom;
       4: areturn
}
