Compiled from "ResourceUDT.java"
public final class com.barchart.udt.ResourceUDT {
  public static final java.lang.String PACKAGE_NAME;

  public static final java.lang.String PROPERTY_LIBRARY_EXTRACT_LOCATION;

  public static final java.lang.String PROPERTY_LOADER_CLASS_NAME;

  public static final java.lang.String DEFAULT_LIBRARY_EXTRACT_LOCATION;

  public static final java.lang.String DEFAULT_LIBRARY_LOADER_CLASS;

  private com.barchart.udt.ResourceUDT();
    Code:
       0: aload_0
       1: invokespecial #1                  // Method java/lang/Object."<init>":()V
       4: return

  public static java.lang.String getLibraryExtractLocation();
    Code:
       0: getstatic     #2                  // Field PROPERTY_LIBRARY_EXTRACT_LOCATION:Ljava/lang/String;
       3: ldc           #3                  // String ./lib/bin
       5: invokestatic  #4                  // Method java/lang/System.getProperty:(Ljava/lang/String;Ljava/lang/String;)Ljava/lang/String;
       8: areturn

  public static void setLibraryExtractLocation(java.lang.String);
    Code:
       0: getstatic     #2                  // Field PROPERTY_LIBRARY_EXTRACT_LOCATION:Ljava/lang/String;
       3: aload_0
       4: invokestatic  #5                  // Method java/lang/System.setProperty:(Ljava/lang/String;Ljava/lang/String;)Ljava/lang/String;
       7: pop
       8: return

  public static java.lang.String getLibraryLoaderClassName();
    Code:
       0: getstatic     #6                  // Field PROPERTY_LOADER_CLASS_NAME:Ljava/lang/String;
       3: getstatic     #7                  // Field DEFAULT_LIBRARY_LOADER_CLASS:Ljava/lang/String;
       6: invokestatic  #4                  // Method java/lang/System.getProperty:(Ljava/lang/String;Ljava/lang/String;)Ljava/lang/String;
       9: areturn

  public static void setLibraryLoaderClassName(java.lang.String);
    Code:
       0: getstatic     #6                  // Field PROPERTY_LOADER_CLASS_NAME:Ljava/lang/String;
       3: aload_0
       4: invokestatic  #5                  // Method java/lang/System.setProperty:(Ljava/lang/String;Ljava/lang/String;)Ljava/lang/String;
       7: pop
       8: return

  static {};
    Code:
       0: ldc_w         #8                  // class com/barchart/udt/ResourceUDT
       3: invokevirtual #9                  // Method java/lang/Class.getPackage:()Ljava/lang/Package;
       6: invokevirtual #10                 // Method java/lang/Package.getName:()Ljava/lang/String;
       9: putstatic     #11                 // Field PACKAGE_NAME:Ljava/lang/String;
      12: new           #12                 // class java/lang/StringBuilder
      15: dup
      16: invokespecial #13                 // Method java/lang/StringBuilder."<init>":()V
      19: getstatic     #11                 // Field PACKAGE_NAME:Ljava/lang/String;
      22: invokevirtual #14                 // Method java/lang/StringBuilder.append:(Ljava/lang/String;)Ljava/lang/StringBuilder;
      25: ldc           #15                 // String .library.extract.location
      27: invokevirtual #14                 // Method java/lang/StringBuilder.append:(Ljava/lang/String;)Ljava/lang/StringBuilder;
      30: invokevirtual #16                 // Method java/lang/StringBuilder.toString:()Ljava/lang/String;
      33: putstatic     #2                  // Field PROPERTY_LIBRARY_EXTRACT_LOCATION:Ljava/lang/String;
      36: new           #12                 // class java/lang/StringBuilder
      39: dup
      40: invokespecial #13                 // Method java/lang/StringBuilder."<init>":()V
      43: getstatic     #11                 // Field PACKAGE_NAME:Ljava/lang/String;
      46: invokevirtual #14                 // Method java/lang/StringBuilder.append:(Ljava/lang/String;)Ljava/lang/StringBuilder;
      49: ldc           #17                 // String .loader.class.name
      51: invokevirtual #14                 // Method java/lang/StringBuilder.append:(Ljava/lang/String;)Ljava/lang/StringBuilder;
      54: invokevirtual #16                 // Method java/lang/StringBuilder.toString:()Ljava/lang/String;
      57: putstatic     #6                  // Field PROPERTY_LOADER_CLASS_NAME:Ljava/lang/String;
      60: ldc_w         #18                 // class com/barchart/udt/lib/LibraryLoaderUDT
      63: invokevirtual #19                 // Method java/lang/Class.getName:()Ljava/lang/String;
      66: putstatic     #7                  // Field DEFAULT_LIBRARY_LOADER_CLASS:Ljava/lang/String;
      69: return
}
