Compiled from "Parent.java"
class javafx.scene.Parent$5 {
  static final int[] $SwitchMap$com$sun$javafx$scene$LayoutFlags;

  static final int[] $SwitchMap$javafx$scene$AccessibleAttribute;

  static {};
    Code:
       0: invokestatic  #1                  // Method javafx/scene/AccessibleAttribute.values:()[Ljavafx/scene/AccessibleAttribute;
       3: arraylength
       4: newarray       int
       6: putstatic     #2                  // Field $SwitchMap$javafx$scene$AccessibleAttribute:[I
       9: getstatic     #2                  // Field $SwitchMap$javafx$scene$AccessibleAttribute:[I
      12: getstatic     #3                  // Field javafx/scene/AccessibleAttribute.CHILDREN:Ljavafx/scene/AccessibleAttribute;
      15: invokevirtual #4                  // Method javafx/scene/AccessibleAttribute.ordinal:()I
      18: iconst_1
      19: iastore
      20: goto          24
      23: astore_0
      24: invokestatic  #6                  // Method com/sun/javafx/scene/LayoutFlags.values:()[Lcom/sun/javafx/scene/LayoutFlags;
      27: arraylength
      28: newarray       int
      30: putstatic     #7                  // Field $SwitchMap$com$sun$javafx$scene$LayoutFlags:[I
      33: getstatic     #7                  // Field $SwitchMap$com$sun$javafx$scene$LayoutFlags:[I
      36: getstatic     #8                  // Field com/sun/javafx/scene/LayoutFlags.CLEAN:Lcom/sun/javafx/scene/LayoutFlags;
      39: invokevirtual #9                  // Method com/sun/javafx/scene/LayoutFlags.ordinal:()I
      42: iconst_1
      43: iastore
      44: goto          48
      47: astore_0
      48: getstatic     #7                  // Field $SwitchMap$com$sun$javafx$scene$LayoutFlags:[I
      51: getstatic     #10                 // Field com/sun/javafx/scene/LayoutFlags.NEEDS_LAYOUT:Lcom/sun/javafx/scene/LayoutFlags;
      54: invokevirtual #9                  // Method com/sun/javafx/scene/LayoutFlags.ordinal:()I
      57: iconst_2
      58: iastore
      59: goto          63
      62: astore_0
      63: getstatic     #7                  // Field $SwitchMap$com$sun$javafx$scene$LayoutFlags:[I
      66: getstatic     #11                 // Field com/sun/javafx/scene/LayoutFlags.DIRTY_BRANCH:Lcom/sun/javafx/scene/LayoutFlags;
      69: invokevirtual #9                  // Method com/sun/javafx/scene/LayoutFlags.ordinal:()I
      72: iconst_3
      73: iastore
      74: goto          78
      77: astore_0
      78: return
    Exception table:
       from    to  target type
           9    20    23   Class java/lang/NoSuchFieldError
          33    44    47   Class java/lang/NoSuchFieldError
          48    59    62   Class java/lang/NoSuchFieldError
          63    74    77   Class java/lang/NoSuchFieldError
}
