Compiled from "MethodRegistry.java"
public class net.bytebuddy.dynamic.scaffold.MethodRegistry$Default$Prepared implements net.bytebuddy.dynamic.scaffold.MethodRegistry$Prepared {
  private final java.util.LinkedHashMap<net.bytebuddy.description.method.MethodDescription, net.bytebuddy.dynamic.scaffold.MethodRegistry$Default$Prepared$Entry> implementations;

  private final net.bytebuddy.implementation.LoadedTypeInitializer loadedTypeInitializer;

  private final net.bytebuddy.dynamic.scaffold.TypeInitializer typeInitializer;

  private final net.bytebuddy.description.type.TypeDescription instrumentedType;

  private final net.bytebuddy.dynamic.scaffold.MethodGraph$Linked methodGraph;

  private final net.bytebuddy.description.method.MethodList<?> methods;

  protected net.bytebuddy.dynamic.scaffold.MethodRegistry$Default$Prepared(java.util.LinkedHashMap<net.bytebuddy.description.method.MethodDescription, net.bytebuddy.dynamic.scaffold.MethodRegistry$Default$Prepared$Entry>, net.bytebuddy.implementation.LoadedTypeInitializer, net.bytebuddy.dynamic.scaffold.TypeInitializer, net.bytebuddy.description.type.TypeDescription, net.bytebuddy.dynamic.scaffold.MethodGraph$Linked, net.bytebuddy.description.method.MethodList<?>);
    Code:
       0: aload_0
       1: invokespecial #85                 // Method java/lang/Object."<init>":()V
       4: aload_0
       5: aload_1
       6: putfield      #87                 // Field implementations:Ljava/util/LinkedHashMap;
       9: aload_0
      10: aload_2
      11: putfield      #89                 // Field loadedTypeInitializer:Lnet/bytebuddy/implementation/LoadedTypeInitializer;
      14: aload_0
      15: aload_3
      16: putfield      #91                 // Field typeInitializer:Lnet/bytebuddy/dynamic/scaffold/TypeInitializer;
      19: aload_0
      20: aload         4
      22: putfield      #93                 // Field instrumentedType:Lnet/bytebuddy/description/type/TypeDescription;
      25: aload_0
      26: aload         5
      28: putfield      #95                 // Field methodGraph:Lnet/bytebuddy/dynamic/scaffold/MethodGraph$Linked;
      31: aload_0
      32: aload         6
      34: putfield      #97                 // Field methods:Lnet/bytebuddy/description/method/MethodList;
      37: return

  public net.bytebuddy.description.type.TypeDescription getInstrumentedType();
    Code:
       0: aload_0
       1: getfield      #93                 // Field instrumentedType:Lnet/bytebuddy/description/type/TypeDescription;
       4: areturn

  public net.bytebuddy.implementation.LoadedTypeInitializer getLoadedTypeInitializer();
    Code:
       0: aload_0
       1: getfield      #89                 // Field loadedTypeInitializer:Lnet/bytebuddy/implementation/LoadedTypeInitializer;
       4: areturn

  public net.bytebuddy.dynamic.scaffold.TypeInitializer getTypeInitializer();
    Code:
       0: aload_0
       1: getfield      #91                 // Field typeInitializer:Lnet/bytebuddy/dynamic/scaffold/TypeInitializer;
       4: areturn

  public net.bytebuddy.description.method.MethodList<?> getMethods();
    Code:
       0: aload_0
       1: getfield      #97                 // Field methods:Lnet/bytebuddy/description/method/MethodList;
       4: areturn

  public net.bytebuddy.description.method.MethodList<?> getInstrumentedMethods();
    Code:
       0: new           #56                 // class net/bytebuddy/description/method/MethodList$Explicit
       3: dup
       4: new           #111                // class java/util/ArrayList
       7: dup
       8: aload_0
       9: getfield      #87                 // Field implementations:Ljava/util/LinkedHashMap;
      12: invokevirtual #117                // Method java/util/LinkedHashMap.keySet:()Ljava/util/Set;
      15: invokespecial #120                // Method java/util/ArrayList."<init>":(Ljava/util/Collection;)V
      18: invokespecial #123                // Method net/bytebuddy/description/method/MethodList$Explicit."<init>":(Ljava/util/List;)V
      21: invokestatic  #129                // Method net/bytebuddy/matcher/ElementMatchers.isTypeInitializer:()Lnet/bytebuddy/matcher/ElementMatcher$Junction;
      24: invokestatic  #133                // Method net/bytebuddy/matcher/ElementMatchers.not:(Lnet/bytebuddy/matcher/ElementMatcher;)Lnet/bytebuddy/matcher/ElementMatcher$Junction;
      27: invokevirtual #137                // Method net/bytebuddy/description/method/MethodList$Explicit.filter:(Lnet/bytebuddy/matcher/ElementMatcher;)Lnet/bytebuddy/matcher/FilterableList;
      30: checkcast     #58                 // class net/bytebuddy/description/method/MethodList
      33: areturn

  public net.bytebuddy.dynamic.scaffold.MethodRegistry$Compiled compile(net.bytebuddy.implementation.Implementation$Target$Factory, net.bytebuddy.ClassFileVersion);
    Code:
       0: new           #141                // class java/util/HashMap
       3: dup
       4: invokespecial #142                // Method java/util/HashMap."<init>":()V
       7: astore_3
       8: new           #141                // class java/util/HashMap
      11: dup
      12: invokespecial #142                // Method java/util/HashMap."<init>":()V
      15: astore        4
      17: new           #113                // class java/util/LinkedHashMap
      20: dup
      21: invokespecial #143                // Method java/util/LinkedHashMap."<init>":()V
      24: astore        5
      26: aload_1
      27: aload_0
      28: getfield      #93                 // Field instrumentedType:Lnet/bytebuddy/description/type/TypeDescription;
      31: aload_0
      32: getfield      #95                 // Field methodGraph:Lnet/bytebuddy/dynamic/scaffold/MethodGraph$Linked;
      35: aload_2
      36: invokeinterface #147,  4          // InterfaceMethod net/bytebuddy/implementation/Implementation$Target$Factory.make:(Lnet/bytebuddy/description/type/TypeDescription;Lnet/bytebuddy/dynamic/scaffold/MethodGraph$Linked;Lnet/bytebuddy/ClassFileVersion;)Lnet/bytebuddy/implementation/Implementation$Target;
      41: astore        6
      43: aload_0
      44: getfield      #87                 // Field implementations:Ljava/util/LinkedHashMap;
      47: invokevirtual #150                // Method java/util/LinkedHashMap.entrySet:()Ljava/util/Set;
      50: invokeinterface #156,  1          // InterfaceMethod java/util/Set.iterator:()Ljava/util/Iterator;
      55: astore        7
      57: aload         7
      59: invokeinterface #162,  1          // InterfaceMethod java/util/Iterator.hasNext:()Z
      64: ifeq          308
      67: aload         7
      69: invokeinterface #166,  1          // InterfaceMethod java/util/Iterator.next:()Ljava/lang/Object;
      74: checkcast     #39                 // class java/util/Map$Entry
      77: astore        8
      79: aload_3
      80: aload         8
      82: invokeinterface #169,  1          // InterfaceMethod java/util/Map$Entry.getValue:()Ljava/lang/Object;
      87: checkcast     #15                 // class net/bytebuddy/dynamic/scaffold/MethodRegistry$Default$Prepared$Entry
      90: invokevirtual #173                // Method net/bytebuddy/dynamic/scaffold/MethodRegistry$Default$Prepared$Entry.getHandler:()Lnet/bytebuddy/dynamic/scaffold/MethodRegistry$Handler;
      93: invokeinterface #177,  2          // InterfaceMethod java/util/Map.get:(Ljava/lang/Object;)Ljava/lang/Object;
      98: checkcast     #37                 // class net/bytebuddy/dynamic/scaffold/MethodRegistry$Handler$Compiled
     101: astore        9
     103: aload         9
     105: ifnonnull     152
     108: aload         8
     110: invokeinterface #169,  1          // InterfaceMethod java/util/Map$Entry.getValue:()Ljava/lang/Object;
     115: checkcast     #15                 // class net/bytebuddy/dynamic/scaffold/MethodRegistry$Default$Prepared$Entry
     118: invokevirtual #173                // Method net/bytebuddy/dynamic/scaffold/MethodRegistry$Default$Prepared$Entry.getHandler:()Lnet/bytebuddy/dynamic/scaffold/MethodRegistry$Handler;
     121: aload         6
     123: invokeinterface #180,  2          // InterfaceMethod net/bytebuddy/dynamic/scaffold/MethodRegistry$Handler.compile:(Lnet/bytebuddy/implementation/Implementation$Target;)Lnet/bytebuddy/dynamic/scaffold/MethodRegistry$Handler$Compiled;
     128: astore        9
     130: aload_3
     131: aload         8
     133: invokeinterface #169,  1          // InterfaceMethod java/util/Map$Entry.getValue:()Ljava/lang/Object;
     138: checkcast     #15                 // class net/bytebuddy/dynamic/scaffold/MethodRegistry$Default$Prepared$Entry
     141: invokevirtual #173                // Method net/bytebuddy/dynamic/scaffold/MethodRegistry$Default$Prepared$Entry.getHandler:()Lnet/bytebuddy/dynamic/scaffold/MethodRegistry$Handler;
     144: aload         9
     146: invokeinterface #184,  3          // InterfaceMethod java/util/Map.put:(Ljava/lang/Object;Ljava/lang/Object;)Ljava/lang/Object;
     151: pop
     152: aload         4
     154: aload         8
     156: invokeinterface #169,  1          // InterfaceMethod java/util/Map$Entry.getValue:()Ljava/lang/Object;
     161: checkcast     #15                 // class net/bytebuddy/dynamic/scaffold/MethodRegistry$Default$Prepared$Entry
     164: invokevirtual #188                // Method net/bytebuddy/dynamic/scaffold/MethodRegistry$Default$Prepared$Entry.getAppenderFactory:()Lnet/bytebuddy/implementation/attribute/MethodAttributeAppender$Factory;
     167: invokeinterface #177,  2          // InterfaceMethod java/util/Map.get:(Ljava/lang/Object;)Ljava/lang/Object;
     172: checkcast     #45                 // class net/bytebuddy/implementation/attribute/MethodAttributeAppender
     175: astore        10
     177: aload         10
     179: ifnonnull     229
     182: aload         8
     184: invokeinterface #169,  1          // InterfaceMethod java/util/Map$Entry.getValue:()Ljava/lang/Object;
     189: checkcast     #15                 // class net/bytebuddy/dynamic/scaffold/MethodRegistry$Default$Prepared$Entry
     192: invokevirtual #188                // Method net/bytebuddy/dynamic/scaffold/MethodRegistry$Default$Prepared$Entry.getAppenderFactory:()Lnet/bytebuddy/implementation/attribute/MethodAttributeAppender$Factory;
     195: aload_0
     196: getfield      #93                 // Field instrumentedType:Lnet/bytebuddy/description/type/TypeDescription;
     199: invokeinterface #191,  2          // InterfaceMethod net/bytebuddy/implementation/attribute/MethodAttributeAppender$Factory.make:(Lnet/bytebuddy/description/type/TypeDescription;)Lnet/bytebuddy/implementation/attribute/MethodAttributeAppender;
     204: astore        10
     206: aload         4
     208: aload         8
     210: invokeinterface #169,  1          // InterfaceMethod java/util/Map$Entry.getValue:()Ljava/lang/Object;
     215: checkcast     #15                 // class net/bytebuddy/dynamic/scaffold/MethodRegistry$Default$Prepared$Entry
     218: invokevirtual #188                // Method net/bytebuddy/dynamic/scaffold/MethodRegistry$Default$Prepared$Entry.getAppenderFactory:()Lnet/bytebuddy/implementation/attribute/MethodAttributeAppender$Factory;
     221: aload         10
     223: invokeinterface #184,  3          // InterfaceMethod java/util/Map.put:(Ljava/lang/Object;Ljava/lang/Object;)Ljava/lang/Object;
     228: pop
     229: aload         5
     231: aload         8
     233: invokeinterface #194,  1          // InterfaceMethod java/util/Map$Entry.getKey:()Ljava/lang/Object;
     238: new           #49                 // class net/bytebuddy/dynamic/scaffold/MethodRegistry$Default$Compiled$Entry
     241: dup
     242: aload         9
     244: aload         10
     246: aload         8
     248: invokeinterface #169,  1          // InterfaceMethod java/util/Map$Entry.getValue:()Ljava/lang/Object;
     253: checkcast     #15                 // class net/bytebuddy/dynamic/scaffold/MethodRegistry$Default$Prepared$Entry
     256: invokevirtual #198                // Method net/bytebuddy/dynamic/scaffold/MethodRegistry$Default$Prepared$Entry.getMethodDescription:()Lnet/bytebuddy/description/method/MethodDescription;
     259: aload         8
     261: invokeinterface #169,  1          // InterfaceMethod java/util/Map$Entry.getValue:()Ljava/lang/Object;
     266: checkcast     #15                 // class net/bytebuddy/dynamic/scaffold/MethodRegistry$Default$Prepared$Entry
     269: invokevirtual #201                // Method net/bytebuddy/dynamic/scaffold/MethodRegistry$Default$Prepared$Entry.resolveBridgeTypes:()Ljava/util/Set;
     272: aload         8
     274: invokeinterface #169,  1          // InterfaceMethod java/util/Map$Entry.getValue:()Ljava/lang/Object;
     279: checkcast     #15                 // class net/bytebuddy/dynamic/scaffold/MethodRegistry$Default$Prepared$Entry
     282: invokevirtual #205                // Method net/bytebuddy/dynamic/scaffold/MethodRegistry$Default$Prepared$Entry.getVisibility:()Lnet/bytebuddy/description/modifier/Visibility;
     285: aload         8
     287: invokeinterface #169,  1          // InterfaceMethod java/util/Map$Entry.getValue:()Ljava/lang/Object;
     292: checkcast     #15                 // class net/bytebuddy/dynamic/scaffold/MethodRegistry$Default$Prepared$Entry
     295: invokevirtual #208                // Method net/bytebuddy/dynamic/scaffold/MethodRegistry$Default$Prepared$Entry.isBridgeMethod:()Z
     298: invokespecial #211                // Method net/bytebuddy/dynamic/scaffold/MethodRegistry$Default$Compiled$Entry."<init>":(Lnet/bytebuddy/dynamic/scaffold/MethodRegistry$Handler$Compiled;Lnet/bytebuddy/implementation/attribute/MethodAttributeAppender;Lnet/bytebuddy/description/method/MethodDescription;Ljava/util/Set;Lnet/bytebuddy/description/modifier/Visibility;Z)V
     301: invokevirtual #212                // Method java/util/LinkedHashMap.put:(Ljava/lang/Object;Ljava/lang/Object;)Ljava/lang/Object;
     304: pop
     305: goto          57
     308: new           #47                 // class net/bytebuddy/dynamic/scaffold/MethodRegistry$Default$Compiled
     311: dup
     312: aload_0
     313: getfield      #93                 // Field instrumentedType:Lnet/bytebuddy/description/type/TypeDescription;
     316: aload_0
     317: getfield      #89                 // Field loadedTypeInitializer:Lnet/bytebuddy/implementation/LoadedTypeInitializer;
     320: aload_0
     321: getfield      #91                 // Field typeInitializer:Lnet/bytebuddy/dynamic/scaffold/TypeInitializer;
     324: aload_0
     325: getfield      #97                 // Field methods:Lnet/bytebuddy/description/method/MethodList;
     328: aload         5
     330: aload_2
     331: getstatic     #218                // Field net/bytebuddy/ClassFileVersion.JAVA_V5:Lnet/bytebuddy/ClassFileVersion;
     334: invokevirtual #222                // Method net/bytebuddy/ClassFileVersion.isAtLeast:(Lnet/bytebuddy/ClassFileVersion;)Z
     337: invokespecial #225                // Method net/bytebuddy/dynamic/scaffold/MethodRegistry$Default$Compiled."<init>":(Lnet/bytebuddy/description/type/TypeDescription;Lnet/bytebuddy/implementation/LoadedTypeInitializer;Lnet/bytebuddy/dynamic/scaffold/TypeInitializer;Lnet/bytebuddy/description/method/MethodList;Ljava/util/LinkedHashMap;Z)V
     340: areturn

  public boolean equals(java.lang.Object);
    Code:
       0: aload_0
       1: aload_1
       2: if_acmpne     7
       5: iconst_1
       6: ireturn
       7: aload_1
       8: ifnonnull     13
      11: iconst_0
      12: ireturn
      13: aload_0
      14: invokevirtual #250                // Method java/lang/Object.getClass:()Ljava/lang/Class;
      17: aload_1
      18: invokevirtual #250                // Method java/lang/Object.getClass:()Ljava/lang/Class;
      21: if_acmpeq     26
      24: iconst_0
      25: ireturn
      26: aload_0
      27: getfield      #87                 // Field implementations:Ljava/util/LinkedHashMap;
      30: aload_1
      31: checkcast     #2                  // class net/bytebuddy/dynamic/scaffold/MethodRegistry$Default$Prepared
      34: getfield      #87                 // Field implementations:Ljava/util/LinkedHashMap;
      37: invokevirtual #252                // Method java/util/LinkedHashMap.equals:(Ljava/lang/Object;)Z
      40: ifne          45
      43: iconst_0
      44: ireturn
      45: aload_0
      46: getfield      #89                 // Field loadedTypeInitializer:Lnet/bytebuddy/implementation/LoadedTypeInitializer;
      49: aload_1
      50: checkcast     #2                  // class net/bytebuddy/dynamic/scaffold/MethodRegistry$Default$Prepared
      53: getfield      #89                 // Field loadedTypeInitializer:Lnet/bytebuddy/implementation/LoadedTypeInitializer;
      56: invokevirtual #253                // Method java/lang/Object.equals:(Ljava/lang/Object;)Z
      59: ifne          64
      62: iconst_0
      63: ireturn
      64: aload_0
      65: getfield      #91                 // Field typeInitializer:Lnet/bytebuddy/dynamic/scaffold/TypeInitializer;
      68: aload_1
      69: checkcast     #2                  // class net/bytebuddy/dynamic/scaffold/MethodRegistry$Default$Prepared
      72: getfield      #91                 // Field typeInitializer:Lnet/bytebuddy/dynamic/scaffold/TypeInitializer;
      75: invokevirtual #253                // Method java/lang/Object.equals:(Ljava/lang/Object;)Z
      78: ifne          83
      81: iconst_0
      82: ireturn
      83: aload_0
      84: getfield      #93                 // Field instrumentedType:Lnet/bytebuddy/description/type/TypeDescription;
      87: aload_1
      88: checkcast     #2                  // class net/bytebuddy/dynamic/scaffold/MethodRegistry$Default$Prepared
      91: getfield      #93                 // Field instrumentedType:Lnet/bytebuddy/description/type/TypeDescription;
      94: invokevirtual #253                // Method java/lang/Object.equals:(Ljava/lang/Object;)Z
      97: ifne          102
     100: iconst_0
     101: ireturn
     102: aload_0
     103: getfield      #95                 // Field methodGraph:Lnet/bytebuddy/dynamic/scaffold/MethodGraph$Linked;
     106: aload_1
     107: checkcast     #2                  // class net/bytebuddy/dynamic/scaffold/MethodRegistry$Default$Prepared
     110: getfield      #95                 // Field methodGraph:Lnet/bytebuddy/dynamic/scaffold/MethodGraph$Linked;
     113: invokevirtual #253                // Method java/lang/Object.equals:(Ljava/lang/Object;)Z
     116: ifne          121
     119: iconst_0
     120: ireturn
     121: aload_0
     122: getfield      #97                 // Field methods:Lnet/bytebuddy/description/method/MethodList;
     125: aload_1
     126: checkcast     #2                  // class net/bytebuddy/dynamic/scaffold/MethodRegistry$Default$Prepared
     129: getfield      #97                 // Field methods:Lnet/bytebuddy/description/method/MethodList;
     132: invokevirtual #253                // Method java/lang/Object.equals:(Ljava/lang/Object;)Z
     135: ifne          140
     138: iconst_0
     139: ireturn
     140: iconst_1
     141: ireturn

  public int hashCode();
    Code:
       0: bipush        17
       2: bipush        31
       4: imul
       5: aload_0
       6: getfield      #87                 // Field implementations:Ljava/util/LinkedHashMap;
       9: invokevirtual #257                // Method java/util/LinkedHashMap.hashCode:()I
      12: iadd
      13: bipush        31
      15: imul
      16: aload_0
      17: getfield      #89                 // Field loadedTypeInitializer:Lnet/bytebuddy/implementation/LoadedTypeInitializer;
      20: invokevirtual #258                // Method java/lang/Object.hashCode:()I
      23: iadd
      24: bipush        31
      26: imul
      27: aload_0
      28: getfield      #91                 // Field typeInitializer:Lnet/bytebuddy/dynamic/scaffold/TypeInitializer;
      31: invokevirtual #258                // Method java/lang/Object.hashCode:()I
      34: iadd
      35: bipush        31
      37: imul
      38: aload_0
      39: getfield      #93                 // Field instrumentedType:Lnet/bytebuddy/description/type/TypeDescription;
      42: invokevirtual #258                // Method java/lang/Object.hashCode:()I
      45: iadd
      46: bipush        31
      48: imul
      49: aload_0
      50: getfield      #95                 // Field methodGraph:Lnet/bytebuddy/dynamic/scaffold/MethodGraph$Linked;
      53: invokevirtual #258                // Method java/lang/Object.hashCode:()I
      56: iadd
      57: bipush        31
      59: imul
      60: aload_0
      61: getfield      #97                 // Field methods:Lnet/bytebuddy/description/method/MethodList;
      64: invokevirtual #258                // Method java/lang/Object.hashCode:()I
      67: iadd
      68: ireturn
}
