Compiled from "MethodGraph.java"
public abstract class net.bytebuddy.dynamic.scaffold.MethodGraph$Compiler$Default$Key<S> {
  protected final java.lang.String internalName;

  protected final int parameterCount;

  protected net.bytebuddy.dynamic.scaffold.MethodGraph$Compiler$Default$Key(java.lang.String, int);
    Code:
       0: aload_0
       1: invokespecial #33                 // Method java/lang/Object."<init>":()V
       4: aload_0
       5: aload_1
       6: putfield      #35                 // Field internalName:Ljava/lang/String;
       9: aload_0
      10: iload_2
      11: putfield      #37                 // Field parameterCount:I
      14: return

  protected abstract java.util.Set<S> getIdentifiers();

  public int hashCode();
    Code:
       0: aload_0
       1: getfield      #35                 // Field internalName:Ljava/lang/String;
       4: invokevirtual #49                 // Method java/lang/String.hashCode:()I
       7: bipush        31
       9: aload_0
      10: getfield      #37                 // Field parameterCount:I
      13: imul
      14: iadd
      15: ireturn

  public boolean equals(java.lang.Object);
    Code:
       0: aload_0
       1: aload_1
       2: if_acmpne     7
       5: iconst_1
       6: ireturn
       7: aload_1
       8: instanceof    #2                  // class net/bytebuddy/dynamic/scaffold/MethodGraph$Compiler$Default$Key
      11: ifne          16
      14: iconst_0
      15: ireturn
      16: aload_1
      17: checkcast     #2                  // class net/bytebuddy/dynamic/scaffold/MethodGraph$Compiler$Default$Key
      20: astore_2
      21: aload_0
      22: getfield      #35                 // Field internalName:Ljava/lang/String;
      25: aload_2
      26: getfield      #35                 // Field internalName:Ljava/lang/String;
      29: invokevirtual #53                 // Method java/lang/String.equals:(Ljava/lang/Object;)Z
      32: ifeq          64
      35: aload_0
      36: getfield      #37                 // Field parameterCount:I
      39: aload_2
      40: getfield      #37                 // Field parameterCount:I
      43: if_icmpne     64
      46: aload_0
      47: invokevirtual #55                 // Method getIdentifiers:()Ljava/util/Set;
      50: aload_2
      51: invokevirtual #55                 // Method getIdentifiers:()Ljava/util/Set;
      54: invokestatic  #61                 // Method java/util/Collections.disjoint:(Ljava/util/Collection;Ljava/util/Collection;)Z
      57: ifne          64
      60: iconst_1
      61: goto          65
      64: iconst_0
      65: ireturn
}
