Compiled from "TypeWriter.java"
public class net.bytebuddy.dynamic.scaffold.TypeWriter$Default$ForInlining$WithFullProcessing$RedefinitionClassVisitor$AttributeObtainingFieldVisitor extends net.bytebuddy.jar.asm.FieldVisitor {
  private final net.bytebuddy.dynamic.scaffold.TypeWriter$FieldPool$Record record;

  final net.bytebuddy.dynamic.scaffold.TypeWriter$Default$ForInlining$WithFullProcessing$RedefinitionClassVisitor this$1;

  protected net.bytebuddy.dynamic.scaffold.TypeWriter$Default$ForInlining$WithFullProcessing$RedefinitionClassVisitor$AttributeObtainingFieldVisitor(net.bytebuddy.dynamic.scaffold.TypeWriter$Default$ForInlining$WithFullProcessing$RedefinitionClassVisitor, net.bytebuddy.jar.asm.FieldVisitor, net.bytebuddy.dynamic.scaffold.TypeWriter$FieldPool$Record);
    Code:
       0: aload_0
       1: aload_1
       2: putfield      #39                 // Field this$1:Lnet/bytebuddy/dynamic/scaffold/TypeWriter$Default$ForInlining$WithFullProcessing$RedefinitionClassVisitor;
       5: aload_0
       6: getstatic     #45                 // Field net/bytebuddy/utility/OpenedClassReader.ASM_API:I
       9: aload_2
      10: invokespecial #48                 // Method net/bytebuddy/jar/asm/FieldVisitor."<init>":(ILnet/bytebuddy/jar/asm/FieldVisitor;)V
      13: aload_0
      14: aload_3
      15: putfield      #50                 // Field record:Lnet/bytebuddy/dynamic/scaffold/TypeWriter$FieldPool$Record;
      18: return

  public net.bytebuddy.jar.asm.AnnotationVisitor visitTypeAnnotation(int, net.bytebuddy.jar.asm.TypePath, java.lang.String, boolean);
    Code:
       0: aload_0
       1: getfield      #39                 // Field this$1:Lnet/bytebuddy/dynamic/scaffold/TypeWriter$Default$ForInlining$WithFullProcessing$RedefinitionClassVisitor;
       4: getfield      #61                 // Field net/bytebuddy/dynamic/scaffold/TypeWriter$Default$ForInlining$WithFullProcessing$RedefinitionClassVisitor.this$0:Lnet/bytebuddy/dynamic/scaffold/TypeWriter$Default$ForInlining$WithFullProcessing;
       7: getfield      #65                 // Field net/bytebuddy/dynamic/scaffold/TypeWriter$Default$ForInlining$WithFullProcessing.annotationRetention:Lnet/bytebuddy/implementation/attribute/AnnotationRetention;
      10: invokevirtual #71                 // Method net/bytebuddy/implementation/attribute/AnnotationRetention.isEnabled:()Z
      13: ifeq          28
      16: aload_0
      17: iload_1
      18: aload_2
      19: aload_3
      20: iload         4
      22: invokespecial #73                 // Method net/bytebuddy/jar/asm/FieldVisitor.visitTypeAnnotation:(ILnet/bytebuddy/jar/asm/TypePath;Ljava/lang/String;Z)Lnet/bytebuddy/jar/asm/AnnotationVisitor;
      25: goto          31
      28: invokestatic  #77                 // Method net/bytebuddy/dynamic/scaffold/TypeWriter$Default$ForInlining.access$400:()Lnet/bytebuddy/jar/asm/AnnotationVisitor;
      31: areturn

  public net.bytebuddy.jar.asm.AnnotationVisitor visitAnnotation(java.lang.String, boolean);
    Code:
       0: aload_0
       1: getfield      #39                 // Field this$1:Lnet/bytebuddy/dynamic/scaffold/TypeWriter$Default$ForInlining$WithFullProcessing$RedefinitionClassVisitor;
       4: getfield      #61                 // Field net/bytebuddy/dynamic/scaffold/TypeWriter$Default$ForInlining$WithFullProcessing$RedefinitionClassVisitor.this$0:Lnet/bytebuddy/dynamic/scaffold/TypeWriter$Default$ForInlining$WithFullProcessing;
       7: getfield      #65                 // Field net/bytebuddy/dynamic/scaffold/TypeWriter$Default$ForInlining$WithFullProcessing.annotationRetention:Lnet/bytebuddy/implementation/attribute/AnnotationRetention;
      10: invokevirtual #71                 // Method net/bytebuddy/implementation/attribute/AnnotationRetention.isEnabled:()Z
      13: ifeq          25
      16: aload_0
      17: aload_1
      18: iload_2
      19: invokespecial #88                 // Method net/bytebuddy/jar/asm/FieldVisitor.visitAnnotation:(Ljava/lang/String;Z)Lnet/bytebuddy/jar/asm/AnnotationVisitor;
      22: goto          28
      25: invokestatic  #77                 // Method net/bytebuddy/dynamic/scaffold/TypeWriter$Default$ForInlining.access$400:()Lnet/bytebuddy/jar/asm/AnnotationVisitor;
      28: areturn

  public void visitEnd();
    Code:
       0: aload_0
       1: getfield      #50                 // Field record:Lnet/bytebuddy/dynamic/scaffold/TypeWriter$FieldPool$Record;
       4: aload_0
       5: getfield      #93                 // Field fv:Lnet/bytebuddy/jar/asm/FieldVisitor;
       8: aload_0
       9: getfield      #39                 // Field this$1:Lnet/bytebuddy/dynamic/scaffold/TypeWriter$Default$ForInlining$WithFullProcessing$RedefinitionClassVisitor;
      12: getfield      #61                 // Field net/bytebuddy/dynamic/scaffold/TypeWriter$Default$ForInlining$WithFullProcessing$RedefinitionClassVisitor.this$0:Lnet/bytebuddy/dynamic/scaffold/TypeWriter$Default$ForInlining$WithFullProcessing;
      15: getfield      #97                 // Field net/bytebuddy/dynamic/scaffold/TypeWriter$Default$ForInlining$WithFullProcessing.annotationValueFilterFactory:Lnet/bytebuddy/implementation/attribute/AnnotationValueFilter$Factory;
      18: invokeinterface #101,  3          // InterfaceMethod net/bytebuddy/dynamic/scaffold/TypeWriter$FieldPool$Record.apply:(Lnet/bytebuddy/jar/asm/FieldVisitor;Lnet/bytebuddy/implementation/attribute/AnnotationValueFilter$Factory;)V
      23: aload_0
      24: invokespecial #103                // Method net/bytebuddy/jar/asm/FieldVisitor.visitEnd:()V
      27: return
}
