Compiled from "ModifyWorkspacePropertiesRequest.java"
public interface software.amazon.awssdk.services.workspaces.model.ModifyWorkspacePropertiesRequest$Builder extends software.amazon.awssdk.services.workspaces.model.WorkSpacesRequest$Builder, software.amazon.awssdk.core.SdkPojo, software.amazon.awssdk.utils.builder.CopyableBuilder<software.amazon.awssdk.services.workspaces.model.ModifyWorkspacePropertiesRequest$Builder, software.amazon.awssdk.services.workspaces.model.ModifyWorkspacePropertiesRequest> {
  public abstract software.amazon.awssdk.services.workspaces.model.ModifyWorkspacePropertiesRequest$Builder workspaceId(java.lang.String);

  public abstract software.amazon.awssdk.services.workspaces.model.ModifyWorkspacePropertiesRequest$Builder workspaceProperties(software.amazon.awssdk.services.workspaces.model.WorkspaceProperties);

  public default software.amazon.awssdk.services.workspaces.model.ModifyWorkspacePropertiesRequest$Builder workspaceProperties(java.util.function.Consumer<software.amazon.awssdk.services.workspaces.model.WorkspaceProperties$Builder>);
    Code:
       0: aload_0
       1: invokestatic  #1                  // Method software/amazon/awssdk/services/workspaces/model/WorkspaceProperties.builder:()Lsoftware/amazon/awssdk/services/workspaces/model/WorkspaceProperties$Builder;
       4: aload_1
       5: invokeinterface #2,  2            // InterfaceMethod software/amazon/awssdk/services/workspaces/model/WorkspaceProperties$Builder.applyMutation:(Ljava/util/function/Consumer;)Lsoftware/amazon/awssdk/utils/builder/SdkBuilder;
      10: checkcast     #3                  // class software/amazon/awssdk/services/workspaces/model/WorkspaceProperties$Builder
      13: invokeinterface #4,  1            // InterfaceMethod software/amazon/awssdk/services/workspaces/model/WorkspaceProperties$Builder.build:()Ljava/lang/Object;
      18: checkcast     #5                  // class software/amazon/awssdk/services/workspaces/model/WorkspaceProperties
      21: invokeinterface #6,  2            // InterfaceMethod workspaceProperties:(Lsoftware/amazon/awssdk/services/workspaces/model/WorkspaceProperties;)Lsoftware/amazon/awssdk/services/workspaces/model/ModifyWorkspacePropertiesRequest$Builder;
      26: areturn

  public abstract software.amazon.awssdk.services.workspaces.model.ModifyWorkspacePropertiesRequest$Builder overrideConfiguration(software.amazon.awssdk.awscore.AwsRequestOverrideConfiguration);

  public abstract software.amazon.awssdk.services.workspaces.model.ModifyWorkspacePropertiesRequest$Builder overrideConfiguration(java.util.function.Consumer<software.amazon.awssdk.awscore.AwsRequestOverrideConfiguration$Builder>);

  public default software.amazon.awssdk.awscore.AwsRequest$Builder overrideConfiguration(java.util.function.Consumer);
    Code:
       0: aload_0
       1: aload_1
       2: invokeinterface #7,  2            // InterfaceMethod overrideConfiguration:(Ljava/util/function/Consumer;)Lsoftware/amazon/awssdk/services/workspaces/model/ModifyWorkspacePropertiesRequest$Builder;
       7: areturn

  public default software.amazon.awssdk.awscore.AwsRequest$Builder overrideConfiguration(software.amazon.awssdk.awscore.AwsRequestOverrideConfiguration);
    Code:
       0: aload_0
       1: aload_1
       2: invokeinterface #8,  2            // InterfaceMethod overrideConfiguration:(Lsoftware/amazon/awssdk/awscore/AwsRequestOverrideConfiguration;)Lsoftware/amazon/awssdk/services/workspaces/model/ModifyWorkspacePropertiesRequest$Builder;
       7: areturn
}
