Compiled from "WildFlySwarmClasspathConf.java"
public class org.wildfly.swarm.bootstrap.util.WildFlySwarmClasspathConf$Matcher {
  private org.wildfly.swarm.bootstrap.util.WildFlySwarmClasspathConf$Action action;

  public org.wildfly.swarm.bootstrap.util.WildFlySwarmClasspathConf$Matcher();
    Code:
       0: aload_0
       1: invokespecial #1                  // Method java/lang/Object."<init>":()V
       4: return

  void setAction(org.wildfly.swarm.bootstrap.util.WildFlySwarmClasspathConf$Action);
    Code:
       0: aload_0
       1: aload_1
       2: putfield      #2                  // Field action:Lorg/wildfly/swarm/bootstrap/util/WildFlySwarmClasspathConf$Action;
       5: return

  org.wildfly.swarm.bootstrap.util.WildFlySwarmClasspathConf$Action getAction();
    Code:
       0: aload_0
       1: getfield      #2                  // Field action:Lorg/wildfly/swarm/bootstrap/util/WildFlySwarmClasspathConf$Action;
       4: areturn

  boolean matches(java.util.jar.JarFile);
    Code:
       0: iconst_0
       1: ireturn

  boolean matches(java.lang.String, java.lang.String);
    Code:
       0: iconst_0
       1: ireturn
}
