Compiled from "PurgeOptions.java"
public class io.nats.client.PurgeOptions$Builder {
  private java.lang.String subject;

  private long seq;

  private long keep;

  public io.nats.client.PurgeOptions$Builder();
    Code:
       0: aload_0
       1: invokespecial #1                  // Method java/lang/Object."<init>":()V
       4: return

  public io.nats.client.PurgeOptions$Builder subject(java.lang.String);
    Code:
       0: aload_0
       1: aload_1
       2: putfield      #2                  // Field subject:Ljava/lang/String;
       5: aload_0
       6: areturn

  public io.nats.client.PurgeOptions$Builder seq(long);
    Code:
       0: aload_0
       1: lload_1
       2: putfield      #3                  // Field seq:J
       5: aload_0
       6: areturn

  public io.nats.client.PurgeOptions$Builder keep(long);
    Code:
       0: aload_0
       1: lload_1
       2: putfield      #4                  // Field keep:J
       5: aload_0
       6: areturn

  public io.nats.client.PurgeOptions build();
    Code:
       0: aload_0
       1: getfield      #2                  // Field subject:Ljava/lang/String;
       4: iconst_0
       5: invokestatic  #5                  // Method io/nats/client/support/Validator.validateSubject:(Ljava/lang/String;Z)Ljava/lang/String;
       8: pop
       9: aload_0
      10: getfield      #3                  // Field seq:J
      13: lconst_0
      14: lcmp
      15: ifle          37
      18: aload_0
      19: getfield      #4                  // Field keep:J
      22: lconst_0
      23: lcmp
      24: ifle          37
      27: new           #6                  // class java/lang/IllegalArgumentException
      30: dup
      31: ldc           #7                  // String seq and keep are mutually exclusive.
      33: invokespecial #8                  // Method java/lang/IllegalArgumentException."<init>":(Ljava/lang/String;)V
      36: athrow
      37: new           #9                  // class io/nats/client/PurgeOptions
      40: dup
      41: aload_0
      42: getfield      #2                  // Field subject:Ljava/lang/String;
      45: aload_0
      46: getfield      #3                  // Field seq:J
      49: aload_0
      50: getfield      #4                  // Field keep:J
      53: aconst_null
      54: invokespecial #10                 // Method io/nats/client/PurgeOptions."<init>":(Ljava/lang/String;JJLio/nats/client/PurgeOptions$1;)V
      57: areturn
}
