Compiled from "EJBComponentSuspendDeploymentUnitProcessor.java"
public class org.jboss.as.ejb3.deployment.processors.EJBComponentSuspendDeploymentUnitProcessor implements org.jboss.as.server.deployment.DeploymentUnitProcessor {
  public static final java.lang.String ENTRY_POINT_NAME;

  static final java.util.Set<org.jboss.as.ejb3.component.MethodIntf> INTERFACES;

  public org.jboss.as.ejb3.deployment.processors.EJBComponentSuspendDeploymentUnitProcessor();
    Code:
       0: aload_0
       1: invokespecial #1                  // Method java/lang/Object."<init>":()V
       4: return

  public void deploy(org.jboss.as.server.deployment.DeploymentPhaseContext);
    Code:
       0: aload_1
       1: invokeinterface #2,  1            // InterfaceMethod org/jboss/as/server/deployment/DeploymentPhaseContext.getDeploymentUnit:()Lorg/jboss/as/server/deployment/DeploymentUnit;
       6: astore_2
       7: aload_2
       8: invokestatic  #3                  // Method org/wildfly/extension/requestcontroller/RequestControllerActivationMarker.isRequestControllerEnabled:(Lorg/jboss/as/server/deployment/DeploymentUnit;)Z
      11: ifne          15
      14: return
      15: aload_2
      16: invokeinterface #4,  1            // InterfaceMethod org/jboss/as/server/deployment/DeploymentUnit.getParent:()Lorg/jboss/as/server/deployment/DeploymentUnit;
      21: ifnonnull     34
      24: aload_2
      25: invokeinterface #5,  1            // InterfaceMethod org/jboss/as/server/deployment/DeploymentUnit.getName:()Ljava/lang/String;
      30: astore_3
      31: goto          46
      34: aload_2
      35: invokeinterface #4,  1            // InterfaceMethod org/jboss/as/server/deployment/DeploymentUnit.getParent:()Lorg/jboss/as/server/deployment/DeploymentUnit;
      40: invokeinterface #5,  1            // InterfaceMethod org/jboss/as/server/deployment/DeploymentUnit.getName:()Ljava/lang/String;
      45: astore_3
      46: aload_2
      47: getstatic     #6                  // Field org/jboss/as/ee/component/Attachments.EE_MODULE_DESCRIPTION:Lorg/jboss/as/server/deployment/AttachmentKey;
      50: invokeinterface #7,  2            // InterfaceMethod org/jboss/as/server/deployment/DeploymentUnit.getAttachment:(Lorg/jboss/as/server/deployment/AttachmentKey;)Ljava/lang/Object;
      55: checkcast     #8                  // class org/jboss/as/ee/component/EEModuleDescription
      58: invokevirtual #9                  // Method org/jboss/as/ee/component/EEModuleDescription.getComponentDescriptions:()Ljava/util/Collection;
      61: invokeinterface #10,  1           // InterfaceMethod java/util/Collection.iterator:()Ljava/util/Iterator;
      66: astore        4
      68: aload         4
      70: invokeinterface #11,  1           // InterfaceMethod java/util/Iterator.hasNext:()Z
      75: ifeq          174
      78: aload         4
      80: invokeinterface #12,  1           // InterfaceMethod java/util/Iterator.next:()Ljava/lang/Object;
      85: checkcast     #13                 // class org/jboss/as/ee/component/ComponentDescription
      88: astore        5
      90: aload         5
      92: instanceof    #14                 // class org/jboss/as/ejb3/component/EJBComponentDescription
      95: ifeq          171
      98: new           #15                 // class java/lang/StringBuilder
     101: dup
     102: invokespecial #16                 // Method java/lang/StringBuilder."<init>":()V
     105: ldc           #18                 // String ejb.
     107: invokevirtual #19                 // Method java/lang/StringBuilder.append:(Ljava/lang/String;)Ljava/lang/StringBuilder;
     110: aload_2
     111: invokeinterface #5,  1            // InterfaceMethod org/jboss/as/server/deployment/DeploymentUnit.getName:()Ljava/lang/String;
     116: invokevirtual #19                 // Method java/lang/StringBuilder.append:(Ljava/lang/String;)Ljava/lang/StringBuilder;
     119: ldc           #20                 // String .
     121: invokevirtual #19                 // Method java/lang/StringBuilder.append:(Ljava/lang/String;)Ljava/lang/StringBuilder;
     124: aload         5
     126: invokevirtual #21                 // Method org/jboss/as/ee/component/ComponentDescription.getComponentName:()Ljava/lang/String;
     129: invokevirtual #19                 // Method java/lang/StringBuilder.append:(Ljava/lang/String;)Ljava/lang/StringBuilder;
     132: invokevirtual #22                 // Method java/lang/StringBuilder.toString:()Ljava/lang/String;
     135: astore        6
     137: aload_1
     138: invokeinterface #23,  1           // InterfaceMethod org/jboss/as/server/deployment/DeploymentPhaseContext.getServiceTarget:()Lorg/jboss/msc/service/ServiceTarget;
     143: aload_3
     144: aload         6
     146: invokestatic  #24                 // Method org/wildfly/extension/requestcontroller/ControlPointService.install:(Lorg/jboss/msc/service/ServiceTarget;Ljava/lang/String;Ljava/lang/String;)V
     149: aload         5
     151: invokevirtual #25                 // Method org/jboss/as/ee/component/ComponentDescription.getConfigurators:()Ljava/util/Deque;
     154: new           #26                 // class org/jboss/as/ejb3/deployment/processors/EJBComponentSuspendDeploymentUnitProcessor$1
     157: dup
     158: aload_0
     159: aload_3
     160: aload         6
     162: invokespecial #27                 // Method org/jboss/as/ejb3/deployment/processors/EJBComponentSuspendDeploymentUnitProcessor$1."<init>":(Lorg/jboss/as/ejb3/deployment/processors/EJBComponentSuspendDeploymentUnitProcessor;Ljava/lang/String;Ljava/lang/String;)V
     165: invokeinterface #28,  2           // InterfaceMethod java/util/Deque.add:(Ljava/lang/Object;)Z
     170: pop
     171: goto          68
     174: return

  public void undeploy(org.jboss.as.server.deployment.DeploymentUnit);
    Code:
       0: return

  static {};
    Code:
       0: getstatic     #29                 // Field org/jboss/as/ejb3/component/MethodIntf.REMOTE:Lorg/jboss/as/ejb3/component/MethodIntf;
       3: getstatic     #30                 // Field org/jboss/as/ejb3/component/MethodIntf.HOME:Lorg/jboss/as/ejb3/component/MethodIntf;
       6: getstatic     #31                 // Field org/jboss/as/ejb3/component/MethodIntf.MESSAGE_ENDPOINT:Lorg/jboss/as/ejb3/component/MethodIntf;
       9: invokestatic  #32                 // Method java/util/EnumSet.of:(Ljava/lang/Enum;Ljava/lang/Enum;Ljava/lang/Enum;)Ljava/util/EnumSet;
      12: putstatic     #33                 // Field INTERFACES:Ljava/util/Set;
      15: return
}
