Compiled from "EjbClientContextSetupProcessor.java"
final class org.jboss.as.ejb3.deployment.processors.EjbClientContextSetupProcessor$RegistractionService implements org.jboss.msc.service.Service<java.lang.Void> {
  private final org.jboss.modules.Module module;

  final org.jboss.msc.value.InjectedValue<org.jboss.as.ejb3.remote.TCCLEJBClientContextSelectorService> tcclEJBClientContextSelectorServiceController;

  final org.jboss.msc.value.InjectedValue<org.jboss.ejb.client.EJBClientContext> ejbClientContextInjectedValue;

  private org.jboss.as.ejb3.deployment.processors.EjbClientContextSetupProcessor$RegistractionService(org.jboss.modules.Module);
    Code:
       0: aload_0
       1: invokespecial #2                  // Method java/lang/Object."<init>":()V
       4: aload_0
       5: new           #3                  // class org/jboss/msc/value/InjectedValue
       8: dup
       9: invokespecial #4                  // Method org/jboss/msc/value/InjectedValue."<init>":()V
      12: putfield      #5                  // Field tcclEJBClientContextSelectorServiceController:Lorg/jboss/msc/value/InjectedValue;
      15: aload_0
      16: new           #3                  // class org/jboss/msc/value/InjectedValue
      19: dup
      20: invokespecial #4                  // Method org/jboss/msc/value/InjectedValue."<init>":()V
      23: putfield      #6                  // Field ejbClientContextInjectedValue:Lorg/jboss/msc/value/InjectedValue;
      26: aload_0
      27: aload_1
      28: putfield      #7                  // Field module:Lorg/jboss/modules/Module;
      31: return

  public void start(org.jboss.msc.service.StartContext) throws org.jboss.msc.service.StartException;
    Code:
       0: aload_0
       1: getfield      #6                  // Field ejbClientContextInjectedValue:Lorg/jboss/msc/value/InjectedValue;
       4: invokevirtual #8                  // Method org/jboss/msc/value/InjectedValue.getValue:()Ljava/lang/Object;
       7: checkcast     #9                  // class org/jboss/ejb/client/EJBClientContext
      10: astore_2
      11: aload_0
      12: getfield      #5                  // Field tcclEJBClientContextSelectorServiceController:Lorg/jboss/msc/value/InjectedValue;
      15: invokevirtual #8                  // Method org/jboss/msc/value/InjectedValue.getValue:()Ljava/lang/Object;
      18: checkcast     #10                 // class org/jboss/as/ejb3/remote/TCCLEJBClientContextSelectorService
      21: astore_3
      22: getstatic     #11                 // Field org/jboss/as/ejb3/logging/EjbLogger.DEPLOYMENT_LOGGER:Lorg/jboss/as/ejb3/logging/EjbLogger;
      25: ldc           #12                 // String Registering EJB client context %s for classloader %s
      27: aload_2
      28: aload_0
      29: getfield      #7                  // Field module:Lorg/jboss/modules/Module;
      32: invokevirtual #13                 // Method org/jboss/modules/Module.getClassLoader:()Lorg/jboss/modules/ModuleClassLoader;
      35: invokeinterface #14,  4           // InterfaceMethod org/jboss/as/ejb3/logging/EjbLogger.debugf:(Ljava/lang/String;Ljava/lang/Object;Ljava/lang/Object;)V
      40: aload_3
      41: aload_2
      42: aload_0
      43: getfield      #7                  // Field module:Lorg/jboss/modules/Module;
      46: invokevirtual #13                 // Method org/jboss/modules/Module.getClassLoader:()Lorg/jboss/modules/ModuleClassLoader;
      49: invokevirtual #15                 // Method org/jboss/as/ejb3/remote/TCCLEJBClientContextSelectorService.registerEJBClientContext:(Lorg/jboss/ejb/client/EJBClientContext;Ljava/lang/ClassLoader;)V
      52: return

  public void stop(org.jboss.msc.service.StopContext);
    Code:
       0: aload_0
       1: getfield      #5                  // Field tcclEJBClientContextSelectorServiceController:Lorg/jboss/msc/value/InjectedValue;
       4: invokevirtual #8                  // Method org/jboss/msc/value/InjectedValue.getValue:()Ljava/lang/Object;
       7: checkcast     #10                 // class org/jboss/as/ejb3/remote/TCCLEJBClientContextSelectorService
      10: astore_2
      11: getstatic     #11                 // Field org/jboss/as/ejb3/logging/EjbLogger.DEPLOYMENT_LOGGER:Lorg/jboss/as/ejb3/logging/EjbLogger;
      14: ldc           #16                 // String unRegistering EJB client context for classloader %s
      16: aload_0
      17: getfield      #7                  // Field module:Lorg/jboss/modules/Module;
      20: invokevirtual #13                 // Method org/jboss/modules/Module.getClassLoader:()Lorg/jboss/modules/ModuleClassLoader;
      23: invokeinterface #17,  3           // InterfaceMethod org/jboss/as/ejb3/logging/EjbLogger.debugf:(Ljava/lang/String;Ljava/lang/Object;)V
      28: aload_2
      29: aload_0
      30: getfield      #7                  // Field module:Lorg/jboss/modules/Module;
      33: invokevirtual #13                 // Method org/jboss/modules/Module.getClassLoader:()Lorg/jboss/modules/ModuleClassLoader;
      36: invokevirtual #18                 // Method org/jboss/as/ejb3/remote/TCCLEJBClientContextSelectorService.unRegisterEJBClientContext:(Ljava/lang/ClassLoader;)Lorg/jboss/ejb/client/EJBClientContext;
      39: pop
      40: return

  public java.lang.Void getValue() throws java.lang.IllegalStateException, java.lang.IllegalArgumentException;
    Code:
       0: aconst_null
       1: areturn

  public java.lang.Object getValue() throws java.lang.IllegalStateException, java.lang.IllegalArgumentException;
    Code:
       0: aload_0
       1: invokevirtual #19                 // Method getValue:()Ljava/lang/Void;
       4: areturn

  org.jboss.as.ejb3.deployment.processors.EjbClientContextSetupProcessor$RegistractionService(org.jboss.modules.Module, org.jboss.as.ejb3.deployment.processors.EjbClientContextSetupProcessor$1);
    Code:
       0: aload_0
       1: aload_1
       2: invokespecial #1                  // Method "<init>":(Lorg/jboss/modules/Module;)V
       5: return
}
