Compiled from "EjbJndiBindingsDeploymentUnitProcessor.java"
class org.jboss.as.ejb3.deployment.processors.EjbJndiBindingsDeploymentUnitProcessor$2$1 implements org.jboss.as.ee.component.DependencyConfigurator<org.jboss.msc.service.Service<org.jboss.as.ee.component.Component>> {
  final org.jboss.as.ejb3.deployment.processors.EjbJndiBindingsDeploymentUnitProcessor$2 this$1;

  org.jboss.as.ejb3.deployment.processors.EjbJndiBindingsDeploymentUnitProcessor$2$1(org.jboss.as.ejb3.deployment.processors.EjbJndiBindingsDeploymentUnitProcessor$2);
    Code:
       0: aload_0
       1: aload_1
       2: putfield      #1                  // Field this$1:Lorg/jboss/as/ejb3/deployment/processors/EjbJndiBindingsDeploymentUnitProcessor$2;
       5: aload_0
       6: invokespecial #2                  // Method java/lang/Object."<init>":()V
       9: return

  public void configureDependency(org.jboss.msc.service.ServiceBuilder<?>, org.jboss.msc.service.Service<org.jboss.as.ee.component.Component>) throws org.jboss.as.server.deployment.DeploymentUnitProcessingException;
    Code:
       0: aload_1
       1: aload_0
       2: getfield      #1                  // Field this$1:Lorg/jboss/as/ejb3/deployment/processors/EjbJndiBindingsDeploymentUnitProcessor$2;
       5: getfield      #3                  // Field org/jboss/as/ejb3/deployment/processors/EjbJndiBindingsDeploymentUnitProcessor$2.val$deploymentUnit:Lorg/jboss/as/server/deployment/DeploymentUnit;
       8: invokeinterface #4,  1            // InterfaceMethod org/jboss/as/server/deployment/DeploymentUnit.getParent:()Lorg/jboss/as/server/deployment/DeploymentUnit;
      13: ifnonnull     31
      16: aload_0
      17: getfield      #1                  // Field this$1:Lorg/jboss/as/ejb3/deployment/processors/EjbJndiBindingsDeploymentUnitProcessor$2;
      20: getfield      #3                  // Field org/jboss/as/ejb3/deployment/processors/EjbJndiBindingsDeploymentUnitProcessor$2.val$deploymentUnit:Lorg/jboss/as/server/deployment/DeploymentUnit;
      23: invokeinterface #5,  1            // InterfaceMethod org/jboss/as/server/deployment/DeploymentUnit.getName:()Ljava/lang/String;
      28: goto          48
      31: aload_0
      32: getfield      #1                  // Field this$1:Lorg/jboss/as/ejb3/deployment/processors/EjbJndiBindingsDeploymentUnitProcessor$2;
      35: getfield      #3                  // Field org/jboss/as/ejb3/deployment/processors/EjbJndiBindingsDeploymentUnitProcessor$2.val$deploymentUnit:Lorg/jboss/as/server/deployment/DeploymentUnit;
      38: invokeinterface #4,  1            // InterfaceMethod org/jboss/as/server/deployment/DeploymentUnit.getParent:()Lorg/jboss/as/server/deployment/DeploymentUnit;
      43: invokeinterface #5,  1            // InterfaceMethod org/jboss/as/server/deployment/DeploymentUnit.getName:()Ljava/lang/String;
      48: new           #6                  // class java/lang/StringBuilder
      51: dup
      52: invokespecial #7                  // Method java/lang/StringBuilder."<init>":()V
      55: ldc           #9                  // String ejb.
      57: invokevirtual #10                 // Method java/lang/StringBuilder.append:(Ljava/lang/String;)Ljava/lang/StringBuilder;
      60: aload_0
      61: getfield      #1                  // Field this$1:Lorg/jboss/as/ejb3/deployment/processors/EjbJndiBindingsDeploymentUnitProcessor$2;
      64: getfield      #3                  // Field org/jboss/as/ejb3/deployment/processors/EjbJndiBindingsDeploymentUnitProcessor$2.val$deploymentUnit:Lorg/jboss/as/server/deployment/DeploymentUnit;
      67: invokeinterface #5,  1            // InterfaceMethod org/jboss/as/server/deployment/DeploymentUnit.getName:()Ljava/lang/String;
      72: invokevirtual #10                 // Method java/lang/StringBuilder.append:(Ljava/lang/String;)Ljava/lang/StringBuilder;
      75: ldc           #11                 // String .
      77: invokevirtual #10                 // Method java/lang/StringBuilder.append:(Ljava/lang/String;)Ljava/lang/StringBuilder;
      80: aload_0
      81: getfield      #1                  // Field this$1:Lorg/jboss/as/ejb3/deployment/processors/EjbJndiBindingsDeploymentUnitProcessor$2;
      84: getfield      #12                 // Field org/jboss/as/ejb3/deployment/processors/EjbJndiBindingsDeploymentUnitProcessor$2.val$componentDescription:Lorg/jboss/as/ejb3/component/EJBComponentDescription;
      87: invokevirtual #13                 // Method org/jboss/as/ejb3/component/EJBComponentDescription.getComponentName:()Ljava/lang/String;
      90: invokevirtual #10                 // Method java/lang/StringBuilder.append:(Ljava/lang/String;)Ljava/lang/StringBuilder;
      93: invokevirtual #14                 // Method java/lang/StringBuilder.toString:()Ljava/lang/String;
      96: invokestatic  #15                 // Method org/wildfly/extension/requestcontroller/ControlPointService.serviceName:(Ljava/lang/String;Ljava/lang/String;)Lorg/jboss/msc/service/ServiceName;
      99: ldc           #16                 // class org/wildfly/extension/requestcontroller/ControlPoint
     101: aload_0
     102: getfield      #1                  // Field this$1:Lorg/jboss/as/ejb3/deployment/processors/EjbJndiBindingsDeploymentUnitProcessor$2;
     105: getfield      #17                 // Field org/jboss/as/ejb3/deployment/processors/EjbJndiBindingsDeploymentUnitProcessor$2.val$controlPointInjectedValue:Lorg/jboss/msc/value/InjectedValue;
     108: invokeinterface #18,  4           // InterfaceMethod org/jboss/msc/service/ServiceBuilder.addDependency:(Lorg/jboss/msc/service/ServiceName;Ljava/lang/Class;Lorg/jboss/msc/inject/Injector;)Lorg/jboss/msc/service/ServiceBuilder;
     113: pop
     114: return
}
