Compiled from "ValueDecoderFactory.java"
public final class org.codehaus.stax2.ri.typed.ValueDecoderFactory$BooleanDecoder extends org.codehaus.stax2.ri.typed.ValueDecoderFactory$DecoderBase {
  protected boolean mValue;

  public org.codehaus.stax2.ri.typed.ValueDecoderFactory$BooleanDecoder();
    Code:
       0: aload_0
       1: invokespecial #1                  // Method org/codehaus/stax2/ri/typed/ValueDecoderFactory$DecoderBase."<init>":()V
       4: return

  public java.lang.String getType();
    Code:
       0: ldc           #2                  // String boolean
       2: areturn

  public boolean getValue();
    Code:
       0: aload_0
       1: getfield      #3                  // Field mValue:Z
       4: ireturn

  public void decode(java.lang.String) throws java.lang.IllegalArgumentException;
    Code:
       0: aload_1
       1: invokevirtual #4                  // Method java/lang/String.length:()I
       4: istore_2
       5: aload_1
       6: iconst_0
       7: invokevirtual #5                  // Method java/lang/String.charAt:(I)C
      10: istore_3
      11: iload_3
      12: bipush        116
      14: if_icmpne     58
      17: iload_2
      18: iconst_4
      19: if_icmpne     149
      22: aload_1
      23: iconst_1
      24: invokevirtual #5                  // Method java/lang/String.charAt:(I)C
      27: bipush        114
      29: if_icmpne     149
      32: aload_1
      33: iconst_2
      34: invokevirtual #5                  // Method java/lang/String.charAt:(I)C
      37: bipush        117
      39: if_icmpne     149
      42: aload_1
      43: iconst_3
      44: invokevirtual #5                  // Method java/lang/String.charAt:(I)C
      47: bipush        101
      49: if_icmpne     149
      52: aload_0
      53: iconst_1
      54: putfield      #3                  // Field mValue:Z
      57: return
      58: iload_3
      59: bipush        102
      61: if_icmpne     115
      64: iload_2
      65: iconst_5
      66: if_icmpne     149
      69: aload_1
      70: iconst_1
      71: invokevirtual #5                  // Method java/lang/String.charAt:(I)C
      74: bipush        97
      76: if_icmpne     149
      79: aload_1
      80: iconst_2
      81: invokevirtual #5                  // Method java/lang/String.charAt:(I)C
      84: bipush        108
      86: if_icmpne     149
      89: aload_1
      90: iconst_3
      91: invokevirtual #5                  // Method java/lang/String.charAt:(I)C
      94: bipush        115
      96: if_icmpne     149
      99: aload_1
     100: iconst_4
     101: invokevirtual #5                  // Method java/lang/String.charAt:(I)C
     104: bipush        101
     106: if_icmpne     149
     109: aload_0
     110: iconst_0
     111: putfield      #3                  // Field mValue:Z
     114: return
     115: iload_3
     116: bipush        48
     118: if_icmpne     132
     121: iload_2
     122: iconst_1
     123: if_icmpne     149
     126: aload_0
     127: iconst_0
     128: putfield      #3                  // Field mValue:Z
     131: return
     132: iload_3
     133: bipush        49
     135: if_icmpne     149
     138: iload_2
     139: iconst_1
     140: if_icmpne     149
     143: aload_0
     144: iconst_1
     145: putfield      #3                  // Field mValue:Z
     148: return
     149: aload_0
     150: aload_1
     151: invokevirtual #6                  // Method constructInvalidValue:(Ljava/lang/String;)Ljava/lang/IllegalArgumentException;
     154: athrow

  public void decode(char[], int, int) throws java.lang.IllegalArgumentException;
    Code:
       0: iload_3
       1: iload_2
       2: isub
       3: istore        4
       5: aload_1
       6: iload_2
       7: caload
       8: istore        5
      10: iload         5
      12: bipush        116
      14: if_icmpne     59
      17: iload         4
      19: iconst_4
      20: if_icmpne     156
      23: aload_1
      24: iload_2
      25: iconst_1
      26: iadd
      27: caload
      28: bipush        114
      30: if_icmpne     156
      33: aload_1
      34: iload_2
      35: iconst_2
      36: iadd
      37: caload
      38: bipush        117
      40: if_icmpne     156
      43: aload_1
      44: iload_2
      45: iconst_3
      46: iadd
      47: caload
      48: bipush        101
      50: if_icmpne     156
      53: aload_0
      54: iconst_1
      55: putfield      #3                  // Field mValue:Z
      58: return
      59: iload         5
      61: bipush        102
      63: if_icmpne     118
      66: iload         4
      68: iconst_5
      69: if_icmpne     156
      72: aload_1
      73: iload_2
      74: iconst_1
      75: iadd
      76: caload
      77: bipush        97
      79: if_icmpne     156
      82: aload_1
      83: iload_2
      84: iconst_2
      85: iadd
      86: caload
      87: bipush        108
      89: if_icmpne     156
      92: aload_1
      93: iload_2
      94: iconst_3
      95: iadd
      96: caload
      97: bipush        115
      99: if_icmpne     156
     102: aload_1
     103: iload_2
     104: iconst_4
     105: iadd
     106: caload
     107: bipush        101
     109: if_icmpne     156
     112: aload_0
     113: iconst_0
     114: putfield      #3                  // Field mValue:Z
     117: return
     118: iload         5
     120: bipush        48
     122: if_icmpne     137
     125: iload         4
     127: iconst_1
     128: if_icmpne     156
     131: aload_0
     132: iconst_0
     133: putfield      #3                  // Field mValue:Z
     136: return
     137: iload         5
     139: bipush        49
     141: if_icmpne     156
     144: iload         4
     146: iconst_1
     147: if_icmpne     156
     150: aload_0
     151: iconst_1
     152: putfield      #3                  // Field mValue:Z
     155: return
     156: aload_0
     157: aload_1
     158: iload_2
     159: iload_3
     160: invokevirtual #7                  // Method constructInvalidValue:([CII)Ljava/lang/IllegalArgumentException;
     163: athrow
}
