Compiled from "NexusUtils.java"
public class org.sonatype.nexus.plugins.p2.repository.internal.NexusUtils {
  private static final java.lang.String GENERATED_AT_ATTRIBUTE;

  private static final java.lang.String DOT;

  private org.sonatype.nexus.plugins.p2.repository.internal.NexusUtils();
    Code:
       0: aload_0
       1: invokespecial #1                  // Method java/lang/Object."<init>":()V
       4: return

  static java.io.File retrieveFile(org.sonatype.nexus.proxy.repository.Repository, java.lang.String) throws org.sonatype.nexus.proxy.LocalStorageException;
    Code:
       0: new           #2                  // class org/sonatype/nexus/proxy/ResourceStoreRequest
       3: dup
       4: aload_1
       5: invokespecial #3                  // Method org/sonatype/nexus/proxy/ResourceStoreRequest."<init>":(Ljava/lang/String;)V
       8: astore_2
       9: aload_0
      10: invokeinterface #4,  1            // InterfaceMethod org/sonatype/nexus/proxy/repository/Repository.getLocalStorage:()Lorg/sonatype/nexus/proxy/storage/local/LocalRepositoryStorage;
      15: checkcast     #5                  // class org/sonatype/nexus/proxy/storage/local/fs/DefaultFSLocalRepositoryStorage
      18: aload_0
      19: aload_2
      20: invokevirtual #6                  // Method org/sonatype/nexus/proxy/storage/local/fs/DefaultFSLocalRepositoryStorage.getFileFromBase:(Lorg/sonatype/nexus/proxy/repository/Repository;Lorg/sonatype/nexus/proxy/ResourceStoreRequest;)Ljava/io/File;
      23: astore_3
      24: aload_3
      25: areturn

  static java.io.File safeRetrieveFile(org.sonatype.nexus.proxy.repository.Repository, java.lang.String);
    Code:
       0: aload_0
       1: aload_1
       2: invokestatic  #7                  // Method retrieveFile:(Lorg/sonatype/nexus/proxy/repository/Repository;Ljava/lang/String;)Ljava/io/File;
       5: areturn
       6: astore_2
       7: aconst_null
       8: areturn
    Exception table:
       from    to  target type
           0     5     6   Class org/sonatype/nexus/proxy/LocalStorageException

  static org.sonatype.nexus.proxy.item.StorageItem retrieveItem(org.sonatype.nexus.proxy.repository.Repository, java.lang.String) throws java.lang.Exception;
    Code:
       0: new           #2                  // class org/sonatype/nexus/proxy/ResourceStoreRequest
       3: dup
       4: aload_1
       5: invokespecial #3                  // Method org/sonatype/nexus/proxy/ResourceStoreRequest."<init>":(Ljava/lang/String;)V
       8: astore_2
       9: aload_0
      10: aload_2
      11: invokeinterface #9,  2            // InterfaceMethod org/sonatype/nexus/proxy/repository/Repository.retrieveItem:(Lorg/sonatype/nexus/proxy/ResourceStoreRequest;)Lorg/sonatype/nexus/proxy/item/StorageItem;
      16: astore_3
      17: aload_3
      18: areturn

  static org.sonatype.nexus.proxy.item.StorageItem safeRetrieveItem(org.sonatype.nexus.proxy.repository.Repository, java.lang.String);
    Code:
       0: aload_0
       1: aload_1
       2: invokestatic  #10                 // Method retrieveItem:(Lorg/sonatype/nexus/proxy/repository/Repository;Ljava/lang/String;)Lorg/sonatype/nexus/proxy/item/StorageItem;
       5: areturn
       6: astore_2
       7: aconst_null
       8: areturn
    Exception table:
       from    to  target type
           0     5     6   Class java/lang/Exception

  public static void storeItem(org.sonatype.nexus.proxy.repository.Repository, org.sonatype.nexus.proxy.ResourceStoreRequest, java.io.InputStream, java.lang.String, java.util.Map<java.lang.String, java.lang.String>) throws java.lang.Exception;
    Code:
       0: new           #12                 // class org/sonatype/nexus/proxy/item/DefaultStorageFileItem
       3: dup
       4: aload_0
       5: aload_1
       6: iconst_1
       7: iconst_1
       8: new           #13                 // class org/sonatype/nexus/proxy/item/PreparedContentLocator
      11: dup
      12: aload_2
      13: aload_3
      14: ldc2_w        #15                 // long -1l
      17: invokespecial #17                 // Method org/sonatype/nexus/proxy/item/PreparedContentLocator."<init>":(Ljava/io/InputStream;Ljava/lang/String;J)V
      20: invokespecial #18                 // Method org/sonatype/nexus/proxy/item/DefaultStorageFileItem."<init>":(Lorg/sonatype/nexus/proxy/repository/Repository;Lorg/sonatype/nexus/proxy/ResourceStoreRequest;ZZLorg/sonatype/nexus/proxy/item/ContentLocator;)V
      23: astore        5
      25: aload         4
      27: ifnull        42
      30: aload         5
      32: invokevirtual #19                 // Method org/sonatype/nexus/proxy/item/DefaultStorageFileItem.getRepositoryItemAttributes:()Lorg/sonatype/nexus/proxy/attributes/Attributes;
      35: aload         4
      37: invokeinterface #20,  2           // InterfaceMethod org/sonatype/nexus/proxy/attributes/Attributes.putAll:(Ljava/util/Map;)V
      42: aload_0
      43: iconst_0
      44: aload         5
      46: invokeinterface #21,  3           // InterfaceMethod org/sonatype/nexus/proxy/repository/Repository.storeItem:(ZLorg/sonatype/nexus/proxy/item/StorageItem;)V
      51: return

  static void createLink(org.sonatype.nexus.proxy.repository.Repository, org.sonatype.nexus.proxy.item.StorageItem, java.lang.String) throws java.lang.Exception;
    Code:
       0: new           #2                  // class org/sonatype/nexus/proxy/ResourceStoreRequest
       3: dup
       4: aload_2
       5: invokespecial #3                  // Method org/sonatype/nexus/proxy/ResourceStoreRequest."<init>":(Ljava/lang/String;)V
       8: astore_3
       9: aload_3
      10: invokevirtual #22                 // Method org/sonatype/nexus/proxy/ResourceStoreRequest.getRequestContext:()Lorg/sonatype/nexus/proxy/RequestContext;
      13: aload_1
      14: invokeinterface #23,  1           // InterfaceMethod org/sonatype/nexus/proxy/item/StorageItem.getItemContext:()Lorg/sonatype/nexus/proxy/RequestContext;
      19: invokevirtual #24                 // Method org/sonatype/nexus/proxy/RequestContext.setParentContext:(Lorg/sonatype/nexus/proxy/RequestContext;)V
      22: new           #25                 // class org/sonatype/nexus/proxy/item/DefaultStorageLinkItem
      25: dup
      26: aload_0
      27: aload_3
      28: iconst_1
      29: iconst_1
      30: aload_1
      31: invokeinterface #26,  1           // InterfaceMethod org/sonatype/nexus/proxy/item/StorageItem.getRepositoryItemUid:()Lorg/sonatype/nexus/proxy/item/RepositoryItemUid;
      36: invokespecial #27                 // Method org/sonatype/nexus/proxy/item/DefaultStorageLinkItem."<init>":(Lorg/sonatype/nexus/proxy/repository/Repository;Lorg/sonatype/nexus/proxy/ResourceStoreRequest;ZZLorg/sonatype/nexus/proxy/item/RepositoryItemUid;)V
      39: astore        4
      41: aload_0
      42: iconst_0
      43: aload         4
      45: invokeinterface #21,  3           // InterfaceMethod org/sonatype/nexus/proxy/repository/Repository.storeItem:(ZLorg/sonatype/nexus/proxy/item/StorageItem;)V
      50: return

  static java.io.File localStorageOfRepositoryAsFile(org.sonatype.nexus.proxy.repository.Repository) throws org.sonatype.nexus.proxy.LocalStorageException;
    Code:
       0: aload_0
       1: invokeinterface #28,  1           // InterfaceMethod org/sonatype/nexus/proxy/repository/Repository.getLocalUrl:()Ljava/lang/String;
       6: ifnull        46
       9: aload_0
      10: invokeinterface #4,  1            // InterfaceMethod org/sonatype/nexus/proxy/repository/Repository.getLocalStorage:()Lorg/sonatype/nexus/proxy/storage/local/LocalRepositoryStorage;
      15: instanceof    #5                  // class org/sonatype/nexus/proxy/storage/local/fs/DefaultFSLocalRepositoryStorage
      18: ifeq          46
      21: aload_0
      22: invokeinterface #4,  1            // InterfaceMethod org/sonatype/nexus/proxy/repository/Repository.getLocalStorage:()Lorg/sonatype/nexus/proxy/storage/local/LocalRepositoryStorage;
      27: checkcast     #5                  // class org/sonatype/nexus/proxy/storage/local/fs/DefaultFSLocalRepositoryStorage
      30: aload_0
      31: new           #2                  // class org/sonatype/nexus/proxy/ResourceStoreRequest
      34: dup
      35: ldc           #30                 // String /
      37: invokespecial #3                  // Method org/sonatype/nexus/proxy/ResourceStoreRequest."<init>":(Ljava/lang/String;)V
      40: invokevirtual #31                 // Method org/sonatype/nexus/proxy/storage/local/fs/DefaultFSLocalRepositoryStorage.getBaseDir:(Lorg/sonatype/nexus/proxy/repository/Repository;Lorg/sonatype/nexus/proxy/ResourceStoreRequest;)Ljava/io/File;
      43: astore_1
      44: aload_1
      45: areturn
      46: new           #8                  // class org/sonatype/nexus/proxy/LocalStorageException
      49: dup
      50: ldc           #32                 // String Repository [%s] does not have an local storage
      52: iconst_1
      53: anewarray     #33                 // class java/lang/Object
      56: dup
      57: iconst_0
      58: aload_0
      59: invokeinterface #34,  1           // InterfaceMethod org/sonatype/nexus/proxy/repository/Repository.getId:()Ljava/lang/String;
      64: aastore
      65: invokestatic  #35                 // Method java/lang/String.format:(Ljava/lang/String;[Ljava/lang/Object;)Ljava/lang/String;
      68: invokespecial #36                 // Method org/sonatype/nexus/proxy/LocalStorageException."<init>":(Ljava/lang/String;)V
      71: athrow

  static java.lang.String getRelativePath(java.io.File, java.io.File);
    Code:
       0: aload_0
       1: invokestatic  #37                 // Method getReversePathSegments:(Ljava/io/File;)[Ljava/lang/String;
       4: astore_2
       5: aload_1
       6: invokestatic  #37                 // Method getReversePathSegments:(Ljava/io/File;)[Ljava/lang/String;
       9: astore_3
      10: ldc           #38                 // String
      12: astore        4
      14: aload_2
      15: arraylength
      16: iconst_1
      17: isub
      18: istore        5
      20: aload_3
      21: arraylength
      22: iconst_1
      23: isub
      24: istore        6
      26: iload         5
      28: iflt          59
      31: iload         6
      33: iflt          59
      36: aload_2
      37: iload         5
      39: aaload
      40: aload_3
      41: iload         6
      43: aaload
      44: invokevirtual #39                 // Method java/lang/String.equals:(Ljava/lang/Object;)Z
      47: ifeq          59
      50: iinc          5, -1
      53: iinc          6, -1
      56: goto          26
      59: iload         5
      61: iflt          98
      64: new           #40                 // class java/lang/StringBuilder
      67: dup
      68: invokespecial #41                 // Method java/lang/StringBuilder."<init>":()V
      71: aload         4
      73: invokevirtual #42                 // Method java/lang/StringBuilder.append:(Ljava/lang/String;)Ljava/lang/StringBuilder;
      76: ldc           #43                 // String ..
      78: invokevirtual #42                 // Method java/lang/StringBuilder.append:(Ljava/lang/String;)Ljava/lang/StringBuilder;
      81: getstatic     #44                 // Field java/io/File.separator:Ljava/lang/String;
      84: invokevirtual #42                 // Method java/lang/StringBuilder.append:(Ljava/lang/String;)Ljava/lang/StringBuilder;
      87: invokevirtual #45                 // Method java/lang/StringBuilder.toString:()Ljava/lang/String;
      90: astore        4
      92: iinc          5, -1
      95: goto          59
      98: iload         6
     100: iconst_1
     101: if_icmplt     140
     104: new           #40                 // class java/lang/StringBuilder
     107: dup
     108: invokespecial #41                 // Method java/lang/StringBuilder."<init>":()V
     111: aload         4
     113: invokevirtual #42                 // Method java/lang/StringBuilder.append:(Ljava/lang/String;)Ljava/lang/StringBuilder;
     116: aload_3
     117: iload         6
     119: aaload
     120: invokevirtual #42                 // Method java/lang/StringBuilder.append:(Ljava/lang/String;)Ljava/lang/StringBuilder;
     123: getstatic     #44                 // Field java/io/File.separator:Ljava/lang/String;
     126: invokevirtual #42                 // Method java/lang/StringBuilder.append:(Ljava/lang/String;)Ljava/lang/StringBuilder;
     129: invokevirtual #45                 // Method java/lang/StringBuilder.toString:()Ljava/lang/String;
     132: astore        4
     134: iinc          6, -1
     137: goto          98
     140: new           #40                 // class java/lang/StringBuilder
     143: dup
     144: invokespecial #41                 // Method java/lang/StringBuilder."<init>":()V
     147: aload         4
     149: invokevirtual #42                 // Method java/lang/StringBuilder.append:(Ljava/lang/String;)Ljava/lang/StringBuilder;
     152: aload_3
     153: iload         6
     155: aaload
     156: invokevirtual #42                 // Method java/lang/StringBuilder.append:(Ljava/lang/String;)Ljava/lang/StringBuilder;
     159: invokevirtual #45                 // Method java/lang/StringBuilder.toString:()Ljava/lang/String;
     162: astore        4
     164: aload         4
     166: areturn

  static boolean isHidden(java.lang.String);
    Code:
       0: aload_0
       1: ifnonnull     6
       4: iconst_0
       5: ireturn
       6: aload_0
       7: ldc           #47                 // String .
       9: invokevirtual #48                 // Method java/lang/String.startsWith:(Ljava/lang/String;)Z
      12: ifne          52
      15: aload_0
      16: ldc           #49                 // String /.
      18: invokevirtual #48                 // Method java/lang/String.startsWith:(Ljava/lang/String;)Z
      21: ifne          52
      24: aload_0
      25: new           #40                 // class java/lang/StringBuilder
      28: dup
      29: invokespecial #41                 // Method java/lang/StringBuilder."<init>":()V
      32: getstatic     #44                 // Field java/io/File.separator:Ljava/lang/String;
      35: invokevirtual #42                 // Method java/lang/StringBuilder.append:(Ljava/lang/String;)Ljava/lang/StringBuilder;
      38: ldc           #47                 // String .
      40: invokevirtual #42                 // Method java/lang/StringBuilder.append:(Ljava/lang/String;)Ljava/lang/StringBuilder;
      43: invokevirtual #45                 // Method java/lang/StringBuilder.toString:()Ljava/lang/String;
      46: invokevirtual #48                 // Method java/lang/String.startsWith:(Ljava/lang/String;)Z
      49: ifeq          56
      52: iconst_1
      53: goto          57
      56: iconst_0
      57: ireturn

  public static java.io.File createTemporaryP2Repository() throws java.io.IOException;
    Code:
       0: ldc           #50                 // String nexus-p2-repository-plugin
       2: ldc           #38                 // String
       4: invokestatic  #51                 // Method java/io/File.createTempFile:(Ljava/lang/String;Ljava/lang/String;)Ljava/io/File;
       7: astore_0
       8: aload_0
       9: invokevirtual #52                 // Method java/io/File.toPath:()Ljava/nio/file/Path;
      12: invokestatic  #53                 // Method org/sonatype/nexus/util/file/DirSupport.delete:(Ljava/nio/file/Path;)V
      15: aload_0
      16: invokevirtual #52                 // Method java/io/File.toPath:()Ljava/nio/file/Path;
      19: invokestatic  #54                 // Method org/sonatype/nexus/util/file/DirSupport.mkdir:(Ljava/nio/file/Path;)V
      22: aload_0
      23: areturn

  public static void storeItemFromFile(java.lang.String, java.io.File, org.sonatype.nexus.proxy.repository.Repository, java.lang.String) throws java.lang.Exception;
    Code:
       0: new           #55                 // class java/io/FileInputStream
       3: dup
       4: aload_1
       5: invokespecial #56                 // Method java/io/FileInputStream."<init>":(Ljava/io/File;)V
       8: astore        4
      10: aconst_null
      11: astore        5
      13: new           #57                 // class java/util/HashMap
      16: dup
      17: invokespecial #58                 // Method java/util/HashMap."<init>":()V
      20: astore        6
      22: aload         6
      24: ldc           #59                 // String p2Repository.generated.timestamp
      26: new           #60                 // class java/util/Date
      29: dup
      30: invokespecial #61                 // Method java/util/Date."<init>":()V
      33: invokevirtual #62                 // Method java/util/Date.toString:()Ljava/lang/String;
      36: invokeinterface #63,  3           // InterfaceMethod java/util/Map.put:(Ljava/lang/Object;Ljava/lang/Object;)Ljava/lang/Object;
      41: pop
      42: new           #2                  // class org/sonatype/nexus/proxy/ResourceStoreRequest
      45: dup
      46: aload_0
      47: invokespecial #3                  // Method org/sonatype/nexus/proxy/ResourceStoreRequest."<init>":(Ljava/lang/String;)V
      50: astore        7
      52: aload_2
      53: aload         7
      55: aload         4
      57: aload_3
      58: aload         6
      60: invokestatic  #64                 // Method storeItem:(Lorg/sonatype/nexus/proxy/repository/Repository;Lorg/sonatype/nexus/proxy/ResourceStoreRequest;Ljava/io/InputStream;Ljava/lang/String;Ljava/util/Map;)V
      63: aload         4
      65: ifnull        150
      68: aload         5
      70: ifnull        93
      73: aload         4
      75: invokevirtual #65                 // Method java/io/InputStream.close:()V
      78: goto          150
      81: astore        6
      83: aload         5
      85: aload         6
      87: invokevirtual #67                 // Method java/lang/Throwable.addSuppressed:(Ljava/lang/Throwable;)V
      90: goto          150
      93: aload         4
      95: invokevirtual #65                 // Method java/io/InputStream.close:()V
      98: goto          150
     101: astore        6
     103: aload         6
     105: astore        5
     107: aload         6
     109: athrow
     110: astore        8
     112: aload         4
     114: ifnull        147
     117: aload         5
     119: ifnull        142
     122: aload         4
     124: invokevirtual #65                 // Method java/io/InputStream.close:()V
     127: goto          147
     130: astore        9
     132: aload         5
     134: aload         9
     136: invokevirtual #67                 // Method java/lang/Throwable.addSuppressed:(Ljava/lang/Throwable;)V
     139: goto          147
     142: aload         4
     144: invokevirtual #65                 // Method java/io/InputStream.close:()V
     147: aload         8
     149: athrow
     150: return
    Exception table:
       from    to  target type
          73    78    81   Class java/lang/Throwable
          13    63   101   Class java/lang/Throwable
          13    63   110   any
         122   127   130   Class java/lang/Throwable
         101   112   110   any

  private static java.lang.String[] getReversePathSegments(java.io.File);
    Code:
       0: new           #68                 // class java/util/ArrayList
       3: dup
       4: invokespecial #69                 // Method java/util/ArrayList."<init>":()V
       7: astore_1
       8: aload_0
       9: invokevirtual #70                 // Method java/io/File.getCanonicalFile:()Ljava/io/File;
      12: astore_2
      13: aload_2
      14: ifnull        36
      17: aload_1
      18: aload_2
      19: invokevirtual #71                 // Method java/io/File.getName:()Ljava/lang/String;
      22: invokeinterface #72,  2           // InterfaceMethod java/util/List.add:(Ljava/lang/Object;)Z
      27: pop
      28: aload_2
      29: invokevirtual #73                 // Method java/io/File.getParentFile:()Ljava/io/File;
      32: astore_2
      33: goto          13
      36: goto          42
      39: astore_3
      40: aconst_null
      41: areturn
      42: aload_1
      43: aload_1
      44: invokeinterface #75,  1           // InterfaceMethod java/util/List.size:()I
      49: anewarray     #76                 // class java/lang/String
      52: invokeinterface #77,  2           // InterfaceMethod java/util/List.toArray:([Ljava/lang/Object;)[Ljava/lang/Object;
      57: checkcast     #78                 // class "[Ljava/lang/String;"
      60: areturn
    Exception table:
       from    to  target type
           8    36    39   Class java/io/IOException
}
