Compiled from "P2MetadataEventsInspector.java"
public class org.sonatype.nexus.plugins.p2.repository.internal.P2MetadataEventsInspector {
  private final javax.inject.Provider<org.sonatype.nexus.plugins.p2.repository.P2RepositoryAggregator> p2RepositoryAggregator;

  public org.sonatype.nexus.plugins.p2.repository.internal.P2MetadataEventsInspector(javax.inject.Provider<org.sonatype.nexus.plugins.p2.repository.P2RepositoryAggregator>, org.sonatype.sisu.goodies.eventbus.EventBus);
    Code:
       0: aload_0
       1: invokespecial #1                  // Method java/lang/Object."<init>":()V
       4: aload_0
       5: aload_1
       6: invokestatic  #2                  // Method com/google/common/base/Preconditions.checkNotNull:(Ljava/lang/Object;)Ljava/lang/Object;
       9: checkcast     #3                  // class javax/inject/Provider
      12: putfield      #4                  // Field p2RepositoryAggregator:Ljavax/inject/Provider;
      15: aload_2
      16: invokestatic  #2                  // Method com/google/common/base/Preconditions.checkNotNull:(Ljava/lang/Object;)Ljava/lang/Object;
      19: checkcast     #5                  // class org/sonatype/sisu/goodies/eventbus/EventBus
      22: aload_0
      23: invokeinterface #6,  2            // InterfaceMethod org/sonatype/sisu/goodies/eventbus/EventBus.register:(Ljava/lang/Object;)Lorg/sonatype/sisu/goodies/eventbus/EventBus;
      28: pop
      29: return

  public void onItemStored(org.sonatype.nexus.proxy.events.RepositoryItemEventStore);
    Code:
       0: aload_1
       1: invokevirtual #7                  // Method org/sonatype/nexus/proxy/events/RepositoryItemEventStore.getItem:()Lorg/sonatype/nexus/proxy/item/StorageItem;
       4: invokestatic  #8                  // Method isP2ContentXML:(Lorg/sonatype/nexus/proxy/item/StorageItem;)Z
       7: ifeq          31
      10: aload_0
      11: getfield      #4                  // Field p2RepositoryAggregator:Ljavax/inject/Provider;
      14: invokeinterface #9,  1            // InterfaceMethod javax/inject/Provider.get:()Ljava/lang/Object;
      19: checkcast     #10                 // class org/sonatype/nexus/plugins/p2/repository/P2RepositoryAggregator
      22: aload_1
      23: invokevirtual #7                  // Method org/sonatype/nexus/proxy/events/RepositoryItemEventStore.getItem:()Lorg/sonatype/nexus/proxy/item/StorageItem;
      26: invokeinterface #11,  2           // InterfaceMethod org/sonatype/nexus/plugins/p2/repository/P2RepositoryAggregator.updateP2Metadata:(Lorg/sonatype/nexus/proxy/item/StorageItem;)V
      31: return

  public void onItemCached(org.sonatype.nexus.proxy.events.RepositoryItemEventCache);
    Code:
       0: aload_1
       1: invokevirtual #12                 // Method org/sonatype/nexus/proxy/events/RepositoryItemEventCache.getItem:()Lorg/sonatype/nexus/proxy/item/StorageItem;
       4: invokestatic  #8                  // Method isP2ContentXML:(Lorg/sonatype/nexus/proxy/item/StorageItem;)Z
       7: ifeq          31
      10: aload_0
      11: getfield      #4                  // Field p2RepositoryAggregator:Ljavax/inject/Provider;
      14: invokeinterface #9,  1            // InterfaceMethod javax/inject/Provider.get:()Ljava/lang/Object;
      19: checkcast     #10                 // class org/sonatype/nexus/plugins/p2/repository/P2RepositoryAggregator
      22: aload_1
      23: invokevirtual #12                 // Method org/sonatype/nexus/proxy/events/RepositoryItemEventCache.getItem:()Lorg/sonatype/nexus/proxy/item/StorageItem;
      26: invokeinterface #11,  2           // InterfaceMethod org/sonatype/nexus/plugins/p2/repository/P2RepositoryAggregator.updateP2Metadata:(Lorg/sonatype/nexus/proxy/item/StorageItem;)V
      31: return

  public void onItemRemoved(org.sonatype.nexus.proxy.events.RepositoryItemEventDelete);
    Code:
       0: aload_1
       1: invokevirtual #13                 // Method org/sonatype/nexus/proxy/events/RepositoryItemEventDelete.getItem:()Lorg/sonatype/nexus/proxy/item/StorageItem;
       4: invokestatic  #8                  // Method isP2ContentXML:(Lorg/sonatype/nexus/proxy/item/StorageItem;)Z
       7: ifeq          31
      10: aload_0
      11: getfield      #4                  // Field p2RepositoryAggregator:Ljavax/inject/Provider;
      14: invokeinterface #9,  1            // InterfaceMethod javax/inject/Provider.get:()Ljava/lang/Object;
      19: checkcast     #10                 // class org/sonatype/nexus/plugins/p2/repository/P2RepositoryAggregator
      22: aload_1
      23: invokevirtual #13                 // Method org/sonatype/nexus/proxy/events/RepositoryItemEventDelete.getItem:()Lorg/sonatype/nexus/proxy/item/StorageItem;
      26: invokeinterface #14,  2           // InterfaceMethod org/sonatype/nexus/plugins/p2/repository/P2RepositoryAggregator.removeP2Metadata:(Lorg/sonatype/nexus/proxy/item/StorageItem;)V
      31: return

  private static boolean isP2ContentXML(org.sonatype.nexus.proxy.item.StorageItem);
    Code:
       0: aload_0
       1: ifnonnull     6
       4: iconst_0
       5: ireturn
       6: aload_0
       7: invokeinterface #15,  1           // InterfaceMethod org/sonatype/nexus/proxy/item/StorageItem.getPath:()Ljava/lang/String;
      12: invokestatic  #16                 // Method org/sonatype/nexus/plugins/p2/repository/internal/NexusUtils.isHidden:(Ljava/lang/String;)Z
      15: ifne          34
      18: aload_0
      19: invokeinterface #15,  1           // InterfaceMethod org/sonatype/nexus/proxy/item/StorageItem.getPath:()Ljava/lang/String;
      24: invokestatic  #17                 // Method isP2ContentXML:(Ljava/lang/String;)Z
      27: ifeq          34
      30: iconst_1
      31: goto          35
      34: iconst_0
      35: ireturn

  static boolean isP2ContentXML(java.lang.String);
    Code:
       0: aload_0
       1: ifnonnull     6
       4: iconst_0
       5: ireturn
       6: aload_0
       7: ldc           #18                 // String p2Content.xml
       9: invokevirtual #19                 // Method java/lang/String.endsWith:(Ljava/lang/String;)Z
      12: ireturn
}
