Compiled from "GrouperComboboxTag.java"
public class edu.internet2.middleware.grouper.ui.tags.GrouperComboboxTag extends javax.servlet.jsp.tagext.SimpleTagSupport {
  private java.lang.String id;

  private int width;

  private java.lang.String filterOperation;

  private java.lang.String comboDefaultText;

  private java.lang.String comboDefaultValue;

  private java.lang.String additionalFormElementNames;

  public edu.internet2.middleware.grouper.ui.tags.GrouperComboboxTag();
    Code:
       0: aload_0
       1: invokespecial #1                  // Method javax/servlet/jsp/tagext/SimpleTagSupport."<init>":()V
       4: aload_0
       5: iconst_m1
       6: putfield      #2                  // Field width:I
       9: return

  public void setAdditionalFormElementNames(java.lang.String);
    Code:
       0: aload_0
       1: aload_1
       2: putfield      #3                  // Field additionalFormElementNames:Ljava/lang/String;
       5: return

  public void setComboDefaultText(java.lang.String);
    Code:
       0: aload_0
       1: aload_1
       2: putfield      #4                  // Field comboDefaultText:Ljava/lang/String;
       5: return

  public void setComboDefaultValue(java.lang.String);
    Code:
       0: aload_0
       1: aload_1
       2: putfield      #5                  // Field comboDefaultValue:Ljava/lang/String;
       5: return

  public void doTag() throws javax.servlet.jsp.JspException, java.io.IOException;
    Code:
       0: new           #6                  // class java/lang/StringBuilder
       3: dup
       4: invokespecial #7                  // Method java/lang/StringBuilder."<init>":()V
       7: astore_1
       8: aload_0
       9: getfield      #8                  // Field filterOperation:Ljava/lang/String;
      12: ldc           #9                  // String /
      14: invokestatic  #10                 // Method org/apache/commons/lang/StringUtils.contains:(Ljava/lang/String;Ljava/lang/String;)Z
      17: ifne          46
      20: aload_0
      21: new           #6                  // class java/lang/StringBuilder
      24: dup
      25: invokespecial #7                  // Method java/lang/StringBuilder."<init>":()V
      28: ldc           #11                 // String ../app/
      30: invokevirtual #12                 // Method java/lang/StringBuilder.append:(Ljava/lang/String;)Ljava/lang/StringBuilder;
      33: aload_0
      34: getfield      #8                  // Field filterOperation:Ljava/lang/String;
      37: invokevirtual #12                 // Method java/lang/StringBuilder.append:(Ljava/lang/String;)Ljava/lang/StringBuilder;
      40: invokevirtual #13                 // Method java/lang/StringBuilder.toString:()Ljava/lang/String;
      43: putfield      #8                  // Field filterOperation:Ljava/lang/String;
      46: aload_1
      47: ldc           #14                 // String <div id=\"
      49: invokevirtual #12                 // Method java/lang/StringBuilder.append:(Ljava/lang/String;)Ljava/lang/StringBuilder;
      52: new           #6                  // class java/lang/StringBuilder
      55: dup
      56: invokespecial #7                  // Method java/lang/StringBuilder."<init>":()V
      59: aload_0
      60: getfield      #15                 // Field id:Ljava/lang/String;
      63: invokevirtual #12                 // Method java/lang/StringBuilder.append:(Ljava/lang/String;)Ljava/lang/StringBuilder;
      66: ldc           #16                 // String Div
      68: invokevirtual #12                 // Method java/lang/StringBuilder.append:(Ljava/lang/String;)Ljava/lang/StringBuilder;
      71: invokevirtual #13                 // Method java/lang/StringBuilder.toString:()Ljava/lang/String;
      74: invokevirtual #12                 // Method java/lang/StringBuilder.append:(Ljava/lang/String;)Ljava/lang/StringBuilder;
      77: ldc           #17                 // String \"
      79: invokevirtual #12                 // Method java/lang/StringBuilder.append:(Ljava/lang/String;)Ljava/lang/StringBuilder;
      82: pop
      83: aload_0
      84: getfield      #2                  // Field width:I
      87: iconst_m1
      88: if_icmpeq     110
      91: aload_1
      92: ldc           #18                 // String  style=\"
      94: invokevirtual #12                 // Method java/lang/StringBuilder.append:(Ljava/lang/String;)Ljava/lang/StringBuilder;
      97: aload_0
      98: getfield      #2                  // Field width:I
     101: invokevirtual #19                 // Method java/lang/StringBuilder.append:(I)Ljava/lang/StringBuilder;
     104: ldc           #17                 // String \"
     106: invokevirtual #12                 // Method java/lang/StringBuilder.append:(Ljava/lang/String;)Ljava/lang/StringBuilder;
     109: pop
     110: aload_1
     111: ldc           #20                 // String ></div>\n
     113: invokevirtual #12                 // Method java/lang/StringBuilder.append:(Ljava/lang/String;)Ljava/lang/StringBuilder;
     116: pop
     117: aload_1
     118: ldc           #21                 // String <script type=\"text/javascript\"> \n
     120: invokevirtual #12                 // Method java/lang/StringBuilder.append:(Ljava/lang/String;)Ljava/lang/StringBuilder;
     123: pop
     124: aload_1
     125: ldc           #22                 // String guiRegisterDhtmlxCombo(\'
     127: invokevirtual #12                 // Method java/lang/StringBuilder.append:(Ljava/lang/String;)Ljava/lang/StringBuilder;
     130: aload_0
     131: getfield      #15                 // Field id:Ljava/lang/String;
     134: invokevirtual #12                 // Method java/lang/StringBuilder.append:(Ljava/lang/String;)Ljava/lang/StringBuilder;
     137: ldc           #23                 // String Div\', \'
     139: invokevirtual #12                 // Method java/lang/StringBuilder.append:(Ljava/lang/String;)Ljava/lang/StringBuilder;
     142: aload_0
     143: getfield      #15                 // Field id:Ljava/lang/String;
     146: invokevirtual #12                 // Method java/lang/StringBuilder.append:(Ljava/lang/String;)Ljava/lang/StringBuilder;
     149: ldc           #24                 // String \',
     151: invokevirtual #12                 // Method java/lang/StringBuilder.append:(Ljava/lang/String;)Ljava/lang/StringBuilder;
     154: aload_0
     155: getfield      #2                  // Field width:I
     158: iconst_m1
     159: if_icmpne     166
     162: aconst_null
     163: goto          173
     166: aload_0
     167: getfield      #2                  // Field width:I
     170: invokestatic  #25                 // Method java/lang/Integer.valueOf:(I)Ljava/lang/Integer;
     173: invokevirtual #26                 // Method java/lang/StringBuilder.append:(Ljava/lang/Object;)Ljava/lang/StringBuilder;
     176: ldc           #27                 // String , true, \"
     178: invokevirtual #12                 // Method java/lang/StringBuilder.append:(Ljava/lang/String;)Ljava/lang/StringBuilder;
     181: pop
     182: aload_1
     183: aload_0
     184: getfield      #8                  // Field filterOperation:Ljava/lang/String;
     187: invokevirtual #12                 // Method java/lang/StringBuilder.append:(Ljava/lang/String;)Ljava/lang/StringBuilder;
     190: ldc           #28                 // String \",
     192: invokevirtual #12                 // Method java/lang/StringBuilder.append:(Ljava/lang/String;)Ljava/lang/StringBuilder;
     195: pop
     196: aload_0
     197: getfield      #4                  // Field comboDefaultText:Ljava/lang/String;
     200: invokestatic  #29                 // Method org/apache/commons/lang/StringUtils.isBlank:(Ljava/lang/String;)Z
     203: ifeq          216
     206: aload_1
     207: ldc           #30                 // String null
     209: invokevirtual #12                 // Method java/lang/StringBuilder.append:(Ljava/lang/String;)Ljava/lang/StringBuilder;
     212: pop
     213: goto          239
     216: aload_1
     217: ldc           #31                 // String \'
     219: invokevirtual #12                 // Method java/lang/StringBuilder.append:(Ljava/lang/String;)Ljava/lang/StringBuilder;
     222: aload_0
     223: getfield      #4                  // Field comboDefaultText:Ljava/lang/String;
     226: iconst_1
     227: invokestatic  #32                 // Method edu/internet2/middleware/grouper/ui/util/GrouperUiUtils.escapeJavascript:(Ljava/lang/String;Z)Ljava/lang/String;
     230: invokevirtual #12                 // Method java/lang/StringBuilder.append:(Ljava/lang/String;)Ljava/lang/StringBuilder;
     233: ldc           #31                 // String \'
     235: invokevirtual #12                 // Method java/lang/StringBuilder.append:(Ljava/lang/String;)Ljava/lang/StringBuilder;
     238: pop
     239: aload_1
     240: ldc           #33                 // String ,
     242: invokevirtual #12                 // Method java/lang/StringBuilder.append:(Ljava/lang/String;)Ljava/lang/StringBuilder;
     245: pop
     246: aload_0
     247: getfield      #5                  // Field comboDefaultValue:Ljava/lang/String;
     250: invokestatic  #29                 // Method org/apache/commons/lang/StringUtils.isBlank:(Ljava/lang/String;)Z
     253: ifeq          266
     256: aload_1
     257: ldc           #30                 // String null
     259: invokevirtual #12                 // Method java/lang/StringBuilder.append:(Ljava/lang/String;)Ljava/lang/StringBuilder;
     262: pop
     263: goto          289
     266: aload_1
     267: ldc           #31                 // String \'
     269: invokevirtual #12                 // Method java/lang/StringBuilder.append:(Ljava/lang/String;)Ljava/lang/StringBuilder;
     272: aload_0
     273: getfield      #5                  // Field comboDefaultValue:Ljava/lang/String;
     276: iconst_1
     277: invokestatic  #32                 // Method edu/internet2/middleware/grouper/ui/util/GrouperUiUtils.escapeJavascript:(Ljava/lang/String;Z)Ljava/lang/String;
     280: invokevirtual #12                 // Method java/lang/StringBuilder.append:(Ljava/lang/String;)Ljava/lang/StringBuilder;
     283: ldc           #31                 // String \'
     285: invokevirtual #12                 // Method java/lang/StringBuilder.append:(Ljava/lang/String;)Ljava/lang/StringBuilder;
     288: pop
     289: aload_1
     290: ldc           #33                 // String ,
     292: invokevirtual #12                 // Method java/lang/StringBuilder.append:(Ljava/lang/String;)Ljava/lang/StringBuilder;
     295: pop
     296: aload_0
     297: getfield      #3                  // Field additionalFormElementNames:Ljava/lang/String;
     300: invokestatic  #29                 // Method org/apache/commons/lang/StringUtils.isBlank:(Ljava/lang/String;)Z
     303: ifeq          316
     306: aload_1
     307: ldc           #30                 // String null
     309: invokevirtual #12                 // Method java/lang/StringBuilder.append:(Ljava/lang/String;)Ljava/lang/StringBuilder;
     312: pop
     313: goto          339
     316: aload_1
     317: ldc           #31                 // String \'
     319: invokevirtual #12                 // Method java/lang/StringBuilder.append:(Ljava/lang/String;)Ljava/lang/StringBuilder;
     322: aload_0
     323: getfield      #3                  // Field additionalFormElementNames:Ljava/lang/String;
     326: iconst_1
     327: invokestatic  #32                 // Method edu/internet2/middleware/grouper/ui/util/GrouperUiUtils.escapeJavascript:(Ljava/lang/String;Z)Ljava/lang/String;
     330: invokevirtual #12                 // Method java/lang/StringBuilder.append:(Ljava/lang/String;)Ljava/lang/StringBuilder;
     333: ldc           #31                 // String \'
     335: invokevirtual #12                 // Method java/lang/StringBuilder.append:(Ljava/lang/String;)Ljava/lang/StringBuilder;
     338: pop
     339: aload_1
     340: ldc           #34                 // String );\n
     342: invokevirtual #12                 // Method java/lang/StringBuilder.append:(Ljava/lang/String;)Ljava/lang/StringBuilder;
     345: pop
     346: aload_1
     347: ldc           #35                 // String </script>\n
     349: invokevirtual #12                 // Method java/lang/StringBuilder.append:(Ljava/lang/String;)Ljava/lang/StringBuilder;
     352: pop
     353: aload_0
     354: invokevirtual #36                 // Method getJspContext:()Ljavax/servlet/jsp/JspContext;
     357: invokevirtual #37                 // Method javax/servlet/jsp/JspContext.getOut:()Ljavax/servlet/jsp/JspWriter;
     360: aload_1
     361: invokevirtual #13                 // Method java/lang/StringBuilder.toString:()Ljava/lang/String;
     364: invokevirtual #38                 // Method javax/servlet/jsp/JspWriter.print:(Ljava/lang/String;)V
     367: return

  public void setId(java.lang.String);
    Code:
       0: aload_0
       1: aload_1
       2: putfield      #15                 // Field id:Ljava/lang/String;
       5: return

  public void setWidth(int);
    Code:
       0: aload_0
       1: iload_1
       2: putfield      #2                  // Field width:I
       5: return

  public void setFilterOperation(java.lang.String);
    Code:
       0: aload_0
       1: aload_1
       2: putfield      #8                  // Field filterOperation:Ljava/lang/String;
       5: return
}
