Compiled from "Config.java"
public class org.kohsuke.args4j.Config$ConfigHandler extends org.xml.sax.helpers.DefaultHandler {
  org.kohsuke.args4j.Config config;

  org.kohsuke.args4j.spi.ConfigElement currentCE;

  final org.kohsuke.args4j.Config this$0;

  public org.kohsuke.args4j.Config$ConfigHandler(org.kohsuke.args4j.Config, org.kohsuke.args4j.Config);
    Code:
       0: aload_0
       1: aload_1
       2: putfield      #1                  // Field this$0:Lorg/kohsuke/args4j/Config;
       5: aload_0
       6: invokespecial #2                  // Method org/xml/sax/helpers/DefaultHandler."<init>":()V
       9: aload_0
      10: aload_2
      11: putfield      #3                  // Field config:Lorg/kohsuke/args4j/Config;
      14: return

  public void startElement(java.lang.String, java.lang.String, java.lang.String, org.xml.sax.Attributes) throws org.xml.sax.SAXException;
    Code:
       0: aload_3
       1: ldc           #4                  // String option
       3: invokevirtual #5                  // Method java/lang/String.equals:(Ljava/lang/Object;)Z
       6: ifne          18
       9: aload_3
      10: ldc           #6                  // String argument
      12: invokevirtual #5                  // Method java/lang/String.equals:(Ljava/lang/Object;)Z
      15: ifeq          246
      18: aload_0
      19: new           #7                  // class org/kohsuke/args4j/spi/ConfigElement
      22: dup
      23: invokespecial #8                  // Method org/kohsuke/args4j/spi/ConfigElement."<init>":()V
      26: putfield      #9                  // Field currentCE:Lorg/kohsuke/args4j/spi/ConfigElement;
      29: aload_0
      30: getfield      #9                  // Field currentCE:Lorg/kohsuke/args4j/spi/ConfigElement;
      33: aload         4
      35: ldc           #10                 // String field
      37: invokeinterface #11,  2           // InterfaceMethod org/xml/sax/Attributes.getValue:(Ljava/lang/String;)Ljava/lang/String;
      42: putfield      #12                 // Field org/kohsuke/args4j/spi/ConfigElement.field:Ljava/lang/String;
      45: aload_0
      46: getfield      #9                  // Field currentCE:Lorg/kohsuke/args4j/spi/ConfigElement;
      49: aload         4
      51: ldc           #13                 // String handler
      53: invokeinterface #11,  2           // InterfaceMethod org/xml/sax/Attributes.getValue:(Ljava/lang/String;)Ljava/lang/String;
      58: putfield      #14                 // Field org/kohsuke/args4j/spi/ConfigElement.handler:Ljava/lang/String;
      61: aload_0
      62: getfield      #9                  // Field currentCE:Lorg/kohsuke/args4j/spi/ConfigElement;
      65: aload         4
      67: ldc           #15                 // String metavar
      69: invokeinterface #11,  2           // InterfaceMethod org/xml/sax/Attributes.getValue:(Ljava/lang/String;)Ljava/lang/String;
      74: putfield      #16                 // Field org/kohsuke/args4j/spi/ConfigElement.metavar:Ljava/lang/String;
      77: aload_0
      78: getfield      #9                  // Field currentCE:Lorg/kohsuke/args4j/spi/ConfigElement;
      81: aload         4
      83: ldc           #17                 // String method
      85: invokeinterface #11,  2           // InterfaceMethod org/xml/sax/Attributes.getValue:(Ljava/lang/String;)Ljava/lang/String;
      90: putfield      #18                 // Field org/kohsuke/args4j/spi/ConfigElement.method:Ljava/lang/String;
      93: aload_0
      94: getfield      #9                  // Field currentCE:Lorg/kohsuke/args4j/spi/ConfigElement;
      97: aload         4
      99: ldc           #19                 // String name
     101: invokeinterface #11,  2           // InterfaceMethod org/xml/sax/Attributes.getValue:(Ljava/lang/String;)Ljava/lang/String;
     106: putfield      #20                 // Field org/kohsuke/args4j/spi/ConfigElement.name:Ljava/lang/String;
     109: aload_0
     110: getfield      #9                  // Field currentCE:Lorg/kohsuke/args4j/spi/ConfigElement;
     113: aload         4
     115: ldc           #21                 // String usage
     117: invokeinterface #11,  2           // InterfaceMethod org/xml/sax/Attributes.getValue:(Ljava/lang/String;)Ljava/lang/String;
     122: putfield      #22                 // Field org/kohsuke/args4j/spi/ConfigElement.usage:Ljava/lang/String;
     125: aload_0
     126: getfield      #9                  // Field currentCE:Lorg/kohsuke/args4j/spi/ConfigElement;
     129: aload         4
     131: ldc           #23                 // String multiValued
     133: invokeinterface #11,  2           // InterfaceMethod org/xml/sax/Attributes.getValue:(Ljava/lang/String;)Ljava/lang/String;
     138: invokestatic  #24                 // Method java/lang/Boolean.getBoolean:(Ljava/lang/String;)Z
     141: putfield      #25                 // Field org/kohsuke/args4j/spi/ConfigElement.multiValued:Z
     144: aload_0
     145: getfield      #9                  // Field currentCE:Lorg/kohsuke/args4j/spi/ConfigElement;
     148: aload         4
     150: ldc           #26                 // String required
     152: invokeinterface #11,  2           // InterfaceMethod org/xml/sax/Attributes.getValue:(Ljava/lang/String;)Ljava/lang/String;
     157: invokestatic  #24                 // Method java/lang/Boolean.getBoolean:(Ljava/lang/String;)Z
     160: putfield      #27                 // Field org/kohsuke/args4j/spi/ConfigElement.required:Z
     163: aload         4
     165: ldc           #28                 // String aliases
     167: invokeinterface #11,  2           // InterfaceMethod org/xml/sax/Attributes.getValue:(Ljava/lang/String;)Ljava/lang/String;
     172: ifnull        199
     175: aload_0
     176: getfield      #9                  // Field currentCE:Lorg/kohsuke/args4j/spi/ConfigElement;
     179: aload         4
     181: ldc           #28                 // String aliases
     183: invokeinterface #11,  2           // InterfaceMethod org/xml/sax/Attributes.getValue:(Ljava/lang/String;)Ljava/lang/String;
     188: ldc           #29                 // String ,
     190: invokevirtual #30                 // Method java/lang/String.split:(Ljava/lang/String;)[Ljava/lang/String;
     193: putfield      #31                 // Field org/kohsuke/args4j/spi/ConfigElement.aliases:[Ljava/lang/String;
     196: goto          210
     199: aload_0
     200: getfield      #9                  // Field currentCE:Lorg/kohsuke/args4j/spi/ConfigElement;
     203: iconst_0
     204: anewarray     #32                 // class java/lang/String
     207: putfield      #31                 // Field org/kohsuke/args4j/spi/ConfigElement.aliases:[Ljava/lang/String;
     210: aload_3
     211: ldc           #4                  // String option
     213: invokevirtual #5                  // Method java/lang/String.equals:(Ljava/lang/Object;)Z
     216: ifeq          229
     219: aload_0
     220: getfield      #3                  // Field config:Lorg/kohsuke/args4j/Config;
     223: getfield      #33                 // Field org/kohsuke/args4j/Config.options:Ljava/util/List;
     226: goto          236
     229: aload_0
     230: getfield      #3                  // Field config:Lorg/kohsuke/args4j/Config;
     233: getfield      #34                 // Field org/kohsuke/args4j/Config.arguments:Ljava/util/List;
     236: aload_0
     237: getfield      #9                  // Field currentCE:Lorg/kohsuke/args4j/spi/ConfigElement;
     240: invokeinterface #35,  2           // InterfaceMethod java/util/List.add:(Ljava/lang/Object;)Z
     245: pop
     246: return
}
