Compiled from "OptionHandlerRegistry.java"
public class org.kohsuke.args4j.OptionHandlerRegistry {
  private static org.kohsuke.args4j.OptionHandlerRegistry instance;

  private final java.util.Map<java.lang.Class, org.kohsuke.args4j.OptionHandlerRegistry$OptionHandlerFactory> handlers;

  public static synchronized org.kohsuke.args4j.OptionHandlerRegistry getRegistry();
    Code:
       0: getstatic     #2                  // Field instance:Lorg/kohsuke/args4j/OptionHandlerRegistry;
       3: ifnonnull     16
       6: new           #3                  // class org/kohsuke/args4j/OptionHandlerRegistry
       9: dup
      10: invokespecial #4                  // Method "<init>":()V
      13: putstatic     #2                  // Field instance:Lorg/kohsuke/args4j/OptionHandlerRegistry;
      16: getstatic     #2                  // Field instance:Lorg/kohsuke/args4j/OptionHandlerRegistry;
      19: areturn

  private org.kohsuke.args4j.OptionHandlerRegistry();
    Code:
       0: aload_0
       1: invokespecial #5                  // Method java/lang/Object."<init>":()V
       4: aload_0
       5: new           #6                  // class java/util/HashMap
       8: dup
       9: invokespecial #7                  // Method java/util/HashMap."<init>":()V
      12: invokestatic  #8                  // Method java/util/Collections.synchronizedMap:(Ljava/util/Map;)Ljava/util/Map;
      15: putfield      #9                  // Field handlers:Ljava/util/Map;
      18: aload_0
      19: invokespecial #10                 // Method initHandlers:()V
      22: return

  private void initHandlers();
    Code:
       0: aload_0
       1: ldc_w         #11                 // class java/lang/Boolean
       4: ldc_w         #12                 // class org/kohsuke/args4j/spi/BooleanOptionHandler
       7: invokevirtual #13                 // Method registerHandler:(Ljava/lang/Class;Ljava/lang/Class;)V
      10: aload_0
      11: getstatic     #14                 // Field java/lang/Boolean.TYPE:Ljava/lang/Class;
      14: ldc_w         #12                 // class org/kohsuke/args4j/spi/BooleanOptionHandler
      17: invokevirtual #13                 // Method registerHandler:(Ljava/lang/Class;Ljava/lang/Class;)V
      20: aload_0
      21: ldc_w         #15                 // class java/io/File
      24: ldc_w         #16                 // class org/kohsuke/args4j/spi/FileOptionHandler
      27: invokevirtual #13                 // Method registerHandler:(Ljava/lang/Class;Ljava/lang/Class;)V
      30: aload_0
      31: ldc_w         #17                 // class java/net/URL
      34: ldc_w         #18                 // class org/kohsuke/args4j/spi/URLOptionHandler
      37: invokevirtual #13                 // Method registerHandler:(Ljava/lang/Class;Ljava/lang/Class;)V
      40: aload_0
      41: ldc_w         #19                 // class java/net/URI
      44: ldc_w         #20                 // class org/kohsuke/args4j/spi/URIOptionHandler
      47: invokevirtual #13                 // Method registerHandler:(Ljava/lang/Class;Ljava/lang/Class;)V
      50: aload_0
      51: ldc_w         #21                 // class java/lang/Integer
      54: ldc_w         #22                 // class org/kohsuke/args4j/spi/IntOptionHandler
      57: invokevirtual #13                 // Method registerHandler:(Ljava/lang/Class;Ljava/lang/Class;)V
      60: aload_0
      61: getstatic     #23                 // Field java/lang/Integer.TYPE:Ljava/lang/Class;
      64: ldc_w         #22                 // class org/kohsuke/args4j/spi/IntOptionHandler
      67: invokevirtual #13                 // Method registerHandler:(Ljava/lang/Class;Ljava/lang/Class;)V
      70: aload_0
      71: ldc_w         #24                 // class java/lang/Double
      74: ldc_w         #25                 // class org/kohsuke/args4j/spi/DoubleOptionHandler
      77: invokevirtual #13                 // Method registerHandler:(Ljava/lang/Class;Ljava/lang/Class;)V
      80: aload_0
      81: getstatic     #26                 // Field java/lang/Double.TYPE:Ljava/lang/Class;
      84: ldc_w         #25                 // class org/kohsuke/args4j/spi/DoubleOptionHandler
      87: invokevirtual #13                 // Method registerHandler:(Ljava/lang/Class;Ljava/lang/Class;)V
      90: aload_0
      91: ldc_w         #27                 // class java/lang/String
      94: ldc_w         #28                 // class org/kohsuke/args4j/spi/StringOptionHandler
      97: invokevirtual #13                 // Method registerHandler:(Ljava/lang/Class;Ljava/lang/Class;)V
     100: aload_0
     101: ldc_w         #29                 // class java/lang/Byte
     104: ldc_w         #30                 // class org/kohsuke/args4j/spi/ByteOptionHandler
     107: invokevirtual #13                 // Method registerHandler:(Ljava/lang/Class;Ljava/lang/Class;)V
     110: aload_0
     111: getstatic     #31                 // Field java/lang/Byte.TYPE:Ljava/lang/Class;
     114: ldc_w         #30                 // class org/kohsuke/args4j/spi/ByteOptionHandler
     117: invokevirtual #13                 // Method registerHandler:(Ljava/lang/Class;Ljava/lang/Class;)V
     120: aload_0
     121: ldc_w         #32                 // class java/lang/Character
     124: ldc_w         #33                 // class org/kohsuke/args4j/spi/CharOptionHandler
     127: invokevirtual #13                 // Method registerHandler:(Ljava/lang/Class;Ljava/lang/Class;)V
     130: aload_0
     131: getstatic     #34                 // Field java/lang/Character.TYPE:Ljava/lang/Class;
     134: ldc_w         #33                 // class org/kohsuke/args4j/spi/CharOptionHandler
     137: invokevirtual #13                 // Method registerHandler:(Ljava/lang/Class;Ljava/lang/Class;)V
     140: aload_0
     141: ldc_w         #35                 // class java/lang/Float
     144: ldc_w         #36                 // class org/kohsuke/args4j/spi/FloatOptionHandler
     147: invokevirtual #13                 // Method registerHandler:(Ljava/lang/Class;Ljava/lang/Class;)V
     150: aload_0
     151: getstatic     #37                 // Field java/lang/Float.TYPE:Ljava/lang/Class;
     154: ldc_w         #36                 // class org/kohsuke/args4j/spi/FloatOptionHandler
     157: invokevirtual #13                 // Method registerHandler:(Ljava/lang/Class;Ljava/lang/Class;)V
     160: aload_0
     161: ldc_w         #38                 // class java/lang/Long
     164: ldc_w         #39                 // class org/kohsuke/args4j/spi/LongOptionHandler
     167: invokevirtual #13                 // Method registerHandler:(Ljava/lang/Class;Ljava/lang/Class;)V
     170: aload_0
     171: getstatic     #40                 // Field java/lang/Long.TYPE:Ljava/lang/Class;
     174: ldc_w         #39                 // class org/kohsuke/args4j/spi/LongOptionHandler
     177: invokevirtual #13                 // Method registerHandler:(Ljava/lang/Class;Ljava/lang/Class;)V
     180: aload_0
     181: ldc_w         #41                 // class java/lang/Short
     184: ldc_w         #42                 // class org/kohsuke/args4j/spi/ShortOptionHandler
     187: invokevirtual #13                 // Method registerHandler:(Ljava/lang/Class;Ljava/lang/Class;)V
     190: aload_0
     191: getstatic     #43                 // Field java/lang/Short.TYPE:Ljava/lang/Class;
     194: ldc_w         #42                 // class org/kohsuke/args4j/spi/ShortOptionHandler
     197: invokevirtual #13                 // Method registerHandler:(Ljava/lang/Class;Ljava/lang/Class;)V
     200: aload_0
     201: ldc_w         #44                 // class java/net/InetAddress
     204: ldc_w         #45                 // class org/kohsuke/args4j/spi/InetAddressOptionHandler
     207: invokevirtual #13                 // Method registerHandler:(Ljava/lang/Class;Ljava/lang/Class;)V
     210: aload_0
     211: ldc_w         #46                 // class java/util/regex/Pattern
     214: ldc_w         #47                 // class org/kohsuke/args4j/spi/PatternOptionHandler
     217: invokevirtual #13                 // Method registerHandler:(Ljava/lang/Class;Ljava/lang/Class;)V
     220: aload_0
     221: ldc_w         #48                 // class java/util/Map
     224: ldc_w         #49                 // class org/kohsuke/args4j/spi/MapOptionHandler
     227: invokevirtual #13                 // Method registerHandler:(Ljava/lang/Class;Ljava/lang/Class;)V
     230: ldc           #50                 // String java.nio.file.Path
     232: invokestatic  #51                 // Method java/lang/Class.forName:(Ljava/lang/String;)Ljava/lang/Class;
     235: astore_1
     236: aload_0
     237: aload_1
     238: ldc_w         #52                 // class org/kohsuke/args4j/spi/PathOptionHandler
     241: invokevirtual #13                 // Method registerHandler:(Ljava/lang/Class;Ljava/lang/Class;)V
     244: goto          248
     247: astore_1
     248: return
    Exception table:
       from    to  target type
         230   244   247   Class java/lang/ClassNotFoundException

  private static java.lang.reflect.Constructor<? extends org.kohsuke.args4j.spi.OptionHandler> getConstructor(java.lang.Class<? extends org.kohsuke.args4j.spi.OptionHandler>);
    Code:
       0: aload_0
       1: iconst_3
       2: anewarray     #54                 // class java/lang/Class
       5: dup
       6: iconst_0
       7: ldc_w         #55                 // class org/kohsuke/args4j/CmdLineParser
      10: aastore
      11: dup
      12: iconst_1
      13: ldc_w         #56                 // class org/kohsuke/args4j/OptionDef
      16: aastore
      17: dup
      18: iconst_2
      19: ldc_w         #57                 // class org/kohsuke/args4j/spi/Setter
      22: aastore
      23: invokevirtual #58                 // Method java/lang/Class.getConstructor:([Ljava/lang/Class;)Ljava/lang/reflect/Constructor;
      26: areturn
      27: astore_1
      28: new           #60                 // class java/lang/IllegalArgumentException
      31: dup
      32: getstatic     #61                 // Field org/kohsuke/args4j/Messages.NO_CONSTRUCTOR_ON_HANDLER:Lorg/kohsuke/args4j/Messages;
      35: iconst_1
      36: anewarray     #62                 // class java/lang/Object
      39: dup
      40: iconst_0
      41: aload_0
      42: aastore
      43: invokevirtual #63                 // Method org/kohsuke/args4j/Messages.format:([Ljava/lang/Object;)Ljava/lang/String;
      46: invokespecial #64                 // Method java/lang/IllegalArgumentException."<init>":(Ljava/lang/String;)V
      49: athrow
    Exception table:
       from    to  target type
           0    26    27   Class java/lang/NoSuchMethodException

  public void registerHandler(java.lang.Class, java.lang.Class<? extends org.kohsuke.args4j.spi.OptionHandler>);
    Code:
       0: aload_1
       1: ldc           #65                 // String valueType
       3: invokestatic  #66                 // Method org/kohsuke/args4j/Utilities.checkNonNull:(Ljava/lang/Object;Ljava/lang/String;)V
       6: aload_2
       7: ldc           #67                 // String handlerClass
       9: invokestatic  #66                 // Method org/kohsuke/args4j/Utilities.checkNonNull:(Ljava/lang/Object;Ljava/lang/String;)V
      12: ldc_w         #68                 // class org/kohsuke/args4j/spi/OptionHandler
      15: aload_2
      16: invokevirtual #69                 // Method java/lang/Class.isAssignableFrom:(Ljava/lang/Class;)Z
      19: ifne          40
      22: new           #60                 // class java/lang/IllegalArgumentException
      25: dup
      26: getstatic     #70                 // Field org/kohsuke/args4j/Messages.NO_OPTIONHANDLER:Lorg/kohsuke/args4j/Messages;
      29: iconst_0
      30: anewarray     #62                 // class java/lang/Object
      33: invokevirtual #63                 // Method org/kohsuke/args4j/Messages.format:([Ljava/lang/Object;)Ljava/lang/String;
      36: invokespecial #64                 // Method java/lang/IllegalArgumentException."<init>":(Ljava/lang/String;)V
      39: athrow
      40: aload_0
      41: getfield      #9                  // Field handlers:Ljava/util/Map;
      44: aload_1
      45: new           #71                 // class org/kohsuke/args4j/OptionHandlerRegistry$DefaultConstructorHandlerFactory
      48: dup
      49: aload_0
      50: aload_2
      51: invokespecial #72                 // Method org/kohsuke/args4j/OptionHandlerRegistry$DefaultConstructorHandlerFactory."<init>":(Lorg/kohsuke/args4j/OptionHandlerRegistry;Ljava/lang/Class;)V
      54: invokeinterface #73,  3           // InterfaceMethod java/util/Map.put:(Ljava/lang/Object;Ljava/lang/Object;)Ljava/lang/Object;
      59: pop
      60: return

  public void registerHandler(java.lang.Class, org.kohsuke.args4j.OptionHandlerRegistry$OptionHandlerFactory);
    Code:
       0: aload_1
       1: ldc           #65                 // String valueType
       3: invokestatic  #66                 // Method org/kohsuke/args4j/Utilities.checkNonNull:(Ljava/lang/Object;Ljava/lang/String;)V
       6: aload_2
       7: ldc           #74                 // String factory
       9: invokestatic  #66                 // Method org/kohsuke/args4j/Utilities.checkNonNull:(Ljava/lang/Object;Ljava/lang/String;)V
      12: aload_0
      13: getfield      #9                  // Field handlers:Ljava/util/Map;
      16: aload_1
      17: aload_2
      18: invokeinterface #73,  3           // InterfaceMethod java/util/Map.put:(Ljava/lang/Object;Ljava/lang/Object;)Ljava/lang/Object;
      23: pop
      24: return

  protected org.kohsuke.args4j.spi.OptionHandler createOptionHandler(org.kohsuke.args4j.CmdLineParser, org.kohsuke.args4j.OptionDef, org.kohsuke.args4j.spi.Setter);
    Code:
       0: aload_2
       1: ldc           #75                 // String CmdLineParser
       3: invokestatic  #66                 // Method org/kohsuke/args4j/Utilities.checkNonNull:(Ljava/lang/Object;Ljava/lang/String;)V
       6: aload_2
       7: ldc           #76                 // String OptionDef
       9: invokestatic  #66                 // Method org/kohsuke/args4j/Utilities.checkNonNull:(Ljava/lang/Object;Ljava/lang/String;)V
      12: aload_3
      13: ldc           #77                 // String Setter
      15: invokestatic  #66                 // Method org/kohsuke/args4j/Utilities.checkNonNull:(Ljava/lang/Object;Ljava/lang/String;)V
      18: aload_2
      19: invokevirtual #78                 // Method org/kohsuke/args4j/OptionDef.handler:()Ljava/lang/Class;
      22: astore        4
      24: aload         4
      26: ldc_w         #68                 // class org/kohsuke/args4j/spi/OptionHandler
      29: if_acmpne     119
      32: aload_3
      33: invokeinterface #79,  1           // InterfaceMethod org/kohsuke/args4j/spi/Setter.getType:()Ljava/lang/Class;
      38: astore        5
      40: ldc_w         #80                 // class java/lang/Enum
      43: aload         5
      45: invokevirtual #69                 // Method java/lang/Class.isAssignableFrom:(Ljava/lang/Class;)Z
      48: ifeq          64
      51: new           #81                 // class org/kohsuke/args4j/spi/EnumOptionHandler
      54: dup
      55: aload_1
      56: aload_2
      57: aload_3
      58: aload         5
      60: invokespecial #82                 // Method org/kohsuke/args4j/spi/EnumOptionHandler."<init>":(Lorg/kohsuke/args4j/CmdLineParser;Lorg/kohsuke/args4j/OptionDef;Lorg/kohsuke/args4j/spi/Setter;Ljava/lang/Class;)V
      63: areturn
      64: aload_0
      65: getfield      #9                  // Field handlers:Ljava/util/Map;
      68: aload         5
      70: invokeinterface #83,  2           // InterfaceMethod java/util/Map.get:(Ljava/lang/Object;)Ljava/lang/Object;
      75: checkcast     #84                 // class org/kohsuke/args4j/OptionHandlerRegistry$OptionHandlerFactory
      78: astore        6
      80: aload         6
      82: ifnonnull     108
      85: new           #85                 // class org/kohsuke/args4j/IllegalAnnotationError
      88: dup
      89: getstatic     #86                 // Field org/kohsuke/args4j/Messages.UNKNOWN_HANDLER:Lorg/kohsuke/args4j/Messages;
      92: iconst_1
      93: anewarray     #62                 // class java/lang/Object
      96: dup
      97: iconst_0
      98: aload         5
     100: aastore
     101: invokevirtual #63                 // Method org/kohsuke/args4j/Messages.format:([Ljava/lang/Object;)Ljava/lang/String;
     104: invokespecial #87                 // Method org/kohsuke/args4j/IllegalAnnotationError."<init>":(Ljava/lang/String;)V
     107: athrow
     108: aload         6
     110: aload_1
     111: aload_2
     112: aload_3
     113: invokeinterface #88,  4           // InterfaceMethod org/kohsuke/args4j/OptionHandlerRegistry$OptionHandlerFactory.getHandler:(Lorg/kohsuke/args4j/CmdLineParser;Lorg/kohsuke/args4j/OptionDef;Lorg/kohsuke/args4j/spi/Setter;)Lorg/kohsuke/args4j/spi/OptionHandler;
     118: areturn
     119: new           #71                 // class org/kohsuke/args4j/OptionHandlerRegistry$DefaultConstructorHandlerFactory
     122: dup
     123: aload_0
     124: aload         4
     126: invokespecial #72                 // Method org/kohsuke/args4j/OptionHandlerRegistry$DefaultConstructorHandlerFactory."<init>":(Lorg/kohsuke/args4j/OptionHandlerRegistry;Ljava/lang/Class;)V
     129: aload_1
     130: aload_2
     131: aload_3
     132: invokevirtual #89                 // Method org/kohsuke/args4j/OptionHandlerRegistry$DefaultConstructorHandlerFactory.getHandler:(Lorg/kohsuke/args4j/CmdLineParser;Lorg/kohsuke/args4j/OptionDef;Lorg/kohsuke/args4j/spi/Setter;)Lorg/kohsuke/args4j/spi/OptionHandler;
     135: areturn

  static java.lang.reflect.Constructor access$000(java.lang.Class);
    Code:
       0: aload_0
       1: invokestatic  #1                  // Method getConstructor:(Ljava/lang/Class;)Ljava/lang/reflect/Constructor;
       4: areturn
}
