Compiled from "Runnables.java"
public final class org.apache.pulsar.common.util.Runnables {
  private static final org.slf4j.Logger LOGGER;

  private org.apache.pulsar.common.util.Runnables();
    Code:
       0: aload_0
       1: invokespecial #2                  // Method java/lang/Object."<init>":()V
       4: return

  public static java.lang.Runnable catchingAndLoggingThrowables(java.lang.Runnable);
    Code:
       0: new           #3                  // class org/apache/pulsar/common/util/Runnables$CatchingAndLoggingRunnable
       3: dup
       4: aload_0
       5: aconst_null
       6: invokespecial #4                  // Method org/apache/pulsar/common/util/Runnables$CatchingAndLoggingRunnable."<init>":(Ljava/lang/Runnable;Lorg/apache/pulsar/common/util/Runnables$1;)V
       9: areturn

  static org.slf4j.Logger access$100();
    Code:
       0: getstatic     #1                  // Field LOGGER:Lorg/slf4j/Logger;
       3: areturn

  static {};
    Code:
       0: ldc           #5                  // class org/apache/pulsar/common/util/Runnables
       2: invokestatic  #6                  // Method org/slf4j/LoggerFactory.getLogger:(Ljava/lang/Class;)Lorg/slf4j/Logger;
       5: putstatic     #1                  // Field LOGGER:Lorg/slf4j/Logger;
       8: return
}
