Compiled from "AccessConstraintDescriptionProviderUtil.java"
public class org.jboss.as.controller.access.management.AccessConstraintDescriptionProviderUtil {
  public org.jboss.as.controller.access.management.AccessConstraintDescriptionProviderUtil();
    Code:
       0: aload_0
       1: invokespecial #2                  // Method java/lang/Object."<init>":()V
       4: return

  public static void addAccessConstraints(org.jboss.dmr.ModelNode, java.util.List<org.jboss.as.controller.access.management.AccessConstraintDefinition>, java.util.Locale);
    Code:
       0: aload_1
       1: invokeinterface #3,  1            // InterfaceMethod java/util/List.size:()I
       6: ifle          188
       9: new           #4                  // class org/jboss/dmr/ModelNode
      12: dup
      13: invokespecial #5                  // Method org/jboss/dmr/ModelNode."<init>":()V
      16: astore_3
      17: aload_1
      18: invokeinterface #6,  1            // InterfaceMethod java/util/List.iterator:()Ljava/util/Iterator;
      23: astore        4
      25: aload         4
      27: invokeinterface #7,  1            // InterfaceMethod java/util/Iterator.hasNext:()Z
      32: ifeq          177
      35: aload         4
      37: invokeinterface #8,  1            // InterfaceMethod java/util/Iterator.next:()Ljava/lang/Object;
      42: checkcast     #9                  // class org/jboss/as/controller/access/management/AccessConstraintDefinition
      45: astore        5
      47: aload_3
      48: iconst_2
      49: anewarray     #10                 // class java/lang/String
      52: dup
      53: iconst_0
      54: aload         5
      56: invokeinterface #11,  1           // InterfaceMethod org/jboss/as/controller/access/management/AccessConstraintDefinition.getType:()Ljava/lang/String;
      61: aastore
      62: dup
      63: iconst_1
      64: aload         5
      66: invokeinterface #12,  1           // InterfaceMethod org/jboss/as/controller/access/management/AccessConstraintDefinition.getName:()Ljava/lang/String;
      71: aastore
      72: invokevirtual #13                 // Method org/jboss/dmr/ModelNode.get:([Ljava/lang/String;)Lorg/jboss/dmr/ModelNode;
      75: astore        6
      77: aload         6
      79: ldc           #14                 // String type
      81: invokevirtual #15                 // Method org/jboss/dmr/ModelNode.get:(Ljava/lang/String;)Lorg/jboss/dmr/ModelNode;
      84: aload         5
      86: invokeinterface #16,  1           // InterfaceMethod org/jboss/as/controller/access/management/AccessConstraintDefinition.isCore:()Z
      91: ifeq          99
      94: ldc           #17                 // String core
      96: goto          106
      99: aload         5
     101: invokeinterface #18,  1           // InterfaceMethod org/jboss/as/controller/access/management/AccessConstraintDefinition.getSubsystemName:()Ljava/lang/String;
     106: invokevirtual #19                 // Method org/jboss/dmr/ModelNode.set:(Ljava/lang/String;)Lorg/jboss/dmr/ModelNode;
     109: pop
     110: aload         5
     112: aload_2
     113: invokeinterface #20,  2           // InterfaceMethod org/jboss/as/controller/access/management/AccessConstraintDefinition.getDescription:(Ljava/util/Locale;)Ljava/lang/String;
     118: astore        7
     120: aload         7
     122: ifnull        138
     125: aload         6
     127: ldc           #21                 // String description
     129: invokevirtual #15                 // Method org/jboss/dmr/ModelNode.get:(Ljava/lang/String;)Lorg/jboss/dmr/ModelNode;
     132: aload         7
     134: invokevirtual #19                 // Method org/jboss/dmr/ModelNode.set:(Ljava/lang/String;)Lorg/jboss/dmr/ModelNode;
     137: pop
     138: aload         5
     140: aload_2
     141: invokeinterface #22,  2           // InterfaceMethod org/jboss/as/controller/access/management/AccessConstraintDefinition.getModelDescriptionDetails:(Ljava/util/Locale;)Lorg/jboss/dmr/ModelNode;
     146: astore        8
     148: aload         8
     150: ifnull        174
     153: aload         8
     155: invokevirtual #23                 // Method org/jboss/dmr/ModelNode.isDefined:()Z
     158: ifeq          174
     161: aload         6
     163: ldc           #24                 // String details
     165: invokevirtual #15                 // Method org/jboss/dmr/ModelNode.get:(Ljava/lang/String;)Lorg/jboss/dmr/ModelNode;
     168: aload         8
     170: invokevirtual #25                 // Method org/jboss/dmr/ModelNode.set:(Lorg/jboss/dmr/ModelNode;)Lorg/jboss/dmr/ModelNode;
     173: pop
     174: goto          25
     177: aload_0
     178: ldc           #26                 // String access-constraints
     180: invokevirtual #15                 // Method org/jboss/dmr/ModelNode.get:(Ljava/lang/String;)Lorg/jboss/dmr/ModelNode;
     183: aload_3
     184: invokevirtual #25                 // Method org/jboss/dmr/ModelNode.set:(Lorg/jboss/dmr/ModelNode;)Lorg/jboss/dmr/ModelNode;
     187: pop
     188: return
}
