Compiled from "BackOffConfig.java"
public final class net.yudichev.jiotty.common.async.backoff.BackOffConfig implements net.yudichev.jiotty.common.async.backoff.BackOffProvider$BaseBackOffConfig {
  private final java.time.Duration maxInterval;

  private final java.time.Duration initialInterval;

  private final java.time.Duration maxElapsedTime;

  private final double multiplier;

  private final double randomizationFactor;

  private static final byte STAGE_INITIALIZING;

  private static final byte STAGE_UNINITIALIZED;

  private static final byte STAGE_INITIALIZED;

  private volatile transient net.yudichev.jiotty.common.async.backoff.BackOffConfig$InitShim initShim;

  private net.yudichev.jiotty.common.async.backoff.BackOffConfig(net.yudichev.jiotty.common.async.backoff.BackOffConfig$Builder);
    Code:
       0: aload_0
       1: invokespecial #1                  // Method java/lang/Object."<init>":()V
       4: aload_0
       5: new           #2                  // class net/yudichev/jiotty/common/async/backoff/BackOffConfig$InitShim
       8: dup
       9: aload_0
      10: invokespecial #3                  // Method net/yudichev/jiotty/common/async/backoff/BackOffConfig$InitShim."<init>":(Lnet/yudichev/jiotty/common/async/backoff/BackOffConfig;)V
      13: putfield      #4                  // Field initShim:Lnet/yudichev/jiotty/common/async/backoff/BackOffConfig$InitShim;
      16: aload_1
      17: getfield      #5                  // Field net/yudichev/jiotty/common/async/backoff/BackOffConfig$Builder.maxInterval:Ljava/time/Duration;
      20: ifnull        34
      23: aload_0
      24: getfield      #4                  // Field initShim:Lnet/yudichev/jiotty/common/async/backoff/BackOffConfig$InitShim;
      27: aload_1
      28: getfield      #5                  // Field net/yudichev/jiotty/common/async/backoff/BackOffConfig$Builder.maxInterval:Ljava/time/Duration;
      31: invokevirtual #6                  // Method net/yudichev/jiotty/common/async/backoff/BackOffConfig$InitShim.setMaxInterval:(Ljava/time/Duration;)V
      34: aload_1
      35: getfield      #7                  // Field net/yudichev/jiotty/common/async/backoff/BackOffConfig$Builder.initialInterval:Ljava/time/Duration;
      38: ifnull        52
      41: aload_0
      42: getfield      #4                  // Field initShim:Lnet/yudichev/jiotty/common/async/backoff/BackOffConfig$InitShim;
      45: aload_1
      46: getfield      #7                  // Field net/yudichev/jiotty/common/async/backoff/BackOffConfig$Builder.initialInterval:Ljava/time/Duration;
      49: invokevirtual #8                  // Method net/yudichev/jiotty/common/async/backoff/BackOffConfig$InitShim.setInitialInterval:(Ljava/time/Duration;)V
      52: aload_1
      53: getfield      #9                  // Field net/yudichev/jiotty/common/async/backoff/BackOffConfig$Builder.maxElapsedTime:Ljava/time/Duration;
      56: ifnull        70
      59: aload_0
      60: getfield      #4                  // Field initShim:Lnet/yudichev/jiotty/common/async/backoff/BackOffConfig$InitShim;
      63: aload_1
      64: getfield      #9                  // Field net/yudichev/jiotty/common/async/backoff/BackOffConfig$Builder.maxElapsedTime:Ljava/time/Duration;
      67: invokevirtual #10                 // Method net/yudichev/jiotty/common/async/backoff/BackOffConfig$InitShim.setMaxElapsedTime:(Ljava/time/Duration;)V
      70: aload_1
      71: invokevirtual #11                 // Method net/yudichev/jiotty/common/async/backoff/BackOffConfig$Builder.multiplierIsSet:()Z
      74: ifeq          88
      77: aload_0
      78: getfield      #4                  // Field initShim:Lnet/yudichev/jiotty/common/async/backoff/BackOffConfig$InitShim;
      81: aload_1
      82: getfield      #12                 // Field net/yudichev/jiotty/common/async/backoff/BackOffConfig$Builder.multiplier:D
      85: invokevirtual #13                 // Method net/yudichev/jiotty/common/async/backoff/BackOffConfig$InitShim.setMultiplier:(D)V
      88: aload_1
      89: invokevirtual #14                 // Method net/yudichev/jiotty/common/async/backoff/BackOffConfig$Builder.randomizationFactorIsSet:()Z
      92: ifeq          106
      95: aload_0
      96: getfield      #4                  // Field initShim:Lnet/yudichev/jiotty/common/async/backoff/BackOffConfig$InitShim;
      99: aload_1
     100: getfield      #15                 // Field net/yudichev/jiotty/common/async/backoff/BackOffConfig$Builder.randomizationFactor:D
     103: invokevirtual #16                 // Method net/yudichev/jiotty/common/async/backoff/BackOffConfig$InitShim.setRandomizationFactor:(D)V
     106: aload_0
     107: aload_0
     108: getfield      #4                  // Field initShim:Lnet/yudichev/jiotty/common/async/backoff/BackOffConfig$InitShim;
     111: invokevirtual #17                 // Method net/yudichev/jiotty/common/async/backoff/BackOffConfig$InitShim.maxInterval:()Ljava/time/Duration;
     114: putfield      #18                 // Field maxInterval:Ljava/time/Duration;
     117: aload_0
     118: aload_0
     119: getfield      #4                  // Field initShim:Lnet/yudichev/jiotty/common/async/backoff/BackOffConfig$InitShim;
     122: invokevirtual #19                 // Method net/yudichev/jiotty/common/async/backoff/BackOffConfig$InitShim.initialInterval:()Ljava/time/Duration;
     125: putfield      #20                 // Field initialInterval:Ljava/time/Duration;
     128: aload_0
     129: aload_0
     130: getfield      #4                  // Field initShim:Lnet/yudichev/jiotty/common/async/backoff/BackOffConfig$InitShim;
     133: invokevirtual #21                 // Method net/yudichev/jiotty/common/async/backoff/BackOffConfig$InitShim.maxElapsedTime:()Ljava/time/Duration;
     136: putfield      #22                 // Field maxElapsedTime:Ljava/time/Duration;
     139: aload_0
     140: aload_0
     141: getfield      #4                  // Field initShim:Lnet/yudichev/jiotty/common/async/backoff/BackOffConfig$InitShim;
     144: invokevirtual #23                 // Method net/yudichev/jiotty/common/async/backoff/BackOffConfig$InitShim.multiplier:()D
     147: putfield      #24                 // Field multiplier:D
     150: aload_0
     151: aload_0
     152: getfield      #4                  // Field initShim:Lnet/yudichev/jiotty/common/async/backoff/BackOffConfig$InitShim;
     155: invokevirtual #25                 // Method net/yudichev/jiotty/common/async/backoff/BackOffConfig$InitShim.randomizationFactor:()D
     158: putfield      #26                 // Field randomizationFactor:D
     161: aload_0
     162: aconst_null
     163: putfield      #4                  // Field initShim:Lnet/yudichev/jiotty/common/async/backoff/BackOffConfig$InitShim;
     166: return

  private net.yudichev.jiotty.common.async.backoff.BackOffConfig(java.time.Duration, java.time.Duration, java.time.Duration, double, double);
    Code:
       0: aload_0
       1: invokespecial #1                  // Method java/lang/Object."<init>":()V
       4: aload_0
       5: new           #2                  // class net/yudichev/jiotty/common/async/backoff/BackOffConfig$InitShim
       8: dup
       9: aload_0
      10: invokespecial #3                  // Method net/yudichev/jiotty/common/async/backoff/BackOffConfig$InitShim."<init>":(Lnet/yudichev/jiotty/common/async/backoff/BackOffConfig;)V
      13: putfield      #4                  // Field initShim:Lnet/yudichev/jiotty/common/async/backoff/BackOffConfig$InitShim;
      16: aload_0
      17: aload_1
      18: putfield      #18                 // Field maxInterval:Ljava/time/Duration;
      21: aload_0
      22: aload_2
      23: putfield      #20                 // Field initialInterval:Ljava/time/Duration;
      26: aload_0
      27: aload_3
      28: putfield      #22                 // Field maxElapsedTime:Ljava/time/Duration;
      31: aload_0
      32: dload         4
      34: putfield      #24                 // Field multiplier:D
      37: aload_0
      38: dload         6
      40: putfield      #26                 // Field randomizationFactor:D
      43: aload_0
      44: aconst_null
      45: putfield      #4                  // Field initShim:Lnet/yudichev/jiotty/common/async/backoff/BackOffConfig$InitShim;
      48: return

  private java.time.Duration maxIntervalInitialize();
    Code:
       0: aload_0
       1: invokespecial #27                 // InterfaceMethod net/yudichev/jiotty/common/async/backoff/BackOffProvider$BaseBackOffConfig.maxInterval:()Ljava/time/Duration;
       4: areturn

  private java.time.Duration initialIntervalInitialize();
    Code:
       0: aload_0
       1: invokespecial #28                 // InterfaceMethod net/yudichev/jiotty/common/async/backoff/BackOffProvider$BaseBackOffConfig.initialInterval:()Ljava/time/Duration;
       4: areturn

  private java.time.Duration maxElapsedTimeInitialize();
    Code:
       0: aload_0
       1: invokespecial #29                 // InterfaceMethod net/yudichev/jiotty/common/async/backoff/BackOffProvider$BaseBackOffConfig.maxElapsedTime:()Ljava/time/Duration;
       4: areturn

  private double multiplierInitialize();
    Code:
       0: aload_0
       1: invokespecial #30                 // InterfaceMethod net/yudichev/jiotty/common/async/backoff/BackOffProvider$BaseBackOffConfig.multiplier:()D
       4: dreturn

  private double randomizationFactorInitialize();
    Code:
       0: aload_0
       1: invokespecial #31                 // InterfaceMethod net/yudichev/jiotty/common/async/backoff/BackOffProvider$BaseBackOffConfig.randomizationFactor:()D
       4: dreturn

  public java.time.Duration maxInterval();
    Code:
       0: aload_0
       1: getfield      #4                  // Field initShim:Lnet/yudichev/jiotty/common/async/backoff/BackOffConfig$InitShim;
       4: astore_1
       5: aload_1
       6: ifnull        16
       9: aload_1
      10: invokevirtual #17                 // Method net/yudichev/jiotty/common/async/backoff/BackOffConfig$InitShim.maxInterval:()Ljava/time/Duration;
      13: goto          20
      16: aload_0
      17: getfield      #18                 // Field maxInterval:Ljava/time/Duration;
      20: areturn

  public java.time.Duration initialInterval();
    Code:
       0: aload_0
       1: getfield      #4                  // Field initShim:Lnet/yudichev/jiotty/common/async/backoff/BackOffConfig$InitShim;
       4: astore_1
       5: aload_1
       6: ifnull        16
       9: aload_1
      10: invokevirtual #19                 // Method net/yudichev/jiotty/common/async/backoff/BackOffConfig$InitShim.initialInterval:()Ljava/time/Duration;
      13: goto          20
      16: aload_0
      17: getfield      #20                 // Field initialInterval:Ljava/time/Duration;
      20: areturn

  public java.time.Duration maxElapsedTime();
    Code:
       0: aload_0
       1: getfield      #4                  // Field initShim:Lnet/yudichev/jiotty/common/async/backoff/BackOffConfig$InitShim;
       4: astore_1
       5: aload_1
       6: ifnull        16
       9: aload_1
      10: invokevirtual #21                 // Method net/yudichev/jiotty/common/async/backoff/BackOffConfig$InitShim.maxElapsedTime:()Ljava/time/Duration;
      13: goto          20
      16: aload_0
      17: getfield      #22                 // Field maxElapsedTime:Ljava/time/Duration;
      20: areturn

  public double multiplier();
    Code:
       0: aload_0
       1: getfield      #4                  // Field initShim:Lnet/yudichev/jiotty/common/async/backoff/BackOffConfig$InitShim;
       4: astore_1
       5: aload_1
       6: ifnull        16
       9: aload_1
      10: invokevirtual #23                 // Method net/yudichev/jiotty/common/async/backoff/BackOffConfig$InitShim.multiplier:()D
      13: goto          20
      16: aload_0
      17: getfield      #24                 // Field multiplier:D
      20: dreturn

  public double randomizationFactor();
    Code:
       0: aload_0
       1: getfield      #4                  // Field initShim:Lnet/yudichev/jiotty/common/async/backoff/BackOffConfig$InitShim;
       4: astore_1
       5: aload_1
       6: ifnull        16
       9: aload_1
      10: invokevirtual #25                 // Method net/yudichev/jiotty/common/async/backoff/BackOffConfig$InitShim.randomizationFactor:()D
      13: goto          20
      16: aload_0
      17: getfield      #26                 // Field randomizationFactor:D
      20: dreturn

  public final net.yudichev.jiotty.common.async.backoff.BackOffConfig withMaxInterval(java.time.Duration);
    Code:
       0: aload_0
       1: getfield      #18                 // Field maxInterval:Ljava/time/Duration;
       4: aload_1
       5: if_acmpne     10
       8: aload_0
       9: areturn
      10: aload_1
      11: ldc           #32                 // String maxInterval
      13: invokestatic  #33                 // Method java/util/Objects.requireNonNull:(Ljava/lang/Object;Ljava/lang/String;)Ljava/lang/Object;
      16: checkcast     #34                 // class java/time/Duration
      19: astore_2
      20: new           #35                 // class net/yudichev/jiotty/common/async/backoff/BackOffConfig
      23: dup
      24: aload_2
      25: aload_0
      26: getfield      #20                 // Field initialInterval:Ljava/time/Duration;
      29: aload_0
      30: getfield      #22                 // Field maxElapsedTime:Ljava/time/Duration;
      33: aload_0
      34: getfield      #24                 // Field multiplier:D
      37: aload_0
      38: getfield      #26                 // Field randomizationFactor:D
      41: invokespecial #36                 // Method "<init>":(Ljava/time/Duration;Ljava/time/Duration;Ljava/time/Duration;DD)V
      44: areturn

  public final net.yudichev.jiotty.common.async.backoff.BackOffConfig withInitialInterval(java.time.Duration);
    Code:
       0: aload_0
       1: getfield      #20                 // Field initialInterval:Ljava/time/Duration;
       4: aload_1
       5: if_acmpne     10
       8: aload_0
       9: areturn
      10: aload_1
      11: ldc           #37                 // String initialInterval
      13: invokestatic  #33                 // Method java/util/Objects.requireNonNull:(Ljava/lang/Object;Ljava/lang/String;)Ljava/lang/Object;
      16: checkcast     #34                 // class java/time/Duration
      19: astore_2
      20: new           #35                 // class net/yudichev/jiotty/common/async/backoff/BackOffConfig
      23: dup
      24: aload_0
      25: getfield      #18                 // Field maxInterval:Ljava/time/Duration;
      28: aload_2
      29: aload_0
      30: getfield      #22                 // Field maxElapsedTime:Ljava/time/Duration;
      33: aload_0
      34: getfield      #24                 // Field multiplier:D
      37: aload_0
      38: getfield      #26                 // Field randomizationFactor:D
      41: invokespecial #36                 // Method "<init>":(Ljava/time/Duration;Ljava/time/Duration;Ljava/time/Duration;DD)V
      44: areturn

  public final net.yudichev.jiotty.common.async.backoff.BackOffConfig withMaxElapsedTime(java.time.Duration);
    Code:
       0: aload_0
       1: getfield      #22                 // Field maxElapsedTime:Ljava/time/Duration;
       4: aload_1
       5: if_acmpne     10
       8: aload_0
       9: areturn
      10: aload_1
      11: ldc           #38                 // String maxElapsedTime
      13: invokestatic  #33                 // Method java/util/Objects.requireNonNull:(Ljava/lang/Object;Ljava/lang/String;)Ljava/lang/Object;
      16: checkcast     #34                 // class java/time/Duration
      19: astore_2
      20: new           #35                 // class net/yudichev/jiotty/common/async/backoff/BackOffConfig
      23: dup
      24: aload_0
      25: getfield      #18                 // Field maxInterval:Ljava/time/Duration;
      28: aload_0
      29: getfield      #20                 // Field initialInterval:Ljava/time/Duration;
      32: aload_2
      33: aload_0
      34: getfield      #24                 // Field multiplier:D
      37: aload_0
      38: getfield      #26                 // Field randomizationFactor:D
      41: invokespecial #36                 // Method "<init>":(Ljava/time/Duration;Ljava/time/Duration;Ljava/time/Duration;DD)V
      44: areturn

  public final net.yudichev.jiotty.common.async.backoff.BackOffConfig withMultiplier(double);
    Code:
       0: aload_0
       1: getfield      #24                 // Field multiplier:D
       4: invokestatic  #39                 // Method java/lang/Double.doubleToLongBits:(D)J
       7: dload_1
       8: invokestatic  #39                 // Method java/lang/Double.doubleToLongBits:(D)J
      11: lcmp
      12: ifne          17
      15: aload_0
      16: areturn
      17: new           #35                 // class net/yudichev/jiotty/common/async/backoff/BackOffConfig
      20: dup
      21: aload_0
      22: getfield      #18                 // Field maxInterval:Ljava/time/Duration;
      25: aload_0
      26: getfield      #20                 // Field initialInterval:Ljava/time/Duration;
      29: aload_0
      30: getfield      #22                 // Field maxElapsedTime:Ljava/time/Duration;
      33: dload_1
      34: aload_0
      35: getfield      #26                 // Field randomizationFactor:D
      38: invokespecial #36                 // Method "<init>":(Ljava/time/Duration;Ljava/time/Duration;Ljava/time/Duration;DD)V
      41: areturn

  public final net.yudichev.jiotty.common.async.backoff.BackOffConfig withRandomizationFactor(double);
    Code:
       0: aload_0
       1: getfield      #26                 // Field randomizationFactor:D
       4: invokestatic  #39                 // Method java/lang/Double.doubleToLongBits:(D)J
       7: dload_1
       8: invokestatic  #39                 // Method java/lang/Double.doubleToLongBits:(D)J
      11: lcmp
      12: ifne          17
      15: aload_0
      16: areturn
      17: new           #35                 // class net/yudichev/jiotty/common/async/backoff/BackOffConfig
      20: dup
      21: aload_0
      22: getfield      #18                 // Field maxInterval:Ljava/time/Duration;
      25: aload_0
      26: getfield      #20                 // Field initialInterval:Ljava/time/Duration;
      29: aload_0
      30: getfield      #22                 // Field maxElapsedTime:Ljava/time/Duration;
      33: aload_0
      34: getfield      #24                 // Field multiplier:D
      37: dload_1
      38: invokespecial #36                 // Method "<init>":(Ljava/time/Duration;Ljava/time/Duration;Ljava/time/Duration;DD)V
      41: areturn

  public boolean equals(java.lang.Object);
    Code:
       0: aload_0
       1: aload_1
       2: if_acmpne     7
       5: iconst_1
       6: ireturn
       7: aload_1
       8: instanceof    #35                 // class net/yudichev/jiotty/common/async/backoff/BackOffConfig
      11: ifeq          29
      14: aload_0
      15: aload_1
      16: checkcast     #35                 // class net/yudichev/jiotty/common/async/backoff/BackOffConfig
      19: invokevirtual #40                 // Method equalTo:(Lnet/yudichev/jiotty/common/async/backoff/BackOffConfig;)Z
      22: ifeq          29
      25: iconst_1
      26: goto          30
      29: iconst_0
      30: ireturn

  private boolean equalTo(net.yudichev.jiotty.common.async.backoff.BackOffConfig);
    Code:
       0: aload_0
       1: getfield      #18                 // Field maxInterval:Ljava/time/Duration;
       4: aload_1
       5: getfield      #18                 // Field maxInterval:Ljava/time/Duration;
       8: invokevirtual #41                 // Method java/time/Duration.equals:(Ljava/lang/Object;)Z
      11: ifeq          82
      14: aload_0
      15: getfield      #20                 // Field initialInterval:Ljava/time/Duration;
      18: aload_1
      19: getfield      #20                 // Field initialInterval:Ljava/time/Duration;
      22: invokevirtual #41                 // Method java/time/Duration.equals:(Ljava/lang/Object;)Z
      25: ifeq          82
      28: aload_0
      29: getfield      #22                 // Field maxElapsedTime:Ljava/time/Duration;
      32: aload_1
      33: getfield      #22                 // Field maxElapsedTime:Ljava/time/Duration;
      36: invokevirtual #41                 // Method java/time/Duration.equals:(Ljava/lang/Object;)Z
      39: ifeq          82
      42: aload_0
      43: getfield      #24                 // Field multiplier:D
      46: invokestatic  #39                 // Method java/lang/Double.doubleToLongBits:(D)J
      49: aload_1
      50: getfield      #24                 // Field multiplier:D
      53: invokestatic  #39                 // Method java/lang/Double.doubleToLongBits:(D)J
      56: lcmp
      57: ifne          82
      60: aload_0
      61: getfield      #26                 // Field randomizationFactor:D
      64: invokestatic  #39                 // Method java/lang/Double.doubleToLongBits:(D)J
      67: aload_1
      68: getfield      #26                 // Field randomizationFactor:D
      71: invokestatic  #39                 // Method java/lang/Double.doubleToLongBits:(D)J
      74: lcmp
      75: ifne          82
      78: iconst_1
      79: goto          83
      82: iconst_0
      83: ireturn

  public int hashCode();
    Code:
       0: sipush        5381
       3: istore_1
       4: iload_1
       5: iload_1
       6: iconst_5
       7: ishl
       8: aload_0
       9: getfield      #18                 // Field maxInterval:Ljava/time/Duration;
      12: invokevirtual #42                 // Method java/time/Duration.hashCode:()I
      15: iadd
      16: iadd
      17: istore_1
      18: iload_1
      19: iload_1
      20: iconst_5
      21: ishl
      22: aload_0
      23: getfield      #20                 // Field initialInterval:Ljava/time/Duration;
      26: invokevirtual #42                 // Method java/time/Duration.hashCode:()I
      29: iadd
      30: iadd
      31: istore_1
      32: iload_1
      33: iload_1
      34: iconst_5
      35: ishl
      36: aload_0
      37: getfield      #22                 // Field maxElapsedTime:Ljava/time/Duration;
      40: invokevirtual #42                 // Method java/time/Duration.hashCode:()I
      43: iadd
      44: iadd
      45: istore_1
      46: iload_1
      47: iload_1
      48: iconst_5
      49: ishl
      50: aload_0
      51: getfield      #24                 // Field multiplier:D
      54: invokestatic  #43                 // Method com/google/common/primitives/Doubles.hashCode:(D)I
      57: iadd
      58: iadd
      59: istore_1
      60: iload_1
      61: iload_1
      62: iconst_5
      63: ishl
      64: aload_0
      65: getfield      #26                 // Field randomizationFactor:D
      68: invokestatic  #43                 // Method com/google/common/primitives/Doubles.hashCode:(D)I
      71: iadd
      72: iadd
      73: istore_1
      74: iload_1
      75: ireturn

  public java.lang.String toString();
    Code:
       0: ldc           #44                 // String BackOffConfig
       2: invokestatic  #45                 // Method com/google/common/base/MoreObjects.toStringHelper:(Ljava/lang/String;)Lcom/google/common/base/MoreObjects$ToStringHelper;
       5: invokevirtual #46                 // Method com/google/common/base/MoreObjects$ToStringHelper.omitNullValues:()Lcom/google/common/base/MoreObjects$ToStringHelper;
       8: ldc           #32                 // String maxInterval
      10: aload_0
      11: getfield      #18                 // Field maxInterval:Ljava/time/Duration;
      14: invokevirtual #47                 // Method com/google/common/base/MoreObjects$ToStringHelper.add:(Ljava/lang/String;Ljava/lang/Object;)Lcom/google/common/base/MoreObjects$ToStringHelper;
      17: ldc           #37                 // String initialInterval
      19: aload_0
      20: getfield      #20                 // Field initialInterval:Ljava/time/Duration;
      23: invokevirtual #47                 // Method com/google/common/base/MoreObjects$ToStringHelper.add:(Ljava/lang/String;Ljava/lang/Object;)Lcom/google/common/base/MoreObjects$ToStringHelper;
      26: ldc           #38                 // String maxElapsedTime
      28: aload_0
      29: getfield      #22                 // Field maxElapsedTime:Ljava/time/Duration;
      32: invokevirtual #47                 // Method com/google/common/base/MoreObjects$ToStringHelper.add:(Ljava/lang/String;Ljava/lang/Object;)Lcom/google/common/base/MoreObjects$ToStringHelper;
      35: ldc           #48                 // String multiplier
      37: aload_0
      38: getfield      #24                 // Field multiplier:D
      41: invokevirtual #49                 // Method com/google/common/base/MoreObjects$ToStringHelper.add:(Ljava/lang/String;D)Lcom/google/common/base/MoreObjects$ToStringHelper;
      44: ldc           #50                 // String randomizationFactor
      46: aload_0
      47: getfield      #26                 // Field randomizationFactor:D
      50: invokevirtual #49                 // Method com/google/common/base/MoreObjects$ToStringHelper.add:(Ljava/lang/String;D)Lcom/google/common/base/MoreObjects$ToStringHelper;
      53: invokevirtual #51                 // Method com/google/common/base/MoreObjects$ToStringHelper.toString:()Ljava/lang/String;
      56: areturn

  static net.yudichev.jiotty.common.async.backoff.BackOffConfig copyOf(net.yudichev.jiotty.common.async.backoff.BackOffProvider$BaseBackOffConfig);
    Code:
       0: aload_0
       1: instanceof    #35                 // class net/yudichev/jiotty/common/async/backoff/BackOffConfig
       4: ifeq          12
       7: aload_0
       8: checkcast     #35                 // class net/yudichev/jiotty/common/async/backoff/BackOffConfig
      11: areturn
      12: invokestatic  #52                 // Method builder:()Lnet/yudichev/jiotty/common/async/backoff/BackOffConfig$Builder;
      15: aload_0
      16: invokevirtual #53                 // Method net/yudichev/jiotty/common/async/backoff/BackOffConfig$Builder.from:(Lnet/yudichev/jiotty/common/async/backoff/BackOffProvider$BaseBackOffConfig;)Lnet/yudichev/jiotty/common/async/backoff/BackOffConfig$Builder;
      19: invokevirtual #54                 // Method net/yudichev/jiotty/common/async/backoff/BackOffConfig$Builder.build:()Lnet/yudichev/jiotty/common/async/backoff/BackOffConfig;
      22: areturn

  public static net.yudichev.jiotty.common.async.backoff.BackOffConfig$Builder builder();
    Code:
       0: new           #55                 // class net/yudichev/jiotty/common/async/backoff/BackOffConfig$Builder
       3: dup
       4: invokespecial #56                 // Method net/yudichev/jiotty/common/async/backoff/BackOffConfig$Builder."<init>":()V
       7: areturn
}
