Compiled from "BackingOffExceptionHandlerModule.java"
public final class net.yudichev.jiotty.common.async.backoff.BackingOffExceptionHandlerModule extends net.yudichev.jiotty.common.inject.BaseLifecycleComponentModule implements net.yudichev.jiotty.common.inject.ExposedKeyModule<net.yudichev.jiotty.common.async.backoff.BackingOffExceptionHandler> {
  private final net.yudichev.jiotty.common.inject.BindingSpec<net.yudichev.jiotty.common.async.backoff.BackOffConfig> configSpec;

  private final net.yudichev.jiotty.common.inject.BindingSpec<java.util.function.Predicate<? super java.lang.Throwable>> retryableExceptionPredicateSpec;

  private final com.google.inject.Key<net.yudichev.jiotty.common.async.backoff.BackingOffExceptionHandler> exposedKey;

  private net.yudichev.jiotty.common.async.backoff.BackingOffExceptionHandlerModule(net.yudichev.jiotty.common.inject.BindingSpec<java.util.function.Predicate<? super java.lang.Throwable>>, net.yudichev.jiotty.common.inject.BindingSpec<net.yudichev.jiotty.common.async.backoff.BackOffConfig>, net.yudichev.jiotty.common.inject.SpecifiedAnnotation);
    Code:
       0: aload_0
       1: invokespecial #1                  // Method net/yudichev/jiotty/common/inject/BaseLifecycleComponentModule."<init>":()V
       4: aload_0
       5: aload_1
       6: invokestatic  #2                  // Method com/google/common/base/Preconditions.checkNotNull:(Ljava/lang/Object;)Ljava/lang/Object;
       9: checkcast     #3                  // class net/yudichev/jiotty/common/inject/BindingSpec
      12: putfield      #4                  // Field retryableExceptionPredicateSpec:Lnet/yudichev/jiotty/common/inject/BindingSpec;
      15: aload_0
      16: aload_2
      17: invokestatic  #2                  // Method com/google/common/base/Preconditions.checkNotNull:(Ljava/lang/Object;)Ljava/lang/Object;
      20: checkcast     #3                  // class net/yudichev/jiotty/common/inject/BindingSpec
      23: putfield      #5                  // Field configSpec:Lnet/yudichev/jiotty/common/inject/BindingSpec;
      26: aload_0
      27: aload_3
      28: aload_0
      29: invokespecial #6                  // InterfaceMethod net/yudichev/jiotty/common/inject/ExposedKeyModule.getExposedKey:()Lcom/google/inject/Key;
      32: invokevirtual #7                  // Method com/google/inject/Key.getTypeLiteral:()Lcom/google/inject/TypeLiteral;
      35: invokevirtual #8                  // Method net/yudichev/jiotty/common/inject/SpecifiedAnnotation.specify:(Lcom/google/inject/TypeLiteral;)Lcom/google/inject/Key;
      38: putfield      #9                  // Field exposedKey:Lcom/google/inject/Key;
      41: return

  public static net.yudichev.jiotty.common.async.backoff.BackingOffExceptionHandlerModule$Builder builder();
    Code:
       0: new           #10                 // class net/yudichev/jiotty/common/async/backoff/BackingOffExceptionHandlerModule$Builder
       3: dup
       4: invokespecial #11                 // Method net/yudichev/jiotty/common/async/backoff/BackingOffExceptionHandlerModule$Builder."<init>":()V
       7: areturn

  public com.google.inject.Key<net.yudichev.jiotty.common.async.backoff.BackingOffExceptionHandler> getExposedKey();
    Code:
       0: aload_0
       1: getfield      #9                  // Field exposedKey:Lcom/google/inject/Key;
       4: areturn

  protected void configure();
    Code:
       0: aload_0
       1: getfield      #5                  // Field configSpec:Lnet/yudichev/jiotty/common/inject/BindingSpec;
       4: ldc           #12                 // class net/yudichev/jiotty/common/async/backoff/BackOffConfig
       6: invokevirtual #13                 // Method net/yudichev/jiotty/common/inject/BindingSpec.bind:(Ljava/lang/Class;)Lnet/yudichev/jiotty/common/inject/BindingSpec$AnnotatedBindingMethodChoice;
       9: ldc           #14                 // class net/yudichev/jiotty/common/async/backoff/BackOffProvider$Dependency
      11: invokeinterface #15,  2           // InterfaceMethod net/yudichev/jiotty/common/inject/BindingSpec$AnnotatedBindingMethodChoice.annotatedWith:(Ljava/lang/Class;)Lnet/yudichev/jiotty/common/inject/BindingSpec$ScopedBindingMethodChoice;
      16: aload_0
      17: invokedynamic #16,  0             // InvokeDynamic #0:accept:(Lnet/yudichev/jiotty/common/async/backoff/BackingOffExceptionHandlerModule;)Ljava/util/function/Consumer;
      22: invokeinterface #17,  2           // InterfaceMethod net/yudichev/jiotty/common/inject/BindingSpec$ScopedBindingMethodChoice.installedBy:(Ljava/util/function/Consumer;)Lcom/google/inject/Key;
      27: pop
      28: aload_0
      29: ldc           #18                 // class net/yudichev/jiotty/common/lang/backoff/BackOff
      31: invokevirtual #19                 // Method bind:(Ljava/lang/Class;)Lcom/google/inject/binder/AnnotatedBindingBuilder;
      34: ldc           #20                 // class net/yudichev/jiotty/common/async/backoff/BackingOffExceptionHandlerImpl$Dependency
      36: invokeinterface #21,  2           // InterfaceMethod com/google/inject/binder/AnnotatedBindingBuilder.annotatedWith:(Ljava/lang/Class;)Lcom/google/inject/binder/LinkedBindingBuilder;
      41: ldc           #22                 // class net/yudichev/jiotty/common/async/backoff/BackOffProvider
      43: invokeinterface #23,  2           // InterfaceMethod com/google/inject/binder/LinkedBindingBuilder.toProvider:(Ljava/lang/Class;)Lcom/google/inject/binder/ScopedBindingBuilder;
      48: pop
      49: aload_0
      50: getfield      #4                  // Field retryableExceptionPredicateSpec:Lnet/yudichev/jiotty/common/inject/BindingSpec;
      53: new           #24                 // class net/yudichev/jiotty/common/async/backoff/BackingOffExceptionHandlerModule$1
      56: dup
      57: aload_0
      58: invokespecial #25                 // Method net/yudichev/jiotty/common/async/backoff/BackingOffExceptionHandlerModule$1."<init>":(Lnet/yudichev/jiotty/common/async/backoff/BackingOffExceptionHandlerModule;)V
      61: invokevirtual #26                 // Method net/yudichev/jiotty/common/inject/BindingSpec.bind:(Lcom/google/inject/TypeLiteral;)Lnet/yudichev/jiotty/common/inject/BindingSpec$AnnotatedBindingMethodChoice;
      64: ldc           #20                 // class net/yudichev/jiotty/common/async/backoff/BackingOffExceptionHandlerImpl$Dependency
      66: invokeinterface #15,  2           // InterfaceMethod net/yudichev/jiotty/common/inject/BindingSpec$AnnotatedBindingMethodChoice.annotatedWith:(Ljava/lang/Class;)Lnet/yudichev/jiotty/common/inject/BindingSpec$ScopedBindingMethodChoice;
      71: aload_0
      72: invokedynamic #16,  0             // InvokeDynamic #0:accept:(Lnet/yudichev/jiotty/common/async/backoff/BackingOffExceptionHandlerModule;)Ljava/util/function/Consumer;
      77: invokeinterface #17,  2           // InterfaceMethod net/yudichev/jiotty/common/inject/BindingSpec$ScopedBindingMethodChoice.installedBy:(Ljava/util/function/Consumer;)Lcom/google/inject/Key;
      82: pop
      83: aload_0
      84: aload_0
      85: getfield      #9                  // Field exposedKey:Lcom/google/inject/Key;
      88: invokevirtual #27                 // Method bind:(Lcom/google/inject/Key;)Lcom/google/inject/binder/LinkedBindingBuilder;
      91: ldc           #28                 // class net/yudichev/jiotty/common/async/backoff/BackingOffExceptionHandlerImpl
      93: invokeinterface #29,  2           // InterfaceMethod com/google/inject/binder/LinkedBindingBuilder.to:(Ljava/lang/Class;)Lcom/google/inject/binder/ScopedBindingBuilder;
      98: pop
      99: aload_0
     100: aload_0
     101: getfield      #9                  // Field exposedKey:Lcom/google/inject/Key;
     104: invokevirtual #30                 // Method expose:(Lcom/google/inject/Key;)V
     107: return
}
