Compiled from "UnaryArithmeticOperation.java"
public class org.hibernate.jpa.criteria.expression.UnaryArithmeticOperation<T> extends org.hibernate.jpa.criteria.expression.ExpressionImpl<T> implements org.hibernate.jpa.criteria.expression.UnaryOperatorExpression<T>, java.io.Serializable {
  private final org.hibernate.jpa.criteria.expression.UnaryArithmeticOperation$Operation operation;

  private final javax.persistence.criteria.Expression<T> operand;

  public org.hibernate.jpa.criteria.expression.UnaryArithmeticOperation(org.hibernate.jpa.criteria.CriteriaBuilderImpl, org.hibernate.jpa.criteria.expression.UnaryArithmeticOperation$Operation, javax.persistence.criteria.Expression<T>);
    Code:
       0: aload_0
       1: aload_1
       2: aload_3
       3: invokeinterface #1,  1            // InterfaceMethod javax/persistence/criteria/Expression.getJavaType:()Ljava/lang/Class;
       8: invokespecial #2                  // Method org/hibernate/jpa/criteria/expression/ExpressionImpl."<init>":(Lorg/hibernate/jpa/criteria/CriteriaBuilderImpl;Ljava/lang/Class;)V
      11: aload_0
      12: aload_2
      13: putfield      #3                  // Field operation:Lorg/hibernate/jpa/criteria/expression/UnaryArithmeticOperation$Operation;
      16: aload_0
      17: aload_3
      18: putfield      #4                  // Field operand:Ljavax/persistence/criteria/Expression;
      21: return

  public org.hibernate.jpa.criteria.expression.UnaryArithmeticOperation$Operation getOperation();
    Code:
       0: aload_0
       1: getfield      #3                  // Field operation:Lorg/hibernate/jpa/criteria/expression/UnaryArithmeticOperation$Operation;
       4: areturn

  public javax.persistence.criteria.Expression<T> getOperand();
    Code:
       0: aload_0
       1: getfield      #4                  // Field operand:Ljavax/persistence/criteria/Expression;
       4: areturn

  public void registerParameters(org.hibernate.jpa.criteria.ParameterRegistry);
    Code:
       0: aload_0
       1: invokevirtual #5                  // Method getOperand:()Ljavax/persistence/criteria/Expression;
       4: aload_1
       5: invokestatic  #6                  // Method org/hibernate/jpa/criteria/ParameterContainer$Helper.possibleParameter:(Ljavax/persistence/criteria/Selection;Lorg/hibernate/jpa/criteria/ParameterRegistry;)V
       8: return

  public java.lang.String render(org.hibernate.jpa.criteria.compile.RenderingContext);
    Code:
       0: new           #7                  // class java/lang/StringBuilder
       3: dup
       4: invokespecial #8                  // Method java/lang/StringBuilder."<init>":()V
       7: aload_0
       8: invokevirtual #9                  // Method getOperation:()Lorg/hibernate/jpa/criteria/expression/UnaryArithmeticOperation$Operation;
      11: getstatic     #10                 // Field org/hibernate/jpa/criteria/expression/UnaryArithmeticOperation$Operation.UNARY_MINUS:Lorg/hibernate/jpa/criteria/expression/UnaryArithmeticOperation$Operation;
      14: if_acmpne     22
      17: bipush        45
      19: goto          24
      22: bipush        43
      24: invokevirtual #11                 // Method java/lang/StringBuilder.append:(C)Ljava/lang/StringBuilder;
      27: aload_0
      28: invokevirtual #5                  // Method getOperand:()Ljavax/persistence/criteria/Expression;
      31: checkcast     #12                 // class org/hibernate/jpa/criteria/Renderable
      34: aload_1
      35: invokeinterface #13,  2           // InterfaceMethod org/hibernate/jpa/criteria/Renderable.render:(Lorg/hibernate/jpa/criteria/compile/RenderingContext;)Ljava/lang/String;
      40: invokevirtual #14                 // Method java/lang/StringBuilder.append:(Ljava/lang/String;)Ljava/lang/StringBuilder;
      43: invokevirtual #15                 // Method java/lang/StringBuilder.toString:()Ljava/lang/String;
      46: areturn

  public java.lang.String renderProjection(org.hibernate.jpa.criteria.compile.RenderingContext);
    Code:
       0: aload_0
       1: aload_1
       2: invokevirtual #16                 // Method render:(Lorg/hibernate/jpa/criteria/compile/RenderingContext;)Ljava/lang/String;
       5: areturn
}
