Compiled from "DefaultDataBuffer.java"
class org.springframework.core.io.buffer.DefaultDataBuffer$SlicedDefaultDataBuffer extends org.springframework.core.io.buffer.DefaultDataBuffer {
  org.springframework.core.io.buffer.DefaultDataBuffer$SlicedDefaultDataBuffer(java.nio.ByteBuffer, org.springframework.core.io.buffer.DefaultDataBufferFactory, int);
    Code:
       0: aload_0
       1: aload_2
       2: aload_1
       3: aconst_null
       4: invokespecial #1                  // Method org/springframework/core/io/buffer/DefaultDataBuffer."<init>":(Lorg/springframework/core/io/buffer/DefaultDataBufferFactory;Ljava/nio/ByteBuffer;Lorg/springframework/core/io/buffer/DefaultDataBuffer$1;)V
       7: aload_0
       8: iload_3
       9: invokevirtual #2                  // Method writePosition:(I)Lorg/springframework/core/io/buffer/DefaultDataBuffer;
      12: pop
      13: return

  public org.springframework.core.io.buffer.DefaultDataBuffer capacity(int);
    Code:
       0: new           #3                  // class java/lang/UnsupportedOperationException
       3: dup
       4: ldc           #4                  // String Changing the capacity of a sliced buffer is not supported
       6: invokespecial #5                  // Method java/lang/UnsupportedOperationException."<init>":(Ljava/lang/String;)V
       9: athrow

  public org.springframework.core.io.buffer.DataBuffer slice(int, int);
    Code:
       0: aload_0
       1: iload_1
       2: iload_2
       3: invokespecial #6                  // Method org/springframework/core/io/buffer/DefaultDataBuffer.slice:(II)Lorg/springframework/core/io/buffer/DefaultDataBuffer;
       6: areturn

  public org.springframework.core.io.buffer.DataBuffer write(java.nio.ByteBuffer[]);
    Code:
       0: aload_0
       1: aload_1
       2: invokespecial #7                  // Method org/springframework/core/io/buffer/DefaultDataBuffer.write:([Ljava/nio/ByteBuffer;)Lorg/springframework/core/io/buffer/DefaultDataBuffer;
       5: areturn

  public org.springframework.core.io.buffer.DataBuffer write(org.springframework.core.io.buffer.DataBuffer[]);
    Code:
       0: aload_0
       1: aload_1
       2: invokespecial #8                  // Method org/springframework/core/io/buffer/DefaultDataBuffer.write:([Lorg/springframework/core/io/buffer/DataBuffer;)Lorg/springframework/core/io/buffer/DefaultDataBuffer;
       5: areturn

  public org.springframework.core.io.buffer.DataBuffer write(byte[], int, int);
    Code:
       0: aload_0
       1: aload_1
       2: iload_2
       3: iload_3
       4: invokespecial #9                  // Method org/springframework/core/io/buffer/DefaultDataBuffer.write:([BII)Lorg/springframework/core/io/buffer/DefaultDataBuffer;
       7: areturn

  public org.springframework.core.io.buffer.DataBuffer write(byte[]);
    Code:
       0: aload_0
       1: aload_1
       2: invokespecial #10                 // Method org/springframework/core/io/buffer/DefaultDataBuffer.write:([B)Lorg/springframework/core/io/buffer/DefaultDataBuffer;
       5: areturn

  public org.springframework.core.io.buffer.DataBuffer write(byte);
    Code:
       0: aload_0
       1: iload_1
       2: invokespecial #11                 // Method org/springframework/core/io/buffer/DefaultDataBuffer.write:(B)Lorg/springframework/core/io/buffer/DefaultDataBuffer;
       5: areturn

  public org.springframework.core.io.buffer.DataBuffer read(byte[], int, int);
    Code:
       0: aload_0
       1: aload_1
       2: iload_2
       3: iload_3
       4: invokespecial #12                 // Method org/springframework/core/io/buffer/DefaultDataBuffer.read:([BII)Lorg/springframework/core/io/buffer/DefaultDataBuffer;
       7: areturn

  public org.springframework.core.io.buffer.DataBuffer read(byte[]);
    Code:
       0: aload_0
       1: aload_1
       2: invokespecial #13                 // Method org/springframework/core/io/buffer/DefaultDataBuffer.read:([B)Lorg/springframework/core/io/buffer/DefaultDataBuffer;
       5: areturn

  public org.springframework.core.io.buffer.DataBuffer writePosition(int);
    Code:
       0: aload_0
       1: iload_1
       2: invokespecial #14                 // Method org/springframework/core/io/buffer/DefaultDataBuffer.writePosition:(I)Lorg/springframework/core/io/buffer/DefaultDataBuffer;
       5: areturn

  public org.springframework.core.io.buffer.DataBuffer readPosition(int);
    Code:
       0: aload_0
       1: iload_1
       2: invokespecial #15                 // Method org/springframework/core/io/buffer/DefaultDataBuffer.readPosition:(I)Lorg/springframework/core/io/buffer/DefaultDataBuffer;
       5: areturn

  public org.springframework.core.io.buffer.DataBuffer capacity(int);
    Code:
       0: aload_0
       1: iload_1
       2: invokevirtual #16                 // Method capacity:(I)Lorg/springframework/core/io/buffer/DefaultDataBuffer;
       5: areturn

  public org.springframework.core.io.buffer.DataBufferFactory factory();
    Code:
       0: aload_0
       1: invokespecial #17                 // Method org/springframework/core/io/buffer/DefaultDataBuffer.factory:()Lorg/springframework/core/io/buffer/DefaultDataBufferFactory;
       4: areturn
}
