Compiled from "ConnectorServerFactoryBean.java"
class org.springframework.jmx.support.ConnectorServerFactoryBean$1 extends java.lang.Thread {
  final javax.management.remote.JMXConnectorServer val$serverToStart;

  final org.springframework.jmx.support.ConnectorServerFactoryBean this$0;

  org.springframework.jmx.support.ConnectorServerFactoryBean$1(org.springframework.jmx.support.ConnectorServerFactoryBean, javax.management.remote.JMXConnectorServer);
    Code:
       0: aload_0
       1: aload_1
       2: putfield      #1                  // Field this$0:Lorg/springframework/jmx/support/ConnectorServerFactoryBean;
       5: aload_0
       6: aload_2
       7: putfield      #2                  // Field val$serverToStart:Ljavax/management/remote/JMXConnectorServer;
      10: aload_0
      11: invokespecial #3                  // Method java/lang/Thread."<init>":()V
      14: return

  public void run();
    Code:
       0: aload_0
       1: getfield      #2                  // Field val$serverToStart:Ljavax/management/remote/JMXConnectorServer;
       4: invokevirtual #4                  // Method javax/management/remote/JMXConnectorServer.start:()V
       7: goto          22
      10: astore_1
      11: new           #6                  // class org/springframework/jmx/JmxException
      14: dup
      15: ldc           #7                  // String Could not start JMX connector server after delay
      17: aload_1
      18: invokespecial #8                  // Method org/springframework/jmx/JmxException."<init>":(Ljava/lang/String;Ljava/lang/Throwable;)V
      21: athrow
      22: return
    Exception table:
       from    to  target type
           0     7    10   Class java/io/IOException
}
