Compiled from "CompilationUnitModelResolver.java"
public abstract class net.jangaroo.jooc.model.CompilationUnitModelResolver {
  public net.jangaroo.jooc.model.CompilationUnitModelResolver();
    Code:
       0: aload_0
       1: invokespecial #1                  // Method java/lang/Object."<init>":()V
       4: return

  public abstract net.jangaroo.jooc.model.CompilationUnitModel resolveCompilationUnit(java.lang.String);

  public boolean implementsInterface(net.jangaroo.jooc.model.CompilationUnitModel, java.lang.String);
    Code:
       0: aload_1
       1: ifnonnull     6
       4: iconst_0
       5: ireturn
       6: aload_1
       7: invokevirtual #2                  // Method net/jangaroo/jooc/model/CompilationUnitModel.getClassModel:()Lnet/jangaroo/jooc/model/ClassModel;
      10: astore_3
      11: aload_3
      12: invokevirtual #3                  // Method net/jangaroo/jooc/model/ClassModel.isInterface:()Z
      15: ifeq          31
      18: aload_2
      19: aload_1
      20: invokevirtual #4                  // Method net/jangaroo/jooc/model/CompilationUnitModel.getQName:()Ljava/lang/String;
      23: invokevirtual #5                  // Method java/lang/String.equals:(Ljava/lang/Object;)Z
      26: ifeq          31
      29: iconst_1
      30: ireturn
      31: aload_3
      32: invokevirtual #6                  // Method net/jangaroo/jooc/model/ClassModel.getInterfaces:()Ljava/util/List;
      35: invokeinterface #7,  1            // InterfaceMethod java/util/List.iterator:()Ljava/util/Iterator;
      40: astore        4
      42: aload         4
      44: invokeinterface #8,  1            // InterfaceMethod java/util/Iterator.hasNext:()Z
      49: ifeq          120
      52: aload         4
      54: invokeinterface #9,  1            // InterfaceMethod java/util/Iterator.next:()Ljava/lang/Object;
      59: checkcast     #10                 // class java/lang/String
      62: astore        5
      64: aload_0
      65: aload         5
      67: invokevirtual #11                 // Method resolveCompilationUnit:(Ljava/lang/String;)Lnet/jangaroo/jooc/model/CompilationUnitModel;
      70: astore        6
      72: aload         6
      74: ifnonnull     105
      77: new           #12                 // class java/lang/NullPointerException
      80: dup
      81: new           #13                 // class java/lang/StringBuilder
      84: dup
      85: invokespecial #14                 // Method java/lang/StringBuilder."<init>":()V
      88: ldc           #15                 // String AS3 compilation unit not found:
      90: invokevirtual #16                 // Method java/lang/StringBuilder.append:(Ljava/lang/String;)Ljava/lang/StringBuilder;
      93: aload         5
      95: invokevirtual #16                 // Method java/lang/StringBuilder.append:(Ljava/lang/String;)Ljava/lang/StringBuilder;
      98: invokevirtual #17                 // Method java/lang/StringBuilder.toString:()Ljava/lang/String;
     101: invokespecial #18                 // Method java/lang/NullPointerException."<init>":(Ljava/lang/String;)V
     104: athrow
     105: aload_0
     106: aload         6
     108: aload_2
     109: invokevirtual #19                 // Method implementsInterface:(Lnet/jangaroo/jooc/model/CompilationUnitModel;Ljava/lang/String;)Z
     112: ifeq          117
     115: iconst_1
     116: ireturn
     117: goto          42
     120: aload_0
     121: aload_0
     122: aload_3
     123: invokevirtual #20                 // Method getSuperclassCompilationUnit:(Lnet/jangaroo/jooc/model/ClassModel;)Lnet/jangaroo/jooc/model/CompilationUnitModel;
     126: aload_2
     127: invokevirtual #19                 // Method implementsInterface:(Lnet/jangaroo/jooc/model/CompilationUnitModel;Ljava/lang/String;)Z
     130: ireturn

  public net.jangaroo.jooc.model.CompilationUnitModel getSuperclassCompilationUnit(net.jangaroo.jooc.model.ClassModel);
    Code:
       0: aload_1
       1: invokevirtual #21                 // Method net/jangaroo/jooc/model/ClassModel.getSuperclass:()Ljava/lang/String;
       4: astore_2
       5: aload_2
       6: ifnonnull     13
       9: aconst_null
      10: goto          18
      13: aload_0
      14: aload_2
      15: invokevirtual #11                 // Method resolveCompilationUnit:(Ljava/lang/String;)Lnet/jangaroo/jooc/model/CompilationUnitModel;
      18: areturn

  public net.jangaroo.jooc.model.ClassModel getSuperclass(net.jangaroo.jooc.model.ClassModel);
    Code:
       0: aload_0
       1: aload_1
       2: invokevirtual #20                 // Method getSuperclassCompilationUnit:(Lnet/jangaroo/jooc/model/ClassModel;)Lnet/jangaroo/jooc/model/CompilationUnitModel;
       5: astore_2
       6: aload_2
       7: ifnonnull     14
      10: aconst_null
      11: goto          18
      14: aload_2
      15: invokevirtual #2                  // Method net/jangaroo/jooc/model/CompilationUnitModel.getClassModel:()Lnet/jangaroo/jooc/model/ClassModel;
      18: areturn
}
