Compiled from "ReturnModel.java"
public class net.jangaroo.jooc.model.ReturnModel extends net.jangaroo.jooc.model.DocumentedModel implements net.jangaroo.jooc.model.TypedModel {
  private net.jangaroo.jooc.model.MethodModel method;

  public net.jangaroo.jooc.model.ReturnModel(net.jangaroo.jooc.model.MethodModel);
    Code:
       0: aload_0
       1: invokespecial #1                  // Method net/jangaroo/jooc/model/DocumentedModel."<init>":()V
       4: aload_0
       5: aload_1
       6: putfield      #2                  // Field method:Lnet/jangaroo/jooc/model/MethodModel;
       9: return

  public java.lang.String getType();
    Code:
       0: aload_0
       1: getfield      #2                  // Field method:Lnet/jangaroo/jooc/model/MethodModel;
       4: invokevirtual #3                  // Method net/jangaroo/jooc/model/MethodModel.getType:()Ljava/lang/String;
       7: areturn

  public void setType(java.lang.String);
    Code:
       0: aload_0
       1: getfield      #2                  // Field method:Lnet/jangaroo/jooc/model/MethodModel;
       4: aload_1
       5: invokevirtual #4                  // Method net/jangaroo/jooc/model/MethodModel.setType:(Ljava/lang/String;)V
       8: return

  public void visit(net.jangaroo.jooc.model.ModelVisitor);
    Code:
       0: aload_1
       1: aload_0
       2: invokeinterface #5,  2            // InterfaceMethod net/jangaroo/jooc/model/ModelVisitor.visitReturn:(Lnet/jangaroo/jooc/model/ReturnModel;)V
       7: return

  public boolean equals(java.lang.Object);
    Code:
       0: aload_0
       1: aload_1
       2: if_acmpne     7
       5: iconst_1
       6: ireturn
       7: aload_1
       8: ifnull        22
      11: aload_0
      12: invokevirtual #6                  // Method java/lang/Object.getClass:()Ljava/lang/Class;
      15: aload_1
      16: invokevirtual #6                  // Method java/lang/Object.getClass:()Ljava/lang/Class;
      19: if_acmpeq     24
      22: iconst_0
      23: ireturn
      24: aload_1
      25: checkcast     #7                  // class net/jangaroo/jooc/model/ReturnModel
      28: astore_2
      29: aload_0
      30: invokevirtual #8                  // Method getType:()Ljava/lang/String;
      33: astore_3
      34: aload_3
      35: ifnonnull     53
      38: aload_2
      39: invokevirtual #8                  // Method getType:()Ljava/lang/String;
      42: ifnonnull     49
      45: iconst_1
      46: goto          61
      49: iconst_0
      50: goto          61
      53: aload_3
      54: aload_2
      55: invokevirtual #8                  // Method getType:()Ljava/lang/String;
      58: invokevirtual #9                  // Method java/lang/String.equals:(Ljava/lang/Object;)Z
      61: ireturn

  public int hashCode();
    Code:
       0: aload_0
       1: invokevirtual #8                  // Method getType:()Ljava/lang/String;
       4: ifnonnull     11
       7: iconst_0
       8: goto          18
      11: aload_0
      12: invokevirtual #8                  // Method getType:()Ljava/lang/String;
      15: invokevirtual #10                 // Method java/lang/String.hashCode:()I
      18: ireturn
}
