Compiled from "Redis.kt"
public final class io.vertx.kotlin.redis.client.RedisKt {
  public static final java.lang.Object connectAwait(io.vertx.redis.client.Redis, kotlin.coroutines.Continuation<? super io.vertx.redis.client.RedisConnection>);
    Code:
       0: new           #11                 // class io/vertx/kotlin/redis/client/RedisKt$connectAwait$2
       3: dup
       4: aload_0
       5: invokespecial #15                 // Method io/vertx/kotlin/redis/client/RedisKt$connectAwait$2."<init>":(Lio/vertx/redis/client/Redis;)V
       8: checkcast     #17                 // class kotlin/jvm/functions/Function1
      11: aload_1
      12: invokestatic  #23                 // Method io/vertx/kotlin/coroutines/VertxCoroutineKt.awaitResult:(Lkotlin/jvm/functions/Function1;Lkotlin/coroutines/Continuation;)Ljava/lang/Object;
      15: areturn
}
