Compiled from "ReturnsSmartNulls.java"
public class org.mockito.internal.stubbing.defaultanswers.ReturnsSmartNulls implements org.mockito.stubbing.Answer<java.lang.Object>, java.io.Serializable {
  private static final long serialVersionUID;

  private final org.mockito.stubbing.Answer<java.lang.Object> delegate;

  public org.mockito.internal.stubbing.defaultanswers.ReturnsSmartNulls();
    Code:
       0: aload_0
       1: invokespecial #1                  // Method java/lang/Object."<init>":()V
       4: aload_0
       5: new           #2                  // class org/mockito/internal/stubbing/defaultanswers/ReturnsMoreEmptyValues
       8: dup
       9: invokespecial #3                  // Method org/mockito/internal/stubbing/defaultanswers/ReturnsMoreEmptyValues."<init>":()V
      12: putfield      #4                  // Field delegate:Lorg/mockito/stubbing/Answer;
      15: return

  public java.lang.Object answer(org.mockito.invocation.InvocationOnMock) throws java.lang.Throwable;
    Code:
       0: aload_0
       1: getfield      #4                  // Field delegate:Lorg/mockito/stubbing/Answer;
       4: aload_1
       5: invokeinterface #5,  2            // InterfaceMethod org/mockito/stubbing/Answer.answer:(Lorg/mockito/invocation/InvocationOnMock;)Ljava/lang/Object;
      10: astore_2
      11: aload_2
      12: ifnull        17
      15: aload_2
      16: areturn
      17: aload_1
      18: invokeinterface #6,  1            // InterfaceMethod org/mockito/invocation/InvocationOnMock.getMethod:()Ljava/lang/reflect/Method;
      23: invokevirtual #7                  // Method java/lang/reflect/Method.getReturnType:()Ljava/lang/Class;
      26: astore_3
      27: aload_3
      28: invokevirtual #8                  // Method java/lang/Class.isPrimitive:()Z
      31: ifne          68
      34: aload_3
      35: invokevirtual #9                  // Method java/lang/Class.getModifiers:()I
      38: invokestatic  #10                 // Method java/lang/reflect/Modifier.isFinal:(I)Z
      41: ifne          68
      44: new           #11                 // class org/mockito/internal/debugging/LocationImpl
      47: dup
      48: invokespecial #12                 // Method org/mockito/internal/debugging/LocationImpl."<init>":()V
      51: astore        4
      53: aload_3
      54: new           #13                 // class org/mockito/internal/stubbing/defaultanswers/ReturnsSmartNulls$ThrowsSmartNullPointer
      57: dup
      58: aload_1
      59: aload         4
      61: invokespecial #14                 // Method org/mockito/internal/stubbing/defaultanswers/ReturnsSmartNulls$ThrowsSmartNullPointer."<init>":(Lorg/mockito/invocation/InvocationOnMock;Lorg/mockito/invocation/Location;)V
      64: invokestatic  #15                 // Method org/mockito/Mockito.mock:(Ljava/lang/Class;Lorg/mockito/stubbing/Answer;)Ljava/lang/Object;
      67: areturn
      68: aconst_null
      69: areturn
}
