Compiled from "TriesToReturnSelf.java"
public class org.mockito.internal.stubbing.defaultanswers.TriesToReturnSelf implements org.mockito.stubbing.Answer<java.lang.Object>, java.io.Serializable {
  private final org.mockito.internal.stubbing.defaultanswers.ReturnsEmptyValues defaultReturn;

  public org.mockito.internal.stubbing.defaultanswers.TriesToReturnSelf();
    Code:
       0: aload_0
       1: invokespecial #1                  // Method java/lang/Object."<init>":()V
       4: aload_0
       5: new           #2                  // class org/mockito/internal/stubbing/defaultanswers/ReturnsEmptyValues
       8: dup
       9: invokespecial #3                  // Method org/mockito/internal/stubbing/defaultanswers/ReturnsEmptyValues."<init>":()V
      12: putfield      #4                  // Field defaultReturn:Lorg/mockito/internal/stubbing/defaultanswers/ReturnsEmptyValues;
      15: return

  public java.lang.Object answer(org.mockito.invocation.InvocationOnMock) throws java.lang.Throwable;
    Code:
       0: aload_1
       1: invokeinterface #5,  1            // InterfaceMethod org/mockito/invocation/InvocationOnMock.getMethod:()Ljava/lang/reflect/Method;
       6: invokevirtual #6                  // Method java/lang/reflect/Method.getReturnType:()Ljava/lang/Class;
       9: astore_2
      10: aload_1
      11: invokeinterface #7,  1            // InterfaceMethod org/mockito/invocation/InvocationOnMock.getMock:()Ljava/lang/Object;
      16: astore_3
      17: aload_3
      18: invokestatic  #8                  // Method org/mockito/internal/util/MockUtil.getMockHandler:(Ljava/lang/Object;)Lorg/mockito/internal/InternalMockHandler;
      21: invokeinterface #9,  1            // InterfaceMethod org/mockito/internal/InternalMockHandler.getMockSettings:()Lorg/mockito/mock/MockCreationSettings;
      26: invokeinterface #10,  1           // InterfaceMethod org/mockito/mock/MockCreationSettings.getTypeToMock:()Ljava/lang/Class;
      31: astore        4
      33: aload_2
      34: aload         4
      36: invokevirtual #11                 // Method java/lang/Class.isAssignableFrom:(Ljava/lang/Class;)Z
      39: ifeq          49
      42: aload_1
      43: invokeinterface #7,  1            // InterfaceMethod org/mockito/invocation/InvocationOnMock.getMock:()Ljava/lang/Object;
      48: areturn
      49: aload_0
      50: getfield      #4                  // Field defaultReturn:Lorg/mockito/internal/stubbing/defaultanswers/ReturnsEmptyValues;
      53: aload_2
      54: invokevirtual #12                 // Method org/mockito/internal/stubbing/defaultanswers/ReturnsEmptyValues.returnValueFor:(Ljava/lang/Class;)Ljava/lang/Object;
      57: areturn
}
