public class org.bouncycastle.cert.crmf.EncryptedValueParser {
  private org.bouncycastle.asn1.crmf.EncryptedValue value;

  private org.bouncycastle.cert.crmf.EncryptedValuePadder padder;

  public org.bouncycastle.cert.crmf.EncryptedValueParser(org.bouncycastle.asn1.crmf.EncryptedValue);
    Code:
       0: aload_0
       1: invokespecial #118                // Method java/lang/Object."<init>":()V
       4: aload_0
       5: aload_1
       6: putfield      #114                // Field value:Lorg/bouncycastle/asn1/crmf/EncryptedValue;
       9: return

  public org.bouncycastle.cert.crmf.EncryptedValueParser(org.bouncycastle.asn1.crmf.EncryptedValue, org.bouncycastle.cert.crmf.EncryptedValuePadder);
    Code:
       0: aload_0
       1: invokespecial #118                // Method java/lang/Object."<init>":()V
       4: aload_0
       5: aload_1
       6: putfield      #114                // Field value:Lorg/bouncycastle/asn1/crmf/EncryptedValue;
       9: aload_0
      10: aload_2
      11: putfield      #115                // Field padder:Lorg/bouncycastle/cert/crmf/EncryptedValuePadder;
      14: return

  public org.bouncycastle.asn1.x509.AlgorithmIdentifier getIntendedAlg();
    Code:
       0: aload_0
       1: getfield      #114                // Field value:Lorg/bouncycastle/asn1/crmf/EncryptedValue;
       4: invokevirtual #128                // Method org/bouncycastle/asn1/crmf/EncryptedValue.getIntendedAlg:()Lorg/bouncycastle/asn1/x509/AlgorithmIdentifier;
       7: areturn

  private byte[] decryptValue(org.bouncycastle.cert.crmf.ValueDecryptorGenerator) throws org.bouncycastle.cert.crmf.CRMFException;
    Code:
       0: aload_0
       1: getfield      #114                // Field value:Lorg/bouncycastle/asn1/crmf/EncryptedValue;
       4: invokevirtual #125                // Method org/bouncycastle/asn1/crmf/EncryptedValue.getValueHint:()Lorg/bouncycastle/asn1/ASN1OctetString;
       7: ifnull        18
      10: new           #55                 // class java/lang/UnsupportedOperationException
      13: dup
      14: invokespecial #123                // Method java/lang/UnsupportedOperationException."<init>":()V
      17: athrow
      18: aload_1
      19: aload_0
      20: getfield      #114                // Field value:Lorg/bouncycastle/asn1/crmf/EncryptedValue;
      23: invokevirtual #129                // Method org/bouncycastle/asn1/crmf/EncryptedValue.getKeyAlg:()Lorg/bouncycastle/asn1/x509/AlgorithmIdentifier;
      26: aload_0
      27: getfield      #114                // Field value:Lorg/bouncycastle/asn1/crmf/EncryptedValue;
      30: invokevirtual #130                // Method org/bouncycastle/asn1/crmf/EncryptedValue.getSymmAlg:()Lorg/bouncycastle/asn1/x509/AlgorithmIdentifier;
      33: aload_0
      34: getfield      #114                // Field value:Lorg/bouncycastle/asn1/crmf/EncryptedValue;
      37: invokevirtual #126                // Method org/bouncycastle/asn1/crmf/EncryptedValue.getEncSymmKey:()Lorg/bouncycastle/asn1/DERBitString;
      40: invokevirtual #124                // Method org/bouncycastle/asn1/DERBitString.getBytes:()[B
      43: invokeinterface #139,  4          // InterfaceMethod org/bouncycastle/cert/crmf/ValueDecryptorGenerator.getValueDecryptor:(Lorg/bouncycastle/asn1/x509/AlgorithmIdentifier;Lorg/bouncycastle/asn1/x509/AlgorithmIdentifier;[B)Lorg/bouncycastle/operator/InputDecryptor;
      48: astore_2
      49: aload_2
      50: new           #50                 // class java/io/ByteArrayInputStream
      53: dup
      54: aload_0
      55: getfield      #114                // Field value:Lorg/bouncycastle/asn1/crmf/EncryptedValue;
      58: invokevirtual #127                // Method org/bouncycastle/asn1/crmf/EncryptedValue.getEncValue:()Lorg/bouncycastle/asn1/DERBitString;
      61: invokevirtual #124                // Method org/bouncycastle/asn1/DERBitString.getBytes:()[B
      64: invokespecial #116                // Method java/io/ByteArrayInputStream."<init>":([B)V
      67: invokeinterface #140,  2          // InterfaceMethod org/bouncycastle/operator/InputDecryptor.getInputStream:(Ljava/io/InputStream;)Ljava/io/InputStream;
      72: astore_3
      73: aload_3
      74: invokestatic  #137                // Method org/bouncycastle/util/io/Streams.readAll:(Ljava/io/InputStream;)[B
      77: astore        4
      79: aload_0
      80: getfield      #115                // Field padder:Lorg/bouncycastle/cert/crmf/EncryptedValuePadder;
      83: ifnull        98
      86: aload_0
      87: getfield      #115                // Field padder:Lorg/bouncycastle/cert/crmf/EncryptedValuePadder;
      90: aload         4
      92: invokeinterface #138,  2          // InterfaceMethod org/bouncycastle/cert/crmf/EncryptedValuePadder.getUnpaddedData:([B)[B
      97: areturn
      98: aload         4
     100: areturn
     101: astore        4
     103: new           #61                 // class org/bouncycastle/cert/crmf/CRMFException
     106: dup
     107: new           #54                 // class java/lang/StringBuilder
     110: dup
     111: invokespecial #120                // Method java/lang/StringBuilder."<init>":()V
     114: ldc           #1                  // String Cannot parse decrypted data:
     116: invokevirtual #122                // Method java/lang/StringBuilder.append:(Ljava/lang/String;)Ljava/lang/StringBuilder;
     119: aload         4
     121: invokevirtual #117                // Method java/io/IOException.getMessage:()Ljava/lang/String;
     124: invokevirtual #122                // Method java/lang/StringBuilder.append:(Ljava/lang/String;)Ljava/lang/StringBuilder;
     127: invokevirtual #121                // Method java/lang/StringBuilder.toString:()Ljava/lang/String;
     130: aload         4
     132: invokespecial #134                // Method org/bouncycastle/cert/crmf/CRMFException."<init>":(Ljava/lang/String;Ljava/lang/Throwable;)V
     135: athrow
    Exception table:
       from    to  target type
          73    97   101   Class java/io/IOException
          98   100   101   Class java/io/IOException

  public org.bouncycastle.cert.X509CertificateHolder readCertificateHolder(org.bouncycastle.cert.crmf.ValueDecryptorGenerator) throws org.bouncycastle.cert.crmf.CRMFException;
    Code:
       0: new           #60                 // class org/bouncycastle/cert/X509CertificateHolder
       3: dup
       4: aload_0
       5: aload_1
       6: invokespecial #135                // Method decryptValue:(Lorg/bouncycastle/cert/crmf/ValueDecryptorGenerator;)[B
       9: invokestatic  #132                // Method org/bouncycastle/asn1/x509/Certificate.getInstance:(Ljava/lang/Object;)Lorg/bouncycastle/asn1/x509/Certificate;
      12: invokespecial #133                // Method org/bouncycastle/cert/X509CertificateHolder."<init>":(Lorg/bouncycastle/asn1/x509/Certificate;)V
      15: areturn

  public org.bouncycastle.asn1.pkcs.PrivateKeyInfo readPrivateKeyInfo(org.bouncycastle.cert.crmf.ValueDecryptorGenerator) throws org.bouncycastle.cert.crmf.CRMFException;
    Code:
       0: aload_0
       1: aload_1
       2: invokespecial #135                // Method decryptValue:(Lorg/bouncycastle/cert/crmf/ValueDecryptorGenerator;)[B
       5: invokestatic  #131                // Method org/bouncycastle/asn1/pkcs/PrivateKeyInfo.getInstance:(Ljava/lang/Object;)Lorg/bouncycastle/asn1/pkcs/PrivateKeyInfo;
       8: areturn

  public char[] readPassphrase(org.bouncycastle.cert.crmf.ValueDecryptorGenerator) throws org.bouncycastle.cert.crmf.CRMFException;
    Code:
       0: aload_0
       1: aload_1
       2: invokespecial #135                // Method decryptValue:(Lorg/bouncycastle/cert/crmf/ValueDecryptorGenerator;)[B
       5: invokestatic  #136                // Method org/bouncycastle/util/Strings.fromUTF8ByteArray:([B)Ljava/lang/String;
       8: invokevirtual #119                // Method java/lang/String.toCharArray:()[C
      11: areturn
}
