Compiled from "FileTxnLog.java"
class org.apache.zookeeper.server.persistence.FileTxnLog$PositionInputStream extends java.io.FilterInputStream {
  long position;

  protected org.apache.zookeeper.server.persistence.FileTxnLog$PositionInputStream(java.io.InputStream);
    Code:
       0: aload_0
       1: aload_1
       2: invokespecial #1                  // Method java/io/FilterInputStream."<init>":(Ljava/io/InputStream;)V
       5: aload_0
       6: lconst_0
       7: putfield      #2                  // Field position:J
      10: return

  public int read() throws java.io.IOException;
    Code:
       0: aload_0
       1: invokespecial #3                  // Method java/io/FilterInputStream.read:()I
       4: istore_1
       5: iload_1
       6: iconst_m1
       7: if_icmple     20
      10: aload_0
      11: dup
      12: getfield      #2                  // Field position:J
      15: lconst_1
      16: ladd
      17: putfield      #2                  // Field position:J
      20: iload_1
      21: ireturn

  public int read(byte[]) throws java.io.IOException;
    Code:
       0: aload_0
       1: aload_1
       2: invokespecial #4                  // Method java/io/FilterInputStream.read:([B)I
       5: istore_2
       6: iload_2
       7: ifle          21
      10: aload_0
      11: dup
      12: getfield      #2                  // Field position:J
      15: iload_2
      16: i2l
      17: ladd
      18: putfield      #2                  // Field position:J
      21: iload_2
      22: ireturn

  public int read(byte[], int, int) throws java.io.IOException;
    Code:
       0: aload_0
       1: aload_1
       2: iload_2
       3: iload_3
       4: invokespecial #5                  // Method java/io/FilterInputStream.read:([BII)I
       7: istore        4
       9: iload         4
      11: ifle          26
      14: aload_0
      15: dup
      16: getfield      #2                  // Field position:J
      19: iload         4
      21: i2l
      22: ladd
      23: putfield      #2                  // Field position:J
      26: iload         4
      28: ireturn

  public long skip(long) throws java.io.IOException;
    Code:
       0: aload_0
       1: lload_1
       2: invokespecial #6                  // Method java/io/FilterInputStream.skip:(J)J
       5: lstore_3
       6: lload_3
       7: lconst_0
       8: lcmp
       9: ifle          22
      12: aload_0
      13: dup
      14: getfield      #2                  // Field position:J
      17: lload_3
      18: ladd
      19: putfield      #2                  // Field position:J
      22: lload_3
      23: lreturn

  public long getPosition();
    Code:
       0: aload_0
       1: getfield      #2                  // Field position:J
       4: lreturn

  public boolean markSupported();
    Code:
       0: iconst_0
       1: ireturn

  public void mark(int);
    Code:
       0: new           #7                  // class java/lang/UnsupportedOperationException
       3: dup
       4: ldc           #8                  // String mark
       6: invokespecial #9                  // Method java/lang/UnsupportedOperationException."<init>":(Ljava/lang/String;)V
       9: athrow

  public void reset();
    Code:
       0: new           #7                  // class java/lang/UnsupportedOperationException
       3: dup
       4: ldc           #10                 // String reset
       6: invokespecial #9                  // Method java/lang/UnsupportedOperationException."<init>":(Ljava/lang/String;)V
       9: athrow
}
