Compiled from "ClusterTopologyManagerImpl.java"
class org.infinispan.topology.ClusterTopologyManagerImpl$2 implements java.util.concurrent.Callable<java.lang.Void> {
  final org.infinispan.topology.ClusterCacheStatus val$cacheStatus;

  final java.util.Map$Entry val$e;

  final java.util.List val$clusterMembers;

  final boolean val$isMergeView;

  final org.infinispan.topology.ClusterTopologyManagerImpl this$0;

  org.infinispan.topology.ClusterTopologyManagerImpl$2(org.infinispan.topology.ClusterTopologyManagerImpl, org.infinispan.topology.ClusterCacheStatus, java.util.Map$Entry, java.util.List, boolean);
    Code:
       0: aload_0
       1: aload_1
       2: putfield      #1                  // Field this$0:Lorg/infinispan/topology/ClusterTopologyManagerImpl;
       5: aload_0
       6: aload_2
       7: putfield      #2                  // Field val$cacheStatus:Lorg/infinispan/topology/ClusterCacheStatus;
      10: aload_0
      11: aload_3
      12: putfield      #3                  // Field val$e:Ljava/util/Map$Entry;
      15: aload_0
      16: aload         4
      18: putfield      #4                  // Field val$clusterMembers:Ljava/util/List;
      21: aload_0
      22: iload         5
      24: putfield      #5                  // Field val$isMergeView:Z
      27: aload_0
      28: invokespecial #6                  // Method java/lang/Object."<init>":()V
      31: return

  public java.lang.Void call() throws java.lang.Exception;
    Code:
       0: aload_0
       1: getfield      #2                  // Field val$cacheStatus:Lorg/infinispan/topology/ClusterCacheStatus;
       4: aload_0
       5: getfield      #3                  // Field val$e:Ljava/util/Map$Entry;
       8: invokeinterface #7,  1            // InterfaceMethod java/util/Map$Entry.getValue:()Ljava/lang/Object;
      13: checkcast     #8                  // class java/util/Map
      16: aload_0
      17: getfield      #4                  // Field val$clusterMembers:Ljava/util/List;
      20: aload_0
      21: getfield      #5                  // Field val$isMergeView:Z
      24: invokevirtual #9                  // Method org/infinispan/topology/ClusterCacheStatus.doMergePartitions:(Ljava/util/Map;Ljava/util/List;Z)V
      27: aconst_null
      28: areturn

  public java.lang.Object call() throws java.lang.Exception;
    Code:
       0: aload_0
       1: invokevirtual #10                 // Method call:()Ljava/lang/Void;
       4: areturn
}
