Compiled from "Components.java"
public final class org.hortonmachine.hmachine.modules.networktools.epanet.core.Components extends java.lang.Enum<org.hortonmachine.hmachine.modules.networktools.epanet.core.Components> {
  public static final org.hortonmachine.hmachine.modules.networktools.epanet.core.Components EN_NODECOUNT;

  public static final org.hortonmachine.hmachine.modules.networktools.epanet.core.Components EN_TANKCOUNT;

  public static final org.hortonmachine.hmachine.modules.networktools.epanet.core.Components EN_LINKCOUNT;

  public static final org.hortonmachine.hmachine.modules.networktools.epanet.core.Components EN_PATCOUNT;

  public static final org.hortonmachine.hmachine.modules.networktools.epanet.core.Components EN_CURVECOUNT;

  public static final org.hortonmachine.hmachine.modules.networktools.epanet.core.Components EN_CONTROLCOUNT;

  private int code;

  private java.lang.String type;

  private static final org.hortonmachine.hmachine.modules.networktools.epanet.core.Components[] $VALUES;

  public static org.hortonmachine.hmachine.modules.networktools.epanet.core.Components[] values();
    Code:
       0: getstatic     #1                  // Field $VALUES:[Lorg/hortonmachine/hmachine/modules/networktools/epanet/core/Components;
       3: invokevirtual #2                  // Method "[Lorg/hortonmachine/hmachine/modules/networktools/epanet/core/Components;".clone:()Ljava/lang/Object;
       6: checkcast     #3                  // class "[Lorg/hortonmachine/hmachine/modules/networktools/epanet/core/Components;"
       9: areturn

  public static org.hortonmachine.hmachine.modules.networktools.epanet.core.Components valueOf(java.lang.String);
    Code:
       0: ldc           #4                  // class org/hortonmachine/hmachine/modules/networktools/epanet/core/Components
       2: aload_0
       3: invokestatic  #5                  // Method java/lang/Enum.valueOf:(Ljava/lang/Class;Ljava/lang/String;)Ljava/lang/Enum;
       6: checkcast     #4                  // class org/hortonmachine/hmachine/modules/networktools/epanet/core/Components
       9: areturn

  private org.hortonmachine.hmachine.modules.networktools.epanet.core.Components(int, java.lang.String);
    Code:
       0: aload_0
       1: aload_1
       2: iload_2
       3: invokespecial #6                  // Method java/lang/Enum."<init>":(Ljava/lang/String;I)V
       6: aload_0
       7: iload_3
       8: putfield      #7                  // Field code:I
      11: aload_0
      12: aload         4
      14: putfield      #8                  // Field type:Ljava/lang/String;
      17: return

  public int getCode();
    Code:
       0: aload_0
       1: getfield      #7                  // Field code:I
       4: ireturn

  public java.lang.String getType();
    Code:
       0: aload_0
       1: getfield      #8                  // Field type:Ljava/lang/String;
       4: areturn

  static {};
    Code:
       0: new           #4                  // class org/hortonmachine/hmachine/modules/networktools/epanet/core/Components
       3: dup
       4: ldc           #9                  // String EN_NODECOUNT
       6: iconst_0
       7: iconst_0
       8: ldc           #10                 // String Nodes
      10: invokespecial #11                 // Method "<init>":(Ljava/lang/String;IILjava/lang/String;)V
      13: putstatic     #12                 // Field EN_NODECOUNT:Lorg/hortonmachine/hmachine/modules/networktools/epanet/core/Components;
      16: new           #4                  // class org/hortonmachine/hmachine/modules/networktools/epanet/core/Components
      19: dup
      20: ldc           #13                 // String EN_TANKCOUNT
      22: iconst_1
      23: iconst_1
      24: ldc           #14                 // String Reservoirs and tank nodes
      26: invokespecial #11                 // Method "<init>":(Ljava/lang/String;IILjava/lang/String;)V
      29: putstatic     #15                 // Field EN_TANKCOUNT:Lorg/hortonmachine/hmachine/modules/networktools/epanet/core/Components;
      32: new           #4                  // class org/hortonmachine/hmachine/modules/networktools/epanet/core/Components
      35: dup
      36: ldc           #16                 // String EN_LINKCOUNT
      38: iconst_2
      39: iconst_2
      40: ldc           #17                 // String Links
      42: invokespecial #11                 // Method "<init>":(Ljava/lang/String;IILjava/lang/String;)V
      45: putstatic     #18                 // Field EN_LINKCOUNT:Lorg/hortonmachine/hmachine/modules/networktools/epanet/core/Components;
      48: new           #4                  // class org/hortonmachine/hmachine/modules/networktools/epanet/core/Components
      51: dup
      52: ldc           #19                 // String EN_PATCOUNT
      54: iconst_3
      55: iconst_3
      56: ldc           #20                 // String Time patterns
      58: invokespecial #11                 // Method "<init>":(Ljava/lang/String;IILjava/lang/String;)V
      61: putstatic     #21                 // Field EN_PATCOUNT:Lorg/hortonmachine/hmachine/modules/networktools/epanet/core/Components;
      64: new           #4                  // class org/hortonmachine/hmachine/modules/networktools/epanet/core/Components
      67: dup
      68: ldc           #22                 // String EN_CURVECOUNT
      70: iconst_4
      71: iconst_4
      72: ldc           #23                 // String Curves
      74: invokespecial #11                 // Method "<init>":(Ljava/lang/String;IILjava/lang/String;)V
      77: putstatic     #24                 // Field EN_CURVECOUNT:Lorg/hortonmachine/hmachine/modules/networktools/epanet/core/Components;
      80: new           #4                  // class org/hortonmachine/hmachine/modules/networktools/epanet/core/Components
      83: dup
      84: ldc           #25                 // String EN_CONTROLCOUNT
      86: iconst_5
      87: iconst_5
      88: ldc           #26                 // String Simple controls
      90: invokespecial #11                 // Method "<init>":(Ljava/lang/String;IILjava/lang/String;)V
      93: putstatic     #27                 // Field EN_CONTROLCOUNT:Lorg/hortonmachine/hmachine/modules/networktools/epanet/core/Components;
      96: bipush        6
      98: anewarray     #4                  // class org/hortonmachine/hmachine/modules/networktools/epanet/core/Components
     101: dup
     102: iconst_0
     103: getstatic     #12                 // Field EN_NODECOUNT:Lorg/hortonmachine/hmachine/modules/networktools/epanet/core/Components;
     106: aastore
     107: dup
     108: iconst_1
     109: getstatic     #15                 // Field EN_TANKCOUNT:Lorg/hortonmachine/hmachine/modules/networktools/epanet/core/Components;
     112: aastore
     113: dup
     114: iconst_2
     115: getstatic     #18                 // Field EN_LINKCOUNT:Lorg/hortonmachine/hmachine/modules/networktools/epanet/core/Components;
     118: aastore
     119: dup
     120: iconst_3
     121: getstatic     #21                 // Field EN_PATCOUNT:Lorg/hortonmachine/hmachine/modules/networktools/epanet/core/Components;
     124: aastore
     125: dup
     126: iconst_4
     127: getstatic     #24                 // Field EN_CURVECOUNT:Lorg/hortonmachine/hmachine/modules/networktools/epanet/core/Components;
     130: aastore
     131: dup
     132: iconst_5
     133: getstatic     #27                 // Field EN_CONTROLCOUNT:Lorg/hortonmachine/hmachine/modules/networktools/epanet/core/Components;
     136: aastore
     137: putstatic     #1                  // Field $VALUES:[Lorg/hortonmachine/hmachine/modules/networktools/epanet/core/Components;
     140: return
}
