Compiled from "EpanetFeatureTypes.java"
public final class org.hortonmachine.hmachine.modules.networktools.epanet.core.EpanetFeatureTypes$Junctions extends java.lang.Enum<org.hortonmachine.hmachine.modules.networktools.epanet.core.EpanetFeatureTypes$Junctions> implements org.hortonmachine.hmachine.modules.networktools.epanet.core.IEpanetType {
  public static final org.hortonmachine.hmachine.modules.networktools.epanet.core.EpanetFeatureTypes$Junctions ID;

  public static final org.hortonmachine.hmachine.modules.networktools.epanet.core.EpanetFeatureTypes$Junctions ELEVATION;

  public static final org.hortonmachine.hmachine.modules.networktools.epanet.core.EpanetFeatureTypes$Junctions DEPTH;

  public static final org.hortonmachine.hmachine.modules.networktools.epanet.core.EpanetFeatureTypes$Junctions DEMAND;

  public static final org.hortonmachine.hmachine.modules.networktools.epanet.core.EpanetFeatureTypes$Junctions EMITTER_COEFFICIENT;

  public static final org.hortonmachine.hmachine.modules.networktools.epanet.core.EpanetFeatureTypes$Junctions PATTERN;

  private java.lang.Class<?> clazz;

  private java.lang.String attributeName;

  private static final org.hortonmachine.hmachine.modules.networktools.epanet.core.EpanetFeatureTypes$Junctions[] $VALUES;

  public static org.hortonmachine.hmachine.modules.networktools.epanet.core.EpanetFeatureTypes$Junctions[] values();
    Code:
       0: getstatic     #2                  // Field $VALUES:[Lorg/hortonmachine/hmachine/modules/networktools/epanet/core/EpanetFeatureTypes$Junctions;
       3: invokevirtual #3                  // Method "[Lorg/hortonmachine/hmachine/modules/networktools/epanet/core/EpanetFeatureTypes$Junctions;".clone:()Ljava/lang/Object;
       6: checkcast     #4                  // class "[Lorg/hortonmachine/hmachine/modules/networktools/epanet/core/EpanetFeatureTypes$Junctions;"
       9: areturn

  public static org.hortonmachine.hmachine.modules.networktools.epanet.core.EpanetFeatureTypes$Junctions valueOf(java.lang.String);
    Code:
       0: ldc           #5                  // class org/hortonmachine/hmachine/modules/networktools/epanet/core/EpanetFeatureTypes$Junctions
       2: aload_0
       3: invokestatic  #6                  // Method java/lang/Enum.valueOf:(Ljava/lang/Class;Ljava/lang/String;)Ljava/lang/Enum;
       6: checkcast     #5                  // class org/hortonmachine/hmachine/modules/networktools/epanet/core/EpanetFeatureTypes$Junctions
       9: areturn

  private org.hortonmachine.hmachine.modules.networktools.epanet.core.EpanetFeatureTypes$Junctions(java.lang.String, java.lang.Class<?>);
    Code:
       0: aload_0
       1: aload_1
       2: iload_2
       3: invokespecial #7                  // Method java/lang/Enum."<init>":(Ljava/lang/String;I)V
       6: aload_0
       7: aload_3
       8: putfield      #8                  // Field attributeName:Ljava/lang/String;
      11: aload_0
      12: aload         4
      14: putfield      #9                  // Field clazz:Ljava/lang/Class;
      17: return

  public java.lang.Class<?> getClazz();
    Code:
       0: aload_0
       1: getfield      #9                  // Field clazz:Ljava/lang/Class;
       4: areturn

  public java.lang.String getAttributeName();
    Code:
       0: aload_0
       1: getfield      #8                  // Field attributeName:Ljava/lang/String;
       4: areturn

  public java.lang.String getShapefileName();
    Code:
       0: ldc           #10                 // String junctions.shp
       2: areturn

  public java.lang.String getName();
    Code:
       0: ldc           #11                 // String junctions
       2: areturn

  public java.lang.String getPrefix();
    Code:
       0: ldc           #12                 // String J
       2: areturn

  static {};
    Code:
       0: new           #5                  // class org/hortonmachine/hmachine/modules/networktools/epanet/core/EpanetFeatureTypes$Junctions
       3: dup
       4: ldc           #13                 // String ID
       6: iconst_0
       7: ldc           #14                 // String id
       9: ldc           #15                 // class java/lang/String
      11: invokespecial #16                 // Method "<init>":(Ljava/lang/String;ILjava/lang/String;Ljava/lang/Class;)V
      14: putstatic     #17                 // Field ID:Lorg/hortonmachine/hmachine/modules/networktools/epanet/core/EpanetFeatureTypes$Junctions;
      17: new           #5                  // class org/hortonmachine/hmachine/modules/networktools/epanet/core/EpanetFeatureTypes$Junctions
      20: dup
      21: ldc           #18                 // String ELEVATION
      23: iconst_1
      24: ldc           #19                 // String elev
      26: ldc           #20                 // class java/lang/Double
      28: invokespecial #16                 // Method "<init>":(Ljava/lang/String;ILjava/lang/String;Ljava/lang/Class;)V
      31: putstatic     #21                 // Field ELEVATION:Lorg/hortonmachine/hmachine/modules/networktools/epanet/core/EpanetFeatureTypes$Junctions;
      34: new           #5                  // class org/hortonmachine/hmachine/modules/networktools/epanet/core/EpanetFeatureTypes$Junctions
      37: dup
      38: ldc           #22                 // String DEPTH
      40: iconst_2
      41: ldc           #22                 // String DEPTH
      43: ldc           #20                 // class java/lang/Double
      45: invokespecial #16                 // Method "<init>":(Ljava/lang/String;ILjava/lang/String;Ljava/lang/Class;)V
      48: putstatic     #23                 // Field DEPTH:Lorg/hortonmachine/hmachine/modules/networktools/epanet/core/EpanetFeatureTypes$Junctions;
      51: new           #5                  // class org/hortonmachine/hmachine/modules/networktools/epanet/core/EpanetFeatureTypes$Junctions
      54: dup
      55: ldc           #24                 // String DEMAND
      57: iconst_3
      58: ldc           #25                 // String demand
      60: ldc           #20                 // class java/lang/Double
      62: invokespecial #16                 // Method "<init>":(Ljava/lang/String;ILjava/lang/String;Ljava/lang/Class;)V
      65: putstatic     #26                 // Field DEMAND:Lorg/hortonmachine/hmachine/modules/networktools/epanet/core/EpanetFeatureTypes$Junctions;
      68: new           #5                  // class org/hortonmachine/hmachine/modules/networktools/epanet/core/EpanetFeatureTypes$Junctions
      71: dup
      72: ldc           #27                 // String EMITTER_COEFFICIENT
      74: iconst_4
      75: ldc           #28                 // String emitt_coef
      77: ldc           #20                 // class java/lang/Double
      79: invokespecial #16                 // Method "<init>":(Ljava/lang/String;ILjava/lang/String;Ljava/lang/Class;)V
      82: putstatic     #29                 // Field EMITTER_COEFFICIENT:Lorg/hortonmachine/hmachine/modules/networktools/epanet/core/EpanetFeatureTypes$Junctions;
      85: new           #5                  // class org/hortonmachine/hmachine/modules/networktools/epanet/core/EpanetFeatureTypes$Junctions
      88: dup
      89: ldc           #30                 // String PATTERN
      91: iconst_5
      92: ldc           #31                 // String pattern_id
      94: ldc           #15                 // class java/lang/String
      96: invokespecial #16                 // Method "<init>":(Ljava/lang/String;ILjava/lang/String;Ljava/lang/Class;)V
      99: putstatic     #32                 // Field PATTERN:Lorg/hortonmachine/hmachine/modules/networktools/epanet/core/EpanetFeatureTypes$Junctions;
     102: bipush        6
     104: anewarray     #5                  // class org/hortonmachine/hmachine/modules/networktools/epanet/core/EpanetFeatureTypes$Junctions
     107: dup
     108: iconst_0
     109: getstatic     #17                 // Field ID:Lorg/hortonmachine/hmachine/modules/networktools/epanet/core/EpanetFeatureTypes$Junctions;
     112: aastore
     113: dup
     114: iconst_1
     115: getstatic     #21                 // Field ELEVATION:Lorg/hortonmachine/hmachine/modules/networktools/epanet/core/EpanetFeatureTypes$Junctions;
     118: aastore
     119: dup
     120: iconst_2
     121: getstatic     #23                 // Field DEPTH:Lorg/hortonmachine/hmachine/modules/networktools/epanet/core/EpanetFeatureTypes$Junctions;
     124: aastore
     125: dup
     126: iconst_3
     127: getstatic     #26                 // Field DEMAND:Lorg/hortonmachine/hmachine/modules/networktools/epanet/core/EpanetFeatureTypes$Junctions;
     130: aastore
     131: dup
     132: iconst_4
     133: getstatic     #29                 // Field EMITTER_COEFFICIENT:Lorg/hortonmachine/hmachine/modules/networktools/epanet/core/EpanetFeatureTypes$Junctions;
     136: aastore
     137: dup
     138: iconst_5
     139: getstatic     #32                 // Field PATTERN:Lorg/hortonmachine/hmachine/modules/networktools/epanet/core/EpanetFeatureTypes$Junctions;
     142: aastore
     143: putstatic     #2                  // Field $VALUES:[Lorg/hortonmachine/hmachine/modules/networktools/epanet/core/EpanetFeatureTypes$Junctions;
     146: return
}
