Compiled from "TimeParameterCodes.java"
public final class org.hortonmachine.hmachine.modules.networktools.epanet.core.TimeParameterCodes extends java.lang.Enum<org.hortonmachine.hmachine.modules.networktools.epanet.core.TimeParameterCodes> {
  public static final org.hortonmachine.hmachine.modules.networktools.epanet.core.TimeParameterCodes DURATION;

  public static final org.hortonmachine.hmachine.modules.networktools.epanet.core.TimeParameterCodes HYDSTEP;

  public static final org.hortonmachine.hmachine.modules.networktools.epanet.core.TimeParameterCodes QUALSTEP;

  public static final org.hortonmachine.hmachine.modules.networktools.epanet.core.TimeParameterCodes PATTERNSTEP;

  public static final org.hortonmachine.hmachine.modules.networktools.epanet.core.TimeParameterCodes PATTERNSTART;

  public static final org.hortonmachine.hmachine.modules.networktools.epanet.core.TimeParameterCodes REPORTSTEP;

  public static final org.hortonmachine.hmachine.modules.networktools.epanet.core.TimeParameterCodes REPORTSTART;

  public static final org.hortonmachine.hmachine.modules.networktools.epanet.core.TimeParameterCodes RULESTEP;

  public static final org.hortonmachine.hmachine.modules.networktools.epanet.core.TimeParameterCodes STATISTIC;

  public static final org.hortonmachine.hmachine.modules.networktools.epanet.core.TimeParameterCodes STARTCLOCKTIME;

  private int code;

  private java.lang.String key;

  private java.lang.String description;

  private final java.lang.String defaultValue;

  private static final org.hortonmachine.hmachine.modules.networktools.epanet.core.TimeParameterCodes[] $VALUES;

  public static org.hortonmachine.hmachine.modules.networktools.epanet.core.TimeParameterCodes[] values();
    Code:
       0: getstatic     #1                  // Field $VALUES:[Lorg/hortonmachine/hmachine/modules/networktools/epanet/core/TimeParameterCodes;
       3: invokevirtual #2                  // Method "[Lorg/hortonmachine/hmachine/modules/networktools/epanet/core/TimeParameterCodes;".clone:()Ljava/lang/Object;
       6: checkcast     #3                  // class "[Lorg/hortonmachine/hmachine/modules/networktools/epanet/core/TimeParameterCodes;"
       9: areturn

  public static org.hortonmachine.hmachine.modules.networktools.epanet.core.TimeParameterCodes valueOf(java.lang.String);
    Code:
       0: ldc           #4                  // class org/hortonmachine/hmachine/modules/networktools/epanet/core/TimeParameterCodes
       2: aload_0
       3: invokestatic  #5                  // Method java/lang/Enum.valueOf:(Ljava/lang/Class;Ljava/lang/String;)Ljava/lang/Enum;
       6: checkcast     #4                  // class org/hortonmachine/hmachine/modules/networktools/epanet/core/TimeParameterCodes
       9: areturn

  private org.hortonmachine.hmachine.modules.networktools.epanet.core.TimeParameterCodes(int, java.lang.String, java.lang.String, java.lang.String);
    Code:
       0: aload_0
       1: aload_1
       2: iload_2
       3: invokespecial #6                  // Method java/lang/Enum."<init>":(Ljava/lang/String;I)V
       6: aload_0
       7: iload_3
       8: putfield      #7                  // Field code:I
      11: aload_0
      12: aload         4
      14: putfield      #8                  // Field key:Ljava/lang/String;
      17: aload_0
      18: aload         5
      20: putfield      #9                  // Field description:Ljava/lang/String;
      23: aload_0
      24: aload         6
      26: putfield      #10                 // Field defaultValue:Ljava/lang/String;
      29: return

  public int getCode();
    Code:
       0: aload_0
       1: getfield      #7                  // Field code:I
       4: ireturn

  public java.lang.String getKey();
    Code:
       0: aload_0
       1: getfield      #8                  // Field key:Ljava/lang/String;
       4: areturn

  public java.lang.String getDescription();
    Code:
       0: aload_0
       1: getfield      #9                  // Field description:Ljava/lang/String;
       4: areturn

  public java.lang.String getDefaultValue();
    Code:
       0: aload_0
       1: getfield      #10                 // Field defaultValue:Ljava/lang/String;
       4: areturn

  public static org.hortonmachine.hmachine.modules.networktools.epanet.core.TimeParameterCodes forCode(int);
    Code:
       0: invokestatic  #11                 // Method values:()[Lorg/hortonmachine/hmachine/modules/networktools/epanet/core/TimeParameterCodes;
       3: astore_1
       4: aload_1
       5: astore_2
       6: aload_2
       7: arraylength
       8: istore_3
       9: iconst_0
      10: istore        4
      12: iload         4
      14: iload_3
      15: if_icmpge     42
      18: aload_2
      19: iload         4
      21: aaload
      22: astore        5
      24: aload         5
      26: getfield      #7                  // Field code:I
      29: iload_0
      30: if_icmpne     36
      33: aload         5
      35: areturn
      36: iinc          4, 1
      39: goto          12
      42: new           #12                 // class java/lang/IllegalArgumentException
      45: dup
      46: new           #13                 // class java/lang/StringBuilder
      49: dup
      50: invokespecial #14                 // Method java/lang/StringBuilder."<init>":()V
      53: ldc           #15                 // String No type for the given code:
      55: invokevirtual #16                 // Method java/lang/StringBuilder.append:(Ljava/lang/String;)Ljava/lang/StringBuilder;
      58: iload_0
      59: invokevirtual #17                 // Method java/lang/StringBuilder.append:(I)Ljava/lang/StringBuilder;
      62: invokevirtual #18                 // Method java/lang/StringBuilder.toString:()Ljava/lang/String;
      65: invokespecial #19                 // Method java/lang/IllegalArgumentException."<init>":(Ljava/lang/String;)V
      68: athrow

  public static org.hortonmachine.hmachine.modules.networktools.epanet.core.TimeParameterCodes forKey(java.lang.String);
    Code:
       0: invokestatic  #11                 // Method values:()[Lorg/hortonmachine/hmachine/modules/networktools/epanet/core/TimeParameterCodes;
       3: astore_1
       4: aload_1
       5: astore_2
       6: aload_2
       7: arraylength
       8: istore_3
       9: iconst_0
      10: istore        4
      12: iload         4
      14: iload_3
      15: if_icmpge     45
      18: aload_2
      19: iload         4
      21: aaload
      22: astore        5
      24: aload         5
      26: getfield      #8                  // Field key:Ljava/lang/String;
      29: aload_0
      30: invokevirtual #20                 // Method java/lang/String.equals:(Ljava/lang/Object;)Z
      33: ifeq          39
      36: aload         5
      38: areturn
      39: iinc          4, 1
      42: goto          12
      45: new           #12                 // class java/lang/IllegalArgumentException
      48: dup
      49: new           #13                 // class java/lang/StringBuilder
      52: dup
      53: invokespecial #14                 // Method java/lang/StringBuilder."<init>":()V
      56: ldc           #21                 // String No type for the given key:
      58: invokevirtual #16                 // Method java/lang/StringBuilder.append:(Ljava/lang/String;)Ljava/lang/StringBuilder;
      61: aload_0
      62: invokevirtual #16                 // Method java/lang/StringBuilder.append:(Ljava/lang/String;)Ljava/lang/StringBuilder;
      65: invokevirtual #18                 // Method java/lang/StringBuilder.toString:()Ljava/lang/String;
      68: invokespecial #19                 // Method java/lang/IllegalArgumentException."<init>":(Ljava/lang/String;)V
      71: athrow

  static {};
    Code:
       0: new           #4                  // class org/hortonmachine/hmachine/modules/networktools/epanet/core/TimeParameterCodes
       3: dup
       4: ldc           #22                 // String DURATION
       6: iconst_0
       7: iconst_0
       8: ldc           #22                 // String DURATION
      10: ldc           #23                 // String Simulation duration [min]
      12: ldc           #24                 // String 0
      14: invokespecial #25                 // Method "<init>":(Ljava/lang/String;IILjava/lang/String;Ljava/lang/String;Ljava/lang/String;)V
      17: putstatic     #26                 // Field DURATION:Lorg/hortonmachine/hmachine/modules/networktools/epanet/core/TimeParameterCodes;
      20: new           #4                  // class org/hortonmachine/hmachine/modules/networktools/epanet/core/TimeParameterCodes
      23: dup
      24: ldc           #27                 // String HYDSTEP
      26: iconst_1
      27: iconst_1
      28: ldc           #28                 // String HYDRAULIC TIMESTEP
      30: ldc           #29                 // String Hydraulic time step [min]
      32: ldc           #30                 // String 60
      34: invokespecial #25                 // Method "<init>":(Ljava/lang/String;IILjava/lang/String;Ljava/lang/String;Ljava/lang/String;)V
      37: putstatic     #31                 // Field HYDSTEP:Lorg/hortonmachine/hmachine/modules/networktools/epanet/core/TimeParameterCodes;
      40: new           #4                  // class org/hortonmachine/hmachine/modules/networktools/epanet/core/TimeParameterCodes
      43: dup
      44: ldc           #32                 // String QUALSTEP
      46: iconst_2
      47: iconst_2
      48: ldc           #33                 // String QUALITY TIMESTEP
      50: ldc           #34                 // String Water quality time step [min]
      52: ldc           #35                 // String 6
      54: invokespecial #25                 // Method "<init>":(Ljava/lang/String;IILjava/lang/String;Ljava/lang/String;Ljava/lang/String;)V
      57: putstatic     #36                 // Field QUALSTEP:Lorg/hortonmachine/hmachine/modules/networktools/epanet/core/TimeParameterCodes;
      60: new           #4                  // class org/hortonmachine/hmachine/modules/networktools/epanet/core/TimeParameterCodes
      63: dup
      64: ldc           #37                 // String PATTERNSTEP
      66: iconst_3
      67: iconst_3
      68: ldc           #38                 // String PATTERN TIMESTEP
      70: ldc           #39                 // String Time pattern time step [min]
      72: ldc           #30                 // String 60
      74: invokespecial #25                 // Method "<init>":(Ljava/lang/String;IILjava/lang/String;Ljava/lang/String;Ljava/lang/String;)V
      77: putstatic     #40                 // Field PATTERNSTEP:Lorg/hortonmachine/hmachine/modules/networktools/epanet/core/TimeParameterCodes;
      80: new           #4                  // class org/hortonmachine/hmachine/modules/networktools/epanet/core/TimeParameterCodes
      83: dup
      84: ldc           #41                 // String PATTERNSTART
      86: iconst_4
      87: iconst_4
      88: ldc           #42                 // String PATTERN START
      90: ldc           #43                 // String Time pattern start time [min]
      92: ldc           #24                 // String 0
      94: invokespecial #25                 // Method "<init>":(Ljava/lang/String;IILjava/lang/String;Ljava/lang/String;Ljava/lang/String;)V
      97: putstatic     #44                 // Field PATTERNSTART:Lorg/hortonmachine/hmachine/modules/networktools/epanet/core/TimeParameterCodes;
     100: new           #4                  // class org/hortonmachine/hmachine/modules/networktools/epanet/core/TimeParameterCodes
     103: dup
     104: ldc           #45                 // String REPORTSTEP
     106: iconst_5
     107: iconst_5
     108: ldc           #46                 // String REPORT TIMESTEP
     110: ldc           #47                 // String Reporting time step [min]
     112: ldc           #30                 // String 60
     114: invokespecial #25                 // Method "<init>":(Ljava/lang/String;IILjava/lang/String;Ljava/lang/String;Ljava/lang/String;)V
     117: putstatic     #48                 // Field REPORTSTEP:Lorg/hortonmachine/hmachine/modules/networktools/epanet/core/TimeParameterCodes;
     120: new           #4                  // class org/hortonmachine/hmachine/modules/networktools/epanet/core/TimeParameterCodes
     123: dup
     124: ldc           #49                 // String REPORTSTART
     126: bipush        6
     128: bipush        6
     130: ldc           #50                 // String REPORT START
     132: ldc           #51                 // String Report starting time [min]
     134: ldc           #24                 // String 0
     136: invokespecial #25                 // Method "<init>":(Ljava/lang/String;IILjava/lang/String;Ljava/lang/String;Ljava/lang/String;)V
     139: putstatic     #52                 // Field REPORTSTART:Lorg/hortonmachine/hmachine/modules/networktools/epanet/core/TimeParameterCodes;
     142: new           #4                  // class org/hortonmachine/hmachine/modules/networktools/epanet/core/TimeParameterCodes
     145: dup
     146: ldc           #53                 // String RULESTEP
     148: bipush        7
     150: bipush        7
     152: ldc           #54                 // String RULE TIMESTEP
     154: ldc           #55                 // String Time step for evaluating rule-based controls [min]
     156: ldc           #35                 // String 6
     158: invokespecial #25                 // Method "<init>":(Ljava/lang/String;IILjava/lang/String;Ljava/lang/String;Ljava/lang/String;)V
     161: putstatic     #56                 // Field RULESTEP:Lorg/hortonmachine/hmachine/modules/networktools/epanet/core/TimeParameterCodes;
     164: new           #4                  // class org/hortonmachine/hmachine/modules/networktools/epanet/core/TimeParameterCodes
     167: dup
     168: ldc           #57                 // String STATISTIC
     170: bipush        8
     172: bipush        8
     174: ldc           #57                 // String STATISTIC
     176: ldc           #58                 // String Type of time series post-processing to use (can be AVERAGED, MINIMUM, MAXIMUM, NONE)
     178: ldc           #59                 // String NONE
     180: invokespecial #25                 // Method "<init>":(Ljava/lang/String;IILjava/lang/String;Ljava/lang/String;Ljava/lang/String;)V
     183: putstatic     #60                 // Field STATISTIC:Lorg/hortonmachine/hmachine/modules/networktools/epanet/core/TimeParameterCodes;
     186: new           #4                  // class org/hortonmachine/hmachine/modules/networktools/epanet/core/TimeParameterCodes
     189: dup
     190: ldc           #61                 // String STARTCLOCKTIME
     192: bipush        9
     194: iconst_m1
     195: ldc           #62                 // String START CLOCKTIME
     197: ldc           #63                 // String The time of the day at which the simulation begins (format HH:MM AM/PM)
     199: ldc           #64                 // String 12:00 AM
     201: invokespecial #25                 // Method "<init>":(Ljava/lang/String;IILjava/lang/String;Ljava/lang/String;Ljava/lang/String;)V
     204: putstatic     #65                 // Field STARTCLOCKTIME:Lorg/hortonmachine/hmachine/modules/networktools/epanet/core/TimeParameterCodes;
     207: bipush        10
     209: anewarray     #4                  // class org/hortonmachine/hmachine/modules/networktools/epanet/core/TimeParameterCodes
     212: dup
     213: iconst_0
     214: getstatic     #26                 // Field DURATION:Lorg/hortonmachine/hmachine/modules/networktools/epanet/core/TimeParameterCodes;
     217: aastore
     218: dup
     219: iconst_1
     220: getstatic     #31                 // Field HYDSTEP:Lorg/hortonmachine/hmachine/modules/networktools/epanet/core/TimeParameterCodes;
     223: aastore
     224: dup
     225: iconst_2
     226: getstatic     #36                 // Field QUALSTEP:Lorg/hortonmachine/hmachine/modules/networktools/epanet/core/TimeParameterCodes;
     229: aastore
     230: dup
     231: iconst_3
     232: getstatic     #40                 // Field PATTERNSTEP:Lorg/hortonmachine/hmachine/modules/networktools/epanet/core/TimeParameterCodes;
     235: aastore
     236: dup
     237: iconst_4
     238: getstatic     #44                 // Field PATTERNSTART:Lorg/hortonmachine/hmachine/modules/networktools/epanet/core/TimeParameterCodes;
     241: aastore
     242: dup
     243: iconst_5
     244: getstatic     #48                 // Field REPORTSTEP:Lorg/hortonmachine/hmachine/modules/networktools/epanet/core/TimeParameterCodes;
     247: aastore
     248: dup
     249: bipush        6
     251: getstatic     #52                 // Field REPORTSTART:Lorg/hortonmachine/hmachine/modules/networktools/epanet/core/TimeParameterCodes;
     254: aastore
     255: dup
     256: bipush        7
     258: getstatic     #56                 // Field RULESTEP:Lorg/hortonmachine/hmachine/modules/networktools/epanet/core/TimeParameterCodes;
     261: aastore
     262: dup
     263: bipush        8
     265: getstatic     #60                 // Field STATISTIC:Lorg/hortonmachine/hmachine/modules/networktools/epanet/core/TimeParameterCodes;
     268: aastore
     269: dup
     270: bipush        9
     272: getstatic     #65                 // Field STARTCLOCKTIME:Lorg/hortonmachine/hmachine/modules/networktools/epanet/core/TimeParameterCodes;
     275: aastore
     276: putstatic     #1                  // Field $VALUES:[Lorg/hortonmachine/hmachine/modules/networktools/epanet/core/TimeParameterCodes;
     279: return
}
