Compiled from "ConfigurationContext.java"
public class org.apache.axis2.context.ConfigurationContext extends org.apache.axis2.context.AbstractContext {
  private static final org.apache.axis2.util.OnDemandLogger log;

  private final java.util.concurrent.ConcurrentHashMap<java.lang.String, org.apache.axis2.context.OperationContext> operationContextMap;

  private final java.util.Hashtable<java.lang.String, org.apache.axis2.context.ServiceGroupContext> serviceGroupContextMap;

  private java.util.Hashtable<java.lang.String, org.apache.axis2.context.ServiceGroupContext> applicationSessionServiceGroupContexts;

  private org.apache.axis2.engine.AxisConfiguration axisConfiguration;

  private org.apache.axis2.util.threadpool.ThreadFactory threadPool;

  private org.apache.axis2.engine.ListenerManager listenerManager;

  private long serviceGroupContextTimeoutInterval;

  private java.lang.String contextRoot;

  private java.lang.String servicePath;

  private java.lang.String cachedServicePath;

  protected java.util.List<org.apache.axis2.context.ContextListener> contextListeners;

  private boolean stopped;

  public org.apache.axis2.context.ConfigurationContext(org.apache.axis2.engine.AxisConfiguration);
    Code:
       0: aload_0
       1: aconst_null
       2: invokespecial #1                  // Method org/apache/axis2/context/AbstractContext."<init>":(Lorg/apache/axis2/context/AbstractContext;)V
       5: aload_0
       6: new           #2                  // class java/util/concurrent/ConcurrentHashMap
       9: dup
      10: invokespecial #3                  // Method java/util/concurrent/ConcurrentHashMap."<init>":()V
      13: putfield      #4                  // Field operationContextMap:Ljava/util/concurrent/ConcurrentHashMap;
      16: aload_0
      17: new           #5                  // class java/util/Hashtable
      20: dup
      21: invokespecial #6                  // Method java/util/Hashtable."<init>":()V
      24: putfield      #7                  // Field serviceGroupContextMap:Ljava/util/Hashtable;
      27: aload_0
      28: new           #5                  // class java/util/Hashtable
      31: dup
      32: invokespecial #6                  // Method java/util/Hashtable."<init>":()V
      35: putfield      #8                  // Field applicationSessionServiceGroupContexts:Ljava/util/Hashtable;
      38: aload_0
      39: ldc2_w        #9                  // long 30000l
      42: putfield      #11                 // Field serviceGroupContextTimeoutInterval:J
      45: aload_0
      46: aconst_null
      47: putfield      #12                 // Field cachedServicePath:Ljava/lang/String;
      50: aload_0
      51: iconst_0
      52: putfield      #13                 // Field stopped:Z
      55: aload_0
      56: aload_1
      57: putfield      #14                 // Field axisConfiguration:Lorg/apache/axis2/engine/AxisConfiguration;
      60: aload_0
      61: aload_1
      62: invokespecial #15                 // Method initConfigContextTimeout:(Lorg/apache/axis2/engine/AxisConfiguration;)V
      65: return

  private void initConfigContextTimeout(org.apache.axis2.engine.AxisConfiguration);
    Code:
       0: aload_1
       1: ldc           #17                 // String ConfigContextTimeoutInterval
       3: invokevirtual #18                 // Method org/apache/axis2/engine/AxisConfiguration.getParameter:(Ljava/lang/String;)Lorg/apache/axis2/description/Parameter;
       6: astore_2
       7: aload_2
       8: ifnull        39
      11: aload_2
      12: invokevirtual #19                 // Method org/apache/axis2/description/Parameter.getValue:()Ljava/lang/Object;
      15: astore_3
      16: aload_3
      17: ifnull        39
      20: aload_3
      21: instanceof    #20                 // class java/lang/String
      24: ifeq          39
      27: aload_0
      28: aload_3
      29: checkcast     #20                 // class java/lang/String
      32: invokestatic  #21                 // Method java/lang/Integer.parseInt:(Ljava/lang/String;)I
      35: i2l
      36: putfield      #11                 // Field serviceGroupContextTimeoutInterval:J
      39: return

  public void initCluster() throws org.apache.axis2.AxisFault;
    Code:
       0: aload_0
       1: getfield      #14                 // Field axisConfiguration:Lorg/apache/axis2/engine/AxisConfiguration;
       4: invokevirtual #22                 // Method org/apache/axis2/engine/AxisConfiguration.getClusteringAgent:()Lorg/apache/axis2/clustering/ClusteringAgent;
       7: astore_1
       8: aload_1
       9: ifnull        68
      12: aload_1
      13: invokeinterface #23,  1           // InterfaceMethod org/apache/axis2/clustering/ClusteringAgent.getStateManager:()Lorg/apache/axis2/clustering/state/StateManager;
      18: astore_2
      19: aload_2
      20: ifnull        30
      23: aload_2
      24: aload_0
      25: invokeinterface #24,  2           // InterfaceMethod org/apache/axis2/clustering/state/StateManager.setConfigurationContext:(Lorg/apache/axis2/context/ConfigurationContext;)V
      30: aload_1
      31: invokeinterface #25,  1           // InterfaceMethod org/apache/axis2/clustering/ClusteringAgent.getNodeManager:()Lorg/apache/axis2/clustering/management/NodeManager;
      36: astore_3
      37: aload_3
      38: ifnull        48
      41: aload_3
      42: aload_0
      43: invokeinterface #26,  2           // InterfaceMethod org/apache/axis2/clustering/management/NodeManager.setConfigurationContext:(Lorg/apache/axis2/context/ConfigurationContext;)V
      48: aload_1
      49: invokestatic  #27                 // Method shouldClusterBeInitiated:(Lorg/apache/axis2/clustering/ClusteringAgent;)Z
      52: ifeq          68
      55: aload_1
      56: aload_0
      57: invokeinterface #28,  2           // InterfaceMethod org/apache/axis2/clustering/ClusteringAgent.setConfigurationContext:(Lorg/apache/axis2/context/ConfigurationContext;)V
      62: aload_1
      63: invokeinterface #29,  1           // InterfaceMethod org/apache/axis2/clustering/ClusteringAgent.init:()V
      68: return

  private static boolean shouldClusterBeInitiated(org.apache.axis2.clustering.ClusteringAgent);
    Code:
       0: aload_0
       1: ldc           #31                 // String AvoidInitiation
       3: invokeinterface #32,  2           // InterfaceMethod org/apache/axis2/clustering/ClusteringAgent.getParameter:(Ljava/lang/String;)Lorg/apache/axis2/description/Parameter;
       8: astore_1
       9: aload_1
      10: ifnull        23
      13: aload_1
      14: invokevirtual #19                 // Method org/apache/axis2/description/Parameter.getValue:()Ljava/lang/Object;
      17: invokestatic  #33                 // Method org/apache/axis2/util/JavaUtils.isTrueExplicitly:(Ljava/lang/Object;)Z
      20: ifne          27
      23: iconst_1
      24: goto          28
      27: iconst_0
      28: ireturn

  void contextCreated(org.apache.axis2.context.AbstractContext);
    Code:
       0: aload_0
       1: getfield      #34                 // Field contextListeners:Ljava/util/List;
       4: ifnonnull     8
       7: return
       8: aload_0
       9: getfield      #34                 // Field contextListeners:Ljava/util/List;
      12: invokeinterface #35,  1           // InterfaceMethod java/util/List.iterator:()Ljava/util/Iterator;
      17: astore_2
      18: aload_2
      19: invokeinterface #36,  1           // InterfaceMethod java/util/Iterator.hasNext:()Z
      24: ifeq          51
      27: aload_2
      28: invokeinterface #37,  1           // InterfaceMethod java/util/Iterator.next:()Ljava/lang/Object;
      33: astore_3
      34: aload_3
      35: checkcast     #38                 // class org/apache/axis2/context/ContextListener
      38: astore        4
      40: aload         4
      42: aload_1
      43: invokeinterface #39,  2           // InterfaceMethod org/apache/axis2/context/ContextListener.contextCreated:(Lorg/apache/axis2/context/AbstractContext;)V
      48: goto          18
      51: return

  void contextRemoved(org.apache.axis2.context.AbstractContext);
    Code:
       0: aload_0
       1: getfield      #34                 // Field contextListeners:Ljava/util/List;
       4: ifnonnull     8
       7: return
       8: aload_0
       9: getfield      #34                 // Field contextListeners:Ljava/util/List;
      12: invokeinterface #35,  1           // InterfaceMethod java/util/List.iterator:()Ljava/util/Iterator;
      17: astore_2
      18: aload_2
      19: invokeinterface #36,  1           // InterfaceMethod java/util/Iterator.hasNext:()Z
      24: ifeq          51
      27: aload_2
      28: invokeinterface #37,  1           // InterfaceMethod java/util/Iterator.next:()Ljava/lang/Object;
      33: astore_3
      34: aload_3
      35: checkcast     #38                 // class org/apache/axis2/context/ContextListener
      38: astore        4
      40: aload         4
      42: aload_1
      43: invokeinterface #40,  2           // InterfaceMethod org/apache/axis2/context/ContextListener.contextRemoved:(Lorg/apache/axis2/context/AbstractContext;)V
      48: goto          18
      51: return

  public void addContextListener(org.apache.axis2.context.ContextListener);
    Code:
       0: aload_0
       1: getfield      #34                 // Field contextListeners:Ljava/util/List;
       4: ifnonnull     18
       7: aload_0
       8: new           #41                 // class java/util/ArrayList
      11: dup
      12: invokespecial #42                 // Method java/util/ArrayList."<init>":()V
      15: putfield      #34                 // Field contextListeners:Ljava/util/List;
      18: aload_0
      19: getfield      #34                 // Field contextListeners:Ljava/util/List;
      22: aload_1
      23: invokeinterface #43,  2           // InterfaceMethod java/util/List.add:(Ljava/lang/Object;)Z
      28: pop
      29: return

  public void removeContextListener(org.apache.axis2.context.ContextListener);
    Code:
       0: aload_0
       1: getfield      #34                 // Field contextListeners:Ljava/util/List;
       4: ifnull        18
       7: aload_0
       8: getfield      #34                 // Field contextListeners:Ljava/util/List;
      11: aload_1
      12: invokeinterface #44,  2           // InterfaceMethod java/util/List.remove:(Ljava/lang/Object;)Z
      17: pop
      18: return

  public void fillServiceContextAndServiceGroupContext(org.apache.axis2.context.MessageContext) throws org.apache.axis2.AxisFault;
    Code:
       0: aload_1
       1: invokevirtual #45                 // Method org/apache/axis2/context/MessageContext.getServiceContext:()Lorg/apache/axis2/context/ServiceContext;
       4: astore_3
       5: aload_1
       6: invokevirtual #46                 // Method org/apache/axis2/context/MessageContext.getAxisService:()Lorg/apache/axis2/description/AxisService;
       9: astore        4
      11: aload_3
      12: ifnonnull     264
      15: aload         4
      17: invokevirtual #47                 // Method org/apache/axis2/description/AxisService.getScope:()Ljava/lang/String;
      20: astore        5
      22: ldc           #49                 // String application
      24: aload         5
      26: invokevirtual #50                 // Method java/lang/String.equals:(Ljava/lang/Object;)Z
      29: ifeq          126
      32: aload         4
      34: invokevirtual #51                 // Method org/apache/axis2/description/AxisService.getAxisServiceGroup:()Lorg/apache/axis2/description/AxisServiceGroup;
      37: invokevirtual #52                 // Method org/apache/axis2/description/AxisServiceGroup.getServiceGroupName:()Ljava/lang/String;
      40: astore        6
      42: aload_0
      43: getfield      #8                  // Field applicationSessionServiceGroupContexts:Ljava/util/Hashtable;
      46: aload         6
      48: invokevirtual #53                 // Method java/util/Hashtable.get:(Ljava/lang/Object;)Ljava/lang/Object;
      51: checkcast     #54                 // class org/apache/axis2/context/ServiceGroupContext
      54: astore_2
      55: aload_2
      56: ifnonnull     108
      59: aload_1
      60: invokevirtual #55                 // Method org/apache/axis2/context/MessageContext.getAxisServiceGroup:()Lorg/apache/axis2/description/AxisServiceGroup;
      63: astore        7
      65: aload         7
      67: ifnonnull     83
      70: aload         4
      72: invokevirtual #51                 // Method org/apache/axis2/description/AxisService.getAxisServiceGroup:()Lorg/apache/axis2/description/AxisServiceGroup;
      75: astore        7
      77: aload_1
      78: aload         7
      80: invokevirtual #56                 // Method org/apache/axis2/context/MessageContext.setAxisServiceGroup:(Lorg/apache/axis2/description/AxisServiceGroup;)V
      83: aload_1
      84: invokevirtual #57                 // Method org/apache/axis2/context/MessageContext.getConfigurationContext:()Lorg/apache/axis2/context/ConfigurationContext;
      87: astore        8
      89: aload         8
      91: aload         7
      93: invokevirtual #58                 // Method createServiceGroupContext:(Lorg/apache/axis2/description/AxisServiceGroup;)Lorg/apache/axis2/context/ServiceGroupContext;
      96: astore_2
      97: aload_0
      98: getfield      #8                  // Field applicationSessionServiceGroupContexts:Ljava/util/Hashtable;
     101: aload         6
     103: aload_2
     104: invokevirtual #59                 // Method java/util/Hashtable.put:(Ljava/lang/Object;Ljava/lang/Object;)Ljava/lang/Object;
     107: pop
     108: aload_1
     109: aload_2
     110: invokevirtual #60                 // Method org/apache/axis2/context/MessageContext.setServiceGroupContext:(Lorg/apache/axis2/context/ServiceGroupContext;)V
     113: aload_1
     114: aload_2
     115: aload         4
     117: invokevirtual #61                 // Method org/apache/axis2/context/ServiceGroupContext.getServiceContext:(Lorg/apache/axis2/description/AxisService;)Lorg/apache/axis2/context/ServiceContext;
     120: invokevirtual #62                 // Method org/apache/axis2/context/MessageContext.setServiceContext:(Lorg/apache/axis2/context/ServiceContext;)V
     123: goto          264
     126: ldc           #63                 // String soapsession
     128: aload         5
     130: invokevirtual #50                 // Method java/lang/String.equals:(Ljava/lang/Object;)Z
     133: ifeq          223
     136: aload_0
     137: invokespecial #64                 // Method cleanupServiceGroupContexts:()V
     140: aload_1
     141: invokevirtual #65                 // Method org/apache/axis2/context/MessageContext.getServiceGroupContextId:()Ljava/lang/String;
     144: astore        6
     146: aload         6
     148: ifnull        162
     151: aload_0
     152: aload         6
     154: aload_1
     155: invokevirtual #66                 // Method getServiceGroupContextFromSoapSessionTable:(Ljava/lang/String;Lorg/apache/axis2/context/MessageContext;)Lorg/apache/axis2/context/ServiceGroupContext;
     158: astore_2
     159: goto          205
     162: aload         4
     164: invokevirtual #51                 // Method org/apache/axis2/description/AxisService.getAxisServiceGroup:()Lorg/apache/axis2/description/AxisServiceGroup;
     167: astore        7
     169: aload_0
     170: aload         7
     172: invokevirtual #58                 // Method createServiceGroupContext:(Lorg/apache/axis2/description/AxisServiceGroup;)Lorg/apache/axis2/context/ServiceGroupContext;
     175: astore_2
     176: aload_2
     177: aload         4
     179: invokevirtual #61                 // Method org/apache/axis2/context/ServiceGroupContext.getServiceContext:(Lorg/apache/axis2/description/AxisService;)Lorg/apache/axis2/context/ServiceContext;
     182: astore_3
     183: invokestatic  #67                 // Method org/apache/axiom/util/UIDGenerator.generateURNString:()Ljava/lang/String;
     186: astore        6
     188: aload_2
     189: aload         6
     191: invokevirtual #68                 // Method org/apache/axis2/context/ServiceGroupContext.setId:(Ljava/lang/String;)V
     194: aload_1
     195: aload         6
     197: invokevirtual #69                 // Method org/apache/axis2/context/MessageContext.setServiceGroupContextId:(Ljava/lang/String;)V
     200: aload_0
     201: aload_2
     202: invokevirtual #70                 // Method addServiceGroupContextIntoSoapSessionTable:(Lorg/apache/axis2/context/ServiceGroupContext;)V
     205: aload_1
     206: aload_2
     207: invokevirtual #60                 // Method org/apache/axis2/context/MessageContext.setServiceGroupContext:(Lorg/apache/axis2/context/ServiceGroupContext;)V
     210: aload_1
     211: aload_2
     212: aload         4
     214: invokevirtual #61                 // Method org/apache/axis2/context/ServiceGroupContext.getServiceContext:(Lorg/apache/axis2/description/AxisService;)Lorg/apache/axis2/context/ServiceContext;
     217: invokevirtual #62                 // Method org/apache/axis2/context/MessageContext.setServiceContext:(Lorg/apache/axis2/context/ServiceContext;)V
     220: goto          264
     223: ldc           #71                 // String request
     225: aload         5
     227: invokevirtual #50                 // Method java/lang/String.equals:(Ljava/lang/Object;)Z
     230: ifeq          264
     233: aload         4
     235: invokevirtual #51                 // Method org/apache/axis2/description/AxisService.getAxisServiceGroup:()Lorg/apache/axis2/description/AxisServiceGroup;
     238: astore        6
     240: aload_0
     241: aload         6
     243: invokevirtual #58                 // Method createServiceGroupContext:(Lorg/apache/axis2/description/AxisServiceGroup;)Lorg/apache/axis2/context/ServiceGroupContext;
     246: astore_2
     247: aload_1
     248: aload_2
     249: invokevirtual #60                 // Method org/apache/axis2/context/MessageContext.setServiceGroupContext:(Lorg/apache/axis2/context/ServiceGroupContext;)V
     252: aload_2
     253: aload         4
     255: invokevirtual #61                 // Method org/apache/axis2/context/ServiceGroupContext.getServiceContext:(Lorg/apache/axis2/description/AxisService;)Lorg/apache/axis2/context/ServiceContext;
     258: astore_3
     259: aload_1
     260: aload_3
     261: invokevirtual #62                 // Method org/apache/axis2/context/MessageContext.setServiceContext:(Lorg/apache/axis2/context/ServiceContext;)V
     264: aload_1
     265: invokevirtual #72                 // Method org/apache/axis2/context/MessageContext.getOperationContext:()Lorg/apache/axis2/context/OperationContext;
     268: ifnull        279
     271: aload_1
     272: invokevirtual #72                 // Method org/apache/axis2/context/MessageContext.getOperationContext:()Lorg/apache/axis2/context/OperationContext;
     275: aload_3
     276: invokevirtual #73                 // Method org/apache/axis2/context/OperationContext.setParent:(Lorg/apache/axis2/context/AbstractContext;)V
     279: return

  public boolean registerOperationContext(java.lang.String, org.apache.axis2.context.OperationContext);
    Code:
       0: aload_0
       1: aload_1
       2: aload_2
       3: iconst_0
       4: invokevirtual #74                 // Method registerOperationContext:(Ljava/lang/String;Lorg/apache/axis2/context/OperationContext;Z)Z
       7: ireturn

  public boolean registerOperationContext(java.lang.String, org.apache.axis2.context.OperationContext, boolean);
    Code:
       0: aload_1
       1: ifnonnull     23
       4: getstatic     #75                 // Field log:Lorg/apache/axis2/util/OnDemandLogger;
       7: invokevirtual #76                 // Method org/apache/axis2/util/OnDemandLogger.isDebugEnabled:()Z
      10: ifeq          21
      13: getstatic     #75                 // Field log:Lorg/apache/axis2/util/OnDemandLogger;
      16: ldc           #77                 // String messageID is null. Returning false
      18: invokevirtual #78                 // Method org/apache/axis2/util/OnDemandLogger.debug:(Ljava/lang/Object;)V
      21: iconst_0
      22: ireturn
      23: iconst_0
      24: istore        4
      26: aload_2
      27: aload_1
      28: invokevirtual #79                 // Method org/apache/axis2/context/OperationContext.setKey:(Ljava/lang/String;)V
      31: iload_3
      32: ifeq          48
      35: aload_0
      36: getfield      #4                  // Field operationContextMap:Ljava/util/concurrent/ConcurrentHashMap;
      39: aload_1
      40: aload_2
      41: invokevirtual #80                 // Method java/util/concurrent/ConcurrentHashMap.put:(Ljava/lang/Object;Ljava/lang/Object;)Ljava/lang/Object;
      44: pop
      45: goto          71
      48: aload_0
      49: getfield      #4                  // Field operationContextMap:Ljava/util/concurrent/ConcurrentHashMap;
      52: aload_1
      53: aload_2
      54: invokevirtual #81                 // Method java/util/concurrent/ConcurrentHashMap.putIfAbsent:(Ljava/lang/Object;Ljava/lang/Object;)Ljava/lang/Object;
      57: astore        5
      59: aload         5
      61: ifnull        68
      64: iconst_1
      65: goto          69
      68: iconst_0
      69: istore        4
      71: getstatic     #75                 // Field log:Lorg/apache/axis2/util/OnDemandLogger;
      74: invokevirtual #76                 // Method org/apache/axis2/util/OnDemandLogger.isDebugEnabled:()Z
      77: ifeq          205
      80: getstatic     #75                 // Field log:Lorg/apache/axis2/util/OnDemandLogger;
      83: new           #82                 // class java/lang/StringBuilder
      86: dup
      87: invokespecial #83                 // Method java/lang/StringBuilder."<init>":()V
      90: ldc           #84                 // String registerOperationContext (
      92: invokevirtual #85                 // Method java/lang/StringBuilder.append:(Ljava/lang/String;)Ljava/lang/StringBuilder;
      95: iload_3
      96: invokevirtual #86                 // Method java/lang/StringBuilder.append:(Z)Ljava/lang/StringBuilder;
      99: ldc           #87                 // String ):
     101: invokevirtual #85                 // Method java/lang/StringBuilder.append:(Ljava/lang/String;)Ljava/lang/StringBuilder;
     104: aload_2
     105: invokevirtual #88                 // Method java/lang/StringBuilder.append:(Ljava/lang/Object;)Ljava/lang/StringBuilder;
     108: ldc           #89                 // String  with key:
     110: invokevirtual #85                 // Method java/lang/StringBuilder.append:(Ljava/lang/String;)Ljava/lang/StringBuilder;
     113: aload_1
     114: invokevirtual #85                 // Method java/lang/StringBuilder.append:(Ljava/lang/String;)Ljava/lang/StringBuilder;
     117: invokevirtual #90                 // Method java/lang/StringBuilder.toString:()Ljava/lang/String;
     120: invokevirtual #78                 // Method org/apache/axis2/util/OnDemandLogger.debug:(Ljava/lang/Object;)V
     123: aload_2
     124: invokevirtual #91                 // Method org/apache/axis2/context/OperationContext.getMessageContexts:()Ljava/util/HashMap;
     127: astore        5
     129: aload         5
     131: invokevirtual #92                 // Method java/util/HashMap.values:()Ljava/util/Collection;
     134: invokeinterface #93,  1           // InterfaceMethod java/util/Collection.iterator:()Ljava/util/Iterator;
     139: astore        6
     141: aload         6
     143: invokeinterface #36,  1           // InterfaceMethod java/util/Iterator.hasNext:()Z
     148: ifeq          205
     151: aload         6
     153: invokeinterface #37,  1           // InterfaceMethod java/util/Iterator.next:()Ljava/lang/Object;
     158: checkcast     #94                 // class org/apache/axis2/context/MessageContext
     161: astore        7
     163: getstatic     #75                 // Field log:Lorg/apache/axis2/util/OnDemandLogger;
     166: new           #82                 // class java/lang/StringBuilder
     169: dup
     170: invokespecial #83                 // Method java/lang/StringBuilder."<init>":()V
     173: ldc           #95                 // String msgContext:
     175: invokevirtual #85                 // Method java/lang/StringBuilder.append:(Ljava/lang/String;)Ljava/lang/StringBuilder;
     178: aload         7
     180: invokevirtual #88                 // Method java/lang/StringBuilder.append:(Ljava/lang/Object;)Ljava/lang/StringBuilder;
     183: ldc           #96                 // String  action:
     185: invokevirtual #85                 // Method java/lang/StringBuilder.append:(Ljava/lang/String;)Ljava/lang/StringBuilder;
     188: aload         7
     190: invokevirtual #97                 // Method org/apache/axis2/context/MessageContext.getWSAAction:()Ljava/lang/String;
     193: invokevirtual #85                 // Method java/lang/StringBuilder.append:(Ljava/lang/String;)Ljava/lang/StringBuilder;
     196: invokevirtual #90                 // Method java/lang/StringBuilder.toString:()Ljava/lang/String;
     199: invokevirtual #78                 // Method org/apache/axis2/util/OnDemandLogger.debug:(Ljava/lang/Object;)V
     202: goto          141
     205: iload         4
     207: ifeq          214
     210: iload_3
     211: ifeq          218
     214: iconst_1
     215: goto          219
     218: iconst_0
     219: ireturn

  public void unregisterOperationContext(java.lang.String);
    Code:
       0: aload_1
       1: ifnonnull     24
       4: getstatic     #75                 // Field log:Lorg/apache/axis2/util/OnDemandLogger;
       7: invokevirtual #76                 // Method org/apache/axis2/util/OnDemandLogger.isDebugEnabled:()Z
      10: ifeq          41
      13: getstatic     #75                 // Field log:Lorg/apache/axis2/util/OnDemandLogger;
      16: ldc           #98                 // String messageID is null.
      18: invokevirtual #78                 // Method org/apache/axis2/util/OnDemandLogger.debug:(Ljava/lang/Object;)V
      21: goto          41
      24: aload_0
      25: getfield      #4                  // Field operationContextMap:Ljava/util/concurrent/ConcurrentHashMap;
      28: aload_1
      29: invokevirtual #99                 // Method java/util/concurrent/ConcurrentHashMap.remove:(Ljava/lang/Object;)Ljava/lang/Object;
      32: checkcast     #100                // class org/apache/axis2/context/OperationContext
      35: astore_2
      36: aload_0
      37: aload_2
      38: invokevirtual #101                // Method contextRemoved:(Lorg/apache/axis2/context/AbstractContext;)V
      41: return

  public boolean isAnyOperationContextRegistered();
    Code:
       0: aload_0
       1: getfield      #4                  // Field operationContextMap:Ljava/util/concurrent/ConcurrentHashMap;
       4: invokevirtual #102                // Method java/util/concurrent/ConcurrentHashMap.isEmpty:()Z
       7: ifne          14
      10: iconst_1
      11: goto          15
      14: iconst_0
      15: ireturn

  public void addServiceGroupContextIntoSoapSessionTable(org.apache.axis2.context.ServiceGroupContext);
    Code:
       0: aload_1
       1: invokevirtual #103                // Method org/apache/axis2/context/ServiceGroupContext.getId:()Ljava/lang/String;
       4: astore_2
       5: aload_0
       6: getfield      #7                  // Field serviceGroupContextMap:Ljava/util/Hashtable;
       9: aload_2
      10: aload_1
      11: invokevirtual #59                 // Method java/util/Hashtable.put:(Ljava/lang/Object;Ljava/lang/Object;)Ljava/lang/Object;
      14: pop
      15: aload_1
      16: invokevirtual #104                // Method org/apache/axis2/context/ServiceGroupContext.touch:()V
      19: aload_1
      20: aload_0
      21: invokevirtual #105                // Method org/apache/axis2/context/ServiceGroupContext.setParent:(Lorg/apache/axis2/context/AbstractContext;)V
      24: aload_0
      25: invokespecial #64                 // Method cleanupServiceGroupContexts:()V
      28: return

  public void addServiceGroupContextIntoApplicationScopeTable(org.apache.axis2.context.ServiceGroupContext);
    Code:
       0: aload_0
       1: getfield      #8                  // Field applicationSessionServiceGroupContexts:Ljava/util/Hashtable;
       4: ifnonnull     18
       7: aload_0
       8: new           #5                  // class java/util/Hashtable
      11: dup
      12: invokespecial #6                  // Method java/util/Hashtable."<init>":()V
      15: putfield      #8                  // Field applicationSessionServiceGroupContexts:Ljava/util/Hashtable;
      18: aload_0
      19: getfield      #8                  // Field applicationSessionServiceGroupContexts:Ljava/util/Hashtable;
      22: aload_1
      23: invokevirtual #106                // Method org/apache/axis2/context/ServiceGroupContext.getDescription:()Lorg/apache/axis2/description/AxisServiceGroup;
      26: invokevirtual #52                 // Method org/apache/axis2/description/AxisServiceGroup.getServiceGroupName:()Ljava/lang/String;
      29: aload_1
      30: invokevirtual #59                 // Method java/util/Hashtable.put:(Ljava/lang/Object;Ljava/lang/Object;)Ljava/lang/Object;
      33: pop
      34: return

  public void deployService(org.apache.axis2.description.AxisService) throws org.apache.axis2.AxisFault;
    Code:
       0: aload_0
       1: getfield      #14                 // Field axisConfiguration:Lorg/apache/axis2/engine/AxisConfiguration;
       4: aload_1
       5: invokevirtual #107                // Method org/apache/axis2/engine/AxisConfiguration.addService:(Lorg/apache/axis2/description/AxisService;)V
       8: ldc           #49                 // String application
      10: aload_1
      11: invokevirtual #47                 // Method org/apache/axis2/description/AxisService.getScope:()Ljava/lang/String;
      14: invokevirtual #50                 // Method java/lang/String.equals:(Ljava/lang/Object;)Z
      17: ifeq          33
      20: aload_0
      21: aload_1
      22: invokevirtual #51                 // Method org/apache/axis2/description/AxisService.getAxisServiceGroup:()Lorg/apache/axis2/description/AxisServiceGroup;
      25: invokevirtual #58                 // Method createServiceGroupContext:(Lorg/apache/axis2/description/AxisServiceGroup;)Lorg/apache/axis2/context/ServiceGroupContext;
      28: astore_2
      29: aload_2
      30: invokestatic  #108                // Method org/apache/axis2/engine/DependencyManager.initService:(Lorg/apache/axis2/context/ServiceGroupContext;)V
      33: return

  public org.apache.axis2.engine.AxisConfiguration getAxisConfiguration();
    Code:
       0: aload_0
       1: getfield      #14                 // Field axisConfiguration:Lorg/apache/axis2/engine/AxisConfiguration;
       4: areturn

  public org.apache.axis2.context.OperationContext getOperationContext(java.lang.String);
    Code:
       0: aload_0
       1: getfield      #4                  // Field operationContextMap:Ljava/util/concurrent/ConcurrentHashMap;
       4: aload_1
       5: invokevirtual #109                // Method java/util/concurrent/ConcurrentHashMap.get:(Ljava/lang/Object;)Ljava/lang/Object;
       8: checkcast     #100                // class org/apache/axis2/context/OperationContext
      11: areturn

  public org.apache.axis2.context.OperationContext findOperationContext(java.lang.String, java.lang.String, java.lang.String);
    Code:
       0: aload_1
       1: ifnonnull     6
       4: aconst_null
       5: areturn
       6: aload_2
       7: ifnonnull     12
      10: aconst_null
      11: areturn
      12: aload_0
      13: getfield      #4                  // Field operationContextMap:Ljava/util/concurrent/ConcurrentHashMap;
      16: invokevirtual #110                // Method java/util/concurrent/ConcurrentHashMap.values:()Ljava/util/Collection;
      19: invokeinterface #93,  1           // InterfaceMethod java/util/Collection.iterator:()Ljava/util/Iterator;
      24: astore        4
      26: aload         4
      28: invokeinterface #36,  1           // InterfaceMethod java/util/Iterator.hasNext:()Z
      33: ifeq          138
      36: aload         4
      38: invokeinterface #37,  1           // InterfaceMethod java/util/Iterator.next:()Ljava/lang/Object;
      43: checkcast     #100                // class org/apache/axis2/context/OperationContext
      46: astore        5
      48: aload         5
      50: ifnull        135
      53: aload         5
      55: invokevirtual #111                // Method org/apache/axis2/context/OperationContext.getOperationName:()Ljava/lang/String;
      58: astore        6
      60: aload         5
      62: invokevirtual #112                // Method org/apache/axis2/context/OperationContext.getServiceName:()Ljava/lang/String;
      65: astore        7
      67: aload         5
      69: invokevirtual #113                // Method org/apache/axis2/context/OperationContext.getServiceGroupName:()Ljava/lang/String;
      72: astore        8
      74: aload         6
      76: ifnull        135
      79: aload         6
      81: aload_1
      82: invokevirtual #50                 // Method java/lang/String.equals:(Ljava/lang/Object;)Z
      85: ifeq          135
      88: aload         7
      90: ifnull        135
      93: aload         7
      95: aload_2
      96: invokevirtual #50                 // Method java/lang/String.equals:(Ljava/lang/Object;)Z
      99: ifeq          135
     102: aload         8
     104: ifnull        123
     107: aload_3
     108: ifnull        123
     111: aload         8
     113: aload_3
     114: invokevirtual #50                 // Method java/lang/String.equals:(Ljava/lang/Object;)Z
     117: ifeq          123
     120: aload         5
     122: areturn
     123: aload         8
     125: ifnonnull     135
     128: aload_3
     129: ifnonnull     135
     132: aload         5
     134: areturn
     135: goto          26
     138: aconst_null
     139: areturn

  public org.apache.axis2.context.MessageContext createMessageContext();
    Code:
       0: new           #94                 // class org/apache/axis2/context/MessageContext
       3: dup
       4: aload_0
       5: invokespecial #114                // Method org/apache/axis2/context/MessageContext."<init>":(Lorg/apache/axis2/context/ConfigurationContext;)V
       8: astore_1
       9: aload_0
      10: aload_1
      11: invokevirtual #115                // Method contextCreated:(Lorg/apache/axis2/context/AbstractContext;)V
      14: aload_1
      15: areturn

  public org.apache.axis2.context.ServiceGroupContext createServiceGroupContext(org.apache.axis2.description.AxisServiceGroup);
    Code:
       0: new           #54                 // class org/apache/axis2/context/ServiceGroupContext
       3: dup
       4: aload_0
       5: aload_1
       6: invokespecial #116                // Method org/apache/axis2/context/ServiceGroupContext."<init>":(Lorg/apache/axis2/context/ConfigurationContext;Lorg/apache/axis2/description/AxisServiceGroup;)V
       9: astore_2
      10: aload_0
      11: aload_2
      12: invokevirtual #115                // Method contextCreated:(Lorg/apache/axis2/context/AbstractContext;)V
      15: aload_2
      16: areturn

  public java.io.File getRealPath(java.lang.String);
    Code:
       0: aload_0
       1: getfield      #14                 // Field axisConfiguration:Lorg/apache/axis2/engine/AxisConfiguration;
       4: invokevirtual #117                // Method org/apache/axis2/engine/AxisConfiguration.getRepository:()Ljava/net/URL;
       7: astore_2
       8: aload_2
       9: ifnull        34
      12: new           #118                // class java/io/File
      15: dup
      16: aload_2
      17: invokevirtual #119                // Method java/net/URL.getFile:()Ljava/lang/String;
      20: invokespecial #120                // Method java/io/File."<init>":(Ljava/lang/String;)V
      23: astore_3
      24: new           #118                // class java/io/File
      27: dup
      28: aload_3
      29: aload_1
      30: invokespecial #121                // Method java/io/File."<init>":(Ljava/io/File;Ljava/lang/String;)V
      33: areturn
      34: aconst_null
      35: areturn

  public org.apache.axis2.context.ServiceGroupContext getServiceGroupContextFromSoapSessionTable(java.lang.String, org.apache.axis2.context.MessageContext) throws org.apache.axis2.AxisFault;
    Code:
       0: aload_0
       1: getfield      #7                  // Field serviceGroupContextMap:Ljava/util/Hashtable;
       4: aload_1
       5: invokevirtual #53                 // Method java/util/Hashtable.get:(Ljava/lang/Object;)Ljava/lang/Object;
       8: checkcast     #54                 // class org/apache/axis2/context/ServiceGroupContext
      11: astore_3
      12: aload_3
      13: ifnull        22
      16: aload_3
      17: invokevirtual #104                // Method org/apache/axis2/context/ServiceGroupContext.touch:()V
      20: aload_3
      21: areturn
      22: new           #122                // class org/apache/axis2/AxisFault
      25: dup
      26: new           #82                 // class java/lang/StringBuilder
      29: dup
      30: invokespecial #83                 // Method java/lang/StringBuilder."<init>":()V
      33: ldc           #123                // String Unable to find corresponding context for the serviceGroupId:
      35: invokevirtual #85                 // Method java/lang/StringBuilder.append:(Ljava/lang/String;)Ljava/lang/StringBuilder;
      38: aload_1
      39: invokevirtual #85                 // Method java/lang/StringBuilder.append:(Ljava/lang/String;)Ljava/lang/StringBuilder;
      42: invokevirtual #90                 // Method java/lang/StringBuilder.toString:()Ljava/lang/String;
      45: invokespecial #124                // Method org/apache/axis2/AxisFault."<init>":(Ljava/lang/String;)V
      48: athrow

  public org.apache.axis2.context.ServiceGroupContext getServiceGroupContext(java.lang.String);
    Code:
       0: aload_1
       1: ifnonnull     6
       4: aconst_null
       5: areturn
       6: aconst_null
       7: astore_2
       8: aload_0
       9: getfield      #7                  // Field serviceGroupContextMap:Ljava/util/Hashtable;
      12: ifnull        58
      15: aload_0
      16: getfield      #7                  // Field serviceGroupContextMap:Ljava/util/Hashtable;
      19: aload_1
      20: invokevirtual #53                 // Method java/util/Hashtable.get:(Ljava/lang/Object;)Ljava/lang/Object;
      23: checkcast     #54                 // class org/apache/axis2/context/ServiceGroupContext
      26: astore_2
      27: aload_2
      28: ifnull        38
      31: aload_2
      32: invokevirtual #104                // Method org/apache/axis2/context/ServiceGroupContext.touch:()V
      35: goto          58
      38: aload_0
      39: getfield      #8                  // Field applicationSessionServiceGroupContexts:Ljava/util/Hashtable;
      42: aload_1
      43: invokevirtual #53                 // Method java/util/Hashtable.get:(Ljava/lang/Object;)Ljava/lang/Object;
      46: checkcast     #54                 // class org/apache/axis2/context/ServiceGroupContext
      49: astore_2
      50: aload_2
      51: ifnull        58
      54: aload_2
      55: invokevirtual #104                // Method org/apache/axis2/context/ServiceGroupContext.touch:()V
      58: aload_2
      59: areturn

  public java.lang.String[] getServiceGroupContextIDs();
    Code:
       0: aload_0
       1: getfield      #7                  // Field serviceGroupContextMap:Ljava/util/Hashtable;
       4: invokevirtual #125                // Method java/util/Hashtable.size:()I
       7: aload_0
       8: getfield      #8                  // Field applicationSessionServiceGroupContexts:Ljava/util/Hashtable;
      11: invokevirtual #125                // Method java/util/Hashtable.size:()I
      14: iadd
      15: anewarray     #20                 // class java/lang/String
      18: astore_1
      19: iconst_0
      20: istore_2
      21: aload_0
      22: getfield      #7                  // Field serviceGroupContextMap:Ljava/util/Hashtable;
      25: invokevirtual #126                // Method java/util/Hashtable.keySet:()Ljava/util/Set;
      28: invokeinterface #127,  1          // InterfaceMethod java/util/Set.iterator:()Ljava/util/Iterator;
      33: astore_3
      34: aload_3
      35: invokeinterface #36,  1           // InterfaceMethod java/util/Iterator.hasNext:()Z
      40: ifeq          65
      43: aload_3
      44: invokeinterface #37,  1           // InterfaceMethod java/util/Iterator.next:()Ljava/lang/Object;
      49: astore        4
      51: aload_1
      52: iload_2
      53: aload         4
      55: checkcast     #20                 // class java/lang/String
      58: aastore
      59: iinc          2, 1
      62: goto          34
      65: aload_0
      66: getfield      #8                  // Field applicationSessionServiceGroupContexts:Ljava/util/Hashtable;
      69: invokevirtual #126                // Method java/util/Hashtable.keySet:()Ljava/util/Set;
      72: invokeinterface #127,  1          // InterfaceMethod java/util/Set.iterator:()Ljava/util/Iterator;
      77: astore_3
      78: aload_3
      79: invokeinterface #36,  1           // InterfaceMethod java/util/Iterator.hasNext:()Z
      84: ifeq          109
      87: aload_3
      88: invokeinterface #37,  1           // InterfaceMethod java/util/Iterator.next:()Ljava/lang/Object;
      93: astore        4
      95: aload_1
      96: iload_2
      97: aload         4
      99: checkcast     #20                 // class java/lang/String
     102: aastore
     103: iinc          2, 1
     106: goto          78
     109: aload_1
     110: areturn

  public org.apache.axis2.util.threadpool.ThreadFactory getThreadPool();
    Code:
       0: aload_0
       1: getfield      #128                // Field threadPool:Lorg/apache/axis2/util/threadpool/ThreadFactory;
       4: ifnonnull     18
       7: aload_0
       8: new           #129                // class org/apache/axis2/util/threadpool/ThreadPool
      11: dup
      12: invokespecial #130                // Method org/apache/axis2/util/threadpool/ThreadPool."<init>":()V
      15: putfield      #128                // Field threadPool:Lorg/apache/axis2/util/threadpool/ThreadFactory;
      18: aload_0
      19: getfield      #128                // Field threadPool:Lorg/apache/axis2/util/threadpool/ThreadFactory;
      22: areturn

  public void setAxisConfiguration(org.apache.axis2.engine.AxisConfiguration);
    Code:
       0: aload_0
       1: aload_1
       2: putfield      #14                 // Field axisConfiguration:Lorg/apache/axis2/engine/AxisConfiguration;
       5: return

  public void setThreadPool(org.apache.axis2.util.threadpool.ThreadFactory) throws org.apache.axis2.AxisFault;
    Code:
       0: aload_0
       1: getfield      #128                // Field threadPool:Lorg/apache/axis2/util/threadpool/ThreadFactory;
       4: ifnonnull     15
       7: aload_0
       8: aload_1
       9: putfield      #128                // Field threadPool:Lorg/apache/axis2/util/threadpool/ThreadFactory;
      12: goto          28
      15: new           #122                // class org/apache/axis2/AxisFault
      18: dup
      19: ldc           #131                // String threadpoolset
      21: invokestatic  #132                // Method org/apache/axis2/i18n/Messages.getMessage:(Ljava/lang/String;)Ljava/lang/String;
      24: invokespecial #124                // Method org/apache/axis2/AxisFault."<init>":(Ljava/lang/String;)V
      27: athrow
      28: return

  public void removeServiceGroupContext(java.lang.String);
    Code:
       0: aload_0
       1: getfield      #7                  // Field serviceGroupContextMap:Ljava/util/Hashtable;
       4: ifnonnull     8
       7: return
       8: aload_0
       9: getfield      #7                  // Field serviceGroupContextMap:Ljava/util/Hashtable;
      12: aload_1
      13: invokevirtual #53                 // Method java/util/Hashtable.get:(Ljava/lang/Object;)Ljava/lang/Object;
      16: checkcast     #54                 // class org/apache/axis2/context/ServiceGroupContext
      19: astore_2
      20: aload_0
      21: getfield      #7                  // Field serviceGroupContextMap:Ljava/util/Hashtable;
      24: aload_1
      25: invokevirtual #133                // Method java/util/Hashtable.remove:(Ljava/lang/Object;)Ljava/lang/Object;
      28: pop
      29: aload_0
      30: aload_2
      31: invokespecial #134                // Method cleanupServiceContexts:(Lorg/apache/axis2/context/ServiceGroupContext;)V
      34: return

  private void cleanupServiceGroupContexts();
    Code:
       0: aload_0
       1: getfield      #7                  // Field serviceGroupContextMap:Ljava/util/Hashtable;
       4: ifnonnull     8
       7: return
       8: new           #135                // class java/util/Date
      11: dup
      12: invokespecial #136                // Method java/util/Date."<init>":()V
      15: invokevirtual #137                // Method java/util/Date.getTime:()J
      18: lstore_1
      19: aload_0
      20: getfield      #7                  // Field serviceGroupContextMap:Ljava/util/Hashtable;
      23: dup
      24: astore_3
      25: monitorenter
      26: aload_0
      27: getfield      #7                  // Field serviceGroupContextMap:Ljava/util/Hashtable;
      30: invokevirtual #126                // Method java/util/Hashtable.keySet:()Ljava/util/Set;
      33: invokeinterface #127,  1          // InterfaceMethod java/util/Set.iterator:()Ljava/util/Iterator;
      38: astore        4
      40: aload         4
      42: invokeinterface #36,  1           // InterfaceMethod java/util/Iterator.hasNext:()Z
      47: ifeq          113
      50: aload         4
      52: invokeinterface #37,  1           // InterfaceMethod java/util/Iterator.next:()Ljava/lang/Object;
      57: checkcast     #20                 // class java/lang/String
      60: astore        5
      62: aload_0
      63: getfield      #7                  // Field serviceGroupContextMap:Ljava/util/Hashtable;
      66: aload         5
      68: invokevirtual #53                 // Method java/util/Hashtable.get:(Ljava/lang/Object;)Ljava/lang/Object;
      71: checkcast     #54                 // class org/apache/axis2/context/ServiceGroupContext
      74: astore        6
      76: lload_1
      77: aload         6
      79: invokevirtual #138                // Method org/apache/axis2/context/ServiceGroupContext.getLastTouchedTime:()J
      82: lsub
      83: aload_0
      84: invokevirtual #139                // Method getServiceGroupContextTimeoutInterval:()J
      87: lcmp
      88: ifle          110
      91: aload         4
      93: invokeinterface #140,  1          // InterfaceMethod java/util/Iterator.remove:()V
      98: aload_0
      99: aload         6
     101: invokespecial #134                // Method cleanupServiceContexts:(Lorg/apache/axis2/context/ServiceGroupContext;)V
     104: aload_0
     105: aload         6
     107: invokevirtual #101                // Method contextRemoved:(Lorg/apache/axis2/context/AbstractContext;)V
     110: goto          40
     113: aload_3
     114: monitorexit
     115: goto          125
     118: astore        7
     120: aload_3
     121: monitorexit
     122: aload         7
     124: athrow
     125: return
    Exception table:
       from    to  target type
          26   115   118   any
         118   122   118   any

  public org.apache.axis2.engine.ListenerManager getListenerManager();
    Code:
       0: aload_0
       1: getfield      #141                // Field listenerManager:Lorg/apache/axis2/engine/ListenerManager;
       4: areturn

  public void setTransportManager(org.apache.axis2.engine.ListenerManager);
    Code:
       0: aload_0
       1: aload_1
       2: putfield      #141                // Field listenerManager:Lorg/apache/axis2/engine/ListenerManager;
       5: return

  private void cleanupServiceContexts(org.apache.axis2.context.ServiceGroupContext);
    Code:
       0: aload_1
       1: ifnonnull     5
       4: return
       5: aload_1
       6: invokevirtual #142                // Method org/apache/axis2/context/ServiceGroupContext.getServiceContexts:()Ljava/util/Iterator;
       9: astore_2
      10: aload_2
      11: ifnonnull     15
      14: return
      15: aload_2
      16: invokeinterface #36,  1           // InterfaceMethod java/util/Iterator.hasNext:()Z
      21: ifeq          41
      24: aload_2
      25: invokeinterface #37,  1           // InterfaceMethod java/util/Iterator.next:()Ljava/lang/Object;
      30: checkcast     #143                // class org/apache/axis2/context/ServiceContext
      33: astore_3
      34: aload_3
      35: invokestatic  #144                // Method org/apache/axis2/engine/DependencyManager.destroyServiceObject:(Lorg/apache/axis2/context/ServiceContext;)V
      38: goto          15
      41: return

  public void cleanupContexts();
    Code:
       0: aload_0
       1: getfield      #8                  // Field applicationSessionServiceGroupContexts:Ljava/util/Hashtable;
       4: ifnull        66
       7: aload_0
       8: getfield      #8                  // Field applicationSessionServiceGroupContexts:Ljava/util/Hashtable;
      11: invokevirtual #125                // Method java/util/Hashtable.size:()I
      14: ifle          66
      17: aload_0
      18: getfield      #8                  // Field applicationSessionServiceGroupContexts:Ljava/util/Hashtable;
      21: invokevirtual #145                // Method java/util/Hashtable.values:()Ljava/util/Collection;
      24: invokeinterface #93,  1           // InterfaceMethod java/util/Collection.iterator:()Ljava/util/Iterator;
      29: astore_1
      30: aload_1
      31: invokeinterface #36,  1           // InterfaceMethod java/util/Iterator.hasNext:()Z
      36: ifeq          59
      39: aload_1
      40: invokeinterface #37,  1           // InterfaceMethod java/util/Iterator.next:()Ljava/lang/Object;
      45: astore_2
      46: aload_2
      47: checkcast     #54                 // class org/apache/axis2/context/ServiceGroupContext
      50: astore_3
      51: aload_0
      52: aload_3
      53: invokespecial #134                // Method cleanupServiceContexts:(Lorg/apache/axis2/context/ServiceGroupContext;)V
      56: goto          30
      59: aload_0
      60: getfield      #8                  // Field applicationSessionServiceGroupContexts:Ljava/util/Hashtable;
      63: invokevirtual #146                // Method java/util/Hashtable.clear:()V
      66: aload_0
      67: getfield      #7                  // Field serviceGroupContextMap:Ljava/util/Hashtable;
      70: ifnull        132
      73: aload_0
      74: getfield      #7                  // Field serviceGroupContextMap:Ljava/util/Hashtable;
      77: invokevirtual #125                // Method java/util/Hashtable.size:()I
      80: ifle          132
      83: aload_0
      84: getfield      #7                  // Field serviceGroupContextMap:Ljava/util/Hashtable;
      87: invokevirtual #145                // Method java/util/Hashtable.values:()Ljava/util/Collection;
      90: invokeinterface #93,  1           // InterfaceMethod java/util/Collection.iterator:()Ljava/util/Iterator;
      95: astore_1
      96: aload_1
      97: invokeinterface #36,  1           // InterfaceMethod java/util/Iterator.hasNext:()Z
     102: ifeq          125
     105: aload_1
     106: invokeinterface #37,  1           // InterfaceMethod java/util/Iterator.next:()Ljava/lang/Object;
     111: astore_2
     112: aload_2
     113: checkcast     #54                 // class org/apache/axis2/context/ServiceGroupContext
     116: astore_3
     117: aload_0
     118: aload_3
     119: invokespecial #134                // Method cleanupServiceContexts:(Lorg/apache/axis2/context/ServiceGroupContext;)V
     122: goto          96
     125: aload_0
     126: getfield      #7                  // Field serviceGroupContextMap:Ljava/util/Hashtable;
     129: invokevirtual #146                // Method java/util/Hashtable.clear:()V
     132: return

  public void shutdownModulesAndServices() throws org.apache.axis2.AxisFault;
    Code:
       0: aload_0
       1: getfield      #13                 // Field stopped:Z
       4: ifeq          25
       7: getstatic     #75                 // Field log:Lorg/apache/axis2/util/OnDemandLogger;
      10: invokevirtual #76                 // Method org/apache/axis2/util/OnDemandLogger.isDebugEnabled:()Z
      13: ifeq          24
      16: getstatic     #75                 // Field log:Lorg/apache/axis2/util/OnDemandLogger;
      19: ldc           #147                // String ConfigurationContext is stopped, modules and services not being shut down
      21: invokevirtual #78                 // Method org/apache/axis2/util/OnDemandLogger.debug:(Ljava/lang/Object;)V
      24: return
      25: getstatic     #75                 // Field log:Lorg/apache/axis2/util/OnDemandLogger;
      28: invokevirtual #76                 // Method org/apache/axis2/util/OnDemandLogger.isDebugEnabled:()Z
      31: ifeq          42
      34: getstatic     #75                 // Field log:Lorg/apache/axis2/util/OnDemandLogger;
      37: ldc           #148                // String Invoke modules shutdown.
      39: invokevirtual #78                 // Method org/apache/axis2/util/OnDemandLogger.debug:(Ljava/lang/Object;)V
      42: aload_0
      43: getfield      #14                 // Field axisConfiguration:Lorg/apache/axis2/engine/AxisConfiguration;
      46: ifnull        185
      49: aload_0
      50: getfield      #14                 // Field axisConfiguration:Lorg/apache/axis2/engine/AxisConfiguration;
      53: invokevirtual #149                // Method org/apache/axis2/engine/AxisConfiguration.getModules:()Ljava/util/HashMap;
      56: astore_1
      57: getstatic     #75                 // Field log:Lorg/apache/axis2/util/OnDemandLogger;
      60: invokevirtual #76                 // Method org/apache/axis2/util/OnDemandLogger.isDebugEnabled:()Z
      63: ifeq          91
      66: getstatic     #75                 // Field log:Lorg/apache/axis2/util/OnDemandLogger;
      69: new           #82                 // class java/lang/StringBuilder
      72: dup
      73: invokespecial #83                 // Method java/lang/StringBuilder."<init>":()V
      76: ldc           #150                // String Modules to be shutdown from axisConfiguration:
      78: invokevirtual #85                 // Method java/lang/StringBuilder.append:(Ljava/lang/String;)Ljava/lang/StringBuilder;
      81: aload_1
      82: invokevirtual #88                 // Method java/lang/StringBuilder.append:(Ljava/lang/Object;)Ljava/lang/StringBuilder;
      85: invokevirtual #90                 // Method java/lang/StringBuilder.toString:()Ljava/lang/String;
      88: invokevirtual #78                 // Method org/apache/axis2/util/OnDemandLogger.debug:(Ljava/lang/Object;)V
      91: aload_1
      92: ifnull        185
      95: aload_1
      96: invokevirtual #92                 // Method java/util/HashMap.values:()Ljava/util/Collection;
      99: invokeinterface #93,  1           // InterfaceMethod java/util/Collection.iterator:()Ljava/util/Iterator;
     104: astore_2
     105: aload_2
     106: invokeinterface #36,  1           // InterfaceMethod java/util/Iterator.hasNext:()Z
     111: ifeq          185
     114: aload_2
     115: invokeinterface #37,  1           // InterfaceMethod java/util/Iterator.next:()Ljava/lang/Object;
     120: checkcast     #151                // class org/apache/axis2/description/AxisModule
     123: astore_3
     124: aload_3
     125: invokevirtual #152                // Method org/apache/axis2/description/AxisModule.getModule:()Lorg/apache/axis2/modules/Module;
     128: astore        4
     130: aload         4
     132: ifnull        182
     135: aload         4
     137: aload_0
     138: invokeinterface #153,  2          // InterfaceMethod org/apache/axis2/modules/Module.shutdown:(Lorg/apache/axis2/context/ConfigurationContext;)V
     143: goto          182
     146: astore        5
     148: getstatic     #75                 // Field log:Lorg/apache/axis2/util/OnDemandLogger;
     151: new           #82                 // class java/lang/StringBuilder
     154: dup
     155: invokespecial #83                 // Method java/lang/StringBuilder."<init>":()V
     158: ldc           #155                // String Could not shutdown module
     160: invokevirtual #85                 // Method java/lang/StringBuilder.append:(Ljava/lang/String;)Ljava/lang/StringBuilder;
     163: aload         4
     165: invokevirtual #156                // Method java/lang/Object.getClass:()Ljava/lang/Class;
     168: invokevirtual #157                // Method java/lang/Class.getName:()Ljava/lang/String;
     171: invokevirtual #85                 // Method java/lang/StringBuilder.append:(Ljava/lang/String;)Ljava/lang/StringBuilder;
     174: invokevirtual #90                 // Method java/lang/StringBuilder.toString:()Ljava/lang/String;
     177: aload         5
     179: invokevirtual #158                // Method org/apache/axis2/util/OnDemandLogger.warn:(Ljava/lang/Object;Ljava/lang/Throwable;)V
     182: goto          105
     185: aload_0
     186: invokevirtual #159                // Method cleanupContexts:()V
     189: getstatic     #75                 // Field log:Lorg/apache/axis2/util/OnDemandLogger;
     192: invokevirtual #76                 // Method org/apache/axis2/util/OnDemandLogger.isDebugEnabled:()Z
     195: ifeq          206
     198: getstatic     #75                 // Field log:Lorg/apache/axis2/util/OnDemandLogger;
     201: ldc           #160                // String Invoke services shutdown.
     203: invokevirtual #78                 // Method org/apache/axis2/util/OnDemandLogger.debug:(Ljava/lang/Object;)V
     206: aload_0
     207: getfield      #14                 // Field axisConfiguration:Lorg/apache/axis2/engine/AxisConfiguration;
     210: ifnull        303
     213: aload_0
     214: getfield      #14                 // Field axisConfiguration:Lorg/apache/axis2/engine/AxisConfiguration;
     217: invokevirtual #161                // Method org/apache/axis2/engine/AxisConfiguration.getServices:()Ljava/util/HashMap;
     220: invokevirtual #92                 // Method java/util/HashMap.values:()Ljava/util/Collection;
     223: invokeinterface #93,  1           // InterfaceMethod java/util/Collection.iterator:()Ljava/util/Iterator;
     228: astore_1
     229: aload_1
     230: invokeinterface #36,  1           // InterfaceMethod java/util/Iterator.hasNext:()Z
     235: ifeq          303
     238: aload_1
     239: invokeinterface #37,  1           // InterfaceMethod java/util/Iterator.next:()Ljava/lang/Object;
     244: checkcast     #162                // class org/apache/axis2/description/AxisService
     247: astore_2
     248: aload_2
     249: invokevirtual #163                // Method org/apache/axis2/description/AxisService.getServiceLifeCycle:()Lorg/apache/axis2/engine/ServiceLifeCycle;
     252: astore_3
     253: aload_3
     254: ifnull        300
     257: aload_3
     258: aload_0
     259: aload_2
     260: invokeinterface #164,  3          // InterfaceMethod org/apache/axis2/engine/ServiceLifeCycle.shutDown:(Lorg/apache/axis2/context/ConfigurationContext;Lorg/apache/axis2/description/AxisService;)V
     265: goto          300
     268: astore        4
     270: getstatic     #75                 // Field log:Lorg/apache/axis2/util/OnDemandLogger;
     273: new           #82                 // class java/lang/StringBuilder
     276: dup
     277: invokespecial #83                 // Method java/lang/StringBuilder."<init>":()V
     280: ldc           #165                // String Could not shutdown service
     282: invokevirtual #85                 // Method java/lang/StringBuilder.append:(Ljava/lang/String;)Ljava/lang/StringBuilder;
     285: aload_2
     286: invokevirtual #166                // Method org/apache/axis2/description/AxisService.getName:()Ljava/lang/String;
     289: invokevirtual #85                 // Method java/lang/StringBuilder.append:(Ljava/lang/String;)Ljava/lang/StringBuilder;
     292: invokevirtual #90                 // Method java/lang/StringBuilder.toString:()Ljava/lang/String;
     295: aload         4
     297: invokevirtual #158                // Method org/apache/axis2/util/OnDemandLogger.warn:(Ljava/lang/Object;Ljava/lang/Throwable;)V
     300: goto          229
     303: aload_0
     304: iconst_1
     305: putfield      #13                 // Field stopped:Z
     308: return
    Exception table:
       from    to  target type
         135   143   146   Class java/lang/Exception
         257   265   268   Class java/lang/Exception

  public void terminate() throws org.apache.axis2.AxisFault;
    Code:
       0: aload_0
       1: invokevirtual #167                // Method shutdownModulesAndServices:()V
       4: aload_0
       5: getfield      #141                // Field listenerManager:Lorg/apache/axis2/engine/ListenerManager;
       8: ifnull        18
      11: aload_0
      12: getfield      #141                // Field listenerManager:Lorg/apache/axis2/engine/ListenerManager;
      15: invokevirtual #168                // Method org/apache/axis2/engine/ListenerManager.destroy:()V
      18: aload_0
      19: getfield      #14                 // Field axisConfiguration:Lorg/apache/axis2/engine/AxisConfiguration;
      22: ifnull        41
      25: aload_0
      26: getfield      #14                 // Field axisConfiguration:Lorg/apache/axis2/engine/AxisConfiguration;
      29: invokevirtual #169                // Method org/apache/axis2/engine/AxisConfiguration.cleanup:()V
      32: aload_0
      33: invokespecial #170                // Method cleanupTemp:()V
      36: aload_0
      37: aconst_null
      38: putfield      #14                 // Field axisConfiguration:Lorg/apache/axis2/engine/AxisConfiguration;
      41: return

  private void cleanupTemp();
    Code:
       0: aload_0
       1: getfield      #14                 // Field axisConfiguration:Lorg/apache/axis2/engine/AxisConfiguration;
       4: ldc           #171                // String artifactsDIR
       6: invokevirtual #172                // Method org/apache/axis2/engine/AxisConfiguration.getParameterValue:(Ljava/lang/String;)Ljava/lang/Object;
       9: checkcast     #118                // class java/io/File
      12: astore_1
      13: aload_1
      14: ifnonnull     43
      17: new           #173                // class org/apache/axis2/context/ConfigurationContext$1
      20: dup
      21: aload_0
      22: invokespecial #174                // Method org/apache/axis2/context/ConfigurationContext$1."<init>":(Lorg/apache/axis2/context/ConfigurationContext;)V
      25: invokestatic  #175                // Method org/apache/axis2/java/security/AccessController.doPrivileged:(Ljava/security/PrivilegedAction;)Ljava/lang/Object;
      28: checkcast     #20                 // class java/lang/String
      31: astore_2
      32: new           #118                // class java/io/File
      35: dup
      36: aload_2
      37: ldc           #176                // String _axis2
      39: invokespecial #177                // Method java/io/File."<init>":(Ljava/lang/String;Ljava/lang/String;)V
      42: astore_1
      43: aload_0
      44: aload_1
      45: invokespecial #178                // Method deleteTempFiles:(Ljava/io/File;)V
      48: return

  private void deleteTempFiles(java.io.File);
    Code:
       0: new           #179                // class org/apache/axis2/context/ConfigurationContext$2
       3: dup
       4: aload_0
       5: aload_1
       6: invokespecial #180                // Method org/apache/axis2/context/ConfigurationContext$2."<init>":(Lorg/apache/axis2/context/ConfigurationContext;Ljava/io/File;)V
       9: invokestatic  #175                // Method org/apache/axis2/java/security/AccessController.doPrivileged:(Ljava/security/PrivilegedAction;)Ljava/lang/Object;
      12: checkcast     #181                // class java/lang/Boolean
      15: astore_2
      16: aload_2
      17: invokevirtual #182                // Method java/lang/Boolean.booleanValue:()Z
      20: ifeq          75
      23: new           #183                // class org/apache/axis2/context/ConfigurationContext$3
      26: dup
      27: aload_0
      28: aload_1
      29: invokespecial #184                // Method org/apache/axis2/context/ConfigurationContext$3."<init>":(Lorg/apache/axis2/context/ConfigurationContext;Ljava/io/File;)V
      32: invokestatic  #175                // Method org/apache/axis2/java/security/AccessController.doPrivileged:(Ljava/security/PrivilegedAction;)Ljava/lang/Object;
      35: checkcast     #185                // class "[Ljava/lang/String;"
      38: astore_3
      39: iconst_0
      40: istore        4
      42: aload_3
      43: ifnull        75
      46: iload         4
      48: aload_3
      49: arraylength
      50: if_icmpge     75
      53: aload_0
      54: new           #118                // class java/io/File
      57: dup
      58: aload_1
      59: aload_3
      60: iload         4
      62: aaload
      63: invokespecial #121                // Method java/io/File."<init>":(Ljava/io/File;Ljava/lang/String;)V
      66: invokespecial #178                // Method deleteTempFiles:(Ljava/io/File;)V
      69: iinc          4, 1
      72: goto          42
      75: new           #186                // class org/apache/axis2/context/ConfigurationContext$4
      78: dup
      79: aload_0
      80: aload_1
      81: invokespecial #187                // Method org/apache/axis2/context/ConfigurationContext$4."<init>":(Lorg/apache/axis2/context/ConfigurationContext;Ljava/io/File;)V
      84: invokestatic  #175                // Method org/apache/axis2/java/security/AccessController.doPrivileged:(Ljava/security/PrivilegedAction;)Ljava/lang/Object;
      87: pop
      88: return

  public java.lang.String getServiceContextPath();
    Code:
       0: aload_0
       1: getfield      #12                 // Field cachedServicePath:Ljava/lang/String;
       4: ifnonnull     15
       7: aload_0
       8: aload_0
       9: invokespecial #188                // Method internalGetServiceContextPath:()Ljava/lang/String;
      12: putfield      #12                 // Field cachedServicePath:Ljava/lang/String;
      15: aload_0
      16: getfield      #12                 // Field cachedServicePath:Ljava/lang/String;
      19: areturn

  private java.lang.String internalGetServiceContextPath();
    Code:
       0: aload_0
       1: invokevirtual #189                // Method getContextRoot:()Ljava/lang/String;
       4: astore_1
       5: ldc           #190                // String /
       7: astore_2
       8: aload_1
       9: ifnull        96
      12: aload_1
      13: ldc           #190                // String /
      15: invokevirtual #50                 // Method java/lang/String.equals:(Ljava/lang/Object;)Z
      18: ifne          41
      21: new           #82                 // class java/lang/StringBuilder
      24: dup
      25: invokespecial #83                 // Method java/lang/StringBuilder."<init>":()V
      28: aload_1
      29: invokevirtual #85                 // Method java/lang/StringBuilder.append:(Ljava/lang/String;)Ljava/lang/StringBuilder;
      32: ldc           #190                // String /
      34: invokevirtual #85                 // Method java/lang/StringBuilder.append:(Ljava/lang/String;)Ljava/lang/StringBuilder;
      37: invokevirtual #90                 // Method java/lang/StringBuilder.toString:()Ljava/lang/String;
      40: astore_2
      41: aload_0
      42: getfield      #191                // Field servicePath:Ljava/lang/String;
      45: ifnull        61
      48: aload_0
      49: getfield      #191                // Field servicePath:Ljava/lang/String;
      52: invokevirtual #192                // Method java/lang/String.trim:()Ljava/lang/String;
      55: invokevirtual #193                // Method java/lang/String.length:()I
      58: ifne          71
      61: new           #194                // class java/lang/IllegalArgumentException
      64: dup
      65: ldc           #195                // String service path cannot be null or empty
      67: invokespecial #196                // Method java/lang/IllegalArgumentException."<init>":(Ljava/lang/String;)V
      70: athrow
      71: new           #82                 // class java/lang/StringBuilder
      74: dup
      75: invokespecial #83                 // Method java/lang/StringBuilder."<init>":()V
      78: aload_2
      79: invokevirtual #85                 // Method java/lang/StringBuilder.append:(Ljava/lang/String;)Ljava/lang/StringBuilder;
      82: aload_0
      83: getfield      #191                // Field servicePath:Ljava/lang/String;
      86: invokevirtual #192                // Method java/lang/String.trim:()Ljava/lang/String;
      89: invokevirtual #85                 // Method java/lang/StringBuilder.append:(Ljava/lang/String;)Ljava/lang/StringBuilder;
      92: invokevirtual #90                 // Method java/lang/StringBuilder.toString:()Ljava/lang/String;
      95: astore_2
      96: aload_2
      97: areturn

  public java.lang.String getServicePath();
    Code:
       0: aload_0
       1: getfield      #191                // Field servicePath:Ljava/lang/String;
       4: ifnull        20
       7: aload_0
       8: getfield      #191                // Field servicePath:Ljava/lang/String;
      11: invokevirtual #192                // Method java/lang/String.trim:()Ljava/lang/String;
      14: invokevirtual #193                // Method java/lang/String.length:()I
      17: ifne          30
      20: new           #194                // class java/lang/IllegalArgumentException
      23: dup
      24: ldc           #195                // String service path cannot be null or empty
      26: invokespecial #196                // Method java/lang/IllegalArgumentException."<init>":(Ljava/lang/String;)V
      29: athrow
      30: aload_0
      31: getfield      #191                // Field servicePath:Ljava/lang/String;
      34: invokevirtual #192                // Method java/lang/String.trim:()Ljava/lang/String;
      37: areturn

  public void setServicePath(java.lang.String);
    Code:
       0: aload_0
       1: aload_1
       2: putfield      #191                // Field servicePath:Ljava/lang/String;
       5: return

  public java.lang.String getContextRoot();
    Code:
       0: aload_0
       1: getfield      #197                // Field contextRoot:Ljava/lang/String;
       4: ifnonnull     26
       7: aload_0
       8: aload_0
       9: getfield      #14                 // Field axisConfiguration:Lorg/apache/axis2/engine/AxisConfiguration;
      12: ldc           #198                // String contextRoot
      14: invokevirtual #18                 // Method org/apache/axis2/engine/AxisConfiguration.getParameter:(Ljava/lang/String;)Lorg/apache/axis2/description/Parameter;
      17: invokevirtual #19                 // Method org/apache/axis2/description/Parameter.getValue:()Ljava/lang/Object;
      20: checkcast     #20                 // class java/lang/String
      23: putfield      #197                // Field contextRoot:Ljava/lang/String;
      26: aload_0
      27: getfield      #197                // Field contextRoot:Ljava/lang/String;
      30: areturn

  public void setContextRoot(java.lang.String);
    Code:
       0: aload_1
       1: ifnull        20
       4: aload_0
       5: aload_1
       6: invokevirtual #192                // Method java/lang/String.trim:()Ljava/lang/String;
       9: putfield      #197                // Field contextRoot:Ljava/lang/String;
      12: aload_0
      13: aload_0
      14: invokespecial #188                // Method internalGetServiceContextPath:()Ljava/lang/String;
      17: putfield      #12                 // Field cachedServicePath:Ljava/lang/String;
      20: return

  public long getServiceGroupContextTimeoutInterval();
    Code:
       0: aload_0
       1: ldc           #17                 // String ConfigContextTimeoutInterval
       3: invokevirtual #199                // Method getProperty:(Ljava/lang/String;)Ljava/lang/Object;
       6: checkcast     #200                // class java/lang/Integer
       9: astore_1
      10: aload_1
      11: ifnull        23
      14: aload_0
      15: aload_1
      16: invokevirtual #201                // Method java/lang/Integer.intValue:()I
      19: i2l
      20: putfield      #11                 // Field serviceGroupContextTimeoutInterval:J
      23: aload_0
      24: getfield      #11                 // Field serviceGroupContextTimeoutInterval:J
      27: lreturn

  public void removeServiceGroupContext(org.apache.axis2.description.AxisServiceGroup);
    Code:
       0: aload_1
       1: ifnonnull     5
       4: return
       5: aload_1
       6: invokevirtual #52                 // Method org/apache/axis2/description/AxisServiceGroup.getServiceGroupName:()Ljava/lang/String;
       9: astore_2
      10: aload_0
      11: getfield      #8                  // Field applicationSessionServiceGroupContexts:Ljava/util/Hashtable;
      14: aload_2
      15: invokevirtual #53                 // Method java/util/Hashtable.get:(Ljava/lang/Object;)Ljava/lang/Object;
      18: astore_3
      19: aload_3
      20: ifnull        36
      23: aload_0
      24: getfield      #8                  // Field applicationSessionServiceGroupContexts:Ljava/util/Hashtable;
      27: aload_1
      28: invokevirtual #52                 // Method org/apache/axis2/description/AxisServiceGroup.getServiceGroupName:()Ljava/lang/String;
      31: invokevirtual #133                // Method java/util/Hashtable.remove:(Ljava/lang/Object;)Ljava/lang/Object;
      34: pop
      35: return
      36: new           #41                 // class java/util/ArrayList
      39: dup
      40: invokespecial #42                 // Method java/util/ArrayList."<init>":()V
      43: astore        4
      45: aload_0
      46: getfield      #7                  // Field serviceGroupContextMap:Ljava/util/Hashtable;
      49: invokevirtual #145                // Method java/util/Hashtable.values:()Ljava/util/Collection;
      52: invokeinterface #93,  1           // InterfaceMethod java/util/Collection.iterator:()Ljava/util/Iterator;
      57: astore        5
      59: aload         5
      61: invokeinterface #36,  1           // InterfaceMethod java/util/Iterator.hasNext:()Z
      66: ifeq          107
      69: aload         5
      71: invokeinterface #37,  1           // InterfaceMethod java/util/Iterator.next:()Ljava/lang/Object;
      76: checkcast     #54                 // class org/apache/axis2/context/ServiceGroupContext
      79: astore        6
      81: aload         6
      83: invokevirtual #106                // Method org/apache/axis2/context/ServiceGroupContext.getDescription:()Lorg/apache/axis2/description/AxisServiceGroup;
      86: aload_1
      87: invokevirtual #202                // Method java/lang/Object.equals:(Ljava/lang/Object;)Z
      90: ifeq          104
      93: aload         4
      95: aload         6
      97: invokevirtual #103                // Method org/apache/axis2/context/ServiceGroupContext.getId:()Ljava/lang/String;
     100: invokevirtual #203                // Method java/util/ArrayList.add:(Ljava/lang/Object;)Z
     103: pop
     104: goto          59
     107: aload         4
     109: invokevirtual #204                // Method java/util/ArrayList.iterator:()Ljava/util/Iterator;
     112: astore        6
     114: aload         6
     116: invokeinterface #36,  1           // InterfaceMethod java/util/Iterator.hasNext:()Z
     121: ifeq          153
     124: aload         6
     126: invokeinterface #37,  1           // InterfaceMethod java/util/Iterator.next:()Ljava/lang/Object;
     131: astore        7
     133: aload         7
     135: checkcast     #20                 // class java/lang/String
     138: astore        8
     140: aload_0
     141: getfield      #7                  // Field serviceGroupContextMap:Ljava/util/Hashtable;
     144: aload         8
     146: invokevirtual #133                // Method java/util/Hashtable.remove:(Ljava/lang/Object;)Ljava/lang/Object;
     149: pop
     150: goto          114
     153: return

  public org.apache.axis2.context.ConfigurationContext getRootContext();
    Code:
       0: aload_0
       1: areturn

  static {};
    Code:
       0: new           #205                // class org/apache/axis2/util/OnDemandLogger
       3: dup
       4: ldc           #206                // class org/apache/axis2/context/ConfigurationContext
       6: invokespecial #207                // Method org/apache/axis2/util/OnDemandLogger."<init>":(Ljava/lang/Class;)V
       9: putstatic     #75                 // Field log:Lorg/apache/axis2/util/OnDemandLogger;
      12: return
}
