Compiled from "OperationContextFactory.java"
public class org.apache.axis2.context.OperationContextFactory implements org.apache.axis2.wsdl.WSDLConstants {
  public org.apache.axis2.context.OperationContextFactory();
    Code:
       0: aload_0
       1: invokespecial #1                  // Method java/lang/Object."<init>":()V
       4: return

  public static org.apache.axis2.context.OperationContext createOperationContext(int, org.apache.axis2.description.AxisOperation, org.apache.axis2.context.ServiceContext) throws org.apache.axis2.AxisFault;
    Code:
       0: bipush        12
       2: iload_0
       3: if_icmpeq     48
       6: bipush        10
       8: iload_0
       9: if_icmpeq     48
      12: bipush        13
      14: iload_0
      15: if_icmpeq     48
      18: bipush        11
      20: iload_0
      21: if_icmpeq     48
      24: bipush        14
      26: iload_0
      27: if_icmpeq     48
      30: bipush        16
      32: iload_0
      33: if_icmpeq     48
      36: bipush        17
      38: iload_0
      39: if_icmpeq     48
      42: bipush        15
      44: iload_0
      45: if_icmpne     54
      48: aload_2
      49: aload_1
      50: invokevirtual #3                  // Method org/apache/axis2/context/ServiceContext.createOperationContext:(Lorg/apache/axis2/description/AxisOperation;)Lorg/apache/axis2/context/OperationContext;
      53: areturn
      54: new           #4                  // class org/apache/axis2/AxisFault
      57: dup
      58: ldc           #5                  // String unSupportedMEP
      60: new           #6                  // class java/lang/StringBuilder
      63: dup
      64: invokespecial #7                  // Method java/lang/StringBuilder."<init>":()V
      67: ldc           #8                  // String ID is
      69: invokevirtual #9                  // Method java/lang/StringBuilder.append:(Ljava/lang/String;)Ljava/lang/StringBuilder;
      72: iload_0
      73: invokevirtual #10                 // Method java/lang/StringBuilder.append:(I)Ljava/lang/StringBuilder;
      76: invokevirtual #11                 // Method java/lang/StringBuilder.toString:()Ljava/lang/String;
      79: invokestatic  #12                 // Method org/apache/axis2/i18n/Messages.getMessage:(Ljava/lang/String;Ljava/lang/String;)Ljava/lang/String;
      82: invokespecial #13                 // Method org/apache/axis2/AxisFault."<init>":(Ljava/lang/String;)V
      85: athrow
}
