Compiled from "DescribeMetricSetResponse.java"
public final class software.amazon.awssdk.services.lookoutmetrics.model.DescribeMetricSetResponse extends software.amazon.awssdk.services.lookoutmetrics.model.LookoutMetricsResponse implements software.amazon.awssdk.utils.builder.ToCopyableBuilder<software.amazon.awssdk.services.lookoutmetrics.model.DescribeMetricSetResponse$Builder, software.amazon.awssdk.services.lookoutmetrics.model.DescribeMetricSetResponse> {
  private static final software.amazon.awssdk.core.SdkField<java.lang.String> METRIC_SET_ARN_FIELD;

  private static final software.amazon.awssdk.core.SdkField<java.lang.String> ANOMALY_DETECTOR_ARN_FIELD;

  private static final software.amazon.awssdk.core.SdkField<java.lang.String> METRIC_SET_NAME_FIELD;

  private static final software.amazon.awssdk.core.SdkField<java.lang.String> METRIC_SET_DESCRIPTION_FIELD;

  private static final software.amazon.awssdk.core.SdkField<java.time.Instant> CREATION_TIME_FIELD;

  private static final software.amazon.awssdk.core.SdkField<java.time.Instant> LAST_MODIFICATION_TIME_FIELD;

  private static final software.amazon.awssdk.core.SdkField<java.lang.Integer> OFFSET_FIELD;

  private static final software.amazon.awssdk.core.SdkField<java.util.List<software.amazon.awssdk.services.lookoutmetrics.model.Metric>> METRIC_LIST_FIELD;

  private static final software.amazon.awssdk.core.SdkField<software.amazon.awssdk.services.lookoutmetrics.model.TimestampColumn> TIMESTAMP_COLUMN_FIELD;

  private static final software.amazon.awssdk.core.SdkField<java.util.List<java.lang.String>> DIMENSION_LIST_FIELD;

  private static final software.amazon.awssdk.core.SdkField<java.lang.String> METRIC_SET_FREQUENCY_FIELD;

  private static final software.amazon.awssdk.core.SdkField<java.lang.String> TIMEZONE_FIELD;

  private static final software.amazon.awssdk.core.SdkField<software.amazon.awssdk.services.lookoutmetrics.model.MetricSource> METRIC_SOURCE_FIELD;

  private static final software.amazon.awssdk.core.SdkField<java.util.List<software.amazon.awssdk.services.lookoutmetrics.model.MetricSetDimensionFilter>> DIMENSION_FILTER_LIST_FIELD;

  private static final java.util.List<software.amazon.awssdk.core.SdkField<?>> SDK_FIELDS;

  private final java.lang.String metricSetArn;

  private final java.lang.String anomalyDetectorArn;

  private final java.lang.String metricSetName;

  private final java.lang.String metricSetDescription;

  private final java.time.Instant creationTime;

  private final java.time.Instant lastModificationTime;

  private final java.lang.Integer offset;

  private final java.util.List<software.amazon.awssdk.services.lookoutmetrics.model.Metric> metricList;

  private final software.amazon.awssdk.services.lookoutmetrics.model.TimestampColumn timestampColumn;

  private final java.util.List<java.lang.String> dimensionList;

  private final java.lang.String metricSetFrequency;

  private final java.lang.String timezone;

  private final software.amazon.awssdk.services.lookoutmetrics.model.MetricSource metricSource;

  private final java.util.List<software.amazon.awssdk.services.lookoutmetrics.model.MetricSetDimensionFilter> dimensionFilterList;

  private software.amazon.awssdk.services.lookoutmetrics.model.DescribeMetricSetResponse(software.amazon.awssdk.services.lookoutmetrics.model.DescribeMetricSetResponse$BuilderImpl);
    Code:
       0: aload_0
       1: aload_1
       2: invokespecial #17                 // Method software/amazon/awssdk/services/lookoutmetrics/model/LookoutMetricsResponse."<init>":(Lsoftware/amazon/awssdk/services/lookoutmetrics/model/LookoutMetricsResponse$Builder;)V
       5: aload_0
       6: aload_1
       7: invokestatic  #18                 // Method software/amazon/awssdk/services/lookoutmetrics/model/DescribeMetricSetResponse$BuilderImpl.access$000:(Lsoftware/amazon/awssdk/services/lookoutmetrics/model/DescribeMetricSetResponse$BuilderImpl;)Ljava/lang/String;
      10: putfield      #16                 // Field metricSetArn:Ljava/lang/String;
      13: aload_0
      14: aload_1
      15: invokestatic  #19                 // Method software/amazon/awssdk/services/lookoutmetrics/model/DescribeMetricSetResponse$BuilderImpl.access$100:(Lsoftware/amazon/awssdk/services/lookoutmetrics/model/DescribeMetricSetResponse$BuilderImpl;)Ljava/lang/String;
      18: putfield      #15                 // Field anomalyDetectorArn:Ljava/lang/String;
      21: aload_0
      22: aload_1
      23: invokestatic  #20                 // Method software/amazon/awssdk/services/lookoutmetrics/model/DescribeMetricSetResponse$BuilderImpl.access$200:(Lsoftware/amazon/awssdk/services/lookoutmetrics/model/DescribeMetricSetResponse$BuilderImpl;)Ljava/lang/String;
      26: putfield      #14                 // Field metricSetName:Ljava/lang/String;
      29: aload_0
      30: aload_1
      31: invokestatic  #21                 // Method software/amazon/awssdk/services/lookoutmetrics/model/DescribeMetricSetResponse$BuilderImpl.access$300:(Lsoftware/amazon/awssdk/services/lookoutmetrics/model/DescribeMetricSetResponse$BuilderImpl;)Ljava/lang/String;
      34: putfield      #13                 // Field metricSetDescription:Ljava/lang/String;
      37: aload_0
      38: aload_1
      39: invokestatic  #22                 // Method software/amazon/awssdk/services/lookoutmetrics/model/DescribeMetricSetResponse$BuilderImpl.access$400:(Lsoftware/amazon/awssdk/services/lookoutmetrics/model/DescribeMetricSetResponse$BuilderImpl;)Ljava/time/Instant;
      42: putfield      #12                 // Field creationTime:Ljava/time/Instant;
      45: aload_0
      46: aload_1
      47: invokestatic  #23                 // Method software/amazon/awssdk/services/lookoutmetrics/model/DescribeMetricSetResponse$BuilderImpl.access$500:(Lsoftware/amazon/awssdk/services/lookoutmetrics/model/DescribeMetricSetResponse$BuilderImpl;)Ljava/time/Instant;
      50: putfield      #11                 // Field lastModificationTime:Ljava/time/Instant;
      53: aload_0
      54: aload_1
      55: invokestatic  #24                 // Method software/amazon/awssdk/services/lookoutmetrics/model/DescribeMetricSetResponse$BuilderImpl.access$600:(Lsoftware/amazon/awssdk/services/lookoutmetrics/model/DescribeMetricSetResponse$BuilderImpl;)Ljava/lang/Integer;
      58: putfield      #10                 // Field offset:Ljava/lang/Integer;
      61: aload_0
      62: aload_1
      63: invokestatic  #25                 // Method software/amazon/awssdk/services/lookoutmetrics/model/DescribeMetricSetResponse$BuilderImpl.access$700:(Lsoftware/amazon/awssdk/services/lookoutmetrics/model/DescribeMetricSetResponse$BuilderImpl;)Ljava/util/List;
      66: putfield      #9                  // Field metricList:Ljava/util/List;
      69: aload_0
      70: aload_1
      71: invokestatic  #26                 // Method software/amazon/awssdk/services/lookoutmetrics/model/DescribeMetricSetResponse$BuilderImpl.access$800:(Lsoftware/amazon/awssdk/services/lookoutmetrics/model/DescribeMetricSetResponse$BuilderImpl;)Lsoftware/amazon/awssdk/services/lookoutmetrics/model/TimestampColumn;
      74: putfield      #8                  // Field timestampColumn:Lsoftware/amazon/awssdk/services/lookoutmetrics/model/TimestampColumn;
      77: aload_0
      78: aload_1
      79: invokestatic  #27                 // Method software/amazon/awssdk/services/lookoutmetrics/model/DescribeMetricSetResponse$BuilderImpl.access$900:(Lsoftware/amazon/awssdk/services/lookoutmetrics/model/DescribeMetricSetResponse$BuilderImpl;)Ljava/util/List;
      82: putfield      #7                  // Field dimensionList:Ljava/util/List;
      85: aload_0
      86: aload_1
      87: invokestatic  #28                 // Method software/amazon/awssdk/services/lookoutmetrics/model/DescribeMetricSetResponse$BuilderImpl.access$1000:(Lsoftware/amazon/awssdk/services/lookoutmetrics/model/DescribeMetricSetResponse$BuilderImpl;)Ljava/lang/String;
      90: putfield      #6                  // Field metricSetFrequency:Ljava/lang/String;
      93: aload_0
      94: aload_1
      95: invokestatic  #29                 // Method software/amazon/awssdk/services/lookoutmetrics/model/DescribeMetricSetResponse$BuilderImpl.access$1100:(Lsoftware/amazon/awssdk/services/lookoutmetrics/model/DescribeMetricSetResponse$BuilderImpl;)Ljava/lang/String;
      98: putfield      #5                  // Field timezone:Ljava/lang/String;
     101: aload_0
     102: aload_1
     103: invokestatic  #30                 // Method software/amazon/awssdk/services/lookoutmetrics/model/DescribeMetricSetResponse$BuilderImpl.access$1200:(Lsoftware/amazon/awssdk/services/lookoutmetrics/model/DescribeMetricSetResponse$BuilderImpl;)Lsoftware/amazon/awssdk/services/lookoutmetrics/model/MetricSource;
     106: putfield      #4                  // Field metricSource:Lsoftware/amazon/awssdk/services/lookoutmetrics/model/MetricSource;
     109: aload_0
     110: aload_1
     111: invokestatic  #31                 // Method software/amazon/awssdk/services/lookoutmetrics/model/DescribeMetricSetResponse$BuilderImpl.access$1300:(Lsoftware/amazon/awssdk/services/lookoutmetrics/model/DescribeMetricSetResponse$BuilderImpl;)Ljava/util/List;
     114: putfield      #3                  // Field dimensionFilterList:Ljava/util/List;
     117: return

  public final java.lang.String metricSetArn();
    Code:
       0: aload_0
       1: getfield      #16                 // Field metricSetArn:Ljava/lang/String;
       4: areturn

  public final java.lang.String anomalyDetectorArn();
    Code:
       0: aload_0
       1: getfield      #15                 // Field anomalyDetectorArn:Ljava/lang/String;
       4: areturn

  public final java.lang.String metricSetName();
    Code:
       0: aload_0
       1: getfield      #14                 // Field metricSetName:Ljava/lang/String;
       4: areturn

  public final java.lang.String metricSetDescription();
    Code:
       0: aload_0
       1: getfield      #13                 // Field metricSetDescription:Ljava/lang/String;
       4: areturn

  public final java.time.Instant creationTime();
    Code:
       0: aload_0
       1: getfield      #12                 // Field creationTime:Ljava/time/Instant;
       4: areturn

  public final java.time.Instant lastModificationTime();
    Code:
       0: aload_0
       1: getfield      #11                 // Field lastModificationTime:Ljava/time/Instant;
       4: areturn

  public final java.lang.Integer offset();
    Code:
       0: aload_0
       1: getfield      #10                 // Field offset:Ljava/lang/Integer;
       4: areturn

  public final boolean hasMetricList();
    Code:
       0: aload_0
       1: getfield      #9                  // Field metricList:Ljava/util/List;
       4: ifnull        21
       7: aload_0
       8: getfield      #9                  // Field metricList:Ljava/util/List;
      11: instanceof    #32                 // class software/amazon/awssdk/core/util/SdkAutoConstructList
      14: ifne          21
      17: iconst_1
      18: goto          22
      21: iconst_0
      22: ireturn

  public final java.util.List<software.amazon.awssdk.services.lookoutmetrics.model.Metric> metricList();
    Code:
       0: aload_0
       1: getfield      #9                  // Field metricList:Ljava/util/List;
       4: areturn

  public final software.amazon.awssdk.services.lookoutmetrics.model.TimestampColumn timestampColumn();
    Code:
       0: aload_0
       1: getfield      #8                  // Field timestampColumn:Lsoftware/amazon/awssdk/services/lookoutmetrics/model/TimestampColumn;
       4: areturn

  public final boolean hasDimensionList();
    Code:
       0: aload_0
       1: getfield      #7                  // Field dimensionList:Ljava/util/List;
       4: ifnull        21
       7: aload_0
       8: getfield      #7                  // Field dimensionList:Ljava/util/List;
      11: instanceof    #32                 // class software/amazon/awssdk/core/util/SdkAutoConstructList
      14: ifne          21
      17: iconst_1
      18: goto          22
      21: iconst_0
      22: ireturn

  public final java.util.List<java.lang.String> dimensionList();
    Code:
       0: aload_0
       1: getfield      #7                  // Field dimensionList:Ljava/util/List;
       4: areturn

  public final software.amazon.awssdk.services.lookoutmetrics.model.Frequency metricSetFrequency();
    Code:
       0: aload_0
       1: getfield      #6                  // Field metricSetFrequency:Ljava/lang/String;
       4: invokestatic  #33                 // Method software/amazon/awssdk/services/lookoutmetrics/model/Frequency.fromValue:(Ljava/lang/String;)Lsoftware/amazon/awssdk/services/lookoutmetrics/model/Frequency;
       7: areturn

  public final java.lang.String metricSetFrequencyAsString();
    Code:
       0: aload_0
       1: getfield      #6                  // Field metricSetFrequency:Ljava/lang/String;
       4: areturn

  public final java.lang.String timezone();
    Code:
       0: aload_0
       1: getfield      #5                  // Field timezone:Ljava/lang/String;
       4: areturn

  public final software.amazon.awssdk.services.lookoutmetrics.model.MetricSource metricSource();
    Code:
       0: aload_0
       1: getfield      #4                  // Field metricSource:Lsoftware/amazon/awssdk/services/lookoutmetrics/model/MetricSource;
       4: areturn

  public final boolean hasDimensionFilterList();
    Code:
       0: aload_0
       1: getfield      #3                  // Field dimensionFilterList:Ljava/util/List;
       4: ifnull        21
       7: aload_0
       8: getfield      #3                  // Field dimensionFilterList:Ljava/util/List;
      11: instanceof    #32                 // class software/amazon/awssdk/core/util/SdkAutoConstructList
      14: ifne          21
      17: iconst_1
      18: goto          22
      21: iconst_0
      22: ireturn

  public final java.util.List<software.amazon.awssdk.services.lookoutmetrics.model.MetricSetDimensionFilter> dimensionFilterList();
    Code:
       0: aload_0
       1: getfield      #3                  // Field dimensionFilterList:Ljava/util/List;
       4: areturn

  public software.amazon.awssdk.services.lookoutmetrics.model.DescribeMetricSetResponse$Builder toBuilder();
    Code:
       0: new           #34                 // class software/amazon/awssdk/services/lookoutmetrics/model/DescribeMetricSetResponse$BuilderImpl
       3: dup
       4: aload_0
       5: aconst_null
       6: invokespecial #35                 // Method software/amazon/awssdk/services/lookoutmetrics/model/DescribeMetricSetResponse$BuilderImpl."<init>":(Lsoftware/amazon/awssdk/services/lookoutmetrics/model/DescribeMetricSetResponse;Lsoftware/amazon/awssdk/services/lookoutmetrics/model/DescribeMetricSetResponse$1;)V
       9: areturn

  public static software.amazon.awssdk.services.lookoutmetrics.model.DescribeMetricSetResponse$Builder builder();
    Code:
       0: new           #34                 // class software/amazon/awssdk/services/lookoutmetrics/model/DescribeMetricSetResponse$BuilderImpl
       3: dup
       4: aconst_null
       5: invokespecial #36                 // Method software/amazon/awssdk/services/lookoutmetrics/model/DescribeMetricSetResponse$BuilderImpl."<init>":(Lsoftware/amazon/awssdk/services/lookoutmetrics/model/DescribeMetricSetResponse$1;)V
       8: areturn

  public static java.lang.Class<? extends software.amazon.awssdk.services.lookoutmetrics.model.DescribeMetricSetResponse$Builder> serializableBuilderClass();
    Code:
       0: ldc           #34                 // class software/amazon/awssdk/services/lookoutmetrics/model/DescribeMetricSetResponse$BuilderImpl
       2: areturn

  public final int hashCode();
    Code:
       0: iconst_1
       1: istore_1
       2: bipush        31
       4: iload_1
       5: imul
       6: aload_0
       7: invokespecial #37                 // Method software/amazon/awssdk/services/lookoutmetrics/model/LookoutMetricsResponse.hashCode:()I
      10: iadd
      11: istore_1
      12: bipush        31
      14: iload_1
      15: imul
      16: aload_0
      17: invokevirtual #38                 // Method metricSetArn:()Ljava/lang/String;
      20: invokestatic  #39                 // Method java/util/Objects.hashCode:(Ljava/lang/Object;)I
      23: iadd
      24: istore_1
      25: bipush        31
      27: iload_1
      28: imul
      29: aload_0
      30: invokevirtual #40                 // Method anomalyDetectorArn:()Ljava/lang/String;
      33: invokestatic  #39                 // Method java/util/Objects.hashCode:(Ljava/lang/Object;)I
      36: iadd
      37: istore_1
      38: bipush        31
      40: iload_1
      41: imul
      42: aload_0
      43: invokevirtual #41                 // Method metricSetName:()Ljava/lang/String;
      46: invokestatic  #39                 // Method java/util/Objects.hashCode:(Ljava/lang/Object;)I
      49: iadd
      50: istore_1
      51: bipush        31
      53: iload_1
      54: imul
      55: aload_0
      56: invokevirtual #42                 // Method metricSetDescription:()Ljava/lang/String;
      59: invokestatic  #39                 // Method java/util/Objects.hashCode:(Ljava/lang/Object;)I
      62: iadd
      63: istore_1
      64: bipush        31
      66: iload_1
      67: imul
      68: aload_0
      69: invokevirtual #43                 // Method creationTime:()Ljava/time/Instant;
      72: invokestatic  #39                 // Method java/util/Objects.hashCode:(Ljava/lang/Object;)I
      75: iadd
      76: istore_1
      77: bipush        31
      79: iload_1
      80: imul
      81: aload_0
      82: invokevirtual #44                 // Method lastModificationTime:()Ljava/time/Instant;
      85: invokestatic  #39                 // Method java/util/Objects.hashCode:(Ljava/lang/Object;)I
      88: iadd
      89: istore_1
      90: bipush        31
      92: iload_1
      93: imul
      94: aload_0
      95: invokevirtual #45                 // Method offset:()Ljava/lang/Integer;
      98: invokestatic  #39                 // Method java/util/Objects.hashCode:(Ljava/lang/Object;)I
     101: iadd
     102: istore_1
     103: bipush        31
     105: iload_1
     106: imul
     107: aload_0
     108: invokevirtual #46                 // Method hasMetricList:()Z
     111: ifeq          121
     114: aload_0
     115: invokevirtual #47                 // Method metricList:()Ljava/util/List;
     118: goto          122
     121: aconst_null
     122: invokestatic  #39                 // Method java/util/Objects.hashCode:(Ljava/lang/Object;)I
     125: iadd
     126: istore_1
     127: bipush        31
     129: iload_1
     130: imul
     131: aload_0
     132: invokevirtual #48                 // Method timestampColumn:()Lsoftware/amazon/awssdk/services/lookoutmetrics/model/TimestampColumn;
     135: invokestatic  #39                 // Method java/util/Objects.hashCode:(Ljava/lang/Object;)I
     138: iadd
     139: istore_1
     140: bipush        31
     142: iload_1
     143: imul
     144: aload_0
     145: invokevirtual #49                 // Method hasDimensionList:()Z
     148: ifeq          158
     151: aload_0
     152: invokevirtual #50                 // Method dimensionList:()Ljava/util/List;
     155: goto          159
     158: aconst_null
     159: invokestatic  #39                 // Method java/util/Objects.hashCode:(Ljava/lang/Object;)I
     162: iadd
     163: istore_1
     164: bipush        31
     166: iload_1
     167: imul
     168: aload_0
     169: invokevirtual #51                 // Method metricSetFrequencyAsString:()Ljava/lang/String;
     172: invokestatic  #39                 // Method java/util/Objects.hashCode:(Ljava/lang/Object;)I
     175: iadd
     176: istore_1
     177: bipush        31
     179: iload_1
     180: imul
     181: aload_0
     182: invokevirtual #52                 // Method timezone:()Ljava/lang/String;
     185: invokestatic  #39                 // Method java/util/Objects.hashCode:(Ljava/lang/Object;)I
     188: iadd
     189: istore_1
     190: bipush        31
     192: iload_1
     193: imul
     194: aload_0
     195: invokevirtual #53                 // Method metricSource:()Lsoftware/amazon/awssdk/services/lookoutmetrics/model/MetricSource;
     198: invokestatic  #39                 // Method java/util/Objects.hashCode:(Ljava/lang/Object;)I
     201: iadd
     202: istore_1
     203: bipush        31
     205: iload_1
     206: imul
     207: aload_0
     208: invokevirtual #54                 // Method hasDimensionFilterList:()Z
     211: ifeq          221
     214: aload_0
     215: invokevirtual #55                 // Method dimensionFilterList:()Ljava/util/List;
     218: goto          222
     221: aconst_null
     222: invokestatic  #39                 // Method java/util/Objects.hashCode:(Ljava/lang/Object;)I
     225: iadd
     226: istore_1
     227: iload_1
     228: ireturn

  public final boolean equals(java.lang.Object);
    Code:
       0: aload_0
       1: aload_1
       2: invokespecial #56                 // Method software/amazon/awssdk/services/lookoutmetrics/model/LookoutMetricsResponse.equals:(Ljava/lang/Object;)Z
       5: ifeq          20
       8: aload_0
       9: aload_1
      10: invokevirtual #57                 // Method equalsBySdkFields:(Ljava/lang/Object;)Z
      13: ifeq          20
      16: iconst_1
      17: goto          21
      20: iconst_0
      21: ireturn

  public final boolean equalsBySdkFields(java.lang.Object);
    Code:
       0: aload_0
       1: aload_1
       2: if_acmpne     7
       5: iconst_1
       6: ireturn
       7: aload_1
       8: ifnonnull     13
      11: iconst_0
      12: ireturn
      13: aload_1
      14: instanceof    #58                 // class software/amazon/awssdk/services/lookoutmetrics/model/DescribeMetricSetResponse
      17: ifne          22
      20: iconst_0
      21: ireturn
      22: aload_1
      23: checkcast     #58                 // class software/amazon/awssdk/services/lookoutmetrics/model/DescribeMetricSetResponse
      26: astore_2
      27: aload_0
      28: invokevirtual #38                 // Method metricSetArn:()Ljava/lang/String;
      31: aload_2
      32: invokevirtual #38                 // Method metricSetArn:()Ljava/lang/String;
      35: invokestatic  #59                 // Method java/util/Objects.equals:(Ljava/lang/Object;Ljava/lang/Object;)Z
      38: ifeq          260
      41: aload_0
      42: invokevirtual #40                 // Method anomalyDetectorArn:()Ljava/lang/String;
      45: aload_2
      46: invokevirtual #40                 // Method anomalyDetectorArn:()Ljava/lang/String;
      49: invokestatic  #59                 // Method java/util/Objects.equals:(Ljava/lang/Object;Ljava/lang/Object;)Z
      52: ifeq          260
      55: aload_0
      56: invokevirtual #41                 // Method metricSetName:()Ljava/lang/String;
      59: aload_2
      60: invokevirtual #41                 // Method metricSetName:()Ljava/lang/String;
      63: invokestatic  #59                 // Method java/util/Objects.equals:(Ljava/lang/Object;Ljava/lang/Object;)Z
      66: ifeq          260
      69: aload_0
      70: invokevirtual #42                 // Method metricSetDescription:()Ljava/lang/String;
      73: aload_2
      74: invokevirtual #42                 // Method metricSetDescription:()Ljava/lang/String;
      77: invokestatic  #59                 // Method java/util/Objects.equals:(Ljava/lang/Object;Ljava/lang/Object;)Z
      80: ifeq          260
      83: aload_0
      84: invokevirtual #43                 // Method creationTime:()Ljava/time/Instant;
      87: aload_2
      88: invokevirtual #43                 // Method creationTime:()Ljava/time/Instant;
      91: invokestatic  #59                 // Method java/util/Objects.equals:(Ljava/lang/Object;Ljava/lang/Object;)Z
      94: ifeq          260
      97: aload_0
      98: invokevirtual #44                 // Method lastModificationTime:()Ljava/time/Instant;
     101: aload_2
     102: invokevirtual #44                 // Method lastModificationTime:()Ljava/time/Instant;
     105: invokestatic  #59                 // Method java/util/Objects.equals:(Ljava/lang/Object;Ljava/lang/Object;)Z
     108: ifeq          260
     111: aload_0
     112: invokevirtual #45                 // Method offset:()Ljava/lang/Integer;
     115: aload_2
     116: invokevirtual #45                 // Method offset:()Ljava/lang/Integer;
     119: invokestatic  #59                 // Method java/util/Objects.equals:(Ljava/lang/Object;Ljava/lang/Object;)Z
     122: ifeq          260
     125: aload_0
     126: invokevirtual #46                 // Method hasMetricList:()Z
     129: aload_2
     130: invokevirtual #46                 // Method hasMetricList:()Z
     133: if_icmpne     260
     136: aload_0
     137: invokevirtual #47                 // Method metricList:()Ljava/util/List;
     140: aload_2
     141: invokevirtual #47                 // Method metricList:()Ljava/util/List;
     144: invokestatic  #59                 // Method java/util/Objects.equals:(Ljava/lang/Object;Ljava/lang/Object;)Z
     147: ifeq          260
     150: aload_0
     151: invokevirtual #48                 // Method timestampColumn:()Lsoftware/amazon/awssdk/services/lookoutmetrics/model/TimestampColumn;
     154: aload_2
     155: invokevirtual #48                 // Method timestampColumn:()Lsoftware/amazon/awssdk/services/lookoutmetrics/model/TimestampColumn;
     158: invokestatic  #59                 // Method java/util/Objects.equals:(Ljava/lang/Object;Ljava/lang/Object;)Z
     161: ifeq          260
     164: aload_0
     165: invokevirtual #49                 // Method hasDimensionList:()Z
     168: aload_2
     169: invokevirtual #49                 // Method hasDimensionList:()Z
     172: if_icmpne     260
     175: aload_0
     176: invokevirtual #50                 // Method dimensionList:()Ljava/util/List;
     179: aload_2
     180: invokevirtual #50                 // Method dimensionList:()Ljava/util/List;
     183: invokestatic  #59                 // Method java/util/Objects.equals:(Ljava/lang/Object;Ljava/lang/Object;)Z
     186: ifeq          260
     189: aload_0
     190: invokevirtual #51                 // Method metricSetFrequencyAsString:()Ljava/lang/String;
     193: aload_2
     194: invokevirtual #51                 // Method metricSetFrequencyAsString:()Ljava/lang/String;
     197: invokestatic  #59                 // Method java/util/Objects.equals:(Ljava/lang/Object;Ljava/lang/Object;)Z
     200: ifeq          260
     203: aload_0
     204: invokevirtual #52                 // Method timezone:()Ljava/lang/String;
     207: aload_2
     208: invokevirtual #52                 // Method timezone:()Ljava/lang/String;
     211: invokestatic  #59                 // Method java/util/Objects.equals:(Ljava/lang/Object;Ljava/lang/Object;)Z
     214: ifeq          260
     217: aload_0
     218: invokevirtual #53                 // Method metricSource:()Lsoftware/amazon/awssdk/services/lookoutmetrics/model/MetricSource;
     221: aload_2
     222: invokevirtual #53                 // Method metricSource:()Lsoftware/amazon/awssdk/services/lookoutmetrics/model/MetricSource;
     225: invokestatic  #59                 // Method java/util/Objects.equals:(Ljava/lang/Object;Ljava/lang/Object;)Z
     228: ifeq          260
     231: aload_0
     232: invokevirtual #54                 // Method hasDimensionFilterList:()Z
     235: aload_2
     236: invokevirtual #54                 // Method hasDimensionFilterList:()Z
     239: if_icmpne     260
     242: aload_0
     243: invokevirtual #55                 // Method dimensionFilterList:()Ljava/util/List;
     246: aload_2
     247: invokevirtual #55                 // Method dimensionFilterList:()Ljava/util/List;
     250: invokestatic  #59                 // Method java/util/Objects.equals:(Ljava/lang/Object;Ljava/lang/Object;)Z
     253: ifeq          260
     256: iconst_1
     257: goto          261
     260: iconst_0
     261: ireturn

  public final java.lang.String toString();
    Code:
       0: ldc           #60                 // String DescribeMetricSetResponse
       2: invokestatic  #61                 // Method software/amazon/awssdk/utils/ToString.builder:(Ljava/lang/String;)Lsoftware/amazon/awssdk/utils/ToString;
       5: ldc           #62                 // String MetricSetArn
       7: aload_0
       8: invokevirtual #38                 // Method metricSetArn:()Ljava/lang/String;
      11: invokevirtual #63                 // Method software/amazon/awssdk/utils/ToString.add:(Ljava/lang/String;Ljava/lang/Object;)Lsoftware/amazon/awssdk/utils/ToString;
      14: ldc           #64                 // String AnomalyDetectorArn
      16: aload_0
      17: invokevirtual #40                 // Method anomalyDetectorArn:()Ljava/lang/String;
      20: invokevirtual #63                 // Method software/amazon/awssdk/utils/ToString.add:(Ljava/lang/String;Ljava/lang/Object;)Lsoftware/amazon/awssdk/utils/ToString;
      23: ldc           #65                 // String MetricSetName
      25: aload_0
      26: invokevirtual #41                 // Method metricSetName:()Ljava/lang/String;
      29: invokevirtual #63                 // Method software/amazon/awssdk/utils/ToString.add:(Ljava/lang/String;Ljava/lang/Object;)Lsoftware/amazon/awssdk/utils/ToString;
      32: ldc           #66                 // String MetricSetDescription
      34: aload_0
      35: invokevirtual #42                 // Method metricSetDescription:()Ljava/lang/String;
      38: invokevirtual #63                 // Method software/amazon/awssdk/utils/ToString.add:(Ljava/lang/String;Ljava/lang/Object;)Lsoftware/amazon/awssdk/utils/ToString;
      41: ldc           #67                 // String CreationTime
      43: aload_0
      44: invokevirtual #43                 // Method creationTime:()Ljava/time/Instant;
      47: invokevirtual #63                 // Method software/amazon/awssdk/utils/ToString.add:(Ljava/lang/String;Ljava/lang/Object;)Lsoftware/amazon/awssdk/utils/ToString;
      50: ldc           #68                 // String LastModificationTime
      52: aload_0
      53: invokevirtual #44                 // Method lastModificationTime:()Ljava/time/Instant;
      56: invokevirtual #63                 // Method software/amazon/awssdk/utils/ToString.add:(Ljava/lang/String;Ljava/lang/Object;)Lsoftware/amazon/awssdk/utils/ToString;
      59: ldc           #69                 // String Offset
      61: aload_0
      62: invokevirtual #45                 // Method offset:()Ljava/lang/Integer;
      65: invokevirtual #63                 // Method software/amazon/awssdk/utils/ToString.add:(Ljava/lang/String;Ljava/lang/Object;)Lsoftware/amazon/awssdk/utils/ToString;
      68: ldc           #70                 // String MetricList
      70: aload_0
      71: invokevirtual #46                 // Method hasMetricList:()Z
      74: ifeq          84
      77: aload_0
      78: invokevirtual #47                 // Method metricList:()Ljava/util/List;
      81: goto          85
      84: aconst_null
      85: invokevirtual #63                 // Method software/amazon/awssdk/utils/ToString.add:(Ljava/lang/String;Ljava/lang/Object;)Lsoftware/amazon/awssdk/utils/ToString;
      88: ldc           #71                 // String TimestampColumn
      90: aload_0
      91: invokevirtual #48                 // Method timestampColumn:()Lsoftware/amazon/awssdk/services/lookoutmetrics/model/TimestampColumn;
      94: invokevirtual #63                 // Method software/amazon/awssdk/utils/ToString.add:(Ljava/lang/String;Ljava/lang/Object;)Lsoftware/amazon/awssdk/utils/ToString;
      97: ldc           #72                 // String DimensionList
      99: aload_0
     100: invokevirtual #49                 // Method hasDimensionList:()Z
     103: ifeq          113
     106: aload_0
     107: invokevirtual #50                 // Method dimensionList:()Ljava/util/List;
     110: goto          114
     113: aconst_null
     114: invokevirtual #63                 // Method software/amazon/awssdk/utils/ToString.add:(Ljava/lang/String;Ljava/lang/Object;)Lsoftware/amazon/awssdk/utils/ToString;
     117: ldc           #73                 // String MetricSetFrequency
     119: aload_0
     120: invokevirtual #51                 // Method metricSetFrequencyAsString:()Ljava/lang/String;
     123: invokevirtual #63                 // Method software/amazon/awssdk/utils/ToString.add:(Ljava/lang/String;Ljava/lang/Object;)Lsoftware/amazon/awssdk/utils/ToString;
     126: ldc           #74                 // String Timezone
     128: aload_0
     129: invokevirtual #52                 // Method timezone:()Ljava/lang/String;
     132: invokevirtual #63                 // Method software/amazon/awssdk/utils/ToString.add:(Ljava/lang/String;Ljava/lang/Object;)Lsoftware/amazon/awssdk/utils/ToString;
     135: ldc           #75                 // String MetricSource
     137: aload_0
     138: invokevirtual #53                 // Method metricSource:()Lsoftware/amazon/awssdk/services/lookoutmetrics/model/MetricSource;
     141: invokevirtual #63                 // Method software/amazon/awssdk/utils/ToString.add:(Ljava/lang/String;Ljava/lang/Object;)Lsoftware/amazon/awssdk/utils/ToString;
     144: ldc           #76                 // String DimensionFilterList
     146: aload_0
     147: invokevirtual #54                 // Method hasDimensionFilterList:()Z
     150: ifeq          160
     153: aload_0
     154: invokevirtual #55                 // Method dimensionFilterList:()Ljava/util/List;
     157: goto          161
     160: aconst_null
     161: invokevirtual #63                 // Method software/amazon/awssdk/utils/ToString.add:(Ljava/lang/String;Ljava/lang/Object;)Lsoftware/amazon/awssdk/utils/ToString;
     164: invokevirtual #77                 // Method software/amazon/awssdk/utils/ToString.build:()Ljava/lang/String;
     167: areturn

  public final <T> java.util.Optional<T> getValueForField(java.lang.String, java.lang.Class<T>);
    Code:
       0: aload_1
       1: astore_3
       2: iconst_m1
       3: istore        4
       5: aload_3
       6: invokevirtual #78                 // Method java/lang/String.hashCode:()I
       9: lookupswitch  { // 14
           -2011583463: 302
           -1935912781: 222
           -1166046881: 207
            -740769324: 147
            -595544547: 162
            -536117206: 177
            -383353316: 334
             513646340: 270
            1359345644: 254
            1382653582: 238
            1750336108: 192
            1781892235: 132
            1791203851: 318
            1857467658: 286
               default: 347
          }
     132: aload_3
     133: ldc           #62                 // String MetricSetArn
     135: invokevirtual #79                 // Method java/lang/String.equals:(Ljava/lang/Object;)Z
     138: ifeq          347
     141: iconst_0
     142: istore        4
     144: goto          347
     147: aload_3
     148: ldc           #64                 // String AnomalyDetectorArn
     150: invokevirtual #79                 // Method java/lang/String.equals:(Ljava/lang/Object;)Z
     153: ifeq          347
     156: iconst_1
     157: istore        4
     159: goto          347
     162: aload_3
     163: ldc           #65                 // String MetricSetName
     165: invokevirtual #79                 // Method java/lang/String.equals:(Ljava/lang/Object;)Z
     168: ifeq          347
     171: iconst_2
     172: istore        4
     174: goto          347
     177: aload_3
     178: ldc           #66                 // String MetricSetDescription
     180: invokevirtual #79                 // Method java/lang/String.equals:(Ljava/lang/Object;)Z
     183: ifeq          347
     186: iconst_3
     187: istore        4
     189: goto          347
     192: aload_3
     193: ldc           #67                 // String CreationTime
     195: invokevirtual #79                 // Method java/lang/String.equals:(Ljava/lang/Object;)Z
     198: ifeq          347
     201: iconst_4
     202: istore        4
     204: goto          347
     207: aload_3
     208: ldc           #68                 // String LastModificationTime
     210: invokevirtual #79                 // Method java/lang/String.equals:(Ljava/lang/Object;)Z
     213: ifeq          347
     216: iconst_5
     217: istore        4
     219: goto          347
     222: aload_3
     223: ldc           #69                 // String Offset
     225: invokevirtual #79                 // Method java/lang/String.equals:(Ljava/lang/Object;)Z
     228: ifeq          347
     231: bipush        6
     233: istore        4
     235: goto          347
     238: aload_3
     239: ldc           #70                 // String MetricList
     241: invokevirtual #79                 // Method java/lang/String.equals:(Ljava/lang/Object;)Z
     244: ifeq          347
     247: bipush        7
     249: istore        4
     251: goto          347
     254: aload_3
     255: ldc           #71                 // String TimestampColumn
     257: invokevirtual #79                 // Method java/lang/String.equals:(Ljava/lang/Object;)Z
     260: ifeq          347
     263: bipush        8
     265: istore        4
     267: goto          347
     270: aload_3
     271: ldc           #72                 // String DimensionList
     273: invokevirtual #79                 // Method java/lang/String.equals:(Ljava/lang/Object;)Z
     276: ifeq          347
     279: bipush        9
     281: istore        4
     283: goto          347
     286: aload_3
     287: ldc           #73                 // String MetricSetFrequency
     289: invokevirtual #79                 // Method java/lang/String.equals:(Ljava/lang/Object;)Z
     292: ifeq          347
     295: bipush        10
     297: istore        4
     299: goto          347
     302: aload_3
     303: ldc           #74                 // String Timezone
     305: invokevirtual #79                 // Method java/lang/String.equals:(Ljava/lang/Object;)Z
     308: ifeq          347
     311: bipush        11
     313: istore        4
     315: goto          347
     318: aload_3
     319: ldc           #75                 // String MetricSource
     321: invokevirtual #79                 // Method java/lang/String.equals:(Ljava/lang/Object;)Z
     324: ifeq          347
     327: bipush        12
     329: istore        4
     331: goto          347
     334: aload_3
     335: ldc           #76                 // String DimensionFilterList
     337: invokevirtual #79                 // Method java/lang/String.equals:(Ljava/lang/Object;)Z
     340: ifeq          347
     343: bipush        13
     345: istore        4
     347: iload         4
     349: tableswitch   { // 0 to 13
                     0: 420
                     1: 432
                     2: 444
                     3: 456
                     4: 468
                     5: 480
                     6: 492
                     7: 504
                     8: 516
                     9: 528
                    10: 540
                    11: 552
                    12: 564
                    13: 576
               default: 588
          }
     420: aload_2
     421: aload_0
     422: invokevirtual #38                 // Method metricSetArn:()Ljava/lang/String;
     425: invokevirtual #80                 // Method java/lang/Class.cast:(Ljava/lang/Object;)Ljava/lang/Object;
     428: invokestatic  #81                 // Method java/util/Optional.ofNullable:(Ljava/lang/Object;)Ljava/util/Optional;
     431: areturn
     432: aload_2
     433: aload_0
     434: invokevirtual #40                 // Method anomalyDetectorArn:()Ljava/lang/String;
     437: invokevirtual #80                 // Method java/lang/Class.cast:(Ljava/lang/Object;)Ljava/lang/Object;
     440: invokestatic  #81                 // Method java/util/Optional.ofNullable:(Ljava/lang/Object;)Ljava/util/Optional;
     443: areturn
     444: aload_2
     445: aload_0
     446: invokevirtual #41                 // Method metricSetName:()Ljava/lang/String;
     449: invokevirtual #80                 // Method java/lang/Class.cast:(Ljava/lang/Object;)Ljava/lang/Object;
     452: invokestatic  #81                 // Method java/util/Optional.ofNullable:(Ljava/lang/Object;)Ljava/util/Optional;
     455: areturn
     456: aload_2
     457: aload_0
     458: invokevirtual #42                 // Method metricSetDescription:()Ljava/lang/String;
     461: invokevirtual #80                 // Method java/lang/Class.cast:(Ljava/lang/Object;)Ljava/lang/Object;
     464: invokestatic  #81                 // Method java/util/Optional.ofNullable:(Ljava/lang/Object;)Ljava/util/Optional;
     467: areturn
     468: aload_2
     469: aload_0
     470: invokevirtual #43                 // Method creationTime:()Ljava/time/Instant;
     473: invokevirtual #80                 // Method java/lang/Class.cast:(Ljava/lang/Object;)Ljava/lang/Object;
     476: invokestatic  #81                 // Method java/util/Optional.ofNullable:(Ljava/lang/Object;)Ljava/util/Optional;
     479: areturn
     480: aload_2
     481: aload_0
     482: invokevirtual #44                 // Method lastModificationTime:()Ljava/time/Instant;
     485: invokevirtual #80                 // Method java/lang/Class.cast:(Ljava/lang/Object;)Ljava/lang/Object;
     488: invokestatic  #81                 // Method java/util/Optional.ofNullable:(Ljava/lang/Object;)Ljava/util/Optional;
     491: areturn
     492: aload_2
     493: aload_0
     494: invokevirtual #45                 // Method offset:()Ljava/lang/Integer;
     497: invokevirtual #80                 // Method java/lang/Class.cast:(Ljava/lang/Object;)Ljava/lang/Object;
     500: invokestatic  #81                 // Method java/util/Optional.ofNullable:(Ljava/lang/Object;)Ljava/util/Optional;
     503: areturn
     504: aload_2
     505: aload_0
     506: invokevirtual #47                 // Method metricList:()Ljava/util/List;
     509: invokevirtual #80                 // Method java/lang/Class.cast:(Ljava/lang/Object;)Ljava/lang/Object;
     512: invokestatic  #81                 // Method java/util/Optional.ofNullable:(Ljava/lang/Object;)Ljava/util/Optional;
     515: areturn
     516: aload_2
     517: aload_0
     518: invokevirtual #48                 // Method timestampColumn:()Lsoftware/amazon/awssdk/services/lookoutmetrics/model/TimestampColumn;
     521: invokevirtual #80                 // Method java/lang/Class.cast:(Ljava/lang/Object;)Ljava/lang/Object;
     524: invokestatic  #81                 // Method java/util/Optional.ofNullable:(Ljava/lang/Object;)Ljava/util/Optional;
     527: areturn
     528: aload_2
     529: aload_0
     530: invokevirtual #50                 // Method dimensionList:()Ljava/util/List;
     533: invokevirtual #80                 // Method java/lang/Class.cast:(Ljava/lang/Object;)Ljava/lang/Object;
     536: invokestatic  #81                 // Method java/util/Optional.ofNullable:(Ljava/lang/Object;)Ljava/util/Optional;
     539: areturn
     540: aload_2
     541: aload_0
     542: invokevirtual #51                 // Method metricSetFrequencyAsString:()Ljava/lang/String;
     545: invokevirtual #80                 // Method java/lang/Class.cast:(Ljava/lang/Object;)Ljava/lang/Object;
     548: invokestatic  #81                 // Method java/util/Optional.ofNullable:(Ljava/lang/Object;)Ljava/util/Optional;
     551: areturn
     552: aload_2
     553: aload_0
     554: invokevirtual #52                 // Method timezone:()Ljava/lang/String;
     557: invokevirtual #80                 // Method java/lang/Class.cast:(Ljava/lang/Object;)Ljava/lang/Object;
     560: invokestatic  #81                 // Method java/util/Optional.ofNullable:(Ljava/lang/Object;)Ljava/util/Optional;
     563: areturn
     564: aload_2
     565: aload_0
     566: invokevirtual #53                 // Method metricSource:()Lsoftware/amazon/awssdk/services/lookoutmetrics/model/MetricSource;
     569: invokevirtual #80                 // Method java/lang/Class.cast:(Ljava/lang/Object;)Ljava/lang/Object;
     572: invokestatic  #81                 // Method java/util/Optional.ofNullable:(Ljava/lang/Object;)Ljava/util/Optional;
     575: areturn
     576: aload_2
     577: aload_0
     578: invokevirtual #55                 // Method dimensionFilterList:()Ljava/util/List;
     581: invokevirtual #80                 // Method java/lang/Class.cast:(Ljava/lang/Object;)Ljava/lang/Object;
     584: invokestatic  #81                 // Method java/util/Optional.ofNullable:(Ljava/lang/Object;)Ljava/util/Optional;
     587: areturn
     588: invokestatic  #82                 // Method java/util/Optional.empty:()Ljava/util/Optional;
     591: areturn

  public final java.util.List<software.amazon.awssdk.core.SdkField<?>> sdkFields();
    Code:
       0: getstatic     #1                  // Field SDK_FIELDS:Ljava/util/List;
       3: areturn

  private static <T> java.util.function.Function<java.lang.Object, T> getter(java.util.function.Function<software.amazon.awssdk.services.lookoutmetrics.model.DescribeMetricSetResponse, T>);
    Code:
       0: aload_0
       1: invokedynamic #83,  0             // InvokeDynamic #0:apply:(Ljava/util/function/Function;)Ljava/util/function/Function;
       6: areturn

  private static <T> java.util.function.BiConsumer<java.lang.Object, T> setter(java.util.function.BiConsumer<software.amazon.awssdk.services.lookoutmetrics.model.DescribeMetricSetResponse$Builder, T>);
    Code:
       0: aload_0
       1: invokedynamic #84,  0             // InvokeDynamic #1:accept:(Ljava/util/function/BiConsumer;)Ljava/util/function/BiConsumer;
       6: areturn

  public software.amazon.awssdk.awscore.AwsResponse$Builder toBuilder();
    Code:
       0: aload_0
       1: invokevirtual #85                 // Method toBuilder:()Lsoftware/amazon/awssdk/services/lookoutmetrics/model/DescribeMetricSetResponse$Builder;
       4: areturn

  public software.amazon.awssdk.core.SdkResponse$Builder toBuilder();
    Code:
       0: aload_0
       1: invokevirtual #85                 // Method toBuilder:()Lsoftware/amazon/awssdk/services/lookoutmetrics/model/DescribeMetricSetResponse$Builder;
       4: areturn

  public software.amazon.awssdk.utils.builder.CopyableBuilder toBuilder();
    Code:
       0: aload_0
       1: invokevirtual #85                 // Method toBuilder:()Lsoftware/amazon/awssdk/services/lookoutmetrics/model/DescribeMetricSetResponse$Builder;
       4: areturn

  private static void lambda$setter$1(java.util.function.BiConsumer, java.lang.Object, java.lang.Object);
    Code:
       0: aload_0
       1: aload_1
       2: checkcast     #86                 // class software/amazon/awssdk/services/lookoutmetrics/model/DescribeMetricSetResponse$Builder
       5: aload_2
       6: invokeinterface #87,  3           // InterfaceMethod java/util/function/BiConsumer.accept:(Ljava/lang/Object;Ljava/lang/Object;)V
      11: return

  private static java.lang.Object lambda$getter$0(java.util.function.Function, java.lang.Object);
    Code:
       0: aload_0
       1: aload_1
       2: checkcast     #58                 // class software/amazon/awssdk/services/lookoutmetrics/model/DescribeMetricSetResponse
       5: invokeinterface #88,  2           // InterfaceMethod java/util/function/Function.apply:(Ljava/lang/Object;)Ljava/lang/Object;
      10: areturn

  static java.lang.String access$1600(software.amazon.awssdk.services.lookoutmetrics.model.DescribeMetricSetResponse);
    Code:
       0: aload_0
       1: getfield      #16                 // Field metricSetArn:Ljava/lang/String;
       4: areturn

  static java.lang.String access$1700(software.amazon.awssdk.services.lookoutmetrics.model.DescribeMetricSetResponse);
    Code:
       0: aload_0
       1: getfield      #15                 // Field anomalyDetectorArn:Ljava/lang/String;
       4: areturn

  static java.lang.String access$1800(software.amazon.awssdk.services.lookoutmetrics.model.DescribeMetricSetResponse);
    Code:
       0: aload_0
       1: getfield      #14                 // Field metricSetName:Ljava/lang/String;
       4: areturn

  static java.lang.String access$1900(software.amazon.awssdk.services.lookoutmetrics.model.DescribeMetricSetResponse);
    Code:
       0: aload_0
       1: getfield      #13                 // Field metricSetDescription:Ljava/lang/String;
       4: areturn

  static java.time.Instant access$2000(software.amazon.awssdk.services.lookoutmetrics.model.DescribeMetricSetResponse);
    Code:
       0: aload_0
       1: getfield      #12                 // Field creationTime:Ljava/time/Instant;
       4: areturn

  static java.time.Instant access$2100(software.amazon.awssdk.services.lookoutmetrics.model.DescribeMetricSetResponse);
    Code:
       0: aload_0
       1: getfield      #11                 // Field lastModificationTime:Ljava/time/Instant;
       4: areturn

  static java.lang.Integer access$2200(software.amazon.awssdk.services.lookoutmetrics.model.DescribeMetricSetResponse);
    Code:
       0: aload_0
       1: getfield      #10                 // Field offset:Ljava/lang/Integer;
       4: areturn

  static java.util.List access$2300(software.amazon.awssdk.services.lookoutmetrics.model.DescribeMetricSetResponse);
    Code:
       0: aload_0
       1: getfield      #9                  // Field metricList:Ljava/util/List;
       4: areturn

  static software.amazon.awssdk.services.lookoutmetrics.model.TimestampColumn access$2400(software.amazon.awssdk.services.lookoutmetrics.model.DescribeMetricSetResponse);
    Code:
       0: aload_0
       1: getfield      #8                  // Field timestampColumn:Lsoftware/amazon/awssdk/services/lookoutmetrics/model/TimestampColumn;
       4: areturn

  static java.util.List access$2500(software.amazon.awssdk.services.lookoutmetrics.model.DescribeMetricSetResponse);
    Code:
       0: aload_0
       1: getfield      #7                  // Field dimensionList:Ljava/util/List;
       4: areturn

  static java.lang.String access$2600(software.amazon.awssdk.services.lookoutmetrics.model.DescribeMetricSetResponse);
    Code:
       0: aload_0
       1: getfield      #6                  // Field metricSetFrequency:Ljava/lang/String;
       4: areturn

  static java.lang.String access$2700(software.amazon.awssdk.services.lookoutmetrics.model.DescribeMetricSetResponse);
    Code:
       0: aload_0
       1: getfield      #5                  // Field timezone:Ljava/lang/String;
       4: areturn

  static software.amazon.awssdk.services.lookoutmetrics.model.MetricSource access$2800(software.amazon.awssdk.services.lookoutmetrics.model.DescribeMetricSetResponse);
    Code:
       0: aload_0
       1: getfield      #4                  // Field metricSource:Lsoftware/amazon/awssdk/services/lookoutmetrics/model/MetricSource;
       4: areturn

  static java.util.List access$2900(software.amazon.awssdk.services.lookoutmetrics.model.DescribeMetricSetResponse);
    Code:
       0: aload_0
       1: getfield      #3                  // Field dimensionFilterList:Ljava/util/List;
       4: areturn

  software.amazon.awssdk.services.lookoutmetrics.model.DescribeMetricSetResponse(software.amazon.awssdk.services.lookoutmetrics.model.DescribeMetricSetResponse$BuilderImpl, software.amazon.awssdk.services.lookoutmetrics.model.DescribeMetricSetResponse$1);
    Code:
       0: aload_0
       1: aload_1
       2: invokespecial #2                  // Method "<init>":(Lsoftware/amazon/awssdk/services/lookoutmetrics/model/DescribeMetricSetResponse$BuilderImpl;)V
       5: return

  static java.util.List access$3100();
    Code:
       0: getstatic     #1                  // Field SDK_FIELDS:Ljava/util/List;
       3: areturn

  static {};
    Code:
       0: getstatic     #89                 // Field software/amazon/awssdk/core/protocol/MarshallingType.STRING:Lsoftware/amazon/awssdk/core/protocol/MarshallingType;
       3: invokestatic  #90                 // Method software/amazon/awssdk/core/SdkField.builder:(Lsoftware/amazon/awssdk/core/protocol/MarshallingType;)Lsoftware/amazon/awssdk/core/SdkField$Builder;
       6: ldc           #62                 // String MetricSetArn
       8: invokevirtual #91                 // Method software/amazon/awssdk/core/SdkField$Builder.memberName:(Ljava/lang/String;)Lsoftware/amazon/awssdk/core/SdkField$Builder;
      11: invokedynamic #92,  0             // InvokeDynamic #2:apply:()Ljava/util/function/Function;
      16: invokestatic  #93                 // Method getter:(Ljava/util/function/Function;)Ljava/util/function/Function;
      19: invokevirtual #94                 // Method software/amazon/awssdk/core/SdkField$Builder.getter:(Ljava/util/function/Function;)Lsoftware/amazon/awssdk/core/SdkField$Builder;
      22: invokedynamic #95,  0             // InvokeDynamic #3:accept:()Ljava/util/function/BiConsumer;
      27: invokestatic  #96                 // Method setter:(Ljava/util/function/BiConsumer;)Ljava/util/function/BiConsumer;
      30: invokevirtual #97                 // Method software/amazon/awssdk/core/SdkField$Builder.setter:(Ljava/util/function/BiConsumer;)Lsoftware/amazon/awssdk/core/SdkField$Builder;
      33: iconst_1
      34: anewarray     #98                 // class software/amazon/awssdk/core/traits/Trait
      37: dup
      38: iconst_0
      39: invokestatic  #99                 // Method software/amazon/awssdk/core/traits/LocationTrait.builder:()Lsoftware/amazon/awssdk/core/traits/LocationTrait$Builder;
      42: getstatic     #100                // Field software/amazon/awssdk/core/protocol/MarshallLocation.PAYLOAD:Lsoftware/amazon/awssdk/core/protocol/MarshallLocation;
      45: invokevirtual #101                // Method software/amazon/awssdk/core/traits/LocationTrait$Builder.location:(Lsoftware/amazon/awssdk/core/protocol/MarshallLocation;)Lsoftware/amazon/awssdk/core/traits/LocationTrait$Builder;
      48: ldc           #62                 // String MetricSetArn
      50: invokevirtual #102                // Method software/amazon/awssdk/core/traits/LocationTrait$Builder.locationName:(Ljava/lang/String;)Lsoftware/amazon/awssdk/core/traits/LocationTrait$Builder;
      53: invokevirtual #103                // Method software/amazon/awssdk/core/traits/LocationTrait$Builder.build:()Lsoftware/amazon/awssdk/core/traits/LocationTrait;
      56: aastore
      57: invokevirtual #104                // Method software/amazon/awssdk/core/SdkField$Builder.traits:([Lsoftware/amazon/awssdk/core/traits/Trait;)Lsoftware/amazon/awssdk/core/SdkField$Builder;
      60: invokevirtual #105                // Method software/amazon/awssdk/core/SdkField$Builder.build:()Lsoftware/amazon/awssdk/core/SdkField;
      63: putstatic     #106                // Field METRIC_SET_ARN_FIELD:Lsoftware/amazon/awssdk/core/SdkField;
      66: getstatic     #89                 // Field software/amazon/awssdk/core/protocol/MarshallingType.STRING:Lsoftware/amazon/awssdk/core/protocol/MarshallingType;
      69: invokestatic  #90                 // Method software/amazon/awssdk/core/SdkField.builder:(Lsoftware/amazon/awssdk/core/protocol/MarshallingType;)Lsoftware/amazon/awssdk/core/SdkField$Builder;
      72: ldc           #64                 // String AnomalyDetectorArn
      74: invokevirtual #91                 // Method software/amazon/awssdk/core/SdkField$Builder.memberName:(Ljava/lang/String;)Lsoftware/amazon/awssdk/core/SdkField$Builder;
      77: invokedynamic #107,  0            // InvokeDynamic #4:apply:()Ljava/util/function/Function;
      82: invokestatic  #93                 // Method getter:(Ljava/util/function/Function;)Ljava/util/function/Function;
      85: invokevirtual #94                 // Method software/amazon/awssdk/core/SdkField$Builder.getter:(Ljava/util/function/Function;)Lsoftware/amazon/awssdk/core/SdkField$Builder;
      88: invokedynamic #108,  0            // InvokeDynamic #5:accept:()Ljava/util/function/BiConsumer;
      93: invokestatic  #96                 // Method setter:(Ljava/util/function/BiConsumer;)Ljava/util/function/BiConsumer;
      96: invokevirtual #97                 // Method software/amazon/awssdk/core/SdkField$Builder.setter:(Ljava/util/function/BiConsumer;)Lsoftware/amazon/awssdk/core/SdkField$Builder;
      99: iconst_1
     100: anewarray     #98                 // class software/amazon/awssdk/core/traits/Trait
     103: dup
     104: iconst_0
     105: invokestatic  #99                 // Method software/amazon/awssdk/core/traits/LocationTrait.builder:()Lsoftware/amazon/awssdk/core/traits/LocationTrait$Builder;
     108: getstatic     #100                // Field software/amazon/awssdk/core/protocol/MarshallLocation.PAYLOAD:Lsoftware/amazon/awssdk/core/protocol/MarshallLocation;
     111: invokevirtual #101                // Method software/amazon/awssdk/core/traits/LocationTrait$Builder.location:(Lsoftware/amazon/awssdk/core/protocol/MarshallLocation;)Lsoftware/amazon/awssdk/core/traits/LocationTrait$Builder;
     114: ldc           #64                 // String AnomalyDetectorArn
     116: invokevirtual #102                // Method software/amazon/awssdk/core/traits/LocationTrait$Builder.locationName:(Ljava/lang/String;)Lsoftware/amazon/awssdk/core/traits/LocationTrait$Builder;
     119: invokevirtual #103                // Method software/amazon/awssdk/core/traits/LocationTrait$Builder.build:()Lsoftware/amazon/awssdk/core/traits/LocationTrait;
     122: aastore
     123: invokevirtual #104                // Method software/amazon/awssdk/core/SdkField$Builder.traits:([Lsoftware/amazon/awssdk/core/traits/Trait;)Lsoftware/amazon/awssdk/core/SdkField$Builder;
     126: invokevirtual #105                // Method software/amazon/awssdk/core/SdkField$Builder.build:()Lsoftware/amazon/awssdk/core/SdkField;
     129: putstatic     #109                // Field ANOMALY_DETECTOR_ARN_FIELD:Lsoftware/amazon/awssdk/core/SdkField;
     132: getstatic     #89                 // Field software/amazon/awssdk/core/protocol/MarshallingType.STRING:Lsoftware/amazon/awssdk/core/protocol/MarshallingType;
     135: invokestatic  #90                 // Method software/amazon/awssdk/core/SdkField.builder:(Lsoftware/amazon/awssdk/core/protocol/MarshallingType;)Lsoftware/amazon/awssdk/core/SdkField$Builder;
     138: ldc           #65                 // String MetricSetName
     140: invokevirtual #91                 // Method software/amazon/awssdk/core/SdkField$Builder.memberName:(Ljava/lang/String;)Lsoftware/amazon/awssdk/core/SdkField$Builder;
     143: invokedynamic #110,  0            // InvokeDynamic #6:apply:()Ljava/util/function/Function;
     148: invokestatic  #93                 // Method getter:(Ljava/util/function/Function;)Ljava/util/function/Function;
     151: invokevirtual #94                 // Method software/amazon/awssdk/core/SdkField$Builder.getter:(Ljava/util/function/Function;)Lsoftware/amazon/awssdk/core/SdkField$Builder;
     154: invokedynamic #111,  0            // InvokeDynamic #7:accept:()Ljava/util/function/BiConsumer;
     159: invokestatic  #96                 // Method setter:(Ljava/util/function/BiConsumer;)Ljava/util/function/BiConsumer;
     162: invokevirtual #97                 // Method software/amazon/awssdk/core/SdkField$Builder.setter:(Ljava/util/function/BiConsumer;)Lsoftware/amazon/awssdk/core/SdkField$Builder;
     165: iconst_1
     166: anewarray     #98                 // class software/amazon/awssdk/core/traits/Trait
     169: dup
     170: iconst_0
     171: invokestatic  #99                 // Method software/amazon/awssdk/core/traits/LocationTrait.builder:()Lsoftware/amazon/awssdk/core/traits/LocationTrait$Builder;
     174: getstatic     #100                // Field software/amazon/awssdk/core/protocol/MarshallLocation.PAYLOAD:Lsoftware/amazon/awssdk/core/protocol/MarshallLocation;
     177: invokevirtual #101                // Method software/amazon/awssdk/core/traits/LocationTrait$Builder.location:(Lsoftware/amazon/awssdk/core/protocol/MarshallLocation;)Lsoftware/amazon/awssdk/core/traits/LocationTrait$Builder;
     180: ldc           #65                 // String MetricSetName
     182: invokevirtual #102                // Method software/amazon/awssdk/core/traits/LocationTrait$Builder.locationName:(Ljava/lang/String;)Lsoftware/amazon/awssdk/core/traits/LocationTrait$Builder;
     185: invokevirtual #103                // Method software/amazon/awssdk/core/traits/LocationTrait$Builder.build:()Lsoftware/amazon/awssdk/core/traits/LocationTrait;
     188: aastore
     189: invokevirtual #104                // Method software/amazon/awssdk/core/SdkField$Builder.traits:([Lsoftware/amazon/awssdk/core/traits/Trait;)Lsoftware/amazon/awssdk/core/SdkField$Builder;
     192: invokevirtual #105                // Method software/amazon/awssdk/core/SdkField$Builder.build:()Lsoftware/amazon/awssdk/core/SdkField;
     195: putstatic     #112                // Field METRIC_SET_NAME_FIELD:Lsoftware/amazon/awssdk/core/SdkField;
     198: getstatic     #89                 // Field software/amazon/awssdk/core/protocol/MarshallingType.STRING:Lsoftware/amazon/awssdk/core/protocol/MarshallingType;
     201: invokestatic  #90                 // Method software/amazon/awssdk/core/SdkField.builder:(Lsoftware/amazon/awssdk/core/protocol/MarshallingType;)Lsoftware/amazon/awssdk/core/SdkField$Builder;
     204: ldc           #66                 // String MetricSetDescription
     206: invokevirtual #91                 // Method software/amazon/awssdk/core/SdkField$Builder.memberName:(Ljava/lang/String;)Lsoftware/amazon/awssdk/core/SdkField$Builder;
     209: invokedynamic #113,  0            // InvokeDynamic #8:apply:()Ljava/util/function/Function;
     214: invokestatic  #93                 // Method getter:(Ljava/util/function/Function;)Ljava/util/function/Function;
     217: invokevirtual #94                 // Method software/amazon/awssdk/core/SdkField$Builder.getter:(Ljava/util/function/Function;)Lsoftware/amazon/awssdk/core/SdkField$Builder;
     220: invokedynamic #114,  0            // InvokeDynamic #9:accept:()Ljava/util/function/BiConsumer;
     225: invokestatic  #96                 // Method setter:(Ljava/util/function/BiConsumer;)Ljava/util/function/BiConsumer;
     228: invokevirtual #97                 // Method software/amazon/awssdk/core/SdkField$Builder.setter:(Ljava/util/function/BiConsumer;)Lsoftware/amazon/awssdk/core/SdkField$Builder;
     231: iconst_1
     232: anewarray     #98                 // class software/amazon/awssdk/core/traits/Trait
     235: dup
     236: iconst_0
     237: invokestatic  #99                 // Method software/amazon/awssdk/core/traits/LocationTrait.builder:()Lsoftware/amazon/awssdk/core/traits/LocationTrait$Builder;
     240: getstatic     #100                // Field software/amazon/awssdk/core/protocol/MarshallLocation.PAYLOAD:Lsoftware/amazon/awssdk/core/protocol/MarshallLocation;
     243: invokevirtual #101                // Method software/amazon/awssdk/core/traits/LocationTrait$Builder.location:(Lsoftware/amazon/awssdk/core/protocol/MarshallLocation;)Lsoftware/amazon/awssdk/core/traits/LocationTrait$Builder;
     246: ldc           #66                 // String MetricSetDescription
     248: invokevirtual #102                // Method software/amazon/awssdk/core/traits/LocationTrait$Builder.locationName:(Ljava/lang/String;)Lsoftware/amazon/awssdk/core/traits/LocationTrait$Builder;
     251: invokevirtual #103                // Method software/amazon/awssdk/core/traits/LocationTrait$Builder.build:()Lsoftware/amazon/awssdk/core/traits/LocationTrait;
     254: aastore
     255: invokevirtual #104                // Method software/amazon/awssdk/core/SdkField$Builder.traits:([Lsoftware/amazon/awssdk/core/traits/Trait;)Lsoftware/amazon/awssdk/core/SdkField$Builder;
     258: invokevirtual #105                // Method software/amazon/awssdk/core/SdkField$Builder.build:()Lsoftware/amazon/awssdk/core/SdkField;
     261: putstatic     #115                // Field METRIC_SET_DESCRIPTION_FIELD:Lsoftware/amazon/awssdk/core/SdkField;
     264: getstatic     #116                // Field software/amazon/awssdk/core/protocol/MarshallingType.INSTANT:Lsoftware/amazon/awssdk/core/protocol/MarshallingType;
     267: invokestatic  #90                 // Method software/amazon/awssdk/core/SdkField.builder:(Lsoftware/amazon/awssdk/core/protocol/MarshallingType;)Lsoftware/amazon/awssdk/core/SdkField$Builder;
     270: ldc           #67                 // String CreationTime
     272: invokevirtual #91                 // Method software/amazon/awssdk/core/SdkField$Builder.memberName:(Ljava/lang/String;)Lsoftware/amazon/awssdk/core/SdkField$Builder;
     275: invokedynamic #117,  0            // InvokeDynamic #10:apply:()Ljava/util/function/Function;
     280: invokestatic  #93                 // Method getter:(Ljava/util/function/Function;)Ljava/util/function/Function;
     283: invokevirtual #94                 // Method software/amazon/awssdk/core/SdkField$Builder.getter:(Ljava/util/function/Function;)Lsoftware/amazon/awssdk/core/SdkField$Builder;
     286: invokedynamic #118,  0            // InvokeDynamic #11:accept:()Ljava/util/function/BiConsumer;
     291: invokestatic  #96                 // Method setter:(Ljava/util/function/BiConsumer;)Ljava/util/function/BiConsumer;
     294: invokevirtual #97                 // Method software/amazon/awssdk/core/SdkField$Builder.setter:(Ljava/util/function/BiConsumer;)Lsoftware/amazon/awssdk/core/SdkField$Builder;
     297: iconst_1
     298: anewarray     #98                 // class software/amazon/awssdk/core/traits/Trait
     301: dup
     302: iconst_0
     303: invokestatic  #99                 // Method software/amazon/awssdk/core/traits/LocationTrait.builder:()Lsoftware/amazon/awssdk/core/traits/LocationTrait$Builder;
     306: getstatic     #100                // Field software/amazon/awssdk/core/protocol/MarshallLocation.PAYLOAD:Lsoftware/amazon/awssdk/core/protocol/MarshallLocation;
     309: invokevirtual #101                // Method software/amazon/awssdk/core/traits/LocationTrait$Builder.location:(Lsoftware/amazon/awssdk/core/protocol/MarshallLocation;)Lsoftware/amazon/awssdk/core/traits/LocationTrait$Builder;
     312: ldc           #67                 // String CreationTime
     314: invokevirtual #102                // Method software/amazon/awssdk/core/traits/LocationTrait$Builder.locationName:(Ljava/lang/String;)Lsoftware/amazon/awssdk/core/traits/LocationTrait$Builder;
     317: invokevirtual #103                // Method software/amazon/awssdk/core/traits/LocationTrait$Builder.build:()Lsoftware/amazon/awssdk/core/traits/LocationTrait;
     320: aastore
     321: invokevirtual #104                // Method software/amazon/awssdk/core/SdkField$Builder.traits:([Lsoftware/amazon/awssdk/core/traits/Trait;)Lsoftware/amazon/awssdk/core/SdkField$Builder;
     324: invokevirtual #105                // Method software/amazon/awssdk/core/SdkField$Builder.build:()Lsoftware/amazon/awssdk/core/SdkField;
     327: putstatic     #119                // Field CREATION_TIME_FIELD:Lsoftware/amazon/awssdk/core/SdkField;
     330: getstatic     #116                // Field software/amazon/awssdk/core/protocol/MarshallingType.INSTANT:Lsoftware/amazon/awssdk/core/protocol/MarshallingType;
     333: invokestatic  #90                 // Method software/amazon/awssdk/core/SdkField.builder:(Lsoftware/amazon/awssdk/core/protocol/MarshallingType;)Lsoftware/amazon/awssdk/core/SdkField$Builder;
     336: ldc           #68                 // String LastModificationTime
     338: invokevirtual #91                 // Method software/amazon/awssdk/core/SdkField$Builder.memberName:(Ljava/lang/String;)Lsoftware/amazon/awssdk/core/SdkField$Builder;
     341: invokedynamic #120,  0            // InvokeDynamic #12:apply:()Ljava/util/function/Function;
     346: invokestatic  #93                 // Method getter:(Ljava/util/function/Function;)Ljava/util/function/Function;
     349: invokevirtual #94                 // Method software/amazon/awssdk/core/SdkField$Builder.getter:(Ljava/util/function/Function;)Lsoftware/amazon/awssdk/core/SdkField$Builder;
     352: invokedynamic #121,  0            // InvokeDynamic #13:accept:()Ljava/util/function/BiConsumer;
     357: invokestatic  #96                 // Method setter:(Ljava/util/function/BiConsumer;)Ljava/util/function/BiConsumer;
     360: invokevirtual #97                 // Method software/amazon/awssdk/core/SdkField$Builder.setter:(Ljava/util/function/BiConsumer;)Lsoftware/amazon/awssdk/core/SdkField$Builder;
     363: iconst_1
     364: anewarray     #98                 // class software/amazon/awssdk/core/traits/Trait
     367: dup
     368: iconst_0
     369: invokestatic  #99                 // Method software/amazon/awssdk/core/traits/LocationTrait.builder:()Lsoftware/amazon/awssdk/core/traits/LocationTrait$Builder;
     372: getstatic     #100                // Field software/amazon/awssdk/core/protocol/MarshallLocation.PAYLOAD:Lsoftware/amazon/awssdk/core/protocol/MarshallLocation;
     375: invokevirtual #101                // Method software/amazon/awssdk/core/traits/LocationTrait$Builder.location:(Lsoftware/amazon/awssdk/core/protocol/MarshallLocation;)Lsoftware/amazon/awssdk/core/traits/LocationTrait$Builder;
     378: ldc           #68                 // String LastModificationTime
     380: invokevirtual #102                // Method software/amazon/awssdk/core/traits/LocationTrait$Builder.locationName:(Ljava/lang/String;)Lsoftware/amazon/awssdk/core/traits/LocationTrait$Builder;
     383: invokevirtual #103                // Method software/amazon/awssdk/core/traits/LocationTrait$Builder.build:()Lsoftware/amazon/awssdk/core/traits/LocationTrait;
     386: aastore
     387: invokevirtual #104                // Method software/amazon/awssdk/core/SdkField$Builder.traits:([Lsoftware/amazon/awssdk/core/traits/Trait;)Lsoftware/amazon/awssdk/core/SdkField$Builder;
     390: invokevirtual #105                // Method software/amazon/awssdk/core/SdkField$Builder.build:()Lsoftware/amazon/awssdk/core/SdkField;
     393: putstatic     #122                // Field LAST_MODIFICATION_TIME_FIELD:Lsoftware/amazon/awssdk/core/SdkField;
     396: getstatic     #123                // Field software/amazon/awssdk/core/protocol/MarshallingType.INTEGER:Lsoftware/amazon/awssdk/core/protocol/MarshallingType;
     399: invokestatic  #90                 // Method software/amazon/awssdk/core/SdkField.builder:(Lsoftware/amazon/awssdk/core/protocol/MarshallingType;)Lsoftware/amazon/awssdk/core/SdkField$Builder;
     402: ldc           #69                 // String Offset
     404: invokevirtual #91                 // Method software/amazon/awssdk/core/SdkField$Builder.memberName:(Ljava/lang/String;)Lsoftware/amazon/awssdk/core/SdkField$Builder;
     407: invokedynamic #124,  0            // InvokeDynamic #14:apply:()Ljava/util/function/Function;
     412: invokestatic  #93                 // Method getter:(Ljava/util/function/Function;)Ljava/util/function/Function;
     415: invokevirtual #94                 // Method software/amazon/awssdk/core/SdkField$Builder.getter:(Ljava/util/function/Function;)Lsoftware/amazon/awssdk/core/SdkField$Builder;
     418: invokedynamic #125,  0            // InvokeDynamic #15:accept:()Ljava/util/function/BiConsumer;
     423: invokestatic  #96                 // Method setter:(Ljava/util/function/BiConsumer;)Ljava/util/function/BiConsumer;
     426: invokevirtual #97                 // Method software/amazon/awssdk/core/SdkField$Builder.setter:(Ljava/util/function/BiConsumer;)Lsoftware/amazon/awssdk/core/SdkField$Builder;
     429: iconst_1
     430: anewarray     #98                 // class software/amazon/awssdk/core/traits/Trait
     433: dup
     434: iconst_0
     435: invokestatic  #99                 // Method software/amazon/awssdk/core/traits/LocationTrait.builder:()Lsoftware/amazon/awssdk/core/traits/LocationTrait$Builder;
     438: getstatic     #100                // Field software/amazon/awssdk/core/protocol/MarshallLocation.PAYLOAD:Lsoftware/amazon/awssdk/core/protocol/MarshallLocation;
     441: invokevirtual #101                // Method software/amazon/awssdk/core/traits/LocationTrait$Builder.location:(Lsoftware/amazon/awssdk/core/protocol/MarshallLocation;)Lsoftware/amazon/awssdk/core/traits/LocationTrait$Builder;
     444: ldc           #69                 // String Offset
     446: invokevirtual #102                // Method software/amazon/awssdk/core/traits/LocationTrait$Builder.locationName:(Ljava/lang/String;)Lsoftware/amazon/awssdk/core/traits/LocationTrait$Builder;
     449: invokevirtual #103                // Method software/amazon/awssdk/core/traits/LocationTrait$Builder.build:()Lsoftware/amazon/awssdk/core/traits/LocationTrait;
     452: aastore
     453: invokevirtual #104                // Method software/amazon/awssdk/core/SdkField$Builder.traits:([Lsoftware/amazon/awssdk/core/traits/Trait;)Lsoftware/amazon/awssdk/core/SdkField$Builder;
     456: invokevirtual #105                // Method software/amazon/awssdk/core/SdkField$Builder.build:()Lsoftware/amazon/awssdk/core/SdkField;
     459: putstatic     #126                // Field OFFSET_FIELD:Lsoftware/amazon/awssdk/core/SdkField;
     462: getstatic     #127                // Field software/amazon/awssdk/core/protocol/MarshallingType.LIST:Lsoftware/amazon/awssdk/core/protocol/MarshallingType;
     465: invokestatic  #90                 // Method software/amazon/awssdk/core/SdkField.builder:(Lsoftware/amazon/awssdk/core/protocol/MarshallingType;)Lsoftware/amazon/awssdk/core/SdkField$Builder;
     468: ldc           #70                 // String MetricList
     470: invokevirtual #91                 // Method software/amazon/awssdk/core/SdkField$Builder.memberName:(Ljava/lang/String;)Lsoftware/amazon/awssdk/core/SdkField$Builder;
     473: invokedynamic #128,  0            // InvokeDynamic #16:apply:()Ljava/util/function/Function;
     478: invokestatic  #93                 // Method getter:(Ljava/util/function/Function;)Ljava/util/function/Function;
     481: invokevirtual #94                 // Method software/amazon/awssdk/core/SdkField$Builder.getter:(Ljava/util/function/Function;)Lsoftware/amazon/awssdk/core/SdkField$Builder;
     484: invokedynamic #129,  0            // InvokeDynamic #17:accept:()Ljava/util/function/BiConsumer;
     489: invokestatic  #96                 // Method setter:(Ljava/util/function/BiConsumer;)Ljava/util/function/BiConsumer;
     492: invokevirtual #97                 // Method software/amazon/awssdk/core/SdkField$Builder.setter:(Ljava/util/function/BiConsumer;)Lsoftware/amazon/awssdk/core/SdkField$Builder;
     495: iconst_2
     496: anewarray     #98                 // class software/amazon/awssdk/core/traits/Trait
     499: dup
     500: iconst_0
     501: invokestatic  #99                 // Method software/amazon/awssdk/core/traits/LocationTrait.builder:()Lsoftware/amazon/awssdk/core/traits/LocationTrait$Builder;
     504: getstatic     #100                // Field software/amazon/awssdk/core/protocol/MarshallLocation.PAYLOAD:Lsoftware/amazon/awssdk/core/protocol/MarshallLocation;
     507: invokevirtual #101                // Method software/amazon/awssdk/core/traits/LocationTrait$Builder.location:(Lsoftware/amazon/awssdk/core/protocol/MarshallLocation;)Lsoftware/amazon/awssdk/core/traits/LocationTrait$Builder;
     510: ldc           #70                 // String MetricList
     512: invokevirtual #102                // Method software/amazon/awssdk/core/traits/LocationTrait$Builder.locationName:(Ljava/lang/String;)Lsoftware/amazon/awssdk/core/traits/LocationTrait$Builder;
     515: invokevirtual #103                // Method software/amazon/awssdk/core/traits/LocationTrait$Builder.build:()Lsoftware/amazon/awssdk/core/traits/LocationTrait;
     518: aastore
     519: dup
     520: iconst_1
     521: invokestatic  #130                // Method software/amazon/awssdk/core/traits/ListTrait.builder:()Lsoftware/amazon/awssdk/core/traits/ListTrait$Builder;
     524: aconst_null
     525: invokevirtual #131                // Method software/amazon/awssdk/core/traits/ListTrait$Builder.memberLocationName:(Ljava/lang/String;)Lsoftware/amazon/awssdk/core/traits/ListTrait$Builder;
     528: getstatic     #132                // Field software/amazon/awssdk/core/protocol/MarshallingType.SDK_POJO:Lsoftware/amazon/awssdk/core/protocol/MarshallingType;
     531: invokestatic  #90                 // Method software/amazon/awssdk/core/SdkField.builder:(Lsoftware/amazon/awssdk/core/protocol/MarshallingType;)Lsoftware/amazon/awssdk/core/SdkField$Builder;
     534: invokedynamic #133,  0            // InvokeDynamic #18:get:()Ljava/util/function/Supplier;
     539: invokevirtual #134                // Method software/amazon/awssdk/core/SdkField$Builder.constructor:(Ljava/util/function/Supplier;)Lsoftware/amazon/awssdk/core/SdkField$Builder;
     542: iconst_1
     543: anewarray     #98                 // class software/amazon/awssdk/core/traits/Trait
     546: dup
     547: iconst_0
     548: invokestatic  #99                 // Method software/amazon/awssdk/core/traits/LocationTrait.builder:()Lsoftware/amazon/awssdk/core/traits/LocationTrait$Builder;
     551: getstatic     #100                // Field software/amazon/awssdk/core/protocol/MarshallLocation.PAYLOAD:Lsoftware/amazon/awssdk/core/protocol/MarshallLocation;
     554: invokevirtual #101                // Method software/amazon/awssdk/core/traits/LocationTrait$Builder.location:(Lsoftware/amazon/awssdk/core/protocol/MarshallLocation;)Lsoftware/amazon/awssdk/core/traits/LocationTrait$Builder;
     557: ldc           #135                // String member
     559: invokevirtual #102                // Method software/amazon/awssdk/core/traits/LocationTrait$Builder.locationName:(Ljava/lang/String;)Lsoftware/amazon/awssdk/core/traits/LocationTrait$Builder;
     562: invokevirtual #103                // Method software/amazon/awssdk/core/traits/LocationTrait$Builder.build:()Lsoftware/amazon/awssdk/core/traits/LocationTrait;
     565: aastore
     566: invokevirtual #104                // Method software/amazon/awssdk/core/SdkField$Builder.traits:([Lsoftware/amazon/awssdk/core/traits/Trait;)Lsoftware/amazon/awssdk/core/SdkField$Builder;
     569: invokevirtual #105                // Method software/amazon/awssdk/core/SdkField$Builder.build:()Lsoftware/amazon/awssdk/core/SdkField;
     572: invokevirtual #136                // Method software/amazon/awssdk/core/traits/ListTrait$Builder.memberFieldInfo:(Lsoftware/amazon/awssdk/core/SdkField;)Lsoftware/amazon/awssdk/core/traits/ListTrait$Builder;
     575: invokevirtual #137                // Method software/amazon/awssdk/core/traits/ListTrait$Builder.build:()Lsoftware/amazon/awssdk/core/traits/ListTrait;
     578: aastore
     579: invokevirtual #104                // Method software/amazon/awssdk/core/SdkField$Builder.traits:([Lsoftware/amazon/awssdk/core/traits/Trait;)Lsoftware/amazon/awssdk/core/SdkField$Builder;
     582: invokevirtual #105                // Method software/amazon/awssdk/core/SdkField$Builder.build:()Lsoftware/amazon/awssdk/core/SdkField;
     585: putstatic     #138                // Field METRIC_LIST_FIELD:Lsoftware/amazon/awssdk/core/SdkField;
     588: getstatic     #132                // Field software/amazon/awssdk/core/protocol/MarshallingType.SDK_POJO:Lsoftware/amazon/awssdk/core/protocol/MarshallingType;
     591: invokestatic  #90                 // Method software/amazon/awssdk/core/SdkField.builder:(Lsoftware/amazon/awssdk/core/protocol/MarshallingType;)Lsoftware/amazon/awssdk/core/SdkField$Builder;
     594: ldc           #71                 // String TimestampColumn
     596: invokevirtual #91                 // Method software/amazon/awssdk/core/SdkField$Builder.memberName:(Ljava/lang/String;)Lsoftware/amazon/awssdk/core/SdkField$Builder;
     599: invokedynamic #139,  0            // InvokeDynamic #19:apply:()Ljava/util/function/Function;
     604: invokestatic  #93                 // Method getter:(Ljava/util/function/Function;)Ljava/util/function/Function;
     607: invokevirtual #94                 // Method software/amazon/awssdk/core/SdkField$Builder.getter:(Ljava/util/function/Function;)Lsoftware/amazon/awssdk/core/SdkField$Builder;
     610: invokedynamic #140,  0            // InvokeDynamic #20:accept:()Ljava/util/function/BiConsumer;
     615: invokestatic  #96                 // Method setter:(Ljava/util/function/BiConsumer;)Ljava/util/function/BiConsumer;
     618: invokevirtual #97                 // Method software/amazon/awssdk/core/SdkField$Builder.setter:(Ljava/util/function/BiConsumer;)Lsoftware/amazon/awssdk/core/SdkField$Builder;
     621: invokedynamic #141,  0            // InvokeDynamic #21:get:()Ljava/util/function/Supplier;
     626: invokevirtual #134                // Method software/amazon/awssdk/core/SdkField$Builder.constructor:(Ljava/util/function/Supplier;)Lsoftware/amazon/awssdk/core/SdkField$Builder;
     629: iconst_1
     630: anewarray     #98                 // class software/amazon/awssdk/core/traits/Trait
     633: dup
     634: iconst_0
     635: invokestatic  #99                 // Method software/amazon/awssdk/core/traits/LocationTrait.builder:()Lsoftware/amazon/awssdk/core/traits/LocationTrait$Builder;
     638: getstatic     #100                // Field software/amazon/awssdk/core/protocol/MarshallLocation.PAYLOAD:Lsoftware/amazon/awssdk/core/protocol/MarshallLocation;
     641: invokevirtual #101                // Method software/amazon/awssdk/core/traits/LocationTrait$Builder.location:(Lsoftware/amazon/awssdk/core/protocol/MarshallLocation;)Lsoftware/amazon/awssdk/core/traits/LocationTrait$Builder;
     644: ldc           #71                 // String TimestampColumn
     646: invokevirtual #102                // Method software/amazon/awssdk/core/traits/LocationTrait$Builder.locationName:(Ljava/lang/String;)Lsoftware/amazon/awssdk/core/traits/LocationTrait$Builder;
     649: invokevirtual #103                // Method software/amazon/awssdk/core/traits/LocationTrait$Builder.build:()Lsoftware/amazon/awssdk/core/traits/LocationTrait;
     652: aastore
     653: invokevirtual #104                // Method software/amazon/awssdk/core/SdkField$Builder.traits:([Lsoftware/amazon/awssdk/core/traits/Trait;)Lsoftware/amazon/awssdk/core/SdkField$Builder;
     656: invokevirtual #105                // Method software/amazon/awssdk/core/SdkField$Builder.build:()Lsoftware/amazon/awssdk/core/SdkField;
     659: putstatic     #142                // Field TIMESTAMP_COLUMN_FIELD:Lsoftware/amazon/awssdk/core/SdkField;
     662: getstatic     #127                // Field software/amazon/awssdk/core/protocol/MarshallingType.LIST:Lsoftware/amazon/awssdk/core/protocol/MarshallingType;
     665: invokestatic  #90                 // Method software/amazon/awssdk/core/SdkField.builder:(Lsoftware/amazon/awssdk/core/protocol/MarshallingType;)Lsoftware/amazon/awssdk/core/SdkField$Builder;
     668: ldc           #72                 // String DimensionList
     670: invokevirtual #91                 // Method software/amazon/awssdk/core/SdkField$Builder.memberName:(Ljava/lang/String;)Lsoftware/amazon/awssdk/core/SdkField$Builder;
     673: invokedynamic #143,  0            // InvokeDynamic #22:apply:()Ljava/util/function/Function;
     678: invokestatic  #93                 // Method getter:(Ljava/util/function/Function;)Ljava/util/function/Function;
     681: invokevirtual #94                 // Method software/amazon/awssdk/core/SdkField$Builder.getter:(Ljava/util/function/Function;)Lsoftware/amazon/awssdk/core/SdkField$Builder;
     684: invokedynamic #144,  0            // InvokeDynamic #23:accept:()Ljava/util/function/BiConsumer;
     689: invokestatic  #96                 // Method setter:(Ljava/util/function/BiConsumer;)Ljava/util/function/BiConsumer;
     692: invokevirtual #97                 // Method software/amazon/awssdk/core/SdkField$Builder.setter:(Ljava/util/function/BiConsumer;)Lsoftware/amazon/awssdk/core/SdkField$Builder;
     695: iconst_2
     696: anewarray     #98                 // class software/amazon/awssdk/core/traits/Trait
     699: dup
     700: iconst_0
     701: invokestatic  #99                 // Method software/amazon/awssdk/core/traits/LocationTrait.builder:()Lsoftware/amazon/awssdk/core/traits/LocationTrait$Builder;
     704: getstatic     #100                // Field software/amazon/awssdk/core/protocol/MarshallLocation.PAYLOAD:Lsoftware/amazon/awssdk/core/protocol/MarshallLocation;
     707: invokevirtual #101                // Method software/amazon/awssdk/core/traits/LocationTrait$Builder.location:(Lsoftware/amazon/awssdk/core/protocol/MarshallLocation;)Lsoftware/amazon/awssdk/core/traits/LocationTrait$Builder;
     710: ldc           #72                 // String DimensionList
     712: invokevirtual #102                // Method software/amazon/awssdk/core/traits/LocationTrait$Builder.locationName:(Ljava/lang/String;)Lsoftware/amazon/awssdk/core/traits/LocationTrait$Builder;
     715: invokevirtual #103                // Method software/amazon/awssdk/core/traits/LocationTrait$Builder.build:()Lsoftware/amazon/awssdk/core/traits/LocationTrait;
     718: aastore
     719: dup
     720: iconst_1
     721: invokestatic  #130                // Method software/amazon/awssdk/core/traits/ListTrait.builder:()Lsoftware/amazon/awssdk/core/traits/ListTrait$Builder;
     724: aconst_null
     725: invokevirtual #131                // Method software/amazon/awssdk/core/traits/ListTrait$Builder.memberLocationName:(Ljava/lang/String;)Lsoftware/amazon/awssdk/core/traits/ListTrait$Builder;
     728: getstatic     #89                 // Field software/amazon/awssdk/core/protocol/MarshallingType.STRING:Lsoftware/amazon/awssdk/core/protocol/MarshallingType;
     731: invokestatic  #90                 // Method software/amazon/awssdk/core/SdkField.builder:(Lsoftware/amazon/awssdk/core/protocol/MarshallingType;)Lsoftware/amazon/awssdk/core/SdkField$Builder;
     734: iconst_1
     735: anewarray     #98                 // class software/amazon/awssdk/core/traits/Trait
     738: dup
     739: iconst_0
     740: invokestatic  #99                 // Method software/amazon/awssdk/core/traits/LocationTrait.builder:()Lsoftware/amazon/awssdk/core/traits/LocationTrait$Builder;
     743: getstatic     #100                // Field software/amazon/awssdk/core/protocol/MarshallLocation.PAYLOAD:Lsoftware/amazon/awssdk/core/protocol/MarshallLocation;
     746: invokevirtual #101                // Method software/amazon/awssdk/core/traits/LocationTrait$Builder.location:(Lsoftware/amazon/awssdk/core/protocol/MarshallLocation;)Lsoftware/amazon/awssdk/core/traits/LocationTrait$Builder;
     749: ldc           #135                // String member
     751: invokevirtual #102                // Method software/amazon/awssdk/core/traits/LocationTrait$Builder.locationName:(Ljava/lang/String;)Lsoftware/amazon/awssdk/core/traits/LocationTrait$Builder;
     754: invokevirtual #103                // Method software/amazon/awssdk/core/traits/LocationTrait$Builder.build:()Lsoftware/amazon/awssdk/core/traits/LocationTrait;
     757: aastore
     758: invokevirtual #104                // Method software/amazon/awssdk/core/SdkField$Builder.traits:([Lsoftware/amazon/awssdk/core/traits/Trait;)Lsoftware/amazon/awssdk/core/SdkField$Builder;
     761: invokevirtual #105                // Method software/amazon/awssdk/core/SdkField$Builder.build:()Lsoftware/amazon/awssdk/core/SdkField;
     764: invokevirtual #136                // Method software/amazon/awssdk/core/traits/ListTrait$Builder.memberFieldInfo:(Lsoftware/amazon/awssdk/core/SdkField;)Lsoftware/amazon/awssdk/core/traits/ListTrait$Builder;
     767: invokevirtual #137                // Method software/amazon/awssdk/core/traits/ListTrait$Builder.build:()Lsoftware/amazon/awssdk/core/traits/ListTrait;
     770: aastore
     771: invokevirtual #104                // Method software/amazon/awssdk/core/SdkField$Builder.traits:([Lsoftware/amazon/awssdk/core/traits/Trait;)Lsoftware/amazon/awssdk/core/SdkField$Builder;
     774: invokevirtual #105                // Method software/amazon/awssdk/core/SdkField$Builder.build:()Lsoftware/amazon/awssdk/core/SdkField;
     777: putstatic     #145                // Field DIMENSION_LIST_FIELD:Lsoftware/amazon/awssdk/core/SdkField;
     780: getstatic     #89                 // Field software/amazon/awssdk/core/protocol/MarshallingType.STRING:Lsoftware/amazon/awssdk/core/protocol/MarshallingType;
     783: invokestatic  #90                 // Method software/amazon/awssdk/core/SdkField.builder:(Lsoftware/amazon/awssdk/core/protocol/MarshallingType;)Lsoftware/amazon/awssdk/core/SdkField$Builder;
     786: ldc           #73                 // String MetricSetFrequency
     788: invokevirtual #91                 // Method software/amazon/awssdk/core/SdkField$Builder.memberName:(Ljava/lang/String;)Lsoftware/amazon/awssdk/core/SdkField$Builder;
     791: invokedynamic #146,  0            // InvokeDynamic #24:apply:()Ljava/util/function/Function;
     796: invokestatic  #93                 // Method getter:(Ljava/util/function/Function;)Ljava/util/function/Function;
     799: invokevirtual #94                 // Method software/amazon/awssdk/core/SdkField$Builder.getter:(Ljava/util/function/Function;)Lsoftware/amazon/awssdk/core/SdkField$Builder;
     802: invokedynamic #147,  0            // InvokeDynamic #25:accept:()Ljava/util/function/BiConsumer;
     807: invokestatic  #96                 // Method setter:(Ljava/util/function/BiConsumer;)Ljava/util/function/BiConsumer;
     810: invokevirtual #97                 // Method software/amazon/awssdk/core/SdkField$Builder.setter:(Ljava/util/function/BiConsumer;)Lsoftware/amazon/awssdk/core/SdkField$Builder;
     813: iconst_1
     814: anewarray     #98                 // class software/amazon/awssdk/core/traits/Trait
     817: dup
     818: iconst_0
     819: invokestatic  #99                 // Method software/amazon/awssdk/core/traits/LocationTrait.builder:()Lsoftware/amazon/awssdk/core/traits/LocationTrait$Builder;
     822: getstatic     #100                // Field software/amazon/awssdk/core/protocol/MarshallLocation.PAYLOAD:Lsoftware/amazon/awssdk/core/protocol/MarshallLocation;
     825: invokevirtual #101                // Method software/amazon/awssdk/core/traits/LocationTrait$Builder.location:(Lsoftware/amazon/awssdk/core/protocol/MarshallLocation;)Lsoftware/amazon/awssdk/core/traits/LocationTrait$Builder;
     828: ldc           #73                 // String MetricSetFrequency
     830: invokevirtual #102                // Method software/amazon/awssdk/core/traits/LocationTrait$Builder.locationName:(Ljava/lang/String;)Lsoftware/amazon/awssdk/core/traits/LocationTrait$Builder;
     833: invokevirtual #103                // Method software/amazon/awssdk/core/traits/LocationTrait$Builder.build:()Lsoftware/amazon/awssdk/core/traits/LocationTrait;
     836: aastore
     837: invokevirtual #104                // Method software/amazon/awssdk/core/SdkField$Builder.traits:([Lsoftware/amazon/awssdk/core/traits/Trait;)Lsoftware/amazon/awssdk/core/SdkField$Builder;
     840: invokevirtual #105                // Method software/amazon/awssdk/core/SdkField$Builder.build:()Lsoftware/amazon/awssdk/core/SdkField;
     843: putstatic     #148                // Field METRIC_SET_FREQUENCY_FIELD:Lsoftware/amazon/awssdk/core/SdkField;
     846: getstatic     #89                 // Field software/amazon/awssdk/core/protocol/MarshallingType.STRING:Lsoftware/amazon/awssdk/core/protocol/MarshallingType;
     849: invokestatic  #90                 // Method software/amazon/awssdk/core/SdkField.builder:(Lsoftware/amazon/awssdk/core/protocol/MarshallingType;)Lsoftware/amazon/awssdk/core/SdkField$Builder;
     852: ldc           #74                 // String Timezone
     854: invokevirtual #91                 // Method software/amazon/awssdk/core/SdkField$Builder.memberName:(Ljava/lang/String;)Lsoftware/amazon/awssdk/core/SdkField$Builder;
     857: invokedynamic #149,  0            // InvokeDynamic #26:apply:()Ljava/util/function/Function;
     862: invokestatic  #93                 // Method getter:(Ljava/util/function/Function;)Ljava/util/function/Function;
     865: invokevirtual #94                 // Method software/amazon/awssdk/core/SdkField$Builder.getter:(Ljava/util/function/Function;)Lsoftware/amazon/awssdk/core/SdkField$Builder;
     868: invokedynamic #150,  0            // InvokeDynamic #27:accept:()Ljava/util/function/BiConsumer;
     873: invokestatic  #96                 // Method setter:(Ljava/util/function/BiConsumer;)Ljava/util/function/BiConsumer;
     876: invokevirtual #97                 // Method software/amazon/awssdk/core/SdkField$Builder.setter:(Ljava/util/function/BiConsumer;)Lsoftware/amazon/awssdk/core/SdkField$Builder;
     879: iconst_1
     880: anewarray     #98                 // class software/amazon/awssdk/core/traits/Trait
     883: dup
     884: iconst_0
     885: invokestatic  #99                 // Method software/amazon/awssdk/core/traits/LocationTrait.builder:()Lsoftware/amazon/awssdk/core/traits/LocationTrait$Builder;
     888: getstatic     #100                // Field software/amazon/awssdk/core/protocol/MarshallLocation.PAYLOAD:Lsoftware/amazon/awssdk/core/protocol/MarshallLocation;
     891: invokevirtual #101                // Method software/amazon/awssdk/core/traits/LocationTrait$Builder.location:(Lsoftware/amazon/awssdk/core/protocol/MarshallLocation;)Lsoftware/amazon/awssdk/core/traits/LocationTrait$Builder;
     894: ldc           #74                 // String Timezone
     896: invokevirtual #102                // Method software/amazon/awssdk/core/traits/LocationTrait$Builder.locationName:(Ljava/lang/String;)Lsoftware/amazon/awssdk/core/traits/LocationTrait$Builder;
     899: invokevirtual #103                // Method software/amazon/awssdk/core/traits/LocationTrait$Builder.build:()Lsoftware/amazon/awssdk/core/traits/LocationTrait;
     902: aastore
     903: invokevirtual #104                // Method software/amazon/awssdk/core/SdkField$Builder.traits:([Lsoftware/amazon/awssdk/core/traits/Trait;)Lsoftware/amazon/awssdk/core/SdkField$Builder;
     906: invokevirtual #105                // Method software/amazon/awssdk/core/SdkField$Builder.build:()Lsoftware/amazon/awssdk/core/SdkField;
     909: putstatic     #151                // Field TIMEZONE_FIELD:Lsoftware/amazon/awssdk/core/SdkField;
     912: getstatic     #132                // Field software/amazon/awssdk/core/protocol/MarshallingType.SDK_POJO:Lsoftware/amazon/awssdk/core/protocol/MarshallingType;
     915: invokestatic  #90                 // Method software/amazon/awssdk/core/SdkField.builder:(Lsoftware/amazon/awssdk/core/protocol/MarshallingType;)Lsoftware/amazon/awssdk/core/SdkField$Builder;
     918: ldc           #75                 // String MetricSource
     920: invokevirtual #91                 // Method software/amazon/awssdk/core/SdkField$Builder.memberName:(Ljava/lang/String;)Lsoftware/amazon/awssdk/core/SdkField$Builder;
     923: invokedynamic #152,  0            // InvokeDynamic #28:apply:()Ljava/util/function/Function;
     928: invokestatic  #93                 // Method getter:(Ljava/util/function/Function;)Ljava/util/function/Function;
     931: invokevirtual #94                 // Method software/amazon/awssdk/core/SdkField$Builder.getter:(Ljava/util/function/Function;)Lsoftware/amazon/awssdk/core/SdkField$Builder;
     934: invokedynamic #153,  0            // InvokeDynamic #29:accept:()Ljava/util/function/BiConsumer;
     939: invokestatic  #96                 // Method setter:(Ljava/util/function/BiConsumer;)Ljava/util/function/BiConsumer;
     942: invokevirtual #97                 // Method software/amazon/awssdk/core/SdkField$Builder.setter:(Ljava/util/function/BiConsumer;)Lsoftware/amazon/awssdk/core/SdkField$Builder;
     945: invokedynamic #154,  0            // InvokeDynamic #30:get:()Ljava/util/function/Supplier;
     950: invokevirtual #134                // Method software/amazon/awssdk/core/SdkField$Builder.constructor:(Ljava/util/function/Supplier;)Lsoftware/amazon/awssdk/core/SdkField$Builder;
     953: iconst_1
     954: anewarray     #98                 // class software/amazon/awssdk/core/traits/Trait
     957: dup
     958: iconst_0
     959: invokestatic  #99                 // Method software/amazon/awssdk/core/traits/LocationTrait.builder:()Lsoftware/amazon/awssdk/core/traits/LocationTrait$Builder;
     962: getstatic     #100                // Field software/amazon/awssdk/core/protocol/MarshallLocation.PAYLOAD:Lsoftware/amazon/awssdk/core/protocol/MarshallLocation;
     965: invokevirtual #101                // Method software/amazon/awssdk/core/traits/LocationTrait$Builder.location:(Lsoftware/amazon/awssdk/core/protocol/MarshallLocation;)Lsoftware/amazon/awssdk/core/traits/LocationTrait$Builder;
     968: ldc           #75                 // String MetricSource
     970: invokevirtual #102                // Method software/amazon/awssdk/core/traits/LocationTrait$Builder.locationName:(Ljava/lang/String;)Lsoftware/amazon/awssdk/core/traits/LocationTrait$Builder;
     973: invokevirtual #103                // Method software/amazon/awssdk/core/traits/LocationTrait$Builder.build:()Lsoftware/amazon/awssdk/core/traits/LocationTrait;
     976: aastore
     977: invokevirtual #104                // Method software/amazon/awssdk/core/SdkField$Builder.traits:([Lsoftware/amazon/awssdk/core/traits/Trait;)Lsoftware/amazon/awssdk/core/SdkField$Builder;
     980: invokevirtual #105                // Method software/amazon/awssdk/core/SdkField$Builder.build:()Lsoftware/amazon/awssdk/core/SdkField;
     983: putstatic     #155                // Field METRIC_SOURCE_FIELD:Lsoftware/amazon/awssdk/core/SdkField;
     986: getstatic     #127                // Field software/amazon/awssdk/core/protocol/MarshallingType.LIST:Lsoftware/amazon/awssdk/core/protocol/MarshallingType;
     989: invokestatic  #90                 // Method software/amazon/awssdk/core/SdkField.builder:(Lsoftware/amazon/awssdk/core/protocol/MarshallingType;)Lsoftware/amazon/awssdk/core/SdkField$Builder;
     992: ldc           #76                 // String DimensionFilterList
     994: invokevirtual #91                 // Method software/amazon/awssdk/core/SdkField$Builder.memberName:(Ljava/lang/String;)Lsoftware/amazon/awssdk/core/SdkField$Builder;
     997: invokedynamic #156,  0            // InvokeDynamic #31:apply:()Ljava/util/function/Function;
    1002: invokestatic  #93                 // Method getter:(Ljava/util/function/Function;)Ljava/util/function/Function;
    1005: invokevirtual #94                 // Method software/amazon/awssdk/core/SdkField$Builder.getter:(Ljava/util/function/Function;)Lsoftware/amazon/awssdk/core/SdkField$Builder;
    1008: invokedynamic #157,  0            // InvokeDynamic #32:accept:()Ljava/util/function/BiConsumer;
    1013: invokestatic  #96                 // Method setter:(Ljava/util/function/BiConsumer;)Ljava/util/function/BiConsumer;
    1016: invokevirtual #97                 // Method software/amazon/awssdk/core/SdkField$Builder.setter:(Ljava/util/function/BiConsumer;)Lsoftware/amazon/awssdk/core/SdkField$Builder;
    1019: iconst_2
    1020: anewarray     #98                 // class software/amazon/awssdk/core/traits/Trait
    1023: dup
    1024: iconst_0
    1025: invokestatic  #99                 // Method software/amazon/awssdk/core/traits/LocationTrait.builder:()Lsoftware/amazon/awssdk/core/traits/LocationTrait$Builder;
    1028: getstatic     #100                // Field software/amazon/awssdk/core/protocol/MarshallLocation.PAYLOAD:Lsoftware/amazon/awssdk/core/protocol/MarshallLocation;
    1031: invokevirtual #101                // Method software/amazon/awssdk/core/traits/LocationTrait$Builder.location:(Lsoftware/amazon/awssdk/core/protocol/MarshallLocation;)Lsoftware/amazon/awssdk/core/traits/LocationTrait$Builder;
    1034: ldc           #76                 // String DimensionFilterList
    1036: invokevirtual #102                // Method software/amazon/awssdk/core/traits/LocationTrait$Builder.locationName:(Ljava/lang/String;)Lsoftware/amazon/awssdk/core/traits/LocationTrait$Builder;
    1039: invokevirtual #103                // Method software/amazon/awssdk/core/traits/LocationTrait$Builder.build:()Lsoftware/amazon/awssdk/core/traits/LocationTrait;
    1042: aastore
    1043: dup
    1044: iconst_1
    1045: invokestatic  #130                // Method software/amazon/awssdk/core/traits/ListTrait.builder:()Lsoftware/amazon/awssdk/core/traits/ListTrait$Builder;
    1048: aconst_null
    1049: invokevirtual #131                // Method software/amazon/awssdk/core/traits/ListTrait$Builder.memberLocationName:(Ljava/lang/String;)Lsoftware/amazon/awssdk/core/traits/ListTrait$Builder;
    1052: getstatic     #132                // Field software/amazon/awssdk/core/protocol/MarshallingType.SDK_POJO:Lsoftware/amazon/awssdk/core/protocol/MarshallingType;
    1055: invokestatic  #90                 // Method software/amazon/awssdk/core/SdkField.builder:(Lsoftware/amazon/awssdk/core/protocol/MarshallingType;)Lsoftware/amazon/awssdk/core/SdkField$Builder;
    1058: invokedynamic #158,  0            // InvokeDynamic #33:get:()Ljava/util/function/Supplier;
    1063: invokevirtual #134                // Method software/amazon/awssdk/core/SdkField$Builder.constructor:(Ljava/util/function/Supplier;)Lsoftware/amazon/awssdk/core/SdkField$Builder;
    1066: iconst_1
    1067: anewarray     #98                 // class software/amazon/awssdk/core/traits/Trait
    1070: dup
    1071: iconst_0
    1072: invokestatic  #99                 // Method software/amazon/awssdk/core/traits/LocationTrait.builder:()Lsoftware/amazon/awssdk/core/traits/LocationTrait$Builder;
    1075: getstatic     #100                // Field software/amazon/awssdk/core/protocol/MarshallLocation.PAYLOAD:Lsoftware/amazon/awssdk/core/protocol/MarshallLocation;
    1078: invokevirtual #101                // Method software/amazon/awssdk/core/traits/LocationTrait$Builder.location:(Lsoftware/amazon/awssdk/core/protocol/MarshallLocation;)Lsoftware/amazon/awssdk/core/traits/LocationTrait$Builder;
    1081: ldc           #135                // String member
    1083: invokevirtual #102                // Method software/amazon/awssdk/core/traits/LocationTrait$Builder.locationName:(Ljava/lang/String;)Lsoftware/amazon/awssdk/core/traits/LocationTrait$Builder;
    1086: invokevirtual #103                // Method software/amazon/awssdk/core/traits/LocationTrait$Builder.build:()Lsoftware/amazon/awssdk/core/traits/LocationTrait;
    1089: aastore
    1090: invokevirtual #104                // Method software/amazon/awssdk/core/SdkField$Builder.traits:([Lsoftware/amazon/awssdk/core/traits/Trait;)Lsoftware/amazon/awssdk/core/SdkField$Builder;
    1093: invokevirtual #105                // Method software/amazon/awssdk/core/SdkField$Builder.build:()Lsoftware/amazon/awssdk/core/SdkField;
    1096: invokevirtual #136                // Method software/amazon/awssdk/core/traits/ListTrait$Builder.memberFieldInfo:(Lsoftware/amazon/awssdk/core/SdkField;)Lsoftware/amazon/awssdk/core/traits/ListTrait$Builder;
    1099: invokevirtual #137                // Method software/amazon/awssdk/core/traits/ListTrait$Builder.build:()Lsoftware/amazon/awssdk/core/traits/ListTrait;
    1102: aastore
    1103: invokevirtual #104                // Method software/amazon/awssdk/core/SdkField$Builder.traits:([Lsoftware/amazon/awssdk/core/traits/Trait;)Lsoftware/amazon/awssdk/core/SdkField$Builder;
    1106: invokevirtual #105                // Method software/amazon/awssdk/core/SdkField$Builder.build:()Lsoftware/amazon/awssdk/core/SdkField;
    1109: putstatic     #159                // Field DIMENSION_FILTER_LIST_FIELD:Lsoftware/amazon/awssdk/core/SdkField;
    1112: bipush        14
    1114: anewarray     #160                // class software/amazon/awssdk/core/SdkField
    1117: dup
    1118: iconst_0
    1119: getstatic     #106                // Field METRIC_SET_ARN_FIELD:Lsoftware/amazon/awssdk/core/SdkField;
    1122: aastore
    1123: dup
    1124: iconst_1
    1125: getstatic     #109                // Field ANOMALY_DETECTOR_ARN_FIELD:Lsoftware/amazon/awssdk/core/SdkField;
    1128: aastore
    1129: dup
    1130: iconst_2
    1131: getstatic     #112                // Field METRIC_SET_NAME_FIELD:Lsoftware/amazon/awssdk/core/SdkField;
    1134: aastore
    1135: dup
    1136: iconst_3
    1137: getstatic     #115                // Field METRIC_SET_DESCRIPTION_FIELD:Lsoftware/amazon/awssdk/core/SdkField;
    1140: aastore
    1141: dup
    1142: iconst_4
    1143: getstatic     #119                // Field CREATION_TIME_FIELD:Lsoftware/amazon/awssdk/core/SdkField;
    1146: aastore
    1147: dup
    1148: iconst_5
    1149: getstatic     #122                // Field LAST_MODIFICATION_TIME_FIELD:Lsoftware/amazon/awssdk/core/SdkField;
    1152: aastore
    1153: dup
    1154: bipush        6
    1156: getstatic     #126                // Field OFFSET_FIELD:Lsoftware/amazon/awssdk/core/SdkField;
    1159: aastore
    1160: dup
    1161: bipush        7
    1163: getstatic     #138                // Field METRIC_LIST_FIELD:Lsoftware/amazon/awssdk/core/SdkField;
    1166: aastore
    1167: dup
    1168: bipush        8
    1170: getstatic     #142                // Field TIMESTAMP_COLUMN_FIELD:Lsoftware/amazon/awssdk/core/SdkField;
    1173: aastore
    1174: dup
    1175: bipush        9
    1177: getstatic     #145                // Field DIMENSION_LIST_FIELD:Lsoftware/amazon/awssdk/core/SdkField;
    1180: aastore
    1181: dup
    1182: bipush        10
    1184: getstatic     #148                // Field METRIC_SET_FREQUENCY_FIELD:Lsoftware/amazon/awssdk/core/SdkField;
    1187: aastore
    1188: dup
    1189: bipush        11
    1191: getstatic     #151                // Field TIMEZONE_FIELD:Lsoftware/amazon/awssdk/core/SdkField;
    1194: aastore
    1195: dup
    1196: bipush        12
    1198: getstatic     #155                // Field METRIC_SOURCE_FIELD:Lsoftware/amazon/awssdk/core/SdkField;
    1201: aastore
    1202: dup
    1203: bipush        13
    1205: getstatic     #159                // Field DIMENSION_FILTER_LIST_FIELD:Lsoftware/amazon/awssdk/core/SdkField;
    1208: aastore
    1209: invokestatic  #161                // Method java/util/Arrays.asList:([Ljava/lang/Object;)Ljava/util/List;
    1212: invokestatic  #162                // Method java/util/Collections.unmodifiableList:(Ljava/util/List;)Ljava/util/List;
    1215: putstatic     #1                  // Field SDK_FIELDS:Ljava/util/List;
    1218: return
}
