Compiled from "DetectedMetricSetConfig.java"
public interface software.amazon.awssdk.services.lookoutmetrics.model.DetectedMetricSetConfig$Builder extends software.amazon.awssdk.core.SdkPojo, software.amazon.awssdk.utils.builder.CopyableBuilder<software.amazon.awssdk.services.lookoutmetrics.model.DetectedMetricSetConfig$Builder, software.amazon.awssdk.services.lookoutmetrics.model.DetectedMetricSetConfig> {
  public abstract software.amazon.awssdk.services.lookoutmetrics.model.DetectedMetricSetConfig$Builder offset(software.amazon.awssdk.services.lookoutmetrics.model.DetectedField);

  public default software.amazon.awssdk.services.lookoutmetrics.model.DetectedMetricSetConfig$Builder offset(java.util.function.Consumer<software.amazon.awssdk.services.lookoutmetrics.model.DetectedField$Builder>);
    Code:
       0: aload_0
       1: invokestatic  #1                  // Method software/amazon/awssdk/services/lookoutmetrics/model/DetectedField.builder:()Lsoftware/amazon/awssdk/services/lookoutmetrics/model/DetectedField$Builder;
       4: aload_1
       5: invokeinterface #2,  2            // InterfaceMethod software/amazon/awssdk/services/lookoutmetrics/model/DetectedField$Builder.applyMutation:(Ljava/util/function/Consumer;)Lsoftware/amazon/awssdk/utils/builder/SdkBuilder;
      10: checkcast     #3                  // class software/amazon/awssdk/services/lookoutmetrics/model/DetectedField$Builder
      13: invokeinterface #4,  1            // InterfaceMethod software/amazon/awssdk/services/lookoutmetrics/model/DetectedField$Builder.build:()Ljava/lang/Object;
      18: checkcast     #5                  // class software/amazon/awssdk/services/lookoutmetrics/model/DetectedField
      21: invokeinterface #6,  2            // InterfaceMethod offset:(Lsoftware/amazon/awssdk/services/lookoutmetrics/model/DetectedField;)Lsoftware/amazon/awssdk/services/lookoutmetrics/model/DetectedMetricSetConfig$Builder;
      26: areturn

  public abstract software.amazon.awssdk.services.lookoutmetrics.model.DetectedMetricSetConfig$Builder metricSetFrequency(software.amazon.awssdk.services.lookoutmetrics.model.DetectedField);

  public default software.amazon.awssdk.services.lookoutmetrics.model.DetectedMetricSetConfig$Builder metricSetFrequency(java.util.function.Consumer<software.amazon.awssdk.services.lookoutmetrics.model.DetectedField$Builder>);
    Code:
       0: aload_0
       1: invokestatic  #1                  // Method software/amazon/awssdk/services/lookoutmetrics/model/DetectedField.builder:()Lsoftware/amazon/awssdk/services/lookoutmetrics/model/DetectedField$Builder;
       4: aload_1
       5: invokeinterface #2,  2            // InterfaceMethod software/amazon/awssdk/services/lookoutmetrics/model/DetectedField$Builder.applyMutation:(Ljava/util/function/Consumer;)Lsoftware/amazon/awssdk/utils/builder/SdkBuilder;
      10: checkcast     #3                  // class software/amazon/awssdk/services/lookoutmetrics/model/DetectedField$Builder
      13: invokeinterface #4,  1            // InterfaceMethod software/amazon/awssdk/services/lookoutmetrics/model/DetectedField$Builder.build:()Ljava/lang/Object;
      18: checkcast     #5                  // class software/amazon/awssdk/services/lookoutmetrics/model/DetectedField
      21: invokeinterface #7,  2            // InterfaceMethod metricSetFrequency:(Lsoftware/amazon/awssdk/services/lookoutmetrics/model/DetectedField;)Lsoftware/amazon/awssdk/services/lookoutmetrics/model/DetectedMetricSetConfig$Builder;
      26: areturn

  public abstract software.amazon.awssdk.services.lookoutmetrics.model.DetectedMetricSetConfig$Builder metricSource(software.amazon.awssdk.services.lookoutmetrics.model.DetectedMetricSource);

  public default software.amazon.awssdk.services.lookoutmetrics.model.DetectedMetricSetConfig$Builder metricSource(java.util.function.Consumer<software.amazon.awssdk.services.lookoutmetrics.model.DetectedMetricSource$Builder>);
    Code:
       0: aload_0
       1: invokestatic  #8                  // Method software/amazon/awssdk/services/lookoutmetrics/model/DetectedMetricSource.builder:()Lsoftware/amazon/awssdk/services/lookoutmetrics/model/DetectedMetricSource$Builder;
       4: aload_1
       5: invokeinterface #9,  2            // InterfaceMethod software/amazon/awssdk/services/lookoutmetrics/model/DetectedMetricSource$Builder.applyMutation:(Ljava/util/function/Consumer;)Lsoftware/amazon/awssdk/utils/builder/SdkBuilder;
      10: checkcast     #10                 // class software/amazon/awssdk/services/lookoutmetrics/model/DetectedMetricSource$Builder
      13: invokeinterface #11,  1           // InterfaceMethod software/amazon/awssdk/services/lookoutmetrics/model/DetectedMetricSource$Builder.build:()Ljava/lang/Object;
      18: checkcast     #12                 // class software/amazon/awssdk/services/lookoutmetrics/model/DetectedMetricSource
      21: invokeinterface #13,  2           // InterfaceMethod metricSource:(Lsoftware/amazon/awssdk/services/lookoutmetrics/model/DetectedMetricSource;)Lsoftware/amazon/awssdk/services/lookoutmetrics/model/DetectedMetricSetConfig$Builder;
      26: areturn
}
