Compiled from "DetectedS3SourceConfig.java"
final class software.amazon.awssdk.services.lookoutmetrics.model.DetectedS3SourceConfig$BuilderImpl implements software.amazon.awssdk.services.lookoutmetrics.model.DetectedS3SourceConfig$Builder {
  private software.amazon.awssdk.services.lookoutmetrics.model.DetectedFileFormatDescriptor fileFormatDescriptor;

  private software.amazon.awssdk.services.lookoutmetrics.model.DetectedS3SourceConfig$BuilderImpl();
    Code:
       0: aload_0
       1: invokespecial #4                  // Method java/lang/Object."<init>":()V
       4: return

  private software.amazon.awssdk.services.lookoutmetrics.model.DetectedS3SourceConfig$BuilderImpl(software.amazon.awssdk.services.lookoutmetrics.model.DetectedS3SourceConfig);
    Code:
       0: aload_0
       1: invokespecial #4                  // Method java/lang/Object."<init>":()V
       4: aload_0
       5: aload_1
       6: invokestatic  #5                  // Method software/amazon/awssdk/services/lookoutmetrics/model/DetectedS3SourceConfig.access$300:(Lsoftware/amazon/awssdk/services/lookoutmetrics/model/DetectedS3SourceConfig;)Lsoftware/amazon/awssdk/services/lookoutmetrics/model/DetectedFileFormatDescriptor;
       9: invokevirtual #6                  // Method fileFormatDescriptor:(Lsoftware/amazon/awssdk/services/lookoutmetrics/model/DetectedFileFormatDescriptor;)Lsoftware/amazon/awssdk/services/lookoutmetrics/model/DetectedS3SourceConfig$Builder;
      12: pop
      13: return

  public final software.amazon.awssdk.services.lookoutmetrics.model.DetectedFileFormatDescriptor$Builder getFileFormatDescriptor();
    Code:
       0: aload_0
       1: getfield      #3                  // Field fileFormatDescriptor:Lsoftware/amazon/awssdk/services/lookoutmetrics/model/DetectedFileFormatDescriptor;
       4: ifnull        17
       7: aload_0
       8: getfield      #3                  // Field fileFormatDescriptor:Lsoftware/amazon/awssdk/services/lookoutmetrics/model/DetectedFileFormatDescriptor;
      11: invokevirtual #7                  // Method software/amazon/awssdk/services/lookoutmetrics/model/DetectedFileFormatDescriptor.toBuilder:()Lsoftware/amazon/awssdk/services/lookoutmetrics/model/DetectedFileFormatDescriptor$Builder;
      14: goto          18
      17: aconst_null
      18: areturn

  public final void setFileFormatDescriptor(software.amazon.awssdk.services.lookoutmetrics.model.DetectedFileFormatDescriptor$BuilderImpl);
    Code:
       0: aload_0
       1: aload_1
       2: ifnull        12
       5: aload_1
       6: invokevirtual #8                  // Method software/amazon/awssdk/services/lookoutmetrics/model/DetectedFileFormatDescriptor$BuilderImpl.build:()Lsoftware/amazon/awssdk/services/lookoutmetrics/model/DetectedFileFormatDescriptor;
       9: goto          13
      12: aconst_null
      13: putfield      #3                  // Field fileFormatDescriptor:Lsoftware/amazon/awssdk/services/lookoutmetrics/model/DetectedFileFormatDescriptor;
      16: return

  public final software.amazon.awssdk.services.lookoutmetrics.model.DetectedS3SourceConfig$Builder fileFormatDescriptor(software.amazon.awssdk.services.lookoutmetrics.model.DetectedFileFormatDescriptor);
    Code:
       0: aload_0
       1: aload_1
       2: putfield      #3                  // Field fileFormatDescriptor:Lsoftware/amazon/awssdk/services/lookoutmetrics/model/DetectedFileFormatDescriptor;
       5: aload_0
       6: areturn

  public software.amazon.awssdk.services.lookoutmetrics.model.DetectedS3SourceConfig build();
    Code:
       0: new           #9                  // class software/amazon/awssdk/services/lookoutmetrics/model/DetectedS3SourceConfig
       3: dup
       4: aload_0
       5: aconst_null
       6: invokespecial #10                 // Method software/amazon/awssdk/services/lookoutmetrics/model/DetectedS3SourceConfig."<init>":(Lsoftware/amazon/awssdk/services/lookoutmetrics/model/DetectedS3SourceConfig$BuilderImpl;Lsoftware/amazon/awssdk/services/lookoutmetrics/model/DetectedS3SourceConfig$1;)V
       9: areturn

  public java.util.List<software.amazon.awssdk.core.SdkField<?>> sdkFields();
    Code:
       0: invokestatic  #11                 // Method software/amazon/awssdk/services/lookoutmetrics/model/DetectedS3SourceConfig.access$500:()Ljava/util/List;
       3: areturn

  public java.lang.Object build();
    Code:
       0: aload_0
       1: invokevirtual #12                 // Method build:()Lsoftware/amazon/awssdk/services/lookoutmetrics/model/DetectedS3SourceConfig;
       4: areturn

  static software.amazon.awssdk.services.lookoutmetrics.model.DetectedFileFormatDescriptor access$000(software.amazon.awssdk.services.lookoutmetrics.model.DetectedS3SourceConfig$BuilderImpl);
    Code:
       0: aload_0
       1: getfield      #3                  // Field fileFormatDescriptor:Lsoftware/amazon/awssdk/services/lookoutmetrics/model/DetectedFileFormatDescriptor;
       4: areturn

  software.amazon.awssdk.services.lookoutmetrics.model.DetectedS3SourceConfig$BuilderImpl(software.amazon.awssdk.services.lookoutmetrics.model.DetectedS3SourceConfig, software.amazon.awssdk.services.lookoutmetrics.model.DetectedS3SourceConfig$1);
    Code:
       0: aload_0
       1: aload_1
       2: invokespecial #2                  // Method "<init>":(Lsoftware/amazon/awssdk/services/lookoutmetrics/model/DetectedS3SourceConfig;)V
       5: return

  software.amazon.awssdk.services.lookoutmetrics.model.DetectedS3SourceConfig$BuilderImpl(software.amazon.awssdk.services.lookoutmetrics.model.DetectedS3SourceConfig$1);
    Code:
       0: aload_0
       1: invokespecial #1                  // Method "<init>":()V
       4: return
}
