Compiled from "GetFeedbackRequest.java"
final class software.amazon.awssdk.services.lookoutmetrics.model.GetFeedbackRequest$BuilderImpl extends software.amazon.awssdk.services.lookoutmetrics.model.LookoutMetricsRequest$BuilderImpl implements software.amazon.awssdk.services.lookoutmetrics.model.GetFeedbackRequest$Builder {
  private java.lang.String anomalyDetectorArn;

  private software.amazon.awssdk.services.lookoutmetrics.model.AnomalyGroupTimeSeries anomalyGroupTimeSeriesFeedback;

  private java.lang.Integer maxResults;

  private java.lang.String nextToken;

  private software.amazon.awssdk.services.lookoutmetrics.model.GetFeedbackRequest$BuilderImpl();
    Code:
       0: aload_0
       1: invokespecial #7                  // Method software/amazon/awssdk/services/lookoutmetrics/model/LookoutMetricsRequest$BuilderImpl."<init>":()V
       4: return

  private software.amazon.awssdk.services.lookoutmetrics.model.GetFeedbackRequest$BuilderImpl(software.amazon.awssdk.services.lookoutmetrics.model.GetFeedbackRequest);
    Code:
       0: aload_0
       1: aload_1
       2: invokespecial #8                  // Method software/amazon/awssdk/services/lookoutmetrics/model/LookoutMetricsRequest$BuilderImpl."<init>":(Lsoftware/amazon/awssdk/services/lookoutmetrics/model/LookoutMetricsRequest;)V
       5: aload_0
       6: aload_1
       7: invokestatic  #9                  // Method software/amazon/awssdk/services/lookoutmetrics/model/GetFeedbackRequest.access$600:(Lsoftware/amazon/awssdk/services/lookoutmetrics/model/GetFeedbackRequest;)Ljava/lang/String;
      10: invokevirtual #10                 // Method anomalyDetectorArn:(Ljava/lang/String;)Lsoftware/amazon/awssdk/services/lookoutmetrics/model/GetFeedbackRequest$Builder;
      13: pop
      14: aload_0
      15: aload_1
      16: invokestatic  #11                 // Method software/amazon/awssdk/services/lookoutmetrics/model/GetFeedbackRequest.access$700:(Lsoftware/amazon/awssdk/services/lookoutmetrics/model/GetFeedbackRequest;)Lsoftware/amazon/awssdk/services/lookoutmetrics/model/AnomalyGroupTimeSeries;
      19: invokevirtual #12                 // Method anomalyGroupTimeSeriesFeedback:(Lsoftware/amazon/awssdk/services/lookoutmetrics/model/AnomalyGroupTimeSeries;)Lsoftware/amazon/awssdk/services/lookoutmetrics/model/GetFeedbackRequest$Builder;
      22: pop
      23: aload_0
      24: aload_1
      25: invokestatic  #13                 // Method software/amazon/awssdk/services/lookoutmetrics/model/GetFeedbackRequest.access$800:(Lsoftware/amazon/awssdk/services/lookoutmetrics/model/GetFeedbackRequest;)Ljava/lang/Integer;
      28: invokevirtual #14                 // Method maxResults:(Ljava/lang/Integer;)Lsoftware/amazon/awssdk/services/lookoutmetrics/model/GetFeedbackRequest$Builder;
      31: pop
      32: aload_0
      33: aload_1
      34: invokestatic  #15                 // Method software/amazon/awssdk/services/lookoutmetrics/model/GetFeedbackRequest.access$900:(Lsoftware/amazon/awssdk/services/lookoutmetrics/model/GetFeedbackRequest;)Ljava/lang/String;
      37: invokevirtual #16                 // Method nextToken:(Ljava/lang/String;)Lsoftware/amazon/awssdk/services/lookoutmetrics/model/GetFeedbackRequest$Builder;
      40: pop
      41: return

  public final java.lang.String getAnomalyDetectorArn();
    Code:
       0: aload_0
       1: getfield      #6                  // Field anomalyDetectorArn:Ljava/lang/String;
       4: areturn

  public final void setAnomalyDetectorArn(java.lang.String);
    Code:
       0: aload_0
       1: aload_1
       2: putfield      #6                  // Field anomalyDetectorArn:Ljava/lang/String;
       5: return

  public final software.amazon.awssdk.services.lookoutmetrics.model.GetFeedbackRequest$Builder anomalyDetectorArn(java.lang.String);
    Code:
       0: aload_0
       1: aload_1
       2: putfield      #6                  // Field anomalyDetectorArn:Ljava/lang/String;
       5: aload_0
       6: areturn

  public final software.amazon.awssdk.services.lookoutmetrics.model.AnomalyGroupTimeSeries$Builder getAnomalyGroupTimeSeriesFeedback();
    Code:
       0: aload_0
       1: getfield      #5                  // Field anomalyGroupTimeSeriesFeedback:Lsoftware/amazon/awssdk/services/lookoutmetrics/model/AnomalyGroupTimeSeries;
       4: ifnull        17
       7: aload_0
       8: getfield      #5                  // Field anomalyGroupTimeSeriesFeedback:Lsoftware/amazon/awssdk/services/lookoutmetrics/model/AnomalyGroupTimeSeries;
      11: invokevirtual #17                 // Method software/amazon/awssdk/services/lookoutmetrics/model/AnomalyGroupTimeSeries.toBuilder:()Lsoftware/amazon/awssdk/services/lookoutmetrics/model/AnomalyGroupTimeSeries$Builder;
      14: goto          18
      17: aconst_null
      18: areturn

  public final void setAnomalyGroupTimeSeriesFeedback(software.amazon.awssdk.services.lookoutmetrics.model.AnomalyGroupTimeSeries$BuilderImpl);
    Code:
       0: aload_0
       1: aload_1
       2: ifnull        12
       5: aload_1
       6: invokevirtual #18                 // Method software/amazon/awssdk/services/lookoutmetrics/model/AnomalyGroupTimeSeries$BuilderImpl.build:()Lsoftware/amazon/awssdk/services/lookoutmetrics/model/AnomalyGroupTimeSeries;
       9: goto          13
      12: aconst_null
      13: putfield      #5                  // Field anomalyGroupTimeSeriesFeedback:Lsoftware/amazon/awssdk/services/lookoutmetrics/model/AnomalyGroupTimeSeries;
      16: return

  public final software.amazon.awssdk.services.lookoutmetrics.model.GetFeedbackRequest$Builder anomalyGroupTimeSeriesFeedback(software.amazon.awssdk.services.lookoutmetrics.model.AnomalyGroupTimeSeries);
    Code:
       0: aload_0
       1: aload_1
       2: putfield      #5                  // Field anomalyGroupTimeSeriesFeedback:Lsoftware/amazon/awssdk/services/lookoutmetrics/model/AnomalyGroupTimeSeries;
       5: aload_0
       6: areturn

  public final java.lang.Integer getMaxResults();
    Code:
       0: aload_0
       1: getfield      #4                  // Field maxResults:Ljava/lang/Integer;
       4: areturn

  public final void setMaxResults(java.lang.Integer);
    Code:
       0: aload_0
       1: aload_1
       2: putfield      #4                  // Field maxResults:Ljava/lang/Integer;
       5: return

  public final software.amazon.awssdk.services.lookoutmetrics.model.GetFeedbackRequest$Builder maxResults(java.lang.Integer);
    Code:
       0: aload_0
       1: aload_1
       2: putfield      #4                  // Field maxResults:Ljava/lang/Integer;
       5: aload_0
       6: areturn

  public final java.lang.String getNextToken();
    Code:
       0: aload_0
       1: getfield      #3                  // Field nextToken:Ljava/lang/String;
       4: areturn

  public final void setNextToken(java.lang.String);
    Code:
       0: aload_0
       1: aload_1
       2: putfield      #3                  // Field nextToken:Ljava/lang/String;
       5: return

  public final software.amazon.awssdk.services.lookoutmetrics.model.GetFeedbackRequest$Builder nextToken(java.lang.String);
    Code:
       0: aload_0
       1: aload_1
       2: putfield      #3                  // Field nextToken:Ljava/lang/String;
       5: aload_0
       6: areturn

  public software.amazon.awssdk.services.lookoutmetrics.model.GetFeedbackRequest$Builder overrideConfiguration(software.amazon.awssdk.awscore.AwsRequestOverrideConfiguration);
    Code:
       0: aload_0
       1: aload_1
       2: invokespecial #19                 // Method software/amazon/awssdk/services/lookoutmetrics/model/LookoutMetricsRequest$BuilderImpl.overrideConfiguration:(Lsoftware/amazon/awssdk/awscore/AwsRequestOverrideConfiguration;)Lsoftware/amazon/awssdk/awscore/AwsRequest$Builder;
       5: pop
       6: aload_0
       7: areturn

  public software.amazon.awssdk.services.lookoutmetrics.model.GetFeedbackRequest$Builder overrideConfiguration(java.util.function.Consumer<software.amazon.awssdk.awscore.AwsRequestOverrideConfiguration$Builder>);
    Code:
       0: aload_0
       1: aload_1
       2: invokespecial #20                 // Method software/amazon/awssdk/services/lookoutmetrics/model/LookoutMetricsRequest$BuilderImpl.overrideConfiguration:(Ljava/util/function/Consumer;)Lsoftware/amazon/awssdk/awscore/AwsRequest$Builder;
       5: pop
       6: aload_0
       7: areturn

  public software.amazon.awssdk.services.lookoutmetrics.model.GetFeedbackRequest build();
    Code:
       0: new           #21                 // class software/amazon/awssdk/services/lookoutmetrics/model/GetFeedbackRequest
       3: dup
       4: aload_0
       5: aconst_null
       6: invokespecial #22                 // Method software/amazon/awssdk/services/lookoutmetrics/model/GetFeedbackRequest."<init>":(Lsoftware/amazon/awssdk/services/lookoutmetrics/model/GetFeedbackRequest$BuilderImpl;Lsoftware/amazon/awssdk/services/lookoutmetrics/model/GetFeedbackRequest$1;)V
       9: areturn

  public java.util.List<software.amazon.awssdk.core.SdkField<?>> sdkFields();
    Code:
       0: invokestatic  #23                 // Method software/amazon/awssdk/services/lookoutmetrics/model/GetFeedbackRequest.access$1100:()Ljava/util/List;
       3: areturn

  public software.amazon.awssdk.services.lookoutmetrics.model.LookoutMetricsRequest build();
    Code:
       0: aload_0
       1: invokevirtual #24                 // Method build:()Lsoftware/amazon/awssdk/services/lookoutmetrics/model/GetFeedbackRequest;
       4: areturn

  public software.amazon.awssdk.awscore.AwsRequest build();
    Code:
       0: aload_0
       1: invokevirtual #24                 // Method build:()Lsoftware/amazon/awssdk/services/lookoutmetrics/model/GetFeedbackRequest;
       4: areturn

  public software.amazon.awssdk.awscore.AwsRequest$Builder overrideConfiguration(java.util.function.Consumer);
    Code:
       0: aload_0
       1: aload_1
       2: invokevirtual #25                 // Method overrideConfiguration:(Ljava/util/function/Consumer;)Lsoftware/amazon/awssdk/services/lookoutmetrics/model/GetFeedbackRequest$Builder;
       5: areturn

  public software.amazon.awssdk.awscore.AwsRequest$Builder overrideConfiguration(software.amazon.awssdk.awscore.AwsRequestOverrideConfiguration);
    Code:
       0: aload_0
       1: aload_1
       2: invokevirtual #26                 // Method overrideConfiguration:(Lsoftware/amazon/awssdk/awscore/AwsRequestOverrideConfiguration;)Lsoftware/amazon/awssdk/services/lookoutmetrics/model/GetFeedbackRequest$Builder;
       5: areturn

  public software.amazon.awssdk.core.SdkRequest build();
    Code:
       0: aload_0
       1: invokevirtual #24                 // Method build:()Lsoftware/amazon/awssdk/services/lookoutmetrics/model/GetFeedbackRequest;
       4: areturn

  public java.lang.Object build();
    Code:
       0: aload_0
       1: invokevirtual #24                 // Method build:()Lsoftware/amazon/awssdk/services/lookoutmetrics/model/GetFeedbackRequest;
       4: areturn

  static java.lang.String access$000(software.amazon.awssdk.services.lookoutmetrics.model.GetFeedbackRequest$BuilderImpl);
    Code:
       0: aload_0
       1: getfield      #6                  // Field anomalyDetectorArn:Ljava/lang/String;
       4: areturn

  static software.amazon.awssdk.services.lookoutmetrics.model.AnomalyGroupTimeSeries access$100(software.amazon.awssdk.services.lookoutmetrics.model.GetFeedbackRequest$BuilderImpl);
    Code:
       0: aload_0
       1: getfield      #5                  // Field anomalyGroupTimeSeriesFeedback:Lsoftware/amazon/awssdk/services/lookoutmetrics/model/AnomalyGroupTimeSeries;
       4: areturn

  static java.lang.Integer access$200(software.amazon.awssdk.services.lookoutmetrics.model.GetFeedbackRequest$BuilderImpl);
    Code:
       0: aload_0
       1: getfield      #4                  // Field maxResults:Ljava/lang/Integer;
       4: areturn

  static java.lang.String access$300(software.amazon.awssdk.services.lookoutmetrics.model.GetFeedbackRequest$BuilderImpl);
    Code:
       0: aload_0
       1: getfield      #3                  // Field nextToken:Ljava/lang/String;
       4: areturn

  software.amazon.awssdk.services.lookoutmetrics.model.GetFeedbackRequest$BuilderImpl(software.amazon.awssdk.services.lookoutmetrics.model.GetFeedbackRequest, software.amazon.awssdk.services.lookoutmetrics.model.GetFeedbackRequest$1);
    Code:
       0: aload_0
       1: aload_1
       2: invokespecial #2                  // Method "<init>":(Lsoftware/amazon/awssdk/services/lookoutmetrics/model/GetFeedbackRequest;)V
       5: return

  software.amazon.awssdk.services.lookoutmetrics.model.GetFeedbackRequest$BuilderImpl(software.amazon.awssdk.services.lookoutmetrics.model.GetFeedbackRequest$1);
    Code:
       0: aload_0
       1: invokespecial #1                  // Method "<init>":()V
       4: return
}
