Compiled from "GetFeedbackRequest.java"
public interface software.amazon.awssdk.services.lookoutmetrics.model.GetFeedbackRequest$Builder extends software.amazon.awssdk.services.lookoutmetrics.model.LookoutMetricsRequest$Builder, software.amazon.awssdk.core.SdkPojo, software.amazon.awssdk.utils.builder.CopyableBuilder<software.amazon.awssdk.services.lookoutmetrics.model.GetFeedbackRequest$Builder, software.amazon.awssdk.services.lookoutmetrics.model.GetFeedbackRequest> {
  public abstract software.amazon.awssdk.services.lookoutmetrics.model.GetFeedbackRequest$Builder anomalyDetectorArn(java.lang.String);

  public abstract software.amazon.awssdk.services.lookoutmetrics.model.GetFeedbackRequest$Builder anomalyGroupTimeSeriesFeedback(software.amazon.awssdk.services.lookoutmetrics.model.AnomalyGroupTimeSeries);

  public default software.amazon.awssdk.services.lookoutmetrics.model.GetFeedbackRequest$Builder anomalyGroupTimeSeriesFeedback(java.util.function.Consumer<software.amazon.awssdk.services.lookoutmetrics.model.AnomalyGroupTimeSeries$Builder>);
    Code:
       0: aload_0
       1: invokestatic  #1                  // Method software/amazon/awssdk/services/lookoutmetrics/model/AnomalyGroupTimeSeries.builder:()Lsoftware/amazon/awssdk/services/lookoutmetrics/model/AnomalyGroupTimeSeries$Builder;
       4: aload_1
       5: invokeinterface #2,  2            // InterfaceMethod software/amazon/awssdk/services/lookoutmetrics/model/AnomalyGroupTimeSeries$Builder.applyMutation:(Ljava/util/function/Consumer;)Lsoftware/amazon/awssdk/utils/builder/SdkBuilder;
      10: checkcast     #3                  // class software/amazon/awssdk/services/lookoutmetrics/model/AnomalyGroupTimeSeries$Builder
      13: invokeinterface #4,  1            // InterfaceMethod software/amazon/awssdk/services/lookoutmetrics/model/AnomalyGroupTimeSeries$Builder.build:()Ljava/lang/Object;
      18: checkcast     #5                  // class software/amazon/awssdk/services/lookoutmetrics/model/AnomalyGroupTimeSeries
      21: invokeinterface #6,  2            // InterfaceMethod anomalyGroupTimeSeriesFeedback:(Lsoftware/amazon/awssdk/services/lookoutmetrics/model/AnomalyGroupTimeSeries;)Lsoftware/amazon/awssdk/services/lookoutmetrics/model/GetFeedbackRequest$Builder;
      26: areturn

  public abstract software.amazon.awssdk.services.lookoutmetrics.model.GetFeedbackRequest$Builder maxResults(java.lang.Integer);

  public abstract software.amazon.awssdk.services.lookoutmetrics.model.GetFeedbackRequest$Builder nextToken(java.lang.String);

  public abstract software.amazon.awssdk.services.lookoutmetrics.model.GetFeedbackRequest$Builder overrideConfiguration(software.amazon.awssdk.awscore.AwsRequestOverrideConfiguration);

  public abstract software.amazon.awssdk.services.lookoutmetrics.model.GetFeedbackRequest$Builder overrideConfiguration(java.util.function.Consumer<software.amazon.awssdk.awscore.AwsRequestOverrideConfiguration$Builder>);

  public default software.amazon.awssdk.awscore.AwsRequest$Builder overrideConfiguration(java.util.function.Consumer);
    Code:
       0: aload_0
       1: aload_1
       2: invokeinterface #7,  2            // InterfaceMethod overrideConfiguration:(Ljava/util/function/Consumer;)Lsoftware/amazon/awssdk/services/lookoutmetrics/model/GetFeedbackRequest$Builder;
       7: areturn

  public default software.amazon.awssdk.awscore.AwsRequest$Builder overrideConfiguration(software.amazon.awssdk.awscore.AwsRequestOverrideConfiguration);
    Code:
       0: aload_0
       1: aload_1
       2: invokeinterface #8,  2            // InterfaceMethod overrideConfiguration:(Lsoftware/amazon/awssdk/awscore/AwsRequestOverrideConfiguration;)Lsoftware/amazon/awssdk/services/lookoutmetrics/model/GetFeedbackRequest$Builder;
       7: areturn
}
