Compiled from "ListAnomalyGroupSummariesResponse.java"
final class software.amazon.awssdk.services.lookoutmetrics.model.ListAnomalyGroupSummariesResponse$BuilderImpl extends software.amazon.awssdk.services.lookoutmetrics.model.LookoutMetricsResponse$BuilderImpl implements software.amazon.awssdk.services.lookoutmetrics.model.ListAnomalyGroupSummariesResponse$Builder {
  private java.util.List<software.amazon.awssdk.services.lookoutmetrics.model.AnomalyGroupSummary> anomalyGroupSummaryList;

  private software.amazon.awssdk.services.lookoutmetrics.model.AnomalyGroupStatistics anomalyGroupStatistics;

  private java.lang.String nextToken;

  private software.amazon.awssdk.services.lookoutmetrics.model.ListAnomalyGroupSummariesResponse$BuilderImpl();
    Code:
       0: aload_0
       1: invokespecial #6                  // Method software/amazon/awssdk/services/lookoutmetrics/model/LookoutMetricsResponse$BuilderImpl."<init>":()V
       4: aload_0
       5: invokestatic  #7                  // Method software/amazon/awssdk/core/util/DefaultSdkAutoConstructList.getInstance:()Lsoftware/amazon/awssdk/core/util/DefaultSdkAutoConstructList;
       8: putfield      #5                  // Field anomalyGroupSummaryList:Ljava/util/List;
      11: return

  private software.amazon.awssdk.services.lookoutmetrics.model.ListAnomalyGroupSummariesResponse$BuilderImpl(software.amazon.awssdk.services.lookoutmetrics.model.ListAnomalyGroupSummariesResponse);
    Code:
       0: aload_0
       1: aload_1
       2: invokespecial #8                  // Method software/amazon/awssdk/services/lookoutmetrics/model/LookoutMetricsResponse$BuilderImpl."<init>":(Lsoftware/amazon/awssdk/services/lookoutmetrics/model/LookoutMetricsResponse;)V
       5: aload_0
       6: invokestatic  #7                  // Method software/amazon/awssdk/core/util/DefaultSdkAutoConstructList.getInstance:()Lsoftware/amazon/awssdk/core/util/DefaultSdkAutoConstructList;
       9: putfield      #5                  // Field anomalyGroupSummaryList:Ljava/util/List;
      12: aload_0
      13: aload_1
      14: invokestatic  #9                  // Method software/amazon/awssdk/services/lookoutmetrics/model/ListAnomalyGroupSummariesResponse.access$500:(Lsoftware/amazon/awssdk/services/lookoutmetrics/model/ListAnomalyGroupSummariesResponse;)Ljava/util/List;
      17: invokevirtual #10                 // Method anomalyGroupSummaryList:(Ljava/util/Collection;)Lsoftware/amazon/awssdk/services/lookoutmetrics/model/ListAnomalyGroupSummariesResponse$Builder;
      20: pop
      21: aload_0
      22: aload_1
      23: invokestatic  #11                 // Method software/amazon/awssdk/services/lookoutmetrics/model/ListAnomalyGroupSummariesResponse.access$600:(Lsoftware/amazon/awssdk/services/lookoutmetrics/model/ListAnomalyGroupSummariesResponse;)Lsoftware/amazon/awssdk/services/lookoutmetrics/model/AnomalyGroupStatistics;
      26: invokevirtual #12                 // Method anomalyGroupStatistics:(Lsoftware/amazon/awssdk/services/lookoutmetrics/model/AnomalyGroupStatistics;)Lsoftware/amazon/awssdk/services/lookoutmetrics/model/ListAnomalyGroupSummariesResponse$Builder;
      29: pop
      30: aload_0
      31: aload_1
      32: invokestatic  #13                 // Method software/amazon/awssdk/services/lookoutmetrics/model/ListAnomalyGroupSummariesResponse.access$700:(Lsoftware/amazon/awssdk/services/lookoutmetrics/model/ListAnomalyGroupSummariesResponse;)Ljava/lang/String;
      35: invokevirtual #14                 // Method nextToken:(Ljava/lang/String;)Lsoftware/amazon/awssdk/services/lookoutmetrics/model/ListAnomalyGroupSummariesResponse$Builder;
      38: pop
      39: return

  public final java.util.List<software.amazon.awssdk.services.lookoutmetrics.model.AnomalyGroupSummary$Builder> getAnomalyGroupSummaryList();
    Code:
       0: aload_0
       1: getfield      #5                  // Field anomalyGroupSummaryList:Ljava/util/List;
       4: invokestatic  #15                 // Method software/amazon/awssdk/services/lookoutmetrics/model/AnomalyGroupSummaryListCopier.copyToBuilder:(Ljava/util/Collection;)Ljava/util/List;
       7: astore_1
       8: aload_1
       9: instanceof    #16                 // class software/amazon/awssdk/core/util/SdkAutoConstructList
      12: ifeq          17
      15: aconst_null
      16: areturn
      17: aload_1
      18: areturn

  public final void setAnomalyGroupSummaryList(java.util.Collection<software.amazon.awssdk.services.lookoutmetrics.model.AnomalyGroupSummary$BuilderImpl>);
    Code:
       0: aload_0
       1: aload_1
       2: invokestatic  #17                 // Method software/amazon/awssdk/services/lookoutmetrics/model/AnomalyGroupSummaryListCopier.copyFromBuilder:(Ljava/util/Collection;)Ljava/util/List;
       5: putfield      #5                  // Field anomalyGroupSummaryList:Ljava/util/List;
       8: return

  public final software.amazon.awssdk.services.lookoutmetrics.model.ListAnomalyGroupSummariesResponse$Builder anomalyGroupSummaryList(java.util.Collection<software.amazon.awssdk.services.lookoutmetrics.model.AnomalyGroupSummary>);
    Code:
       0: aload_0
       1: aload_1
       2: invokestatic  #18                 // Method software/amazon/awssdk/services/lookoutmetrics/model/AnomalyGroupSummaryListCopier.copy:(Ljava/util/Collection;)Ljava/util/List;
       5: putfield      #5                  // Field anomalyGroupSummaryList:Ljava/util/List;
       8: aload_0
       9: areturn

  public final software.amazon.awssdk.services.lookoutmetrics.model.ListAnomalyGroupSummariesResponse$Builder anomalyGroupSummaryList(software.amazon.awssdk.services.lookoutmetrics.model.AnomalyGroupSummary...);
    Code:
       0: aload_0
       1: aload_1
       2: invokestatic  #19                 // Method java/util/Arrays.asList:([Ljava/lang/Object;)Ljava/util/List;
       5: invokevirtual #10                 // Method anomalyGroupSummaryList:(Ljava/util/Collection;)Lsoftware/amazon/awssdk/services/lookoutmetrics/model/ListAnomalyGroupSummariesResponse$Builder;
       8: pop
       9: aload_0
      10: areturn

  public final software.amazon.awssdk.services.lookoutmetrics.model.ListAnomalyGroupSummariesResponse$Builder anomalyGroupSummaryList(java.util.function.Consumer<software.amazon.awssdk.services.lookoutmetrics.model.AnomalyGroupSummary$Builder>...);
    Code:
       0: aload_0
       1: aload_1
       2: invokestatic  #20                 // InterfaceMethod java/util/stream/Stream.of:([Ljava/lang/Object;)Ljava/util/stream/Stream;
       5: invokedynamic #21,  0             // InvokeDynamic #0:apply:()Ljava/util/function/Function;
      10: invokeinterface #22,  2           // InterfaceMethod java/util/stream/Stream.map:(Ljava/util/function/Function;)Ljava/util/stream/Stream;
      15: invokestatic  #23                 // Method java/util/stream/Collectors.toList:()Ljava/util/stream/Collector;
      18: invokeinterface #24,  2           // InterfaceMethod java/util/stream/Stream.collect:(Ljava/util/stream/Collector;)Ljava/lang/Object;
      23: checkcast     #25                 // class java/util/Collection
      26: invokevirtual #10                 // Method anomalyGroupSummaryList:(Ljava/util/Collection;)Lsoftware/amazon/awssdk/services/lookoutmetrics/model/ListAnomalyGroupSummariesResponse$Builder;
      29: pop
      30: aload_0
      31: areturn

  public final software.amazon.awssdk.services.lookoutmetrics.model.AnomalyGroupStatistics$Builder getAnomalyGroupStatistics();
    Code:
       0: aload_0
       1: getfield      #4                  // Field anomalyGroupStatistics:Lsoftware/amazon/awssdk/services/lookoutmetrics/model/AnomalyGroupStatistics;
       4: ifnull        17
       7: aload_0
       8: getfield      #4                  // Field anomalyGroupStatistics:Lsoftware/amazon/awssdk/services/lookoutmetrics/model/AnomalyGroupStatistics;
      11: invokevirtual #26                 // Method software/amazon/awssdk/services/lookoutmetrics/model/AnomalyGroupStatistics.toBuilder:()Lsoftware/amazon/awssdk/services/lookoutmetrics/model/AnomalyGroupStatistics$Builder;
      14: goto          18
      17: aconst_null
      18: areturn

  public final void setAnomalyGroupStatistics(software.amazon.awssdk.services.lookoutmetrics.model.AnomalyGroupStatistics$BuilderImpl);
    Code:
       0: aload_0
       1: aload_1
       2: ifnull        12
       5: aload_1
       6: invokevirtual #27                 // Method software/amazon/awssdk/services/lookoutmetrics/model/AnomalyGroupStatistics$BuilderImpl.build:()Lsoftware/amazon/awssdk/services/lookoutmetrics/model/AnomalyGroupStatistics;
       9: goto          13
      12: aconst_null
      13: putfield      #4                  // Field anomalyGroupStatistics:Lsoftware/amazon/awssdk/services/lookoutmetrics/model/AnomalyGroupStatistics;
      16: return

  public final software.amazon.awssdk.services.lookoutmetrics.model.ListAnomalyGroupSummariesResponse$Builder anomalyGroupStatistics(software.amazon.awssdk.services.lookoutmetrics.model.AnomalyGroupStatistics);
    Code:
       0: aload_0
       1: aload_1
       2: putfield      #4                  // Field anomalyGroupStatistics:Lsoftware/amazon/awssdk/services/lookoutmetrics/model/AnomalyGroupStatistics;
       5: aload_0
       6: areturn

  public final java.lang.String getNextToken();
    Code:
       0: aload_0
       1: getfield      #3                  // Field nextToken:Ljava/lang/String;
       4: areturn

  public final void setNextToken(java.lang.String);
    Code:
       0: aload_0
       1: aload_1
       2: putfield      #3                  // Field nextToken:Ljava/lang/String;
       5: return

  public final software.amazon.awssdk.services.lookoutmetrics.model.ListAnomalyGroupSummariesResponse$Builder nextToken(java.lang.String);
    Code:
       0: aload_0
       1: aload_1
       2: putfield      #3                  // Field nextToken:Ljava/lang/String;
       5: aload_0
       6: areturn

  public software.amazon.awssdk.services.lookoutmetrics.model.ListAnomalyGroupSummariesResponse build();
    Code:
       0: new           #28                 // class software/amazon/awssdk/services/lookoutmetrics/model/ListAnomalyGroupSummariesResponse
       3: dup
       4: aload_0
       5: aconst_null
       6: invokespecial #29                 // Method software/amazon/awssdk/services/lookoutmetrics/model/ListAnomalyGroupSummariesResponse."<init>":(Lsoftware/amazon/awssdk/services/lookoutmetrics/model/ListAnomalyGroupSummariesResponse$BuilderImpl;Lsoftware/amazon/awssdk/services/lookoutmetrics/model/ListAnomalyGroupSummariesResponse$1;)V
       9: areturn

  public java.util.List<software.amazon.awssdk.core.SdkField<?>> sdkFields();
    Code:
       0: invokestatic  #30                 // Method software/amazon/awssdk/services/lookoutmetrics/model/ListAnomalyGroupSummariesResponse.access$900:()Ljava/util/List;
       3: areturn

  public software.amazon.awssdk.services.lookoutmetrics.model.LookoutMetricsResponse build();
    Code:
       0: aload_0
       1: invokevirtual #31                 // Method build:()Lsoftware/amazon/awssdk/services/lookoutmetrics/model/ListAnomalyGroupSummariesResponse;
       4: areturn

  public software.amazon.awssdk.awscore.AwsResponse build();
    Code:
       0: aload_0
       1: invokevirtual #31                 // Method build:()Lsoftware/amazon/awssdk/services/lookoutmetrics/model/ListAnomalyGroupSummariesResponse;
       4: areturn

  public software.amazon.awssdk.core.SdkResponse build();
    Code:
       0: aload_0
       1: invokevirtual #31                 // Method build:()Lsoftware/amazon/awssdk/services/lookoutmetrics/model/ListAnomalyGroupSummariesResponse;
       4: areturn

  public java.lang.Object build();
    Code:
       0: aload_0
       1: invokevirtual #31                 // Method build:()Lsoftware/amazon/awssdk/services/lookoutmetrics/model/ListAnomalyGroupSummariesResponse;
       4: areturn

  private static software.amazon.awssdk.services.lookoutmetrics.model.AnomalyGroupSummary lambda$anomalyGroupSummaryList$0(java.util.function.Consumer);
    Code:
       0: invokestatic  #32                 // Method software/amazon/awssdk/services/lookoutmetrics/model/AnomalyGroupSummary.builder:()Lsoftware/amazon/awssdk/services/lookoutmetrics/model/AnomalyGroupSummary$Builder;
       3: aload_0
       4: invokeinterface #33,  2           // InterfaceMethod software/amazon/awssdk/services/lookoutmetrics/model/AnomalyGroupSummary$Builder.applyMutation:(Ljava/util/function/Consumer;)Lsoftware/amazon/awssdk/utils/builder/SdkBuilder;
       9: checkcast     #34                 // class software/amazon/awssdk/services/lookoutmetrics/model/AnomalyGroupSummary$Builder
      12: invokeinterface #35,  1           // InterfaceMethod software/amazon/awssdk/services/lookoutmetrics/model/AnomalyGroupSummary$Builder.build:()Ljava/lang/Object;
      17: checkcast     #36                 // class software/amazon/awssdk/services/lookoutmetrics/model/AnomalyGroupSummary
      20: areturn

  static java.util.List access$000(software.amazon.awssdk.services.lookoutmetrics.model.ListAnomalyGroupSummariesResponse$BuilderImpl);
    Code:
       0: aload_0
       1: getfield      #5                  // Field anomalyGroupSummaryList:Ljava/util/List;
       4: areturn

  static software.amazon.awssdk.services.lookoutmetrics.model.AnomalyGroupStatistics access$100(software.amazon.awssdk.services.lookoutmetrics.model.ListAnomalyGroupSummariesResponse$BuilderImpl);
    Code:
       0: aload_0
       1: getfield      #4                  // Field anomalyGroupStatistics:Lsoftware/amazon/awssdk/services/lookoutmetrics/model/AnomalyGroupStatistics;
       4: areturn

  static java.lang.String access$200(software.amazon.awssdk.services.lookoutmetrics.model.ListAnomalyGroupSummariesResponse$BuilderImpl);
    Code:
       0: aload_0
       1: getfield      #3                  // Field nextToken:Ljava/lang/String;
       4: areturn

  software.amazon.awssdk.services.lookoutmetrics.model.ListAnomalyGroupSummariesResponse$BuilderImpl(software.amazon.awssdk.services.lookoutmetrics.model.ListAnomalyGroupSummariesResponse, software.amazon.awssdk.services.lookoutmetrics.model.ListAnomalyGroupSummariesResponse$1);
    Code:
       0: aload_0
       1: aload_1
       2: invokespecial #2                  // Method "<init>":(Lsoftware/amazon/awssdk/services/lookoutmetrics/model/ListAnomalyGroupSummariesResponse;)V
       5: return

  software.amazon.awssdk.services.lookoutmetrics.model.ListAnomalyGroupSummariesResponse$BuilderImpl(software.amazon.awssdk.services.lookoutmetrics.model.ListAnomalyGroupSummariesResponse$1);
    Code:
       0: aload_0
       1: invokespecial #1                  // Method "<init>":()V
       4: return
}
