Compiled from "ListAnomalyGroupSummariesResponse.java"
public interface software.amazon.awssdk.services.lookoutmetrics.model.ListAnomalyGroupSummariesResponse$Builder extends software.amazon.awssdk.services.lookoutmetrics.model.LookoutMetricsResponse$Builder, software.amazon.awssdk.core.SdkPojo, software.amazon.awssdk.utils.builder.CopyableBuilder<software.amazon.awssdk.services.lookoutmetrics.model.ListAnomalyGroupSummariesResponse$Builder, software.amazon.awssdk.services.lookoutmetrics.model.ListAnomalyGroupSummariesResponse> {
  public abstract software.amazon.awssdk.services.lookoutmetrics.model.ListAnomalyGroupSummariesResponse$Builder anomalyGroupSummaryList(java.util.Collection<software.amazon.awssdk.services.lookoutmetrics.model.AnomalyGroupSummary>);

  public abstract software.amazon.awssdk.services.lookoutmetrics.model.ListAnomalyGroupSummariesResponse$Builder anomalyGroupSummaryList(software.amazon.awssdk.services.lookoutmetrics.model.AnomalyGroupSummary...);

  public abstract software.amazon.awssdk.services.lookoutmetrics.model.ListAnomalyGroupSummariesResponse$Builder anomalyGroupSummaryList(java.util.function.Consumer<software.amazon.awssdk.services.lookoutmetrics.model.AnomalyGroupSummary$Builder>...);

  public abstract software.amazon.awssdk.services.lookoutmetrics.model.ListAnomalyGroupSummariesResponse$Builder anomalyGroupStatistics(software.amazon.awssdk.services.lookoutmetrics.model.AnomalyGroupStatistics);

  public default software.amazon.awssdk.services.lookoutmetrics.model.ListAnomalyGroupSummariesResponse$Builder anomalyGroupStatistics(java.util.function.Consumer<software.amazon.awssdk.services.lookoutmetrics.model.AnomalyGroupStatistics$Builder>);
    Code:
       0: aload_0
       1: invokestatic  #1                  // Method software/amazon/awssdk/services/lookoutmetrics/model/AnomalyGroupStatistics.builder:()Lsoftware/amazon/awssdk/services/lookoutmetrics/model/AnomalyGroupStatistics$Builder;
       4: aload_1
       5: invokeinterface #2,  2            // InterfaceMethod software/amazon/awssdk/services/lookoutmetrics/model/AnomalyGroupStatistics$Builder.applyMutation:(Ljava/util/function/Consumer;)Lsoftware/amazon/awssdk/utils/builder/SdkBuilder;
      10: checkcast     #3                  // class software/amazon/awssdk/services/lookoutmetrics/model/AnomalyGroupStatistics$Builder
      13: invokeinterface #4,  1            // InterfaceMethod software/amazon/awssdk/services/lookoutmetrics/model/AnomalyGroupStatistics$Builder.build:()Ljava/lang/Object;
      18: checkcast     #5                  // class software/amazon/awssdk/services/lookoutmetrics/model/AnomalyGroupStatistics
      21: invokeinterface #6,  2            // InterfaceMethod anomalyGroupStatistics:(Lsoftware/amazon/awssdk/services/lookoutmetrics/model/AnomalyGroupStatistics;)Lsoftware/amazon/awssdk/services/lookoutmetrics/model/ListAnomalyGroupSummariesResponse$Builder;
      26: areturn

  public abstract software.amazon.awssdk.services.lookoutmetrics.model.ListAnomalyGroupSummariesResponse$Builder nextToken(java.lang.String);
}
