Compiled from "PutFeedbackRequest.java"
final class software.amazon.awssdk.services.lookoutmetrics.model.PutFeedbackRequest$BuilderImpl extends software.amazon.awssdk.services.lookoutmetrics.model.LookoutMetricsRequest$BuilderImpl implements software.amazon.awssdk.services.lookoutmetrics.model.PutFeedbackRequest$Builder {
  private java.lang.String anomalyDetectorArn;

  private software.amazon.awssdk.services.lookoutmetrics.model.AnomalyGroupTimeSeriesFeedback anomalyGroupTimeSeriesFeedback;

  private software.amazon.awssdk.services.lookoutmetrics.model.PutFeedbackRequest$BuilderImpl();
    Code:
       0: aload_0
       1: invokespecial #5                  // Method software/amazon/awssdk/services/lookoutmetrics/model/LookoutMetricsRequest$BuilderImpl."<init>":()V
       4: return

  private software.amazon.awssdk.services.lookoutmetrics.model.PutFeedbackRequest$BuilderImpl(software.amazon.awssdk.services.lookoutmetrics.model.PutFeedbackRequest);
    Code:
       0: aload_0
       1: aload_1
       2: invokespecial #6                  // Method software/amazon/awssdk/services/lookoutmetrics/model/LookoutMetricsRequest$BuilderImpl."<init>":(Lsoftware/amazon/awssdk/services/lookoutmetrics/model/LookoutMetricsRequest;)V
       5: aload_0
       6: aload_1
       7: invokestatic  #7                  // Method software/amazon/awssdk/services/lookoutmetrics/model/PutFeedbackRequest.access$400:(Lsoftware/amazon/awssdk/services/lookoutmetrics/model/PutFeedbackRequest;)Ljava/lang/String;
      10: invokevirtual #8                  // Method anomalyDetectorArn:(Ljava/lang/String;)Lsoftware/amazon/awssdk/services/lookoutmetrics/model/PutFeedbackRequest$Builder;
      13: pop
      14: aload_0
      15: aload_1
      16: invokestatic  #9                  // Method software/amazon/awssdk/services/lookoutmetrics/model/PutFeedbackRequest.access$500:(Lsoftware/amazon/awssdk/services/lookoutmetrics/model/PutFeedbackRequest;)Lsoftware/amazon/awssdk/services/lookoutmetrics/model/AnomalyGroupTimeSeriesFeedback;
      19: invokevirtual #10                 // Method anomalyGroupTimeSeriesFeedback:(Lsoftware/amazon/awssdk/services/lookoutmetrics/model/AnomalyGroupTimeSeriesFeedback;)Lsoftware/amazon/awssdk/services/lookoutmetrics/model/PutFeedbackRequest$Builder;
      22: pop
      23: return

  public final java.lang.String getAnomalyDetectorArn();
    Code:
       0: aload_0
       1: getfield      #4                  // Field anomalyDetectorArn:Ljava/lang/String;
       4: areturn

  public final void setAnomalyDetectorArn(java.lang.String);
    Code:
       0: aload_0
       1: aload_1
       2: putfield      #4                  // Field anomalyDetectorArn:Ljava/lang/String;
       5: return

  public final software.amazon.awssdk.services.lookoutmetrics.model.PutFeedbackRequest$Builder anomalyDetectorArn(java.lang.String);
    Code:
       0: aload_0
       1: aload_1
       2: putfield      #4                  // Field anomalyDetectorArn:Ljava/lang/String;
       5: aload_0
       6: areturn

  public final software.amazon.awssdk.services.lookoutmetrics.model.AnomalyGroupTimeSeriesFeedback$Builder getAnomalyGroupTimeSeriesFeedback();
    Code:
       0: aload_0
       1: getfield      #3                  // Field anomalyGroupTimeSeriesFeedback:Lsoftware/amazon/awssdk/services/lookoutmetrics/model/AnomalyGroupTimeSeriesFeedback;
       4: ifnull        17
       7: aload_0
       8: getfield      #3                  // Field anomalyGroupTimeSeriesFeedback:Lsoftware/amazon/awssdk/services/lookoutmetrics/model/AnomalyGroupTimeSeriesFeedback;
      11: invokevirtual #11                 // Method software/amazon/awssdk/services/lookoutmetrics/model/AnomalyGroupTimeSeriesFeedback.toBuilder:()Lsoftware/amazon/awssdk/services/lookoutmetrics/model/AnomalyGroupTimeSeriesFeedback$Builder;
      14: goto          18
      17: aconst_null
      18: areturn

  public final void setAnomalyGroupTimeSeriesFeedback(software.amazon.awssdk.services.lookoutmetrics.model.AnomalyGroupTimeSeriesFeedback$BuilderImpl);
    Code:
       0: aload_0
       1: aload_1
       2: ifnull        12
       5: aload_1
       6: invokevirtual #12                 // Method software/amazon/awssdk/services/lookoutmetrics/model/AnomalyGroupTimeSeriesFeedback$BuilderImpl.build:()Lsoftware/amazon/awssdk/services/lookoutmetrics/model/AnomalyGroupTimeSeriesFeedback;
       9: goto          13
      12: aconst_null
      13: putfield      #3                  // Field anomalyGroupTimeSeriesFeedback:Lsoftware/amazon/awssdk/services/lookoutmetrics/model/AnomalyGroupTimeSeriesFeedback;
      16: return

  public final software.amazon.awssdk.services.lookoutmetrics.model.PutFeedbackRequest$Builder anomalyGroupTimeSeriesFeedback(software.amazon.awssdk.services.lookoutmetrics.model.AnomalyGroupTimeSeriesFeedback);
    Code:
       0: aload_0
       1: aload_1
       2: putfield      #3                  // Field anomalyGroupTimeSeriesFeedback:Lsoftware/amazon/awssdk/services/lookoutmetrics/model/AnomalyGroupTimeSeriesFeedback;
       5: aload_0
       6: areturn

  public software.amazon.awssdk.services.lookoutmetrics.model.PutFeedbackRequest$Builder overrideConfiguration(software.amazon.awssdk.awscore.AwsRequestOverrideConfiguration);
    Code:
       0: aload_0
       1: aload_1
       2: invokespecial #13                 // Method software/amazon/awssdk/services/lookoutmetrics/model/LookoutMetricsRequest$BuilderImpl.overrideConfiguration:(Lsoftware/amazon/awssdk/awscore/AwsRequestOverrideConfiguration;)Lsoftware/amazon/awssdk/awscore/AwsRequest$Builder;
       5: pop
       6: aload_0
       7: areturn

  public software.amazon.awssdk.services.lookoutmetrics.model.PutFeedbackRequest$Builder overrideConfiguration(java.util.function.Consumer<software.amazon.awssdk.awscore.AwsRequestOverrideConfiguration$Builder>);
    Code:
       0: aload_0
       1: aload_1
       2: invokespecial #14                 // Method software/amazon/awssdk/services/lookoutmetrics/model/LookoutMetricsRequest$BuilderImpl.overrideConfiguration:(Ljava/util/function/Consumer;)Lsoftware/amazon/awssdk/awscore/AwsRequest$Builder;
       5: pop
       6: aload_0
       7: areturn

  public software.amazon.awssdk.services.lookoutmetrics.model.PutFeedbackRequest build();
    Code:
       0: new           #15                 // class software/amazon/awssdk/services/lookoutmetrics/model/PutFeedbackRequest
       3: dup
       4: aload_0
       5: aconst_null
       6: invokespecial #16                 // Method software/amazon/awssdk/services/lookoutmetrics/model/PutFeedbackRequest."<init>":(Lsoftware/amazon/awssdk/services/lookoutmetrics/model/PutFeedbackRequest$BuilderImpl;Lsoftware/amazon/awssdk/services/lookoutmetrics/model/PutFeedbackRequest$1;)V
       9: areturn

  public java.util.List<software.amazon.awssdk.core.SdkField<?>> sdkFields();
    Code:
       0: invokestatic  #17                 // Method software/amazon/awssdk/services/lookoutmetrics/model/PutFeedbackRequest.access$700:()Ljava/util/List;
       3: areturn

  public software.amazon.awssdk.services.lookoutmetrics.model.LookoutMetricsRequest build();
    Code:
       0: aload_0
       1: invokevirtual #18                 // Method build:()Lsoftware/amazon/awssdk/services/lookoutmetrics/model/PutFeedbackRequest;
       4: areturn

  public software.amazon.awssdk.awscore.AwsRequest build();
    Code:
       0: aload_0
       1: invokevirtual #18                 // Method build:()Lsoftware/amazon/awssdk/services/lookoutmetrics/model/PutFeedbackRequest;
       4: areturn

  public software.amazon.awssdk.awscore.AwsRequest$Builder overrideConfiguration(java.util.function.Consumer);
    Code:
       0: aload_0
       1: aload_1
       2: invokevirtual #19                 // Method overrideConfiguration:(Ljava/util/function/Consumer;)Lsoftware/amazon/awssdk/services/lookoutmetrics/model/PutFeedbackRequest$Builder;
       5: areturn

  public software.amazon.awssdk.awscore.AwsRequest$Builder overrideConfiguration(software.amazon.awssdk.awscore.AwsRequestOverrideConfiguration);
    Code:
       0: aload_0
       1: aload_1
       2: invokevirtual #20                 // Method overrideConfiguration:(Lsoftware/amazon/awssdk/awscore/AwsRequestOverrideConfiguration;)Lsoftware/amazon/awssdk/services/lookoutmetrics/model/PutFeedbackRequest$Builder;
       5: areturn

  public software.amazon.awssdk.core.SdkRequest build();
    Code:
       0: aload_0
       1: invokevirtual #18                 // Method build:()Lsoftware/amazon/awssdk/services/lookoutmetrics/model/PutFeedbackRequest;
       4: areturn

  public java.lang.Object build();
    Code:
       0: aload_0
       1: invokevirtual #18                 // Method build:()Lsoftware/amazon/awssdk/services/lookoutmetrics/model/PutFeedbackRequest;
       4: areturn

  static java.lang.String access$000(software.amazon.awssdk.services.lookoutmetrics.model.PutFeedbackRequest$BuilderImpl);
    Code:
       0: aload_0
       1: getfield      #4                  // Field anomalyDetectorArn:Ljava/lang/String;
       4: areturn

  static software.amazon.awssdk.services.lookoutmetrics.model.AnomalyGroupTimeSeriesFeedback access$100(software.amazon.awssdk.services.lookoutmetrics.model.PutFeedbackRequest$BuilderImpl);
    Code:
       0: aload_0
       1: getfield      #3                  // Field anomalyGroupTimeSeriesFeedback:Lsoftware/amazon/awssdk/services/lookoutmetrics/model/AnomalyGroupTimeSeriesFeedback;
       4: areturn

  software.amazon.awssdk.services.lookoutmetrics.model.PutFeedbackRequest$BuilderImpl(software.amazon.awssdk.services.lookoutmetrics.model.PutFeedbackRequest, software.amazon.awssdk.services.lookoutmetrics.model.PutFeedbackRequest$1);
    Code:
       0: aload_0
       1: aload_1
       2: invokespecial #2                  // Method "<init>":(Lsoftware/amazon/awssdk/services/lookoutmetrics/model/PutFeedbackRequest;)V
       5: return

  software.amazon.awssdk.services.lookoutmetrics.model.PutFeedbackRequest$BuilderImpl(software.amazon.awssdk.services.lookoutmetrics.model.PutFeedbackRequest$1);
    Code:
       0: aload_0
       1: invokespecial #1                  // Method "<init>":()V
       4: return
}
