Compiled from "DefaultConsistentHashFactory.java"
public class org.infinispan.distribution.ch.impl.DefaultConsistentHashFactory$Externalizer extends org.infinispan.commons.marshall.AbstractExternalizer<org.infinispan.distribution.ch.impl.DefaultConsistentHashFactory> {
  public org.infinispan.distribution.ch.impl.DefaultConsistentHashFactory$Externalizer();
    Code:
       0: aload_0
       1: invokespecial #1                  // Method org/infinispan/commons/marshall/AbstractExternalizer."<init>":()V
       4: return

  public void writeObject(java.io.ObjectOutput, org.infinispan.distribution.ch.impl.DefaultConsistentHashFactory) throws java.io.IOException;
    Code:
       0: return

  public org.infinispan.distribution.ch.impl.DefaultConsistentHashFactory readObject(java.io.ObjectInput) throws java.io.IOException, java.lang.ClassNotFoundException;
    Code:
       0: new           #2                  // class org/infinispan/distribution/ch/impl/DefaultConsistentHashFactory
       3: dup
       4: invokespecial #3                  // Method org/infinispan/distribution/ch/impl/DefaultConsistentHashFactory."<init>":()V
       7: areturn

  public java.lang.Integer getId();
    Code:
       0: bipush        91
       2: invokestatic  #5                  // Method java/lang/Integer.valueOf:(I)Ljava/lang/Integer;
       5: areturn

  public java.util.Set<java.lang.Class<? extends org.infinispan.distribution.ch.impl.DefaultConsistentHashFactory>> getTypeClasses();
    Code:
       0: ldc           #2                  // class org/infinispan/distribution/ch/impl/DefaultConsistentHashFactory
       2: invokestatic  #6                  // Method java/util/Collections.singleton:(Ljava/lang/Object;)Ljava/util/Set;
       5: areturn

  public java.lang.Object readObject(java.io.ObjectInput) throws java.io.IOException, java.lang.ClassNotFoundException;
    Code:
       0: aload_0
       1: aload_1
       2: invokevirtual #7                  // Method readObject:(Ljava/io/ObjectInput;)Lorg/infinispan/distribution/ch/impl/DefaultConsistentHashFactory;
       5: areturn

  public void writeObject(java.io.ObjectOutput, java.lang.Object) throws java.io.IOException;
    Code:
       0: aload_0
       1: aload_1
       2: aload_2
       3: checkcast     #2                  // class org/infinispan/distribution/ch/impl/DefaultConsistentHashFactory
       6: invokevirtual #8                  // Method writeObject:(Ljava/io/ObjectOutput;Lorg/infinispan/distribution/ch/impl/DefaultConsistentHashFactory;)V
       9: return
}
