Compiled from "WindowAllocationManager.java"
class org.apache.coyote.http2.WindowAllocationManager {
  private static final org.apache.juli.logging.Log log;

  private static final org.apache.tomcat.util.res.StringManager sm;

  private static final int NONE;

  private static final int STREAM;

  private static final int CONNECTION;

  private final org.apache.coyote.http2.Stream stream;

  private int waitingFor;

  org.apache.coyote.http2.WindowAllocationManager(org.apache.coyote.http2.Stream);
    Code:
       0: aload_0
       1: invokespecial #1                  // Method java/lang/Object."<init>":()V
       4: aload_0
       5: iconst_0
       6: putfield      #3                  // Field waitingFor:I
       9: aload_0
      10: aload_1
      11: putfield      #4                  // Field stream:Lorg/apache/coyote/http2/Stream;
      14: return

  void waitForStream(long) throws java.lang.InterruptedException;
    Code:
       0: getstatic     #5                  // Field log:Lorg/apache/juli/logging/Log;
       3: invokeinterface #6,  1            // InterfaceMethod org/apache/juli/logging/Log.isDebugEnabled:()Z
       8: ifeq          58
      11: getstatic     #5                  // Field log:Lorg/apache/juli/logging/Log;
      14: getstatic     #7                  // Field sm:Lorg/apache/tomcat/util/res/StringManager;
      17: ldc           #8                  // String windowAllocationManager.waitFor.stream
      19: iconst_3
      20: anewarray     #9                  // class java/lang/Object
      23: dup
      24: iconst_0
      25: aload_0
      26: getfield      #4                  // Field stream:Lorg/apache/coyote/http2/Stream;
      29: invokevirtual #10                 // Method org/apache/coyote/http2/Stream.getConnectionId:()Ljava/lang/String;
      32: aastore
      33: dup
      34: iconst_1
      35: aload_0
      36: getfield      #4                  // Field stream:Lorg/apache/coyote/http2/Stream;
      39: invokevirtual #11                 // Method org/apache/coyote/http2/Stream.getIdentifier:()Ljava/lang/Integer;
      42: aastore
      43: dup
      44: iconst_2
      45: lload_1
      46: invokestatic  #12                 // Method java/lang/Long.toString:(J)Ljava/lang/String;
      49: aastore
      50: invokevirtual #13                 // Method org/apache/tomcat/util/res/StringManager.getString:(Ljava/lang/String;[Ljava/lang/Object;)Ljava/lang/String;
      53: invokeinterface #14,  2           // InterfaceMethod org/apache/juli/logging/Log.debug:(Ljava/lang/Object;)V
      58: aload_0
      59: iconst_1
      60: lload_1
      61: invokespecial #15                 // Method waitFor:(IJ)V
      64: return

  void waitForConnection(long) throws java.lang.InterruptedException;
    Code:
       0: getstatic     #5                  // Field log:Lorg/apache/juli/logging/Log;
       3: invokeinterface #6,  1            // InterfaceMethod org/apache/juli/logging/Log.isDebugEnabled:()Z
       8: ifeq          58
      11: getstatic     #5                  // Field log:Lorg/apache/juli/logging/Log;
      14: getstatic     #7                  // Field sm:Lorg/apache/tomcat/util/res/StringManager;
      17: ldc           #16                 // String windowAllocationManager.waitFor.connection
      19: iconst_3
      20: anewarray     #9                  // class java/lang/Object
      23: dup
      24: iconst_0
      25: aload_0
      26: getfield      #4                  // Field stream:Lorg/apache/coyote/http2/Stream;
      29: invokevirtual #10                 // Method org/apache/coyote/http2/Stream.getConnectionId:()Ljava/lang/String;
      32: aastore
      33: dup
      34: iconst_1
      35: aload_0
      36: getfield      #4                  // Field stream:Lorg/apache/coyote/http2/Stream;
      39: invokevirtual #11                 // Method org/apache/coyote/http2/Stream.getIdentifier:()Ljava/lang/Integer;
      42: aastore
      43: dup
      44: iconst_2
      45: lload_1
      46: invokestatic  #12                 // Method java/lang/Long.toString:(J)Ljava/lang/String;
      49: aastore
      50: invokevirtual #13                 // Method org/apache/tomcat/util/res/StringManager.getString:(Ljava/lang/String;[Ljava/lang/Object;)Ljava/lang/String;
      53: invokeinterface #14,  2           // InterfaceMethod org/apache/juli/logging/Log.debug:(Ljava/lang/Object;)V
      58: aload_0
      59: iconst_2
      60: lload_1
      61: invokespecial #15                 // Method waitFor:(IJ)V
      64: return

  void waitForStreamNonBlocking();
    Code:
       0: getstatic     #5                  // Field log:Lorg/apache/juli/logging/Log;
       3: invokeinterface #6,  1            // InterfaceMethod org/apache/juli/logging/Log.isDebugEnabled:()Z
       8: ifeq          51
      11: getstatic     #5                  // Field log:Lorg/apache/juli/logging/Log;
      14: getstatic     #7                  // Field sm:Lorg/apache/tomcat/util/res/StringManager;
      17: ldc           #17                 // String windowAllocationManager.waitForNonBlocking.stream
      19: iconst_2
      20: anewarray     #9                  // class java/lang/Object
      23: dup
      24: iconst_0
      25: aload_0
      26: getfield      #4                  // Field stream:Lorg/apache/coyote/http2/Stream;
      29: invokevirtual #10                 // Method org/apache/coyote/http2/Stream.getConnectionId:()Ljava/lang/String;
      32: aastore
      33: dup
      34: iconst_1
      35: aload_0
      36: getfield      #4                  // Field stream:Lorg/apache/coyote/http2/Stream;
      39: invokevirtual #11                 // Method org/apache/coyote/http2/Stream.getIdentifier:()Ljava/lang/Integer;
      42: aastore
      43: invokevirtual #13                 // Method org/apache/tomcat/util/res/StringManager.getString:(Ljava/lang/String;[Ljava/lang/Object;)Ljava/lang/String;
      46: invokeinterface #14,  2           // InterfaceMethod org/apache/juli/logging/Log.debug:(Ljava/lang/Object;)V
      51: aload_0
      52: iconst_1
      53: invokespecial #18                 // Method waitForNonBlocking:(I)V
      56: return

  void waitForConnectionNonBlocking();
    Code:
       0: getstatic     #5                  // Field log:Lorg/apache/juli/logging/Log;
       3: invokeinterface #6,  1            // InterfaceMethod org/apache/juli/logging/Log.isDebugEnabled:()Z
       8: ifeq          51
      11: getstatic     #5                  // Field log:Lorg/apache/juli/logging/Log;
      14: getstatic     #7                  // Field sm:Lorg/apache/tomcat/util/res/StringManager;
      17: ldc           #19                 // String windowAllocationManager.waitForNonBlocking.connection
      19: iconst_2
      20: anewarray     #9                  // class java/lang/Object
      23: dup
      24: iconst_0
      25: aload_0
      26: getfield      #4                  // Field stream:Lorg/apache/coyote/http2/Stream;
      29: invokevirtual #10                 // Method org/apache/coyote/http2/Stream.getConnectionId:()Ljava/lang/String;
      32: aastore
      33: dup
      34: iconst_1
      35: aload_0
      36: getfield      #4                  // Field stream:Lorg/apache/coyote/http2/Stream;
      39: invokevirtual #11                 // Method org/apache/coyote/http2/Stream.getIdentifier:()Ljava/lang/Integer;
      42: aastore
      43: invokevirtual #13                 // Method org/apache/tomcat/util/res/StringManager.getString:(Ljava/lang/String;[Ljava/lang/Object;)Ljava/lang/String;
      46: invokeinterface #14,  2           // InterfaceMethod org/apache/juli/logging/Log.debug:(Ljava/lang/Object;)V
      51: aload_0
      52: iconst_2
      53: invokespecial #18                 // Method waitForNonBlocking:(I)V
      56: return

  void notifyStream();
    Code:
       0: aload_0
       1: iconst_1
       2: invokespecial #20                 // Method notify:(I)V
       5: return

  void notifyConnection();
    Code:
       0: aload_0
       1: iconst_2
       2: invokespecial #20                 // Method notify:(I)V
       5: return

  void notifyAny();
    Code:
       0: aload_0
       1: iconst_3
       2: invokespecial #20                 // Method notify:(I)V
       5: return

  boolean isWaitingForStream();
    Code:
       0: aload_0
       1: iconst_1
       2: invokespecial #21                 // Method isWaitingFor:(I)Z
       5: ireturn

  boolean isWaitingForConnection();
    Code:
       0: aload_0
       1: iconst_2
       2: invokespecial #21                 // Method isWaitingFor:(I)Z
       5: ireturn

  private boolean isWaitingFor(int);
    Code:
       0: aload_0
       1: getfield      #4                  // Field stream:Lorg/apache/coyote/http2/Stream;
       4: dup
       5: astore_2
       6: monitorenter
       7: aload_0
       8: getfield      #3                  // Field waitingFor:I
      11: iload_1
      12: iand
      13: ifle          20
      16: iconst_1
      17: goto          21
      20: iconst_0
      21: aload_2
      22: monitorexit
      23: ireturn
      24: astore_3
      25: aload_2
      26: monitorexit
      27: aload_3
      28: athrow
    Exception table:
       from    to  target type
           7    23    24   any
          24    27    24   any

  private void waitFor(int, long) throws java.lang.InterruptedException;
    Code:
       0: aload_0
       1: getfield      #4                  // Field stream:Lorg/apache/coyote/http2/Stream;
       4: dup
       5: astore        4
       7: monitorenter
       8: aload_0
       9: getfield      #3                  // Field waitingFor:I
      12: ifeq          55
      15: new           #22                 // class java/lang/IllegalStateException
      18: dup
      19: getstatic     #7                  // Field sm:Lorg/apache/tomcat/util/res/StringManager;
      22: ldc           #23                 // String windowAllocationManager.waitFor.ise
      24: iconst_2
      25: anewarray     #9                  // class java/lang/Object
      28: dup
      29: iconst_0
      30: aload_0
      31: getfield      #4                  // Field stream:Lorg/apache/coyote/http2/Stream;
      34: invokevirtual #10                 // Method org/apache/coyote/http2/Stream.getConnectionId:()Ljava/lang/String;
      37: aastore
      38: dup
      39: iconst_1
      40: aload_0
      41: getfield      #4                  // Field stream:Lorg/apache/coyote/http2/Stream;
      44: invokevirtual #11                 // Method org/apache/coyote/http2/Stream.getIdentifier:()Ljava/lang/Integer;
      47: aastore
      48: invokevirtual #13                 // Method org/apache/tomcat/util/res/StringManager.getString:(Ljava/lang/String;[Ljava/lang/Object;)Ljava/lang/String;
      51: invokespecial #24                 // Method java/lang/IllegalStateException."<init>":(Ljava/lang/String;)V
      54: athrow
      55: aload_0
      56: iload_1
      57: putfield      #3                  // Field waitingFor:I
      60: lload_2
      61: lconst_0
      62: lcmp
      63: ifge          76
      66: aload_0
      67: getfield      #4                  // Field stream:Lorg/apache/coyote/http2/Stream;
      70: invokevirtual #25                 // Method java/lang/Object.wait:()V
      73: goto          84
      76: aload_0
      77: getfield      #4                  // Field stream:Lorg/apache/coyote/http2/Stream;
      80: lload_2
      81: invokevirtual #26                 // Method java/lang/Object.wait:(J)V
      84: aload         4
      86: monitorexit
      87: goto          98
      90: astore        5
      92: aload         4
      94: monitorexit
      95: aload         5
      97: athrow
      98: return
    Exception table:
       from    to  target type
           8    87    90   any
          90    95    90   any

  private void waitForNonBlocking(int);
    Code:
       0: aload_0
       1: getfield      #4                  // Field stream:Lorg/apache/coyote/http2/Stream;
       4: dup
       5: astore_2
       6: monitorenter
       7: aload_0
       8: getfield      #3                  // Field waitingFor:I
      11: ifne          22
      14: aload_0
      15: iload_1
      16: putfield      #3                  // Field waitingFor:I
      19: goto          73
      22: aload_0
      23: getfield      #3                  // Field waitingFor:I
      26: iload_1
      27: if_icmpne     33
      30: goto          73
      33: new           #22                 // class java/lang/IllegalStateException
      36: dup
      37: getstatic     #7                  // Field sm:Lorg/apache/tomcat/util/res/StringManager;
      40: ldc           #23                 // String windowAllocationManager.waitFor.ise
      42: iconst_2
      43: anewarray     #9                  // class java/lang/Object
      46: dup
      47: iconst_0
      48: aload_0
      49: getfield      #4                  // Field stream:Lorg/apache/coyote/http2/Stream;
      52: invokevirtual #10                 // Method org/apache/coyote/http2/Stream.getConnectionId:()Ljava/lang/String;
      55: aastore
      56: dup
      57: iconst_1
      58: aload_0
      59: getfield      #4                  // Field stream:Lorg/apache/coyote/http2/Stream;
      62: invokevirtual #11                 // Method org/apache/coyote/http2/Stream.getIdentifier:()Ljava/lang/Integer;
      65: aastore
      66: invokevirtual #13                 // Method org/apache/tomcat/util/res/StringManager.getString:(Ljava/lang/String;[Ljava/lang/Object;)Ljava/lang/String;
      69: invokespecial #24                 // Method java/lang/IllegalStateException."<init>":(Ljava/lang/String;)V
      72: athrow
      73: aload_2
      74: monitorexit
      75: goto          83
      78: astore_3
      79: aload_2
      80: monitorexit
      81: aload_3
      82: athrow
      83: return
    Exception table:
       from    to  target type
           7    75    78   any
          78    81    78   any

  private void notify(int);
    Code:
       0: getstatic     #5                  // Field log:Lorg/apache/juli/logging/Log;
       3: invokeinterface #6,  1            // InterfaceMethod org/apache/juli/logging/Log.isDebugEnabled:()Z
       8: ifeq          68
      11: getstatic     #5                  // Field log:Lorg/apache/juli/logging/Log;
      14: getstatic     #7                  // Field sm:Lorg/apache/tomcat/util/res/StringManager;
      17: ldc           #27                 // String windowAllocationManager.notify
      19: iconst_4
      20: anewarray     #9                  // class java/lang/Object
      23: dup
      24: iconst_0
      25: aload_0
      26: getfield      #4                  // Field stream:Lorg/apache/coyote/http2/Stream;
      29: invokevirtual #10                 // Method org/apache/coyote/http2/Stream.getConnectionId:()Ljava/lang/String;
      32: aastore
      33: dup
      34: iconst_1
      35: aload_0
      36: getfield      #4                  // Field stream:Lorg/apache/coyote/http2/Stream;
      39: invokevirtual #11                 // Method org/apache/coyote/http2/Stream.getIdentifier:()Ljava/lang/Integer;
      42: aastore
      43: dup
      44: iconst_2
      45: aload_0
      46: getfield      #3                  // Field waitingFor:I
      49: invokestatic  #28                 // Method java/lang/Integer.toString:(I)Ljava/lang/String;
      52: aastore
      53: dup
      54: iconst_3
      55: iload_1
      56: invokestatic  #28                 // Method java/lang/Integer.toString:(I)Ljava/lang/String;
      59: aastore
      60: invokevirtual #13                 // Method org/apache/tomcat/util/res/StringManager.getString:(Ljava/lang/String;[Ljava/lang/Object;)Ljava/lang/String;
      63: invokeinterface #14,  2           // InterfaceMethod org/apache/juli/logging/Log.debug:(Ljava/lang/Object;)V
      68: aload_0
      69: getfield      #4                  // Field stream:Lorg/apache/coyote/http2/Stream;
      72: dup
      73: astore_2
      74: monitorenter
      75: iload_1
      76: aload_0
      77: getfield      #3                  // Field waitingFor:I
      80: iand
      81: ifle          236
      84: aload_0
      85: iconst_0
      86: putfield      #3                  // Field waitingFor:I
      89: aload_0
      90: getfield      #4                  // Field stream:Lorg/apache/coyote/http2/Stream;
      93: invokevirtual #29                 // Method org/apache/coyote/http2/Stream.getCoyoteResponse:()Lorg/apache/coyote/Response;
      96: astore_3
      97: aload_3
      98: ifnull        236
     101: aload_3
     102: invokevirtual #30                 // Method org/apache/coyote/Response.getWriteListener:()Ljavax/servlet/WriteListener;
     105: ifnonnull     169
     108: getstatic     #5                  // Field log:Lorg/apache/juli/logging/Log;
     111: invokeinterface #6,  1            // InterfaceMethod org/apache/juli/logging/Log.isDebugEnabled:()Z
     116: ifeq          159
     119: getstatic     #5                  // Field log:Lorg/apache/juli/logging/Log;
     122: getstatic     #7                  // Field sm:Lorg/apache/tomcat/util/res/StringManager;
     125: ldc           #31                 // String windowAllocationManager.notified
     127: iconst_2
     128: anewarray     #9                  // class java/lang/Object
     131: dup
     132: iconst_0
     133: aload_0
     134: getfield      #4                  // Field stream:Lorg/apache/coyote/http2/Stream;
     137: invokevirtual #10                 // Method org/apache/coyote/http2/Stream.getConnectionId:()Ljava/lang/String;
     140: aastore
     141: dup
     142: iconst_1
     143: aload_0
     144: getfield      #4                  // Field stream:Lorg/apache/coyote/http2/Stream;
     147: invokevirtual #11                 // Method org/apache/coyote/http2/Stream.getIdentifier:()Ljava/lang/Integer;
     150: aastore
     151: invokevirtual #13                 // Method org/apache/tomcat/util/res/StringManager.getString:(Ljava/lang/String;[Ljava/lang/Object;)Ljava/lang/String;
     154: invokeinterface #14,  2           // InterfaceMethod org/apache/juli/logging/Log.debug:(Ljava/lang/Object;)V
     159: aload_0
     160: getfield      #4                  // Field stream:Lorg/apache/coyote/http2/Stream;
     163: invokevirtual #32                 // Method java/lang/Object.notify:()V
     166: goto          236
     169: getstatic     #5                  // Field log:Lorg/apache/juli/logging/Log;
     172: invokeinterface #6,  1            // InterfaceMethod org/apache/juli/logging/Log.isDebugEnabled:()Z
     177: ifeq          220
     180: getstatic     #5                  // Field log:Lorg/apache/juli/logging/Log;
     183: getstatic     #7                  // Field sm:Lorg/apache/tomcat/util/res/StringManager;
     186: ldc           #33                 // String windowAllocationManager.dispatched
     188: iconst_2
     189: anewarray     #9                  // class java/lang/Object
     192: dup
     193: iconst_0
     194: aload_0
     195: getfield      #4                  // Field stream:Lorg/apache/coyote/http2/Stream;
     198: invokevirtual #10                 // Method org/apache/coyote/http2/Stream.getConnectionId:()Ljava/lang/String;
     201: aastore
     202: dup
     203: iconst_1
     204: aload_0
     205: getfield      #4                  // Field stream:Lorg/apache/coyote/http2/Stream;
     208: invokevirtual #11                 // Method org/apache/coyote/http2/Stream.getIdentifier:()Ljava/lang/Integer;
     211: aastore
     212: invokevirtual #13                 // Method org/apache/tomcat/util/res/StringManager.getString:(Ljava/lang/String;[Ljava/lang/Object;)Ljava/lang/String;
     215: invokeinterface #14,  2           // InterfaceMethod org/apache/juli/logging/Log.debug:(Ljava/lang/Object;)V
     220: aload_3
     221: getstatic     #34                 // Field org/apache/coyote/ActionCode.DISPATCH_WRITE:Lorg/apache/coyote/ActionCode;
     224: aconst_null
     225: invokevirtual #35                 // Method org/apache/coyote/Response.action:(Lorg/apache/coyote/ActionCode;Ljava/lang/Object;)V
     228: aload_3
     229: getstatic     #36                 // Field org/apache/coyote/ActionCode.DISPATCH_EXECUTE:Lorg/apache/coyote/ActionCode;
     232: aconst_null
     233: invokevirtual #35                 // Method org/apache/coyote/Response.action:(Lorg/apache/coyote/ActionCode;Ljava/lang/Object;)V
     236: aload_2
     237: monitorexit
     238: goto          248
     241: astore        4
     243: aload_2
     244: monitorexit
     245: aload         4
     247: athrow
     248: return
    Exception table:
       from    to  target type
          75   238   241   any
         241   245   241   any

  static {};
    Code:
       0: ldc           #2                  // class org/apache/coyote/http2/WindowAllocationManager
       2: invokestatic  #37                 // Method org/apache/juli/logging/LogFactory.getLog:(Ljava/lang/Class;)Lorg/apache/juli/logging/Log;
       5: putstatic     #5                  // Field log:Lorg/apache/juli/logging/Log;
       8: ldc           #2                  // class org/apache/coyote/http2/WindowAllocationManager
      10: invokestatic  #38                 // Method org/apache/tomcat/util/res/StringManager.getManager:(Ljava/lang/Class;)Lorg/apache/tomcat/util/res/StringManager;
      13: putstatic     #7                  // Field sm:Lorg/apache/tomcat/util/res/StringManager;
      16: return
}
