Compiled from "SimplePrincipalMappingProvider.java"
public class org.jboss.security.mapping.providers.principal.SimplePrincipalMappingProvider extends org.jboss.security.mapping.providers.principal.AbstractPrincipalMappingProvider {
  private static final java.lang.String PRINCIPALS_MAP;

  private org.jboss.security.mapping.MappingResult<java.security.Principal> result;

  java.util.Properties principalMapProperties;

  public org.jboss.security.mapping.providers.principal.SimplePrincipalMappingProvider();
    Code:
       0: aload_0
       1: invokespecial #1                  // Method org/jboss/security/mapping/providers/principal/AbstractPrincipalMappingProvider."<init>":()V
       4: aload_0
       5: aconst_null
       6: putfield      #2                  // Field principalMapProperties:Ljava/util/Properties;
       9: return

  public void init(java.util.Map<java.lang.String, java.lang.Object>);
    Code:
       0: aload_1
       1: ifnull        30
       4: aload_1
       5: ldc           #4                  // String principalsMap
       7: invokeinterface #5,  2            // InterfaceMethod java/util/Map.containsKey:(Ljava/lang/Object;)Z
      12: ifeq          30
      15: aload_0
      16: aload_1
      17: ldc           #4                  // String principalsMap
      19: invokeinterface #6,  2            // InterfaceMethod java/util/Map.get:(Ljava/lang/Object;)Ljava/lang/Object;
      24: checkcast     #7                  // class java/util/Properties
      27: putfield      #2                  // Field principalMapProperties:Ljava/util/Properties;
      30: return

  public void performMapping(java.util.Map<java.lang.String, java.lang.Object>, java.security.Principal);
    Code:
       0: aload_2
       1: instanceof    #8                  // class org/jboss/security/SimplePrincipal
       4: ifne          8
       7: return
       8: aload_2
       9: checkcast     #8                  // class org/jboss/security/SimplePrincipal
      12: astore_3
      13: aload_0
      14: getfield      #2                  // Field principalMapProperties:Ljava/util/Properties;
      17: ifnull        62
      20: aload_0
      21: getfield      #2                  // Field principalMapProperties:Ljava/util/Properties;
      24: aload_3
      25: invokevirtual #9                  // Method org/jboss/security/SimplePrincipal.getName:()Ljava/lang/String;
      28: invokevirtual #10                 // Method java/util/Properties.getProperty:(Ljava/lang/String;)Ljava/lang/String;
      31: astore        4
      33: aload         4
      35: ifnull        62
      38: aload         4
      40: invokevirtual #11                 // Method java/lang/String.length:()I
      43: ifle          62
      46: aload_0
      47: getfield      #12                 // Field result:Lorg/jboss/security/mapping/MappingResult;
      50: new           #8                  // class org/jboss/security/SimplePrincipal
      53: dup
      54: aload         4
      56: invokespecial #13                 // Method org/jboss/security/SimplePrincipal."<init>":(Ljava/lang/String;)V
      59: invokevirtual #14                 // Method org/jboss/security/mapping/MappingResult.setMappedObject:(Ljava/lang/Object;)V
      62: return

  public void setMappingResult(org.jboss.security.mapping.MappingResult<java.security.Principal>);
    Code:
       0: aload_0
       1: aload_1
       2: putfield      #12                 // Field result:Lorg/jboss/security/mapping/MappingResult;
       5: return

  public void performMapping(java.util.Map, java.lang.Object);
    Code:
       0: aload_0
       1: aload_1
       2: aload_2
       3: checkcast     #15                 // class java/security/Principal
       6: invokevirtual #16                 // Method performMapping:(Ljava/util/Map;Ljava/security/Principal;)V
       9: return
}
