Compiled from "CommonTlsContextUtil.java"
public final class io.grpc.xds.internal.sds.CommonTlsContextUtil {
  private io.grpc.xds.internal.sds.CommonTlsContextUtil();
    Code:
       0: aload_0
       1: invokespecial #20                 // Method java/lang/Object."<init>":()V
       4: return

  static boolean hasCertProviderInstance(io.grpc.xds.shaded.io.envoyproxy.envoy.extensions.transport_sockets.tls.v3.CommonTlsContext);
    Code:
       0: aload_0
       1: ifnull        22
       4: aload_0
       5: invokevirtual #28                 // Method io/grpc/xds/shaded/io/envoyproxy/envoy/extensions/transport_sockets/tls/v3/CommonTlsContext.hasTlsCertificateCertificateProviderInstance:()Z
       8: ifne          18
      11: aload_0
      12: invokestatic  #31                 // Method hasCertProviderValidationContext:(Lio/grpc/xds/shaded/io/envoyproxy/envoy/extensions/transport_sockets/tls/v3/CommonTlsContext;)Z
      15: ifeq          22
      18: iconst_1
      19: goto          23
      22: iconst_0
      23: ireturn

  private static boolean hasCertProviderValidationContext(io.grpc.xds.shaded.io.envoyproxy.envoy.extensions.transport_sockets.tls.v3.CommonTlsContext);
    Code:
       0: aload_0
       1: invokevirtual #36                 // Method io/grpc/xds/shaded/io/envoyproxy/envoy/extensions/transport_sockets/tls/v3/CommonTlsContext.hasCombinedValidationContext:()Z
       4: ifeq          17
       7: aload_0
       8: invokevirtual #40                 // Method io/grpc/xds/shaded/io/envoyproxy/envoy/extensions/transport_sockets/tls/v3/CommonTlsContext.getCombinedValidationContext:()Lio/grpc/xds/shaded/io/envoyproxy/envoy/extensions/transport_sockets/tls/v3/CommonTlsContext$CombinedCertificateValidationContext;
      11: astore_1
      12: aload_1
      13: invokevirtual #43                 // Method io/grpc/xds/shaded/io/envoyproxy/envoy/extensions/transport_sockets/tls/v3/CommonTlsContext$CombinedCertificateValidationContext.hasValidationContextCertificateProviderInstance:()Z
      16: ireturn
      17: aload_0
      18: invokevirtual #44                 // Method io/grpc/xds/shaded/io/envoyproxy/envoy/extensions/transport_sockets/tls/v3/CommonTlsContext.hasValidationContextCertificateProviderInstance:()Z
      21: ireturn

  public static io.grpc.xds.shaded.io.envoyproxy.envoy.extensions.transport_sockets.tls.v3.CommonTlsContext$CertificateProviderInstance convert(io.grpc.xds.shaded.io.envoyproxy.envoy.extensions.transport_sockets.tls.v3.CertificateProviderPluginInstance);
    Code:
       0: invokestatic  #52                 // Method io/grpc/xds/shaded/io/envoyproxy/envoy/extensions/transport_sockets/tls/v3/CommonTlsContext$CertificateProviderInstance.newBuilder:()Lio/grpc/xds/shaded/io/envoyproxy/envoy/extensions/transport_sockets/tls/v3/CommonTlsContext$CertificateProviderInstance$Builder;
       3: aload_0
       4: invokevirtual #58                 // Method io/grpc/xds/shaded/io/envoyproxy/envoy/extensions/transport_sockets/tls/v3/CertificateProviderPluginInstance.getInstanceName:()Ljava/lang/String;
       7: invokevirtual #62                 // Method io/grpc/xds/shaded/io/envoyproxy/envoy/extensions/transport_sockets/tls/v3/CommonTlsContext$CertificateProviderInstance$Builder.setInstanceName:(Ljava/lang/String;)Lio/grpc/xds/shaded/io/envoyproxy/envoy/extensions/transport_sockets/tls/v3/CommonTlsContext$CertificateProviderInstance$Builder;
      10: aload_0
      11: invokevirtual #65                 // Method io/grpc/xds/shaded/io/envoyproxy/envoy/extensions/transport_sockets/tls/v3/CertificateProviderPluginInstance.getCertificateName:()Ljava/lang/String;
      14: invokevirtual #68                 // Method io/grpc/xds/shaded/io/envoyproxy/envoy/extensions/transport_sockets/tls/v3/CommonTlsContext$CertificateProviderInstance$Builder.setCertificateName:(Ljava/lang/String;)Lio/grpc/xds/shaded/io/envoyproxy/envoy/extensions/transport_sockets/tls/v3/CommonTlsContext$CertificateProviderInstance$Builder;
      17: invokevirtual #72                 // Method io/grpc/xds/shaded/io/envoyproxy/envoy/extensions/transport_sockets/tls/v3/CommonTlsContext$CertificateProviderInstance$Builder.build:()Lio/grpc/xds/shaded/io/envoyproxy/envoy/extensions/transport_sockets/tls/v3/CommonTlsContext$CertificateProviderInstance;
      20: areturn
}
