Compiled from "TableParagraphPreProcessor.java"
final class com.vladsch.flexmark.ext.tables.internal.TableParagraphPreProcessor$1 implements com.vladsch.flexmark.parser.block.CharacterNodeFactory {
  com.vladsch.flexmark.ext.tables.internal.TableParagraphPreProcessor$1();
    Code:
       0: aload_0
       1: invokespecial #1                  // Method java/lang/Object."<init>":()V
       4: return

  public boolean skipNext(char);
    Code:
       0: iload_1
       1: bipush        32
       3: if_icmpeq     12
       6: iload_1
       7: bipush        9
       9: if_icmpne     16
      12: iconst_1
      13: goto          17
      16: iconst_0
      17: ireturn

  public boolean skipPrev(char);
    Code:
       0: iload_1
       1: bipush        32
       3: if_icmpeq     12
       6: iload_1
       7: bipush        9
       9: if_icmpne     16
      12: iconst_1
      13: goto          17
      16: iconst_0
      17: ireturn

  public boolean wantSkippedWhitespace();
    Code:
       0: iconst_1
       1: ireturn

  public com.vladsch.flexmark.ast.Node create();
    Code:
       0: new           #2                  // class com/vladsch/flexmark/ext/tables/internal/TableColumnSeparator
       3: dup
       4: invokespecial #3                  // Method com/vladsch/flexmark/ext/tables/internal/TableColumnSeparator."<init>":()V
       7: areturn

  public java.lang.Object create();
    Code:
       0: aload_0
       1: invokevirtual #4                  // Method create:()Lcom/vladsch/flexmark/ast/Node;
       4: areturn
}
