Compiled from "JodaTimeConverters.java"
public final class org.springframework.data.convert.JodaTimeConverters$LocalDateTimeToJodaLocalDateTime extends java.lang.Enum<org.springframework.data.convert.JodaTimeConverters$LocalDateTimeToJodaLocalDateTime> implements org.springframework.core.convert.converter.Converter<java.time.LocalDateTime, org.joda.time.LocalDateTime> {
  public static final org.springframework.data.convert.JodaTimeConverters$LocalDateTimeToJodaLocalDateTime INSTANCE;

  private static final org.springframework.data.convert.JodaTimeConverters$LocalDateTimeToJodaLocalDateTime[] $VALUES;

  public static org.springframework.data.convert.JodaTimeConverters$LocalDateTimeToJodaLocalDateTime[] values();
    Code:
       0: getstatic     #1                  // Field $VALUES:[Lorg/springframework/data/convert/JodaTimeConverters$LocalDateTimeToJodaLocalDateTime;
       3: invokevirtual #2                  // Method "[Lorg/springframework/data/convert/JodaTimeConverters$LocalDateTimeToJodaLocalDateTime;".clone:()Ljava/lang/Object;
       6: checkcast     #3                  // class "[Lorg/springframework/data/convert/JodaTimeConverters$LocalDateTimeToJodaLocalDateTime;"
       9: areturn

  public static org.springframework.data.convert.JodaTimeConverters$LocalDateTimeToJodaLocalDateTime valueOf(java.lang.String);
    Code:
       0: ldc           #4                  // class org/springframework/data/convert/JodaTimeConverters$LocalDateTimeToJodaLocalDateTime
       2: aload_0
       3: invokestatic  #5                  // Method java/lang/Enum.valueOf:(Ljava/lang/Class;Ljava/lang/String;)Ljava/lang/Enum;
       6: checkcast     #4                  // class org/springframework/data/convert/JodaTimeConverters$LocalDateTimeToJodaLocalDateTime
       9: areturn

  private org.springframework.data.convert.JodaTimeConverters$LocalDateTimeToJodaLocalDateTime();
    Code:
       0: aload_0
       1: aload_1
       2: iload_2
       3: invokespecial #6                  // Method java/lang/Enum."<init>":(Ljava/lang/String;I)V
       6: return

  public org.joda.time.LocalDateTime convert(java.time.LocalDateTime);
    Code:
       0: getstatic     #7                  // Field org/springframework/data/convert/Jsr310Converters$LocalDateTimeToDateConverter.INSTANCE:Lorg/springframework/data/convert/Jsr310Converters$LocalDateTimeToDateConverter;
       3: aload_1
       4: invokevirtual #8                  // Method org/springframework/data/convert/Jsr310Converters$LocalDateTimeToDateConverter.convert:(Ljava/time/LocalDateTime;)Ljava/util/Date;
       7: invokestatic  #9                  // Method org/joda/time/LocalDateTime.fromDateFields:(Ljava/util/Date;)Lorg/joda/time/LocalDateTime;
      10: areturn

  public java.lang.Object convert(java.lang.Object);
    Code:
       0: aload_0
       1: aload_1
       2: checkcast     #10                 // class java/time/LocalDateTime
       5: invokevirtual #11                 // Method convert:(Ljava/time/LocalDateTime;)Lorg/joda/time/LocalDateTime;
       8: areturn

  static {};
    Code:
       0: new           #4                  // class org/springframework/data/convert/JodaTimeConverters$LocalDateTimeToJodaLocalDateTime
       3: dup
       4: ldc           #12                 // String INSTANCE
       6: iconst_0
       7: invokespecial #13                 // Method "<init>":(Ljava/lang/String;I)V
      10: putstatic     #14                 // Field INSTANCE:Lorg/springframework/data/convert/JodaTimeConverters$LocalDateTimeToJodaLocalDateTime;
      13: iconst_1
      14: anewarray     #4                  // class org/springframework/data/convert/JodaTimeConverters$LocalDateTimeToJodaLocalDateTime
      17: dup
      18: iconst_0
      19: getstatic     #14                 // Field INSTANCE:Lorg/springframework/data/convert/JodaTimeConverters$LocalDateTimeToJodaLocalDateTime;
      22: aastore
      23: putstatic     #1                  // Field $VALUES:[Lorg/springframework/data/convert/JodaTimeConverters$LocalDateTimeToJodaLocalDateTime;
      26: return
}
