Compiled from "GroupBy.java"
public final class cool.scx.sql.group_by.GroupBy {
  private final java.util.List<cool.scx.sql.group_by.GroupByBody> groupByBodyList;

  public cool.scx.sql.group_by.GroupBy();
    Code:
       0: aload_0
       1: invokespecial #1                  // Method java/lang/Object."<init>":()V
       4: aload_0
       5: new           #7                  // class java/util/ArrayList
       8: dup
       9: invokespecial #9                  // Method java/util/ArrayList."<init>":()V
      12: putfield      #10                 // Field groupByBodyList:Ljava/util/List;
      15: return

  public cool.scx.sql.group_by.GroupBy(cool.scx.sql.group_by.GroupBy);
    Code:
       0: aload_0
       1: invokespecial #1                  // Method java/lang/Object."<init>":()V
       4: aload_0
       5: new           #7                  // class java/util/ArrayList
       8: dup
       9: aload_1
      10: getfield      #10                 // Field groupByBodyList:Ljava/util/List;
      13: invokespecial #16                 // Method java/util/ArrayList."<init>":(Ljava/util/Collection;)V
      16: putfield      #10                 // Field groupByBodyList:Ljava/util/List;
      19: return

  public cool.scx.sql.group_by.GroupBy add(java.lang.String, cool.scx.sql.group_by.GroupByOption...);
    Code:
       0: new           #19                 // class cool/scx/sql/group_by/GroupByOption$Info
       3: dup
       4: aload_2
       5: invokespecial #21                 // Method cool/scx/sql/group_by/GroupByOption$Info."<init>":([Lcool/scx/sql/group_by/GroupByOption;)V
       8: astore_3
       9: new           #24                 // class cool/scx/sql/group_by/GroupByBody
      12: dup
      13: aload_1
      14: aload_3
      15: invokespecial #26                 // Method cool/scx/sql/group_by/GroupByBody."<init>":(Ljava/lang/String;Lcool/scx/sql/group_by/GroupByOption$Info;)V
      18: astore        4
      20: aload_0
      21: getfield      #10                 // Field groupByBodyList:Ljava/util/List;
      24: aload         4
      26: invokeinterface #29,  2           // InterfaceMethod java/util/List.add:(Ljava/lang/Object;)Z
      31: pop
      32: aload_0
      33: areturn

  public cool.scx.sql.group_by.GroupBy remove(java.lang.String);
    Code:
       0: aload_0
       1: getfield      #10                 // Field groupByBodyList:Ljava/util/List;
       4: aload_1
       5: invokedynamic #35,  0             // InvokeDynamic #0:test:(Ljava/lang/String;)Ljava/util/function/Predicate;
      10: invokeinterface #39,  2           // InterfaceMethod java/util/List.removeIf:(Ljava/util/function/Predicate;)Z
      15: pop
      16: aload_0
      17: areturn

  public cool.scx.sql.group_by.GroupBy clear();
    Code:
       0: aload_0
       1: getfield      #10                 // Field groupByBodyList:Ljava/util/List;
       4: invokeinterface #43,  1           // InterfaceMethod java/util/List.clear:()V
       9: aload_0
      10: areturn

  public java.lang.String[] getGroupByColumns();
    Code:
       0: aload_0
       1: getfield      #10                 // Field groupByBodyList:Ljava/util/List;
       4: invokeinterface #46,  1           // InterfaceMethod java/util/List.stream:()Ljava/util/stream/Stream;
       9: invokedynamic #50,  0             // InvokeDynamic #1:apply:()Ljava/util/function/Function;
      14: invokeinterface #54,  2           // InterfaceMethod java/util/stream/Stream.map:(Ljava/util/function/Function;)Ljava/util/stream/Stream;
      19: invokeinterface #60,  1           // InterfaceMethod java/util/stream/Stream.distinct:()Ljava/util/stream/Stream;
      24: invokedynamic #63,  0             // InvokeDynamic #2:apply:()Ljava/util/function/IntFunction;
      29: invokeinterface #66,  2           // InterfaceMethod java/util/stream/Stream.toArray:(Ljava/util/function/IntFunction;)[Ljava/lang/Object;
      34: checkcast     #70                 // class "[Ljava/lang/String;"
      37: areturn

  private static java.lang.String[] lambda$getGroupByColumns$1(int);
    Code:
       0: iload_0
       1: anewarray     #72                 // class java/lang/String
       4: areturn

  private static boolean lambda$remove$0(java.lang.String, cool.scx.sql.group_by.GroupByBody);
    Code:
       0: aload_1
       1: invokevirtual #74                 // Method cool/scx/sql/group_by/GroupByBody.name:()Ljava/lang/String;
       4: aload_0
       5: invokevirtual #78                 // Method java/lang/String.trim:()Ljava/lang/String;
       8: invokevirtual #81                 // Method java/lang/String.equals:(Ljava/lang/Object;)Z
      11: ireturn
}
