Compiled from "DecisionTypeEnumeration.java"
public final class org.opensaml.saml.saml2.core.DecisionTypeEnumeration {
  public static final org.opensaml.saml.saml2.core.DecisionTypeEnumeration PERMIT;

  public static final org.opensaml.saml.saml2.core.DecisionTypeEnumeration DENY;

  public static final org.opensaml.saml.saml2.core.DecisionTypeEnumeration INDETERMINATE;

  private java.lang.String decisionType;

  protected org.opensaml.saml.saml2.core.DecisionTypeEnumeration(java.lang.String);
    Code:
       0: aload_0
       1: invokespecial #1                  // Method java/lang/Object."<init>":()V
       4: aload_0
       5: aload_1
       6: putfield      #2                  // Field decisionType:Ljava/lang/String;
       9: return

  public java.lang.String toString();
    Code:
       0: aload_0
       1: getfield      #2                  // Field decisionType:Ljava/lang/String;
       4: areturn

  static {};
    Code:
       0: new           #3                  // class org/opensaml/saml/saml2/core/DecisionTypeEnumeration
       3: dup
       4: ldc           #4                  // String Permit
       6: invokespecial #5                  // Method "<init>":(Ljava/lang/String;)V
       9: putstatic     #6                  // Field PERMIT:Lorg/opensaml/saml/saml2/core/DecisionTypeEnumeration;
      12: new           #3                  // class org/opensaml/saml/saml2/core/DecisionTypeEnumeration
      15: dup
      16: ldc           #7                  // String Deny
      18: invokespecial #5                  // Method "<init>":(Ljava/lang/String;)V
      21: putstatic     #8                  // Field DENY:Lorg/opensaml/saml/saml2/core/DecisionTypeEnumeration;
      24: new           #3                  // class org/opensaml/saml/saml2/core/DecisionTypeEnumeration
      27: dup
      28: ldc           #9                  // String Indeterminate
      30: invokespecial #5                  // Method "<init>":(Ljava/lang/String;)V
      33: putstatic     #10                 // Field INDETERMINATE:Lorg/opensaml/saml/saml2/core/DecisionTypeEnumeration;
      36: return
}
