Compiled from "AssociateBrowserSettingsRequest.scala"
public interface zio.aws.workspacesweb.model.AssociateBrowserSettingsRequest$ReadOnly {
  public static zio.aws.workspacesweb.model.AssociateBrowserSettingsRequest asEditable$(zio.aws.workspacesweb.model.AssociateBrowserSettingsRequest$ReadOnly);
    Code:
       0: aload_0
       1: invokespecial #20                 // InterfaceMethod asEditable:()Lzio/aws/workspacesweb/model/AssociateBrowserSettingsRequest;
       4: areturn

  public default zio.aws.workspacesweb.model.AssociateBrowserSettingsRequest asEditable();
    Code:
       0: new           #12                 // class zio/aws/workspacesweb/model/AssociateBrowserSettingsRequest
       3: dup
       4: aload_0
       5: invokeinterface #25,  1           // InterfaceMethod browserSettingsArn:()Ljava/lang/String;
      10: aload_0
      11: invokeinterface #28,  1           // InterfaceMethod portalArn:()Ljava/lang/String;
      16: invokespecial #32                 // Method zio/aws/workspacesweb/model/AssociateBrowserSettingsRequest."<init>":(Ljava/lang/String;Ljava/lang/String;)V
      19: areturn

  public abstract java.lang.String browserSettingsArn();

  public abstract java.lang.String portalArn();

  public static zio.ZIO getBrowserSettingsArn$(zio.aws.workspacesweb.model.AssociateBrowserSettingsRequest$ReadOnly);
    Code:
       0: aload_0
       1: invokespecial #39                 // InterfaceMethod getBrowserSettingsArn:()Lzio/ZIO;
       4: areturn

  public default zio.ZIO<java.lang.Object, scala.runtime.Nothing$, java.lang.String> getBrowserSettingsArn();
    Code:
       0: getstatic     #46                 // Field zio/ZIO$.MODULE$:Lzio/ZIO$;
       3: aload_0
       4: invokedynamic #67,  0             // InvokeDynamic #0:apply:(Lzio/aws/workspacesweb/model/AssociateBrowserSettingsRequest$ReadOnly;)Lscala/Function0;
       9: ldc           #69                 // String zio.aws.workspacesweb.model.AssociateBrowserSettingsRequest.ReadOnly.getBrowserSettingsArn(AssociateBrowserSettingsRequest.scala:36)
      11: invokevirtual #73                 // Method zio/ZIO$.succeed:(Lscala/Function0;Ljava/lang/Object;)Lzio/ZIO;
      14: areturn

  public static zio.ZIO getPortalArn$(zio.aws.workspacesweb.model.AssociateBrowserSettingsRequest$ReadOnly);
    Code:
       0: aload_0
       1: invokespecial #77                 // InterfaceMethod getPortalArn:()Lzio/ZIO;
       4: areturn

  public default zio.ZIO<java.lang.Object, scala.runtime.Nothing$, java.lang.String> getPortalArn();
    Code:
       0: getstatic     #46                 // Field zio/ZIO$.MODULE$:Lzio/ZIO$;
       3: aload_0
       4: invokedynamic #82,  0             // InvokeDynamic #1:apply:(Lzio/aws/workspacesweb/model/AssociateBrowserSettingsRequest$ReadOnly;)Lscala/Function0;
       9: ldc           #84                 // String zio.aws.workspacesweb.model.AssociateBrowserSettingsRequest.ReadOnly.getPortalArn(AssociateBrowserSettingsRequest.scala:37)
      11: invokevirtual #73                 // Method zio/ZIO$.succeed:(Lscala/Function0;Ljava/lang/Object;)Lzio/ZIO;
      14: areturn

  public static java.lang.String $anonfun$getBrowserSettingsArn$1(zio.aws.workspacesweb.model.AssociateBrowserSettingsRequest$ReadOnly);
    Code:
       0: aload_0
       1: invokeinterface #25,  1           // InterfaceMethod browserSettingsArn:()Ljava/lang/String;
       6: areturn

  public static java.lang.String $anonfun$getPortalArn$1(zio.aws.workspacesweb.model.AssociateBrowserSettingsRequest$ReadOnly);
    Code:
       0: aload_0
       1: invokeinterface #28,  1           // InterfaceMethod portalArn:()Ljava/lang/String;
       6: areturn

  public static void $init$(zio.aws.workspacesweb.model.AssociateBrowserSettingsRequest$ReadOnly);
    Code:
       0: return

  private static java.lang.Object $deserializeLambda$(java.lang.invoke.SerializedLambda);
    Code:
       0: aload_0
       1: invokedynamic #98,  0             // InvokeDynamic #2:lambdaDeserialize:(Ljava/lang/invoke/SerializedLambda;)Ljava/lang/Object;
       6: areturn
}
