Compiled from "GetIdentityProviderResponse.scala"
public final class zio.aws.workspacesweb.model.GetIdentityProviderResponse$Wrapper implements zio.aws.workspacesweb.model.GetIdentityProviderResponse$ReadOnly {
  private final scala.Option<zio.aws.workspacesweb.model.IdentityProvider$ReadOnly> identityProvider;

  public zio.aws.workspacesweb.model.GetIdentityProviderResponse asEditable();
    Code:
       0: aload_0
       1: invokestatic  #29                 // InterfaceMethod zio/aws/workspacesweb/model/GetIdentityProviderResponse$ReadOnly.asEditable$:(Lzio/aws/workspacesweb/model/GetIdentityProviderResponse$ReadOnly;)Lzio/aws/workspacesweb/model/GetIdentityProviderResponse;
       4: areturn

  public zio.ZIO<java.lang.Object, zio.aws.core.AwsError, zio.aws.workspacesweb.model.IdentityProvider$ReadOnly> getIdentityProvider();
    Code:
       0: aload_0
       1: invokestatic  #38                 // InterfaceMethod zio/aws/workspacesweb/model/GetIdentityProviderResponse$ReadOnly.getIdentityProvider$:(Lzio/aws/workspacesweb/model/GetIdentityProviderResponse$ReadOnly;)Lzio/ZIO;
       4: areturn

  public scala.Option<zio.aws.workspacesweb.model.IdentityProvider$ReadOnly> identityProvider();
    Code:
       0: aload_0
       1: getfield      #42                 // Field identityProvider:Lscala/Option;
       4: areturn

  public static final zio.aws.workspacesweb.model.IdentityProvider$ReadOnly $anonfun$identityProvider$1(software.amazon.awssdk.services.workspacesweb.model.IdentityProvider);
    Code:
       0: getstatic     #51                 // Field zio/aws/workspacesweb/model/IdentityProvider$.MODULE$:Lzio/aws/workspacesweb/model/IdentityProvider$;
       3: aload_0
       4: invokevirtual #54                 // Method zio/aws/workspacesweb/model/IdentityProvider$.wrap:(Lsoftware/amazon/awssdk/services/workspacesweb/model/IdentityProvider;)Lzio/aws/workspacesweb/model/IdentityProvider$ReadOnly;
       7: areturn

  public zio.aws.workspacesweb.model.GetIdentityProviderResponse$Wrapper(software.amazon.awssdk.services.workspacesweb.model.GetIdentityProviderResponse);
    Code:
       0: aload_0
       1: invokespecial #61                 // Method java/lang/Object."<init>":()V
       4: aload_0
       5: invokestatic  #65                 // InterfaceMethod zio/aws/workspacesweb/model/GetIdentityProviderResponse$ReadOnly.$init$:(Lzio/aws/workspacesweb/model/GetIdentityProviderResponse$ReadOnly;)V
       8: aload_0
       9: getstatic     #70                 // Field scala/Option$.MODULE$:Lscala/Option$;
      12: aload_1
      13: invokevirtual #75                 // Method software/amazon/awssdk/services/workspacesweb/model/GetIdentityProviderResponse.identityProvider:()Lsoftware/amazon/awssdk/services/workspacesweb/model/IdentityProvider;
      16: invokevirtual #79                 // Method scala/Option$.apply:(Ljava/lang/Object;)Lscala/Option;
      19: invokedynamic #97,  0             // InvokeDynamic #0:apply:()Lscala/Function1;
      24: invokevirtual #103                // Method scala/Option.map:(Lscala/Function1;)Lscala/Option;
      27: putfield      #42                 // Field identityProvider:Lscala/Option;
      30: return

  private static java.lang.Object $deserializeLambda$(java.lang.invoke.SerializedLambda);
    Code:
       0: aload_0
       1: invokedynamic #116,  0            // InvokeDynamic #1:lambdaDeserialize:(Ljava/lang/invoke/SerializedLambda;)Ljava/lang/Object;
       6: areturn
}
