Compiled from "GetIdentityProviderResponse.scala"
public interface zio.aws.workspacesweb.model.GetIdentityProviderResponse$ReadOnly {
  public static zio.aws.workspacesweb.model.GetIdentityProviderResponse asEditable$(zio.aws.workspacesweb.model.GetIdentityProviderResponse$ReadOnly);
    Code:
       0: aload_0
       1: invokespecial #24                 // InterfaceMethod asEditable:()Lzio/aws/workspacesweb/model/GetIdentityProviderResponse;
       4: areturn

  public default zio.aws.workspacesweb.model.GetIdentityProviderResponse asEditable();
    Code:
       0: new           #12                 // class zio/aws/workspacesweb/model/GetIdentityProviderResponse
       3: dup
       4: aload_0
       5: invokeinterface #29,  1           // InterfaceMethod identityProvider:()Lscala/Option;
      10: invokedynamic #50,  0             // InvokeDynamic #0:apply:()Lscala/Function1;
      15: invokevirtual #56                 // Method scala/Option.map:(Lscala/Function1;)Lscala/Option;
      18: invokespecial #60                 // Method zio/aws/workspacesweb/model/GetIdentityProviderResponse."<init>":(Lscala/Option;)V
      21: areturn

  public abstract scala.Option<zio.aws.workspacesweb.model.IdentityProvider$ReadOnly> identityProvider();

  public static zio.ZIO getIdentityProvider$(zio.aws.workspacesweb.model.GetIdentityProviderResponse$ReadOnly);
    Code:
       0: aload_0
       1: invokespecial #68                 // InterfaceMethod getIdentityProvider:()Lzio/ZIO;
       4: areturn

  public default zio.ZIO<java.lang.Object, zio.aws.core.AwsError, zio.aws.workspacesweb.model.IdentityProvider$ReadOnly> getIdentityProvider();
    Code:
       0: getstatic     #75                 // Field zio/aws/core/AwsError$.MODULE$:Lzio/aws/core/AwsError$;
       3: ldc           #76                 // String identityProvider
       5: aload_0
       6: invokedynamic #87,  0             // InvokeDynamic #1:apply:(Lzio/aws/workspacesweb/model/GetIdentityProviderResponse$ReadOnly;)Lscala/Function0;
      11: invokevirtual #91                 // Method zio/aws/core/AwsError$.unwrapOptionField:(Ljava/lang/String;Lscala/Function0;)Lzio/ZIO;
      14: areturn

  public static zio.aws.workspacesweb.model.IdentityProvider $anonfun$asEditable$1(zio.aws.workspacesweb.model.IdentityProvider$ReadOnly);
    Code:
       0: aload_0
       1: invokeinterface #95,  1           // InterfaceMethod zio/aws/workspacesweb/model/IdentityProvider$ReadOnly.asEditable:()Lzio/aws/workspacesweb/model/IdentityProvider;
       6: areturn

  public static scala.Option $anonfun$getIdentityProvider$1(zio.aws.workspacesweb.model.GetIdentityProviderResponse$ReadOnly);
    Code:
       0: aload_0
       1: invokeinterface #29,  1           // InterfaceMethod identityProvider:()Lscala/Option;
       6: areturn

  public static void $init$(zio.aws.workspacesweb.model.GetIdentityProviderResponse$ReadOnly);
    Code:
       0: return

  private static java.lang.Object $deserializeLambda$(java.lang.invoke.SerializedLambda);
    Code:
       0: aload_0
       1: invokedynamic #110,  0            // InvokeDynamic #2:lambdaDeserialize:(Ljava/lang/invoke/SerializedLambda;)Ljava/lang/Object;
       6: areturn
}
