Compiled from "GetPortalServiceProviderMetadataResponse.scala"
public final class zio.aws.workspacesweb.model.GetPortalServiceProviderMetadataResponse$Wrapper implements zio.aws.workspacesweb.model.GetPortalServiceProviderMetadataResponse$ReadOnly {
  private final java.lang.String portalArn;

  private final scala.Option<java.lang.String> serviceProviderSamlMetadata;

  public zio.aws.workspacesweb.model.GetPortalServiceProviderMetadataResponse asEditable();
    Code:
       0: aload_0
       1: invokestatic  #38                 // InterfaceMethod zio/aws/workspacesweb/model/GetPortalServiceProviderMetadataResponse$ReadOnly.asEditable$:(Lzio/aws/workspacesweb/model/GetPortalServiceProviderMetadataResponse$ReadOnly;)Lzio/aws/workspacesweb/model/GetPortalServiceProviderMetadataResponse;
       4: areturn

  public zio.ZIO<java.lang.Object, scala.runtime.Nothing$, java.lang.String> getPortalArn();
    Code:
       0: aload_0
       1: invokestatic  #47                 // InterfaceMethod zio/aws/workspacesweb/model/GetPortalServiceProviderMetadataResponse$ReadOnly.getPortalArn$:(Lzio/aws/workspacesweb/model/GetPortalServiceProviderMetadataResponse$ReadOnly;)Lzio/ZIO;
       4: areturn

  public zio.ZIO<java.lang.Object, zio.aws.core.AwsError, java.lang.String> getServiceProviderSamlMetadata();
    Code:
       0: aload_0
       1: invokestatic  #52                 // InterfaceMethod zio/aws/workspacesweb/model/GetPortalServiceProviderMetadataResponse$ReadOnly.getServiceProviderSamlMetadata$:(Lzio/aws/workspacesweb/model/GetPortalServiceProviderMetadataResponse$ReadOnly;)Lzio/ZIO;
       4: areturn

  public java.lang.String portalArn();
    Code:
       0: aload_0
       1: getfield      #55                 // Field portalArn:Ljava/lang/String;
       4: areturn

  public scala.Option<java.lang.String> serviceProviderSamlMetadata();
    Code:
       0: aload_0
       1: getfield      #59                 // Field serviceProviderSamlMetadata:Lscala/Option;
       4: areturn

  public static final java.lang.String $anonfun$serviceProviderSamlMetadata$1(java.lang.String);
    Code:
       0: getstatic     #68                 // Field zio/prelude/Newtype$.MODULE$:Lzio/prelude/Newtype$;
       3: getstatic     #71                 // Field zio/aws/workspacesweb/model/package$primitives$SamlMetadata$.MODULE$:Lzio/aws/workspacesweb/model/package$primitives$SamlMetadata$;
       6: aload_0
       7: invokevirtual #75                 // Method zio/prelude/Newtype$.unsafeWrap:(Lzio/prelude/Newtype;Ljava/lang/Object;)Ljava/lang/Object;
      10: checkcast     #77                 // class java/lang/String
      13: areturn

  public zio.aws.workspacesweb.model.GetPortalServiceProviderMetadataResponse$Wrapper(software.amazon.awssdk.services.workspacesweb.model.GetPortalServiceProviderMetadataResponse);
    Code:
       0: aload_0
       1: invokespecial #83                 // Method java/lang/Object."<init>":()V
       4: aload_0
       5: invokestatic  #87                 // InterfaceMethod zio/aws/workspacesweb/model/GetPortalServiceProviderMetadataResponse$ReadOnly.$init$:(Lzio/aws/workspacesweb/model/GetPortalServiceProviderMetadataResponse$ReadOnly;)V
       8: aload_0
       9: getstatic     #68                 // Field zio/prelude/Newtype$.MODULE$:Lzio/prelude/Newtype$;
      12: getstatic     #90                 // Field zio/aws/workspacesweb/model/package$primitives$ARN$.MODULE$:Lzio/aws/workspacesweb/model/package$primitives$ARN$;
      15: aload_1
      16: invokevirtual #94                 // Method software/amazon/awssdk/services/workspacesweb/model/GetPortalServiceProviderMetadataResponse.portalArn:()Ljava/lang/String;
      19: invokevirtual #75                 // Method zio/prelude/Newtype$.unsafeWrap:(Lzio/prelude/Newtype;Ljava/lang/Object;)Ljava/lang/Object;
      22: checkcast     #77                 // class java/lang/String
      25: putfield      #55                 // Field portalArn:Ljava/lang/String;
      28: aload_0
      29: getstatic     #99                 // Field scala/Option$.MODULE$:Lscala/Option$;
      32: aload_1
      33: invokevirtual #101                // Method software/amazon/awssdk/services/workspacesweb/model/GetPortalServiceProviderMetadataResponse.serviceProviderSamlMetadata:()Ljava/lang/String;
      36: invokevirtual #105                // Method scala/Option$.apply:(Ljava/lang/Object;)Lscala/Option;
      39: invokedynamic #123,  0            // InvokeDynamic #0:apply:()Lscala/Function1;
      44: invokevirtual #129                // Method scala/Option.map:(Lscala/Function1;)Lscala/Option;
      47: putfield      #59                 // Field serviceProviderSamlMetadata:Lscala/Option;
      50: return

  private static java.lang.Object $deserializeLambda$(java.lang.invoke.SerializedLambda);
    Code:
       0: aload_0
       1: invokedynamic #142,  0            // InvokeDynamic #1:lambdaDeserialize:(Ljava/lang/invoke/SerializedLambda;)Ljava/lang/Object;
       6: areturn
}
