Compiled from "PortalSummary.scala"
public interface zio.aws.workspacesweb.model.PortalSummary$ReadOnly {
  public static zio.aws.workspacesweb.model.PortalSummary asEditable$(zio.aws.workspacesweb.model.PortalSummary$ReadOnly);
    Code:
       0: aload_0
       1: invokespecial #20                 // InterfaceMethod asEditable:()Lzio/aws/workspacesweb/model/PortalSummary;
       4: areturn

  public default zio.aws.workspacesweb.model.PortalSummary asEditable();
    Code:
       0: new           #12                 // class zio/aws/workspacesweb/model/PortalSummary
       3: dup
       4: aload_0
       5: invokeinterface #25,  1           // InterfaceMethod browserSettingsArn:()Lscala/Option;
      10: invokedynamic #46,  0             // InvokeDynamic #0:apply:()Lscala/Function1;
      15: invokevirtual #52                 // Method scala/Option.map:(Lscala/Function1;)Lscala/Option;
      18: aload_0
      19: invokeinterface #55,  1           // InterfaceMethod browserType:()Lscala/Option;
      24: invokedynamic #62,  0             // InvokeDynamic #1:apply:()Lscala/Function1;
      29: invokevirtual #52                 // Method scala/Option.map:(Lscala/Function1;)Lscala/Option;
      32: aload_0
      33: invokeinterface #65,  1           // InterfaceMethod creationDate:()Lscala/Option;
      38: invokedynamic #72,  0             // InvokeDynamic #2:apply:()Lscala/Function1;
      43: invokevirtual #52                 // Method scala/Option.map:(Lscala/Function1;)Lscala/Option;
      46: aload_0
      47: invokeinterface #75,  1           // InterfaceMethod displayName:()Lscala/Option;
      52: invokedynamic #80,  0             // InvokeDynamic #3:apply:()Lscala/Function1;
      57: invokevirtual #52                 // Method scala/Option.map:(Lscala/Function1;)Lscala/Option;
      60: aload_0
      61: invokeinterface #83,  1           // InterfaceMethod networkSettingsArn:()Lscala/Option;
      66: invokedynamic #88,  0             // InvokeDynamic #4:apply:()Lscala/Function1;
      71: invokevirtual #52                 // Method scala/Option.map:(Lscala/Function1;)Lscala/Option;
      74: aload_0
      75: invokeinterface #91,  1           // InterfaceMethod portalArn:()Lscala/Option;
      80: invokedynamic #96,  0             // InvokeDynamic #5:apply:()Lscala/Function1;
      85: invokevirtual #52                 // Method scala/Option.map:(Lscala/Function1;)Lscala/Option;
      88: aload_0
      89: invokeinterface #99,  1           // InterfaceMethod portalEndpoint:()Lscala/Option;
      94: invokedynamic #104,  0            // InvokeDynamic #6:apply:()Lscala/Function1;
      99: invokevirtual #52                 // Method scala/Option.map:(Lscala/Function1;)Lscala/Option;
     102: aload_0
     103: invokeinterface #107,  1          // InterfaceMethod portalStatus:()Lscala/Option;
     108: invokedynamic #114,  0            // InvokeDynamic #7:apply:()Lscala/Function1;
     113: invokevirtual #52                 // Method scala/Option.map:(Lscala/Function1;)Lscala/Option;
     116: aload_0
     117: invokeinterface #117,  1          // InterfaceMethod rendererType:()Lscala/Option;
     122: invokedynamic #124,  0            // InvokeDynamic #8:apply:()Lscala/Function1;
     127: invokevirtual #52                 // Method scala/Option.map:(Lscala/Function1;)Lscala/Option;
     130: aload_0
     131: invokeinterface #127,  1          // InterfaceMethod trustStoreArn:()Lscala/Option;
     136: invokedynamic #132,  0            // InvokeDynamic #9:apply:()Lscala/Function1;
     141: invokevirtual #52                 // Method scala/Option.map:(Lscala/Function1;)Lscala/Option;
     144: aload_0
     145: invokeinterface #135,  1          // InterfaceMethod userSettingsArn:()Lscala/Option;
     150: invokedynamic #140,  0            // InvokeDynamic #10:apply:()Lscala/Function1;
     155: invokevirtual #52                 // Method scala/Option.map:(Lscala/Function1;)Lscala/Option;
     158: invokespecial #144                // Method zio/aws/workspacesweb/model/PortalSummary."<init>":(Lscala/Option;Lscala/Option;Lscala/Option;Lscala/Option;Lscala/Option;Lscala/Option;Lscala/Option;Lscala/Option;Lscala/Option;Lscala/Option;Lscala/Option;)V
     161: areturn

  public abstract scala.Option<java.lang.String> browserSettingsArn();

  public abstract scala.Option<zio.aws.workspacesweb.model.BrowserType> browserType();

  public abstract scala.Option<java.time.Instant> creationDate();

  public abstract scala.Option<java.lang.String> displayName();

  public abstract scala.Option<java.lang.String> networkSettingsArn();

  public abstract scala.Option<java.lang.String> portalArn();

  public abstract scala.Option<java.lang.String> portalEndpoint();

  public abstract scala.Option<zio.aws.workspacesweb.model.PortalStatus> portalStatus();

  public abstract scala.Option<zio.aws.workspacesweb.model.RendererType> rendererType();

  public abstract scala.Option<java.lang.String> trustStoreArn();

  public abstract scala.Option<java.lang.String> userSettingsArn();

  public static zio.ZIO getBrowserSettingsArn$(zio.aws.workspacesweb.model.PortalSummary$ReadOnly);
    Code:
       0: aload_0
       1: invokespecial #156                // InterfaceMethod getBrowserSettingsArn:()Lzio/ZIO;
       4: areturn

  public default zio.ZIO<java.lang.Object, zio.aws.core.AwsError, java.lang.String> getBrowserSettingsArn();
    Code:
       0: getstatic     #163                // Field zio/aws/core/AwsError$.MODULE$:Lzio/aws/core/AwsError$;
       3: ldc           #164                // String browserSettingsArn
       5: aload_0
       6: invokedynamic #175,  0            // InvokeDynamic #11:apply:(Lzio/aws/workspacesweb/model/PortalSummary$ReadOnly;)Lscala/Function0;
      11: invokevirtual #179                // Method zio/aws/core/AwsError$.unwrapOptionField:(Ljava/lang/String;Lscala/Function0;)Lzio/ZIO;
      14: areturn

  public static zio.ZIO getBrowserType$(zio.aws.workspacesweb.model.PortalSummary$ReadOnly);
    Code:
       0: aload_0
       1: invokespecial #183                // InterfaceMethod getBrowserType:()Lzio/ZIO;
       4: areturn

  public default zio.ZIO<java.lang.Object, zio.aws.core.AwsError, zio.aws.workspacesweb.model.BrowserType> getBrowserType();
    Code:
       0: getstatic     #163                // Field zio/aws/core/AwsError$.MODULE$:Lzio/aws/core/AwsError$;
       3: ldc           #185                // String browserType
       5: aload_0
       6: invokedynamic #190,  0            // InvokeDynamic #12:apply:(Lzio/aws/workspacesweb/model/PortalSummary$ReadOnly;)Lscala/Function0;
      11: invokevirtual #179                // Method zio/aws/core/AwsError$.unwrapOptionField:(Ljava/lang/String;Lscala/Function0;)Lzio/ZIO;
      14: areturn

  public static zio.ZIO getCreationDate$(zio.aws.workspacesweb.model.PortalSummary$ReadOnly);
    Code:
       0: aload_0
       1: invokespecial #194                // InterfaceMethod getCreationDate:()Lzio/ZIO;
       4: areturn

  public default zio.ZIO<java.lang.Object, zio.aws.core.AwsError, java.time.Instant> getCreationDate();
    Code:
       0: getstatic     #163                // Field zio/aws/core/AwsError$.MODULE$:Lzio/aws/core/AwsError$;
       3: ldc           #196                // String creationDate
       5: aload_0
       6: invokedynamic #201,  0            // InvokeDynamic #13:apply:(Lzio/aws/workspacesweb/model/PortalSummary$ReadOnly;)Lscala/Function0;
      11: invokevirtual #179                // Method zio/aws/core/AwsError$.unwrapOptionField:(Ljava/lang/String;Lscala/Function0;)Lzio/ZIO;
      14: areturn

  public static zio.ZIO getDisplayName$(zio.aws.workspacesweb.model.PortalSummary$ReadOnly);
    Code:
       0: aload_0
       1: invokespecial #205                // InterfaceMethod getDisplayName:()Lzio/ZIO;
       4: areturn

  public default zio.ZIO<java.lang.Object, zio.aws.core.AwsError, java.lang.String> getDisplayName();
    Code:
       0: getstatic     #163                // Field zio/aws/core/AwsError$.MODULE$:Lzio/aws/core/AwsError$;
       3: ldc           #206                // String displayName
       5: aload_0
       6: invokedynamic #211,  0            // InvokeDynamic #14:apply:(Lzio/aws/workspacesweb/model/PortalSummary$ReadOnly;)Lscala/Function0;
      11: invokevirtual #179                // Method zio/aws/core/AwsError$.unwrapOptionField:(Ljava/lang/String;Lscala/Function0;)Lzio/ZIO;
      14: areturn

  public static zio.ZIO getNetworkSettingsArn$(zio.aws.workspacesweb.model.PortalSummary$ReadOnly);
    Code:
       0: aload_0
       1: invokespecial #215                // InterfaceMethod getNetworkSettingsArn:()Lzio/ZIO;
       4: areturn

  public default zio.ZIO<java.lang.Object, zio.aws.core.AwsError, java.lang.String> getNetworkSettingsArn();
    Code:
       0: getstatic     #163                // Field zio/aws/core/AwsError$.MODULE$:Lzio/aws/core/AwsError$;
       3: ldc           #216                // String networkSettingsArn
       5: aload_0
       6: invokedynamic #221,  0            // InvokeDynamic #15:apply:(Lzio/aws/workspacesweb/model/PortalSummary$ReadOnly;)Lscala/Function0;
      11: invokevirtual #179                // Method zio/aws/core/AwsError$.unwrapOptionField:(Ljava/lang/String;Lscala/Function0;)Lzio/ZIO;
      14: areturn

  public static zio.ZIO getPortalArn$(zio.aws.workspacesweb.model.PortalSummary$ReadOnly);
    Code:
       0: aload_0
       1: invokespecial #225                // InterfaceMethod getPortalArn:()Lzio/ZIO;
       4: areturn

  public default zio.ZIO<java.lang.Object, zio.aws.core.AwsError, java.lang.String> getPortalArn();
    Code:
       0: getstatic     #163                // Field zio/aws/core/AwsError$.MODULE$:Lzio/aws/core/AwsError$;
       3: ldc           #226                // String portalArn
       5: aload_0
       6: invokedynamic #231,  0            // InvokeDynamic #16:apply:(Lzio/aws/workspacesweb/model/PortalSummary$ReadOnly;)Lscala/Function0;
      11: invokevirtual #179                // Method zio/aws/core/AwsError$.unwrapOptionField:(Ljava/lang/String;Lscala/Function0;)Lzio/ZIO;
      14: areturn

  public static zio.ZIO getPortalEndpoint$(zio.aws.workspacesweb.model.PortalSummary$ReadOnly);
    Code:
       0: aload_0
       1: invokespecial #235                // InterfaceMethod getPortalEndpoint:()Lzio/ZIO;
       4: areturn

  public default zio.ZIO<java.lang.Object, zio.aws.core.AwsError, java.lang.String> getPortalEndpoint();
    Code:
       0: getstatic     #163                // Field zio/aws/core/AwsError$.MODULE$:Lzio/aws/core/AwsError$;
       3: ldc           #236                // String portalEndpoint
       5: aload_0
       6: invokedynamic #241,  0            // InvokeDynamic #17:apply:(Lzio/aws/workspacesweb/model/PortalSummary$ReadOnly;)Lscala/Function0;
      11: invokevirtual #179                // Method zio/aws/core/AwsError$.unwrapOptionField:(Ljava/lang/String;Lscala/Function0;)Lzio/ZIO;
      14: areturn

  public static zio.ZIO getPortalStatus$(zio.aws.workspacesweb.model.PortalSummary$ReadOnly);
    Code:
       0: aload_0
       1: invokespecial #245                // InterfaceMethod getPortalStatus:()Lzio/ZIO;
       4: areturn

  public default zio.ZIO<java.lang.Object, zio.aws.core.AwsError, zio.aws.workspacesweb.model.PortalStatus> getPortalStatus();
    Code:
       0: getstatic     #163                // Field zio/aws/core/AwsError$.MODULE$:Lzio/aws/core/AwsError$;
       3: ldc           #247                // String portalStatus
       5: aload_0
       6: invokedynamic #252,  0            // InvokeDynamic #18:apply:(Lzio/aws/workspacesweb/model/PortalSummary$ReadOnly;)Lscala/Function0;
      11: invokevirtual #179                // Method zio/aws/core/AwsError$.unwrapOptionField:(Ljava/lang/String;Lscala/Function0;)Lzio/ZIO;
      14: areturn

  public static zio.ZIO getRendererType$(zio.aws.workspacesweb.model.PortalSummary$ReadOnly);
    Code:
       0: aload_0
       1: invokespecial #256                // InterfaceMethod getRendererType:()Lzio/ZIO;
       4: areturn

  public default zio.ZIO<java.lang.Object, zio.aws.core.AwsError, zio.aws.workspacesweb.model.RendererType> getRendererType();
    Code:
       0: getstatic     #163                // Field zio/aws/core/AwsError$.MODULE$:Lzio/aws/core/AwsError$;
       3: ldc_w         #258                // String rendererType
       6: aload_0
       7: invokedynamic #263,  0            // InvokeDynamic #19:apply:(Lzio/aws/workspacesweb/model/PortalSummary$ReadOnly;)Lscala/Function0;
      12: invokevirtual #179                // Method zio/aws/core/AwsError$.unwrapOptionField:(Ljava/lang/String;Lscala/Function0;)Lzio/ZIO;
      15: areturn

  public static zio.ZIO getTrustStoreArn$(zio.aws.workspacesweb.model.PortalSummary$ReadOnly);
    Code:
       0: aload_0
       1: invokespecial #267                // InterfaceMethod getTrustStoreArn:()Lzio/ZIO;
       4: areturn

  public default zio.ZIO<java.lang.Object, zio.aws.core.AwsError, java.lang.String> getTrustStoreArn();
    Code:
       0: getstatic     #163                // Field zio/aws/core/AwsError$.MODULE$:Lzio/aws/core/AwsError$;
       3: ldc_w         #268                // String trustStoreArn
       6: aload_0
       7: invokedynamic #273,  0            // InvokeDynamic #20:apply:(Lzio/aws/workspacesweb/model/PortalSummary$ReadOnly;)Lscala/Function0;
      12: invokevirtual #179                // Method zio/aws/core/AwsError$.unwrapOptionField:(Ljava/lang/String;Lscala/Function0;)Lzio/ZIO;
      15: areturn

  public static zio.ZIO getUserSettingsArn$(zio.aws.workspacesweb.model.PortalSummary$ReadOnly);
    Code:
       0: aload_0
       1: invokespecial #277                // InterfaceMethod getUserSettingsArn:()Lzio/ZIO;
       4: areturn

  public default zio.ZIO<java.lang.Object, zio.aws.core.AwsError, java.lang.String> getUserSettingsArn();
    Code:
       0: getstatic     #163                // Field zio/aws/core/AwsError$.MODULE$:Lzio/aws/core/AwsError$;
       3: ldc_w         #278                // String userSettingsArn
       6: aload_0
       7: invokedynamic #283,  0            // InvokeDynamic #21:apply:(Lzio/aws/workspacesweb/model/PortalSummary$ReadOnly;)Lscala/Function0;
      12: invokevirtual #179                // Method zio/aws/core/AwsError$.unwrapOptionField:(Ljava/lang/String;Lscala/Function0;)Lzio/ZIO;
      15: areturn

  public static java.lang.String $anonfun$asEditable$1(java.lang.String);
    Code:
       0: aload_0
       1: areturn

  public static zio.aws.workspacesweb.model.BrowserType $anonfun$asEditable$2(zio.aws.workspacesweb.model.BrowserType);
    Code:
       0: aload_0
       1: areturn

  public static java.time.Instant $anonfun$asEditable$3(java.time.Instant);
    Code:
       0: aload_0
       1: areturn

  public static java.lang.String $anonfun$asEditable$4(java.lang.String);
    Code:
       0: aload_0
       1: areturn

  public static java.lang.String $anonfun$asEditable$5(java.lang.String);
    Code:
       0: aload_0
       1: areturn

  public static java.lang.String $anonfun$asEditable$6(java.lang.String);
    Code:
       0: aload_0
       1: areturn

  public static java.lang.String $anonfun$asEditable$7(java.lang.String);
    Code:
       0: aload_0
       1: areturn

  public static zio.aws.workspacesweb.model.PortalStatus $anonfun$asEditable$8(zio.aws.workspacesweb.model.PortalStatus);
    Code:
       0: aload_0
       1: areturn

  public static zio.aws.workspacesweb.model.RendererType $anonfun$asEditable$9(zio.aws.workspacesweb.model.RendererType);
    Code:
       0: aload_0
       1: areturn

  public static java.lang.String $anonfun$asEditable$10(java.lang.String);
    Code:
       0: aload_0
       1: areturn

  public static java.lang.String $anonfun$asEditable$11(java.lang.String);
    Code:
       0: aload_0
       1: areturn

  public static scala.Option $anonfun$getBrowserSettingsArn$1(zio.aws.workspacesweb.model.PortalSummary$ReadOnly);
    Code:
       0: aload_0
       1: invokeinterface #25,  1           // InterfaceMethod browserSettingsArn:()Lscala/Option;
       6: areturn

  public static scala.Option $anonfun$getBrowserType$1(zio.aws.workspacesweb.model.PortalSummary$ReadOnly);
    Code:
       0: aload_0
       1: invokeinterface #55,  1           // InterfaceMethod browserType:()Lscala/Option;
       6: areturn

  public static scala.Option $anonfun$getCreationDate$1(zio.aws.workspacesweb.model.PortalSummary$ReadOnly);
    Code:
       0: aload_0
       1: invokeinterface #65,  1           // InterfaceMethod creationDate:()Lscala/Option;
       6: areturn

  public static scala.Option $anonfun$getDisplayName$1(zio.aws.workspacesweb.model.PortalSummary$ReadOnly);
    Code:
       0: aload_0
       1: invokeinterface #75,  1           // InterfaceMethod displayName:()Lscala/Option;
       6: areturn

  public static scala.Option $anonfun$getNetworkSettingsArn$1(zio.aws.workspacesweb.model.PortalSummary$ReadOnly);
    Code:
       0: aload_0
       1: invokeinterface #83,  1           // InterfaceMethod networkSettingsArn:()Lscala/Option;
       6: areturn

  public static scala.Option $anonfun$getPortalArn$1(zio.aws.workspacesweb.model.PortalSummary$ReadOnly);
    Code:
       0: aload_0
       1: invokeinterface #91,  1           // InterfaceMethod portalArn:()Lscala/Option;
       6: areturn

  public static scala.Option $anonfun$getPortalEndpoint$1(zio.aws.workspacesweb.model.PortalSummary$ReadOnly);
    Code:
       0: aload_0
       1: invokeinterface #99,  1           // InterfaceMethod portalEndpoint:()Lscala/Option;
       6: areturn

  public static scala.Option $anonfun$getPortalStatus$1(zio.aws.workspacesweb.model.PortalSummary$ReadOnly);
    Code:
       0: aload_0
       1: invokeinterface #107,  1          // InterfaceMethod portalStatus:()Lscala/Option;
       6: areturn

  public static scala.Option $anonfun$getRendererType$1(zio.aws.workspacesweb.model.PortalSummary$ReadOnly);
    Code:
       0: aload_0
       1: invokeinterface #117,  1          // InterfaceMethod rendererType:()Lscala/Option;
       6: areturn

  public static scala.Option $anonfun$getTrustStoreArn$1(zio.aws.workspacesweb.model.PortalSummary$ReadOnly);
    Code:
       0: aload_0
       1: invokeinterface #127,  1          // InterfaceMethod trustStoreArn:()Lscala/Option;
       6: areturn

  public static scala.Option $anonfun$getUserSettingsArn$1(zio.aws.workspacesweb.model.PortalSummary$ReadOnly);
    Code:
       0: aload_0
       1: invokeinterface #135,  1          // InterfaceMethod userSettingsArn:()Lscala/Option;
       6: areturn

  public static void $init$(zio.aws.workspacesweb.model.PortalSummary$ReadOnly);
    Code:
       0: return

  private static java.lang.Object $deserializeLambda$(java.lang.invoke.SerializedLambda);
    Code:
       0: aload_0
       1: invokedynamic #303,  0            // InvokeDynamic #22:lambdaDeserialize:(Ljava/lang/invoke/SerializedLambda;)Ljava/lang/Object;
       6: areturn
}
