Compiled from "CloneMessage.java"
public class org.graylog.plugins.pipelineprocessor.functions.messages.CloneMessage extends org.graylog.plugins.pipelineprocessor.ast.functions.AbstractFunction<org.graylog2.plugin.Message> {
  private static final org.slf4j.Logger LOG;

  public static final java.lang.String NAME;

  private final org.graylog.plugins.pipelineprocessor.ast.functions.ParameterDescriptor<org.graylog2.plugin.Message, org.graylog2.plugin.Message> messageParam;

  public org.graylog.plugins.pipelineprocessor.functions.messages.CloneMessage();
    Code:
       0: aload_0
       1: invokespecial #1                  // Method org/graylog/plugins/pipelineprocessor/ast/functions/AbstractFunction."<init>":()V
       4: aload_0
       5: ldc           #2                  // String message
       7: ldc           #3                  // class org/graylog2/plugin/Message
       9: invokestatic  #4                  // Method org/graylog/plugins/pipelineprocessor/ast/functions/ParameterDescriptor.type:(Ljava/lang/String;Ljava/lang/Class;)Lorg/graylog/plugins/pipelineprocessor/ast/functions/ParameterDescriptor$Builder;
      12: invokevirtual #5                  // Method org/graylog/plugins/pipelineprocessor/ast/functions/ParameterDescriptor$Builder.optional:()Lorg/graylog/plugins/pipelineprocessor/ast/functions/ParameterDescriptor$Builder;
      15: ldc           #6                  // String The message to use, defaults to \'$message\'
      17: invokevirtual #7                  // Method org/graylog/plugins/pipelineprocessor/ast/functions/ParameterDescriptor$Builder.description:(Ljava/lang/String;)Lorg/graylog/plugins/pipelineprocessor/ast/functions/ParameterDescriptor$Builder;
      20: invokevirtual #8                  // Method org/graylog/plugins/pipelineprocessor/ast/functions/ParameterDescriptor$Builder.build:()Lorg/graylog/plugins/pipelineprocessor/ast/functions/ParameterDescriptor;
      23: putfield      #9                  // Field messageParam:Lorg/graylog/plugins/pipelineprocessor/ast/functions/ParameterDescriptor;
      26: return

  public org.graylog2.plugin.Message evaluate(org.graylog.plugins.pipelineprocessor.ast.functions.FunctionArgs, org.graylog.plugins.pipelineprocessor.EvaluationContext);
    Code:
       0: aload_0
       1: getfield      #9                  // Field messageParam:Lorg/graylog/plugins/pipelineprocessor/ast/functions/ParameterDescriptor;
       4: aload_1
       5: aload_2
       6: invokevirtual #10                 // Method org/graylog/plugins/pipelineprocessor/ast/functions/ParameterDescriptor.optional:(Lorg/graylog/plugins/pipelineprocessor/ast/functions/FunctionArgs;Lorg/graylog/plugins/pipelineprocessor/EvaluationContext;)Ljava/util/Optional;
       9: aload_2
      10: invokevirtual #11                 // Method org/graylog/plugins/pipelineprocessor/EvaluationContext.currentMessage:()Lorg/graylog2/plugin/Message;
      13: invokevirtual #12                 // Method java/util/Optional.orElse:(Ljava/lang/Object;)Ljava/lang/Object;
      16: checkcast     #3                  // class org/graylog2/plugin/Message
      19: astore_3
      20: aload_3
      21: ldc           #13                 // String timestamp
      23: invokevirtual #14                 // Method org/graylog2/plugin/Message.getField:(Ljava/lang/String;)Ljava/lang/Object;
      26: astore        4
      28: aload         4
      30: instanceof    #15                 // class org/joda/time/DateTime
      33: ifeq          69
      36: new           #3                  // class org/graylog2/plugin/Message
      39: dup
      40: aload_3
      41: invokevirtual #16                 // Method org/graylog2/plugin/Message.getMessage:()Ljava/lang/String;
      44: aload_3
      45: invokevirtual #17                 // Method org/graylog2/plugin/Message.getSource:()Ljava/lang/String;
      48: aload_3
      49: invokevirtual #18                 // Method org/graylog2/plugin/Message.getTimestamp:()Lorg/joda/time/DateTime;
      52: invokespecial #19                 // Method org/graylog2/plugin/Message."<init>":(Ljava/lang/String;Ljava/lang/String;Lorg/joda/time/DateTime;)V
      55: astore        5
      57: aload         5
      59: aload_3
      60: invokevirtual #20                 // Method org/graylog2/plugin/Message.getFields:()Ljava/util/Map;
      63: invokevirtual #21                 // Method org/graylog2/plugin/Message.addFields:(Ljava/util/Map;)V
      66: goto          163
      69: getstatic     #22                 // Field LOG:Lorg/slf4j/Logger;
      72: ldc           #23                 // String Invalid timestamp <{}> (type: {}) in message <{}>. Using current time instead.
      74: iconst_3
      75: anewarray     #24                 // class java/lang/Object
      78: dup
      79: iconst_0
      80: aload         4
      82: aastore
      83: dup
      84: iconst_1
      85: aload         4
      87: invokevirtual #25                 // Method java/lang/Object.getClass:()Ljava/lang/Class;
      90: invokevirtual #26                 // Method java/lang/Class.getCanonicalName:()Ljava/lang/String;
      93: aastore
      94: dup
      95: iconst_2
      96: aload_3
      97: invokevirtual #27                 // Method org/graylog2/plugin/Message.getId:()Ljava/lang/String;
     100: aastore
     101: invokeinterface #28,  3           // InterfaceMethod org/slf4j/Logger.warn:(Ljava/lang/String;[Ljava/lang/Object;)V
     106: getstatic     #29                 // Field org/joda/time/DateTimeZone.UTC:Lorg/joda/time/DateTimeZone;
     109: invokestatic  #30                 // Method org/joda/time/DateTime.now:(Lorg/joda/time/DateTimeZone;)Lorg/joda/time/DateTime;
     112: astore        6
     114: new           #3                  // class org/graylog2/plugin/Message
     117: dup
     118: aload_3
     119: invokevirtual #16                 // Method org/graylog2/plugin/Message.getMessage:()Ljava/lang/String;
     122: aload_3
     123: invokevirtual #17                 // Method org/graylog2/plugin/Message.getSource:()Ljava/lang/String;
     126: aload         6
     128: invokespecial #19                 // Method org/graylog2/plugin/Message."<init>":(Ljava/lang/String;Ljava/lang/String;Lorg/joda/time/DateTime;)V
     131: astore        5
     133: aload         5
     135: aload_3
     136: invokevirtual #20                 // Method org/graylog2/plugin/Message.getFields:()Ljava/util/Map;
     139: invokevirtual #21                 // Method org/graylog2/plugin/Message.addFields:(Ljava/util/Map;)V
     142: aload         5
     144: ldc           #13                 // String timestamp
     146: aload         6
     148: invokevirtual #31                 // Method org/graylog2/plugin/Message.addField:(Ljava/lang/String;Ljava/lang/Object;)V
     151: aload         5
     153: ldc           #32                 // String gl2_original_timestamp
     155: aload         4
     157: invokestatic  #33                 // Method java/lang/String.valueOf:(Ljava/lang/Object;)Ljava/lang/String;
     160: invokevirtual #31                 // Method org/graylog2/plugin/Message.addField:(Ljava/lang/String;Ljava/lang/Object;)V
     163: aload         5
     165: aload_3
     166: invokevirtual #34                 // Method org/graylog2/plugin/Message.getStreams:()Ljava/util/Set;
     169: invokevirtual #35                 // Method org/graylog2/plugin/Message.addStreams:(Ljava/lang/Iterable;)V
     172: aload_2
     173: aload         5
     175: invokevirtual #36                 // Method org/graylog/plugins/pipelineprocessor/EvaluationContext.addCreatedMessage:(Lorg/graylog2/plugin/Message;)V
     178: aload         5
     180: areturn

  public org.graylog.plugins.pipelineprocessor.ast.functions.FunctionDescriptor<org.graylog2.plugin.Message> descriptor();
    Code:
       0: invokestatic  #37                 // Method org/graylog/plugins/pipelineprocessor/ast/functions/FunctionDescriptor.builder:()Lorg/graylog/plugins/pipelineprocessor/ast/functions/FunctionDescriptor$Builder;
       3: ldc           #39                 // String clone_message
       5: invokevirtual #40                 // Method org/graylog/plugins/pipelineprocessor/ast/functions/FunctionDescriptor$Builder.name:(Ljava/lang/String;)Lorg/graylog/plugins/pipelineprocessor/ast/functions/FunctionDescriptor$Builder;
       8: aload_0
       9: getfield      #9                  // Field messageParam:Lorg/graylog/plugins/pipelineprocessor/ast/functions/ParameterDescriptor;
      12: invokestatic  #41                 // Method com/google/common/collect/ImmutableList.of:(Ljava/lang/Object;)Lcom/google/common/collect/ImmutableList;
      15: invokevirtual #42                 // Method org/graylog/plugins/pipelineprocessor/ast/functions/FunctionDescriptor$Builder.params:(Lcom/google/common/collect/ImmutableList;)Lorg/graylog/plugins/pipelineprocessor/ast/functions/FunctionDescriptor$Builder;
      18: ldc           #3                  // class org/graylog2/plugin/Message
      20: invokevirtual #43                 // Method org/graylog/plugins/pipelineprocessor/ast/functions/FunctionDescriptor$Builder.returnType:(Ljava/lang/Class;)Lorg/graylog/plugins/pipelineprocessor/ast/functions/FunctionDescriptor$Builder;
      23: ldc           #44                 // String Clones a message
      25: invokevirtual #45                 // Method org/graylog/plugins/pipelineprocessor/ast/functions/FunctionDescriptor$Builder.description:(Ljava/lang/String;)Lorg/graylog/plugins/pipelineprocessor/ast/functions/FunctionDescriptor$Builder;
      28: invokevirtual #46                 // Method org/graylog/plugins/pipelineprocessor/ast/functions/FunctionDescriptor$Builder.build:()Lorg/graylog/plugins/pipelineprocessor/ast/functions/FunctionDescriptor;
      31: areturn

  public java.lang.Object evaluate(org.graylog.plugins.pipelineprocessor.ast.functions.FunctionArgs, org.graylog.plugins.pipelineprocessor.EvaluationContext);
    Code:
       0: aload_0
       1: aload_1
       2: aload_2
       3: invokevirtual #47                 // Method evaluate:(Lorg/graylog/plugins/pipelineprocessor/ast/functions/FunctionArgs;Lorg/graylog/plugins/pipelineprocessor/EvaluationContext;)Lorg/graylog2/plugin/Message;
       6: areturn

  static {};
    Code:
       0: ldc           #38                 // class org/graylog/plugins/pipelineprocessor/functions/messages/CloneMessage
       2: invokestatic  #48                 // Method org/slf4j/LoggerFactory.getLogger:(Ljava/lang/Class;)Lorg/slf4j/Logger;
       5: putstatic     #22                 // Field LOG:Lorg/slf4j/Logger;
       8: return
}
