Compiled from "UnsafeUriCharactersEncoder.java"
public final class org.apache.camel.util.UnsafeUriCharactersEncoder {
  private static java.util.BitSet unsafeCharacters;

  private static final char[] HEX_DIGITS;

  private org.apache.camel.util.UnsafeUriCharactersEncoder();
    Code:
       0: aload_0
       1: invokespecial #13                 // Method java/lang/Object."<init>":()V
       4: return

  public static java.lang.String encode(java.lang.String);
    Code:
       0: aload_0
       1: ifnonnull     8
       4: iconst_0
       5: goto          12
       8: aload_0
       9: invokevirtual #23                 // Method java/lang/String.length:()I
      12: istore_1
      13: iload_1
      14: ifne          19
      17: aload_0
      18: areturn
      19: aload_0
      20: invokevirtual #27                 // Method java/lang/String.toCharArray:()[C
      23: astore_2
      24: iconst_0
      25: istore_3
      26: aload_2
      27: iload_3
      28: caload
      29: ifle          56
      32: aload_2
      33: iload_3
      34: caload
      35: sipush        128
      38: if_icmpge     56
      41: getstatic     #30                 // Field unsafeCharacters:Ljava/util/BitSet;
      44: aload_2
      45: iload_3
      46: caload
      47: invokevirtual #36                 // Method java/util/BitSet.get:(I)Z
      50: ifeq          56
      53: goto          67
      56: iinc          3, 1
      59: iload_3
      60: aload_2
      61: arraylength
      62: if_icmplt     26
      65: aload_0
      66: areturn
      67: new           #38                 // class java/lang/StringBuilder
      70: dup
      71: invokespecial #39                 // Method java/lang/StringBuilder."<init>":()V
      74: astore_3
      75: iconst_0
      76: istore        4
      78: iload         4
      80: aload_2
      81: arraylength
      82: if_icmpge     225
      85: aload_2
      86: iload         4
      88: caload
      89: istore        5
      91: iload         5
      93: ifle          212
      96: iload         5
      98: sipush        128
     101: if_icmpge     212
     104: getstatic     #30                 // Field unsafeCharacters:Ljava/util/BitSet;
     107: iload         5
     109: invokevirtual #36                 // Method java/util/BitSet.get:(I)Z
     112: ifeq          212
     115: iload         5
     117: bipush        37
     119: if_icmpne     202
     122: iload         4
     124: iconst_1
     125: iadd
     126: aload_2
     127: arraylength
     128: if_icmpge     140
     131: aload_2
     132: iload         4
     134: iconst_1
     135: iadd
     136: caload
     137: goto          142
     140: bipush        32
     142: istore        6
     144: iload         4
     146: iconst_2
     147: iadd
     148: aload_2
     149: arraylength
     150: if_icmpge     162
     153: aload_2
     154: iload         4
     156: iconst_2
     157: iadd
     158: caload
     159: goto          164
     162: bipush        32
     164: istore        7
     166: iload         6
     168: invokestatic  #43                 // Method isHexDigit:(C)Z
     171: ifeq          192
     174: iload         7
     176: invokestatic  #43                 // Method isHexDigit:(C)Z
     179: ifeq          192
     182: aload_3
     183: iload         5
     185: invokevirtual #47                 // Method java/lang/StringBuilder.append:(C)Ljava/lang/StringBuilder;
     188: pop
     189: goto          199
     192: aload_3
     193: iload         5
     195: i2b
     196: invokestatic  #51                 // Method appendEscape:(Ljava/lang/StringBuilder;B)V
     199: goto          219
     202: aload_3
     203: iload         5
     205: i2b
     206: invokestatic  #51                 // Method appendEscape:(Ljava/lang/StringBuilder;B)V
     209: goto          219
     212: aload_3
     213: iload         5
     215: invokevirtual #47                 // Method java/lang/StringBuilder.append:(C)Ljava/lang/StringBuilder;
     218: pop
     219: iinc          4, 1
     222: goto          78
     225: aload_3
     226: invokevirtual #55                 // Method java/lang/StringBuilder.toString:()Ljava/lang/String;
     229: areturn

  private static void appendEscape(java.lang.StringBuilder, byte);
    Code:
       0: aload_0
       1: bipush        37
       3: invokevirtual #47                 // Method java/lang/StringBuilder.append:(C)Ljava/lang/StringBuilder;
       6: pop
       7: aload_0
       8: getstatic     #69                 // Field HEX_DIGITS:[C
      11: iload_1
      12: iconst_4
      13: ishr
      14: bipush        15
      16: iand
      17: caload
      18: invokevirtual #47                 // Method java/lang/StringBuilder.append:(C)Ljava/lang/StringBuilder;
      21: pop
      22: aload_0
      23: getstatic     #69                 // Field HEX_DIGITS:[C
      26: iload_1
      27: iconst_0
      28: ishr
      29: bipush        15
      31: iand
      32: caload
      33: invokevirtual #47                 // Method java/lang/StringBuilder.append:(C)Ljava/lang/StringBuilder;
      36: pop
      37: return

  private static boolean isHexDigit(char);
    Code:
       0: getstatic     #69                 // Field HEX_DIGITS:[C
       3: astore_1
       4: aload_1
       5: arraylength
       6: istore_2
       7: iconst_0
       8: istore_3
       9: iload_3
      10: iload_2
      11: if_icmpge     33
      14: aload_1
      15: iload_3
      16: caload
      17: istore        4
      19: iload         4
      21: iload_0
      22: if_icmpne     27
      25: iconst_1
      26: ireturn
      27: iinc          3, 1
      30: goto          9
      33: iconst_0
      34: ireturn

  static {};
    Code:
       0: bipush        16
       2: newarray       char
       4: dup
       5: iconst_0
       6: bipush        48
       8: castore
       9: dup
      10: iconst_1
      11: bipush        49
      13: castore
      14: dup
      15: iconst_2
      16: bipush        50
      18: castore
      19: dup
      20: iconst_3
      21: bipush        51
      23: castore
      24: dup
      25: iconst_4
      26: bipush        52
      28: castore
      29: dup
      30: iconst_5
      31: bipush        53
      33: castore
      34: dup
      35: bipush        6
      37: bipush        54
      39: castore
      40: dup
      41: bipush        7
      43: bipush        55
      45: castore
      46: dup
      47: bipush        8
      49: bipush        56
      51: castore
      52: dup
      53: bipush        9
      55: bipush        57
      57: castore
      58: dup
      59: bipush        10
      61: bipush        65
      63: castore
      64: dup
      65: bipush        11
      67: bipush        66
      69: castore
      70: dup
      71: bipush        12
      73: bipush        67
      75: castore
      76: dup
      77: bipush        13
      79: bipush        68
      81: castore
      82: dup
      83: bipush        14
      85: bipush        69
      87: castore
      88: dup
      89: bipush        15
      91: bipush        70
      93: castore
      94: putstatic     #69                 // Field HEX_DIGITS:[C
      97: new           #32                 // class java/util/BitSet
     100: dup
     101: sipush        256
     104: invokespecial #79                 // Method java/util/BitSet."<init>":(I)V
     107: putstatic     #30                 // Field unsafeCharacters:Ljava/util/BitSet;
     110: getstatic     #30                 // Field unsafeCharacters:Ljava/util/BitSet;
     113: bipush        32
     115: invokevirtual #82                 // Method java/util/BitSet.set:(I)V
     118: getstatic     #30                 // Field unsafeCharacters:Ljava/util/BitSet;
     121: bipush        34
     123: invokevirtual #82                 // Method java/util/BitSet.set:(I)V
     126: getstatic     #30                 // Field unsafeCharacters:Ljava/util/BitSet;
     129: bipush        60
     131: invokevirtual #82                 // Method java/util/BitSet.set:(I)V
     134: getstatic     #30                 // Field unsafeCharacters:Ljava/util/BitSet;
     137: bipush        62
     139: invokevirtual #82                 // Method java/util/BitSet.set:(I)V
     142: getstatic     #30                 // Field unsafeCharacters:Ljava/util/BitSet;
     145: bipush        35
     147: invokevirtual #82                 // Method java/util/BitSet.set:(I)V
     150: getstatic     #30                 // Field unsafeCharacters:Ljava/util/BitSet;
     153: bipush        37
     155: invokevirtual #82                 // Method java/util/BitSet.set:(I)V
     158: getstatic     #30                 // Field unsafeCharacters:Ljava/util/BitSet;
     161: bipush        123
     163: invokevirtual #82                 // Method java/util/BitSet.set:(I)V
     166: getstatic     #30                 // Field unsafeCharacters:Ljava/util/BitSet;
     169: bipush        125
     171: invokevirtual #82                 // Method java/util/BitSet.set:(I)V
     174: getstatic     #30                 // Field unsafeCharacters:Ljava/util/BitSet;
     177: bipush        124
     179: invokevirtual #82                 // Method java/util/BitSet.set:(I)V
     182: getstatic     #30                 // Field unsafeCharacters:Ljava/util/BitSet;
     185: bipush        92
     187: invokevirtual #82                 // Method java/util/BitSet.set:(I)V
     190: getstatic     #30                 // Field unsafeCharacters:Ljava/util/BitSet;
     193: bipush        94
     195: invokevirtual #82                 // Method java/util/BitSet.set:(I)V
     198: getstatic     #30                 // Field unsafeCharacters:Ljava/util/BitSet;
     201: bipush        126
     203: invokevirtual #82                 // Method java/util/BitSet.set:(I)V
     206: getstatic     #30                 // Field unsafeCharacters:Ljava/util/BitSet;
     209: bipush        91
     211: invokevirtual #82                 // Method java/util/BitSet.set:(I)V
     214: getstatic     #30                 // Field unsafeCharacters:Ljava/util/BitSet;
     217: bipush        93
     219: invokevirtual #82                 // Method java/util/BitSet.set:(I)V
     222: getstatic     #30                 // Field unsafeCharacters:Ljava/util/BitSet;
     225: bipush        96
     227: invokevirtual #82                 // Method java/util/BitSet.set:(I)V
     230: return
}
