Compiled from "YamlMapFactoryBean.java"
class org.springframework.beans.factory.config.YamlMapFactoryBean$1 implements org.springframework.beans.factory.config.YamlProcessor$MatchCallback {
  final java.util.Map val$result;

  final org.springframework.beans.factory.config.YamlMapFactoryBean this$0;

  org.springframework.beans.factory.config.YamlMapFactoryBean$1(org.springframework.beans.factory.config.YamlMapFactoryBean, java.util.Map);
    Code:
       0: aload_0
       1: aload_1
       2: putfield      #1                  // Field this$0:Lorg/springframework/beans/factory/config/YamlMapFactoryBean;
       5: aload_0
       6: aload_2
       7: putfield      #2                  // Field val$result:Ljava/util/Map;
      10: aload_0
      11: invokespecial #3                  // Method java/lang/Object."<init>":()V
      14: return

  public void process(java.util.Properties, java.util.Map<java.lang.String, java.lang.Object>);
    Code:
       0: aload_0
       1: getfield      #1                  // Field this$0:Lorg/springframework/beans/factory/config/YamlMapFactoryBean;
       4: aload_0
       5: getfield      #2                  // Field val$result:Ljava/util/Map;
       8: aload_2
       9: invokestatic  #4                  // Method org/springframework/beans/factory/config/YamlMapFactoryBean.access$000:(Lorg/springframework/beans/factory/config/YamlMapFactoryBean;Ljava/util/Map;Ljava/util/Map;)V
      12: return
}
