Compiled from "EOLConvertingInputStream.java"
public class org.apache.james.mime4j.io.EOLConvertingInputStream extends java.io.InputStream {
  public static final int CONVERT_CR;

  public static final int CONVERT_LF;

  public static final int CONVERT_BOTH;

  private java.io.PushbackInputStream in;

  private int previous;

  private int flags;

  public org.apache.james.mime4j.io.EOLConvertingInputStream(java.io.InputStream);
    Code:
       0: aload_0
       1: aload_1
       2: iconst_3
       3: invokespecial #1                  // Method "<init>":(Ljava/io/InputStream;I)V
       6: return

  public org.apache.james.mime4j.io.EOLConvertingInputStream(java.io.InputStream, int);
    Code:
       0: aload_0
       1: invokespecial #2                  // Method java/io/InputStream."<init>":()V
       4: aload_0
       5: aconst_null
       6: putfield      #3                  // Field in:Ljava/io/PushbackInputStream;
       9: aload_0
      10: iconst_0
      11: putfield      #4                  // Field previous:I
      14: aload_0
      15: iconst_3
      16: putfield      #5                  // Field flags:I
      19: aload_0
      20: new           #6                  // class java/io/PushbackInputStream
      23: dup
      24: aload_1
      25: iconst_2
      26: invokespecial #7                  // Method java/io/PushbackInputStream."<init>":(Ljava/io/InputStream;I)V
      29: putfield      #3                  // Field in:Ljava/io/PushbackInputStream;
      32: aload_0
      33: iload_2
      34: putfield      #5                  // Field flags:I
      37: return

  public void close() throws java.io.IOException;
    Code:
       0: aload_0
       1: getfield      #3                  // Field in:Ljava/io/PushbackInputStream;
       4: invokevirtual #8                  // Method java/io/PushbackInputStream.close:()V
       7: return

  public int read() throws java.io.IOException;
    Code:
       0: aload_0
       1: getfield      #3                  // Field in:Ljava/io/PushbackInputStream;
       4: invokevirtual #9                  // Method java/io/PushbackInputStream.read:()I
       7: istore_1
       8: iload_1
       9: iconst_m1
      10: if_icmpne     15
      13: iconst_m1
      14: ireturn
      15: aload_0
      16: getfield      #5                  // Field flags:I
      19: iconst_1
      20: iand
      21: ifeq          69
      24: iload_1
      25: bipush        13
      27: if_icmpne     69
      30: aload_0
      31: getfield      #3                  // Field in:Ljava/io/PushbackInputStream;
      34: invokevirtual #9                  // Method java/io/PushbackInputStream.read:()I
      37: istore_2
      38: iload_2
      39: iconst_m1
      40: if_icmpeq     51
      43: aload_0
      44: getfield      #3                  // Field in:Ljava/io/PushbackInputStream;
      47: iload_2
      48: invokevirtual #10                 // Method java/io/PushbackInputStream.unread:(I)V
      51: iload_2
      52: bipush        10
      54: if_icmpeq     66
      57: aload_0
      58: getfield      #3                  // Field in:Ljava/io/PushbackInputStream;
      61: bipush        10
      63: invokevirtual #10                 // Method java/io/PushbackInputStream.unread:(I)V
      66: goto          105
      69: aload_0
      70: getfield      #5                  // Field flags:I
      73: iconst_2
      74: iand
      75: ifeq          105
      78: iload_1
      79: bipush        10
      81: if_icmpne     105
      84: aload_0
      85: getfield      #4                  // Field previous:I
      88: bipush        13
      90: if_icmpeq     105
      93: bipush        13
      95: istore_1
      96: aload_0
      97: getfield      #3                  // Field in:Ljava/io/PushbackInputStream;
     100: bipush        10
     102: invokevirtual #10                 // Method java/io/PushbackInputStream.unread:(I)V
     105: aload_0
     106: iload_1
     107: putfield      #4                  // Field previous:I
     110: iload_1
     111: ireturn
}
