Compiled from "OWLDataPropertyCharacteristicsViewComponent.java"
public class org.protege.editor.owl.ui.view.dataproperty.OWLDataPropertyCharacteristicsViewComponent extends org.protege.editor.owl.ui.view.dataproperty.AbstractOWLDataPropertyViewComponent {
  private javax.swing.JCheckBox checkBox;

  private org.semanticweb.owlapi.model.OWLDataProperty prop;

  private org.semanticweb.owlapi.model.OWLOntologyChangeListener listener;

  public org.protege.editor.owl.ui.view.dataproperty.OWLDataPropertyCharacteristicsViewComponent();
    Code:
       0: aload_0
       1: invokespecial #2                  // Method org/protege/editor/owl/ui/view/dataproperty/AbstractOWLDataPropertyViewComponent."<init>":()V
       4: return

  protected org.semanticweb.owlapi.model.OWLDataProperty updateView(org.semanticweb.owlapi.model.OWLDataProperty);
    Code:
       0: aload_0
       1: aload_1
       2: putfield      #1                  // Field prop:Lorg/semanticweb/owlapi/model/OWLDataProperty;
       5: aload_0
       6: getfield      #3                  // Field checkBox:Ljavax/swing/JCheckBox;
       9: aload_1
      10: ifnull        17
      13: iconst_1
      14: goto          18
      17: iconst_0
      18: invokevirtual #4                  // Method javax/swing/JCheckBox.setEnabled:(Z)V
      21: aload_0
      22: getfield      #3                  // Field checkBox:Ljavax/swing/JCheckBox;
      25: iconst_0
      26: invokevirtual #5                  // Method javax/swing/JCheckBox.setSelected:(Z)V
      29: aload_1
      30: ifnonnull     35
      33: aconst_null
      34: areturn
      35: aload_0
      36: invokevirtual #6                  // Method getOWLModelManager:()Lorg/protege/editor/owl/model/OWLModelManager;
      39: invokeinterface #7,  1            // InterfaceMethod org/protege/editor/owl/model/OWLModelManager.getActiveOntologies:()Ljava/util/Set;
      44: invokeinterface #8,  1            // InterfaceMethod java/util/Set.iterator:()Ljava/util/Iterator;
      49: astore_2
      50: aload_2
      51: invokeinterface #9,  1            // InterfaceMethod java/util/Iterator.hasNext:()Z
      56: ifeq          101
      59: aload_2
      60: invokeinterface #10,  1           // InterfaceMethod java/util/Iterator.next:()Ljava/lang/Object;
      65: checkcast     #11                 // class org/semanticweb/owlapi/model/OWLOntology
      68: astore_3
      69: aload_3
      70: aload_0
      71: getfield      #1                  // Field prop:Lorg/semanticweb/owlapi/model/OWLDataProperty;
      74: invokeinterface #12,  2           // InterfaceMethod org/semanticweb/owlapi/model/OWLOntology.getFunctionalDataPropertyAxioms:(Lorg/semanticweb/owlapi/model/OWLDataPropertyExpression;)Ljava/util/Set;
      79: invokeinterface #13,  1           // InterfaceMethod java/util/Set.isEmpty:()Z
      84: ifne          98
      87: aload_0
      88: getfield      #3                  // Field checkBox:Ljavax/swing/JCheckBox;
      91: iconst_1
      92: invokevirtual #5                  // Method javax/swing/JCheckBox.setSelected:(Z)V
      95: goto          101
      98: goto          50
     101: aload_1
     102: areturn

  public void disposeView();
    Code:
       0: aload_0
       1: invokespecial #14                 // Method org/protege/editor/owl/ui/view/dataproperty/AbstractOWLDataPropertyViewComponent.disposeView:()V
       4: aload_0
       5: invokevirtual #6                  // Method getOWLModelManager:()Lorg/protege/editor/owl/model/OWLModelManager;
       8: aload_0
       9: getfield      #15                 // Field listener:Lorg/semanticweb/owlapi/model/OWLOntologyChangeListener;
      12: invokeinterface #16,  2           // InterfaceMethod org/protege/editor/owl/model/OWLModelManager.removeOntologyChangeListener:(Lorg/semanticweb/owlapi/model/OWLOntologyChangeListener;)V
      17: return

  public void initialiseView() throws java.lang.Exception;
    Code:
       0: aload_0
       1: new           #17                 // class java/awt/BorderLayout
       4: dup
       5: invokespecial #18                 // Method java/awt/BorderLayout."<init>":()V
       8: invokevirtual #19                 // Method setLayout:(Ljava/awt/LayoutManager;)V
      11: aload_0
      12: new           #20                 // class javax/swing/JCheckBox
      15: dup
      16: ldc           #21                 // String Functional
      18: invokespecial #22                 // Method javax/swing/JCheckBox."<init>":(Ljava/lang/String;)V
      21: putfield      #3                  // Field checkBox:Ljavax/swing/JCheckBox;
      24: new           #23                 // class javax/swing/Box
      27: dup
      28: iconst_3
      29: invokespecial #25                 // Method javax/swing/Box."<init>":(I)V
      32: astore_1
      33: aload_1
      34: iconst_0
      35: invokevirtual #26                 // Method javax/swing/Box.setOpaque:(Z)V
      38: aload_1
      39: aload_0
      40: getfield      #3                  // Field checkBox:Ljavax/swing/JCheckBox;
      43: invokevirtual #27                 // Method javax/swing/Box.add:(Ljava/awt/Component;)Ljava/awt/Component;
      46: pop
      47: aload_0
      48: new           #28                 // class javax/swing/JScrollPane
      51: dup
      52: aload_1
      53: invokespecial #29                 // Method javax/swing/JScrollPane."<init>":(Ljava/awt/Component;)V
      56: invokevirtual #30                 // Method add:(Ljava/awt/Component;)Ljava/awt/Component;
      59: pop
      60: aload_0
      61: new           #31                 // class org/protege/editor/owl/ui/view/dataproperty/OWLDataPropertyCharacteristicsViewComponent$1
      64: dup
      65: aload_0
      66: invokespecial #32                 // Method org/protege/editor/owl/ui/view/dataproperty/OWLDataPropertyCharacteristicsViewComponent$1."<init>":(Lorg/protege/editor/owl/ui/view/dataproperty/OWLDataPropertyCharacteristicsViewComponent;)V
      69: putfield      #15                 // Field listener:Lorg/semanticweb/owlapi/model/OWLOntologyChangeListener;
      72: aload_0
      73: invokevirtual #6                  // Method getOWLModelManager:()Lorg/protege/editor/owl/model/OWLModelManager;
      76: aload_0
      77: getfield      #15                 // Field listener:Lorg/semanticweb/owlapi/model/OWLOntologyChangeListener;
      80: invokeinterface #33,  2           // InterfaceMethod org/protege/editor/owl/model/OWLModelManager.addOntologyChangeListener:(Lorg/semanticweb/owlapi/model/OWLOntologyChangeListener;)V
      85: aload_0
      86: getfield      #3                  // Field checkBox:Ljavax/swing/JCheckBox;
      89: aload_0
      90: invokedynamic #34,  0             // InvokeDynamic #0:actionPerformed:(Lorg/protege/editor/owl/ui/view/dataproperty/OWLDataPropertyCharacteristicsViewComponent;)Ljava/awt/event/ActionListener;
      95: invokevirtual #35                 // Method javax/swing/JCheckBox.addActionListener:(Ljava/awt/event/ActionListener;)V
      98: return

  private void updateOntology();
    Code:
       0: aload_0
       1: getfield      #1                  // Field prop:Lorg/semanticweb/owlapi/model/OWLDataProperty;
       4: ifnonnull     8
       7: return
       8: aload_0
       9: invokevirtual #6                  // Method getOWLModelManager:()Lorg/protege/editor/owl/model/OWLModelManager;
      12: invokeinterface #36,  1           // InterfaceMethod org/protege/editor/owl/model/OWLModelManager.getOWLDataFactory:()Lorg/semanticweb/owlapi/model/OWLDataFactory;
      17: astore_1
      18: aload_1
      19: aload_0
      20: getfield      #1                  // Field prop:Lorg/semanticweb/owlapi/model/OWLDataProperty;
      23: invokeinterface #37,  2           // InterfaceMethod org/semanticweb/owlapi/model/OWLDataFactory.getOWLFunctionalDataPropertyAxiom:(Lorg/semanticweb/owlapi/model/OWLDataPropertyExpression;)Lorg/semanticweb/owlapi/model/OWLFunctionalDataPropertyAxiom;
      28: astore_2
      29: aload_0
      30: getfield      #3                  // Field checkBox:Ljavax/swing/JCheckBox;
      33: invokevirtual #38                 // Method javax/swing/JCheckBox.isSelected:()Z
      36: ifeq          101
      39: invokestatic  #39                 // Method org/protege/editor/owl/model/axiom/FreshAxiomLocationPreferences.getPreferences:()Lorg/protege/editor/owl/model/axiom/FreshAxiomLocationPreferences;
      42: astore_3
      43: aload_3
      44: invokevirtual #40                 // Method org/protege/editor/owl/model/axiom/FreshAxiomLocationPreferences.getFreshAxiomLocation:()Lorg/protege/editor/owl/model/axiom/FreshAxiomLocation;
      47: invokevirtual #41                 // Method org/protege/editor/owl/model/axiom/FreshAxiomLocation.getStrategyFactory:()Lorg/protege/editor/owl/model/axiom/FreshAxiomLocationStrategyFactory;
      50: astore        4
      52: aload         4
      54: aload_0
      55: invokevirtual #42                 // Method getOWLEditorKit:()Lorg/protege/editor/owl/OWLEditorKit;
      58: invokeinterface #43,  2           // InterfaceMethod org/protege/editor/owl/model/axiom/FreshAxiomLocationStrategyFactory.getStrategy:(Lorg/protege/editor/owl/OWLEditorKit;)Lorg/protege/editor/owl/model/axiom/FreshAxiomLocationStrategy;
      63: astore        5
      65: aload         5
      67: aload_2
      68: aload_0
      69: invokevirtual #6                  // Method getOWLModelManager:()Lorg/protege/editor/owl/model/OWLModelManager;
      72: invokeinterface #44,  3           // InterfaceMethod org/protege/editor/owl/model/axiom/FreshAxiomLocationStrategy.getFreshAxiomLocation:(Lorg/semanticweb/owlapi/model/OWLAxiom;Lorg/protege/editor/owl/model/HasActiveOntology;)Lorg/semanticweb/owlapi/model/OWLOntology;
      77: astore        6
      79: aload_0
      80: invokevirtual #6                  // Method getOWLModelManager:()Lorg/protege/editor/owl/model/OWLModelManager;
      83: new           #45                 // class org/semanticweb/owlapi/model/AddAxiom
      86: dup
      87: aload         6
      89: aload_2
      90: invokespecial #46                 // Method org/semanticweb/owlapi/model/AddAxiom."<init>":(Lorg/semanticweb/owlapi/model/OWLOntology;Lorg/semanticweb/owlapi/model/OWLAxiom;)V
      93: invokeinterface #47,  2           // InterfaceMethod org/protege/editor/owl/model/OWLModelManager.applyChange:(Lorg/semanticweb/owlapi/model/OWLOntologyChange;)V
      98: goto          177
     101: new           #48                 // class java/util/ArrayList
     104: dup
     105: invokespecial #49                 // Method java/util/ArrayList."<init>":()V
     108: astore_3
     109: aload_0
     110: invokevirtual #6                  // Method getOWLModelManager:()Lorg/protege/editor/owl/model/OWLModelManager;
     113: invokeinterface #7,  1            // InterfaceMethod org/protege/editor/owl/model/OWLModelManager.getActiveOntologies:()Ljava/util/Set;
     118: invokeinterface #8,  1            // InterfaceMethod java/util/Set.iterator:()Ljava/util/Iterator;
     123: astore        4
     125: aload         4
     127: invokeinterface #9,  1            // InterfaceMethod java/util/Iterator.hasNext:()Z
     132: ifeq          167
     135: aload         4
     137: invokeinterface #10,  1           // InterfaceMethod java/util/Iterator.next:()Ljava/lang/Object;
     142: checkcast     #11                 // class org/semanticweb/owlapi/model/OWLOntology
     145: astore        5
     147: aload_3
     148: new           #50                 // class org/semanticweb/owlapi/model/RemoveAxiom
     151: dup
     152: aload         5
     154: aload_2
     155: invokespecial #51                 // Method org/semanticweb/owlapi/model/RemoveAxiom."<init>":(Lorg/semanticweb/owlapi/model/OWLOntology;Lorg/semanticweb/owlapi/model/OWLAxiom;)V
     158: invokeinterface #52,  2           // InterfaceMethod java/util/List.add:(Ljava/lang/Object;)Z
     163: pop
     164: goto          125
     167: aload_0
     168: invokevirtual #6                  // Method getOWLModelManager:()Lorg/protege/editor/owl/model/OWLModelManager;
     171: aload_3
     172: invokeinterface #53,  2           // InterfaceMethod org/protege/editor/owl/model/OWLModelManager.applyChanges:(Ljava/util/List;)V
     177: return

  protected org.semanticweb.owlapi.model.OWLProperty updateView(org.semanticweb.owlapi.model.OWLProperty);
    Code:
       0: aload_0
       1: aload_1
       2: checkcast     #54                 // class org/semanticweb/owlapi/model/OWLDataProperty
       5: invokevirtual #55                 // Method updateView:(Lorg/semanticweb/owlapi/model/OWLDataProperty;)Lorg/semanticweb/owlapi/model/OWLDataProperty;
       8: areturn

  private void lambda$initialiseView$0(java.awt.event.ActionEvent);
    Code:
       0: aload_0
       1: invokespecial #56                 // Method updateOntology:()V
       4: return

  static org.semanticweb.owlapi.model.OWLDataProperty access$000(org.protege.editor.owl.ui.view.dataproperty.OWLDataPropertyCharacteristicsViewComponent);
    Code:
       0: aload_0
       1: getfield      #1                  // Field prop:Lorg/semanticweb/owlapi/model/OWLDataProperty;
       4: areturn
}
