Compiled from "DefaultGameLiftClient.kt"
final class aws.sdk.kotlin.services.gamelift.DefaultGameLiftClient$listTagsForResource$3 extends kotlin.jvm.internal.Lambda implements kotlin.jvm.functions.Function1<aws.smithy.kotlin.runtime.http.middleware.Retry$Config, kotlin.Unit> {
  final aws.sdk.kotlin.services.gamelift.DefaultGameLiftClient this$0;

  aws.sdk.kotlin.services.gamelift.DefaultGameLiftClient$listTagsForResource$3(aws.sdk.kotlin.services.gamelift.DefaultGameLiftClient);
    Code:
       0: aload_0
       1: aload_1
       2: putfield      #13                 // Field this$0:Laws/sdk/kotlin/services/gamelift/DefaultGameLiftClient;
       5: aload_0
       6: iconst_1
       7: invokespecial #16                 // Method kotlin/jvm/internal/Lambda."<init>":(I)V
      10: return

  public final void invoke(aws.smithy.kotlin.runtime.http.middleware.Retry$Config);
    Code:
       0: aload_1
       1: ldc           #24                 // String $this$install
       3: invokestatic  #30                 // Method kotlin/jvm/internal/Intrinsics.checkNotNullParameter:(Ljava/lang/Object;Ljava/lang/String;)V
       6: aload_1
       7: aload_0
       8: getfield      #13                 // Field this$0:Laws/sdk/kotlin/services/gamelift/DefaultGameLiftClient;
      11: invokevirtual #36                 // Method aws/sdk/kotlin/services/gamelift/DefaultGameLiftClient.getConfig:()Laws/sdk/kotlin/services/gamelift/GameLiftClient$Config;
      14: invokevirtual #42                 // Method aws/sdk/kotlin/services/gamelift/GameLiftClient$Config.getRetryStrategy:()Laws/smithy/kotlin/runtime/retries/RetryStrategy;
      17: invokevirtual #48                 // Method aws/smithy/kotlin/runtime/http/middleware/Retry$Config.setStrategy:(Laws/smithy/kotlin/runtime/retries/RetryStrategy;)V
      20: aload_1
      21: getstatic     #54                 // Field aws/sdk/kotlin/runtime/http/retries/AwsDefaultRetryPolicy.INSTANCE:Laws/sdk/kotlin/runtime/http/retries/AwsDefaultRetryPolicy;
      24: checkcast     #56                 // class aws/smithy/kotlin/runtime/retries/RetryPolicy
      27: invokevirtual #60                 // Method aws/smithy/kotlin/runtime/http/middleware/Retry$Config.setPolicy:(Laws/smithy/kotlin/runtime/retries/RetryPolicy;)V
      30: return

  public java.lang.Object invoke(java.lang.Object);
    Code:
       0: aload_0
       1: aload_1
       2: checkcast     #44                 // class aws/smithy/kotlin/runtime/http/middleware/Retry$Config
       5: invokevirtual #64                 // Method invoke:(Laws/smithy/kotlin/runtime/http/middleware/Retry$Config;)V
       8: getstatic     #69                 // Field kotlin/Unit.INSTANCE:Lkotlin/Unit;
      11: areturn
}
