Compiled from "Filter.java"
final class org.junit.runner.manipulation.Filter$1 extends org.junit.runner.manipulation.Filter {
  org.junit.runner.manipulation.Filter$1();
    Code:
       0: aload_0
       1: invokespecial #1                  // Method org/junit/runner/manipulation/Filter."<init>":()V
       4: return

  public boolean shouldRun(org.junit.runner.Description);
    Code:
       0: iconst_1
       1: ireturn

  public java.lang.String describe();
    Code:
       0: ldc           #2                  // String all tests
       2: areturn

  public void apply(java.lang.Object) throws org.junit.runner.manipulation.NoTestsRemainException;
    Code:
       0: return

  public org.junit.runner.manipulation.Filter intersect(org.junit.runner.manipulation.Filter);
    Code:
       0: aload_1
       1: areturn
}
