Compiled from "DefaultHttpRequestParserFactory.java"
public class org.apache.hc.core5.http.impl.nio.DefaultHttpRequestParserFactory implements org.apache.hc.core5.http.nio.NHttpMessageParserFactory<org.apache.hc.core5.http.HttpRequest> {
  public static final org.apache.hc.core5.http.impl.nio.DefaultHttpRequestParserFactory INSTANCE;

  private final org.apache.hc.core5.http.config.Http1Config http1Config;

  private final org.apache.hc.core5.http.message.LineParser lineParser;

  private final org.apache.hc.core5.http.HttpRequestFactory<org.apache.hc.core5.http.HttpRequest> requestFactory;

  public org.apache.hc.core5.http.impl.nio.DefaultHttpRequestParserFactory(org.apache.hc.core5.http.config.Http1Config, org.apache.hc.core5.http.HttpRequestFactory<org.apache.hc.core5.http.HttpRequest>, org.apache.hc.core5.http.message.LineParser);
    Code:
       0: aload_0
       1: invokespecial #1                  // Method java/lang/Object."<init>":()V
       4: aload_0
       5: aload_1
       6: ifnull        13
       9: aload_1
      10: goto          16
      13: getstatic     #2                  // Field org/apache/hc/core5/http/config/Http1Config.DEFAULT:Lorg/apache/hc/core5/http/config/Http1Config;
      16: putfield      #3                  // Field http1Config:Lorg/apache/hc/core5/http/config/Http1Config;
      19: aload_0
      20: aload_2
      21: ifnull        28
      24: aload_2
      25: goto          31
      28: getstatic     #4                  // Field org/apache/hc/core5/http/impl/nio/DefaultHttpRequestFactory.INSTANCE:Lorg/apache/hc/core5/http/impl/nio/DefaultHttpRequestFactory;
      31: putfield      #5                  // Field requestFactory:Lorg/apache/hc/core5/http/HttpRequestFactory;
      34: aload_0
      35: aload_3
      36: ifnull        43
      39: aload_3
      40: goto          46
      43: getstatic     #6                  // Field org/apache/hc/core5/http/message/LazyLineParser.INSTANCE:Lorg/apache/hc/core5/http/message/LazyLineParser;
      46: putfield      #7                  // Field lineParser:Lorg/apache/hc/core5/http/message/LineParser;
      49: return

  public org.apache.hc.core5.http.impl.nio.DefaultHttpRequestParserFactory(org.apache.hc.core5.http.config.Http1Config);
    Code:
       0: aload_0
       1: aload_1
       2: aconst_null
       3: aconst_null
       4: invokespecial #8                  // Method "<init>":(Lorg/apache/hc/core5/http/config/Http1Config;Lorg/apache/hc/core5/http/HttpRequestFactory;Lorg/apache/hc/core5/http/message/LineParser;)V
       7: return

  public org.apache.hc.core5.http.impl.nio.DefaultHttpRequestParserFactory();
    Code:
       0: aload_0
       1: aconst_null
       2: invokespecial #9                  // Method "<init>":(Lorg/apache/hc/core5/http/config/Http1Config;)V
       5: return

  public org.apache.hc.core5.http.nio.NHttpMessageParser<org.apache.hc.core5.http.HttpRequest> create();
    Code:
       0: new           #10                 // class org/apache/hc/core5/http/impl/nio/DefaultHttpRequestParser
       3: dup
       4: aload_0
       5: getfield      #5                  // Field requestFactory:Lorg/apache/hc/core5/http/HttpRequestFactory;
       8: aload_0
       9: getfield      #7                  // Field lineParser:Lorg/apache/hc/core5/http/message/LineParser;
      12: aload_0
      13: getfield      #3                  // Field http1Config:Lorg/apache/hc/core5/http/config/Http1Config;
      16: invokespecial #11                 // Method org/apache/hc/core5/http/impl/nio/DefaultHttpRequestParser."<init>":(Lorg/apache/hc/core5/http/HttpRequestFactory;Lorg/apache/hc/core5/http/message/LineParser;Lorg/apache/hc/core5/http/config/Http1Config;)V
      19: areturn

  static {};
    Code:
       0: new           #12                 // class org/apache/hc/core5/http/impl/nio/DefaultHttpRequestParserFactory
       3: dup
       4: invokespecial #13                 // Method "<init>":()V
       7: putstatic     #14                 // Field INSTANCE:Lorg/apache/hc/core5/http/impl/nio/DefaultHttpRequestParserFactory;
      10: return
}
