Compiled from "DefaultHttpRequestParser.java"
public class org.apache.hc.core5.http.impl.nio.DefaultHttpRequestParser<T extends org.apache.hc.core5.http.HttpRequest> extends org.apache.hc.core5.http.impl.nio.AbstractMessageParser<T> {
  private final org.apache.hc.core5.http.HttpRequestFactory<T> requestFactory;

  public org.apache.hc.core5.http.impl.nio.DefaultHttpRequestParser(org.apache.hc.core5.http.HttpRequestFactory<T>, org.apache.hc.core5.http.message.LineParser, org.apache.hc.core5.http.config.Http1Config);
    Code:
       0: aload_0
       1: aload_2
       2: aload_3
       3: invokespecial #1                  // Method org/apache/hc/core5/http/impl/nio/AbstractMessageParser."<init>":(Lorg/apache/hc/core5/http/message/LineParser;Lorg/apache/hc/core5/http/config/Http1Config;)V
       6: aload_0
       7: aload_1
       8: ldc           #2                  // String Request factory
      10: invokestatic  #3                  // Method org/apache/hc/core5/util/Args.notNull:(Ljava/lang/Object;Ljava/lang/String;)Ljava/lang/Object;
      13: checkcast     #4                  // class org/apache/hc/core5/http/HttpRequestFactory
      16: putfield      #5                  // Field requestFactory:Lorg/apache/hc/core5/http/HttpRequestFactory;
      19: return

  public org.apache.hc.core5.http.impl.nio.DefaultHttpRequestParser(org.apache.hc.core5.http.HttpRequestFactory<T>, org.apache.hc.core5.http.config.Http1Config);
    Code:
       0: aload_0
       1: aload_1
       2: aconst_null
       3: aload_2
       4: invokespecial #6                  // Method "<init>":(Lorg/apache/hc/core5/http/HttpRequestFactory;Lorg/apache/hc/core5/http/message/LineParser;Lorg/apache/hc/core5/http/config/Http1Config;)V
       7: return

  public org.apache.hc.core5.http.impl.nio.DefaultHttpRequestParser(org.apache.hc.core5.http.HttpRequestFactory<T>);
    Code:
       0: aload_0
       1: aload_1
       2: aconst_null
       3: invokespecial #7                  // Method "<init>":(Lorg/apache/hc/core5/http/HttpRequestFactory;Lorg/apache/hc/core5/http/config/Http1Config;)V
       6: return

  public T parse(org.apache.hc.core5.http.nio.SessionInputBuffer, boolean) throws java.io.IOException, org.apache.hc.core5.http.HttpException;
    Code:
       0: aload_0
       1: aload_1
       2: iload_2
       3: invokespecial #8                  // Method org/apache/hc/core5/http/impl/nio/AbstractMessageParser.parse:(Lorg/apache/hc/core5/http/nio/SessionInputBuffer;Z)Lorg/apache/hc/core5/http/HttpMessage;
       6: checkcast     #9                  // class org/apache/hc/core5/http/HttpRequest
       9: areturn
      10: astore_3
      11: new           #11                 // class org/apache/hc/core5/http/RequestHeaderFieldsTooLargeException
      14: dup
      15: aload_3
      16: invokevirtual #12                 // Method org/apache/hc/core5/http/MessageConstraintException.getMessage:()Ljava/lang/String;
      19: aload_3
      20: invokespecial #13                 // Method org/apache/hc/core5/http/RequestHeaderFieldsTooLargeException."<init>":(Ljava/lang/String;Ljava/lang/Throwable;)V
      23: athrow
    Exception table:
       from    to  target type
           0     9    10   Class org/apache/hc/core5/http/MessageConstraintException

  protected T createMessage(org.apache.hc.core5.util.CharArrayBuffer) throws org.apache.hc.core5.http.HttpException;
    Code:
       0: aload_0
       1: invokevirtual #14                 // Method getLineParser:()Lorg/apache/hc/core5/http/message/LineParser;
       4: aload_1
       5: invokeinterface #15,  2           // InterfaceMethod org/apache/hc/core5/http/message/LineParser.parseRequestLine:(Lorg/apache/hc/core5/util/CharArrayBuffer;)Lorg/apache/hc/core5/http/message/RequestLine;
      10: astore_2
      11: aload_0
      12: getfield      #5                  // Field requestFactory:Lorg/apache/hc/core5/http/HttpRequestFactory;
      15: aload_2
      16: invokevirtual #16                 // Method org/apache/hc/core5/http/message/RequestLine.getMethod:()Ljava/lang/String;
      19: aload_2
      20: invokevirtual #17                 // Method org/apache/hc/core5/http/message/RequestLine.getUri:()Ljava/lang/String;
      23: invokeinterface #18,  3           // InterfaceMethod org/apache/hc/core5/http/HttpRequestFactory.newHttpRequest:(Ljava/lang/String;Ljava/lang/String;)Lorg/apache/hc/core5/http/HttpRequest;
      28: astore_3
      29: aload_3
      30: aload_2
      31: invokevirtual #19                 // Method org/apache/hc/core5/http/message/RequestLine.getProtocolVersion:()Lorg/apache/hc/core5/http/ProtocolVersion;
      34: invokeinterface #20,  2           // InterfaceMethod org/apache/hc/core5/http/HttpRequest.setVersion:(Lorg/apache/hc/core5/http/ProtocolVersion;)V
      39: aload_3
      40: areturn

  public org.apache.hc.core5.http.HttpMessage parse(org.apache.hc.core5.http.nio.SessionInputBuffer, boolean) throws java.io.IOException, org.apache.hc.core5.http.HttpException;
    Code:
       0: aload_0
       1: aload_1
       2: iload_2
       3: invokevirtual #21                 // Method parse:(Lorg/apache/hc/core5/http/nio/SessionInputBuffer;Z)Lorg/apache/hc/core5/http/HttpRequest;
       6: areturn

  protected org.apache.hc.core5.http.HttpMessage createMessage(org.apache.hc.core5.util.CharArrayBuffer) throws org.apache.hc.core5.http.HttpException;
    Code:
       0: aload_0
       1: aload_1
       2: invokevirtual #22                 // Method createMessage:(Lorg/apache/hc/core5/util/CharArrayBuffer;)Lorg/apache/hc/core5/http/HttpRequest;
       5: areturn

  public org.apache.hc.core5.http.MessageHeaders parse(org.apache.hc.core5.http.nio.SessionInputBuffer, boolean) throws java.io.IOException, org.apache.hc.core5.http.HttpException;
    Code:
       0: aload_0
       1: aload_1
       2: iload_2
       3: invokevirtual #21                 // Method parse:(Lorg/apache/hc/core5/http/nio/SessionInputBuffer;Z)Lorg/apache/hc/core5/http/HttpRequest;
       6: areturn
}
