Compiled from "ServerHttp1StreamHandler.java"
class org.apache.hc.core5.http.impl.nio.ServerHttp1StreamHandler implements org.apache.hc.core5.http.nio.ResourceHolder {
  private final org.apache.hc.core5.http.impl.nio.Http1StreamChannel<org.apache.hc.core5.http.HttpResponse> outputChannel;

  private final org.apache.hc.core5.http.nio.DataStreamChannel internalDataChannel;

  private final org.apache.hc.core5.http.nio.ResponseChannel responseChannel;

  private final org.apache.hc.core5.http.protocol.HttpProcessor httpProcessor;

  private final org.apache.hc.core5.http.nio.HandlerFactory<org.apache.hc.core5.http.nio.AsyncServerExchangeHandler> exchangeHandlerFactory;

  private final org.apache.hc.core5.http.ConnectionReuseStrategy connectionReuseStrategy;

  private final org.apache.hc.core5.http.protocol.HttpCoreContext context;

  private final java.util.concurrent.atomic.AtomicBoolean responseCommitted;

  private final java.util.concurrent.atomic.AtomicBoolean done;

  private volatile boolean keepAlive;

  private volatile org.apache.hc.core5.http.nio.AsyncServerExchangeHandler exchangeHandler;

  private volatile org.apache.hc.core5.http.HttpRequest receivedRequest;

  private volatile org.apache.hc.core5.http.impl.nio.MessageState requestState;

  private volatile org.apache.hc.core5.http.impl.nio.MessageState responseState;

  org.apache.hc.core5.http.impl.nio.ServerHttp1StreamHandler(org.apache.hc.core5.http.impl.nio.Http1StreamChannel<org.apache.hc.core5.http.HttpResponse>, org.apache.hc.core5.http.protocol.HttpProcessor, org.apache.hc.core5.http.ConnectionReuseStrategy, org.apache.hc.core5.http.nio.HandlerFactory<org.apache.hc.core5.http.nio.AsyncServerExchangeHandler>, org.apache.hc.core5.http.protocol.HttpCoreContext);
    Code:
       0: aload_0
       1: invokespecial #6                  // Method java/lang/Object."<init>":()V
       4: aload_0
       5: aload_1
       6: putfield      #7                  // Field outputChannel:Lorg/apache/hc/core5/http/impl/nio/Http1StreamChannel;
       9: aload_0
      10: new           #8                  // class org/apache/hc/core5/http/impl/nio/ServerHttp1StreamHandler$1
      13: dup
      14: aload_0
      15: aload_1
      16: invokespecial #9                  // Method org/apache/hc/core5/http/impl/nio/ServerHttp1StreamHandler$1."<init>":(Lorg/apache/hc/core5/http/impl/nio/ServerHttp1StreamHandler;Lorg/apache/hc/core5/http/impl/nio/Http1StreamChannel;)V
      19: putfield      #10                 // Field internalDataChannel:Lorg/apache/hc/core5/http/nio/DataStreamChannel;
      22: aload_0
      23: new           #11                 // class org/apache/hc/core5/http/impl/nio/ServerHttp1StreamHandler$2
      26: dup
      27: aload_0
      28: invokespecial #12                 // Method org/apache/hc/core5/http/impl/nio/ServerHttp1StreamHandler$2."<init>":(Lorg/apache/hc/core5/http/impl/nio/ServerHttp1StreamHandler;)V
      31: putfield      #13                 // Field responseChannel:Lorg/apache/hc/core5/http/nio/ResponseChannel;
      34: aload_0
      35: aload_2
      36: putfield      #14                 // Field httpProcessor:Lorg/apache/hc/core5/http/protocol/HttpProcessor;
      39: aload_0
      40: aload_3
      41: putfield      #15                 // Field connectionReuseStrategy:Lorg/apache/hc/core5/http/ConnectionReuseStrategy;
      44: aload_0
      45: aload         4
      47: putfield      #16                 // Field exchangeHandlerFactory:Lorg/apache/hc/core5/http/nio/HandlerFactory;
      50: aload_0
      51: aload         5
      53: putfield      #17                 // Field context:Lorg/apache/hc/core5/http/protocol/HttpCoreContext;
      56: aload_0
      57: new           #18                 // class java/util/concurrent/atomic/AtomicBoolean
      60: dup
      61: iconst_0
      62: invokespecial #19                 // Method java/util/concurrent/atomic/AtomicBoolean."<init>":(Z)V
      65: putfield      #20                 // Field responseCommitted:Ljava/util/concurrent/atomic/AtomicBoolean;
      68: aload_0
      69: new           #18                 // class java/util/concurrent/atomic/AtomicBoolean
      72: dup
      73: iconst_0
      74: invokespecial #19                 // Method java/util/concurrent/atomic/AtomicBoolean."<init>":(Z)V
      77: putfield      #21                 // Field done:Ljava/util/concurrent/atomic/AtomicBoolean;
      80: aload_0
      81: iconst_1
      82: putfield      #5                  // Field keepAlive:Z
      85: aload_0
      86: getstatic     #22                 // Field org/apache/hc/core5/http/impl/nio/MessageState.HEADERS:Lorg/apache/hc/core5/http/impl/nio/MessageState;
      89: putfield      #23                 // Field requestState:Lorg/apache/hc/core5/http/impl/nio/MessageState;
      92: aload_0
      93: getstatic     #24                 // Field org/apache/hc/core5/http/impl/nio/MessageState.IDLE:Lorg/apache/hc/core5/http/impl/nio/MessageState;
      96: putfield      #4                  // Field responseState:Lorg/apache/hc/core5/http/impl/nio/MessageState;
      99: return

  private void commitResponse(org.apache.hc.core5.http.HttpResponse, org.apache.hc.core5.http.EntityDetails) throws org.apache.hc.core5.http.HttpException, java.io.IOException;
    Code:
       0: aload_0
       1: getfield      #20                 // Field responseCommitted:Ljava/util/concurrent/atomic/AtomicBoolean;
       4: iconst_0
       5: iconst_1
       6: invokevirtual #25                 // Method java/util/concurrent/atomic/AtomicBoolean.compareAndSet:(ZZ)Z
       9: ifeq          272
      12: aload_1
      13: invokeinterface #26,  1           // InterfaceMethod org/apache/hc/core5/http/HttpResponse.getVersion:()Lorg/apache/hc/core5/http/ProtocolVersion;
      18: astore_3
      19: aload_3
      20: ifnull        42
      23: aload_3
      24: getstatic     #27                 // Field org/apache/hc/core5/http/HttpVersion.HTTP_2:Lorg/apache/hc/core5/http/HttpVersion;
      27: invokevirtual #28                 // Method org/apache/hc/core5/http/ProtocolVersion.greaterEquals:(Lorg/apache/hc/core5/http/ProtocolVersion;)Z
      30: ifeq          42
      33: new           #29                 // class org/apache/hc/core5/http/UnsupportedHttpVersionException
      36: dup
      37: aload_3
      38: invokespecial #30                 // Method org/apache/hc/core5/http/UnsupportedHttpVersionException."<init>":(Lorg/apache/hc/core5/http/ProtocolVersion;)V
      41: athrow
      42: aload_1
      43: invokeinterface #31,  1           // InterfaceMethod org/apache/hc/core5/http/HttpResponse.getCode:()I
      48: istore        4
      50: iload         4
      52: sipush        200
      55: if_icmpge     86
      58: new           #32                 // class org/apache/hc/core5/http/HttpException
      61: dup
      62: new           #33                 // class java/lang/StringBuilder
      65: dup
      66: invokespecial #34                 // Method java/lang/StringBuilder."<init>":()V
      69: ldc           #35                 // String Invalid response:
      71: invokevirtual #36                 // Method java/lang/StringBuilder.append:(Ljava/lang/String;)Ljava/lang/StringBuilder;
      74: iload         4
      76: invokevirtual #37                 // Method java/lang/StringBuilder.append:(I)Ljava/lang/StringBuilder;
      79: invokevirtual #38                 // Method java/lang/StringBuilder.toString:()Ljava/lang/String;
      82: invokespecial #39                 // Method org/apache/hc/core5/http/HttpException."<init>":(Ljava/lang/String;)V
      85: athrow
      86: aload_0
      87: getfield      #17                 // Field context:Lorg/apache/hc/core5/http/protocol/HttpCoreContext;
      90: aload_3
      91: ifnull        98
      94: aload_3
      95: goto          101
      98: getstatic     #40                 // Field org/apache/hc/core5/http/HttpVersion.HTTP_1_1:Lorg/apache/hc/core5/http/HttpVersion;
     101: invokevirtual #41                 // Method org/apache/hc/core5/http/protocol/HttpCoreContext.setProtocolVersion:(Lorg/apache/hc/core5/http/ProtocolVersion;)V
     104: aload_0
     105: getfield      #17                 // Field context:Lorg/apache/hc/core5/http/protocol/HttpCoreContext;
     108: ldc           #42                 // String http.response
     110: aload_1
     111: invokevirtual #43                 // Method org/apache/hc/core5/http/protocol/HttpCoreContext.setAttribute:(Ljava/lang/String;Ljava/lang/Object;)Ljava/lang/Object;
     114: pop
     115: aload_0
     116: getfield      #14                 // Field httpProcessor:Lorg/apache/hc/core5/http/protocol/HttpProcessor;
     119: aload_1
     120: aload_2
     121: aload_0
     122: getfield      #17                 // Field context:Lorg/apache/hc/core5/http/protocol/HttpCoreContext;
     125: invokeinterface #44,  4           // InterfaceMethod org/apache/hc/core5/http/protocol/HttpProcessor.process:(Lorg/apache/hc/core5/http/HttpResponse;Lorg/apache/hc/core5/http/EntityDetails;Lorg/apache/hc/core5/http/protocol/HttpContext;)V
     130: aload_2
     131: ifnull        159
     134: aload_0
     135: getfield      #45                 // Field receivedRequest:Lorg/apache/hc/core5/http/HttpRequest;
     138: ifnull        163
     141: getstatic     #46                 // Field org/apache/hc/core5/http/Method.HEAD:Lorg/apache/hc/core5/http/Method;
     144: aload_0
     145: getfield      #45                 // Field receivedRequest:Lorg/apache/hc/core5/http/HttpRequest;
     148: invokeinterface #47,  1           // InterfaceMethod org/apache/hc/core5/http/HttpRequest.getMethod:()Ljava/lang/String;
     153: invokevirtual #48                 // Method org/apache/hc/core5/http/Method.isSame:(Ljava/lang/String;)Z
     156: ifeq          163
     159: iconst_1
     160: goto          164
     163: iconst_0
     164: istore        5
     166: aload_0
     167: getfield      #15                 // Field connectionReuseStrategy:Lorg/apache/hc/core5/http/ConnectionReuseStrategy;
     170: aload_0
     171: getfield      #45                 // Field receivedRequest:Lorg/apache/hc/core5/http/HttpRequest;
     174: aload_1
     175: aload_0
     176: getfield      #17                 // Field context:Lorg/apache/hc/core5/http/protocol/HttpCoreContext;
     179: invokeinterface #49,  4           // InterfaceMethod org/apache/hc/core5/http/ConnectionReuseStrategy.keepAlive:(Lorg/apache/hc/core5/http/HttpRequest;Lorg/apache/hc/core5/http/HttpResponse;Lorg/apache/hc/core5/http/protocol/HttpContext;)Z
     184: ifne          192
     187: aload_0
     188: iconst_0
     189: putfield      #5                  // Field keepAlive:Z
     192: aload_0
     193: getfield      #7                  // Field outputChannel:Lorg/apache/hc/core5/http/impl/nio/Http1StreamChannel;
     196: aload_1
     197: iload         5
     199: iload         5
     201: ifeq          210
     204: getstatic     #50                 // Field org/apache/hc/core5/http/impl/nio/FlushMode.IMMEDIATE:Lorg/apache/hc/core5/http/impl/nio/FlushMode;
     207: goto          213
     210: getstatic     #51                 // Field org/apache/hc/core5/http/impl/nio/FlushMode.BUFFER:Lorg/apache/hc/core5/http/impl/nio/FlushMode;
     213: invokeinterface #52,  4           // InterfaceMethod org/apache/hc/core5/http/impl/nio/Http1StreamChannel.submit:(Lorg/apache/hc/core5/http/HttpMessage;ZLorg/apache/hc/core5/http/impl/nio/FlushMode;)V
     218: iload         5
     220: ifeq          249
     223: aload_0
     224: getfield      #5                  // Field keepAlive:Z
     227: ifne          239
     230: aload_0
     231: getfield      #7                  // Field outputChannel:Lorg/apache/hc/core5/http/impl/nio/Http1StreamChannel;
     234: invokeinterface #53,  1           // InterfaceMethod org/apache/hc/core5/http/impl/nio/Http1StreamChannel.close:()V
     239: aload_0
     240: getstatic     #54                 // Field org/apache/hc/core5/http/impl/nio/MessageState.COMPLETE:Lorg/apache/hc/core5/http/impl/nio/MessageState;
     243: putfield      #4                  // Field responseState:Lorg/apache/hc/core5/http/impl/nio/MessageState;
     246: goto          269
     249: aload_0
     250: getstatic     #55                 // Field org/apache/hc/core5/http/impl/nio/MessageState.BODY:Lorg/apache/hc/core5/http/impl/nio/MessageState;
     253: putfield      #4                  // Field responseState:Lorg/apache/hc/core5/http/impl/nio/MessageState;
     256: aload_0
     257: getfield      #56                 // Field exchangeHandler:Lorg/apache/hc/core5/http/nio/AsyncServerExchangeHandler;
     260: aload_0
     261: getfield      #10                 // Field internalDataChannel:Lorg/apache/hc/core5/http/nio/DataStreamChannel;
     264: invokeinterface #57,  2           // InterfaceMethod org/apache/hc/core5/http/nio/AsyncServerExchangeHandler.produce:(Lorg/apache/hc/core5/http/nio/DataStreamChannel;)V
     269: goto          282
     272: new           #32                 // class org/apache/hc/core5/http/HttpException
     275: dup
     276: ldc           #58                 // String Response already committed
     278: invokespecial #39                 // Method org/apache/hc/core5/http/HttpException."<init>":(Ljava/lang/String;)V
     281: athrow
     282: return

  private void commitInformation(org.apache.hc.core5.http.HttpResponse) throws java.io.IOException, org.apache.hc.core5.http.HttpException;
    Code:
       0: aload_0
       1: getfield      #20                 // Field responseCommitted:Ljava/util/concurrent/atomic/AtomicBoolean;
       4: invokevirtual #59                 // Method java/util/concurrent/atomic/AtomicBoolean.get:()Z
       7: ifeq          20
      10: new           #32                 // class org/apache/hc/core5/http/HttpException
      13: dup
      14: ldc           #58                 // String Response already committed
      16: invokespecial #39                 // Method org/apache/hc/core5/http/HttpException."<init>":(Ljava/lang/String;)V
      19: athrow
      20: aload_1
      21: invokeinterface #31,  1           // InterfaceMethod org/apache/hc/core5/http/HttpResponse.getCode:()I
      26: istore_2
      27: iload_2
      28: bipush        100
      30: if_icmplt     40
      33: iload_2
      34: sipush        200
      37: if_icmplt     67
      40: new           #32                 // class org/apache/hc/core5/http/HttpException
      43: dup
      44: new           #33                 // class java/lang/StringBuilder
      47: dup
      48: invokespecial #34                 // Method java/lang/StringBuilder."<init>":()V
      51: ldc           #60                 // String Invalid intermediate response:
      53: invokevirtual #36                 // Method java/lang/StringBuilder.append:(Ljava/lang/String;)Ljava/lang/StringBuilder;
      56: iload_2
      57: invokevirtual #37                 // Method java/lang/StringBuilder.append:(I)Ljava/lang/StringBuilder;
      60: invokevirtual #38                 // Method java/lang/StringBuilder.toString:()Ljava/lang/String;
      63: invokespecial #39                 // Method org/apache/hc/core5/http/HttpException."<init>":(Ljava/lang/String;)V
      66: athrow
      67: aload_0
      68: getfield      #7                  // Field outputChannel:Lorg/apache/hc/core5/http/impl/nio/Http1StreamChannel;
      71: aload_1
      72: iconst_1
      73: getstatic     #50                 // Field org/apache/hc/core5/http/impl/nio/FlushMode.IMMEDIATE:Lorg/apache/hc/core5/http/impl/nio/FlushMode;
      76: invokeinterface #52,  4           // InterfaceMethod org/apache/hc/core5/http/impl/nio/Http1StreamChannel.submit:(Lorg/apache/hc/core5/http/HttpMessage;ZLorg/apache/hc/core5/http/impl/nio/FlushMode;)V
      81: return

  private void commitPromise() throws org.apache.hc.core5.http.HttpException;
    Code:
       0: new           #32                 // class org/apache/hc/core5/http/HttpException
       3: dup
       4: ldc           #61                 // String HTTP/1.1 does not support server push
       6: invokespecial #39                 // Method org/apache/hc/core5/http/HttpException."<init>":(Ljava/lang/String;)V
       9: athrow

  void activateChannel() throws java.io.IOException, org.apache.hc.core5.http.HttpException;
    Code:
       0: aload_0
       1: getfield      #7                  // Field outputChannel:Lorg/apache/hc/core5/http/impl/nio/Http1StreamChannel;
       4: invokeinterface #62,  1           // InterfaceMethod org/apache/hc/core5/http/impl/nio/Http1StreamChannel.activate:()V
       9: return

  boolean isResponseFinal();
    Code:
       0: aload_0
       1: getfield      #4                  // Field responseState:Lorg/apache/hc/core5/http/impl/nio/MessageState;
       4: getstatic     #54                 // Field org/apache/hc/core5/http/impl/nio/MessageState.COMPLETE:Lorg/apache/hc/core5/http/impl/nio/MessageState;
       7: if_acmpne     14
      10: iconst_1
      11: goto          15
      14: iconst_0
      15: ireturn

  boolean keepAlive();
    Code:
       0: aload_0
       1: getfield      #5                  // Field keepAlive:Z
       4: ireturn

  boolean isCompleted();
    Code:
       0: aload_0
       1: getfield      #23                 // Field requestState:Lorg/apache/hc/core5/http/impl/nio/MessageState;
       4: getstatic     #54                 // Field org/apache/hc/core5/http/impl/nio/MessageState.COMPLETE:Lorg/apache/hc/core5/http/impl/nio/MessageState;
       7: if_acmpne     24
      10: aload_0
      11: getfield      #4                  // Field responseState:Lorg/apache/hc/core5/http/impl/nio/MessageState;
      14: getstatic     #54                 // Field org/apache/hc/core5/http/impl/nio/MessageState.COMPLETE:Lorg/apache/hc/core5/http/impl/nio/MessageState;
      17: if_acmpne     24
      20: iconst_1
      21: goto          25
      24: iconst_0
      25: ireturn

  void terminateExchange(org.apache.hc.core5.http.HttpException) throws org.apache.hc.core5.http.HttpException, java.io.IOException;
    Code:
       0: aload_0
       1: getfield      #21                 // Field done:Ljava/util/concurrent/atomic/AtomicBoolean;
       4: invokevirtual #59                 // Method java/util/concurrent/atomic/AtomicBoolean.get:()Z
       7: ifne          20
      10: aload_0
      11: getfield      #23                 // Field requestState:Lorg/apache/hc/core5/http/impl/nio/MessageState;
      14: getstatic     #22                 // Field org/apache/hc/core5/http/impl/nio/MessageState.HEADERS:Lorg/apache/hc/core5/http/impl/nio/MessageState;
      17: if_acmpeq     30
      20: new           #63                 // class org/apache/hc/core5/http/ProtocolException
      23: dup
      24: ldc           #64                 // String Unexpected message head
      26: invokespecial #65                 // Method org/apache/hc/core5/http/ProtocolException."<init>":(Ljava/lang/String;)V
      29: athrow
      30: aload_0
      31: aconst_null
      32: putfield      #45                 // Field receivedRequest:Lorg/apache/hc/core5/http/HttpRequest;
      35: aload_0
      36: getstatic     #54                 // Field org/apache/hc/core5/http/impl/nio/MessageState.COMPLETE:Lorg/apache/hc/core5/http/impl/nio/MessageState;
      39: putfield      #23                 // Field requestState:Lorg/apache/hc/core5/http/impl/nio/MessageState;
      42: new           #66                 // class org/apache/hc/core5/http/message/BasicHttpResponse
      45: dup
      46: aload_1
      47: invokestatic  #67                 // Method org/apache/hc/core5/http/impl/ServerSupport.toStatusCode:(Ljava/lang/Exception;)I
      50: invokespecial #68                 // Method org/apache/hc/core5/http/message/BasicHttpResponse."<init>":(I)V
      53: astore_2
      54: aload_2
      55: ldc           #69                 // String Connection
      57: ldc           #70                 // String close
      59: invokeinterface #71,  3           // InterfaceMethod org/apache/hc/core5/http/HttpResponse.addHeader:(Ljava/lang/String;Ljava/lang/Object;)V
      64: new           #72                 // class org/apache/hc/core5/http/nio/support/BasicResponseProducer
      67: dup
      68: aload_2
      69: aload_1
      70: invokestatic  #73                 // Method org/apache/hc/core5/http/impl/ServerSupport.toErrorMessage:(Ljava/lang/Exception;)Ljava/lang/String;
      73: invokespecial #74                 // Method org/apache/hc/core5/http/nio/support/BasicResponseProducer."<init>":(Lorg/apache/hc/core5/http/HttpResponse;Ljava/lang/String;)V
      76: astore_3
      77: aload_0
      78: new           #75                 // class org/apache/hc/core5/http/nio/support/ImmediateResponseExchangeHandler
      81: dup
      82: aload_3
      83: invokespecial #76                 // Method org/apache/hc/core5/http/nio/support/ImmediateResponseExchangeHandler."<init>":(Lorg/apache/hc/core5/http/nio/AsyncResponseProducer;)V
      86: putfield      #56                 // Field exchangeHandler:Lorg/apache/hc/core5/http/nio/AsyncServerExchangeHandler;
      89: aload_0
      90: getfield      #56                 // Field exchangeHandler:Lorg/apache/hc/core5/http/nio/AsyncServerExchangeHandler;
      93: aconst_null
      94: aconst_null
      95: aload_0
      96: getfield      #13                 // Field responseChannel:Lorg/apache/hc/core5/http/nio/ResponseChannel;
      99: aload_0
     100: getfield      #17                 // Field context:Lorg/apache/hc/core5/http/protocol/HttpCoreContext;
     103: invokeinterface #77,  5           // InterfaceMethod org/apache/hc/core5/http/nio/AsyncServerExchangeHandler.handleRequest:(Lorg/apache/hc/core5/http/HttpRequest;Lorg/apache/hc/core5/http/EntityDetails;Lorg/apache/hc/core5/http/nio/ResponseChannel;Lorg/apache/hc/core5/http/protocol/HttpContext;)V
     108: return

  void consumeHeader(org.apache.hc.core5.http.HttpRequest, org.apache.hc.core5.http.EntityDetails) throws org.apache.hc.core5.http.HttpException, java.io.IOException;
    Code:
       0: aload_0
       1: getfield      #21                 // Field done:Ljava/util/concurrent/atomic/AtomicBoolean;
       4: invokevirtual #59                 // Method java/util/concurrent/atomic/AtomicBoolean.get:()Z
       7: ifne          20
      10: aload_0
      11: getfield      #23                 // Field requestState:Lorg/apache/hc/core5/http/impl/nio/MessageState;
      14: getstatic     #22                 // Field org/apache/hc/core5/http/impl/nio/MessageState.HEADERS:Lorg/apache/hc/core5/http/impl/nio/MessageState;
      17: if_acmpeq     30
      20: new           #63                 // class org/apache/hc/core5/http/ProtocolException
      23: dup
      24: ldc           #64                 // String Unexpected message head
      26: invokespecial #65                 // Method org/apache/hc/core5/http/ProtocolException."<init>":(Ljava/lang/String;)V
      29: athrow
      30: aload_0
      31: aload_1
      32: putfield      #45                 // Field receivedRequest:Lorg/apache/hc/core5/http/HttpRequest;
      35: aload_0
      36: aload_2
      37: ifnonnull     46
      40: getstatic     #54                 // Field org/apache/hc/core5/http/impl/nio/MessageState.COMPLETE:Lorg/apache/hc/core5/http/impl/nio/MessageState;
      43: goto          49
      46: getstatic     #55                 // Field org/apache/hc/core5/http/impl/nio/MessageState.BODY:Lorg/apache/hc/core5/http/impl/nio/MessageState;
      49: putfield      #23                 // Field requestState:Lorg/apache/hc/core5/http/impl/nio/MessageState;
      52: aload_0
      53: getfield      #16                 // Field exchangeHandlerFactory:Lorg/apache/hc/core5/http/nio/HandlerFactory;
      56: aload_1
      57: aload_0
      58: getfield      #17                 // Field context:Lorg/apache/hc/core5/http/protocol/HttpCoreContext;
      61: invokeinterface #78,  3           // InterfaceMethod org/apache/hc/core5/http/nio/HandlerFactory.create:(Lorg/apache/hc/core5/http/HttpRequest;Lorg/apache/hc/core5/http/protocol/HttpContext;)Lorg/apache/hc/core5/http/nio/ResourceHolder;
      66: checkcast     #79                 // class org/apache/hc/core5/http/nio/AsyncServerExchangeHandler
      69: astore_3
      70: goto          112
      73: astore        4
      75: new           #75                 // class org/apache/hc/core5/http/nio/support/ImmediateResponseExchangeHandler
      78: dup
      79: sipush        421
      82: aload         4
      84: invokevirtual #81                 // Method org/apache/hc/core5/http/MisdirectedRequestException.getMessage:()Ljava/lang/String;
      87: invokespecial #82                 // Method org/apache/hc/core5/http/nio/support/ImmediateResponseExchangeHandler."<init>":(ILjava/lang/String;)V
      90: astore_3
      91: goto          112
      94: astore        4
      96: new           #75                 // class org/apache/hc/core5/http/nio/support/ImmediateResponseExchangeHandler
      99: dup
     100: sipush        500
     103: aload         4
     105: invokevirtual #83                 // Method org/apache/hc/core5/http/HttpException.getMessage:()Ljava/lang/String;
     108: invokespecial #82                 // Method org/apache/hc/core5/http/nio/support/ImmediateResponseExchangeHandler."<init>":(ILjava/lang/String;)V
     111: astore_3
     112: aload_3
     113: ifnonnull     129
     116: new           #75                 // class org/apache/hc/core5/http/nio/support/ImmediateResponseExchangeHandler
     119: dup
     120: sipush        404
     123: ldc           #84                 // String Cannot handle request
     125: invokespecial #82                 // Method org/apache/hc/core5/http/nio/support/ImmediateResponseExchangeHandler."<init>":(ILjava/lang/String;)V
     128: astore_3
     129: aload_0
     130: aload_3
     131: putfield      #56                 // Field exchangeHandler:Lorg/apache/hc/core5/http/nio/AsyncServerExchangeHandler;
     134: aload_1
     135: invokeinterface #85,  1           // InterfaceMethod org/apache/hc/core5/http/HttpRequest.getVersion:()Lorg/apache/hc/core5/http/ProtocolVersion;
     140: astore        4
     142: aload         4
     144: ifnull        168
     147: aload         4
     149: getstatic     #27                 // Field org/apache/hc/core5/http/HttpVersion.HTTP_2:Lorg/apache/hc/core5/http/HttpVersion;
     152: invokevirtual #28                 // Method org/apache/hc/core5/http/ProtocolVersion.greaterEquals:(Lorg/apache/hc/core5/http/ProtocolVersion;)Z
     155: ifeq          168
     158: new           #29                 // class org/apache/hc/core5/http/UnsupportedHttpVersionException
     161: dup
     162: aload         4
     164: invokespecial #30                 // Method org/apache/hc/core5/http/UnsupportedHttpVersionException."<init>":(Lorg/apache/hc/core5/http/ProtocolVersion;)V
     167: athrow
     168: aload_0
     169: getfield      #17                 // Field context:Lorg/apache/hc/core5/http/protocol/HttpCoreContext;
     172: aload         4
     174: ifnull        182
     177: aload         4
     179: goto          185
     182: getstatic     #40                 // Field org/apache/hc/core5/http/HttpVersion.HTTP_1_1:Lorg/apache/hc/core5/http/HttpVersion;
     185: invokevirtual #41                 // Method org/apache/hc/core5/http/protocol/HttpCoreContext.setProtocolVersion:(Lorg/apache/hc/core5/http/ProtocolVersion;)V
     188: aload_0
     189: getfield      #17                 // Field context:Lorg/apache/hc/core5/http/protocol/HttpCoreContext;
     192: ldc           #86                 // String http.request
     194: aload_1
     195: invokevirtual #43                 // Method org/apache/hc/core5/http/protocol/HttpCoreContext.setAttribute:(Ljava/lang/String;Ljava/lang/Object;)Ljava/lang/Object;
     198: pop
     199: aload_0
     200: getfield      #14                 // Field httpProcessor:Lorg/apache/hc/core5/http/protocol/HttpProcessor;
     203: aload_1
     204: aload_2
     205: aload_0
     206: getfield      #17                 // Field context:Lorg/apache/hc/core5/http/protocol/HttpCoreContext;
     209: invokeinterface #87,  4           // InterfaceMethod org/apache/hc/core5/http/protocol/HttpProcessor.process:(Lorg/apache/hc/core5/http/HttpRequest;Lorg/apache/hc/core5/http/EntityDetails;Lorg/apache/hc/core5/http/protocol/HttpContext;)V
     214: aload_0
     215: getfield      #56                 // Field exchangeHandler:Lorg/apache/hc/core5/http/nio/AsyncServerExchangeHandler;
     218: aload_1
     219: aload_2
     220: aload_0
     221: getfield      #13                 // Field responseChannel:Lorg/apache/hc/core5/http/nio/ResponseChannel;
     224: aload_0
     225: getfield      #17                 // Field context:Lorg/apache/hc/core5/http/protocol/HttpCoreContext;
     228: invokeinterface #77,  5           // InterfaceMethod org/apache/hc/core5/http/nio/AsyncServerExchangeHandler.handleRequest:(Lorg/apache/hc/core5/http/HttpRequest;Lorg/apache/hc/core5/http/EntityDetails;Lorg/apache/hc/core5/http/nio/ResponseChannel;Lorg/apache/hc/core5/http/protocol/HttpContext;)V
     233: goto          327
     236: astore        5
     238: aload_0
     239: getfield      #20                 // Field responseCommitted:Ljava/util/concurrent/atomic/AtomicBoolean;
     242: invokevirtual #59                 // Method java/util/concurrent/atomic/AtomicBoolean.get:()Z
     245: ifne          324
     248: new           #66                 // class org/apache/hc/core5/http/message/BasicHttpResponse
     251: dup
     252: aload         5
     254: invokestatic  #67                 // Method org/apache/hc/core5/http/impl/ServerSupport.toStatusCode:(Ljava/lang/Exception;)I
     257: invokespecial #68                 // Method org/apache/hc/core5/http/message/BasicHttpResponse."<init>":(I)V
     260: astore        6
     262: aload         6
     264: ldc           #69                 // String Connection
     266: ldc           #70                 // String close
     268: invokeinterface #71,  3           // InterfaceMethod org/apache/hc/core5/http/HttpResponse.addHeader:(Ljava/lang/String;Ljava/lang/Object;)V
     273: new           #72                 // class org/apache/hc/core5/http/nio/support/BasicResponseProducer
     276: dup
     277: aload         6
     279: aload         5
     281: invokestatic  #73                 // Method org/apache/hc/core5/http/impl/ServerSupport.toErrorMessage:(Ljava/lang/Exception;)Ljava/lang/String;
     284: invokespecial #74                 // Method org/apache/hc/core5/http/nio/support/BasicResponseProducer."<init>":(Lorg/apache/hc/core5/http/HttpResponse;Ljava/lang/String;)V
     287: astore        7
     289: aload_0
     290: new           #75                 // class org/apache/hc/core5/http/nio/support/ImmediateResponseExchangeHandler
     293: dup
     294: aload         7
     296: invokespecial #76                 // Method org/apache/hc/core5/http/nio/support/ImmediateResponseExchangeHandler."<init>":(Lorg/apache/hc/core5/http/nio/AsyncResponseProducer;)V
     299: putfield      #56                 // Field exchangeHandler:Lorg/apache/hc/core5/http/nio/AsyncServerExchangeHandler;
     302: aload_0
     303: getfield      #56                 // Field exchangeHandler:Lorg/apache/hc/core5/http/nio/AsyncServerExchangeHandler;
     306: aload_1
     307: aload_2
     308: aload_0
     309: getfield      #13                 // Field responseChannel:Lorg/apache/hc/core5/http/nio/ResponseChannel;
     312: aload_0
     313: getfield      #17                 // Field context:Lorg/apache/hc/core5/http/protocol/HttpCoreContext;
     316: invokeinterface #77,  5           // InterfaceMethod org/apache/hc/core5/http/nio/AsyncServerExchangeHandler.handleRequest:(Lorg/apache/hc/core5/http/HttpRequest;Lorg/apache/hc/core5/http/EntityDetails;Lorg/apache/hc/core5/http/nio/ResponseChannel;Lorg/apache/hc/core5/http/protocol/HttpContext;)V
     321: goto          327
     324: aload         5
     326: athrow
     327: return
    Exception table:
       from    to  target type
          52    70    73   Class org/apache/hc/core5/http/MisdirectedRequestException
          52    70    94   Class org/apache/hc/core5/http/HttpException
         199   233   236   Class org/apache/hc/core5/http/HttpException

  boolean isOutputReady();
    Code:
       0: getstatic     #88                 // Field org/apache/hc/core5/http/impl/nio/ServerHttp1StreamHandler$3.$SwitchMap$org$apache$hc$core5$http$impl$nio$MessageState:[I
       3: aload_0
       4: getfield      #4                  // Field responseState:Lorg/apache/hc/core5/http/impl/nio/MessageState;
       7: invokevirtual #89                 // Method org/apache/hc/core5/http/impl/nio/MessageState.ordinal:()I
      10: iaload
      11: lookupswitch  { // 1
                     1: 28
               default: 46
          }
      28: aload_0
      29: getfield      #56                 // Field exchangeHandler:Lorg/apache/hc/core5/http/nio/AsyncServerExchangeHandler;
      32: invokeinterface #90,  1           // InterfaceMethod org/apache/hc/core5/http/nio/AsyncServerExchangeHandler.available:()I
      37: ifle          44
      40: iconst_1
      41: goto          45
      44: iconst_0
      45: ireturn
      46: iconst_0
      47: ireturn

  void produceOutput() throws org.apache.hc.core5.http.HttpException, java.io.IOException;
    Code:
       0: getstatic     #88                 // Field org/apache/hc/core5/http/impl/nio/ServerHttp1StreamHandler$3.$SwitchMap$org$apache$hc$core5$http$impl$nio$MessageState:[I
       3: aload_0
       4: getfield      #4                  // Field responseState:Lorg/apache/hc/core5/http/impl/nio/MessageState;
       7: invokevirtual #89                 // Method org/apache/hc/core5/http/impl/nio/MessageState.ordinal:()I
      10: iaload
      11: lookupswitch  { // 1
                     1: 28
               default: 41
          }
      28: aload_0
      29: getfield      #56                 // Field exchangeHandler:Lorg/apache/hc/core5/http/nio/AsyncServerExchangeHandler;
      32: aload_0
      33: getfield      #10                 // Field internalDataChannel:Lorg/apache/hc/core5/http/nio/DataStreamChannel;
      36: invokeinterface #57,  2           // InterfaceMethod org/apache/hc/core5/http/nio/AsyncServerExchangeHandler.produce:(Lorg/apache/hc/core5/http/nio/DataStreamChannel;)V
      41: return

  void consumeData(java.nio.ByteBuffer) throws org.apache.hc.core5.http.HttpException, java.io.IOException;
    Code:
       0: aload_0
       1: getfield      #21                 // Field done:Ljava/util/concurrent/atomic/AtomicBoolean;
       4: invokevirtual #59                 // Method java/util/concurrent/atomic/AtomicBoolean.get:()Z
       7: ifne          20
      10: aload_0
      11: getfield      #23                 // Field requestState:Lorg/apache/hc/core5/http/impl/nio/MessageState;
      14: getstatic     #55                 // Field org/apache/hc/core5/http/impl/nio/MessageState.BODY:Lorg/apache/hc/core5/http/impl/nio/MessageState;
      17: if_acmpeq     30
      20: new           #63                 // class org/apache/hc/core5/http/ProtocolException
      23: dup
      24: ldc           #91                 // String Unexpected message data
      26: invokespecial #65                 // Method org/apache/hc/core5/http/ProtocolException."<init>":(Ljava/lang/String;)V
      29: athrow
      30: aload_0
      31: getfield      #4                  // Field responseState:Lorg/apache/hc/core5/http/impl/nio/MessageState;
      34: getstatic     #92                 // Field org/apache/hc/core5/http/impl/nio/MessageState.ACK:Lorg/apache/hc/core5/http/impl/nio/MessageState;
      37: if_acmpne     49
      40: aload_0
      41: getfield      #7                  // Field outputChannel:Lorg/apache/hc/core5/http/impl/nio/Http1StreamChannel;
      44: invokeinterface #93,  1           // InterfaceMethod org/apache/hc/core5/http/impl/nio/Http1StreamChannel.requestOutput:()V
      49: aload_0
      50: getfield      #56                 // Field exchangeHandler:Lorg/apache/hc/core5/http/nio/AsyncServerExchangeHandler;
      53: aload_1
      54: invokeinterface #94,  2           // InterfaceMethod org/apache/hc/core5/http/nio/AsyncServerExchangeHandler.consume:(Ljava/nio/ByteBuffer;)V
      59: return

  void updateCapacity(org.apache.hc.core5.http.nio.CapacityChannel) throws java.io.IOException;
    Code:
       0: aload_0
       1: getfield      #56                 // Field exchangeHandler:Lorg/apache/hc/core5/http/nio/AsyncServerExchangeHandler;
       4: aload_1
       5: invokeinterface #95,  2           // InterfaceMethod org/apache/hc/core5/http/nio/AsyncServerExchangeHandler.updateCapacity:(Lorg/apache/hc/core5/http/nio/CapacityChannel;)V
      10: return

  void dataEnd(java.util.List<? extends org.apache.hc.core5.http.Header>) throws org.apache.hc.core5.http.HttpException, java.io.IOException;
    Code:
       0: aload_0
       1: getfield      #21                 // Field done:Ljava/util/concurrent/atomic/AtomicBoolean;
       4: invokevirtual #59                 // Method java/util/concurrent/atomic/AtomicBoolean.get:()Z
       7: ifne          20
      10: aload_0
      11: getfield      #23                 // Field requestState:Lorg/apache/hc/core5/http/impl/nio/MessageState;
      14: getstatic     #55                 // Field org/apache/hc/core5/http/impl/nio/MessageState.BODY:Lorg/apache/hc/core5/http/impl/nio/MessageState;
      17: if_acmpeq     30
      20: new           #63                 // class org/apache/hc/core5/http/ProtocolException
      23: dup
      24: ldc           #91                 // String Unexpected message data
      26: invokespecial #65                 // Method org/apache/hc/core5/http/ProtocolException."<init>":(Ljava/lang/String;)V
      29: athrow
      30: aload_0
      31: getstatic     #54                 // Field org/apache/hc/core5/http/impl/nio/MessageState.COMPLETE:Lorg/apache/hc/core5/http/impl/nio/MessageState;
      34: putfield      #23                 // Field requestState:Lorg/apache/hc/core5/http/impl/nio/MessageState;
      37: aload_0
      38: getfield      #56                 // Field exchangeHandler:Lorg/apache/hc/core5/http/nio/AsyncServerExchangeHandler;
      41: aload_1
      42: invokeinterface #96,  2           // InterfaceMethod org/apache/hc/core5/http/nio/AsyncServerExchangeHandler.streamEnd:(Ljava/util/List;)V
      47: return

  void failed(java.lang.Exception);
    Code:
       0: aload_0
       1: getfield      #21                 // Field done:Ljava/util/concurrent/atomic/AtomicBoolean;
       4: invokevirtual #59                 // Method java/util/concurrent/atomic/AtomicBoolean.get:()Z
       7: ifne          20
      10: aload_0
      11: getfield      #56                 // Field exchangeHandler:Lorg/apache/hc/core5/http/nio/AsyncServerExchangeHandler;
      14: aload_1
      15: invokeinterface #97,  2           // InterfaceMethod org/apache/hc/core5/http/nio/AsyncServerExchangeHandler.failed:(Ljava/lang/Exception;)V
      20: return

  public void releaseResources();
    Code:
       0: aload_0
       1: getfield      #21                 // Field done:Ljava/util/concurrent/atomic/AtomicBoolean;
       4: iconst_0
       5: iconst_1
       6: invokevirtual #25                 // Method java/util/concurrent/atomic/AtomicBoolean.compareAndSet:(ZZ)Z
       9: ifeq          35
      12: aload_0
      13: getstatic     #54                 // Field org/apache/hc/core5/http/impl/nio/MessageState.COMPLETE:Lorg/apache/hc/core5/http/impl/nio/MessageState;
      16: putfield      #23                 // Field requestState:Lorg/apache/hc/core5/http/impl/nio/MessageState;
      19: aload_0
      20: getstatic     #54                 // Field org/apache/hc/core5/http/impl/nio/MessageState.COMPLETE:Lorg/apache/hc/core5/http/impl/nio/MessageState;
      23: putfield      #4                  // Field responseState:Lorg/apache/hc/core5/http/impl/nio/MessageState;
      26: aload_0
      27: getfield      #56                 // Field exchangeHandler:Lorg/apache/hc/core5/http/nio/AsyncServerExchangeHandler;
      30: invokeinterface #98,  1           // InterfaceMethod org/apache/hc/core5/http/nio/AsyncServerExchangeHandler.releaseResources:()V
      35: return

  void appendState(java.lang.StringBuilder);
    Code:
       0: aload_1
       1: ldc           #99                 // String requestState=
       3: invokevirtual #36                 // Method java/lang/StringBuilder.append:(Ljava/lang/String;)Ljava/lang/StringBuilder;
       6: aload_0
       7: getfield      #23                 // Field requestState:Lorg/apache/hc/core5/http/impl/nio/MessageState;
      10: invokevirtual #100                // Method java/lang/StringBuilder.append:(Ljava/lang/Object;)Ljava/lang/StringBuilder;
      13: ldc           #101                // String , responseState=
      15: invokevirtual #36                 // Method java/lang/StringBuilder.append:(Ljava/lang/String;)Ljava/lang/StringBuilder;
      18: aload_0
      19: getfield      #4                  // Field responseState:Lorg/apache/hc/core5/http/impl/nio/MessageState;
      22: invokevirtual #100                // Method java/lang/StringBuilder.append:(Ljava/lang/Object;)Ljava/lang/StringBuilder;
      25: ldc           #102                // String , responseCommitted=
      27: invokevirtual #36                 // Method java/lang/StringBuilder.append:(Ljava/lang/String;)Ljava/lang/StringBuilder;
      30: aload_0
      31: getfield      #20                 // Field responseCommitted:Ljava/util/concurrent/atomic/AtomicBoolean;
      34: invokevirtual #100                // Method java/lang/StringBuilder.append:(Ljava/lang/Object;)Ljava/lang/StringBuilder;
      37: ldc           #103                // String , keepAlive=
      39: invokevirtual #36                 // Method java/lang/StringBuilder.append:(Ljava/lang/String;)Ljava/lang/StringBuilder;
      42: aload_0
      43: getfield      #5                  // Field keepAlive:Z
      46: invokevirtual #104                // Method java/lang/StringBuilder.append:(Z)Ljava/lang/StringBuilder;
      49: ldc           #105                // String , done=
      51: invokevirtual #36                 // Method java/lang/StringBuilder.append:(Ljava/lang/String;)Ljava/lang/StringBuilder;
      54: aload_0
      55: getfield      #21                 // Field done:Ljava/util/concurrent/atomic/AtomicBoolean;
      58: invokevirtual #100                // Method java/lang/StringBuilder.append:(Ljava/lang/Object;)Ljava/lang/StringBuilder;
      61: pop
      62: return

  public java.lang.String toString();
    Code:
       0: new           #33                 // class java/lang/StringBuilder
       3: dup
       4: invokespecial #34                 // Method java/lang/StringBuilder."<init>":()V
       7: astore_1
       8: aload_1
       9: ldc           #106                // String [
      11: invokevirtual #36                 // Method java/lang/StringBuilder.append:(Ljava/lang/String;)Ljava/lang/StringBuilder;
      14: pop
      15: aload_0
      16: aload_1
      17: invokevirtual #107                // Method appendState:(Ljava/lang/StringBuilder;)V
      20: aload_1
      21: ldc           #108                // String ]
      23: invokevirtual #36                 // Method java/lang/StringBuilder.append:(Ljava/lang/String;)Ljava/lang/StringBuilder;
      26: pop
      27: aload_1
      28: invokevirtual #38                 // Method java/lang/StringBuilder.toString:()Ljava/lang/String;
      31: areturn

  static boolean access$000(org.apache.hc.core5.http.impl.nio.ServerHttp1StreamHandler);
    Code:
       0: aload_0
       1: getfield      #5                  // Field keepAlive:Z
       4: ireturn

  static org.apache.hc.core5.http.impl.nio.MessageState access$102(org.apache.hc.core5.http.impl.nio.ServerHttp1StreamHandler, org.apache.hc.core5.http.impl.nio.MessageState);
    Code:
       0: aload_0
       1: aload_1
       2: dup_x1
       3: putfield      #4                  // Field responseState:Lorg/apache/hc/core5/http/impl/nio/MessageState;
       6: areturn

  static void access$200(org.apache.hc.core5.http.impl.nio.ServerHttp1StreamHandler, org.apache.hc.core5.http.HttpResponse) throws java.io.IOException, org.apache.hc.core5.http.HttpException;
    Code:
       0: aload_0
       1: aload_1
       2: invokespecial #3                  // Method commitInformation:(Lorg/apache/hc/core5/http/HttpResponse;)V
       5: return

  static void access$300(org.apache.hc.core5.http.impl.nio.ServerHttp1StreamHandler, org.apache.hc.core5.http.HttpResponse, org.apache.hc.core5.http.EntityDetails) throws org.apache.hc.core5.http.HttpException, java.io.IOException;
    Code:
       0: aload_0
       1: aload_1
       2: aload_2
       3: invokespecial #2                  // Method commitResponse:(Lorg/apache/hc/core5/http/HttpResponse;Lorg/apache/hc/core5/http/EntityDetails;)V
       6: return

  static void access$400(org.apache.hc.core5.http.impl.nio.ServerHttp1StreamHandler) throws org.apache.hc.core5.http.HttpException;
    Code:
       0: aload_0
       1: invokespecial #1                  // Method commitPromise:()V
       4: return
}
