Compiled from "Dom4JXmlWriter.java"
public class com.thoughtworks.xstream.io.xml.Dom4JXmlWriter extends com.thoughtworks.xstream.io.xml.AbstractXmlWriter {
  private final org.dom4j.io.XMLWriter writer;

  private final com.thoughtworks.xstream.core.util.FastStack elementStack;

  private org.xml.sax.helpers.AttributesImpl attributes;

  private boolean started;

  private boolean children;

  public com.thoughtworks.xstream.io.xml.Dom4JXmlWriter(org.dom4j.io.XMLWriter);
    Code:
       0: aload_0
       1: aload_1
       2: new           #1                  // class com/thoughtworks/xstream/io/xml/XmlFriendlyNameCoder
       5: dup
       6: invokespecial #2                  // Method com/thoughtworks/xstream/io/xml/XmlFriendlyNameCoder."<init>":()V
       9: invokespecial #3                  // Method "<init>":(Lorg/dom4j/io/XMLWriter;Lcom/thoughtworks/xstream/io/naming/NameCoder;)V
      12: return

  public com.thoughtworks.xstream.io.xml.Dom4JXmlWriter(org.dom4j.io.XMLWriter, com.thoughtworks.xstream.io.naming.NameCoder);
    Code:
       0: aload_0
       1: aload_2
       2: invokespecial #4                  // Method com/thoughtworks/xstream/io/xml/AbstractXmlWriter."<init>":(Lcom/thoughtworks/xstream/io/naming/NameCoder;)V
       5: aload_0
       6: aload_1
       7: putfield      #5                  // Field writer:Lorg/dom4j/io/XMLWriter;
      10: aload_0
      11: new           #6                  // class com/thoughtworks/xstream/core/util/FastStack
      14: dup
      15: bipush        16
      17: invokespecial #7                  // Method com/thoughtworks/xstream/core/util/FastStack."<init>":(I)V
      20: putfield      #8                  // Field elementStack:Lcom/thoughtworks/xstream/core/util/FastStack;
      23: aload_0
      24: new           #9                  // class org/xml/sax/helpers/AttributesImpl
      27: dup
      28: invokespecial #10                 // Method org/xml/sax/helpers/AttributesImpl."<init>":()V
      31: putfield      #11                 // Field attributes:Lorg/xml/sax/helpers/AttributesImpl;
      34: aload_1
      35: invokevirtual #12                 // Method org/dom4j/io/XMLWriter.startDocument:()V
      38: goto          51
      41: astore_3
      42: new           #14                 // class com/thoughtworks/xstream/io/StreamException
      45: dup
      46: aload_3
      47: invokespecial #15                 // Method com/thoughtworks/xstream/io/StreamException."<init>":(Ljava/lang/Throwable;)V
      50: athrow
      51: return
    Exception table:
       from    to  target type
          34    38    41   Class org/xml/sax/SAXException

  public com.thoughtworks.xstream.io.xml.Dom4JXmlWriter(org.dom4j.io.XMLWriter, com.thoughtworks.xstream.io.xml.XmlFriendlyReplacer);
    Code:
       0: aload_0
       1: aload_1
       2: aload_2
       3: invokespecial #3                  // Method "<init>":(Lorg/dom4j/io/XMLWriter;Lcom/thoughtworks/xstream/io/naming/NameCoder;)V
       6: return

  public void startNode(java.lang.String);
    Code:
       0: aload_0
       1: getfield      #8                  // Field elementStack:Lcom/thoughtworks/xstream/core/util/FastStack;
       4: invokevirtual #16                 // Method com/thoughtworks/xstream/core/util/FastStack.size:()I
       7: ifle          32
      10: aload_0
      11: invokespecial #17                 // Method startElement:()V
      14: goto          27
      17: astore_2
      18: new           #14                 // class com/thoughtworks/xstream/io/StreamException
      21: dup
      22: aload_2
      23: invokespecial #15                 // Method com/thoughtworks/xstream/io/StreamException."<init>":(Ljava/lang/Throwable;)V
      26: athrow
      27: aload_0
      28: iconst_0
      29: putfield      #18                 // Field started:Z
      32: aload_0
      33: getfield      #8                  // Field elementStack:Lcom/thoughtworks/xstream/core/util/FastStack;
      36: aload_0
      37: aload_1
      38: invokevirtual #19                 // Method encodeNode:(Ljava/lang/String;)Ljava/lang/String;
      41: invokevirtual #20                 // Method com/thoughtworks/xstream/core/util/FastStack.push:(Ljava/lang/Object;)Ljava/lang/Object;
      44: pop
      45: aload_0
      46: iconst_0
      47: putfield      #21                 // Field children:Z
      50: return
    Exception table:
       from    to  target type
          10    14    17   Class org/xml/sax/SAXException

  public void setValue(java.lang.String);
    Code:
       0: aload_1
       1: invokevirtual #22                 // Method java/lang/String.toCharArray:()[C
       4: astore_2
       5: aload_2
       6: arraylength
       7: ifle          43
      10: aload_0
      11: invokespecial #17                 // Method startElement:()V
      14: aload_0
      15: getfield      #5                  // Field writer:Lorg/dom4j/io/XMLWriter;
      18: aload_2
      19: iconst_0
      20: aload_2
      21: arraylength
      22: invokevirtual #23                 // Method org/dom4j/io/XMLWriter.characters:([CII)V
      25: goto          38
      28: astore_3
      29: new           #14                 // class com/thoughtworks/xstream/io/StreamException
      32: dup
      33: aload_3
      34: invokespecial #15                 // Method com/thoughtworks/xstream/io/StreamException."<init>":(Ljava/lang/Throwable;)V
      37: athrow
      38: aload_0
      39: iconst_1
      40: putfield      #21                 // Field children:Z
      43: return
    Exception table:
       from    to  target type
          10    25    28   Class org/xml/sax/SAXException

  public void addAttribute(java.lang.String, java.lang.String);
    Code:
       0: aload_0
       1: getfield      #11                 // Field attributes:Lorg/xml/sax/helpers/AttributesImpl;
       4: ldc           #24                 // String
       6: ldc           #24                 // String
       8: aload_0
       9: aload_1
      10: invokevirtual #25                 // Method encodeAttribute:(Ljava/lang/String;)Ljava/lang/String;
      13: ldc           #26                 // String string
      15: aload_2
      16: invokevirtual #27                 // Method org/xml/sax/helpers/AttributesImpl.addAttribute:(Ljava/lang/String;Ljava/lang/String;Ljava/lang/String;Ljava/lang/String;Ljava/lang/String;)V
      19: return

  public void endNode();
    Code:
       0: aload_0
       1: getfield      #21                 // Field children:Z
       4: ifne          95
       7: new           #28                 // class org/dom4j/tree/DefaultElement
      10: dup
      11: aload_0
      12: getfield      #8                  // Field elementStack:Lcom/thoughtworks/xstream/core/util/FastStack;
      15: invokevirtual #29                 // Method com/thoughtworks/xstream/core/util/FastStack.pop:()Ljava/lang/Object;
      18: checkcast     #30                 // class java/lang/String
      21: invokespecial #31                 // Method org/dom4j/tree/DefaultElement."<init>":(Ljava/lang/String;)V
      24: astore_1
      25: iconst_0
      26: istore_2
      27: iload_2
      28: aload_0
      29: getfield      #11                 // Field attributes:Lorg/xml/sax/helpers/AttributesImpl;
      32: invokevirtual #32                 // Method org/xml/sax/helpers/AttributesImpl.getLength:()I
      35: if_icmpge     67
      38: aload_1
      39: aload_0
      40: getfield      #11                 // Field attributes:Lorg/xml/sax/helpers/AttributesImpl;
      43: iload_2
      44: invokevirtual #33                 // Method org/xml/sax/helpers/AttributesImpl.getQName:(I)Ljava/lang/String;
      47: aload_0
      48: getfield      #11                 // Field attributes:Lorg/xml/sax/helpers/AttributesImpl;
      51: iload_2
      52: invokevirtual #34                 // Method org/xml/sax/helpers/AttributesImpl.getValue:(I)Ljava/lang/String;
      55: invokeinterface #35,  3           // InterfaceMethod org/dom4j/Element.addAttribute:(Ljava/lang/String;Ljava/lang/String;)Lorg/dom4j/Element;
      60: pop
      61: iinc          2, 1
      64: goto          27
      67: aload_0
      68: getfield      #5                  // Field writer:Lorg/dom4j/io/XMLWriter;
      71: aload_1
      72: invokevirtual #36                 // Method org/dom4j/io/XMLWriter.write:(Lorg/dom4j/Element;)V
      75: aload_0
      76: getfield      #11                 // Field attributes:Lorg/xml/sax/helpers/AttributesImpl;
      79: invokevirtual #37                 // Method org/xml/sax/helpers/AttributesImpl.clear:()V
      82: aload_0
      83: iconst_1
      84: putfield      #21                 // Field children:Z
      87: aload_0
      88: iconst_1
      89: putfield      #18                 // Field started:Z
      92: goto          120
      95: aload_0
      96: invokespecial #17                 // Method startElement:()V
      99: aload_0
     100: getfield      #5                  // Field writer:Lorg/dom4j/io/XMLWriter;
     103: ldc           #24                 // String
     105: ldc           #24                 // String
     107: aload_0
     108: getfield      #8                  // Field elementStack:Lcom/thoughtworks/xstream/core/util/FastStack;
     111: invokevirtual #29                 // Method com/thoughtworks/xstream/core/util/FastStack.pop:()Ljava/lang/Object;
     114: checkcast     #30                 // class java/lang/String
     117: invokevirtual #38                 // Method org/dom4j/io/XMLWriter.endElement:(Ljava/lang/String;Ljava/lang/String;Ljava/lang/String;)V
     120: goto          143
     123: astore_1
     124: new           #14                 // class com/thoughtworks/xstream/io/StreamException
     127: dup
     128: aload_1
     129: invokespecial #15                 // Method com/thoughtworks/xstream/io/StreamException."<init>":(Ljava/lang/Throwable;)V
     132: athrow
     133: astore_1
     134: new           #14                 // class com/thoughtworks/xstream/io/StreamException
     137: dup
     138: aload_1
     139: invokespecial #15                 // Method com/thoughtworks/xstream/io/StreamException."<init>":(Ljava/lang/Throwable;)V
     142: athrow
     143: return
    Exception table:
       from    to  target type
           0   120   123   Class org/xml/sax/SAXException
           0   120   133   Class java/io/IOException

  public void flush();
    Code:
       0: aload_0
       1: getfield      #5                  // Field writer:Lorg/dom4j/io/XMLWriter;
       4: invokevirtual #40                 // Method org/dom4j/io/XMLWriter.flush:()V
       7: goto          20
      10: astore_1
      11: new           #14                 // class com/thoughtworks/xstream/io/StreamException
      14: dup
      15: aload_1
      16: invokespecial #15                 // Method com/thoughtworks/xstream/io/StreamException."<init>":(Ljava/lang/Throwable;)V
      19: athrow
      20: return
    Exception table:
       from    to  target type
           0     7    10   Class java/io/IOException

  public void close();
    Code:
       0: aload_0
       1: getfield      #5                  // Field writer:Lorg/dom4j/io/XMLWriter;
       4: invokevirtual #41                 // Method org/dom4j/io/XMLWriter.endDocument:()V
       7: goto          20
      10: astore_1
      11: new           #14                 // class com/thoughtworks/xstream/io/StreamException
      14: dup
      15: aload_1
      16: invokespecial #15                 // Method com/thoughtworks/xstream/io/StreamException."<init>":(Ljava/lang/Throwable;)V
      19: athrow
      20: return
    Exception table:
       from    to  target type
           0     7    10   Class org/xml/sax/SAXException

  private void startElement() throws org.xml.sax.SAXException;
    Code:
       0: aload_0
       1: getfield      #18                 // Field started:Z
       4: ifne          44
       7: aload_0
       8: getfield      #5                  // Field writer:Lorg/dom4j/io/XMLWriter;
      11: ldc           #24                 // String
      13: ldc           #24                 // String
      15: aload_0
      16: getfield      #8                  // Field elementStack:Lcom/thoughtworks/xstream/core/util/FastStack;
      19: invokevirtual #42                 // Method com/thoughtworks/xstream/core/util/FastStack.peek:()Ljava/lang/Object;
      22: checkcast     #30                 // class java/lang/String
      25: aload_0
      26: getfield      #11                 // Field attributes:Lorg/xml/sax/helpers/AttributesImpl;
      29: invokevirtual #43                 // Method org/dom4j/io/XMLWriter.startElement:(Ljava/lang/String;Ljava/lang/String;Ljava/lang/String;Lorg/xml/sax/Attributes;)V
      32: aload_0
      33: getfield      #11                 // Field attributes:Lorg/xml/sax/helpers/AttributesImpl;
      36: invokevirtual #37                 // Method org/xml/sax/helpers/AttributesImpl.clear:()V
      39: aload_0
      40: iconst_1
      41: putfield      #18                 // Field started:Z
      44: return
}
