Compiled from "JDomDriver.java"
public class com.thoughtworks.xstream.io.xml.JDomDriver extends com.thoughtworks.xstream.io.xml.AbstractXmlDriver {
  public com.thoughtworks.xstream.io.xml.JDomDriver();
    Code:
       0: aload_0
       1: new           #1                  // class com/thoughtworks/xstream/io/xml/XmlFriendlyNameCoder
       4: dup
       5: invokespecial #2                  // Method com/thoughtworks/xstream/io/xml/XmlFriendlyNameCoder."<init>":()V
       8: invokespecial #3                  // Method com/thoughtworks/xstream/io/xml/AbstractXmlDriver."<init>":(Lcom/thoughtworks/xstream/io/naming/NameCoder;)V
      11: return

  public com.thoughtworks.xstream.io.xml.JDomDriver(com.thoughtworks.xstream.io.naming.NameCoder);
    Code:
       0: aload_0
       1: aload_1
       2: invokespecial #3                  // Method com/thoughtworks/xstream/io/xml/AbstractXmlDriver."<init>":(Lcom/thoughtworks/xstream/io/naming/NameCoder;)V
       5: return

  public com.thoughtworks.xstream.io.xml.JDomDriver(com.thoughtworks.xstream.io.xml.XmlFriendlyReplacer);
    Code:
       0: aload_0
       1: aload_1
       2: invokespecial #4                  // Method "<init>":(Lcom/thoughtworks/xstream/io/naming/NameCoder;)V
       5: return

  public com.thoughtworks.xstream.io.HierarchicalStreamReader createReader(java.io.Reader);
    Code:
       0: new           #5                  // class org/jdom/input/SAXBuilder
       3: dup
       4: invokespecial #6                  // Method org/jdom/input/SAXBuilder."<init>":()V
       7: astore_2
       8: aload_2
       9: aload_1
      10: invokevirtual #7                  // Method org/jdom/input/SAXBuilder.build:(Ljava/io/Reader;)Lorg/jdom/Document;
      13: astore_3
      14: new           #8                  // class com/thoughtworks/xstream/io/xml/JDomReader
      17: dup
      18: aload_3
      19: aload_0
      20: invokevirtual #9                  // Method getNameCoder:()Lcom/thoughtworks/xstream/io/naming/NameCoder;
      23: invokespecial #10                 // Method com/thoughtworks/xstream/io/xml/JDomReader."<init>":(Lorg/jdom/Document;Lcom/thoughtworks/xstream/io/naming/NameCoder;)V
      26: areturn
      27: astore_2
      28: new           #12                 // class com/thoughtworks/xstream/io/StreamException
      31: dup
      32: aload_2
      33: invokespecial #13                 // Method com/thoughtworks/xstream/io/StreamException."<init>":(Ljava/lang/Throwable;)V
      36: athrow
      37: astore_2
      38: new           #12                 // class com/thoughtworks/xstream/io/StreamException
      41: dup
      42: aload_2
      43: invokespecial #13                 // Method com/thoughtworks/xstream/io/StreamException."<init>":(Ljava/lang/Throwable;)V
      46: athrow
    Exception table:
       from    to  target type
           0    26    27   Class java/io/IOException
           0    26    37   Class org/jdom/JDOMException

  public com.thoughtworks.xstream.io.HierarchicalStreamReader createReader(java.io.InputStream);
    Code:
       0: new           #5                  // class org/jdom/input/SAXBuilder
       3: dup
       4: invokespecial #6                  // Method org/jdom/input/SAXBuilder."<init>":()V
       7: astore_2
       8: aload_2
       9: aload_1
      10: invokevirtual #15                 // Method org/jdom/input/SAXBuilder.build:(Ljava/io/InputStream;)Lorg/jdom/Document;
      13: astore_3
      14: new           #8                  // class com/thoughtworks/xstream/io/xml/JDomReader
      17: dup
      18: aload_3
      19: aload_0
      20: invokevirtual #9                  // Method getNameCoder:()Lcom/thoughtworks/xstream/io/naming/NameCoder;
      23: invokespecial #10                 // Method com/thoughtworks/xstream/io/xml/JDomReader."<init>":(Lorg/jdom/Document;Lcom/thoughtworks/xstream/io/naming/NameCoder;)V
      26: areturn
      27: astore_2
      28: new           #12                 // class com/thoughtworks/xstream/io/StreamException
      31: dup
      32: aload_2
      33: invokespecial #13                 // Method com/thoughtworks/xstream/io/StreamException."<init>":(Ljava/lang/Throwable;)V
      36: athrow
      37: astore_2
      38: new           #12                 // class com/thoughtworks/xstream/io/StreamException
      41: dup
      42: aload_2
      43: invokespecial #13                 // Method com/thoughtworks/xstream/io/StreamException."<init>":(Ljava/lang/Throwable;)V
      46: athrow
    Exception table:
       from    to  target type
           0    26    27   Class java/io/IOException
           0    26    37   Class org/jdom/JDOMException

  public com.thoughtworks.xstream.io.HierarchicalStreamReader createReader(java.net.URL);
    Code:
       0: new           #5                  // class org/jdom/input/SAXBuilder
       3: dup
       4: invokespecial #6                  // Method org/jdom/input/SAXBuilder."<init>":()V
       7: astore_2
       8: aload_2
       9: aload_1
      10: invokevirtual #16                 // Method org/jdom/input/SAXBuilder.build:(Ljava/net/URL;)Lorg/jdom/Document;
      13: astore_3
      14: new           #8                  // class com/thoughtworks/xstream/io/xml/JDomReader
      17: dup
      18: aload_3
      19: aload_0
      20: invokevirtual #9                  // Method getNameCoder:()Lcom/thoughtworks/xstream/io/naming/NameCoder;
      23: invokespecial #10                 // Method com/thoughtworks/xstream/io/xml/JDomReader."<init>":(Lorg/jdom/Document;Lcom/thoughtworks/xstream/io/naming/NameCoder;)V
      26: areturn
      27: astore_2
      28: new           #12                 // class com/thoughtworks/xstream/io/StreamException
      31: dup
      32: aload_2
      33: invokespecial #13                 // Method com/thoughtworks/xstream/io/StreamException."<init>":(Ljava/lang/Throwable;)V
      36: athrow
      37: astore_2
      38: new           #12                 // class com/thoughtworks/xstream/io/StreamException
      41: dup
      42: aload_2
      43: invokespecial #13                 // Method com/thoughtworks/xstream/io/StreamException."<init>":(Ljava/lang/Throwable;)V
      46: athrow
    Exception table:
       from    to  target type
           0    26    27   Class java/io/IOException
           0    26    37   Class org/jdom/JDOMException

  public com.thoughtworks.xstream.io.HierarchicalStreamReader createReader(java.io.File);
    Code:
       0: new           #5                  // class org/jdom/input/SAXBuilder
       3: dup
       4: invokespecial #6                  // Method org/jdom/input/SAXBuilder."<init>":()V
       7: astore_2
       8: aload_2
       9: aload_1
      10: invokevirtual #17                 // Method org/jdom/input/SAXBuilder.build:(Ljava/io/File;)Lorg/jdom/Document;
      13: astore_3
      14: new           #8                  // class com/thoughtworks/xstream/io/xml/JDomReader
      17: dup
      18: aload_3
      19: aload_0
      20: invokevirtual #9                  // Method getNameCoder:()Lcom/thoughtworks/xstream/io/naming/NameCoder;
      23: invokespecial #10                 // Method com/thoughtworks/xstream/io/xml/JDomReader."<init>":(Lorg/jdom/Document;Lcom/thoughtworks/xstream/io/naming/NameCoder;)V
      26: areturn
      27: astore_2
      28: new           #12                 // class com/thoughtworks/xstream/io/StreamException
      31: dup
      32: aload_2
      33: invokespecial #13                 // Method com/thoughtworks/xstream/io/StreamException."<init>":(Ljava/lang/Throwable;)V
      36: athrow
      37: astore_2
      38: new           #12                 // class com/thoughtworks/xstream/io/StreamException
      41: dup
      42: aload_2
      43: invokespecial #13                 // Method com/thoughtworks/xstream/io/StreamException."<init>":(Ljava/lang/Throwable;)V
      46: athrow
    Exception table:
       from    to  target type
           0    26    27   Class java/io/IOException
           0    26    37   Class org/jdom/JDOMException

  public com.thoughtworks.xstream.io.HierarchicalStreamWriter createWriter(java.io.Writer);
    Code:
       0: new           #18                 // class com/thoughtworks/xstream/io/xml/PrettyPrintWriter
       3: dup
       4: aload_1
       5: aload_0
       6: invokevirtual #9                  // Method getNameCoder:()Lcom/thoughtworks/xstream/io/naming/NameCoder;
       9: invokespecial #19                 // Method com/thoughtworks/xstream/io/xml/PrettyPrintWriter."<init>":(Ljava/io/Writer;Lcom/thoughtworks/xstream/io/naming/NameCoder;)V
      12: areturn

  public com.thoughtworks.xstream.io.HierarchicalStreamWriter createWriter(java.io.OutputStream);
    Code:
       0: new           #18                 // class com/thoughtworks/xstream/io/xml/PrettyPrintWriter
       3: dup
       4: new           #20                 // class java/io/OutputStreamWriter
       7: dup
       8: aload_1
       9: invokespecial #21                 // Method java/io/OutputStreamWriter."<init>":(Ljava/io/OutputStream;)V
      12: invokespecial #22                 // Method com/thoughtworks/xstream/io/xml/PrettyPrintWriter."<init>":(Ljava/io/Writer;)V
      15: areturn
}
