Compiled from "XmlFriendlyNameCoder.java"
class com.thoughtworks.xstream.io.xml.XmlFriendlyNameCoder$IntPair {
  int min;

  int max;

  public com.thoughtworks.xstream.io.xml.XmlFriendlyNameCoder$IntPair(int, int);
    Code:
       0: aload_0
       1: invokespecial #1                  // Method java/lang/Object."<init>":()V
       4: aload_0
       5: iload_1
       6: putfield      #2                  // Field min:I
       9: aload_0
      10: iload_2
      11: putfield      #3                  // Field max:I
      14: return
}
