Compiled from "BytecodeReadingParanamer.java"
class org.picocontainer.paranamer.BytecodeReadingParanamer$TypeCollector {
  private static final java.lang.String COMMA;

  private final java.lang.String methodName;

  private final java.lang.Class<?>[] parameterTypes;

  private final boolean throwExceptionIfMissing;

  private org.picocontainer.paranamer.BytecodeReadingParanamer$MethodCollector collector;

  public static final java.lang.String __PARANAMER_DATA;

  private org.picocontainer.paranamer.BytecodeReadingParanamer$TypeCollector(java.lang.String, java.lang.Class<?>[], boolean);
    Code:
       0: aload_0
       1: invokespecial #36                 // Method java/lang/Object."<init>":()V
       4: aload_0
       5: aload_1
       6: putfield      #38                 // Field methodName:Ljava/lang/String;
       9: aload_0
      10: aload_2
      11: putfield      #40                 // Field parameterTypes:[Ljava/lang/Class;
      14: aload_0
      15: iload_3
      16: putfield      #42                 // Field throwExceptionIfMissing:Z
      19: aload_0
      20: aconst_null
      21: putfield      #44                 // Field collector:Lorg/picocontainer/paranamer/BytecodeReadingParanamer$MethodCollector;
      24: return

  public org.picocontainer.paranamer.BytecodeReadingParanamer$MethodCollector visitMethod(int, java.lang.String, java.lang.String);
    Code:
       0: aload_0
       1: getfield      #44                 // Field collector:Lorg/picocontainer/paranamer/BytecodeReadingParanamer$MethodCollector;
       4: ifnull        9
       7: aconst_null
       8: areturn
       9: aload_2
      10: aload_0
      11: getfield      #38                 // Field methodName:Ljava/lang/String;
      14: invokevirtual #54                 // Method java/lang/String.equals:(Ljava/lang/Object;)Z
      17: ifne          22
      20: aconst_null
      21: areturn
      22: aload_3
      23: invokestatic  #58                 // Method org/picocontainer/paranamer/BytecodeReadingParanamer$Type.access$400:(Ljava/lang/String;)[Lorg/picocontainer/paranamer/BytecodeReadingParanamer$Type;
      26: astore        4
      28: iconst_0
      29: istore        5
      31: aload         4
      33: astore        6
      35: aload         6
      37: arraylength
      38: istore        7
      40: iconst_0
      41: istore        8
      43: iload         8
      45: iload         7
      47: if_icmpge     92
      50: aload         6
      52: iload         8
      54: aaload
      55: astore        9
      57: aload         9
      59: invokestatic  #62                 // Method org/picocontainer/paranamer/BytecodeReadingParanamer$Type.access$500:(Lorg/picocontainer/paranamer/BytecodeReadingParanamer$Type;)Ljava/lang/String;
      62: ldc           #64                 // String long
      64: invokevirtual #54                 // Method java/lang/String.equals:(Ljava/lang/Object;)Z
      67: ifne          83
      70: aload         9
      72: invokestatic  #62                 // Method org/picocontainer/paranamer/BytecodeReadingParanamer$Type.access$500:(Lorg/picocontainer/paranamer/BytecodeReadingParanamer$Type;)Ljava/lang/String;
      75: ldc           #66                 // String double
      77: invokevirtual #54                 // Method java/lang/String.equals:(Ljava/lang/Object;)Z
      80: ifeq          86
      83: iinc          5, 1
      86: iinc          8, 1
      89: goto          43
      92: aload         4
      94: arraylength
      95: istore        6
      97: iload         6
      99: aload_0
     100: getfield      #40                 // Field parameterTypes:[Ljava/lang/Class;
     103: arraylength
     104: if_icmpeq     109
     107: aconst_null
     108: areturn
     109: iconst_0
     110: istore        7
     112: iload         7
     114: aload         4
     116: arraylength
     117: if_icmpge     152
     120: aload_0
     121: aload         4
     123: iload         7
     125: invokespecial #70                 // Method correctTypeName:([Lorg/picocontainer/paranamer/BytecodeReadingParanamer$Type;I)Ljava/lang/String;
     128: aload_0
     129: getfield      #40                 // Field parameterTypes:[Ljava/lang/Class;
     132: iload         7
     134: aaload
     135: invokevirtual #76                 // Method java/lang/Class.getName:()Ljava/lang/String;
     138: invokevirtual #54                 // Method java/lang/String.equals:(Ljava/lang/Object;)Z
     141: ifne          146
     144: aconst_null
     145: areturn
     146: iinc          7, 1
     149: goto          112
     152: aload_0
     153: new           #7                  // class org/picocontainer/paranamer/BytecodeReadingParanamer$MethodCollector
     156: dup
     157: iload_1
     158: invokestatic  #82                 // Method java/lang/reflect/Modifier.isStatic:(I)Z
     161: ifeq          168
     164: iconst_0
     165: goto          169
     168: iconst_1
     169: aload         4
     171: arraylength
     172: iload         5
     174: iadd
     175: aconst_null
     176: invokespecial #85                 // Method org/picocontainer/paranamer/BytecodeReadingParanamer$MethodCollector."<init>":(IILorg/picocontainer/paranamer/BytecodeReadingParanamer$1;)V
     179: putfield      #44                 // Field collector:Lorg/picocontainer/paranamer/BytecodeReadingParanamer$MethodCollector;
     182: aload_0
     183: getfield      #44                 // Field collector:Lorg/picocontainer/paranamer/BytecodeReadingParanamer$MethodCollector;
     186: areturn

  private java.lang.String correctTypeName(org.picocontainer.paranamer.BytecodeReadingParanamer$Type[], int);
    Code:
       0: aload_1
       1: iload_2
       2: aaload
       3: invokestatic  #62                 // Method org/picocontainer/paranamer/BytecodeReadingParanamer$Type.access$500:(Lorg/picocontainer/paranamer/BytecodeReadingParanamer$Type;)Ljava/lang/String;
       6: astore_3
       7: ldc           #101                // String
       9: astore        4
      11: aload_3
      12: ldc           #103                // String []
      14: invokevirtual #107                // Method java/lang/String.endsWith:(Ljava/lang/String;)Z
      17: ifeq          57
      20: new           #109                // class java/lang/StringBuilder
      23: dup
      24: invokespecial #110                // Method java/lang/StringBuilder."<init>":()V
      27: aload         4
      29: invokevirtual #114                // Method java/lang/StringBuilder.append:(Ljava/lang/String;)Ljava/lang/StringBuilder;
      32: ldc           #116                // String [
      34: invokevirtual #114                // Method java/lang/StringBuilder.append:(Ljava/lang/String;)Ljava/lang/StringBuilder;
      37: invokevirtual #119                // Method java/lang/StringBuilder.toString:()Ljava/lang/String;
      40: astore        4
      42: aload_3
      43: iconst_0
      44: aload_3
      45: invokevirtual #123                // Method java/lang/String.length:()I
      48: iconst_2
      49: isub
      50: invokevirtual #127                // Method java/lang/String.substring:(II)Ljava/lang/String;
      53: astore_3
      54: goto          11
      57: aload         4
      59: ldc           #101                // String
      61: invokevirtual #54                 // Method java/lang/String.equals:(Ljava/lang/Object;)Z
      64: ifne          143
      67: invokestatic  #131                // Method org/picocontainer/paranamer/BytecodeReadingParanamer.access$700:()Ljava/util/Map;
      70: aload_3
      71: invokeinterface #136,  2          // InterfaceMethod java/util/Map.containsKey:(Ljava/lang/Object;)Z
      76: ifeq          113
      79: new           #109                // class java/lang/StringBuilder
      82: dup
      83: invokespecial #110                // Method java/lang/StringBuilder."<init>":()V
      86: aload         4
      88: invokevirtual #114                // Method java/lang/StringBuilder.append:(Ljava/lang/String;)Ljava/lang/StringBuilder;
      91: invokestatic  #131                // Method org/picocontainer/paranamer/BytecodeReadingParanamer.access$700:()Ljava/util/Map;
      94: aload_3
      95: invokeinterface #140,  2          // InterfaceMethod java/util/Map.get:(Ljava/lang/Object;)Ljava/lang/Object;
     100: checkcast     #50                 // class java/lang/String
     103: invokevirtual #114                // Method java/lang/StringBuilder.append:(Ljava/lang/String;)Ljava/lang/StringBuilder;
     106: invokevirtual #119                // Method java/lang/StringBuilder.toString:()Ljava/lang/String;
     109: astore_3
     110: goto          143
     113: new           #109                // class java/lang/StringBuilder
     116: dup
     117: invokespecial #110                // Method java/lang/StringBuilder."<init>":()V
     120: aload         4
     122: invokevirtual #114                // Method java/lang/StringBuilder.append:(Ljava/lang/String;)Ljava/lang/StringBuilder;
     125: ldc           #142                // String L
     127: invokevirtual #114                // Method java/lang/StringBuilder.append:(Ljava/lang/String;)Ljava/lang/StringBuilder;
     130: aload_3
     131: invokevirtual #114                // Method java/lang/StringBuilder.append:(Ljava/lang/String;)Ljava/lang/StringBuilder;
     134: ldc           #144                // String ;
     136: invokevirtual #114                // Method java/lang/StringBuilder.append:(Ljava/lang/String;)Ljava/lang/StringBuilder;
     139: invokevirtual #119                // Method java/lang/StringBuilder.toString:()Ljava/lang/String;
     142: astore_3
     143: aload_3
     144: areturn

  private java.lang.String[] getParameterNamesForMethod();
    Code:
       0: aload_0
       1: getfield      #44                 // Field collector:Lorg/picocontainer/paranamer/BytecodeReadingParanamer$MethodCollector;
       4: ifnonnull     11
       7: getstatic     #154                // Field org/picocontainer/paranamer/Paranamer.EMPTY_NAMES:[Ljava/lang/String;
      10: areturn
      11: aload_0
      12: getfield      #44                 // Field collector:Lorg/picocontainer/paranamer/BytecodeReadingParanamer$MethodCollector;
      15: invokestatic  #158                // Method org/picocontainer/paranamer/BytecodeReadingParanamer$MethodCollector.access$800:(Lorg/picocontainer/paranamer/BytecodeReadingParanamer$MethodCollector;)Z
      18: ifne          62
      21: aload_0
      22: getfield      #42                 // Field throwExceptionIfMissing:Z
      25: ifeq          58
      28: new           #160                // class org/picocontainer/paranamer/ParameterNamesNotFoundException
      31: dup
      32: new           #109                // class java/lang/StringBuilder
      35: dup
      36: invokespecial #110                // Method java/lang/StringBuilder."<init>":()V
      39: ldc           #162                // String Parameter names not found for
      41: invokevirtual #114                // Method java/lang/StringBuilder.append:(Ljava/lang/String;)Ljava/lang/StringBuilder;
      44: aload_0
      45: getfield      #38                 // Field methodName:Ljava/lang/String;
      48: invokevirtual #114                // Method java/lang/StringBuilder.append:(Ljava/lang/String;)Ljava/lang/StringBuilder;
      51: invokevirtual #119                // Method java/lang/StringBuilder.toString:()Ljava/lang/String;
      54: invokespecial #165                // Method org/picocontainer/paranamer/ParameterNamesNotFoundException."<init>":(Ljava/lang/String;)V
      57: athrow
      58: getstatic     #154                // Field org/picocontainer/paranamer/Paranamer.EMPTY_NAMES:[Ljava/lang/String;
      61: areturn
      62: aload_0
      63: getfield      #44                 // Field collector:Lorg/picocontainer/paranamer/BytecodeReadingParanamer$MethodCollector;
      66: invokestatic  #169                // Method org/picocontainer/paranamer/BytecodeReadingParanamer$MethodCollector.access$900:(Lorg/picocontainer/paranamer/BytecodeReadingParanamer$MethodCollector;)Ljava/lang/String;
      69: ldc           #20                 // String ,
      71: invokevirtual #173                // Method java/lang/String.split:(Ljava/lang/String;)[Ljava/lang/String;
      74: areturn

  org.picocontainer.paranamer.BytecodeReadingParanamer$TypeCollector(java.lang.String, java.lang.Class[], boolean, org.picocontainer.paranamer.BytecodeReadingParanamer$1);
    Code:
       0: aload_0
       1: aload_1
       2: aload_2
       3: iload_3
       4: invokespecial #176                // Method "<init>":(Ljava/lang/String;[Ljava/lang/Class;Z)V
       7: return

  static java.lang.String[] access$300(org.picocontainer.paranamer.BytecodeReadingParanamer$TypeCollector);
    Code:
       0: aload_0
       1: invokespecial #185                // Method getParameterNamesForMethod:()[Ljava/lang/String;
       4: areturn
}
