Compiled from "PartitionFn.java"
class software.amazon.awssdk.services.s3control.endpoints.internal.PartitionFn$PartitionData {
  private final java.util.List<software.amazon.awssdk.services.s3control.endpoints.internal.Partition> partitions;

  private final java.util.Map<java.lang.String, software.amazon.awssdk.services.s3control.endpoints.internal.Partition> regionMap;

  private software.amazon.awssdk.services.s3control.endpoints.internal.PartitionFn$PartitionData();
    Code:
       0: aload_0
       1: invokespecial #4                  // Method java/lang/Object."<init>":()V
       4: aload_0
       5: new           #5                  // class java/util/ArrayList
       8: dup
       9: invokespecial #6                  // Method java/util/ArrayList."<init>":()V
      12: putfield      #2                  // Field partitions:Ljava/util/List;
      15: aload_0
      16: new           #7                  // class java/util/HashMap
      19: dup
      20: invokespecial #8                  // Method java/util/HashMap."<init>":()V
      23: putfield      #3                  // Field regionMap:Ljava/util/Map;
      26: return

  static java.util.Map access$000(software.amazon.awssdk.services.s3control.endpoints.internal.PartitionFn$PartitionData);
    Code:
       0: aload_0
       1: getfield      #3                  // Field regionMap:Ljava/util/Map;
       4: areturn

  static java.util.List access$100(software.amazon.awssdk.services.s3control.endpoints.internal.PartitionFn$PartitionData);
    Code:
       0: aload_0
       1: getfield      #2                  // Field partitions:Ljava/util/List;
       4: areturn

  software.amazon.awssdk.services.s3control.endpoints.internal.PartitionFn$PartitionData(software.amazon.awssdk.services.s3control.endpoints.internal.PartitionFn$1);
    Code:
       0: aload_0
       1: invokespecial #1                  // Method "<init>":()V
       4: return
}
