Compiled from "RandomAdaptor.java"
public class org.apache.commons.math3.random.RandomAdaptor extends java.util.Random implements org.apache.commons.math3.random.RandomGenerator {
  private static final long serialVersionUID;

  private final org.apache.commons.math3.random.RandomGenerator randomGenerator;

  private org.apache.commons.math3.random.RandomAdaptor();
    Code:
       0: aload_0
       1: invokespecial #1                  // Method java/util/Random."<init>":()V
       4: aload_0
       5: aconst_null
       6: putfield      #2                  // Field randomGenerator:Lorg/apache/commons/math3/random/RandomGenerator;
       9: return

  public org.apache.commons.math3.random.RandomAdaptor(org.apache.commons.math3.random.RandomGenerator);
    Code:
       0: aload_0
       1: invokespecial #1                  // Method java/util/Random."<init>":()V
       4: aload_0
       5: aload_1
       6: putfield      #2                  // Field randomGenerator:Lorg/apache/commons/math3/random/RandomGenerator;
       9: return

  public static java.util.Random createAdaptor(org.apache.commons.math3.random.RandomGenerator);
    Code:
       0: new           #3                  // class org/apache/commons/math3/random/RandomAdaptor
       3: dup
       4: aload_0
       5: invokespecial #4                  // Method "<init>":(Lorg/apache/commons/math3/random/RandomGenerator;)V
       8: areturn

  public boolean nextBoolean();
    Code:
       0: aload_0
       1: getfield      #2                  // Field randomGenerator:Lorg/apache/commons/math3/random/RandomGenerator;
       4: invokeinterface #5,  1            // InterfaceMethod org/apache/commons/math3/random/RandomGenerator.nextBoolean:()Z
       9: ireturn

  public void nextBytes(byte[]);
    Code:
       0: aload_0
       1: getfield      #2                  // Field randomGenerator:Lorg/apache/commons/math3/random/RandomGenerator;
       4: aload_1
       5: invokeinterface #6,  2            // InterfaceMethod org/apache/commons/math3/random/RandomGenerator.nextBytes:([B)V
      10: return

  public double nextDouble();
    Code:
       0: aload_0
       1: getfield      #2                  // Field randomGenerator:Lorg/apache/commons/math3/random/RandomGenerator;
       4: invokeinterface #7,  1            // InterfaceMethod org/apache/commons/math3/random/RandomGenerator.nextDouble:()D
       9: dreturn

  public float nextFloat();
    Code:
       0: aload_0
       1: getfield      #2                  // Field randomGenerator:Lorg/apache/commons/math3/random/RandomGenerator;
       4: invokeinterface #8,  1            // InterfaceMethod org/apache/commons/math3/random/RandomGenerator.nextFloat:()F
       9: freturn

  public double nextGaussian();
    Code:
       0: aload_0
       1: getfield      #2                  // Field randomGenerator:Lorg/apache/commons/math3/random/RandomGenerator;
       4: invokeinterface #9,  1            // InterfaceMethod org/apache/commons/math3/random/RandomGenerator.nextGaussian:()D
       9: dreturn

  public int nextInt();
    Code:
       0: aload_0
       1: getfield      #2                  // Field randomGenerator:Lorg/apache/commons/math3/random/RandomGenerator;
       4: invokeinterface #10,  1           // InterfaceMethod org/apache/commons/math3/random/RandomGenerator.nextInt:()I
       9: ireturn

  public int nextInt(int);
    Code:
       0: aload_0
       1: getfield      #2                  // Field randomGenerator:Lorg/apache/commons/math3/random/RandomGenerator;
       4: iload_1
       5: invokeinterface #11,  2           // InterfaceMethod org/apache/commons/math3/random/RandomGenerator.nextInt:(I)I
      10: ireturn

  public long nextLong();
    Code:
       0: aload_0
       1: getfield      #2                  // Field randomGenerator:Lorg/apache/commons/math3/random/RandomGenerator;
       4: invokeinterface #12,  1           // InterfaceMethod org/apache/commons/math3/random/RandomGenerator.nextLong:()J
       9: lreturn

  public void setSeed(int);
    Code:
       0: aload_0
       1: getfield      #2                  // Field randomGenerator:Lorg/apache/commons/math3/random/RandomGenerator;
       4: ifnull        17
       7: aload_0
       8: getfield      #2                  // Field randomGenerator:Lorg/apache/commons/math3/random/RandomGenerator;
      11: iload_1
      12: invokeinterface #13,  2           // InterfaceMethod org/apache/commons/math3/random/RandomGenerator.setSeed:(I)V
      17: return

  public void setSeed(int[]);
    Code:
       0: aload_0
       1: getfield      #2                  // Field randomGenerator:Lorg/apache/commons/math3/random/RandomGenerator;
       4: ifnull        17
       7: aload_0
       8: getfield      #2                  // Field randomGenerator:Lorg/apache/commons/math3/random/RandomGenerator;
      11: aload_1
      12: invokeinterface #14,  2           // InterfaceMethod org/apache/commons/math3/random/RandomGenerator.setSeed:([I)V
      17: return

  public void setSeed(long);
    Code:
       0: aload_0
       1: getfield      #2                  // Field randomGenerator:Lorg/apache/commons/math3/random/RandomGenerator;
       4: ifnull        17
       7: aload_0
       8: getfield      #2                  // Field randomGenerator:Lorg/apache/commons/math3/random/RandomGenerator;
      11: lload_1
      12: invokeinterface #15,  3           // InterfaceMethod org/apache/commons/math3/random/RandomGenerator.setSeed:(J)V
      17: return
}
