Compiled from "SpringWebMvcThymeleafBindStatus.java"
class org.thymeleaf.spring5.context.webmvc.SpringWebMvcThymeleafBindStatus implements org.thymeleaf.spring5.context.IThymeleafBindStatus {
  private final org.springframework.web.servlet.support.BindStatus bindStatus;

  org.thymeleaf.spring5.context.webmvc.SpringWebMvcThymeleafBindStatus(org.springframework.web.servlet.support.BindStatus);
    Code:
       0: aload_0
       1: invokespecial #1                  // Method java/lang/Object."<init>":()V
       4: aload_1
       5: ldc           #2                  // String BindStatus cannot be null
       7: invokestatic  #3                  // Method org/thymeleaf/util/Validate.notNull:(Ljava/lang/Object;Ljava/lang/String;)V
      10: aload_0
      11: aload_1
      12: putfield      #4                  // Field bindStatus:Lorg/springframework/web/servlet/support/BindStatus;
      15: return

  public java.lang.String getPath();
    Code:
       0: aload_0
       1: getfield      #4                  // Field bindStatus:Lorg/springframework/web/servlet/support/BindStatus;
       4: invokevirtual #5                  // Method org/springframework/web/servlet/support/BindStatus.getPath:()Ljava/lang/String;
       7: areturn

  public java.lang.String getExpression();
    Code:
       0: aload_0
       1: getfield      #4                  // Field bindStatus:Lorg/springframework/web/servlet/support/BindStatus;
       4: invokevirtual #6                  // Method org/springframework/web/servlet/support/BindStatus.getExpression:()Ljava/lang/String;
       7: areturn

  public java.lang.Object getValue();
    Code:
       0: aload_0
       1: getfield      #4                  // Field bindStatus:Lorg/springframework/web/servlet/support/BindStatus;
       4: invokevirtual #7                  // Method org/springframework/web/servlet/support/BindStatus.getValue:()Ljava/lang/Object;
       7: areturn

  public java.lang.Class<?> getValueType();
    Code:
       0: aload_0
       1: getfield      #4                  // Field bindStatus:Lorg/springframework/web/servlet/support/BindStatus;
       4: invokevirtual #8                  // Method org/springframework/web/servlet/support/BindStatus.getValueType:()Ljava/lang/Class;
       7: areturn

  public java.lang.Object getActualValue();
    Code:
       0: aload_0
       1: getfield      #4                  // Field bindStatus:Lorg/springframework/web/servlet/support/BindStatus;
       4: invokevirtual #9                  // Method org/springframework/web/servlet/support/BindStatus.getActualValue:()Ljava/lang/Object;
       7: areturn

  public java.lang.String getDisplayValue();
    Code:
       0: aload_0
       1: getfield      #4                  // Field bindStatus:Lorg/springframework/web/servlet/support/BindStatus;
       4: invokevirtual #10                 // Method org/springframework/web/servlet/support/BindStatus.getDisplayValue:()Ljava/lang/String;
       7: areturn

  public boolean isError();
    Code:
       0: aload_0
       1: getfield      #4                  // Field bindStatus:Lorg/springframework/web/servlet/support/BindStatus;
       4: invokevirtual #11                 // Method org/springframework/web/servlet/support/BindStatus.isError:()Z
       7: ireturn

  public java.lang.String[] getErrorCodes();
    Code:
       0: aload_0
       1: getfield      #4                  // Field bindStatus:Lorg/springframework/web/servlet/support/BindStatus;
       4: invokevirtual #12                 // Method org/springframework/web/servlet/support/BindStatus.getErrorCodes:()[Ljava/lang/String;
       7: areturn

  public java.lang.String getErrorCode();
    Code:
       0: aload_0
       1: getfield      #4                  // Field bindStatus:Lorg/springframework/web/servlet/support/BindStatus;
       4: invokevirtual #13                 // Method org/springframework/web/servlet/support/BindStatus.getErrorCode:()Ljava/lang/String;
       7: areturn

  public java.lang.String[] getErrorMessages();
    Code:
       0: aload_0
       1: getfield      #4                  // Field bindStatus:Lorg/springframework/web/servlet/support/BindStatus;
       4: invokevirtual #14                 // Method org/springframework/web/servlet/support/BindStatus.getErrorMessages:()[Ljava/lang/String;
       7: areturn

  public java.lang.String getErrorMessage();
    Code:
       0: aload_0
       1: getfield      #4                  // Field bindStatus:Lorg/springframework/web/servlet/support/BindStatus;
       4: invokevirtual #15                 // Method org/springframework/web/servlet/support/BindStatus.getErrorMessage:()Ljava/lang/String;
       7: areturn

  public java.lang.String getErrorMessagesAsString(java.lang.String);
    Code:
       0: aload_0
       1: getfield      #4                  // Field bindStatus:Lorg/springframework/web/servlet/support/BindStatus;
       4: aload_1
       5: invokevirtual #16                 // Method org/springframework/web/servlet/support/BindStatus.getErrorMessagesAsString:(Ljava/lang/String;)Ljava/lang/String;
       8: areturn

  public org.springframework.validation.Errors getErrors();
    Code:
       0: aload_0
       1: getfield      #4                  // Field bindStatus:Lorg/springframework/web/servlet/support/BindStatus;
       4: invokevirtual #17                 // Method org/springframework/web/servlet/support/BindStatus.getErrors:()Lorg/springframework/validation/Errors;
       7: areturn

  public java.beans.PropertyEditor getEditor();
    Code:
       0: aload_0
       1: getfield      #4                  // Field bindStatus:Lorg/springframework/web/servlet/support/BindStatus;
       4: invokevirtual #18                 // Method org/springframework/web/servlet/support/BindStatus.getEditor:()Ljava/beans/PropertyEditor;
       7: areturn

  public java.beans.PropertyEditor findEditor(java.lang.Class<?>);
    Code:
       0: aload_0
       1: getfield      #4                  // Field bindStatus:Lorg/springframework/web/servlet/support/BindStatus;
       4: aload_1
       5: invokevirtual #19                 // Method org/springframework/web/servlet/support/BindStatus.findEditor:(Ljava/lang/Class;)Ljava/beans/PropertyEditor;
       8: areturn

  public java.lang.String toString();
    Code:
       0: aload_0
       1: getfield      #4                  // Field bindStatus:Lorg/springframework/web/servlet/support/BindStatus;
       4: invokevirtual #20                 // Method org/springframework/web/servlet/support/BindStatus.toString:()Ljava/lang/String;
       7: areturn
}
