Compiled from "CodecOutputList.java"
final class io.netty.handler.codec.CodecOutputList extends java.util.AbstractList<java.lang.Object> implements java.util.RandomAccess {
  private static final io.netty.handler.codec.CodecOutputList$CodecOutputListRecycler NOOP_RECYCLER;

  private static final io.netty.util.concurrent.FastThreadLocal<io.netty.handler.codec.CodecOutputList$CodecOutputLists> CODEC_OUTPUT_LISTS_POOL;

  private final io.netty.handler.codec.CodecOutputList$CodecOutputListRecycler recycler;

  private int size;

  private java.lang.Object[] array;

  private boolean insertSinceRecycled;

  static io.netty.handler.codec.CodecOutputList newInstance();
    Code:
       0: getstatic     #3                  // Field CODEC_OUTPUT_LISTS_POOL:Lio/netty/util/concurrent/FastThreadLocal;
       3: invokevirtual #4                  // Method io/netty/util/concurrent/FastThreadLocal.get:()Ljava/lang/Object;
       6: checkcast     #5                  // class io/netty/handler/codec/CodecOutputList$CodecOutputLists
       9: invokevirtual #6                  // Method io/netty/handler/codec/CodecOutputList$CodecOutputLists.getOrCreate:()Lio/netty/handler/codec/CodecOutputList;
      12: areturn

  private io.netty.handler.codec.CodecOutputList(io.netty.handler.codec.CodecOutputList$CodecOutputListRecycler, int);
    Code:
       0: aload_0
       1: invokespecial #7                  // Method java/util/AbstractList."<init>":()V
       4: aload_0
       5: aload_1
       6: putfield      #8                  // Field recycler:Lio/netty/handler/codec/CodecOutputList$CodecOutputListRecycler;
       9: aload_0
      10: iload_2
      11: anewarray     #9                  // class java/lang/Object
      14: putfield      #10                 // Field array:[Ljava/lang/Object;
      17: return

  public java.lang.Object get(int);
    Code:
       0: aload_0
       1: iload_1
       2: invokespecial #11                 // Method checkIndex:(I)V
       5: aload_0
       6: getfield      #10                 // Field array:[Ljava/lang/Object;
       9: iload_1
      10: aaload
      11: areturn

  public int size();
    Code:
       0: aload_0
       1: getfield      #12                 // Field size:I
       4: ireturn

  public boolean add(java.lang.Object);
    Code:
       0: aload_1
       1: ldc           #13                 // String element
       3: invokestatic  #14                 // Method io/netty/util/internal/ObjectUtil.checkNotNull:(Ljava/lang/Object;Ljava/lang/String;)Ljava/lang/Object;
       6: pop
       7: aload_0
       8: aload_0
       9: getfield      #12                 // Field size:I
      12: aload_1
      13: invokespecial #15                 // Method insert:(ILjava/lang/Object;)V
      16: goto          33
      19: astore_2
      20: aload_0
      21: invokespecial #17                 // Method expandArray:()V
      24: aload_0
      25: aload_0
      26: getfield      #12                 // Field size:I
      29: aload_1
      30: invokespecial #15                 // Method insert:(ILjava/lang/Object;)V
      33: aload_0
      34: dup
      35: getfield      #12                 // Field size:I
      38: iconst_1
      39: iadd
      40: putfield      #12                 // Field size:I
      43: iconst_1
      44: ireturn
    Exception table:
       from    to  target type
           7    16    19   Class java/lang/IndexOutOfBoundsException

  public java.lang.Object set(int, java.lang.Object);
    Code:
       0: aload_2
       1: ldc           #13                 // String element
       3: invokestatic  #14                 // Method io/netty/util/internal/ObjectUtil.checkNotNull:(Ljava/lang/Object;Ljava/lang/String;)Ljava/lang/Object;
       6: pop
       7: aload_0
       8: iload_1
       9: invokespecial #11                 // Method checkIndex:(I)V
      12: aload_0
      13: getfield      #10                 // Field array:[Ljava/lang/Object;
      16: iload_1
      17: aaload
      18: astore_3
      19: aload_0
      20: iload_1
      21: aload_2
      22: invokespecial #15                 // Method insert:(ILjava/lang/Object;)V
      25: aload_3
      26: areturn

  public void add(int, java.lang.Object);
    Code:
       0: aload_2
       1: ldc           #13                 // String element
       3: invokestatic  #14                 // Method io/netty/util/internal/ObjectUtil.checkNotNull:(Ljava/lang/Object;Ljava/lang/String;)Ljava/lang/Object;
       6: pop
       7: aload_0
       8: iload_1
       9: invokespecial #11                 // Method checkIndex:(I)V
      12: aload_0
      13: getfield      #12                 // Field size:I
      16: aload_0
      17: getfield      #10                 // Field array:[Ljava/lang/Object;
      20: arraylength
      21: if_icmpne     28
      24: aload_0
      25: invokespecial #17                 // Method expandArray:()V
      28: iload_1
      29: aload_0
      30: getfield      #12                 // Field size:I
      33: if_icmpeq     57
      36: aload_0
      37: getfield      #10                 // Field array:[Ljava/lang/Object;
      40: iload_1
      41: aload_0
      42: getfield      #10                 // Field array:[Ljava/lang/Object;
      45: iload_1
      46: iconst_1
      47: iadd
      48: aload_0
      49: getfield      #12                 // Field size:I
      52: iload_1
      53: isub
      54: invokestatic  #18                 // Method java/lang/System.arraycopy:(Ljava/lang/Object;ILjava/lang/Object;II)V
      57: aload_0
      58: iload_1
      59: aload_2
      60: invokespecial #15                 // Method insert:(ILjava/lang/Object;)V
      63: aload_0
      64: dup
      65: getfield      #12                 // Field size:I
      68: iconst_1
      69: iadd
      70: putfield      #12                 // Field size:I
      73: return

  public java.lang.Object remove(int);
    Code:
       0: aload_0
       1: iload_1
       2: invokespecial #11                 // Method checkIndex:(I)V
       5: aload_0
       6: getfield      #10                 // Field array:[Ljava/lang/Object;
       9: iload_1
      10: aaload
      11: astore_2
      12: aload_0
      13: getfield      #12                 // Field size:I
      16: iload_1
      17: isub
      18: iconst_1
      19: isub
      20: istore_3
      21: iload_3
      22: ifle          41
      25: aload_0
      26: getfield      #10                 // Field array:[Ljava/lang/Object;
      29: iload_1
      30: iconst_1
      31: iadd
      32: aload_0
      33: getfield      #10                 // Field array:[Ljava/lang/Object;
      36: iload_1
      37: iload_3
      38: invokestatic  #18                 // Method java/lang/System.arraycopy:(Ljava/lang/Object;ILjava/lang/Object;II)V
      41: aload_0
      42: getfield      #10                 // Field array:[Ljava/lang/Object;
      45: aload_0
      46: dup
      47: getfield      #12                 // Field size:I
      50: iconst_1
      51: isub
      52: dup_x1
      53: putfield      #12                 // Field size:I
      56: aconst_null
      57: aastore
      58: aload_2
      59: areturn

  public void clear();
    Code:
       0: aload_0
       1: iconst_0
       2: putfield      #12                 // Field size:I
       5: return

  boolean insertSinceRecycled();
    Code:
       0: aload_0
       1: getfield      #19                 // Field insertSinceRecycled:Z
       4: ireturn

  void recycle();
    Code:
       0: iconst_0
       1: istore_1
       2: iload_1
       3: aload_0
       4: getfield      #12                 // Field size:I
       7: if_icmpge     23
      10: aload_0
      11: getfield      #10                 // Field array:[Ljava/lang/Object;
      14: iload_1
      15: aconst_null
      16: aastore
      17: iinc          1, 1
      20: goto          2
      23: aload_0
      24: iconst_0
      25: putfield      #12                 // Field size:I
      28: aload_0
      29: iconst_0
      30: putfield      #19                 // Field insertSinceRecycled:Z
      33: aload_0
      34: getfield      #8                  // Field recycler:Lio/netty/handler/codec/CodecOutputList$CodecOutputListRecycler;
      37: aload_0
      38: invokeinterface #20,  2           // InterfaceMethod io/netty/handler/codec/CodecOutputList$CodecOutputListRecycler.recycle:(Lio/netty/handler/codec/CodecOutputList;)V
      43: return

  java.lang.Object getUnsafe(int);
    Code:
       0: aload_0
       1: getfield      #10                 // Field array:[Ljava/lang/Object;
       4: iload_1
       5: aaload
       6: areturn

  private void checkIndex(int);
    Code:
       0: iload_1
       1: aload_0
       2: getfield      #12                 // Field size:I
       5: if_icmplt     55
       8: new           #16                 // class java/lang/IndexOutOfBoundsException
      11: dup
      12: new           #21                 // class java/lang/StringBuilder
      15: dup
      16: invokespecial #22                 // Method java/lang/StringBuilder."<init>":()V
      19: ldc           #23                 // String expected: index < (
      21: invokevirtual #24                 // Method java/lang/StringBuilder.append:(Ljava/lang/String;)Ljava/lang/StringBuilder;
      24: aload_0
      25: getfield      #12                 // Field size:I
      28: invokevirtual #25                 // Method java/lang/StringBuilder.append:(I)Ljava/lang/StringBuilder;
      31: ldc           #26                 // String ),but actual is (
      33: invokevirtual #24                 // Method java/lang/StringBuilder.append:(Ljava/lang/String;)Ljava/lang/StringBuilder;
      36: aload_0
      37: getfield      #12                 // Field size:I
      40: invokevirtual #25                 // Method java/lang/StringBuilder.append:(I)Ljava/lang/StringBuilder;
      43: ldc           #27                 // String )
      45: invokevirtual #24                 // Method java/lang/StringBuilder.append:(Ljava/lang/String;)Ljava/lang/StringBuilder;
      48: invokevirtual #28                 // Method java/lang/StringBuilder.toString:()Ljava/lang/String;
      51: invokespecial #29                 // Method java/lang/IndexOutOfBoundsException."<init>":(Ljava/lang/String;)V
      54: athrow
      55: return

  private void insert(int, java.lang.Object);
    Code:
       0: aload_0
       1: getfield      #10                 // Field array:[Ljava/lang/Object;
       4: iload_1
       5: aload_2
       6: aastore
       7: aload_0
       8: iconst_1
       9: putfield      #19                 // Field insertSinceRecycled:Z
      12: return

  private void expandArray();
    Code:
       0: aload_0
       1: getfield      #10                 // Field array:[Ljava/lang/Object;
       4: arraylength
       5: iconst_1
       6: ishl
       7: istore_1
       8: iload_1
       9: ifge          20
      12: new           #30                 // class java/lang/OutOfMemoryError
      15: dup
      16: invokespecial #31                 // Method java/lang/OutOfMemoryError."<init>":()V
      19: athrow
      20: iload_1
      21: anewarray     #9                  // class java/lang/Object
      24: astore_2
      25: aload_0
      26: getfield      #10                 // Field array:[Ljava/lang/Object;
      29: iconst_0
      30: aload_2
      31: iconst_0
      32: aload_0
      33: getfield      #10                 // Field array:[Ljava/lang/Object;
      36: arraylength
      37: invokestatic  #18                 // Method java/lang/System.arraycopy:(Ljava/lang/Object;ILjava/lang/Object;II)V
      40: aload_0
      41: aload_2
      42: putfield      #10                 // Field array:[Ljava/lang/Object;
      45: return

  io.netty.handler.codec.CodecOutputList(io.netty.handler.codec.CodecOutputList$CodecOutputListRecycler, int, io.netty.handler.codec.CodecOutputList$1);
    Code:
       0: aload_0
       1: aload_1
       2: iload_2
       3: invokespecial #2                  // Method "<init>":(Lio/netty/handler/codec/CodecOutputList$CodecOutputListRecycler;I)V
       6: return

  static io.netty.handler.codec.CodecOutputList$CodecOutputListRecycler access$100();
    Code:
       0: getstatic     #1                  // Field NOOP_RECYCLER:Lio/netty/handler/codec/CodecOutputList$CodecOutputListRecycler;
       3: areturn

  static {};
    Code:
       0: new           #32                 // class io/netty/handler/codec/CodecOutputList$1
       3: dup
       4: invokespecial #33                 // Method io/netty/handler/codec/CodecOutputList$1."<init>":()V
       7: putstatic     #1                  // Field NOOP_RECYCLER:Lio/netty/handler/codec/CodecOutputList$CodecOutputListRecycler;
      10: new           #34                 // class io/netty/handler/codec/CodecOutputList$2
      13: dup
      14: invokespecial #35                 // Method io/netty/handler/codec/CodecOutputList$2."<init>":()V
      17: putstatic     #3                  // Field CODEC_OUTPUT_LISTS_POOL:Lio/netty/util/concurrent/FastThreadLocal;
      20: return
}
