Compiled from "SerializedLine.java"
public class technology.dice.dicewhere.lineprocessing.SerializedLine {
  private technology.dice.dicewhere.parsing.ParsedLine parsedLine;

  private final technology.dice.dicewhere.api.api.IP startIp;

  public technology.dice.dicewhere.lineprocessing.SerializedLine(technology.dice.dicewhere.api.api.IP, technology.dice.dicewhere.parsing.ParsedLine);
    Code:
       0: aload_0
       1: invokespecial #1                  // Method java/lang/Object."<init>":()V
       4: aload_0
       5: aload_1
       6: putfield      #2                  // Field startIp:Ltechnology/dice/dicewhere/api/api/IP;
       9: aload_0
      10: aload_2
      11: putfield      #3                  // Field parsedLine:Ltechnology/dice/dicewhere/parsing/ParsedLine;
      14: return

  public technology.dice.dicewhere.api.api.IP getStartIp();
    Code:
       0: aload_0
       1: getfield      #2                  // Field startIp:Ltechnology/dice/dicewhere/api/api/IP;
       4: areturn

  public technology.dice.dicewhere.parsing.ParsedLine getParsedLine();
    Code:
       0: aload_0
       1: getfield      #3                  // Field parsedLine:Ltechnology/dice/dicewhere/parsing/ParsedLine;
       4: areturn
}
