Compiled from "GlobberStrategy.java"
final class org.sonatype.guice.bean.reflect.GlobberStrategy$5 extends org.sonatype.guice.bean.reflect.GlobberStrategy {
  org.sonatype.guice.bean.reflect.GlobberStrategy$5(java.lang.String, int);
    Code:
       0: aload_0
       1: aload_1
       2: iload_2
       3: aconst_null
       4: invokespecial #1                  // Method org/sonatype/guice/bean/reflect/GlobberStrategy."<init>":(Ljava/lang/String;ILorg/sonatype/guice/bean/reflect/GlobberStrategy$1;)V
       7: return

  final java.lang.Object compile(java.lang.String);
    Code:
       0: new           #2                  // class java/lang/StringBuilder
       3: dup
       4: invokespecial #3                  // Method java/lang/StringBuilder."<init>":()V
       7: ldc           #4                  // String \\Q
       9: invokevirtual #5                  // Method java/lang/StringBuilder.append:(Ljava/lang/String;)Ljava/lang/StringBuilder;
      12: aload_1
      13: ldc           #6                  // String \\*+
      15: ldc           #7                  // String \\\\E.*\\\\Q
      17: invokevirtual #8                  // Method java/lang/String.replaceAll:(Ljava/lang/String;Ljava/lang/String;)Ljava/lang/String;
      20: invokevirtual #5                  // Method java/lang/StringBuilder.append:(Ljava/lang/String;)Ljava/lang/StringBuilder;
      23: ldc           #9                  // String \\E
      25: invokevirtual #5                  // Method java/lang/StringBuilder.append:(Ljava/lang/String;)Ljava/lang/StringBuilder;
      28: invokevirtual #10                 // Method java/lang/StringBuilder.toString:()Ljava/lang/String;
      31: invokestatic  #11                 // Method java/util/regex/Pattern.compile:(Ljava/lang/String;)Ljava/util/regex/Pattern;
      34: areturn

  final boolean matches(java.lang.Object, java.lang.String);
    Code:
       0: aload_1
       1: checkcast     #12                 // class java/util/regex/Pattern
       4: aload_2
       5: invokestatic  #13                 // Method basename:(Ljava/lang/String;)Ljava/lang/String;
       8: invokevirtual #14                 // Method java/util/regex/Pattern.matcher:(Ljava/lang/CharSequence;)Ljava/util/regex/Matcher;
      11: invokevirtual #15                 // Method java/util/regex/Matcher.matches:()Z
      14: ireturn
}
