Compiled from "DecoratorMetadataBean.java"
class org.jboss.weld.bean.builtin.DecoratorMetadataBean$SerializableProxy<T> extends org.jboss.weld.bean.ForwardingDecorator<T> implements java.io.Serializable {
  private static final long serialVersionUID;

  private org.jboss.weld.serialization.BeanHolder<T> holder;

  public static <T> org.jboss.weld.bean.builtin.DecoratorMetadataBean$SerializableProxy<T> of(java.lang.String, javax.enterprise.inject.spi.Bean<T>);
    Code:
       0: new           #1                  // class org/jboss/weld/bean/builtin/DecoratorMetadataBean$SerializableProxy
       3: dup
       4: aload_0
       5: aload_1
       6: invokespecial #2                  // Method "<init>":(Ljava/lang/String;Ljavax/enterprise/inject/spi/Bean;)V
       9: areturn

  protected org.jboss.weld.bean.builtin.DecoratorMetadataBean$SerializableProxy(java.lang.String, javax.enterprise.inject.spi.Bean<T>);
    Code:
       0: aload_0
       1: invokespecial #3                  // Method org/jboss/weld/bean/ForwardingDecorator."<init>":()V
       4: aload_0
       5: new           #4                  // class org/jboss/weld/serialization/BeanHolder
       8: dup
       9: aload_1
      10: aload_2
      11: invokespecial #5                  // Method org/jboss/weld/serialization/BeanHolder."<init>":(Ljava/lang/String;Ljavax/enterprise/inject/spi/Bean;)V
      14: putfield      #6                  // Field holder:Lorg/jboss/weld/serialization/BeanHolder;
      17: return

  public javax.enterprise.inject.spi.Decorator<T> delegate();
    Code:
       0: aload_0
       1: getfield      #6                  // Field holder:Lorg/jboss/weld/serialization/BeanHolder;
       4: invokevirtual #7                  // Method org/jboss/weld/serialization/BeanHolder.get:()Ljava/lang/Object;
       7: checkcast     #8                  // class javax/enterprise/inject/spi/Decorator
      10: areturn

  public javax.enterprise.inject.spi.Bean delegate();
    Code:
       0: aload_0
       1: invokevirtual #9                  // Method delegate:()Ljavax/enterprise/inject/spi/Decorator;
       4: areturn

  public javax.enterprise.context.spi.Contextual delegate();
    Code:
       0: aload_0
       1: invokevirtual #9                  // Method delegate:()Ljavax/enterprise/inject/spi/Decorator;
       4: areturn
}
