Compiled from "ManagerCodeGen.java"
public class info.archinnov.achilles.internals.codegen.ManagerCodeGen$ManagerAndDSLClasses {
  public final com.squareup.javapoet.TypeSpec managerClass;

  public final java.util.List<com.squareup.javapoet.TypeSpec> dslClasses;

  public info.archinnov.achilles.internals.codegen.ManagerCodeGen$ManagerAndDSLClasses(com.squareup.javapoet.TypeSpec, java.util.List<com.squareup.javapoet.TypeSpec>);
    Code:
       0: aload_0
       1: invokespecial #1                  // Method java/lang/Object."<init>":()V
       4: aload_0
       5: aload_1
       6: putfield      #2                  // Field managerClass:Lcom/squareup/javapoet/TypeSpec;
       9: aload_0
      10: aload_2
      11: putfield      #3                  // Field dslClasses:Ljava/util/List;
      14: return
}
