Compiled from "SOAPBindingUtil.java"
public final class org.apache.cxf.binding.soap.SOAPBindingUtil {
  private static java.util.Map<java.lang.String, java.lang.String> bindingMap;

  private org.apache.cxf.binding.soap.SOAPBindingUtil();
    Code:
       0: aload_0
       1: invokespecial #1                  // Method java/lang/Object."<init>":()V
       4: return

  public static java.lang.String getBindingAnnotation(java.lang.String);
    Code:
       0: getstatic     #2                  // Field bindingMap:Ljava/util/Map;
       3: aload_0
       4: invokevirtual #3                  // Method java/lang/String.toUpperCase:()Ljava/lang/String;
       7: invokeinterface #4,  2            // InterfaceMethod java/util/Map.get:(Ljava/lang/Object;)Ljava/lang/Object;
      12: checkcast     #5                  // class java/lang/String
      15: areturn

  public static <T> T getProxy(java.lang.Class<T>, java.lang.Object);
    Code:
       0: new           #6                  // class org/apache/cxf/common/util/ExtensionInvocationHandler
       3: dup
       4: aload_1
       5: invokespecial #7                  // Method org/apache/cxf/common/util/ExtensionInvocationHandler."<init>":(Ljava/lang/Object;)V
       8: astore_2
       9: aconst_null
      10: astore_3
      11: invokestatic  #8                  // Method java/lang/Thread.currentThread:()Ljava/lang/Thread;
      14: invokevirtual #9                  // Method java/lang/Thread.getContextClassLoader:()Ljava/lang/ClassLoader;
      17: iconst_1
      18: anewarray     #10                 // class java/lang/Class
      21: dup
      22: iconst_0
      23: aload_0
      24: aastore
      25: aload_2
      26: invokestatic  #11                 // Method java/lang/reflect/Proxy.newProxyInstance:(Ljava/lang/ClassLoader;[Ljava/lang/Class;Ljava/lang/reflect/InvocationHandler;)Ljava/lang/Object;
      29: astore_3
      30: goto          96
      33: astore        4
      35: invokestatic  #8                  // Method java/lang/Thread.currentThread:()Ljava/lang/Thread;
      38: invokevirtual #9                  // Method java/lang/Thread.getContextClassLoader:()Ljava/lang/ClassLoader;
      41: astore        5
      43: aload         5
      45: aload_0
      46: invokevirtual #13                 // Method java/lang/Class.getClassLoader:()Ljava/lang/ClassLoader;
      49: if_acmpeq     72
      52: aload_0
      53: invokevirtual #13                 // Method java/lang/Class.getClassLoader:()Ljava/lang/ClassLoader;
      56: iconst_1
      57: anewarray     #10                 // class java/lang/Class
      60: dup
      61: iconst_0
      62: aload_0
      63: aastore
      64: aload_2
      65: invokestatic  #11                 // Method java/lang/reflect/Proxy.newProxyInstance:(Ljava/lang/ClassLoader;[Ljava/lang/Class;Ljava/lang/reflect/InvocationHandler;)Ljava/lang/Object;
      68: astore_3
      69: goto          96
      72: aload         4
      74: instanceof    #14                 // class java/lang/RuntimeException
      77: ifeq          86
      80: aload         4
      82: checkcast     #14                 // class java/lang/RuntimeException
      85: athrow
      86: new           #14                 // class java/lang/RuntimeException
      89: dup
      90: aload         4
      92: invokespecial #15                 // Method java/lang/RuntimeException."<init>":(Ljava/lang/Throwable;)V
      95: athrow
      96: aload_0
      97: aload_3
      98: invokevirtual #16                 // Method java/lang/Class.cast:(Ljava/lang/Object;)Ljava/lang/Object;
     101: areturn
    Exception table:
       from    to  target type
          11    30    33   Class java/lang/Throwable

  public static boolean isSOAPBinding(javax.wsdl.Binding);
    Code:
       0: aload_0
       1: invokeinterface #17,  1           // InterfaceMethod javax/wsdl/Binding.getExtensibilityElements:()Ljava/util/List;
       6: invokeinterface #18,  1           // InterfaceMethod java/util/List.iterator:()Ljava/util/Iterator;
      11: astore_1
      12: aload_1
      13: invokeinterface #19,  1           // InterfaceMethod java/util/Iterator.hasNext:()Z
      18: ifeq          40
      21: aload_1
      22: invokeinterface #20,  1           // InterfaceMethod java/util/Iterator.next:()Ljava/lang/Object;
      27: astore_2
      28: aload_2
      29: invokestatic  #21                 // Method isSOAPBinding:(Ljava/lang/Object;)Z
      32: ifeq          37
      35: iconst_1
      36: ireturn
      37: goto          12
      40: iconst_0
      41: ireturn

  public static java.lang.String getBindingStyle(javax.wsdl.Binding);
    Code:
       0: aload_0
       1: invokeinterface #17,  1           // InterfaceMethod javax/wsdl/Binding.getExtensibilityElements:()Ljava/util/List;
       6: invokeinterface #18,  1           // InterfaceMethod java/util/List.iterator:()Ljava/util/Iterator;
      11: astore_1
      12: aload_1
      13: invokeinterface #19,  1           // InterfaceMethod java/util/Iterator.hasNext:()Z
      18: ifeq          48
      21: aload_1
      22: invokeinterface #20,  1           // InterfaceMethod java/util/Iterator.next:()Ljava/lang/Object;
      27: astore_2
      28: aload_2
      29: invokestatic  #21                 // Method isSOAPBinding:(Ljava/lang/Object;)Z
      32: ifeq          45
      35: aload_2
      36: invokestatic  #22                 // Method getSoapBinding:(Ljava/lang/Object;)Lorg/apache/cxf/binding/soap/wsdl/extensions/SoapBinding;
      39: invokeinterface #23,  1           // InterfaceMethod org/apache/cxf/binding/soap/wsdl/extensions/SoapBinding.getStyle:()Ljava/lang/String;
      44: areturn
      45: goto          12
      48: ldc           #24                 // String
      50: areturn

  public static org.apache.cxf.binding.soap.wsdl.extensions.SoapOperation getSoapOperation(java.util.List<javax.wsdl.extensions.ExtensibilityElement>);
    Code:
       0: aload_0
       1: ifnull        45
       4: aload_0
       5: invokeinterface #18,  1           // InterfaceMethod java/util/List.iterator:()Ljava/util/Iterator;
      10: astore_1
      11: aload_1
      12: invokeinterface #19,  1           // InterfaceMethod java/util/Iterator.hasNext:()Z
      17: ifeq          45
      20: aload_1
      21: invokeinterface #20,  1           // InterfaceMethod java/util/Iterator.next:()Ljava/lang/Object;
      26: checkcast     #25                 // class javax/wsdl/extensions/ExtensibilityElement
      29: astore_2
      30: aload_2
      31: invokestatic  #26                 // Method isSOAPOperation:(Ljava/lang/Object;)Z
      34: ifeq          42
      37: aload_2
      38: invokestatic  #27                 // Method getSoapOperation:(Ljava/lang/Object;)Lorg/apache/cxf/binding/soap/wsdl/extensions/SoapOperation;
      41: areturn
      42: goto          11
      45: aconst_null
      46: areturn

  public static org.apache.cxf.binding.soap.wsdl.extensions.SoapOperation getSoapOperation(java.lang.Object);
    Code:
       0: aload_0
       1: invokestatic  #26                 // Method isSOAPOperation:(Ljava/lang/Object;)Z
       4: ifeq          18
       7: ldc_w         #28                 // class org/apache/cxf/binding/soap/wsdl/extensions/SoapOperation
      10: aload_0
      11: invokestatic  #29                 // Method getProxy:(Ljava/lang/Class;Ljava/lang/Object;)Ljava/lang/Object;
      14: checkcast     #28                 // class org/apache/cxf/binding/soap/wsdl/extensions/SoapOperation
      17: areturn
      18: aconst_null
      19: areturn

  public static java.lang.String getSOAPOperationStyle(javax.wsdl.BindingOperation);
    Code:
       0: ldc           #24                 // String
       2: astore_1
       3: aload_0
       4: ifnull        58
       7: aload_0
       8: invokeinterface #30,  1           // InterfaceMethod javax/wsdl/BindingOperation.getExtensibilityElements:()Ljava/util/List;
      13: invokeinterface #18,  1           // InterfaceMethod java/util/List.iterator:()Ljava/util/Iterator;
      18: astore_2
      19: aload_2
      20: invokeinterface #19,  1           // InterfaceMethod java/util/Iterator.hasNext:()Z
      25: ifeq          58
      28: aload_2
      29: invokeinterface #20,  1           // InterfaceMethod java/util/Iterator.next:()Ljava/lang/Object;
      34: astore_3
      35: aload_3
      36: invokestatic  #26                 // Method isSOAPOperation:(Ljava/lang/Object;)Z
      39: ifeq          55
      42: aload_3
      43: invokestatic  #27                 // Method getSoapOperation:(Ljava/lang/Object;)Lorg/apache/cxf/binding/soap/wsdl/extensions/SoapOperation;
      46: invokeinterface #31,  1           // InterfaceMethod org/apache/cxf/binding/soap/wsdl/extensions/SoapOperation.getStyle:()Ljava/lang/String;
      51: astore_1
      52: goto          58
      55: goto          19
      58: aload_1
      59: areturn

  public static org.apache.cxf.binding.soap.wsdl.extensions.SoapBody getBindingInputSOAPBody(javax.wsdl.BindingOperation);
    Code:
       0: aload_0
       1: invokeinterface #32,  1           // InterfaceMethod javax/wsdl/BindingOperation.getBindingInput:()Ljavax/wsdl/BindingInput;
       6: astore_1
       7: aload_1
       8: ifnull        54
      11: aload_1
      12: invokeinterface #33,  1           // InterfaceMethod javax/wsdl/BindingInput.getExtensibilityElements:()Ljava/util/List;
      17: invokeinterface #18,  1           // InterfaceMethod java/util/List.iterator:()Ljava/util/Iterator;
      22: astore_2
      23: aload_2
      24: invokeinterface #19,  1           // InterfaceMethod java/util/Iterator.hasNext:()Z
      29: ifeq          54
      32: aload_2
      33: invokeinterface #20,  1           // InterfaceMethod java/util/Iterator.next:()Ljava/lang/Object;
      38: astore_3
      39: aload_3
      40: invokestatic  #34                 // Method isSOAPBody:(Ljava/lang/Object;)Z
      43: ifeq          51
      46: aload_3
      47: invokestatic  #35                 // Method getSoapBody:(Ljava/lang/Object;)Lorg/apache/cxf/binding/soap/wsdl/extensions/SoapBody;
      50: areturn
      51: goto          23
      54: aconst_null
      55: areturn

  public static org.apache.cxf.binding.soap.wsdl.extensions.SoapBody getBindingOutputSOAPBody(javax.wsdl.BindingOperation);
    Code:
       0: aload_0
       1: invokeinterface #36,  1           // InterfaceMethod javax/wsdl/BindingOperation.getBindingOutput:()Ljavax/wsdl/BindingOutput;
       6: astore_1
       7: aload_1
       8: ifnull        54
      11: aload_1
      12: invokeinterface #37,  1           // InterfaceMethod javax/wsdl/BindingOutput.getExtensibilityElements:()Ljava/util/List;
      17: invokeinterface #18,  1           // InterfaceMethod java/util/List.iterator:()Ljava/util/Iterator;
      22: astore_2
      23: aload_2
      24: invokeinterface #19,  1           // InterfaceMethod java/util/Iterator.hasNext:()Z
      29: ifeq          54
      32: aload_2
      33: invokeinterface #20,  1           // InterfaceMethod java/util/Iterator.next:()Ljava/lang/Object;
      38: astore_3
      39: aload_3
      40: invokestatic  #34                 // Method isSOAPBody:(Ljava/lang/Object;)Z
      43: ifeq          51
      46: aload_3
      47: invokestatic  #35                 // Method getSoapBody:(Ljava/lang/Object;)Lorg/apache/cxf/binding/soap/wsdl/extensions/SoapBody;
      50: areturn
      51: goto          23
      54: aconst_null
      55: areturn

  public static org.apache.cxf.binding.soap.wsdl.extensions.SoapBody getSoapBody(java.util.List<javax.wsdl.extensions.ExtensibilityElement>);
    Code:
       0: aload_0
       1: ifnull        45
       4: aload_0
       5: invokeinterface #18,  1           // InterfaceMethod java/util/List.iterator:()Ljava/util/Iterator;
      10: astore_1
      11: aload_1
      12: invokeinterface #19,  1           // InterfaceMethod java/util/Iterator.hasNext:()Z
      17: ifeq          45
      20: aload_1
      21: invokeinterface #20,  1           // InterfaceMethod java/util/Iterator.next:()Ljava/lang/Object;
      26: checkcast     #25                 // class javax/wsdl/extensions/ExtensibilityElement
      29: astore_2
      30: aload_2
      31: invokestatic  #34                 // Method isSOAPBody:(Ljava/lang/Object;)Z
      34: ifeq          42
      37: aload_2
      38: invokestatic  #35                 // Method getSoapBody:(Ljava/lang/Object;)Lorg/apache/cxf/binding/soap/wsdl/extensions/SoapBody;
      41: areturn
      42: goto          11
      45: aconst_null
      46: areturn

  public static org.apache.cxf.binding.soap.wsdl.extensions.SoapBody getSoapBody(java.lang.Object);
    Code:
       0: aload_0
       1: invokestatic  #34                 // Method isSOAPBody:(Ljava/lang/Object;)Z
       4: ifeq          18
       7: ldc_w         #38                 // class org/apache/cxf/binding/soap/wsdl/extensions/SoapBody
      10: aload_0
      11: invokestatic  #29                 // Method getProxy:(Ljava/lang/Class;Ljava/lang/Object;)Ljava/lang/Object;
      14: checkcast     #38                 // class org/apache/cxf/binding/soap/wsdl/extensions/SoapBody
      17: areturn
      18: aconst_null
      19: areturn

  public static boolean isSOAPBody(java.lang.Object);
    Code:
       0: aload_0
       1: instanceof    #39                 // class javax/wsdl/extensions/soap/SOAPBody
       4: ifne          14
       7: aload_0
       8: instanceof    #40                 // class javax/wsdl/extensions/soap12/SOAP12Body
      11: ifeq          18
      14: iconst_1
      15: goto          19
      18: iconst_0
      19: ireturn

  public static boolean isSOAPHeader(java.lang.Object);
    Code:
       0: aload_0
       1: instanceof    #41                 // class javax/wsdl/extensions/soap/SOAPHeader
       4: ifne          14
       7: aload_0
       8: instanceof    #42                 // class javax/wsdl/extensions/soap12/SOAP12Header
      11: ifeq          18
      14: iconst_1
      15: goto          19
      18: iconst_0
      19: ireturn

  public static java.util.List<org.apache.cxf.binding.soap.wsdl.extensions.SoapHeader> getSoapHeaders(java.util.List<javax.wsdl.extensions.ExtensibilityElement>);
    Code:
       0: new           #43                 // class java/util/ArrayList
       3: dup
       4: invokespecial #44                 // Method java/util/ArrayList."<init>":()V
       7: astore_1
       8: aload_0
       9: ifnull        59
      12: aload_0
      13: invokeinterface #18,  1           // InterfaceMethod java/util/List.iterator:()Ljava/util/Iterator;
      18: astore_2
      19: aload_2
      20: invokeinterface #19,  1           // InterfaceMethod java/util/Iterator.hasNext:()Z
      25: ifeq          59
      28: aload_2
      29: invokeinterface #20,  1           // InterfaceMethod java/util/Iterator.next:()Ljava/lang/Object;
      34: checkcast     #25                 // class javax/wsdl/extensions/ExtensibilityElement
      37: astore_3
      38: aload_3
      39: invokestatic  #45                 // Method isSOAPHeader:(Ljava/lang/Object;)Z
      42: ifeq          56
      45: aload_1
      46: aload_3
      47: invokestatic  #46                 // Method getSoapHeader:(Ljava/lang/Object;)Lorg/apache/cxf/binding/soap/wsdl/extensions/SoapHeader;
      50: invokeinterface #47,  2           // InterfaceMethod java/util/List.add:(Ljava/lang/Object;)Z
      55: pop
      56: goto          19
      59: aload_1
      60: areturn

  public static org.apache.cxf.binding.soap.wsdl.extensions.SoapHeader getSoapHeader(java.lang.Object);
    Code:
       0: aload_0
       1: invokestatic  #45                 // Method isSOAPHeader:(Ljava/lang/Object;)Z
       4: ifeq          18
       7: ldc_w         #48                 // class org/apache/cxf/binding/soap/wsdl/extensions/SoapHeader
      10: aload_0
      11: invokestatic  #29                 // Method getProxy:(Ljava/lang/Class;Ljava/lang/Object;)Ljava/lang/Object;
      14: checkcast     #48                 // class org/apache/cxf/binding/soap/wsdl/extensions/SoapHeader
      17: areturn
      18: aconst_null
      19: areturn

  public static org.apache.cxf.binding.soap.wsdl.extensions.SoapAddress getSoapAddress(java.lang.Object);
    Code:
       0: aload_0
       1: invokestatic  #49                 // Method isSOAPAddress:(Ljava/lang/Object;)Z
       4: ifeq          18
       7: ldc_w         #50                 // class org/apache/cxf/binding/soap/wsdl/extensions/SoapAddress
      10: aload_0
      11: invokestatic  #29                 // Method getProxy:(Ljava/lang/Class;Ljava/lang/Object;)Ljava/lang/Object;
      14: checkcast     #50                 // class org/apache/cxf/binding/soap/wsdl/extensions/SoapAddress
      17: areturn
      18: aconst_null
      19: areturn

  public static boolean isSOAPAddress(java.lang.Object);
    Code:
       0: aload_0
       1: instanceof    #51                 // class javax/wsdl/extensions/soap/SOAPAddress
       4: ifne          14
       7: aload_0
       8: instanceof    #52                 // class javax/wsdl/extensions/soap12/SOAP12Address
      11: ifeq          18
      14: iconst_1
      15: goto          19
      18: iconst_0
      19: ireturn

  public static org.apache.cxf.binding.soap.wsdl.extensions.SoapHeader getBindingInputSOAPHeader(javax.wsdl.BindingOperation);
    Code:
       0: aload_0
       1: invokeinterface #32,  1           // InterfaceMethod javax/wsdl/BindingOperation.getBindingInput:()Ljavax/wsdl/BindingInput;
       6: astore_1
       7: aload_1
       8: ifnull        60
      11: aload_1
      12: invokeinterface #33,  1           // InterfaceMethod javax/wsdl/BindingInput.getExtensibilityElements:()Ljava/util/List;
      17: invokeinterface #18,  1           // InterfaceMethod java/util/List.iterator:()Ljava/util/Iterator;
      22: astore_2
      23: aload_2
      24: invokeinterface #19,  1           // InterfaceMethod java/util/Iterator.hasNext:()Z
      29: ifeq          60
      32: aload_2
      33: invokeinterface #20,  1           // InterfaceMethod java/util/Iterator.next:()Ljava/lang/Object;
      38: astore_3
      39: aload_3
      40: invokestatic  #45                 // Method isSOAPHeader:(Ljava/lang/Object;)Z
      43: ifeq          57
      46: ldc_w         #48                 // class org/apache/cxf/binding/soap/wsdl/extensions/SoapHeader
      49: aload_3
      50: invokestatic  #29                 // Method getProxy:(Ljava/lang/Class;Ljava/lang/Object;)Ljava/lang/Object;
      53: checkcast     #48                 // class org/apache/cxf/binding/soap/wsdl/extensions/SoapHeader
      56: areturn
      57: goto          23
      60: aconst_null
      61: areturn

  public static java.util.List<org.apache.cxf.binding.soap.wsdl.extensions.SoapHeader> getBindingInputSOAPHeaders(javax.wsdl.BindingOperation);
    Code:
       0: new           #43                 // class java/util/ArrayList
       3: dup
       4: invokespecial #44                 // Method java/util/ArrayList."<init>":()V
       7: astore_1
       8: aload_0
       9: invokeinterface #32,  1           // InterfaceMethod javax/wsdl/BindingOperation.getBindingInput:()Ljavax/wsdl/BindingInput;
      14: astore_2
      15: aload_2
      16: ifnull        74
      19: aload_2
      20: invokeinterface #33,  1           // InterfaceMethod javax/wsdl/BindingInput.getExtensibilityElements:()Ljava/util/List;
      25: invokeinterface #18,  1           // InterfaceMethod java/util/List.iterator:()Ljava/util/Iterator;
      30: astore_3
      31: aload_3
      32: invokeinterface #19,  1           // InterfaceMethod java/util/Iterator.hasNext:()Z
      37: ifeq          74
      40: aload_3
      41: invokeinterface #20,  1           // InterfaceMethod java/util/Iterator.next:()Ljava/lang/Object;
      46: astore        4
      48: aload         4
      50: invokestatic  #45                 // Method isSOAPHeader:(Ljava/lang/Object;)Z
      53: ifeq          71
      56: aload_1
      57: ldc_w         #48                 // class org/apache/cxf/binding/soap/wsdl/extensions/SoapHeader
      60: aload         4
      62: invokestatic  #29                 // Method getProxy:(Ljava/lang/Class;Ljava/lang/Object;)Ljava/lang/Object;
      65: invokeinterface #47,  2           // InterfaceMethod java/util/List.add:(Ljava/lang/Object;)Z
      70: pop
      71: goto          31
      74: aload_1
      75: areturn

  public static org.apache.cxf.binding.soap.wsdl.extensions.SoapHeader getBindingOutputSOAPHeader(javax.wsdl.BindingOperation);
    Code:
       0: aload_0
       1: invokeinterface #36,  1           // InterfaceMethod javax/wsdl/BindingOperation.getBindingOutput:()Ljavax/wsdl/BindingOutput;
       6: astore_1
       7: aload_1
       8: ifnull        60
      11: aload_1
      12: invokeinterface #37,  1           // InterfaceMethod javax/wsdl/BindingOutput.getExtensibilityElements:()Ljava/util/List;
      17: invokeinterface #18,  1           // InterfaceMethod java/util/List.iterator:()Ljava/util/Iterator;
      22: astore_2
      23: aload_2
      24: invokeinterface #19,  1           // InterfaceMethod java/util/Iterator.hasNext:()Z
      29: ifeq          60
      32: aload_2
      33: invokeinterface #20,  1           // InterfaceMethod java/util/Iterator.next:()Ljava/lang/Object;
      38: astore_3
      39: aload_3
      40: invokestatic  #45                 // Method isSOAPHeader:(Ljava/lang/Object;)Z
      43: ifeq          57
      46: ldc_w         #48                 // class org/apache/cxf/binding/soap/wsdl/extensions/SoapHeader
      49: aload_3
      50: invokestatic  #29                 // Method getProxy:(Ljava/lang/Class;Ljava/lang/Object;)Ljava/lang/Object;
      53: checkcast     #48                 // class org/apache/cxf/binding/soap/wsdl/extensions/SoapHeader
      56: areturn
      57: goto          23
      60: aconst_null
      61: areturn

  public static java.util.List<org.apache.cxf.binding.soap.wsdl.extensions.SoapHeader> getBindingOutputSOAPHeaders(javax.wsdl.BindingOperation);
    Code:
       0: new           #43                 // class java/util/ArrayList
       3: dup
       4: invokespecial #44                 // Method java/util/ArrayList."<init>":()V
       7: astore_1
       8: aload_0
       9: invokeinterface #36,  1           // InterfaceMethod javax/wsdl/BindingOperation.getBindingOutput:()Ljavax/wsdl/BindingOutput;
      14: astore_2
      15: aload_2
      16: ifnull        74
      19: aload_2
      20: invokeinterface #37,  1           // InterfaceMethod javax/wsdl/BindingOutput.getExtensibilityElements:()Ljava/util/List;
      25: invokeinterface #18,  1           // InterfaceMethod java/util/List.iterator:()Ljava/util/Iterator;
      30: astore_3
      31: aload_3
      32: invokeinterface #19,  1           // InterfaceMethod java/util/Iterator.hasNext:()Z
      37: ifeq          74
      40: aload_3
      41: invokeinterface #20,  1           // InterfaceMethod java/util/Iterator.next:()Ljava/lang/Object;
      46: astore        4
      48: aload         4
      50: invokestatic  #45                 // Method isSOAPHeader:(Ljava/lang/Object;)Z
      53: ifeq          71
      56: aload_1
      57: ldc_w         #48                 // class org/apache/cxf/binding/soap/wsdl/extensions/SoapHeader
      60: aload         4
      62: invokestatic  #29                 // Method getProxy:(Ljava/lang/Class;Ljava/lang/Object;)Ljava/lang/Object;
      65: invokeinterface #47,  2           // InterfaceMethod java/util/List.add:(Ljava/lang/Object;)Z
      70: pop
      71: goto          31
      74: aload_1
      75: areturn

  public static org.apache.cxf.binding.soap.wsdl.extensions.SoapBinding getSoapBinding(java.util.List<javax.wsdl.extensions.ExtensibilityElement>);
    Code:
       0: aload_0
       1: invokeinterface #18,  1           // InterfaceMethod java/util/List.iterator:()Ljava/util/Iterator;
       6: astore_1
       7: aload_1
       8: invokeinterface #19,  1           // InterfaceMethod java/util/Iterator.hasNext:()Z
      13: ifeq          41
      16: aload_1
      17: invokeinterface #20,  1           // InterfaceMethod java/util/Iterator.next:()Ljava/lang/Object;
      22: checkcast     #25                 // class javax/wsdl/extensions/ExtensibilityElement
      25: astore_2
      26: aload_2
      27: invokestatic  #21                 // Method isSOAPBinding:(Ljava/lang/Object;)Z
      30: ifeq          38
      33: aload_2
      34: invokestatic  #22                 // Method getSoapBinding:(Ljava/lang/Object;)Lorg/apache/cxf/binding/soap/wsdl/extensions/SoapBinding;
      37: areturn
      38: goto          7
      41: aconst_null
      42: areturn

  public static org.apache.cxf.binding.soap.wsdl.extensions.SoapBinding getSoapBinding(java.lang.Object);
    Code:
       0: aload_0
       1: invokestatic  #21                 // Method isSOAPBinding:(Ljava/lang/Object;)Z
       4: ifeq          18
       7: ldc_w         #53                 // class org/apache/cxf/binding/soap/wsdl/extensions/SoapBinding
      10: aload_0
      11: invokestatic  #29                 // Method getProxy:(Ljava/lang/Class;Ljava/lang/Object;)Ljava/lang/Object;
      14: checkcast     #53                 // class org/apache/cxf/binding/soap/wsdl/extensions/SoapBinding
      17: areturn
      18: aconst_null
      19: areturn

  public static boolean isSOAPBinding(java.lang.Object);
    Code:
       0: aload_0
       1: instanceof    #54                 // class javax/wsdl/extensions/soap/SOAPBinding
       4: ifne          14
       7: aload_0
       8: instanceof    #55                 // class javax/wsdl/extensions/soap12/SOAP12Binding
      11: ifeq          18
      14: iconst_1
      15: goto          19
      18: iconst_0
      19: ireturn

  public static java.util.List<org.apache.cxf.binding.soap.wsdl.extensions.SoapFault> getBindingOperationSoapFaults(javax.wsdl.BindingOperation);
    Code:
       0: new           #43                 // class java/util/ArrayList
       3: dup
       4: invokespecial #44                 // Method java/util/ArrayList."<init>":()V
       7: astore_1
       8: aload_0
       9: invokeinterface #56,  1           // InterfaceMethod javax/wsdl/BindingOperation.getBindingFaults:()Ljava/util/Map;
      14: invokeinterface #57,  1           // InterfaceMethod java/util/Map.values:()Ljava/util/Collection;
      19: invokeinterface #58,  1           // InterfaceMethod java/util/Collection.iterator:()Ljava/util/Iterator;
      24: astore_2
      25: aload_2
      26: invokeinterface #19,  1           // InterfaceMethod java/util/Iterator.hasNext:()Z
      31: ifeq          117
      34: aload_2
      35: invokeinterface #20,  1           // InterfaceMethod java/util/Iterator.next:()Ljava/lang/Object;
      40: astore_3
      41: aload_3
      42: instanceof    #59                 // class javax/wsdl/BindingFault
      45: ifne          51
      48: goto          25
      51: aload_3
      52: checkcast     #59                 // class javax/wsdl/BindingFault
      55: astore        4
      57: aload         4
      59: invokeinterface #60,  1           // InterfaceMethod javax/wsdl/BindingFault.getExtensibilityElements:()Ljava/util/List;
      64: invokeinterface #18,  1           // InterfaceMethod java/util/List.iterator:()Ljava/util/Iterator;
      69: astore        5
      71: aload         5
      73: invokeinterface #19,  1           // InterfaceMethod java/util/Iterator.hasNext:()Z
      78: ifeq          114
      81: aload         5
      83: invokeinterface #20,  1           // InterfaceMethod java/util/Iterator.next:()Ljava/lang/Object;
      88: astore        6
      90: aload         6
      92: invokestatic  #61                 // Method getSoapFault:(Ljava/lang/Object;)Lorg/apache/cxf/binding/soap/wsdl/extensions/SoapFault;
      95: astore        7
      97: aload         7
      99: ifnull        111
     102: aload_1
     103: aload         7
     105: invokeinterface #47,  2           // InterfaceMethod java/util/List.add:(Ljava/lang/Object;)Z
     110: pop
     111: goto          71
     114: goto          25
     117: aload_1
     118: areturn

  public static org.apache.cxf.binding.soap.wsdl.extensions.SoapFault getSoapFault(java.lang.Object);
    Code:
       0: aload_0
       1: invokestatic  #62                 // Method isSOAPFault:(Ljava/lang/Object;)Z
       4: ifeq          18
       7: ldc_w         #63                 // class org/apache/cxf/binding/soap/wsdl/extensions/SoapFault
      10: aload_0
      11: invokestatic  #29                 // Method getProxy:(Ljava/lang/Class;Ljava/lang/Object;)Ljava/lang/Object;
      14: checkcast     #63                 // class org/apache/cxf/binding/soap/wsdl/extensions/SoapFault
      17: areturn
      18: aconst_null
      19: areturn

  public static boolean isMixedStyle(javax.wsdl.Binding);
    Code:
       0: ldc           #24                 // String
       2: astore_1
       3: ldc           #24                 // String
       5: astore_2
       6: ldc           #24                 // String
       8: astore_3
       9: aload_0
      10: invokeinterface #17,  1           // InterfaceMethod javax/wsdl/Binding.getExtensibilityElements:()Ljava/util/List;
      15: invokeinterface #18,  1           // InterfaceMethod java/util/List.iterator:()Ljava/util/Iterator;
      20: astore        4
      22: aload         4
      24: invokeinterface #19,  1           // InterfaceMethod java/util/Iterator.hasNext:()Z
      29: ifeq          74
      32: aload         4
      34: invokeinterface #20,  1           // InterfaceMethod java/util/Iterator.next:()Ljava/lang/Object;
      39: astore        5
      41: aload         5
      43: invokestatic  #21                 // Method isSOAPBinding:(Ljava/lang/Object;)Z
      46: ifeq          71
      49: aload         5
      51: invokestatic  #22                 // Method getSoapBinding:(Ljava/lang/Object;)Lorg/apache/cxf/binding/soap/wsdl/extensions/SoapBinding;
      54: astore        6
      56: aload         6
      58: invokeinterface #23,  1           // InterfaceMethod org/apache/cxf/binding/soap/wsdl/extensions/SoapBinding.getStyle:()Ljava/lang/String;
      63: astore_1
      64: aload_1
      65: ifnonnull     71
      68: ldc           #24                 // String
      70: astore_1
      71: goto          22
      74: aload_0
      75: invokeinterface #64,  1           // InterfaceMethod javax/wsdl/Binding.getBindingOperations:()Ljava/util/List;
      80: invokeinterface #18,  1           // InterfaceMethod java/util/List.iterator:()Ljava/util/Iterator;
      85: astore        4
      87: aload         4
      89: invokeinterface #19,  1           // InterfaceMethod java/util/Iterator.hasNext:()Z
      94: ifeq          301
      97: aload         4
      99: invokeinterface #20,  1           // InterfaceMethod java/util/Iterator.next:()Ljava/lang/Object;
     104: astore        5
     106: aload         5
     108: checkcast     #65                 // class javax/wsdl/BindingOperation
     111: astore        6
     113: aload         6
     115: invokeinterface #30,  1           // InterfaceMethod javax/wsdl/BindingOperation.getExtensibilityElements:()Ljava/util/List;
     120: invokeinterface #18,  1           // InterfaceMethod java/util/List.iterator:()Ljava/util/Iterator;
     125: astore        7
     127: aload         7
     129: invokeinterface #19,  1           // InterfaceMethod java/util/Iterator.hasNext:()Z
     134: ifeq          298
     137: aload         7
     139: invokeinterface #20,  1           // InterfaceMethod java/util/Iterator.next:()Ljava/lang/Object;
     144: astore        8
     146: aload         8
     148: invokestatic  #26                 // Method isSOAPOperation:(Ljava/lang/Object;)Z
     151: ifeq          295
     154: aload         8
     156: invokestatic  #27                 // Method getSoapOperation:(Ljava/lang/Object;)Lorg/apache/cxf/binding/soap/wsdl/extensions/SoapOperation;
     159: astore        9
     161: aload         9
     163: invokeinterface #31,  1           // InterfaceMethod org/apache/cxf/binding/soap/wsdl/extensions/SoapOperation.getStyle:()Ljava/lang/String;
     168: astore_3
     169: aload_3
     170: ifnonnull     176
     173: ldc           #24                 // String
     175: astore_3
     176: ldc           #24                 // String
     178: aload_1
     179: invokevirtual #66                 // Method java/lang/String.equals:(Ljava/lang/Object;)Z
     182: ifeq          194
     185: ldc           #24                 // String
     187: aload_2
     188: invokevirtual #66                 // Method java/lang/String.equals:(Ljava/lang/Object;)Z
     191: ifne          211
     194: ldc           #24                 // String
     196: aload_1
     197: invokevirtual #66                 // Method java/lang/String.equals:(Ljava/lang/Object;)Z
     200: ifeq          216
     203: aload_2
     204: aload_3
     205: invokevirtual #67                 // Method java/lang/String.equalsIgnoreCase:(Ljava/lang/String;)Z
     208: ifeq          216
     211: aload_3
     212: astore_2
     213: goto          295
     216: ldc           #24                 // String
     218: aload_1
     219: invokevirtual #66                 // Method java/lang/String.equals:(Ljava/lang/Object;)Z
     222: ifne          242
     225: ldc           #24                 // String
     227: aload_2
     228: invokevirtual #66                 // Method java/lang/String.equals:(Ljava/lang/Object;)Z
     231: ifeq          242
     234: aload_1
     235: aload_3
     236: invokevirtual #67                 // Method java/lang/String.equalsIgnoreCase:(Ljava/lang/String;)Z
     239: ifne          258
     242: aload_1
     243: aload_2
     244: invokevirtual #67                 // Method java/lang/String.equalsIgnoreCase:(Ljava/lang/String;)Z
     247: ifeq          263
     250: aload_1
     251: aload_3
     252: invokevirtual #67                 // Method java/lang/String.equalsIgnoreCase:(Ljava/lang/String;)Z
     255: ifeq          263
     258: aload_3
     259: astore_2
     260: goto          295
     263: ldc           #24                 // String
     265: aload_1
     266: invokevirtual #66                 // Method java/lang/String.equals:(Ljava/lang/Object;)Z
     269: ifne          293
     272: ldc           #24                 // String
     274: aload_3
     275: invokevirtual #66                 // Method java/lang/String.equals:(Ljava/lang/Object;)Z
     278: ifeq          293
     281: ldc           #24                 // String
     283: aload_2
     284: invokevirtual #66                 // Method java/lang/String.equals:(Ljava/lang/Object;)Z
     287: ifeq          293
     290: goto          127
     293: iconst_1
     294: ireturn
     295: goto          127
     298: goto          87
     301: iconst_0
     302: ireturn

  public static java.lang.String getCanonicalBindingStyle(javax.wsdl.Binding);
    Code:
       0: aload_0
       1: invokestatic  #68                 // Method getBindingStyle:(Ljavax/wsdl/Binding;)Ljava/lang/String;
       4: astore_1
       5: aload_1
       6: invokestatic  #69                 // Method org/apache/cxf/common/util/StringUtils.isEmpty:(Ljava/lang/String;)Z
       9: ifne          14
      12: aload_1
      13: areturn
      14: aload_0
      15: invokeinterface #64,  1           // InterfaceMethod javax/wsdl/Binding.getBindingOperations:()Ljava/util/List;
      20: invokeinterface #18,  1           // InterfaceMethod java/util/List.iterator:()Ljava/util/Iterator;
      25: astore_2
      26: aload_2
      27: invokeinterface #19,  1           // InterfaceMethod java/util/Iterator.hasNext:()Z
      32: ifeq          69
      35: aload_2
      36: invokeinterface #20,  1           // InterfaceMethod java/util/Iterator.next:()Ljava/lang/Object;
      41: astore_3
      42: aload_3
      43: checkcast     #65                 // class javax/wsdl/BindingOperation
      46: astore        4
      48: aload         4
      50: invokestatic  #70                 // Method getSOAPOperationStyle:(Ljavax/wsdl/BindingOperation;)Ljava/lang/String;
      53: astore        5
      55: aload         5
      57: invokestatic  #69                 // Method org/apache/cxf/common/util/StringUtils.isEmpty:(Ljava/lang/String;)Z
      60: ifne          66
      63: aload         5
      65: areturn
      66: goto          26
      69: ldc           #24                 // String
      71: areturn

  public static boolean isSOAPOperation(java.lang.Object);
    Code:
       0: aload_0
       1: instanceof    #71                 // class javax/wsdl/extensions/soap/SOAPOperation
       4: ifne          14
       7: aload_0
       8: instanceof    #72                 // class javax/wsdl/extensions/soap12/SOAP12Operation
      11: ifeq          18
      14: iconst_1
      15: goto          19
      18: iconst_0
      19: ireturn

  public static boolean isSOAPFault(java.lang.Object);
    Code:
       0: aload_0
       1: instanceof    #73                 // class javax/wsdl/extensions/soap/SOAPFault
       4: ifne          14
       7: aload_0
       8: instanceof    #74                 // class javax/wsdl/extensions/soap12/SOAP12Fault
      11: ifeq          18
      14: iconst_1
      15: goto          19
      18: iconst_0
      19: ireturn

  public static org.apache.cxf.binding.soap.wsdl.extensions.SoapAddress createSoapAddress(javax.wsdl.extensions.ExtensionRegistry, boolean) throws javax.wsdl.WSDLException;
    Code:
       0: aconst_null
       1: astore_2
       2: iload_1
       3: ifeq          20
       6: aload_0
       7: ldc_w         #75                 // class javax/wsdl/Port
      10: getstatic     #76                 // Field org/apache/cxf/wsdl/WSDLConstants.QNAME_SOAP12_BINDING_ADDRESS:Ljavax/xml/namespace/QName;
      13: invokevirtual #77                 // Method javax/wsdl/extensions/ExtensionRegistry.createExtension:(Ljava/lang/Class;Ljavax/xml/namespace/QName;)Ljavax/wsdl/extensions/ExtensibilityElement;
      16: astore_2
      17: goto          31
      20: aload_0
      21: ldc_w         #75                 // class javax/wsdl/Port
      24: getstatic     #78                 // Field org/apache/cxf/wsdl/WSDLConstants.QNAME_SOAP_BINDING_ADDRESS:Ljavax/xml/namespace/QName;
      27: invokevirtual #77                 // Method javax/wsdl/extensions/ExtensionRegistry.createExtension:(Ljava/lang/Class;Ljavax/xml/namespace/QName;)Ljavax/wsdl/extensions/ExtensibilityElement;
      30: astore_2
      31: aload_2
      32: invokestatic  #79                 // Method getSoapAddress:(Ljava/lang/Object;)Lorg/apache/cxf/binding/soap/wsdl/extensions/SoapAddress;
      35: areturn

  public static org.apache.cxf.binding.soap.wsdl.extensions.SoapBody createSoapBody(javax.wsdl.extensions.ExtensionRegistry, java.lang.Class<?>, boolean) throws javax.wsdl.WSDLException;
    Code:
       0: aconst_null
       1: astore_3
       2: iload_2
       3: ifeq          26
       6: aload_0
       7: aload_1
       8: new           #80                 // class javax/xml/namespace/QName
      11: dup
      12: ldc           #81                 // String http://schemas.xmlsoap.org/wsdl/soap12/
      14: ldc           #82                 // String body
      16: invokespecial #83                 // Method javax/xml/namespace/QName."<init>":(Ljava/lang/String;Ljava/lang/String;)V
      19: invokevirtual #77                 // Method javax/wsdl/extensions/ExtensionRegistry.createExtension:(Ljava/lang/Class;Ljavax/xml/namespace/QName;)Ljavax/wsdl/extensions/ExtensibilityElement;
      22: astore_3
      23: goto          43
      26: aload_0
      27: aload_1
      28: new           #80                 // class javax/xml/namespace/QName
      31: dup
      32: ldc           #84                 // String http://schemas.xmlsoap.org/wsdl/soap/
      34: ldc           #82                 // String body
      36: invokespecial #83                 // Method javax/xml/namespace/QName."<init>":(Ljava/lang/String;Ljava/lang/String;)V
      39: invokevirtual #77                 // Method javax/wsdl/extensions/ExtensionRegistry.createExtension:(Ljava/lang/Class;Ljavax/xml/namespace/QName;)Ljavax/wsdl/extensions/ExtensibilityElement;
      42: astore_3
      43: aload_3
      44: invokestatic  #35                 // Method getSoapBody:(Ljava/lang/Object;)Lorg/apache/cxf/binding/soap/wsdl/extensions/SoapBody;
      47: areturn

  public static org.apache.cxf.binding.soap.wsdl.extensions.SoapBinding createSoapBinding(javax.wsdl.extensions.ExtensionRegistry, boolean) throws javax.wsdl.WSDLException;
    Code:
       0: aconst_null
       1: astore_2
       2: iload_1
       3: ifeq          39
       6: aload_0
       7: ldc_w         #85                 // class javax/wsdl/Binding
      10: new           #80                 // class javax/xml/namespace/QName
      13: dup
      14: ldc           #81                 // String http://schemas.xmlsoap.org/wsdl/soap12/
      16: ldc           #86                 // String binding
      18: invokespecial #83                 // Method javax/xml/namespace/QName."<init>":(Ljava/lang/String;Ljava/lang/String;)V
      21: invokevirtual #77                 // Method javax/wsdl/extensions/ExtensionRegistry.createExtension:(Ljava/lang/Class;Ljavax/xml/namespace/QName;)Ljavax/wsdl/extensions/ExtensibilityElement;
      24: astore_2
      25: aload_2
      26: checkcast     #55                 // class javax/wsdl/extensions/soap12/SOAP12Binding
      29: ldc           #87                 // String http://schemas.xmlsoap.org/soap/http
      31: invokeinterface #88,  2           // InterfaceMethod javax/wsdl/extensions/soap12/SOAP12Binding.setTransportURI:(Ljava/lang/String;)V
      36: goto          69
      39: aload_0
      40: ldc_w         #85                 // class javax/wsdl/Binding
      43: new           #80                 // class javax/xml/namespace/QName
      46: dup
      47: ldc           #84                 // String http://schemas.xmlsoap.org/wsdl/soap/
      49: ldc           #86                 // String binding
      51: invokespecial #83                 // Method javax/xml/namespace/QName."<init>":(Ljava/lang/String;Ljava/lang/String;)V
      54: invokevirtual #77                 // Method javax/wsdl/extensions/ExtensionRegistry.createExtension:(Ljava/lang/Class;Ljavax/xml/namespace/QName;)Ljavax/wsdl/extensions/ExtensibilityElement;
      57: astore_2
      58: aload_2
      59: checkcast     #54                 // class javax/wsdl/extensions/soap/SOAPBinding
      62: ldc           #87                 // String http://schemas.xmlsoap.org/soap/http
      64: invokeinterface #89,  2           // InterfaceMethod javax/wsdl/extensions/soap/SOAPBinding.setTransportURI:(Ljava/lang/String;)V
      69: aload_2
      70: invokestatic  #22                 // Method getSoapBinding:(Ljava/lang/Object;)Lorg/apache/cxf/binding/soap/wsdl/extensions/SoapBinding;
      73: areturn

  public static org.apache.cxf.binding.soap.wsdl.extensions.SoapOperation createSoapOperation(javax.wsdl.extensions.ExtensionRegistry, boolean) throws javax.wsdl.WSDLException;
    Code:
       0: aconst_null
       1: astore_2
       2: iload_1
       3: ifeq          28
       6: aload_0
       7: ldc_w         #65                 // class javax/wsdl/BindingOperation
      10: new           #80                 // class javax/xml/namespace/QName
      13: dup
      14: ldc           #81                 // String http://schemas.xmlsoap.org/wsdl/soap12/
      16: ldc           #90                 // String operation
      18: invokespecial #83                 // Method javax/xml/namespace/QName."<init>":(Ljava/lang/String;Ljava/lang/String;)V
      21: invokevirtual #77                 // Method javax/wsdl/extensions/ExtensionRegistry.createExtension:(Ljava/lang/Class;Ljavax/xml/namespace/QName;)Ljavax/wsdl/extensions/ExtensibilityElement;
      24: astore_2
      25: goto          47
      28: aload_0
      29: ldc_w         #65                 // class javax/wsdl/BindingOperation
      32: new           #80                 // class javax/xml/namespace/QName
      35: dup
      36: ldc           #84                 // String http://schemas.xmlsoap.org/wsdl/soap/
      38: ldc           #90                 // String operation
      40: invokespecial #83                 // Method javax/xml/namespace/QName."<init>":(Ljava/lang/String;Ljava/lang/String;)V
      43: invokevirtual #77                 // Method javax/wsdl/extensions/ExtensionRegistry.createExtension:(Ljava/lang/Class;Ljavax/xml/namespace/QName;)Ljavax/wsdl/extensions/ExtensibilityElement;
      46: astore_2
      47: aload_2
      48: invokestatic  #27                 // Method getSoapOperation:(Ljava/lang/Object;)Lorg/apache/cxf/binding/soap/wsdl/extensions/SoapOperation;
      51: areturn

  public static org.apache.cxf.binding.soap.wsdl.extensions.SoapFault createSoapFault(javax.wsdl.extensions.ExtensionRegistry, boolean) throws javax.wsdl.WSDLException;
    Code:
       0: aconst_null
       1: astore_2
       2: iload_1
       3: ifeq          28
       6: aload_0
       7: ldc_w         #59                 // class javax/wsdl/BindingFault
      10: new           #80                 // class javax/xml/namespace/QName
      13: dup
      14: ldc           #81                 // String http://schemas.xmlsoap.org/wsdl/soap12/
      16: ldc           #91                 // String fault
      18: invokespecial #83                 // Method javax/xml/namespace/QName."<init>":(Ljava/lang/String;Ljava/lang/String;)V
      21: invokevirtual #77                 // Method javax/wsdl/extensions/ExtensionRegistry.createExtension:(Ljava/lang/Class;Ljavax/xml/namespace/QName;)Ljavax/wsdl/extensions/ExtensibilityElement;
      24: astore_2
      25: goto          47
      28: aload_0
      29: ldc_w         #59                 // class javax/wsdl/BindingFault
      32: new           #80                 // class javax/xml/namespace/QName
      35: dup
      36: ldc           #84                 // String http://schemas.xmlsoap.org/wsdl/soap/
      38: ldc           #91                 // String fault
      40: invokespecial #83                 // Method javax/xml/namespace/QName."<init>":(Ljava/lang/String;Ljava/lang/String;)V
      43: invokevirtual #77                 // Method javax/wsdl/extensions/ExtensionRegistry.createExtension:(Ljava/lang/Class;Ljavax/xml/namespace/QName;)Ljavax/wsdl/extensions/ExtensibilityElement;
      46: astore_2
      47: aload_2
      48: invokestatic  #61                 // Method getSoapFault:(Ljava/lang/Object;)Lorg/apache/cxf/binding/soap/wsdl/extensions/SoapFault;
      51: areturn

  public static org.apache.cxf.binding.soap.wsdl.extensions.SoapHeader createSoapHeader(javax.wsdl.extensions.ExtensionRegistry, java.lang.Class<?>, boolean) throws javax.wsdl.WSDLException;
    Code:
       0: aconst_null
       1: astore_3
       2: iload_2
       3: ifeq          26
       6: aload_0
       7: aload_1
       8: new           #80                 // class javax/xml/namespace/QName
      11: dup
      12: ldc           #81                 // String http://schemas.xmlsoap.org/wsdl/soap12/
      14: ldc           #92                 // String header
      16: invokespecial #83                 // Method javax/xml/namespace/QName."<init>":(Ljava/lang/String;Ljava/lang/String;)V
      19: invokevirtual #77                 // Method javax/wsdl/extensions/ExtensionRegistry.createExtension:(Ljava/lang/Class;Ljavax/xml/namespace/QName;)Ljavax/wsdl/extensions/ExtensibilityElement;
      22: astore_3
      23: goto          43
      26: aload_0
      27: aload_1
      28: new           #80                 // class javax/xml/namespace/QName
      31: dup
      32: ldc           #84                 // String http://schemas.xmlsoap.org/wsdl/soap/
      34: ldc           #92                 // String header
      36: invokespecial #83                 // Method javax/xml/namespace/QName."<init>":(Ljava/lang/String;Ljava/lang/String;)V
      39: invokevirtual #77                 // Method javax/wsdl/extensions/ExtensionRegistry.createExtension:(Ljava/lang/Class;Ljavax/xml/namespace/QName;)Ljavax/wsdl/extensions/ExtensibilityElement;
      42: astore_3
      43: aload_3
      44: invokestatic  #46                 // Method getSoapHeader:(Ljava/lang/Object;)Lorg/apache/cxf/binding/soap/wsdl/extensions/SoapHeader;
      47: areturn

  public static void addSOAPNamespace(javax.wsdl.Definition, boolean);
    Code:
       0: aload_0
       1: invokeinterface #93,  1           // InterfaceMethod javax/wsdl/Definition.getNamespaces:()Ljava/util/Map;
       6: astore_2
       7: iload_1
       8: ifeq          40
      11: aload_2
      12: invokeinterface #57,  1           // InterfaceMethod java/util/Map.values:()Ljava/util/Collection;
      17: ldc           #81                 // String http://schemas.xmlsoap.org/wsdl/soap12/
      19: invokeinterface #94,  2           // InterfaceMethod java/util/Collection.contains:(Ljava/lang/Object;)Z
      24: ifne          40
      27: aload_0
      28: ldc           #95                 // String soap12
      30: ldc           #81                 // String http://schemas.xmlsoap.org/wsdl/soap12/
      32: invokeinterface #96,  3           // InterfaceMethod javax/wsdl/Definition.addNamespace:(Ljava/lang/String;Ljava/lang/String;)V
      37: goto          66
      40: aload_2
      41: invokeinterface #57,  1           // InterfaceMethod java/util/Map.values:()Ljava/util/Collection;
      46: ldc           #84                 // String http://schemas.xmlsoap.org/wsdl/soap/
      48: invokeinterface #94,  2           // InterfaceMethod java/util/Collection.contains:(Ljava/lang/Object;)Z
      53: ifne          66
      56: aload_0
      57: ldc           #97                 // String soap
      59: ldc           #84                 // String http://schemas.xmlsoap.org/wsdl/soap/
      61: invokeinterface #96,  3           // InterfaceMethod javax/wsdl/Definition.addNamespace:(Ljava/lang/String;Ljava/lang/String;)V
      66: return

  public static javax.jws.soap.SOAPBinding$Style getSoapStyle(java.lang.String);
    Code:
       0: ldc           #24                 // String
       2: aload_0
       3: invokevirtual #66                 // Method java/lang/String.equals:(Ljava/lang/Object;)Z
       6: ifeq          11
       9: aconst_null
      10: areturn
      11: ldc           #98                 // String RPC
      13: aload_0
      14: invokevirtual #67                 // Method java/lang/String.equalsIgnoreCase:(Ljava/lang/String;)Z
      17: ifeq          24
      20: getstatic     #99                 // Field javax/jws/soap/SOAPBinding$Style.RPC:Ljavax/jws/soap/SOAPBinding$Style;
      23: areturn
      24: getstatic     #100                // Field javax/jws/soap/SOAPBinding$Style.DOCUMENT:Ljavax/jws/soap/SOAPBinding$Style;
      27: areturn

  public static javax.jws.soap.SOAPBinding$Use getSoapUse(java.lang.String);
    Code:
       0: ldc           #24                 // String
       2: aload_0
       3: invokevirtual #66                 // Method java/lang/String.equals:(Ljava/lang/Object;)Z
       6: ifeq          11
       9: aconst_null
      10: areturn
      11: ldc           #101                // String ENCODED
      13: aload_0
      14: invokevirtual #67                 // Method java/lang/String.equalsIgnoreCase:(Ljava/lang/String;)Z
      17: ifeq          24
      20: getstatic     #102                // Field javax/jws/soap/SOAPBinding$Use.ENCODED:Ljavax/jws/soap/SOAPBinding$Use;
      23: areturn
      24: getstatic     #103                // Field javax/jws/soap/SOAPBinding$Use.LITERAL:Ljavax/jws/soap/SOAPBinding$Use;
      27: areturn

  static {};
    Code:
       0: new           #104                // class java/util/HashMap
       3: dup
       4: invokespecial #105                // Method java/util/HashMap."<init>":()V
       7: putstatic     #2                  // Field bindingMap:Ljava/util/Map;
      10: getstatic     #2                  // Field bindingMap:Ljava/util/Map;
      13: ldc           #98                 // String RPC
      15: ldc           #106                // String SOAPBinding.Style.RPC
      17: invokeinterface #107,  3          // InterfaceMethod java/util/Map.put:(Ljava/lang/Object;Ljava/lang/Object;)Ljava/lang/Object;
      22: pop
      23: getstatic     #2                  // Field bindingMap:Ljava/util/Map;
      26: ldc           #108                // String DOCUMENT
      28: ldc           #109                // String SOAPBinding.Style.DOCUMENT
      30: invokeinterface #107,  3          // InterfaceMethod java/util/Map.put:(Ljava/lang/Object;Ljava/lang/Object;)Ljava/lang/Object;
      35: pop
      36: getstatic     #2                  // Field bindingMap:Ljava/util/Map;
      39: ldc           #110                // String LITERAL
      41: ldc           #111                // String SOAPBinding.Use.LITERAL
      43: invokeinterface #107,  3          // InterfaceMethod java/util/Map.put:(Ljava/lang/Object;Ljava/lang/Object;)Ljava/lang/Object;
      48: pop
      49: getstatic     #2                  // Field bindingMap:Ljava/util/Map;
      52: ldc           #101                // String ENCODED
      54: ldc           #112                // String SOAPBinding.Use.ENCODED
      56: invokeinterface #107,  3          // InterfaceMethod java/util/Map.put:(Ljava/lang/Object;Ljava/lang/Object;)Ljava/lang/Object;
      61: pop
      62: getstatic     #2                  // Field bindingMap:Ljava/util/Map;
      65: ldc           #113                // String BARE
      67: ldc           #114                // String SOAPBinding.ParameterStyle.BARE
      69: invokeinterface #107,  3          // InterfaceMethod java/util/Map.put:(Ljava/lang/Object;Ljava/lang/Object;)Ljava/lang/Object;
      74: pop
      75: getstatic     #2                  // Field bindingMap:Ljava/util/Map;
      78: ldc           #115                // String WRAPPED
      80: ldc           #116                // String SOAPBinding.ParameterStyle.WRAPPED
      82: invokeinterface #107,  3          // InterfaceMethod java/util/Map.put:(Ljava/lang/Object;Ljava/lang/Object;)Ljava/lang/Object;
      87: pop
      88: return
}
