Compiled from "StagingRuleFailureDTO.java"
public class com.sonatype.nexus.staging.api.dto.StagingRuleFailureDTO {
  private java.lang.String ruleName;

  private java.util.List<java.lang.String> messages;

  public com.sonatype.nexus.staging.api.dto.StagingRuleFailureDTO();
    Code:
       0: aload_0
       1: invokespecial #1                  // Method java/lang/Object."<init>":()V
       4: aload_0
       5: new           #2                  // class java/util/ArrayList
       8: dup
       9: invokespecial #3                  // Method java/util/ArrayList."<init>":()V
      12: putfield      #4                  // Field messages:Ljava/util/List;
      15: return

  public java.util.List<java.lang.String> getMessages();
    Code:
       0: aload_0
       1: getfield      #4                  // Field messages:Ljava/util/List;
       4: areturn

  public void setMessages(java.util.List<java.lang.String>);
    Code:
       0: aload_0
       1: aload_1
       2: putfield      #4                  // Field messages:Ljava/util/List;
       5: return

  public void addMessage(java.lang.String);
    Code:
       0: aload_0
       1: getfield      #4                  // Field messages:Ljava/util/List;
       4: aload_1
       5: invokeinterface #5,  2            // InterfaceMethod java/util/List.add:(Ljava/lang/Object;)Z
      10: pop
      11: return

  public java.lang.String getRuleName();
    Code:
       0: aload_0
       1: getfield      #6                  // Field ruleName:Ljava/lang/String;
       4: areturn

  public void setRuleName(java.lang.String);
    Code:
       0: aload_0
       1: aload_1
       2: putfield      #6                  // Field ruleName:Ljava/lang/String;
       5: return

  public java.lang.String toString();
    Code:
       0: new           #7                  // class java/lang/StringBuilder
       3: dup
       4: invokespecial #8                  // Method java/lang/StringBuilder."<init>":()V
       7: aload_0
       8: getfield      #6                  // Field ruleName:Ljava/lang/String;
      11: invokevirtual #9                  // Method java/lang/StringBuilder.append:(Ljava/lang/String;)Ljava/lang/StringBuilder;
      14: ldc           #10                 // String :
      16: invokevirtual #9                  // Method java/lang/StringBuilder.append:(Ljava/lang/String;)Ljava/lang/StringBuilder;
      19: aload_0
      20: getfield      #4                  // Field messages:Ljava/util/List;
      23: invokevirtual #11                 // Method java/lang/StringBuilder.append:(Ljava/lang/Object;)Ljava/lang/StringBuilder;
      26: invokevirtual #12                 // Method java/lang/StringBuilder.toString:()Ljava/lang/String;
      29: areturn
}
