Compiled from "FileWatcherCertificateProviderProvider.java"
final class io.grpc.xds.internal.certprovider.FileWatcherCertificateProviderProvider implements io.grpc.xds.internal.certprovider.CertificateProviderProvider {
  private static final java.lang.String CERT_FILE_KEY;

  private static final java.lang.String KEY_FILE_KEY;

  private static final java.lang.String ROOT_FILE_KEY;

  private static final java.lang.String REFRESH_INTERVAL_KEY;

  static final long REFRESH_INTERVAL_DEFAULT;

  static final java.lang.String FILE_WATCHER_PROVIDER_NAME;

  final io.grpc.xds.internal.certprovider.FileWatcherCertificateProvider$Factory fileWatcherCertificateProviderFactory;

  private final io.grpc.xds.internal.certprovider.FileWatcherCertificateProviderProvider$ScheduledExecutorServiceFactory scheduledExecutorServiceFactory;

  private final io.grpc.internal.TimeProvider timeProvider;

  io.grpc.xds.internal.certprovider.FileWatcherCertificateProviderProvider();
    Code:
       0: aload_0
       1: invokestatic  #56                 // Method io/grpc/xds/internal/certprovider/FileWatcherCertificateProvider$Factory.getInstance:()Lio/grpc/xds/internal/certprovider/FileWatcherCertificateProvider$Factory;
       4: invokestatic  #60                 // Method io/grpc/xds/internal/certprovider/FileWatcherCertificateProviderProvider$ScheduledExecutorServiceFactory.access$000:()Lio/grpc/xds/internal/certprovider/FileWatcherCertificateProviderProvider$ScheduledExecutorServiceFactory;
       7: getstatic     #65                 // Field io/grpc/internal/TimeProvider.SYSTEM_TIME_PROVIDER:Lio/grpc/internal/TimeProvider;
      10: invokespecial #68                 // Method "<init>":(Lio/grpc/xds/internal/certprovider/FileWatcherCertificateProvider$Factory;Lio/grpc/xds/internal/certprovider/FileWatcherCertificateProviderProvider$ScheduledExecutorServiceFactory;Lio/grpc/internal/TimeProvider;)V
      13: return

  io.grpc.xds.internal.certprovider.FileWatcherCertificateProviderProvider(io.grpc.xds.internal.certprovider.FileWatcherCertificateProvider$Factory, io.grpc.xds.internal.certprovider.FileWatcherCertificateProviderProvider$ScheduledExecutorServiceFactory, io.grpc.internal.TimeProvider);
    Code:
       0: aload_0
       1: invokespecial #72                 // Method java/lang/Object."<init>":()V
       4: aload_0
       5: aload_1
       6: putfield      #74                 // Field fileWatcherCertificateProviderFactory:Lio/grpc/xds/internal/certprovider/FileWatcherCertificateProvider$Factory;
       9: aload_0
      10: aload_2
      11: putfield      #76                 // Field scheduledExecutorServiceFactory:Lio/grpc/xds/internal/certprovider/FileWatcherCertificateProviderProvider$ScheduledExecutorServiceFactory;
      14: aload_0
      15: aload_3
      16: putfield      #78                 // Field timeProvider:Lio/grpc/internal/TimeProvider;
      19: return

  public java.lang.String getName();
    Code:
       0: ldc           #44                 // String file_watcher
       2: areturn

  public io.grpc.xds.internal.certprovider.CertificateProvider createCertificateProvider(java.lang.Object, io.grpc.xds.internal.certprovider.CertificateProvider$DistributorWatcher, boolean);
    Code:
       0: aload_1
       1: invokestatic  #86                 // Method validateAndTranslateConfig:(Ljava/lang/Object;)Lio/grpc/xds/internal/certprovider/FileWatcherCertificateProviderProvider$Config;
       4: astore        4
       6: aload_0
       7: getfield      #74                 // Field fileWatcherCertificateProviderFactory:Lio/grpc/xds/internal/certprovider/FileWatcherCertificateProvider$Factory;
      10: aload_2
      11: iload_3
      12: aload         4
      14: getfield      #89                 // Field io/grpc/xds/internal/certprovider/FileWatcherCertificateProviderProvider$Config.certFile:Ljava/lang/String;
      17: aload         4
      19: getfield      #92                 // Field io/grpc/xds/internal/certprovider/FileWatcherCertificateProviderProvider$Config.keyFile:Ljava/lang/String;
      22: aload         4
      24: getfield      #95                 // Field io/grpc/xds/internal/certprovider/FileWatcherCertificateProviderProvider$Config.rootFile:Ljava/lang/String;
      27: aload         4
      29: getfield      #99                 // Field io/grpc/xds/internal/certprovider/FileWatcherCertificateProviderProvider$Config.refrehInterval:Ljava/lang/Long;
      32: invokevirtual #105                // Method java/lang/Long.longValue:()J
      35: aload_0
      36: getfield      #76                 // Field scheduledExecutorServiceFactory:Lio/grpc/xds/internal/certprovider/FileWatcherCertificateProviderProvider$ScheduledExecutorServiceFactory;
      39: invokevirtual #109                // Method io/grpc/xds/internal/certprovider/FileWatcherCertificateProviderProvider$ScheduledExecutorServiceFactory.create:()Ljava/util/concurrent/ScheduledExecutorService;
      42: aload_0
      43: getfield      #78                 // Field timeProvider:Lio/grpc/internal/TimeProvider;
      46: invokevirtual #112                // Method io/grpc/xds/internal/certprovider/FileWatcherCertificateProvider$Factory.create:(Lio/grpc/xds/internal/certprovider/CertificateProvider$DistributorWatcher;ZLjava/lang/String;Ljava/lang/String;Ljava/lang/String;JLjava/util/concurrent/ScheduledExecutorService;Lio/grpc/internal/TimeProvider;)Lio/grpc/xds/internal/certprovider/FileWatcherCertificateProvider;
      49: areturn

  private static java.lang.String checkForNullAndGet(java.util.Map<java.lang.String, ?>, java.lang.String);
    Code:
       0: aload_0
       1: aload_1
       2: invokestatic  #128                // Method io/grpc/internal/JsonUtil.getString:(Ljava/util/Map;Ljava/lang/String;)Ljava/lang/String;
       5: new           #130                // class java/lang/StringBuilder
       8: dup
       9: invokespecial #131                // Method java/lang/StringBuilder."<init>":()V
      12: ldc           #133                // String \'
      14: invokevirtual #137                // Method java/lang/StringBuilder.append:(Ljava/lang/String;)Ljava/lang/StringBuilder;
      17: aload_1
      18: invokevirtual #137                // Method java/lang/StringBuilder.append:(Ljava/lang/String;)Ljava/lang/StringBuilder;
      21: ldc           #139                // String \' is required in the config
      23: invokevirtual #137                // Method java/lang/StringBuilder.append:(Ljava/lang/String;)Ljava/lang/StringBuilder;
      26: invokevirtual #142                // Method java/lang/StringBuilder.toString:()Ljava/lang/String;
      29: invokestatic  #148                // Method com/google/common/base/Preconditions.checkNotNull:(Ljava/lang/Object;Ljava/lang/Object;)Ljava/lang/Object;
      32: checkcast     #150                // class java/lang/String
      35: areturn

  private static io.grpc.xds.internal.certprovider.FileWatcherCertificateProviderProvider$Config validateAndTranslateConfig(java.lang.Object);
    Code:
       0: aload_0
       1: instanceof    #158                // class java/util/Map
       4: ldc           #160                // String Only Map supported for config
       6: invokestatic  #164                // Method com/google/common/base/Preconditions.checkArgument:(ZLjava/lang/Object;)V
       9: aload_0
      10: checkcast     #158                // class java/util/Map
      13: astore_1
      14: new           #9                  // class io/grpc/xds/internal/certprovider/FileWatcherCertificateProviderProvider$Config
      17: dup
      18: invokespecial #165                // Method io/grpc/xds/internal/certprovider/FileWatcherCertificateProviderProvider$Config."<init>":()V
      21: astore_2
      22: aload_2
      23: aload_1
      24: ldc           #27                 // String certificate_file
      26: invokestatic  #167                // Method checkForNullAndGet:(Ljava/util/Map;Ljava/lang/String;)Ljava/lang/String;
      29: putfield      #89                 // Field io/grpc/xds/internal/certprovider/FileWatcherCertificateProviderProvider$Config.certFile:Ljava/lang/String;
      32: aload_2
      33: aload_1
      34: ldc           #30                 // String private_key_file
      36: invokestatic  #167                // Method checkForNullAndGet:(Ljava/util/Map;Ljava/lang/String;)Ljava/lang/String;
      39: putfield      #92                 // Field io/grpc/xds/internal/certprovider/FileWatcherCertificateProviderProvider$Config.keyFile:Ljava/lang/String;
      42: aload_2
      43: aload_1
      44: ldc           #33                 // String ca_certificate_file
      46: invokestatic  #167                // Method checkForNullAndGet:(Ljava/util/Map;Ljava/lang/String;)Ljava/lang/String;
      49: putfield      #95                 // Field io/grpc/xds/internal/certprovider/FileWatcherCertificateProviderProvider$Config.rootFile:Ljava/lang/String;
      52: aload_1
      53: ldc           #36                 // String refresh_interval
      55: invokestatic  #128                // Method io/grpc/internal/JsonUtil.getString:(Ljava/util/Map;Ljava/lang/String;)Ljava/lang/String;
      58: astore_3
      59: aload_3
      60: ifnull        118
      63: aload_3
      64: invokestatic  #173                // Method com/google/protobuf/util/Durations.parse:(Ljava/lang/String;)Lcom/google/protobuf/Duration;
      67: astore        4
      69: aload_2
      70: aload         4
      72: invokevirtual #178                // Method com/google/protobuf/Duration.getSeconds:()J
      75: invokestatic  #182                // Method java/lang/Long.valueOf:(J)Ljava/lang/Long;
      78: putfield      #99                 // Field io/grpc/xds/internal/certprovider/FileWatcherCertificateProviderProvider$Config.refrehInterval:Ljava/lang/Long;
      81: aload_2
      82: getfield      #99                 // Field io/grpc/xds/internal/certprovider/FileWatcherCertificateProviderProvider$Config.refrehInterval:Ljava/lang/Long;
      85: invokevirtual #105                // Method java/lang/Long.longValue:()J
      88: lconst_0
      89: lcmp
      90: ifle          97
      93: iconst_1
      94: goto          98
      97: iconst_0
      98: ldc           #184                // String refreshInterval needs to be greater than 0
     100: invokestatic  #164                // Method com/google/common/base/Preconditions.checkArgument:(ZLjava/lang/Object;)V
     103: goto          118
     106: astore        4
     108: new           #186                // class java/lang/IllegalArgumentException
     111: dup
     112: aload         4
     114: invokespecial #189                // Method java/lang/IllegalArgumentException."<init>":(Ljava/lang/Throwable;)V
     117: athrow
     118: aload_2
     119: getfield      #99                 // Field io/grpc/xds/internal/certprovider/FileWatcherCertificateProviderProvider$Config.refrehInterval:Ljava/lang/Long;
     122: ifnonnull     135
     125: aload_2
     126: ldc2_w        #39                 // long 600l
     129: invokestatic  #182                // Method java/lang/Long.valueOf:(J)Ljava/lang/Long;
     132: putfield      #99                 // Field io/grpc/xds/internal/certprovider/FileWatcherCertificateProviderProvider$Config.refrehInterval:Ljava/lang/Long;
     135: aload_2
     136: areturn
    Exception table:
       from    to  target type
          63   103   106   Class java/text/ParseException
}
