public class org.bouncycastle.asn1.x509.IssuingDistributionPoint extends org.bouncycastle.asn1.ASN1Object {
  private org.bouncycastle.asn1.x509.DistributionPointName distributionPoint;

  private boolean onlyContainsUserCerts;

  private boolean onlyContainsCACerts;

  private org.bouncycastle.asn1.x509.ReasonFlags onlySomeReasons;

  private boolean indirectCRL;

  private boolean onlyContainsAttributeCerts;

  private org.bouncycastle.asn1.ASN1Sequence seq;

  public static org.bouncycastle.asn1.x509.IssuingDistributionPoint getInstance(org.bouncycastle.asn1.ASN1TaggedObject, boolean);
    Code:
       0: aload_0
       1: iload_1
       2: invokestatic  #158                // Method org/bouncycastle/asn1/ASN1Sequence.getInstance:(Lorg/bouncycastle/asn1/ASN1TaggedObject;Z)Lorg/bouncycastle/asn1/ASN1Sequence;
       5: invokestatic  #167                // Method getInstance:(Ljava/lang/Object;)Lorg/bouncycastle/asn1/x509/IssuingDistributionPoint;
       8: areturn

  public static org.bouncycastle.asn1.x509.IssuingDistributionPoint getInstance(java.lang.Object);
    Code:
       0: aload_0
       1: instanceof    #74                 // class org/bouncycastle/asn1/x509/IssuingDistributionPoint
       4: ifeq          12
       7: aload_0
       8: checkcast     #74                 // class org/bouncycastle/asn1/x509/IssuingDistributionPoint
      11: areturn
      12: aload_0
      13: ifnull        28
      16: new           #74                 // class org/bouncycastle/asn1/x509/IssuingDistributionPoint
      19: dup
      20: aload_0
      21: invokestatic  #157                // Method org/bouncycastle/asn1/ASN1Sequence.getInstance:(Ljava/lang/Object;)Lorg/bouncycastle/asn1/ASN1Sequence;
      24: invokespecial #166                // Method "<init>":(Lorg/bouncycastle/asn1/ASN1Sequence;)V
      27: areturn
      28: aconst_null
      29: areturn

  public org.bouncycastle.asn1.x509.IssuingDistributionPoint(org.bouncycastle.asn1.x509.DistributionPointName, boolean, boolean, org.bouncycastle.asn1.x509.ReasonFlags, boolean, boolean);
    Code:
       0: aload_0
       1: invokespecial #154                // Method org/bouncycastle/asn1/ASN1Object."<init>":()V
       4: aload_0
       5: aload_1
       6: putfield      #142                // Field distributionPoint:Lorg/bouncycastle/asn1/x509/DistributionPointName;
       9: aload_0
      10: iload         5
      12: putfield      #137                // Field indirectCRL:Z
      15: aload_0
      16: iload         6
      18: putfield      #138                // Field onlyContainsAttributeCerts:Z
      21: aload_0
      22: iload_3
      23: putfield      #139                // Field onlyContainsCACerts:Z
      26: aload_0
      27: iload_2
      28: putfield      #140                // Field onlyContainsUserCerts:Z
      31: aload_0
      32: aload         4
      34: putfield      #143                // Field onlySomeReasons:Lorg/bouncycastle/asn1/x509/ReasonFlags;
      37: new           #67                 // class org/bouncycastle/asn1/ASN1EncodableVector
      40: dup
      41: invokespecial #152                // Method org/bouncycastle/asn1/ASN1EncodableVector."<init>":()V
      44: astore        7
      46: aload_1
      47: ifnull        65
      50: aload         7
      52: new           #72                 // class org/bouncycastle/asn1/DERTaggedObject
      55: dup
      56: iconst_1
      57: iconst_0
      58: aload_1
      59: invokespecial #162                // Method org/bouncycastle/asn1/DERTaggedObject."<init>":(ZILorg/bouncycastle/asn1/ASN1Encodable;)V
      62: invokevirtual #153                // Method org/bouncycastle/asn1/ASN1EncodableVector.add:(Lorg/bouncycastle/asn1/ASN1Encodable;)V
      65: iload_2
      66: ifeq          87
      69: aload         7
      71: new           #72                 // class org/bouncycastle/asn1/DERTaggedObject
      74: dup
      75: iconst_0
      76: iconst_1
      77: iconst_1
      78: invokestatic  #150                // Method org/bouncycastle/asn1/ASN1Boolean.getInstance:(Z)Lorg/bouncycastle/asn1/ASN1Boolean;
      81: invokespecial #162                // Method org/bouncycastle/asn1/DERTaggedObject."<init>":(ZILorg/bouncycastle/asn1/ASN1Encodable;)V
      84: invokevirtual #153                // Method org/bouncycastle/asn1/ASN1EncodableVector.add:(Lorg/bouncycastle/asn1/ASN1Encodable;)V
      87: iload_3
      88: ifeq          109
      91: aload         7
      93: new           #72                 // class org/bouncycastle/asn1/DERTaggedObject
      96: dup
      97: iconst_0
      98: iconst_2
      99: iconst_1
     100: invokestatic  #150                // Method org/bouncycastle/asn1/ASN1Boolean.getInstance:(Z)Lorg/bouncycastle/asn1/ASN1Boolean;
     103: invokespecial #162                // Method org/bouncycastle/asn1/DERTaggedObject."<init>":(ZILorg/bouncycastle/asn1/ASN1Encodable;)V
     106: invokevirtual #153                // Method org/bouncycastle/asn1/ASN1EncodableVector.add:(Lorg/bouncycastle/asn1/ASN1Encodable;)V
     109: aload         4
     111: ifnull        130
     114: aload         7
     116: new           #72                 // class org/bouncycastle/asn1/DERTaggedObject
     119: dup
     120: iconst_0
     121: iconst_3
     122: aload         4
     124: invokespecial #162                // Method org/bouncycastle/asn1/DERTaggedObject."<init>":(ZILorg/bouncycastle/asn1/ASN1Encodable;)V
     127: invokevirtual #153                // Method org/bouncycastle/asn1/ASN1EncodableVector.add:(Lorg/bouncycastle/asn1/ASN1Encodable;)V
     130: iload         5
     132: ifeq          153
     135: aload         7
     137: new           #72                 // class org/bouncycastle/asn1/DERTaggedObject
     140: dup
     141: iconst_0
     142: iconst_4
     143: iconst_1
     144: invokestatic  #150                // Method org/bouncycastle/asn1/ASN1Boolean.getInstance:(Z)Lorg/bouncycastle/asn1/ASN1Boolean;
     147: invokespecial #162                // Method org/bouncycastle/asn1/DERTaggedObject."<init>":(ZILorg/bouncycastle/asn1/ASN1Encodable;)V
     150: invokevirtual #153                // Method org/bouncycastle/asn1/ASN1EncodableVector.add:(Lorg/bouncycastle/asn1/ASN1Encodable;)V
     153: iload         6
     155: ifeq          176
     158: aload         7
     160: new           #72                 // class org/bouncycastle/asn1/DERTaggedObject
     163: dup
     164: iconst_0
     165: iconst_5
     166: iconst_1
     167: invokestatic  #150                // Method org/bouncycastle/asn1/ASN1Boolean.getInstance:(Z)Lorg/bouncycastle/asn1/ASN1Boolean;
     170: invokespecial #162                // Method org/bouncycastle/asn1/DERTaggedObject."<init>":(ZILorg/bouncycastle/asn1/ASN1Encodable;)V
     173: invokevirtual #153                // Method org/bouncycastle/asn1/ASN1EncodableVector.add:(Lorg/bouncycastle/asn1/ASN1Encodable;)V
     176: aload_0
     177: new           #71                 // class org/bouncycastle/asn1/DERSequence
     180: dup
     181: aload         7
     183: invokespecial #161                // Method org/bouncycastle/asn1/DERSequence."<init>":(Lorg/bouncycastle/asn1/ASN1EncodableVector;)V
     186: putfield      #141                // Field seq:Lorg/bouncycastle/asn1/ASN1Sequence;
     189: return

  public org.bouncycastle.asn1.x509.IssuingDistributionPoint(org.bouncycastle.asn1.x509.DistributionPointName, boolean, boolean);
    Code:
       0: aload_0
       1: aload_1
       2: iconst_0
       3: iconst_0
       4: aconst_null
       5: iload_2
       6: iload_3
       7: invokespecial #168                // Method "<init>":(Lorg/bouncycastle/asn1/x509/DistributionPointName;ZZLorg/bouncycastle/asn1/x509/ReasonFlags;ZZ)V
      10: return

  private org.bouncycastle.asn1.x509.IssuingDistributionPoint(org.bouncycastle.asn1.ASN1Sequence);
    Code:
       0: aload_0
       1: invokespecial #154                // Method org/bouncycastle/asn1/ASN1Object."<init>":()V
       4: aload_0
       5: aload_1
       6: putfield      #141                // Field seq:Lorg/bouncycastle/asn1/ASN1Sequence;
       9: iconst_0
      10: istore_2
      11: iload_2
      12: aload_1
      13: invokevirtual #155                // Method org/bouncycastle/asn1/ASN1Sequence.size:()I
      16: if_icmpeq     179
      19: aload_1
      20: iload_2
      21: invokevirtual #156                // Method org/bouncycastle/asn1/ASN1Sequence.getObjectAt:(I)Lorg/bouncycastle/asn1/ASN1Encodable;
      24: invokestatic  #160                // Method org/bouncycastle/asn1/ASN1TaggedObject.getInstance:(Ljava/lang/Object;)Lorg/bouncycastle/asn1/ASN1TaggedObject;
      27: astore_3
      28: aload_3
      29: invokevirtual #159                // Method org/bouncycastle/asn1/ASN1TaggedObject.getTagNo:()I
      32: tableswitch   { // 0 to 5
                     0: 72
                     1: 84
                     2: 99
                     3: 114
                     4: 133
                     5: 148
               default: 163
          }
      72: aload_0
      73: aload_3
      74: iconst_1
      75: invokestatic  #164                // Method org/bouncycastle/asn1/x509/DistributionPointName.getInstance:(Lorg/bouncycastle/asn1/ASN1TaggedObject;Z)Lorg/bouncycastle/asn1/x509/DistributionPointName;
      78: putfield      #142                // Field distributionPoint:Lorg/bouncycastle/asn1/x509/DistributionPointName;
      81: goto          173
      84: aload_0
      85: aload_3
      86: iconst_0
      87: invokestatic  #151                // Method org/bouncycastle/asn1/ASN1Boolean.getInstance:(Lorg/bouncycastle/asn1/ASN1TaggedObject;Z)Lorg/bouncycastle/asn1/ASN1Boolean;
      90: invokevirtual #149                // Method org/bouncycastle/asn1/ASN1Boolean.isTrue:()Z
      93: putfield      #140                // Field onlyContainsUserCerts:Z
      96: goto          173
      99: aload_0
     100: aload_3
     101: iconst_0
     102: invokestatic  #151                // Method org/bouncycastle/asn1/ASN1Boolean.getInstance:(Lorg/bouncycastle/asn1/ASN1TaggedObject;Z)Lorg/bouncycastle/asn1/ASN1Boolean;
     105: invokevirtual #149                // Method org/bouncycastle/asn1/ASN1Boolean.isTrue:()Z
     108: putfield      #139                // Field onlyContainsCACerts:Z
     111: goto          173
     114: aload_0
     115: new           #75                 // class org/bouncycastle/asn1/x509/ReasonFlags
     118: dup
     119: aload_3
     120: iconst_0
     121: invokestatic  #172                // Method org/bouncycastle/asn1/x509/ReasonFlags.getInstance:(Lorg/bouncycastle/asn1/ASN1TaggedObject;Z)Lorg/bouncycastle/asn1/DERBitString;
     124: invokespecial #171                // Method org/bouncycastle/asn1/x509/ReasonFlags."<init>":(Lorg/bouncycastle/asn1/DERBitString;)V
     127: putfield      #143                // Field onlySomeReasons:Lorg/bouncycastle/asn1/x509/ReasonFlags;
     130: goto          173
     133: aload_0
     134: aload_3
     135: iconst_0
     136: invokestatic  #151                // Method org/bouncycastle/asn1/ASN1Boolean.getInstance:(Lorg/bouncycastle/asn1/ASN1TaggedObject;Z)Lorg/bouncycastle/asn1/ASN1Boolean;
     139: invokevirtual #149                // Method org/bouncycastle/asn1/ASN1Boolean.isTrue:()Z
     142: putfield      #137                // Field indirectCRL:Z
     145: goto          173
     148: aload_0
     149: aload_3
     150: iconst_0
     151: invokestatic  #151                // Method org/bouncycastle/asn1/ASN1Boolean.getInstance:(Lorg/bouncycastle/asn1/ASN1TaggedObject;Z)Lorg/bouncycastle/asn1/ASN1Boolean;
     154: invokevirtual #149                // Method org/bouncycastle/asn1/ASN1Boolean.isTrue:()Z
     157: putfield      #138                // Field onlyContainsAttributeCerts:Z
     160: goto          173
     163: new           #63                 // class java/lang/IllegalArgumentException
     166: dup
     167: ldc           #14                 // String unknown tag in IssuingDistributionPoint
     169: invokespecial #144                // Method java/lang/IllegalArgumentException."<init>":(Ljava/lang/String;)V
     172: athrow
     173: iinc          2, 1
     176: goto          11
     179: return

  public boolean onlyContainsUserCerts();
    Code:
       0: aload_0
       1: getfield      #140                // Field onlyContainsUserCerts:Z
       4: ireturn

  public boolean onlyContainsCACerts();
    Code:
       0: aload_0
       1: getfield      #139                // Field onlyContainsCACerts:Z
       4: ireturn

  public boolean isIndirectCRL();
    Code:
       0: aload_0
       1: getfield      #137                // Field indirectCRL:Z
       4: ireturn

  public boolean onlyContainsAttributeCerts();
    Code:
       0: aload_0
       1: getfield      #138                // Field onlyContainsAttributeCerts:Z
       4: ireturn

  public org.bouncycastle.asn1.x509.DistributionPointName getDistributionPoint();
    Code:
       0: aload_0
       1: getfield      #142                // Field distributionPoint:Lorg/bouncycastle/asn1/x509/DistributionPointName;
       4: areturn

  public org.bouncycastle.asn1.x509.ReasonFlags getOnlySomeReasons();
    Code:
       0: aload_0
       1: getfield      #143                // Field onlySomeReasons:Lorg/bouncycastle/asn1/x509/ReasonFlags;
       4: areturn

  public org.bouncycastle.asn1.ASN1Primitive toASN1Primitive();
    Code:
       0: aload_0
       1: getfield      #141                // Field seq:Lorg/bouncycastle/asn1/ASN1Sequence;
       4: areturn

  public java.lang.String toString();
    Code:
       0: ldc           #8                  // String line.separator
       2: invokestatic  #148                // Method java/lang/System.getProperty:(Ljava/lang/String;)Ljava/lang/String;
       5: astore_1
       6: new           #64                 // class java/lang/StringBuffer
       9: dup
      10: invokespecial #145                // Method java/lang/StringBuffer."<init>":()V
      13: astore_2
      14: aload_2
      15: ldc           #3                  // String IssuingDistributionPoint: [
      17: invokevirtual #147                // Method java/lang/StringBuffer.append:(Ljava/lang/String;)Ljava/lang/StringBuffer;
      20: pop
      21: aload_2
      22: aload_1
      23: invokevirtual #147                // Method java/lang/StringBuffer.append:(Ljava/lang/String;)Ljava/lang/StringBuffer;
      26: pop
      27: aload_0
      28: getfield      #142                // Field distributionPoint:Lorg/bouncycastle/asn1/x509/DistributionPointName;
      31: ifnull        49
      34: aload_0
      35: aload_2
      36: aload_1
      37: ldc           #5                  // String distributionPoint
      39: aload_0
      40: getfield      #142                // Field distributionPoint:Lorg/bouncycastle/asn1/x509/DistributionPointName;
      43: invokevirtual #163                // Method org/bouncycastle/asn1/x509/DistributionPointName.toString:()Ljava/lang/String;
      46: invokespecial #169                // Method appendObject:(Ljava/lang/StringBuffer;Ljava/lang/String;Ljava/lang/String;Ljava/lang/String;)V
      49: aload_0
      50: getfield      #140                // Field onlyContainsUserCerts:Z
      53: ifeq          72
      56: aload_0
      57: aload_2
      58: aload_1
      59: ldc           #11                 // String onlyContainsUserCerts
      61: aload_0
      62: aload_0
      63: getfield      #140                // Field onlyContainsUserCerts:Z
      66: invokespecial #165                // Method booleanToString:(Z)Ljava/lang/String;
      69: invokespecial #169                // Method appendObject:(Ljava/lang/StringBuffer;Ljava/lang/String;Ljava/lang/String;Ljava/lang/String;)V
      72: aload_0
      73: getfield      #139                // Field onlyContainsCACerts:Z
      76: ifeq          95
      79: aload_0
      80: aload_2
      81: aload_1
      82: ldc           #10                 // String onlyContainsCACerts
      84: aload_0
      85: aload_0
      86: getfield      #139                // Field onlyContainsCACerts:Z
      89: invokespecial #165                // Method booleanToString:(Z)Ljava/lang/String;
      92: invokespecial #169                // Method appendObject:(Ljava/lang/StringBuffer;Ljava/lang/String;Ljava/lang/String;Ljava/lang/String;)V
      95: aload_0
      96: getfield      #143                // Field onlySomeReasons:Lorg/bouncycastle/asn1/x509/ReasonFlags;
      99: ifnull        117
     102: aload_0
     103: aload_2
     104: aload_1
     105: ldc           #12                 // String onlySomeReasons
     107: aload_0
     108: getfield      #143                // Field onlySomeReasons:Lorg/bouncycastle/asn1/x509/ReasonFlags;
     111: invokevirtual #170                // Method org/bouncycastle/asn1/x509/ReasonFlags.toString:()Ljava/lang/String;
     114: invokespecial #169                // Method appendObject:(Ljava/lang/StringBuffer;Ljava/lang/String;Ljava/lang/String;Ljava/lang/String;)V
     117: aload_0
     118: getfield      #138                // Field onlyContainsAttributeCerts:Z
     121: ifeq          140
     124: aload_0
     125: aload_2
     126: aload_1
     127: ldc           #9                  // String onlyContainsAttributeCerts
     129: aload_0
     130: aload_0
     131: getfield      #138                // Field onlyContainsAttributeCerts:Z
     134: invokespecial #165                // Method booleanToString:(Z)Ljava/lang/String;
     137: invokespecial #169                // Method appendObject:(Ljava/lang/StringBuffer;Ljava/lang/String;Ljava/lang/String;Ljava/lang/String;)V
     140: aload_0
     141: getfield      #137                // Field indirectCRL:Z
     144: ifeq          163
     147: aload_0
     148: aload_2
     149: aload_1
     150: ldc           #7                  // String indirectCRL
     152: aload_0
     153: aload_0
     154: getfield      #137                // Field indirectCRL:Z
     157: invokespecial #165                // Method booleanToString:(Z)Ljava/lang/String;
     160: invokespecial #169                // Method appendObject:(Ljava/lang/StringBuffer;Ljava/lang/String;Ljava/lang/String;Ljava/lang/String;)V
     163: aload_2
     164: ldc           #4                  // String ]
     166: invokevirtual #147                // Method java/lang/StringBuffer.append:(Ljava/lang/String;)Ljava/lang/StringBuffer;
     169: pop
     170: aload_2
     171: aload_1
     172: invokevirtual #147                // Method java/lang/StringBuffer.append:(Ljava/lang/String;)Ljava/lang/StringBuffer;
     175: pop
     176: aload_2
     177: invokevirtual #146                // Method java/lang/StringBuffer.toString:()Ljava/lang/String;
     180: areturn

  private void appendObject(java.lang.StringBuffer, java.lang.String, java.lang.String, java.lang.String);
    Code:
       0: ldc           #1                  // String
       2: astore        5
       4: aload_1
       5: aload         5
       7: invokevirtual #147                // Method java/lang/StringBuffer.append:(Ljava/lang/String;)Ljava/lang/StringBuffer;
      10: pop
      11: aload_1
      12: aload_3
      13: invokevirtual #147                // Method java/lang/StringBuffer.append:(Ljava/lang/String;)Ljava/lang/StringBuffer;
      16: pop
      17: aload_1
      18: ldc           #2                  // String :
      20: invokevirtual #147                // Method java/lang/StringBuffer.append:(Ljava/lang/String;)Ljava/lang/StringBuffer;
      23: pop
      24: aload_1
      25: aload_2
      26: invokevirtual #147                // Method java/lang/StringBuffer.append:(Ljava/lang/String;)Ljava/lang/StringBuffer;
      29: pop
      30: aload_1
      31: aload         5
      33: invokevirtual #147                // Method java/lang/StringBuffer.append:(Ljava/lang/String;)Ljava/lang/StringBuffer;
      36: pop
      37: aload_1
      38: aload         5
      40: invokevirtual #147                // Method java/lang/StringBuffer.append:(Ljava/lang/String;)Ljava/lang/StringBuffer;
      43: pop
      44: aload_1
      45: aload         4
      47: invokevirtual #147                // Method java/lang/StringBuffer.append:(Ljava/lang/String;)Ljava/lang/StringBuffer;
      50: pop
      51: aload_1
      52: aload_2
      53: invokevirtual #147                // Method java/lang/StringBuffer.append:(Ljava/lang/String;)Ljava/lang/StringBuffer;
      56: pop
      57: return

  private java.lang.String booleanToString(boolean);
    Code:
       0: iload_1
       1: ifeq          9
       4: ldc           #13                 // String true
       6: goto          11
       9: ldc           #6                  // String false
      11: areturn
}
