Compiled from "ConnectionReleaseMode.java"
public final class org.hibernate.ConnectionReleaseMode extends java.lang.Enum<org.hibernate.ConnectionReleaseMode> {
  public static final org.hibernate.ConnectionReleaseMode AFTER_STATEMENT;

  public static final org.hibernate.ConnectionReleaseMode AFTER_TRANSACTION;

  public static final org.hibernate.ConnectionReleaseMode ON_CLOSE;

  private static final org.hibernate.ConnectionReleaseMode[] $VALUES;

  public static org.hibernate.ConnectionReleaseMode[] values();
    Code:
       0: getstatic     #1                  // Field $VALUES:[Lorg/hibernate/ConnectionReleaseMode;
       3: invokevirtual #2                  // Method "[Lorg/hibernate/ConnectionReleaseMode;".clone:()Ljava/lang/Object;
       6: checkcast     #3                  // class "[Lorg/hibernate/ConnectionReleaseMode;"
       9: areturn

  public static org.hibernate.ConnectionReleaseMode valueOf(java.lang.String);
    Code:
       0: ldc           #4                  // class org/hibernate/ConnectionReleaseMode
       2: aload_0
       3: invokestatic  #5                  // Method java/lang/Enum.valueOf:(Ljava/lang/Class;Ljava/lang/String;)Ljava/lang/Enum;
       6: checkcast     #4                  // class org/hibernate/ConnectionReleaseMode
       9: areturn

  private org.hibernate.ConnectionReleaseMode();
    Code:
       0: aload_0
       1: aload_1
       2: iload_2
       3: invokespecial #6                  // Method java/lang/Enum."<init>":(Ljava/lang/String;I)V
       6: return

  public static org.hibernate.ConnectionReleaseMode parse(java.lang.String);
    Code:
       0: aload_0
       1: getstatic     #7                  // Field java/util/Locale.ROOT:Ljava/util/Locale;
       4: invokevirtual #8                  // Method java/lang/String.toUpperCase:(Ljava/util/Locale;)Ljava/lang/String;
       7: invokestatic  #9                  // Method valueOf:(Ljava/lang/String;)Lorg/hibernate/ConnectionReleaseMode;
      10: areturn

  public static org.hibernate.ConnectionReleaseMode interpret(java.lang.Object);
    Code:
       0: aload_0
       1: ifnonnull     6
       4: aconst_null
       5: areturn
       6: aload_0
       7: instanceof    #4                  // class org/hibernate/ConnectionReleaseMode
      10: ifeq          18
      13: aload_0
      14: checkcast     #4                  // class org/hibernate/ConnectionReleaseMode
      17: areturn
      18: aload_0
      19: invokevirtual #10                 // Method java/lang/Object.toString:()Ljava/lang/String;
      22: astore_1
      23: aload_1
      24: invokestatic  #11                 // Method org/hibernate/internal/util/StringHelper.isEmpty:(Ljava/lang/String;)Z
      27: ifeq          32
      30: aconst_null
      31: areturn
      32: aload_1
      33: ldc           #12                 // String auto
      35: invokevirtual #13                 // Method java/lang/String.equalsIgnoreCase:(Ljava/lang/String;)Z
      38: ifeq          43
      41: aconst_null
      42: areturn
      43: aload_1
      44: invokestatic  #14                 // Method parse:(Ljava/lang/String;)Lorg/hibernate/ConnectionReleaseMode;
      47: areturn

  static {};
    Code:
       0: new           #4                  // class org/hibernate/ConnectionReleaseMode
       3: dup
       4: ldc           #15                 // String AFTER_STATEMENT
       6: iconst_0
       7: invokespecial #16                 // Method "<init>":(Ljava/lang/String;I)V
      10: putstatic     #17                 // Field AFTER_STATEMENT:Lorg/hibernate/ConnectionReleaseMode;
      13: new           #4                  // class org/hibernate/ConnectionReleaseMode
      16: dup
      17: ldc           #18                 // String AFTER_TRANSACTION
      19: iconst_1
      20: invokespecial #16                 // Method "<init>":(Ljava/lang/String;I)V
      23: putstatic     #19                 // Field AFTER_TRANSACTION:Lorg/hibernate/ConnectionReleaseMode;
      26: new           #4                  // class org/hibernate/ConnectionReleaseMode
      29: dup
      30: ldc           #20                 // String ON_CLOSE
      32: iconst_2
      33: invokespecial #16                 // Method "<init>":(Ljava/lang/String;I)V
      36: putstatic     #21                 // Field ON_CLOSE:Lorg/hibernate/ConnectionReleaseMode;
      39: iconst_3
      40: anewarray     #4                  // class org/hibernate/ConnectionReleaseMode
      43: dup
      44: iconst_0
      45: getstatic     #17                 // Field AFTER_STATEMENT:Lorg/hibernate/ConnectionReleaseMode;
      48: aastore
      49: dup
      50: iconst_1
      51: getstatic     #19                 // Field AFTER_TRANSACTION:Lorg/hibernate/ConnectionReleaseMode;
      54: aastore
      55: dup
      56: iconst_2
      57: getstatic     #21                 // Field ON_CLOSE:Lorg/hibernate/ConnectionReleaseMode;
      60: aastore
      61: putstatic     #1                  // Field $VALUES:[Lorg/hibernate/ConnectionReleaseMode;
      64: return
}
