Compiled from "PersistentMessageGroup.java"
class org.springframework.integration.store.PersistentMessageGroup implements org.springframework.integration.store.MessageGroup {
  private static final org.apache.commons.logging.Log logger;

  private final org.springframework.integration.store.MessageGroupStore messageGroupStore;

  private final java.util.Collection<org.springframework.messaging.Message<?>> messages;

  private final org.springframework.integration.store.MessageGroup original;

  private volatile org.springframework.messaging.Message<?> oneMessage;

  private volatile int size;

  org.springframework.integration.store.PersistentMessageGroup(org.springframework.integration.store.MessageGroupStore, org.springframework.integration.store.MessageGroup);
    Code:
       0: aload_0
       1: invokespecial #4                  // Method java/lang/Object."<init>":()V
       4: aload_0
       5: new           #5                  // class org/springframework/integration/store/PersistentMessageGroup$PersistentCollection
       8: dup
       9: aload_0
      10: invokespecial #6                  // Method org/springframework/integration/store/PersistentMessageGroup$PersistentCollection."<init>":(Lorg/springframework/integration/store/PersistentMessageGroup;)V
      13: putfield      #7                  // Field messages:Ljava/util/Collection;
      16: aload_0
      17: aload_1
      18: putfield      #1                  // Field messageGroupStore:Lorg/springframework/integration/store/MessageGroupStore;
      21: aload_0
      22: aload_2
      23: putfield      #3                  // Field original:Lorg/springframework/integration/store/MessageGroup;
      26: return

  public void setSize(int);
    Code:
       0: aload_0
       1: iload_1
       2: putfield      #8                  // Field size:I
       5: return

  public java.util.Collection<org.springframework.messaging.Message<?>> getMessages();
    Code:
       0: aload_0
       1: getfield      #7                  // Field messages:Ljava/util/Collection;
       4: invokestatic  #9                  // Method java/util/Collections.unmodifiableCollection:(Ljava/util/Collection;)Ljava/util/Collection;
       7: areturn

  public org.springframework.messaging.Message<?> getOne();
    Code:
       0: aload_0
       1: getfield      #10                 // Field oneMessage:Lorg/springframework/messaging/Message;
       4: ifnonnull     96
       7: aload_0
       8: dup
       9: astore_1
      10: monitorenter
      11: aload_0
      12: getfield      #10                 // Field oneMessage:Lorg/springframework/messaging/Message;
      15: ifnonnull     86
      18: getstatic     #2                  // Field logger:Lorg/apache/commons/logging/Log;
      21: invokeinterface #11,  1           // InterfaceMethod org/apache/commons/logging/Log.isDebugEnabled:()Z
      26: ifeq          64
      29: getstatic     #2                  // Field logger:Lorg/apache/commons/logging/Log;
      32: new           #12                 // class java/lang/StringBuilder
      35: dup
      36: invokespecial #13                 // Method java/lang/StringBuilder."<init>":()V
      39: ldc           #14                 // String Lazy loading of one message for messageGroup:
      41: invokevirtual #15                 // Method java/lang/StringBuilder.append:(Ljava/lang/String;)Ljava/lang/StringBuilder;
      44: aload_0
      45: getfield      #3                  // Field original:Lorg/springframework/integration/store/MessageGroup;
      48: invokeinterface #16,  1           // InterfaceMethod org/springframework/integration/store/MessageGroup.getGroupId:()Ljava/lang/Object;
      53: invokevirtual #17                 // Method java/lang/StringBuilder.append:(Ljava/lang/Object;)Ljava/lang/StringBuilder;
      56: invokevirtual #18                 // Method java/lang/StringBuilder.toString:()Ljava/lang/String;
      59: invokeinterface #19,  2           // InterfaceMethod org/apache/commons/logging/Log.debug:(Ljava/lang/Object;)V
      64: aload_0
      65: aload_0
      66: getfield      #1                  // Field messageGroupStore:Lorg/springframework/integration/store/MessageGroupStore;
      69: aload_0
      70: getfield      #3                  // Field original:Lorg/springframework/integration/store/MessageGroup;
      73: invokeinterface #16,  1           // InterfaceMethod org/springframework/integration/store/MessageGroup.getGroupId:()Ljava/lang/Object;
      78: invokeinterface #20,  2           // InterfaceMethod org/springframework/integration/store/MessageGroupStore.getOneMessageFromGroup:(Ljava/lang/Object;)Lorg/springframework/messaging/Message;
      83: putfield      #10                 // Field oneMessage:Lorg/springframework/messaging/Message;
      86: aload_1
      87: monitorexit
      88: goto          96
      91: astore_2
      92: aload_1
      93: monitorexit
      94: aload_2
      95: athrow
      96: aload_0
      97: getfield      #10                 // Field oneMessage:Lorg/springframework/messaging/Message;
     100: areturn
    Exception table:
       from    to  target type
          11    88    91   any
          91    94    91   any

  public int getSequenceSize();
    Code:
       0: aload_0
       1: invokevirtual #21                 // Method size:()I
       4: ifne          9
       7: iconst_0
       8: ireturn
       9: aload_0
      10: invokevirtual #22                 // Method getOne:()Lorg/springframework/messaging/Message;
      13: astore_1
      14: aload_1
      15: ifnull        48
      18: aload_1
      19: invokeinterface #23,  1           // InterfaceMethod org/springframework/messaging/Message.getHeaders:()Lorg/springframework/messaging/MessageHeaders;
      24: ldc           #25                 // String sequenceSize
      26: ldc           #26                 // class java/lang/Integer
      28: invokevirtual #27                 // Method org/springframework/messaging/MessageHeaders.get:(Ljava/lang/Object;Ljava/lang/Class;)Ljava/lang/Object;
      31: checkcast     #26                 // class java/lang/Integer
      34: astore_2
      35: aload_2
      36: ifnull        46
      39: aload_2
      40: invokevirtual #28                 // Method java/lang/Integer.intValue:()I
      43: goto          47
      46: iconst_0
      47: ireturn
      48: iconst_0
      49: ireturn

  public int size();
    Code:
       0: aload_0
       1: getfield      #8                  // Field size:I
       4: ifne          96
       7: aload_0
       8: dup
       9: astore_1
      10: monitorenter
      11: aload_0
      12: getfield      #8                  // Field size:I
      15: ifne          86
      18: getstatic     #2                  // Field logger:Lorg/apache/commons/logging/Log;
      21: invokeinterface #11,  1           // InterfaceMethod org/apache/commons/logging/Log.isDebugEnabled:()Z
      26: ifeq          64
      29: getstatic     #2                  // Field logger:Lorg/apache/commons/logging/Log;
      32: new           #12                 // class java/lang/StringBuilder
      35: dup
      36: invokespecial #13                 // Method java/lang/StringBuilder."<init>":()V
      39: ldc           #29                 // String Lazy loading of group size for messageGroup:
      41: invokevirtual #15                 // Method java/lang/StringBuilder.append:(Ljava/lang/String;)Ljava/lang/StringBuilder;
      44: aload_0
      45: getfield      #3                  // Field original:Lorg/springframework/integration/store/MessageGroup;
      48: invokeinterface #16,  1           // InterfaceMethod org/springframework/integration/store/MessageGroup.getGroupId:()Ljava/lang/Object;
      53: invokevirtual #17                 // Method java/lang/StringBuilder.append:(Ljava/lang/Object;)Ljava/lang/StringBuilder;
      56: invokevirtual #18                 // Method java/lang/StringBuilder.toString:()Ljava/lang/String;
      59: invokeinterface #19,  2           // InterfaceMethod org/apache/commons/logging/Log.debug:(Ljava/lang/Object;)V
      64: aload_0
      65: aload_0
      66: getfield      #1                  // Field messageGroupStore:Lorg/springframework/integration/store/MessageGroupStore;
      69: aload_0
      70: getfield      #3                  // Field original:Lorg/springframework/integration/store/MessageGroup;
      73: invokeinterface #16,  1           // InterfaceMethod org/springframework/integration/store/MessageGroup.getGroupId:()Ljava/lang/Object;
      78: invokeinterface #30,  2           // InterfaceMethod org/springframework/integration/store/MessageGroupStore.messageGroupSize:(Ljava/lang/Object;)I
      83: putfield      #8                  // Field size:I
      86: aload_1
      87: monitorexit
      88: goto          96
      91: astore_2
      92: aload_1
      93: monitorexit
      94: aload_2
      95: athrow
      96: aload_0
      97: getfield      #8                  // Field size:I
     100: ireturn
    Exception table:
       from    to  target type
          11    88    91   any
          91    94    91   any

  public java.lang.Object getGroupId();
    Code:
       0: aload_0
       1: getfield      #3                  // Field original:Lorg/springframework/integration/store/MessageGroup;
       4: invokeinterface #16,  1           // InterfaceMethod org/springframework/integration/store/MessageGroup.getGroupId:()Ljava/lang/Object;
       9: areturn

  public boolean canAdd(org.springframework.messaging.Message<?>);
    Code:
       0: aload_0
       1: getfield      #3                  // Field original:Lorg/springframework/integration/store/MessageGroup;
       4: aload_1
       5: invokeinterface #31,  2           // InterfaceMethod org/springframework/integration/store/MessageGroup.canAdd:(Lorg/springframework/messaging/Message;)Z
      10: ireturn

  public int getLastReleasedMessageSequenceNumber();
    Code:
       0: aload_0
       1: getfield      #3                  // Field original:Lorg/springframework/integration/store/MessageGroup;
       4: invokeinterface #32,  1           // InterfaceMethod org/springframework/integration/store/MessageGroup.getLastReleasedMessageSequenceNumber:()I
       9: ireturn

  public boolean isComplete();
    Code:
       0: aload_0
       1: getfield      #3                  // Field original:Lorg/springframework/integration/store/MessageGroup;
       4: invokeinterface #33,  1           // InterfaceMethod org/springframework/integration/store/MessageGroup.isComplete:()Z
       9: ireturn

  public void complete();
    Code:
       0: aload_0
       1: getfield      #3                  // Field original:Lorg/springframework/integration/store/MessageGroup;
       4: invokeinterface #34,  1           // InterfaceMethod org/springframework/integration/store/MessageGroup.complete:()V
       9: return

  public long getTimestamp();
    Code:
       0: aload_0
       1: getfield      #3                  // Field original:Lorg/springframework/integration/store/MessageGroup;
       4: invokeinterface #35,  1           // InterfaceMethod org/springframework/integration/store/MessageGroup.getTimestamp:()J
       9: lreturn

  public long getLastModified();
    Code:
       0: aload_0
       1: getfield      #3                  // Field original:Lorg/springframework/integration/store/MessageGroup;
       4: invokeinterface #36,  1           // InterfaceMethod org/springframework/integration/store/MessageGroup.getLastModified:()J
       9: lreturn

  public void setLastModified(long);
    Code:
       0: aload_0
       1: getfield      #3                  // Field original:Lorg/springframework/integration/store/MessageGroup;
       4: lload_1
       5: invokeinterface #37,  3           // InterfaceMethod org/springframework/integration/store/MessageGroup.setLastModified:(J)V
      10: return

  public void add(org.springframework.messaging.Message<?>);
    Code:
       0: aload_0
       1: getfield      #3                  // Field original:Lorg/springframework/integration/store/MessageGroup;
       4: aload_1
       5: invokeinterface #38,  2           // InterfaceMethod org/springframework/integration/store/MessageGroup.add:(Lorg/springframework/messaging/Message;)V
      10: return

  public boolean remove(org.springframework.messaging.Message<?>);
    Code:
       0: aload_0
       1: getfield      #3                  // Field original:Lorg/springframework/integration/store/MessageGroup;
       4: aload_1
       5: invokeinterface #39,  2           // InterfaceMethod org/springframework/integration/store/MessageGroup.remove:(Lorg/springframework/messaging/Message;)Z
      10: ireturn

  public void setLastReleasedMessageSequenceNumber(int);
    Code:
       0: aload_0
       1: getfield      #3                  // Field original:Lorg/springframework/integration/store/MessageGroup;
       4: iload_1
       5: invokeinterface #40,  2           // InterfaceMethod org/springframework/integration/store/MessageGroup.setLastReleasedMessageSequenceNumber:(I)V
      10: return

  public void clear();
    Code:
       0: aload_0
       1: getfield      #3                  // Field original:Lorg/springframework/integration/store/MessageGroup;
       4: invokeinterface #41,  1           // InterfaceMethod org/springframework/integration/store/MessageGroup.clear:()V
       9: return

  static org.springframework.integration.store.MessageGroup access$000(org.springframework.integration.store.PersistentMessageGroup);
    Code:
       0: aload_0
       1: getfield      #3                  // Field original:Lorg/springframework/integration/store/MessageGroup;
       4: areturn

  static org.apache.commons.logging.Log access$100();
    Code:
       0: getstatic     #2                  // Field logger:Lorg/apache/commons/logging/Log;
       3: areturn

  static org.springframework.integration.store.MessageGroupStore access$200(org.springframework.integration.store.PersistentMessageGroup);
    Code:
       0: aload_0
       1: getfield      #1                  // Field messageGroupStore:Lorg/springframework/integration/store/MessageGroupStore;
       4: areturn

  static {};
    Code:
       0: ldc           #42                 // class org/springframework/integration/store/PersistentMessageGroup
       2: invokestatic  #43                 // Method org/apache/commons/logging/LogFactory.getLog:(Ljava/lang/Class;)Lorg/apache/commons/logging/Log;
       5: putstatic     #2                  // Field logger:Lorg/apache/commons/logging/Log;
       8: return
}
