Compiled from "MultipartWriterImpl.java"
class org.apache.axiom.mime.impl.axiom.MultipartWriterImpl implements org.apache.axiom.mime.MultipartWriter {
  private final java.io.OutputStream out;

  private final java.lang.String boundary;

  private final byte[] buffer;

  public org.apache.axiom.mime.impl.axiom.MultipartWriterImpl(java.io.OutputStream, java.lang.String);
    Code:
       0: aload_0
       1: invokespecial #1                  // Method java/lang/Object."<init>":()V
       4: aload_0
       5: sipush        256
       8: newarray       byte
      10: putfield      #2                  // Field buffer:[B
      13: aload_0
      14: aload_1
      15: putfield      #3                  // Field out:Ljava/io/OutputStream;
      18: aload_0
      19: aload_2
      20: putfield      #4                  // Field boundary:Ljava/lang/String;
      23: return

  void writeAscii(java.lang.String) throws java.io.IOException;
    Code:
       0: iconst_0
       1: istore_2
       2: iconst_0
       3: istore_3
       4: aload_1
       5: invokevirtual #5                  // Method java/lang/String.length:()I
       8: istore        4
      10: iload_3
      11: iload         4
      13: if_icmpge     104
      16: aload_1
      17: iload_3
      18: invokevirtual #6                  // Method java/lang/String.charAt:(I)C
      21: istore        5
      23: iload         5
      25: sipush        128
      28: if_icmplt     64
      31: new           #7                  // class java/io/IOException
      34: dup
      35: new           #8                  // class java/lang/StringBuilder
      38: dup
      39: invokespecial #9                  // Method java/lang/StringBuilder."<init>":()V
      42: ldc           #10                 // String Illegal character \'
      44: invokevirtual #11                 // Method java/lang/StringBuilder.append:(Ljava/lang/String;)Ljava/lang/StringBuilder;
      47: iload         5
      49: invokevirtual #12                 // Method java/lang/StringBuilder.append:(C)Ljava/lang/StringBuilder;
      52: ldc           #13                 // String \'
      54: invokevirtual #11                 // Method java/lang/StringBuilder.append:(Ljava/lang/String;)Ljava/lang/StringBuilder;
      57: invokevirtual #14                 // Method java/lang/StringBuilder.toString:()Ljava/lang/String;
      60: invokespecial #15                 // Method java/io/IOException."<init>":(Ljava/lang/String;)V
      63: athrow
      64: aload_0
      65: getfield      #2                  // Field buffer:[B
      68: iload_2
      69: iinc          2, 1
      72: iload         5
      74: i2b
      75: bastore
      76: iload_2
      77: aload_0
      78: getfield      #2                  // Field buffer:[B
      81: arraylength
      82: if_icmpne     98
      85: aload_0
      86: getfield      #3                  // Field out:Ljava/io/OutputStream;
      89: aload_0
      90: getfield      #2                  // Field buffer:[B
      93: invokevirtual #16                 // Method java/io/OutputStream.write:([B)V
      96: iconst_0
      97: istore_2
      98: iinc          3, 1
     101: goto          10
     104: iload_2
     105: ifle          121
     108: aload_0
     109: getfield      #3                  // Field out:Ljava/io/OutputStream;
     112: aload_0
     113: getfield      #2                  // Field buffer:[B
     116: iconst_0
     117: iload_2
     118: invokevirtual #17                 // Method java/io/OutputStream.write:([BII)V
     121: return

  public java.io.OutputStream writePart(java.lang.String, java.lang.String, java.lang.String, java.util.List) throws java.io.IOException;
    Code:
       0: aload_2
       1: ldc           #18                 // String 8bit
       3: invokevirtual #19                 // Method java/lang/String.equals:(Ljava/lang/Object;)Z
       6: ifne          18
       9: aload_2
      10: ldc           #20                 // String binary
      12: invokevirtual #19                 // Method java/lang/String.equals:(Ljava/lang/Object;)Z
      15: ifeq          27
      18: aload_0
      19: getfield      #3                  // Field out:Ljava/io/OutputStream;
      22: astore        5
      24: goto          43
      27: new           #21                 // class org/apache/axiom/util/base64/Base64EncodingOutputStream
      30: dup
      31: aload_0
      32: getfield      #3                  // Field out:Ljava/io/OutputStream;
      35: invokespecial #22                 // Method org/apache/axiom/util/base64/Base64EncodingOutputStream."<init>":(Ljava/io/OutputStream;)V
      38: astore        5
      40: ldc           #23                 // String base64
      42: astore_2
      43: aload_0
      44: ldc           #24                 // String --
      46: invokevirtual #25                 // Method writeAscii:(Ljava/lang/String;)V
      49: aload_0
      50: aload_0
      51: getfield      #4                  // Field boundary:Ljava/lang/String;
      54: invokevirtual #25                 // Method writeAscii:(Ljava/lang/String;)V
      57: aload_1
      58: ifnull        72
      61: aload_0
      62: ldc           #26                 // String \r\nContent-Type:
      64: invokevirtual #25                 // Method writeAscii:(Ljava/lang/String;)V
      67: aload_0
      68: aload_1
      69: invokevirtual #25                 // Method writeAscii:(Ljava/lang/String;)V
      72: aload_0
      73: ldc           #27                 // String \r\nContent-Transfer-Encoding:
      75: invokevirtual #25                 // Method writeAscii:(Ljava/lang/String;)V
      78: aload_0
      79: aload_2
      80: invokevirtual #25                 // Method writeAscii:(Ljava/lang/String;)V
      83: aload_3
      84: ifnull        107
      87: aload_0
      88: ldc           #28                 // String \r\nContent-ID: <
      90: invokevirtual #25                 // Method writeAscii:(Ljava/lang/String;)V
      93: aload_0
      94: aload_3
      95: invokevirtual #25                 // Method writeAscii:(Ljava/lang/String;)V
      98: aload_0
      99: getfield      #3                  // Field out:Ljava/io/OutputStream;
     102: bipush        62
     104: invokevirtual #29                 // Method java/io/OutputStream.write:(I)V
     107: aload         4
     109: ifnull        176
     112: aload         4
     114: invokeinterface #30,  1           // InterfaceMethod java/util/List.iterator:()Ljava/util/Iterator;
     119: astore        6
     121: aload         6
     123: invokeinterface #31,  1           // InterfaceMethod java/util/Iterator.hasNext:()Z
     128: ifeq          176
     131: aload         6
     133: invokeinterface #32,  1           // InterfaceMethod java/util/Iterator.next:()Ljava/lang/Object;
     138: checkcast     #33                 // class org/apache/axiom/mime/Header
     141: astore        7
     143: aload_0
     144: ldc           #34                 // String \r\n
     146: invokevirtual #25                 // Method writeAscii:(Ljava/lang/String;)V
     149: aload_0
     150: aload         7
     152: invokevirtual #35                 // Method org/apache/axiom/mime/Header.getName:()Ljava/lang/String;
     155: invokevirtual #25                 // Method writeAscii:(Ljava/lang/String;)V
     158: aload_0
     159: ldc           #36                 // String :
     161: invokevirtual #25                 // Method writeAscii:(Ljava/lang/String;)V
     164: aload_0
     165: aload         7
     167: invokevirtual #37                 // Method org/apache/axiom/mime/Header.getValue:()Ljava/lang/String;
     170: invokevirtual #25                 // Method writeAscii:(Ljava/lang/String;)V
     173: goto          121
     176: aload_0
     177: ldc           #38                 // String \r\n\r\n
     179: invokevirtual #25                 // Method writeAscii:(Ljava/lang/String;)V
     182: new           #39                 // class org/apache/axiom/mime/impl/axiom/MultipartWriterImpl$PartOutputStream
     185: dup
     186: aload_0
     187: aload         5
     189: invokespecial #40                 // Method org/apache/axiom/mime/impl/axiom/MultipartWriterImpl$PartOutputStream."<init>":(Lorg/apache/axiom/mime/impl/axiom/MultipartWriterImpl;Ljava/io/OutputStream;)V
     192: areturn

  public java.io.OutputStream writePart(java.lang.String, java.lang.String, java.lang.String) throws java.io.IOException;
    Code:
       0: aload_0
       1: aload_1
       2: aload_2
       3: aload_3
       4: aconst_null
       5: invokevirtual #41                 // Method writePart:(Ljava/lang/String;Ljava/lang/String;Ljava/lang/String;Ljava/util/List;)Ljava/io/OutputStream;
       8: areturn

  public void writePart(javax.activation.DataHandler, java.lang.String, java.lang.String, java.util.List) throws java.io.IOException;
    Code:
       0: aload_0
       1: aload_1
       2: invokevirtual #42                 // Method javax/activation/DataHandler.getContentType:()Ljava/lang/String;
       5: aload_2
       6: aload_3
       7: aload         4
       9: invokevirtual #41                 // Method writePart:(Ljava/lang/String;Ljava/lang/String;Ljava/lang/String;Ljava/util/List;)Ljava/io/OutputStream;
      12: astore        5
      14: aload_1
      15: aload         5
      17: invokevirtual #43                 // Method javax/activation/DataHandler.writeTo:(Ljava/io/OutputStream;)V
      20: aload         5
      22: invokevirtual #44                 // Method java/io/OutputStream.close:()V
      25: return

  public void writePart(javax.activation.DataHandler, java.lang.String, java.lang.String) throws java.io.IOException;
    Code:
       0: aload_0
       1: aload_1
       2: aload_2
       3: aload_3
       4: aconst_null
       5: invokevirtual #45                 // Method writePart:(Ljavax/activation/DataHandler;Ljava/lang/String;Ljava/lang/String;Ljava/util/List;)V
       8: return

  public void complete() throws java.io.IOException;
    Code:
       0: aload_0
       1: ldc           #24                 // String --
       3: invokevirtual #25                 // Method writeAscii:(Ljava/lang/String;)V
       6: aload_0
       7: aload_0
       8: getfield      #4                  // Field boundary:Ljava/lang/String;
      11: invokevirtual #25                 // Method writeAscii:(Ljava/lang/String;)V
      14: aload_0
      15: ldc           #46                 // String --\r\n
      17: invokevirtual #25                 // Method writeAscii:(Ljava/lang/String;)V
      20: return
}
