Compiled from "UndeployAction.java"
public class org.jboss.as.cli.gui.metacommand.UndeployAction extends javax.swing.AbstractAction {
  private org.jboss.as.cli.gui.CliGuiContext cliGuiCtx;

  public org.jboss.as.cli.gui.metacommand.UndeployAction(org.jboss.as.cli.gui.CliGuiContext);
    Code:
       0: aload_0
       1: ldc           #1                  // String Undeploy
       3: invokespecial #2                  // Method javax/swing/AbstractAction."<init>":(Ljava/lang/String;)V
       6: aload_0
       7: aload_1
       8: putfield      #3                  // Field cliGuiCtx:Lorg/jboss/as/cli/gui/CliGuiContext;
      11: return

  public void actionPerformed(java.awt.event.ActionEvent);
    Code:
       0: new           #4                  // class org/jboss/as/cli/gui/metacommand/UndeployCommandDialog
       3: dup
       4: aload_0
       5: getfield      #3                  // Field cliGuiCtx:Lorg/jboss/as/cli/gui/CliGuiContext;
       8: invokespecial #5                  // Method org/jboss/as/cli/gui/metacommand/UndeployCommandDialog."<init>":(Lorg/jboss/as/cli/gui/CliGuiContext;)V
      11: astore_2
      12: aload_2
      13: aload_0
      14: getfield      #3                  // Field cliGuiCtx:Lorg/jboss/as/cli/gui/CliGuiContext;
      17: invokevirtual #6                  // Method org/jboss/as/cli/gui/CliGuiContext.getMainWindow:()Ljava/awt/Window;
      20: invokevirtual #7                  // Method org/jboss/as/cli/gui/metacommand/UndeployCommandDialog.setLocationRelativeTo:(Ljava/awt/Component;)V
      23: aload_2
      24: iconst_1
      25: invokevirtual #8                  // Method org/jboss/as/cli/gui/metacommand/UndeployCommandDialog.setVisible:(Z)V
      28: return
}
