Compiled from "ComponentProvider.java"
public interface org.glassfish.jersey.spi.ComponentProvider {
  public abstract void initialize(org.glassfish.jersey.internal.inject.InjectionManager);

  public abstract boolean bind(java.lang.Class<?>, java.util.Set<java.lang.Class<?>>);

  public default boolean bind(java.lang.Class<?>, org.glassfish.jersey.model.ContractProvider);
    Code:
       0: aload_2
       1: ifnonnull     10
       4: invokestatic  #1                  // Method java/util/Collections.emptySet:()Ljava/util/Set;
       7: goto          14
      10: aload_2
      11: invokevirtual #2                  // Method org/glassfish/jersey/model/ContractProvider.getContracts:()Ljava/util/Set;
      14: astore_3
      15: aload_0
      16: aload_1
      17: aload_3
      18: invokeinterface #3,  3            // InterfaceMethod bind:(Ljava/lang/Class;Ljava/util/Set;)Z
      23: ireturn

  public abstract void done();
}
