Compiled from "JaxbHbmFilterParameterType.java"
public class org.hibernate.boot.jaxb.hbm.spi.JaxbHbmFilterParameterType implements java.io.Serializable {
  protected java.lang.String parameterName;

  protected java.lang.String parameterValueTypeName;

  public org.hibernate.boot.jaxb.hbm.spi.JaxbHbmFilterParameterType();
    Code:
       0: aload_0
       1: invokespecial #1                  // Method java/lang/Object."<init>":()V
       4: return

  public java.lang.String getParameterName();
    Code:
       0: aload_0
       1: getfield      #2                  // Field parameterName:Ljava/lang/String;
       4: areturn

  public void setParameterName(java.lang.String);
    Code:
       0: aload_0
       1: aload_1
       2: putfield      #2                  // Field parameterName:Ljava/lang/String;
       5: return

  public java.lang.String getParameterValueTypeName();
    Code:
       0: aload_0
       1: getfield      #3                  // Field parameterValueTypeName:Ljava/lang/String;
       4: areturn

  public void setParameterValueTypeName(java.lang.String);
    Code:
       0: aload_0
       1: aload_1
       2: putfield      #3                  // Field parameterValueTypeName:Ljava/lang/String;
       5: return
}
