Compiled from "JaxbHbmVersionAttributeType.java"
public class org.hibernate.boot.jaxb.hbm.spi.JaxbHbmVersionAttributeType extends org.hibernate.boot.jaxb.hbm.spi.JaxbHbmBaseVersionAttributeType implements java.io.Serializable,org.hibernate.boot.jaxb.hbm.spi.SingularAttributeInfo,org.hibernate.boot.jaxb.hbm.spi.ToolingHintContainer {
  protected java.util.List<org.hibernate.boot.jaxb.hbm.spi.JaxbHbmColumnType> column;

  protected java.lang.Boolean insert;

  protected java.lang.String type;

  protected org.hibernate.boot.jaxb.hbm.spi.JaxbHbmUnsavedValueVersionEnum unsavedValue;

  public org.hibernate.boot.jaxb.hbm.spi.JaxbHbmVersionAttributeType();
    Code:
       0: aload_0
       1: invokespecial #1                  // Method org/hibernate/boot/jaxb/hbm/spi/JaxbHbmBaseVersionAttributeType."<init>":()V
       4: return

  public java.util.List<org.hibernate.boot.jaxb.hbm.spi.JaxbHbmColumnType> getColumn();
    Code:
       0: aload_0
       1: getfield      #2                  // Field column:Ljava/util/List;
       4: ifnonnull     18
       7: aload_0
       8: new           #3                  // class java/util/ArrayList
      11: dup
      12: invokespecial #4                  // Method java/util/ArrayList."<init>":()V
      15: putfield      #2                  // Field column:Ljava/util/List;
      18: aload_0
      19: getfield      #2                  // Field column:Ljava/util/List;
      22: areturn

  public java.lang.Boolean isInsert();
    Code:
       0: aload_0
       1: getfield      #5                  // Field insert:Ljava/lang/Boolean;
       4: areturn

  public void setInsert(java.lang.Boolean);
    Code:
       0: aload_0
       1: aload_1
       2: putfield      #5                  // Field insert:Ljava/lang/Boolean;
       5: return

  public java.lang.String getType();
    Code:
       0: aload_0
       1: getfield      #6                  // Field type:Ljava/lang/String;
       4: ifnonnull     10
       7: ldc           #7                  // String integer
       9: areturn
      10: aload_0
      11: getfield      #6                  // Field type:Ljava/lang/String;
      14: areturn

  public void setType(java.lang.String);
    Code:
       0: aload_0
       1: aload_1
       2: putfield      #6                  // Field type:Ljava/lang/String;
       5: return

  public org.hibernate.boot.jaxb.hbm.spi.JaxbHbmUnsavedValueVersionEnum getUnsavedValue();
    Code:
       0: aload_0
       1: getfield      #8                  // Field unsavedValue:Lorg/hibernate/boot/jaxb/hbm/spi/JaxbHbmUnsavedValueVersionEnum;
       4: ifnonnull     11
       7: getstatic     #9                  // Field org/hibernate/boot/jaxb/hbm/spi/JaxbHbmUnsavedValueVersionEnum.UNDEFINED:Lorg/hibernate/boot/jaxb/hbm/spi/JaxbHbmUnsavedValueVersionEnum;
      10: areturn
      11: aload_0
      12: getfield      #8                  // Field unsavedValue:Lorg/hibernate/boot/jaxb/hbm/spi/JaxbHbmUnsavedValueVersionEnum;
      15: areturn

  public void setUnsavedValue(org.hibernate.boot.jaxb.hbm.spi.JaxbHbmUnsavedValueVersionEnum);
    Code:
       0: aload_0
       1: aload_1
       2: putfield      #8                  // Field unsavedValue:Lorg/hibernate/boot/jaxb/hbm/spi/JaxbHbmUnsavedValueVersionEnum;
       5: return
}
