Compiled from "TopicMetrics.java"
public class pl.allegro.tech.hermes.api.TopicMetrics$Builder {
  private pl.allegro.tech.hermes.api.TopicMetrics topicMetrics;

  public pl.allegro.tech.hermes.api.TopicMetrics$Builder();
    Code:
       0: aload_0
       1: invokespecial #1                  // Method java/lang/Object."<init>":()V
       4: aload_0
       5: new           #2                  // class pl/allegro/tech/hermes/api/TopicMetrics
       8: dup
       9: invokespecial #3                  // Method pl/allegro/tech/hermes/api/TopicMetrics."<init>":()V
      12: putfield      #4                  // Field topicMetrics:Lpl/allegro/tech/hermes/api/TopicMetrics;
      15: return

  public pl.allegro.tech.hermes.api.TopicMetrics$Builder withPublished(long);
    Code:
       0: aload_0
       1: getfield      #4                  // Field topicMetrics:Lpl/allegro/tech/hermes/api/TopicMetrics;
       4: lload_1
       5: invokestatic  #5                  // Method pl/allegro/tech/hermes/api/TopicMetrics.access$002:(Lpl/allegro/tech/hermes/api/TopicMetrics;J)J
       8: pop2
       9: aload_0
      10: areturn

  public pl.allegro.tech.hermes.api.TopicMetrics$Builder withRate(java.lang.String);
    Code:
       0: aload_0
       1: getfield      #4                  // Field topicMetrics:Lpl/allegro/tech/hermes/api/TopicMetrics;
       4: aload_1
       5: invokestatic  #6                  // Method pl/allegro/tech/hermes/api/TopicMetrics.access$102:(Lpl/allegro/tech/hermes/api/TopicMetrics;Ljava/lang/String;)Ljava/lang/String;
       8: pop
       9: aload_0
      10: areturn

  public pl.allegro.tech.hermes.api.TopicMetrics$Builder withDeliveryRate(java.lang.String);
    Code:
       0: aload_0
       1: getfield      #4                  // Field topicMetrics:Lpl/allegro/tech/hermes/api/TopicMetrics;
       4: aload_1
       5: invokestatic  #7                  // Method pl/allegro/tech/hermes/api/TopicMetrics.access$202:(Lpl/allegro/tech/hermes/api/TopicMetrics;Ljava/lang/String;)Ljava/lang/String;
       8: pop
       9: aload_0
      10: areturn

  public pl.allegro.tech.hermes.api.TopicMetrics$Builder withSubscriptions(int);
    Code:
       0: aload_0
       1: getfield      #4                  // Field topicMetrics:Lpl/allegro/tech/hermes/api/TopicMetrics;
       4: iload_1
       5: invokestatic  #8                  // Method pl/allegro/tech/hermes/api/TopicMetrics.access$302:(Lpl/allegro/tech/hermes/api/TopicMetrics;I)I
       8: pop
       9: aload_0
      10: areturn

  public static pl.allegro.tech.hermes.api.TopicMetrics$Builder topicMetrics();
    Code:
       0: new           #9                  // class pl/allegro/tech/hermes/api/TopicMetrics$Builder
       3: dup
       4: invokespecial #10                 // Method "<init>":()V
       7: areturn

  public pl.allegro.tech.hermes.api.TopicMetrics build();
    Code:
       0: aload_0
       1: getfield      #4                  // Field topicMetrics:Lpl/allegro/tech/hermes/api/TopicMetrics;
       4: areturn
}
