Compiled from "MessageType.java"
public final class org.piangles.gateway.MessageType extends java.lang.Enum<org.piangles.gateway.MessageType> {
  public static final org.piangles.gateway.MessageType Response;

  public static final org.piangles.gateway.MessageType Event;

  private static final org.piangles.gateway.MessageType[] $VALUES;

  public static org.piangles.gateway.MessageType[] values();
    Code:
       0: getstatic     #1                  // Field $VALUES:[Lorg/piangles/gateway/MessageType;
       3: invokevirtual #2                  // Method "[Lorg/piangles/gateway/MessageType;".clone:()Ljava/lang/Object;
       6: checkcast     #3                  // class "[Lorg/piangles/gateway/MessageType;"
       9: areturn

  public static org.piangles.gateway.MessageType valueOf(java.lang.String);
    Code:
       0: ldc           #4                  // class org/piangles/gateway/MessageType
       2: aload_0
       3: invokestatic  #5                  // Method java/lang/Enum.valueOf:(Ljava/lang/Class;Ljava/lang/String;)Ljava/lang/Enum;
       6: checkcast     #4                  // class org/piangles/gateway/MessageType
       9: areturn

  private org.piangles.gateway.MessageType();
    Code:
       0: aload_0
       1: aload_1
       2: iload_2
       3: invokespecial #6                  // Method java/lang/Enum."<init>":(Ljava/lang/String;I)V
       6: return

  static {};
    Code:
       0: new           #4                  // class org/piangles/gateway/MessageType
       3: dup
       4: ldc           #7                  // String Response
       6: iconst_0
       7: invokespecial #8                  // Method "<init>":(Ljava/lang/String;I)V
      10: putstatic     #9                  // Field Response:Lorg/piangles/gateway/MessageType;
      13: new           #4                  // class org/piangles/gateway/MessageType
      16: dup
      17: ldc           #10                 // String Event
      19: iconst_1
      20: invokespecial #8                  // Method "<init>":(Ljava/lang/String;I)V
      23: putstatic     #11                 // Field Event:Lorg/piangles/gateway/MessageType;
      26: iconst_2
      27: anewarray     #4                  // class org/piangles/gateway/MessageType
      30: dup
      31: iconst_0
      32: getstatic     #9                  // Field Response:Lorg/piangles/gateway/MessageType;
      35: aastore
      36: dup
      37: iconst_1
      38: getstatic     #11                 // Field Event:Lorg/piangles/gateway/MessageType;
      41: aastore
      42: putstatic     #1                  // Field $VALUES:[Lorg/piangles/gateway/MessageType;
      45: return
}
