Compiled from "EncryptedKeySha1SecurityTokenImpl.java"
public class org.apache.wss4j.stax.impl.securityToken.EncryptedKeySha1SecurityTokenImpl extends org.apache.xml.security.stax.impl.securityToken.AbstractInboundSecurityToken implements org.apache.wss4j.stax.securityToken.EncryptedKeySha1SecurityToken {
  private javax.security.auth.callback.CallbackHandler callbackHandler;

  public org.apache.wss4j.stax.impl.securityToken.EncryptedKeySha1SecurityTokenImpl(org.apache.wss4j.stax.ext.WSInboundSecurityContext, javax.security.auth.callback.CallbackHandler, java.lang.String, java.lang.String);
    Code:
       0: aload_0
       1: aload_1
       2: aload         4
       4: getstatic     #1                  // Field org/apache/wss4j/stax/securityToken/WSSecurityTokenConstants.KeyIdentifier_EncryptedKeySha1Identifier:Lorg/apache/xml/security/stax/securityToken/SecurityTokenConstants$KeyIdentifier;
       7: iconst_0
       8: invokespecial #2                  // Method org/apache/xml/security/stax/impl/securityToken/AbstractInboundSecurityToken."<init>":(Lorg/apache/xml/security/stax/ext/InboundSecurityContext;Ljava/lang/String;Lorg/apache/xml/security/stax/securityToken/SecurityTokenConstants$KeyIdentifier;Z)V
      11: aload_0
      12: aload_2
      13: putfield      #3                  // Field callbackHandler:Ljavax/security/auth/callback/CallbackHandler;
      16: aload_0
      17: aload_3
      18: invokevirtual #4                  // Method setSha1Identifier:(Ljava/lang/String;)V
      21: return

  public boolean isAsymmetric() throws org.apache.xml.security.exceptions.XMLSecurityException;
    Code:
       0: iconst_0
       1: ireturn

  protected java.security.Key getKey(java.lang.String, org.apache.xml.security.stax.ext.XMLSecurityConstants$AlgorithmUsage, java.lang.String) throws org.apache.xml.security.exceptions.XMLSecurityException;
    Code:
       0: aload_0
       1: invokevirtual #5                  // Method getSecretKey:()Ljava/util/Map;
       4: aload_1
       5: invokeinterface #6,  2            // InterfaceMethod java/util/Map.get:(Ljava/lang/Object;)Ljava/lang/Object;
      10: checkcast     #7                  // class java/security/Key
      13: astore        4
      15: aload         4
      17: ifnull        23
      20: aload         4
      22: areturn
      23: new           #8                  // class org/apache/wss4j/common/ext/WSPasswordCallback
      26: dup
      27: aload_0
      28: invokevirtual #9                  // Method getSha1Identifier:()Ljava/lang/String;
      31: aconst_null
      32: ldc           #10                 // String http://docs.oasis-open.org/wss/oasis-wss-soap-message-security-1.1#EncryptedKeySHA1
      34: bipush        9
      36: invokespecial #11                 // Method org/apache/wss4j/common/ext/WSPasswordCallback."<init>":(Ljava/lang/String;Ljava/lang/String;Ljava/lang/String;I)V
      39: astore        5
      41: aload_0
      42: getfield      #3                  // Field callbackHandler:Ljavax/security/auth/callback/CallbackHandler;
      45: aload         5
      47: aload_0
      48: invokevirtual #9                  // Method getSha1Identifier:()Ljava/lang/String;
      51: invokestatic  #12                 // Method org/apache/wss4j/stax/utils/WSSUtils.doSecretKeyCallback:(Ljavax/security/auth/callback/CallbackHandler;Ljavax/security/auth/callback/Callback;Ljava/lang/String;)V
      54: aload         5
      56: invokevirtual #13                 // Method org/apache/wss4j/common/ext/WSPasswordCallback.getKey:()[B
      59: ifnonnull     86
      62: new           #14                 // class org/apache/wss4j/common/ext/WSSecurityException
      65: dup
      66: getstatic     #15                 // Field org/apache/wss4j/common/ext/WSSecurityException$ErrorCode.FAILURE:Lorg/apache/wss4j/common/ext/WSSecurityException$ErrorCode;
      69: ldc           #16                 // String noKey
      71: iconst_1
      72: anewarray     #17                 // class java/lang/Object
      75: dup
      76: iconst_0
      77: aload_0
      78: invokevirtual #9                  // Method getSha1Identifier:()Ljava/lang/String;
      81: aastore
      82: invokespecial #18                 // Method org/apache/wss4j/common/ext/WSSecurityException."<init>":(Lorg/apache/wss4j/common/ext/WSSecurityException$ErrorCode;Ljava/lang/String;[Ljava/lang/Object;)V
      85: athrow
      86: aload_1
      87: invokestatic  #19                 // Method org/apache/xml/security/algorithms/JCEMapper.getJCEKeyAlgorithmFromURI:(Ljava/lang/String;)Ljava/lang/String;
      90: astore        6
      92: new           #20                 // class javax/crypto/spec/SecretKeySpec
      95: dup
      96: aload         5
      98: invokevirtual #13                 // Method org/apache/wss4j/common/ext/WSPasswordCallback.getKey:()[B
     101: aload         6
     103: invokespecial #21                 // Method javax/crypto/spec/SecretKeySpec."<init>":([BLjava/lang/String;)V
     106: astore        4
     108: aload_0
     109: aload_1
     110: aload         4
     112: invokevirtual #22                 // Method setSecretKey:(Ljava/lang/String;Ljava/security/Key;)V
     115: aload         4
     117: areturn

  public org.apache.xml.security.stax.securityToken.SecurityTokenConstants$TokenType getTokenType();
    Code:
       0: getstatic     #23                 // Field org/apache/wss4j/stax/securityToken/WSSecurityTokenConstants.EncryptedKeyToken:Lorg/apache/xml/security/stax/securityToken/SecurityTokenConstants$TokenType;
       3: areturn
}
