Compiled from "InitializationContextImpl.java"
public class org.infinispan.persistence.InitializationContextImpl implements org.infinispan.persistence.spi.InitializationContext {
  private final org.infinispan.configuration.cache.StoreConfiguration configuration;

  private final org.infinispan.Cache cache;

  private final org.infinispan.commons.marshall.StreamingMarshaller marshaller;

  private final org.infinispan.util.TimeService timeService;

  private final org.infinispan.commons.io.ByteBufferFactory byteBufferFactory;

  private final org.infinispan.marshall.core.MarshalledEntryFactory marshalledEntryFactory;

  public org.infinispan.persistence.InitializationContextImpl(org.infinispan.configuration.cache.StoreConfiguration, org.infinispan.Cache, org.infinispan.commons.marshall.StreamingMarshaller, org.infinispan.util.TimeService, org.infinispan.commons.io.ByteBufferFactory, org.infinispan.marshall.core.MarshalledEntryFactory);
    Code:
       0: aload_0
       1: invokespecial #1                  // Method java/lang/Object."<init>":()V
       4: aload_0
       5: aload_1
       6: putfield      #2                  // Field configuration:Lorg/infinispan/configuration/cache/StoreConfiguration;
       9: aload_0
      10: aload_2
      11: putfield      #3                  // Field cache:Lorg/infinispan/Cache;
      14: aload_0
      15: aload_3
      16: putfield      #4                  // Field marshaller:Lorg/infinispan/commons/marshall/StreamingMarshaller;
      19: aload_0
      20: aload         4
      22: putfield      #5                  // Field timeService:Lorg/infinispan/util/TimeService;
      25: aload_0
      26: aload         5
      28: putfield      #6                  // Field byteBufferFactory:Lorg/infinispan/commons/io/ByteBufferFactory;
      31: aload_0
      32: aload         6
      34: putfield      #7                  // Field marshalledEntryFactory:Lorg/infinispan/marshall/core/MarshalledEntryFactory;
      37: return

  public org.infinispan.configuration.cache.StoreConfiguration getConfiguration();
    Code:
       0: aload_0
       1: getfield      #2                  // Field configuration:Lorg/infinispan/configuration/cache/StoreConfiguration;
       4: areturn

  public org.infinispan.Cache getCache();
    Code:
       0: aload_0
       1: getfield      #3                  // Field cache:Lorg/infinispan/Cache;
       4: areturn

  public org.infinispan.commons.marshall.StreamingMarshaller getMarshaller();
    Code:
       0: aload_0
       1: getfield      #4                  // Field marshaller:Lorg/infinispan/commons/marshall/StreamingMarshaller;
       4: areturn

  public org.infinispan.util.TimeService getTimeService();
    Code:
       0: aload_0
       1: getfield      #5                  // Field timeService:Lorg/infinispan/util/TimeService;
       4: areturn

  public org.infinispan.commons.io.ByteBufferFactory getByteBufferFactory();
    Code:
       0: aload_0
       1: getfield      #6                  // Field byteBufferFactory:Lorg/infinispan/commons/io/ByteBufferFactory;
       4: areturn

  public org.infinispan.marshall.core.MarshalledEntryFactory getMarshalledEntryFactory();
    Code:
       0: aload_0
       1: getfield      #7                  // Field marshalledEntryFactory:Lorg/infinispan/marshall/core/MarshalledEntryFactory;
       4: areturn
}
