Compiled from "ReactiveWebServerInitializedEvent.java"
public class org.springframework.boot.web.reactive.context.ReactiveWebServerInitializedEvent extends org.springframework.boot.web.context.WebServerInitializedEvent {
  private final org.springframework.boot.web.reactive.context.ReactiveWebServerApplicationContext applicationContext;

  public org.springframework.boot.web.reactive.context.ReactiveWebServerInitializedEvent(org.springframework.boot.web.server.WebServer, org.springframework.boot.web.reactive.context.ReactiveWebServerApplicationContext);
    Code:
       0: aload_0
       1: aload_1
       2: invokespecial #1                  // Method org/springframework/boot/web/context/WebServerInitializedEvent."<init>":(Lorg/springframework/boot/web/server/WebServer;)V
       5: aload_0
       6: aload_2
       7: putfield      #2                  // Field applicationContext:Lorg/springframework/boot/web/reactive/context/ReactiveWebServerApplicationContext;
      10: return

  public org.springframework.boot.web.reactive.context.ReactiveWebServerApplicationContext getApplicationContext();
    Code:
       0: aload_0
       1: getfield      #2                  // Field applicationContext:Lorg/springframework/boot/web/reactive/context/ReactiveWebServerApplicationContext;
       4: areturn

  public org.springframework.boot.web.context.WebServerApplicationContext getApplicationContext();
    Code:
       0: aload_0
       1: invokevirtual #3                  // Method getApplicationContext:()Lorg/springframework/boot/web/reactive/context/ReactiveWebServerApplicationContext;
       4: areturn
}
