Compiled from "ApiDescriptionReader.java"
public class springfox.documentation.spring.web.scanners.ApiDescriptionReader {
  private final springfox.documentation.spring.web.readers.operation.OperationReader operationReader;

  private final springfox.documentation.spring.web.plugins.DocumentationPluginsManager pluginsManager;

  private final springfox.documentation.spring.web.scanners.ApiDescriptionLookup lookup;

  public springfox.documentation.spring.web.scanners.ApiDescriptionReader(springfox.documentation.spring.web.readers.operation.OperationReader, springfox.documentation.spring.web.plugins.DocumentationPluginsManager, springfox.documentation.spring.web.scanners.ApiDescriptionLookup);
    Code:
       0: aload_0
       1: invokespecial #1                  // Method java/lang/Object."<init>":()V
       4: aload_0
       5: aload_1
       6: putfield      #2                  // Field operationReader:Lspringfox/documentation/spring/web/readers/operation/OperationReader;
       9: aload_0
      10: aload_2
      11: putfield      #3                  // Field pluginsManager:Lspringfox/documentation/spring/web/plugins/DocumentationPluginsManager;
      14: aload_0
      15: aload_3
      16: putfield      #4                  // Field lookup:Lspringfox/documentation/spring/web/scanners/ApiDescriptionLookup;
      19: return

  public java.util.List<springfox.documentation.service.ApiDescription> read(springfox.documentation.spi.service.contexts.RequestMappingContext);
    Code:
       0: aload_1
       1: invokevirtual #5                  // Method springfox/documentation/spi/service/contexts/RequestMappingContext.getPatternsCondition:()Lorg/springframework/web/servlet/mvc/condition/PatternsRequestCondition;
       4: astore_2
       5: aload_1
       6: invokevirtual #6                  // Method springfox/documentation/spi/service/contexts/RequestMappingContext.getDocumentationContext:()Lspringfox/documentation/spi/service/contexts/DocumentationContext;
       9: invokevirtual #7                  // Method springfox/documentation/spi/service/contexts/DocumentationContext.getApiSelector:()Lspringfox/documentation/spi/service/contexts/ApiSelector;
      12: astore_3
      13: invokestatic  #8                  // Method com/google/common/collect/Lists.newArrayList:()Ljava/util/ArrayList;
      16: astore        4
      18: aload_0
      19: aload_3
      20: aload_2
      21: invokespecial #9                  // Method matchingPaths:(Lspringfox/documentation/spi/service/contexts/ApiSelector;Lorg/springframework/web/servlet/mvc/condition/PatternsRequestCondition;)Ljava/util/List;
      24: invokeinterface #10,  1           // InterfaceMethod java/util/List.iterator:()Ljava/util/Iterator;
      29: astore        5
      31: aload         5
      33: invokeinterface #11,  1           // InterfaceMethod java/util/Iterator.hasNext:()Z
      38: ifeq          177
      41: aload         5
      43: invokeinterface #12,  1           // InterfaceMethod java/util/Iterator.next:()Ljava/lang/Object;
      48: checkcast     #13                 // class java/lang/String
      51: astore        6
      53: aload_1
      54: invokevirtual #14                 // Method springfox/documentation/spi/service/contexts/RequestMappingContext.getName:()Ljava/lang/String;
      57: astore        7
      59: aload_1
      60: aload         6
      62: invokevirtual #15                 // Method springfox/documentation/spi/service/contexts/RequestMappingContext.copyPatternUsing:(Ljava/lang/String;)Lspringfox/documentation/spi/service/contexts/RequestMappingContext;
      65: astore        8
      67: aload_0
      68: getfield      #2                  // Field operationReader:Lspringfox/documentation/spring/web/readers/operation/OperationReader;
      71: aload         8
      73: invokeinterface #16,  2           // InterfaceMethod springfox/documentation/spring/web/readers/operation/OperationReader.read:(Lspringfox/documentation/spi/service/contexts/RequestMappingContext;)Ljava/util/List;
      78: astore        9
      80: aload         9
      82: invokeinterface #17,  1           // InterfaceMethod java/util/List.size:()I
      87: ifle          174
      90: aload         8
      92: invokevirtual #18                 // Method springfox/documentation/spi/service/contexts/RequestMappingContext.apiDescriptionBuilder:()Lspringfox/documentation/builders/ApiDescriptionBuilder;
      95: aload         9
      97: invokevirtual #19                 // Method springfox/documentation/builders/ApiDescriptionBuilder.operations:(Ljava/util/List;)Lspringfox/documentation/builders/ApiDescriptionBuilder;
     100: aload_0
     101: getfield      #3                  // Field pluginsManager:Lspringfox/documentation/spring/web/plugins/DocumentationPluginsManager;
     104: new           #20                 // class springfox/documentation/spi/service/contexts/PathContext
     107: dup
     108: aload_1
     109: aload         9
     111: invokestatic  #21                 // Method com/google/common/collect/FluentIterable.from:(Ljava/lang/Iterable;)Lcom/google/common/collect/FluentIterable;
     114: invokevirtual #22                 // Method com/google/common/collect/FluentIterable.first:()Lcom/google/common/base/Optional;
     117: invokespecial #23                 // Method springfox/documentation/spi/service/contexts/PathContext."<init>":(Lspringfox/documentation/spi/service/contexts/RequestMappingContext;Lcom/google/common/base/Optional;)V
     120: invokevirtual #24                 // Method springfox/documentation/spring/web/plugins/DocumentationPluginsManager.decorator:(Lspringfox/documentation/spi/service/contexts/PathContext;)Lcom/google/common/base/Function;
     123: invokevirtual #25                 // Method springfox/documentation/builders/ApiDescriptionBuilder.pathDecorator:(Lcom/google/common/base/Function;)Lspringfox/documentation/builders/ApiDescriptionBuilder;
     126: aload         6
     128: invokevirtual #26                 // Method springfox/documentation/builders/ApiDescriptionBuilder.path:(Ljava/lang/String;)Lspringfox/documentation/builders/ApiDescriptionBuilder;
     131: aload         7
     133: invokevirtual #27                 // Method springfox/documentation/builders/ApiDescriptionBuilder.description:(Ljava/lang/String;)Lspringfox/documentation/builders/ApiDescriptionBuilder;
     136: iconst_0
     137: invokevirtual #28                 // Method springfox/documentation/builders/ApiDescriptionBuilder.hidden:(Z)Lspringfox/documentation/builders/ApiDescriptionBuilder;
     140: pop
     141: aload         8
     143: invokevirtual #18                 // Method springfox/documentation/spi/service/contexts/RequestMappingContext.apiDescriptionBuilder:()Lspringfox/documentation/builders/ApiDescriptionBuilder;
     146: invokevirtual #29                 // Method springfox/documentation/builders/ApiDescriptionBuilder.build:()Lspringfox/documentation/service/ApiDescription;
     149: astore        10
     151: aload_0
     152: getfield      #4                  // Field lookup:Lspringfox/documentation/spring/web/scanners/ApiDescriptionLookup;
     155: aload_1
     156: invokevirtual #30                 // Method springfox/documentation/spi/service/contexts/RequestMappingContext.key:()Lspringfox/documentation/RequestHandlerKey;
     159: aload         10
     161: invokevirtual #31                 // Method springfox/documentation/spring/web/scanners/ApiDescriptionLookup.add:(Lspringfox/documentation/RequestHandlerKey;Lspringfox/documentation/service/ApiDescription;)V
     164: aload         4
     166: aload         10
     168: invokeinterface #32,  2           // InterfaceMethod java/util/List.add:(Ljava/lang/Object;)Z
     173: pop
     174: goto          31
     177: aload         4
     179: areturn

  private java.util.List<java.lang.String> matchingPaths(springfox.documentation.spi.service.contexts.ApiSelector, org.springframework.web.servlet.mvc.condition.PatternsRequestCondition);
    Code:
       0: invokestatic  #33                 // Method com/google/common/collect/Ordering.natural:()Lcom/google/common/collect/Ordering;
       3: aload_2
       4: invokevirtual #34                 // Method org/springframework/web/servlet/mvc/condition/PatternsRequestCondition.getPatterns:()Ljava/util/Set;
       7: invokestatic  #21                 // Method com/google/common/collect/FluentIterable.from:(Ljava/lang/Iterable;)Lcom/google/common/collect/FluentIterable;
      10: aload_1
      11: invokevirtual #35                 // Method springfox/documentation/spi/service/contexts/ApiSelector.getPathSelector:()Lcom/google/common/base/Predicate;
      14: invokevirtual #36                 // Method com/google/common/collect/FluentIterable.filter:(Lcom/google/common/base/Predicate;)Lcom/google/common/collect/FluentIterable;
      17: invokevirtual #37                 // Method com/google/common/collect/Ordering.sortedCopy:(Ljava/lang/Iterable;)Ljava/util/List;
      20: areturn
}
