Compiled from "AbstractEpollChannel.java"
class io.netty.channel.epoll.AbstractEpollChannel$AbstractEpollUnsafe$1 implements java.lang.Runnable {
  final io.netty.channel.epoll.AbstractEpollChannel$AbstractEpollUnsafe this$1;

  io.netty.channel.epoll.AbstractEpollChannel$AbstractEpollUnsafe$1(io.netty.channel.epoll.AbstractEpollChannel$AbstractEpollUnsafe);
    Code:
       0: aload_0
       1: aload_1
       2: putfield      #1                  // Field this$1:Lio/netty/channel/epoll/AbstractEpollChannel$AbstractEpollUnsafe;
       5: aload_0
       6: invokespecial #2                  // Method java/lang/Object."<init>":()V
       9: return

  public void run();
    Code:
       0: aload_0
       1: getfield      #1                  // Field this$1:Lio/netty/channel/epoll/AbstractEpollChannel$AbstractEpollUnsafe;
       4: getfield      #3                  // Field io/netty/channel/epoll/AbstractEpollChannel$AbstractEpollUnsafe.this$0:Lio/netty/channel/epoll/AbstractEpollChannel;
       7: iconst_0
       8: putfield      #4                  // Field io/netty/channel/epoll/AbstractEpollChannel.epollInReadyRunnablePending:Z
      11: aload_0
      12: getfield      #1                  // Field this$1:Lio/netty/channel/epoll/AbstractEpollChannel$AbstractEpollUnsafe;
      15: invokevirtual #5                  // Method io/netty/channel/epoll/AbstractEpollChannel$AbstractEpollUnsafe.epollInReady:()V
      18: return
}
