Compiled from "NestableGroup.java"
class org.jboss.security.NestableGroup$IndexEnumeration<T extends java.security.Principal> implements java.util.Enumeration<java.security.Principal> {
  private java.util.Enumeration<? extends java.security.Principal> iter;

  final org.jboss.security.NestableGroup this$0;

  org.jboss.security.NestableGroup$IndexEnumeration(org.jboss.security.NestableGroup);
    Code:
       0: aload_0
       1: aload_1
       2: putfield      #1                  // Field this$0:Lorg/jboss/security/NestableGroup;
       5: aload_0
       6: invokespecial #2                  // Method java/lang/Object."<init>":()V
       9: aload_1
      10: invokestatic  #3                  // Method org/jboss/security/NestableGroup.access$000:(Lorg/jboss/security/NestableGroup;)Ljava/util/LinkedList;
      13: invokevirtual #4                  // Method java/util/LinkedList.size:()I
      16: ifle          41
      19: aload_1
      20: invokestatic  #3                  // Method org/jboss/security/NestableGroup.access$000:(Lorg/jboss/security/NestableGroup;)Ljava/util/LinkedList;
      23: iconst_0
      24: invokevirtual #5                  // Method java/util/LinkedList.get:(I)Ljava/lang/Object;
      27: checkcast     #6                  // class java/security/acl/Group
      30: astore_2
      31: aload_0
      32: aload_2
      33: invokeinterface #7,  1            // InterfaceMethod java/security/acl/Group.members:()Ljava/util/Enumeration;
      38: putfield      #8                  // Field iter:Ljava/util/Enumeration;
      41: return

  public boolean hasMoreElements();
    Code:
       0: aload_0
       1: getfield      #8                  // Field iter:Ljava/util/Enumeration;
       4: ifnull        23
       7: aload_0
       8: getfield      #8                  // Field iter:Ljava/util/Enumeration;
      11: invokeinterface #9,  1            // InterfaceMethod java/util/Enumeration.hasMoreElements:()Z
      16: ifeq          23
      19: iconst_1
      20: goto          24
      23: iconst_0
      24: istore_1
      25: iload_1
      26: ireturn

  public java.security.Principal nextElement();
    Code:
       0: aconst_null
       1: astore_1
       2: aload_0
       3: getfield      #8                  // Field iter:Ljava/util/Enumeration;
       6: ifnull        22
       9: aload_0
      10: getfield      #8                  // Field iter:Ljava/util/Enumeration;
      13: invokeinterface #10,  1           // InterfaceMethod java/util/Enumeration.nextElement:()Ljava/lang/Object;
      18: checkcast     #11                 // class java/security/Principal
      21: astore_1
      22: aload_1
      23: areturn

  public java.lang.Object nextElement();
    Code:
       0: aload_0
       1: invokevirtual #12                 // Method nextElement:()Ljava/security/Principal;
       4: areturn
}
