Compiled from "RunAsIdentity.java"
public class org.jboss.security.RunAsIdentity extends org.jboss.security.SimplePrincipal implements java.lang.Cloneable,org.jboss.security.RunAs {
  private static final long serialVersionUID;

  private java.util.HashSet<java.security.Principal> runAsRoles;

  private java.util.HashSet<java.security.Principal> principalsSet;

  private static final java.lang.String ANOYMOUS_PRINCIPAL;

  public org.jboss.security.RunAsIdentity(java.lang.String, java.lang.String);
    Code:
       0: aload_0
       1: aload_2
       2: ifnull        9
       5: aload_2
       6: goto          12
       9: getstatic     #1                  // Field ANOYMOUS_PRINCIPAL:Ljava/lang/String;
      12: invokespecial #2                  // Method org/jboss/security/SimplePrincipal."<init>":(Ljava/lang/String;)V
      15: aload_0
      16: new           #3                  // class java/util/HashSet
      19: dup
      20: invokespecial #4                  // Method java/util/HashSet."<init>":()V
      23: putfield      #5                  // Field runAsRoles:Ljava/util/HashSet;
      26: aload_1
      27: ifnonnull     41
      30: getstatic     #6                  // Field org/jboss/security/PicketBoxMessages.MESSAGES:Lorg/jboss/security/PicketBoxMessages;
      33: ldc           #7                  // String roleName
      35: invokeinterface #8,  2            // InterfaceMethod org/jboss/security/PicketBoxMessages.invalidNullArgument:(Ljava/lang/String;)Ljava/lang/IllegalArgumentException;
      40: athrow
      41: aload_0
      42: getfield      #5                  // Field runAsRoles:Ljava/util/HashSet;
      45: new           #9                  // class org/jboss/security/SimplePrincipal
      48: dup
      49: aload_1
      50: invokespecial #2                  // Method org/jboss/security/SimplePrincipal."<init>":(Ljava/lang/String;)V
      53: invokevirtual #10                 // Method java/util/HashSet.add:(Ljava/lang/Object;)Z
      56: pop
      57: return

  public org.jboss.security.RunAsIdentity(java.lang.String, java.lang.String, java.util.Set<java.lang.String>);
    Code:
       0: aload_0
       1: aload_1
       2: aload_2
       3: invokespecial #11                 // Method "<init>":(Ljava/lang/String;Ljava/lang/String;)V
       6: aload_3
       7: ifnull        60
      10: aload_3
      11: invokeinterface #12,  1           // InterfaceMethod java/util/Set.iterator:()Ljava/util/Iterator;
      16: astore        4
      18: aload         4
      20: invokeinterface #13,  1           // InterfaceMethod java/util/Iterator.hasNext:()Z
      25: ifeq          60
      28: aload         4
      30: invokeinterface #14,  1           // InterfaceMethod java/util/Iterator.next:()Ljava/lang/Object;
      35: checkcast     #15                 // class java/lang/String
      38: astore        5
      40: aload_0
      41: getfield      #5                  // Field runAsRoles:Ljava/util/HashSet;
      44: new           #9                  // class org/jboss/security/SimplePrincipal
      47: dup
      48: aload         5
      50: invokespecial #2                  // Method org/jboss/security/SimplePrincipal."<init>":(Ljava/lang/String;)V
      53: invokevirtual #10                 // Method java/util/HashSet.add:(Ljava/lang/Object;)Z
      56: pop
      57: goto          18
      60: return

  public java.util.Set<java.security.Principal> getRunAsRoles();
    Code:
       0: new           #3                  // class java/util/HashSet
       3: dup
       4: aload_0
       5: getfield      #5                  // Field runAsRoles:Ljava/util/HashSet;
       8: invokespecial #16                 // Method java/util/HashSet."<init>":(Ljava/util/Collection;)V
      11: areturn

  public org.jboss.security.identity.RoleGroup getRunAsRolesAsRoleGroup();
    Code:
       0: new           #17                 // class org/jboss/security/identity/plugins/SimpleRoleGroup
       3: dup
       4: aload_0
       5: getfield      #5                  // Field runAsRoles:Ljava/util/HashSet;
       8: invokespecial #18                 // Method org/jboss/security/identity/plugins/SimpleRoleGroup."<init>":(Ljava/util/Set;)V
      11: areturn

  public synchronized java.util.Set<java.security.Principal> getPrincipalsSet();
    Code:
       0: aload_0
       1: getfield      #19                 // Field principalsSet:Ljava/util/HashSet;
       4: ifnonnull     82
       7: aload_0
       8: new           #3                  // class java/util/HashSet
      11: dup
      12: invokespecial #4                  // Method java/util/HashSet."<init>":()V
      15: putfield      #19                 // Field principalsSet:Ljava/util/HashSet;
      18: aload_0
      19: getfield      #19                 // Field principalsSet:Ljava/util/HashSet;
      22: aload_0
      23: invokevirtual #10                 // Method java/util/HashSet.add:(Ljava/lang/Object;)Z
      26: pop
      27: new           #20                 // class org/jboss/security/SimpleGroup
      30: dup
      31: ldc           #21                 // String Roles
      33: invokespecial #22                 // Method org/jboss/security/SimpleGroup."<init>":(Ljava/lang/String;)V
      36: astore_1
      37: aload_0
      38: getfield      #19                 // Field principalsSet:Ljava/util/HashSet;
      41: aload_1
      42: invokevirtual #10                 // Method java/util/HashSet.add:(Ljava/lang/Object;)Z
      45: pop
      46: aload_0
      47: getfield      #5                  // Field runAsRoles:Ljava/util/HashSet;
      50: invokevirtual #23                 // Method java/util/HashSet.iterator:()Ljava/util/Iterator;
      53: astore_2
      54: aload_2
      55: invokeinterface #13,  1           // InterfaceMethod java/util/Iterator.hasNext:()Z
      60: ifeq          82
      63: aload_2
      64: invokeinterface #14,  1           // InterfaceMethod java/util/Iterator.next:()Ljava/lang/Object;
      69: checkcast     #24                 // class java/security/Principal
      72: astore_3
      73: aload_1
      74: aload_3
      75: invokevirtual #25                 // Method org/jboss/security/SimpleGroup.addMember:(Ljava/security/Principal;)Z
      78: pop
      79: goto          54
      82: aload_0
      83: getfield      #19                 // Field principalsSet:Ljava/util/HashSet;
      86: areturn

  public boolean doesUserHaveRole(java.security.Principal);
    Code:
       0: aload_0
       1: getfield      #5                  // Field runAsRoles:Ljava/util/HashSet;
       4: aload_1
       5: invokevirtual #26                 // Method java/util/HashSet.contains:(Ljava/lang/Object;)Z
       8: ireturn

  public boolean doesUserHaveRole(java.util.Set<java.security.Principal>);
    Code:
       0: aload_1
       1: invokeinterface #12,  1           // InterfaceMethod java/util/Set.iterator:()Ljava/util/Iterator;
       6: astore_2
       7: aload_2
       8: invokeinterface #13,  1           // InterfaceMethod java/util/Iterator.hasNext:()Z
      13: ifeq          39
      16: aload_2
      17: invokeinterface #14,  1           // InterfaceMethod java/util/Iterator.next:()Ljava/lang/Object;
      22: checkcast     #24                 // class java/security/Principal
      25: astore_3
      26: aload_0
      27: aload_3
      28: invokevirtual #27                 // Method doesUserHaveRole:(Ljava/security/Principal;)Z
      31: ifeq          36
      34: iconst_1
      35: ireturn
      36: goto          7
      39: iconst_0
      40: ireturn

  public java.lang.String toString();
    Code:
       0: new           #28                 // class java/lang/StringBuilder
       3: dup
       4: invokespecial #29                 // Method java/lang/StringBuilder."<init>":()V
       7: ldc           #30                 // String [roles=
       9: invokevirtual #31                 // Method java/lang/StringBuilder.append:(Ljava/lang/String;)Ljava/lang/StringBuilder;
      12: aload_0
      13: getfield      #5                  // Field runAsRoles:Ljava/util/HashSet;
      16: invokevirtual #32                 // Method java/lang/StringBuilder.append:(Ljava/lang/Object;)Ljava/lang/StringBuilder;
      19: ldc           #33                 // String ,principal=
      21: invokevirtual #31                 // Method java/lang/StringBuilder.append:(Ljava/lang/String;)Ljava/lang/StringBuilder;
      24: aload_0
      25: invokevirtual #34                 // Method getName:()Ljava/lang/String;
      28: invokevirtual #31                 // Method java/lang/StringBuilder.append:(Ljava/lang/String;)Ljava/lang/StringBuilder;
      31: ldc           #35                 // String ]
      33: invokevirtual #31                 // Method java/lang/StringBuilder.append:(Ljava/lang/String;)Ljava/lang/StringBuilder;
      36: invokevirtual #36                 // Method java/lang/StringBuilder.toString:()Ljava/lang/String;
      39: areturn

  public synchronized java.lang.Object clone() throws java.lang.CloneNotSupportedException;
    Code:
       0: aload_0
       1: invokespecial #37                 // Method java/lang/Object.clone:()Ljava/lang/Object;
       4: checkcast     #38                 // class org/jboss/security/RunAsIdentity
       7: astore_1
       8: aload_1
       9: ifnull        51
      12: aload_1
      13: aload_0
      14: getfield      #19                 // Field principalsSet:Ljava/util/HashSet;
      17: ifnull        33
      20: aload_0
      21: getfield      #19                 // Field principalsSet:Ljava/util/HashSet;
      24: invokevirtual #39                 // Method java/util/HashSet.clone:()Ljava/lang/Object;
      27: checkcast     #3                  // class java/util/HashSet
      30: goto          34
      33: aconst_null
      34: putfield      #19                 // Field principalsSet:Ljava/util/HashSet;
      37: aload_1
      38: aload_0
      39: getfield      #5                  // Field runAsRoles:Ljava/util/HashSet;
      42: invokevirtual #39                 // Method java/util/HashSet.clone:()Ljava/lang/Object;
      45: checkcast     #3                  // class java/util/HashSet
      48: putfield      #5                  // Field runAsRoles:Ljava/util/HashSet;
      51: aload_1
      52: areturn

  public <T> T getIdentity();
    Code:
       0: aload_0
       1: invokevirtual #34                 // Method getName:()Ljava/lang/String;
       4: areturn

  public <T> T getProof();
    Code:
       0: ldc           #41                 // String JavaEE
       2: areturn
}
