Compiled from "SecurityUtil.java"
public class org.jboss.security.SecurityUtil {
  private static java.lang.String LEGACY_JAAS_CONTEXT_ROOT;

  public org.jboss.security.SecurityUtil();
    Code:
       0: aload_0
       1: invokespecial #1                  // Method java/lang/Object."<init>":()V
       4: return

  public static java.lang.String unprefixSecurityDomain(java.lang.String);
    Code:
       0: aconst_null
       1: astore_1
       2: aload_0
       3: ifnull        76
       6: aload_0
       7: ldc           #3                  // String java:jboss/jaas/
       9: invokevirtual #4                  // Method java/lang/String.startsWith:(Ljava/lang/String;)Z
      12: ifeq          28
      15: aload_0
      16: ldc           #3                  // String java:jboss/jaas/
      18: invokevirtual #5                  // Method java/lang/String.length:()I
      21: invokevirtual #6                  // Method java/lang/String.substring:(I)Ljava/lang/String;
      24: astore_1
      25: goto          76
      28: aload_0
      29: ldc           #7                  // String java:jboss/jbsx/
      31: invokevirtual #4                  // Method java/lang/String.startsWith:(Ljava/lang/String;)Z
      34: ifeq          50
      37: aload_0
      38: ldc           #7                  // String java:jboss/jbsx/
      40: invokevirtual #5                  // Method java/lang/String.length:()I
      43: invokevirtual #6                  // Method java/lang/String.substring:(I)Ljava/lang/String;
      46: astore_1
      47: goto          76
      50: aload_0
      51: getstatic     #8                  // Field LEGACY_JAAS_CONTEXT_ROOT:Ljava/lang/String;
      54: invokevirtual #4                  // Method java/lang/String.startsWith:(Ljava/lang/String;)Z
      57: ifeq          74
      60: aload_0
      61: getstatic     #8                  // Field LEGACY_JAAS_CONTEXT_ROOT:Ljava/lang/String;
      64: invokevirtual #5                  // Method java/lang/String.length:()I
      67: invokevirtual #6                  // Method java/lang/String.substring:(I)Ljava/lang/String;
      70: astore_1
      71: goto          76
      74: aload_0
      75: astore_1
      76: aload_1
      77: areturn

  public static java.security.acl.Group getSubjectRoles(javax.security.auth.Subject);
    Code:
       0: aload_0
       1: ifnonnull     15
       4: getstatic     #9                  // Field org/jboss/security/PicketBoxMessages.MESSAGES:Lorg/jboss/security/PicketBoxMessages;
       7: ldc           #10                 // String theSubject
       9: invokeinterface #11,  2           // InterfaceMethod org/jboss/security/PicketBoxMessages.invalidNullArgument:(Ljava/lang/String;)Ljava/lang/IllegalArgumentException;
      14: athrow
      15: aload_0
      16: ldc           #12                 // class java/security/acl/Group
      18: invokevirtual #13                 // Method javax/security/auth/Subject.getPrincipals:(Ljava/lang/Class;)Ljava/util/Set;
      21: astore_1
      22: aload_1
      23: invokeinterface #14,  1           // InterfaceMethod java/util/Set.iterator:()Ljava/util/Iterator;
      28: astore_2
      29: aconst_null
      30: astore_3
      31: aload_2
      32: invokeinterface #15,  1           // InterfaceMethod java/util/Iterator.hasNext:()Z
      37: ifeq          76
      40: aload_2
      41: invokeinterface #16,  1           // InterfaceMethod java/util/Iterator.next:()Ljava/lang/Object;
      46: checkcast     #12                 // class java/security/acl/Group
      49: astore        4
      51: aload         4
      53: invokeinterface #17,  1           // InterfaceMethod java/security/acl/Group.getName:()Ljava/lang/String;
      58: astore        5
      60: aload         5
      62: ldc           #18                 // String Roles
      64: invokevirtual #19                 // Method java/lang/String.equals:(Ljava/lang/Object;)Z
      67: ifeq          73
      70: aload         4
      72: astore_3
      73: goto          31
      76: aload_3
      77: areturn

  public static org.jboss.security.config.ApplicationPolicy getApplicationPolicy(java.lang.String);
    Code:
       0: aload_0
       1: invokestatic  #20                 // Method org/jboss/security/config/SecurityConfiguration.getApplicationPolicy:(Ljava/lang/String;)Lorg/jboss/security/config/ApplicationPolicy;
       4: areturn

  public static org.jboss.security.AuthenticationManager getAuthenticationManager(java.lang.String, java.lang.String);
    Code:
       0: ldc           #21                 // String /securityMgr
       2: astore_2
       3: aconst_null
       4: astore_3
       5: aload_0
       6: aload_1
       7: invokevirtual #4                  // Method java/lang/String.startsWith:(Ljava/lang/String;)Z
      10: ifeq          35
      13: new           #22                 // class java/lang/StringBuilder
      16: dup
      17: invokespecial #23                 // Method java/lang/StringBuilder."<init>":()V
      20: aload_0
      21: invokevirtual #24                 // Method java/lang/StringBuilder.append:(Ljava/lang/String;)Ljava/lang/StringBuilder;
      24: aload_2
      25: invokevirtual #24                 // Method java/lang/StringBuilder.append:(Ljava/lang/String;)Ljava/lang/StringBuilder;
      28: invokevirtual #25                 // Method java/lang/StringBuilder.toString:()Ljava/lang/String;
      31: astore_3
      32: goto          63
      35: new           #22                 // class java/lang/StringBuilder
      38: dup
      39: invokespecial #23                 // Method java/lang/StringBuilder."<init>":()V
      42: aload_1
      43: invokevirtual #24                 // Method java/lang/StringBuilder.append:(Ljava/lang/String;)Ljava/lang/StringBuilder;
      46: ldc           #26                 // String /
      48: invokevirtual #24                 // Method java/lang/StringBuilder.append:(Ljava/lang/String;)Ljava/lang/StringBuilder;
      51: aload_0
      52: invokevirtual #24                 // Method java/lang/StringBuilder.append:(Ljava/lang/String;)Ljava/lang/StringBuilder;
      55: aload_2
      56: invokevirtual #24                 // Method java/lang/StringBuilder.append:(Ljava/lang/String;)Ljava/lang/StringBuilder;
      59: invokevirtual #25                 // Method java/lang/StringBuilder.toString:()Ljava/lang/String;
      62: astore_3
      63: aconst_null
      64: astore        4
      66: new           #27                 // class javax/naming/InitialContext
      69: dup
      70: invokespecial #28                 // Method javax/naming/InitialContext."<init>":()V
      73: astore        5
      75: aload         5
      77: aload_3
      78: invokevirtual #29                 // Method javax/naming/InitialContext.lookup:(Ljava/lang/String;)Ljava/lang/Object;
      81: checkcast     #30                 // class org/jboss/security/AuthenticationManager
      84: astore        4
      86: goto          101
      89: astore        5
      91: getstatic     #32                 // Field org/jboss/security/PicketBoxLogger.LOGGER:Lorg/jboss/security/PicketBoxLogger;
      94: aload         5
      96: invokeinterface #33,  2           // InterfaceMethod org/jboss/security/PicketBoxLogger.debugIgnoredException:(Ljava/lang/Throwable;)V
     101: aload         4
     103: areturn
    Exception table:
       from    to  target type
          66    86    89   Class java/lang/Exception

  public static org.jboss.security.AuthorizationManager getAuthorizationManager(java.lang.String, java.lang.String);
    Code:
       0: ldc           #34                 // String /authorizationMgr
       2: astore_2
       3: aconst_null
       4: astore_3
       5: aload_0
       6: aload_1
       7: invokevirtual #4                  // Method java/lang/String.startsWith:(Ljava/lang/String;)Z
      10: ifeq          35
      13: new           #22                 // class java/lang/StringBuilder
      16: dup
      17: invokespecial #23                 // Method java/lang/StringBuilder."<init>":()V
      20: aload_0
      21: invokevirtual #24                 // Method java/lang/StringBuilder.append:(Ljava/lang/String;)Ljava/lang/StringBuilder;
      24: aload_2
      25: invokevirtual #24                 // Method java/lang/StringBuilder.append:(Ljava/lang/String;)Ljava/lang/StringBuilder;
      28: invokevirtual #25                 // Method java/lang/StringBuilder.toString:()Ljava/lang/String;
      31: astore_3
      32: goto          63
      35: new           #22                 // class java/lang/StringBuilder
      38: dup
      39: invokespecial #23                 // Method java/lang/StringBuilder."<init>":()V
      42: aload_1
      43: invokevirtual #24                 // Method java/lang/StringBuilder.append:(Ljava/lang/String;)Ljava/lang/StringBuilder;
      46: ldc           #26                 // String /
      48: invokevirtual #24                 // Method java/lang/StringBuilder.append:(Ljava/lang/String;)Ljava/lang/StringBuilder;
      51: aload_0
      52: invokevirtual #24                 // Method java/lang/StringBuilder.append:(Ljava/lang/String;)Ljava/lang/StringBuilder;
      55: aload_2
      56: invokevirtual #24                 // Method java/lang/StringBuilder.append:(Ljava/lang/String;)Ljava/lang/StringBuilder;
      59: invokevirtual #25                 // Method java/lang/StringBuilder.toString:()Ljava/lang/String;
      62: astore_3
      63: aconst_null
      64: astore        4
      66: new           #27                 // class javax/naming/InitialContext
      69: dup
      70: invokespecial #28                 // Method javax/naming/InitialContext."<init>":()V
      73: astore        5
      75: aload         5
      77: aload_3
      78: invokevirtual #29                 // Method javax/naming/InitialContext.lookup:(Ljava/lang/String;)Ljava/lang/Object;
      81: checkcast     #35                 // class org/jboss/security/AuthorizationManager
      84: astore        4
      86: goto          101
      89: astore        5
      91: getstatic     #32                 // Field org/jboss/security/PicketBoxLogger.LOGGER:Lorg/jboss/security/PicketBoxLogger;
      94: aload         5
      96: invokeinterface #33,  2           // InterfaceMethod org/jboss/security/PicketBoxLogger.debugIgnoredException:(Ljava/lang/Throwable;)V
     101: aload         4
     103: areturn
    Exception table:
       from    to  target type
          66    86    89   Class java/lang/Exception

  public static org.jboss.security.audit.AuditManager getAuditManager(java.lang.String, java.lang.String);
    Code:
       0: ldc           #36                 // String /auditMgr
       2: astore_2
       3: aconst_null
       4: astore_3
       5: aload_0
       6: aload_1
       7: invokevirtual #4                  // Method java/lang/String.startsWith:(Ljava/lang/String;)Z
      10: ifeq          35
      13: new           #22                 // class java/lang/StringBuilder
      16: dup
      17: invokespecial #23                 // Method java/lang/StringBuilder."<init>":()V
      20: aload_0
      21: invokevirtual #24                 // Method java/lang/StringBuilder.append:(Ljava/lang/String;)Ljava/lang/StringBuilder;
      24: aload_2
      25: invokevirtual #24                 // Method java/lang/StringBuilder.append:(Ljava/lang/String;)Ljava/lang/StringBuilder;
      28: invokevirtual #25                 // Method java/lang/StringBuilder.toString:()Ljava/lang/String;
      31: astore_3
      32: goto          63
      35: new           #22                 // class java/lang/StringBuilder
      38: dup
      39: invokespecial #23                 // Method java/lang/StringBuilder."<init>":()V
      42: aload_1
      43: invokevirtual #24                 // Method java/lang/StringBuilder.append:(Ljava/lang/String;)Ljava/lang/StringBuilder;
      46: ldc           #26                 // String /
      48: invokevirtual #24                 // Method java/lang/StringBuilder.append:(Ljava/lang/String;)Ljava/lang/StringBuilder;
      51: aload_0
      52: invokevirtual #24                 // Method java/lang/StringBuilder.append:(Ljava/lang/String;)Ljava/lang/StringBuilder;
      55: aload_2
      56: invokevirtual #24                 // Method java/lang/StringBuilder.append:(Ljava/lang/String;)Ljava/lang/StringBuilder;
      59: invokevirtual #25                 // Method java/lang/StringBuilder.toString:()Ljava/lang/String;
      62: astore_3
      63: aconst_null
      64: astore        4
      66: new           #27                 // class javax/naming/InitialContext
      69: dup
      70: invokespecial #28                 // Method javax/naming/InitialContext."<init>":()V
      73: astore        5
      75: aload         5
      77: aload_3
      78: invokevirtual #29                 // Method javax/naming/InitialContext.lookup:(Ljava/lang/String;)Ljava/lang/Object;
      81: checkcast     #37                 // class org/jboss/security/audit/AuditManager
      84: astore        4
      86: goto          101
      89: astore        5
      91: getstatic     #32                 // Field org/jboss/security/PicketBoxLogger.LOGGER:Lorg/jboss/security/PicketBoxLogger;
      94: aload         5
      96: invokeinterface #33,  2           // InterfaceMethod org/jboss/security/PicketBoxLogger.debugIgnoredException:(Ljava/lang/Throwable;)V
     101: aload         4
     103: areturn
    Exception table:
       from    to  target type
          66    86    89   Class java/lang/Exception

  public static org.jboss.security.identitytrust.IdentityTrustManager getIdentityTrustManager(java.lang.String, java.lang.String);
    Code:
       0: ldc           #38                 // String /identityTrustMgr
       2: astore_2
       3: aconst_null
       4: astore_3
       5: aload_0
       6: aload_1
       7: invokevirtual #4                  // Method java/lang/String.startsWith:(Ljava/lang/String;)Z
      10: ifeq          35
      13: new           #22                 // class java/lang/StringBuilder
      16: dup
      17: invokespecial #23                 // Method java/lang/StringBuilder."<init>":()V
      20: aload_0
      21: invokevirtual #24                 // Method java/lang/StringBuilder.append:(Ljava/lang/String;)Ljava/lang/StringBuilder;
      24: aload_2
      25: invokevirtual #24                 // Method java/lang/StringBuilder.append:(Ljava/lang/String;)Ljava/lang/StringBuilder;
      28: invokevirtual #25                 // Method java/lang/StringBuilder.toString:()Ljava/lang/String;
      31: astore_3
      32: goto          63
      35: new           #22                 // class java/lang/StringBuilder
      38: dup
      39: invokespecial #23                 // Method java/lang/StringBuilder."<init>":()V
      42: aload_1
      43: invokevirtual #24                 // Method java/lang/StringBuilder.append:(Ljava/lang/String;)Ljava/lang/StringBuilder;
      46: ldc           #26                 // String /
      48: invokevirtual #24                 // Method java/lang/StringBuilder.append:(Ljava/lang/String;)Ljava/lang/StringBuilder;
      51: aload_0
      52: invokevirtual #24                 // Method java/lang/StringBuilder.append:(Ljava/lang/String;)Ljava/lang/StringBuilder;
      55: aload_2
      56: invokevirtual #24                 // Method java/lang/StringBuilder.append:(Ljava/lang/String;)Ljava/lang/StringBuilder;
      59: invokevirtual #25                 // Method java/lang/StringBuilder.toString:()Ljava/lang/String;
      62: astore_3
      63: aconst_null
      64: astore        4
      66: new           #27                 // class javax/naming/InitialContext
      69: dup
      70: invokespecial #28                 // Method javax/naming/InitialContext."<init>":()V
      73: astore        5
      75: aload         5
      77: aload_3
      78: invokevirtual #29                 // Method javax/naming/InitialContext.lookup:(Ljava/lang/String;)Ljava/lang/Object;
      81: checkcast     #39                 // class org/jboss/security/identitytrust/IdentityTrustManager
      84: astore        4
      86: goto          101
      89: astore        5
      91: getstatic     #32                 // Field org/jboss/security/PicketBoxLogger.LOGGER:Lorg/jboss/security/PicketBoxLogger;
      94: aload         5
      96: invokeinterface #33,  2           // InterfaceMethod org/jboss/security/PicketBoxLogger.debugIgnoredException:(Ljava/lang/Throwable;)V
     101: aload         4
     103: areturn
    Exception table:
       from    to  target type
          66    86    89   Class java/lang/Exception

  public static org.jboss.security.mapping.MappingManager getMappingManager(java.lang.String, java.lang.String);
    Code:
       0: ldc           #40                 // String /mappingMgr
       2: astore_2
       3: aconst_null
       4: astore_3
       5: aload_0
       6: aload_1
       7: invokevirtual #4                  // Method java/lang/String.startsWith:(Ljava/lang/String;)Z
      10: ifeq          35
      13: new           #22                 // class java/lang/StringBuilder
      16: dup
      17: invokespecial #23                 // Method java/lang/StringBuilder."<init>":()V
      20: aload_0
      21: invokevirtual #24                 // Method java/lang/StringBuilder.append:(Ljava/lang/String;)Ljava/lang/StringBuilder;
      24: aload_2
      25: invokevirtual #24                 // Method java/lang/StringBuilder.append:(Ljava/lang/String;)Ljava/lang/StringBuilder;
      28: invokevirtual #25                 // Method java/lang/StringBuilder.toString:()Ljava/lang/String;
      31: astore_3
      32: goto          63
      35: new           #22                 // class java/lang/StringBuilder
      38: dup
      39: invokespecial #23                 // Method java/lang/StringBuilder."<init>":()V
      42: aload_1
      43: invokevirtual #24                 // Method java/lang/StringBuilder.append:(Ljava/lang/String;)Ljava/lang/StringBuilder;
      46: ldc           #26                 // String /
      48: invokevirtual #24                 // Method java/lang/StringBuilder.append:(Ljava/lang/String;)Ljava/lang/StringBuilder;
      51: aload_0
      52: invokevirtual #24                 // Method java/lang/StringBuilder.append:(Ljava/lang/String;)Ljava/lang/StringBuilder;
      55: aload_2
      56: invokevirtual #24                 // Method java/lang/StringBuilder.append:(Ljava/lang/String;)Ljava/lang/StringBuilder;
      59: invokevirtual #25                 // Method java/lang/StringBuilder.toString:()Ljava/lang/String;
      62: astore_3
      63: aconst_null
      64: astore        4
      66: new           #27                 // class javax/naming/InitialContext
      69: dup
      70: invokespecial #28                 // Method javax/naming/InitialContext."<init>":()V
      73: astore        5
      75: aload         5
      77: aload_3
      78: invokevirtual #29                 // Method javax/naming/InitialContext.lookup:(Ljava/lang/String;)Ljava/lang/Object;
      81: checkcast     #41                 // class org/jboss/security/mapping/MappingManager
      84: astore        4
      86: goto          101
      89: astore        5
      91: getstatic     #32                 // Field org/jboss/security/PicketBoxLogger.LOGGER:Lorg/jboss/security/PicketBoxLogger;
      94: aload         5
      96: invokeinterface #33,  2           // InterfaceMethod org/jboss/security/PicketBoxLogger.debugIgnoredException:(Ljava/lang/Throwable;)V
     101: aload         4
     103: areturn
    Exception table:
       from    to  target type
          66    86    89   Class java/lang/Exception

  public static org.jboss.security.authorization.PolicyRegistration getPolicyRegistration();
    Code:
       0: ldc           #42                 // String java:/policyRegistration
       2: astore_0
       3: aconst_null
       4: astore_1
       5: new           #27                 // class javax/naming/InitialContext
       8: dup
       9: invokespecial #28                 // Method javax/naming/InitialContext."<init>":()V
      12: astore_2
      13: aload_2
      14: aload_0
      15: invokevirtual #29                 // Method javax/naming/InitialContext.lookup:(Ljava/lang/String;)Ljava/lang/Object;
      18: checkcast     #43                 // class org/jboss/security/authorization/PolicyRegistration
      21: astore_1
      22: goto          35
      25: astore_2
      26: getstatic     #32                 // Field org/jboss/security/PicketBoxLogger.LOGGER:Lorg/jboss/security/PicketBoxLogger;
      29: aload_2
      30: invokeinterface #33,  2           // InterfaceMethod org/jboss/security/PicketBoxLogger.debugIgnoredException:(Ljava/lang/Throwable;)V
      35: aload_1
      36: areturn
    Exception table:
       from    to  target type
           5    22    25   Class java/lang/Exception

  static {};
    Code:
       0: ldc           #44                 // String java:/jaas/
       2: putstatic     #8                  // Field LEGACY_JAAS_CONTEXT_ROOT:Ljava/lang/String;
       5: return
}
