Compiled from "DistributedDoubleBarrier.java"
public class org.apache.curator.framework.recipes.barriers.DistributedDoubleBarrier {
  private final org.apache.curator.framework.CuratorFramework client;

  private final java.lang.String barrierPath;

  private final int memberQty;

  private final java.lang.String ourPath;

  private final java.lang.String readyPath;

  private final java.util.concurrent.atomic.AtomicBoolean hasBeenNotified;

  private final java.util.concurrent.atomic.AtomicBoolean connectionLost;

  private final org.apache.zookeeper.Watcher watcher;

  private static final java.lang.String READY_NODE;

  public org.apache.curator.framework.recipes.barriers.DistributedDoubleBarrier(org.apache.curator.framework.CuratorFramework, java.lang.String, int);
    Code:
       0: aload_0
       1: invokespecial #41                 // Method java/lang/Object."<init>":()V
       4: aload_0
       5: new           #43                 // class java/util/concurrent/atomic/AtomicBoolean
       8: dup
       9: iconst_0
      10: invokespecial #46                 // Method java/util/concurrent/atomic/AtomicBoolean."<init>":(Z)V
      13: putfield      #48                 // Field hasBeenNotified:Ljava/util/concurrent/atomic/AtomicBoolean;
      16: aload_0
      17: new           #43                 // class java/util/concurrent/atomic/AtomicBoolean
      20: dup
      21: iconst_0
      22: invokespecial #46                 // Method java/util/concurrent/atomic/AtomicBoolean."<init>":(Z)V
      25: putfield      #50                 // Field connectionLost:Ljava/util/concurrent/atomic/AtomicBoolean;
      28: aload_0
      29: new           #9                  // class org/apache/curator/framework/recipes/barriers/DistributedDoubleBarrier$1
      32: dup
      33: aload_0
      34: invokespecial #53                 // Method org/apache/curator/framework/recipes/barriers/DistributedDoubleBarrier$1."<init>":(Lorg/apache/curator/framework/recipes/barriers/DistributedDoubleBarrier;)V
      37: putfield      #55                 // Field watcher:Lorg/apache/zookeeper/Watcher;
      40: iload_3
      41: ifle          48
      44: iconst_1
      45: goto          49
      48: iconst_0
      49: ldc           #61                 // String memberQty cannot be 0
      51: invokestatic  #67                 // Method org/apache/curator/shaded/com/google/common/base/Preconditions.checkState:(ZLjava/lang/Object;)V
      54: aload_0
      55: aload_1
      56: putfield      #69                 // Field client:Lorg/apache/curator/framework/CuratorFramework;
      59: aload_0
      60: aload_2
      61: invokestatic  #75                 // Method org/apache/curator/utils/PathUtils.validatePath:(Ljava/lang/String;)Ljava/lang/String;
      64: putfield      #77                 // Field barrierPath:Ljava/lang/String;
      67: aload_0
      68: iload_3
      69: putfield      #79                 // Field memberQty:I
      72: aload_0
      73: aload_2
      74: invokestatic  #85                 // Method java/util/UUID.randomUUID:()Ljava/util/UUID;
      77: invokevirtual #89                 // Method java/util/UUID.toString:()Ljava/lang/String;
      80: invokestatic  #95                 // Method org/apache/curator/utils/ZKPaths.makePath:(Ljava/lang/String;Ljava/lang/String;)Ljava/lang/String;
      83: putfield      #97                 // Field ourPath:Ljava/lang/String;
      86: aload_0
      87: aload_2
      88: ldc           #36                 // String ready
      90: invokestatic  #95                 // Method org/apache/curator/utils/ZKPaths.makePath:(Ljava/lang/String;Ljava/lang/String;)Ljava/lang/String;
      93: putfield      #99                 // Field readyPath:Ljava/lang/String;
      96: return

  public void enter() throws java.lang.Exception;
    Code:
       0: aload_0
       1: ldc2_w        #105                // long -1l
       4: aconst_null
       5: invokevirtual #109                // Method enter:(JLjava/util/concurrent/TimeUnit;)Z
       8: pop
       9: return

  public boolean enter(long, java.util.concurrent.TimeUnit) throws java.lang.Exception;
    Code:
       0: invokestatic  #115                // Method java/lang/System.currentTimeMillis:()J
       3: lstore        4
       5: aload_3
       6: ifnull        13
       9: iconst_1
      10: goto          14
      13: iconst_0
      14: istore        6
      16: iload         6
      18: ifeq          32
      21: getstatic     #121                // Field java/util/concurrent/TimeUnit.MILLISECONDS:Ljava/util/concurrent/TimeUnit;
      24: lload_1
      25: aload_3
      26: invokevirtual #125                // Method java/util/concurrent/TimeUnit.convert:(JLjava/util/concurrent/TimeUnit;)J
      29: goto          35
      32: ldc2_w        #126                // long 9223372036854775807l
      35: lstore        7
      37: aload_0
      38: getfield      #69                 // Field client:Lorg/apache/curator/framework/CuratorFramework;
      41: invokeinterface #131,  1          // InterfaceMethod org/apache/curator/framework/CuratorFramework.checkExists:()Lorg/apache/curator/framework/api/ExistsBuilder;
      46: aload_0
      47: getfield      #55                 // Field watcher:Lorg/apache/zookeeper/Watcher;
      50: invokeinterface #137,  2          // InterfaceMethod org/apache/curator/framework/api/ExistsBuilder.usingWatcher:(Lorg/apache/zookeeper/Watcher;)Ljava/lang/Object;
      55: checkcast     #139                // class org/apache/curator/framework/api/BackgroundPathable
      58: aload_0
      59: getfield      #99                 // Field readyPath:Ljava/lang/String;
      62: invokeinterface #143,  2          // InterfaceMethod org/apache/curator/framework/api/BackgroundPathable.forPath:(Ljava/lang/String;)Ljava/lang/Object;
      67: ifnull        74
      70: iconst_1
      71: goto          75
      74: iconst_0
      75: istore        9
      77: aload_0
      78: getfield      #69                 // Field client:Lorg/apache/curator/framework/CuratorFramework;
      81: invokeinterface #147,  1          // InterfaceMethod org/apache/curator/framework/CuratorFramework.create:()Lorg/apache/curator/framework/api/CreateBuilder;
      86: invokeinterface #153,  1          // InterfaceMethod org/apache/curator/framework/api/CreateBuilder.creatingParentContainersIfNeeded:()Lorg/apache/curator/framework/api/ProtectACLCreateModeStatPathAndBytesable;
      91: getstatic     #159                // Field org/apache/zookeeper/CreateMode.EPHEMERAL:Lorg/apache/zookeeper/CreateMode;
      94: invokeinterface #165,  2          // InterfaceMethod org/apache/curator/framework/api/ProtectACLCreateModeStatPathAndBytesable.withMode:(Lorg/apache/zookeeper/CreateMode;)Ljava/lang/Object;
      99: checkcast     #167                // class org/apache/curator/framework/api/ACLBackgroundPathAndBytesable
     102: aload_0
     103: getfield      #97                 // Field ourPath:Ljava/lang/String;
     106: invokeinterface #168,  2          // InterfaceMethod org/apache/curator/framework/api/ACLBackgroundPathAndBytesable.forPath:(Ljava/lang/String;)Ljava/lang/Object;
     111: pop
     112: iload         9
     114: ifne          130
     117: aload_0
     118: lload         4
     120: iload         6
     122: lload         7
     124: invokespecial #172                // Method internalEnter:(JZJ)Z
     127: ifeq          134
     130: iconst_1
     131: goto          135
     134: iconst_0
     135: istore        10
     137: aload_0
     138: getfield      #50                 // Field connectionLost:Ljava/util/concurrent/atomic/AtomicBoolean;
     141: invokevirtual #176                // Method java/util/concurrent/atomic/AtomicBoolean.get:()Z
     144: ifeq          155
     147: new           #16                 // class org/apache/zookeeper/KeeperException$ConnectionLossException
     150: dup
     151: invokespecial #177                // Method org/apache/zookeeper/KeeperException$ConnectionLossException."<init>":()V
     154: athrow
     155: iload         10
     157: ireturn

  public synchronized void leave() throws java.lang.Exception;
    Code:
       0: aload_0
       1: ldc2_w        #105                // long -1l
       4: aconst_null
       5: invokevirtual #189                // Method leave:(JLjava/util/concurrent/TimeUnit;)Z
       8: pop
       9: return

  public synchronized boolean leave(long, java.util.concurrent.TimeUnit) throws java.lang.Exception;
    Code:
       0: invokestatic  #115                // Method java/lang/System.currentTimeMillis:()J
       3: lstore        4
       5: aload_3
       6: ifnull        13
       9: iconst_1
      10: goto          14
      13: iconst_0
      14: istore        6
      16: iload         6
      18: ifeq          32
      21: getstatic     #121                // Field java/util/concurrent/TimeUnit.MILLISECONDS:Ljava/util/concurrent/TimeUnit;
      24: lload_1
      25: aload_3
      26: invokevirtual #125                // Method java/util/concurrent/TimeUnit.convert:(JLjava/util/concurrent/TimeUnit;)J
      29: goto          35
      32: ldc2_w        #126                // long 9223372036854775807l
      35: lstore        7
      37: aload_0
      38: lload         4
      40: iload         6
      42: lload         7
      44: invokespecial #192                // Method internalLeave:(JZJ)Z
      47: ireturn

  protected java.util.List<java.lang.String> getChildrenForEntering() throws java.lang.Exception;
    Code:
       0: aload_0
       1: getfield      #69                 // Field client:Lorg/apache/curator/framework/CuratorFramework;
       4: invokeinterface #200,  1          // InterfaceMethod org/apache/curator/framework/CuratorFramework.getChildren:()Lorg/apache/curator/framework/api/GetChildrenBuilder;
       9: aload_0
      10: getfield      #77                 // Field barrierPath:Ljava/lang/String;
      13: invokeinterface #203,  2          // InterfaceMethod org/apache/curator/framework/api/GetChildrenBuilder.forPath:(Ljava/lang/String;)Ljava/lang/Object;
      18: checkcast     #205                // class java/util/List
      21: areturn

  private java.util.List<java.lang.String> filterAndSortChildren(java.util.List<java.lang.String>);
    Code:
       0: aload_1
       1: new           #7                  // class org/apache/curator/framework/recipes/barriers/DistributedDoubleBarrier$2
       4: dup
       5: aload_0
       6: invokespecial #209                // Method org/apache/curator/framework/recipes/barriers/DistributedDoubleBarrier$2."<init>":(Lorg/apache/curator/framework/recipes/barriers/DistributedDoubleBarrier;)V
       9: invokestatic  #215                // Method org/apache/curator/shaded/com/google/common/collect/Iterables.filter:(Ljava/lang/Iterable;Lorg/apache/curator/shaded/com/google/common/base/Predicate;)Ljava/lang/Iterable;
      12: astore_2
      13: aload_2
      14: invokestatic  #221                // Method org/apache/curator/shaded/com/google/common/collect/Lists.newArrayList:(Ljava/lang/Iterable;)Ljava/util/ArrayList;
      17: astore_3
      18: aload_3
      19: invokestatic  #227                // Method java/util/Collections.sort:(Ljava/util/List;)V
      22: aload_3
      23: areturn

  private boolean internalLeave(long, boolean, long) throws java.lang.Exception;
    Code:
       0: aload_0
       1: getfield      #97                 // Field ourPath:Ljava/lang/String;
       4: invokestatic  #239                // Method org/apache/curator/utils/ZKPaths.getNodeFromPath:(Ljava/lang/String;)Ljava/lang/String;
       7: astore        6
       9: iconst_1
      10: istore        7
      12: iconst_1
      13: istore        8
      15: aload_0
      16: getfield      #50                 // Field connectionLost:Ljava/util/concurrent/atomic/AtomicBoolean;
      19: invokevirtual #176                // Method java/util/concurrent/atomic/AtomicBoolean.get:()Z
      22: ifeq          33
      25: new           #16                 // class org/apache/zookeeper/KeeperException$ConnectionLossException
      28: dup
      29: invokespecial #177                // Method org/apache/zookeeper/KeeperException$ConnectionLossException."<init>":()V
      32: athrow
      33: aload_0
      34: getfield      #69                 // Field client:Lorg/apache/curator/framework/CuratorFramework;
      37: invokeinterface #200,  1          // InterfaceMethod org/apache/curator/framework/CuratorFramework.getChildren:()Lorg/apache/curator/framework/api/GetChildrenBuilder;
      42: aload_0
      43: getfield      #77                 // Field barrierPath:Ljava/lang/String;
      46: invokeinterface #203,  2          // InterfaceMethod org/apache/curator/framework/api/GetChildrenBuilder.forPath:(Ljava/lang/String;)Ljava/lang/Object;
      51: checkcast     #205                // class java/util/List
      54: astore        9
      56: goto          66
      59: astore        10
      61: invokestatic  #242                // Method org/apache/curator/shaded/com/google/common/collect/Lists.newArrayList:()Ljava/util/ArrayList;
      64: astore        9
      66: aload_0
      67: aload         9
      69: invokespecial #244                // Method filterAndSortChildren:(Ljava/util/List;)Ljava/util/List;
      72: astore        9
      74: aload         9
      76: ifnull        422
      79: aload         9
      81: invokeinterface #248,  1          // InterfaceMethod java/util/List.size:()I
      86: ifne          92
      89: goto          422
      92: aload         9
      94: aload         6
      96: invokeinterface #252,  2          // InterfaceMethod java/util/List.indexOf:(Ljava/lang/Object;)I
     101: istore        10
     103: iload         10
     105: ifge          149
     108: iload         7
     110: ifeq          149
     113: aload_0
     114: getfield      #50                 // Field connectionLost:Ljava/util/concurrent/atomic/AtomicBoolean;
     117: invokevirtual #176                // Method java/util/concurrent/atomic/AtomicBoolean.get:()Z
     120: ifeq          126
     123: goto          422
     126: new           #254                // class java/lang/IllegalStateException
     129: dup
     130: ldc_w         #256                // String Our path (%s) is missing
     133: iconst_1
     134: anewarray     #4                  // class java/lang/Object
     137: dup
     138: iconst_0
     139: aload         6
     141: aastore
     142: invokestatic  #260                // Method java/lang/String.format:(Ljava/lang/String;[Ljava/lang/Object;)Ljava/lang/String;
     145: invokespecial #263                // Method java/lang/IllegalStateException."<init>":(Ljava/lang/String;)V
     148: athrow
     149: aload         9
     151: invokeinterface #248,  1          // InterfaceMethod java/util/List.size:()I
     156: iconst_1
     157: if_icmpne     227
     160: iload         7
     162: ifeq          218
     165: aload         9
     167: iconst_0
     168: invokeinterface #266,  2          // InterfaceMethod java/util/List.get:(I)Ljava/lang/Object;
     173: checkcast     #59                 // class java/lang/String
     176: aload         6
     178: invokevirtual #270                // Method java/lang/String.equals:(Ljava/lang/Object;)Z
     181: ifne          218
     184: new           #254                // class java/lang/IllegalStateException
     187: dup
     188: ldc_w         #272                // String Last path (%s) is not ours (%s)
     191: iconst_2
     192: anewarray     #4                  // class java/lang/Object
     195: dup
     196: iconst_0
     197: aload         9
     199: iconst_0
     200: invokeinterface #266,  2          // InterfaceMethod java/util/List.get:(I)Ljava/lang/Object;
     205: aastore
     206: dup
     207: iconst_1
     208: aload         6
     210: aastore
     211: invokestatic  #260                // Method java/lang/String.format:(Ljava/lang/String;[Ljava/lang/Object;)Ljava/lang/String;
     214: invokespecial #263                // Method java/lang/IllegalStateException."<init>":(Ljava/lang/String;)V
     217: athrow
     218: aload_0
     219: iload         7
     221: invokespecial #275                // Method checkDeleteOurPath:(Z)V
     224: goto          422
     227: iload         10
     229: ifne          236
     232: iconst_1
     233: goto          237
     236: iconst_0
     237: istore        12
     239: iload         12
     241: ifeq          308
     244: aload_0
     245: getfield      #77                 // Field barrierPath:Ljava/lang/String;
     248: aload         9
     250: aload         9
     252: invokeinterface #248,  1          // InterfaceMethod java/util/List.size:()I
     257: iconst_1
     258: isub
     259: invokeinterface #266,  2          // InterfaceMethod java/util/List.get:(I)Ljava/lang/Object;
     264: checkcast     #59                 // class java/lang/String
     267: invokestatic  #95                 // Method org/apache/curator/utils/ZKPaths.makePath:(Ljava/lang/String;Ljava/lang/String;)Ljava/lang/String;
     270: astore        13
     272: aload_0
     273: getfield      #69                 // Field client:Lorg/apache/curator/framework/CuratorFramework;
     276: invokeinterface #131,  1          // InterfaceMethod org/apache/curator/framework/CuratorFramework.checkExists:()Lorg/apache/curator/framework/api/ExistsBuilder;
     281: aload_0
     282: getfield      #55                 // Field watcher:Lorg/apache/zookeeper/Watcher;
     285: invokeinterface #137,  2          // InterfaceMethod org/apache/curator/framework/api/ExistsBuilder.usingWatcher:(Lorg/apache/zookeeper/Watcher;)Ljava/lang/Object;
     290: checkcast     #139                // class org/apache/curator/framework/api/BackgroundPathable
     293: aload         13
     295: invokeinterface #143,  2          // InterfaceMethod org/apache/curator/framework/api/BackgroundPathable.forPath:(Ljava/lang/String;)Ljava/lang/Object;
     300: checkcast     #277                // class org/apache/zookeeper/data/Stat
     303: astore        11
     305: goto          370
     308: aload_0
     309: getfield      #77                 // Field barrierPath:Ljava/lang/String;
     312: aload         9
     314: iconst_0
     315: invokeinterface #266,  2          // InterfaceMethod java/util/List.get:(I)Ljava/lang/Object;
     320: checkcast     #59                 // class java/lang/String
     323: invokestatic  #95                 // Method org/apache/curator/utils/ZKPaths.makePath:(Ljava/lang/String;Ljava/lang/String;)Ljava/lang/String;
     326: astore        13
     328: aload_0
     329: getfield      #69                 // Field client:Lorg/apache/curator/framework/CuratorFramework;
     332: invokeinterface #131,  1          // InterfaceMethod org/apache/curator/framework/CuratorFramework.checkExists:()Lorg/apache/curator/framework/api/ExistsBuilder;
     337: aload_0
     338: getfield      #55                 // Field watcher:Lorg/apache/zookeeper/Watcher;
     341: invokeinterface #137,  2          // InterfaceMethod org/apache/curator/framework/api/ExistsBuilder.usingWatcher:(Lorg/apache/zookeeper/Watcher;)Ljava/lang/Object;
     346: checkcast     #139                // class org/apache/curator/framework/api/BackgroundPathable
     349: aload         13
     351: invokeinterface #143,  2          // InterfaceMethod org/apache/curator/framework/api/BackgroundPathable.forPath:(Ljava/lang/String;)Ljava/lang/Object;
     356: checkcast     #277                // class org/apache/zookeeper/data/Stat
     359: astore        11
     361: aload_0
     362: iload         7
     364: invokespecial #275                // Method checkDeleteOurPath:(Z)V
     367: iconst_0
     368: istore        7
     370: aload         11
     372: ifnull        419
     375: iload_3
     376: ifeq          415
     379: invokestatic  #115                // Method java/lang/System.currentTimeMillis:()J
     382: lload_1
     383: lsub
     384: lstore        13
     386: lload         4
     388: lload         13
     390: lsub
     391: lstore        15
     393: lload         15
     395: lconst_0
     396: lcmp
     397: ifgt          406
     400: iconst_0
     401: istore        8
     403: goto          422
     406: aload_0
     407: lload         15
     409: invokevirtual #281                // Method java/lang/Object.wait:(J)V
     412: goto          419
     415: aload_0
     416: invokevirtual #283                // Method java/lang/Object.wait:()V
     419: goto          15
     422: aload_0
     423: getfield      #69                 // Field client:Lorg/apache/curator/framework/CuratorFramework;
     426: invokeinterface #287,  1          // InterfaceMethod org/apache/curator/framework/CuratorFramework.delete:()Lorg/apache/curator/framework/api/DeleteBuilder;
     431: aload_0
     432: getfield      #99                 // Field readyPath:Ljava/lang/String;
     435: invokeinterface #290,  2          // InterfaceMethod org/apache/curator/framework/api/DeleteBuilder.forPath:(Ljava/lang/String;)Ljava/lang/Object;
     440: pop
     441: goto          446
     444: astore        9
     446: iload         8
     448: ireturn
    Exception table:
       from    to  target type
          33    56    59   Class org/apache/zookeeper/KeeperException$NoNodeException
         422   441   444   Class org/apache/zookeeper/KeeperException$NoNodeException

  private void checkDeleteOurPath(boolean) throws java.lang.Exception;
    Code:
       0: iload_1
       1: ifeq          23
       4: aload_0
       5: getfield      #69                 // Field client:Lorg/apache/curator/framework/CuratorFramework;
       8: invokeinterface #287,  1          // InterfaceMethod org/apache/curator/framework/CuratorFramework.delete:()Lorg/apache/curator/framework/api/DeleteBuilder;
      13: aload_0
      14: getfield      #97                 // Field ourPath:Ljava/lang/String;
      17: invokeinterface #290,  2          // InterfaceMethod org/apache/curator/framework/api/DeleteBuilder.forPath:(Ljava/lang/String;)Ljava/lang/Object;
      22: pop
      23: return

  private synchronized boolean internalEnter(long, boolean, long) throws java.lang.Exception;
    Code:
       0: iconst_1
       1: istore        6
       3: aload_0
       4: invokevirtual #305                // Method getChildrenForEntering:()Ljava/util/List;
       7: astore        7
       9: aload         7
      11: ifnull        24
      14: aload         7
      16: invokeinterface #248,  1          // InterfaceMethod java/util/List.size:()I
      21: goto          25
      24: iconst_0
      25: istore        8
      27: iload         8
      29: aload_0
      30: getfield      #79                 // Field memberQty:I
      33: if_icmplt     63
      36: aload_0
      37: getfield      #69                 // Field client:Lorg/apache/curator/framework/CuratorFramework;
      40: invokeinterface #147,  1          // InterfaceMethod org/apache/curator/framework/CuratorFramework.create:()Lorg/apache/curator/framework/api/CreateBuilder;
      45: aload_0
      46: getfield      #99                 // Field readyPath:Ljava/lang/String;
      49: invokeinterface #306,  2          // InterfaceMethod org/apache/curator/framework/api/CreateBuilder.forPath:(Ljava/lang/String;)Ljava/lang/Object;
      54: pop
      55: goto          130
      58: astore        9
      60: goto          130
      63: iload_3
      64: ifeq          126
      67: aload_0
      68: getfield      #48                 // Field hasBeenNotified:Ljava/util/concurrent/atomic/AtomicBoolean;
      71: invokevirtual #176                // Method java/util/concurrent/atomic/AtomicBoolean.get:()Z
      74: ifne          126
      77: invokestatic  #115                // Method java/lang/System.currentTimeMillis:()J
      80: lload_1
      81: lsub
      82: lstore        9
      84: lload         4
      86: lload         9
      88: lsub
      89: lstore        11
      91: lload         11
      93: lconst_0
      94: lcmp
      95: ifgt          104
      98: iconst_0
      99: istore        6
     101: goto          110
     104: aload_0
     105: lload         11
     107: invokevirtual #281                // Method java/lang/Object.wait:(J)V
     110: aload_0
     111: getfield      #48                 // Field hasBeenNotified:Ljava/util/concurrent/atomic/AtomicBoolean;
     114: invokevirtual #176                // Method java/util/concurrent/atomic/AtomicBoolean.get:()Z
     117: ifne          123
     120: iconst_0
     121: istore        6
     123: goto          130
     126: aload_0
     127: invokevirtual #283                // Method java/lang/Object.wait:()V
     130: iload         6
     132: ireturn
    Exception table:
       from    to  target type
          36    55    58   Class org/apache/zookeeper/KeeperException$NodeExistsException

  static java.util.concurrent.atomic.AtomicBoolean access$000(org.apache.curator.framework.recipes.barriers.DistributedDoubleBarrier);
    Code:
       0: aload_0
       1: getfield      #50                 // Field connectionLost:Ljava/util/concurrent/atomic/AtomicBoolean;
       4: areturn

  static org.apache.curator.framework.CuratorFramework access$100(org.apache.curator.framework.recipes.barriers.DistributedDoubleBarrier);
    Code:
       0: aload_0
       1: getfield      #69                 // Field client:Lorg/apache/curator/framework/CuratorFramework;
       4: areturn

  static java.util.concurrent.atomic.AtomicBoolean access$200(org.apache.curator.framework.recipes.barriers.DistributedDoubleBarrier);
    Code:
       0: aload_0
       1: getfield      #48                 // Field hasBeenNotified:Ljava/util/concurrent/atomic/AtomicBoolean;
       4: areturn
}
