Compiled from "DeleteOriginEndpointResponse.java"
final class software.amazon.awssdk.services.mediapackagev2.model.DeleteOriginEndpointResponse$BuilderImpl extends software.amazon.awssdk.services.mediapackagev2.model.MediaPackageV2Response$BuilderImpl implements software.amazon.awssdk.services.mediapackagev2.model.DeleteOriginEndpointResponse$Builder {
  private software.amazon.awssdk.services.mediapackagev2.model.DeleteOriginEndpointResponse$BuilderImpl();
    Code:
       0: aload_0
       1: invokespecial #3                  // Method software/amazon/awssdk/services/mediapackagev2/model/MediaPackageV2Response$BuilderImpl."<init>":()V
       4: return

  private software.amazon.awssdk.services.mediapackagev2.model.DeleteOriginEndpointResponse$BuilderImpl(software.amazon.awssdk.services.mediapackagev2.model.DeleteOriginEndpointResponse);
    Code:
       0: aload_0
       1: aload_1
       2: invokespecial #4                  // Method software/amazon/awssdk/services/mediapackagev2/model/MediaPackageV2Response$BuilderImpl."<init>":(Lsoftware/amazon/awssdk/services/mediapackagev2/model/MediaPackageV2Response;)V
       5: return

  public software.amazon.awssdk.services.mediapackagev2.model.DeleteOriginEndpointResponse build();
    Code:
       0: new           #5                  // class software/amazon/awssdk/services/mediapackagev2/model/DeleteOriginEndpointResponse
       3: dup
       4: aload_0
       5: aconst_null
       6: invokespecial #6                  // Method software/amazon/awssdk/services/mediapackagev2/model/DeleteOriginEndpointResponse."<init>":(Lsoftware/amazon/awssdk/services/mediapackagev2/model/DeleteOriginEndpointResponse$BuilderImpl;Lsoftware/amazon/awssdk/services/mediapackagev2/model/DeleteOriginEndpointResponse$1;)V
       9: areturn

  public java.util.List<software.amazon.awssdk.core.SdkField<?>> sdkFields();
    Code:
       0: invokestatic  #7                  // Method software/amazon/awssdk/services/mediapackagev2/model/DeleteOriginEndpointResponse.access$300:()Ljava/util/List;
       3: areturn

  public software.amazon.awssdk.services.mediapackagev2.model.MediaPackageV2Response build();
    Code:
       0: aload_0
       1: invokevirtual #8                  // Method build:()Lsoftware/amazon/awssdk/services/mediapackagev2/model/DeleteOriginEndpointResponse;
       4: areturn

  public software.amazon.awssdk.awscore.AwsResponse build();
    Code:
       0: aload_0
       1: invokevirtual #8                  // Method build:()Lsoftware/amazon/awssdk/services/mediapackagev2/model/DeleteOriginEndpointResponse;
       4: areturn

  public software.amazon.awssdk.core.SdkResponse build();
    Code:
       0: aload_0
       1: invokevirtual #8                  // Method build:()Lsoftware/amazon/awssdk/services/mediapackagev2/model/DeleteOriginEndpointResponse;
       4: areturn

  public java.lang.Object build();
    Code:
       0: aload_0
       1: invokevirtual #8                  // Method build:()Lsoftware/amazon/awssdk/services/mediapackagev2/model/DeleteOriginEndpointResponse;
       4: areturn

  software.amazon.awssdk.services.mediapackagev2.model.DeleteOriginEndpointResponse$BuilderImpl(software.amazon.awssdk.services.mediapackagev2.model.DeleteOriginEndpointResponse, software.amazon.awssdk.services.mediapackagev2.model.DeleteOriginEndpointResponse$1);
    Code:
       0: aload_0
       1: aload_1
       2: invokespecial #2                  // Method "<init>":(Lsoftware/amazon/awssdk/services/mediapackagev2/model/DeleteOriginEndpointResponse;)V
       5: return

  software.amazon.awssdk.services.mediapackagev2.model.DeleteOriginEndpointResponse$BuilderImpl(software.amazon.awssdk.services.mediapackagev2.model.DeleteOriginEndpointResponse$1);
    Code:
       0: aload_0
       1: invokespecial #1                  // Method "<init>":()V
       4: return
}
