Compiled from "ValidationExceptionType.java"
public final class software.amazon.awssdk.services.mediapackagev2.model.ValidationExceptionType extends java.lang.Enum<software.amazon.awssdk.services.mediapackagev2.model.ValidationExceptionType> {
  public static final software.amazon.awssdk.services.mediapackagev2.model.ValidationExceptionType CONTAINER_TYPE_IMMUTABLE;

  public static final software.amazon.awssdk.services.mediapackagev2.model.ValidationExceptionType INVALID_PAGINATION_TOKEN;

  public static final software.amazon.awssdk.services.mediapackagev2.model.ValidationExceptionType INVALID_PAGINATION_MAX_RESULTS;

  public static final software.amazon.awssdk.services.mediapackagev2.model.ValidationExceptionType INVALID_POLICY;

  public static final software.amazon.awssdk.services.mediapackagev2.model.ValidationExceptionType INVALID_ROLE_ARN;

  public static final software.amazon.awssdk.services.mediapackagev2.model.ValidationExceptionType MANIFEST_NAME_COLLISION;

  public static final software.amazon.awssdk.services.mediapackagev2.model.ValidationExceptionType ENCRYPTION_METHOD_CONTAINER_TYPE_MISMATCH;

  public static final software.amazon.awssdk.services.mediapackagev2.model.ValidationExceptionType CENC_IV_INCOMPATIBLE;

  public static final software.amazon.awssdk.services.mediapackagev2.model.ValidationExceptionType ENCRYPTION_CONTRACT_WITHOUT_AUDIO_RENDITION_INCOMPATIBLE;

  public static final software.amazon.awssdk.services.mediapackagev2.model.ValidationExceptionType ENCRYPTION_CONTRACT_UNENCRYPTED;

  public static final software.amazon.awssdk.services.mediapackagev2.model.ValidationExceptionType ENCRYPTION_CONTRACT_SHARED;

  public static final software.amazon.awssdk.services.mediapackagev2.model.ValidationExceptionType NUM_MANIFESTS_LOW;

  public static final software.amazon.awssdk.services.mediapackagev2.model.ValidationExceptionType NUM_MANIFESTS_HIGH;

  public static final software.amazon.awssdk.services.mediapackagev2.model.ValidationExceptionType DRM_SYSTEMS_ENCRYPTION_METHOD_INCOMPATIBLE;

  public static final software.amazon.awssdk.services.mediapackagev2.model.ValidationExceptionType ROLE_ARN_NOT_ASSUMABLE;

  public static final software.amazon.awssdk.services.mediapackagev2.model.ValidationExceptionType ROLE_ARN_LENGTH_OUT_OF_RANGE;

  public static final software.amazon.awssdk.services.mediapackagev2.model.ValidationExceptionType ROLE_ARN_INVALID_FORMAT;

  public static final software.amazon.awssdk.services.mediapackagev2.model.ValidationExceptionType URL_INVALID;

  public static final software.amazon.awssdk.services.mediapackagev2.model.ValidationExceptionType URL_SCHEME;

  public static final software.amazon.awssdk.services.mediapackagev2.model.ValidationExceptionType URL_USER_INFO;

  public static final software.amazon.awssdk.services.mediapackagev2.model.ValidationExceptionType URL_PORT;

  public static final software.amazon.awssdk.services.mediapackagev2.model.ValidationExceptionType URL_UNKNOWN_HOST;

  public static final software.amazon.awssdk.services.mediapackagev2.model.ValidationExceptionType URL_LOCAL_ADDRESS;

  public static final software.amazon.awssdk.services.mediapackagev2.model.ValidationExceptionType URL_LOOPBACK_ADDRESS;

  public static final software.amazon.awssdk.services.mediapackagev2.model.ValidationExceptionType URL_LINK_LOCAL_ADDRESS;

  public static final software.amazon.awssdk.services.mediapackagev2.model.ValidationExceptionType URL_MULTICAST_ADDRESS;

  public static final software.amazon.awssdk.services.mediapackagev2.model.ValidationExceptionType MEMBER_INVALID;

  public static final software.amazon.awssdk.services.mediapackagev2.model.ValidationExceptionType MEMBER_MISSING;

  public static final software.amazon.awssdk.services.mediapackagev2.model.ValidationExceptionType MEMBER_MIN_VALUE;

  public static final software.amazon.awssdk.services.mediapackagev2.model.ValidationExceptionType MEMBER_MAX_VALUE;

  public static final software.amazon.awssdk.services.mediapackagev2.model.ValidationExceptionType MEMBER_MIN_LENGTH;

  public static final software.amazon.awssdk.services.mediapackagev2.model.ValidationExceptionType MEMBER_MAX_LENGTH;

  public static final software.amazon.awssdk.services.mediapackagev2.model.ValidationExceptionType MEMBER_INVALID_ENUM_VALUE;

  public static final software.amazon.awssdk.services.mediapackagev2.model.ValidationExceptionType MEMBER_DOES_NOT_MATCH_PATTERN;

  public static final software.amazon.awssdk.services.mediapackagev2.model.ValidationExceptionType UNKNOWN_TO_SDK_VERSION;

  private static final java.util.Map<java.lang.String, software.amazon.awssdk.services.mediapackagev2.model.ValidationExceptionType> VALUE_MAP;

  private final java.lang.String value;

  private static final software.amazon.awssdk.services.mediapackagev2.model.ValidationExceptionType[] $VALUES;

  public static software.amazon.awssdk.services.mediapackagev2.model.ValidationExceptionType[] values();
    Code:
       0: getstatic     #1                  // Field $VALUES:[Lsoftware/amazon/awssdk/services/mediapackagev2/model/ValidationExceptionType;
       3: invokevirtual #2                  // Method "[Lsoftware/amazon/awssdk/services/mediapackagev2/model/ValidationExceptionType;".clone:()Ljava/lang/Object;
       6: checkcast     #3                  // class "[Lsoftware/amazon/awssdk/services/mediapackagev2/model/ValidationExceptionType;"
       9: areturn

  public static software.amazon.awssdk.services.mediapackagev2.model.ValidationExceptionType valueOf(java.lang.String);
    Code:
       0: ldc           #4                  // class software/amazon/awssdk/services/mediapackagev2/model/ValidationExceptionType
       2: aload_0
       3: invokestatic  #5                  // Method java/lang/Enum.valueOf:(Ljava/lang/Class;Ljava/lang/String;)Ljava/lang/Enum;
       6: checkcast     #4                  // class software/amazon/awssdk/services/mediapackagev2/model/ValidationExceptionType
       9: areturn

  private software.amazon.awssdk.services.mediapackagev2.model.ValidationExceptionType(java.lang.String);
    Code:
       0: aload_0
       1: aload_1
       2: iload_2
       3: invokespecial #6                  // Method java/lang/Enum."<init>":(Ljava/lang/String;I)V
       6: aload_0
       7: aload_3
       8: putfield      #7                  // Field value:Ljava/lang/String;
      11: return

  public java.lang.String toString();
    Code:
       0: aload_0
       1: getfield      #7                  // Field value:Ljava/lang/String;
       4: invokestatic  #8                  // Method java/lang/String.valueOf:(Ljava/lang/Object;)Ljava/lang/String;
       7: areturn

  public static software.amazon.awssdk.services.mediapackagev2.model.ValidationExceptionType fromValue(java.lang.String);
    Code:
       0: aload_0
       1: ifnonnull     6
       4: aconst_null
       5: areturn
       6: getstatic     #9                  // Field VALUE_MAP:Ljava/util/Map;
       9: aload_0
      10: getstatic     #10                 // Field UNKNOWN_TO_SDK_VERSION:Lsoftware/amazon/awssdk/services/mediapackagev2/model/ValidationExceptionType;
      13: invokeinterface #11,  3           // InterfaceMethod java/util/Map.getOrDefault:(Ljava/lang/Object;Ljava/lang/Object;)Ljava/lang/Object;
      18: checkcast     #4                  // class software/amazon/awssdk/services/mediapackagev2/model/ValidationExceptionType
      21: areturn

  public static java.util.Set<software.amazon.awssdk.services.mediapackagev2.model.ValidationExceptionType> knownValues();
    Code:
       0: ldc           #4                  // class software/amazon/awssdk/services/mediapackagev2/model/ValidationExceptionType
       2: invokestatic  #12                 // Method java/util/EnumSet.allOf:(Ljava/lang/Class;)Ljava/util/EnumSet;
       5: astore_0
       6: aload_0
       7: getstatic     #10                 // Field UNKNOWN_TO_SDK_VERSION:Lsoftware/amazon/awssdk/services/mediapackagev2/model/ValidationExceptionType;
      10: invokeinterface #13,  2           // InterfaceMethod java/util/Set.remove:(Ljava/lang/Object;)Z
      15: pop
      16: aload_0
      17: areturn

  static {};
    Code:
       0: new           #4                  // class software/amazon/awssdk/services/mediapackagev2/model/ValidationExceptionType
       3: dup
       4: ldc           #14                 // String CONTAINER_TYPE_IMMUTABLE
       6: iconst_0
       7: ldc           #14                 // String CONTAINER_TYPE_IMMUTABLE
       9: invokespecial #15                 // Method "<init>":(Ljava/lang/String;ILjava/lang/String;)V
      12: putstatic     #16                 // Field CONTAINER_TYPE_IMMUTABLE:Lsoftware/amazon/awssdk/services/mediapackagev2/model/ValidationExceptionType;
      15: new           #4                  // class software/amazon/awssdk/services/mediapackagev2/model/ValidationExceptionType
      18: dup
      19: ldc           #17                 // String INVALID_PAGINATION_TOKEN
      21: iconst_1
      22: ldc           #17                 // String INVALID_PAGINATION_TOKEN
      24: invokespecial #15                 // Method "<init>":(Ljava/lang/String;ILjava/lang/String;)V
      27: putstatic     #18                 // Field INVALID_PAGINATION_TOKEN:Lsoftware/amazon/awssdk/services/mediapackagev2/model/ValidationExceptionType;
      30: new           #4                  // class software/amazon/awssdk/services/mediapackagev2/model/ValidationExceptionType
      33: dup
      34: ldc           #19                 // String INVALID_PAGINATION_MAX_RESULTS
      36: iconst_2
      37: ldc           #19                 // String INVALID_PAGINATION_MAX_RESULTS
      39: invokespecial #15                 // Method "<init>":(Ljava/lang/String;ILjava/lang/String;)V
      42: putstatic     #20                 // Field INVALID_PAGINATION_MAX_RESULTS:Lsoftware/amazon/awssdk/services/mediapackagev2/model/ValidationExceptionType;
      45: new           #4                  // class software/amazon/awssdk/services/mediapackagev2/model/ValidationExceptionType
      48: dup
      49: ldc           #21                 // String INVALID_POLICY
      51: iconst_3
      52: ldc           #21                 // String INVALID_POLICY
      54: invokespecial #15                 // Method "<init>":(Ljava/lang/String;ILjava/lang/String;)V
      57: putstatic     #22                 // Field INVALID_POLICY:Lsoftware/amazon/awssdk/services/mediapackagev2/model/ValidationExceptionType;
      60: new           #4                  // class software/amazon/awssdk/services/mediapackagev2/model/ValidationExceptionType
      63: dup
      64: ldc           #23                 // String INVALID_ROLE_ARN
      66: iconst_4
      67: ldc           #23                 // String INVALID_ROLE_ARN
      69: invokespecial #15                 // Method "<init>":(Ljava/lang/String;ILjava/lang/String;)V
      72: putstatic     #24                 // Field INVALID_ROLE_ARN:Lsoftware/amazon/awssdk/services/mediapackagev2/model/ValidationExceptionType;
      75: new           #4                  // class software/amazon/awssdk/services/mediapackagev2/model/ValidationExceptionType
      78: dup
      79: ldc           #25                 // String MANIFEST_NAME_COLLISION
      81: iconst_5
      82: ldc           #25                 // String MANIFEST_NAME_COLLISION
      84: invokespecial #15                 // Method "<init>":(Ljava/lang/String;ILjava/lang/String;)V
      87: putstatic     #26                 // Field MANIFEST_NAME_COLLISION:Lsoftware/amazon/awssdk/services/mediapackagev2/model/ValidationExceptionType;
      90: new           #4                  // class software/amazon/awssdk/services/mediapackagev2/model/ValidationExceptionType
      93: dup
      94: ldc           #27                 // String ENCRYPTION_METHOD_CONTAINER_TYPE_MISMATCH
      96: bipush        6
      98: ldc           #27                 // String ENCRYPTION_METHOD_CONTAINER_TYPE_MISMATCH
     100: invokespecial #15                 // Method "<init>":(Ljava/lang/String;ILjava/lang/String;)V
     103: putstatic     #28                 // Field ENCRYPTION_METHOD_CONTAINER_TYPE_MISMATCH:Lsoftware/amazon/awssdk/services/mediapackagev2/model/ValidationExceptionType;
     106: new           #4                  // class software/amazon/awssdk/services/mediapackagev2/model/ValidationExceptionType
     109: dup
     110: ldc           #29                 // String CENC_IV_INCOMPATIBLE
     112: bipush        7
     114: ldc           #29                 // String CENC_IV_INCOMPATIBLE
     116: invokespecial #15                 // Method "<init>":(Ljava/lang/String;ILjava/lang/String;)V
     119: putstatic     #30                 // Field CENC_IV_INCOMPATIBLE:Lsoftware/amazon/awssdk/services/mediapackagev2/model/ValidationExceptionType;
     122: new           #4                  // class software/amazon/awssdk/services/mediapackagev2/model/ValidationExceptionType
     125: dup
     126: ldc           #31                 // String ENCRYPTION_CONTRACT_WITHOUT_AUDIO_RENDITION_INCOMPATIBLE
     128: bipush        8
     130: ldc           #31                 // String ENCRYPTION_CONTRACT_WITHOUT_AUDIO_RENDITION_INCOMPATIBLE
     132: invokespecial #15                 // Method "<init>":(Ljava/lang/String;ILjava/lang/String;)V
     135: putstatic     #32                 // Field ENCRYPTION_CONTRACT_WITHOUT_AUDIO_RENDITION_INCOMPATIBLE:Lsoftware/amazon/awssdk/services/mediapackagev2/model/ValidationExceptionType;
     138: new           #4                  // class software/amazon/awssdk/services/mediapackagev2/model/ValidationExceptionType
     141: dup
     142: ldc           #33                 // String ENCRYPTION_CONTRACT_UNENCRYPTED
     144: bipush        9
     146: ldc           #33                 // String ENCRYPTION_CONTRACT_UNENCRYPTED
     148: invokespecial #15                 // Method "<init>":(Ljava/lang/String;ILjava/lang/String;)V
     151: putstatic     #34                 // Field ENCRYPTION_CONTRACT_UNENCRYPTED:Lsoftware/amazon/awssdk/services/mediapackagev2/model/ValidationExceptionType;
     154: new           #4                  // class software/amazon/awssdk/services/mediapackagev2/model/ValidationExceptionType
     157: dup
     158: ldc           #35                 // String ENCRYPTION_CONTRACT_SHARED
     160: bipush        10
     162: ldc           #35                 // String ENCRYPTION_CONTRACT_SHARED
     164: invokespecial #15                 // Method "<init>":(Ljava/lang/String;ILjava/lang/String;)V
     167: putstatic     #36                 // Field ENCRYPTION_CONTRACT_SHARED:Lsoftware/amazon/awssdk/services/mediapackagev2/model/ValidationExceptionType;
     170: new           #4                  // class software/amazon/awssdk/services/mediapackagev2/model/ValidationExceptionType
     173: dup
     174: ldc           #37                 // String NUM_MANIFESTS_LOW
     176: bipush        11
     178: ldc           #37                 // String NUM_MANIFESTS_LOW
     180: invokespecial #15                 // Method "<init>":(Ljava/lang/String;ILjava/lang/String;)V
     183: putstatic     #38                 // Field NUM_MANIFESTS_LOW:Lsoftware/amazon/awssdk/services/mediapackagev2/model/ValidationExceptionType;
     186: new           #4                  // class software/amazon/awssdk/services/mediapackagev2/model/ValidationExceptionType
     189: dup
     190: ldc           #39                 // String NUM_MANIFESTS_HIGH
     192: bipush        12
     194: ldc           #39                 // String NUM_MANIFESTS_HIGH
     196: invokespecial #15                 // Method "<init>":(Ljava/lang/String;ILjava/lang/String;)V
     199: putstatic     #40                 // Field NUM_MANIFESTS_HIGH:Lsoftware/amazon/awssdk/services/mediapackagev2/model/ValidationExceptionType;
     202: new           #4                  // class software/amazon/awssdk/services/mediapackagev2/model/ValidationExceptionType
     205: dup
     206: ldc           #41                 // String DRM_SYSTEMS_ENCRYPTION_METHOD_INCOMPATIBLE
     208: bipush        13
     210: ldc           #41                 // String DRM_SYSTEMS_ENCRYPTION_METHOD_INCOMPATIBLE
     212: invokespecial #15                 // Method "<init>":(Ljava/lang/String;ILjava/lang/String;)V
     215: putstatic     #42                 // Field DRM_SYSTEMS_ENCRYPTION_METHOD_INCOMPATIBLE:Lsoftware/amazon/awssdk/services/mediapackagev2/model/ValidationExceptionType;
     218: new           #4                  // class software/amazon/awssdk/services/mediapackagev2/model/ValidationExceptionType
     221: dup
     222: ldc           #43                 // String ROLE_ARN_NOT_ASSUMABLE
     224: bipush        14
     226: ldc           #43                 // String ROLE_ARN_NOT_ASSUMABLE
     228: invokespecial #15                 // Method "<init>":(Ljava/lang/String;ILjava/lang/String;)V
     231: putstatic     #44                 // Field ROLE_ARN_NOT_ASSUMABLE:Lsoftware/amazon/awssdk/services/mediapackagev2/model/ValidationExceptionType;
     234: new           #4                  // class software/amazon/awssdk/services/mediapackagev2/model/ValidationExceptionType
     237: dup
     238: ldc           #45                 // String ROLE_ARN_LENGTH_OUT_OF_RANGE
     240: bipush        15
     242: ldc           #45                 // String ROLE_ARN_LENGTH_OUT_OF_RANGE
     244: invokespecial #15                 // Method "<init>":(Ljava/lang/String;ILjava/lang/String;)V
     247: putstatic     #46                 // Field ROLE_ARN_LENGTH_OUT_OF_RANGE:Lsoftware/amazon/awssdk/services/mediapackagev2/model/ValidationExceptionType;
     250: new           #4                  // class software/amazon/awssdk/services/mediapackagev2/model/ValidationExceptionType
     253: dup
     254: ldc           #47                 // String ROLE_ARN_INVALID_FORMAT
     256: bipush        16
     258: ldc           #47                 // String ROLE_ARN_INVALID_FORMAT
     260: invokespecial #15                 // Method "<init>":(Ljava/lang/String;ILjava/lang/String;)V
     263: putstatic     #48                 // Field ROLE_ARN_INVALID_FORMAT:Lsoftware/amazon/awssdk/services/mediapackagev2/model/ValidationExceptionType;
     266: new           #4                  // class software/amazon/awssdk/services/mediapackagev2/model/ValidationExceptionType
     269: dup
     270: ldc           #49                 // String URL_INVALID
     272: bipush        17
     274: ldc           #49                 // String URL_INVALID
     276: invokespecial #15                 // Method "<init>":(Ljava/lang/String;ILjava/lang/String;)V
     279: putstatic     #50                 // Field URL_INVALID:Lsoftware/amazon/awssdk/services/mediapackagev2/model/ValidationExceptionType;
     282: new           #4                  // class software/amazon/awssdk/services/mediapackagev2/model/ValidationExceptionType
     285: dup
     286: ldc           #51                 // String URL_SCHEME
     288: bipush        18
     290: ldc           #51                 // String URL_SCHEME
     292: invokespecial #15                 // Method "<init>":(Ljava/lang/String;ILjava/lang/String;)V
     295: putstatic     #52                 // Field URL_SCHEME:Lsoftware/amazon/awssdk/services/mediapackagev2/model/ValidationExceptionType;
     298: new           #4                  // class software/amazon/awssdk/services/mediapackagev2/model/ValidationExceptionType
     301: dup
     302: ldc           #53                 // String URL_USER_INFO
     304: bipush        19
     306: ldc           #53                 // String URL_USER_INFO
     308: invokespecial #15                 // Method "<init>":(Ljava/lang/String;ILjava/lang/String;)V
     311: putstatic     #54                 // Field URL_USER_INFO:Lsoftware/amazon/awssdk/services/mediapackagev2/model/ValidationExceptionType;
     314: new           #4                  // class software/amazon/awssdk/services/mediapackagev2/model/ValidationExceptionType
     317: dup
     318: ldc           #55                 // String URL_PORT
     320: bipush        20
     322: ldc           #55                 // String URL_PORT
     324: invokespecial #15                 // Method "<init>":(Ljava/lang/String;ILjava/lang/String;)V
     327: putstatic     #56                 // Field URL_PORT:Lsoftware/amazon/awssdk/services/mediapackagev2/model/ValidationExceptionType;
     330: new           #4                  // class software/amazon/awssdk/services/mediapackagev2/model/ValidationExceptionType
     333: dup
     334: ldc           #57                 // String URL_UNKNOWN_HOST
     336: bipush        21
     338: ldc           #57                 // String URL_UNKNOWN_HOST
     340: invokespecial #15                 // Method "<init>":(Ljava/lang/String;ILjava/lang/String;)V
     343: putstatic     #58                 // Field URL_UNKNOWN_HOST:Lsoftware/amazon/awssdk/services/mediapackagev2/model/ValidationExceptionType;
     346: new           #4                  // class software/amazon/awssdk/services/mediapackagev2/model/ValidationExceptionType
     349: dup
     350: ldc           #59                 // String URL_LOCAL_ADDRESS
     352: bipush        22
     354: ldc           #59                 // String URL_LOCAL_ADDRESS
     356: invokespecial #15                 // Method "<init>":(Ljava/lang/String;ILjava/lang/String;)V
     359: putstatic     #60                 // Field URL_LOCAL_ADDRESS:Lsoftware/amazon/awssdk/services/mediapackagev2/model/ValidationExceptionType;
     362: new           #4                  // class software/amazon/awssdk/services/mediapackagev2/model/ValidationExceptionType
     365: dup
     366: ldc           #61                 // String URL_LOOPBACK_ADDRESS
     368: bipush        23
     370: ldc           #61                 // String URL_LOOPBACK_ADDRESS
     372: invokespecial #15                 // Method "<init>":(Ljava/lang/String;ILjava/lang/String;)V
     375: putstatic     #62                 // Field URL_LOOPBACK_ADDRESS:Lsoftware/amazon/awssdk/services/mediapackagev2/model/ValidationExceptionType;
     378: new           #4                  // class software/amazon/awssdk/services/mediapackagev2/model/ValidationExceptionType
     381: dup
     382: ldc           #63                 // String URL_LINK_LOCAL_ADDRESS
     384: bipush        24
     386: ldc           #63                 // String URL_LINK_LOCAL_ADDRESS
     388: invokespecial #15                 // Method "<init>":(Ljava/lang/String;ILjava/lang/String;)V
     391: putstatic     #64                 // Field URL_LINK_LOCAL_ADDRESS:Lsoftware/amazon/awssdk/services/mediapackagev2/model/ValidationExceptionType;
     394: new           #4                  // class software/amazon/awssdk/services/mediapackagev2/model/ValidationExceptionType
     397: dup
     398: ldc           #65                 // String URL_MULTICAST_ADDRESS
     400: bipush        25
     402: ldc           #65                 // String URL_MULTICAST_ADDRESS
     404: invokespecial #15                 // Method "<init>":(Ljava/lang/String;ILjava/lang/String;)V
     407: putstatic     #66                 // Field URL_MULTICAST_ADDRESS:Lsoftware/amazon/awssdk/services/mediapackagev2/model/ValidationExceptionType;
     410: new           #4                  // class software/amazon/awssdk/services/mediapackagev2/model/ValidationExceptionType
     413: dup
     414: ldc           #67                 // String MEMBER_INVALID
     416: bipush        26
     418: ldc           #67                 // String MEMBER_INVALID
     420: invokespecial #15                 // Method "<init>":(Ljava/lang/String;ILjava/lang/String;)V
     423: putstatic     #68                 // Field MEMBER_INVALID:Lsoftware/amazon/awssdk/services/mediapackagev2/model/ValidationExceptionType;
     426: new           #4                  // class software/amazon/awssdk/services/mediapackagev2/model/ValidationExceptionType
     429: dup
     430: ldc           #69                 // String MEMBER_MISSING
     432: bipush        27
     434: ldc           #69                 // String MEMBER_MISSING
     436: invokespecial #15                 // Method "<init>":(Ljava/lang/String;ILjava/lang/String;)V
     439: putstatic     #70                 // Field MEMBER_MISSING:Lsoftware/amazon/awssdk/services/mediapackagev2/model/ValidationExceptionType;
     442: new           #4                  // class software/amazon/awssdk/services/mediapackagev2/model/ValidationExceptionType
     445: dup
     446: ldc           #71                 // String MEMBER_MIN_VALUE
     448: bipush        28
     450: ldc           #71                 // String MEMBER_MIN_VALUE
     452: invokespecial #15                 // Method "<init>":(Ljava/lang/String;ILjava/lang/String;)V
     455: putstatic     #72                 // Field MEMBER_MIN_VALUE:Lsoftware/amazon/awssdk/services/mediapackagev2/model/ValidationExceptionType;
     458: new           #4                  // class software/amazon/awssdk/services/mediapackagev2/model/ValidationExceptionType
     461: dup
     462: ldc           #73                 // String MEMBER_MAX_VALUE
     464: bipush        29
     466: ldc           #73                 // String MEMBER_MAX_VALUE
     468: invokespecial #15                 // Method "<init>":(Ljava/lang/String;ILjava/lang/String;)V
     471: putstatic     #74                 // Field MEMBER_MAX_VALUE:Lsoftware/amazon/awssdk/services/mediapackagev2/model/ValidationExceptionType;
     474: new           #4                  // class software/amazon/awssdk/services/mediapackagev2/model/ValidationExceptionType
     477: dup
     478: ldc           #75                 // String MEMBER_MIN_LENGTH
     480: bipush        30
     482: ldc           #75                 // String MEMBER_MIN_LENGTH
     484: invokespecial #15                 // Method "<init>":(Ljava/lang/String;ILjava/lang/String;)V
     487: putstatic     #76                 // Field MEMBER_MIN_LENGTH:Lsoftware/amazon/awssdk/services/mediapackagev2/model/ValidationExceptionType;
     490: new           #4                  // class software/amazon/awssdk/services/mediapackagev2/model/ValidationExceptionType
     493: dup
     494: ldc           #77                 // String MEMBER_MAX_LENGTH
     496: bipush        31
     498: ldc           #77                 // String MEMBER_MAX_LENGTH
     500: invokespecial #15                 // Method "<init>":(Ljava/lang/String;ILjava/lang/String;)V
     503: putstatic     #78                 // Field MEMBER_MAX_LENGTH:Lsoftware/amazon/awssdk/services/mediapackagev2/model/ValidationExceptionType;
     506: new           #4                  // class software/amazon/awssdk/services/mediapackagev2/model/ValidationExceptionType
     509: dup
     510: ldc           #79                 // String MEMBER_INVALID_ENUM_VALUE
     512: bipush        32
     514: ldc           #79                 // String MEMBER_INVALID_ENUM_VALUE
     516: invokespecial #15                 // Method "<init>":(Ljava/lang/String;ILjava/lang/String;)V
     519: putstatic     #80                 // Field MEMBER_INVALID_ENUM_VALUE:Lsoftware/amazon/awssdk/services/mediapackagev2/model/ValidationExceptionType;
     522: new           #4                  // class software/amazon/awssdk/services/mediapackagev2/model/ValidationExceptionType
     525: dup
     526: ldc           #81                 // String MEMBER_DOES_NOT_MATCH_PATTERN
     528: bipush        33
     530: ldc           #81                 // String MEMBER_DOES_NOT_MATCH_PATTERN
     532: invokespecial #15                 // Method "<init>":(Ljava/lang/String;ILjava/lang/String;)V
     535: putstatic     #82                 // Field MEMBER_DOES_NOT_MATCH_PATTERN:Lsoftware/amazon/awssdk/services/mediapackagev2/model/ValidationExceptionType;
     538: new           #4                  // class software/amazon/awssdk/services/mediapackagev2/model/ValidationExceptionType
     541: dup
     542: ldc           #83                 // String UNKNOWN_TO_SDK_VERSION
     544: bipush        34
     546: aconst_null
     547: invokespecial #15                 // Method "<init>":(Ljava/lang/String;ILjava/lang/String;)V
     550: putstatic     #10                 // Field UNKNOWN_TO_SDK_VERSION:Lsoftware/amazon/awssdk/services/mediapackagev2/model/ValidationExceptionType;
     553: bipush        35
     555: anewarray     #4                  // class software/amazon/awssdk/services/mediapackagev2/model/ValidationExceptionType
     558: dup
     559: iconst_0
     560: getstatic     #16                 // Field CONTAINER_TYPE_IMMUTABLE:Lsoftware/amazon/awssdk/services/mediapackagev2/model/ValidationExceptionType;
     563: aastore
     564: dup
     565: iconst_1
     566: getstatic     #18                 // Field INVALID_PAGINATION_TOKEN:Lsoftware/amazon/awssdk/services/mediapackagev2/model/ValidationExceptionType;
     569: aastore
     570: dup
     571: iconst_2
     572: getstatic     #20                 // Field INVALID_PAGINATION_MAX_RESULTS:Lsoftware/amazon/awssdk/services/mediapackagev2/model/ValidationExceptionType;
     575: aastore
     576: dup
     577: iconst_3
     578: getstatic     #22                 // Field INVALID_POLICY:Lsoftware/amazon/awssdk/services/mediapackagev2/model/ValidationExceptionType;
     581: aastore
     582: dup
     583: iconst_4
     584: getstatic     #24                 // Field INVALID_ROLE_ARN:Lsoftware/amazon/awssdk/services/mediapackagev2/model/ValidationExceptionType;
     587: aastore
     588: dup
     589: iconst_5
     590: getstatic     #26                 // Field MANIFEST_NAME_COLLISION:Lsoftware/amazon/awssdk/services/mediapackagev2/model/ValidationExceptionType;
     593: aastore
     594: dup
     595: bipush        6
     597: getstatic     #28                 // Field ENCRYPTION_METHOD_CONTAINER_TYPE_MISMATCH:Lsoftware/amazon/awssdk/services/mediapackagev2/model/ValidationExceptionType;
     600: aastore
     601: dup
     602: bipush        7
     604: getstatic     #30                 // Field CENC_IV_INCOMPATIBLE:Lsoftware/amazon/awssdk/services/mediapackagev2/model/ValidationExceptionType;
     607: aastore
     608: dup
     609: bipush        8
     611: getstatic     #32                 // Field ENCRYPTION_CONTRACT_WITHOUT_AUDIO_RENDITION_INCOMPATIBLE:Lsoftware/amazon/awssdk/services/mediapackagev2/model/ValidationExceptionType;
     614: aastore
     615: dup
     616: bipush        9
     618: getstatic     #34                 // Field ENCRYPTION_CONTRACT_UNENCRYPTED:Lsoftware/amazon/awssdk/services/mediapackagev2/model/ValidationExceptionType;
     621: aastore
     622: dup
     623: bipush        10
     625: getstatic     #36                 // Field ENCRYPTION_CONTRACT_SHARED:Lsoftware/amazon/awssdk/services/mediapackagev2/model/ValidationExceptionType;
     628: aastore
     629: dup
     630: bipush        11
     632: getstatic     #38                 // Field NUM_MANIFESTS_LOW:Lsoftware/amazon/awssdk/services/mediapackagev2/model/ValidationExceptionType;
     635: aastore
     636: dup
     637: bipush        12
     639: getstatic     #40                 // Field NUM_MANIFESTS_HIGH:Lsoftware/amazon/awssdk/services/mediapackagev2/model/ValidationExceptionType;
     642: aastore
     643: dup
     644: bipush        13
     646: getstatic     #42                 // Field DRM_SYSTEMS_ENCRYPTION_METHOD_INCOMPATIBLE:Lsoftware/amazon/awssdk/services/mediapackagev2/model/ValidationExceptionType;
     649: aastore
     650: dup
     651: bipush        14
     653: getstatic     #44                 // Field ROLE_ARN_NOT_ASSUMABLE:Lsoftware/amazon/awssdk/services/mediapackagev2/model/ValidationExceptionType;
     656: aastore
     657: dup
     658: bipush        15
     660: getstatic     #46                 // Field ROLE_ARN_LENGTH_OUT_OF_RANGE:Lsoftware/amazon/awssdk/services/mediapackagev2/model/ValidationExceptionType;
     663: aastore
     664: dup
     665: bipush        16
     667: getstatic     #48                 // Field ROLE_ARN_INVALID_FORMAT:Lsoftware/amazon/awssdk/services/mediapackagev2/model/ValidationExceptionType;
     670: aastore
     671: dup
     672: bipush        17
     674: getstatic     #50                 // Field URL_INVALID:Lsoftware/amazon/awssdk/services/mediapackagev2/model/ValidationExceptionType;
     677: aastore
     678: dup
     679: bipush        18
     681: getstatic     #52                 // Field URL_SCHEME:Lsoftware/amazon/awssdk/services/mediapackagev2/model/ValidationExceptionType;
     684: aastore
     685: dup
     686: bipush        19
     688: getstatic     #54                 // Field URL_USER_INFO:Lsoftware/amazon/awssdk/services/mediapackagev2/model/ValidationExceptionType;
     691: aastore
     692: dup
     693: bipush        20
     695: getstatic     #56                 // Field URL_PORT:Lsoftware/amazon/awssdk/services/mediapackagev2/model/ValidationExceptionType;
     698: aastore
     699: dup
     700: bipush        21
     702: getstatic     #58                 // Field URL_UNKNOWN_HOST:Lsoftware/amazon/awssdk/services/mediapackagev2/model/ValidationExceptionType;
     705: aastore
     706: dup
     707: bipush        22
     709: getstatic     #60                 // Field URL_LOCAL_ADDRESS:Lsoftware/amazon/awssdk/services/mediapackagev2/model/ValidationExceptionType;
     712: aastore
     713: dup
     714: bipush        23
     716: getstatic     #62                 // Field URL_LOOPBACK_ADDRESS:Lsoftware/amazon/awssdk/services/mediapackagev2/model/ValidationExceptionType;
     719: aastore
     720: dup
     721: bipush        24
     723: getstatic     #64                 // Field URL_LINK_LOCAL_ADDRESS:Lsoftware/amazon/awssdk/services/mediapackagev2/model/ValidationExceptionType;
     726: aastore
     727: dup
     728: bipush        25
     730: getstatic     #66                 // Field URL_MULTICAST_ADDRESS:Lsoftware/amazon/awssdk/services/mediapackagev2/model/ValidationExceptionType;
     733: aastore
     734: dup
     735: bipush        26
     737: getstatic     #68                 // Field MEMBER_INVALID:Lsoftware/amazon/awssdk/services/mediapackagev2/model/ValidationExceptionType;
     740: aastore
     741: dup
     742: bipush        27
     744: getstatic     #70                 // Field MEMBER_MISSING:Lsoftware/amazon/awssdk/services/mediapackagev2/model/ValidationExceptionType;
     747: aastore
     748: dup
     749: bipush        28
     751: getstatic     #72                 // Field MEMBER_MIN_VALUE:Lsoftware/amazon/awssdk/services/mediapackagev2/model/ValidationExceptionType;
     754: aastore
     755: dup
     756: bipush        29
     758: getstatic     #74                 // Field MEMBER_MAX_VALUE:Lsoftware/amazon/awssdk/services/mediapackagev2/model/ValidationExceptionType;
     761: aastore
     762: dup
     763: bipush        30
     765: getstatic     #76                 // Field MEMBER_MIN_LENGTH:Lsoftware/amazon/awssdk/services/mediapackagev2/model/ValidationExceptionType;
     768: aastore
     769: dup
     770: bipush        31
     772: getstatic     #78                 // Field MEMBER_MAX_LENGTH:Lsoftware/amazon/awssdk/services/mediapackagev2/model/ValidationExceptionType;
     775: aastore
     776: dup
     777: bipush        32
     779: getstatic     #80                 // Field MEMBER_INVALID_ENUM_VALUE:Lsoftware/amazon/awssdk/services/mediapackagev2/model/ValidationExceptionType;
     782: aastore
     783: dup
     784: bipush        33
     786: getstatic     #82                 // Field MEMBER_DOES_NOT_MATCH_PATTERN:Lsoftware/amazon/awssdk/services/mediapackagev2/model/ValidationExceptionType;
     789: aastore
     790: dup
     791: bipush        34
     793: getstatic     #10                 // Field UNKNOWN_TO_SDK_VERSION:Lsoftware/amazon/awssdk/services/mediapackagev2/model/ValidationExceptionType;
     796: aastore
     797: putstatic     #1                  // Field $VALUES:[Lsoftware/amazon/awssdk/services/mediapackagev2/model/ValidationExceptionType;
     800: ldc           #4                  // class software/amazon/awssdk/services/mediapackagev2/model/ValidationExceptionType
     802: invokedynamic #84,  0             // InvokeDynamic #0:apply:()Ljava/util/function/Function;
     807: invokestatic  #85                 // Method software/amazon/awssdk/utils/internal/EnumUtils.uniqueIndex:(Ljava/lang/Class;Ljava/util/function/Function;)Ljava/util/Map;
     810: putstatic     #9                  // Field VALUE_MAP:Ljava/util/Map;
     813: return
}
