Compiled from "EvaluationResult.java"
public interface software.amazon.awssdk.services.iam.model.EvaluationResult$Builder extends software.amazon.awssdk.core.SdkPojo, software.amazon.awssdk.utils.builder.CopyableBuilder<software.amazon.awssdk.services.iam.model.EvaluationResult$Builder, software.amazon.awssdk.services.iam.model.EvaluationResult> {
  public abstract software.amazon.awssdk.services.iam.model.EvaluationResult$Builder evalActionName(java.lang.String);

  public abstract software.amazon.awssdk.services.iam.model.EvaluationResult$Builder evalResourceName(java.lang.String);

  public abstract software.amazon.awssdk.services.iam.model.EvaluationResult$Builder evalDecision(java.lang.String);

  public abstract software.amazon.awssdk.services.iam.model.EvaluationResult$Builder evalDecision(software.amazon.awssdk.services.iam.model.PolicyEvaluationDecisionType);

  public abstract software.amazon.awssdk.services.iam.model.EvaluationResult$Builder matchedStatements(java.util.Collection<software.amazon.awssdk.services.iam.model.Statement>);

  public abstract software.amazon.awssdk.services.iam.model.EvaluationResult$Builder matchedStatements(software.amazon.awssdk.services.iam.model.Statement...);

  public abstract software.amazon.awssdk.services.iam.model.EvaluationResult$Builder matchedStatements(java.util.function.Consumer<software.amazon.awssdk.services.iam.model.Statement$Builder>...);

  public abstract software.amazon.awssdk.services.iam.model.EvaluationResult$Builder missingContextValues(java.util.Collection<java.lang.String>);

  public abstract software.amazon.awssdk.services.iam.model.EvaluationResult$Builder missingContextValues(java.lang.String...);

  public abstract software.amazon.awssdk.services.iam.model.EvaluationResult$Builder organizationsDecisionDetail(software.amazon.awssdk.services.iam.model.OrganizationsDecisionDetail);

  public default software.amazon.awssdk.services.iam.model.EvaluationResult$Builder organizationsDecisionDetail(java.util.function.Consumer<software.amazon.awssdk.services.iam.model.OrganizationsDecisionDetail$Builder>);
    Code:
       0: aload_0
       1: invokestatic  #1                  // Method software/amazon/awssdk/services/iam/model/OrganizationsDecisionDetail.builder:()Lsoftware/amazon/awssdk/services/iam/model/OrganizationsDecisionDetail$Builder;
       4: aload_1
       5: invokeinterface #2,  2            // InterfaceMethod software/amazon/awssdk/services/iam/model/OrganizationsDecisionDetail$Builder.applyMutation:(Ljava/util/function/Consumer;)Lsoftware/amazon/awssdk/utils/builder/SdkBuilder;
      10: checkcast     #3                  // class software/amazon/awssdk/services/iam/model/OrganizationsDecisionDetail$Builder
      13: invokeinterface #4,  1            // InterfaceMethod software/amazon/awssdk/services/iam/model/OrganizationsDecisionDetail$Builder.build:()Ljava/lang/Object;
      18: checkcast     #5                  // class software/amazon/awssdk/services/iam/model/OrganizationsDecisionDetail
      21: invokeinterface #6,  2            // InterfaceMethod organizationsDecisionDetail:(Lsoftware/amazon/awssdk/services/iam/model/OrganizationsDecisionDetail;)Lsoftware/amazon/awssdk/services/iam/model/EvaluationResult$Builder;
      26: areturn

  public abstract software.amazon.awssdk.services.iam.model.EvaluationResult$Builder permissionsBoundaryDecisionDetail(software.amazon.awssdk.services.iam.model.PermissionsBoundaryDecisionDetail);

  public default software.amazon.awssdk.services.iam.model.EvaluationResult$Builder permissionsBoundaryDecisionDetail(java.util.function.Consumer<software.amazon.awssdk.services.iam.model.PermissionsBoundaryDecisionDetail$Builder>);
    Code:
       0: aload_0
       1: invokestatic  #7                  // Method software/amazon/awssdk/services/iam/model/PermissionsBoundaryDecisionDetail.builder:()Lsoftware/amazon/awssdk/services/iam/model/PermissionsBoundaryDecisionDetail$Builder;
       4: aload_1
       5: invokeinterface #8,  2            // InterfaceMethod software/amazon/awssdk/services/iam/model/PermissionsBoundaryDecisionDetail$Builder.applyMutation:(Ljava/util/function/Consumer;)Lsoftware/amazon/awssdk/utils/builder/SdkBuilder;
      10: checkcast     #9                  // class software/amazon/awssdk/services/iam/model/PermissionsBoundaryDecisionDetail$Builder
      13: invokeinterface #10,  1           // InterfaceMethod software/amazon/awssdk/services/iam/model/PermissionsBoundaryDecisionDetail$Builder.build:()Ljava/lang/Object;
      18: checkcast     #11                 // class software/amazon/awssdk/services/iam/model/PermissionsBoundaryDecisionDetail
      21: invokeinterface #12,  2           // InterfaceMethod permissionsBoundaryDecisionDetail:(Lsoftware/amazon/awssdk/services/iam/model/PermissionsBoundaryDecisionDetail;)Lsoftware/amazon/awssdk/services/iam/model/EvaluationResult$Builder;
      26: areturn

  public abstract software.amazon.awssdk.services.iam.model.EvaluationResult$Builder evalDecisionDetailsWithStrings(java.util.Map<java.lang.String, java.lang.String>);

  public abstract software.amazon.awssdk.services.iam.model.EvaluationResult$Builder evalDecisionDetails(java.util.Map<java.lang.String, software.amazon.awssdk.services.iam.model.PolicyEvaluationDecisionType>);

  public abstract software.amazon.awssdk.services.iam.model.EvaluationResult$Builder resourceSpecificResults(java.util.Collection<software.amazon.awssdk.services.iam.model.ResourceSpecificResult>);

  public abstract software.amazon.awssdk.services.iam.model.EvaluationResult$Builder resourceSpecificResults(software.amazon.awssdk.services.iam.model.ResourceSpecificResult...);

  public abstract software.amazon.awssdk.services.iam.model.EvaluationResult$Builder resourceSpecificResults(java.util.function.Consumer<software.amazon.awssdk.services.iam.model.ResourceSpecificResult$Builder>...);
}
