Compiled from "PolicyGrantingServiceAccess.java"
final class software.amazon.awssdk.services.iam.model.PolicyGrantingServiceAccess$BuilderImpl implements software.amazon.awssdk.services.iam.model.PolicyGrantingServiceAccess$Builder {
  private java.lang.String policyName;

  private java.lang.String policyType;

  private java.lang.String policyArn;

  private java.lang.String entityType;

  private java.lang.String entityName;

  private software.amazon.awssdk.services.iam.model.PolicyGrantingServiceAccess$BuilderImpl();
    Code:
       0: aload_0
       1: invokespecial #8                  // Method java/lang/Object."<init>":()V
       4: return

  private software.amazon.awssdk.services.iam.model.PolicyGrantingServiceAccess$BuilderImpl(software.amazon.awssdk.services.iam.model.PolicyGrantingServiceAccess);
    Code:
       0: aload_0
       1: invokespecial #8                  // Method java/lang/Object."<init>":()V
       4: aload_0
       5: aload_1
       6: invokestatic  #9                  // Method software/amazon/awssdk/services/iam/model/PolicyGrantingServiceAccess.access$700:(Lsoftware/amazon/awssdk/services/iam/model/PolicyGrantingServiceAccess;)Ljava/lang/String;
       9: invokevirtual #10                 // Method policyName:(Ljava/lang/String;)Lsoftware/amazon/awssdk/services/iam/model/PolicyGrantingServiceAccess$Builder;
      12: pop
      13: aload_0
      14: aload_1
      15: invokestatic  #11                 // Method software/amazon/awssdk/services/iam/model/PolicyGrantingServiceAccess.access$800:(Lsoftware/amazon/awssdk/services/iam/model/PolicyGrantingServiceAccess;)Ljava/lang/String;
      18: invokevirtual #12                 // Method policyType:(Ljava/lang/String;)Lsoftware/amazon/awssdk/services/iam/model/PolicyGrantingServiceAccess$Builder;
      21: pop
      22: aload_0
      23: aload_1
      24: invokestatic  #13                 // Method software/amazon/awssdk/services/iam/model/PolicyGrantingServiceAccess.access$900:(Lsoftware/amazon/awssdk/services/iam/model/PolicyGrantingServiceAccess;)Ljava/lang/String;
      27: invokevirtual #14                 // Method policyArn:(Ljava/lang/String;)Lsoftware/amazon/awssdk/services/iam/model/PolicyGrantingServiceAccess$Builder;
      30: pop
      31: aload_0
      32: aload_1
      33: invokestatic  #15                 // Method software/amazon/awssdk/services/iam/model/PolicyGrantingServiceAccess.access$1000:(Lsoftware/amazon/awssdk/services/iam/model/PolicyGrantingServiceAccess;)Ljava/lang/String;
      36: invokevirtual #16                 // Method entityType:(Ljava/lang/String;)Lsoftware/amazon/awssdk/services/iam/model/PolicyGrantingServiceAccess$Builder;
      39: pop
      40: aload_0
      41: aload_1
      42: invokestatic  #17                 // Method software/amazon/awssdk/services/iam/model/PolicyGrantingServiceAccess.access$1100:(Lsoftware/amazon/awssdk/services/iam/model/PolicyGrantingServiceAccess;)Ljava/lang/String;
      45: invokevirtual #18                 // Method entityName:(Ljava/lang/String;)Lsoftware/amazon/awssdk/services/iam/model/PolicyGrantingServiceAccess$Builder;
      48: pop
      49: return

  public final java.lang.String getPolicyName();
    Code:
       0: aload_0
       1: getfield      #7                  // Field policyName:Ljava/lang/String;
       4: areturn

  public final software.amazon.awssdk.services.iam.model.PolicyGrantingServiceAccess$Builder policyName(java.lang.String);
    Code:
       0: aload_0
       1: aload_1
       2: putfield      #7                  // Field policyName:Ljava/lang/String;
       5: aload_0
       6: areturn

  public final void setPolicyName(java.lang.String);
    Code:
       0: aload_0
       1: aload_1
       2: putfield      #7                  // Field policyName:Ljava/lang/String;
       5: return

  public final java.lang.String getPolicyType();
    Code:
       0: aload_0
       1: getfield      #6                  // Field policyType:Ljava/lang/String;
       4: areturn

  public final software.amazon.awssdk.services.iam.model.PolicyGrantingServiceAccess$Builder policyType(java.lang.String);
    Code:
       0: aload_0
       1: aload_1
       2: putfield      #6                  // Field policyType:Ljava/lang/String;
       5: aload_0
       6: areturn

  public final software.amazon.awssdk.services.iam.model.PolicyGrantingServiceAccess$Builder policyType(software.amazon.awssdk.services.iam.model.PolicyType);
    Code:
       0: aload_0
       1: aload_1
       2: ifnonnull     9
       5: aconst_null
       6: goto          13
       9: aload_1
      10: invokevirtual #19                 // Method software/amazon/awssdk/services/iam/model/PolicyType.toString:()Ljava/lang/String;
      13: invokevirtual #12                 // Method policyType:(Ljava/lang/String;)Lsoftware/amazon/awssdk/services/iam/model/PolicyGrantingServiceAccess$Builder;
      16: pop
      17: aload_0
      18: areturn

  public final void setPolicyType(java.lang.String);
    Code:
       0: aload_0
       1: aload_1
       2: putfield      #6                  // Field policyType:Ljava/lang/String;
       5: return

  public final java.lang.String getPolicyArn();
    Code:
       0: aload_0
       1: getfield      #5                  // Field policyArn:Ljava/lang/String;
       4: areturn

  public final software.amazon.awssdk.services.iam.model.PolicyGrantingServiceAccess$Builder policyArn(java.lang.String);
    Code:
       0: aload_0
       1: aload_1
       2: putfield      #5                  // Field policyArn:Ljava/lang/String;
       5: aload_0
       6: areturn

  public final void setPolicyArn(java.lang.String);
    Code:
       0: aload_0
       1: aload_1
       2: putfield      #5                  // Field policyArn:Ljava/lang/String;
       5: return

  public final java.lang.String getEntityType();
    Code:
       0: aload_0
       1: getfield      #4                  // Field entityType:Ljava/lang/String;
       4: areturn

  public final software.amazon.awssdk.services.iam.model.PolicyGrantingServiceAccess$Builder entityType(java.lang.String);
    Code:
       0: aload_0
       1: aload_1
       2: putfield      #4                  // Field entityType:Ljava/lang/String;
       5: aload_0
       6: areturn

  public final software.amazon.awssdk.services.iam.model.PolicyGrantingServiceAccess$Builder entityType(software.amazon.awssdk.services.iam.model.PolicyOwnerEntityType);
    Code:
       0: aload_0
       1: aload_1
       2: ifnonnull     9
       5: aconst_null
       6: goto          13
       9: aload_1
      10: invokevirtual #20                 // Method software/amazon/awssdk/services/iam/model/PolicyOwnerEntityType.toString:()Ljava/lang/String;
      13: invokevirtual #16                 // Method entityType:(Ljava/lang/String;)Lsoftware/amazon/awssdk/services/iam/model/PolicyGrantingServiceAccess$Builder;
      16: pop
      17: aload_0
      18: areturn

  public final void setEntityType(java.lang.String);
    Code:
       0: aload_0
       1: aload_1
       2: putfield      #4                  // Field entityType:Ljava/lang/String;
       5: return

  public final java.lang.String getEntityName();
    Code:
       0: aload_0
       1: getfield      #3                  // Field entityName:Ljava/lang/String;
       4: areturn

  public final software.amazon.awssdk.services.iam.model.PolicyGrantingServiceAccess$Builder entityName(java.lang.String);
    Code:
       0: aload_0
       1: aload_1
       2: putfield      #3                  // Field entityName:Ljava/lang/String;
       5: aload_0
       6: areturn

  public final void setEntityName(java.lang.String);
    Code:
       0: aload_0
       1: aload_1
       2: putfield      #3                  // Field entityName:Ljava/lang/String;
       5: return

  public software.amazon.awssdk.services.iam.model.PolicyGrantingServiceAccess build();
    Code:
       0: new           #21                 // class software/amazon/awssdk/services/iam/model/PolicyGrantingServiceAccess
       3: dup
       4: aload_0
       5: aconst_null
       6: invokespecial #22                 // Method software/amazon/awssdk/services/iam/model/PolicyGrantingServiceAccess."<init>":(Lsoftware/amazon/awssdk/services/iam/model/PolicyGrantingServiceAccess$BuilderImpl;Lsoftware/amazon/awssdk/services/iam/model/PolicyGrantingServiceAccess$1;)V
       9: areturn

  public java.util.List<software.amazon.awssdk.core.SdkField<?>> sdkFields();
    Code:
       0: invokestatic  #23                 // Method software/amazon/awssdk/services/iam/model/PolicyGrantingServiceAccess.access$1300:()Ljava/util/List;
       3: areturn

  public java.lang.Object build();
    Code:
       0: aload_0
       1: invokevirtual #24                 // Method build:()Lsoftware/amazon/awssdk/services/iam/model/PolicyGrantingServiceAccess;
       4: areturn

  static java.lang.String access$000(software.amazon.awssdk.services.iam.model.PolicyGrantingServiceAccess$BuilderImpl);
    Code:
       0: aload_0
       1: getfield      #7                  // Field policyName:Ljava/lang/String;
       4: areturn

  static java.lang.String access$100(software.amazon.awssdk.services.iam.model.PolicyGrantingServiceAccess$BuilderImpl);
    Code:
       0: aload_0
       1: getfield      #6                  // Field policyType:Ljava/lang/String;
       4: areturn

  static java.lang.String access$200(software.amazon.awssdk.services.iam.model.PolicyGrantingServiceAccess$BuilderImpl);
    Code:
       0: aload_0
       1: getfield      #5                  // Field policyArn:Ljava/lang/String;
       4: areturn

  static java.lang.String access$300(software.amazon.awssdk.services.iam.model.PolicyGrantingServiceAccess$BuilderImpl);
    Code:
       0: aload_0
       1: getfield      #4                  // Field entityType:Ljava/lang/String;
       4: areturn

  static java.lang.String access$400(software.amazon.awssdk.services.iam.model.PolicyGrantingServiceAccess$BuilderImpl);
    Code:
       0: aload_0
       1: getfield      #3                  // Field entityName:Ljava/lang/String;
       4: areturn

  software.amazon.awssdk.services.iam.model.PolicyGrantingServiceAccess$BuilderImpl(software.amazon.awssdk.services.iam.model.PolicyGrantingServiceAccess, software.amazon.awssdk.services.iam.model.PolicyGrantingServiceAccess$1);
    Code:
       0: aload_0
       1: aload_1
       2: invokespecial #2                  // Method "<init>":(Lsoftware/amazon/awssdk/services/iam/model/PolicyGrantingServiceAccess;)V
       5: return

  software.amazon.awssdk.services.iam.model.PolicyGrantingServiceAccess$BuilderImpl(software.amazon.awssdk.services.iam.model.PolicyGrantingServiceAccess$1);
    Code:
       0: aload_0
       1: invokespecial #1                  // Method "<init>":()V
       4: return
}
