Compiled from "ServerCertificateMetadata.java"
final class software.amazon.awssdk.services.iam.model.ServerCertificateMetadata$BuilderImpl implements software.amazon.awssdk.services.iam.model.ServerCertificateMetadata$Builder {
  private java.lang.String path;

  private java.lang.String serverCertificateName;

  private java.lang.String serverCertificateId;

  private java.lang.String arn;

  private java.time.Instant uploadDate;

  private java.time.Instant expiration;

  private software.amazon.awssdk.services.iam.model.ServerCertificateMetadata$BuilderImpl();
    Code:
       0: aload_0
       1: invokespecial #9                  // Method java/lang/Object."<init>":()V
       4: return

  private software.amazon.awssdk.services.iam.model.ServerCertificateMetadata$BuilderImpl(software.amazon.awssdk.services.iam.model.ServerCertificateMetadata);
    Code:
       0: aload_0
       1: invokespecial #9                  // Method java/lang/Object."<init>":()V
       4: aload_0
       5: aload_1
       6: invokestatic  #10                 // Method software/amazon/awssdk/services/iam/model/ServerCertificateMetadata.access$800:(Lsoftware/amazon/awssdk/services/iam/model/ServerCertificateMetadata;)Ljava/lang/String;
       9: invokevirtual #11                 // Method path:(Ljava/lang/String;)Lsoftware/amazon/awssdk/services/iam/model/ServerCertificateMetadata$Builder;
      12: pop
      13: aload_0
      14: aload_1
      15: invokestatic  #12                 // Method software/amazon/awssdk/services/iam/model/ServerCertificateMetadata.access$900:(Lsoftware/amazon/awssdk/services/iam/model/ServerCertificateMetadata;)Ljava/lang/String;
      18: invokevirtual #13                 // Method serverCertificateName:(Ljava/lang/String;)Lsoftware/amazon/awssdk/services/iam/model/ServerCertificateMetadata$Builder;
      21: pop
      22: aload_0
      23: aload_1
      24: invokestatic  #14                 // Method software/amazon/awssdk/services/iam/model/ServerCertificateMetadata.access$1000:(Lsoftware/amazon/awssdk/services/iam/model/ServerCertificateMetadata;)Ljava/lang/String;
      27: invokevirtual #15                 // Method serverCertificateId:(Ljava/lang/String;)Lsoftware/amazon/awssdk/services/iam/model/ServerCertificateMetadata$Builder;
      30: pop
      31: aload_0
      32: aload_1
      33: invokestatic  #16                 // Method software/amazon/awssdk/services/iam/model/ServerCertificateMetadata.access$1100:(Lsoftware/amazon/awssdk/services/iam/model/ServerCertificateMetadata;)Ljava/lang/String;
      36: invokevirtual #17                 // Method arn:(Ljava/lang/String;)Lsoftware/amazon/awssdk/services/iam/model/ServerCertificateMetadata$Builder;
      39: pop
      40: aload_0
      41: aload_1
      42: invokestatic  #18                 // Method software/amazon/awssdk/services/iam/model/ServerCertificateMetadata.access$1200:(Lsoftware/amazon/awssdk/services/iam/model/ServerCertificateMetadata;)Ljava/time/Instant;
      45: invokevirtual #19                 // Method uploadDate:(Ljava/time/Instant;)Lsoftware/amazon/awssdk/services/iam/model/ServerCertificateMetadata$Builder;
      48: pop
      49: aload_0
      50: aload_1
      51: invokestatic  #20                 // Method software/amazon/awssdk/services/iam/model/ServerCertificateMetadata.access$1300:(Lsoftware/amazon/awssdk/services/iam/model/ServerCertificateMetadata;)Ljava/time/Instant;
      54: invokevirtual #21                 // Method expiration:(Ljava/time/Instant;)Lsoftware/amazon/awssdk/services/iam/model/ServerCertificateMetadata$Builder;
      57: pop
      58: return

  public final java.lang.String getPath();
    Code:
       0: aload_0
       1: getfield      #8                  // Field path:Ljava/lang/String;
       4: areturn

  public final software.amazon.awssdk.services.iam.model.ServerCertificateMetadata$Builder path(java.lang.String);
    Code:
       0: aload_0
       1: aload_1
       2: putfield      #8                  // Field path:Ljava/lang/String;
       5: aload_0
       6: areturn

  public final void setPath(java.lang.String);
    Code:
       0: aload_0
       1: aload_1
       2: putfield      #8                  // Field path:Ljava/lang/String;
       5: return

  public final java.lang.String getServerCertificateName();
    Code:
       0: aload_0
       1: getfield      #7                  // Field serverCertificateName:Ljava/lang/String;
       4: areturn

  public final software.amazon.awssdk.services.iam.model.ServerCertificateMetadata$Builder serverCertificateName(java.lang.String);
    Code:
       0: aload_0
       1: aload_1
       2: putfield      #7                  // Field serverCertificateName:Ljava/lang/String;
       5: aload_0
       6: areturn

  public final void setServerCertificateName(java.lang.String);
    Code:
       0: aload_0
       1: aload_1
       2: putfield      #7                  // Field serverCertificateName:Ljava/lang/String;
       5: return

  public final java.lang.String getServerCertificateId();
    Code:
       0: aload_0
       1: getfield      #6                  // Field serverCertificateId:Ljava/lang/String;
       4: areturn

  public final software.amazon.awssdk.services.iam.model.ServerCertificateMetadata$Builder serverCertificateId(java.lang.String);
    Code:
       0: aload_0
       1: aload_1
       2: putfield      #6                  // Field serverCertificateId:Ljava/lang/String;
       5: aload_0
       6: areturn

  public final void setServerCertificateId(java.lang.String);
    Code:
       0: aload_0
       1: aload_1
       2: putfield      #6                  // Field serverCertificateId:Ljava/lang/String;
       5: return

  public final java.lang.String getArn();
    Code:
       0: aload_0
       1: getfield      #5                  // Field arn:Ljava/lang/String;
       4: areturn

  public final software.amazon.awssdk.services.iam.model.ServerCertificateMetadata$Builder arn(java.lang.String);
    Code:
       0: aload_0
       1: aload_1
       2: putfield      #5                  // Field arn:Ljava/lang/String;
       5: aload_0
       6: areturn

  public final void setArn(java.lang.String);
    Code:
       0: aload_0
       1: aload_1
       2: putfield      #5                  // Field arn:Ljava/lang/String;
       5: return

  public final java.time.Instant getUploadDate();
    Code:
       0: aload_0
       1: getfield      #4                  // Field uploadDate:Ljava/time/Instant;
       4: areturn

  public final software.amazon.awssdk.services.iam.model.ServerCertificateMetadata$Builder uploadDate(java.time.Instant);
    Code:
       0: aload_0
       1: aload_1
       2: putfield      #4                  // Field uploadDate:Ljava/time/Instant;
       5: aload_0
       6: areturn

  public final void setUploadDate(java.time.Instant);
    Code:
       0: aload_0
       1: aload_1
       2: putfield      #4                  // Field uploadDate:Ljava/time/Instant;
       5: return

  public final java.time.Instant getExpiration();
    Code:
       0: aload_0
       1: getfield      #3                  // Field expiration:Ljava/time/Instant;
       4: areturn

  public final software.amazon.awssdk.services.iam.model.ServerCertificateMetadata$Builder expiration(java.time.Instant);
    Code:
       0: aload_0
       1: aload_1
       2: putfield      #3                  // Field expiration:Ljava/time/Instant;
       5: aload_0
       6: areturn

  public final void setExpiration(java.time.Instant);
    Code:
       0: aload_0
       1: aload_1
       2: putfield      #3                  // Field expiration:Ljava/time/Instant;
       5: return

  public software.amazon.awssdk.services.iam.model.ServerCertificateMetadata build();
    Code:
       0: new           #22                 // class software/amazon/awssdk/services/iam/model/ServerCertificateMetadata
       3: dup
       4: aload_0
       5: aconst_null
       6: invokespecial #23                 // Method software/amazon/awssdk/services/iam/model/ServerCertificateMetadata."<init>":(Lsoftware/amazon/awssdk/services/iam/model/ServerCertificateMetadata$BuilderImpl;Lsoftware/amazon/awssdk/services/iam/model/ServerCertificateMetadata$1;)V
       9: areturn

  public java.util.List<software.amazon.awssdk.core.SdkField<?>> sdkFields();
    Code:
       0: invokestatic  #24                 // Method software/amazon/awssdk/services/iam/model/ServerCertificateMetadata.access$1500:()Ljava/util/List;
       3: areturn

  public java.lang.Object build();
    Code:
       0: aload_0
       1: invokevirtual #25                 // Method build:()Lsoftware/amazon/awssdk/services/iam/model/ServerCertificateMetadata;
       4: areturn

  static java.lang.String access$000(software.amazon.awssdk.services.iam.model.ServerCertificateMetadata$BuilderImpl);
    Code:
       0: aload_0
       1: getfield      #8                  // Field path:Ljava/lang/String;
       4: areturn

  static java.lang.String access$100(software.amazon.awssdk.services.iam.model.ServerCertificateMetadata$BuilderImpl);
    Code:
       0: aload_0
       1: getfield      #7                  // Field serverCertificateName:Ljava/lang/String;
       4: areturn

  static java.lang.String access$200(software.amazon.awssdk.services.iam.model.ServerCertificateMetadata$BuilderImpl);
    Code:
       0: aload_0
       1: getfield      #6                  // Field serverCertificateId:Ljava/lang/String;
       4: areturn

  static java.lang.String access$300(software.amazon.awssdk.services.iam.model.ServerCertificateMetadata$BuilderImpl);
    Code:
       0: aload_0
       1: getfield      #5                  // Field arn:Ljava/lang/String;
       4: areturn

  static java.time.Instant access$400(software.amazon.awssdk.services.iam.model.ServerCertificateMetadata$BuilderImpl);
    Code:
       0: aload_0
       1: getfield      #4                  // Field uploadDate:Ljava/time/Instant;
       4: areturn

  static java.time.Instant access$500(software.amazon.awssdk.services.iam.model.ServerCertificateMetadata$BuilderImpl);
    Code:
       0: aload_0
       1: getfield      #3                  // Field expiration:Ljava/time/Instant;
       4: areturn

  software.amazon.awssdk.services.iam.model.ServerCertificateMetadata$BuilderImpl(software.amazon.awssdk.services.iam.model.ServerCertificateMetadata, software.amazon.awssdk.services.iam.model.ServerCertificateMetadata$1);
    Code:
       0: aload_0
       1: aload_1
       2: invokespecial #2                  // Method "<init>":(Lsoftware/amazon/awssdk/services/iam/model/ServerCertificateMetadata;)V
       5: return

  software.amazon.awssdk.services.iam.model.ServerCertificateMetadata$BuilderImpl(software.amazon.awssdk.services.iam.model.ServerCertificateMetadata$1);
    Code:
       0: aload_0
       1: invokespecial #1                  // Method "<init>":()V
       4: return
}
