Compiled from "LocalDate.java"
public final class org.joda.time.LocalDate$Property extends org.joda.time.field.AbstractReadableInstantFieldProperty {
  private static final long serialVersionUID;

  private transient org.joda.time.LocalDate iInstant;

  private transient org.joda.time.DateTimeField iField;

  org.joda.time.LocalDate$Property(org.joda.time.LocalDate, org.joda.time.DateTimeField);
    Code:
       0: aload_0
       1: invokespecial #1                  // Method org/joda/time/field/AbstractReadableInstantFieldProperty."<init>":()V
       4: aload_0
       5: aload_1
       6: putfield      #2                  // Field iInstant:Lorg/joda/time/LocalDate;
       9: aload_0
      10: aload_2
      11: putfield      #3                  // Field iField:Lorg/joda/time/DateTimeField;
      14: return

  private void writeObject(java.io.ObjectOutputStream) throws java.io.IOException;
    Code:
       0: aload_1
       1: aload_0
       2: getfield      #2                  // Field iInstant:Lorg/joda/time/LocalDate;
       5: invokevirtual #4                  // Method java/io/ObjectOutputStream.writeObject:(Ljava/lang/Object;)V
       8: aload_1
       9: aload_0
      10: getfield      #3                  // Field iField:Lorg/joda/time/DateTimeField;
      13: invokevirtual #5                  // Method org/joda/time/DateTimeField.getType:()Lorg/joda/time/DateTimeFieldType;
      16: invokevirtual #4                  // Method java/io/ObjectOutputStream.writeObject:(Ljava/lang/Object;)V
      19: return

  private void readObject(java.io.ObjectInputStream) throws java.io.IOException, java.lang.ClassNotFoundException;
    Code:
       0: aload_0
       1: aload_1
       2: invokevirtual #6                  // Method java/io/ObjectInputStream.readObject:()Ljava/lang/Object;
       5: checkcast     #7                  // class org/joda/time/LocalDate
       8: putfield      #2                  // Field iInstant:Lorg/joda/time/LocalDate;
      11: aload_1
      12: invokevirtual #6                  // Method java/io/ObjectInputStream.readObject:()Ljava/lang/Object;
      15: checkcast     #8                  // class org/joda/time/DateTimeFieldType
      18: astore_2
      19: aload_0
      20: aload_2
      21: aload_0
      22: getfield      #2                  // Field iInstant:Lorg/joda/time/LocalDate;
      25: invokevirtual #9                  // Method org/joda/time/LocalDate.getChronology:()Lorg/joda/time/Chronology;
      28: invokevirtual #10                 // Method org/joda/time/DateTimeFieldType.getField:(Lorg/joda/time/Chronology;)Lorg/joda/time/DateTimeField;
      31: putfield      #3                  // Field iField:Lorg/joda/time/DateTimeField;
      34: return

  public org.joda.time.DateTimeField getField();
    Code:
       0: aload_0
       1: getfield      #3                  // Field iField:Lorg/joda/time/DateTimeField;
       4: areturn

  protected long getMillis();
    Code:
       0: aload_0
       1: getfield      #2                  // Field iInstant:Lorg/joda/time/LocalDate;
       4: invokevirtual #11                 // Method org/joda/time/LocalDate.getLocalMillis:()J
       7: lreturn

  protected org.joda.time.Chronology getChronology();
    Code:
       0: aload_0
       1: getfield      #2                  // Field iInstant:Lorg/joda/time/LocalDate;
       4: invokevirtual #9                  // Method org/joda/time/LocalDate.getChronology:()Lorg/joda/time/Chronology;
       7: areturn

  public org.joda.time.LocalDate getLocalDate();
    Code:
       0: aload_0
       1: getfield      #2                  // Field iInstant:Lorg/joda/time/LocalDate;
       4: areturn

  public org.joda.time.LocalDate addToCopy(int);
    Code:
       0: aload_0
       1: getfield      #2                  // Field iInstant:Lorg/joda/time/LocalDate;
       4: aload_0
       5: getfield      #3                  // Field iField:Lorg/joda/time/DateTimeField;
       8: aload_0
       9: getfield      #2                  // Field iInstant:Lorg/joda/time/LocalDate;
      12: invokevirtual #11                 // Method org/joda/time/LocalDate.getLocalMillis:()J
      15: iload_1
      16: invokevirtual #12                 // Method org/joda/time/DateTimeField.add:(JI)J
      19: invokevirtual #13                 // Method org/joda/time/LocalDate.withLocalMillis:(J)Lorg/joda/time/LocalDate;
      22: areturn

  public org.joda.time.LocalDate addWrapFieldToCopy(int);
    Code:
       0: aload_0
       1: getfield      #2                  // Field iInstant:Lorg/joda/time/LocalDate;
       4: aload_0
       5: getfield      #3                  // Field iField:Lorg/joda/time/DateTimeField;
       8: aload_0
       9: getfield      #2                  // Field iInstant:Lorg/joda/time/LocalDate;
      12: invokevirtual #11                 // Method org/joda/time/LocalDate.getLocalMillis:()J
      15: iload_1
      16: invokevirtual #14                 // Method org/joda/time/DateTimeField.addWrapField:(JI)J
      19: invokevirtual #13                 // Method org/joda/time/LocalDate.withLocalMillis:(J)Lorg/joda/time/LocalDate;
      22: areturn

  public org.joda.time.LocalDate setCopy(int);
    Code:
       0: aload_0
       1: getfield      #2                  // Field iInstant:Lorg/joda/time/LocalDate;
       4: aload_0
       5: getfield      #3                  // Field iField:Lorg/joda/time/DateTimeField;
       8: aload_0
       9: getfield      #2                  // Field iInstant:Lorg/joda/time/LocalDate;
      12: invokevirtual #11                 // Method org/joda/time/LocalDate.getLocalMillis:()J
      15: iload_1
      16: invokevirtual #15                 // Method org/joda/time/DateTimeField.set:(JI)J
      19: invokevirtual #13                 // Method org/joda/time/LocalDate.withLocalMillis:(J)Lorg/joda/time/LocalDate;
      22: areturn

  public org.joda.time.LocalDate setCopy(java.lang.String, java.util.Locale);
    Code:
       0: aload_0
       1: getfield      #2                  // Field iInstant:Lorg/joda/time/LocalDate;
       4: aload_0
       5: getfield      #3                  // Field iField:Lorg/joda/time/DateTimeField;
       8: aload_0
       9: getfield      #2                  // Field iInstant:Lorg/joda/time/LocalDate;
      12: invokevirtual #11                 // Method org/joda/time/LocalDate.getLocalMillis:()J
      15: aload_1
      16: aload_2
      17: invokevirtual #16                 // Method org/joda/time/DateTimeField.set:(JLjava/lang/String;Ljava/util/Locale;)J
      20: invokevirtual #13                 // Method org/joda/time/LocalDate.withLocalMillis:(J)Lorg/joda/time/LocalDate;
      23: areturn

  public org.joda.time.LocalDate setCopy(java.lang.String);
    Code:
       0: aload_0
       1: aload_1
       2: aconst_null
       3: invokevirtual #17                 // Method setCopy:(Ljava/lang/String;Ljava/util/Locale;)Lorg/joda/time/LocalDate;
       6: areturn

  public org.joda.time.LocalDate withMaximumValue();
    Code:
       0: aload_0
       1: aload_0
       2: invokevirtual #18                 // Method getMaximumValue:()I
       5: invokevirtual #19                 // Method setCopy:(I)Lorg/joda/time/LocalDate;
       8: areturn

  public org.joda.time.LocalDate withMinimumValue();
    Code:
       0: aload_0
       1: aload_0
       2: invokevirtual #20                 // Method getMinimumValue:()I
       5: invokevirtual #19                 // Method setCopy:(I)Lorg/joda/time/LocalDate;
       8: areturn

  public org.joda.time.LocalDate roundFloorCopy();
    Code:
       0: aload_0
       1: getfield      #2                  // Field iInstant:Lorg/joda/time/LocalDate;
       4: aload_0
       5: getfield      #3                  // Field iField:Lorg/joda/time/DateTimeField;
       8: aload_0
       9: getfield      #2                  // Field iInstant:Lorg/joda/time/LocalDate;
      12: invokevirtual #11                 // Method org/joda/time/LocalDate.getLocalMillis:()J
      15: invokevirtual #21                 // Method org/joda/time/DateTimeField.roundFloor:(J)J
      18: invokevirtual #13                 // Method org/joda/time/LocalDate.withLocalMillis:(J)Lorg/joda/time/LocalDate;
      21: areturn

  public org.joda.time.LocalDate roundCeilingCopy();
    Code:
       0: aload_0
       1: getfield      #2                  // Field iInstant:Lorg/joda/time/LocalDate;
       4: aload_0
       5: getfield      #3                  // Field iField:Lorg/joda/time/DateTimeField;
       8: aload_0
       9: getfield      #2                  // Field iInstant:Lorg/joda/time/LocalDate;
      12: invokevirtual #11                 // Method org/joda/time/LocalDate.getLocalMillis:()J
      15: invokevirtual #22                 // Method org/joda/time/DateTimeField.roundCeiling:(J)J
      18: invokevirtual #13                 // Method org/joda/time/LocalDate.withLocalMillis:(J)Lorg/joda/time/LocalDate;
      21: areturn

  public org.joda.time.LocalDate roundHalfFloorCopy();
    Code:
       0: aload_0
       1: getfield      #2                  // Field iInstant:Lorg/joda/time/LocalDate;
       4: aload_0
       5: getfield      #3                  // Field iField:Lorg/joda/time/DateTimeField;
       8: aload_0
       9: getfield      #2                  // Field iInstant:Lorg/joda/time/LocalDate;
      12: invokevirtual #11                 // Method org/joda/time/LocalDate.getLocalMillis:()J
      15: invokevirtual #23                 // Method org/joda/time/DateTimeField.roundHalfFloor:(J)J
      18: invokevirtual #13                 // Method org/joda/time/LocalDate.withLocalMillis:(J)Lorg/joda/time/LocalDate;
      21: areturn

  public org.joda.time.LocalDate roundHalfCeilingCopy();
    Code:
       0: aload_0
       1: getfield      #2                  // Field iInstant:Lorg/joda/time/LocalDate;
       4: aload_0
       5: getfield      #3                  // Field iField:Lorg/joda/time/DateTimeField;
       8: aload_0
       9: getfield      #2                  // Field iInstant:Lorg/joda/time/LocalDate;
      12: invokevirtual #11                 // Method org/joda/time/LocalDate.getLocalMillis:()J
      15: invokevirtual #24                 // Method org/joda/time/DateTimeField.roundHalfCeiling:(J)J
      18: invokevirtual #13                 // Method org/joda/time/LocalDate.withLocalMillis:(J)Lorg/joda/time/LocalDate;
      21: areturn

  public org.joda.time.LocalDate roundHalfEvenCopy();
    Code:
       0: aload_0
       1: getfield      #2                  // Field iInstant:Lorg/joda/time/LocalDate;
       4: aload_0
       5: getfield      #3                  // Field iField:Lorg/joda/time/DateTimeField;
       8: aload_0
       9: getfield      #2                  // Field iInstant:Lorg/joda/time/LocalDate;
      12: invokevirtual #11                 // Method org/joda/time/LocalDate.getLocalMillis:()J
      15: invokevirtual #25                 // Method org/joda/time/DateTimeField.roundHalfEven:(J)J
      18: invokevirtual #13                 // Method org/joda/time/LocalDate.withLocalMillis:(J)Lorg/joda/time/LocalDate;
      21: areturn
}
