Compiled from "ThreadContextDataInjector.java"
public class org.apache.logging.log4j.core.impl.ThreadContextDataInjector$ForCopyOnWriteThreadContextMap implements org.apache.logging.log4j.core.ContextDataInjector {
  private final java.util.List<org.apache.logging.log4j.core.util.ContextDataProvider> providers;

  public org.apache.logging.log4j.core.impl.ThreadContextDataInjector$ForCopyOnWriteThreadContextMap();
    Code:
       0: aload_0
       1: invokespecial #1                  // Method java/lang/Object."<init>":()V
       4: aload_0
       5: invokestatic  #2                  // Method org/apache/logging/log4j/core/impl/ThreadContextDataInjector.access$000:()Ljava/util/List;
       8: putfield      #3                  // Field providers:Ljava/util/List;
      11: return

  public org.apache.logging.log4j.util.StringMap injectContextData(java.util.List<org.apache.logging.log4j.core.config.Property>, org.apache.logging.log4j.util.StringMap);
    Code:
       0: aload_0
       1: getfield      #3                  // Field providers:Ljava/util/List;
       4: invokeinterface #4,  1            // InterfaceMethod java/util/List.size:()I
       9: iconst_1
      10: if_icmpne     45
      13: aload_1
      14: ifnull        26
      17: aload_1
      18: invokeinterface #5,  1            // InterfaceMethod java/util/List.isEmpty:()Z
      23: ifeq          45
      26: aload_0
      27: getfield      #3                  // Field providers:Ljava/util/List;
      30: iconst_0
      31: invokeinterface #6,  2            // InterfaceMethod java/util/List.get:(I)Ljava/lang/Object;
      36: checkcast     #7                  // class org/apache/logging/log4j/core/util/ContextDataProvider
      39: invokeinterface #8,  1            // InterfaceMethod org/apache/logging/log4j/core/util/ContextDataProvider.supplyStringMap:()Lorg/apache/logging/log4j/util/StringMap;
      44: areturn
      45: aload_1
      46: ifnonnull     53
      49: iconst_0
      50: goto          59
      53: aload_1
      54: invokeinterface #4,  1            // InterfaceMethod java/util/List.size:()I
      59: istore_3
      60: aload_0
      61: getfield      #3                  // Field providers:Ljava/util/List;
      64: invokeinterface #4,  1            // InterfaceMethod java/util/List.size:()I
      69: anewarray     #9                  // class org/apache/logging/log4j/util/StringMap
      72: astore        4
      74: iconst_0
      75: istore        5
      77: iload         5
      79: aload_0
      80: getfield      #3                  // Field providers:Ljava/util/List;
      83: invokeinterface #4,  1            // InterfaceMethod java/util/List.size:()I
      88: if_icmpge     134
      91: aload         4
      93: iload         5
      95: aload_0
      96: getfield      #3                  // Field providers:Ljava/util/List;
      99: iload         5
     101: invokeinterface #6,  2            // InterfaceMethod java/util/List.get:(I)Ljava/lang/Object;
     106: checkcast     #7                  // class org/apache/logging/log4j/core/util/ContextDataProvider
     109: invokeinterface #8,  1            // InterfaceMethod org/apache/logging/log4j/core/util/ContextDataProvider.supplyStringMap:()Lorg/apache/logging/log4j/util/StringMap;
     114: aastore
     115: iload_3
     116: aload         4
     118: iload         5
     120: aaload
     121: invokeinterface #10,  1           // InterfaceMethod org/apache/logging/log4j/util/StringMap.size:()I
     126: iadd
     127: istore_3
     128: iinc          5, 1
     131: goto          77
     134: iload_3
     135: invokestatic  #11                 // Method org/apache/logging/log4j/core/impl/ContextDataFactory.createContextData:(I)Lorg/apache/logging/log4j/util/StringMap;
     138: astore        5
     140: aload_1
     141: aload         5
     143: invokestatic  #12                 // Method org/apache/logging/log4j/core/impl/ThreadContextDataInjector.copyProperties:(Ljava/util/List;Lorg/apache/logging/log4j/util/StringMap;)V
     146: aload         4
     148: astore        6
     150: aload         6
     152: arraylength
     153: istore        7
     155: iconst_0
     156: istore        8
     158: iload         8
     160: iload         7
     162: if_icmpge     187
     165: aload         6
     167: iload         8
     169: aaload
     170: astore        9
     172: aload         5
     174: aload         9
     176: invokeinterface #13,  2           // InterfaceMethod org/apache/logging/log4j/util/StringMap.putAll:(Lorg/apache/logging/log4j/util/ReadOnlyStringMap;)V
     181: iinc          8, 1
     184: goto          158
     187: aload         5
     189: areturn

  public org.apache.logging.log4j.util.ReadOnlyStringMap rawContextData();
    Code:
       0: invokestatic  #14                 // Method org/apache/logging/log4j/ThreadContext.getThreadContextMap:()Lorg/apache/logging/log4j/spi/ReadOnlyThreadContextMap;
       3: invokeinterface #15,  1           // InterfaceMethod org/apache/logging/log4j/spi/ReadOnlyThreadContextMap.getReadOnlyContextData:()Lorg/apache/logging/log4j/util/StringMap;
       8: areturn
}
