Compiled from "UserTransactionFactory.java"
public class com.arjuna.mw.wst11.UserTransactionFactory {
  public com.arjuna.mw.wst11.UserTransactionFactory();
    Code:
       0: aload_0
       1: invokespecial #1                  // Method java/lang/Object."<init>":()V
       4: return

  public static com.arjuna.mw.wst11.UserTransaction userTransaction();
    Code:
       0: invokestatic  #2                  // Method com/arjuna/mw/wst11/UserTransaction.getUserTransaction:()Lcom/arjuna/mw/wst11/UserTransaction;
       3: areturn

  public static com.arjuna.mw.wst11.UserTransaction userSubordinateTransaction();
    Code:
       0: invokestatic  #2                  // Method com/arjuna/mw/wst11/UserTransaction.getUserTransaction:()Lcom/arjuna/mw/wst11/UserTransaction;
       3: invokevirtual #3                  // Method com/arjuna/mw/wst11/UserTransaction.getUserSubordinateTransaction:()Lcom/arjuna/mw/wst11/UserTransaction;
       6: areturn
}
