Compiled from "WebSocketReaderServlet.java"
public class org.apache.pulsar.websocket.WebSocketReaderServlet extends org.eclipse.jetty.websocket.servlet.WebSocketServlet {
  private static final transient long serialVersionUID;

  public static final java.lang.String SERVLET_PATH;

  public static final java.lang.String SERVLET_PATH_V2;

  private final transient org.apache.pulsar.websocket.WebSocketService service;

  public org.apache.pulsar.websocket.WebSocketReaderServlet(org.apache.pulsar.websocket.WebSocketService);
    Code:
       0: aload_0
       1: invokespecial #1                  // Method org/eclipse/jetty/websocket/servlet/WebSocketServlet."<init>":()V
       4: aload_0
       5: aload_1
       6: putfield      #2                  // Field service:Lorg/apache/pulsar/websocket/WebSocketService;
       9: return

  public void configure(org.eclipse.jetty.websocket.servlet.WebSocketServletFactory);
    Code:
       0: aload_1
       1: invokeinterface #3,  1            // InterfaceMethod org/eclipse/jetty/websocket/servlet/WebSocketServletFactory.getPolicy:()Lorg/eclipse/jetty/websocket/api/WebSocketPolicy;
       6: aload_0
       7: getfield      #2                  // Field service:Lorg/apache/pulsar/websocket/WebSocketService;
      10: invokevirtual #4                  // Method org/apache/pulsar/websocket/WebSocketService.getConfig:()Lorg/apache/pulsar/broker/ServiceConfiguration;
      13: invokevirtual #5                  // Method org/apache/pulsar/broker/ServiceConfiguration.getWebSocketMaxTextFrameSize:()I
      16: invokevirtual #6                  // Method org/eclipse/jetty/websocket/api/WebSocketPolicy.setMaxTextMessageSize:(I)V
      19: aload_0
      20: getfield      #2                  // Field service:Lorg/apache/pulsar/websocket/WebSocketService;
      23: invokevirtual #4                  // Method org/apache/pulsar/websocket/WebSocketService.getConfig:()Lorg/apache/pulsar/broker/ServiceConfiguration;
      26: invokevirtual #7                  // Method org/apache/pulsar/broker/ServiceConfiguration.getWebSocketSessionIdleTimeoutMillis:()I
      29: ifle          52
      32: aload_1
      33: invokeinterface #3,  1            // InterfaceMethod org/eclipse/jetty/websocket/servlet/WebSocketServletFactory.getPolicy:()Lorg/eclipse/jetty/websocket/api/WebSocketPolicy;
      38: aload_0
      39: getfield      #2                  // Field service:Lorg/apache/pulsar/websocket/WebSocketService;
      42: invokevirtual #4                  // Method org/apache/pulsar/websocket/WebSocketService.getConfig:()Lorg/apache/pulsar/broker/ServiceConfiguration;
      45: invokevirtual #7                  // Method org/apache/pulsar/broker/ServiceConfiguration.getWebSocketSessionIdleTimeoutMillis:()I
      48: i2l
      49: invokevirtual #8                  // Method org/eclipse/jetty/websocket/api/WebSocketPolicy.setIdleTimeout:(J)V
      52: aload_1
      53: aload_0
      54: invokedynamic #9,  0              // InvokeDynamic #0:createWebSocket:(Lorg/apache/pulsar/websocket/WebSocketReaderServlet;)Lorg/eclipse/jetty/websocket/servlet/WebSocketCreator;
      59: invokeinterface #10,  2           // InterfaceMethod org/eclipse/jetty/websocket/servlet/WebSocketServletFactory.setCreator:(Lorg/eclipse/jetty/websocket/servlet/WebSocketCreator;)V
      64: return

  private java.lang.Object lambda$configure$0(org.eclipse.jetty.websocket.servlet.ServletUpgradeRequest, org.eclipse.jetty.websocket.servlet.ServletUpgradeResponse);
    Code:
       0: new           #11                 // class org/apache/pulsar/websocket/ReaderHandler
       3: dup
       4: aload_0
       5: getfield      #2                  // Field service:Lorg/apache/pulsar/websocket/WebSocketService;
       8: aload_1
       9: invokevirtual #12                 // Method org/eclipse/jetty/websocket/servlet/ServletUpgradeRequest.getHttpServletRequest:()Ljavax/servlet/http/HttpServletRequest;
      12: aload_2
      13: invokespecial #13                 // Method org/apache/pulsar/websocket/ReaderHandler."<init>":(Lorg/apache/pulsar/websocket/WebSocketService;Ljavax/servlet/http/HttpServletRequest;Lorg/eclipse/jetty/websocket/servlet/ServletUpgradeResponse;)V
      16: areturn
}
