Compiled from "AbstractManipulationCriteriaQuery.java"
class org.hibernate.query.criteria.internal.AbstractManipulationCriteriaQuery$1$1 implements org.hibernate.jpa.spi.HibernateEntityManagerImplementor$QueryOptions {
  final java.util.Map val$implicitParameterTypes;

  final org.hibernate.query.criteria.internal.AbstractManipulationCriteriaQuery$1 this$1;

  org.hibernate.query.criteria.internal.AbstractManipulationCriteriaQuery$1$1(org.hibernate.query.criteria.internal.AbstractManipulationCriteriaQuery$1, java.util.Map);
    Code:
       0: aload_0
       1: aload_1
       2: putfield      #1                  // Field this$1:Lorg/hibernate/query/criteria/internal/AbstractManipulationCriteriaQuery$1;
       5: aload_0
       6: aload_2
       7: putfield      #2                  // Field val$implicitParameterTypes:Ljava/util/Map;
      10: aload_0
      11: invokespecial #3                  // Method java/lang/Object."<init>":()V
      14: return

  public java.util.List<org.hibernate.query.criteria.internal.ValueHandlerFactory$ValueHandler> getValueHandlers();
    Code:
       0: aconst_null
       1: areturn

  public java.util.Map<java.lang.String, java.lang.Class> getNamedParameterExplicitTypes();
    Code:
       0: aload_0
       1: getfield      #2                  // Field val$implicitParameterTypes:Ljava/util/Map;
       4: areturn

  public org.hibernate.jpa.spi.HibernateEntityManagerImplementor$QueryOptions$ResultMetadataValidator getResultMetadataValidator();
    Code:
       0: aconst_null
       1: areturn
}
