Compiled from "TransactionLocal.java"
public class org.jboss.tm.TransactionLocal {
  private static final java.lang.Object NULL_VALUE;

  protected final javax.transaction.TransactionManager transactionManager;

  protected org.jboss.tm.TransactionLocalDelegate delegate;

  public org.jboss.tm.TransactionLocal();
    Code:
       0: aload_0
       1: invokespecial #1                  // Method java/lang/Object."<init>":()V
       4: aload_0
       5: invokestatic  #2                  // Method org/jboss/tm/TransactionManagerLocator.locateTransactionManager:()Ljavax/transaction/TransactionManager;
       8: putfield      #3                  // Field transactionManager:Ljavax/transaction/TransactionManager;
      11: aload_0
      12: invokevirtual #4                  // Method initDelegate:()V
      15: return

  public org.jboss.tm.TransactionLocal(javax.transaction.TransactionManager);
    Code:
       0: aload_0
       1: invokespecial #1                  // Method java/lang/Object."<init>":()V
       4: aload_1
       5: ifnonnull     18
       8: new           #5                  // class java/lang/IllegalArgumentException
      11: dup
      12: ldc           #6                  // String Null transaction manager
      14: invokespecial #7                  // Method java/lang/IllegalArgumentException."<init>":(Ljava/lang/String;)V
      17: athrow
      18: aload_0
      19: aload_1
      20: putfield      #3                  // Field transactionManager:Ljavax/transaction/TransactionManager;
      23: aload_0
      24: invokevirtual #4                  // Method initDelegate:()V
      27: return

  public void lock() throws java.lang.InterruptedException;
    Code:
       0: aload_0
       1: aload_0
       2: invokevirtual #8                  // Method getTransaction:()Ljavax/transaction/Transaction;
       5: invokevirtual #9                  // Method lock:(Ljavax/transaction/Transaction;)V
       8: return

  public void lock(javax.transaction.Transaction) throws java.lang.InterruptedException;
    Code:
       0: aload_1
       1: ifnonnull     5
       4: return
       5: aload_0
       6: getfield      #10                 // Field delegate:Lorg/jboss/tm/TransactionLocalDelegate;
       9: aload_0
      10: aload_1
      11: invokeinterface #11,  3           // InterfaceMethod org/jboss/tm/TransactionLocalDelegate.lock:(Lorg/jboss/tm/TransactionLocal;Ljavax/transaction/Transaction;)V
      16: return

  public void unlock();
    Code:
       0: aload_0
       1: aload_0
       2: invokevirtual #8                  // Method getTransaction:()Ljavax/transaction/Transaction;
       5: invokevirtual #12                 // Method unlock:(Ljavax/transaction/Transaction;)V
       8: return

  public void unlock(javax.transaction.Transaction);
    Code:
       0: aload_1
       1: ifnonnull     5
       4: return
       5: aload_0
       6: getfield      #10                 // Field delegate:Lorg/jboss/tm/TransactionLocalDelegate;
       9: aload_0
      10: aload_1
      11: invokeinterface #13,  3           // InterfaceMethod org/jboss/tm/TransactionLocalDelegate.unlock:(Lorg/jboss/tm/TransactionLocal;Ljavax/transaction/Transaction;)V
      16: return

  protected java.lang.Object initialValue();
    Code:
       0: aconst_null
       1: areturn

  protected java.lang.Object getValue(javax.transaction.Transaction);
    Code:
       0: aload_0
       1: getfield      #10                 // Field delegate:Lorg/jboss/tm/TransactionLocalDelegate;
       4: aload_0
       5: aload_1
       6: invokeinterface #14,  3           // InterfaceMethod org/jboss/tm/TransactionLocalDelegate.getValue:(Lorg/jboss/tm/TransactionLocal;Ljavax/transaction/Transaction;)Ljava/lang/Object;
      11: areturn

  protected void storeValue(javax.transaction.Transaction, java.lang.Object);
    Code:
       0: aload_0
       1: getfield      #10                 // Field delegate:Lorg/jboss/tm/TransactionLocalDelegate;
       4: aload_0
       5: aload_1
       6: aload_2
       7: invokeinterface #15,  4           // InterfaceMethod org/jboss/tm/TransactionLocalDelegate.storeValue:(Lorg/jboss/tm/TransactionLocal;Ljavax/transaction/Transaction;Ljava/lang/Object;)V
      12: return

  protected boolean containsValue(javax.transaction.Transaction);
    Code:
       0: aload_0
       1: getfield      #10                 // Field delegate:Lorg/jboss/tm/TransactionLocalDelegate;
       4: aload_0
       5: aload_1
       6: invokeinterface #16,  3           // InterfaceMethod org/jboss/tm/TransactionLocalDelegate.containsValue:(Lorg/jboss/tm/TransactionLocal;Ljavax/transaction/Transaction;)Z
      11: ireturn

  public java.lang.Object get();
    Code:
       0: aload_0
       1: aload_0
       2: invokevirtual #8                  // Method getTransaction:()Ljavax/transaction/Transaction;
       5: invokevirtual #17                 // Method get:(Ljavax/transaction/Transaction;)Ljava/lang/Object;
       8: areturn

  public java.lang.Object get(javax.transaction.Transaction);
    Code:
       0: aload_1
       1: ifnonnull     9
       4: aload_0
       5: invokevirtual #18                 // Method initialValue:()Ljava/lang/Object;
       8: areturn
       9: aload_0
      10: aload_1
      11: invokevirtual #19                 // Method getValue:(Ljavax/transaction/Transaction;)Ljava/lang/Object;
      14: astore_2
      15: aload_2
      16: ifnonnull     47
      19: aload_0
      20: invokevirtual #18                 // Method initialValue:()Ljava/lang/Object;
      23: astore_2
      24: aload_2
      25: ifnonnull     32
      28: getstatic     #20                 // Field NULL_VALUE:Ljava/lang/Object;
      31: astore_2
      32: aload_0
      33: aload_1
      34: aload_2
      35: invokevirtual #21                 // Method storeValue:(Ljavax/transaction/Transaction;Ljava/lang/Object;)V
      38: goto          47
      41: astore_3
      42: aload_0
      43: invokevirtual #18                 // Method initialValue:()Ljava/lang/Object;
      46: areturn
      47: aload_2
      48: getstatic     #20                 // Field NULL_VALUE:Ljava/lang/Object;
      51: if_acmpne     56
      54: aconst_null
      55: areturn
      56: aload_2
      57: areturn
    Exception table:
       from    to  target type
          32    38    41   Class java/lang/IllegalStateException

  public void set(java.lang.Object);
    Code:
       0: aload_0
       1: aload_0
       2: invokevirtual #8                  // Method getTransaction:()Ljavax/transaction/Transaction;
       5: aload_1
       6: invokevirtual #23                 // Method set:(Ljavax/transaction/Transaction;Ljava/lang/Object;)V
       9: return

  public void set(javax.transaction.Transaction, java.lang.Object);
    Code:
       0: aload_1
       1: ifnonnull     14
       4: new           #22                 // class java/lang/IllegalStateException
       7: dup
       8: ldc           #24                 // String there is no transaction
      10: invokespecial #25                 // Method java/lang/IllegalStateException."<init>":(Ljava/lang/String;)V
      13: athrow
      14: aload_0
      15: aload_1
      16: invokevirtual #26                 // Method containsValue:(Ljavax/transaction/Transaction;)Z
      19: ifne          27
      22: aload_0
      23: invokevirtual #18                 // Method initialValue:()Ljava/lang/Object;
      26: pop
      27: aload_2
      28: ifnonnull     35
      31: getstatic     #20                 // Field NULL_VALUE:Ljava/lang/Object;
      34: astore_2
      35: aload_0
      36: aload_1
      37: aload_2
      38: invokevirtual #21                 // Method storeValue:(Ljavax/transaction/Transaction;Ljava/lang/Object;)V
      41: return

  public javax.transaction.Transaction getTransaction();
    Code:
       0: aload_0
       1: getfield      #3                  // Field transactionManager:Ljavax/transaction/TransactionManager;
       4: invokeinterface #27,  1           // InterfaceMethod javax/transaction/TransactionManager.getTransaction:()Ljavax/transaction/Transaction;
       9: areturn
      10: astore_1
      11: new           #22                 // class java/lang/IllegalStateException
      14: dup
      15: new           #29                 // class java/lang/StringBuilder
      18: dup
      19: invokespecial #30                 // Method java/lang/StringBuilder."<init>":()V
      22: ldc           #31                 // String An error occured while getting the transaction associated with the current thread:
      24: invokevirtual #32                 // Method java/lang/StringBuilder.append:(Ljava/lang/String;)Ljava/lang/StringBuilder;
      27: aload_1
      28: invokevirtual #33                 // Method java/lang/StringBuilder.append:(Ljava/lang/Object;)Ljava/lang/StringBuilder;
      31: invokevirtual #34                 // Method java/lang/StringBuilder.toString:()Ljava/lang/String;
      34: invokespecial #25                 // Method java/lang/IllegalStateException."<init>":(Ljava/lang/String;)V
      37: athrow
    Exception table:
       from    to  target type
           0     9    10   Class javax/transaction/SystemException

  protected void initDelegate();
    Code:
       0: aload_0
       1: getfield      #3                  // Field transactionManager:Ljavax/transaction/TransactionManager;
       4: instanceof    #35                 // class org/jboss/tm/TransactionLocalDelegate
       7: ifeq          24
      10: aload_0
      11: aload_0
      12: getfield      #3                  // Field transactionManager:Ljavax/transaction/TransactionManager;
      15: checkcast     #35                 // class org/jboss/tm/TransactionLocalDelegate
      18: putfield      #10                 // Field delegate:Lorg/jboss/tm/TransactionLocalDelegate;
      21: goto          39
      24: aload_0
      25: new           #36                 // class org/jboss/tm/TransactionLocalDelegateImpl
      28: dup
      29: aload_0
      30: getfield      #3                  // Field transactionManager:Ljavax/transaction/TransactionManager;
      33: invokespecial #37                 // Method org/jboss/tm/TransactionLocalDelegateImpl."<init>":(Ljavax/transaction/TransactionManager;)V
      36: putfield      #10                 // Field delegate:Lorg/jboss/tm/TransactionLocalDelegate;
      39: return

  static {};
    Code:
       0: new           #38                 // class java/lang/Object
       3: dup
       4: invokespecial #1                  // Method java/lang/Object."<init>":()V
       7: putstatic     #20                 // Field NULL_VALUE:Ljava/lang/Object;
      10: return
}
