Compiled from "AttCertValidityPeriod.java"
public class org.apache.kerby.x509.type.AttCertValidityPeriod extends org.apache.kerby.asn1.type.Asn1SequenceType {
  static org.apache.kerby.asn1.Asn1FieldInfo[] fieldInfos;

  public org.apache.kerby.x509.type.AttCertValidityPeriod();
    Code:
       0: aload_0
       1: getstatic     #1                  // Field fieldInfos:[Lorg/apache/kerby/asn1/Asn1FieldInfo;
       4: invokespecial #2                  // Method org/apache/kerby/asn1/type/Asn1SequenceType."<init>":([Lorg/apache/kerby/asn1/Asn1FieldInfo;)V
       7: return

  public org.apache.kerby.asn1.type.Asn1GeneralizedTime getNotBeforeTime();
    Code:
       0: aload_0
       1: getstatic     #3                  // Field org/apache/kerby/x509/type/AttCertValidityPeriod$AttCertValidityPeriodField.NOT_BEFORE:Lorg/apache/kerby/x509/type/AttCertValidityPeriod$AttCertValidityPeriodField;
       4: ldc_w         #4                  // class org/apache/kerby/asn1/type/Asn1GeneralizedTime
       7: invokevirtual #5                  // Method getFieldAs:(Lorg/apache/kerby/asn1/EnumType;Ljava/lang/Class;)Lorg/apache/kerby/asn1/type/Asn1Type;
      10: checkcast     #4                  // class org/apache/kerby/asn1/type/Asn1GeneralizedTime
      13: areturn

  public void setNotBeforeTime(org.apache.kerby.asn1.type.Asn1GeneralizedTime);
    Code:
       0: aload_0
       1: getstatic     #3                  // Field org/apache/kerby/x509/type/AttCertValidityPeriod$AttCertValidityPeriodField.NOT_BEFORE:Lorg/apache/kerby/x509/type/AttCertValidityPeriod$AttCertValidityPeriodField;
       4: aload_1
       5: invokevirtual #6                  // Method setFieldAs:(Lorg/apache/kerby/asn1/EnumType;Lorg/apache/kerby/asn1/type/Asn1Type;)V
       8: return

  public org.apache.kerby.asn1.type.Asn1GeneralizedTime getNotAfterTime();
    Code:
       0: aload_0
       1: getstatic     #7                  // Field org/apache/kerby/x509/type/AttCertValidityPeriod$AttCertValidityPeriodField.NOT_AFTER:Lorg/apache/kerby/x509/type/AttCertValidityPeriod$AttCertValidityPeriodField;
       4: ldc_w         #4                  // class org/apache/kerby/asn1/type/Asn1GeneralizedTime
       7: invokevirtual #5                  // Method getFieldAs:(Lorg/apache/kerby/asn1/EnumType;Ljava/lang/Class;)Lorg/apache/kerby/asn1/type/Asn1Type;
      10: checkcast     #4                  // class org/apache/kerby/asn1/type/Asn1GeneralizedTime
      13: areturn

  public void setNotAfterTime(org.apache.kerby.asn1.type.Asn1GeneralizedTime);
    Code:
       0: aload_0
       1: getstatic     #7                  // Field org/apache/kerby/x509/type/AttCertValidityPeriod$AttCertValidityPeriodField.NOT_AFTER:Lorg/apache/kerby/x509/type/AttCertValidityPeriod$AttCertValidityPeriodField;
       4: aload_1
       5: invokevirtual #6                  // Method setFieldAs:(Lorg/apache/kerby/asn1/EnumType;Lorg/apache/kerby/asn1/type/Asn1Type;)V
       8: return

  static {};
    Code:
       0: iconst_2
       1: anewarray     #8                  // class org/apache/kerby/asn1/Asn1FieldInfo
       4: dup
       5: iconst_0
       6: new           #8                  // class org/apache/kerby/asn1/Asn1FieldInfo
       9: dup
      10: getstatic     #3                  // Field org/apache/kerby/x509/type/AttCertValidityPeriod$AttCertValidityPeriodField.NOT_BEFORE:Lorg/apache/kerby/x509/type/AttCertValidityPeriod$AttCertValidityPeriodField;
      13: ldc_w         #9                  // class org/apache/kerby/asn1/type/Asn1UtcTime
      16: invokespecial #10                 // Method org/apache/kerby/asn1/Asn1FieldInfo."<init>":(Lorg/apache/kerby/asn1/EnumType;Ljava/lang/Class;)V
      19: aastore
      20: dup
      21: iconst_1
      22: new           #8                  // class org/apache/kerby/asn1/Asn1FieldInfo
      25: dup
      26: getstatic     #7                  // Field org/apache/kerby/x509/type/AttCertValidityPeriod$AttCertValidityPeriodField.NOT_AFTER:Lorg/apache/kerby/x509/type/AttCertValidityPeriod$AttCertValidityPeriodField;
      29: ldc_w         #9                  // class org/apache/kerby/asn1/type/Asn1UtcTime
      32: invokespecial #10                 // Method org/apache/kerby/asn1/Asn1FieldInfo."<init>":(Lorg/apache/kerby/asn1/EnumType;Ljava/lang/Class;)V
      35: aastore
      36: putstatic     #1                  // Field fieldInfos:[Lorg/apache/kerby/asn1/Asn1FieldInfo;
      39: return
}
