Compiled from "CacheUtilities.java"
public class org.glassfish.hk2.utilities.cache.CacheUtilities {
  public org.glassfish.hk2.utilities.cache.CacheUtilities();
    Code:
       0: aload_0
       1: invokespecial #1                  // Method java/lang/Object."<init>":()V
       4: return

  public static <K, V> org.glassfish.hk2.utilities.cache.WeakCARCache<K, V> createWeakCARCache(org.glassfish.hk2.utilities.cache.Computable<K, V>, int, boolean);
    Code:
       0: new           #2                  // class org/glassfish/hk2/utilities/cache/internal/WeakCARCacheImpl
       3: dup
       4: aload_0
       5: iload_1
       6: iload_2
       7: invokespecial #3                  // Method org/glassfish/hk2/utilities/cache/internal/WeakCARCacheImpl."<init>":(Lorg/glassfish/hk2/utilities/cache/Computable;IZ)V
      10: areturn
}
