Compiled from "LRUHybridCache.java"
class org.glassfish.hk2.utilities.cache.LRUHybridCache$OriginThreadAwareFuture$1 implements java.util.concurrent.Callable<org.glassfish.hk2.utilities.cache.HybridCacheEntry<V>> {
  final org.glassfish.hk2.utilities.cache.LRUHybridCache val$this$0;

  final java.lang.Object val$key;

  final org.glassfish.hk2.utilities.cache.LRUHybridCache$OriginThreadAwareFuture this$1;

  org.glassfish.hk2.utilities.cache.LRUHybridCache$OriginThreadAwareFuture$1(org.glassfish.hk2.utilities.cache.LRUHybridCache$OriginThreadAwareFuture, org.glassfish.hk2.utilities.cache.LRUHybridCache, java.lang.Object);
    Code:
       0: aload_0
       1: aload_1
       2: putfield      #1                  // Field this$1:Lorg/glassfish/hk2/utilities/cache/LRUHybridCache$OriginThreadAwareFuture;
       5: aload_0
       6: aload_2
       7: putfield      #2                  // Field val$this$0:Lorg/glassfish/hk2/utilities/cache/LRUHybridCache;
      10: aload_0
      11: aload_3
      12: putfield      #3                  // Field val$key:Ljava/lang/Object;
      15: aload_0
      16: invokespecial #4                  // Method java/lang/Object."<init>":()V
      19: return

  public org.glassfish.hk2.utilities.cache.HybridCacheEntry<V> call() throws java.lang.Exception;
    Code:
       0: aload_0
       1: getfield      #1                  // Field this$1:Lorg/glassfish/hk2/utilities/cache/LRUHybridCache$OriginThreadAwareFuture;
       4: getfield      #5                  // Field org/glassfish/hk2/utilities/cache/LRUHybridCache$OriginThreadAwareFuture.this$0:Lorg/glassfish/hk2/utilities/cache/LRUHybridCache;
       7: invokestatic  #6                  // Method org/glassfish/hk2/utilities/cache/LRUHybridCache.access$000:(Lorg/glassfish/hk2/utilities/cache/LRUHybridCache;)Lorg/glassfish/hk2/utilities/cache/Computable;
      10: aload_0
      11: getfield      #3                  // Field val$key:Ljava/lang/Object;
      14: invokeinterface #7,  2            // InterfaceMethod org/glassfish/hk2/utilities/cache/Computable.compute:(Ljava/lang/Object;)Ljava/lang/Object;
      19: checkcast     #8                  // class org/glassfish/hk2/utilities/cache/HybridCacheEntry
      22: astore_1
      23: aload_1
      24: astore_2
      25: aload_0
      26: getfield      #1                  // Field this$1:Lorg/glassfish/hk2/utilities/cache/LRUHybridCache$OriginThreadAwareFuture;
      29: ldc2_w        #9                  // long -1l
      32: invokestatic  #11                 // Method org/glassfish/hk2/utilities/cache/LRUHybridCache$OriginThreadAwareFuture.access$102:(Lorg/glassfish/hk2/utilities/cache/LRUHybridCache$OriginThreadAwareFuture;J)J
      35: pop2
      36: aload_2
      37: areturn
      38: astore_3
      39: aload_0
      40: getfield      #1                  // Field this$1:Lorg/glassfish/hk2/utilities/cache/LRUHybridCache$OriginThreadAwareFuture;
      43: ldc2_w        #9                  // long -1l
      46: invokestatic  #11                 // Method org/glassfish/hk2/utilities/cache/LRUHybridCache$OriginThreadAwareFuture.access$102:(Lorg/glassfish/hk2/utilities/cache/LRUHybridCache$OriginThreadAwareFuture;J)J
      49: pop2
      50: aload_3
      51: athrow
    Exception table:
       from    to  target type
           0    25    38   any

  public java.lang.Object call() throws java.lang.Exception;
    Code:
       0: aload_0
       1: invokevirtual #12                 // Method call:()Lorg/glassfish/hk2/utilities/cache/HybridCacheEntry;
       4: areturn
}
