Compiled from "ForwardingNavigableSet.java"
public abstract class com.google.common.collect.ForwardingNavigableSet<E> extends com.google.common.collect.ForwardingSortedSet<E> implements java.util.NavigableSet<E> {
  protected com.google.common.collect.ForwardingNavigableSet();
    Code:
       0: aload_0
       1: invokespecial #1                  // Method com/google/common/collect/ForwardingSortedSet."<init>":()V
       4: return

  protected abstract java.util.NavigableSet<E> delegate();

  public E lower(E);
    Code:
       0: aload_0
       1: invokevirtual #2                  // Method delegate:()Ljava/util/NavigableSet;
       4: aload_1
       5: invokeinterface #3,  2            // InterfaceMethod java/util/NavigableSet.lower:(Ljava/lang/Object;)Ljava/lang/Object;
      10: areturn

  protected E standardLower(E);
    Code:
       0: aload_0
       1: aload_1
       2: iconst_0
       3: invokevirtual #4                  // Method headSet:(Ljava/lang/Object;Z)Ljava/util/NavigableSet;
       6: invokeinterface #5,  1            // InterfaceMethod java/util/NavigableSet.descendingIterator:()Ljava/util/Iterator;
      11: aconst_null
      12: invokestatic  #6                  // Method com/google/common/collect/Iterators.getNext:(Ljava/util/Iterator;Ljava/lang/Object;)Ljava/lang/Object;
      15: areturn

  public E floor(E);
    Code:
       0: aload_0
       1: invokevirtual #2                  // Method delegate:()Ljava/util/NavigableSet;
       4: aload_1
       5: invokeinterface #7,  2            // InterfaceMethod java/util/NavigableSet.floor:(Ljava/lang/Object;)Ljava/lang/Object;
      10: areturn

  protected E standardFloor(E);
    Code:
       0: aload_0
       1: aload_1
       2: iconst_1
       3: invokevirtual #4                  // Method headSet:(Ljava/lang/Object;Z)Ljava/util/NavigableSet;
       6: invokeinterface #5,  1            // InterfaceMethod java/util/NavigableSet.descendingIterator:()Ljava/util/Iterator;
      11: aconst_null
      12: invokestatic  #6                  // Method com/google/common/collect/Iterators.getNext:(Ljava/util/Iterator;Ljava/lang/Object;)Ljava/lang/Object;
      15: areturn

  public E ceiling(E);
    Code:
       0: aload_0
       1: invokevirtual #2                  // Method delegate:()Ljava/util/NavigableSet;
       4: aload_1
       5: invokeinterface #8,  2            // InterfaceMethod java/util/NavigableSet.ceiling:(Ljava/lang/Object;)Ljava/lang/Object;
      10: areturn

  protected E standardCeiling(E);
    Code:
       0: aload_0
       1: aload_1
       2: iconst_1
       3: invokevirtual #9                  // Method tailSet:(Ljava/lang/Object;Z)Ljava/util/NavigableSet;
       6: invokeinterface #10,  1           // InterfaceMethod java/util/NavigableSet.iterator:()Ljava/util/Iterator;
      11: aconst_null
      12: invokestatic  #6                  // Method com/google/common/collect/Iterators.getNext:(Ljava/util/Iterator;Ljava/lang/Object;)Ljava/lang/Object;
      15: areturn

  public E higher(E);
    Code:
       0: aload_0
       1: invokevirtual #2                  // Method delegate:()Ljava/util/NavigableSet;
       4: aload_1
       5: invokeinterface #11,  2           // InterfaceMethod java/util/NavigableSet.higher:(Ljava/lang/Object;)Ljava/lang/Object;
      10: areturn

  protected E standardHigher(E);
    Code:
       0: aload_0
       1: aload_1
       2: iconst_0
       3: invokevirtual #9                  // Method tailSet:(Ljava/lang/Object;Z)Ljava/util/NavigableSet;
       6: invokeinterface #10,  1           // InterfaceMethod java/util/NavigableSet.iterator:()Ljava/util/Iterator;
      11: aconst_null
      12: invokestatic  #6                  // Method com/google/common/collect/Iterators.getNext:(Ljava/util/Iterator;Ljava/lang/Object;)Ljava/lang/Object;
      15: areturn

  public E pollFirst();
    Code:
       0: aload_0
       1: invokevirtual #2                  // Method delegate:()Ljava/util/NavigableSet;
       4: invokeinterface #12,  1           // InterfaceMethod java/util/NavigableSet.pollFirst:()Ljava/lang/Object;
       9: areturn

  protected E standardPollFirst();
    Code:
       0: aload_0
       1: aload_0
       2: invokevirtual #13                 // Method iterator:()Ljava/util/Iterator;
       5: invokespecial #14                 // Method poll:(Ljava/util/Iterator;)Ljava/lang/Object;
       8: areturn

  public E pollLast();
    Code:
       0: aload_0
       1: invokevirtual #2                  // Method delegate:()Ljava/util/NavigableSet;
       4: invokeinterface #15,  1           // InterfaceMethod java/util/NavigableSet.pollLast:()Ljava/lang/Object;
       9: areturn

  protected E standardPollLast();
    Code:
       0: aload_0
       1: aload_0
       2: invokevirtual #2                  // Method delegate:()Ljava/util/NavigableSet;
       5: invokeinterface #5,  1            // InterfaceMethod java/util/NavigableSet.descendingIterator:()Ljava/util/Iterator;
      10: invokespecial #14                 // Method poll:(Ljava/util/Iterator;)Ljava/lang/Object;
      13: areturn

  protected E standardFirst();
    Code:
       0: aload_0
       1: invokevirtual #13                 // Method iterator:()Ljava/util/Iterator;
       4: invokeinterface #16,  1           // InterfaceMethod java/util/Iterator.next:()Ljava/lang/Object;
       9: areturn

  protected E standardLast();
    Code:
       0: aload_0
       1: invokevirtual #17                 // Method descendingIterator:()Ljava/util/Iterator;
       4: invokeinterface #16,  1           // InterfaceMethod java/util/Iterator.next:()Ljava/lang/Object;
       9: areturn

  public java.util.NavigableSet<E> descendingSet();
    Code:
       0: aload_0
       1: invokevirtual #2                  // Method delegate:()Ljava/util/NavigableSet;
       4: invokeinterface #18,  1           // InterfaceMethod java/util/NavigableSet.descendingSet:()Ljava/util/NavigableSet;
       9: areturn

  public java.util.Iterator<E> descendingIterator();
    Code:
       0: aload_0
       1: invokevirtual #2                  // Method delegate:()Ljava/util/NavigableSet;
       4: invokeinterface #5,  1            // InterfaceMethod java/util/NavigableSet.descendingIterator:()Ljava/util/Iterator;
       9: areturn

  public java.util.NavigableSet<E> subSet(E, boolean, E, boolean);
    Code:
       0: aload_0
       1: invokevirtual #2                  // Method delegate:()Ljava/util/NavigableSet;
       4: aload_1
       5: iload_2
       6: aload_3
       7: iload         4
       9: invokeinterface #19,  5           // InterfaceMethod java/util/NavigableSet.subSet:(Ljava/lang/Object;ZLjava/lang/Object;Z)Ljava/util/NavigableSet;
      14: areturn

  protected java.util.NavigableSet<E> standardSubSet(E, boolean, E, boolean);
    Code:
       0: aload_0
       1: aload_1
       2: iload_2
       3: invokevirtual #9                  // Method tailSet:(Ljava/lang/Object;Z)Ljava/util/NavigableSet;
       6: aload_3
       7: iload         4
       9: invokeinterface #20,  3           // InterfaceMethod java/util/NavigableSet.headSet:(Ljava/lang/Object;Z)Ljava/util/NavigableSet;
      14: areturn

  protected java.util.SortedSet<E> standardSubSet(E, E);
    Code:
       0: aload_0
       1: aload_1
       2: iconst_1
       3: aload_2
       4: iconst_0
       5: invokevirtual #21                 // Method subSet:(Ljava/lang/Object;ZLjava/lang/Object;Z)Ljava/util/NavigableSet;
       8: areturn

  public java.util.NavigableSet<E> headSet(E, boolean);
    Code:
       0: aload_0
       1: invokevirtual #2                  // Method delegate:()Ljava/util/NavigableSet;
       4: aload_1
       5: iload_2
       6: invokeinterface #20,  3           // InterfaceMethod java/util/NavigableSet.headSet:(Ljava/lang/Object;Z)Ljava/util/NavigableSet;
      11: areturn

  protected java.util.SortedSet<E> standardHeadSet(E);
    Code:
       0: aload_0
       1: aload_1
       2: iconst_0
       3: invokevirtual #4                  // Method headSet:(Ljava/lang/Object;Z)Ljava/util/NavigableSet;
       6: areturn

  public java.util.NavigableSet<E> tailSet(E, boolean);
    Code:
       0: aload_0
       1: invokevirtual #2                  // Method delegate:()Ljava/util/NavigableSet;
       4: aload_1
       5: iload_2
       6: invokeinterface #22,  3           // InterfaceMethod java/util/NavigableSet.tailSet:(Ljava/lang/Object;Z)Ljava/util/NavigableSet;
      11: areturn

  protected java.util.SortedSet<E> standardTailSet(E);
    Code:
       0: aload_0
       1: aload_1
       2: iconst_1
       3: invokevirtual #9                  // Method tailSet:(Ljava/lang/Object;Z)Ljava/util/NavigableSet;
       6: areturn

  private E poll(java.util.Iterator<E>);
    Code:
       0: aload_1
       1: invokeinterface #23,  1           // InterfaceMethod java/util/Iterator.hasNext:()Z
       6: ifeq          24
       9: aload_1
      10: invokeinterface #16,  1           // InterfaceMethod java/util/Iterator.next:()Ljava/lang/Object;
      15: astore_2
      16: aload_1
      17: invokeinterface #24,  1           // InterfaceMethod java/util/Iterator.remove:()V
      22: aload_2
      23: areturn
      24: aconst_null
      25: areturn

  protected java.util.SortedSet delegate();
    Code:
       0: aload_0
       1: invokevirtual #2                  // Method delegate:()Ljava/util/NavigableSet;
       4: areturn

  protected java.util.Set delegate();
    Code:
       0: aload_0
       1: invokevirtual #2                  // Method delegate:()Ljava/util/NavigableSet;
       4: areturn

  protected java.util.Collection delegate();
    Code:
       0: aload_0
       1: invokevirtual #2                  // Method delegate:()Ljava/util/NavigableSet;
       4: areturn

  protected java.lang.Object delegate();
    Code:
       0: aload_0
       1: invokevirtual #2                  // Method delegate:()Ljava/util/NavigableSet;
       4: areturn
}
