Compiled from "Maps.java"
class com.google.common.collect.Maps$AsMapView$2$1 implements java.util.Iterator<java.util.Map$Entry<K, V>> {
  final java.util.Iterator val$backingIterator;

  final com.google.common.collect.Maps$AsMapView$2 this$1;

  com.google.common.collect.Maps$AsMapView$2$1(com.google.common.collect.Maps$AsMapView$2, java.util.Iterator);
    Code:
       0: aload_0
       1: aload_1
       2: putfield      #1                  // Field this$1:Lcom/google/common/collect/Maps$AsMapView$2;
       5: aload_0
       6: aload_2
       7: putfield      #2                  // Field val$backingIterator:Ljava/util/Iterator;
      10: aload_0
      11: invokespecial #3                  // Method java/lang/Object."<init>":()V
      14: return

  public boolean hasNext();
    Code:
       0: aload_0
       1: getfield      #2                  // Field val$backingIterator:Ljava/util/Iterator;
       4: invokeinterface #4,  1            // InterfaceMethod java/util/Iterator.hasNext:()Z
       9: ireturn

  public java.util.Map$Entry<K, V> next();
    Code:
       0: aload_0
       1: getfield      #2                  // Field val$backingIterator:Ljava/util/Iterator;
       4: invokeinterface #5,  1            // InterfaceMethod java/util/Iterator.next:()Ljava/lang/Object;
       9: astore_1
      10: aload_1
      11: aload_0
      12: getfield      #1                  // Field this$1:Lcom/google/common/collect/Maps$AsMapView$2;
      15: getfield      #6                  // Field com/google/common/collect/Maps$AsMapView$2.this$0:Lcom/google/common/collect/Maps$AsMapView;
      18: getfield      #7                  // Field com/google/common/collect/Maps$AsMapView.function:Lcom/google/common/base/Function;
      21: aload_1
      22: invokeinterface #8,  2            // InterfaceMethod com/google/common/base/Function.apply:(Ljava/lang/Object;)Ljava/lang/Object;
      27: invokestatic  #9                  // Method com/google/common/collect/Maps.immutableEntry:(Ljava/lang/Object;Ljava/lang/Object;)Ljava/util/Map$Entry;
      30: areturn

  public void remove();
    Code:
       0: aload_0
       1: getfield      #2                  // Field val$backingIterator:Ljava/util/Iterator;
       4: invokeinterface #10,  1           // InterfaceMethod java/util/Iterator.remove:()V
       9: return

  public java.lang.Object next();
    Code:
       0: aload_0
       1: invokevirtual #11                 // Method next:()Ljava/util/Map$Entry;
       4: areturn
}
