Compiled from "Multimaps.java"
class com.google.common.collect.Multimaps$FilteredMultimap$Keys extends com.google.common.collect.Multimaps$Keys<K, V> {
  final com.google.common.collect.Multimaps$FilteredMultimap this$0;

  com.google.common.collect.Multimaps$FilteredMultimap$Keys(com.google.common.collect.Multimaps$FilteredMultimap);
    Code:
       0: aload_0
       1: aload_1
       2: putfield      #1                  // Field this$0:Lcom/google/common/collect/Multimaps$FilteredMultimap;
       5: aload_0
       6: invokespecial #2                  // Method com/google/common/collect/Multimaps$Keys."<init>":()V
       9: return

  com.google.common.collect.Multimap<K, V> multimap();
    Code:
       0: aload_0
       1: getfield      #1                  // Field this$0:Lcom/google/common/collect/Multimaps$FilteredMultimap;
       4: areturn

  public int remove(java.lang.Object, int);
    Code:
       0: iload_2
       1: iflt          8
       4: iconst_1
       5: goto          9
       8: iconst_0
       9: invokestatic  #3                  // Method com/google/common/base/Preconditions.checkArgument:(Z)V
      12: aload_0
      13: getfield      #1                  // Field this$0:Lcom/google/common/collect/Multimaps$FilteredMultimap;
      16: getfield      #4                  // Field com/google/common/collect/Multimaps$FilteredMultimap.unfiltered:Lcom/google/common/collect/Multimap;
      19: invokeinterface #5,  1            // InterfaceMethod com/google/common/collect/Multimap.asMap:()Ljava/util/Map;
      24: aload_1
      25: invokeinterface #6,  2            // InterfaceMethod java/util/Map.get:(Ljava/lang/Object;)Ljava/lang/Object;
      30: checkcast     #7                  // class java/util/Collection
      33: astore_3
      34: aload_3
      35: ifnonnull     40
      38: iconst_0
      39: ireturn
      40: iconst_0
      41: istore        4
      43: iconst_0
      44: istore        5
      46: aload_3
      47: invokeinterface #8,  1            // InterfaceMethod java/util/Collection.iterator:()Ljava/util/Iterator;
      52: astore        6
      54: aload         6
      56: invokeinterface #9,  1            // InterfaceMethod java/util/Iterator.hasNext:()Z
      61: ifeq          104
      64: aload_0
      65: getfield      #1                  // Field this$0:Lcom/google/common/collect/Multimaps$FilteredMultimap;
      68: aload_1
      69: aload         6
      71: invokeinterface #10,  1           // InterfaceMethod java/util/Iterator.next:()Ljava/lang/Object;
      76: invokevirtual #11                 // Method com/google/common/collect/Multimaps$FilteredMultimap.satisfiesPredicate:(Ljava/lang/Object;Ljava/lang/Object;)Z
      79: ifeq          54
      82: iinc          4, 1
      85: iload         5
      87: iload_2
      88: if_icmpge     54
      91: aload         6
      93: invokeinterface #12,  1           // InterfaceMethod java/util/Iterator.remove:()V
      98: iinc          5, 1
     101: goto          54
     104: iload         4
     106: ireturn

  java.util.Set<com.google.common.collect.Multiset$Entry<K>> createEntrySet();
    Code:
       0: new           #13                 // class com/google/common/collect/Multimaps$FilteredMultimap$Keys$EntrySet
       3: dup
       4: aload_0
       5: invokespecial #14                 // Method com/google/common/collect/Multimaps$FilteredMultimap$Keys$EntrySet."<init>":(Lcom/google/common/collect/Multimaps$FilteredMultimap$Keys;)V
       8: areturn
}
