Compiled from "Input.java"
class org.xmlunit.builder.Input$StreamBuilder$2 extends javax.xml.transform.stream.StreamSource {
  final java.lang.String val$s;

  org.xmlunit.builder.Input$StreamBuilder$2(java.lang.String);
    Code:
       0: aload_0
       1: aload_1
       2: putfield      #1                  // Field val$s:Ljava/lang/String;
       5: aload_0
       6: invokespecial #2                  // Method javax/xml/transform/stream/StreamSource."<init>":()V
       9: return

  public java.io.Reader getReader();
    Code:
       0: new           #3                  // class java/io/StringReader
       3: dup
       4: aload_0
       5: getfield      #1                  // Field val$s:Ljava/lang/String;
       8: invokespecial #4                  // Method java/io/StringReader."<init>":(Ljava/lang/String;)V
      11: areturn
}
