Compiled from "ClosableResourceUtils.java"
public final class com.mchange.v1.util.ClosableResourceUtils {
  private static final com.mchange.v2.log.MLogger logger;

  public static java.lang.Exception attemptClose(com.mchange.v1.util.ClosableResource);
    Code:
       0: aload_0
       1: ifnull        10
       4: aload_0
       5: invokeinterface #1,  1            // InterfaceMethod com/mchange/v1/util/ClosableResource.close:()V
      10: aconst_null
      11: areturn
      12: astore_1
      13: getstatic     #3                  // Field logger:Lcom/mchange/v2/log/MLogger;
      16: getstatic     #4                  // Field com/mchange/v2/log/MLevel.WARNING:Lcom/mchange/v2/log/MLevel;
      19: invokeinterface #5,  2            // InterfaceMethod com/mchange/v2/log/MLogger.isLoggable:(Lcom/mchange/v2/log/MLevel;)Z
      24: ifeq          41
      27: getstatic     #3                  // Field logger:Lcom/mchange/v2/log/MLogger;
      30: getstatic     #4                  // Field com/mchange/v2/log/MLevel.WARNING:Lcom/mchange/v2/log/MLevel;
      33: ldc           #6                  // String CloseableResource close FAILED.
      35: aload_1
      36: invokeinterface #7,  4            // InterfaceMethod com/mchange/v2/log/MLogger.log:(Lcom/mchange/v2/log/MLevel;Ljava/lang/String;Ljava/lang/Throwable;)V
      41: aload_1
      42: areturn
    Exception table:
       from    to  target type
           0    11    12   Class java/lang/Exception

  private com.mchange.v1.util.ClosableResourceUtils();
    Code:
       0: aload_0
       1: invokespecial #8                  // Method java/lang/Object."<init>":()V
       4: return

  static {};
    Code:
       0: ldc           #9                  // class com/mchange/v1/util/ClosableResourceUtils
       2: invokestatic  #10                 // Method com/mchange/v2/log/MLog.getLogger:(Ljava/lang/Class;)Lcom/mchange/v2/log/MLogger;
       5: putstatic     #3                  // Field logger:Lcom/mchange/v2/log/MLogger;
       8: return
}
