Compiled from "TextHandler.java"
public class org.apache.geronimo.mail.handlers.TextHandler implements javax.activation.DataContentHandler {
  javax.activation.ActivationDataFlavor dataFlavor;

  public org.apache.geronimo.mail.handlers.TextHandler();
    Code:
       0: aload_0
       1: invokespecial #1                  // Method java/lang/Object."<init>":()V
       4: aload_0
       5: new           #2                  // class javax/activation/ActivationDataFlavor
       8: dup
       9: ldc_w         #3                  // class java/lang/String
      12: ldc           #4                  // String text/plain
      14: ldc           #5                  // String Text String
      16: invokespecial #6                  // Method javax/activation/ActivationDataFlavor."<init>":(Ljava/lang/Class;Ljava/lang/String;Ljava/lang/String;)V
      19: putfield      #7                  // Field dataFlavor:Ljavax/activation/ActivationDataFlavor;
      22: return

  public org.apache.geronimo.mail.handlers.TextHandler(javax.activation.ActivationDataFlavor);
    Code:
       0: aload_0
       1: invokespecial #1                  // Method java/lang/Object."<init>":()V
       4: aload_0
       5: aload_1
       6: putfield      #7                  // Field dataFlavor:Ljavax/activation/ActivationDataFlavor;
       9: return

  protected javax.activation.ActivationDataFlavor getDF();
    Code:
       0: aload_0
       1: getfield      #7                  // Field dataFlavor:Ljavax/activation/ActivationDataFlavor;
       4: areturn

  public java.awt.datatransfer.DataFlavor[] getTransferDataFlavors();
    Code:
       0: iconst_1
       1: anewarray     #8                  // class java/awt/datatransfer/DataFlavor
       4: dup
       5: iconst_0
       6: aload_0
       7: getfield      #7                  // Field dataFlavor:Ljavax/activation/ActivationDataFlavor;
      10: aastore
      11: areturn

  public java.lang.Object getTransferData(java.awt.datatransfer.DataFlavor, javax.activation.DataSource) throws java.io.IOException;
    Code:
       0: aload_0
       1: invokevirtual #9                  // Method getDF:()Ljavax/activation/ActivationDataFlavor;
       4: aload_1
       5: invokevirtual #10                 // Method javax/activation/ActivationDataFlavor.equals:(Ljava/awt/datatransfer/DataFlavor;)Z
       8: ifeq          17
      11: aload_0
      12: aload_2
      13: invokevirtual #11                 // Method getContent:(Ljavax/activation/DataSource;)Ljava/lang/Object;
      16: areturn
      17: aconst_null
      18: areturn

  public java.lang.Object getContent(javax.activation.DataSource) throws java.io.IOException;
    Code:
       0: aload_1
       1: invokeinterface #12,  1           // InterfaceMethod javax/activation/DataSource.getInputStream:()Ljava/io/InputStream;
       6: astore_2
       7: new           #13                 // class java/io/ByteArrayOutputStream
      10: dup
      11: invokespecial #14                 // Method java/io/ByteArrayOutputStream."<init>":()V
      14: astore_3
      15: sipush        1000
      18: newarray       byte
      20: astore        5
      22: aload_2
      23: aload         5
      25: iconst_0
      26: aload         5
      28: arraylength
      29: invokevirtual #15                 // Method java/io/InputStream.read:([BII)I
      32: dup
      33: istore        4
      35: ifle          50
      38: aload_3
      39: aload         5
      41: iconst_0
      42: iload         4
      44: invokevirtual #16                 // Method java/io/ByteArrayOutputStream.write:([BII)V
      47: goto          22
      50: aload_2
      51: invokevirtual #17                 // Method java/io/InputStream.close:()V
      54: goto          66
      57: astore        6
      59: aload_2
      60: invokevirtual #17                 // Method java/io/InputStream.close:()V
      63: aload         6
      65: athrow
      66: aload_3
      67: aload_0
      68: aload_1
      69: invokeinterface #18,  1           // InterfaceMethod javax/activation/DataSource.getContentType:()Ljava/lang/String;
      74: invokevirtual #19                 // Method getCharSet:(Ljava/lang/String;)Ljava/lang/String;
      77: invokevirtual #20                 // Method java/io/ByteArrayOutputStream.toString:(Ljava/lang/String;)Ljava/lang/String;
      80: areturn
      81: astore        6
      83: new           #22                 // class java/io/UnsupportedEncodingException
      86: dup
      87: aload         6
      89: invokevirtual #23                 // Method javax/mail/internet/ParseException.getMessage:()Ljava/lang/String;
      92: invokespecial #24                 // Method java/io/UnsupportedEncodingException."<init>":(Ljava/lang/String;)V
      95: athrow
    Exception table:
       from    to  target type
          22    50    57   any
          57    59    57   any
          66    80    81   Class javax/mail/internet/ParseException

  public void writeTo(java.lang.Object, java.lang.String, java.io.OutputStream) throws java.io.IOException;
    Code:
       0: aload_0
       1: aload_2
       2: invokevirtual #19                 // Method getCharSet:(Ljava/lang/String;)Ljava/lang/String;
       5: astore        5
       7: new           #25                 // class java/io/OutputStreamWriter
      10: dup
      11: aload_3
      12: aload         5
      14: invokespecial #26                 // Method java/io/OutputStreamWriter."<init>":(Ljava/io/OutputStream;Ljava/lang/String;)V
      17: astore        4
      19: goto          37
      22: astore        5
      24: new           #22                 // class java/io/UnsupportedEncodingException
      27: dup
      28: aload         5
      30: invokevirtual #28                 // Method java/lang/Exception.toString:()Ljava/lang/String;
      33: invokespecial #24                 // Method java/io/UnsupportedEncodingException."<init>":(Ljava/lang/String;)V
      36: athrow
      37: aload_1
      38: checkcast     #3                  // class java/lang/String
      41: astore        5
      43: aload         4
      45: aload         5
      47: iconst_0
      48: aload         5
      50: invokevirtual #29                 // Method java/lang/String.length:()I
      53: invokevirtual #30                 // Method java/io/OutputStreamWriter.write:(Ljava/lang/String;II)V
      56: aload         4
      58: invokevirtual #31                 // Method java/io/OutputStreamWriter.flush:()V
      61: return
    Exception table:
       from    to  target type
           0    19    22   Class java/lang/Exception

  protected java.lang.String getCharSet(java.lang.String) throws javax.mail.internet.ParseException;
    Code:
       0: new           #32                 // class javax/mail/internet/ContentType
       3: dup
       4: aload_1
       5: invokespecial #33                 // Method javax/mail/internet/ContentType."<init>":(Ljava/lang/String;)V
       8: astore_2
       9: aload_2
      10: ldc           #34                 // String charset
      12: invokevirtual #35                 // Method javax/mail/internet/ContentType.getParameter:(Ljava/lang/String;)Ljava/lang/String;
      15: astore_3
      16: aload_3
      17: ifnonnull     23
      20: ldc           #36                 // String us-ascii
      22: astore_3
      23: aload_3
      24: invokestatic  #37                 // Method javax/mail/internet/MimeUtility.javaCharset:(Ljava/lang/String;)Ljava/lang/String;
      27: areturn
}
