Compiled from "DefineClassHelper.java"
class javassist.util.proxy.DefineClassHelper$JavaOther extends javassist.util.proxy.DefineClassHelper$Helper {
  private final java.lang.reflect.Method defineClass;

  private final javassist.util.proxy.SecurityActions stack;

  private javassist.util.proxy.DefineClassHelper$JavaOther();
    Code:
       0: aload_0
       1: aconst_null
       2: invokespecial #2                  // Method javassist/util/proxy/DefineClassHelper$Helper."<init>":(Ljavassist/util/proxy/DefineClassHelper$1;)V
       5: aload_0
       6: aload_0
       7: invokespecial #3                  // Method getDefineClassMethod:()Ljava/lang/reflect/Method;
      10: putfield      #4                  // Field defineClass:Ljava/lang/reflect/Method;
      13: aload_0
      14: getstatic     #5                  // Field javassist/util/proxy/SecurityActions.stack:Ljavassist/util/proxy/SecurityActions;
      17: putfield      #6                  // Field stack:Ljavassist/util/proxy/SecurityActions;
      20: return

  private final java.lang.reflect.Method getDefineClassMethod();
    Code:
       0: invokestatic  #7                  // Method javassist/util/proxy/DefineClassHelper.access$400:()Ljavassist/util/proxy/DefineClassHelper$Helper;
       3: ifnull        30
       6: aload_0
       7: getfield      #6                  // Field stack:Ljavassist/util/proxy/SecurityActions;
      10: invokevirtual #8                  // Method javassist/util/proxy/SecurityActions.getCallerClass:()Ljava/lang/Class;
      13: aload_0
      14: invokevirtual #9                  // Method java/lang/Object.getClass:()Ljava/lang/Class;
      17: if_acmpeq     30
      20: new           #10                 // class java/lang/IllegalAccessError
      23: dup
      24: ldc           #11                 // String Access denied for caller.
      26: invokespecial #12                 // Method java/lang/IllegalAccessError."<init>":(Ljava/lang/String;)V
      29: athrow
      30: ldc           #13                 // class java/lang/ClassLoader
      32: ldc           #14                 // String defineClass
      34: iconst_5
      35: anewarray     #15                 // class java/lang/Class
      38: dup
      39: iconst_0
      40: ldc           #16                 // class java/lang/String
      42: aastore
      43: dup
      44: iconst_1
      45: ldc           #17                 // class "[B"
      47: aastore
      48: dup
      49: iconst_2
      50: getstatic     #18                 // Field java/lang/Integer.TYPE:Ljava/lang/Class;
      53: aastore
      54: dup
      55: iconst_3
      56: getstatic     #18                 // Field java/lang/Integer.TYPE:Ljava/lang/Class;
      59: aastore
      60: dup
      61: iconst_4
      62: ldc           #19                 // class java/security/ProtectionDomain
      64: aastore
      65: invokestatic  #20                 // Method javassist/util/proxy/SecurityActions.getDeclaredMethod:(Ljava/lang/Class;Ljava/lang/String;[Ljava/lang/Class;)Ljava/lang/reflect/Method;
      68: areturn
      69: astore_1
      70: new           #22                 // class java/lang/RuntimeException
      73: dup
      74: ldc           #23                 // String cannot initialize
      76: aload_1
      77: invokespecial #24                 // Method java/lang/RuntimeException."<init>":(Ljava/lang/String;Ljava/lang/Throwable;)V
      80: athrow
    Exception table:
       from    to  target type
          30    68    69   Class java/lang/NoSuchMethodException

  java.lang.Class<?> defineClass(java.lang.String, byte[], int, int, java.lang.Class<?>, java.lang.ClassLoader, java.security.ProtectionDomain) throws java.lang.ClassFormatError, javassist.CannotCompileException;
    Code:
       0: aload_0
       1: getfield      #6                  // Field stack:Ljavassist/util/proxy/SecurityActions;
       4: invokevirtual #8                  // Method javassist/util/proxy/SecurityActions.getCallerClass:()Ljava/lang/Class;
       7: astore        8
       9: aload         8
      11: ldc           #25                 // class javassist/util/proxy/DefineClassHelper
      13: if_acmpeq     35
      16: aload         8
      18: aload_0
      19: invokevirtual #9                  // Method java/lang/Object.getClass:()Ljava/lang/Class;
      22: if_acmpeq     35
      25: new           #10                 // class java/lang/IllegalAccessError
      28: dup
      29: ldc           #11                 // String Access denied for caller.
      31: invokespecial #12                 // Method java/lang/IllegalAccessError."<init>":(Ljava/lang/String;)V
      34: athrow
      35: aload_0
      36: getfield      #4                  // Field defineClass:Ljava/lang/reflect/Method;
      39: iconst_1
      40: invokestatic  #26                 // Method javassist/util/proxy/SecurityActions.setAccessible:(Ljava/lang/reflect/AccessibleObject;Z)V
      43: aload_0
      44: getfield      #4                  // Field defineClass:Ljava/lang/reflect/Method;
      47: aload         6
      49: iconst_5
      50: anewarray     #27                 // class java/lang/Object
      53: dup
      54: iconst_0
      55: aload_1
      56: aastore
      57: dup
      58: iconst_1
      59: aload_2
      60: aastore
      61: dup
      62: iconst_2
      63: iload_3
      64: invokestatic  #28                 // Method java/lang/Integer.valueOf:(I)Ljava/lang/Integer;
      67: aastore
      68: dup
      69: iconst_3
      70: iload         4
      72: invokestatic  #28                 // Method java/lang/Integer.valueOf:(I)Ljava/lang/Integer;
      75: aastore
      76: dup
      77: iconst_4
      78: aload         7
      80: aastore
      81: invokevirtual #29                 // Method java/lang/reflect/Method.invoke:(Ljava/lang/Object;[Ljava/lang/Object;)Ljava/lang/Object;
      84: checkcast     #15                 // class java/lang/Class
      87: areturn
      88: astore        9
      90: aload         9
      92: instanceof    #31                 // class java/lang/ClassFormatError
      95: ifeq          104
      98: aload         9
     100: checkcast     #31                 // class java/lang/ClassFormatError
     103: athrow
     104: aload         9
     106: instanceof    #22                 // class java/lang/RuntimeException
     109: ifeq          118
     112: aload         9
     114: checkcast     #22                 // class java/lang/RuntimeException
     117: athrow
     118: new           #32                 // class javassist/CannotCompileException
     121: dup
     122: aload         9
     124: invokespecial #33                 // Method javassist/CannotCompileException."<init>":(Ljava/lang/Throwable;)V
     127: athrow
    Exception table:
       from    to  target type
          35    87    88   Class java/lang/Throwable

  javassist.util.proxy.DefineClassHelper$JavaOther(javassist.util.proxy.DefineClassHelper$1);
    Code:
       0: aload_0
       1: invokespecial #1                  // Method "<init>":()V
       4: return
}
