Compiled from "RuntimeLayer.java"
public final class io.grpc.xds.shaded.io.envoyproxy.envoy.config.bootstrap.v3.RuntimeLayer$LayerSpecifierCase extends java.lang.Enum<io.grpc.xds.shaded.io.envoyproxy.envoy.config.bootstrap.v3.RuntimeLayer$LayerSpecifierCase> implements com.google.protobuf.Internal$EnumLite, com.google.protobuf.AbstractMessageLite$InternalOneOfEnum {
  public static final io.grpc.xds.shaded.io.envoyproxy.envoy.config.bootstrap.v3.RuntimeLayer$LayerSpecifierCase STATIC_LAYER;

  public static final io.grpc.xds.shaded.io.envoyproxy.envoy.config.bootstrap.v3.RuntimeLayer$LayerSpecifierCase DISK_LAYER;

  public static final io.grpc.xds.shaded.io.envoyproxy.envoy.config.bootstrap.v3.RuntimeLayer$LayerSpecifierCase ADMIN_LAYER;

  public static final io.grpc.xds.shaded.io.envoyproxy.envoy.config.bootstrap.v3.RuntimeLayer$LayerSpecifierCase RTDS_LAYER;

  public static final io.grpc.xds.shaded.io.envoyproxy.envoy.config.bootstrap.v3.RuntimeLayer$LayerSpecifierCase LAYERSPECIFIER_NOT_SET;

  private final int value;

  private static final io.grpc.xds.shaded.io.envoyproxy.envoy.config.bootstrap.v3.RuntimeLayer$LayerSpecifierCase[] $VALUES;

  public static io.grpc.xds.shaded.io.envoyproxy.envoy.config.bootstrap.v3.RuntimeLayer$LayerSpecifierCase[] values();
    Code:
       0: getstatic     #33                 // Field $VALUES:[Lio/grpc/xds/shaded/io/envoyproxy/envoy/config/bootstrap/v3/RuntimeLayer$LayerSpecifierCase;
       3: invokevirtual #38                 // Method "[Lio/grpc/xds/shaded/io/envoyproxy/envoy/config/bootstrap/v3/RuntimeLayer$LayerSpecifierCase;".clone:()Ljava/lang/Object;
       6: checkcast     #34                 // class "[Lio/grpc/xds/shaded/io/envoyproxy/envoy/config/bootstrap/v3/RuntimeLayer$LayerSpecifierCase;"
       9: areturn

  public static io.grpc.xds.shaded.io.envoyproxy.envoy.config.bootstrap.v3.RuntimeLayer$LayerSpecifierCase valueOf(java.lang.String);
    Code:
       0: ldc           #2                  // class io/grpc/xds/shaded/io/envoyproxy/envoy/config/bootstrap/v3/RuntimeLayer$LayerSpecifierCase
       2: aload_0
       3: invokestatic  #43                 // Method java/lang/Enum.valueOf:(Ljava/lang/Class;Ljava/lang/String;)Ljava/lang/Enum;
       6: checkcast     #2                  // class io/grpc/xds/shaded/io/envoyproxy/envoy/config/bootstrap/v3/RuntimeLayer$LayerSpecifierCase
       9: areturn

  private io.grpc.xds.shaded.io.envoyproxy.envoy.config.bootstrap.v3.RuntimeLayer$LayerSpecifierCase(int);
    Code:
       0: aload_0
       1: aload_1
       2: iload_2
       3: invokespecial #51                 // Method java/lang/Enum."<init>":(Ljava/lang/String;I)V
       6: aload_0
       7: iload_3
       8: putfield      #53                 // Field value:I
      11: return

  public static io.grpc.xds.shaded.io.envoyproxy.envoy.config.bootstrap.v3.RuntimeLayer$LayerSpecifierCase valueOf(int);
    Code:
       0: iload_0
       1: invokestatic  #59                 // Method forNumber:(I)Lio/grpc/xds/shaded/io/envoyproxy/envoy/config/bootstrap/v3/RuntimeLayer$LayerSpecifierCase;
       4: areturn

  public static io.grpc.xds.shaded.io.envoyproxy.envoy.config.bootstrap.v3.RuntimeLayer$LayerSpecifierCase forNumber(int);
    Code:
       0: iload_0
       1: tableswitch   { // 0 to 5
                     0: 56
                     1: 60
                     2: 40
                     3: 44
                     4: 48
                     5: 52
               default: 60
          }
      40: getstatic     #61                 // Field STATIC_LAYER:Lio/grpc/xds/shaded/io/envoyproxy/envoy/config/bootstrap/v3/RuntimeLayer$LayerSpecifierCase;
      43: areturn
      44: getstatic     #63                 // Field DISK_LAYER:Lio/grpc/xds/shaded/io/envoyproxy/envoy/config/bootstrap/v3/RuntimeLayer$LayerSpecifierCase;
      47: areturn
      48: getstatic     #65                 // Field ADMIN_LAYER:Lio/grpc/xds/shaded/io/envoyproxy/envoy/config/bootstrap/v3/RuntimeLayer$LayerSpecifierCase;
      51: areturn
      52: getstatic     #67                 // Field RTDS_LAYER:Lio/grpc/xds/shaded/io/envoyproxy/envoy/config/bootstrap/v3/RuntimeLayer$LayerSpecifierCase;
      55: areturn
      56: getstatic     #69                 // Field LAYERSPECIFIER_NOT_SET:Lio/grpc/xds/shaded/io/envoyproxy/envoy/config/bootstrap/v3/RuntimeLayer$LayerSpecifierCase;
      59: areturn
      60: aconst_null
      61: areturn

  public int getNumber();
    Code:
       0: aload_0
       1: getfield      #53                 // Field value:I
       4: ireturn

  static {};
    Code:
       0: new           #2                  // class io/grpc/xds/shaded/io/envoyproxy/envoy/config/bootstrap/v3/RuntimeLayer$LayerSpecifierCase
       3: dup
       4: ldc           #74                 // String STATIC_LAYER
       6: iconst_0
       7: iconst_2
       8: invokespecial #76                 // Method "<init>":(Ljava/lang/String;II)V
      11: putstatic     #61                 // Field STATIC_LAYER:Lio/grpc/xds/shaded/io/envoyproxy/envoy/config/bootstrap/v3/RuntimeLayer$LayerSpecifierCase;
      14: new           #2                  // class io/grpc/xds/shaded/io/envoyproxy/envoy/config/bootstrap/v3/RuntimeLayer$LayerSpecifierCase
      17: dup
      18: ldc           #77                 // String DISK_LAYER
      20: iconst_1
      21: iconst_3
      22: invokespecial #76                 // Method "<init>":(Ljava/lang/String;II)V
      25: putstatic     #63                 // Field DISK_LAYER:Lio/grpc/xds/shaded/io/envoyproxy/envoy/config/bootstrap/v3/RuntimeLayer$LayerSpecifierCase;
      28: new           #2                  // class io/grpc/xds/shaded/io/envoyproxy/envoy/config/bootstrap/v3/RuntimeLayer$LayerSpecifierCase
      31: dup
      32: ldc           #78                 // String ADMIN_LAYER
      34: iconst_2
      35: iconst_4
      36: invokespecial #76                 // Method "<init>":(Ljava/lang/String;II)V
      39: putstatic     #65                 // Field ADMIN_LAYER:Lio/grpc/xds/shaded/io/envoyproxy/envoy/config/bootstrap/v3/RuntimeLayer$LayerSpecifierCase;
      42: new           #2                  // class io/grpc/xds/shaded/io/envoyproxy/envoy/config/bootstrap/v3/RuntimeLayer$LayerSpecifierCase
      45: dup
      46: ldc           #79                 // String RTDS_LAYER
      48: iconst_3
      49: iconst_5
      50: invokespecial #76                 // Method "<init>":(Ljava/lang/String;II)V
      53: putstatic     #67                 // Field RTDS_LAYER:Lio/grpc/xds/shaded/io/envoyproxy/envoy/config/bootstrap/v3/RuntimeLayer$LayerSpecifierCase;
      56: new           #2                  // class io/grpc/xds/shaded/io/envoyproxy/envoy/config/bootstrap/v3/RuntimeLayer$LayerSpecifierCase
      59: dup
      60: ldc           #80                 // String LAYERSPECIFIER_NOT_SET
      62: iconst_4
      63: iconst_0
      64: invokespecial #76                 // Method "<init>":(Ljava/lang/String;II)V
      67: putstatic     #69                 // Field LAYERSPECIFIER_NOT_SET:Lio/grpc/xds/shaded/io/envoyproxy/envoy/config/bootstrap/v3/RuntimeLayer$LayerSpecifierCase;
      70: iconst_5
      71: anewarray     #2                  // class io/grpc/xds/shaded/io/envoyproxy/envoy/config/bootstrap/v3/RuntimeLayer$LayerSpecifierCase
      74: dup
      75: iconst_0
      76: getstatic     #61                 // Field STATIC_LAYER:Lio/grpc/xds/shaded/io/envoyproxy/envoy/config/bootstrap/v3/RuntimeLayer$LayerSpecifierCase;
      79: aastore
      80: dup
      81: iconst_1
      82: getstatic     #63                 // Field DISK_LAYER:Lio/grpc/xds/shaded/io/envoyproxy/envoy/config/bootstrap/v3/RuntimeLayer$LayerSpecifierCase;
      85: aastore
      86: dup
      87: iconst_2
      88: getstatic     #65                 // Field ADMIN_LAYER:Lio/grpc/xds/shaded/io/envoyproxy/envoy/config/bootstrap/v3/RuntimeLayer$LayerSpecifierCase;
      91: aastore
      92: dup
      93: iconst_3
      94: getstatic     #67                 // Field RTDS_LAYER:Lio/grpc/xds/shaded/io/envoyproxy/envoy/config/bootstrap/v3/RuntimeLayer$LayerSpecifierCase;
      97: aastore
      98: dup
      99: iconst_4
     100: getstatic     #69                 // Field LAYERSPECIFIER_NOT_SET:Lio/grpc/xds/shaded/io/envoyproxy/envoy/config/bootstrap/v3/RuntimeLayer$LayerSpecifierCase;
     103: aastore
     104: putstatic     #33                 // Field $VALUES:[Lio/grpc/xds/shaded/io/envoyproxy/envoy/config/bootstrap/v3/RuntimeLayer$LayerSpecifierCase;
     107: return
}
