Compiled from "AnnotatedClass.java"
public final class org.apache.htrace.shaded.fasterxml.jackson.databind.introspect.AnnotatedClass extends org.apache.htrace.shaded.fasterxml.jackson.databind.introspect.Annotated {
  private static final org.apache.htrace.shaded.fasterxml.jackson.databind.introspect.AnnotationMap[] NO_ANNOTATION_MAPS;

  protected final java.lang.Class<?> _class;

  protected final java.util.List<java.lang.Class<?>> _superTypes;

  protected final org.apache.htrace.shaded.fasterxml.jackson.databind.AnnotationIntrospector _annotationIntrospector;

  protected final org.apache.htrace.shaded.fasterxml.jackson.databind.introspect.ClassIntrospector$MixInResolver _mixInResolver;

  protected final java.lang.Class<?> _primaryMixIn;

  protected org.apache.htrace.shaded.fasterxml.jackson.databind.introspect.AnnotationMap _classAnnotations;

  protected boolean _creatorsResolved;

  protected org.apache.htrace.shaded.fasterxml.jackson.databind.introspect.AnnotatedConstructor _defaultConstructor;

  protected java.util.List<org.apache.htrace.shaded.fasterxml.jackson.databind.introspect.AnnotatedConstructor> _constructors;

  protected java.util.List<org.apache.htrace.shaded.fasterxml.jackson.databind.introspect.AnnotatedMethod> _creatorMethods;

  protected org.apache.htrace.shaded.fasterxml.jackson.databind.introspect.AnnotatedMethodMap _memberMethods;

  protected java.util.List<org.apache.htrace.shaded.fasterxml.jackson.databind.introspect.AnnotatedField> _fields;

  private org.apache.htrace.shaded.fasterxml.jackson.databind.introspect.AnnotatedClass(java.lang.Class<?>, java.util.List<java.lang.Class<?>>, org.apache.htrace.shaded.fasterxml.jackson.databind.AnnotationIntrospector, org.apache.htrace.shaded.fasterxml.jackson.databind.introspect.ClassIntrospector$MixInResolver, org.apache.htrace.shaded.fasterxml.jackson.databind.introspect.AnnotationMap);
    Code:
       0: aload_0
       1: invokespecial #42                 // Method org/apache/htrace/shaded/fasterxml/jackson/databind/introspect/Annotated."<init>":()V
       4: aload_0
       5: iconst_0
       6: putfield      #44                 // Field _creatorsResolved:Z
       9: aload_0
      10: aload_1
      11: putfield      #46                 // Field _class:Ljava/lang/Class;
      14: aload_0
      15: aload_2
      16: putfield      #48                 // Field _superTypes:Ljava/util/List;
      19: aload_0
      20: aload_3
      21: putfield      #50                 // Field _annotationIntrospector:Lorg/apache/htrace/shaded/fasterxml/jackson/databind/AnnotationIntrospector;
      24: aload_0
      25: aload         4
      27: putfield      #52                 // Field _mixInResolver:Lorg/apache/htrace/shaded/fasterxml/jackson/databind/introspect/ClassIntrospector$MixInResolver;
      30: aload_0
      31: aload_0
      32: getfield      #52                 // Field _mixInResolver:Lorg/apache/htrace/shaded/fasterxml/jackson/databind/introspect/ClassIntrospector$MixInResolver;
      35: ifnonnull     42
      38: aconst_null
      39: goto          55
      42: aload_0
      43: getfield      #52                 // Field _mixInResolver:Lorg/apache/htrace/shaded/fasterxml/jackson/databind/introspect/ClassIntrospector$MixInResolver;
      46: aload_0
      47: getfield      #46                 // Field _class:Ljava/lang/Class;
      50: invokeinterface #64,  2           // InterfaceMethod org/apache/htrace/shaded/fasterxml/jackson/databind/introspect/ClassIntrospector$MixInResolver.findMixInClassFor:(Ljava/lang/Class;)Ljava/lang/Class;
      55: putfield      #66                 // Field _primaryMixIn:Ljava/lang/Class;
      58: aload_0
      59: aload         5
      61: putfield      #68                 // Field _classAnnotations:Lorg/apache/htrace/shaded/fasterxml/jackson/databind/introspect/AnnotationMap;
      64: return

  public org.apache.htrace.shaded.fasterxml.jackson.databind.introspect.AnnotatedClass withAnnotations(org.apache.htrace.shaded.fasterxml.jackson.databind.introspect.AnnotationMap);
    Code:
       0: new           #2                  // class org/apache/htrace/shaded/fasterxml/jackson/databind/introspect/AnnotatedClass
       3: dup
       4: aload_0
       5: getfield      #46                 // Field _class:Ljava/lang/Class;
       8: aload_0
       9: getfield      #48                 // Field _superTypes:Ljava/util/List;
      12: aload_0
      13: getfield      #50                 // Field _annotationIntrospector:Lorg/apache/htrace/shaded/fasterxml/jackson/databind/AnnotationIntrospector;
      16: aload_0
      17: getfield      #52                 // Field _mixInResolver:Lorg/apache/htrace/shaded/fasterxml/jackson/databind/introspect/ClassIntrospector$MixInResolver;
      20: aload_1
      21: invokespecial #79                 // Method "<init>":(Ljava/lang/Class;Ljava/util/List;Lorg/apache/htrace/shaded/fasterxml/jackson/databind/AnnotationIntrospector;Lorg/apache/htrace/shaded/fasterxml/jackson/databind/introspect/ClassIntrospector$MixInResolver;Lorg/apache/htrace/shaded/fasterxml/jackson/databind/introspect/AnnotationMap;)V
      24: areturn

  public static org.apache.htrace.shaded.fasterxml.jackson.databind.introspect.AnnotatedClass construct(java.lang.Class<?>, org.apache.htrace.shaded.fasterxml.jackson.databind.AnnotationIntrospector, org.apache.htrace.shaded.fasterxml.jackson.databind.introspect.ClassIntrospector$MixInResolver);
    Code:
       0: new           #2                  // class org/apache/htrace/shaded/fasterxml/jackson/databind/introspect/AnnotatedClass
       3: dup
       4: aload_0
       5: aload_0
       6: aconst_null
       7: invokestatic  #88                 // Method org/apache/htrace/shaded/fasterxml/jackson/databind/util/ClassUtil.findSuperTypes:(Ljava/lang/Class;Ljava/lang/Class;)Ljava/util/List;
      10: aload_1
      11: aload_2
      12: aconst_null
      13: invokespecial #79                 // Method "<init>":(Ljava/lang/Class;Ljava/util/List;Lorg/apache/htrace/shaded/fasterxml/jackson/databind/AnnotationIntrospector;Lorg/apache/htrace/shaded/fasterxml/jackson/databind/introspect/ClassIntrospector$MixInResolver;Lorg/apache/htrace/shaded/fasterxml/jackson/databind/introspect/AnnotationMap;)V
      16: areturn

  public static org.apache.htrace.shaded.fasterxml.jackson.databind.introspect.AnnotatedClass constructWithoutSuperTypes(java.lang.Class<?>, org.apache.htrace.shaded.fasterxml.jackson.databind.AnnotationIntrospector, org.apache.htrace.shaded.fasterxml.jackson.databind.introspect.ClassIntrospector$MixInResolver);
    Code:
       0: new           #2                  // class org/apache/htrace/shaded/fasterxml/jackson/databind/introspect/AnnotatedClass
       3: dup
       4: aload_0
       5: invokestatic  #95                 // Method java/util/Collections.emptyList:()Ljava/util/List;
       8: aload_1
       9: aload_2
      10: aconst_null
      11: invokespecial #79                 // Method "<init>":(Ljava/lang/Class;Ljava/util/List;Lorg/apache/htrace/shaded/fasterxml/jackson/databind/AnnotationIntrospector;Lorg/apache/htrace/shaded/fasterxml/jackson/databind/introspect/ClassIntrospector$MixInResolver;Lorg/apache/htrace/shaded/fasterxml/jackson/databind/introspect/AnnotationMap;)V
      14: areturn

  public java.lang.Class<?> getAnnotated();
    Code:
       0: aload_0
       1: getfield      #46                 // Field _class:Ljava/lang/Class;
       4: areturn

  public int getModifiers();
    Code:
       0: aload_0
       1: getfield      #46                 // Field _class:Ljava/lang/Class;
       4: invokevirtual #101                // Method java/lang/Class.getModifiers:()I
       7: ireturn

  public java.lang.String getName();
    Code:
       0: aload_0
       1: getfield      #46                 // Field _class:Ljava/lang/Class;
       4: invokevirtual #105                // Method java/lang/Class.getName:()Ljava/lang/String;
       7: areturn

  public <A extends java.lang.annotation.Annotation> A getAnnotation(java.lang.Class<A>);
    Code:
       0: aload_0
       1: getfield      #68                 // Field _classAnnotations:Lorg/apache/htrace/shaded/fasterxml/jackson/databind/introspect/AnnotationMap;
       4: ifnonnull     11
       7: aload_0
       8: invokespecial #110                // Method resolveClassAnnotations:()V
      11: aload_0
      12: getfield      #68                 // Field _classAnnotations:Lorg/apache/htrace/shaded/fasterxml/jackson/databind/introspect/AnnotationMap;
      15: aload_1
      16: invokevirtual #113                // Method org/apache/htrace/shaded/fasterxml/jackson/databind/introspect/AnnotationMap.get:(Ljava/lang/Class;)Ljava/lang/annotation/Annotation;
      19: areturn

  public java.lang.reflect.Type getGenericType();
    Code:
       0: aload_0
       1: getfield      #46                 // Field _class:Ljava/lang/Class;
       4: areturn

  public java.lang.Class<?> getRawType();
    Code:
       0: aload_0
       1: getfield      #46                 // Field _class:Ljava/lang/Class;
       4: areturn

  public java.lang.Iterable<java.lang.annotation.Annotation> annotations();
    Code:
       0: aload_0
       1: getfield      #68                 // Field _classAnnotations:Lorg/apache/htrace/shaded/fasterxml/jackson/databind/introspect/AnnotationMap;
       4: ifnonnull     11
       7: aload_0
       8: invokespecial #110                // Method resolveClassAnnotations:()V
      11: aload_0
      12: getfield      #68                 // Field _classAnnotations:Lorg/apache/htrace/shaded/fasterxml/jackson/databind/introspect/AnnotationMap;
      15: invokevirtual #122                // Method org/apache/htrace/shaded/fasterxml/jackson/databind/introspect/AnnotationMap.annotations:()Ljava/lang/Iterable;
      18: areturn

  protected org.apache.htrace.shaded.fasterxml.jackson.databind.introspect.AnnotationMap getAllAnnotations();
    Code:
       0: aload_0
       1: getfield      #68                 // Field _classAnnotations:Lorg/apache/htrace/shaded/fasterxml/jackson/databind/introspect/AnnotationMap;
       4: ifnonnull     11
       7: aload_0
       8: invokespecial #110                // Method resolveClassAnnotations:()V
      11: aload_0
      12: getfield      #68                 // Field _classAnnotations:Lorg/apache/htrace/shaded/fasterxml/jackson/databind/introspect/AnnotationMap;
      15: areturn

  public org.apache.htrace.shaded.fasterxml.jackson.databind.util.Annotations getAnnotations();
    Code:
       0: aload_0
       1: getfield      #68                 // Field _classAnnotations:Lorg/apache/htrace/shaded/fasterxml/jackson/databind/introspect/AnnotationMap;
       4: ifnonnull     11
       7: aload_0
       8: invokespecial #110                // Method resolveClassAnnotations:()V
      11: aload_0
      12: getfield      #68                 // Field _classAnnotations:Lorg/apache/htrace/shaded/fasterxml/jackson/databind/introspect/AnnotationMap;
      15: areturn

  public boolean hasAnnotations();
    Code:
       0: aload_0
       1: getfield      #68                 // Field _classAnnotations:Lorg/apache/htrace/shaded/fasterxml/jackson/databind/introspect/AnnotationMap;
       4: ifnonnull     11
       7: aload_0
       8: invokespecial #110                // Method resolveClassAnnotations:()V
      11: aload_0
      12: getfield      #68                 // Field _classAnnotations:Lorg/apache/htrace/shaded/fasterxml/jackson/databind/introspect/AnnotationMap;
      15: invokevirtual #131                // Method org/apache/htrace/shaded/fasterxml/jackson/databind/introspect/AnnotationMap.size:()I
      18: ifle          25
      21: iconst_1
      22: goto          26
      25: iconst_0
      26: ireturn

  public org.apache.htrace.shaded.fasterxml.jackson.databind.introspect.AnnotatedConstructor getDefaultConstructor();
    Code:
       0: aload_0
       1: getfield      #44                 // Field _creatorsResolved:Z
       4: ifne          11
       7: aload_0
       8: invokespecial #136                // Method resolveCreators:()V
      11: aload_0
      12: getfield      #138                // Field _defaultConstructor:Lorg/apache/htrace/shaded/fasterxml/jackson/databind/introspect/AnnotatedConstructor;
      15: areturn

  public java.util.List<org.apache.htrace.shaded.fasterxml.jackson.databind.introspect.AnnotatedConstructor> getConstructors();
    Code:
       0: aload_0
       1: getfield      #44                 // Field _creatorsResolved:Z
       4: ifne          11
       7: aload_0
       8: invokespecial #136                // Method resolveCreators:()V
      11: aload_0
      12: getfield      #141                // Field _constructors:Ljava/util/List;
      15: areturn

  public java.util.List<org.apache.htrace.shaded.fasterxml.jackson.databind.introspect.AnnotatedMethod> getStaticMethods();
    Code:
       0: aload_0
       1: getfield      #44                 // Field _creatorsResolved:Z
       4: ifne          11
       7: aload_0
       8: invokespecial #136                // Method resolveCreators:()V
      11: aload_0
      12: getfield      #144                // Field _creatorMethods:Ljava/util/List;
      15: areturn

  public java.lang.Iterable<org.apache.htrace.shaded.fasterxml.jackson.databind.introspect.AnnotatedMethod> memberMethods();
    Code:
       0: aload_0
       1: getfield      #147                // Field _memberMethods:Lorg/apache/htrace/shaded/fasterxml/jackson/databind/introspect/AnnotatedMethodMap;
       4: ifnonnull     11
       7: aload_0
       8: invokespecial #150                // Method resolveMemberMethods:()V
      11: aload_0
      12: getfield      #147                // Field _memberMethods:Lorg/apache/htrace/shaded/fasterxml/jackson/databind/introspect/AnnotatedMethodMap;
      15: areturn

  public int getMemberMethodCount();
    Code:
       0: aload_0
       1: getfield      #147                // Field _memberMethods:Lorg/apache/htrace/shaded/fasterxml/jackson/databind/introspect/AnnotatedMethodMap;
       4: ifnonnull     11
       7: aload_0
       8: invokespecial #150                // Method resolveMemberMethods:()V
      11: aload_0
      12: getfield      #147                // Field _memberMethods:Lorg/apache/htrace/shaded/fasterxml/jackson/databind/introspect/AnnotatedMethodMap;
      15: invokevirtual #154                // Method org/apache/htrace/shaded/fasterxml/jackson/databind/introspect/AnnotatedMethodMap.size:()I
      18: ireturn

  public org.apache.htrace.shaded.fasterxml.jackson.databind.introspect.AnnotatedMethod findMethod(java.lang.String, java.lang.Class<?>[]);
    Code:
       0: aload_0
       1: getfield      #147                // Field _memberMethods:Lorg/apache/htrace/shaded/fasterxml/jackson/databind/introspect/AnnotatedMethodMap;
       4: ifnonnull     11
       7: aload_0
       8: invokespecial #150                // Method resolveMemberMethods:()V
      11: aload_0
      12: getfield      #147                // Field _memberMethods:Lorg/apache/htrace/shaded/fasterxml/jackson/databind/introspect/AnnotatedMethodMap;
      15: aload_1
      16: aload_2
      17: invokevirtual #159                // Method org/apache/htrace/shaded/fasterxml/jackson/databind/introspect/AnnotatedMethodMap.find:(Ljava/lang/String;[Ljava/lang/Class;)Lorg/apache/htrace/shaded/fasterxml/jackson/databind/introspect/AnnotatedMethod;
      20: areturn

  public int getFieldCount();
    Code:
       0: aload_0
       1: getfield      #167                // Field _fields:Ljava/util/List;
       4: ifnonnull     11
       7: aload_0
       8: invokespecial #170                // Method resolveFields:()V
      11: aload_0
      12: getfield      #167                // Field _fields:Ljava/util/List;
      15: invokeinterface #171,  1          // InterfaceMethod java/util/List.size:()I
      20: ireturn

  public java.lang.Iterable<org.apache.htrace.shaded.fasterxml.jackson.databind.introspect.AnnotatedField> fields();
    Code:
       0: aload_0
       1: getfield      #167                // Field _fields:Ljava/util/List;
       4: ifnonnull     11
       7: aload_0
       8: invokespecial #170                // Method resolveFields:()V
      11: aload_0
      12: getfield      #167                // Field _fields:Ljava/util/List;
      15: areturn

  private void resolveClassAnnotations();
    Code:
       0: aload_0
       1: new           #60                 // class org/apache/htrace/shaded/fasterxml/jackson/databind/introspect/AnnotationMap
       4: dup
       5: invokespecial #173                // Method org/apache/htrace/shaded/fasterxml/jackson/databind/introspect/AnnotationMap."<init>":()V
       8: putfield      #68                 // Field _classAnnotations:Lorg/apache/htrace/shaded/fasterxml/jackson/databind/introspect/AnnotationMap;
      11: aload_0
      12: getfield      #50                 // Field _annotationIntrospector:Lorg/apache/htrace/shaded/fasterxml/jackson/databind/AnnotationIntrospector;
      15: ifnull        119
      18: aload_0
      19: getfield      #66                 // Field _primaryMixIn:Ljava/lang/Class;
      22: ifnull        41
      25: aload_0
      26: aload_0
      27: getfield      #68                 // Field _classAnnotations:Lorg/apache/htrace/shaded/fasterxml/jackson/databind/introspect/AnnotationMap;
      30: aload_0
      31: getfield      #46                 // Field _class:Ljava/lang/Class;
      34: aload_0
      35: getfield      #66                 // Field _primaryMixIn:Ljava/lang/Class;
      38: invokevirtual #177                // Method _addClassMixIns:(Lorg/apache/htrace/shaded/fasterxml/jackson/databind/introspect/AnnotationMap;Ljava/lang/Class;Ljava/lang/Class;)V
      41: aload_0
      42: aload_0
      43: getfield      #68                 // Field _classAnnotations:Lorg/apache/htrace/shaded/fasterxml/jackson/databind/introspect/AnnotationMap;
      46: aload_0
      47: getfield      #46                 // Field _class:Ljava/lang/Class;
      50: invokevirtual #181                // Method java/lang/Class.getDeclaredAnnotations:()[Ljava/lang/annotation/Annotation;
      53: invokespecial #185                // Method _addAnnotationsIfNotPresent:(Lorg/apache/htrace/shaded/fasterxml/jackson/databind/introspect/AnnotationMap;[Ljava/lang/annotation/Annotation;)V
      56: aload_0
      57: getfield      #48                 // Field _superTypes:Ljava/util/List;
      60: invokeinterface #189,  1          // InterfaceMethod java/util/List.iterator:()Ljava/util/Iterator;
      65: astore_1
      66: aload_1
      67: invokeinterface #194,  1          // InterfaceMethod java/util/Iterator.hasNext:()Z
      72: ifeq          109
      75: aload_1
      76: invokeinterface #198,  1          // InterfaceMethod java/util/Iterator.next:()Ljava/lang/Object;
      81: checkcast     #54                 // class java/lang/Class
      84: astore_2
      85: aload_0
      86: aload_0
      87: getfield      #68                 // Field _classAnnotations:Lorg/apache/htrace/shaded/fasterxml/jackson/databind/introspect/AnnotationMap;
      90: aload_2
      91: invokevirtual #201                // Method _addClassMixIns:(Lorg/apache/htrace/shaded/fasterxml/jackson/databind/introspect/AnnotationMap;Ljava/lang/Class;)V
      94: aload_0
      95: aload_0
      96: getfield      #68                 // Field _classAnnotations:Lorg/apache/htrace/shaded/fasterxml/jackson/databind/introspect/AnnotationMap;
      99: aload_2
     100: invokevirtual #181                // Method java/lang/Class.getDeclaredAnnotations:()[Ljava/lang/annotation/Annotation;
     103: invokespecial #185                // Method _addAnnotationsIfNotPresent:(Lorg/apache/htrace/shaded/fasterxml/jackson/databind/introspect/AnnotationMap;[Ljava/lang/annotation/Annotation;)V
     106: goto          66
     109: aload_0
     110: aload_0
     111: getfield      #68                 // Field _classAnnotations:Lorg/apache/htrace/shaded/fasterxml/jackson/databind/introspect/AnnotationMap;
     114: ldc           #203                // class java/lang/Object
     116: invokevirtual #201                // Method _addClassMixIns:(Lorg/apache/htrace/shaded/fasterxml/jackson/databind/introspect/AnnotationMap;Ljava/lang/Class;)V
     119: return

  private void resolveCreators();
    Code:
       0: aconst_null
       1: astore_1
       2: aload_0
       3: getfield      #46                 // Field _class:Ljava/lang/Class;
       6: invokevirtual #209                // Method java/lang/Class.getDeclaredConstructors:()[Ljava/lang/reflect/Constructor;
       9: astore_2
      10: aload_2
      11: astore_3
      12: aload_3
      13: arraylength
      14: istore        4
      16: iconst_0
      17: istore        5
      19: iload         5
      21: iload         4
      23: if_icmpge     94
      26: aload_3
      27: iload         5
      29: aaload
      30: astore        6
      32: aload         6
      34: invokevirtual #217                // Method java/lang/reflect/Constructor.getParameterTypes:()[Ljava/lang/Class;
      37: arraylength
      38: ifne          55
      41: aload_0
      42: aload_0
      43: aload         6
      45: iconst_1
      46: invokevirtual #221                // Method _constructConstructor:(Ljava/lang/reflect/Constructor;Z)Lorg/apache/htrace/shaded/fasterxml/jackson/databind/introspect/AnnotatedConstructor;
      49: putfield      #138                // Field _defaultConstructor:Lorg/apache/htrace/shaded/fasterxml/jackson/databind/introspect/AnnotatedConstructor;
      52: goto          88
      55: aload_1
      56: ifnonnull     74
      59: new           #223                // class java/util/ArrayList
      62: dup
      63: bipush        10
      65: aload_2
      66: arraylength
      67: invokestatic  #229                // Method java/lang/Math.max:(II)I
      70: invokespecial #232                // Method java/util/ArrayList."<init>":(I)V
      73: astore_1
      74: aload_1
      75: aload_0
      76: aload         6
      78: iconst_0
      79: invokevirtual #221                // Method _constructConstructor:(Ljava/lang/reflect/Constructor;Z)Lorg/apache/htrace/shaded/fasterxml/jackson/databind/introspect/AnnotatedConstructor;
      82: invokeinterface #236,  2          // InterfaceMethod java/util/List.add:(Ljava/lang/Object;)Z
      87: pop
      88: iinc          5, 1
      91: goto          19
      94: aload_1
      95: ifnonnull     108
      98: aload_0
      99: invokestatic  #95                 // Method java/util/Collections.emptyList:()Ljava/util/List;
     102: putfield      #141                // Field _constructors:Ljava/util/List;
     105: goto          113
     108: aload_0
     109: aload_1
     110: putfield      #141                // Field _constructors:Ljava/util/List;
     113: aload_0
     114: getfield      #66                 // Field _primaryMixIn:Ljava/lang/Class;
     117: ifnull        147
     120: aload_0
     121: getfield      #138                // Field _defaultConstructor:Lorg/apache/htrace/shaded/fasterxml/jackson/databind/introspect/AnnotatedConstructor;
     124: ifnonnull     139
     127: aload_0
     128: getfield      #141                // Field _constructors:Ljava/util/List;
     131: invokeinterface #239,  1          // InterfaceMethod java/util/List.isEmpty:()Z
     136: ifne          147
     139: aload_0
     140: aload_0
     141: getfield      #66                 // Field _primaryMixIn:Ljava/lang/Class;
     144: invokevirtual #243                // Method _addConstructorMixIns:(Ljava/lang/Class;)V
     147: aload_0
     148: getfield      #50                 // Field _annotationIntrospector:Lorg/apache/htrace/shaded/fasterxml/jackson/databind/AnnotationIntrospector;
     151: ifnull        241
     154: aload_0
     155: getfield      #138                // Field _defaultConstructor:Lorg/apache/htrace/shaded/fasterxml/jackson/databind/introspect/AnnotatedConstructor;
     158: ifnull        180
     161: aload_0
     162: getfield      #50                 // Field _annotationIntrospector:Lorg/apache/htrace/shaded/fasterxml/jackson/databind/AnnotationIntrospector;
     165: aload_0
     166: getfield      #138                // Field _defaultConstructor:Lorg/apache/htrace/shaded/fasterxml/jackson/databind/introspect/AnnotatedConstructor;
     169: invokevirtual #247                // Method org/apache/htrace/shaded/fasterxml/jackson/databind/AnnotationIntrospector.hasIgnoreMarker:(Lorg/apache/htrace/shaded/fasterxml/jackson/databind/introspect/AnnotatedMember;)Z
     172: ifeq          180
     175: aload_0
     176: aconst_null
     177: putfield      #138                // Field _defaultConstructor:Lorg/apache/htrace/shaded/fasterxml/jackson/databind/introspect/AnnotatedConstructor;
     180: aload_0
     181: getfield      #141                // Field _constructors:Ljava/util/List;
     184: ifnull        241
     187: aload_0
     188: getfield      #141                // Field _constructors:Ljava/util/List;
     191: invokeinterface #171,  1          // InterfaceMethod java/util/List.size:()I
     196: istore_3
     197: iinc          3, -1
     200: iload_3
     201: iflt          241
     204: aload_0
     205: getfield      #50                 // Field _annotationIntrospector:Lorg/apache/htrace/shaded/fasterxml/jackson/databind/AnnotationIntrospector;
     208: aload_0
     209: getfield      #141                // Field _constructors:Ljava/util/List;
     212: iload_3
     213: invokeinterface #250,  2          // InterfaceMethod java/util/List.get:(I)Ljava/lang/Object;
     218: checkcast     #252                // class org/apache/htrace/shaded/fasterxml/jackson/databind/introspect/AnnotatedMember
     221: invokevirtual #247                // Method org/apache/htrace/shaded/fasterxml/jackson/databind/AnnotationIntrospector.hasIgnoreMarker:(Lorg/apache/htrace/shaded/fasterxml/jackson/databind/introspect/AnnotatedMember;)Z
     224: ifeq          197
     227: aload_0
     228: getfield      #141                // Field _constructors:Ljava/util/List;
     231: iload_3
     232: invokeinterface #255,  2          // InterfaceMethod java/util/List.remove:(I)Ljava/lang/Object;
     237: pop
     238: goto          197
     241: aconst_null
     242: astore_3
     243: aload_0
     244: getfield      #46                 // Field _class:Ljava/lang/Class;
     247: invokevirtual #259                // Method java/lang/Class.getDeclaredMethods:()[Ljava/lang/reflect/Method;
     250: astore        4
     252: aload         4
     254: arraylength
     255: istore        5
     257: iconst_0
     258: istore        6
     260: iload         6
     262: iload         5
     264: if_icmpge     321
     267: aload         4
     269: iload         6
     271: aaload
     272: astore        7
     274: aload         7
     276: invokevirtual #264                // Method java/lang/reflect/Method.getModifiers:()I
     279: invokestatic  #270                // Method java/lang/reflect/Modifier.isStatic:(I)Z
     282: ifne          288
     285: goto          315
     288: aload_3
     289: ifnonnull     302
     292: new           #223                // class java/util/ArrayList
     295: dup
     296: bipush        8
     298: invokespecial #232                // Method java/util/ArrayList."<init>":(I)V
     301: astore_3
     302: aload_3
     303: aload_0
     304: aload         7
     306: invokevirtual #274                // Method _constructCreatorMethod:(Ljava/lang/reflect/Method;)Lorg/apache/htrace/shaded/fasterxml/jackson/databind/introspect/AnnotatedMethod;
     309: invokeinterface #236,  2          // InterfaceMethod java/util/List.add:(Ljava/lang/Object;)Z
     314: pop
     315: iinc          6, 1
     318: goto          260
     321: aload_3
     322: ifnonnull     335
     325: aload_0
     326: invokestatic  #95                 // Method java/util/Collections.emptyList:()Ljava/util/List;
     329: putfield      #144                // Field _creatorMethods:Ljava/util/List;
     332: goto          420
     335: aload_0
     336: aload_3
     337: putfield      #144                // Field _creatorMethods:Ljava/util/List;
     340: aload_0
     341: getfield      #66                 // Field _primaryMixIn:Ljava/lang/Class;
     344: ifnull        355
     347: aload_0
     348: aload_0
     349: getfield      #66                 // Field _primaryMixIn:Ljava/lang/Class;
     352: invokevirtual #277                // Method _addFactoryMixIns:(Ljava/lang/Class;)V
     355: aload_0
     356: getfield      #50                 // Field _annotationIntrospector:Lorg/apache/htrace/shaded/fasterxml/jackson/databind/AnnotationIntrospector;
     359: ifnull        420
     362: aload_0
     363: getfield      #144                // Field _creatorMethods:Ljava/util/List;
     366: invokeinterface #171,  1          // InterfaceMethod java/util/List.size:()I
     371: istore        4
     373: iinc          4, -1
     376: iload         4
     378: iflt          420
     381: aload_0
     382: getfield      #50                 // Field _annotationIntrospector:Lorg/apache/htrace/shaded/fasterxml/jackson/databind/AnnotationIntrospector;
     385: aload_0
     386: getfield      #144                // Field _creatorMethods:Ljava/util/List;
     389: iload         4
     391: invokeinterface #250,  2          // InterfaceMethod java/util/List.get:(I)Ljava/lang/Object;
     396: checkcast     #252                // class org/apache/htrace/shaded/fasterxml/jackson/databind/introspect/AnnotatedMember
     399: invokevirtual #247                // Method org/apache/htrace/shaded/fasterxml/jackson/databind/AnnotationIntrospector.hasIgnoreMarker:(Lorg/apache/htrace/shaded/fasterxml/jackson/databind/introspect/AnnotatedMember;)Z
     402: ifeq          373
     405: aload_0
     406: getfield      #144                // Field _creatorMethods:Ljava/util/List;
     409: iload         4
     411: invokeinterface #255,  2          // InterfaceMethod java/util/List.remove:(I)Ljava/lang/Object;
     416: pop
     417: goto          373
     420: aload_0
     421: iconst_1
     422: putfield      #44                 // Field _creatorsResolved:Z
     425: return

  private void resolveMemberMethods();
    Code:
       0: aload_0
       1: new           #153                // class org/apache/htrace/shaded/fasterxml/jackson/databind/introspect/AnnotatedMethodMap
       4: dup
       5: invokespecial #293                // Method org/apache/htrace/shaded/fasterxml/jackson/databind/introspect/AnnotatedMethodMap."<init>":()V
       8: putfield      #147                // Field _memberMethods:Lorg/apache/htrace/shaded/fasterxml/jackson/databind/introspect/AnnotatedMethodMap;
      11: new           #153                // class org/apache/htrace/shaded/fasterxml/jackson/databind/introspect/AnnotatedMethodMap
      14: dup
      15: invokespecial #293                // Method org/apache/htrace/shaded/fasterxml/jackson/databind/introspect/AnnotatedMethodMap."<init>":()V
      18: astore_1
      19: aload_0
      20: aload_0
      21: getfield      #46                 // Field _class:Ljava/lang/Class;
      24: aload_0
      25: getfield      #147                // Field _memberMethods:Lorg/apache/htrace/shaded/fasterxml/jackson/databind/introspect/AnnotatedMethodMap;
      28: aload_0
      29: getfield      #66                 // Field _primaryMixIn:Ljava/lang/Class;
      32: aload_1
      33: invokevirtual #297                // Method _addMemberMethods:(Ljava/lang/Class;Lorg/apache/htrace/shaded/fasterxml/jackson/databind/introspect/AnnotatedMethodMap;Ljava/lang/Class;Lorg/apache/htrace/shaded/fasterxml/jackson/databind/introspect/AnnotatedMethodMap;)V
      36: aload_0
      37: getfield      #48                 // Field _superTypes:Ljava/util/List;
      40: invokeinterface #189,  1          // InterfaceMethod java/util/List.iterator:()Ljava/util/Iterator;
      45: astore_2
      46: aload_2
      47: invokeinterface #194,  1          // InterfaceMethod java/util/Iterator.hasNext:()Z
      52: ifeq          103
      55: aload_2
      56: invokeinterface #198,  1          // InterfaceMethod java/util/Iterator.next:()Ljava/lang/Object;
      61: checkcast     #54                 // class java/lang/Class
      64: astore_3
      65: aload_0
      66: getfield      #52                 // Field _mixInResolver:Lorg/apache/htrace/shaded/fasterxml/jackson/databind/introspect/ClassIntrospector$MixInResolver;
      69: ifnonnull     76
      72: aconst_null
      73: goto          86
      76: aload_0
      77: getfield      #52                 // Field _mixInResolver:Lorg/apache/htrace/shaded/fasterxml/jackson/databind/introspect/ClassIntrospector$MixInResolver;
      80: aload_3
      81: invokeinterface #64,  2           // InterfaceMethod org/apache/htrace/shaded/fasterxml/jackson/databind/introspect/ClassIntrospector$MixInResolver.findMixInClassFor:(Ljava/lang/Class;)Ljava/lang/Class;
      86: astore        4
      88: aload_0
      89: aload_3
      90: aload_0
      91: getfield      #147                // Field _memberMethods:Lorg/apache/htrace/shaded/fasterxml/jackson/databind/introspect/AnnotatedMethodMap;
      94: aload         4
      96: aload_1
      97: invokevirtual #297                // Method _addMemberMethods:(Ljava/lang/Class;Lorg/apache/htrace/shaded/fasterxml/jackson/databind/introspect/AnnotatedMethodMap;Ljava/lang/Class;Lorg/apache/htrace/shaded/fasterxml/jackson/databind/introspect/AnnotatedMethodMap;)V
     100: goto          46
     103: aload_0
     104: getfield      #52                 // Field _mixInResolver:Lorg/apache/htrace/shaded/fasterxml/jackson/databind/introspect/ClassIntrospector$MixInResolver;
     107: ifnull        140
     110: aload_0
     111: getfield      #52                 // Field _mixInResolver:Lorg/apache/htrace/shaded/fasterxml/jackson/databind/introspect/ClassIntrospector$MixInResolver;
     114: ldc           #203                // class java/lang/Object
     116: invokeinterface #64,  2           // InterfaceMethod org/apache/htrace/shaded/fasterxml/jackson/databind/introspect/ClassIntrospector$MixInResolver.findMixInClassFor:(Ljava/lang/Class;)Ljava/lang/Class;
     121: astore_2
     122: aload_2
     123: ifnull        140
     126: aload_0
     127: aload_0
     128: getfield      #46                 // Field _class:Ljava/lang/Class;
     131: aload_0
     132: getfield      #147                // Field _memberMethods:Lorg/apache/htrace/shaded/fasterxml/jackson/databind/introspect/AnnotatedMethodMap;
     135: aload_2
     136: aload_1
     137: invokevirtual #300                // Method _addMethodMixIns:(Ljava/lang/Class;Lorg/apache/htrace/shaded/fasterxml/jackson/databind/introspect/AnnotatedMethodMap;Ljava/lang/Class;Lorg/apache/htrace/shaded/fasterxml/jackson/databind/introspect/AnnotatedMethodMap;)V
     140: aload_0
     141: getfield      #50                 // Field _annotationIntrospector:Lorg/apache/htrace/shaded/fasterxml/jackson/databind/AnnotationIntrospector;
     144: ifnull        234
     147: aload_1
     148: invokevirtual #301                // Method org/apache/htrace/shaded/fasterxml/jackson/databind/introspect/AnnotatedMethodMap.isEmpty:()Z
     151: ifne          234
     154: aload_1
     155: invokevirtual #302                // Method org/apache/htrace/shaded/fasterxml/jackson/databind/introspect/AnnotatedMethodMap.iterator:()Ljava/util/Iterator;
     158: astore_2
     159: aload_2
     160: invokeinterface #194,  1          // InterfaceMethod java/util/Iterator.hasNext:()Z
     165: ifeq          234
     168: aload_2
     169: invokeinterface #198,  1          // InterfaceMethod java/util/Iterator.next:()Ljava/lang/Object;
     174: checkcast     #304                // class org/apache/htrace/shaded/fasterxml/jackson/databind/introspect/AnnotatedMethod
     177: astore_3
     178: ldc           #203                // class java/lang/Object
     180: aload_3
     181: invokevirtual #305                // Method org/apache/htrace/shaded/fasterxml/jackson/databind/introspect/AnnotatedMethod.getName:()Ljava/lang/String;
     184: aload_3
     185: invokevirtual #308                // Method org/apache/htrace/shaded/fasterxml/jackson/databind/introspect/AnnotatedMethod.getRawParameterTypes:()[Ljava/lang/Class;
     188: invokevirtual #312                // Method java/lang/Class.getDeclaredMethod:(Ljava/lang/String;[Ljava/lang/Class;)Ljava/lang/reflect/Method;
     191: astore        4
     193: aload         4
     195: ifnull        226
     198: aload_0
     199: aload         4
     201: invokevirtual #315                // Method _constructMethod:(Ljava/lang/reflect/Method;)Lorg/apache/htrace/shaded/fasterxml/jackson/databind/introspect/AnnotatedMethod;
     204: astore        5
     206: aload_0
     207: aload_3
     208: invokevirtual #318                // Method org/apache/htrace/shaded/fasterxml/jackson/databind/introspect/AnnotatedMethod.getAnnotated:()Ljava/lang/reflect/Method;
     211: aload         5
     213: iconst_0
     214: invokevirtual #322                // Method _addMixOvers:(Ljava/lang/reflect/Method;Lorg/apache/htrace/shaded/fasterxml/jackson/databind/introspect/AnnotatedMethod;Z)V
     217: aload_0
     218: getfield      #147                // Field _memberMethods:Lorg/apache/htrace/shaded/fasterxml/jackson/databind/introspect/AnnotatedMethodMap;
     221: aload         5
     223: invokevirtual #325                // Method org/apache/htrace/shaded/fasterxml/jackson/databind/introspect/AnnotatedMethodMap.add:(Lorg/apache/htrace/shaded/fasterxml/jackson/databind/introspect/AnnotatedMethod;)V
     226: goto          231
     229: astore        4
     231: goto          159
     234: return
    Exception table:
       from    to  target type
         178   226   229   Class java/lang/Exception

  private void resolveFields();
    Code:
       0: aload_0
       1: aload_0
       2: getfield      #46                 // Field _class:Ljava/lang/Class;
       5: aconst_null
       6: invokevirtual #338                // Method _findFields:(Ljava/lang/Class;Ljava/util/Map;)Ljava/util/Map;
       9: astore_1
      10: aload_1
      11: ifnull        23
      14: aload_1
      15: invokeinterface #341,  1          // InterfaceMethod java/util/Map.size:()I
      20: ifne          33
      23: aload_0
      24: invokestatic  #95                 // Method java/util/Collections.emptyList:()Ljava/util/List;
      27: putfield      #167                // Field _fields:Ljava/util/List;
      30: goto          66
      33: aload_0
      34: new           #223                // class java/util/ArrayList
      37: dup
      38: aload_1
      39: invokeinterface #341,  1          // InterfaceMethod java/util/Map.size:()I
      44: invokespecial #232                // Method java/util/ArrayList."<init>":(I)V
      47: putfield      #167                // Field _fields:Ljava/util/List;
      50: aload_0
      51: getfield      #167                // Field _fields:Ljava/util/List;
      54: aload_1
      55: invokeinterface #345,  1          // InterfaceMethod java/util/Map.values:()Ljava/util/Collection;
      60: invokeinterface #349,  2          // InterfaceMethod java/util/List.addAll:(Ljava/util/Collection;)Z
      65: pop
      66: return

  protected void _addClassMixIns(org.apache.htrace.shaded.fasterxml.jackson.databind.introspect.AnnotationMap, java.lang.Class<?>);
    Code:
       0: aload_0
       1: getfield      #52                 // Field _mixInResolver:Lorg/apache/htrace/shaded/fasterxml/jackson/databind/introspect/ClassIntrospector$MixInResolver;
       4: ifnull        23
       7: aload_0
       8: aload_1
       9: aload_2
      10: aload_0
      11: getfield      #52                 // Field _mixInResolver:Lorg/apache/htrace/shaded/fasterxml/jackson/databind/introspect/ClassIntrospector$MixInResolver;
      14: aload_2
      15: invokeinterface #64,  2           // InterfaceMethod org/apache/htrace/shaded/fasterxml/jackson/databind/introspect/ClassIntrospector$MixInResolver.findMixInClassFor:(Ljava/lang/Class;)Ljava/lang/Class;
      20: invokevirtual #177                // Method _addClassMixIns:(Lorg/apache/htrace/shaded/fasterxml/jackson/databind/introspect/AnnotationMap;Ljava/lang/Class;Ljava/lang/Class;)V
      23: return

  protected void _addClassMixIns(org.apache.htrace.shaded.fasterxml.jackson.databind.introspect.AnnotationMap, java.lang.Class<?>, java.lang.Class<?>);
    Code:
       0: aload_3
       1: ifnonnull     5
       4: return
       5: aload_0
       6: aload_1
       7: aload_3
       8: invokevirtual #181                // Method java/lang/Class.getDeclaredAnnotations:()[Ljava/lang/annotation/Annotation;
      11: invokespecial #185                // Method _addAnnotationsIfNotPresent:(Lorg/apache/htrace/shaded/fasterxml/jackson/databind/introspect/AnnotationMap;[Ljava/lang/annotation/Annotation;)V
      14: aload_3
      15: aload_2
      16: invokestatic  #88                 // Method org/apache/htrace/shaded/fasterxml/jackson/databind/util/ClassUtil.findSuperTypes:(Ljava/lang/Class;Ljava/lang/Class;)Ljava/util/List;
      19: invokeinterface #189,  1          // InterfaceMethod java/util/List.iterator:()Ljava/util/Iterator;
      24: astore        4
      26: aload         4
      28: invokeinterface #194,  1          // InterfaceMethod java/util/Iterator.hasNext:()Z
      33: ifeq          61
      36: aload         4
      38: invokeinterface #198,  1          // InterfaceMethod java/util/Iterator.next:()Ljava/lang/Object;
      43: checkcast     #54                 // class java/lang/Class
      46: astore        5
      48: aload_0
      49: aload_1
      50: aload         5
      52: invokevirtual #181                // Method java/lang/Class.getDeclaredAnnotations:()[Ljava/lang/annotation/Annotation;
      55: invokespecial #185                // Method _addAnnotationsIfNotPresent:(Lorg/apache/htrace/shaded/fasterxml/jackson/databind/introspect/AnnotationMap;[Ljava/lang/annotation/Annotation;)V
      58: goto          26
      61: return

  protected void _addConstructorMixIns(java.lang.Class<?>);
    Code:
       0: aconst_null
       1: astore_2
       2: aload_0
       3: getfield      #141                // Field _constructors:Ljava/util/List;
       6: ifnonnull     13
       9: iconst_0
      10: goto          22
      13: aload_0
      14: getfield      #141                // Field _constructors:Ljava/util/List;
      17: invokeinterface #171,  1          // InterfaceMethod java/util/List.size:()I
      22: istore_3
      23: aload_1
      24: invokevirtual #209                // Method java/lang/Class.getDeclaredConstructors:()[Ljava/lang/reflect/Constructor;
      27: astore        4
      29: aload         4
      31: arraylength
      32: istore        5
      34: iconst_0
      35: istore        6
      37: iload         6
      39: iload         5
      41: if_icmpge     204
      44: aload         4
      46: iload         6
      48: aaload
      49: astore        7
      51: aload         7
      53: invokevirtual #217                // Method java/lang/reflect/Constructor.getParameterTypes:()[Ljava/lang/Class;
      56: arraylength
      57: ifne          81
      60: aload_0
      61: getfield      #138                // Field _defaultConstructor:Lorg/apache/htrace/shaded/fasterxml/jackson/databind/introspect/AnnotatedConstructor;
      64: ifnull        198
      67: aload_0
      68: aload         7
      70: aload_0
      71: getfield      #138                // Field _defaultConstructor:Lorg/apache/htrace/shaded/fasterxml/jackson/databind/introspect/AnnotatedConstructor;
      74: iconst_0
      75: invokevirtual #359                // Method _addMixOvers:(Ljava/lang/reflect/Constructor;Lorg/apache/htrace/shaded/fasterxml/jackson/databind/introspect/AnnotatedConstructor;Z)V
      78: goto          198
      81: aload_2
      82: ifnonnull     133
      85: iload_3
      86: anewarray     #361                // class org/apache/htrace/shaded/fasterxml/jackson/databind/introspect/MemberKey
      89: astore_2
      90: iconst_0
      91: istore        8
      93: iload         8
      95: iload_3
      96: if_icmpge     133
      99: aload_2
     100: iload         8
     102: new           #361                // class org/apache/htrace/shaded/fasterxml/jackson/databind/introspect/MemberKey
     105: dup
     106: aload_0
     107: getfield      #141                // Field _constructors:Ljava/util/List;
     110: iload         8
     112: invokeinterface #250,  2          // InterfaceMethod java/util/List.get:(I)Ljava/lang/Object;
     117: checkcast     #363                // class org/apache/htrace/shaded/fasterxml/jackson/databind/introspect/AnnotatedConstructor
     120: invokevirtual #366                // Method org/apache/htrace/shaded/fasterxml/jackson/databind/introspect/AnnotatedConstructor.getAnnotated:()Ljava/lang/reflect/Constructor;
     123: invokespecial #369                // Method org/apache/htrace/shaded/fasterxml/jackson/databind/introspect/MemberKey."<init>":(Ljava/lang/reflect/Constructor;)V
     126: aastore
     127: iinc          8, 1
     130: goto          93
     133: new           #361                // class org/apache/htrace/shaded/fasterxml/jackson/databind/introspect/MemberKey
     136: dup
     137: aload         7
     139: invokespecial #369                // Method org/apache/htrace/shaded/fasterxml/jackson/databind/introspect/MemberKey."<init>":(Ljava/lang/reflect/Constructor;)V
     142: astore        8
     144: iconst_0
     145: istore        9
     147: iload         9
     149: iload_3
     150: if_icmpge     198
     153: aload         8
     155: aload_2
     156: iload         9
     158: aaload
     159: invokevirtual #372                // Method org/apache/htrace/shaded/fasterxml/jackson/databind/introspect/MemberKey.equals:(Ljava/lang/Object;)Z
     162: ifne          168
     165: goto          192
     168: aload_0
     169: aload         7
     171: aload_0
     172: getfield      #141                // Field _constructors:Ljava/util/List;
     175: iload         9
     177: invokeinterface #250,  2          // InterfaceMethod java/util/List.get:(I)Ljava/lang/Object;
     182: checkcast     #363                // class org/apache/htrace/shaded/fasterxml/jackson/databind/introspect/AnnotatedConstructor
     185: iconst_1
     186: invokevirtual #359                // Method _addMixOvers:(Ljava/lang/reflect/Constructor;Lorg/apache/htrace/shaded/fasterxml/jackson/databind/introspect/AnnotatedConstructor;Z)V
     189: goto          198
     192: iinc          9, 1
     195: goto          147
     198: iinc          6, 1
     201: goto          37
     204: return

  protected void _addFactoryMixIns(java.lang.Class<?>);
    Code:
       0: aconst_null
       1: astore_2
       2: aload_0
       3: getfield      #144                // Field _creatorMethods:Ljava/util/List;
       6: invokeinterface #171,  1          // InterfaceMethod java/util/List.size:()I
      11: istore_3
      12: aload_1
      13: invokevirtual #259                // Method java/lang/Class.getDeclaredMethods:()[Ljava/lang/reflect/Method;
      16: astore        4
      18: aload         4
      20: arraylength
      21: istore        5
      23: iconst_0
      24: istore        6
      26: iload         6
      28: iload         5
      30: if_icmpge     189
      33: aload         4
      35: iload         6
      37: aaload
      38: astore        7
      40: aload         7
      42: invokevirtual #264                // Method java/lang/reflect/Method.getModifiers:()I
      45: invokestatic  #270                // Method java/lang/reflect/Modifier.isStatic:(I)Z
      48: ifne          54
      51: goto          183
      54: aload         7
      56: invokevirtual #377                // Method java/lang/reflect/Method.getParameterTypes:()[Ljava/lang/Class;
      59: arraylength
      60: ifne          66
      63: goto          183
      66: aload_2
      67: ifnonnull     118
      70: iload_3
      71: anewarray     #361                // class org/apache/htrace/shaded/fasterxml/jackson/databind/introspect/MemberKey
      74: astore_2
      75: iconst_0
      76: istore        8
      78: iload         8
      80: iload_3
      81: if_icmpge     118
      84: aload_2
      85: iload         8
      87: new           #361                // class org/apache/htrace/shaded/fasterxml/jackson/databind/introspect/MemberKey
      90: dup
      91: aload_0
      92: getfield      #144                // Field _creatorMethods:Ljava/util/List;
      95: iload         8
      97: invokeinterface #250,  2          // InterfaceMethod java/util/List.get:(I)Ljava/lang/Object;
     102: checkcast     #304                // class org/apache/htrace/shaded/fasterxml/jackson/databind/introspect/AnnotatedMethod
     105: invokevirtual #318                // Method org/apache/htrace/shaded/fasterxml/jackson/databind/introspect/AnnotatedMethod.getAnnotated:()Ljava/lang/reflect/Method;
     108: invokespecial #380                // Method org/apache/htrace/shaded/fasterxml/jackson/databind/introspect/MemberKey."<init>":(Ljava/lang/reflect/Method;)V
     111: aastore
     112: iinc          8, 1
     115: goto          78
     118: new           #361                // class org/apache/htrace/shaded/fasterxml/jackson/databind/introspect/MemberKey
     121: dup
     122: aload         7
     124: invokespecial #380                // Method org/apache/htrace/shaded/fasterxml/jackson/databind/introspect/MemberKey."<init>":(Ljava/lang/reflect/Method;)V
     127: astore        8
     129: iconst_0
     130: istore        9
     132: iload         9
     134: iload_3
     135: if_icmpge     183
     138: aload         8
     140: aload_2
     141: iload         9
     143: aaload
     144: invokevirtual #372                // Method org/apache/htrace/shaded/fasterxml/jackson/databind/introspect/MemberKey.equals:(Ljava/lang/Object;)Z
     147: ifne          153
     150: goto          177
     153: aload_0
     154: aload         7
     156: aload_0
     157: getfield      #144                // Field _creatorMethods:Ljava/util/List;
     160: iload         9
     162: invokeinterface #250,  2          // InterfaceMethod java/util/List.get:(I)Ljava/lang/Object;
     167: checkcast     #304                // class org/apache/htrace/shaded/fasterxml/jackson/databind/introspect/AnnotatedMethod
     170: iconst_1
     171: invokevirtual #322                // Method _addMixOvers:(Ljava/lang/reflect/Method;Lorg/apache/htrace/shaded/fasterxml/jackson/databind/introspect/AnnotatedMethod;Z)V
     174: goto          183
     177: iinc          9, 1
     180: goto          132
     183: iinc          6, 1
     186: goto          26
     189: return

  protected void _addMemberMethods(java.lang.Class<?>, org.apache.htrace.shaded.fasterxml.jackson.databind.introspect.AnnotatedMethodMap, java.lang.Class<?>, org.apache.htrace.shaded.fasterxml.jackson.databind.introspect.AnnotatedMethodMap);
    Code:
       0: aload_3
       1: ifnull        13
       4: aload_0
       5: aload_1
       6: aload_2
       7: aload_3
       8: aload         4
      10: invokevirtual #300                // Method _addMethodMixIns:(Ljava/lang/Class;Lorg/apache/htrace/shaded/fasterxml/jackson/databind/introspect/AnnotatedMethodMap;Ljava/lang/Class;Lorg/apache/htrace/shaded/fasterxml/jackson/databind/introspect/AnnotatedMethodMap;)V
      13: aload_1
      14: ifnonnull     18
      17: return
      18: aload_1
      19: invokevirtual #259                // Method java/lang/Class.getDeclaredMethods:()[Ljava/lang/reflect/Method;
      22: astore        5
      24: aload         5
      26: arraylength
      27: istore        6
      29: iconst_0
      30: istore        7
      32: iload         7
      34: iload         6
      36: if_icmpge     161
      39: aload         5
      41: iload         7
      43: aaload
      44: astore        8
      46: aload_0
      47: aload         8
      49: invokevirtual #386                // Method _isIncludableMemberMethod:(Ljava/lang/reflect/Method;)Z
      52: ifne          58
      55: goto          155
      58: aload_2
      59: aload         8
      61: invokevirtual #388                // Method org/apache/htrace/shaded/fasterxml/jackson/databind/introspect/AnnotatedMethodMap.find:(Ljava/lang/reflect/Method;)Lorg/apache/htrace/shaded/fasterxml/jackson/databind/introspect/AnnotatedMethod;
      64: astore        9
      66: aload         9
      68: ifnonnull     114
      71: aload_0
      72: aload         8
      74: invokevirtual #315                // Method _constructMethod:(Ljava/lang/reflect/Method;)Lorg/apache/htrace/shaded/fasterxml/jackson/databind/introspect/AnnotatedMethod;
      77: astore        10
      79: aload_2
      80: aload         10
      82: invokevirtual #325                // Method org/apache/htrace/shaded/fasterxml/jackson/databind/introspect/AnnotatedMethodMap.add:(Lorg/apache/htrace/shaded/fasterxml/jackson/databind/introspect/AnnotatedMethod;)V
      85: aload         4
      87: aload         8
      89: invokevirtual #390                // Method org/apache/htrace/shaded/fasterxml/jackson/databind/introspect/AnnotatedMethodMap.remove:(Ljava/lang/reflect/Method;)Lorg/apache/htrace/shaded/fasterxml/jackson/databind/introspect/AnnotatedMethod;
      92: astore        9
      94: aload         9
      96: ifnull        111
      99: aload_0
     100: aload         9
     102: invokevirtual #318                // Method org/apache/htrace/shaded/fasterxml/jackson/databind/introspect/AnnotatedMethod.getAnnotated:()Ljava/lang/reflect/Method;
     105: aload         10
     107: iconst_0
     108: invokevirtual #322                // Method _addMixOvers:(Ljava/lang/reflect/Method;Lorg/apache/htrace/shaded/fasterxml/jackson/databind/introspect/AnnotatedMethod;Z)V
     111: goto          155
     114: aload_0
     115: aload         8
     117: aload         9
     119: invokevirtual #394                // Method _addMixUnders:(Ljava/lang/reflect/Method;Lorg/apache/htrace/shaded/fasterxml/jackson/databind/introspect/AnnotatedMethod;)V
     122: aload         9
     124: invokevirtual #397                // Method org/apache/htrace/shaded/fasterxml/jackson/databind/introspect/AnnotatedMethod.getDeclaringClass:()Ljava/lang/Class;
     127: invokevirtual #400                // Method java/lang/Class.isInterface:()Z
     130: ifeq          155
     133: aload         8
     135: invokevirtual #401                // Method java/lang/reflect/Method.getDeclaringClass:()Ljava/lang/Class;
     138: invokevirtual #400                // Method java/lang/Class.isInterface:()Z
     141: ifne          155
     144: aload_2
     145: aload         9
     147: aload         8
     149: invokevirtual #404                // Method org/apache/htrace/shaded/fasterxml/jackson/databind/introspect/AnnotatedMethod.withMethod:(Ljava/lang/reflect/Method;)Lorg/apache/htrace/shaded/fasterxml/jackson/databind/introspect/AnnotatedMethod;
     152: invokevirtual #325                // Method org/apache/htrace/shaded/fasterxml/jackson/databind/introspect/AnnotatedMethodMap.add:(Lorg/apache/htrace/shaded/fasterxml/jackson/databind/introspect/AnnotatedMethod;)V
     155: iinc          7, 1
     158: goto          32
     161: return

  protected void _addMethodMixIns(java.lang.Class<?>, org.apache.htrace.shaded.fasterxml.jackson.databind.introspect.AnnotatedMethodMap, java.lang.Class<?>, org.apache.htrace.shaded.fasterxml.jackson.databind.introspect.AnnotatedMethodMap);
    Code:
       0: new           #223                // class java/util/ArrayList
       3: dup
       4: invokespecial #410                // Method java/util/ArrayList."<init>":()V
       7: astore        5
       9: aload         5
      11: aload_3
      12: invokeinterface #236,  2          // InterfaceMethod java/util/List.add:(Ljava/lang/Object;)Z
      17: pop
      18: aload_3
      19: aload_1
      20: aload         5
      22: invokestatic  #413                // Method org/apache/htrace/shaded/fasterxml/jackson/databind/util/ClassUtil.findSuperTypes:(Ljava/lang/Class;Ljava/lang/Class;Ljava/util/List;)Ljava/util/List;
      25: pop
      26: aload         5
      28: invokeinterface #189,  1          // InterfaceMethod java/util/List.iterator:()Ljava/util/Iterator;
      33: astore        6
      35: aload         6
      37: invokeinterface #194,  1          // InterfaceMethod java/util/Iterator.hasNext:()Z
      42: ifeq          142
      45: aload         6
      47: invokeinterface #198,  1          // InterfaceMethod java/util/Iterator.next:()Ljava/lang/Object;
      52: checkcast     #54                 // class java/lang/Class
      55: astore        7
      57: aload         7
      59: invokevirtual #259                // Method java/lang/Class.getDeclaredMethods:()[Ljava/lang/reflect/Method;
      62: astore        8
      64: aload         8
      66: arraylength
      67: istore        9
      69: iconst_0
      70: istore        10
      72: iload         10
      74: iload         9
      76: if_icmpge     139
      79: aload         8
      81: iload         10
      83: aaload
      84: astore        11
      86: aload_0
      87: aload         11
      89: invokevirtual #386                // Method _isIncludableMemberMethod:(Ljava/lang/reflect/Method;)Z
      92: ifne          98
      95: goto          133
      98: aload_2
      99: aload         11
     101: invokevirtual #388                // Method org/apache/htrace/shaded/fasterxml/jackson/databind/introspect/AnnotatedMethodMap.find:(Ljava/lang/reflect/Method;)Lorg/apache/htrace/shaded/fasterxml/jackson/databind/introspect/AnnotatedMethod;
     104: astore        12
     106: aload         12
     108: ifnull        122
     111: aload_0
     112: aload         11
     114: aload         12
     116: invokevirtual #394                // Method _addMixUnders:(Ljava/lang/reflect/Method;Lorg/apache/htrace/shaded/fasterxml/jackson/databind/introspect/AnnotatedMethod;)V
     119: goto          133
     122: aload         4
     124: aload_0
     125: aload         11
     127: invokevirtual #315                // Method _constructMethod:(Ljava/lang/reflect/Method;)Lorg/apache/htrace/shaded/fasterxml/jackson/databind/introspect/AnnotatedMethod;
     130: invokevirtual #325                // Method org/apache/htrace/shaded/fasterxml/jackson/databind/introspect/AnnotatedMethodMap.add:(Lorg/apache/htrace/shaded/fasterxml/jackson/databind/introspect/AnnotatedMethod;)V
     133: iinc          10, 1
     136: goto          72
     139: goto          35
     142: return

  protected java.util.Map<java.lang.String, org.apache.htrace.shaded.fasterxml.jackson.databind.introspect.AnnotatedField> _findFields(java.lang.Class<?>, java.util.Map<java.lang.String, org.apache.htrace.shaded.fasterxml.jackson.databind.introspect.AnnotatedField>);
    Code:
       0: aload_1
       1: invokevirtual #418                // Method java/lang/Class.getSuperclass:()Ljava/lang/Class;
       4: astore_3
       5: aload_3
       6: ifnull        124
       9: aload_0
      10: aload_3
      11: aload_2
      12: invokevirtual #338                // Method _findFields:(Ljava/lang/Class;Ljava/util/Map;)Ljava/util/Map;
      15: astore_2
      16: aload_1
      17: invokevirtual #422                // Method java/lang/Class.getDeclaredFields:()[Ljava/lang/reflect/Field;
      20: astore        4
      22: aload         4
      24: arraylength
      25: istore        5
      27: iconst_0
      28: istore        6
      30: iload         6
      32: iload         5
      34: if_icmpge     92
      37: aload         4
      39: iload         6
      41: aaload
      42: astore        7
      44: aload_0
      45: aload         7
      47: invokespecial #428                // Method _isIncludableField:(Ljava/lang/reflect/Field;)Z
      50: ifne          56
      53: goto          86
      56: aload_2
      57: ifnonnull     68
      60: new           #432                // class java/util/LinkedHashMap
      63: dup
      64: invokespecial #433                // Method java/util/LinkedHashMap."<init>":()V
      67: astore_2
      68: aload_2
      69: aload         7
      71: invokevirtual #434                // Method java/lang/reflect/Field.getName:()Ljava/lang/String;
      74: aload_0
      75: aload         7
      77: invokevirtual #438                // Method _constructField:(Ljava/lang/reflect/Field;)Lorg/apache/htrace/shaded/fasterxml/jackson/databind/introspect/AnnotatedField;
      80: invokeinterface #442,  3          // InterfaceMethod java/util/Map.put:(Ljava/lang/Object;Ljava/lang/Object;)Ljava/lang/Object;
      85: pop
      86: iinc          6, 1
      89: goto          30
      92: aload_0
      93: getfield      #52                 // Field _mixInResolver:Lorg/apache/htrace/shaded/fasterxml/jackson/databind/introspect/ClassIntrospector$MixInResolver;
      96: ifnull        124
      99: aload_0
     100: getfield      #52                 // Field _mixInResolver:Lorg/apache/htrace/shaded/fasterxml/jackson/databind/introspect/ClassIntrospector$MixInResolver;
     103: aload_1
     104: invokeinterface #64,  2           // InterfaceMethod org/apache/htrace/shaded/fasterxml/jackson/databind/introspect/ClassIntrospector$MixInResolver.findMixInClassFor:(Ljava/lang/Class;)Ljava/lang/Class;
     109: astore        4
     111: aload         4
     113: ifnull        124
     116: aload_0
     117: aload_3
     118: aload         4
     120: aload_2
     121: invokevirtual #446                // Method _addFieldMixIns:(Ljava/lang/Class;Ljava/lang/Class;Ljava/util/Map;)V
     124: aload_2
     125: areturn

  protected void _addFieldMixIns(java.lang.Class<?>, java.lang.Class<?>, java.util.Map<java.lang.String, org.apache.htrace.shaded.fasterxml.jackson.databind.introspect.AnnotatedField>);
    Code:
       0: new           #223                // class java/util/ArrayList
       3: dup
       4: invokespecial #410                // Method java/util/ArrayList."<init>":()V
       7: astore        4
       9: aload         4
      11: aload_2
      12: invokeinterface #236,  2          // InterfaceMethod java/util/List.add:(Ljava/lang/Object;)Z
      17: pop
      18: aload_2
      19: aload_1
      20: aload         4
      22: invokestatic  #413                // Method org/apache/htrace/shaded/fasterxml/jackson/databind/util/ClassUtil.findSuperTypes:(Ljava/lang/Class;Ljava/lang/Class;Ljava/util/List;)Ljava/util/List;
      25: pop
      26: aload         4
      28: invokeinterface #189,  1          // InterfaceMethod java/util/List.iterator:()Ljava/util/Iterator;
      33: astore        5
      35: aload         5
      37: invokeinterface #194,  1          // InterfaceMethod java/util/Iterator.hasNext:()Z
      42: ifeq          143
      45: aload         5
      47: invokeinterface #198,  1          // InterfaceMethod java/util/Iterator.next:()Ljava/lang/Object;
      52: checkcast     #54                 // class java/lang/Class
      55: astore        6
      57: aload         6
      59: invokevirtual #422                // Method java/lang/Class.getDeclaredFields:()[Ljava/lang/reflect/Field;
      62: astore        7
      64: aload         7
      66: arraylength
      67: istore        8
      69: iconst_0
      70: istore        9
      72: iload         9
      74: iload         8
      76: if_icmpge     140
      79: aload         7
      81: iload         9
      83: aaload
      84: astore        10
      86: aload_0
      87: aload         10
      89: invokespecial #428                // Method _isIncludableField:(Ljava/lang/reflect/Field;)Z
      92: ifne          98
      95: goto          134
      98: aload         10
     100: invokevirtual #434                // Method java/lang/reflect/Field.getName:()Ljava/lang/String;
     103: astore        11
     105: aload_3
     106: aload         11
     108: invokeinterface #452,  2          // InterfaceMethod java/util/Map.get:(Ljava/lang/Object;)Ljava/lang/Object;
     113: checkcast     #454                // class org/apache/htrace/shaded/fasterxml/jackson/databind/introspect/AnnotatedField
     116: astore        12
     118: aload         12
     120: ifnull        134
     123: aload_0
     124: aload         12
     126: aload         10
     128: invokevirtual #455                // Method java/lang/reflect/Field.getDeclaredAnnotations:()[Ljava/lang/annotation/Annotation;
     131: invokespecial #459                // Method _addOrOverrideAnnotations:(Lorg/apache/htrace/shaded/fasterxml/jackson/databind/introspect/AnnotatedMember;[Ljava/lang/annotation/Annotation;)V
     134: iinc          9, 1
     137: goto          72
     140: goto          35
     143: return

  protected org.apache.htrace.shaded.fasterxml.jackson.databind.introspect.AnnotatedMethod _constructMethod(java.lang.reflect.Method);
    Code:
       0: aload_0
       1: getfield      #50                 // Field _annotationIntrospector:Lorg/apache/htrace/shaded/fasterxml/jackson/databind/AnnotationIntrospector;
       4: ifnonnull     21
       7: new           #304                // class org/apache/htrace/shaded/fasterxml/jackson/databind/introspect/AnnotatedMethod
      10: dup
      11: aload_1
      12: aload_0
      13: invokespecial #465                // Method _emptyAnnotationMap:()Lorg/apache/htrace/shaded/fasterxml/jackson/databind/introspect/AnnotationMap;
      16: aconst_null
      17: invokespecial #468                // Method org/apache/htrace/shaded/fasterxml/jackson/databind/introspect/AnnotatedMethod."<init>":(Ljava/lang/reflect/Method;Lorg/apache/htrace/shaded/fasterxml/jackson/databind/introspect/AnnotationMap;[Lorg/apache/htrace/shaded/fasterxml/jackson/databind/introspect/AnnotationMap;)V
      20: areturn
      21: new           #304                // class org/apache/htrace/shaded/fasterxml/jackson/databind/introspect/AnnotatedMethod
      24: dup
      25: aload_1
      26: aload_0
      27: aload_1
      28: invokevirtual #469                // Method java/lang/reflect/Method.getDeclaredAnnotations:()[Ljava/lang/annotation/Annotation;
      31: invokevirtual #473                // Method _collectRelevantAnnotations:([Ljava/lang/annotation/Annotation;)Lorg/apache/htrace/shaded/fasterxml/jackson/databind/introspect/AnnotationMap;
      34: aconst_null
      35: invokespecial #468                // Method org/apache/htrace/shaded/fasterxml/jackson/databind/introspect/AnnotatedMethod."<init>":(Ljava/lang/reflect/Method;Lorg/apache/htrace/shaded/fasterxml/jackson/databind/introspect/AnnotationMap;[Lorg/apache/htrace/shaded/fasterxml/jackson/databind/introspect/AnnotationMap;)V
      38: areturn

  protected org.apache.htrace.shaded.fasterxml.jackson.databind.introspect.AnnotatedConstructor _constructConstructor(java.lang.reflect.Constructor<?>, boolean);
    Code:
       0: aload_0
       1: getfield      #50                 // Field _annotationIntrospector:Lorg/apache/htrace/shaded/fasterxml/jackson/databind/AnnotationIntrospector;
       4: ifnonnull     29
       7: new           #363                // class org/apache/htrace/shaded/fasterxml/jackson/databind/introspect/AnnotatedConstructor
      10: dup
      11: aload_1
      12: aload_0
      13: invokespecial #465                // Method _emptyAnnotationMap:()Lorg/apache/htrace/shaded/fasterxml/jackson/databind/introspect/AnnotationMap;
      16: aload_0
      17: aload_1
      18: invokevirtual #217                // Method java/lang/reflect/Constructor.getParameterTypes:()[Ljava/lang/Class;
      21: arraylength
      22: invokespecial #477                // Method _emptyAnnotationMaps:(I)[Lorg/apache/htrace/shaded/fasterxml/jackson/databind/introspect/AnnotationMap;
      25: invokespecial #480                // Method org/apache/htrace/shaded/fasterxml/jackson/databind/introspect/AnnotatedConstructor."<init>":(Ljava/lang/reflect/Constructor;Lorg/apache/htrace/shaded/fasterxml/jackson/databind/introspect/AnnotationMap;[Lorg/apache/htrace/shaded/fasterxml/jackson/databind/introspect/AnnotationMap;)V
      28: areturn
      29: iload_2
      30: ifeq          51
      33: new           #363                // class org/apache/htrace/shaded/fasterxml/jackson/databind/introspect/AnnotatedConstructor
      36: dup
      37: aload_1
      38: aload_0
      39: aload_1
      40: invokevirtual #481                // Method java/lang/reflect/Constructor.getDeclaredAnnotations:()[Ljava/lang/annotation/Annotation;
      43: invokevirtual #473                // Method _collectRelevantAnnotations:([Ljava/lang/annotation/Annotation;)Lorg/apache/htrace/shaded/fasterxml/jackson/databind/introspect/AnnotationMap;
      46: aconst_null
      47: invokespecial #480                // Method org/apache/htrace/shaded/fasterxml/jackson/databind/introspect/AnnotatedConstructor."<init>":(Ljava/lang/reflect/Constructor;Lorg/apache/htrace/shaded/fasterxml/jackson/databind/introspect/AnnotationMap;[Lorg/apache/htrace/shaded/fasterxml/jackson/databind/introspect/AnnotationMap;)V
      50: areturn
      51: aload_1
      52: invokevirtual #485                // Method java/lang/reflect/Constructor.getParameterAnnotations:()[[Ljava/lang/annotation/Annotation;
      55: astore_3
      56: aload_1
      57: invokevirtual #217                // Method java/lang/reflect/Constructor.getParameterTypes:()[Ljava/lang/Class;
      60: arraylength
      61: istore        4
      63: aconst_null
      64: astore        5
      66: iload         4
      68: aload_3
      69: arraylength
      70: if_icmpeq     246
      73: aload_1
      74: invokevirtual #486                // Method java/lang/reflect/Constructor.getDeclaringClass:()Ljava/lang/Class;
      77: astore        6
      79: aload         6
      81: invokevirtual #489                // Method java/lang/Class.isEnum:()Z
      84: ifeq          129
      87: iload         4
      89: aload_3
      90: arraylength
      91: iconst_2
      92: iadd
      93: if_icmpne     129
      96: aload_3
      97: astore        7
      99: aload         7
     101: arraylength
     102: iconst_2
     103: iadd
     104: anewarray     #491                // class "[Ljava/lang/annotation/Annotation;"
     107: astore_3
     108: aload         7
     110: iconst_0
     111: aload_3
     112: iconst_2
     113: aload         7
     115: arraylength
     116: invokestatic  #497                // Method java/lang/System.arraycopy:(Ljava/lang/Object;ILjava/lang/Object;II)V
     119: aload_0
     120: aload_3
     121: invokevirtual #500                // Method _collectRelevantAnnotations:([[Ljava/lang/annotation/Annotation;)[Lorg/apache/htrace/shaded/fasterxml/jackson/databind/introspect/AnnotationMap;
     124: astore        5
     126: goto          176
     129: aload         6
     131: invokevirtual #506                // Method java/lang/Class.isMemberClass:()Z
     134: ifeq          176
     137: iload         4
     139: aload_3
     140: arraylength
     141: iconst_1
     142: iadd
     143: if_icmpne     176
     146: aload_3
     147: astore        7
     149: aload         7
     151: arraylength
     152: iconst_1
     153: iadd
     154: anewarray     #491                // class "[Ljava/lang/annotation/Annotation;"
     157: astore_3
     158: aload         7
     160: iconst_0
     161: aload_3
     162: iconst_1
     163: aload         7
     165: arraylength
     166: invokestatic  #497                // Method java/lang/System.arraycopy:(Ljava/lang/Object;ILjava/lang/Object;II)V
     169: aload_0
     170: aload_3
     171: invokevirtual #500                // Method _collectRelevantAnnotations:([[Ljava/lang/annotation/Annotation;)[Lorg/apache/htrace/shaded/fasterxml/jackson/databind/introspect/AnnotationMap;
     174: astore        5
     176: aload         5
     178: ifnonnull     243
     181: new           #508                // class java/lang/IllegalStateException
     184: dup
     185: new           #510                // class java/lang/StringBuilder
     188: dup
     189: invokespecial #511                // Method java/lang/StringBuilder."<init>":()V
     192: ldc_w         #513                // String Internal error: constructor for
     195: invokevirtual #517                // Method java/lang/StringBuilder.append:(Ljava/lang/String;)Ljava/lang/StringBuilder;
     198: aload_1
     199: invokevirtual #486                // Method java/lang/reflect/Constructor.getDeclaringClass:()Ljava/lang/Class;
     202: invokevirtual #105                // Method java/lang/Class.getName:()Ljava/lang/String;
     205: invokevirtual #517                // Method java/lang/StringBuilder.append:(Ljava/lang/String;)Ljava/lang/StringBuilder;
     208: ldc_w         #519                // String  has mismatch:
     211: invokevirtual #517                // Method java/lang/StringBuilder.append:(Ljava/lang/String;)Ljava/lang/StringBuilder;
     214: iload         4
     216: invokevirtual #522                // Method java/lang/StringBuilder.append:(I)Ljava/lang/StringBuilder;
     219: ldc_w         #524                // String  parameters;
     222: invokevirtual #517                // Method java/lang/StringBuilder.append:(Ljava/lang/String;)Ljava/lang/StringBuilder;
     225: aload_3
     226: arraylength
     227: invokevirtual #522                // Method java/lang/StringBuilder.append:(I)Ljava/lang/StringBuilder;
     230: ldc_w         #526                // String  sets of annotations
     233: invokevirtual #517                // Method java/lang/StringBuilder.append:(Ljava/lang/String;)Ljava/lang/StringBuilder;
     236: invokevirtual #529                // Method java/lang/StringBuilder.toString:()Ljava/lang/String;
     239: invokespecial #532                // Method java/lang/IllegalStateException."<init>":(Ljava/lang/String;)V
     242: athrow
     243: goto          253
     246: aload_0
     247: aload_3
     248: invokevirtual #500                // Method _collectRelevantAnnotations:([[Ljava/lang/annotation/Annotation;)[Lorg/apache/htrace/shaded/fasterxml/jackson/databind/introspect/AnnotationMap;
     251: astore        5
     253: new           #363                // class org/apache/htrace/shaded/fasterxml/jackson/databind/introspect/AnnotatedConstructor
     256: dup
     257: aload_1
     258: aload_0
     259: aload_1
     260: invokevirtual #481                // Method java/lang/reflect/Constructor.getDeclaredAnnotations:()[Ljava/lang/annotation/Annotation;
     263: invokevirtual #473                // Method _collectRelevantAnnotations:([Ljava/lang/annotation/Annotation;)Lorg/apache/htrace/shaded/fasterxml/jackson/databind/introspect/AnnotationMap;
     266: aload         5
     268: invokespecial #480                // Method org/apache/htrace/shaded/fasterxml/jackson/databind/introspect/AnnotatedConstructor."<init>":(Ljava/lang/reflect/Constructor;Lorg/apache/htrace/shaded/fasterxml/jackson/databind/introspect/AnnotationMap;[Lorg/apache/htrace/shaded/fasterxml/jackson/databind/introspect/AnnotationMap;)V
     271: areturn

  protected org.apache.htrace.shaded.fasterxml.jackson.databind.introspect.AnnotatedMethod _constructCreatorMethod(java.lang.reflect.Method);
    Code:
       0: aload_0
       1: getfield      #50                 // Field _annotationIntrospector:Lorg/apache/htrace/shaded/fasterxml/jackson/databind/AnnotationIntrospector;
       4: ifnonnull     29
       7: new           #304                // class org/apache/htrace/shaded/fasterxml/jackson/databind/introspect/AnnotatedMethod
      10: dup
      11: aload_1
      12: aload_0
      13: invokespecial #465                // Method _emptyAnnotationMap:()Lorg/apache/htrace/shaded/fasterxml/jackson/databind/introspect/AnnotationMap;
      16: aload_0
      17: aload_1
      18: invokevirtual #377                // Method java/lang/reflect/Method.getParameterTypes:()[Ljava/lang/Class;
      21: arraylength
      22: invokespecial #477                // Method _emptyAnnotationMaps:(I)[Lorg/apache/htrace/shaded/fasterxml/jackson/databind/introspect/AnnotationMap;
      25: invokespecial #468                // Method org/apache/htrace/shaded/fasterxml/jackson/databind/introspect/AnnotatedMethod."<init>":(Ljava/lang/reflect/Method;Lorg/apache/htrace/shaded/fasterxml/jackson/databind/introspect/AnnotationMap;[Lorg/apache/htrace/shaded/fasterxml/jackson/databind/introspect/AnnotationMap;)V
      28: areturn
      29: new           #304                // class org/apache/htrace/shaded/fasterxml/jackson/databind/introspect/AnnotatedMethod
      32: dup
      33: aload_1
      34: aload_0
      35: aload_1
      36: invokevirtual #469                // Method java/lang/reflect/Method.getDeclaredAnnotations:()[Ljava/lang/annotation/Annotation;
      39: invokevirtual #473                // Method _collectRelevantAnnotations:([Ljava/lang/annotation/Annotation;)Lorg/apache/htrace/shaded/fasterxml/jackson/databind/introspect/AnnotationMap;
      42: aload_0
      43: aload_1
      44: invokevirtual #538                // Method java/lang/reflect/Method.getParameterAnnotations:()[[Ljava/lang/annotation/Annotation;
      47: invokevirtual #500                // Method _collectRelevantAnnotations:([[Ljava/lang/annotation/Annotation;)[Lorg/apache/htrace/shaded/fasterxml/jackson/databind/introspect/AnnotationMap;
      50: invokespecial #468                // Method org/apache/htrace/shaded/fasterxml/jackson/databind/introspect/AnnotatedMethod."<init>":(Ljava/lang/reflect/Method;Lorg/apache/htrace/shaded/fasterxml/jackson/databind/introspect/AnnotationMap;[Lorg/apache/htrace/shaded/fasterxml/jackson/databind/introspect/AnnotationMap;)V
      53: areturn

  protected org.apache.htrace.shaded.fasterxml.jackson.databind.introspect.AnnotatedField _constructField(java.lang.reflect.Field);
    Code:
       0: aload_0
       1: getfield      #50                 // Field _annotationIntrospector:Lorg/apache/htrace/shaded/fasterxml/jackson/databind/AnnotationIntrospector;
       4: ifnonnull     20
       7: new           #454                // class org/apache/htrace/shaded/fasterxml/jackson/databind/introspect/AnnotatedField
      10: dup
      11: aload_1
      12: aload_0
      13: invokespecial #465                // Method _emptyAnnotationMap:()Lorg/apache/htrace/shaded/fasterxml/jackson/databind/introspect/AnnotationMap;
      16: invokespecial #541                // Method org/apache/htrace/shaded/fasterxml/jackson/databind/introspect/AnnotatedField."<init>":(Ljava/lang/reflect/Field;Lorg/apache/htrace/shaded/fasterxml/jackson/databind/introspect/AnnotationMap;)V
      19: areturn
      20: new           #454                // class org/apache/htrace/shaded/fasterxml/jackson/databind/introspect/AnnotatedField
      23: dup
      24: aload_1
      25: aload_0
      26: aload_1
      27: invokevirtual #455                // Method java/lang/reflect/Field.getDeclaredAnnotations:()[Ljava/lang/annotation/Annotation;
      30: invokevirtual #473                // Method _collectRelevantAnnotations:([Ljava/lang/annotation/Annotation;)Lorg/apache/htrace/shaded/fasterxml/jackson/databind/introspect/AnnotationMap;
      33: invokespecial #541                // Method org/apache/htrace/shaded/fasterxml/jackson/databind/introspect/AnnotatedField."<init>":(Ljava/lang/reflect/Field;Lorg/apache/htrace/shaded/fasterxml/jackson/databind/introspect/AnnotationMap;)V
      36: areturn

  private org.apache.htrace.shaded.fasterxml.jackson.databind.introspect.AnnotationMap _emptyAnnotationMap();
    Code:
       0: new           #60                 // class org/apache/htrace/shaded/fasterxml/jackson/databind/introspect/AnnotationMap
       3: dup
       4: invokespecial #173                // Method org/apache/htrace/shaded/fasterxml/jackson/databind/introspect/AnnotationMap."<init>":()V
       7: areturn

  private org.apache.htrace.shaded.fasterxml.jackson.databind.introspect.AnnotationMap[] _emptyAnnotationMaps(int);
    Code:
       0: iload_1
       1: ifne          8
       4: getstatic     #543                // Field NO_ANNOTATION_MAPS:[Lorg/apache/htrace/shaded/fasterxml/jackson/databind/introspect/AnnotationMap;
       7: areturn
       8: iload_1
       9: anewarray     #60                 // class org/apache/htrace/shaded/fasterxml/jackson/databind/introspect/AnnotationMap
      12: astore_2
      13: iconst_0
      14: istore_3
      15: iload_3
      16: iload_1
      17: if_icmpge     33
      20: aload_2
      21: iload_3
      22: aload_0
      23: invokespecial #465                // Method _emptyAnnotationMap:()Lorg/apache/htrace/shaded/fasterxml/jackson/databind/introspect/AnnotationMap;
      26: aastore
      27: iinc          3, 1
      30: goto          15
      33: aload_2
      34: areturn

  protected boolean _isIncludableMemberMethod(java.lang.reflect.Method);
    Code:
       0: aload_1
       1: invokevirtual #264                // Method java/lang/reflect/Method.getModifiers:()I
       4: invokestatic  #270                // Method java/lang/reflect/Modifier.isStatic:(I)Z
       7: ifeq          12
      10: iconst_0
      11: ireturn
      12: aload_1
      13: invokevirtual #548                // Method java/lang/reflect/Method.isSynthetic:()Z
      16: ifne          26
      19: aload_1
      20: invokevirtual #551                // Method java/lang/reflect/Method.isBridge:()Z
      23: ifeq          28
      26: iconst_0
      27: ireturn
      28: aload_1
      29: invokevirtual #377                // Method java/lang/reflect/Method.getParameterTypes:()[Ljava/lang/Class;
      32: arraylength
      33: istore_2
      34: iload_2
      35: iconst_2
      36: if_icmpgt     43
      39: iconst_1
      40: goto          44
      43: iconst_0
      44: ireturn

  private boolean _isIncludableField(java.lang.reflect.Field);
    Code:
       0: aload_1
       1: invokevirtual #553                // Method java/lang/reflect/Field.isSynthetic:()Z
       4: ifeq          9
       7: iconst_0
       8: ireturn
       9: aload_1
      10: invokevirtual #554                // Method java/lang/reflect/Field.getModifiers:()I
      13: istore_2
      14: iload_2
      15: invokestatic  #270                // Method java/lang/reflect/Modifier.isStatic:(I)Z
      18: ifne          28
      21: iload_2
      22: invokestatic  #557                // Method java/lang/reflect/Modifier.isTransient:(I)Z
      25: ifeq          30
      28: iconst_0
      29: ireturn
      30: iconst_1
      31: ireturn

  protected org.apache.htrace.shaded.fasterxml.jackson.databind.introspect.AnnotationMap[] _collectRelevantAnnotations(java.lang.annotation.Annotation[][]);
    Code:
       0: aload_1
       1: arraylength
       2: istore_2
       3: iload_2
       4: anewarray     #60                 // class org/apache/htrace/shaded/fasterxml/jackson/databind/introspect/AnnotationMap
       7: astore_3
       8: iconst_0
       9: istore        4
      11: iload         4
      13: iload_2
      14: if_icmpge     35
      17: aload_3
      18: iload         4
      20: aload_0
      21: aload_1
      22: iload         4
      24: aaload
      25: invokevirtual #473                // Method _collectRelevantAnnotations:([Ljava/lang/annotation/Annotation;)Lorg/apache/htrace/shaded/fasterxml/jackson/databind/introspect/AnnotationMap;
      28: aastore
      29: iinc          4, 1
      32: goto          11
      35: aload_3
      36: areturn

  protected org.apache.htrace.shaded.fasterxml.jackson.databind.introspect.AnnotationMap _collectRelevantAnnotations(java.lang.annotation.Annotation[]);
    Code:
       0: new           #60                 // class org/apache/htrace/shaded/fasterxml/jackson/databind/introspect/AnnotationMap
       3: dup
       4: invokespecial #173                // Method org/apache/htrace/shaded/fasterxml/jackson/databind/introspect/AnnotationMap."<init>":()V
       7: astore_2
       8: aload_0
       9: aload_2
      10: aload_1
      11: invokespecial #185                // Method _addAnnotationsIfNotPresent:(Lorg/apache/htrace/shaded/fasterxml/jackson/databind/introspect/AnnotationMap;[Ljava/lang/annotation/Annotation;)V
      14: aload_2
      15: areturn

  private void _addAnnotationsIfNotPresent(org.apache.htrace.shaded.fasterxml.jackson.databind.introspect.AnnotationMap, java.lang.annotation.Annotation[]);
    Code:
       0: aload_2
       1: ifnull        128
       4: aconst_null
       5: astore_3
       6: aload_2
       7: astore        4
       9: aload         4
      11: arraylength
      12: istore        5
      14: iconst_0
      15: istore        6
      17: iload         6
      19: iload         5
      21: if_icmpge     84
      24: aload         4
      26: iload         6
      28: aaload
      29: astore        7
      31: aload_0
      32: aload         7
      34: invokespecial #566                // Method _isAnnotationBundle:(Ljava/lang/annotation/Annotation;)Z
      37: ifeq          72
      40: aload_3
      41: ifnonnull     52
      44: new           #568                // class java/util/LinkedList
      47: dup
      48: invokespecial #569                // Method java/util/LinkedList."<init>":()V
      51: astore_3
      52: aload_3
      53: aload         7
      55: invokeinterface #574,  1          // InterfaceMethod java/lang/annotation/Annotation.annotationType:()Ljava/lang/Class;
      60: invokevirtual #181                // Method java/lang/Class.getDeclaredAnnotations:()[Ljava/lang/annotation/Annotation;
      63: invokeinterface #236,  2          // InterfaceMethod java/util/List.add:(Ljava/lang/Object;)Z
      68: pop
      69: goto          78
      72: aload_1
      73: aload         7
      75: invokevirtual #578                // Method org/apache/htrace/shaded/fasterxml/jackson/databind/introspect/AnnotationMap.addIfNotPresent:(Ljava/lang/annotation/Annotation;)V
      78: iinc          6, 1
      81: goto          17
      84: aload_3
      85: ifnull        128
      88: aload_3
      89: invokeinterface #189,  1          // InterfaceMethod java/util/List.iterator:()Ljava/util/Iterator;
      94: astore        4
      96: aload         4
      98: invokeinterface #194,  1          // InterfaceMethod java/util/Iterator.hasNext:()Z
     103: ifeq          128
     106: aload         4
     108: invokeinterface #198,  1          // InterfaceMethod java/util/Iterator.next:()Ljava/lang/Object;
     113: checkcast     #491                // class "[Ljava/lang/annotation/Annotation;"
     116: astore        5
     118: aload_0
     119: aload_1
     120: aload         5
     122: invokespecial #185                // Method _addAnnotationsIfNotPresent:(Lorg/apache/htrace/shaded/fasterxml/jackson/databind/introspect/AnnotationMap;[Ljava/lang/annotation/Annotation;)V
     125: goto          96
     128: return

  private void _addAnnotationsIfNotPresent(org.apache.htrace.shaded.fasterxml.jackson.databind.introspect.AnnotatedMember, java.lang.annotation.Annotation[]);
    Code:
       0: aload_2
       1: ifnull        128
       4: aconst_null
       5: astore_3
       6: aload_2
       7: astore        4
       9: aload         4
      11: arraylength
      12: istore        5
      14: iconst_0
      15: istore        6
      17: iload         6
      19: iload         5
      21: if_icmpge     84
      24: aload         4
      26: iload         6
      28: aaload
      29: astore        7
      31: aload_0
      32: aload         7
      34: invokespecial #566                // Method _isAnnotationBundle:(Ljava/lang/annotation/Annotation;)Z
      37: ifeq          72
      40: aload_3
      41: ifnonnull     52
      44: new           #568                // class java/util/LinkedList
      47: dup
      48: invokespecial #569                // Method java/util/LinkedList."<init>":()V
      51: astore_3
      52: aload_3
      53: aload         7
      55: invokeinterface #574,  1          // InterfaceMethod java/lang/annotation/Annotation.annotationType:()Ljava/lang/Class;
      60: invokevirtual #181                // Method java/lang/Class.getDeclaredAnnotations:()[Ljava/lang/annotation/Annotation;
      63: invokeinterface #236,  2          // InterfaceMethod java/util/List.add:(Ljava/lang/Object;)Z
      68: pop
      69: goto          78
      72: aload_1
      73: aload         7
      75: invokevirtual #582                // Method org/apache/htrace/shaded/fasterxml/jackson/databind/introspect/AnnotatedMember.addIfNotPresent:(Ljava/lang/annotation/Annotation;)V
      78: iinc          6, 1
      81: goto          17
      84: aload_3
      85: ifnull        128
      88: aload_3
      89: invokeinterface #189,  1          // InterfaceMethod java/util/List.iterator:()Ljava/util/Iterator;
      94: astore        4
      96: aload         4
      98: invokeinterface #194,  1          // InterfaceMethod java/util/Iterator.hasNext:()Z
     103: ifeq          128
     106: aload         4
     108: invokeinterface #198,  1          // InterfaceMethod java/util/Iterator.next:()Ljava/lang/Object;
     113: checkcast     #491                // class "[Ljava/lang/annotation/Annotation;"
     116: astore        5
     118: aload_0
     119: aload_1
     120: aload         5
     122: invokespecial #584                // Method _addAnnotationsIfNotPresent:(Lorg/apache/htrace/shaded/fasterxml/jackson/databind/introspect/AnnotatedMember;[Ljava/lang/annotation/Annotation;)V
     125: goto          96
     128: return

  private void _addOrOverrideAnnotations(org.apache.htrace.shaded.fasterxml.jackson.databind.introspect.AnnotatedMember, java.lang.annotation.Annotation[]);
    Code:
       0: aload_2
       1: ifnull        128
       4: aconst_null
       5: astore_3
       6: aload_2
       7: astore        4
       9: aload         4
      11: arraylength
      12: istore        5
      14: iconst_0
      15: istore        6
      17: iload         6
      19: iload         5
      21: if_icmpge     84
      24: aload         4
      26: iload         6
      28: aaload
      29: astore        7
      31: aload_0
      32: aload         7
      34: invokespecial #566                // Method _isAnnotationBundle:(Ljava/lang/annotation/Annotation;)Z
      37: ifeq          72
      40: aload_3
      41: ifnonnull     52
      44: new           #568                // class java/util/LinkedList
      47: dup
      48: invokespecial #569                // Method java/util/LinkedList."<init>":()V
      51: astore_3
      52: aload_3
      53: aload         7
      55: invokeinterface #574,  1          // InterfaceMethod java/lang/annotation/Annotation.annotationType:()Ljava/lang/Class;
      60: invokevirtual #181                // Method java/lang/Class.getDeclaredAnnotations:()[Ljava/lang/annotation/Annotation;
      63: invokeinterface #236,  2          // InterfaceMethod java/util/List.add:(Ljava/lang/Object;)Z
      68: pop
      69: goto          78
      72: aload_1
      73: aload         7
      75: invokevirtual #589                // Method org/apache/htrace/shaded/fasterxml/jackson/databind/introspect/AnnotatedMember.addOrOverride:(Ljava/lang/annotation/Annotation;)V
      78: iinc          6, 1
      81: goto          17
      84: aload_3
      85: ifnull        128
      88: aload_3
      89: invokeinterface #189,  1          // InterfaceMethod java/util/List.iterator:()Ljava/util/Iterator;
      94: astore        4
      96: aload         4
      98: invokeinterface #194,  1          // InterfaceMethod java/util/Iterator.hasNext:()Z
     103: ifeq          128
     106: aload         4
     108: invokeinterface #198,  1          // InterfaceMethod java/util/Iterator.next:()Ljava/lang/Object;
     113: checkcast     #491                // class "[Ljava/lang/annotation/Annotation;"
     116: astore        5
     118: aload_0
     119: aload_1
     120: aload         5
     122: invokespecial #459                // Method _addOrOverrideAnnotations:(Lorg/apache/htrace/shaded/fasterxml/jackson/databind/introspect/AnnotatedMember;[Ljava/lang/annotation/Annotation;)V
     125: goto          96
     128: return

  protected void _addMixOvers(java.lang.reflect.Constructor<?>, org.apache.htrace.shaded.fasterxml.jackson.databind.introspect.AnnotatedConstructor, boolean);
    Code:
       0: aload_0
       1: aload_2
       2: aload_1
       3: invokevirtual #481                // Method java/lang/reflect/Constructor.getDeclaredAnnotations:()[Ljava/lang/annotation/Annotation;
       6: invokespecial #459                // Method _addOrOverrideAnnotations:(Lorg/apache/htrace/shaded/fasterxml/jackson/databind/introspect/AnnotatedMember;[Ljava/lang/annotation/Annotation;)V
       9: iload_3
      10: ifeq          83
      13: aload_1
      14: invokevirtual #485                // Method java/lang/reflect/Constructor.getParameterAnnotations:()[[Ljava/lang/annotation/Annotation;
      17: astore        4
      19: iconst_0
      20: istore        5
      22: aload         4
      24: arraylength
      25: istore        6
      27: iload         5
      29: iload         6
      31: if_icmpge     83
      34: aload         4
      36: iload         5
      38: aaload
      39: astore        7
      41: aload         7
      43: arraylength
      44: istore        8
      46: iconst_0
      47: istore        9
      49: iload         9
      51: iload         8
      53: if_icmpge     77
      56: aload         7
      58: iload         9
      60: aaload
      61: astore        10
      63: aload_2
      64: iload         5
      66: aload         10
      68: invokevirtual #593                // Method org/apache/htrace/shaded/fasterxml/jackson/databind/introspect/AnnotatedConstructor.addOrOverrideParam:(ILjava/lang/annotation/Annotation;)V
      71: iinc          9, 1
      74: goto          49
      77: iinc          5, 1
      80: goto          27
      83: return

  protected void _addMixOvers(java.lang.reflect.Method, org.apache.htrace.shaded.fasterxml.jackson.databind.introspect.AnnotatedMethod, boolean);
    Code:
       0: aload_0
       1: aload_2
       2: aload_1
       3: invokevirtual #469                // Method java/lang/reflect/Method.getDeclaredAnnotations:()[Ljava/lang/annotation/Annotation;
       6: invokespecial #459                // Method _addOrOverrideAnnotations:(Lorg/apache/htrace/shaded/fasterxml/jackson/databind/introspect/AnnotatedMember;[Ljava/lang/annotation/Annotation;)V
       9: iload_3
      10: ifeq          83
      13: aload_1
      14: invokevirtual #538                // Method java/lang/reflect/Method.getParameterAnnotations:()[[Ljava/lang/annotation/Annotation;
      17: astore        4
      19: iconst_0
      20: istore        5
      22: aload         4
      24: arraylength
      25: istore        6
      27: iload         5
      29: iload         6
      31: if_icmpge     83
      34: aload         4
      36: iload         5
      38: aaload
      39: astore        7
      41: aload         7
      43: arraylength
      44: istore        8
      46: iconst_0
      47: istore        9
      49: iload         9
      51: iload         8
      53: if_icmpge     77
      56: aload         7
      58: iload         9
      60: aaload
      61: astore        10
      63: aload_2
      64: iload         5
      66: aload         10
      68: invokevirtual #597                // Method org/apache/htrace/shaded/fasterxml/jackson/databind/introspect/AnnotatedMethod.addOrOverrideParam:(ILjava/lang/annotation/Annotation;)V
      71: iinc          9, 1
      74: goto          49
      77: iinc          5, 1
      80: goto          27
      83: return

  protected void _addMixUnders(java.lang.reflect.Method, org.apache.htrace.shaded.fasterxml.jackson.databind.introspect.AnnotatedMethod);
    Code:
       0: aload_0
       1: aload_2
       2: aload_1
       3: invokevirtual #469                // Method java/lang/reflect/Method.getDeclaredAnnotations:()[Ljava/lang/annotation/Annotation;
       6: invokespecial #584                // Method _addAnnotationsIfNotPresent:(Lorg/apache/htrace/shaded/fasterxml/jackson/databind/introspect/AnnotatedMember;[Ljava/lang/annotation/Annotation;)V
       9: return

  private final boolean _isAnnotationBundle(java.lang.annotation.Annotation);
    Code:
       0: aload_0
       1: getfield      #50                 // Field _annotationIntrospector:Lorg/apache/htrace/shaded/fasterxml/jackson/databind/AnnotationIntrospector;
       4: ifnull        22
       7: aload_0
       8: getfield      #50                 // Field _annotationIntrospector:Lorg/apache/htrace/shaded/fasterxml/jackson/databind/AnnotationIntrospector;
      11: aload_1
      12: invokevirtual #601                // Method org/apache/htrace/shaded/fasterxml/jackson/databind/AnnotationIntrospector.isAnnotationBundle:(Ljava/lang/annotation/Annotation;)Z
      15: ifeq          22
      18: iconst_1
      19: goto          23
      22: iconst_0
      23: ireturn

  public java.lang.String toString();
    Code:
       0: new           #510                // class java/lang/StringBuilder
       3: dup
       4: invokespecial #511                // Method java/lang/StringBuilder."<init>":()V
       7: ldc_w         #603                // String [AnnotedClass
      10: invokevirtual #517                // Method java/lang/StringBuilder.append:(Ljava/lang/String;)Ljava/lang/StringBuilder;
      13: aload_0
      14: getfield      #46                 // Field _class:Ljava/lang/Class;
      17: invokevirtual #105                // Method java/lang/Class.getName:()Ljava/lang/String;
      20: invokevirtual #517                // Method java/lang/StringBuilder.append:(Ljava/lang/String;)Ljava/lang/StringBuilder;
      23: ldc_w         #605                // String ]
      26: invokevirtual #517                // Method java/lang/StringBuilder.append:(Ljava/lang/String;)Ljava/lang/StringBuilder;
      29: invokevirtual #529                // Method java/lang/StringBuilder.toString:()Ljava/lang/String;
      32: areturn

  public java.lang.reflect.AnnotatedElement getAnnotated();
    Code:
       0: aload_0
       1: invokevirtual #608                // Method getAnnotated:()Ljava/lang/Class;
       4: areturn

  public org.apache.htrace.shaded.fasterxml.jackson.databind.introspect.Annotated withAnnotations(org.apache.htrace.shaded.fasterxml.jackson.databind.introspect.AnnotationMap);
    Code:
       0: aload_0
       1: aload_1
       2: invokevirtual #611                // Method withAnnotations:(Lorg/apache/htrace/shaded/fasterxml/jackson/databind/introspect/AnnotationMap;)Lorg/apache/htrace/shaded/fasterxml/jackson/databind/introspect/AnnotatedClass;
       5: areturn

  static {};
    Code:
       0: iconst_0
       1: anewarray     #60                 // class org/apache/htrace/shaded/fasterxml/jackson/databind/introspect/AnnotationMap
       4: putstatic     #543                // Field NO_ANNOTATION_MAPS:[Lorg/apache/htrace/shaded/fasterxml/jackson/databind/introspect/AnnotationMap;
       7: return
}
