Compiled from "MoveAxiomsWizard.java"
class org.protege.editor.owl.ui.ontology.wizard.move.MoveAxiomsWizard$1 implements java.util.Comparator<org.protege.editor.owl.ui.ontology.wizard.move.MoveAxiomsKit> {
  final org.protege.editor.owl.ui.ontology.wizard.move.MoveAxiomsWizard this$0;

  org.protege.editor.owl.ui.ontology.wizard.move.MoveAxiomsWizard$1(org.protege.editor.owl.ui.ontology.wizard.move.MoveAxiomsWizard);
    Code:
       0: aload_0
       1: aload_1
       2: putfield      #1                  // Field this$0:Lorg/protege/editor/owl/ui/ontology/wizard/move/MoveAxiomsWizard;
       5: aload_0
       6: invokespecial #2                  // Method java/lang/Object."<init>":()V
       9: return

  public int compare(org.protege.editor.owl.ui.ontology.wizard.move.MoveAxiomsKit, org.protege.editor.owl.ui.ontology.wizard.move.MoveAxiomsKit);
    Code:
       0: aload_1
       1: invokevirtual #3                  // Method org/protege/editor/owl/ui/ontology/wizard/move/MoveAxiomsKit.getName:()Ljava/lang/String;
       4: aload_2
       5: invokevirtual #3                  // Method org/protege/editor/owl/ui/ontology/wizard/move/MoveAxiomsKit.getName:()Ljava/lang/String;
       8: invokevirtual #4                  // Method java/lang/String.compareTo:(Ljava/lang/String;)I
      11: ireturn

  public int compare(java.lang.Object, java.lang.Object);
    Code:
       0: aload_0
       1: aload_1
       2: checkcast     #5                  // class org/protege/editor/owl/ui/ontology/wizard/move/MoveAxiomsKit
       5: aload_2
       6: checkcast     #5                  // class org/protege/editor/owl/ui/ontology/wizard/move/MoveAxiomsKit
       9: invokevirtual #6                  // Method compare:(Lorg/protege/editor/owl/ui/ontology/wizard/move/MoveAxiomsKit;Lorg/protege/editor/owl/ui/ontology/wizard/move/MoveAxiomsKit;)I
      12: ireturn
}
