Compiled from "XAHelper.java"
public class com.arjuna.ats.jta.utils.XAHelper {
  public com.arjuna.ats.jta.utils.XAHelper();
    Code:
       0: aload_0
       1: invokespecial #1                  // Method java/lang/Object."<init>":()V
       4: return

  public static java.lang.String printXAErrorCode(javax.transaction.xa.XAException);
    Code:
       0: aload_0
       1: ifnonnull     13
       4: getstatic     #2                  // Field com/arjuna/ats/jta/logging/jtaLogger.i18NLogger:Lcom/arjuna/ats/jta/logging/jtaI18NLogger;
       7: invokeinterface #3,  1            // InterfaceMethod com/arjuna/ats/jta/logging/jtaI18NLogger.get_utils_nullexception:()Ljava/lang/String;
      12: areturn
      13: aload_0
      14: getfield      #4                  // Field javax/transaction/xa/XAException.errorCode:I
      17: lookupswitch  { // 23
                    -9: 272
                    -8: 269
                    -7: 266
                    -6: 263
                    -5: 260
                    -4: 257
                    -3: 254
                    -2: 278
                     3: 251
                     4: 275
                     5: 248
                     6: 245
                     7: 242
                     8: 239
                     9: 236
                   100: 212
                   101: 215
                   102: 218
                   103: 221
                   104: 224
                   105: 227
                   106: 230
                   107: 233
               default: 281
          }
     212: ldc           #5                  // String XAException.XA_RBROLLBACK
     214: areturn
     215: ldc           #6                  // String XAException.XA_RBCOMMFAIL
     217: areturn
     218: ldc           #7                  // String XAException.XA_RBDEADLOCK
     220: areturn
     221: ldc           #8                  // String XAException.XA_RBINTEGRITY
     223: areturn
     224: ldc           #9                  // String XAException.XA_RBOTHER
     226: areturn
     227: ldc           #10                 // String XAException.XA_RBPROTO
     229: areturn
     230: ldc           #11                 // String XAException.XA_RBTIMEOUT
     232: areturn
     233: ldc           #12                 // String XAException.XA_RBTRANSIENT
     235: areturn
     236: ldc           #13                 // String XAException.XA_NOMIGRATE
     238: areturn
     239: ldc           #14                 // String XAException.XA_HEURHAZ
     241: areturn
     242: ldc           #15                 // String XAException.XA_HEURCOM
     244: areturn
     245: ldc           #16                 // String XAException.XA_HEURRB
     247: areturn
     248: ldc           #17                 // String XAException.XA_HEURMIX
     250: areturn
     251: ldc           #18                 // String XAException.XA_RDONLY
     253: areturn
     254: ldc           #19                 // String XAException.XAER_RMERR
     256: areturn
     257: ldc           #20                 // String XAException.XAER_NOTA
     259: areturn
     260: ldc           #21                 // String XAException.XAER_INVAL
     262: areturn
     263: ldc           #22                 // String XAException.XAER_PROTO
     265: areturn
     266: ldc           #23                 // String XAException.XAER_RMFAIL
     268: areturn
     269: ldc           #24                 // String XAException.XAER_DUPID
     271: areturn
     272: ldc           #25                 // String XAException.XAER_OUTSIDE
     274: areturn
     275: ldc           #26                 // String XAException.XA_RETRY
     277: areturn
     278: ldc           #27                 // String XAException.XAER_ASYNC
     280: areturn
     281: new           #28                 // class java/lang/StringBuilder
     284: dup
     285: invokespecial #29                 // Method java/lang/StringBuilder."<init>":()V
     288: getstatic     #2                  // Field com/arjuna/ats/jta/logging/jtaLogger.i18NLogger:Lcom/arjuna/ats/jta/logging/jtaI18NLogger;
     291: invokeinterface #30,  1           // InterfaceMethod com/arjuna/ats/jta/logging/jtaI18NLogger.get_utils_unknownerrorcode:()Ljava/lang/String;
     296: invokevirtual #31                 // Method java/lang/StringBuilder.append:(Ljava/lang/String;)Ljava/lang/StringBuilder;
     299: aload_0
     300: getfield      #4                  // Field javax/transaction/xa/XAException.errorCode:I
     303: invokevirtual #32                 // Method java/lang/StringBuilder.append:(I)Ljava/lang/StringBuilder;
     306: invokevirtual #33                 // Method java/lang/StringBuilder.toString:()Ljava/lang/String;
     309: areturn

  public static boolean sameXID(javax.transaction.xa.Xid, javax.transaction.xa.Xid);
    Code:
       0: aload_0
       1: aload_1
       2: if_acmpne     7
       5: iconst_1
       6: ireturn
       7: aload_0
       8: invokeinterface #34,  1           // InterfaceMethod javax/transaction/xa/Xid.getFormatId:()I
      13: aload_1
      14: invokeinterface #34,  1           // InterfaceMethod javax/transaction/xa/Xid.getFormatId:()I
      19: if_icmpne     166
      22: aload_0
      23: invokeinterface #35,  1           // InterfaceMethod javax/transaction/xa/Xid.getGlobalTransactionId:()[B
      28: astore_2
      29: aload_1
      30: invokeinterface #35,  1           // InterfaceMethod javax/transaction/xa/Xid.getGlobalTransactionId:()[B
      35: astore_3
      36: aload_2
      37: arraylength
      38: aload_3
      39: arraylength
      40: if_icmpne     75
      43: iconst_0
      44: istore        4
      46: iload         4
      48: aload_2
      49: arraylength
      50: if_icmpge     72
      53: aload_2
      54: iload         4
      56: baload
      57: aload_3
      58: iload         4
      60: baload
      61: if_icmpeq     66
      64: iconst_0
      65: ireturn
      66: iinc          4, 1
      69: goto          46
      72: goto          77
      75: iconst_0
      76: ireturn
      77: aload_0
      78: invokeinterface #36,  1           // InterfaceMethod javax/transaction/xa/Xid.getBranchQualifier:()[B
      83: astore        4
      85: aload         4
      87: ifnonnull     94
      90: iconst_0
      91: goto          97
      94: aload         4
      96: arraylength
      97: istore        5
      99: aload_1
     100: invokeinterface #36,  1           // InterfaceMethod javax/transaction/xa/Xid.getBranchQualifier:()[B
     105: astore        6
     107: aload         6
     109: ifnonnull     116
     112: iconst_0
     113: goto          119
     116: aload         6
     118: arraylength
     119: istore        7
     121: iload         5
     123: iload         7
     125: if_icmpne     162
     128: iconst_0
     129: istore        8
     131: iload         8
     133: iload         5
     135: if_icmpge     159
     138: aload         4
     140: iload         8
     142: baload
     143: aload         6
     145: iload         8
     147: baload
     148: if_icmpeq     153
     151: iconst_0
     152: ireturn
     153: iinc          8, 1
     156: goto          131
     159: goto          164
     162: iconst_0
     163: ireturn
     164: iconst_1
     165: ireturn
     166: iconst_0
     167: ireturn

  public static boolean sameTransaction(javax.transaction.xa.Xid, javax.transaction.xa.Xid);
    Code:
       0: aload_0
       1: aload_1
       2: if_acmpne     7
       5: iconst_1
       6: ireturn
       7: aload_0
       8: invokeinterface #34,  1           // InterfaceMethod javax/transaction/xa/Xid.getFormatId:()I
      13: aload_1
      14: invokeinterface #34,  1           // InterfaceMethod javax/transaction/xa/Xid.getFormatId:()I
      19: if_icmpne     76
      22: aload_0
      23: invokeinterface #35,  1           // InterfaceMethod javax/transaction/xa/Xid.getGlobalTransactionId:()[B
      28: astore_2
      29: aload_1
      30: invokeinterface #35,  1           // InterfaceMethod javax/transaction/xa/Xid.getGlobalTransactionId:()[B
      35: astore_3
      36: aload_2
      37: arraylength
      38: aload_3
      39: arraylength
      40: if_icmpne     74
      43: iconst_0
      44: istore        4
      46: iload         4
      48: aload_2
      49: arraylength
      50: if_icmpge     72
      53: aload_2
      54: iload         4
      56: baload
      57: aload_3
      58: iload         4
      60: baload
      61: if_icmpeq     66
      64: iconst_0
      65: ireturn
      66: iinc          4, 1
      69: goto          46
      72: iconst_1
      73: ireturn
      74: iconst_0
      75: ireturn
      76: iconst_0
      77: ireturn

  public static java.lang.String xidToString(javax.transaction.xa.Xid);
    Code:
       0: aload_0
       1: instanceof    #37                 // class com/arjuna/ats/jta/xa/XidImple
       4: ifeq          12
       7: aload_0
       8: invokevirtual #38                 // Method java/lang/Object.toString:()Ljava/lang/String;
      11: areturn
      12: aload_0
      13: invokeinterface #35,  1           // InterfaceMethod javax/transaction/xa/Xid.getGlobalTransactionId:()[B
      18: astore_1
      19: aload_0
      20: invokeinterface #36,  1           // InterfaceMethod javax/transaction/xa/Xid.getBranchQualifier:()[B
      25: astore_2
      26: new           #28                 // class java/lang/StringBuilder
      29: dup
      30: invokespecial #29                 // Method java/lang/StringBuilder."<init>":()V
      33: ldc           #39                 // String <
      35: invokevirtual #31                 // Method java/lang/StringBuilder.append:(Ljava/lang/String;)Ljava/lang/StringBuilder;
      38: aload_0
      39: invokeinterface #34,  1           // InterfaceMethod javax/transaction/xa/Xid.getFormatId:()I
      44: invokevirtual #32                 // Method java/lang/StringBuilder.append:(I)Ljava/lang/StringBuilder;
      47: ldc           #40                 // String ,
      49: invokevirtual #31                 // Method java/lang/StringBuilder.append:(Ljava/lang/String;)Ljava/lang/StringBuilder;
      52: aload_1
      53: arraylength
      54: invokevirtual #32                 // Method java/lang/StringBuilder.append:(I)Ljava/lang/StringBuilder;
      57: ldc           #40                 // String ,
      59: invokevirtual #31                 // Method java/lang/StringBuilder.append:(Ljava/lang/String;)Ljava/lang/StringBuilder;
      62: aload_2
      63: arraylength
      64: invokevirtual #32                 // Method java/lang/StringBuilder.append:(I)Ljava/lang/StringBuilder;
      67: ldc           #40                 // String ,
      69: invokevirtual #31                 // Method java/lang/StringBuilder.append:(Ljava/lang/String;)Ljava/lang/StringBuilder;
      72: invokevirtual #33                 // Method java/lang/StringBuilder.toString:()Ljava/lang/String;
      75: astore_3
      76: iconst_0
      77: istore        4
      79: iload         4
      81: aload_1
      82: arraylength
      83: if_icmpge     114
      86: new           #28                 // class java/lang/StringBuilder
      89: dup
      90: invokespecial #29                 // Method java/lang/StringBuilder."<init>":()V
      93: aload_3
      94: invokevirtual #31                 // Method java/lang/StringBuilder.append:(Ljava/lang/String;)Ljava/lang/StringBuilder;
      97: aload_1
      98: iload         4
     100: baload
     101: invokevirtual #32                 // Method java/lang/StringBuilder.append:(I)Ljava/lang/StringBuilder;
     104: invokevirtual #33                 // Method java/lang/StringBuilder.toString:()Ljava/lang/String;
     107: astore_3
     108: iinc          4, 1
     111: goto          79
     114: iconst_0
     115: istore        4
     117: iload         4
     119: aload_2
     120: arraylength
     121: if_icmpge     152
     124: new           #28                 // class java/lang/StringBuilder
     127: dup
     128: invokespecial #29                 // Method java/lang/StringBuilder."<init>":()V
     131: aload_3
     132: invokevirtual #31                 // Method java/lang/StringBuilder.append:(Ljava/lang/String;)Ljava/lang/StringBuilder;
     135: aload_2
     136: iload         4
     138: baload
     139: invokevirtual #32                 // Method java/lang/StringBuilder.append:(I)Ljava/lang/StringBuilder;
     142: invokevirtual #33                 // Method java/lang/StringBuilder.toString:()Ljava/lang/String;
     145: astore_3
     146: iinc          4, 1
     149: goto          117
     152: new           #28                 // class java/lang/StringBuilder
     155: dup
     156: invokespecial #29                 // Method java/lang/StringBuilder."<init>":()V
     159: aload_3
     160: invokevirtual #31                 // Method java/lang/StringBuilder.append:(Ljava/lang/String;)Ljava/lang/StringBuilder;
     163: ldc           #41                 // String  >
     165: invokevirtual #31                 // Method java/lang/StringBuilder.append:(Ljava/lang/String;)Ljava/lang/StringBuilder;
     168: invokevirtual #33                 // Method java/lang/StringBuilder.toString:()Ljava/lang/String;
     171: astore_3
     172: aload_3
     173: areturn
}
