Compiled from "PostBankBankModel.kt"
public final class app.cybrid.cybrid_api_bank.client.models.PostBankBankModel {
  private final java.lang.String name;

  private final app.cybrid.cybrid_api_bank.client.models.PostBankBankModel$Type type;

  private final java.util.List<java.lang.String> supportedTradingSymbols;

  private final java.util.List<app.cybrid.cybrid_api_bank.client.models.PostBankBankModel$Features> features;

  private final java.util.List<java.lang.String> supportedFiatAccountAssets;

  private final java.util.List<java.lang.String> supportedCountryCodes;

  public app.cybrid.cybrid_api_bank.client.models.PostBankBankModel(java.lang.String, app.cybrid.cybrid_api_bank.client.models.PostBankBankModel$Type, java.util.List<java.lang.String>, java.util.List<? extends app.cybrid.cybrid_api_bank.client.models.PostBankBankModel$Features>, java.util.List<java.lang.String>, java.util.List<java.lang.String>);
    Code:
       0: aload_1
       1: ldc           #11                 // String name
       3: invokestatic  #17                 // Method kotlin/jvm/internal/Intrinsics.checkNotNullParameter:(Ljava/lang/Object;Ljava/lang/String;)V
       6: aload_2
       7: ldc           #19                 // String type
       9: invokestatic  #17                 // Method kotlin/jvm/internal/Intrinsics.checkNotNullParameter:(Ljava/lang/Object;Ljava/lang/String;)V
      12: aload_3
      13: ldc           #21                 // String supportedTradingSymbols
      15: invokestatic  #17                 // Method kotlin/jvm/internal/Intrinsics.checkNotNullParameter:(Ljava/lang/Object;Ljava/lang/String;)V
      18: aload         4
      20: ldc           #23                 // String features
      22: invokestatic  #17                 // Method kotlin/jvm/internal/Intrinsics.checkNotNullParameter:(Ljava/lang/Object;Ljava/lang/String;)V
      25: aload         5
      27: ldc           #25                 // String supportedFiatAccountAssets
      29: invokestatic  #17                 // Method kotlin/jvm/internal/Intrinsics.checkNotNullParameter:(Ljava/lang/Object;Ljava/lang/String;)V
      32: aload_0
      33: invokespecial #28                 // Method java/lang/Object."<init>":()V
      36: aload_0
      37: aload_1
      38: putfield      #31                 // Field name:Ljava/lang/String;
      41: aload_0
      42: aload_2
      43: putfield      #34                 // Field type:Lapp/cybrid/cybrid_api_bank/client/models/PostBankBankModel$Type;
      46: aload_0
      47: aload_3
      48: putfield      #37                 // Field supportedTradingSymbols:Ljava/util/List;
      51: aload_0
      52: aload         4
      54: putfield      #39                 // Field features:Ljava/util/List;
      57: aload_0
      58: aload         5
      60: putfield      #41                 // Field supportedFiatAccountAssets:Ljava/util/List;
      63: aload_0
      64: aload         6
      66: putfield      #44                 // Field supportedCountryCodes:Ljava/util/List;
      69: return

  public app.cybrid.cybrid_api_bank.client.models.PostBankBankModel(java.lang.String, app.cybrid.cybrid_api_bank.client.models.PostBankBankModel$Type, java.util.List, java.util.List, java.util.List, java.util.List, int, kotlin.jvm.internal.DefaultConstructorMarker);
    Code:
       0: iload         7
       2: bipush        32
       4: iand
       5: ifeq          11
       8: aconst_null
       9: astore        6
      11: aload_0
      12: aload_1
      13: aload_2
      14: aload_3
      15: aload         4
      17: aload         5
      19: aload         6
      21: invokespecial #49                 // Method "<init>":(Ljava/lang/String;Lapp/cybrid/cybrid_api_bank/client/models/PostBankBankModel$Type;Ljava/util/List;Ljava/util/List;Ljava/util/List;Ljava/util/List;)V
      24: return

  public final java.lang.String getName();
    Code:
       0: aload_0
       1: getfield      #31                 // Field name:Ljava/lang/String;
       4: areturn

  public final app.cybrid.cybrid_api_bank.client.models.PostBankBankModel$Type getType();
    Code:
       0: aload_0
       1: getfield      #34                 // Field type:Lapp/cybrid/cybrid_api_bank/client/models/PostBankBankModel$Type;
       4: areturn

  public final java.util.List<java.lang.String> getSupportedTradingSymbols();
    Code:
       0: aload_0
       1: getfield      #37                 // Field supportedTradingSymbols:Ljava/util/List;
       4: areturn

  public final java.util.List<app.cybrid.cybrid_api_bank.client.models.PostBankBankModel$Features> getFeatures();
    Code:
       0: aload_0
       1: getfield      #39                 // Field features:Ljava/util/List;
       4: areturn

  public final java.util.List<java.lang.String> getSupportedFiatAccountAssets();
    Code:
       0: aload_0
       1: getfield      #41                 // Field supportedFiatAccountAssets:Ljava/util/List;
       4: areturn

  public final java.util.List<java.lang.String> getSupportedCountryCodes();
    Code:
       0: aload_0
       1: getfield      #44                 // Field supportedCountryCodes:Ljava/util/List;
       4: areturn

  public final java.lang.String component1();
    Code:
       0: aload_0
       1: getfield      #31                 // Field name:Ljava/lang/String;
       4: areturn

  public final app.cybrid.cybrid_api_bank.client.models.PostBankBankModel$Type component2();
    Code:
       0: aload_0
       1: getfield      #34                 // Field type:Lapp/cybrid/cybrid_api_bank/client/models/PostBankBankModel$Type;
       4: areturn

  public final java.util.List<java.lang.String> component3();
    Code:
       0: aload_0
       1: getfield      #37                 // Field supportedTradingSymbols:Ljava/util/List;
       4: areturn

  public final java.util.List<app.cybrid.cybrid_api_bank.client.models.PostBankBankModel$Features> component4();
    Code:
       0: aload_0
       1: getfield      #39                 // Field features:Ljava/util/List;
       4: areturn

  public final java.util.List<java.lang.String> component5();
    Code:
       0: aload_0
       1: getfield      #41                 // Field supportedFiatAccountAssets:Ljava/util/List;
       4: areturn

  public final java.util.List<java.lang.String> component6();
    Code:
       0: aload_0
       1: getfield      #44                 // Field supportedCountryCodes:Ljava/util/List;
       4: areturn

  public final app.cybrid.cybrid_api_bank.client.models.PostBankBankModel copy(java.lang.String, app.cybrid.cybrid_api_bank.client.models.PostBankBankModel$Type, java.util.List<java.lang.String>, java.util.List<? extends app.cybrid.cybrid_api_bank.client.models.PostBankBankModel$Features>, java.util.List<java.lang.String>, java.util.List<java.lang.String>);
    Code:
       0: aload_1
       1: ldc           #11                 // String name
       3: invokestatic  #17                 // Method kotlin/jvm/internal/Intrinsics.checkNotNullParameter:(Ljava/lang/Object;Ljava/lang/String;)V
       6: aload_2
       7: ldc           #19                 // String type
       9: invokestatic  #17                 // Method kotlin/jvm/internal/Intrinsics.checkNotNullParameter:(Ljava/lang/Object;Ljava/lang/String;)V
      12: aload_3
      13: ldc           #21                 // String supportedTradingSymbols
      15: invokestatic  #17                 // Method kotlin/jvm/internal/Intrinsics.checkNotNullParameter:(Ljava/lang/Object;Ljava/lang/String;)V
      18: aload         4
      20: ldc           #23                 // String features
      22: invokestatic  #17                 // Method kotlin/jvm/internal/Intrinsics.checkNotNullParameter:(Ljava/lang/Object;Ljava/lang/String;)V
      25: aload         5
      27: ldc           #25                 // String supportedFiatAccountAssets
      29: invokestatic  #17                 // Method kotlin/jvm/internal/Intrinsics.checkNotNullParameter:(Ljava/lang/Object;Ljava/lang/String;)V
      32: new           #2                  // class app/cybrid/cybrid_api_bank/client/models/PostBankBankModel
      35: dup
      36: aload_1
      37: aload_2
      38: aload_3
      39: aload         4
      41: aload         5
      43: aload         6
      45: invokespecial #49                 // Method "<init>":(Ljava/lang/String;Lapp/cybrid/cybrid_api_bank/client/models/PostBankBankModel$Type;Ljava/util/List;Ljava/util/List;Ljava/util/List;Ljava/util/List;)V
      48: areturn

  public static app.cybrid.cybrid_api_bank.client.models.PostBankBankModel copy$default(app.cybrid.cybrid_api_bank.client.models.PostBankBankModel, java.lang.String, app.cybrid.cybrid_api_bank.client.models.PostBankBankModel$Type, java.util.List, java.util.List, java.util.List, java.util.List, int, java.lang.Object);
    Code:
       0: iload         7
       2: iconst_1
       3: iand
       4: ifeq          12
       7: aload_0
       8: getfield      #31                 // Field name:Ljava/lang/String;
      11: astore_1
      12: iload         7
      14: iconst_2
      15: iand
      16: ifeq          24
      19: aload_0
      20: getfield      #34                 // Field type:Lapp/cybrid/cybrid_api_bank/client/models/PostBankBankModel$Type;
      23: astore_2
      24: iload         7
      26: iconst_4
      27: iand
      28: ifeq          36
      31: aload_0
      32: getfield      #37                 // Field supportedTradingSymbols:Ljava/util/List;
      35: astore_3
      36: iload         7
      38: bipush        8
      40: iand
      41: ifeq          50
      44: aload_0
      45: getfield      #39                 // Field features:Ljava/util/List;
      48: astore        4
      50: iload         7
      52: bipush        16
      54: iand
      55: ifeq          64
      58: aload_0
      59: getfield      #41                 // Field supportedFiatAccountAssets:Ljava/util/List;
      62: astore        5
      64: iload         7
      66: bipush        32
      68: iand
      69: ifeq          78
      72: aload_0
      73: getfield      #44                 // Field supportedCountryCodes:Ljava/util/List;
      76: astore        6
      78: aload_0
      79: aload_1
      80: aload_2
      81: aload_3
      82: aload         4
      84: aload         5
      86: aload         6
      88: invokevirtual #73                 // Method copy:(Ljava/lang/String;Lapp/cybrid/cybrid_api_bank/client/models/PostBankBankModel$Type;Ljava/util/List;Ljava/util/List;Ljava/util/List;Ljava/util/List;)Lapp/cybrid/cybrid_api_bank/client/models/PostBankBankModel;
      91: areturn

  public java.lang.String toString();
    Code:
       0: new           #76                 // class java/lang/StringBuilder
       3: dup
       4: invokespecial #77                 // Method java/lang/StringBuilder."<init>":()V
       7: ldc           #79                 // String PostBankBankModel(name=
       9: invokevirtual #83                 // Method java/lang/StringBuilder.append:(Ljava/lang/String;)Ljava/lang/StringBuilder;
      12: aload_0
      13: getfield      #31                 // Field name:Ljava/lang/String;
      16: invokevirtual #83                 // Method java/lang/StringBuilder.append:(Ljava/lang/String;)Ljava/lang/StringBuilder;
      19: ldc           #85                 // String , type=
      21: invokevirtual #83                 // Method java/lang/StringBuilder.append:(Ljava/lang/String;)Ljava/lang/StringBuilder;
      24: aload_0
      25: getfield      #34                 // Field type:Lapp/cybrid/cybrid_api_bank/client/models/PostBankBankModel$Type;
      28: invokevirtual #88                 // Method java/lang/StringBuilder.append:(Ljava/lang/Object;)Ljava/lang/StringBuilder;
      31: ldc           #90                 // String , supportedTradingSymbols=
      33: invokevirtual #83                 // Method java/lang/StringBuilder.append:(Ljava/lang/String;)Ljava/lang/StringBuilder;
      36: aload_0
      37: getfield      #37                 // Field supportedTradingSymbols:Ljava/util/List;
      40: invokevirtual #88                 // Method java/lang/StringBuilder.append:(Ljava/lang/Object;)Ljava/lang/StringBuilder;
      43: ldc           #92                 // String , features=
      45: invokevirtual #83                 // Method java/lang/StringBuilder.append:(Ljava/lang/String;)Ljava/lang/StringBuilder;
      48: aload_0
      49: getfield      #39                 // Field features:Ljava/util/List;
      52: invokevirtual #88                 // Method java/lang/StringBuilder.append:(Ljava/lang/Object;)Ljava/lang/StringBuilder;
      55: ldc           #94                 // String , supportedFiatAccountAssets=
      57: invokevirtual #83                 // Method java/lang/StringBuilder.append:(Ljava/lang/String;)Ljava/lang/StringBuilder;
      60: aload_0
      61: getfield      #41                 // Field supportedFiatAccountAssets:Ljava/util/List;
      64: invokevirtual #88                 // Method java/lang/StringBuilder.append:(Ljava/lang/Object;)Ljava/lang/StringBuilder;
      67: ldc           #96                 // String , supportedCountryCodes=
      69: invokevirtual #83                 // Method java/lang/StringBuilder.append:(Ljava/lang/String;)Ljava/lang/StringBuilder;
      72: aload_0
      73: getfield      #44                 // Field supportedCountryCodes:Ljava/util/List;
      76: invokevirtual #88                 // Method java/lang/StringBuilder.append:(Ljava/lang/Object;)Ljava/lang/StringBuilder;
      79: bipush        41
      81: invokevirtual #99                 // Method java/lang/StringBuilder.append:(C)Ljava/lang/StringBuilder;
      84: invokevirtual #101                // Method java/lang/StringBuilder.toString:()Ljava/lang/String;
      87: areturn

  public int hashCode();
    Code:
       0: aload_0
       1: getfield      #31                 // Field name:Ljava/lang/String;
       4: invokevirtual #107                // Method java/lang/String.hashCode:()I
       7: istore_1
       8: iload_1
       9: bipush        31
      11: imul
      12: aload_0
      13: getfield      #34                 // Field type:Lapp/cybrid/cybrid_api_bank/client/models/PostBankBankModel$Type;
      16: invokevirtual #110                // Method app/cybrid/cybrid_api_bank/client/models/PostBankBankModel$Type.hashCode:()I
      19: iadd
      20: istore_1
      21: iload_1
      22: bipush        31
      24: imul
      25: aload_0
      26: getfield      #37                 // Field supportedTradingSymbols:Ljava/util/List;
      29: invokevirtual #111                // Method java/lang/Object.hashCode:()I
      32: iadd
      33: istore_1
      34: iload_1
      35: bipush        31
      37: imul
      38: aload_0
      39: getfield      #39                 // Field features:Ljava/util/List;
      42: invokevirtual #111                // Method java/lang/Object.hashCode:()I
      45: iadd
      46: istore_1
      47: iload_1
      48: bipush        31
      50: imul
      51: aload_0
      52: getfield      #41                 // Field supportedFiatAccountAssets:Ljava/util/List;
      55: invokevirtual #111                // Method java/lang/Object.hashCode:()I
      58: iadd
      59: istore_1
      60: iload_1
      61: bipush        31
      63: imul
      64: aload_0
      65: getfield      #44                 // Field supportedCountryCodes:Ljava/util/List;
      68: ifnonnull     75
      71: iconst_0
      72: goto          82
      75: aload_0
      76: getfield      #44                 // Field supportedCountryCodes:Ljava/util/List;
      79: invokevirtual #111                // Method java/lang/Object.hashCode:()I
      82: iadd
      83: istore_1
      84: iload_1
      85: ireturn

  public boolean equals(java.lang.Object);
    Code:
       0: aload_0
       1: aload_1
       2: if_acmpne     7
       5: iconst_1
       6: ireturn
       7: aload_1
       8: instanceof    #2                  // class app/cybrid/cybrid_api_bank/client/models/PostBankBankModel
      11: ifne          16
      14: iconst_0
      15: ireturn
      16: aload_1
      17: checkcast     #2                  // class app/cybrid/cybrid_api_bank/client/models/PostBankBankModel
      20: astore_2
      21: aload_0
      22: getfield      #31                 // Field name:Ljava/lang/String;
      25: aload_2
      26: getfield      #31                 // Field name:Ljava/lang/String;
      29: invokestatic  #119                // Method kotlin/jvm/internal/Intrinsics.areEqual:(Ljava/lang/Object;Ljava/lang/Object;)Z
      32: ifne          37
      35: iconst_0
      36: ireturn
      37: aload_0
      38: getfield      #34                 // Field type:Lapp/cybrid/cybrid_api_bank/client/models/PostBankBankModel$Type;
      41: aload_2
      42: getfield      #34                 // Field type:Lapp/cybrid/cybrid_api_bank/client/models/PostBankBankModel$Type;
      45: if_acmpeq     50
      48: iconst_0
      49: ireturn
      50: aload_0
      51: getfield      #37                 // Field supportedTradingSymbols:Ljava/util/List;
      54: aload_2
      55: getfield      #37                 // Field supportedTradingSymbols:Ljava/util/List;
      58: invokestatic  #119                // Method kotlin/jvm/internal/Intrinsics.areEqual:(Ljava/lang/Object;Ljava/lang/Object;)Z
      61: ifne          66
      64: iconst_0
      65: ireturn
      66: aload_0
      67: getfield      #39                 // Field features:Ljava/util/List;
      70: aload_2
      71: getfield      #39                 // Field features:Ljava/util/List;
      74: invokestatic  #119                // Method kotlin/jvm/internal/Intrinsics.areEqual:(Ljava/lang/Object;Ljava/lang/Object;)Z
      77: ifne          82
      80: iconst_0
      81: ireturn
      82: aload_0
      83: getfield      #41                 // Field supportedFiatAccountAssets:Ljava/util/List;
      86: aload_2
      87: getfield      #41                 // Field supportedFiatAccountAssets:Ljava/util/List;
      90: invokestatic  #119                // Method kotlin/jvm/internal/Intrinsics.areEqual:(Ljava/lang/Object;Ljava/lang/Object;)Z
      93: ifne          98
      96: iconst_0
      97: ireturn
      98: aload_0
      99: getfield      #44                 // Field supportedCountryCodes:Ljava/util/List;
     102: aload_2
     103: getfield      #44                 // Field supportedCountryCodes:Ljava/util/List;
     106: invokestatic  #119                // Method kotlin/jvm/internal/Intrinsics.areEqual:(Ljava/lang/Object;Ljava/lang/Object;)Z
     109: ifne          114
     112: iconst_0
     113: ireturn
     114: iconst_1
     115: ireturn
}
