Compiled from "DefaultBindingTargetVisitor.java"
public abstract class com.google.inject.spi.DefaultBindingTargetVisitor<T, V> implements com.google.inject.spi.BindingTargetVisitor<T, V> {
  public com.google.inject.spi.DefaultBindingTargetVisitor();
    Code:
       0: aload_0
       1: invokespecial #12                 // Method java/lang/Object."<init>":()V
       4: return

  protected V visitOther(com.google.inject.Binding<? extends T>);
    Code:
       0: aconst_null
       1: areturn

  public V visit(com.google.inject.spi.InstanceBinding<? extends T>);
    Code:
       0: aload_0
       1: aload_1
       2: invokevirtual #24                 // Method visitOther:(Lcom/google/inject/Binding;)Ljava/lang/Object;
       5: areturn

  public V visit(com.google.inject.spi.ProviderInstanceBinding<? extends T>);
    Code:
       0: aload_0
       1: aload_1
       2: invokevirtual #24                 // Method visitOther:(Lcom/google/inject/Binding;)Ljava/lang/Object;
       5: areturn

  public V visit(com.google.inject.spi.ProviderKeyBinding<? extends T>);
    Code:
       0: aload_0
       1: aload_1
       2: invokevirtual #24                 // Method visitOther:(Lcom/google/inject/Binding;)Ljava/lang/Object;
       5: areturn

  public V visit(com.google.inject.spi.LinkedKeyBinding<? extends T>);
    Code:
       0: aload_0
       1: aload_1
       2: invokevirtual #24                 // Method visitOther:(Lcom/google/inject/Binding;)Ljava/lang/Object;
       5: areturn

  public V visit(com.google.inject.spi.ExposedBinding<? extends T>);
    Code:
       0: aload_0
       1: aload_1
       2: invokevirtual #24                 // Method visitOther:(Lcom/google/inject/Binding;)Ljava/lang/Object;
       5: areturn

  public V visit(com.google.inject.spi.UntargettedBinding<? extends T>);
    Code:
       0: aload_0
       1: aload_1
       2: invokevirtual #24                 // Method visitOther:(Lcom/google/inject/Binding;)Ljava/lang/Object;
       5: areturn

  public V visit(com.google.inject.spi.ConstructorBinding<? extends T>);
    Code:
       0: aload_0
       1: aload_1
       2: invokevirtual #24                 // Method visitOther:(Lcom/google/inject/Binding;)Ljava/lang/Object;
       5: areturn

  public V visit(com.google.inject.spi.ConvertedConstantBinding<? extends T>);
    Code:
       0: aload_0
       1: aload_1
       2: invokevirtual #24                 // Method visitOther:(Lcom/google/inject/Binding;)Ljava/lang/Object;
       5: areturn

  public V visit(com.google.inject.spi.ProviderBinding<? extends T>);
    Code:
       0: aload_0
       1: aload_1
       2: invokevirtual #24                 // Method visitOther:(Lcom/google/inject/Binding;)Ljava/lang/Object;
       5: areturn
}
