Compiled from "Message.java"
public final class com.google.inject.spi.Message implements java.io.Serializable,com.google.inject.spi.Element {
  private final java.lang.String message;

  private final java.lang.Throwable cause;

  private final java.util.List<java.lang.Object> sources;

  private static final long serialVersionUID;

  public com.google.inject.spi.Message(java.util.List<java.lang.Object>, java.lang.String, java.lang.Throwable);
    Code:
       0: aload_0
       1: invokespecial #25                 // Method java/lang/Object."<init>":()V
       4: aload_0
       5: aload_1
       6: invokestatic  #31                 // Method com/google/common/collect/ImmutableList.copyOf:(Ljava/util/Collection;)Lcom/google/common/collect/ImmutableList;
       9: putfield      #33                 // Field sources:Ljava/util/List;
      12: aload_0
      13: aload_2
      14: ldc           #34                 // String message
      16: invokestatic  #40                 // Method com/google/common/base/Preconditions.checkNotNull:(Ljava/lang/Object;Ljava/lang/Object;)Ljava/lang/Object;
      19: checkcast     #42                 // class java/lang/String
      22: putfield      #44                 // Field message:Ljava/lang/String;
      25: aload_0
      26: aload_3
      27: putfield      #46                 // Field cause:Ljava/lang/Throwable;
      30: return

  public com.google.inject.spi.Message(java.lang.Object, java.lang.String);
    Code:
       0: aload_0
       1: aload_1
       2: invokestatic  #53                 // Method com/google/common/collect/ImmutableList.of:(Ljava/lang/Object;)Lcom/google/common/collect/ImmutableList;
       5: aload_2
       6: aconst_null
       7: invokespecial #55                 // Method "<init>":(Ljava/util/List;Ljava/lang/String;Ljava/lang/Throwable;)V
      10: return

  public com.google.inject.spi.Message(java.lang.String);
    Code:
       0: aload_0
       1: invokestatic  #61                 // Method com/google/common/collect/ImmutableList.of:()Lcom/google/common/collect/ImmutableList;
       4: aload_1
       5: aconst_null
       6: invokespecial #55                 // Method "<init>":(Ljava/util/List;Ljava/lang/String;Ljava/lang/Throwable;)V
       9: return

  public java.lang.String getSource();
    Code:
       0: aload_0
       1: getfield      #33                 // Field sources:Ljava/util/List;
       4: invokeinterface #69,  1           // InterfaceMethod java/util/List.isEmpty:()Z
       9: ifeq          21
      12: getstatic     #74                 // Field com/google/inject/internal/util/SourceProvider.UNKNOWN_SOURCE:Ljava/lang/Object;
      15: invokevirtual #77                 // Method java/lang/Object.toString:()Ljava/lang/String;
      18: goto          47
      21: aload_0
      22: getfield      #33                 // Field sources:Ljava/util/List;
      25: aload_0
      26: getfield      #33                 // Field sources:Ljava/util/List;
      29: invokeinterface #81,  1           // InterfaceMethod java/util/List.size:()I
      34: iconst_1
      35: isub
      36: invokeinterface #85,  2           // InterfaceMethod java/util/List.get:(I)Ljava/lang/Object;
      41: invokestatic  #91                 // Method com/google/inject/internal/Errors.convert:(Ljava/lang/Object;)Ljava/lang/Object;
      44: invokevirtual #77                 // Method java/lang/Object.toString:()Ljava/lang/String;
      47: areturn

  public java.util.List<java.lang.Object> getSources();
    Code:
       0: aload_0
       1: getfield      #33                 // Field sources:Ljava/util/List;
       4: areturn

  public java.lang.String getMessage();
    Code:
       0: aload_0
       1: getfield      #44                 // Field message:Ljava/lang/String;
       4: areturn

  public <T> T acceptVisitor(com.google.inject.spi.ElementVisitor<T>);
    Code:
       0: aload_1
       1: aload_0
       2: invokeinterface #102,  2          // InterfaceMethod com/google/inject/spi/ElementVisitor.visit:(Lcom/google/inject/spi/Message;)Ljava/lang/Object;
       7: areturn

  public java.lang.Throwable getCause();
    Code:
       0: aload_0
       1: getfield      #46                 // Field cause:Ljava/lang/Throwable;
       4: areturn

  public java.lang.String toString();
    Code:
       0: aload_0
       1: getfield      #44                 // Field message:Ljava/lang/String;
       4: areturn

  public int hashCode();
    Code:
       0: aload_0
       1: getfield      #44                 // Field message:Ljava/lang/String;
       4: invokevirtual #110                // Method java/lang/String.hashCode:()I
       7: ireturn

  public boolean equals(java.lang.Object);
    Code:
       0: aload_1
       1: instanceof    #2                  // class com/google/inject/spi/Message
       4: ifne          9
       7: iconst_0
       8: ireturn
       9: aload_1
      10: checkcast     #2                  // class com/google/inject/spi/Message
      13: astore_2
      14: aload_0
      15: getfield      #44                 // Field message:Ljava/lang/String;
      18: aload_2
      19: getfield      #44                 // Field message:Ljava/lang/String;
      22: invokevirtual #114                // Method java/lang/String.equals:(Ljava/lang/Object;)Z
      25: ifeq          60
      28: aload_0
      29: getfield      #46                 // Field cause:Ljava/lang/Throwable;
      32: aload_2
      33: getfield      #46                 // Field cause:Ljava/lang/Throwable;
      36: invokestatic  #120                // Method com/google/common/base/Objects.equal:(Ljava/lang/Object;Ljava/lang/Object;)Z
      39: ifeq          60
      42: aload_0
      43: getfield      #33                 // Field sources:Ljava/util/List;
      46: aload_2
      47: getfield      #33                 // Field sources:Ljava/util/List;
      50: invokevirtual #121                // Method java/lang/Object.equals:(Ljava/lang/Object;)Z
      53: ifeq          60
      56: iconst_1
      57: goto          61
      60: iconst_0
      61: ireturn

  public void applyTo(com.google.inject.Binder);
    Code:
       0: aload_1
       1: aload_0
       2: invokevirtual #127                // Method getSource:()Ljava/lang/String;
       5: invokeinterface #133,  2          // InterfaceMethod com/google/inject/Binder.withSource:(Ljava/lang/Object;)Lcom/google/inject/Binder;
      10: aload_0
      11: invokeinterface #137,  2          // InterfaceMethod com/google/inject/Binder.addError:(Lcom/google/inject/spi/Message;)V
      16: return

  private java.lang.Object writeReplace() throws java.io.ObjectStreamException;
    Code:
       0: aload_0
       1: getfield      #33                 // Field sources:Ljava/util/List;
       4: invokeinterface #147,  1          // InterfaceMethod java/util/List.toArray:()[Ljava/lang/Object;
       9: astore_1
      10: iconst_0
      11: istore_2
      12: iload_2
      13: aload_1
      14: arraylength
      15: if_icmpge     36
      18: aload_1
      19: iload_2
      20: aload_1
      21: iload_2
      22: aaload
      23: invokestatic  #91                 // Method com/google/inject/internal/Errors.convert:(Ljava/lang/Object;)Ljava/lang/Object;
      26: invokevirtual #77                 // Method java/lang/Object.toString:()Ljava/lang/String;
      29: aastore
      30: iinc          2, 1
      33: goto          12
      36: new           #2                  // class com/google/inject/spi/Message
      39: dup
      40: aload_1
      41: invokestatic  #150                // Method com/google/common/collect/ImmutableList.copyOf:([Ljava/lang/Object;)Lcom/google/common/collect/ImmutableList;
      44: aload_0
      45: getfield      #44                 // Field message:Ljava/lang/String;
      48: aload_0
      49: getfield      #46                 // Field cause:Ljava/lang/Throwable;
      52: invokespecial #55                 // Method "<init>":(Ljava/util/List;Ljava/lang/String;Ljava/lang/Throwable;)V
      55: areturn

  public java.lang.Object getSource();
    Code:
       0: aload_0
       1: invokevirtual #127                // Method getSource:()Ljava/lang/String;
       4: areturn
}
