Compiled from "ExecutableArchiveLauncher.java"
class org.springframework.boot.loader.ExecutableArchiveLauncher$1 implements org.springframework.boot.loader.archive.Archive$EntryFilter {
  final org.springframework.boot.loader.ExecutableArchiveLauncher this$0;

  org.springframework.boot.loader.ExecutableArchiveLauncher$1(org.springframework.boot.loader.ExecutableArchiveLauncher);
    Code:
       0: aload_0
       1: aload_1
       2: putfield      #1                  // Field this$0:Lorg/springframework/boot/loader/ExecutableArchiveLauncher;
       5: aload_0
       6: invokespecial #2                  // Method java/lang/Object."<init>":()V
       9: return

  public boolean matches(org.springframework.boot.loader.archive.Archive$Entry);
    Code:
       0: aload_0
       1: getfield      #1                  // Field this$0:Lorg/springframework/boot/loader/ExecutableArchiveLauncher;
       4: aload_1
       5: invokevirtual #3                  // Method org/springframework/boot/loader/ExecutableArchiveLauncher.isNestedArchive:(Lorg/springframework/boot/loader/archive/Archive$Entry;)Z
       8: ireturn
}
