Compiled from "EqMatchers.scala"
public abstract class org.mockito.matchers.EqMatchers$class {
  public static java.lang.Object same(org.mockito.matchers.EqMatchers, java.lang.Object);
    Code:
       0: aload_1
       1: invokestatic  #12                 // Method org/mockito/ArgumentMatchers.same:(Ljava/lang/Object;)Ljava/lang/Object;
       4: areturn

  public static java.lang.Object isA(org.mockito.matchers.EqMatchers, scala.reflect.ClassTag);
    Code:
       0: getstatic     #24                 // Field org/mockito/package$.MODULE$:Lorg/mockito/package$;
       3: aload_1
       4: invokevirtual #28                 // Method org/mockito/package$.clazz:(Lscala/reflect/ClassTag;)Ljava/lang/Class;
       7: invokestatic  #31                 // Method org/mockito/ArgumentMatchers.isA:(Ljava/lang/Class;)Ljava/lang/Object;
      10: areturn

  public static java.lang.Object refEq(org.mockito.matchers.EqMatchers, java.lang.Object, scala.collection.Seq);
    Code:
       0: aload_1
       1: aload_2
       2: getstatic     #40                 // Field scala/reflect/ClassTag$.MODULE$:Lscala/reflect/ClassTag$;
       5: ldc           #42                 // class java/lang/String
       7: invokevirtual #46                 // Method scala/reflect/ClassTag$.apply:(Ljava/lang/Class;)Lscala/reflect/ClassTag;
      10: invokeinterface #52,  2           // InterfaceMethod scala/collection/Seq.toArray:(Lscala/reflect/ClassTag;)Ljava/lang/Object;
      15: checkcast     #54                 // class "[Ljava/lang/String;"
      18: invokestatic  #57                 // Method org/mockito/ArgumentMatchers.refEq:(Ljava/lang/Object;[Ljava/lang/String;)Ljava/lang/Object;
      21: areturn

  public static void $init$(org.mockito.matchers.EqMatchers);
    Code:
       0: return
}
