Compiled from "NumericMatchers.scala"
public final class org.mockito.matchers.N$$anonfun$$eq$tilde$2 extends scala.runtime.AbstractFunction1<T, java.lang.Object> implements scala.Serializable {
  public static final long serialVersionUID;

  private final org.scalactic.TripleEqualsSupport$Spread spread$1;

  public final boolean apply(T);
    Code:
       0: aload_0
       1: getfield      #23                 // Field spread$1:Lorg/scalactic/TripleEqualsSupport$Spread;
       4: aload_1
       5: invokevirtual #28                 // Method org/scalactic/TripleEqualsSupport$Spread.isWithin:(Ljava/lang/Object;)Z
       8: ireturn

  public final java.lang.Object apply(java.lang.Object);
    Code:
       0: aload_0
       1: aload_1
       2: invokevirtual #35                 // Method apply:(Ljava/lang/Object;)Z
       5: invokestatic  #41                 // Method scala/runtime/BoxesRunTime.boxToBoolean:(Z)Ljava/lang/Boolean;
       8: areturn

  public org.mockito.matchers.N$$anonfun$$eq$tilde$2(org.mockito.matchers.N, org.scalactic.TripleEqualsSupport$Spread);
    Code:
       0: aload_0
       1: aload_2
       2: putfield      #23                 // Field spread$1:Lorg/scalactic/TripleEqualsSupport$Spread;
       5: aload_0
       6: invokespecial #47                 // Method scala/runtime/AbstractFunction1."<init>":()V
       9: return
}
