Compiled from "DescriptiveStatistics.java"
public class org.apache.commons.math3.stat.descriptive.DescriptiveStatistics implements org.apache.commons.math3.stat.descriptive.StatisticalSummary,java.io.Serializable {
  public static final int INFINITE_WINDOW;

  private static final long serialVersionUID;

  private static final java.lang.String SET_QUANTILE_METHOD_NAME;

  protected int windowSize;

  private org.apache.commons.math3.util.ResizableDoubleArray eDA;

  private org.apache.commons.math3.stat.descriptive.UnivariateStatistic meanImpl;

  private org.apache.commons.math3.stat.descriptive.UnivariateStatistic geometricMeanImpl;

  private org.apache.commons.math3.stat.descriptive.UnivariateStatistic kurtosisImpl;

  private org.apache.commons.math3.stat.descriptive.UnivariateStatistic maxImpl;

  private org.apache.commons.math3.stat.descriptive.UnivariateStatistic minImpl;

  private org.apache.commons.math3.stat.descriptive.UnivariateStatistic percentileImpl;

  private org.apache.commons.math3.stat.descriptive.UnivariateStatistic skewnessImpl;

  private org.apache.commons.math3.stat.descriptive.UnivariateStatistic varianceImpl;

  private org.apache.commons.math3.stat.descriptive.UnivariateStatistic sumsqImpl;

  private org.apache.commons.math3.stat.descriptive.UnivariateStatistic sumImpl;

  public org.apache.commons.math3.stat.descriptive.DescriptiveStatistics();
    Code:
       0: aload_0
       1: invokespecial #1                  // Method java/lang/Object."<init>":()V
       4: aload_0
       5: iconst_m1
       6: putfield      #2                  // Field windowSize:I
       9: aload_0
      10: new           #3                  // class org/apache/commons/math3/util/ResizableDoubleArray
      13: dup
      14: invokespecial #4                  // Method org/apache/commons/math3/util/ResizableDoubleArray."<init>":()V
      17: putfield      #5                  // Field eDA:Lorg/apache/commons/math3/util/ResizableDoubleArray;
      20: aload_0
      21: new           #6                  // class org/apache/commons/math3/stat/descriptive/moment/Mean
      24: dup
      25: invokespecial #7                  // Method org/apache/commons/math3/stat/descriptive/moment/Mean."<init>":()V
      28: putfield      #8                  // Field meanImpl:Lorg/apache/commons/math3/stat/descriptive/UnivariateStatistic;
      31: aload_0
      32: new           #9                  // class org/apache/commons/math3/stat/descriptive/moment/GeometricMean
      35: dup
      36: invokespecial #10                 // Method org/apache/commons/math3/stat/descriptive/moment/GeometricMean."<init>":()V
      39: putfield      #11                 // Field geometricMeanImpl:Lorg/apache/commons/math3/stat/descriptive/UnivariateStatistic;
      42: aload_0
      43: new           #12                 // class org/apache/commons/math3/stat/descriptive/moment/Kurtosis
      46: dup
      47: invokespecial #13                 // Method org/apache/commons/math3/stat/descriptive/moment/Kurtosis."<init>":()V
      50: putfield      #14                 // Field kurtosisImpl:Lorg/apache/commons/math3/stat/descriptive/UnivariateStatistic;
      53: aload_0
      54: new           #15                 // class org/apache/commons/math3/stat/descriptive/rank/Max
      57: dup
      58: invokespecial #16                 // Method org/apache/commons/math3/stat/descriptive/rank/Max."<init>":()V
      61: putfield      #17                 // Field maxImpl:Lorg/apache/commons/math3/stat/descriptive/UnivariateStatistic;
      64: aload_0
      65: new           #18                 // class org/apache/commons/math3/stat/descriptive/rank/Min
      68: dup
      69: invokespecial #19                 // Method org/apache/commons/math3/stat/descriptive/rank/Min."<init>":()V
      72: putfield      #20                 // Field minImpl:Lorg/apache/commons/math3/stat/descriptive/UnivariateStatistic;
      75: aload_0
      76: new           #21                 // class org/apache/commons/math3/stat/descriptive/rank/Percentile
      79: dup
      80: invokespecial #22                 // Method org/apache/commons/math3/stat/descriptive/rank/Percentile."<init>":()V
      83: putfield      #23                 // Field percentileImpl:Lorg/apache/commons/math3/stat/descriptive/UnivariateStatistic;
      86: aload_0
      87: new           #24                 // class org/apache/commons/math3/stat/descriptive/moment/Skewness
      90: dup
      91: invokespecial #25                 // Method org/apache/commons/math3/stat/descriptive/moment/Skewness."<init>":()V
      94: putfield      #26                 // Field skewnessImpl:Lorg/apache/commons/math3/stat/descriptive/UnivariateStatistic;
      97: aload_0
      98: new           #27                 // class org/apache/commons/math3/stat/descriptive/moment/Variance
     101: dup
     102: invokespecial #28                 // Method org/apache/commons/math3/stat/descriptive/moment/Variance."<init>":()V
     105: putfield      #29                 // Field varianceImpl:Lorg/apache/commons/math3/stat/descriptive/UnivariateStatistic;
     108: aload_0
     109: new           #30                 // class org/apache/commons/math3/stat/descriptive/summary/SumOfSquares
     112: dup
     113: invokespecial #31                 // Method org/apache/commons/math3/stat/descriptive/summary/SumOfSquares."<init>":()V
     116: putfield      #32                 // Field sumsqImpl:Lorg/apache/commons/math3/stat/descriptive/UnivariateStatistic;
     119: aload_0
     120: new           #33                 // class org/apache/commons/math3/stat/descriptive/summary/Sum
     123: dup
     124: invokespecial #34                 // Method org/apache/commons/math3/stat/descriptive/summary/Sum."<init>":()V
     127: putfield      #35                 // Field sumImpl:Lorg/apache/commons/math3/stat/descriptive/UnivariateStatistic;
     130: return

  public org.apache.commons.math3.stat.descriptive.DescriptiveStatistics(int) throws org.apache.commons.math3.exception.MathIllegalArgumentException;
    Code:
       0: aload_0
       1: invokespecial #1                  // Method java/lang/Object."<init>":()V
       4: aload_0
       5: iconst_m1
       6: putfield      #2                  // Field windowSize:I
       9: aload_0
      10: new           #3                  // class org/apache/commons/math3/util/ResizableDoubleArray
      13: dup
      14: invokespecial #4                  // Method org/apache/commons/math3/util/ResizableDoubleArray."<init>":()V
      17: putfield      #5                  // Field eDA:Lorg/apache/commons/math3/util/ResizableDoubleArray;
      20: aload_0
      21: new           #6                  // class org/apache/commons/math3/stat/descriptive/moment/Mean
      24: dup
      25: invokespecial #7                  // Method org/apache/commons/math3/stat/descriptive/moment/Mean."<init>":()V
      28: putfield      #8                  // Field meanImpl:Lorg/apache/commons/math3/stat/descriptive/UnivariateStatistic;
      31: aload_0
      32: new           #9                  // class org/apache/commons/math3/stat/descriptive/moment/GeometricMean
      35: dup
      36: invokespecial #10                 // Method org/apache/commons/math3/stat/descriptive/moment/GeometricMean."<init>":()V
      39: putfield      #11                 // Field geometricMeanImpl:Lorg/apache/commons/math3/stat/descriptive/UnivariateStatistic;
      42: aload_0
      43: new           #12                 // class org/apache/commons/math3/stat/descriptive/moment/Kurtosis
      46: dup
      47: invokespecial #13                 // Method org/apache/commons/math3/stat/descriptive/moment/Kurtosis."<init>":()V
      50: putfield      #14                 // Field kurtosisImpl:Lorg/apache/commons/math3/stat/descriptive/UnivariateStatistic;
      53: aload_0
      54: new           #15                 // class org/apache/commons/math3/stat/descriptive/rank/Max
      57: dup
      58: invokespecial #16                 // Method org/apache/commons/math3/stat/descriptive/rank/Max."<init>":()V
      61: putfield      #17                 // Field maxImpl:Lorg/apache/commons/math3/stat/descriptive/UnivariateStatistic;
      64: aload_0
      65: new           #18                 // class org/apache/commons/math3/stat/descriptive/rank/Min
      68: dup
      69: invokespecial #19                 // Method org/apache/commons/math3/stat/descriptive/rank/Min."<init>":()V
      72: putfield      #20                 // Field minImpl:Lorg/apache/commons/math3/stat/descriptive/UnivariateStatistic;
      75: aload_0
      76: new           #21                 // class org/apache/commons/math3/stat/descriptive/rank/Percentile
      79: dup
      80: invokespecial #22                 // Method org/apache/commons/math3/stat/descriptive/rank/Percentile."<init>":()V
      83: putfield      #23                 // Field percentileImpl:Lorg/apache/commons/math3/stat/descriptive/UnivariateStatistic;
      86: aload_0
      87: new           #24                 // class org/apache/commons/math3/stat/descriptive/moment/Skewness
      90: dup
      91: invokespecial #25                 // Method org/apache/commons/math3/stat/descriptive/moment/Skewness."<init>":()V
      94: putfield      #26                 // Field skewnessImpl:Lorg/apache/commons/math3/stat/descriptive/UnivariateStatistic;
      97: aload_0
      98: new           #27                 // class org/apache/commons/math3/stat/descriptive/moment/Variance
     101: dup
     102: invokespecial #28                 // Method org/apache/commons/math3/stat/descriptive/moment/Variance."<init>":()V
     105: putfield      #29                 // Field varianceImpl:Lorg/apache/commons/math3/stat/descriptive/UnivariateStatistic;
     108: aload_0
     109: new           #30                 // class org/apache/commons/math3/stat/descriptive/summary/SumOfSquares
     112: dup
     113: invokespecial #31                 // Method org/apache/commons/math3/stat/descriptive/summary/SumOfSquares."<init>":()V
     116: putfield      #32                 // Field sumsqImpl:Lorg/apache/commons/math3/stat/descriptive/UnivariateStatistic;
     119: aload_0
     120: new           #33                 // class org/apache/commons/math3/stat/descriptive/summary/Sum
     123: dup
     124: invokespecial #34                 // Method org/apache/commons/math3/stat/descriptive/summary/Sum."<init>":()V
     127: putfield      #35                 // Field sumImpl:Lorg/apache/commons/math3/stat/descriptive/UnivariateStatistic;
     130: aload_0
     131: iload_1
     132: invokevirtual #36                 // Method setWindowSize:(I)V
     135: return

  public org.apache.commons.math3.stat.descriptive.DescriptiveStatistics(double[]);
    Code:
       0: aload_0
       1: invokespecial #1                  // Method java/lang/Object."<init>":()V
       4: aload_0
       5: iconst_m1
       6: putfield      #2                  // Field windowSize:I
       9: aload_0
      10: new           #3                  // class org/apache/commons/math3/util/ResizableDoubleArray
      13: dup
      14: invokespecial #4                  // Method org/apache/commons/math3/util/ResizableDoubleArray."<init>":()V
      17: putfield      #5                  // Field eDA:Lorg/apache/commons/math3/util/ResizableDoubleArray;
      20: aload_0
      21: new           #6                  // class org/apache/commons/math3/stat/descriptive/moment/Mean
      24: dup
      25: invokespecial #7                  // Method org/apache/commons/math3/stat/descriptive/moment/Mean."<init>":()V
      28: putfield      #8                  // Field meanImpl:Lorg/apache/commons/math3/stat/descriptive/UnivariateStatistic;
      31: aload_0
      32: new           #9                  // class org/apache/commons/math3/stat/descriptive/moment/GeometricMean
      35: dup
      36: invokespecial #10                 // Method org/apache/commons/math3/stat/descriptive/moment/GeometricMean."<init>":()V
      39: putfield      #11                 // Field geometricMeanImpl:Lorg/apache/commons/math3/stat/descriptive/UnivariateStatistic;
      42: aload_0
      43: new           #12                 // class org/apache/commons/math3/stat/descriptive/moment/Kurtosis
      46: dup
      47: invokespecial #13                 // Method org/apache/commons/math3/stat/descriptive/moment/Kurtosis."<init>":()V
      50: putfield      #14                 // Field kurtosisImpl:Lorg/apache/commons/math3/stat/descriptive/UnivariateStatistic;
      53: aload_0
      54: new           #15                 // class org/apache/commons/math3/stat/descriptive/rank/Max
      57: dup
      58: invokespecial #16                 // Method org/apache/commons/math3/stat/descriptive/rank/Max."<init>":()V
      61: putfield      #17                 // Field maxImpl:Lorg/apache/commons/math3/stat/descriptive/UnivariateStatistic;
      64: aload_0
      65: new           #18                 // class org/apache/commons/math3/stat/descriptive/rank/Min
      68: dup
      69: invokespecial #19                 // Method org/apache/commons/math3/stat/descriptive/rank/Min."<init>":()V
      72: putfield      #20                 // Field minImpl:Lorg/apache/commons/math3/stat/descriptive/UnivariateStatistic;
      75: aload_0
      76: new           #21                 // class org/apache/commons/math3/stat/descriptive/rank/Percentile
      79: dup
      80: invokespecial #22                 // Method org/apache/commons/math3/stat/descriptive/rank/Percentile."<init>":()V
      83: putfield      #23                 // Field percentileImpl:Lorg/apache/commons/math3/stat/descriptive/UnivariateStatistic;
      86: aload_0
      87: new           #24                 // class org/apache/commons/math3/stat/descriptive/moment/Skewness
      90: dup
      91: invokespecial #25                 // Method org/apache/commons/math3/stat/descriptive/moment/Skewness."<init>":()V
      94: putfield      #26                 // Field skewnessImpl:Lorg/apache/commons/math3/stat/descriptive/UnivariateStatistic;
      97: aload_0
      98: new           #27                 // class org/apache/commons/math3/stat/descriptive/moment/Variance
     101: dup
     102: invokespecial #28                 // Method org/apache/commons/math3/stat/descriptive/moment/Variance."<init>":()V
     105: putfield      #29                 // Field varianceImpl:Lorg/apache/commons/math3/stat/descriptive/UnivariateStatistic;
     108: aload_0
     109: new           #30                 // class org/apache/commons/math3/stat/descriptive/summary/SumOfSquares
     112: dup
     113: invokespecial #31                 // Method org/apache/commons/math3/stat/descriptive/summary/SumOfSquares."<init>":()V
     116: putfield      #32                 // Field sumsqImpl:Lorg/apache/commons/math3/stat/descriptive/UnivariateStatistic;
     119: aload_0
     120: new           #33                 // class org/apache/commons/math3/stat/descriptive/summary/Sum
     123: dup
     124: invokespecial #34                 // Method org/apache/commons/math3/stat/descriptive/summary/Sum."<init>":()V
     127: putfield      #35                 // Field sumImpl:Lorg/apache/commons/math3/stat/descriptive/UnivariateStatistic;
     130: aload_1
     131: ifnull        146
     134: aload_0
     135: new           #3                  // class org/apache/commons/math3/util/ResizableDoubleArray
     138: dup
     139: aload_1
     140: invokespecial #37                 // Method org/apache/commons/math3/util/ResizableDoubleArray."<init>":([D)V
     143: putfield      #5                  // Field eDA:Lorg/apache/commons/math3/util/ResizableDoubleArray;
     146: return

  public org.apache.commons.math3.stat.descriptive.DescriptiveStatistics(org.apache.commons.math3.stat.descriptive.DescriptiveStatistics) throws org.apache.commons.math3.exception.NullArgumentException;
    Code:
       0: aload_0
       1: invokespecial #1                  // Method java/lang/Object."<init>":()V
       4: aload_0
       5: iconst_m1
       6: putfield      #2                  // Field windowSize:I
       9: aload_0
      10: new           #3                  // class org/apache/commons/math3/util/ResizableDoubleArray
      13: dup
      14: invokespecial #4                  // Method org/apache/commons/math3/util/ResizableDoubleArray."<init>":()V
      17: putfield      #5                  // Field eDA:Lorg/apache/commons/math3/util/ResizableDoubleArray;
      20: aload_0
      21: new           #6                  // class org/apache/commons/math3/stat/descriptive/moment/Mean
      24: dup
      25: invokespecial #7                  // Method org/apache/commons/math3/stat/descriptive/moment/Mean."<init>":()V
      28: putfield      #8                  // Field meanImpl:Lorg/apache/commons/math3/stat/descriptive/UnivariateStatistic;
      31: aload_0
      32: new           #9                  // class org/apache/commons/math3/stat/descriptive/moment/GeometricMean
      35: dup
      36: invokespecial #10                 // Method org/apache/commons/math3/stat/descriptive/moment/GeometricMean."<init>":()V
      39: putfield      #11                 // Field geometricMeanImpl:Lorg/apache/commons/math3/stat/descriptive/UnivariateStatistic;
      42: aload_0
      43: new           #12                 // class org/apache/commons/math3/stat/descriptive/moment/Kurtosis
      46: dup
      47: invokespecial #13                 // Method org/apache/commons/math3/stat/descriptive/moment/Kurtosis."<init>":()V
      50: putfield      #14                 // Field kurtosisImpl:Lorg/apache/commons/math3/stat/descriptive/UnivariateStatistic;
      53: aload_0
      54: new           #15                 // class org/apache/commons/math3/stat/descriptive/rank/Max
      57: dup
      58: invokespecial #16                 // Method org/apache/commons/math3/stat/descriptive/rank/Max."<init>":()V
      61: putfield      #17                 // Field maxImpl:Lorg/apache/commons/math3/stat/descriptive/UnivariateStatistic;
      64: aload_0
      65: new           #18                 // class org/apache/commons/math3/stat/descriptive/rank/Min
      68: dup
      69: invokespecial #19                 // Method org/apache/commons/math3/stat/descriptive/rank/Min."<init>":()V
      72: putfield      #20                 // Field minImpl:Lorg/apache/commons/math3/stat/descriptive/UnivariateStatistic;
      75: aload_0
      76: new           #21                 // class org/apache/commons/math3/stat/descriptive/rank/Percentile
      79: dup
      80: invokespecial #22                 // Method org/apache/commons/math3/stat/descriptive/rank/Percentile."<init>":()V
      83: putfield      #23                 // Field percentileImpl:Lorg/apache/commons/math3/stat/descriptive/UnivariateStatistic;
      86: aload_0
      87: new           #24                 // class org/apache/commons/math3/stat/descriptive/moment/Skewness
      90: dup
      91: invokespecial #25                 // Method org/apache/commons/math3/stat/descriptive/moment/Skewness."<init>":()V
      94: putfield      #26                 // Field skewnessImpl:Lorg/apache/commons/math3/stat/descriptive/UnivariateStatistic;
      97: aload_0
      98: new           #27                 // class org/apache/commons/math3/stat/descriptive/moment/Variance
     101: dup
     102: invokespecial #28                 // Method org/apache/commons/math3/stat/descriptive/moment/Variance."<init>":()V
     105: putfield      #29                 // Field varianceImpl:Lorg/apache/commons/math3/stat/descriptive/UnivariateStatistic;
     108: aload_0
     109: new           #30                 // class org/apache/commons/math3/stat/descriptive/summary/SumOfSquares
     112: dup
     113: invokespecial #31                 // Method org/apache/commons/math3/stat/descriptive/summary/SumOfSquares."<init>":()V
     116: putfield      #32                 // Field sumsqImpl:Lorg/apache/commons/math3/stat/descriptive/UnivariateStatistic;
     119: aload_0
     120: new           #33                 // class org/apache/commons/math3/stat/descriptive/summary/Sum
     123: dup
     124: invokespecial #34                 // Method org/apache/commons/math3/stat/descriptive/summary/Sum."<init>":()V
     127: putfield      #35                 // Field sumImpl:Lorg/apache/commons/math3/stat/descriptive/UnivariateStatistic;
     130: aload_1
     131: aload_0
     132: invokestatic  #38                 // Method copy:(Lorg/apache/commons/math3/stat/descriptive/DescriptiveStatistics;Lorg/apache/commons/math3/stat/descriptive/DescriptiveStatistics;)V
     135: return

  public void addValue(double);
    Code:
       0: aload_0
       1: getfield      #2                  // Field windowSize:I
       4: iconst_m1
       5: if_icmpeq     57
       8: aload_0
       9: invokevirtual #39                 // Method getN:()J
      12: aload_0
      13: getfield      #2                  // Field windowSize:I
      16: i2l
      17: lcmp
      18: ifne          33
      21: aload_0
      22: getfield      #5                  // Field eDA:Lorg/apache/commons/math3/util/ResizableDoubleArray;
      25: dload_1
      26: invokevirtual #40                 // Method org/apache/commons/math3/util/ResizableDoubleArray.addElementRolling:(D)D
      29: pop2
      30: goto          65
      33: aload_0
      34: invokevirtual #39                 // Method getN:()J
      37: aload_0
      38: getfield      #2                  // Field windowSize:I
      41: i2l
      42: lcmp
      43: ifge          65
      46: aload_0
      47: getfield      #5                  // Field eDA:Lorg/apache/commons/math3/util/ResizableDoubleArray;
      50: dload_1
      51: invokevirtual #41                 // Method org/apache/commons/math3/util/ResizableDoubleArray.addElement:(D)V
      54: goto          65
      57: aload_0
      58: getfield      #5                  // Field eDA:Lorg/apache/commons/math3/util/ResizableDoubleArray;
      61: dload_1
      62: invokevirtual #41                 // Method org/apache/commons/math3/util/ResizableDoubleArray.addElement:(D)V
      65: return

  public void removeMostRecentValue() throws org.apache.commons.math3.exception.MathIllegalStateException;
    Code:
       0: aload_0
       1: getfield      #5                  // Field eDA:Lorg/apache/commons/math3/util/ResizableDoubleArray;
       4: iconst_1
       5: invokevirtual #42                 // Method org/apache/commons/math3/util/ResizableDoubleArray.discardMostRecentElements:(I)V
       8: goto          27
      11: astore_1
      12: new           #44                 // class org/apache/commons/math3/exception/MathIllegalStateException
      15: dup
      16: getstatic     #45                 // Field org/apache/commons/math3/exception/util/LocalizedFormats.NO_DATA:Lorg/apache/commons/math3/exception/util/LocalizedFormats;
      19: iconst_0
      20: anewarray     #46                 // class java/lang/Object
      23: invokespecial #47                 // Method org/apache/commons/math3/exception/MathIllegalStateException."<init>":(Lorg/apache/commons/math3/exception/util/Localizable;[Ljava/lang/Object;)V
      26: athrow
      27: return
    Exception table:
       from    to  target type
           0     8    11   Class org/apache/commons/math3/exception/MathIllegalArgumentException

  public double replaceMostRecentValue(double) throws org.apache.commons.math3.exception.MathIllegalStateException;
    Code:
       0: aload_0
       1: getfield      #5                  // Field eDA:Lorg/apache/commons/math3/util/ResizableDoubleArray;
       4: dload_1
       5: invokevirtual #48                 // Method org/apache/commons/math3/util/ResizableDoubleArray.substituteMostRecentElement:(D)D
       8: dreturn

  public double getMean();
    Code:
       0: aload_0
       1: aload_0
       2: getfield      #8                  // Field meanImpl:Lorg/apache/commons/math3/stat/descriptive/UnivariateStatistic;
       5: invokevirtual #49                 // Method apply:(Lorg/apache/commons/math3/stat/descriptive/UnivariateStatistic;)D
       8: dreturn

  public double getGeometricMean();
    Code:
       0: aload_0
       1: aload_0
       2: getfield      #11                 // Field geometricMeanImpl:Lorg/apache/commons/math3/stat/descriptive/UnivariateStatistic;
       5: invokevirtual #49                 // Method apply:(Lorg/apache/commons/math3/stat/descriptive/UnivariateStatistic;)D
       8: dreturn

  public double getVariance();
    Code:
       0: aload_0
       1: aload_0
       2: getfield      #29                 // Field varianceImpl:Lorg/apache/commons/math3/stat/descriptive/UnivariateStatistic;
       5: invokevirtual #49                 // Method apply:(Lorg/apache/commons/math3/stat/descriptive/UnivariateStatistic;)D
       8: dreturn

  public double getPopulationVariance();
    Code:
       0: aload_0
       1: new           #27                 // class org/apache/commons/math3/stat/descriptive/moment/Variance
       4: dup
       5: iconst_0
       6: invokespecial #50                 // Method org/apache/commons/math3/stat/descriptive/moment/Variance."<init>":(Z)V
       9: invokevirtual #49                 // Method apply:(Lorg/apache/commons/math3/stat/descriptive/UnivariateStatistic;)D
      12: dreturn

  public double getStandardDeviation();
    Code:
       0: ldc2_w        #51                 // double NaNd
       3: dstore_1
       4: aload_0
       5: invokevirtual #39                 // Method getN:()J
       8: lconst_0
       9: lcmp
      10: ifle          35
      13: aload_0
      14: invokevirtual #39                 // Method getN:()J
      17: lconst_1
      18: lcmp
      19: ifle          33
      22: aload_0
      23: invokevirtual #53                 // Method getVariance:()D
      26: invokestatic  #54                 // Method org/apache/commons/math3/util/FastMath.sqrt:(D)D
      29: dstore_1
      30: goto          35
      33: dconst_0
      34: dstore_1
      35: dload_1
      36: dreturn

  public double getQuadraticMean();
    Code:
       0: aload_0
       1: invokevirtual #39                 // Method getN:()J
       4: lstore_1
       5: lload_1
       6: lconst_0
       7: lcmp
       8: ifle          24
      11: aload_0
      12: invokevirtual #55                 // Method getSumsq:()D
      15: lload_1
      16: l2d
      17: ddiv
      18: invokestatic  #54                 // Method org/apache/commons/math3/util/FastMath.sqrt:(D)D
      21: goto          27
      24: ldc2_w        #51                 // double NaNd
      27: dreturn

  public double getSkewness();
    Code:
       0: aload_0
       1: aload_0
       2: getfield      #26                 // Field skewnessImpl:Lorg/apache/commons/math3/stat/descriptive/UnivariateStatistic;
       5: invokevirtual #49                 // Method apply:(Lorg/apache/commons/math3/stat/descriptive/UnivariateStatistic;)D
       8: dreturn

  public double getKurtosis();
    Code:
       0: aload_0
       1: aload_0
       2: getfield      #14                 // Field kurtosisImpl:Lorg/apache/commons/math3/stat/descriptive/UnivariateStatistic;
       5: invokevirtual #49                 // Method apply:(Lorg/apache/commons/math3/stat/descriptive/UnivariateStatistic;)D
       8: dreturn

  public double getMax();
    Code:
       0: aload_0
       1: aload_0
       2: getfield      #17                 // Field maxImpl:Lorg/apache/commons/math3/stat/descriptive/UnivariateStatistic;
       5: invokevirtual #49                 // Method apply:(Lorg/apache/commons/math3/stat/descriptive/UnivariateStatistic;)D
       8: dreturn

  public double getMin();
    Code:
       0: aload_0
       1: aload_0
       2: getfield      #20                 // Field minImpl:Lorg/apache/commons/math3/stat/descriptive/UnivariateStatistic;
       5: invokevirtual #49                 // Method apply:(Lorg/apache/commons/math3/stat/descriptive/UnivariateStatistic;)D
       8: dreturn

  public long getN();
    Code:
       0: aload_0
       1: getfield      #5                  // Field eDA:Lorg/apache/commons/math3/util/ResizableDoubleArray;
       4: invokevirtual #56                 // Method org/apache/commons/math3/util/ResizableDoubleArray.getNumElements:()I
       7: i2l
       8: lreturn

  public double getSum();
    Code:
       0: aload_0
       1: aload_0
       2: getfield      #35                 // Field sumImpl:Lorg/apache/commons/math3/stat/descriptive/UnivariateStatistic;
       5: invokevirtual #49                 // Method apply:(Lorg/apache/commons/math3/stat/descriptive/UnivariateStatistic;)D
       8: dreturn

  public double getSumsq();
    Code:
       0: aload_0
       1: aload_0
       2: getfield      #32                 // Field sumsqImpl:Lorg/apache/commons/math3/stat/descriptive/UnivariateStatistic;
       5: invokevirtual #49                 // Method apply:(Lorg/apache/commons/math3/stat/descriptive/UnivariateStatistic;)D
       8: dreturn

  public void clear();
    Code:
       0: aload_0
       1: getfield      #5                  // Field eDA:Lorg/apache/commons/math3/util/ResizableDoubleArray;
       4: invokevirtual #57                 // Method org/apache/commons/math3/util/ResizableDoubleArray.clear:()V
       7: return

  public int getWindowSize();
    Code:
       0: aload_0
       1: getfield      #2                  // Field windowSize:I
       4: ireturn

  public void setWindowSize(int) throws org.apache.commons.math3.exception.MathIllegalArgumentException;
    Code:
       0: iload_1
       1: iconst_1
       2: if_icmpge     32
       5: iload_1
       6: iconst_m1
       7: if_icmpeq     32
      10: new           #43                 // class org/apache/commons/math3/exception/MathIllegalArgumentException
      13: dup
      14: getstatic     #58                 // Field org/apache/commons/math3/exception/util/LocalizedFormats.NOT_POSITIVE_WINDOW_SIZE:Lorg/apache/commons/math3/exception/util/LocalizedFormats;
      17: iconst_1
      18: anewarray     #46                 // class java/lang/Object
      21: dup
      22: iconst_0
      23: iload_1
      24: invokestatic  #59                 // Method java/lang/Integer.valueOf:(I)Ljava/lang/Integer;
      27: aastore
      28: invokespecial #60                 // Method org/apache/commons/math3/exception/MathIllegalArgumentException."<init>":(Lorg/apache/commons/math3/exception/util/Localizable;[Ljava/lang/Object;)V
      31: athrow
      32: aload_0
      33: iload_1
      34: putfield      #2                  // Field windowSize:I
      37: iload_1
      38: iconst_m1
      39: if_icmpeq     69
      42: iload_1
      43: aload_0
      44: getfield      #5                  // Field eDA:Lorg/apache/commons/math3/util/ResizableDoubleArray;
      47: invokevirtual #56                 // Method org/apache/commons/math3/util/ResizableDoubleArray.getNumElements:()I
      50: if_icmpge     69
      53: aload_0
      54: getfield      #5                  // Field eDA:Lorg/apache/commons/math3/util/ResizableDoubleArray;
      57: aload_0
      58: getfield      #5                  // Field eDA:Lorg/apache/commons/math3/util/ResizableDoubleArray;
      61: invokevirtual #56                 // Method org/apache/commons/math3/util/ResizableDoubleArray.getNumElements:()I
      64: iload_1
      65: isub
      66: invokevirtual #61                 // Method org/apache/commons/math3/util/ResizableDoubleArray.discardFrontElements:(I)V
      69: return

  public double[] getValues();
    Code:
       0: aload_0
       1: getfield      #5                  // Field eDA:Lorg/apache/commons/math3/util/ResizableDoubleArray;
       4: invokevirtual #62                 // Method org/apache/commons/math3/util/ResizableDoubleArray.getElements:()[D
       7: areturn

  public double[] getSortedValues();
    Code:
       0: aload_0
       1: invokevirtual #63                 // Method getValues:()[D
       4: astore_1
       5: aload_1
       6: invokestatic  #64                 // Method java/util/Arrays.sort:([D)V
       9: aload_1
      10: areturn

  public double getElement(int);
    Code:
       0: aload_0
       1: getfield      #5                  // Field eDA:Lorg/apache/commons/math3/util/ResizableDoubleArray;
       4: iload_1
       5: invokevirtual #65                 // Method org/apache/commons/math3/util/ResizableDoubleArray.getElement:(I)D
       8: dreturn

  public double getPercentile(double) throws org.apache.commons.math3.exception.MathIllegalStateException, org.apache.commons.math3.exception.MathIllegalArgumentException;
    Code:
       0: aload_0
       1: getfield      #23                 // Field percentileImpl:Lorg/apache/commons/math3/stat/descriptive/UnivariateStatistic;
       4: instanceof    #21                 // class org/apache/commons/math3/stat/descriptive/rank/Percentile
       7: ifeq          24
      10: aload_0
      11: getfield      #23                 // Field percentileImpl:Lorg/apache/commons/math3/stat/descriptive/UnivariateStatistic;
      14: checkcast     #21                 // class org/apache/commons/math3/stat/descriptive/rank/Percentile
      17: dload_1
      18: invokevirtual #66                 // Method org/apache/commons/math3/stat/descriptive/rank/Percentile.setQuantile:(D)V
      21: goto          149
      24: aload_0
      25: getfield      #23                 // Field percentileImpl:Lorg/apache/commons/math3/stat/descriptive/UnivariateStatistic;
      28: invokevirtual #67                 // Method java/lang/Object.getClass:()Ljava/lang/Class;
      31: ldc           #68                 // String setQuantile
      33: iconst_1
      34: anewarray     #69                 // class java/lang/Class
      37: dup
      38: iconst_0
      39: getstatic     #70                 // Field java/lang/Double.TYPE:Ljava/lang/Class;
      42: aastore
      43: invokevirtual #71                 // Method java/lang/Class.getMethod:(Ljava/lang/String;[Ljava/lang/Class;)Ljava/lang/reflect/Method;
      46: aload_0
      47: getfield      #23                 // Field percentileImpl:Lorg/apache/commons/math3/stat/descriptive/UnivariateStatistic;
      50: iconst_1
      51: anewarray     #46                 // class java/lang/Object
      54: dup
      55: iconst_0
      56: dload_1
      57: invokestatic  #72                 // Method java/lang/Double.valueOf:(D)Ljava/lang/Double;
      60: aastore
      61: invokevirtual #73                 // Method java/lang/reflect/Method.invoke:(Ljava/lang/Object;[Ljava/lang/Object;)Ljava/lang/Object;
      64: pop
      65: goto          149
      68: astore_3
      69: new           #44                 // class org/apache/commons/math3/exception/MathIllegalStateException
      72: dup
      73: getstatic     #75                 // Field org/apache/commons/math3/exception/util/LocalizedFormats.PERCENTILE_IMPLEMENTATION_UNSUPPORTED_METHOD:Lorg/apache/commons/math3/exception/util/LocalizedFormats;
      76: iconst_2
      77: anewarray     #46                 // class java/lang/Object
      80: dup
      81: iconst_0
      82: aload_0
      83: getfield      #23                 // Field percentileImpl:Lorg/apache/commons/math3/stat/descriptive/UnivariateStatistic;
      86: invokevirtual #67                 // Method java/lang/Object.getClass:()Ljava/lang/Class;
      89: invokevirtual #76                 // Method java/lang/Class.getName:()Ljava/lang/String;
      92: aastore
      93: dup
      94: iconst_1
      95: ldc           #68                 // String setQuantile
      97: aastore
      98: invokespecial #47                 // Method org/apache/commons/math3/exception/MathIllegalStateException."<init>":(Lorg/apache/commons/math3/exception/util/Localizable;[Ljava/lang/Object;)V
     101: athrow
     102: astore_3
     103: new           #44                 // class org/apache/commons/math3/exception/MathIllegalStateException
     106: dup
     107: getstatic     #78                 // Field org/apache/commons/math3/exception/util/LocalizedFormats.PERCENTILE_IMPLEMENTATION_CANNOT_ACCESS_METHOD:Lorg/apache/commons/math3/exception/util/LocalizedFormats;
     110: iconst_2
     111: anewarray     #46                 // class java/lang/Object
     114: dup
     115: iconst_0
     116: ldc           #68                 // String setQuantile
     118: aastore
     119: dup
     120: iconst_1
     121: aload_0
     122: getfield      #23                 // Field percentileImpl:Lorg/apache/commons/math3/stat/descriptive/UnivariateStatistic;
     125: invokevirtual #67                 // Method java/lang/Object.getClass:()Ljava/lang/Class;
     128: invokevirtual #76                 // Method java/lang/Class.getName:()Ljava/lang/String;
     131: aastore
     132: invokespecial #47                 // Method org/apache/commons/math3/exception/MathIllegalStateException."<init>":(Lorg/apache/commons/math3/exception/util/Localizable;[Ljava/lang/Object;)V
     135: athrow
     136: astore_3
     137: new           #80                 // class java/lang/IllegalStateException
     140: dup
     141: aload_3
     142: invokevirtual #81                 // Method java/lang/reflect/InvocationTargetException.getCause:()Ljava/lang/Throwable;
     145: invokespecial #82                 // Method java/lang/IllegalStateException."<init>":(Ljava/lang/Throwable;)V
     148: athrow
     149: aload_0
     150: aload_0
     151: getfield      #23                 // Field percentileImpl:Lorg/apache/commons/math3/stat/descriptive/UnivariateStatistic;
     154: invokevirtual #49                 // Method apply:(Lorg/apache/commons/math3/stat/descriptive/UnivariateStatistic;)D
     157: dreturn
    Exception table:
       from    to  target type
          24    65    68   Class java/lang/NoSuchMethodException
          24    65   102   Class java/lang/IllegalAccessException
          24    65   136   Class java/lang/reflect/InvocationTargetException

  public java.lang.String toString();
    Code:
       0: new           #83                 // class java/lang/StringBuilder
       3: dup
       4: invokespecial #84                 // Method java/lang/StringBuilder."<init>":()V
       7: astore_1
       8: ldc           #85                 // String \n
      10: astore_2
      11: aload_1
      12: ldc           #86                 // String DescriptiveStatistics:
      14: invokevirtual #87                 // Method java/lang/StringBuilder.append:(Ljava/lang/String;)Ljava/lang/StringBuilder;
      17: aload_2
      18: invokevirtual #87                 // Method java/lang/StringBuilder.append:(Ljava/lang/String;)Ljava/lang/StringBuilder;
      21: pop
      22: aload_1
      23: ldc           #88                 // String n:
      25: invokevirtual #87                 // Method java/lang/StringBuilder.append:(Ljava/lang/String;)Ljava/lang/StringBuilder;
      28: aload_0
      29: invokevirtual #39                 // Method getN:()J
      32: invokevirtual #89                 // Method java/lang/StringBuilder.append:(J)Ljava/lang/StringBuilder;
      35: aload_2
      36: invokevirtual #87                 // Method java/lang/StringBuilder.append:(Ljava/lang/String;)Ljava/lang/StringBuilder;
      39: pop
      40: aload_1
      41: ldc           #90                 // String min:
      43: invokevirtual #87                 // Method java/lang/StringBuilder.append:(Ljava/lang/String;)Ljava/lang/StringBuilder;
      46: aload_0
      47: invokevirtual #91                 // Method getMin:()D
      50: invokevirtual #92                 // Method java/lang/StringBuilder.append:(D)Ljava/lang/StringBuilder;
      53: aload_2
      54: invokevirtual #87                 // Method java/lang/StringBuilder.append:(Ljava/lang/String;)Ljava/lang/StringBuilder;
      57: pop
      58: aload_1
      59: ldc           #93                 // String max:
      61: invokevirtual #87                 // Method java/lang/StringBuilder.append:(Ljava/lang/String;)Ljava/lang/StringBuilder;
      64: aload_0
      65: invokevirtual #94                 // Method getMax:()D
      68: invokevirtual #92                 // Method java/lang/StringBuilder.append:(D)Ljava/lang/StringBuilder;
      71: aload_2
      72: invokevirtual #87                 // Method java/lang/StringBuilder.append:(Ljava/lang/String;)Ljava/lang/StringBuilder;
      75: pop
      76: aload_1
      77: ldc           #95                 // String mean:
      79: invokevirtual #87                 // Method java/lang/StringBuilder.append:(Ljava/lang/String;)Ljava/lang/StringBuilder;
      82: aload_0
      83: invokevirtual #96                 // Method getMean:()D
      86: invokevirtual #92                 // Method java/lang/StringBuilder.append:(D)Ljava/lang/StringBuilder;
      89: aload_2
      90: invokevirtual #87                 // Method java/lang/StringBuilder.append:(Ljava/lang/String;)Ljava/lang/StringBuilder;
      93: pop
      94: aload_1
      95: ldc           #97                 // String std dev:
      97: invokevirtual #87                 // Method java/lang/StringBuilder.append:(Ljava/lang/String;)Ljava/lang/StringBuilder;
     100: aload_0
     101: invokevirtual #98                 // Method getStandardDeviation:()D
     104: invokevirtual #92                 // Method java/lang/StringBuilder.append:(D)Ljava/lang/StringBuilder;
     107: aload_2
     108: invokevirtual #87                 // Method java/lang/StringBuilder.append:(Ljava/lang/String;)Ljava/lang/StringBuilder;
     111: pop
     112: aload_1
     113: ldc           #99                 // String median:
     115: invokevirtual #87                 // Method java/lang/StringBuilder.append:(Ljava/lang/String;)Ljava/lang/StringBuilder;
     118: aload_0
     119: ldc2_w        #100                // double 50.0d
     122: invokevirtual #102                // Method getPercentile:(D)D
     125: invokevirtual #92                 // Method java/lang/StringBuilder.append:(D)Ljava/lang/StringBuilder;
     128: aload_2
     129: invokevirtual #87                 // Method java/lang/StringBuilder.append:(Ljava/lang/String;)Ljava/lang/StringBuilder;
     132: pop
     133: goto          148
     136: astore_3
     137: aload_1
     138: ldc           #103                // String median: unavailable
     140: invokevirtual #87                 // Method java/lang/StringBuilder.append:(Ljava/lang/String;)Ljava/lang/StringBuilder;
     143: aload_2
     144: invokevirtual #87                 // Method java/lang/StringBuilder.append:(Ljava/lang/String;)Ljava/lang/StringBuilder;
     147: pop
     148: aload_1
     149: ldc           #104                // String skewness:
     151: invokevirtual #87                 // Method java/lang/StringBuilder.append:(Ljava/lang/String;)Ljava/lang/StringBuilder;
     154: aload_0
     155: invokevirtual #105                // Method getSkewness:()D
     158: invokevirtual #92                 // Method java/lang/StringBuilder.append:(D)Ljava/lang/StringBuilder;
     161: aload_2
     162: invokevirtual #87                 // Method java/lang/StringBuilder.append:(Ljava/lang/String;)Ljava/lang/StringBuilder;
     165: pop
     166: aload_1
     167: ldc           #106                // String kurtosis:
     169: invokevirtual #87                 // Method java/lang/StringBuilder.append:(Ljava/lang/String;)Ljava/lang/StringBuilder;
     172: aload_0
     173: invokevirtual #107                // Method getKurtosis:()D
     176: invokevirtual #92                 // Method java/lang/StringBuilder.append:(D)Ljava/lang/StringBuilder;
     179: aload_2
     180: invokevirtual #87                 // Method java/lang/StringBuilder.append:(Ljava/lang/String;)Ljava/lang/StringBuilder;
     183: pop
     184: aload_1
     185: invokevirtual #108                // Method java/lang/StringBuilder.toString:()Ljava/lang/String;
     188: areturn
    Exception table:
       from    to  target type
         112   133   136   Class org/apache/commons/math3/exception/MathIllegalStateException

  public double apply(org.apache.commons.math3.stat.descriptive.UnivariateStatistic);
    Code:
       0: aload_0
       1: getfield      #5                  // Field eDA:Lorg/apache/commons/math3/util/ResizableDoubleArray;
       4: aload_1
       5: invokevirtual #109                // Method org/apache/commons/math3/util/ResizableDoubleArray.compute:(Lorg/apache/commons/math3/util/MathArrays$Function;)D
       8: dreturn

  public synchronized org.apache.commons.math3.stat.descriptive.UnivariateStatistic getMeanImpl();
    Code:
       0: aload_0
       1: getfield      #8                  // Field meanImpl:Lorg/apache/commons/math3/stat/descriptive/UnivariateStatistic;
       4: areturn

  public synchronized void setMeanImpl(org.apache.commons.math3.stat.descriptive.UnivariateStatistic);
    Code:
       0: aload_0
       1: aload_1
       2: putfield      #8                  // Field meanImpl:Lorg/apache/commons/math3/stat/descriptive/UnivariateStatistic;
       5: return

  public synchronized org.apache.commons.math3.stat.descriptive.UnivariateStatistic getGeometricMeanImpl();
    Code:
       0: aload_0
       1: getfield      #11                 // Field geometricMeanImpl:Lorg/apache/commons/math3/stat/descriptive/UnivariateStatistic;
       4: areturn

  public synchronized void setGeometricMeanImpl(org.apache.commons.math3.stat.descriptive.UnivariateStatistic);
    Code:
       0: aload_0
       1: aload_1
       2: putfield      #11                 // Field geometricMeanImpl:Lorg/apache/commons/math3/stat/descriptive/UnivariateStatistic;
       5: return

  public synchronized org.apache.commons.math3.stat.descriptive.UnivariateStatistic getKurtosisImpl();
    Code:
       0: aload_0
       1: getfield      #14                 // Field kurtosisImpl:Lorg/apache/commons/math3/stat/descriptive/UnivariateStatistic;
       4: areturn

  public synchronized void setKurtosisImpl(org.apache.commons.math3.stat.descriptive.UnivariateStatistic);
    Code:
       0: aload_0
       1: aload_1
       2: putfield      #14                 // Field kurtosisImpl:Lorg/apache/commons/math3/stat/descriptive/UnivariateStatistic;
       5: return

  public synchronized org.apache.commons.math3.stat.descriptive.UnivariateStatistic getMaxImpl();
    Code:
       0: aload_0
       1: getfield      #17                 // Field maxImpl:Lorg/apache/commons/math3/stat/descriptive/UnivariateStatistic;
       4: areturn

  public synchronized void setMaxImpl(org.apache.commons.math3.stat.descriptive.UnivariateStatistic);
    Code:
       0: aload_0
       1: aload_1
       2: putfield      #17                 // Field maxImpl:Lorg/apache/commons/math3/stat/descriptive/UnivariateStatistic;
       5: return

  public synchronized org.apache.commons.math3.stat.descriptive.UnivariateStatistic getMinImpl();
    Code:
       0: aload_0
       1: getfield      #20                 // Field minImpl:Lorg/apache/commons/math3/stat/descriptive/UnivariateStatistic;
       4: areturn

  public synchronized void setMinImpl(org.apache.commons.math3.stat.descriptive.UnivariateStatistic);
    Code:
       0: aload_0
       1: aload_1
       2: putfield      #20                 // Field minImpl:Lorg/apache/commons/math3/stat/descriptive/UnivariateStatistic;
       5: return

  public synchronized org.apache.commons.math3.stat.descriptive.UnivariateStatistic getPercentileImpl();
    Code:
       0: aload_0
       1: getfield      #23                 // Field percentileImpl:Lorg/apache/commons/math3/stat/descriptive/UnivariateStatistic;
       4: areturn

  public synchronized void setPercentileImpl(org.apache.commons.math3.stat.descriptive.UnivariateStatistic) throws org.apache.commons.math3.exception.MathIllegalArgumentException;
    Code:
       0: aload_1
       1: invokevirtual #67                 // Method java/lang/Object.getClass:()Ljava/lang/Class;
       4: ldc           #68                 // String setQuantile
       6: iconst_1
       7: anewarray     #69                 // class java/lang/Class
      10: dup
      11: iconst_0
      12: getstatic     #70                 // Field java/lang/Double.TYPE:Ljava/lang/Class;
      15: aastore
      16: invokevirtual #71                 // Method java/lang/Class.getMethod:(Ljava/lang/String;[Ljava/lang/Class;)Ljava/lang/reflect/Method;
      19: aload_1
      20: iconst_1
      21: anewarray     #46                 // class java/lang/Object
      24: dup
      25: iconst_0
      26: ldc2_w        #100                // double 50.0d
      29: invokestatic  #72                 // Method java/lang/Double.valueOf:(D)Ljava/lang/Double;
      32: aastore
      33: invokevirtual #73                 // Method java/lang/reflect/Method.invoke:(Ljava/lang/Object;[Ljava/lang/Object;)Ljava/lang/Object;
      36: pop
      37: goto          115
      40: astore_2
      41: new           #43                 // class org/apache/commons/math3/exception/MathIllegalArgumentException
      44: dup
      45: getstatic     #75                 // Field org/apache/commons/math3/exception/util/LocalizedFormats.PERCENTILE_IMPLEMENTATION_UNSUPPORTED_METHOD:Lorg/apache/commons/math3/exception/util/LocalizedFormats;
      48: iconst_2
      49: anewarray     #46                 // class java/lang/Object
      52: dup
      53: iconst_0
      54: aload_1
      55: invokevirtual #67                 // Method java/lang/Object.getClass:()Ljava/lang/Class;
      58: invokevirtual #76                 // Method java/lang/Class.getName:()Ljava/lang/String;
      61: aastore
      62: dup
      63: iconst_1
      64: ldc           #68                 // String setQuantile
      66: aastore
      67: invokespecial #60                 // Method org/apache/commons/math3/exception/MathIllegalArgumentException."<init>":(Lorg/apache/commons/math3/exception/util/Localizable;[Ljava/lang/Object;)V
      70: athrow
      71: astore_2
      72: new           #43                 // class org/apache/commons/math3/exception/MathIllegalArgumentException
      75: dup
      76: getstatic     #78                 // Field org/apache/commons/math3/exception/util/LocalizedFormats.PERCENTILE_IMPLEMENTATION_CANNOT_ACCESS_METHOD:Lorg/apache/commons/math3/exception/util/LocalizedFormats;
      79: iconst_2
      80: anewarray     #46                 // class java/lang/Object
      83: dup
      84: iconst_0
      85: ldc           #68                 // String setQuantile
      87: aastore
      88: dup
      89: iconst_1
      90: aload_1
      91: invokevirtual #67                 // Method java/lang/Object.getClass:()Ljava/lang/Class;
      94: invokevirtual #76                 // Method java/lang/Class.getName:()Ljava/lang/String;
      97: aastore
      98: invokespecial #60                 // Method org/apache/commons/math3/exception/MathIllegalArgumentException."<init>":(Lorg/apache/commons/math3/exception/util/Localizable;[Ljava/lang/Object;)V
     101: athrow
     102: astore_2
     103: new           #110                // class java/lang/IllegalArgumentException
     106: dup
     107: aload_2
     108: invokevirtual #81                 // Method java/lang/reflect/InvocationTargetException.getCause:()Ljava/lang/Throwable;
     111: invokespecial #111                // Method java/lang/IllegalArgumentException."<init>":(Ljava/lang/Throwable;)V
     114: athrow
     115: aload_0
     116: aload_1
     117: putfield      #23                 // Field percentileImpl:Lorg/apache/commons/math3/stat/descriptive/UnivariateStatistic;
     120: return
    Exception table:
       from    to  target type
           0    37    40   Class java/lang/NoSuchMethodException
           0    37    71   Class java/lang/IllegalAccessException
           0    37   102   Class java/lang/reflect/InvocationTargetException

  public synchronized org.apache.commons.math3.stat.descriptive.UnivariateStatistic getSkewnessImpl();
    Code:
       0: aload_0
       1: getfield      #26                 // Field skewnessImpl:Lorg/apache/commons/math3/stat/descriptive/UnivariateStatistic;
       4: areturn

  public synchronized void setSkewnessImpl(org.apache.commons.math3.stat.descriptive.UnivariateStatistic);
    Code:
       0: aload_0
       1: aload_1
       2: putfield      #26                 // Field skewnessImpl:Lorg/apache/commons/math3/stat/descriptive/UnivariateStatistic;
       5: return

  public synchronized org.apache.commons.math3.stat.descriptive.UnivariateStatistic getVarianceImpl();
    Code:
       0: aload_0
       1: getfield      #29                 // Field varianceImpl:Lorg/apache/commons/math3/stat/descriptive/UnivariateStatistic;
       4: areturn

  public synchronized void setVarianceImpl(org.apache.commons.math3.stat.descriptive.UnivariateStatistic);
    Code:
       0: aload_0
       1: aload_1
       2: putfield      #29                 // Field varianceImpl:Lorg/apache/commons/math3/stat/descriptive/UnivariateStatistic;
       5: return

  public synchronized org.apache.commons.math3.stat.descriptive.UnivariateStatistic getSumsqImpl();
    Code:
       0: aload_0
       1: getfield      #32                 // Field sumsqImpl:Lorg/apache/commons/math3/stat/descriptive/UnivariateStatistic;
       4: areturn

  public synchronized void setSumsqImpl(org.apache.commons.math3.stat.descriptive.UnivariateStatistic);
    Code:
       0: aload_0
       1: aload_1
       2: putfield      #32                 // Field sumsqImpl:Lorg/apache/commons/math3/stat/descriptive/UnivariateStatistic;
       5: return

  public synchronized org.apache.commons.math3.stat.descriptive.UnivariateStatistic getSumImpl();
    Code:
       0: aload_0
       1: getfield      #35                 // Field sumImpl:Lorg/apache/commons/math3/stat/descriptive/UnivariateStatistic;
       4: areturn

  public synchronized void setSumImpl(org.apache.commons.math3.stat.descriptive.UnivariateStatistic);
    Code:
       0: aload_0
       1: aload_1
       2: putfield      #35                 // Field sumImpl:Lorg/apache/commons/math3/stat/descriptive/UnivariateStatistic;
       5: return

  public org.apache.commons.math3.stat.descriptive.DescriptiveStatistics copy();
    Code:
       0: new           #112                // class org/apache/commons/math3/stat/descriptive/DescriptiveStatistics
       3: dup
       4: invokespecial #113                // Method "<init>":()V
       7: astore_1
       8: aload_0
       9: aload_1
      10: invokestatic  #38                 // Method copy:(Lorg/apache/commons/math3/stat/descriptive/DescriptiveStatistics;Lorg/apache/commons/math3/stat/descriptive/DescriptiveStatistics;)V
      13: aload_1
      14: areturn

  public static void copy(org.apache.commons.math3.stat.descriptive.DescriptiveStatistics, org.apache.commons.math3.stat.descriptive.DescriptiveStatistics) throws org.apache.commons.math3.exception.NullArgumentException;
    Code:
       0: aload_0
       1: invokestatic  #114                // Method org/apache/commons/math3/util/MathUtils.checkNotNull:(Ljava/lang/Object;)V
       4: aload_1
       5: invokestatic  #114                // Method org/apache/commons/math3/util/MathUtils.checkNotNull:(Ljava/lang/Object;)V
       8: aload_1
       9: aload_0
      10: getfield      #5                  // Field eDA:Lorg/apache/commons/math3/util/ResizableDoubleArray;
      13: invokevirtual #115                // Method org/apache/commons/math3/util/ResizableDoubleArray.copy:()Lorg/apache/commons/math3/util/ResizableDoubleArray;
      16: putfield      #5                  // Field eDA:Lorg/apache/commons/math3/util/ResizableDoubleArray;
      19: aload_1
      20: aload_0
      21: getfield      #2                  // Field windowSize:I
      24: putfield      #2                  // Field windowSize:I
      27: aload_1
      28: aload_0
      29: getfield      #17                 // Field maxImpl:Lorg/apache/commons/math3/stat/descriptive/UnivariateStatistic;
      32: invokeinterface #116,  1          // InterfaceMethod org/apache/commons/math3/stat/descriptive/UnivariateStatistic.copy:()Lorg/apache/commons/math3/stat/descriptive/UnivariateStatistic;
      37: putfield      #17                 // Field maxImpl:Lorg/apache/commons/math3/stat/descriptive/UnivariateStatistic;
      40: aload_1
      41: aload_0
      42: getfield      #8                  // Field meanImpl:Lorg/apache/commons/math3/stat/descriptive/UnivariateStatistic;
      45: invokeinterface #116,  1          // InterfaceMethod org/apache/commons/math3/stat/descriptive/UnivariateStatistic.copy:()Lorg/apache/commons/math3/stat/descriptive/UnivariateStatistic;
      50: putfield      #8                  // Field meanImpl:Lorg/apache/commons/math3/stat/descriptive/UnivariateStatistic;
      53: aload_1
      54: aload_0
      55: getfield      #20                 // Field minImpl:Lorg/apache/commons/math3/stat/descriptive/UnivariateStatistic;
      58: invokeinterface #116,  1          // InterfaceMethod org/apache/commons/math3/stat/descriptive/UnivariateStatistic.copy:()Lorg/apache/commons/math3/stat/descriptive/UnivariateStatistic;
      63: putfield      #20                 // Field minImpl:Lorg/apache/commons/math3/stat/descriptive/UnivariateStatistic;
      66: aload_1
      67: aload_0
      68: getfield      #35                 // Field sumImpl:Lorg/apache/commons/math3/stat/descriptive/UnivariateStatistic;
      71: invokeinterface #116,  1          // InterfaceMethod org/apache/commons/math3/stat/descriptive/UnivariateStatistic.copy:()Lorg/apache/commons/math3/stat/descriptive/UnivariateStatistic;
      76: putfield      #35                 // Field sumImpl:Lorg/apache/commons/math3/stat/descriptive/UnivariateStatistic;
      79: aload_1
      80: aload_0
      81: getfield      #29                 // Field varianceImpl:Lorg/apache/commons/math3/stat/descriptive/UnivariateStatistic;
      84: invokeinterface #116,  1          // InterfaceMethod org/apache/commons/math3/stat/descriptive/UnivariateStatistic.copy:()Lorg/apache/commons/math3/stat/descriptive/UnivariateStatistic;
      89: putfield      #29                 // Field varianceImpl:Lorg/apache/commons/math3/stat/descriptive/UnivariateStatistic;
      92: aload_1
      93: aload_0
      94: getfield      #32                 // Field sumsqImpl:Lorg/apache/commons/math3/stat/descriptive/UnivariateStatistic;
      97: invokeinterface #116,  1          // InterfaceMethod org/apache/commons/math3/stat/descriptive/UnivariateStatistic.copy:()Lorg/apache/commons/math3/stat/descriptive/UnivariateStatistic;
     102: putfield      #32                 // Field sumsqImpl:Lorg/apache/commons/math3/stat/descriptive/UnivariateStatistic;
     105: aload_1
     106: aload_0
     107: getfield      #11                 // Field geometricMeanImpl:Lorg/apache/commons/math3/stat/descriptive/UnivariateStatistic;
     110: invokeinterface #116,  1          // InterfaceMethod org/apache/commons/math3/stat/descriptive/UnivariateStatistic.copy:()Lorg/apache/commons/math3/stat/descriptive/UnivariateStatistic;
     115: putfield      #11                 // Field geometricMeanImpl:Lorg/apache/commons/math3/stat/descriptive/UnivariateStatistic;
     118: aload_1
     119: aload_0
     120: getfield      #14                 // Field kurtosisImpl:Lorg/apache/commons/math3/stat/descriptive/UnivariateStatistic;
     123: putfield      #14                 // Field kurtosisImpl:Lorg/apache/commons/math3/stat/descriptive/UnivariateStatistic;
     126: aload_1
     127: aload_0
     128: getfield      #26                 // Field skewnessImpl:Lorg/apache/commons/math3/stat/descriptive/UnivariateStatistic;
     131: putfield      #26                 // Field skewnessImpl:Lorg/apache/commons/math3/stat/descriptive/UnivariateStatistic;
     134: aload_1
     135: aload_0
     136: getfield      #23                 // Field percentileImpl:Lorg/apache/commons/math3/stat/descriptive/UnivariateStatistic;
     139: putfield      #23                 // Field percentileImpl:Lorg/apache/commons/math3/stat/descriptive/UnivariateStatistic;
     142: return
}
