Compiled from "SynchronizedDescriptiveStatistics.java"
public class org.apache.commons.math3.stat.descriptive.SynchronizedDescriptiveStatistics extends org.apache.commons.math3.stat.descriptive.DescriptiveStatistics {
  private static final long serialVersionUID;

  public org.apache.commons.math3.stat.descriptive.SynchronizedDescriptiveStatistics();
    Code:
       0: aload_0
       1: iconst_m1
       2: invokespecial #1                  // Method "<init>":(I)V
       5: return

  public org.apache.commons.math3.stat.descriptive.SynchronizedDescriptiveStatistics(int) throws org.apache.commons.math3.exception.MathIllegalArgumentException;
    Code:
       0: aload_0
       1: iload_1
       2: invokespecial #2                  // Method org/apache/commons/math3/stat/descriptive/DescriptiveStatistics."<init>":(I)V
       5: return

  public org.apache.commons.math3.stat.descriptive.SynchronizedDescriptiveStatistics(org.apache.commons.math3.stat.descriptive.SynchronizedDescriptiveStatistics) throws org.apache.commons.math3.exception.NullArgumentException;
    Code:
       0: aload_0
       1: invokespecial #3                  // Method org/apache/commons/math3/stat/descriptive/DescriptiveStatistics."<init>":()V
       4: aload_1
       5: aload_0
       6: invokestatic  #4                  // Method copy:(Lorg/apache/commons/math3/stat/descriptive/SynchronizedDescriptiveStatistics;Lorg/apache/commons/math3/stat/descriptive/SynchronizedDescriptiveStatistics;)V
       9: return

  public synchronized void addValue(double);
    Code:
       0: aload_0
       1: dload_1
       2: invokespecial #5                  // Method org/apache/commons/math3/stat/descriptive/DescriptiveStatistics.addValue:(D)V
       5: return

  public synchronized double apply(org.apache.commons.math3.stat.descriptive.UnivariateStatistic);
    Code:
       0: aload_0
       1: aload_1
       2: invokespecial #6                  // Method org/apache/commons/math3/stat/descriptive/DescriptiveStatistics.apply:(Lorg/apache/commons/math3/stat/descriptive/UnivariateStatistic;)D
       5: dreturn

  public synchronized void clear();
    Code:
       0: aload_0
       1: invokespecial #7                  // Method org/apache/commons/math3/stat/descriptive/DescriptiveStatistics.clear:()V
       4: return

  public synchronized double getElement(int);
    Code:
       0: aload_0
       1: iload_1
       2: invokespecial #8                  // Method org/apache/commons/math3/stat/descriptive/DescriptiveStatistics.getElement:(I)D
       5: dreturn

  public synchronized long getN();
    Code:
       0: aload_0
       1: invokespecial #9                  // Method org/apache/commons/math3/stat/descriptive/DescriptiveStatistics.getN:()J
       4: lreturn

  public synchronized double getStandardDeviation();
    Code:
       0: aload_0
       1: invokespecial #10                 // Method org/apache/commons/math3/stat/descriptive/DescriptiveStatistics.getStandardDeviation:()D
       4: dreturn

  public synchronized double getQuadraticMean();
    Code:
       0: aload_0
       1: invokespecial #11                 // Method org/apache/commons/math3/stat/descriptive/DescriptiveStatistics.getQuadraticMean:()D
       4: dreturn

  public synchronized double[] getValues();
    Code:
       0: aload_0
       1: invokespecial #12                 // Method org/apache/commons/math3/stat/descriptive/DescriptiveStatistics.getValues:()[D
       4: areturn

  public synchronized int getWindowSize();
    Code:
       0: aload_0
       1: invokespecial #13                 // Method org/apache/commons/math3/stat/descriptive/DescriptiveStatistics.getWindowSize:()I
       4: ireturn

  public synchronized void setWindowSize(int) throws org.apache.commons.math3.exception.MathIllegalArgumentException;
    Code:
       0: aload_0
       1: iload_1
       2: invokespecial #14                 // Method org/apache/commons/math3/stat/descriptive/DescriptiveStatistics.setWindowSize:(I)V
       5: return

  public synchronized java.lang.String toString();
    Code:
       0: aload_0
       1: invokespecial #15                 // Method org/apache/commons/math3/stat/descriptive/DescriptiveStatistics.toString:()Ljava/lang/String;
       4: areturn

  public synchronized org.apache.commons.math3.stat.descriptive.SynchronizedDescriptiveStatistics copy();
    Code:
       0: new           #16                 // class org/apache/commons/math3/stat/descriptive/SynchronizedDescriptiveStatistics
       3: dup
       4: invokespecial #17                 // Method "<init>":()V
       7: astore_1
       8: aload_0
       9: aload_1
      10: invokestatic  #4                  // Method copy:(Lorg/apache/commons/math3/stat/descriptive/SynchronizedDescriptiveStatistics;Lorg/apache/commons/math3/stat/descriptive/SynchronizedDescriptiveStatistics;)V
      13: aload_1
      14: areturn

  public static void copy(org.apache.commons.math3.stat.descriptive.SynchronizedDescriptiveStatistics, org.apache.commons.math3.stat.descriptive.SynchronizedDescriptiveStatistics) throws org.apache.commons.math3.exception.NullArgumentException;
    Code:
       0: aload_0
       1: invokestatic  #18                 // Method org/apache/commons/math3/util/MathUtils.checkNotNull:(Ljava/lang/Object;)V
       4: aload_1
       5: invokestatic  #18                 // Method org/apache/commons/math3/util/MathUtils.checkNotNull:(Ljava/lang/Object;)V
       8: aload_0
       9: dup
      10: astore_2
      11: monitorenter
      12: aload_1
      13: dup
      14: astore_3
      15: monitorenter
      16: aload_0
      17: aload_1
      18: invokestatic  #19                 // Method org/apache/commons/math3/stat/descriptive/DescriptiveStatistics.copy:(Lorg/apache/commons/math3/stat/descriptive/DescriptiveStatistics;Lorg/apache/commons/math3/stat/descriptive/DescriptiveStatistics;)V
      21: aload_3
      22: monitorexit
      23: goto          33
      26: astore        4
      28: aload_3
      29: monitorexit
      30: aload         4
      32: athrow
      33: aload_2
      34: monitorexit
      35: goto          45
      38: astore        5
      40: aload_2
      41: monitorexit
      42: aload         5
      44: athrow
      45: return
    Exception table:
       from    to  target type
          16    23    26   any
          26    30    26   any
          12    35    38   any
          38    42    38   any

  public org.apache.commons.math3.stat.descriptive.DescriptiveStatistics copy();
    Code:
       0: aload_0
       1: invokevirtual #20                 // Method copy:()Lorg/apache/commons/math3/stat/descriptive/SynchronizedDescriptiveStatistics;
       4: areturn
}
