Compiled from "SimpleClassDescriptor.java"
public class org.jboss.marshalling.river.SimpleClassDescriptor extends org.jboss.marshalling.river.ClassDescriptor {
  private final java.lang.Class<?> type;

  private int typeID;

  public org.jboss.marshalling.river.SimpleClassDescriptor(java.lang.Class<?>, int);
    Code:
       0: aload_0
       1: invokespecial #1                  // Method org/jboss/marshalling/river/ClassDescriptor."<init>":()V
       4: aload_0
       5: aload_1
       6: putfield      #2                  // Field type:Ljava/lang/Class;
       9: aload_0
      10: iload_2
      11: putfield      #3                  // Field typeID:I
      14: return

  public java.lang.Class<?> getType();
    Code:
       0: aload_0
       1: getfield      #2                  // Field type:Ljava/lang/Class;
       4: areturn

  public int getTypeID();
    Code:
       0: aload_0
       1: getfield      #3                  // Field typeID:I
       4: ireturn
}
