Compiled from "EvaluationService.java"
class org.eclipse.ui.internal.services.EvaluationService$2 extends org.eclipse.e4.core.contexts.ContextFunction {
  final org.eclipse.ui.internal.services.EvaluationService this$0;

  org.eclipse.ui.internal.services.EvaluationService$2(org.eclipse.ui.internal.services.EvaluationService);
    Code:
       0: aload_0
       1: aload_1
       2: putfield      #62                 // Field this$0:Lorg/eclipse/ui/internal/services/EvaluationService;
       5: aload_0
       6: invokespecial #64                 // Method org/eclipse/e4/core/contexts/ContextFunction."<init>":()V
       9: return

  public java.lang.Object compute(org.eclipse.e4.core.contexts.IEclipseContext, java.lang.String);
    Code:
       0: aload_1
       1: ldc           #1                  // String org.eclipse.ui.internal.services.EvaluationService.default_var
       3: invokeinterface #66,  2           // InterfaceMethod org/eclipse/e4/core/contexts/IEclipseContext.getLocal:(Ljava/lang/String;)Ljava/lang/Object;
       8: astore_3
       9: aload_3
      10: ifnull        22
      13: aload_3
      14: getstatic     #61                 // Field org/eclipse/core/expressions/IEvaluationContext.UNDEFINED_VARIABLE:Ljava/lang/Object;
      17: if_acmpeq     22
      20: aload_3
      21: areturn
      22: aload_1
      23: ldc           #2                  // String org.eclipse.ui.selection
      25: invokeinterface #65,  2           // InterfaceMethod org/eclipse/e4/core/contexts/IEclipseContext.getActive:(Ljava/lang/String;)Ljava/lang/Object;
      30: astore_3
      31: aload_3
      32: instanceof    #37                 // class org/eclipse/jface/viewers/IStructuredSelection
      35: ifeq          52
      38: aload_3
      39: checkcast     #37                 // class org/eclipse/jface/viewers/IStructuredSelection
      42: astore        4
      44: aload         4
      46: invokeinterface #68,  1           // InterfaceMethod org/eclipse/jface/viewers/IStructuredSelection.toList:()Ljava/util/List;
      51: areturn
      52: aload_3
      53: instanceof    #36                 // class org/eclipse/jface/viewers/ISelection
      56: ifeq          76
      59: aload_3
      60: checkcast     #36                 // class org/eclipse/jface/viewers/ISelection
      63: invokeinterface #67,  1           // InterfaceMethod org/eclipse/jface/viewers/ISelection.isEmpty:()Z
      68: ifne          76
      71: aload_3
      72: invokestatic  #63                 // Method java/util/Collections.singleton:(Ljava/lang/Object;)Ljava/util/Set;
      75: areturn
      76: aconst_null
      77: areturn
}
