Compiled from "EvaluationServiceFactory.java"
public class org.eclipse.ui.internal.services.EvaluationServiceFactory extends org.eclipse.ui.services.AbstractServiceFactory {
  public org.eclipse.ui.internal.services.EvaluationServiceFactory();
    Code:
       0: aload_0
       1: invokespecial #37                 // Method org/eclipse/ui/services/AbstractServiceFactory."<init>":()V
       4: return

  public java.lang.Object create(java.lang.Class, org.eclipse.ui.services.IServiceLocator, org.eclipse.ui.services.IServiceLocator);
    Code:
       0: ldc           #1                  // class org/eclipse/ui/services/IEvaluationService
       2: aload_1
       3: invokevirtual #35                 // Method java/lang/Object.equals:(Ljava/lang/Object;)Z
       6: ifne          11
       9: aconst_null
      10: areturn
      11: aload_2
      12: aload_1
      13: invokeinterface #38,  2           // InterfaceMethod org/eclipse/ui/services/IServiceLocator.getService:(Ljava/lang/Class;)Ljava/lang/Object;
      18: astore        4
      20: aload         4
      22: ifnonnull     27
      25: aconst_null
      26: areturn
      27: new           #20                 // class org/eclipse/ui/internal/services/SlaveEvaluationService
      30: dup
      31: aload         4
      33: checkcast     #1                  // class org/eclipse/ui/services/IEvaluationService
      36: invokespecial #36                 // Method org/eclipse/ui/internal/services/SlaveEvaluationService."<init>":(Lorg/eclipse/ui/services/IEvaluationService;)V
      39: areturn
}
