Compiled from "AbstractGraphNode.java"
public abstract class org.hibernate.jpa.graph.internal.AbstractGraphNode<T> implements org.hibernate.graph.spi.GraphNodeImplementor, org.hibernate.jpa.spi.HibernateEntityManagerFactoryAware {
  private static final org.jboss.logging.Logger log;

  private final org.hibernate.engine.spi.SessionFactoryImplementor sessionFactory;

  private final boolean mutable;

  private java.util.Map<java.lang.String, org.hibernate.graph.spi.AttributeNodeImplementor<?>> attributeNodeMap;

  protected org.hibernate.jpa.graph.internal.AbstractGraphNode(org.hibernate.engine.spi.SessionFactoryImplementor, boolean);
    Code:
       0: aload_0
       1: invokespecial #1                  // Method java/lang/Object."<init>":()V
       4: aload_0
       5: aload_1
       6: putfield      #2                  // Field sessionFactory:Lorg/hibernate/engine/spi/SessionFactoryImplementor;
       9: aload_0
      10: iload_2
      11: putfield      #3                  // Field mutable:Z
      14: return

  protected org.hibernate.jpa.graph.internal.AbstractGraphNode(org.hibernate.jpa.graph.internal.AbstractGraphNode<T>, boolean);
    Code:
       0: aload_0
       1: invokespecial #1                  // Method java/lang/Object."<init>":()V
       4: aload_0
       5: aload_1
       6: getfield      #2                  // Field sessionFactory:Lorg/hibernate/engine/spi/SessionFactoryImplementor;
       9: putfield      #2                  // Field sessionFactory:Lorg/hibernate/engine/spi/SessionFactoryImplementor;
      12: aload_0
      13: iload_2
      14: putfield      #3                  // Field mutable:Z
      17: aload_0
      18: aload_1
      19: getfield      #4                  // Field attributeNodeMap:Ljava/util/Map;
      22: invokestatic  #5                  // Method makeSafeMapCopy:(Ljava/util/Map;)Ljava/util/Map;
      25: putfield      #4                  // Field attributeNodeMap:Ljava/util/Map;
      28: return

  private static java.util.Map<java.lang.String, org.hibernate.graph.spi.AttributeNodeImplementor<?>> makeSafeMapCopy(java.util.Map<java.lang.String, org.hibernate.graph.spi.AttributeNodeImplementor<?>>);
    Code:
       0: aload_0
       1: ifnonnull     6
       4: aconst_null
       5: areturn
       6: aload_0
       7: invokestatic  #6                  // Method org/hibernate/internal/util/collections/CollectionHelper.determineProperSizing:(Ljava/util/Map;)I
      10: istore_1
      11: new           #7                  // class java/util/HashMap
      14: dup
      15: iload_1
      16: invokespecial #8                  // Method java/util/HashMap."<init>":(I)V
      19: astore_2
      20: aload_0
      21: invokeinterface #9,  1            // InterfaceMethod java/util/Map.entrySet:()Ljava/util/Set;
      26: invokeinterface #10,  1           // InterfaceMethod java/util/Set.iterator:()Ljava/util/Iterator;
      31: astore_3
      32: aload_3
      33: invokeinterface #11,  1           // InterfaceMethod java/util/Iterator.hasNext:()Z
      38: ifeq          80
      41: aload_3
      42: invokeinterface #12,  1           // InterfaceMethod java/util/Iterator.next:()Ljava/lang/Object;
      47: checkcast     #13                 // class java/util/Map$Entry
      50: astore        4
      52: aload_2
      53: aload         4
      55: invokeinterface #14,  1           // InterfaceMethod java/util/Map$Entry.getKey:()Ljava/lang/Object;
      60: aload         4
      62: invokeinterface #15,  1           // InterfaceMethod java/util/Map$Entry.getValue:()Ljava/lang/Object;
      67: checkcast     #16                 // class org/hibernate/jpa/graph/internal/AttributeNodeImpl
      70: invokevirtual #17                 // Method org/hibernate/jpa/graph/internal/AttributeNodeImpl.makeImmutableCopy:()Lorg/hibernate/jpa/graph/internal/AttributeNodeImpl;
      73: invokevirtual #18                 // Method java/util/HashMap.put:(Ljava/lang/Object;Ljava/lang/Object;)Ljava/lang/Object;
      76: pop
      77: goto          32
      80: aload_2
      81: areturn

  public org.hibernate.engine.spi.SessionFactoryImplementor getFactory();
    Code:
       0: aload_0
       1: getfield      #2                  // Field sessionFactory:Lorg/hibernate/engine/spi/SessionFactoryImplementor;
       4: areturn

  public java.util.List<org.hibernate.graph.spi.AttributeNodeImplementor<?>> attributeImplementorNodes();
    Code:
       0: aload_0
       1: getfield      #4                  // Field attributeNodeMap:Ljava/util/Map;
       4: ifnonnull     11
       7: invokestatic  #19                 // Method java/util/Collections.emptyList:()Ljava/util/List;
      10: areturn
      11: new           #20                 // class java/util/ArrayList
      14: dup
      15: aload_0
      16: getfield      #4                  // Field attributeNodeMap:Ljava/util/Map;
      19: invokeinterface #21,  1           // InterfaceMethod java/util/Map.values:()Ljava/util/Collection;
      24: invokespecial #22                 // Method java/util/ArrayList."<init>":(Ljava/util/Collection;)V
      27: areturn

  public java.util.List<javax.persistence.AttributeNode<?>> attributeNodes();
    Code:
       0: aload_0
       1: getfield      #4                  // Field attributeNodeMap:Ljava/util/Map;
       4: ifnonnull     11
       7: invokestatic  #19                 // Method java/util/Collections.emptyList:()Ljava/util/List;
      10: areturn
      11: new           #20                 // class java/util/ArrayList
      14: dup
      15: aload_0
      16: getfield      #4                  // Field attributeNodeMap:Ljava/util/Map;
      19: invokeinterface #21,  1           // InterfaceMethod java/util/Map.values:()Ljava/util/Collection;
      24: invokespecial #22                 // Method java/util/ArrayList."<init>":(Ljava/util/Collection;)V
      27: areturn

  public void addAttributeNodes(java.lang.String...);
    Code:
       0: aload_1
       1: astore_2
       2: aload_2
       3: arraylength
       4: istore_3
       5: iconst_0
       6: istore        4
       8: iload         4
      10: iload_3
      11: if_icmpge     33
      14: aload_2
      15: iload         4
      17: aaload
      18: astore        5
      20: aload_0
      21: aload         5
      23: invokevirtual #23                 // Method addAttribute:(Ljava/lang/String;)Lorg/hibernate/jpa/graph/internal/AttributeNodeImpl;
      26: pop
      27: iinc          4, 1
      30: goto          8
      33: return

  public org.hibernate.jpa.graph.internal.AttributeNodeImpl addAttribute(java.lang.String);
    Code:
       0: aload_0
       1: aload_0
       2: aload_1
       3: invokespecial #24                 // Method buildAttributeNode:(Ljava/lang/String;)Lorg/hibernate/jpa/graph/internal/AttributeNodeImpl;
       6: invokevirtual #25                 // Method addAttributeNode:(Lorg/hibernate/jpa/graph/internal/AttributeNodeImpl;)Lorg/hibernate/jpa/graph/internal/AttributeNodeImpl;
       9: areturn

  private org.hibernate.jpa.graph.internal.AttributeNodeImpl<?> buildAttributeNode(java.lang.String);
    Code:
       0: aload_0
       1: aload_0
       2: aload_1
       3: invokevirtual #26                 // Method resolveAttribute:(Ljava/lang/String;)Ljavax/persistence/metamodel/Attribute;
       6: invokevirtual #27                 // Method buildAttributeNode:(Ljavax/persistence/metamodel/Attribute;)Lorg/hibernate/jpa/graph/internal/AttributeNodeImpl;
       9: areturn

  protected abstract javax.persistence.metamodel.Attribute<T, ?> resolveAttribute(java.lang.String);

  protected <X> org.hibernate.jpa.graph.internal.AttributeNodeImpl<X> buildAttributeNode(javax.persistence.metamodel.Attribute<T, X>);
    Code:
       0: new           #16                 // class org/hibernate/jpa/graph/internal/AttributeNodeImpl
       3: dup
       4: aload_0
       5: getfield      #2                  // Field sessionFactory:Lorg/hibernate/engine/spi/SessionFactoryImplementor;
       8: aload_0
       9: invokevirtual #28                 // Method getManagedType:()Ljavax/persistence/metamodel/ManagedType;
      12: aload_1
      13: invokespecial #29                 // Method org/hibernate/jpa/graph/internal/AttributeNodeImpl."<init>":(Lorg/hibernate/engine/spi/SessionFactoryImplementor;Ljavax/persistence/metamodel/ManagedType;Ljavax/persistence/metamodel/Attribute;)V
      16: areturn

  protected org.hibernate.jpa.graph.internal.AttributeNodeImpl addAttributeNode(org.hibernate.jpa.graph.internal.AttributeNodeImpl);
    Code:
       0: aload_0
       1: getfield      #3                  // Field mutable:Z
       4: ifne          17
       7: new           #30                 // class java/lang/IllegalStateException
      10: dup
      11: ldc           #31                 // String Entity/sub graph is not mutable
      13: invokespecial #32                 // Method java/lang/IllegalStateException."<init>":(Ljava/lang/String;)V
      16: athrow
      17: aload_0
      18: getfield      #4                  // Field attributeNodeMap:Ljava/util/Map;
      21: ifnonnull     38
      24: aload_0
      25: new           #7                  // class java/util/HashMap
      28: dup
      29: invokespecial #33                 // Method java/util/HashMap."<init>":()V
      32: putfield      #4                  // Field attributeNodeMap:Ljava/util/Map;
      35: goto          85
      38: aload_0
      39: getfield      #4                  // Field attributeNodeMap:Ljava/util/Map;
      42: aload_1
      43: invokevirtual #34                 // Method org/hibernate/jpa/graph/internal/AttributeNodeImpl.getRegistrationName:()Ljava/lang/String;
      46: invokeinterface #35,  2           // InterfaceMethod java/util/Map.get:(Ljava/lang/Object;)Ljava/lang/Object;
      51: checkcast     #36                 // class javax/persistence/AttributeNode
      54: astore_2
      55: aload_2
      56: ifnull        85
      59: getstatic     #37                 // Field log:Lorg/jboss/logging/Logger;
      62: ldc           #38                 // String Encountered request to add entity graph node [%s] using a name [%s] under which another node is already registered [%s]
      64: aload_2
      65: invokevirtual #39                 // Method java/lang/Object.getClass:()Ljava/lang/Class;
      68: invokevirtual #40                 // Method java/lang/Class.getName:()Ljava/lang/String;
      71: aload_1
      72: invokevirtual #34                 // Method org/hibernate/jpa/graph/internal/AttributeNodeImpl.getRegistrationName:()Ljava/lang/String;
      75: aload_1
      76: invokevirtual #39                 // Method java/lang/Object.getClass:()Ljava/lang/Class;
      79: invokevirtual #40                 // Method java/lang/Class.getName:()Ljava/lang/String;
      82: invokevirtual #41                 // Method org/jboss/logging/Logger.debugf:(Ljava/lang/String;Ljava/lang/Object;Ljava/lang/Object;Ljava/lang/Object;)V
      85: aload_0
      86: getfield      #4                  // Field attributeNodeMap:Ljava/util/Map;
      89: aload_1
      90: invokevirtual #34                 // Method org/hibernate/jpa/graph/internal/AttributeNodeImpl.getRegistrationName:()Ljava/lang/String;
      93: aload_1
      94: invokeinterface #42,  3           // InterfaceMethod java/util/Map.put:(Ljava/lang/Object;Ljava/lang/Object;)Ljava/lang/Object;
      99: pop
     100: aload_1
     101: areturn

  protected void addAttributeNodes(javax.persistence.metamodel.Attribute<T, ?>...);
    Code:
       0: aload_1
       1: astore_2
       2: aload_2
       3: arraylength
       4: istore_3
       5: iconst_0
       6: istore        4
       8: iload         4
      10: iload_3
      11: if_icmpge     33
      14: aload_2
      15: iload         4
      17: aaload
      18: astore        5
      20: aload_0
      21: aload         5
      23: invokevirtual #43                 // Method addAttribute:(Ljavax/persistence/metamodel/Attribute;)Lorg/hibernate/jpa/graph/internal/AttributeNodeImpl;
      26: pop
      27: iinc          4, 1
      30: goto          8
      33: return

  protected org.hibernate.jpa.graph.internal.AttributeNodeImpl addAttribute(javax.persistence.metamodel.Attribute);
    Code:
       0: aload_0
       1: aload_0
       2: aload_1
       3: invokevirtual #27                 // Method buildAttributeNode:(Ljavax/persistence/metamodel/Attribute;)Lorg/hibernate/jpa/graph/internal/AttributeNodeImpl;
       6: invokevirtual #25                 // Method addAttributeNode:(Lorg/hibernate/jpa/graph/internal/AttributeNodeImpl;)Lorg/hibernate/jpa/graph/internal/AttributeNodeImpl;
       9: areturn

  public <X> org.hibernate.jpa.graph.internal.SubgraphImpl<X> addSubgraph(javax.persistence.metamodel.Attribute<T, X>);
    Code:
       0: aload_0
       1: aload_1
       2: invokevirtual #43                 // Method addAttribute:(Ljavax/persistence/metamodel/Attribute;)Lorg/hibernate/jpa/graph/internal/AttributeNodeImpl;
       5: invokevirtual #44                 // Method org/hibernate/jpa/graph/internal/AttributeNodeImpl.makeSubgraph:()Lorg/hibernate/jpa/graph/internal/SubgraphImpl;
       8: areturn

  public <X> org.hibernate.jpa.graph.internal.SubgraphImpl<? extends X> addSubgraph(javax.persistence.metamodel.Attribute<T, X>, java.lang.Class<? extends X>);
    Code:
       0: aload_0
       1: aload_1
       2: invokevirtual #43                 // Method addAttribute:(Ljavax/persistence/metamodel/Attribute;)Lorg/hibernate/jpa/graph/internal/AttributeNodeImpl;
       5: aload_2
       6: invokevirtual #45                 // Method org/hibernate/jpa/graph/internal/AttributeNodeImpl.makeSubgraph:(Ljava/lang/Class;)Lorg/hibernate/jpa/graph/internal/SubgraphImpl;
       9: areturn

  public <X> org.hibernate.jpa.graph.internal.SubgraphImpl<X> addSubgraph(java.lang.String);
    Code:
       0: aload_0
       1: aload_1
       2: invokevirtual #23                 // Method addAttribute:(Ljava/lang/String;)Lorg/hibernate/jpa/graph/internal/AttributeNodeImpl;
       5: invokevirtual #44                 // Method org/hibernate/jpa/graph/internal/AttributeNodeImpl.makeSubgraph:()Lorg/hibernate/jpa/graph/internal/SubgraphImpl;
       8: areturn

  public <X> org.hibernate.jpa.graph.internal.SubgraphImpl<X> addSubgraph(java.lang.String, java.lang.Class<X>);
    Code:
       0: aload_0
       1: aload_1
       2: invokevirtual #23                 // Method addAttribute:(Ljava/lang/String;)Lorg/hibernate/jpa/graph/internal/AttributeNodeImpl;
       5: aload_2
       6: invokevirtual #45                 // Method org/hibernate/jpa/graph/internal/AttributeNodeImpl.makeSubgraph:(Ljava/lang/Class;)Lorg/hibernate/jpa/graph/internal/SubgraphImpl;
       9: areturn

  public <X> org.hibernate.jpa.graph.internal.SubgraphImpl<X> addKeySubgraph(javax.persistence.metamodel.Attribute<T, X>);
    Code:
       0: aload_0
       1: aload_1
       2: invokevirtual #43                 // Method addAttribute:(Ljavax/persistence/metamodel/Attribute;)Lorg/hibernate/jpa/graph/internal/AttributeNodeImpl;
       5: invokevirtual #46                 // Method org/hibernate/jpa/graph/internal/AttributeNodeImpl.makeKeySubgraph:()Lorg/hibernate/jpa/graph/internal/SubgraphImpl;
       8: areturn

  public <X> org.hibernate.jpa.graph.internal.SubgraphImpl<? extends X> addKeySubgraph(javax.persistence.metamodel.Attribute<T, X>, java.lang.Class<? extends X>);
    Code:
       0: aload_0
       1: aload_1
       2: invokevirtual #43                 // Method addAttribute:(Ljavax/persistence/metamodel/Attribute;)Lorg/hibernate/jpa/graph/internal/AttributeNodeImpl;
       5: aload_2
       6: invokevirtual #47                 // Method org/hibernate/jpa/graph/internal/AttributeNodeImpl.makeKeySubgraph:(Ljava/lang/Class;)Lorg/hibernate/jpa/graph/internal/SubgraphImpl;
       9: areturn

  public <X> org.hibernate.jpa.graph.internal.SubgraphImpl<X> addKeySubgraph(java.lang.String);
    Code:
       0: aload_0
       1: aload_1
       2: invokevirtual #23                 // Method addAttribute:(Ljava/lang/String;)Lorg/hibernate/jpa/graph/internal/AttributeNodeImpl;
       5: invokevirtual #46                 // Method org/hibernate/jpa/graph/internal/AttributeNodeImpl.makeKeySubgraph:()Lorg/hibernate/jpa/graph/internal/SubgraphImpl;
       8: areturn

  public <X> org.hibernate.jpa.graph.internal.SubgraphImpl<X> addKeySubgraph(java.lang.String, java.lang.Class<X>);
    Code:
       0: aload_0
       1: aload_1
       2: invokevirtual #23                 // Method addAttribute:(Ljava/lang/String;)Lorg/hibernate/jpa/graph/internal/AttributeNodeImpl;
       5: aload_2
       6: invokevirtual #47                 // Method org/hibernate/jpa/graph/internal/AttributeNodeImpl.makeKeySubgraph:(Ljava/lang/Class;)Lorg/hibernate/jpa/graph/internal/SubgraphImpl;
       9: areturn

  public boolean containsAttribute(java.lang.String);
    Code:
       0: aload_0
       1: getfield      #4                  // Field attributeNodeMap:Ljava/util/Map;
       4: ifnull        24
       7: aload_0
       8: getfield      #4                  // Field attributeNodeMap:Ljava/util/Map;
      11: aload_1
      12: invokeinterface #48,  2           // InterfaceMethod java/util/Map.containsKey:(Ljava/lang/Object;)Z
      17: ifeq          24
      20: iconst_1
      21: goto          25
      24: iconst_0
      25: ireturn

  abstract javax.persistence.metamodel.ManagedType getManagedType();

  public org.hibernate.jpa.HibernateEntityManagerFactory getFactory();
    Code:
       0: aload_0
       1: invokevirtual #49                 // Method getFactory:()Lorg/hibernate/engine/spi/SessionFactoryImplementor;
       4: areturn

  static {};
    Code:
       0: ldc           #50                 // class org/hibernate/jpa/graph/internal/AbstractGraphNode
       2: invokestatic  #51                 // Method org/jboss/logging/Logger.getLogger:(Ljava/lang/Class;)Lorg/jboss/logging/Logger;
       5: putstatic     #37                 // Field log:Lorg/jboss/logging/Logger;
       8: return
}
