Compiled from "AdditionalMatchers.java"
public class org.mockito.AdditionalMatchers {
  public org.mockito.AdditionalMatchers();
    Code:
       0: aload_0
       1: invokespecial #1                  // Method java/lang/Object."<init>":()V
       4: return

  public static <T extends java.lang.Comparable<T>> T geq(T);
    Code:
       0: new           #2                  // class org/mockito/internal/matchers/GreaterOrEqual
       3: dup
       4: aload_0
       5: invokespecial #3                  // Method org/mockito/internal/matchers/GreaterOrEqual."<init>":(Ljava/lang/Comparable;)V
       8: invokestatic  #4                  // Method reportMatcher:(Lorg/mockito/ArgumentMatcher;)V
      11: aconst_null
      12: areturn

  public static byte geq(byte);
    Code:
       0: new           #2                  // class org/mockito/internal/matchers/GreaterOrEqual
       3: dup
       4: iload_0
       5: invokestatic  #5                  // Method java/lang/Byte.valueOf:(B)Ljava/lang/Byte;
       8: invokespecial #3                  // Method org/mockito/internal/matchers/GreaterOrEqual."<init>":(Ljava/lang/Comparable;)V
      11: invokestatic  #4                  // Method reportMatcher:(Lorg/mockito/ArgumentMatcher;)V
      14: iconst_0
      15: ireturn

  public static double geq(double);
    Code:
       0: new           #2                  // class org/mockito/internal/matchers/GreaterOrEqual
       3: dup
       4: dload_0
       5: invokestatic  #6                  // Method java/lang/Double.valueOf:(D)Ljava/lang/Double;
       8: invokespecial #3                  // Method org/mockito/internal/matchers/GreaterOrEqual."<init>":(Ljava/lang/Comparable;)V
      11: invokestatic  #4                  // Method reportMatcher:(Lorg/mockito/ArgumentMatcher;)V
      14: dconst_0
      15: dreturn

  public static float geq(float);
    Code:
       0: new           #2                  // class org/mockito/internal/matchers/GreaterOrEqual
       3: dup
       4: fload_0
       5: invokestatic  #7                  // Method java/lang/Float.valueOf:(F)Ljava/lang/Float;
       8: invokespecial #3                  // Method org/mockito/internal/matchers/GreaterOrEqual."<init>":(Ljava/lang/Comparable;)V
      11: invokestatic  #4                  // Method reportMatcher:(Lorg/mockito/ArgumentMatcher;)V
      14: fconst_0
      15: freturn

  public static int geq(int);
    Code:
       0: new           #2                  // class org/mockito/internal/matchers/GreaterOrEqual
       3: dup
       4: iload_0
       5: invokestatic  #8                  // Method java/lang/Integer.valueOf:(I)Ljava/lang/Integer;
       8: invokespecial #3                  // Method org/mockito/internal/matchers/GreaterOrEqual."<init>":(Ljava/lang/Comparable;)V
      11: invokestatic  #4                  // Method reportMatcher:(Lorg/mockito/ArgumentMatcher;)V
      14: iconst_0
      15: ireturn

  public static long geq(long);
    Code:
       0: new           #2                  // class org/mockito/internal/matchers/GreaterOrEqual
       3: dup
       4: lload_0
       5: invokestatic  #9                  // Method java/lang/Long.valueOf:(J)Ljava/lang/Long;
       8: invokespecial #3                  // Method org/mockito/internal/matchers/GreaterOrEqual."<init>":(Ljava/lang/Comparable;)V
      11: invokestatic  #4                  // Method reportMatcher:(Lorg/mockito/ArgumentMatcher;)V
      14: lconst_0
      15: lreturn

  public static short geq(short);
    Code:
       0: new           #2                  // class org/mockito/internal/matchers/GreaterOrEqual
       3: dup
       4: iload_0
       5: invokestatic  #10                 // Method java/lang/Short.valueOf:(S)Ljava/lang/Short;
       8: invokespecial #3                  // Method org/mockito/internal/matchers/GreaterOrEqual."<init>":(Ljava/lang/Comparable;)V
      11: invokestatic  #4                  // Method reportMatcher:(Lorg/mockito/ArgumentMatcher;)V
      14: iconst_0
      15: ireturn

  public static <T extends java.lang.Comparable<T>> T leq(T);
    Code:
       0: new           #11                 // class org/mockito/internal/matchers/LessOrEqual
       3: dup
       4: aload_0
       5: invokespecial #12                 // Method org/mockito/internal/matchers/LessOrEqual."<init>":(Ljava/lang/Comparable;)V
       8: invokestatic  #4                  // Method reportMatcher:(Lorg/mockito/ArgumentMatcher;)V
      11: aconst_null
      12: areturn

  public static byte leq(byte);
    Code:
       0: new           #11                 // class org/mockito/internal/matchers/LessOrEqual
       3: dup
       4: iload_0
       5: invokestatic  #5                  // Method java/lang/Byte.valueOf:(B)Ljava/lang/Byte;
       8: invokespecial #12                 // Method org/mockito/internal/matchers/LessOrEqual."<init>":(Ljava/lang/Comparable;)V
      11: invokestatic  #4                  // Method reportMatcher:(Lorg/mockito/ArgumentMatcher;)V
      14: iconst_0
      15: ireturn

  public static double leq(double);
    Code:
       0: new           #11                 // class org/mockito/internal/matchers/LessOrEqual
       3: dup
       4: dload_0
       5: invokestatic  #6                  // Method java/lang/Double.valueOf:(D)Ljava/lang/Double;
       8: invokespecial #12                 // Method org/mockito/internal/matchers/LessOrEqual."<init>":(Ljava/lang/Comparable;)V
      11: invokestatic  #4                  // Method reportMatcher:(Lorg/mockito/ArgumentMatcher;)V
      14: dconst_0
      15: dreturn

  public static float leq(float);
    Code:
       0: new           #11                 // class org/mockito/internal/matchers/LessOrEqual
       3: dup
       4: fload_0
       5: invokestatic  #7                  // Method java/lang/Float.valueOf:(F)Ljava/lang/Float;
       8: invokespecial #12                 // Method org/mockito/internal/matchers/LessOrEqual."<init>":(Ljava/lang/Comparable;)V
      11: invokestatic  #4                  // Method reportMatcher:(Lorg/mockito/ArgumentMatcher;)V
      14: fconst_0
      15: freturn

  public static int leq(int);
    Code:
       0: new           #11                 // class org/mockito/internal/matchers/LessOrEqual
       3: dup
       4: iload_0
       5: invokestatic  #8                  // Method java/lang/Integer.valueOf:(I)Ljava/lang/Integer;
       8: invokespecial #12                 // Method org/mockito/internal/matchers/LessOrEqual."<init>":(Ljava/lang/Comparable;)V
      11: invokestatic  #4                  // Method reportMatcher:(Lorg/mockito/ArgumentMatcher;)V
      14: iconst_0
      15: ireturn

  public static long leq(long);
    Code:
       0: new           #11                 // class org/mockito/internal/matchers/LessOrEqual
       3: dup
       4: lload_0
       5: invokestatic  #9                  // Method java/lang/Long.valueOf:(J)Ljava/lang/Long;
       8: invokespecial #12                 // Method org/mockito/internal/matchers/LessOrEqual."<init>":(Ljava/lang/Comparable;)V
      11: invokestatic  #4                  // Method reportMatcher:(Lorg/mockito/ArgumentMatcher;)V
      14: lconst_0
      15: lreturn

  public static short leq(short);
    Code:
       0: new           #11                 // class org/mockito/internal/matchers/LessOrEqual
       3: dup
       4: iload_0
       5: invokestatic  #10                 // Method java/lang/Short.valueOf:(S)Ljava/lang/Short;
       8: invokespecial #12                 // Method org/mockito/internal/matchers/LessOrEqual."<init>":(Ljava/lang/Comparable;)V
      11: invokestatic  #4                  // Method reportMatcher:(Lorg/mockito/ArgumentMatcher;)V
      14: iconst_0
      15: ireturn

  public static <T extends java.lang.Comparable<T>> T gt(T);
    Code:
       0: new           #13                 // class org/mockito/internal/matchers/GreaterThan
       3: dup
       4: aload_0
       5: invokespecial #14                 // Method org/mockito/internal/matchers/GreaterThan."<init>":(Ljava/lang/Comparable;)V
       8: invokestatic  #4                  // Method reportMatcher:(Lorg/mockito/ArgumentMatcher;)V
      11: aconst_null
      12: areturn

  public static byte gt(byte);
    Code:
       0: new           #13                 // class org/mockito/internal/matchers/GreaterThan
       3: dup
       4: iload_0
       5: invokestatic  #5                  // Method java/lang/Byte.valueOf:(B)Ljava/lang/Byte;
       8: invokespecial #14                 // Method org/mockito/internal/matchers/GreaterThan."<init>":(Ljava/lang/Comparable;)V
      11: invokestatic  #4                  // Method reportMatcher:(Lorg/mockito/ArgumentMatcher;)V
      14: iconst_0
      15: ireturn

  public static double gt(double);
    Code:
       0: new           #13                 // class org/mockito/internal/matchers/GreaterThan
       3: dup
       4: dload_0
       5: invokestatic  #6                  // Method java/lang/Double.valueOf:(D)Ljava/lang/Double;
       8: invokespecial #14                 // Method org/mockito/internal/matchers/GreaterThan."<init>":(Ljava/lang/Comparable;)V
      11: invokestatic  #4                  // Method reportMatcher:(Lorg/mockito/ArgumentMatcher;)V
      14: dconst_0
      15: dreturn

  public static float gt(float);
    Code:
       0: new           #13                 // class org/mockito/internal/matchers/GreaterThan
       3: dup
       4: fload_0
       5: invokestatic  #7                  // Method java/lang/Float.valueOf:(F)Ljava/lang/Float;
       8: invokespecial #14                 // Method org/mockito/internal/matchers/GreaterThan."<init>":(Ljava/lang/Comparable;)V
      11: invokestatic  #4                  // Method reportMatcher:(Lorg/mockito/ArgumentMatcher;)V
      14: fconst_0
      15: freturn

  public static int gt(int);
    Code:
       0: new           #13                 // class org/mockito/internal/matchers/GreaterThan
       3: dup
       4: iload_0
       5: invokestatic  #8                  // Method java/lang/Integer.valueOf:(I)Ljava/lang/Integer;
       8: invokespecial #14                 // Method org/mockito/internal/matchers/GreaterThan."<init>":(Ljava/lang/Comparable;)V
      11: invokestatic  #4                  // Method reportMatcher:(Lorg/mockito/ArgumentMatcher;)V
      14: iconst_0
      15: ireturn

  public static long gt(long);
    Code:
       0: new           #13                 // class org/mockito/internal/matchers/GreaterThan
       3: dup
       4: lload_0
       5: invokestatic  #9                  // Method java/lang/Long.valueOf:(J)Ljava/lang/Long;
       8: invokespecial #14                 // Method org/mockito/internal/matchers/GreaterThan."<init>":(Ljava/lang/Comparable;)V
      11: invokestatic  #4                  // Method reportMatcher:(Lorg/mockito/ArgumentMatcher;)V
      14: lconst_0
      15: lreturn

  public static short gt(short);
    Code:
       0: new           #13                 // class org/mockito/internal/matchers/GreaterThan
       3: dup
       4: iload_0
       5: invokestatic  #10                 // Method java/lang/Short.valueOf:(S)Ljava/lang/Short;
       8: invokespecial #14                 // Method org/mockito/internal/matchers/GreaterThan."<init>":(Ljava/lang/Comparable;)V
      11: invokestatic  #4                  // Method reportMatcher:(Lorg/mockito/ArgumentMatcher;)V
      14: iconst_0
      15: ireturn

  public static <T extends java.lang.Comparable<T>> T lt(T);
    Code:
       0: new           #15                 // class org/mockito/internal/matchers/LessThan
       3: dup
       4: aload_0
       5: invokespecial #16                 // Method org/mockito/internal/matchers/LessThan."<init>":(Ljava/lang/Comparable;)V
       8: invokestatic  #4                  // Method reportMatcher:(Lorg/mockito/ArgumentMatcher;)V
      11: aconst_null
      12: areturn

  public static byte lt(byte);
    Code:
       0: new           #15                 // class org/mockito/internal/matchers/LessThan
       3: dup
       4: iload_0
       5: invokestatic  #5                  // Method java/lang/Byte.valueOf:(B)Ljava/lang/Byte;
       8: invokespecial #16                 // Method org/mockito/internal/matchers/LessThan."<init>":(Ljava/lang/Comparable;)V
      11: invokestatic  #4                  // Method reportMatcher:(Lorg/mockito/ArgumentMatcher;)V
      14: iconst_0
      15: ireturn

  public static double lt(double);
    Code:
       0: new           #15                 // class org/mockito/internal/matchers/LessThan
       3: dup
       4: dload_0
       5: invokestatic  #6                  // Method java/lang/Double.valueOf:(D)Ljava/lang/Double;
       8: invokespecial #16                 // Method org/mockito/internal/matchers/LessThan."<init>":(Ljava/lang/Comparable;)V
      11: invokestatic  #4                  // Method reportMatcher:(Lorg/mockito/ArgumentMatcher;)V
      14: dconst_0
      15: dreturn

  public static float lt(float);
    Code:
       0: new           #15                 // class org/mockito/internal/matchers/LessThan
       3: dup
       4: fload_0
       5: invokestatic  #7                  // Method java/lang/Float.valueOf:(F)Ljava/lang/Float;
       8: invokespecial #16                 // Method org/mockito/internal/matchers/LessThan."<init>":(Ljava/lang/Comparable;)V
      11: invokestatic  #4                  // Method reportMatcher:(Lorg/mockito/ArgumentMatcher;)V
      14: fconst_0
      15: freturn

  public static int lt(int);
    Code:
       0: new           #15                 // class org/mockito/internal/matchers/LessThan
       3: dup
       4: iload_0
       5: invokestatic  #8                  // Method java/lang/Integer.valueOf:(I)Ljava/lang/Integer;
       8: invokespecial #16                 // Method org/mockito/internal/matchers/LessThan."<init>":(Ljava/lang/Comparable;)V
      11: invokestatic  #4                  // Method reportMatcher:(Lorg/mockito/ArgumentMatcher;)V
      14: iconst_0
      15: ireturn

  public static long lt(long);
    Code:
       0: new           #15                 // class org/mockito/internal/matchers/LessThan
       3: dup
       4: lload_0
       5: invokestatic  #9                  // Method java/lang/Long.valueOf:(J)Ljava/lang/Long;
       8: invokespecial #16                 // Method org/mockito/internal/matchers/LessThan."<init>":(Ljava/lang/Comparable;)V
      11: invokestatic  #4                  // Method reportMatcher:(Lorg/mockito/ArgumentMatcher;)V
      14: lconst_0
      15: lreturn

  public static short lt(short);
    Code:
       0: new           #15                 // class org/mockito/internal/matchers/LessThan
       3: dup
       4: iload_0
       5: invokestatic  #10                 // Method java/lang/Short.valueOf:(S)Ljava/lang/Short;
       8: invokespecial #16                 // Method org/mockito/internal/matchers/LessThan."<init>":(Ljava/lang/Comparable;)V
      11: invokestatic  #4                  // Method reportMatcher:(Lorg/mockito/ArgumentMatcher;)V
      14: iconst_0
      15: ireturn

  public static <T extends java.lang.Comparable<T>> T cmpEq(T);
    Code:
       0: new           #17                 // class org/mockito/internal/matchers/CompareEqual
       3: dup
       4: aload_0
       5: invokespecial #18                 // Method org/mockito/internal/matchers/CompareEqual."<init>":(Ljava/lang/Comparable;)V
       8: invokestatic  #4                  // Method reportMatcher:(Lorg/mockito/ArgumentMatcher;)V
      11: aconst_null
      12: areturn

  public static java.lang.String find(java.lang.String);
    Code:
       0: new           #19                 // class org/mockito/internal/matchers/Find
       3: dup
       4: aload_0
       5: invokespecial #20                 // Method org/mockito/internal/matchers/Find."<init>":(Ljava/lang/String;)V
       8: invokestatic  #4                  // Method reportMatcher:(Lorg/mockito/ArgumentMatcher;)V
      11: aconst_null
      12: areturn

  public static <T> T[] aryEq(T[]);
    Code:
       0: new           #21                 // class org/mockito/internal/matchers/ArrayEquals
       3: dup
       4: aload_0
       5: invokespecial #22                 // Method org/mockito/internal/matchers/ArrayEquals."<init>":(Ljava/lang/Object;)V
       8: invokestatic  #4                  // Method reportMatcher:(Lorg/mockito/ArgumentMatcher;)V
      11: aconst_null
      12: areturn

  public static short[] aryEq(short[]);
    Code:
       0: new           #21                 // class org/mockito/internal/matchers/ArrayEquals
       3: dup
       4: aload_0
       5: invokespecial #22                 // Method org/mockito/internal/matchers/ArrayEquals."<init>":(Ljava/lang/Object;)V
       8: invokestatic  #4                  // Method reportMatcher:(Lorg/mockito/ArgumentMatcher;)V
      11: aconst_null
      12: areturn

  public static long[] aryEq(long[]);
    Code:
       0: new           #21                 // class org/mockito/internal/matchers/ArrayEquals
       3: dup
       4: aload_0
       5: invokespecial #22                 // Method org/mockito/internal/matchers/ArrayEquals."<init>":(Ljava/lang/Object;)V
       8: invokestatic  #4                  // Method reportMatcher:(Lorg/mockito/ArgumentMatcher;)V
      11: aconst_null
      12: areturn

  public static int[] aryEq(int[]);
    Code:
       0: new           #21                 // class org/mockito/internal/matchers/ArrayEquals
       3: dup
       4: aload_0
       5: invokespecial #22                 // Method org/mockito/internal/matchers/ArrayEquals."<init>":(Ljava/lang/Object;)V
       8: invokestatic  #4                  // Method reportMatcher:(Lorg/mockito/ArgumentMatcher;)V
      11: aconst_null
      12: areturn

  public static float[] aryEq(float[]);
    Code:
       0: new           #21                 // class org/mockito/internal/matchers/ArrayEquals
       3: dup
       4: aload_0
       5: invokespecial #22                 // Method org/mockito/internal/matchers/ArrayEquals."<init>":(Ljava/lang/Object;)V
       8: invokestatic  #4                  // Method reportMatcher:(Lorg/mockito/ArgumentMatcher;)V
      11: aconst_null
      12: areturn

  public static double[] aryEq(double[]);
    Code:
       0: new           #21                 // class org/mockito/internal/matchers/ArrayEquals
       3: dup
       4: aload_0
       5: invokespecial #22                 // Method org/mockito/internal/matchers/ArrayEquals."<init>":(Ljava/lang/Object;)V
       8: invokestatic  #4                  // Method reportMatcher:(Lorg/mockito/ArgumentMatcher;)V
      11: aconst_null
      12: areturn

  public static char[] aryEq(char[]);
    Code:
       0: new           #21                 // class org/mockito/internal/matchers/ArrayEquals
       3: dup
       4: aload_0
       5: invokespecial #22                 // Method org/mockito/internal/matchers/ArrayEquals."<init>":(Ljava/lang/Object;)V
       8: invokestatic  #4                  // Method reportMatcher:(Lorg/mockito/ArgumentMatcher;)V
      11: aconst_null
      12: areturn

  public static byte[] aryEq(byte[]);
    Code:
       0: new           #21                 // class org/mockito/internal/matchers/ArrayEquals
       3: dup
       4: aload_0
       5: invokespecial #22                 // Method org/mockito/internal/matchers/ArrayEquals."<init>":(Ljava/lang/Object;)V
       8: invokestatic  #4                  // Method reportMatcher:(Lorg/mockito/ArgumentMatcher;)V
      11: aconst_null
      12: areturn

  public static boolean[] aryEq(boolean[]);
    Code:
       0: new           #21                 // class org/mockito/internal/matchers/ArrayEquals
       3: dup
       4: aload_0
       5: invokespecial #22                 // Method org/mockito/internal/matchers/ArrayEquals."<init>":(Ljava/lang/Object;)V
       8: invokestatic  #4                  // Method reportMatcher:(Lorg/mockito/ArgumentMatcher;)V
      11: aconst_null
      12: areturn

  public static boolean and(boolean, boolean);
    Code:
       0: invokestatic  #23                 // Method org/mockito/internal/progress/ThreadSafeMockingProgress.mockingProgress:()Lorg/mockito/internal/progress/MockingProgress;
       3: invokeinterface #24,  1           // InterfaceMethod org/mockito/internal/progress/MockingProgress.getArgumentMatcherStorage:()Lorg/mockito/internal/progress/ArgumentMatcherStorage;
       8: invokeinterface #25,  1           // InterfaceMethod org/mockito/internal/progress/ArgumentMatcherStorage.reportAnd:()V
      13: iconst_0
      14: ireturn

  public static byte and(byte, byte);
    Code:
       0: invokestatic  #23                 // Method org/mockito/internal/progress/ThreadSafeMockingProgress.mockingProgress:()Lorg/mockito/internal/progress/MockingProgress;
       3: invokeinterface #24,  1           // InterfaceMethod org/mockito/internal/progress/MockingProgress.getArgumentMatcherStorage:()Lorg/mockito/internal/progress/ArgumentMatcherStorage;
       8: invokeinterface #25,  1           // InterfaceMethod org/mockito/internal/progress/ArgumentMatcherStorage.reportAnd:()V
      13: iconst_0
      14: ireturn

  public static char and(char, char);
    Code:
       0: invokestatic  #23                 // Method org/mockito/internal/progress/ThreadSafeMockingProgress.mockingProgress:()Lorg/mockito/internal/progress/MockingProgress;
       3: invokeinterface #24,  1           // InterfaceMethod org/mockito/internal/progress/MockingProgress.getArgumentMatcherStorage:()Lorg/mockito/internal/progress/ArgumentMatcherStorage;
       8: invokeinterface #25,  1           // InterfaceMethod org/mockito/internal/progress/ArgumentMatcherStorage.reportAnd:()V
      13: iconst_0
      14: ireturn

  public static double and(double, double);
    Code:
       0: invokestatic  #23                 // Method org/mockito/internal/progress/ThreadSafeMockingProgress.mockingProgress:()Lorg/mockito/internal/progress/MockingProgress;
       3: invokeinterface #24,  1           // InterfaceMethod org/mockito/internal/progress/MockingProgress.getArgumentMatcherStorage:()Lorg/mockito/internal/progress/ArgumentMatcherStorage;
       8: invokeinterface #25,  1           // InterfaceMethod org/mockito/internal/progress/ArgumentMatcherStorage.reportAnd:()V
      13: dconst_0
      14: dreturn

  public static float and(float, float);
    Code:
       0: invokestatic  #23                 // Method org/mockito/internal/progress/ThreadSafeMockingProgress.mockingProgress:()Lorg/mockito/internal/progress/MockingProgress;
       3: invokeinterface #24,  1           // InterfaceMethod org/mockito/internal/progress/MockingProgress.getArgumentMatcherStorage:()Lorg/mockito/internal/progress/ArgumentMatcherStorage;
       8: invokeinterface #25,  1           // InterfaceMethod org/mockito/internal/progress/ArgumentMatcherStorage.reportAnd:()V
      13: fconst_0
      14: freturn

  public static int and(int, int);
    Code:
       0: invokestatic  #23                 // Method org/mockito/internal/progress/ThreadSafeMockingProgress.mockingProgress:()Lorg/mockito/internal/progress/MockingProgress;
       3: invokeinterface #24,  1           // InterfaceMethod org/mockito/internal/progress/MockingProgress.getArgumentMatcherStorage:()Lorg/mockito/internal/progress/ArgumentMatcherStorage;
       8: invokeinterface #25,  1           // InterfaceMethod org/mockito/internal/progress/ArgumentMatcherStorage.reportAnd:()V
      13: iconst_0
      14: ireturn

  public static long and(long, long);
    Code:
       0: invokestatic  #23                 // Method org/mockito/internal/progress/ThreadSafeMockingProgress.mockingProgress:()Lorg/mockito/internal/progress/MockingProgress;
       3: invokeinterface #24,  1           // InterfaceMethod org/mockito/internal/progress/MockingProgress.getArgumentMatcherStorage:()Lorg/mockito/internal/progress/ArgumentMatcherStorage;
       8: invokeinterface #25,  1           // InterfaceMethod org/mockito/internal/progress/ArgumentMatcherStorage.reportAnd:()V
      13: lconst_0
      14: lreturn

  public static short and(short, short);
    Code:
       0: invokestatic  #23                 // Method org/mockito/internal/progress/ThreadSafeMockingProgress.mockingProgress:()Lorg/mockito/internal/progress/MockingProgress;
       3: invokeinterface #24,  1           // InterfaceMethod org/mockito/internal/progress/MockingProgress.getArgumentMatcherStorage:()Lorg/mockito/internal/progress/ArgumentMatcherStorage;
       8: invokeinterface #25,  1           // InterfaceMethod org/mockito/internal/progress/ArgumentMatcherStorage.reportAnd:()V
      13: iconst_0
      14: ireturn

  public static <T> T and(T, T);
    Code:
       0: invokestatic  #23                 // Method org/mockito/internal/progress/ThreadSafeMockingProgress.mockingProgress:()Lorg/mockito/internal/progress/MockingProgress;
       3: invokeinterface #24,  1           // InterfaceMethod org/mockito/internal/progress/MockingProgress.getArgumentMatcherStorage:()Lorg/mockito/internal/progress/ArgumentMatcherStorage;
       8: invokeinterface #25,  1           // InterfaceMethod org/mockito/internal/progress/ArgumentMatcherStorage.reportAnd:()V
      13: aconst_null
      14: areturn

  public static boolean or(boolean, boolean);
    Code:
       0: invokestatic  #23                 // Method org/mockito/internal/progress/ThreadSafeMockingProgress.mockingProgress:()Lorg/mockito/internal/progress/MockingProgress;
       3: invokeinterface #24,  1           // InterfaceMethod org/mockito/internal/progress/MockingProgress.getArgumentMatcherStorage:()Lorg/mockito/internal/progress/ArgumentMatcherStorage;
       8: invokeinterface #26,  1           // InterfaceMethod org/mockito/internal/progress/ArgumentMatcherStorage.reportOr:()V
      13: iconst_0
      14: ireturn

  public static <T> T or(T, T);
    Code:
       0: invokestatic  #23                 // Method org/mockito/internal/progress/ThreadSafeMockingProgress.mockingProgress:()Lorg/mockito/internal/progress/MockingProgress;
       3: invokeinterface #24,  1           // InterfaceMethod org/mockito/internal/progress/MockingProgress.getArgumentMatcherStorage:()Lorg/mockito/internal/progress/ArgumentMatcherStorage;
       8: invokeinterface #26,  1           // InterfaceMethod org/mockito/internal/progress/ArgumentMatcherStorage.reportOr:()V
      13: aconst_null
      14: areturn

  public static short or(short, short);
    Code:
       0: invokestatic  #23                 // Method org/mockito/internal/progress/ThreadSafeMockingProgress.mockingProgress:()Lorg/mockito/internal/progress/MockingProgress;
       3: invokeinterface #24,  1           // InterfaceMethod org/mockito/internal/progress/MockingProgress.getArgumentMatcherStorage:()Lorg/mockito/internal/progress/ArgumentMatcherStorage;
       8: invokeinterface #26,  1           // InterfaceMethod org/mockito/internal/progress/ArgumentMatcherStorage.reportOr:()V
      13: iconst_0
      14: ireturn

  public static long or(long, long);
    Code:
       0: invokestatic  #23                 // Method org/mockito/internal/progress/ThreadSafeMockingProgress.mockingProgress:()Lorg/mockito/internal/progress/MockingProgress;
       3: invokeinterface #24,  1           // InterfaceMethod org/mockito/internal/progress/MockingProgress.getArgumentMatcherStorage:()Lorg/mockito/internal/progress/ArgumentMatcherStorage;
       8: invokeinterface #26,  1           // InterfaceMethod org/mockito/internal/progress/ArgumentMatcherStorage.reportOr:()V
      13: lconst_0
      14: lreturn

  public static int or(int, int);
    Code:
       0: invokestatic  #23                 // Method org/mockito/internal/progress/ThreadSafeMockingProgress.mockingProgress:()Lorg/mockito/internal/progress/MockingProgress;
       3: invokeinterface #24,  1           // InterfaceMethod org/mockito/internal/progress/MockingProgress.getArgumentMatcherStorage:()Lorg/mockito/internal/progress/ArgumentMatcherStorage;
       8: invokeinterface #26,  1           // InterfaceMethod org/mockito/internal/progress/ArgumentMatcherStorage.reportOr:()V
      13: iconst_0
      14: ireturn

  public static float or(float, float);
    Code:
       0: invokestatic  #23                 // Method org/mockito/internal/progress/ThreadSafeMockingProgress.mockingProgress:()Lorg/mockito/internal/progress/MockingProgress;
       3: invokeinterface #24,  1           // InterfaceMethod org/mockito/internal/progress/MockingProgress.getArgumentMatcherStorage:()Lorg/mockito/internal/progress/ArgumentMatcherStorage;
       8: invokeinterface #26,  1           // InterfaceMethod org/mockito/internal/progress/ArgumentMatcherStorage.reportOr:()V
      13: fconst_0
      14: freturn

  public static double or(double, double);
    Code:
       0: invokestatic  #23                 // Method org/mockito/internal/progress/ThreadSafeMockingProgress.mockingProgress:()Lorg/mockito/internal/progress/MockingProgress;
       3: invokeinterface #24,  1           // InterfaceMethod org/mockito/internal/progress/MockingProgress.getArgumentMatcherStorage:()Lorg/mockito/internal/progress/ArgumentMatcherStorage;
       8: invokeinterface #26,  1           // InterfaceMethod org/mockito/internal/progress/ArgumentMatcherStorage.reportOr:()V
      13: dconst_0
      14: dreturn

  public static char or(char, char);
    Code:
       0: invokestatic  #23                 // Method org/mockito/internal/progress/ThreadSafeMockingProgress.mockingProgress:()Lorg/mockito/internal/progress/MockingProgress;
       3: invokeinterface #24,  1           // InterfaceMethod org/mockito/internal/progress/MockingProgress.getArgumentMatcherStorage:()Lorg/mockito/internal/progress/ArgumentMatcherStorage;
       8: invokeinterface #26,  1           // InterfaceMethod org/mockito/internal/progress/ArgumentMatcherStorage.reportOr:()V
      13: iconst_0
      14: ireturn

  public static byte or(byte, byte);
    Code:
       0: invokestatic  #23                 // Method org/mockito/internal/progress/ThreadSafeMockingProgress.mockingProgress:()Lorg/mockito/internal/progress/MockingProgress;
       3: invokeinterface #24,  1           // InterfaceMethod org/mockito/internal/progress/MockingProgress.getArgumentMatcherStorage:()Lorg/mockito/internal/progress/ArgumentMatcherStorage;
       8: invokeinterface #26,  1           // InterfaceMethod org/mockito/internal/progress/ArgumentMatcherStorage.reportOr:()V
      13: iconst_0
      14: ireturn

  public static <T> T not(T);
    Code:
       0: invokestatic  #23                 // Method org/mockito/internal/progress/ThreadSafeMockingProgress.mockingProgress:()Lorg/mockito/internal/progress/MockingProgress;
       3: invokeinterface #24,  1           // InterfaceMethod org/mockito/internal/progress/MockingProgress.getArgumentMatcherStorage:()Lorg/mockito/internal/progress/ArgumentMatcherStorage;
       8: invokeinterface #27,  1           // InterfaceMethod org/mockito/internal/progress/ArgumentMatcherStorage.reportNot:()V
      13: aconst_null
      14: areturn

  public static short not(short);
    Code:
       0: invokestatic  #23                 // Method org/mockito/internal/progress/ThreadSafeMockingProgress.mockingProgress:()Lorg/mockito/internal/progress/MockingProgress;
       3: invokeinterface #24,  1           // InterfaceMethod org/mockito/internal/progress/MockingProgress.getArgumentMatcherStorage:()Lorg/mockito/internal/progress/ArgumentMatcherStorage;
       8: invokeinterface #27,  1           // InterfaceMethod org/mockito/internal/progress/ArgumentMatcherStorage.reportNot:()V
      13: iconst_0
      14: ireturn

  public static int not(int);
    Code:
       0: invokestatic  #23                 // Method org/mockito/internal/progress/ThreadSafeMockingProgress.mockingProgress:()Lorg/mockito/internal/progress/MockingProgress;
       3: invokeinterface #24,  1           // InterfaceMethod org/mockito/internal/progress/MockingProgress.getArgumentMatcherStorage:()Lorg/mockito/internal/progress/ArgumentMatcherStorage;
       8: invokeinterface #27,  1           // InterfaceMethod org/mockito/internal/progress/ArgumentMatcherStorage.reportNot:()V
      13: iconst_0
      14: ireturn

  public static long not(long);
    Code:
       0: invokestatic  #23                 // Method org/mockito/internal/progress/ThreadSafeMockingProgress.mockingProgress:()Lorg/mockito/internal/progress/MockingProgress;
       3: invokeinterface #24,  1           // InterfaceMethod org/mockito/internal/progress/MockingProgress.getArgumentMatcherStorage:()Lorg/mockito/internal/progress/ArgumentMatcherStorage;
       8: invokeinterface #27,  1           // InterfaceMethod org/mockito/internal/progress/ArgumentMatcherStorage.reportNot:()V
      13: lconst_0
      14: lreturn

  public static float not(float);
    Code:
       0: invokestatic  #23                 // Method org/mockito/internal/progress/ThreadSafeMockingProgress.mockingProgress:()Lorg/mockito/internal/progress/MockingProgress;
       3: invokeinterface #24,  1           // InterfaceMethod org/mockito/internal/progress/MockingProgress.getArgumentMatcherStorage:()Lorg/mockito/internal/progress/ArgumentMatcherStorage;
       8: invokeinterface #27,  1           // InterfaceMethod org/mockito/internal/progress/ArgumentMatcherStorage.reportNot:()V
      13: fconst_0
      14: freturn

  public static double not(double);
    Code:
       0: invokestatic  #23                 // Method org/mockito/internal/progress/ThreadSafeMockingProgress.mockingProgress:()Lorg/mockito/internal/progress/MockingProgress;
       3: invokeinterface #24,  1           // InterfaceMethod org/mockito/internal/progress/MockingProgress.getArgumentMatcherStorage:()Lorg/mockito/internal/progress/ArgumentMatcherStorage;
       8: invokeinterface #27,  1           // InterfaceMethod org/mockito/internal/progress/ArgumentMatcherStorage.reportNot:()V
      13: dconst_0
      14: dreturn

  public static char not(char);
    Code:
       0: invokestatic  #23                 // Method org/mockito/internal/progress/ThreadSafeMockingProgress.mockingProgress:()Lorg/mockito/internal/progress/MockingProgress;
       3: invokeinterface #24,  1           // InterfaceMethod org/mockito/internal/progress/MockingProgress.getArgumentMatcherStorage:()Lorg/mockito/internal/progress/ArgumentMatcherStorage;
       8: invokeinterface #27,  1           // InterfaceMethod org/mockito/internal/progress/ArgumentMatcherStorage.reportNot:()V
      13: iconst_0
      14: ireturn

  public static boolean not(boolean);
    Code:
       0: invokestatic  #23                 // Method org/mockito/internal/progress/ThreadSafeMockingProgress.mockingProgress:()Lorg/mockito/internal/progress/MockingProgress;
       3: invokeinterface #24,  1           // InterfaceMethod org/mockito/internal/progress/MockingProgress.getArgumentMatcherStorage:()Lorg/mockito/internal/progress/ArgumentMatcherStorage;
       8: invokeinterface #27,  1           // InterfaceMethod org/mockito/internal/progress/ArgumentMatcherStorage.reportNot:()V
      13: iconst_0
      14: ireturn

  public static byte not(byte);
    Code:
       0: invokestatic  #23                 // Method org/mockito/internal/progress/ThreadSafeMockingProgress.mockingProgress:()Lorg/mockito/internal/progress/MockingProgress;
       3: invokeinterface #24,  1           // InterfaceMethod org/mockito/internal/progress/MockingProgress.getArgumentMatcherStorage:()Lorg/mockito/internal/progress/ArgumentMatcherStorage;
       8: invokeinterface #27,  1           // InterfaceMethod org/mockito/internal/progress/ArgumentMatcherStorage.reportNot:()V
      13: iconst_0
      14: ireturn

  public static double eq(double, double);
    Code:
       0: new           #28                 // class org/mockito/internal/matchers/EqualsWithDelta
       3: dup
       4: dload_0
       5: invokestatic  #6                  // Method java/lang/Double.valueOf:(D)Ljava/lang/Double;
       8: dload_2
       9: invokestatic  #6                  // Method java/lang/Double.valueOf:(D)Ljava/lang/Double;
      12: invokespecial #29                 // Method org/mockito/internal/matchers/EqualsWithDelta."<init>":(Ljava/lang/Number;Ljava/lang/Number;)V
      15: invokestatic  #4                  // Method reportMatcher:(Lorg/mockito/ArgumentMatcher;)V
      18: dconst_0
      19: dreturn

  public static float eq(float, float);
    Code:
       0: new           #28                 // class org/mockito/internal/matchers/EqualsWithDelta
       3: dup
       4: fload_0
       5: invokestatic  #7                  // Method java/lang/Float.valueOf:(F)Ljava/lang/Float;
       8: fload_1
       9: invokestatic  #7                  // Method java/lang/Float.valueOf:(F)Ljava/lang/Float;
      12: invokespecial #29                 // Method org/mockito/internal/matchers/EqualsWithDelta."<init>":(Ljava/lang/Number;Ljava/lang/Number;)V
      15: invokestatic  #4                  // Method reportMatcher:(Lorg/mockito/ArgumentMatcher;)V
      18: fconst_0
      19: freturn

  private static void reportMatcher(org.mockito.ArgumentMatcher<?>);
    Code:
       0: invokestatic  #23                 // Method org/mockito/internal/progress/ThreadSafeMockingProgress.mockingProgress:()Lorg/mockito/internal/progress/MockingProgress;
       3: invokeinterface #24,  1           // InterfaceMethod org/mockito/internal/progress/MockingProgress.getArgumentMatcherStorage:()Lorg/mockito/internal/progress/ArgumentMatcherStorage;
       8: aload_0
       9: invokeinterface #30,  2           // InterfaceMethod org/mockito/internal/progress/ArgumentMatcherStorage.reportMatcher:(Lorg/mockito/ArgumentMatcher;)V
      14: return
}
