Compiled from "StreamScanner.java"
public abstract class com.ctc.wstx.sr.StreamScanner extends com.ctc.wstx.io.WstxInputData implements com.ctc.wstx.sr.InputProblemReporter,com.ctc.wstx.cfg.InputConfigFlags,com.ctc.wstx.cfg.ParsingErrorMsgs {
  public static final char CHAR_CR_LF_OR_NULL;

  public static final int INT_CR_LF_OR_NULL;

  protected static final char CHAR_FIRST_PURE_TEXT;

  protected static final char CHAR_LOWEST_LEGAL_LOCALNAME_CHAR;

  private static final int VALID_CHAR_COUNT;

  private static final byte NAME_CHAR_INVALID_B;

  private static final byte NAME_CHAR_ALL_VALID_B;

  private static final byte NAME_CHAR_VALID_NONFIRST_B;

  private static final byte[] sCharValidity;

  private static final int VALID_PUBID_CHAR_COUNT;

  private static final byte[] sPubidValidity;

  private static final byte PUBID_CHAR_VALID_B;

  protected final com.ctc.wstx.api.ReaderConfig mConfig;

  protected final boolean mCfgNsEnabled;

  protected boolean mCfgReplaceEntities;

  final com.ctc.wstx.util.SymbolTable mSymbols;

  protected java.lang.String mCurrName;

  protected com.ctc.wstx.io.WstxInputSource mInput;

  protected final com.ctc.wstx.io.WstxInputSource mRootInput;

  protected javax.xml.stream.XMLResolver mEntityResolver;

  protected int mCurrDepth;

  protected int mInputTopDepth;

  protected int mEntityExpansionCount;

  protected boolean mNormalizeLFs;

  protected boolean mAllowXml11EscapedCharsInXml10;

  protected char[] mNameBuffer;

  protected long mTokenInputTotal;

  protected int mTokenInputRow;

  protected int mTokenInputCol;

  protected java.lang.String mDocInputEncoding;

  protected java.lang.String mDocXmlEncoding;

  protected int mDocXmlVersion;

  protected java.util.Map<java.lang.String, com.ctc.wstx.ent.IntEntity> mCachedEntities;

  protected boolean mCfgTreatCharRefsAsEntities;

  protected com.ctc.wstx.ent.EntityDecl mCurrEntity;

  protected com.ctc.wstx.sr.StreamScanner(com.ctc.wstx.io.WstxInputSource, com.ctc.wstx.api.ReaderConfig, javax.xml.stream.XMLResolver);
    Code:
       0: aload_0
       1: invokespecial #1                  // Method com/ctc/wstx/io/WstxInputData."<init>":()V
       4: aload_0
       5: aconst_null
       6: putfield      #2                  // Field mEntityResolver:Ljavax/xml/stream/XMLResolver;
       9: aload_0
      10: aconst_null
      11: putfield      #3                  // Field mNameBuffer:[C
      14: aload_0
      15: lconst_0
      16: putfield      #4                  // Field mTokenInputTotal:J
      19: aload_0
      20: iconst_1
      21: putfield      #5                  // Field mTokenInputRow:I
      24: aload_0
      25: iconst_0
      26: putfield      #6                  // Field mTokenInputCol:I
      29: aload_0
      30: aconst_null
      31: putfield      #7                  // Field mDocInputEncoding:Ljava/lang/String;
      34: aload_0
      35: aconst_null
      36: putfield      #8                  // Field mDocXmlEncoding:Ljava/lang/String;
      39: aload_0
      40: iconst_0
      41: putfield      #10                 // Field mDocXmlVersion:I
      44: aload_0
      45: aload_1
      46: putfield      #11                 // Field mInput:Lcom/ctc/wstx/io/WstxInputSource;
      49: aload_0
      50: aload_1
      51: putfield      #12                 // Field mRootInput:Lcom/ctc/wstx/io/WstxInputSource;
      54: aload_0
      55: aload_2
      56: putfield      #13                 // Field mConfig:Lcom/ctc/wstx/api/ReaderConfig;
      59: aload_0
      60: aload_2
      61: invokevirtual #14                 // Method com/ctc/wstx/api/ReaderConfig.getSymbols:()Lcom/ctc/wstx/util/SymbolTable;
      64: putfield      #15                 // Field mSymbols:Lcom/ctc/wstx/util/SymbolTable;
      67: aload_2
      68: invokevirtual #16                 // Method com/ctc/wstx/api/ReaderConfig.getConfigFlags:()I
      71: istore        4
      73: aload_0
      74: iload         4
      76: iconst_1
      77: iand
      78: ifeq          85
      81: iconst_1
      82: goto          86
      85: iconst_0
      86: putfield      #18                 // Field mCfgNsEnabled:Z
      89: aload_0
      90: iload         4
      92: iconst_4
      93: iand
      94: ifeq          101
      97: iconst_1
      98: goto          102
     101: iconst_0
     102: putfield      #19                 // Field mCfgReplaceEntities:Z
     105: aload_0
     106: aload_0
     107: getfield      #13                 // Field mConfig:Lcom/ctc/wstx/api/ReaderConfig;
     110: invokevirtual #20                 // Method com/ctc/wstx/api/ReaderConfig.willAllowXml11EscapedCharsInXml10:()Z
     113: putfield      #21                 // Field mAllowXml11EscapedCharsInXml10:Z
     116: aload_0
     117: aload_0
     118: getfield      #13                 // Field mConfig:Lcom/ctc/wstx/api/ReaderConfig;
     121: invokevirtual #22                 // Method com/ctc/wstx/api/ReaderConfig.willNormalizeLFs:()Z
     124: putfield      #23                 // Field mNormalizeLFs:Z
     127: aload_0
     128: aconst_null
     129: putfield      #24                 // Field mInputBuffer:[C
     132: aload_0
     133: aload_0
     134: iconst_0
     135: dup_x1
     136: putfield      #25                 // Field mInputEnd:I
     139: putfield      #26                 // Field mInputPtr:I
     142: aload_0
     143: aload_3
     144: putfield      #2                  // Field mEntityResolver:Ljavax/xml/stream/XMLResolver;
     147: aload_0
     148: aload_0
     149: getfield      #13                 // Field mConfig:Lcom/ctc/wstx/api/ReaderConfig;
     152: invokevirtual #27                 // Method com/ctc/wstx/api/ReaderConfig.willTreatCharRefsAsEnts:()Z
     155: putfield      #28                 // Field mCfgTreatCharRefsAsEntities:Z
     158: aload_0
     159: getfield      #28                 // Field mCfgTreatCharRefsAsEntities:Z
     162: ifeq          179
     165: aload_0
     166: new           #29                 // class java/util/HashMap
     169: dup
     170: invokespecial #30                 // Method java/util/HashMap."<init>":()V
     173: putfield      #31                 // Field mCachedEntities:Ljava/util/Map;
     176: goto          186
     179: aload_0
     180: invokestatic  #32                 // Method java/util/Collections.emptyMap:()Ljava/util/Map;
     183: putfield      #31                 // Field mCachedEntities:Ljava/util/Map;
     186: return

  public com.ctc.wstx.api.ReaderConfig getConfig();
    Code:
       0: aload_0
       1: getfield      #13                 // Field mConfig:Lcom/ctc/wstx/api/ReaderConfig;
       4: areturn

  protected com.ctc.wstx.io.WstxInputLocation getLastCharLocation();
    Code:
       0: aload_0
       1: getfield      #11                 // Field mInput:Lcom/ctc/wstx/io/WstxInputSource;
       4: aload_0
       5: getfield      #33                 // Field mCurrInputProcessed:J
       8: aload_0
       9: getfield      #26                 // Field mInputPtr:I
      12: i2l
      13: ladd
      14: lconst_1
      15: lsub
      16: aload_0
      17: getfield      #34                 // Field mCurrInputRow:I
      20: aload_0
      21: getfield      #26                 // Field mInputPtr:I
      24: aload_0
      25: getfield      #35                 // Field mCurrInputRowStart:I
      28: isub
      29: invokevirtual #36                 // Method com/ctc/wstx/io/WstxInputSource.getLocation:(JII)Lcom/ctc/wstx/io/WstxInputLocation;
      32: areturn

  protected java.net.URL getSource() throws java.io.IOException;
    Code:
       0: aload_0
       1: getfield      #11                 // Field mInput:Lcom/ctc/wstx/io/WstxInputSource;
       4: invokevirtual #37                 // Method com/ctc/wstx/io/WstxInputSource.getSource:()Ljava/net/URL;
       7: areturn

  protected java.lang.String getSystemId();
    Code:
       0: aload_0
       1: getfield      #11                 // Field mInput:Lcom/ctc/wstx/io/WstxInputSource;
       4: invokevirtual #38                 // Method com/ctc/wstx/io/WstxInputSource.getSystemId:()Ljava/lang/String;
       7: areturn

  public abstract javax.xml.stream.Location getLocation();

  public org.codehaus.stax2.XMLStreamLocation2 getStartLocation();
    Code:
       0: aload_0
       1: getfield      #11                 // Field mInput:Lcom/ctc/wstx/io/WstxInputSource;
       4: aload_0
       5: getfield      #4                  // Field mTokenInputTotal:J
       8: aload_0
       9: getfield      #5                  // Field mTokenInputRow:I
      12: aload_0
      13: getfield      #6                  // Field mTokenInputCol:I
      16: iconst_1
      17: iadd
      18: invokevirtual #36                 // Method com/ctc/wstx/io/WstxInputSource.getLocation:(JII)Lcom/ctc/wstx/io/WstxInputLocation;
      21: areturn

  public org.codehaus.stax2.XMLStreamLocation2 getCurrentLocation();
    Code:
       0: aload_0
       1: getfield      #11                 // Field mInput:Lcom/ctc/wstx/io/WstxInputSource;
       4: aload_0
       5: getfield      #33                 // Field mCurrInputProcessed:J
       8: aload_0
       9: getfield      #26                 // Field mInputPtr:I
      12: i2l
      13: ladd
      14: aload_0
      15: getfield      #34                 // Field mCurrInputRow:I
      18: aload_0
      19: getfield      #26                 // Field mInputPtr:I
      22: aload_0
      23: getfield      #35                 // Field mCurrInputRowStart:I
      26: isub
      27: iconst_1
      28: iadd
      29: invokevirtual #36                 // Method com/ctc/wstx/io/WstxInputSource.getLocation:(JII)Lcom/ctc/wstx/io/WstxInputLocation;
      32: areturn

  public com.ctc.wstx.exc.WstxException throwWfcException(java.lang.String, boolean) throws com.ctc.wstx.exc.WstxException;
    Code:
       0: aload_0
       1: aload_1
       2: invokevirtual #39                 // Method constructWfcException:(Ljava/lang/String;)Lcom/ctc/wstx/exc/WstxException;
       5: astore_3
       6: iload_2
       7: ifne          12
      10: aload_3
      11: athrow
      12: aload_3
      13: areturn

  public void throwParseError(java.lang.String) throws javax.xml.stream.XMLStreamException;
    Code:
       0: aload_0
       1: aload_1
       2: aconst_null
       3: aconst_null
       4: invokevirtual #40                 // Method throwParseError:(Ljava/lang/String;Ljava/lang/Object;Ljava/lang/Object;)V
       7: return

  public void throwParseError(java.lang.String, java.lang.Object, java.lang.Object) throws javax.xml.stream.XMLStreamException;
    Code:
       0: aload_2
       1: ifnonnull     8
       4: aload_3
       5: ifnull        27
       8: aload_1
       9: iconst_2
      10: anewarray     #41                 // class java/lang/Object
      13: dup
      14: iconst_0
      15: aload_2
      16: aastore
      17: dup
      18: iconst_1
      19: aload_3
      20: aastore
      21: invokestatic  #42                 // Method java/text/MessageFormat.format:(Ljava/lang/String;[Ljava/lang/Object;)Ljava/lang/String;
      24: goto          28
      27: aload_1
      28: astore        4
      30: aload_0
      31: aload         4
      33: invokevirtual #39                 // Method constructWfcException:(Ljava/lang/String;)Lcom/ctc/wstx/exc/WstxException;
      36: athrow

  public void reportProblem(java.lang.String, java.lang.String, java.lang.Object, java.lang.Object) throws javax.xml.stream.XMLStreamException;
    Code:
       0: aload_0
       1: getfield      #13                 // Field mConfig:Lcom/ctc/wstx/api/ReaderConfig;
       4: invokevirtual #43                 // Method com/ctc/wstx/api/ReaderConfig.getXMLReporter:()Ljavax/xml/stream/XMLReporter;
       7: astore        5
       9: aload         5
      11: ifnull        39
      14: aload_0
      15: aload         5
      17: aload_1
      18: aload_2
      19: iconst_2
      20: anewarray     #41                 // class java/lang/Object
      23: dup
      24: iconst_0
      25: aload_3
      26: aastore
      27: dup
      28: iconst_1
      29: aload         4
      31: aastore
      32: invokestatic  #42                 // Method java/text/MessageFormat.format:(Ljava/lang/String;[Ljava/lang/Object;)Ljava/lang/String;
      35: aconst_null
      36: invokevirtual #44                 // Method _reportProblem:(Ljavax/xml/stream/XMLReporter;Ljava/lang/String;Ljava/lang/String;Ljavax/xml/stream/Location;)V
      39: return

  public void reportProblem(javax.xml.stream.Location, java.lang.String, java.lang.String, java.lang.Object, java.lang.Object) throws javax.xml.stream.XMLStreamException;
    Code:
       0: aload_0
       1: getfield      #13                 // Field mConfig:Lcom/ctc/wstx/api/ReaderConfig;
       4: invokevirtual #43                 // Method com/ctc/wstx/api/ReaderConfig.getXMLReporter:()Ljavax/xml/stream/XMLReporter;
       7: astore        6
       9: aload         6
      11: ifnull        58
      14: aload         4
      16: ifnonnull     24
      19: aload         5
      21: ifnull        45
      24: aload_3
      25: iconst_2
      26: anewarray     #41                 // class java/lang/Object
      29: dup
      30: iconst_0
      31: aload         4
      33: aastore
      34: dup
      35: iconst_1
      36: aload         5
      38: aastore
      39: invokestatic  #42                 // Method java/text/MessageFormat.format:(Ljava/lang/String;[Ljava/lang/Object;)Ljava/lang/String;
      42: goto          46
      45: aload_3
      46: astore        7
      48: aload_0
      49: aload         6
      51: aload_2
      52: aload         7
      54: aload_1
      55: invokevirtual #44                 // Method _reportProblem:(Ljavax/xml/stream/XMLReporter;Ljava/lang/String;Ljava/lang/String;Ljavax/xml/stream/Location;)V
      58: return

  protected void _reportProblem(javax.xml.stream.XMLReporter, java.lang.String, java.lang.String, javax.xml.stream.Location) throws javax.xml.stream.XMLStreamException;
    Code:
       0: aload         4
       2: ifnonnull     11
       5: aload_0
       6: invokevirtual #45                 // Method getLastCharLocation:()Lcom/ctc/wstx/io/WstxInputLocation;
       9: astore        4
      11: aload_0
      12: aload_1
      13: new           #46                 // class org/codehaus/stax2/validation/XMLValidationProblem
      16: dup
      17: aload         4
      19: aload_3
      20: iconst_2
      21: aload_2
      22: invokespecial #47                 // Method org/codehaus/stax2/validation/XMLValidationProblem."<init>":(Ljavax/xml/stream/Location;Ljava/lang/String;ILjava/lang/String;)V
      25: invokevirtual #48                 // Method _reportProblem:(Ljavax/xml/stream/XMLReporter;Lorg/codehaus/stax2/validation/XMLValidationProblem;)V
      28: return

  protected void _reportProblem(javax.xml.stream.XMLReporter, org.codehaus.stax2.validation.XMLValidationProblem) throws javax.xml.stream.XMLStreamException;
    Code:
       0: aload_1
       1: ifnull        73
       4: aload_2
       5: invokevirtual #49                 // Method org/codehaus/stax2/validation/XMLValidationProblem.getLocation:()Ljavax/xml/stream/Location;
       8: astore_3
       9: aload_3
      10: ifnonnull     23
      13: aload_0
      14: invokevirtual #45                 // Method getLastCharLocation:()Lcom/ctc/wstx/io/WstxInputLocation;
      17: astore_3
      18: aload_2
      19: aload_3
      20: invokevirtual #50                 // Method org/codehaus/stax2/validation/XMLValidationProblem.setLocation:(Ljavax/xml/stream/Location;)V
      23: aload_2
      24: invokevirtual #51                 // Method org/codehaus/stax2/validation/XMLValidationProblem.getType:()Ljava/lang/String;
      27: ifnonnull     37
      30: aload_2
      31: getstatic     #52                 // Field com/ctc/wstx/cfg/ErrorConsts.WT_VALIDATION:Ljava/lang/String;
      34: invokevirtual #53                 // Method org/codehaus/stax2/validation/XMLValidationProblem.setType:(Ljava/lang/String;)V
      37: aload_1
      38: instanceof    #54                 // class org/codehaus/stax2/XMLReporter2
      41: ifeq          57
      44: aload_1
      45: checkcast     #54                 // class org/codehaus/stax2/XMLReporter2
      48: aload_2
      49: invokeinterface #55,  2           // InterfaceMethod org/codehaus/stax2/XMLReporter2.report:(Lorg/codehaus/stax2/validation/XMLValidationProblem;)V
      54: goto          73
      57: aload_1
      58: aload_2
      59: invokevirtual #56                 // Method org/codehaus/stax2/validation/XMLValidationProblem.getMessage:()Ljava/lang/String;
      62: aload_2
      63: invokevirtual #51                 // Method org/codehaus/stax2/validation/XMLValidationProblem.getType:()Ljava/lang/String;
      66: aload_2
      67: aload_3
      68: invokeinterface #57,  5           // InterfaceMethod javax/xml/stream/XMLReporter.report:(Ljava/lang/String;Ljava/lang/String;Ljava/lang/Object;Ljavax/xml/stream/Location;)V
      73: return

  public void reportValidationProblem(org.codehaus.stax2.validation.XMLValidationProblem) throws javax.xml.stream.XMLStreamException;
    Code:
       0: aload_1
       1: invokevirtual #58                 // Method org/codehaus/stax2/validation/XMLValidationProblem.getSeverity:()I
       4: iconst_2
       5: if_icmple     13
       8: aload_1
       9: invokestatic  #59                 // Method com/ctc/wstx/exc/WstxValidationException.create:(Lorg/codehaus/stax2/validation/XMLValidationProblem;)Lcom/ctc/wstx/exc/WstxValidationException;
      12: athrow
      13: aload_0
      14: getfield      #13                 // Field mConfig:Lcom/ctc/wstx/api/ReaderConfig;
      17: invokevirtual #43                 // Method com/ctc/wstx/api/ReaderConfig.getXMLReporter:()Ljavax/xml/stream/XMLReporter;
      20: astore_2
      21: aload_2
      22: ifnull        34
      25: aload_0
      26: aload_2
      27: aload_1
      28: invokevirtual #48                 // Method _reportProblem:(Ljavax/xml/stream/XMLReporter;Lorg/codehaus/stax2/validation/XMLValidationProblem;)V
      31: goto          47
      34: aload_1
      35: invokevirtual #58                 // Method org/codehaus/stax2/validation/XMLValidationProblem.getSeverity:()I
      38: iconst_2
      39: if_icmplt     47
      42: aload_1
      43: invokestatic  #59                 // Method com/ctc/wstx/exc/WstxValidationException.create:(Lorg/codehaus/stax2/validation/XMLValidationProblem;)Lcom/ctc/wstx/exc/WstxValidationException;
      46: athrow
      47: return

  public void reportValidationProblem(java.lang.String, int) throws javax.xml.stream.XMLStreamException;
    Code:
       0: aload_0
       1: new           #46                 // class org/codehaus/stax2/validation/XMLValidationProblem
       4: dup
       5: aload_0
       6: invokevirtual #45                 // Method getLastCharLocation:()Lcom/ctc/wstx/io/WstxInputLocation;
       9: aload_1
      10: iload_2
      11: invokespecial #60                 // Method org/codehaus/stax2/validation/XMLValidationProblem."<init>":(Ljavax/xml/stream/Location;Ljava/lang/String;I)V
      14: invokevirtual #61                 // Method reportValidationProblem:(Lorg/codehaus/stax2/validation/XMLValidationProblem;)V
      17: return

  public void reportValidationProblem(java.lang.String) throws javax.xml.stream.XMLStreamException;
    Code:
       0: aload_0
       1: new           #46                 // class org/codehaus/stax2/validation/XMLValidationProblem
       4: dup
       5: aload_0
       6: invokevirtual #45                 // Method getLastCharLocation:()Lcom/ctc/wstx/io/WstxInputLocation;
       9: aload_1
      10: iconst_2
      11: invokespecial #60                 // Method org/codehaus/stax2/validation/XMLValidationProblem."<init>":(Ljavax/xml/stream/Location;Ljava/lang/String;I)V
      14: invokevirtual #61                 // Method reportValidationProblem:(Lorg/codehaus/stax2/validation/XMLValidationProblem;)V
      17: return

  public void reportValidationProblem(javax.xml.stream.Location, java.lang.String) throws javax.xml.stream.XMLStreamException;
    Code:
       0: aload_0
       1: new           #46                 // class org/codehaus/stax2/validation/XMLValidationProblem
       4: dup
       5: aload_1
       6: aload_2
       7: invokespecial #62                 // Method org/codehaus/stax2/validation/XMLValidationProblem."<init>":(Ljavax/xml/stream/Location;Ljava/lang/String;)V
      10: invokevirtual #61                 // Method reportValidationProblem:(Lorg/codehaus/stax2/validation/XMLValidationProblem;)V
      13: return

  public void reportValidationProblem(java.lang.String, java.lang.Object, java.lang.Object) throws javax.xml.stream.XMLStreamException;
    Code:
       0: aload_0
       1: aload_1
       2: iconst_2
       3: anewarray     #41                 // class java/lang/Object
       6: dup
       7: iconst_0
       8: aload_2
       9: aastore
      10: dup
      11: iconst_1
      12: aload_3
      13: aastore
      14: invokestatic  #42                 // Method java/text/MessageFormat.format:(Ljava/lang/String;[Ljava/lang/Object;)Ljava/lang/String;
      17: invokevirtual #63                 // Method reportValidationProblem:(Ljava/lang/String;)V
      20: return

  protected com.ctc.wstx.exc.WstxException constructWfcException(java.lang.String);
    Code:
       0: new           #64                 // class com/ctc/wstx/exc/WstxParsingException
       3: dup
       4: aload_1
       5: aload_0
       6: invokevirtual #45                 // Method getLastCharLocation:()Lcom/ctc/wstx/io/WstxInputLocation;
       9: invokespecial #65                 // Method com/ctc/wstx/exc/WstxParsingException."<init>":(Ljava/lang/String;Ljavax/xml/stream/Location;)V
      12: areturn

  protected com.ctc.wstx.exc.WstxException constructFromIOE(java.io.IOException);
    Code:
       0: new           #66                 // class com/ctc/wstx/exc/WstxIOException
       3: dup
       4: aload_1
       5: invokespecial #67                 // Method com/ctc/wstx/exc/WstxIOException."<init>":(Ljava/io/IOException;)V
       8: areturn

  protected com.ctc.wstx.exc.WstxException constructNullCharException();
    Code:
       0: new           #68                 // class com/ctc/wstx/exc/WstxUnexpectedCharException
       3: dup
       4: ldc           #69                 // String Illegal character (NULL, unicode 0) encountered: not valid in any content
       6: aload_0
       7: invokevirtual #45                 // Method getLastCharLocation:()Lcom/ctc/wstx/io/WstxInputLocation;
      10: iconst_0
      11: invokespecial #71                 // Method com/ctc/wstx/exc/WstxUnexpectedCharException."<init>":(Ljava/lang/String;Ljavax/xml/stream/Location;C)V
      14: areturn

  protected void throwUnexpectedChar(int, java.lang.String) throws com.ctc.wstx.exc.WstxException;
    Code:
       0: iload_1
       1: i2c
       2: istore_3
       3: new           #72                 // class java/lang/StringBuilder
       6: dup
       7: invokespecial #73                 // Method java/lang/StringBuilder."<init>":()V
      10: ldc           #74                 // String Unexpected character
      12: invokevirtual #75                 // Method java/lang/StringBuilder.append:(Ljava/lang/String;)Ljava/lang/StringBuilder;
      15: iload_3
      16: invokestatic  #76                 // Method getCharDesc:(C)Ljava/lang/String;
      19: invokevirtual #75                 // Method java/lang/StringBuilder.append:(Ljava/lang/String;)Ljava/lang/StringBuilder;
      22: aload_2
      23: invokevirtual #75                 // Method java/lang/StringBuilder.append:(Ljava/lang/String;)Ljava/lang/StringBuilder;
      26: invokevirtual #77                 // Method java/lang/StringBuilder.toString:()Ljava/lang/String;
      29: astore        4
      31: new           #68                 // class com/ctc/wstx/exc/WstxUnexpectedCharException
      34: dup
      35: aload         4
      37: aload_0
      38: invokevirtual #45                 // Method getLastCharLocation:()Lcom/ctc/wstx/io/WstxInputLocation;
      41: iload_3
      42: invokespecial #71                 // Method com/ctc/wstx/exc/WstxUnexpectedCharException."<init>":(Ljava/lang/String;Ljavax/xml/stream/Location;C)V
      45: athrow

  protected void throwNullChar() throws com.ctc.wstx.exc.WstxException;
    Code:
       0: aload_0
       1: invokevirtual #78                 // Method constructNullCharException:()Lcom/ctc/wstx/exc/WstxException;
       4: athrow

  protected void throwInvalidSpace(int) throws com.ctc.wstx.exc.WstxException;
    Code:
       0: aload_0
       1: iload_1
       2: iconst_0
       3: invokevirtual #79                 // Method throwInvalidSpace:(IZ)Lcom/ctc/wstx/exc/WstxException;
       6: pop
       7: return

  protected com.ctc.wstx.exc.WstxException throwInvalidSpace(int, boolean) throws com.ctc.wstx.exc.WstxException;
    Code:
       0: iload_1
       1: i2c
       2: istore_3
       3: iload_3
       4: ifne          16
       7: aload_0
       8: invokevirtual #78                 // Method constructNullCharException:()Lcom/ctc/wstx/exc/WstxException;
      11: astore        4
      13: goto          90
      16: new           #72                 // class java/lang/StringBuilder
      19: dup
      20: invokespecial #73                 // Method java/lang/StringBuilder."<init>":()V
      23: ldc           #80                 // String Illegal character (
      25: invokevirtual #75                 // Method java/lang/StringBuilder.append:(Ljava/lang/String;)Ljava/lang/StringBuilder;
      28: iload_3
      29: invokestatic  #76                 // Method getCharDesc:(C)Ljava/lang/String;
      32: invokevirtual #75                 // Method java/lang/StringBuilder.append:(Ljava/lang/String;)Ljava/lang/StringBuilder;
      35: ldc           #81                 // String )
      37: invokevirtual #75                 // Method java/lang/StringBuilder.append:(Ljava/lang/String;)Ljava/lang/StringBuilder;
      40: invokevirtual #77                 // Method java/lang/StringBuilder.toString:()Ljava/lang/String;
      43: astore        5
      45: aload_0
      46: getfield      #82                 // Field mXml11:Z
      49: ifeq          74
      52: new           #72                 // class java/lang/StringBuilder
      55: dup
      56: invokespecial #73                 // Method java/lang/StringBuilder."<init>":()V
      59: aload         5
      61: invokevirtual #75                 // Method java/lang/StringBuilder.append:(Ljava/lang/String;)Ljava/lang/StringBuilder;
      64: ldc           #83                 // String  [note: in XML 1.1, it could be included via entity expansion]
      66: invokevirtual #75                 // Method java/lang/StringBuilder.append:(Ljava/lang/String;)Ljava/lang/StringBuilder;
      69: invokevirtual #77                 // Method java/lang/StringBuilder.toString:()Ljava/lang/String;
      72: astore        5
      74: new           #68                 // class com/ctc/wstx/exc/WstxUnexpectedCharException
      77: dup
      78: aload         5
      80: aload_0
      81: invokevirtual #45                 // Method getLastCharLocation:()Lcom/ctc/wstx/io/WstxInputLocation;
      84: iload_3
      85: invokespecial #71                 // Method com/ctc/wstx/exc/WstxUnexpectedCharException."<init>":(Ljava/lang/String;Ljavax/xml/stream/Location;C)V
      88: astore        4
      90: iload_2
      91: ifne          97
      94: aload         4
      96: athrow
      97: aload         4
      99: areturn

  protected void throwUnexpectedEOF(java.lang.String) throws com.ctc.wstx.exc.WstxException;
    Code:
       0: new           #84                 // class com/ctc/wstx/exc/WstxEOFException
       3: dup
       4: new           #72                 // class java/lang/StringBuilder
       7: dup
       8: invokespecial #73                 // Method java/lang/StringBuilder."<init>":()V
      11: ldc           #85                 // String Unexpected EOF
      13: invokevirtual #75                 // Method java/lang/StringBuilder.append:(Ljava/lang/String;)Ljava/lang/StringBuilder;
      16: aload_1
      17: ifnonnull     25
      20: ldc           #86                 // String
      22: goto          26
      25: aload_1
      26: invokevirtual #75                 // Method java/lang/StringBuilder.append:(Ljava/lang/String;)Ljava/lang/StringBuilder;
      29: invokevirtual #77                 // Method java/lang/StringBuilder.toString:()Ljava/lang/String;
      32: aload_0
      33: invokevirtual #45                 // Method getLastCharLocation:()Lcom/ctc/wstx/io/WstxInputLocation;
      36: invokespecial #87                 // Method com/ctc/wstx/exc/WstxEOFException."<init>":(Ljava/lang/String;Ljavax/xml/stream/Location;)V
      39: athrow

  protected void throwUnexpectedEOB(java.lang.String) throws com.ctc.wstx.exc.WstxException;
    Code:
       0: new           #84                 // class com/ctc/wstx/exc/WstxEOFException
       3: dup
       4: new           #72                 // class java/lang/StringBuilder
       7: dup
       8: invokespecial #73                 // Method java/lang/StringBuilder."<init>":()V
      11: ldc           #88                 // String Unexpected end of input block
      13: invokevirtual #75                 // Method java/lang/StringBuilder.append:(Ljava/lang/String;)Ljava/lang/StringBuilder;
      16: aload_1
      17: ifnonnull     25
      20: ldc           #86                 // String
      22: goto          26
      25: aload_1
      26: invokevirtual #75                 // Method java/lang/StringBuilder.append:(Ljava/lang/String;)Ljava/lang/StringBuilder;
      29: invokevirtual #77                 // Method java/lang/StringBuilder.toString:()Ljava/lang/String;
      32: aload_0
      33: invokevirtual #45                 // Method getLastCharLocation:()Lcom/ctc/wstx/io/WstxInputLocation;
      36: invokespecial #87                 // Method com/ctc/wstx/exc/WstxEOFException."<init>":(Ljava/lang/String;Ljavax/xml/stream/Location;)V
      39: athrow

  protected void throwFromIOE(java.io.IOException) throws com.ctc.wstx.exc.WstxException;
    Code:
       0: new           #66                 // class com/ctc/wstx/exc/WstxIOException
       3: dup
       4: aload_1
       5: invokespecial #67                 // Method com/ctc/wstx/exc/WstxIOException."<init>":(Ljava/io/IOException;)V
       8: athrow

  protected void throwFromStrE(javax.xml.stream.XMLStreamException) throws com.ctc.wstx.exc.WstxException;
    Code:
       0: aload_1
       1: instanceof    #89                 // class com/ctc/wstx/exc/WstxException
       4: ifeq          12
       7: aload_1
       8: checkcast     #89                 // class com/ctc/wstx/exc/WstxException
      11: athrow
      12: new           #89                 // class com/ctc/wstx/exc/WstxException
      15: dup
      16: aload_1
      17: invokespecial #90                 // Method com/ctc/wstx/exc/WstxException."<init>":(Ljava/lang/Throwable;)V
      20: athrow

  protected void throwLazyError(java.lang.Exception);
    Code:
       0: aload_1
       1: instanceof    #91                 // class javax/xml/stream/XMLStreamException
       4: ifeq          14
       7: aload_1
       8: checkcast     #91                 // class javax/xml/stream/XMLStreamException
      11: invokestatic  #92                 // Method com/ctc/wstx/exc/WstxLazyException.throwLazily:(Ljavax/xml/stream/XMLStreamException;)V
      14: aload_1
      15: invokestatic  #93                 // Method com/ctc/wstx/util/ExceptionUtil.throwRuntimeException:(Ljava/lang/Throwable;)V
      18: return

  protected java.lang.String tokenTypeDesc(int);
    Code:
       0: iload_1
       1: invokestatic  #94                 // Method com/ctc/wstx/cfg/ErrorConsts.tokenTypeDesc:(I)Ljava/lang/String;
       4: areturn

  public final com.ctc.wstx.io.WstxInputSource getCurrentInput();
    Code:
       0: aload_0
       1: getfield      #11                 // Field mInput:Lcom/ctc/wstx/io/WstxInputSource;
       4: areturn

  protected final int inputInBuffer();
    Code:
       0: aload_0
       1: getfield      #25                 // Field mInputEnd:I
       4: aload_0
       5: getfield      #26                 // Field mInputPtr:I
       8: isub
       9: ireturn

  protected final int getNext() throws javax.xml.stream.XMLStreamException;
    Code:
       0: aload_0
       1: getfield      #26                 // Field mInputPtr:I
       4: aload_0
       5: getfield      #25                 // Field mInputEnd:I
       8: if_icmplt     20
      11: aload_0
      12: invokevirtual #95                 // Method loadMore:()Z
      15: ifne          20
      18: iconst_m1
      19: ireturn
      20: aload_0
      21: getfield      #24                 // Field mInputBuffer:[C
      24: aload_0
      25: dup
      26: getfield      #26                 // Field mInputPtr:I
      29: dup_x1
      30: iconst_1
      31: iadd
      32: putfield      #26                 // Field mInputPtr:I
      35: caload
      36: ireturn

  protected final int peekNext() throws javax.xml.stream.XMLStreamException;
    Code:
       0: aload_0
       1: getfield      #26                 // Field mInputPtr:I
       4: aload_0
       5: getfield      #25                 // Field mInputEnd:I
       8: if_icmplt     20
      11: aload_0
      12: invokevirtual #96                 // Method loadMoreFromCurrent:()Z
      15: ifne          20
      18: iconst_m1
      19: ireturn
      20: aload_0
      21: getfield      #24                 // Field mInputBuffer:[C
      24: aload_0
      25: getfield      #26                 // Field mInputPtr:I
      28: caload
      29: ireturn

  protected final char getNextChar(java.lang.String) throws javax.xml.stream.XMLStreamException;
    Code:
       0: aload_0
       1: getfield      #26                 // Field mInputPtr:I
       4: aload_0
       5: getfield      #25                 // Field mInputEnd:I
       8: if_icmplt     17
      11: aload_0
      12: aload_1
      13: invokevirtual #97                 // Method loadMore:(Ljava/lang/String;)Z
      16: pop
      17: aload_0
      18: getfield      #24                 // Field mInputBuffer:[C
      21: aload_0
      22: dup
      23: getfield      #26                 // Field mInputPtr:I
      26: dup_x1
      27: iconst_1
      28: iadd
      29: putfield      #26                 // Field mInputPtr:I
      32: caload
      33: ireturn

  protected final char getNextCharFromCurrent(java.lang.String) throws javax.xml.stream.XMLStreamException;
    Code:
       0: aload_0
       1: getfield      #26                 // Field mInputPtr:I
       4: aload_0
       5: getfield      #25                 // Field mInputEnd:I
       8: if_icmplt     17
      11: aload_0
      12: aload_1
      13: invokevirtual #98                 // Method loadMoreFromCurrent:(Ljava/lang/String;)Z
      16: pop
      17: aload_0
      18: getfield      #24                 // Field mInputBuffer:[C
      21: aload_0
      22: dup
      23: getfield      #26                 // Field mInputPtr:I
      26: dup_x1
      27: iconst_1
      28: iadd
      29: putfield      #26                 // Field mInputPtr:I
      32: caload
      33: ireturn

  protected final int getNextAfterWS() throws javax.xml.stream.XMLStreamException;
    Code:
       0: aload_0
       1: getfield      #26                 // Field mInputPtr:I
       4: aload_0
       5: getfield      #25                 // Field mInputEnd:I
       8: if_icmplt     20
      11: aload_0
      12: invokevirtual #95                 // Method loadMore:()Z
      15: ifne          20
      18: iconst_m1
      19: ireturn
      20: aload_0
      21: getfield      #24                 // Field mInputBuffer:[C
      24: aload_0
      25: dup
      26: getfield      #26                 // Field mInputPtr:I
      29: dup_x1
      30: iconst_1
      31: iadd
      32: putfield      #26                 // Field mInputPtr:I
      35: caload
      36: istore_1
      37: iload_1
      38: bipush        32
      40: if_icmpgt     121
      43: iload_1
      44: bipush        10
      46: if_icmpeq     55
      49: iload_1
      50: bipush        13
      52: if_icmpne     64
      55: aload_0
      56: iload_1
      57: invokevirtual #99                 // Method skipCRLF:(C)Z
      60: pop
      61: goto          81
      64: iload_1
      65: bipush        32
      67: if_icmpeq     81
      70: iload_1
      71: bipush        9
      73: if_icmpeq     81
      76: aload_0
      77: iload_1
      78: invokevirtual #100                // Method throwInvalidSpace:(I)V
      81: aload_0
      82: getfield      #26                 // Field mInputPtr:I
      85: aload_0
      86: getfield      #25                 // Field mInputEnd:I
      89: if_icmplt     101
      92: aload_0
      93: invokevirtual #95                 // Method loadMore:()Z
      96: ifne          101
      99: iconst_m1
     100: ireturn
     101: aload_0
     102: getfield      #24                 // Field mInputBuffer:[C
     105: aload_0
     106: dup
     107: getfield      #26                 // Field mInputPtr:I
     110: dup_x1
     111: iconst_1
     112: iadd
     113: putfield      #26                 // Field mInputPtr:I
     116: caload
     117: istore_1
     118: goto          37
     121: iload_1
     122: ireturn

  protected final char getNextCharAfterWS(java.lang.String) throws javax.xml.stream.XMLStreamException;
    Code:
       0: aload_0
       1: getfield      #26                 // Field mInputPtr:I
       4: aload_0
       5: getfield      #25                 // Field mInputEnd:I
       8: if_icmplt     17
      11: aload_0
      12: aload_1
      13: invokevirtual #97                 // Method loadMore:(Ljava/lang/String;)Z
      16: pop
      17: aload_0
      18: getfield      #24                 // Field mInputBuffer:[C
      21: aload_0
      22: dup
      23: getfield      #26                 // Field mInputPtr:I
      26: dup_x1
      27: iconst_1
      28: iadd
      29: putfield      #26                 // Field mInputPtr:I
      32: caload
      33: istore_2
      34: iload_2
      35: bipush        32
      37: if_icmpgt     115
      40: iload_2
      41: bipush        10
      43: if_icmpeq     52
      46: iload_2
      47: bipush        13
      49: if_icmpne     61
      52: aload_0
      53: iload_2
      54: invokevirtual #99                 // Method skipCRLF:(C)Z
      57: pop
      58: goto          78
      61: iload_2
      62: bipush        32
      64: if_icmpeq     78
      67: iload_2
      68: bipush        9
      70: if_icmpeq     78
      73: aload_0
      74: iload_2
      75: invokevirtual #100                // Method throwInvalidSpace:(I)V
      78: aload_0
      79: getfield      #26                 // Field mInputPtr:I
      82: aload_0
      83: getfield      #25                 // Field mInputEnd:I
      86: if_icmplt     95
      89: aload_0
      90: aload_1
      91: invokevirtual #97                 // Method loadMore:(Ljava/lang/String;)Z
      94: pop
      95: aload_0
      96: getfield      #24                 // Field mInputBuffer:[C
      99: aload_0
     100: dup
     101: getfield      #26                 // Field mInputPtr:I
     104: dup_x1
     105: iconst_1
     106: iadd
     107: putfield      #26                 // Field mInputPtr:I
     110: caload
     111: istore_2
     112: goto          34
     115: iload_2
     116: ireturn

  protected final char getNextInCurrAfterWS(java.lang.String) throws javax.xml.stream.XMLStreamException;
    Code:
       0: aload_0
       1: aload_1
       2: aload_0
       3: aload_1
       4: invokevirtual #101                // Method getNextCharFromCurrent:(Ljava/lang/String;)C
       7: invokevirtual #102                // Method getNextInCurrAfterWS:(Ljava/lang/String;C)C
      10: ireturn

  protected final char getNextInCurrAfterWS(java.lang.String, char) throws javax.xml.stream.XMLStreamException;
    Code:
       0: iload_2
       1: bipush        32
       3: if_icmpgt     81
       6: iload_2
       7: bipush        10
       9: if_icmpeq     18
      12: iload_2
      13: bipush        13
      15: if_icmpne     27
      18: aload_0
      19: iload_2
      20: invokevirtual #99                 // Method skipCRLF:(C)Z
      23: pop
      24: goto          44
      27: iload_2
      28: bipush        32
      30: if_icmpeq     44
      33: iload_2
      34: bipush        9
      36: if_icmpeq     44
      39: aload_0
      40: iload_2
      41: invokevirtual #100                // Method throwInvalidSpace:(I)V
      44: aload_0
      45: getfield      #26                 // Field mInputPtr:I
      48: aload_0
      49: getfield      #25                 // Field mInputEnd:I
      52: if_icmplt     61
      55: aload_0
      56: aload_1
      57: invokevirtual #98                 // Method loadMoreFromCurrent:(Ljava/lang/String;)Z
      60: pop
      61: aload_0
      62: getfield      #24                 // Field mInputBuffer:[C
      65: aload_0
      66: dup
      67: getfield      #26                 // Field mInputPtr:I
      70: dup_x1
      71: iconst_1
      72: iadd
      73: putfield      #26                 // Field mInputPtr:I
      76: caload
      77: istore_2
      78: goto          0
      81: iload_2
      82: ireturn

  protected final boolean skipCRLF(char) throws javax.xml.stream.XMLStreamException;
    Code:
       0: iload_1
       1: bipush        13
       3: if_icmpne     30
       6: aload_0
       7: invokevirtual #103                // Method peekNext:()I
      10: bipush        10
      12: if_icmpne     30
      15: aload_0
      16: dup
      17: getfield      #26                 // Field mInputPtr:I
      20: iconst_1
      21: iadd
      22: putfield      #26                 // Field mInputPtr:I
      25: iconst_1
      26: istore_2
      27: goto          32
      30: iconst_0
      31: istore_2
      32: aload_0
      33: dup
      34: getfield      #34                 // Field mCurrInputRow:I
      37: iconst_1
      38: iadd
      39: putfield      #34                 // Field mCurrInputRow:I
      42: aload_0
      43: aload_0
      44: getfield      #26                 // Field mInputPtr:I
      47: putfield      #35                 // Field mCurrInputRowStart:I
      50: iload_2
      51: ireturn

  protected final void markLF();
    Code:
       0: aload_0
       1: dup
       2: getfield      #34                 // Field mCurrInputRow:I
       5: iconst_1
       6: iadd
       7: putfield      #34                 // Field mCurrInputRow:I
      10: aload_0
      11: aload_0
      12: getfield      #26                 // Field mInputPtr:I
      15: putfield      #35                 // Field mCurrInputRowStart:I
      18: return

  protected final void markLF(int);
    Code:
       0: aload_0
       1: dup
       2: getfield      #34                 // Field mCurrInputRow:I
       5: iconst_1
       6: iadd
       7: putfield      #34                 // Field mCurrInputRow:I
      10: aload_0
      11: iload_1
      12: putfield      #35                 // Field mCurrInputRowStart:I
      15: return

  protected final void pushback();
    Code:
       0: aload_0
       1: dup
       2: getfield      #26                 // Field mInputPtr:I
       5: iconst_1
       6: isub
       7: putfield      #26                 // Field mInputPtr:I
      10: return

  protected void initInputSource(com.ctc.wstx.io.WstxInputSource, boolean, java.lang.String) throws javax.xml.stream.XMLStreamException;
    Code:
       0: aload_0
       1: iconst_0
       2: putfield      #26                 // Field mInputPtr:I
       5: aload_0
       6: iconst_0
       7: putfield      #25                 // Field mInputEnd:I
      10: aload_0
      11: aload_0
      12: getfield      #104                // Field mCurrDepth:I
      15: putfield      #105                // Field mInputTopDepth:I
      18: aload_0
      19: getfield      #11                 // Field mInput:Lcom/ctc/wstx/io/WstxInputSource;
      22: invokevirtual #106                // Method com/ctc/wstx/io/WstxInputSource.getEntityDepth:()I
      25: iconst_1
      26: iadd
      27: istore        4
      29: aload_0
      30: ldc           #107                // String Maximum entity expansion depth
      32: aload_0
      33: getfield      #13                 // Field mConfig:Lcom/ctc/wstx/api/ReaderConfig;
      36: invokevirtual #108                // Method com/ctc/wstx/api/ReaderConfig.getMaxEntityDepth:()I
      39: i2l
      40: iload         4
      42: i2l
      43: invokevirtual #109                // Method verifyLimit:(Ljava/lang/String;JJ)V
      46: aload_0
      47: aload_1
      48: putfield      #11                 // Field mInput:Lcom/ctc/wstx/io/WstxInputSource;
      51: aload_0
      52: getfield      #11                 // Field mInput:Lcom/ctc/wstx/io/WstxInputSource;
      55: aload_0
      56: aload_0
      57: getfield      #104                // Field mCurrDepth:I
      60: iload         4
      62: invokevirtual #110                // Method com/ctc/wstx/io/WstxInputSource.initInputLocation:(Lcom/ctc/wstx/io/WstxInputData;II)V
      65: iload_2
      66: ifeq          77
      69: aload_0
      70: iconst_1
      71: putfield      #23                 // Field mNormalizeLFs:Z
      74: goto          82
      77: aload_0
      78: iconst_0
      79: putfield      #23                 // Field mNormalizeLFs:Z
      82: return

  protected boolean loadMore() throws javax.xml.stream.XMLStreamException;
    Code:
       0: aload_0
       1: getfield      #11                 // Field mInput:Lcom/ctc/wstx/io/WstxInputSource;
       4: astore_1
       5: aload_0
       6: dup
       7: getfield      #33                 // Field mCurrInputProcessed:J
      10: aload_0
      11: getfield      #25                 // Field mInputEnd:I
      14: i2l
      15: ladd
      16: putfield      #33                 // Field mCurrInputProcessed:J
      19: aload_0
      20: ldc           #111                // String Maximum document characters
      22: aload_0
      23: getfield      #13                 // Field mConfig:Lcom/ctc/wstx/api/ReaderConfig;
      26: invokevirtual #112                // Method com/ctc/wstx/api/ReaderConfig.getMaxCharacters:()J
      29: aload_0
      30: getfield      #33                 // Field mCurrInputProcessed:J
      33: invokevirtual #109                // Method verifyLimit:(Ljava/lang/String;JJ)V
      36: aload_0
      37: dup
      38: getfield      #35                 // Field mCurrInputRowStart:I
      41: aload_0
      42: getfield      #25                 // Field mInputEnd:I
      45: isub
      46: putfield      #35                 // Field mCurrInputRowStart:I
      49: aload_1
      50: aload_0
      51: invokevirtual #113                // Method com/ctc/wstx/io/WstxInputSource.readInto:(Lcom/ctc/wstx/io/WstxInputData;)I
      54: istore_2
      55: iload_2
      56: ifle          61
      59: iconst_1
      60: ireturn
      61: aload_1
      62: invokevirtual #114                // Method com/ctc/wstx/io/WstxInputSource.close:()V
      65: goto          75
      68: astore_3
      69: aload_0
      70: aload_3
      71: invokevirtual #116                // Method constructFromIOE:(Ljava/io/IOException;)Lcom/ctc/wstx/exc/WstxException;
      74: athrow
      75: aload_1
      76: aload_0
      77: getfield      #12                 // Field mRootInput:Lcom/ctc/wstx/io/WstxInputSource;
      80: if_acmpne     85
      83: iconst_0
      84: ireturn
      85: aload_1
      86: invokevirtual #117                // Method com/ctc/wstx/io/WstxInputSource.getParent:()Lcom/ctc/wstx/io/WstxInputSource;
      89: astore_3
      90: aload_3
      91: ifnonnull     99
      94: aload_0
      95: aload_1
      96: invokevirtual #118                // Method throwNullParent:(Lcom/ctc/wstx/io/WstxInputSource;)V
      99: aload_0
     100: getfield      #104                // Field mCurrDepth:I
     103: aload_1
     104: invokevirtual #119                // Method com/ctc/wstx/io/WstxInputSource.getScopeId:()I
     107: if_icmpeq     115
     110: aload_0
     111: aload_1
     112: invokevirtual #120                // Method handleIncompleteEntityProblem:(Lcom/ctc/wstx/io/WstxInputSource;)V
     115: aload_0
     116: aload_3
     117: dup
     118: astore_1
     119: putfield      #11                 // Field mInput:Lcom/ctc/wstx/io/WstxInputSource;
     122: aload_1
     123: aload_0
     124: invokevirtual #121                // Method com/ctc/wstx/io/WstxInputSource.restoreContext:(Lcom/ctc/wstx/io/WstxInputData;)V
     127: aload_0
     128: aload_1
     129: invokevirtual #119                // Method com/ctc/wstx/io/WstxInputSource.getScopeId:()I
     132: putfield      #105                // Field mInputTopDepth:I
     135: aload_0
     136: getfield      #23                 // Field mNormalizeLFs:Z
     139: ifne          158
     142: aload_0
     143: aload_1
     144: invokevirtual #122                // Method com/ctc/wstx/io/WstxInputSource.fromInternalEntity:()Z
     147: ifne          154
     150: iconst_1
     151: goto          155
     154: iconst_0
     155: putfield      #23                 // Field mNormalizeLFs:Z
     158: aload_0
     159: getfield      #26                 // Field mInputPtr:I
     162: aload_0
     163: getfield      #25                 // Field mInputEnd:I
     166: if_icmpge     5
     169: iconst_1
     170: ireturn
    Exception table:
       from    to  target type
          49    60    68   Class java/io/IOException
          61    65    68   Class java/io/IOException

  protected final boolean loadMore(java.lang.String) throws javax.xml.stream.XMLStreamException;
    Code:
       0: aload_0
       1: invokevirtual #95                 // Method loadMore:()Z
       4: ifne          12
       7: aload_0
       8: aload_1
       9: invokevirtual #123                // Method throwUnexpectedEOF:(Ljava/lang/String;)V
      12: iconst_1
      13: ireturn

  protected boolean loadMoreFromCurrent() throws javax.xml.stream.XMLStreamException;
    Code:
       0: aload_0
       1: dup
       2: getfield      #33                 // Field mCurrInputProcessed:J
       5: aload_0
       6: getfield      #25                 // Field mInputEnd:I
       9: i2l
      10: ladd
      11: putfield      #33                 // Field mCurrInputProcessed:J
      14: aload_0
      15: dup
      16: getfield      #35                 // Field mCurrInputRowStart:I
      19: aload_0
      20: getfield      #25                 // Field mInputEnd:I
      23: isub
      24: putfield      #35                 // Field mCurrInputRowStart:I
      27: aload_0
      28: ldc           #111                // String Maximum document characters
      30: aload_0
      31: getfield      #13                 // Field mConfig:Lcom/ctc/wstx/api/ReaderConfig;
      34: invokevirtual #112                // Method com/ctc/wstx/api/ReaderConfig.getMaxCharacters:()J
      37: aload_0
      38: getfield      #33                 // Field mCurrInputProcessed:J
      41: invokevirtual #109                // Method verifyLimit:(Ljava/lang/String;JJ)V
      44: aload_0
      45: getfield      #11                 // Field mInput:Lcom/ctc/wstx/io/WstxInputSource;
      48: aload_0
      49: invokevirtual #113                // Method com/ctc/wstx/io/WstxInputSource.readInto:(Lcom/ctc/wstx/io/WstxInputData;)I
      52: istore_1
      53: iload_1
      54: ifle          61
      57: iconst_1
      58: goto          62
      61: iconst_0
      62: ireturn
      63: astore_1
      64: aload_0
      65: aload_1
      66: invokevirtual #116                // Method constructFromIOE:(Ljava/io/IOException;)Lcom/ctc/wstx/exc/WstxException;
      69: athrow
    Exception table:
       from    to  target type
          44    62    63   Class java/io/IOException

  protected final boolean loadMoreFromCurrent(java.lang.String) throws javax.xml.stream.XMLStreamException;
    Code:
       0: aload_0
       1: invokevirtual #96                 // Method loadMoreFromCurrent:()Z
       4: ifne          12
       7: aload_0
       8: aload_1
       9: invokevirtual #124                // Method throwUnexpectedEOB:(Ljava/lang/String;)V
      12: iconst_1
      13: ireturn

  protected boolean ensureInput(int) throws javax.xml.stream.XMLStreamException;
    Code:
       0: aload_0
       1: getfield      #25                 // Field mInputEnd:I
       4: aload_0
       5: getfield      #26                 // Field mInputPtr:I
       8: isub
       9: istore_2
      10: iload_2
      11: iload_1
      12: if_icmplt     17
      15: iconst_1
      16: ireturn
      17: aload_0
      18: getfield      #11                 // Field mInput:Lcom/ctc/wstx/io/WstxInputSource;
      21: aload_0
      22: iload_1
      23: invokevirtual #125                // Method com/ctc/wstx/io/WstxInputSource.readMore:(Lcom/ctc/wstx/io/WstxInputData;I)Z
      26: ireturn
      27: astore_3
      28: aload_0
      29: aload_3
      30: invokevirtual #116                // Method constructFromIOE:(Ljava/io/IOException;)Lcom/ctc/wstx/exc/WstxException;
      33: athrow
    Exception table:
       from    to  target type
          17    26    27   Class java/io/IOException

  protected void closeAllInput(boolean) throws javax.xml.stream.XMLStreamException;
    Code:
       0: aload_0
       1: getfield      #11                 // Field mInput:Lcom/ctc/wstx/io/WstxInputSource;
       4: astore_2
       5: iload_1
       6: ifeq          16
       9: aload_2
      10: invokevirtual #126                // Method com/ctc/wstx/io/WstxInputSource.closeCompletely:()V
      13: goto          20
      16: aload_2
      17: invokevirtual #114                // Method com/ctc/wstx/io/WstxInputSource.close:()V
      20: goto          30
      23: astore_3
      24: aload_0
      25: aload_3
      26: invokevirtual #116                // Method constructFromIOE:(Ljava/io/IOException;)Lcom/ctc/wstx/exc/WstxException;
      29: athrow
      30: aload_2
      31: aload_0
      32: getfield      #12                 // Field mRootInput:Lcom/ctc/wstx/io/WstxInputSource;
      35: if_acmpne     41
      38: goto          65
      41: aload_2
      42: invokevirtual #117                // Method com/ctc/wstx/io/WstxInputSource.getParent:()Lcom/ctc/wstx/io/WstxInputSource;
      45: astore_3
      46: aload_3
      47: ifnonnull     55
      50: aload_0
      51: aload_2
      52: invokevirtual #118                // Method throwNullParent:(Lcom/ctc/wstx/io/WstxInputSource;)V
      55: aload_0
      56: aload_3
      57: dup
      58: astore_2
      59: putfield      #11                 // Field mInput:Lcom/ctc/wstx/io/WstxInputSource;
      62: goto          5
      65: return
    Exception table:
       from    to  target type
           5    20    23   Class java/io/IOException

  protected void throwNullParent(com.ctc.wstx.io.WstxInputSource);
    Code:
       0: new           #127                // class java/lang/IllegalStateException
       3: dup
       4: getstatic     #128                // Field com/ctc/wstx/cfg/ErrorConsts.ERR_INTERNAL:Ljava/lang/String;
       7: invokespecial #129                // Method java/lang/IllegalStateException."<init>":(Ljava/lang/String;)V
      10: athrow

  protected int resolveSimpleEntity(boolean) throws javax.xml.stream.XMLStreamException;
    Code:
       0: aload_0
       1: getfield      #24                 // Field mInputBuffer:[C
       4: astore_2
       5: aload_0
       6: getfield      #26                 // Field mInputPtr:I
       9: istore_3
      10: aload_2
      11: iload_3
      12: iinc          3, 1
      15: caload
      16: istore        4
      18: iload         4
      20: bipush        35
      22: if_icmpne     298
      25: aload_2
      26: iload_3
      27: iinc          3, 1
      30: caload
      31: istore        4
      33: iconst_0
      34: istore        5
      36: aload_0
      37: getfield      #25                 // Field mInputEnd:I
      40: istore        6
      42: iload         4
      44: bipush        120
      46: if_icmpne     193
      49: iload_3
      50: iload         6
      52: if_icmpge     274
      55: aload_2
      56: iload_3
      57: iinc          3, 1
      60: caload
      61: istore        4
      63: iload         4
      65: bipush        59
      67: if_icmpne     73
      70: goto          274
      73: iload         5
      75: iconst_4
      76: ishl
      77: istore        5
      79: iload         4
      81: bipush        57
      83: if_icmpgt     106
      86: iload         4
      88: bipush        48
      90: if_icmplt     106
      93: iload         5
      95: iload         4
      97: bipush        48
      99: isub
     100: iadd
     101: istore        5
     103: goto          179
     106: iload         4
     108: bipush        97
     110: if_icmplt     136
     113: iload         4
     115: bipush        102
     117: if_icmpgt     136
     120: iload         5
     122: bipush        10
     124: iload         4
     126: bipush        97
     128: isub
     129: iadd
     130: iadd
     131: istore        5
     133: goto          179
     136: iload         4
     138: bipush        65
     140: if_icmplt     166
     143: iload         4
     145: bipush        70
     147: if_icmpgt     166
     150: iload         5
     152: bipush        10
     154: iload         4
     156: bipush        65
     158: isub
     159: iadd
     160: iadd
     161: istore        5
     163: goto          179
     166: aload_0
     167: iload_3
     168: putfield      #26                 // Field mInputPtr:I
     171: aload_0
     172: iload         4
     174: ldc           #130                // String ; expected a hex digit (0-9a-fA-F).
     176: invokevirtual #131                // Method throwUnexpectedChar:(ILjava/lang/String;)V
     179: iload         5
     181: ldc           #132                // int 1114111
     183: if_icmple     49
     186: aload_0
     187: invokespecial #133                // Method reportUnicodeOverflow:()V
     190: goto          49
     193: iload         4
     195: bipush        59
     197: if_icmpeq     274
     200: iload         4
     202: bipush        57
     204: if_icmpgt     241
     207: iload         4
     209: bipush        48
     211: if_icmplt     241
     214: iload         5
     216: bipush        10
     218: imul
     219: iload         4
     221: bipush        48
     223: isub
     224: iadd
     225: istore        5
     227: iload         5
     229: ldc           #132                // int 1114111
     231: if_icmple     254
     234: aload_0
     235: invokespecial #133                // Method reportUnicodeOverflow:()V
     238: goto          254
     241: aload_0
     242: iload_3
     243: putfield      #26                 // Field mInputPtr:I
     246: aload_0
     247: iload         4
     249: ldc           #134                // String ; expected a decimal number.
     251: invokevirtual #131                // Method throwUnexpectedChar:(ILjava/lang/String;)V
     254: iload_3
     255: iload         6
     257: if_icmplt     263
     260: goto          274
     263: aload_2
     264: iload_3
     265: iinc          3, 1
     268: caload
     269: istore        4
     271: goto          193
     274: iload         4
     276: bipush        59
     278: if_icmpne     295
     281: aload_0
     282: iload_3
     283: putfield      #26                 // Field mInputPtr:I
     286: aload_0
     287: iload         5
     289: invokespecial #135                // Method validateChar:(I)V
     292: iload         5
     294: ireturn
     295: goto          582
     298: iload_1
     299: ifeq          582
     302: iload         4
     304: bipush        97
     306: if_icmpne     431
     309: aload_2
     310: iload_3
     311: iinc          3, 1
     314: caload
     315: istore        4
     317: iload         4
     319: bipush        109
     321: if_icmpne     362
     324: aload_2
     325: iload_3
     326: iinc          3, 1
     329: caload
     330: bipush        112
     332: if_icmpne     582
     335: iload_3
     336: aload_0
     337: getfield      #25                 // Field mInputEnd:I
     340: if_icmpge     582
     343: aload_2
     344: iload_3
     345: iinc          3, 1
     348: caload
     349: bipush        59
     351: if_icmpne     582
     354: aload_0
     355: iload_3
     356: putfield      #26                 // Field mInputPtr:I
     359: bipush        38
     361: ireturn
     362: iload         4
     364: bipush        112
     366: if_icmpne     582
     369: aload_2
     370: iload_3
     371: iinc          3, 1
     374: caload
     375: bipush        111
     377: if_icmpne     582
     380: aload_0
     381: getfield      #25                 // Field mInputEnd:I
     384: istore        5
     386: iload_3
     387: iload         5
     389: if_icmpge     428
     392: aload_2
     393: iload_3
     394: iinc          3, 1
     397: caload
     398: bipush        115
     400: if_icmpne     428
     403: iload_3
     404: iload         5
     406: if_icmpge     428
     409: aload_2
     410: iload_3
     411: iinc          3, 1
     414: caload
     415: bipush        59
     417: if_icmpne     428
     420: aload_0
     421: iload_3
     422: putfield      #26                 // Field mInputPtr:I
     425: bipush        39
     427: ireturn
     428: goto          582
     431: iload         4
     433: bipush        103
     435: if_icmpne     468
     438: aload_2
     439: iload_3
     440: iinc          3, 1
     443: caload
     444: bipush        116
     446: if_icmpne     582
     449: aload_2
     450: iload_3
     451: iinc          3, 1
     454: caload
     455: bipush        59
     457: if_icmpne     582
     460: aload_0
     461: iload_3
     462: putfield      #26                 // Field mInputPtr:I
     465: bipush        62
     467: ireturn
     468: iload         4
     470: bipush        108
     472: if_icmpne     505
     475: aload_2
     476: iload_3
     477: iinc          3, 1
     480: caload
     481: bipush        116
     483: if_icmpne     582
     486: aload_2
     487: iload_3
     488: iinc          3, 1
     491: caload
     492: bipush        59
     494: if_icmpne     582
     497: aload_0
     498: iload_3
     499: putfield      #26                 // Field mInputPtr:I
     502: bipush        60
     504: ireturn
     505: iload         4
     507: bipush        113
     509: if_icmpne     582
     512: aload_2
     513: iload_3
     514: iinc          3, 1
     517: caload
     518: bipush        117
     520: if_icmpne     582
     523: aload_2
     524: iload_3
     525: iinc          3, 1
     528: caload
     529: bipush        111
     531: if_icmpne     582
     534: aload_0
     535: getfield      #25                 // Field mInputEnd:I
     538: istore        5
     540: iload_3
     541: iload         5
     543: if_icmpge     582
     546: aload_2
     547: iload_3
     548: iinc          3, 1
     551: caload
     552: bipush        116
     554: if_icmpne     582
     557: iload_3
     558: iload         5
     560: if_icmpge     582
     563: aload_2
     564: iload_3
     565: iinc          3, 1
     568: caload
     569: bipush        59
     571: if_icmpne     582
     574: aload_0
     575: iload_3
     576: putfield      #26                 // Field mInputPtr:I
     579: bipush        34
     581: ireturn
     582: iconst_0
     583: ireturn

  protected int resolveCharOnlyEntity(boolean) throws javax.xml.stream.XMLStreamException;
    Code:
       0: aload_0
       1: getfield      #25                 // Field mInputEnd:I
       4: aload_0
       5: getfield      #26                 // Field mInputPtr:I
       8: isub
       9: istore_2
      10: iload_2
      11: bipush        6
      13: if_icmpge     67
      16: aload_0
      17: dup
      18: getfield      #26                 // Field mInputPtr:I
      21: iconst_1
      22: isub
      23: putfield      #26                 // Field mInputPtr:I
      26: aload_0
      27: bipush        6
      29: invokevirtual #136                // Method ensureInput:(I)Z
      32: ifne          54
      35: aload_0
      36: invokevirtual #137                // Method inputInBuffer:()I
      39: istore_2
      40: iload_2
      41: iconst_3
      42: if_icmpge     57
      45: aload_0
      46: ldc           #139                // String  in entity reference
      48: invokevirtual #123                // Method throwUnexpectedEOF:(Ljava/lang/String;)V
      51: goto          57
      54: bipush        6
      56: istore_2
      57: aload_0
      58: dup
      59: getfield      #26                 // Field mInputPtr:I
      62: iconst_1
      63: iadd
      64: putfield      #26                 // Field mInputPtr:I
      67: aload_0
      68: getfield      #24                 // Field mInputBuffer:[C
      71: aload_0
      72: getfield      #26                 // Field mInputPtr:I
      75: caload
      76: istore_3
      77: iload_3
      78: bipush        35
      80: if_icmpne     99
      83: aload_0
      84: dup
      85: getfield      #26                 // Field mInputPtr:I
      88: iconst_1
      89: iadd
      90: putfield      #26                 // Field mInputPtr:I
      93: aload_0
      94: aconst_null
      95: invokespecial #140                // Method resolveCharEnt:(Ljava/lang/StringBuffer;)I
      98: ireturn
      99: iload_1
     100: ifeq          455
     103: iload_3
     104: bipush        97
     106: if_icmpne     255
     109: aload_0
     110: getfield      #24                 // Field mInputBuffer:[C
     113: aload_0
     114: getfield      #26                 // Field mInputPtr:I
     117: iconst_1
     118: iadd
     119: caload
     120: istore        4
     122: iload         4
     124: bipush        109
     126: if_icmpne     179
     129: iload_2
     130: iconst_4
     131: if_icmplt     252
     134: aload_0
     135: getfield      #24                 // Field mInputBuffer:[C
     138: aload_0
     139: getfield      #26                 // Field mInputPtr:I
     142: iconst_2
     143: iadd
     144: caload
     145: bipush        112
     147: if_icmpne     252
     150: aload_0
     151: getfield      #24                 // Field mInputBuffer:[C
     154: aload_0
     155: getfield      #26                 // Field mInputPtr:I
     158: iconst_3
     159: iadd
     160: caload
     161: bipush        59
     163: if_icmpne     252
     166: aload_0
     167: dup
     168: getfield      #26                 // Field mInputPtr:I
     171: iconst_4
     172: iadd
     173: putfield      #26                 // Field mInputPtr:I
     176: bipush        38
     178: ireturn
     179: iload         4
     181: bipush        112
     183: if_icmpne     252
     186: iload_2
     187: iconst_5
     188: if_icmplt     252
     191: aload_0
     192: getfield      #24                 // Field mInputBuffer:[C
     195: aload_0
     196: getfield      #26                 // Field mInputPtr:I
     199: iconst_2
     200: iadd
     201: caload
     202: bipush        111
     204: if_icmpne     252
     207: aload_0
     208: getfield      #24                 // Field mInputBuffer:[C
     211: aload_0
     212: getfield      #26                 // Field mInputPtr:I
     215: iconst_3
     216: iadd
     217: caload
     218: bipush        115
     220: if_icmpne     252
     223: aload_0
     224: getfield      #24                 // Field mInputBuffer:[C
     227: aload_0
     228: getfield      #26                 // Field mInputPtr:I
     231: iconst_4
     232: iadd
     233: caload
     234: bipush        59
     236: if_icmpne     252
     239: aload_0
     240: dup
     241: getfield      #26                 // Field mInputPtr:I
     244: iconst_5
     245: iadd
     246: putfield      #26                 // Field mInputPtr:I
     249: bipush        39
     251: ireturn
     252: goto          455
     255: iload_3
     256: bipush        108
     258: if_icmpne     311
     261: iload_2
     262: iconst_3
     263: if_icmplt     455
     266: aload_0
     267: getfield      #24                 // Field mInputBuffer:[C
     270: aload_0
     271: getfield      #26                 // Field mInputPtr:I
     274: iconst_1
     275: iadd
     276: caload
     277: bipush        116
     279: if_icmpne     455
     282: aload_0
     283: getfield      #24                 // Field mInputBuffer:[C
     286: aload_0
     287: getfield      #26                 // Field mInputPtr:I
     290: iconst_2
     291: iadd
     292: caload
     293: bipush        59
     295: if_icmpne     455
     298: aload_0
     299: dup
     300: getfield      #26                 // Field mInputPtr:I
     303: iconst_3
     304: iadd
     305: putfield      #26                 // Field mInputPtr:I
     308: bipush        60
     310: ireturn
     311: iload_3
     312: bipush        103
     314: if_icmpne     367
     317: iload_2
     318: iconst_3
     319: if_icmplt     455
     322: aload_0
     323: getfield      #24                 // Field mInputBuffer:[C
     326: aload_0
     327: getfield      #26                 // Field mInputPtr:I
     330: iconst_1
     331: iadd
     332: caload
     333: bipush        116
     335: if_icmpne     455
     338: aload_0
     339: getfield      #24                 // Field mInputBuffer:[C
     342: aload_0
     343: getfield      #26                 // Field mInputPtr:I
     346: iconst_2
     347: iadd
     348: caload
     349: bipush        59
     351: if_icmpne     455
     354: aload_0
     355: dup
     356: getfield      #26                 // Field mInputPtr:I
     359: iconst_3
     360: iadd
     361: putfield      #26                 // Field mInputPtr:I
     364: bipush        62
     366: ireturn
     367: iload_3
     368: bipush        113
     370: if_icmpne     455
     373: iload_2
     374: iconst_5
     375: if_icmplt     455
     378: aload_0
     379: getfield      #24                 // Field mInputBuffer:[C
     382: aload_0
     383: getfield      #26                 // Field mInputPtr:I
     386: iconst_1
     387: iadd
     388: caload
     389: bipush        117
     391: if_icmpne     455
     394: aload_0
     395: getfield      #24                 // Field mInputBuffer:[C
     398: aload_0
     399: getfield      #26                 // Field mInputPtr:I
     402: iconst_2
     403: iadd
     404: caload
     405: bipush        111
     407: if_icmpne     455
     410: aload_0
     411: getfield      #24                 // Field mInputBuffer:[C
     414: aload_0
     415: getfield      #26                 // Field mInputPtr:I
     418: iconst_3
     419: iadd
     420: caload
     421: bipush        116
     423: if_icmpne     455
     426: aload_0
     427: getfield      #24                 // Field mInputBuffer:[C
     430: aload_0
     431: getfield      #26                 // Field mInputPtr:I
     434: iconst_4
     435: iadd
     436: caload
     437: bipush        59
     439: if_icmpne     455
     442: aload_0
     443: dup
     444: getfield      #26                 // Field mInputPtr:I
     447: iconst_5
     448: iadd
     449: putfield      #26                 // Field mInputPtr:I
     452: bipush        34
     454: ireturn
     455: iconst_0
     456: ireturn

  protected com.ctc.wstx.ent.EntityDecl resolveNonCharEntity() throws javax.xml.stream.XMLStreamException;
    Code:
       0: aload_0
       1: getfield      #25                 // Field mInputEnd:I
       4: aload_0
       5: getfield      #26                 // Field mInputPtr:I
       8: isub
       9: istore_1
      10: iload_1
      11: bipush        6
      13: if_icmpge     67
      16: aload_0
      17: dup
      18: getfield      #26                 // Field mInputPtr:I
      21: iconst_1
      22: isub
      23: putfield      #26                 // Field mInputPtr:I
      26: aload_0
      27: bipush        6
      29: invokevirtual #136                // Method ensureInput:(I)Z
      32: ifne          54
      35: aload_0
      36: invokevirtual #137                // Method inputInBuffer:()I
      39: istore_1
      40: iload_1
      41: iconst_3
      42: if_icmpge     57
      45: aload_0
      46: ldc           #139                // String  in entity reference
      48: invokevirtual #123                // Method throwUnexpectedEOF:(Ljava/lang/String;)V
      51: goto          57
      54: bipush        6
      56: istore_1
      57: aload_0
      58: dup
      59: getfield      #26                 // Field mInputPtr:I
      62: iconst_1
      63: iadd
      64: putfield      #26                 // Field mInputPtr:I
      67: aload_0
      68: getfield      #24                 // Field mInputBuffer:[C
      71: aload_0
      72: getfield      #26                 // Field mInputPtr:I
      75: caload
      76: istore_2
      77: iload_2
      78: bipush        35
      80: if_icmpne     85
      83: aconst_null
      84: areturn
      85: iload_2
      86: bipush        97
      88: if_icmpne     212
      91: aload_0
      92: getfield      #24                 // Field mInputBuffer:[C
      95: aload_0
      96: getfield      #26                 // Field mInputPtr:I
      99: iconst_1
     100: iadd
     101: caload
     102: istore_3
     103: iload_3
     104: bipush        109
     106: if_icmpne     148
     109: iload_1
     110: iconst_4
     111: if_icmplt     209
     114: aload_0
     115: getfield      #24                 // Field mInputBuffer:[C
     118: aload_0
     119: getfield      #26                 // Field mInputPtr:I
     122: iconst_2
     123: iadd
     124: caload
     125: bipush        112
     127: if_icmpne     209
     130: aload_0
     131: getfield      #24                 // Field mInputBuffer:[C
     134: aload_0
     135: getfield      #26                 // Field mInputPtr:I
     138: iconst_3
     139: iadd
     140: caload
     141: bipush        59
     143: if_icmpne     209
     146: aconst_null
     147: areturn
     148: iload_3
     149: bipush        112
     151: if_icmpne     209
     154: iload_1
     155: iconst_5
     156: if_icmplt     209
     159: aload_0
     160: getfield      #24                 // Field mInputBuffer:[C
     163: aload_0
     164: getfield      #26                 // Field mInputPtr:I
     167: iconst_2
     168: iadd
     169: caload
     170: bipush        111
     172: if_icmpne     209
     175: aload_0
     176: getfield      #24                 // Field mInputBuffer:[C
     179: aload_0
     180: getfield      #26                 // Field mInputPtr:I
     183: iconst_3
     184: iadd
     185: caload
     186: bipush        115
     188: if_icmpne     209
     191: aload_0
     192: getfield      #24                 // Field mInputBuffer:[C
     195: aload_0
     196: getfield      #26                 // Field mInputPtr:I
     199: iconst_4
     200: iadd
     201: caload
     202: bipush        59
     204: if_icmpne     209
     207: aconst_null
     208: areturn
     209: goto          379
     212: iload_2
     213: bipush        108
     215: if_icmpne     257
     218: iload_1
     219: iconst_3
     220: if_icmplt     379
     223: aload_0
     224: getfield      #24                 // Field mInputBuffer:[C
     227: aload_0
     228: getfield      #26                 // Field mInputPtr:I
     231: iconst_1
     232: iadd
     233: caload
     234: bipush        116
     236: if_icmpne     379
     239: aload_0
     240: getfield      #24                 // Field mInputBuffer:[C
     243: aload_0
     244: getfield      #26                 // Field mInputPtr:I
     247: iconst_2
     248: iadd
     249: caload
     250: bipush        59
     252: if_icmpne     379
     255: aconst_null
     256: areturn
     257: iload_2
     258: bipush        103
     260: if_icmpne     302
     263: iload_1
     264: iconst_3
     265: if_icmplt     379
     268: aload_0
     269: getfield      #24                 // Field mInputBuffer:[C
     272: aload_0
     273: getfield      #26                 // Field mInputPtr:I
     276: iconst_1
     277: iadd
     278: caload
     279: bipush        116
     281: if_icmpne     379
     284: aload_0
     285: getfield      #24                 // Field mInputBuffer:[C
     288: aload_0
     289: getfield      #26                 // Field mInputPtr:I
     292: iconst_2
     293: iadd
     294: caload
     295: bipush        59
     297: if_icmpne     379
     300: aconst_null
     301: areturn
     302: iload_2
     303: bipush        113
     305: if_icmpne     379
     308: iload_1
     309: iconst_5
     310: if_icmplt     379
     313: aload_0
     314: getfield      #24                 // Field mInputBuffer:[C
     317: aload_0
     318: getfield      #26                 // Field mInputPtr:I
     321: iconst_1
     322: iadd
     323: caload
     324: bipush        117
     326: if_icmpne     379
     329: aload_0
     330: getfield      #24                 // Field mInputBuffer:[C
     333: aload_0
     334: getfield      #26                 // Field mInputPtr:I
     337: iconst_2
     338: iadd
     339: caload
     340: bipush        111
     342: if_icmpne     379
     345: aload_0
     346: getfield      #24                 // Field mInputBuffer:[C
     349: aload_0
     350: getfield      #26                 // Field mInputPtr:I
     353: iconst_3
     354: iadd
     355: caload
     356: bipush        116
     358: if_icmpne     379
     361: aload_0
     362: getfield      #24                 // Field mInputBuffer:[C
     365: aload_0
     366: getfield      #26                 // Field mInputPtr:I
     369: iconst_4
     370: iadd
     371: caload
     372: bipush        59
     374: if_icmpne     379
     377: aconst_null
     378: areturn
     379: aload_0
     380: dup
     381: getfield      #26                 // Field mInputPtr:I
     384: iconst_1
     385: iadd
     386: putfield      #26                 // Field mInputPtr:I
     389: aload_0
     390: iload_2
     391: invokevirtual #141                // Method parseEntityName:(C)Ljava/lang/String;
     394: astore_3
     395: aload_0
     396: aload_3
     397: putfield      #142                // Field mCurrName:Ljava/lang/String;
     400: aload_0
     401: aload_3
     402: aconst_null
     403: invokevirtual #143                // Method findEntity:(Ljava/lang/String;Ljava/lang/Object;)Lcom/ctc/wstx/ent/EntityDecl;
     406: areturn

  protected int fullyResolveEntity(boolean) throws javax.xml.stream.XMLStreamException;
    Code:
       0: aload_0
       1: ldc           #139                // String  in entity reference
       3: invokevirtual #101                // Method getNextCharFromCurrent:(Ljava/lang/String;)C
       6: istore_2
       7: iload_2
       8: bipush        35
      10: if_icmpne     74
      13: new           #144                // class java/lang/StringBuffer
      16: dup
      17: ldc           #145                // String #
      19: invokespecial #146                // Method java/lang/StringBuffer."<init>":(Ljava/lang/String;)V
      22: astore_3
      23: aload_0
      24: aload_3
      25: invokespecial #140                // Method resolveCharEnt:(Ljava/lang/StringBuffer;)I
      28: istore        4
      30: aload_0
      31: getfield      #28                 // Field mCfgTreatCharRefsAsEntities:Z
      34: ifeq          71
      37: aload_3
      38: invokevirtual #147                // Method java/lang/StringBuffer.length:()I
      41: newarray       char
      43: astore        5
      45: aload_3
      46: iconst_0
      47: aload_3
      48: invokevirtual #147                // Method java/lang/StringBuffer.length:()I
      51: aload         5
      53: iconst_0
      54: invokevirtual #148                // Method java/lang/StringBuffer.getChars:(II[CI)V
      57: aload_0
      58: aload_0
      59: iload         4
      61: aload         5
      63: invokevirtual #149                // Method getIntEntity:(I[C)Lcom/ctc/wstx/ent/EntityDecl;
      66: putfield      #150                // Field mCurrEntity:Lcom/ctc/wstx/ent/EntityDecl;
      69: iconst_0
      70: ireturn
      71: iload         4
      73: ireturn
      74: aload_0
      75: iload_2
      76: invokevirtual #141                // Method parseEntityName:(C)Ljava/lang/String;
      79: astore_3
      80: aload_3
      81: iconst_0
      82: invokevirtual #151                // Method java/lang/String.charAt:(I)C
      85: istore_2
      86: iconst_0
      87: istore        4
      89: iload_2
      90: bipush        97
      92: if_icmpne     127
      95: aload_3
      96: ldc           #152                // String amp
      98: invokevirtual #153                // Method java/lang/String.equals:(Ljava/lang/Object;)Z
     101: ifeq          111
     104: bipush        38
     106: istore        4
     108: goto          208
     111: aload_3
     112: ldc           #154                // String apos
     114: invokevirtual #153                // Method java/lang/String.equals:(Ljava/lang/Object;)Z
     117: ifeq          208
     120: bipush        39
     122: istore        4
     124: goto          208
     127: iload_2
     128: bipush        103
     130: if_icmpne     158
     133: aload_3
     134: invokevirtual #155                // Method java/lang/String.length:()I
     137: iconst_2
     138: if_icmpne     208
     141: aload_3
     142: iconst_1
     143: invokevirtual #151                // Method java/lang/String.charAt:(I)C
     146: bipush        116
     148: if_icmpne     208
     151: bipush        62
     153: istore        4
     155: goto          208
     158: iload_2
     159: bipush        108
     161: if_icmpne     189
     164: aload_3
     165: invokevirtual #155                // Method java/lang/String.length:()I
     168: iconst_2
     169: if_icmpne     208
     172: aload_3
     173: iconst_1
     174: invokevirtual #151                // Method java/lang/String.charAt:(I)C
     177: bipush        116
     179: if_icmpne     208
     182: bipush        60
     184: istore        4
     186: goto          208
     189: iload_2
     190: bipush        113
     192: if_icmpne     208
     195: aload_3
     196: ldc           #156                // String quot
     198: invokevirtual #153                // Method java/lang/String.equals:(Ljava/lang/Object;)Z
     201: ifeq          208
     204: bipush        34
     206: istore        4
     208: iload         4
     210: ifeq          257
     213: aload_0
     214: getfield      #28                 // Field mCfgTreatCharRefsAsEntities:Z
     217: ifeq          254
     220: aload_3
     221: invokevirtual #155                // Method java/lang/String.length:()I
     224: newarray       char
     226: astore        5
     228: aload_3
     229: iconst_0
     230: aload_3
     231: invokevirtual #155                // Method java/lang/String.length:()I
     234: aload         5
     236: iconst_0
     237: invokevirtual #157                // Method java/lang/String.getChars:(II[CI)V
     240: aload_0
     241: aload_0
     242: iload         4
     244: aload         5
     246: invokevirtual #149                // Method getIntEntity:(I[C)Lcom/ctc/wstx/ent/EntityDecl;
     249: putfield      #150                // Field mCurrEntity:Lcom/ctc/wstx/ent/EntityDecl;
     252: iconst_0
     253: ireturn
     254: iload         4
     256: ireturn
     257: aload_0
     258: aload_3
     259: iload_1
     260: aconst_null
     261: invokevirtual #158                // Method expandEntity:(Ljava/lang/String;ZLjava/lang/Object;)Lcom/ctc/wstx/ent/EntityDecl;
     264: astore        5
     266: aload_0
     267: getfield      #28                 // Field mCfgTreatCharRefsAsEntities:Z
     270: ifeq          279
     273: aload_0
     274: aload         5
     276: putfield      #150                // Field mCurrEntity:Lcom/ctc/wstx/ent/EntityDecl;
     279: iconst_0
     280: ireturn

  protected com.ctc.wstx.ent.EntityDecl getIntEntity(int, char[]);
    Code:
       0: new           #159                // class java/lang/String
       3: dup
       4: aload_2
       5: invokespecial #160                // Method java/lang/String."<init>":([C)V
       8: astore_3
       9: aload_0
      10: getfield      #31                 // Field mCachedEntities:Ljava/util/Map;
      13: aload_3
      14: invokeinterface #161,  2          // InterfaceMethod java/util/Map.get:(Ljava/lang/Object;)Ljava/lang/Object;
      19: checkcast     #162                // class com/ctc/wstx/ent/IntEntity
      22: astore        4
      24: aload         4
      26: ifnonnull     124
      29: iload_1
      30: ldc           #163                // int 65535
      32: if_icmpgt     45
      35: iload_1
      36: i2c
      37: invokestatic  #164                // Method java/lang/Character.toString:(C)Ljava/lang/String;
      40: astore        5
      42: goto          96
      45: new           #144                // class java/lang/StringBuffer
      48: dup
      49: iconst_2
      50: invokespecial #165                // Method java/lang/StringBuffer."<init>":(I)V
      53: astore        6
      55: iload_1
      56: ldc           #166                // int 65536
      58: isub
      59: istore_1
      60: aload         6
      62: iload_1
      63: bipush        10
      65: ishr
      66: ldc           #167                // int 55296
      68: iadd
      69: i2c
      70: invokevirtual #168                // Method java/lang/StringBuffer.append:(C)Ljava/lang/StringBuffer;
      73: pop
      74: aload         6
      76: iload_1
      77: sipush        1023
      80: iand
      81: ldc           #169                // int 56320
      83: iadd
      84: i2c
      85: invokevirtual #168                // Method java/lang/StringBuffer.append:(C)Ljava/lang/StringBuffer;
      88: pop
      89: aload         6
      91: invokevirtual #170                // Method java/lang/StringBuffer.toString:()Ljava/lang/String;
      94: astore        5
      96: new           #159                // class java/lang/String
      99: dup
     100: aload_2
     101: invokespecial #160                // Method java/lang/String."<init>":([C)V
     104: aload         5
     106: invokestatic  #171                // Method com/ctc/wstx/ent/IntEntity.create:(Ljava/lang/String;Ljava/lang/String;)Lcom/ctc/wstx/ent/IntEntity;
     109: astore        4
     111: aload_0
     112: getfield      #31                 // Field mCachedEntities:Ljava/util/Map;
     115: aload_3
     116: aload         4
     118: invokeinterface #172,  3          // InterfaceMethod java/util/Map.put:(Ljava/lang/Object;Ljava/lang/Object;)Ljava/lang/Object;
     123: pop
     124: aload         4
     126: areturn

  protected com.ctc.wstx.ent.EntityDecl expandEntity(java.lang.String, boolean, java.lang.Object) throws javax.xml.stream.XMLStreamException;
    Code:
       0: aload_0
       1: aload_1
       2: putfield      #142                // Field mCurrName:Ljava/lang/String;
       5: aload_0
       6: aload_1
       7: aload_3
       8: invokevirtual #143                // Method findEntity:(Ljava/lang/String;Ljava/lang/Object;)Lcom/ctc/wstx/ent/EntityDecl;
      11: astore        4
      13: aload         4
      15: ifnonnull     36
      18: aload_0
      19: getfield      #19                 // Field mCfgReplaceEntities:Z
      22: ifeq          34
      25: aload_0
      26: aload_0
      27: aload_1
      28: invokespecial #173                // Method expandUnresolvedEntity:(Ljava/lang/String;)Lcom/ctc/wstx/ent/EntityDecl;
      31: putfield      #150                // Field mCurrEntity:Lcom/ctc/wstx/ent/EntityDecl;
      34: aconst_null
      35: areturn
      36: aload_0
      37: getfield      #28                 // Field mCfgTreatCharRefsAsEntities:Z
      40: ifeq          50
      43: aload_0
      44: instanceof    #174                // class com/ctc/wstx/dtd/MinimalDTDReader
      47: ifeq          57
      50: aload_0
      51: aload         4
      53: iload_2
      54: invokespecial #175                // Method expandEntity:(Lcom/ctc/wstx/ent/EntityDecl;Z)V
      57: aload         4
      59: areturn

  private void expandEntity(com.ctc.wstx.ent.EntityDecl, boolean) throws javax.xml.stream.XMLStreamException;
    Code:
       0: aload_1
       1: invokevirtual #176                // Method com/ctc/wstx/ent/EntityDecl.getName:()Ljava/lang/String;
       4: astore_3
       5: aload_0
       6: getfield      #11                 // Field mInput:Lcom/ctc/wstx/io/WstxInputSource;
       9: aload_3
      10: invokevirtual #177                // Method com/ctc/wstx/io/WstxInputSource.isOrIsExpandedFrom:(Ljava/lang/String;)Z
      13: ifeq          21
      16: aload_0
      17: aload_3
      18: invokespecial #178                // Method throwRecursionError:(Ljava/lang/String;)V
      21: aload_1
      22: invokevirtual #179                // Method com/ctc/wstx/ent/EntityDecl.isParsed:()Z
      25: ifne          36
      28: aload_0
      29: ldc           #180                // String Illegal reference to unparsed external entity \"{0}\"
      31: aload_3
      32: aconst_null
      33: invokevirtual #40                 // Method throwParseError:(Ljava/lang/String;Ljava/lang/Object;Ljava/lang/Object;)V
      36: aload_1
      37: invokevirtual #181                // Method com/ctc/wstx/ent/EntityDecl.isExternal:()Z
      40: istore        4
      42: iload         4
      44: ifeq          78
      47: iload_2
      48: ifne          59
      51: aload_0
      52: ldc           #182                // String Encountered a reference to external parsed entity \"{0}\" when expanding attribute value: not legal as per XML 1.0/1.1 #3.1
      54: aload_3
      55: aconst_null
      56: invokevirtual #40                 // Method throwParseError:(Ljava/lang/String;Ljava/lang/Object;Ljava/lang/Object;)V
      59: aload_0
      60: getfield      #13                 // Field mConfig:Lcom/ctc/wstx/api/ReaderConfig;
      63: invokevirtual #183                // Method com/ctc/wstx/api/ReaderConfig.willSupportExternalEntities:()Z
      66: ifne          78
      69: aload_0
      70: ldc           #184                // String Encountered a reference to external entity \"{0}\", but stream reader has feature \"{1}\" disabled
      72: aload_3
      73: ldc           #186                // String javax.xml.stream.isSupportingExternalEntities
      75: invokevirtual #40                 // Method throwParseError:(Ljava/lang/String;Ljava/lang/Object;Ljava/lang/Object;)V
      78: aload_0
      79: ldc           #187                // String Maximum entity expansion count
      81: aload_0
      82: getfield      #13                 // Field mConfig:Lcom/ctc/wstx/api/ReaderConfig;
      85: invokevirtual #188                // Method com/ctc/wstx/api/ReaderConfig.getMaxEntityCount:()J
      88: aload_0
      89: dup
      90: getfield      #189                // Field mEntityExpansionCount:I
      93: iconst_1
      94: iadd
      95: dup_x1
      96: putfield      #189                // Field mEntityExpansionCount:I
      99: i2l
     100: invokevirtual #109                // Method verifyLimit:(Ljava/lang/String;JJ)V
     103: aload_0
     104: getfield      #11                 // Field mInput:Lcom/ctc/wstx/io/WstxInputSource;
     107: astore        5
     109: aload         5
     111: aload_0
     112: invokevirtual #190                // Method com/ctc/wstx/io/WstxInputSource.saveContext:(Lcom/ctc/wstx/io/WstxInputData;)V
     115: aconst_null
     116: astore        6
     118: aload_1
     119: aload         5
     121: aload_0
     122: getfield      #2                  // Field mEntityResolver:Ljavax/xml/stream/XMLResolver;
     125: aload_0
     126: getfield      #13                 // Field mConfig:Lcom/ctc/wstx/api/ReaderConfig;
     129: aload_0
     130: getfield      #10                 // Field mDocXmlVersion:I
     133: invokevirtual #191                // Method com/ctc/wstx/ent/EntityDecl.expand:(Lcom/ctc/wstx/io/WstxInputSource;Ljavax/xml/stream/XMLResolver;Lcom/ctc/wstx/api/ReaderConfig;I)Lcom/ctc/wstx/io/WstxInputSource;
     136: astore        6
     138: goto          174
     141: astore        7
     143: aload_0
     144: ldc           #193                // String (was {0}) {1}
     146: aload         7
     148: invokevirtual #194                // Method java/lang/Object.getClass:()Ljava/lang/Class;
     151: invokevirtual #195                // Method java/lang/Class.getName:()Ljava/lang/String;
     154: aload         7
     156: invokevirtual #196                // Method java/io/FileNotFoundException.getMessage:()Ljava/lang/String;
     159: invokevirtual #40                 // Method throwParseError:(Ljava/lang/String;Ljava/lang/Object;Ljava/lang/Object;)V
     162: goto          174
     165: astore        7
     167: aload_0
     168: aload         7
     170: invokevirtual #116                // Method constructFromIOE:(Ljava/io/IOException;)Lcom/ctc/wstx/exc/WstxException;
     173: athrow
     174: aload_0
     175: aload         6
     177: iload         4
     179: aload_3
     180: invokevirtual #197                // Method initInputSource:(Lcom/ctc/wstx/io/WstxInputSource;ZLjava/lang/String;)V
     183: return
    Exception table:
       from    to  target type
         118   138   141   Class java/io/FileNotFoundException
         118   138   165   Class java/io/IOException

  private com.ctc.wstx.ent.EntityDecl expandUnresolvedEntity(java.lang.String) throws javax.xml.stream.XMLStreamException;
    Code:
       0: aload_0
       1: getfield      #13                 // Field mConfig:Lcom/ctc/wstx/api/ReaderConfig;
       4: invokevirtual #198                // Method com/ctc/wstx/api/ReaderConfig.getUndeclaredEntityResolver:()Ljavax/xml/stream/XMLResolver;
       7: astore_2
       8: aload_2
       9: ifnull        131
      12: aload_0
      13: getfield      #11                 // Field mInput:Lcom/ctc/wstx/io/WstxInputSource;
      16: aload_1
      17: invokevirtual #177                // Method com/ctc/wstx/io/WstxInputSource.isOrIsExpandedFrom:(Ljava/lang/String;)Z
      20: ifeq          28
      23: aload_0
      24: aload_1
      25: invokespecial #178                // Method throwRecursionError:(Ljava/lang/String;)V
      28: aload_0
      29: getfield      #11                 // Field mInput:Lcom/ctc/wstx/io/WstxInputSource;
      32: astore_3
      33: aload_3
      34: aload_0
      35: invokevirtual #190                // Method com/ctc/wstx/io/WstxInputSource.saveContext:(Lcom/ctc/wstx/io/WstxInputData;)V
      38: aload_0
      39: getfield      #10                 // Field mDocXmlVersion:I
      42: istore        4
      44: iload         4
      46: ifne          54
      49: sipush        256
      52: istore        4
      54: aload_3
      55: aload_1
      56: aconst_null
      57: aconst_null
      58: aload_2
      59: aload_0
      60: getfield      #13                 // Field mConfig:Lcom/ctc/wstx/api/ReaderConfig;
      63: iload         4
      65: invokestatic  #199                // Method com/ctc/wstx/io/DefaultInputResolver.resolveEntityUsing:(Lcom/ctc/wstx/io/WstxInputSource;Ljava/lang/String;Ljava/lang/String;Ljava/lang/String;Ljavax/xml/stream/XMLResolver;Lcom/ctc/wstx/api/ReaderConfig;I)Lcom/ctc/wstx/io/WstxInputSource;
      68: astore        5
      70: aload_0
      71: getfield      #28                 // Field mCfgTreatCharRefsAsEntities:Z
      74: ifeq          104
      77: new           #162                // class com/ctc/wstx/ent/IntEntity
      80: dup
      81: invokestatic  #200                // Method com/ctc/wstx/io/WstxInputLocation.getEmptyLocation:()Lcom/ctc/wstx/io/WstxInputLocation;
      84: aload         5
      86: invokevirtual #201                // Method com/ctc/wstx/io/WstxInputSource.getEntityId:()Ljava/lang/String;
      89: aload         5
      91: invokevirtual #37                 // Method com/ctc/wstx/io/WstxInputSource.getSource:()Ljava/net/URL;
      94: iconst_0
      95: newarray       char
      97: invokestatic  #200                // Method com/ctc/wstx/io/WstxInputLocation.getEmptyLocation:()Lcom/ctc/wstx/io/WstxInputLocation;
     100: invokespecial #202                // Method com/ctc/wstx/ent/IntEntity."<init>":(Ljavax/xml/stream/Location;Ljava/lang/String;Ljava/net/URL;[CLjavax/xml/stream/Location;)V
     103: areturn
     104: goto          116
     107: astore        6
     109: aload_0
     110: aload         6
     112: invokevirtual #116                // Method constructFromIOE:(Ljava/io/IOException;)Lcom/ctc/wstx/exc/WstxException;
     115: athrow
     116: aload         5
     118: ifnull        131
     121: aload_0
     122: aload         5
     124: iconst_1
     125: aload_1
     126: invokevirtual #197                // Method initInputSource:(Lcom/ctc/wstx/io/WstxInputSource;ZLjava/lang/String;)V
     129: aconst_null
     130: areturn
     131: aload_0
     132: aload_1
     133: invokevirtual #203                // Method handleUndeclaredEntity:(Ljava/lang/String;)V
     136: aconst_null
     137: areturn
    Exception table:
       from    to  target type
          54   103   107   Class java/io/IOException

  protected abstract com.ctc.wstx.ent.EntityDecl findEntity(java.lang.String, java.lang.Object) throws javax.xml.stream.XMLStreamException;

  protected abstract void handleUndeclaredEntity(java.lang.String) throws javax.xml.stream.XMLStreamException;

  protected abstract void handleIncompleteEntityProblem(com.ctc.wstx.io.WstxInputSource) throws javax.xml.stream.XMLStreamException;

  protected java.lang.String parseLocalName(char) throws javax.xml.stream.XMLStreamException;
    Code:
       0: aload_0
       1: iload_1
       2: invokevirtual #204                // Method isNameStartChar:(C)Z
       5: ifne          28
       8: iload_1
       9: bipush        58
      11: if_icmpne     21
      14: aload_0
      15: iload_1
      16: ldc           #205                // String  (missing namespace prefix?)
      18: invokevirtual #131                // Method throwUnexpectedChar:(ILjava/lang/String;)V
      21: aload_0
      22: iload_1
      23: ldc           #206                // String  (expected a name start character)
      25: invokevirtual #131                // Method throwUnexpectedChar:(ILjava/lang/String;)V
      28: aload_0
      29: getfield      #26                 // Field mInputPtr:I
      32: istore_2
      33: iload_1
      34: istore_3
      35: aload_0
      36: getfield      #25                 // Field mInputEnd:I
      39: istore        4
      41: iload_2
      42: iconst_1
      43: isub
      44: istore        5
      46: aload_0
      47: getfield      #24                 // Field mInputBuffer:[C
      50: astore        6
      52: iload_2
      53: iload         4
      55: if_icmplt     71
      58: aload_0
      59: iload_2
      60: putfield      #26                 // Field mInputPtr:I
      63: aload_0
      64: iload         5
      66: iload_3
      67: invokevirtual #207                // Method parseLocalName2:(II)Ljava/lang/String;
      70: areturn
      71: aload         6
      73: iload_2
      74: caload
      75: istore_1
      76: iload_1
      77: bipush        45
      79: if_icmpge     85
      82: goto          109
      85: aload_0
      86: iload_1
      87: invokevirtual #209                // Method isNameChar:(C)Z
      90: ifne          96
      93: goto          109
      96: iload_3
      97: bipush        31
      99: imul
     100: iload_1
     101: iadd
     102: istore_3
     103: iinc          2, 1
     106: goto          52
     109: aload_0
     110: iload_2
     111: putfield      #26                 // Field mInputPtr:I
     114: aload_0
     115: getfield      #15                 // Field mSymbols:Lcom/ctc/wstx/util/SymbolTable;
     118: aload_0
     119: getfield      #24                 // Field mInputBuffer:[C
     122: iload         5
     124: iload_2
     125: iload         5
     127: isub
     128: iload_3
     129: invokevirtual #210                // Method com/ctc/wstx/util/SymbolTable.findSymbol:([CIII)Ljava/lang/String;
     132: areturn

  protected java.lang.String parseLocalName2(int, int) throws javax.xml.stream.XMLStreamException;
    Code:
       0: aload_0
       1: getfield      #25                 // Field mInputEnd:I
       4: iload_1
       5: isub
       6: istore_3
       7: aload_0
       8: iload_3
       9: bipush        8
      11: iadd
      12: invokevirtual #211                // Method getNameBuffer:(I)[C
      15: astore        4
      17: iload_3
      18: ifle          33
      21: aload_0
      22: getfield      #24                 // Field mInputBuffer:[C
      25: iload_1
      26: aload         4
      28: iconst_0
      29: iload_3
      30: invokestatic  #212                // Method java/lang/System.arraycopy:(Ljava/lang/Object;ILjava/lang/Object;II)V
      33: aload         4
      35: arraylength
      36: istore        5
      38: aload_0
      39: getfield      #26                 // Field mInputPtr:I
      42: aload_0
      43: getfield      #25                 // Field mInputEnd:I
      46: if_icmplt     59
      49: aload_0
      50: invokevirtual #96                 // Method loadMoreFromCurrent:()Z
      53: ifne          59
      56: goto          146
      59: aload_0
      60: getfield      #24                 // Field mInputBuffer:[C
      63: aload_0
      64: getfield      #26                 // Field mInputPtr:I
      67: caload
      68: istore        6
      70: iload         6
      72: bipush        45
      74: if_icmpge     80
      77: goto          146
      80: aload_0
      81: iload         6
      83: invokevirtual #209                // Method isNameChar:(C)Z
      86: ifne          92
      89: goto          146
      92: aload_0
      93: dup
      94: getfield      #26                 // Field mInputPtr:I
      97: iconst_1
      98: iadd
      99: putfield      #26                 // Field mInputPtr:I
     102: iload_3
     103: iload         5
     105: if_icmplt     126
     108: aload_0
     109: aload_0
     110: aload         4
     112: invokevirtual #213                // Method expandBy50Pct:([C)[C
     115: dup
     116: astore        4
     118: putfield      #3                  // Field mNameBuffer:[C
     121: aload         4
     123: arraylength
     124: istore        5
     126: aload         4
     128: iload_3
     129: iinc          3, 1
     132: iload         6
     134: castore
     135: iload_2
     136: bipush        31
     138: imul
     139: iload         6
     141: iadd
     142: istore_2
     143: goto          38
     146: aload_0
     147: getfield      #15                 // Field mSymbols:Lcom/ctc/wstx/util/SymbolTable;
     150: aload         4
     152: iconst_0
     153: iload_3
     154: iload_2
     155: invokevirtual #210                // Method com/ctc/wstx/util/SymbolTable.findSymbol:([CIII)Ljava/lang/String;
     158: areturn

  protected java.lang.String parseFullName() throws javax.xml.stream.XMLStreamException;
    Code:
       0: aload_0
       1: getfield      #26                 // Field mInputPtr:I
       4: aload_0
       5: getfield      #25                 // Field mInputEnd:I
       8: if_icmplt     16
      11: aload_0
      12: invokevirtual #96                 // Method loadMoreFromCurrent:()Z
      15: pop
      16: aload_0
      17: aload_0
      18: getfield      #24                 // Field mInputBuffer:[C
      21: aload_0
      22: dup
      23: getfield      #26                 // Field mInputPtr:I
      26: dup_x1
      27: iconst_1
      28: iadd
      29: putfield      #26                 // Field mInputPtr:I
      32: caload
      33: invokevirtual #214                // Method parseFullName:(C)Ljava/lang/String;
      36: areturn

  protected java.lang.String parseFullName(char) throws javax.xml.stream.XMLStreamException;
    Code:
       0: aload_0
       1: iload_1
       2: invokevirtual #204                // Method isNameStartChar:(C)Z
       5: ifne          52
       8: iload_1
       9: bipush        58
      11: if_icmpne     32
      14: aload_0
      15: getfield      #18                 // Field mCfgNsEnabled:Z
      18: ifeq          52
      21: aload_0
      22: aload_0
      23: invokevirtual #215                // Method parseFNameForError:()Ljava/lang/String;
      26: invokespecial #216                // Method throwNsColonException:(Ljava/lang/String;)V
      29: goto          52
      32: iload_1
      33: bipush        32
      35: if_icmpgt     45
      38: aload_0
      39: iload_1
      40: ldc           #217                // String  (missing name?)
      42: invokevirtual #131                // Method throwUnexpectedChar:(ILjava/lang/String;)V
      45: aload_0
      46: iload_1
      47: ldc           #206                // String  (expected a name start character)
      49: invokevirtual #131                // Method throwUnexpectedChar:(ILjava/lang/String;)V
      52: aload_0
      53: getfield      #26                 // Field mInputPtr:I
      56: istore_2
      57: iload_1
      58: istore_3
      59: aload_0
      60: getfield      #25                 // Field mInputEnd:I
      63: istore        4
      65: iload_2
      66: iconst_1
      67: isub
      68: istore        5
      70: iload_2
      71: iload         4
      73: if_icmplt     89
      76: aload_0
      77: iload_2
      78: putfield      #26                 // Field mInputPtr:I
      81: aload_0
      82: iload         5
      84: iload_3
      85: invokevirtual #218                // Method parseFullName2:(II)Ljava/lang/String;
      88: areturn
      89: aload_0
      90: getfield      #24                 // Field mInputBuffer:[C
      93: iload_2
      94: caload
      95: istore_1
      96: iload_1
      97: bipush        58
      99: if_icmpne     158
     102: aload_0
     103: getfield      #18                 // Field mCfgNsEnabled:Z
     106: ifeq          178
     109: aload_0
     110: iload_2
     111: putfield      #26                 // Field mInputPtr:I
     114: aload_0
     115: new           #72                 // class java/lang/StringBuilder
     118: dup
     119: invokespecial #73                 // Method java/lang/StringBuilder."<init>":()V
     122: new           #159                // class java/lang/String
     125: dup
     126: aload_0
     127: getfield      #24                 // Field mInputBuffer:[C
     130: iload         5
     132: iload_2
     133: iload         5
     135: isub
     136: invokespecial #219                // Method java/lang/String."<init>":([CII)V
     139: invokevirtual #75                 // Method java/lang/StringBuilder.append:(Ljava/lang/String;)Ljava/lang/StringBuilder;
     142: aload_0
     143: invokevirtual #215                // Method parseFNameForError:()Ljava/lang/String;
     146: invokevirtual #75                 // Method java/lang/StringBuilder.append:(Ljava/lang/String;)Ljava/lang/StringBuilder;
     149: invokevirtual #77                 // Method java/lang/StringBuilder.toString:()Ljava/lang/String;
     152: invokespecial #216                // Method throwNsColonException:(Ljava/lang/String;)V
     155: goto          178
     158: iload_1
     159: bipush        45
     161: if_icmpge     167
     164: goto          191
     167: aload_0
     168: iload_1
     169: invokevirtual #209                // Method isNameChar:(C)Z
     172: ifne          178
     175: goto          191
     178: iload_3
     179: bipush        31
     181: imul
     182: iload_1
     183: iadd
     184: istore_3
     185: iinc          2, 1
     188: goto          70
     191: aload_0
     192: iload_2
     193: putfield      #26                 // Field mInputPtr:I
     196: aload_0
     197: getfield      #15                 // Field mSymbols:Lcom/ctc/wstx/util/SymbolTable;
     200: aload_0
     201: getfield      #24                 // Field mInputBuffer:[C
     204: iload         5
     206: iload_2
     207: iload         5
     209: isub
     210: iload_3
     211: invokevirtual #210                // Method com/ctc/wstx/util/SymbolTable.findSymbol:([CIII)Ljava/lang/String;
     214: areturn

  protected java.lang.String parseFullName2(int, int) throws javax.xml.stream.XMLStreamException;
    Code:
       0: aload_0
       1: getfield      #25                 // Field mInputEnd:I
       4: iload_1
       5: isub
       6: istore_3
       7: aload_0
       8: iload_3
       9: bipush        8
      11: iadd
      12: invokevirtual #211                // Method getNameBuffer:(I)[C
      15: astore        4
      17: iload_3
      18: ifle          33
      21: aload_0
      22: getfield      #24                 // Field mInputBuffer:[C
      25: iload_1
      26: aload         4
      28: iconst_0
      29: iload_3
      30: invokestatic  #212                // Method java/lang/System.arraycopy:(Ljava/lang/Object;ILjava/lang/Object;II)V
      33: aload         4
      35: arraylength
      36: istore        5
      38: aload_0
      39: getfield      #26                 // Field mInputPtr:I
      42: aload_0
      43: getfield      #25                 // Field mInputEnd:I
      46: if_icmplt     59
      49: aload_0
      50: invokevirtual #96                 // Method loadMoreFromCurrent:()Z
      53: ifne          59
      56: goto          203
      59: aload_0
      60: getfield      #24                 // Field mInputBuffer:[C
      63: aload_0
      64: getfield      #26                 // Field mInputPtr:I
      67: caload
      68: istore        6
      70: iload         6
      72: bipush        58
      74: if_icmpne     127
      77: aload_0
      78: getfield      #18                 // Field mCfgNsEnabled:Z
      81: ifeq          149
      84: aload_0
      85: new           #72                 // class java/lang/StringBuilder
      88: dup
      89: invokespecial #73                 // Method java/lang/StringBuilder."<init>":()V
      92: new           #159                // class java/lang/String
      95: dup
      96: aload         4
      98: iconst_0
      99: iload_3
     100: invokespecial #219                // Method java/lang/String."<init>":([CII)V
     103: invokevirtual #75                 // Method java/lang/StringBuilder.append:(Ljava/lang/String;)Ljava/lang/StringBuilder;
     106: iload         6
     108: invokevirtual #220                // Method java/lang/StringBuilder.append:(C)Ljava/lang/StringBuilder;
     111: aload_0
     112: invokevirtual #215                // Method parseFNameForError:()Ljava/lang/String;
     115: invokevirtual #75                 // Method java/lang/StringBuilder.append:(Ljava/lang/String;)Ljava/lang/StringBuilder;
     118: invokevirtual #77                 // Method java/lang/StringBuilder.toString:()Ljava/lang/String;
     121: invokespecial #216                // Method throwNsColonException:(Ljava/lang/String;)V
     124: goto          149
     127: iload         6
     129: bipush        45
     131: if_icmpge     137
     134: goto          203
     137: aload_0
     138: iload         6
     140: invokevirtual #209                // Method isNameChar:(C)Z
     143: ifne          149
     146: goto          203
     149: aload_0
     150: dup
     151: getfield      #26                 // Field mInputPtr:I
     154: iconst_1
     155: iadd
     156: putfield      #26                 // Field mInputPtr:I
     159: iload_3
     160: iload         5
     162: if_icmplt     183
     165: aload_0
     166: aload_0
     167: aload         4
     169: invokevirtual #213                // Method expandBy50Pct:([C)[C
     172: dup
     173: astore        4
     175: putfield      #3                  // Field mNameBuffer:[C
     178: aload         4
     180: arraylength
     181: istore        5
     183: aload         4
     185: iload_3
     186: iinc          3, 1
     189: iload         6
     191: castore
     192: iload_2
     193: bipush        31
     195: imul
     196: iload         6
     198: iadd
     199: istore_2
     200: goto          38
     203: aload_0
     204: getfield      #15                 // Field mSymbols:Lcom/ctc/wstx/util/SymbolTable;
     207: aload         4
     209: iconst_0
     210: iload_3
     211: iload_2
     212: invokevirtual #210                // Method com/ctc/wstx/util/SymbolTable.findSymbol:([CIII)Ljava/lang/String;
     215: areturn

  protected java.lang.String parseFNameForError() throws javax.xml.stream.XMLStreamException;
    Code:
       0: new           #72                 // class java/lang/StringBuilder
       3: dup
       4: bipush        100
       6: invokespecial #221                // Method java/lang/StringBuilder."<init>":(I)V
       9: astore_1
      10: aload_0
      11: getfield      #26                 // Field mInputPtr:I
      14: aload_0
      15: getfield      #25                 // Field mInputEnd:I
      18: if_icmpge     41
      21: aload_0
      22: getfield      #24                 // Field mInputBuffer:[C
      25: aload_0
      26: dup
      27: getfield      #26                 // Field mInputPtr:I
      30: dup_x1
      31: iconst_1
      32: iadd
      33: putfield      #26                 // Field mInputPtr:I
      36: caload
      37: istore_2
      38: goto          56
      41: aload_0
      42: invokevirtual #222                // Method getNext:()I
      45: istore_3
      46: iload_3
      47: ifge          53
      50: goto          92
      53: iload_3
      54: i2c
      55: istore_2
      56: iload_2
      57: bipush        58
      59: if_icmpeq     83
      62: aload_0
      63: iload_2
      64: invokevirtual #209                // Method isNameChar:(C)Z
      67: ifne          83
      70: aload_0
      71: dup
      72: getfield      #26                 // Field mInputPtr:I
      75: iconst_1
      76: isub
      77: putfield      #26                 // Field mInputPtr:I
      80: goto          92
      83: aload_1
      84: iload_2
      85: invokevirtual #220                // Method java/lang/StringBuilder.append:(C)Ljava/lang/StringBuilder;
      88: pop
      89: goto          10
      92: aload_1
      93: invokevirtual #77                 // Method java/lang/StringBuilder.toString:()Ljava/lang/String;
      96: areturn

  protected final java.lang.String parseEntityName(char) throws javax.xml.stream.XMLStreamException;
    Code:
       0: aload_0
       1: iload_1
       2: invokevirtual #214                // Method parseFullName:(C)Ljava/lang/String;
       5: astore_2
       6: aload_0
       7: getfield      #26                 // Field mInputPtr:I
      10: aload_0
      11: getfield      #25                 // Field mInputEnd:I
      14: if_icmplt     32
      17: aload_0
      18: invokevirtual #96                 // Method loadMoreFromCurrent:()Z
      21: ifne          32
      24: aload_0
      25: ldc           #223                // String Missing semicolon after reference for entity \"{0}\"
      27: aload_2
      28: aconst_null
      29: invokevirtual #40                 // Method throwParseError:(Ljava/lang/String;Ljava/lang/Object;Ljava/lang/Object;)V
      32: aload_0
      33: getfield      #24                 // Field mInputBuffer:[C
      36: aload_0
      37: dup
      38: getfield      #26                 // Field mInputPtr:I
      41: dup_x1
      42: iconst_1
      43: iadd
      44: putfield      #26                 // Field mInputPtr:I
      47: caload
      48: istore_1
      49: iload_1
      50: bipush        59
      52: if_icmpeq     84
      55: aload_0
      56: iload_1
      57: new           #72                 // class java/lang/StringBuilder
      60: dup
      61: invokespecial #73                 // Method java/lang/StringBuilder."<init>":()V
      64: ldc           #224                // String ; expected a semi-colon after the reference for entity \'
      66: invokevirtual #75                 // Method java/lang/StringBuilder.append:(Ljava/lang/String;)Ljava/lang/StringBuilder;
      69: aload_2
      70: invokevirtual #75                 // Method java/lang/StringBuilder.append:(Ljava/lang/String;)Ljava/lang/StringBuilder;
      73: ldc           #225                // String \'
      75: invokevirtual #75                 // Method java/lang/StringBuilder.append:(Ljava/lang/String;)Ljava/lang/StringBuilder;
      78: invokevirtual #77                 // Method java/lang/StringBuilder.toString:()Ljava/lang/String;
      81: invokevirtual #131                // Method throwUnexpectedChar:(ILjava/lang/String;)V
      84: aload_2
      85: areturn

  protected int skipFullName(char) throws javax.xml.stream.XMLStreamException;
    Code:
       0: aload_0
       1: iload_1
       2: invokevirtual #204                // Method isNameStartChar:(C)Z
       5: ifne          20
       8: aload_0
       9: dup
      10: getfield      #26                 // Field mInputPtr:I
      13: iconst_1
      14: isub
      15: putfield      #26                 // Field mInputPtr:I
      18: iconst_0
      19: ireturn
      20: iconst_1
      21: istore_2
      22: aload_0
      23: getfield      #26                 // Field mInputPtr:I
      26: aload_0
      27: getfield      #25                 // Field mInputEnd:I
      30: if_icmpge     52
      33: aload_0
      34: getfield      #24                 // Field mInputBuffer:[C
      37: aload_0
      38: dup
      39: getfield      #26                 // Field mInputPtr:I
      42: dup_x1
      43: iconst_1
      44: iadd
      45: putfield      #26                 // Field mInputPtr:I
      48: caload
      49: goto          58
      52: aload_0
      53: ldc           #226                // String ; expected an identifier
      55: invokevirtual #227                // Method getNextChar:(Ljava/lang/String;)C
      58: istore_1
      59: iload_1
      60: bipush        58
      62: if_icmpeq     76
      65: aload_0
      66: iload_1
      67: invokevirtual #209                // Method isNameChar:(C)Z
      70: ifne          76
      73: goto          82
      76: iinc          2, 1
      79: goto          22
      82: iload_2
      83: ireturn

  protected final java.lang.String parseSystemId(char, boolean, java.lang.String) throws javax.xml.stream.XMLStreamException;
    Code:
       0: aload_0
       1: iconst_m1
       2: invokevirtual #211                // Method getNameBuffer:(I)[C
       5: astore        4
       7: iconst_0
       8: istore        5
      10: aload_0
      11: getfield      #26                 // Field mInputPtr:I
      14: aload_0
      15: getfield      #25                 // Field mInputEnd:I
      18: if_icmpge     40
      21: aload_0
      22: getfield      #24                 // Field mInputBuffer:[C
      25: aload_0
      26: dup
      27: getfield      #26                 // Field mInputPtr:I
      30: dup_x1
      31: iconst_1
      32: iadd
      33: putfield      #26                 // Field mInputPtr:I
      36: caload
      37: goto          45
      40: aload_0
      41: aload_3
      42: invokevirtual #227                // Method getNextChar:(Ljava/lang/String;)C
      45: istore        6
      47: iload         6
      49: iload_1
      50: if_icmpne     56
      53: goto          170
      56: iload         6
      58: bipush        10
      60: if_icmpne     70
      63: aload_0
      64: invokevirtual #228                // Method markLF:()V
      67: goto          141
      70: iload         6
      72: bipush        13
      74: if_icmpne     141
      77: aload_0
      78: invokevirtual #103                // Method peekNext:()I
      81: bipush        10
      83: if_icmpne     133
      86: aload_0
      87: dup
      88: getfield      #26                 // Field mInputPtr:I
      91: iconst_1
      92: iadd
      93: putfield      #26                 // Field mInputPtr:I
      96: iload_2
      97: ifne          126
     100: iload         5
     102: aload         4
     104: arraylength
     105: if_icmplt     116
     108: aload_0
     109: aload         4
     111: invokevirtual #213                // Method expandBy50Pct:([C)[C
     114: astore        4
     116: aload         4
     118: iload         5
     120: iinc          5, 1
     123: bipush        13
     125: castore
     126: bipush        10
     128: istore        6
     130: goto          141
     133: iload_2
     134: ifeq          141
     137: bipush        10
     139: istore        6
     141: iload         5
     143: aload         4
     145: arraylength
     146: if_icmplt     157
     149: aload_0
     150: aload         4
     152: invokevirtual #213                // Method expandBy50Pct:([C)[C
     155: astore        4
     157: aload         4
     159: iload         5
     161: iinc          5, 1
     164: iload         6
     166: castore
     167: goto          10
     170: iload         5
     172: ifne          180
     175: ldc           #86                 // String
     177: goto          192
     180: new           #159                // class java/lang/String
     183: dup
     184: aload         4
     186: iconst_0
     187: iload         5
     189: invokespecial #219                // Method java/lang/String."<init>":([CII)V
     192: areturn

  protected final java.lang.String parsePublicId(char, java.lang.String) throws javax.xml.stream.XMLStreamException;
    Code:
       0: aload_0
       1: iconst_m1
       2: invokevirtual #211                // Method getNameBuffer:(I)[C
       5: astore_3
       6: iconst_0
       7: istore        4
       9: iconst_0
      10: istore        5
      12: aload_0
      13: getfield      #26                 // Field mInputPtr:I
      16: aload_0
      17: getfield      #25                 // Field mInputEnd:I
      20: if_icmpge     42
      23: aload_0
      24: getfield      #24                 // Field mInputBuffer:[C
      27: aload_0
      28: dup
      29: getfield      #26                 // Field mInputPtr:I
      32: dup_x1
      33: iconst_1
      34: iadd
      35: putfield      #26                 // Field mInputPtr:I
      38: caload
      39: goto          47
      42: aload_0
      43: aload_2
      44: invokevirtual #227                // Method getNextChar:(Ljava/lang/String;)C
      47: istore        6
      49: iload         6
      51: iload_1
      52: if_icmpne     58
      55: goto          216
      58: iload         6
      60: bipush        10
      62: if_icmpne     75
      65: aload_0
      66: invokevirtual #228                // Method markLF:()V
      69: iconst_1
      70: istore        5
      72: goto          12
      75: iload         6
      77: bipush        13
      79: if_icmpne     107
      82: aload_0
      83: invokevirtual #103                // Method peekNext:()I
      86: bipush        10
      88: if_icmpne     101
      91: aload_0
      92: dup
      93: getfield      #26                 // Field mInputPtr:I
      96: iconst_1
      97: iadd
      98: putfield      #26                 // Field mInputPtr:I
     101: iconst_1
     102: istore        5
     104: goto          12
     107: iload         6
     109: bipush        32
     111: if_icmpne     120
     114: iconst_1
     115: istore        5
     117: goto          12
     120: iload         6
     122: sipush        128
     125: if_icmpge     138
     128: getstatic     #229                // Field sPubidValidity:[B
     131: iload         6
     133: baload
     134: iconst_1
     135: if_icmpeq     146
     138: aload_0
     139: iload         6
     141: ldc           #230                // String  in public identifier
     143: invokevirtual #131                // Method throwUnexpectedChar:(ILjava/lang/String;)V
     146: iload         4
     148: aload_3
     149: arraylength
     150: if_icmplt     159
     153: aload_0
     154: aload_3
     155: invokevirtual #213                // Method expandBy50Pct:([C)[C
     158: astore_3
     159: iload         5
     161: ifeq          204
     164: iload         6
     166: bipush        32
     168: if_icmpne     174
     171: goto          12
     174: iconst_0
     175: istore        5
     177: iload         4
     179: ifle          204
     182: aload_3
     183: iload         4
     185: iinc          4, 1
     188: bipush        32
     190: castore
     191: iload         4
     193: aload_3
     194: arraylength
     195: if_icmplt     204
     198: aload_0
     199: aload_3
     200: invokevirtual #213                // Method expandBy50Pct:([C)[C
     203: astore_3
     204: aload_3
     205: iload         4
     207: iinc          4, 1
     210: iload         6
     212: castore
     213: goto          12
     216: iload         4
     218: ifne          226
     221: ldc           #86                 // String
     223: goto          237
     226: new           #159                // class java/lang/String
     229: dup
     230: aload_3
     231: iconst_0
     232: iload         4
     234: invokespecial #219                // Method java/lang/String."<init>":([CII)V
     237: areturn

  protected final void parseUntil(com.ctc.wstx.util.TextBuffer, char, boolean, java.lang.String) throws javax.xml.stream.XMLStreamException;
    Code:
       0: aload_0
       1: getfield      #26                 // Field mInputPtr:I
       4: aload_0
       5: getfield      #25                 // Field mInputEnd:I
       8: if_icmplt     18
      11: aload_0
      12: aload         4
      14: invokevirtual #97                 // Method loadMore:(Ljava/lang/String;)Z
      17: pop
      18: aload_0
      19: getfield      #24                 // Field mInputBuffer:[C
      22: astore        5
      24: aload_0
      25: getfield      #25                 // Field mInputEnd:I
      28: istore        6
      30: aload_0
      31: getfield      #26                 // Field mInputPtr:I
      34: istore        7
      36: iload         7
      38: istore        8
      40: iload         7
      42: iload         6
      44: if_icmpge     272
      47: aload         5
      49: iload         7
      51: iinc          7, 1
      54: caload
      55: istore        9
      57: iload         9
      59: iload_2
      60: if_icmpne     94
      63: iload         7
      65: iload         8
      67: isub
      68: iconst_1
      69: isub
      70: istore        10
      72: iload         10
      74: ifle          87
      77: aload_1
      78: aload         5
      80: iload         8
      82: iload         10
      84: invokevirtual #231                // Method com/ctc/wstx/util/TextBuffer.append:([CII)V
      87: aload_0
      88: iload         7
      90: putfield      #26                 // Field mInputPtr:I
      93: return
      94: iload         9
      96: bipush        10
      98: if_icmpne     114
     101: aload_0
     102: iload         7
     104: putfield      #26                 // Field mInputPtr:I
     107: aload_0
     108: invokevirtual #228                // Method markLF:()V
     111: goto          269
     114: iload         9
     116: bipush        13
     118: if_icmpne     269
     121: iload_3
     122: ifne          158
     125: iload         7
     127: iload         6
     129: if_icmpge     158
     132: aload         5
     134: iload         7
     136: caload
     137: bipush        10
     139: if_icmpne     145
     142: iinc          7, 1
     145: aload_0
     146: iload         7
     148: putfield      #26                 // Field mInputPtr:I
     151: aload_0
     152: invokevirtual #228                // Method markLF:()V
     155: goto          269
     158: iload         7
     160: iload         8
     162: isub
     163: iconst_1
     164: isub
     165: istore        10
     167: iload         10
     169: ifle          182
     172: aload_1
     173: aload         5
     175: iload         8
     177: iload         10
     179: invokevirtual #231                // Method com/ctc/wstx/util/TextBuffer.append:([CII)V
     182: aload_0
     183: iload         7
     185: putfield      #26                 // Field mInputPtr:I
     188: aload_0
     189: aload         4
     191: invokevirtual #227                // Method getNextChar:(Ljava/lang/String;)C
     194: istore        9
     196: iload         9
     198: bipush        10
     200: if_icmpeq     231
     203: aload_0
     204: dup
     205: getfield      #26                 // Field mInputPtr:I
     208: iconst_1
     209: isub
     210: putfield      #26                 // Field mInputPtr:I
     213: aload_1
     214: iload_3
     215: ifeq          223
     218: bipush        10
     220: goto          225
     223: bipush        13
     225: invokevirtual #232                // Method com/ctc/wstx/util/TextBuffer.append:(C)V
     228: goto          256
     231: iload_3
     232: ifeq          244
     235: aload_1
     236: bipush        10
     238: invokevirtual #232                // Method com/ctc/wstx/util/TextBuffer.append:(C)V
     241: goto          256
     244: aload_1
     245: bipush        13
     247: invokevirtual #232                // Method com/ctc/wstx/util/TextBuffer.append:(C)V
     250: aload_1
     251: bipush        10
     253: invokevirtual #232                // Method com/ctc/wstx/util/TextBuffer.append:(C)V
     256: aload_0
     257: getfield      #26                 // Field mInputPtr:I
     260: dup
     261: istore        7
     263: istore        8
     265: aload_0
     266: invokevirtual #228                // Method markLF:()V
     269: goto          40
     272: iload         7
     274: iload         8
     276: isub
     277: istore        9
     279: iload         9
     281: ifle          294
     284: aload_1
     285: aload         5
     287: iload         8
     289: iload         9
     291: invokevirtual #231                // Method com/ctc/wstx/util/TextBuffer.append:([CII)V
     294: aload_0
     295: aload         4
     297: invokevirtual #97                 // Method loadMore:(Ljava/lang/String;)Z
     300: pop
     301: aload_0
     302: getfield      #26                 // Field mInputPtr:I
     305: dup
     306: istore        7
     308: istore        8
     310: aload_0
     311: getfield      #24                 // Field mInputBuffer:[C
     314: astore        5
     316: aload_0
     317: getfield      #25                 // Field mInputEnd:I
     320: istore        6
     322: goto          18

  private int resolveCharEnt(java.lang.StringBuffer) throws javax.xml.stream.XMLStreamException;
    Code:
       0: iconst_0
       1: istore_2
       2: aload_0
       3: ldc           #139                // String  in entity reference
       5: invokevirtual #227                // Method getNextChar:(Ljava/lang/String;)C
       8: istore_3
       9: aload_1
      10: ifnull        19
      13: aload_1
      14: iload_3
      15: invokevirtual #168                // Method java/lang/StringBuffer.append:(C)Ljava/lang/StringBuffer;
      18: pop
      19: iload_3
      20: bipush        120
      22: if_icmpne     177
      25: aload_0
      26: getfield      #26                 // Field mInputPtr:I
      29: aload_0
      30: getfield      #25                 // Field mInputEnd:I
      33: if_icmpge     55
      36: aload_0
      37: getfield      #24                 // Field mInputBuffer:[C
      40: aload_0
      41: dup
      42: getfield      #26                 // Field mInputPtr:I
      45: dup_x1
      46: iconst_1
      47: iadd
      48: putfield      #26                 // Field mInputPtr:I
      51: caload
      52: goto          61
      55: aload_0
      56: ldc           #139                // String  in entity reference
      58: invokevirtual #101                // Method getNextCharFromCurrent:(Ljava/lang/String;)C
      61: istore_3
      62: iload_3
      63: bipush        59
      65: if_icmpne     71
      68: goto          281
      71: aload_1
      72: ifnull        81
      75: aload_1
      76: iload_3
      77: invokevirtual #168                // Method java/lang/StringBuffer.append:(C)Ljava/lang/StringBuffer;
      80: pop
      81: iload_2
      82: iconst_4
      83: ishl
      84: istore_2
      85: iload_3
      86: bipush        57
      88: if_icmpgt     107
      91: iload_3
      92: bipush        48
      94: if_icmplt     107
      97: iload_2
      98: iload_3
      99: bipush        48
     101: isub
     102: iadd
     103: istore_2
     104: goto          164
     107: iload_3
     108: bipush        97
     110: if_icmplt     132
     113: iload_3
     114: bipush        102
     116: if_icmpgt     132
     119: iload_2
     120: bipush        10
     122: iload_3
     123: bipush        97
     125: isub
     126: iadd
     127: iadd
     128: istore_2
     129: goto          164
     132: iload_3
     133: bipush        65
     135: if_icmplt     157
     138: iload_3
     139: bipush        70
     141: if_icmpgt     157
     144: iload_2
     145: bipush        10
     147: iload_3
     148: bipush        65
     150: isub
     151: iadd
     152: iadd
     153: istore_2
     154: goto          164
     157: aload_0
     158: iload_3
     159: ldc           #130                // String ; expected a hex digit (0-9a-fA-F).
     161: invokevirtual #131                // Method throwUnexpectedChar:(ILjava/lang/String;)V
     164: iload_2
     165: ldc           #132                // int 1114111
     167: if_icmple     25
     170: aload_0
     171: invokespecial #133                // Method reportUnicodeOverflow:()V
     174: goto          25
     177: iload_3
     178: bipush        59
     180: if_icmpeq     281
     183: iload_3
     184: bipush        57
     186: if_icmpgt     218
     189: iload_3
     190: bipush        48
     192: if_icmplt     218
     195: iload_2
     196: bipush        10
     198: imul
     199: iload_3
     200: bipush        48
     202: isub
     203: iadd
     204: istore_2
     205: iload_2
     206: ldc           #132                // int 1114111
     208: if_icmple     225
     211: aload_0
     212: invokespecial #133                // Method reportUnicodeOverflow:()V
     215: goto          225
     218: aload_0
     219: iload_3
     220: ldc           #134                // String ; expected a decimal number.
     222: invokevirtual #131                // Method throwUnexpectedChar:(ILjava/lang/String;)V
     225: aload_0
     226: getfield      #26                 // Field mInputPtr:I
     229: aload_0
     230: getfield      #25                 // Field mInputEnd:I
     233: if_icmpge     255
     236: aload_0
     237: getfield      #24                 // Field mInputBuffer:[C
     240: aload_0
     241: dup
     242: getfield      #26                 // Field mInputPtr:I
     245: dup_x1
     246: iconst_1
     247: iadd
     248: putfield      #26                 // Field mInputPtr:I
     251: caload
     252: goto          261
     255: aload_0
     256: ldc           #139                // String  in entity reference
     258: invokevirtual #101                // Method getNextCharFromCurrent:(Ljava/lang/String;)C
     261: istore_3
     262: aload_1
     263: ifnull        177
     266: iload_3
     267: bipush        59
     269: if_icmpeq     177
     272: aload_1
     273: iload_3
     274: invokevirtual #168                // Method java/lang/StringBuffer.append:(C)Ljava/lang/StringBuffer;
     277: pop
     278: goto          177
     281: aload_0
     282: iload_2
     283: invokespecial #135                // Method validateChar:(I)V
     286: iload_2
     287: ireturn

  private final void validateChar(int) throws javax.xml.stream.XMLStreamException;
    Code:
       0: iload_1
       1: ldc           #167                // int 55296
       3: if_icmplt     50
       6: iload_1
       7: ldc           #233                // int 57344
       9: if_icmpge     17
      12: aload_0
      13: iload_1
      14: invokespecial #234                // Method reportIllegalChar:(I)V
      17: iload_1
      18: ldc           #163                // int 65535
      20: if_icmple     36
      23: iload_1
      24: ldc           #132                // int 1114111
      26: if_icmple     103
      29: aload_0
      30: invokespecial #133                // Method reportUnicodeOverflow:()V
      33: goto          103
      36: iload_1
      37: ldc           #235                // int 65534
      39: if_icmplt     103
      42: aload_0
      43: iload_1
      44: invokespecial #234                // Method reportIllegalChar:(I)V
      47: goto          103
      50: iload_1
      51: bipush        32
      53: if_icmpge     103
      56: iload_1
      57: ifne          66
      60: aload_0
      61: ldc           #236                // String Invalid character reference: null character not allowed in XML content.
      63: invokevirtual #237                // Method throwParseError:(Ljava/lang/String;)V
      66: aload_0
      67: getfield      #82                 // Field mXml11:Z
      70: ifne          103
      73: aload_0
      74: getfield      #21                 // Field mAllowXml11EscapedCharsInXml10:Z
      77: ifne          103
      80: iload_1
      81: bipush        9
      83: if_icmpeq     103
      86: iload_1
      87: bipush        10
      89: if_icmpeq     103
      92: iload_1
      93: bipush        13
      95: if_icmpeq     103
      98: aload_0
      99: iload_1
     100: invokespecial #234                // Method reportIllegalChar:(I)V
     103: return

  protected final char[] getNameBuffer(int);
    Code:
       0: aload_0
       1: getfield      #3                  // Field mNameBuffer:[C
       4: astore_2
       5: aload_2
       6: ifnonnull     35
       9: aload_0
      10: iload_1
      11: bipush        48
      13: if_icmple     23
      16: iload_1
      17: bipush        16
      19: iadd
      20: goto          25
      23: bipush        64
      25: newarray       char
      27: dup
      28: astore_2
      29: putfield      #3                  // Field mNameBuffer:[C
      32: goto          71
      35: iload_1
      36: aload_2
      37: arraylength
      38: if_icmplt     71
      41: aload_2
      42: arraylength
      43: istore_3
      44: iload_3
      45: iload_3
      46: iconst_1
      47: ishr
      48: iadd
      49: istore_3
      50: aload_0
      51: iload_1
      52: iload_3
      53: if_icmplt     63
      56: iload_1
      57: bipush        16
      59: iadd
      60: goto          64
      63: iload_3
      64: newarray       char
      66: dup
      67: astore_2
      68: putfield      #3                  // Field mNameBuffer:[C
      71: aload_2
      72: areturn

  protected final char[] expandBy50Pct(char[]);
    Code:
       0: aload_1
       1: arraylength
       2: istore_2
       3: iload_2
       4: iload_2
       5: iconst_1
       6: ishr
       7: iadd
       8: newarray       char
      10: astore_3
      11: aload_1
      12: iconst_0
      13: aload_3
      14: iconst_0
      15: iload_2
      16: invokestatic  #212                // Method java/lang/System.arraycopy:(Ljava/lang/Object;ILjava/lang/Object;II)V
      19: aload_3
      20: areturn

  private void throwNsColonException(java.lang.String) throws javax.xml.stream.XMLStreamException;
    Code:
       0: aload_0
       1: ldc           #238                // String Illegal name \"{0}\" (PI target, entity/notation name): can not contain a colon (XML Namespaces 1.0#6)
       3: aload_1
       4: aconst_null
       5: invokevirtual #40                 // Method throwParseError:(Ljava/lang/String;Ljava/lang/Object;Ljava/lang/Object;)V
       8: return

  private void throwRecursionError(java.lang.String) throws javax.xml.stream.XMLStreamException;
    Code:
       0: aload_0
       1: ldc           #239                // String Illegal entity expansion: entity \"{0}\" expands itself recursively.
       3: aload_1
       4: aconst_null
       5: invokevirtual #40                 // Method throwParseError:(Ljava/lang/String;Ljava/lang/Object;Ljava/lang/Object;)V
       8: return

  private void reportUnicodeOverflow() throws javax.xml.stream.XMLStreamException;
    Code:
       0: aload_0
       1: ldc           #240                // String Illegal character entity: value higher than max allowed (0x{0})
       3: ldc           #132                // int 1114111
       5: invokestatic  #241                // Method java/lang/Integer.toHexString:(I)Ljava/lang/String;
       8: aconst_null
       9: invokevirtual #40                 // Method throwParseError:(Ljava/lang/String;Ljava/lang/Object;Ljava/lang/Object;)V
      12: return

  private void reportIllegalChar(int) throws javax.xml.stream.XMLStreamException;
    Code:
       0: aload_0
       1: ldc           #242                // String Illegal character entity: expansion character (code 0x{0}
       3: iload_1
       4: invokestatic  #241                // Method java/lang/Integer.toHexString:(I)Ljava/lang/String;
       7: aconst_null
       8: invokevirtual #40                 // Method throwParseError:(Ljava/lang/String;Ljava/lang/Object;Ljava/lang/Object;)V
      11: return

  protected void verifyLimit(java.lang.String, long, long) throws javax.xml.stream.XMLStreamException;
    Code:
       0: lload         4
       2: lload_2
       3: lcmp
       4: ifle          14
       7: aload_0
       8: aload_1
       9: lload_2
      10: invokevirtual #243                // Method constructLimitViolation:(Ljava/lang/String;J)Ljavax/xml/stream/XMLStreamException;
      13: athrow
      14: return

  protected javax.xml.stream.XMLStreamException constructLimitViolation(java.lang.String, long) throws javax.xml.stream.XMLStreamException;
    Code:
       0: new           #91                 // class javax/xml/stream/XMLStreamException
       3: dup
       4: new           #72                 // class java/lang/StringBuilder
       7: dup
       8: invokespecial #73                 // Method java/lang/StringBuilder."<init>":()V
      11: aload_1
      12: invokevirtual #75                 // Method java/lang/StringBuilder.append:(Ljava/lang/String;)Ljava/lang/StringBuilder;
      15: ldc           #244                // String  limit (
      17: invokevirtual #75                 // Method java/lang/StringBuilder.append:(Ljava/lang/String;)Ljava/lang/StringBuilder;
      20: lload_2
      21: invokevirtual #245                // Method java/lang/StringBuilder.append:(J)Ljava/lang/StringBuilder;
      24: ldc           #246                // String ) exceeded
      26: invokevirtual #75                 // Method java/lang/StringBuilder.append:(Ljava/lang/String;)Ljava/lang/StringBuilder;
      29: invokevirtual #77                 // Method java/lang/StringBuilder.toString:()Ljava/lang/String;
      32: invokespecial #247                // Method javax/xml/stream/XMLStreamException."<init>":(Ljava/lang/String;)V
      35: areturn

  static {};
    Code:
       0: sipush        256
       3: newarray       byte
       5: putstatic     #248                // Field sCharValidity:[B
       8: getstatic     #248                // Field sCharValidity:[B
      11: bipush        95
      13: iconst_1
      14: bastore
      15: iconst_0
      16: istore_0
      17: bipush        25
      19: istore_1
      20: iload_0
      21: iload_1
      22: if_icmpgt     49
      25: getstatic     #248                // Field sCharValidity:[B
      28: bipush        65
      30: iload_0
      31: iadd
      32: iconst_1
      33: bastore
      34: getstatic     #248                // Field sCharValidity:[B
      37: bipush        97
      39: iload_0
      40: iadd
      41: iconst_1
      42: bastore
      43: iinc          0, 1
      46: goto          20
      49: sipush        192
      52: istore_0
      53: iload_0
      54: sipush        246
      57: if_icmpge     72
      60: getstatic     #248                // Field sCharValidity:[B
      63: iload_0
      64: iconst_1
      65: bastore
      66: iinc          0, 1
      69: goto          53
      72: getstatic     #248                // Field sCharValidity:[B
      75: sipush        215
      78: iconst_0
      79: bastore
      80: getstatic     #248                // Field sCharValidity:[B
      83: sipush        247
      86: iconst_0
      87: bastore
      88: getstatic     #248                // Field sCharValidity:[B
      91: bipush        45
      93: iconst_m1
      94: bastore
      95: getstatic     #248                // Field sCharValidity:[B
      98: bipush        46
     100: iconst_m1
     101: bastore
     102: getstatic     #248                // Field sCharValidity:[B
     105: sipush        183
     108: iconst_m1
     109: bastore
     110: bipush        48
     112: istore_0
     113: iload_0
     114: bipush        57
     116: if_icmpgt     131
     119: getstatic     #248                // Field sCharValidity:[B
     122: iload_0
     123: iconst_m1
     124: bastore
     125: iinc          0, 1
     128: goto          113
     131: sipush        128
     134: newarray       byte
     136: putstatic     #229                // Field sPubidValidity:[B
     139: iconst_0
     140: istore_0
     141: bipush        25
     143: istore_1
     144: iload_0
     145: iload_1
     146: if_icmpgt     173
     149: getstatic     #229                // Field sPubidValidity:[B
     152: bipush        65
     154: iload_0
     155: iadd
     156: iconst_1
     157: bastore
     158: getstatic     #229                // Field sPubidValidity:[B
     161: bipush        97
     163: iload_0
     164: iadd
     165: iconst_1
     166: bastore
     167: iinc          0, 1
     170: goto          144
     173: bipush        48
     175: istore_0
     176: iload_0
     177: bipush        57
     179: if_icmpgt     194
     182: getstatic     #229                // Field sPubidValidity:[B
     185: iload_0
     186: iconst_1
     187: bastore
     188: iinc          0, 1
     191: goto          176
     194: getstatic     #229                // Field sPubidValidity:[B
     197: bipush        10
     199: iconst_1
     200: bastore
     201: getstatic     #229                // Field sPubidValidity:[B
     204: bipush        13
     206: iconst_1
     207: bastore
     208: getstatic     #229                // Field sPubidValidity:[B
     211: bipush        32
     213: iconst_1
     214: bastore
     215: getstatic     #229                // Field sPubidValidity:[B
     218: bipush        45
     220: iconst_1
     221: bastore
     222: getstatic     #229                // Field sPubidValidity:[B
     225: bipush        39
     227: iconst_1
     228: bastore
     229: getstatic     #229                // Field sPubidValidity:[B
     232: bipush        40
     234: iconst_1
     235: bastore
     236: getstatic     #229                // Field sPubidValidity:[B
     239: bipush        41
     241: iconst_1
     242: bastore
     243: getstatic     #229                // Field sPubidValidity:[B
     246: bipush        43
     248: iconst_1
     249: bastore
     250: getstatic     #229                // Field sPubidValidity:[B
     253: bipush        44
     255: iconst_1
     256: bastore
     257: getstatic     #229                // Field sPubidValidity:[B
     260: bipush        46
     262: iconst_1
     263: bastore
     264: getstatic     #229                // Field sPubidValidity:[B
     267: bipush        47
     269: iconst_1
     270: bastore
     271: getstatic     #229                // Field sPubidValidity:[B
     274: bipush        58
     276: iconst_1
     277: bastore
     278: getstatic     #229                // Field sPubidValidity:[B
     281: bipush        61
     283: iconst_1
     284: bastore
     285: getstatic     #229                // Field sPubidValidity:[B
     288: bipush        63
     290: iconst_1
     291: bastore
     292: getstatic     #229                // Field sPubidValidity:[B
     295: bipush        59
     297: iconst_1
     298: bastore
     299: getstatic     #229                // Field sPubidValidity:[B
     302: bipush        33
     304: iconst_1
     305: bastore
     306: getstatic     #229                // Field sPubidValidity:[B
     309: bipush        42
     311: iconst_1
     312: bastore
     313: getstatic     #229                // Field sPubidValidity:[B
     316: bipush        35
     318: iconst_1
     319: bastore
     320: getstatic     #229                // Field sPubidValidity:[B
     323: bipush        64
     325: iconst_1
     326: bastore
     327: getstatic     #229                // Field sPubidValidity:[B
     330: bipush        36
     332: iconst_1
     333: bastore
     334: getstatic     #229                // Field sPubidValidity:[B
     337: bipush        95
     339: iconst_1
     340: bastore
     341: getstatic     #229                // Field sPubidValidity:[B
     344: bipush        37
     346: iconst_1
     347: bastore
     348: return
}
