Compiled from "$AutoValue_DefaultIndexSetCreated.java"
abstract class org.graylog2.indexer.indexset.$AutoValue_DefaultIndexSetCreated extends org.graylog2.indexer.indexset.DefaultIndexSetCreated {
  org.graylog2.indexer.indexset.$AutoValue_DefaultIndexSetCreated();
    Code:
       0: aload_0
       1: invokespecial #1                  // Method org/graylog2/indexer/indexset/DefaultIndexSetCreated."<init>":()V
       4: return

  public java.lang.String toString();
    Code:
       0: ldc           #2                  // String DefaultIndexSetCreated{}
       2: areturn

  public boolean equals(java.lang.Object);
    Code:
       0: aload_1
       1: aload_0
       2: if_acmpne     7
       5: iconst_1
       6: ireturn
       7: aload_1
       8: instanceof    #3                  // class org/graylog2/indexer/indexset/DefaultIndexSetCreated
      11: ifeq          16
      14: iconst_1
      15: ireturn
      16: iconst_0
      17: ireturn

  public int hashCode();
    Code:
       0: iconst_1
       1: istore_1
       2: iload_1
       3: ireturn
}
