Compiled from "DiscoveryOptionsResourceDefinition.java"
public class org.jboss.as.host.controller.discovery.DiscoveryOptionsResourceDefinition extends org.jboss.as.controller.SimpleResourceDefinition {
  public static org.jboss.as.host.controller.discovery.DiscoveryOptionsResourceDefinition INSTANCE;

  public static final org.jboss.as.controller.PrimitiveListAttributeDefinition DISCOVERY_OPTIONS;

  public static final org.jboss.as.controller.ObjectListAttributeDefinition OPTIONS;

  private org.jboss.as.host.controller.discovery.DiscoveryOptionsResourceDefinition();
    Code:
       0: aload_0
       1: ldc           #2                  // String core-service
       3: ldc           #3                  // String discovery-options
       5: invokestatic  #4                  // Method org/jboss/as/controller/PathElement.pathElement:(Ljava/lang/String;Ljava/lang/String;)Lorg/jboss/as/controller/PathElement;
       8: ldc           #3                  // String discovery-options
      10: invokestatic  #5                  // Method org/jboss/as/host/controller/descriptions/HostResolver.getResolver:(Ljava/lang/String;)Lorg/jboss/as/controller/descriptions/ResourceDescriptionResolver;
      13: invokespecial #6                  // Method org/jboss/as/controller/SimpleResourceDefinition."<init>":(Lorg/jboss/as/controller/PathElement;Lorg/jboss/as/controller/descriptions/ResourceDescriptionResolver;)V
      16: return

  public void registerAttributes(org.jboss.as.controller.registry.ManagementResourceRegistration);
    Code:
       0: aload_0
       1: aload_1
       2: invokespecial #7                  // Method org/jboss/as/controller/SimpleResourceDefinition.registerAttributes:(Lorg/jboss/as/controller/registry/ManagementResourceRegistration;)V
       5: aload_1
       6: getstatic     #8                  // Field DISCOVERY_OPTIONS:Lorg/jboss/as/controller/PrimitiveListAttributeDefinition;
       9: new           #9                  // class org/jboss/as/host/controller/operations/DiscoveryOptionsReadAttributeHandler
      12: dup
      13: invokespecial #10                 // Method org/jboss/as/host/controller/operations/DiscoveryOptionsReadAttributeHandler."<init>":()V
      16: invokeinterface #11,  3           // InterfaceMethod org/jboss/as/controller/registry/ManagementResourceRegistration.registerReadOnlyAttribute:(Lorg/jboss/as/controller/AttributeDefinition;Lorg/jboss/as/controller/OperationStepHandler;)V
      21: aload_1
      22: getstatic     #12                 // Field OPTIONS:Lorg/jboss/as/controller/ObjectListAttributeDefinition;
      25: aconst_null
      26: new           #13                 // class org/jboss/as/host/controller/operations/DiscoveryWriteAttributeHandler
      29: dup
      30: invokespecial #14                 // Method org/jboss/as/host/controller/operations/DiscoveryWriteAttributeHandler."<init>":()V
      33: invokeinterface #15,  4           // InterfaceMethod org/jboss/as/controller/registry/ManagementResourceRegistration.registerReadWriteAttribute:(Lorg/jboss/as/controller/AttributeDefinition;Lorg/jboss/as/controller/OperationStepHandler;Lorg/jboss/as/controller/OperationStepHandler;)V
      38: return

  static {};
    Code:
       0: new           #16                 // class org/jboss/as/host/controller/discovery/DiscoveryOptionsResourceDefinition
       3: dup
       4: invokespecial #17                 // Method "<init>":()V
       7: putstatic     #18                 // Field INSTANCE:Lorg/jboss/as/host/controller/discovery/DiscoveryOptionsResourceDefinition;
      10: new           #19                 // class org/jboss/as/controller/PrimitiveListAttributeDefinition$Builder
      13: dup
      14: ldc           #3                  // String discovery-options
      16: getstatic     #20                 // Field org/jboss/dmr/ModelType.PROPERTY:Lorg/jboss/dmr/ModelType;
      19: invokespecial #21                 // Method org/jboss/as/controller/PrimitiveListAttributeDefinition$Builder."<init>":(Ljava/lang/String;Lorg/jboss/dmr/ModelType;)V
      22: iconst_1
      23: invokevirtual #22                 // Method org/jboss/as/controller/PrimitiveListAttributeDefinition$Builder.setAllowNull:(Z)Lorg/jboss/as/controller/AbstractAttributeDefinitionBuilder;
      26: checkcast     #19                 // class org/jboss/as/controller/PrimitiveListAttributeDefinition$Builder
      29: new           #23                 // class org/jboss/as/controller/operations/validation/PropertyValidator
      32: dup
      33: iconst_0
      34: new           #24                 // class org/jboss/as/controller/operations/validation/StringLengthValidator
      37: dup
      38: iconst_1
      39: invokespecial #25                 // Method org/jboss/as/controller/operations/validation/StringLengthValidator."<init>":(I)V
      42: invokespecial #26                 // Method org/jboss/as/controller/operations/validation/PropertyValidator."<init>":(ZLorg/jboss/as/controller/operations/validation/ParameterValidator;)V
      45: invokevirtual #27                 // Method org/jboss/as/controller/PrimitiveListAttributeDefinition$Builder.setElementValidator:(Lorg/jboss/as/controller/operations/validation/ParameterValidator;)Lorg/jboss/as/controller/ListAttributeDefinition$Builder;
      48: checkcast     #19                 // class org/jboss/as/controller/PrimitiveListAttributeDefinition$Builder
      51: iconst_1
      52: invokestatic  #28                 // Method org/jboss/as/controller/ModelVersion.create:(I)Lorg/jboss/as/controller/ModelVersion;
      55: invokevirtual #29                 // Method org/jboss/as/controller/PrimitiveListAttributeDefinition$Builder.setDeprecated:(Lorg/jboss/as/controller/ModelVersion;)Lorg/jboss/as/controller/AbstractAttributeDefinitionBuilder;
      58: checkcast     #19                 // class org/jboss/as/controller/PrimitiveListAttributeDefinition$Builder
      61: invokevirtual #30                 // Method org/jboss/as/controller/PrimitiveListAttributeDefinition$Builder.build:()Lorg/jboss/as/controller/PrimitiveListAttributeDefinition;
      64: putstatic     #8                  // Field DISCOVERY_OPTIONS:Lorg/jboss/as/controller/PrimitiveListAttributeDefinition;
      67: new           #31                 // class org/jboss/as/controller/SimpleAttributeDefinitionBuilder
      70: dup
      71: ldc           #32                 // String name
      73: getstatic     #33                 // Field org/jboss/dmr/ModelType.STRING:Lorg/jboss/dmr/ModelType;
      76: invokespecial #34                 // Method org/jboss/as/controller/SimpleAttributeDefinitionBuilder."<init>":(Ljava/lang/String;Lorg/jboss/dmr/ModelType;)V
      79: iconst_0
      80: invokevirtual #35                 // Method org/jboss/as/controller/SimpleAttributeDefinitionBuilder.setAllowNull:(Z)Lorg/jboss/as/controller/AbstractAttributeDefinitionBuilder;
      83: checkcast     #31                 // class org/jboss/as/controller/SimpleAttributeDefinitionBuilder
      86: new           #24                 // class org/jboss/as/controller/operations/validation/StringLengthValidator
      89: dup
      90: iconst_1
      91: invokespecial #25                 // Method org/jboss/as/controller/operations/validation/StringLengthValidator."<init>":(I)V
      94: invokevirtual #36                 // Method org/jboss/as/controller/SimpleAttributeDefinitionBuilder.setValidator:(Lorg/jboss/as/controller/operations/validation/ParameterValidator;)Lorg/jboss/as/controller/AbstractAttributeDefinitionBuilder;
      97: checkcast     #31                 // class org/jboss/as/controller/SimpleAttributeDefinitionBuilder
     100: invokevirtual #37                 // Method org/jboss/as/controller/SimpleAttributeDefinitionBuilder.build:()Lorg/jboss/as/controller/SimpleAttributeDefinition;
     103: astore_0
     104: iconst_1
     105: getstatic     #38                 // Field org/jboss/as/host/controller/discovery/DiscoveryOptionResourceDefinition.DISCOVERY_ATTRIBUTES:[Lorg/jboss/as/controller/AttributeDefinition;
     108: arraylength
     109: iadd
     110: anewarray     #39                 // class org/jboss/as/controller/AttributeDefinition
     113: astore_1
     114: aload_1
     115: iconst_0
     116: aload_0
     117: aastore
     118: getstatic     #38                 // Field org/jboss/as/host/controller/discovery/DiscoveryOptionResourceDefinition.DISCOVERY_ATTRIBUTES:[Lorg/jboss/as/controller/AttributeDefinition;
     121: iconst_0
     122: aload_1
     123: iconst_1
     124: getstatic     #38                 // Field org/jboss/as/host/controller/discovery/DiscoveryOptionResourceDefinition.DISCOVERY_ATTRIBUTES:[Lorg/jboss/as/controller/AttributeDefinition;
     127: arraylength
     128: invokestatic  #40                 // Method java/lang/System.arraycopy:(Ljava/lang/Object;ILjava/lang/Object;II)V
     131: ldc           #41                 // String custom-discovery
     133: aload_1
     134: invokestatic  #42                 // Method org/jboss/as/controller/ObjectTypeAttributeDefinition$Builder.of:(Ljava/lang/String;[Lorg/jboss/as/controller/AttributeDefinition;)Lorg/jboss/as/controller/ObjectTypeAttributeDefinition$Builder;
     137: iconst_1
     138: anewarray     #43                 // class java/lang/String
     141: dup
     142: iconst_0
     143: ldc           #44                 // String static-discovery
     145: aastore
     146: invokevirtual #45                 // Method org/jboss/as/controller/ObjectTypeAttributeDefinition$Builder.addAlternatives:([Ljava/lang/String;)Lorg/jboss/as/controller/AbstractAttributeDefinitionBuilder;
     149: checkcast     #46                 // class org/jboss/as/controller/ObjectTypeAttributeDefinition$Builder
     152: invokevirtual #47                 // Method org/jboss/as/controller/ObjectTypeAttributeDefinition$Builder.build:()Lorg/jboss/as/controller/ObjectTypeAttributeDefinition;
     155: astore_2
     156: iconst_1
     157: getstatic     #48                 // Field org/jboss/as/host/controller/discovery/StaticDiscoveryResourceDefinition.STATIC_DISCOVERY_ATTRIBUTES:[Lorg/jboss/as/controller/SimpleAttributeDefinition;
     160: arraylength
     161: iadd
     162: anewarray     #39                 // class org/jboss/as/controller/AttributeDefinition
     165: astore_1
     166: aload_1
     167: iconst_0
     168: aload_0
     169: aastore
     170: getstatic     #48                 // Field org/jboss/as/host/controller/discovery/StaticDiscoveryResourceDefinition.STATIC_DISCOVERY_ATTRIBUTES:[Lorg/jboss/as/controller/SimpleAttributeDefinition;
     173: iconst_0
     174: aload_1
     175: iconst_1
     176: getstatic     #48                 // Field org/jboss/as/host/controller/discovery/StaticDiscoveryResourceDefinition.STATIC_DISCOVERY_ATTRIBUTES:[Lorg/jboss/as/controller/SimpleAttributeDefinition;
     179: arraylength
     180: invokestatic  #40                 // Method java/lang/System.arraycopy:(Ljava/lang/Object;ILjava/lang/Object;II)V
     183: ldc           #44                 // String static-discovery
     185: aload_1
     186: invokestatic  #42                 // Method org/jboss/as/controller/ObjectTypeAttributeDefinition$Builder.of:(Ljava/lang/String;[Lorg/jboss/as/controller/AttributeDefinition;)Lorg/jboss/as/controller/ObjectTypeAttributeDefinition$Builder;
     189: iconst_1
     190: anewarray     #43                 // class java/lang/String
     193: dup
     194: iconst_0
     195: ldc           #41                 // String custom-discovery
     197: aastore
     198: invokevirtual #45                 // Method org/jboss/as/controller/ObjectTypeAttributeDefinition$Builder.addAlternatives:([Ljava/lang/String;)Lorg/jboss/as/controller/AbstractAttributeDefinitionBuilder;
     201: checkcast     #46                 // class org/jboss/as/controller/ObjectTypeAttributeDefinition$Builder
     204: invokevirtual #47                 // Method org/jboss/as/controller/ObjectTypeAttributeDefinition$Builder.build:()Lorg/jboss/as/controller/ObjectTypeAttributeDefinition;
     207: astore_3
     208: ldc           #49                 // String list-item
     210: iconst_2
     211: anewarray     #39                 // class org/jboss/as/controller/AttributeDefinition
     214: dup
     215: iconst_0
     216: aload_2
     217: aastore
     218: dup
     219: iconst_1
     220: aload_3
     221: aastore
     222: invokestatic  #42                 // Method org/jboss/as/controller/ObjectTypeAttributeDefinition$Builder.of:(Ljava/lang/String;[Lorg/jboss/as/controller/AttributeDefinition;)Lorg/jboss/as/controller/ObjectTypeAttributeDefinition$Builder;
     225: invokevirtual #47                 // Method org/jboss/as/controller/ObjectTypeAttributeDefinition$Builder.build:()Lorg/jboss/as/controller/ObjectTypeAttributeDefinition;
     228: astore        4
     230: ldc           #50                 // String options
     232: aload         4
     234: invokestatic  #51                 // Method org/jboss/as/controller/ObjectListAttributeDefinition$Builder.of:(Ljava/lang/String;Lorg/jboss/as/controller/ObjectTypeAttributeDefinition;)Lorg/jboss/as/controller/ObjectListAttributeDefinition$Builder;
     237: getstatic     #52                 // Field org/jboss/dmr/ModelType.LIST:Lorg/jboss/dmr/ModelType;
     240: invokevirtual #53                 // Method org/jboss/as/controller/ObjectListAttributeDefinition$Builder.setType:(Lorg/jboss/dmr/ModelType;)Lorg/jboss/as/controller/AbstractAttributeDefinitionBuilder;
     243: checkcast     #54                 // class org/jboss/as/controller/ObjectListAttributeDefinition$Builder
     246: getstatic     #55                 // Field org/jboss/as/controller/registry/AttributeAccess$Flag.STORAGE_CONFIGURATION:Lorg/jboss/as/controller/registry/AttributeAccess$Flag;
     249: invokevirtual #56                 // Method org/jboss/as/controller/ObjectListAttributeDefinition$Builder.addFlag:(Lorg/jboss/as/controller/registry/AttributeAccess$Flag;)Lorg/jboss/as/controller/AbstractAttributeDefinitionBuilder;
     252: checkcast     #54                 // class org/jboss/as/controller/ObjectListAttributeDefinition$Builder
     255: iconst_1
     256: invokevirtual #57                 // Method org/jboss/as/controller/ObjectListAttributeDefinition$Builder.setAllowNull:(Z)Lorg/jboss/as/controller/ObjectListAttributeDefinition$Builder;
     259: new           #58                 // class org/jboss/dmr/ModelNode
     262: dup
     263: invokespecial #59                 // Method org/jboss/dmr/ModelNode."<init>":()V
     266: invokevirtual #60                 // Method org/jboss/dmr/ModelNode.setEmptyList:()Lorg/jboss/dmr/ModelNode;
     269: invokevirtual #61                 // Method org/jboss/as/controller/ObjectListAttributeDefinition$Builder.setDefaultValue:(Lorg/jboss/dmr/ModelNode;)Lorg/jboss/as/controller/AbstractAttributeDefinitionBuilder;
     272: checkcast     #54                 // class org/jboss/as/controller/ObjectListAttributeDefinition$Builder
     275: invokevirtual #62                 // Method org/jboss/as/controller/ObjectListAttributeDefinition$Builder.build:()Lorg/jboss/as/controller/ObjectListAttributeDefinition;
     278: putstatic     #12                 // Field OPTIONS:Lorg/jboss/as/controller/ObjectListAttributeDefinition;
     281: return
}
