Compiled from "DomainControllerData.java"
public class org.jboss.as.host.controller.discovery.DomainControllerData {
  protected java.lang.String host;

  protected int port;

  protected java.lang.String protocol;

  public org.jboss.as.host.controller.discovery.DomainControllerData();
    Code:
       0: aload_0
       1: invokespecial #1                  // Method java/lang/Object."<init>":()V
       4: return

  public org.jboss.as.host.controller.discovery.DomainControllerData(java.lang.String, java.lang.String, int);
    Code:
       0: aload_0
       1: invokespecial #1                  // Method java/lang/Object."<init>":()V
       4: aload_0
       5: aload_1
       6: putfield      #2                  // Field protocol:Ljava/lang/String;
       9: aload_0
      10: aload_2
      11: putfield      #3                  // Field host:Ljava/lang/String;
      14: aload_0
      15: iload_3
      16: putfield      #4                  // Field port:I
      19: return

  public java.lang.String getHost();
    Code:
       0: aload_0
       1: getfield      #3                  // Field host:Ljava/lang/String;
       4: areturn

  public int getPort();
    Code:
       0: aload_0
       1: getfield      #4                  // Field port:I
       4: ireturn

  public java.lang.String getProtocol();
    Code:
       0: aload_0
       1: getfield      #2                  // Field protocol:Ljava/lang/String;
       4: areturn

  public void writeTo(java.io.DataOutput) throws java.lang.Exception;
    Code:
       0: aload_0
       1: getfield      #3                  // Field host:Ljava/lang/String;
       4: aload_1
       5: invokestatic  #5                  // Method org/jboss/as/host/controller/discovery/S3Util.writeString:(Ljava/lang/String;Ljava/io/DataOutput;)V
       8: aload_1
       9: aload_0
      10: getfield      #4                  // Field port:I
      13: invokeinterface #6,  2            // InterfaceMethod java/io/DataOutput.writeInt:(I)V
      18: aload_0
      19: getfield      #2                  // Field protocol:Ljava/lang/String;
      22: aload_1
      23: invokestatic  #5                  // Method org/jboss/as/host/controller/discovery/S3Util.writeString:(Ljava/lang/String;Ljava/io/DataOutput;)V
      26: return

  public void readFrom(java.io.DataInput) throws java.lang.Exception;
    Code:
       0: aload_0
       1: aload_1
       2: invokestatic  #7                  // Method org/jboss/as/host/controller/discovery/S3Util.readString:(Ljava/io/DataInput;)Ljava/lang/String;
       5: putfield      #3                  // Field host:Ljava/lang/String;
       8: aload_0
       9: aload_1
      10: invokeinterface #8,  1            // InterfaceMethod java/io/DataInput.readInt:()I
      15: putfield      #4                  // Field port:I
      18: aload_0
      19: aload_1
      20: invokestatic  #7                  // Method org/jboss/as/host/controller/discovery/S3Util.readString:(Ljava/io/DataInput;)Ljava/lang/String;
      23: putfield      #2                  // Field protocol:Ljava/lang/String;
      26: return

  public java.lang.String toString();
    Code:
       0: new           #9                  // class java/lang/StringBuilder
       3: dup
       4: invokespecial #10                 // Method java/lang/StringBuilder."<init>":()V
       7: astore_1
       8: aload_1
       9: new           #9                  // class java/lang/StringBuilder
      12: dup
      13: invokespecial #10                 // Method java/lang/StringBuilder."<init>":()V
      16: ldc           #11                 // String master_host=
      18: invokevirtual #12                 // Method java/lang/StringBuilder.append:(Ljava/lang/String;)Ljava/lang/StringBuilder;
      21: aload_0
      22: invokevirtual #13                 // Method getHost:()Ljava/lang/String;
      25: invokevirtual #12                 // Method java/lang/StringBuilder.append:(Ljava/lang/String;)Ljava/lang/StringBuilder;
      28: invokevirtual #14                 // Method java/lang/StringBuilder.toString:()Ljava/lang/String;
      31: invokevirtual #12                 // Method java/lang/StringBuilder.append:(Ljava/lang/String;)Ljava/lang/StringBuilder;
      34: pop
      35: aload_1
      36: new           #9                  // class java/lang/StringBuilder
      39: dup
      40: invokespecial #10                 // Method java/lang/StringBuilder."<init>":()V
      43: ldc           #15                 // String ,master_port=
      45: invokevirtual #12                 // Method java/lang/StringBuilder.append:(Ljava/lang/String;)Ljava/lang/StringBuilder;
      48: aload_0
      49: invokevirtual #16                 // Method getPort:()I
      52: invokevirtual #17                 // Method java/lang/StringBuilder.append:(I)Ljava/lang/StringBuilder;
      55: invokevirtual #14                 // Method java/lang/StringBuilder.toString:()Ljava/lang/String;
      58: invokevirtual #12                 // Method java/lang/StringBuilder.append:(Ljava/lang/String;)Ljava/lang/StringBuilder;
      61: pop
      62: aload_1
      63: new           #9                  // class java/lang/StringBuilder
      66: dup
      67: invokespecial #10                 // Method java/lang/StringBuilder."<init>":()V
      70: ldc           #18                 // String ,master_protocol=
      72: invokevirtual #12                 // Method java/lang/StringBuilder.append:(Ljava/lang/String;)Ljava/lang/StringBuilder;
      75: aload_0
      76: invokevirtual #19                 // Method getProtocol:()Ljava/lang/String;
      79: invokevirtual #12                 // Method java/lang/StringBuilder.append:(Ljava/lang/String;)Ljava/lang/StringBuilder;
      82: invokevirtual #14                 // Method java/lang/StringBuilder.toString:()Ljava/lang/String;
      85: invokevirtual #12                 // Method java/lang/StringBuilder.append:(Ljava/lang/String;)Ljava/lang/StringBuilder;
      88: pop
      89: aload_1
      90: invokevirtual #14                 // Method java/lang/StringBuilder.toString:()Ljava/lang/String;
      93: areturn
}
