Compiled from "Shape.scala"
public final class akka.stream.AmorphousShape$$anonfun$deepCopy$2 extends scala.runtime.AbstractFunction1<akka.stream.Outlet<?>, akka.stream.Outlet<?>> implements scala.Serializable {
  public static final long serialVersionUID;

  public final akka.stream.Outlet<?> apply(akka.stream.Outlet<?>);
    Code:
       0: aload_1
       1: invokevirtual #25                 // Method akka/stream/Outlet.carbonCopy:()Lakka/stream/Outlet;
       4: areturn

  public final java.lang.Object apply(java.lang.Object);
    Code:
       0: aload_0
       1: aload_1
       2: checkcast     #21                 // class akka/stream/Outlet
       5: invokevirtual #32                 // Method apply:(Lakka/stream/Outlet;)Lakka/stream/Outlet;
       8: areturn

  public akka.stream.AmorphousShape$$anonfun$deepCopy$2(akka.stream.AmorphousShape);
    Code:
       0: aload_0
       1: invokespecial #39                 // Method scala/runtime/AbstractFunction1."<init>":()V
       4: return
}
