Compiled from "FanOutShape.scala"
public class akka.stream.FanOutShape$Name$ implements scala.Serializable {
  public static final akka.stream.FanOutShape$Name$ MODULE$;

  public static {};
    Code:
       0: new           #2                  // class akka/stream/FanOutShape$Name$
       3: invokespecial #14                 // Method "<init>":()V
       6: return

  public final java.lang.String toString();
    Code:
       0: ldc           #18                 // String Name
       2: areturn

  public <I> akka.stream.FanOutShape$Name<I> apply(java.lang.String);
    Code:
       0: new           #23                 // class akka/stream/FanOutShape$Name
       3: dup
       4: aload_1
       5: invokespecial #26                 // Method akka/stream/FanOutShape$Name."<init>":(Ljava/lang/String;)V
       8: areturn

  public <I> scala.Option<java.lang.String> unapply(akka.stream.FanOutShape$Name<I>);
    Code:
       0: aload_1
       1: ifnonnull     10
       4: getstatic     #35                 // Field scala/None$.MODULE$:Lscala/None$;
       7: goto          21
      10: new           #37                 // class scala/Some
      13: dup
      14: aload_1
      15: invokevirtual #39                 // Method akka/stream/FanOutShape$Name.name:()Ljava/lang/String;
      18: invokespecial #42                 // Method scala/Some."<init>":(Ljava/lang/Object;)V
      21: areturn

  private java.lang.Object readResolve();
    Code:
       0: getstatic     #50                 // Field MODULE$:Lakka/stream/FanOutShape$Name$;
       3: areturn

  public akka.stream.FanOutShape$Name$();
    Code:
       0: aload_0
       1: invokespecial #51                 // Method java/lang/Object."<init>":()V
       4: aload_0
       5: putstatic     #50                 // Field MODULE$:Lakka/stream/FanOutShape$Name$;
       8: return
}
