Compiled from "Fusing.scala"
public final class akka.stream.Fusing$ {
  public static final akka.stream.Fusing$ MODULE$;

  public static {};
    Code:
       0: new           #2                  // class akka/stream/Fusing$
       3: invokespecial #12                 // Method "<init>":()V
       6: return

  public <S extends akka.stream.Shape, M> akka.stream.Fusing$FusedGraph<S, M> aggressive(akka.stream.Graph<S, M>);
    Code:
       0: getstatic     #19                 // Field akka/stream/impl/fusing/Fusing$.MODULE$:Lakka/stream/impl/fusing/Fusing$;
       3: aload_1
       4: invokevirtual #21                 // Method akka/stream/impl/fusing/Fusing$.aggressive:(Lakka/stream/Graph;)Lakka/stream/Fusing$FusedGraph;
       7: areturn

  private akka.stream.Fusing$();
    Code:
       0: aload_0
       1: invokespecial #25                 // Method java/lang/Object."<init>":()V
       4: aload_0
       5: putstatic     #27                 // Field MODULE$:Lakka/stream/Fusing$;
       8: return
}
