Compiled from "SslTlsOptions.scala"
public abstract class akka.stream.IgnoreComplete extends akka.stream.TLSClosing {
  public static boolean canEqual(java.lang.Object);
    Code:
       0: getstatic     #16                 // Field akka/stream/IgnoreComplete$.MODULE$:Lakka/stream/IgnoreComplete$;
       3: aload_0
       4: invokevirtual #18                 // Method akka/stream/IgnoreComplete$.canEqual:(Ljava/lang/Object;)Z
       7: ireturn

  public static scala.collection.Iterator<java.lang.Object> productIterator();
    Code:
       0: getstatic     #16                 // Field akka/stream/IgnoreComplete$.MODULE$:Lakka/stream/IgnoreComplete$;
       3: invokevirtual #22                 // Method akka/stream/IgnoreComplete$.productIterator:()Lscala/collection/Iterator;
       6: areturn

  public static java.lang.Object productElement(int);
    Code:
       0: getstatic     #16                 // Field akka/stream/IgnoreComplete$.MODULE$:Lakka/stream/IgnoreComplete$;
       3: iload_0
       4: invokevirtual #26                 // Method akka/stream/IgnoreComplete$.productElement:(I)Ljava/lang/Object;
       7: areturn

  public static int productArity();
    Code:
       0: getstatic     #16                 // Field akka/stream/IgnoreComplete$.MODULE$:Lakka/stream/IgnoreComplete$;
       3: invokevirtual #30                 // Method akka/stream/IgnoreComplete$.productArity:()I
       6: ireturn

  public static java.lang.String productPrefix();
    Code:
       0: getstatic     #16                 // Field akka/stream/IgnoreComplete$.MODULE$:Lakka/stream/IgnoreComplete$;
       3: invokevirtual #34                 // Method akka/stream/IgnoreComplete$.productPrefix:()Ljava/lang/String;
       6: areturn

  public boolean ignoreCancel();
    Code:
       0: iconst_0
       1: ireturn

  public boolean ignoreComplete();
    Code:
       0: iconst_1
       1: ireturn

  public akka.stream.IgnoreComplete();
    Code:
       0: aload_0
       1: invokespecial #43                 // Method akka/stream/TLSClosing."<init>":()V
       4: return
}
