Compiled from "Shape.scala"
public abstract class akka.stream.InPort {
  private int id;

  public final int hashCode();
    Code:
       0: aload_0
       1: invokespecial #14                 // Method java/lang/Object.hashCode:()I
       4: ireturn

  public final boolean equals(java.lang.Object);
    Code:
       0: aload_0
       1: aload_1
       2: if_acmpne     9
       5: iconst_1
       6: goto          10
       9: iconst_0
      10: ireturn

  public int id();
    Code:
       0: aload_0
       1: getfield      #22                 // Field id:I
       4: ireturn

  public void id_$eq(int);
    Code:
       0: aload_0
       1: iload_1
       2: putfield      #22                 // Field id:I
       5: return

  public akka.stream.Inlet<?> inlet();
    Code:
       0: aload_0
       1: checkcast     #29                 // class akka/stream/Inlet
       4: areturn

  public akka.stream.InPort();
    Code:
       0: aload_0
       1: invokespecial #33                 // Method java/lang/Object."<init>":()V
       4: aload_0
       5: iconst_m1
       6: putfield      #22                 // Field id:I
       9: return
}
