Compiled from "OverflowStrategy.scala"
public abstract class akka.stream.OverflowStrategy extends akka.stream.DelayOverflowStrategy {
  public static akka.stream.OverflowStrategy fail();
    Code:
       0: getstatic     #16                 // Field akka/stream/OverflowStrategy$.MODULE$:Lakka/stream/OverflowStrategy$;
       3: invokevirtual #18                 // Method akka/stream/OverflowStrategy$.fail:()Lakka/stream/OverflowStrategy;
       6: areturn

  public static akka.stream.OverflowStrategy backpressure();
    Code:
       0: getstatic     #16                 // Field akka/stream/OverflowStrategy$.MODULE$:Lakka/stream/OverflowStrategy$;
       3: invokevirtual #21                 // Method akka/stream/OverflowStrategy$.backpressure:()Lakka/stream/OverflowStrategy;
       6: areturn

  public static akka.stream.OverflowStrategy dropNew();
    Code:
       0: getstatic     #16                 // Field akka/stream/OverflowStrategy$.MODULE$:Lakka/stream/OverflowStrategy$;
       3: invokevirtual #24                 // Method akka/stream/OverflowStrategy$.dropNew:()Lakka/stream/OverflowStrategy;
       6: areturn

  public static akka.stream.OverflowStrategy dropBuffer();
    Code:
       0: getstatic     #16                 // Field akka/stream/OverflowStrategy$.MODULE$:Lakka/stream/OverflowStrategy$;
       3: invokevirtual #27                 // Method akka/stream/OverflowStrategy$.dropBuffer:()Lakka/stream/OverflowStrategy;
       6: areturn

  public static akka.stream.OverflowStrategy dropTail();
    Code:
       0: getstatic     #16                 // Field akka/stream/OverflowStrategy$.MODULE$:Lakka/stream/OverflowStrategy$;
       3: invokevirtual #30                 // Method akka/stream/OverflowStrategy$.dropTail:()Lakka/stream/OverflowStrategy;
       6: areturn

  public static akka.stream.OverflowStrategy dropHead();
    Code:
       0: getstatic     #16                 // Field akka/stream/OverflowStrategy$.MODULE$:Lakka/stream/OverflowStrategy$;
       3: invokevirtual #33                 // Method akka/stream/OverflowStrategy$.dropHead:()Lakka/stream/OverflowStrategy;
       6: areturn

  public akka.stream.OverflowStrategy();
    Code:
       0: aload_0
       1: invokespecial #37                 // Method akka/stream/DelayOverflowStrategy."<init>":()V
       4: return
}
