Compiled from "KillSwitch.scala"
public final class akka.stream.SharedKillSwitch implements akka.stream.KillSwitch {
  private final java.lang.String name;

  public final scala.concurrent.Promise<akka.Done> akka$stream$SharedKillSwitch$$shutdownPromise;

  private final akka.stream.Graph<akka.stream.FlowShape<java.lang.Object, java.lang.Object>, akka.stream.SharedKillSwitch> _flow;

  public java.lang.String name();
    Code:
       0: aload_0
       1: getfield      #21                 // Field name:Ljava/lang/String;
       4: areturn

  public void shutdown();
    Code:
       0: aload_0
       1: getfield      #27                 // Field akka$stream$SharedKillSwitch$$shutdownPromise:Lscala/concurrent/Promise;
       4: getstatic     #33                 // Field akka/Done$.MODULE$:Lakka/Done$;
       7: invokeinterface #39,  2           // InterfaceMethod scala/concurrent/Promise.trySuccess:(Ljava/lang/Object;)Z
      12: pop
      13: return

  public void abort(java.lang.Throwable);
    Code:
       0: aload_0
       1: getfield      #27                 // Field akka$stream$SharedKillSwitch$$shutdownPromise:Lscala/concurrent/Promise;
       4: aload_1
       5: invokeinterface #45,  2           // InterfaceMethod scala/concurrent/Promise.tryFailure:(Ljava/lang/Throwable;)Z
      10: pop
      11: return

  public <T> akka.stream.Graph<akka.stream.FlowShape<T, T>, akka.stream.SharedKillSwitch> flow();
    Code:
       0: aload_0
       1: getfield      #51                 // Field _flow:Lakka/stream/Graph;
       4: areturn

  public java.lang.String toString();
    Code:
       0: new           #54                 // class scala/StringContext
       3: dup
       4: getstatic     #59                 // Field scala/Predef$.MODULE$:Lscala/Predef$;
       7: iconst_2
       8: anewarray     #61                 // class java/lang/String
      11: dup
      12: iconst_0
      13: ldc           #63                 // String KillSwitch(
      15: aastore
      16: dup
      17: iconst_1
      18: ldc           #65                 // String )
      20: aastore
      21: checkcast     #67                 // class "[Ljava/lang/Object;"
      24: invokevirtual #71                 // Method scala/Predef$.wrapRefArray:([Ljava/lang/Object;)Lscala/collection/mutable/WrappedArray;
      27: invokespecial #75                 // Method scala/StringContext."<init>":(Lscala/collection/Seq;)V
      30: getstatic     #59                 // Field scala/Predef$.MODULE$:Lscala/Predef$;
      33: iconst_1
      34: anewarray     #4                  // class java/lang/Object
      37: dup
      38: iconst_0
      39: aload_0
      40: invokevirtual #77                 // Method name:()Ljava/lang/String;
      43: aastore
      44: invokevirtual #81                 // Method scala/Predef$.genericWrapArray:(Ljava/lang/Object;)Lscala/collection/mutable/WrappedArray;
      47: invokevirtual #85                 // Method scala/StringContext.s:(Lscala/collection/Seq;)Ljava/lang/String;
      50: areturn

  public akka.stream.SharedKillSwitch(java.lang.String);
    Code:
       0: aload_0
       1: aload_1
       2: putfield      #21                 // Field name:Ljava/lang/String;
       5: aload_0
       6: invokespecial #88                 // Method java/lang/Object."<init>":()V
       9: aload_0
      10: getstatic     #93                 // Field scala/concurrent/Promise$.MODULE$:Lscala/concurrent/Promise$;
      13: invokevirtual #97                 // Method scala/concurrent/Promise$.apply:()Lscala/concurrent/Promise;
      16: putfield      #27                 // Field akka$stream$SharedKillSwitch$$shutdownPromise:Lscala/concurrent/Promise;
      19: aload_0
      20: new           #99                 // class akka/stream/SharedKillSwitch$SharedKillSwitchFlow
      23: dup
      24: aload_0
      25: invokespecial #102                // Method akka/stream/SharedKillSwitch$SharedKillSwitchFlow."<init>":(Lakka/stream/SharedKillSwitch;)V
      28: putfield      #51                 // Field _flow:Lakka/stream/Graph;
      31: return
}
