Compiled from "ActorMaterializer.scala"
public final class akka.stream.StreamSubscriptionTimeoutTerminationMode$ {
  public static final akka.stream.StreamSubscriptionTimeoutTerminationMode$ MODULE$;

  public static {};
    Code:
       0: new           #2                  // class akka/stream/StreamSubscriptionTimeoutTerminationMode$
       3: invokespecial #12                 // Method "<init>":()V
       6: return

  public akka.stream.StreamSubscriptionTimeoutTerminationMode noop();
    Code:
       0: getstatic     #19                 // Field akka/stream/StreamSubscriptionTimeoutTerminationMode$NoopTermination$.MODULE$:Lakka/stream/StreamSubscriptionTimeoutTerminationMode$NoopTermination$;
       3: areturn

  public akka.stream.StreamSubscriptionTimeoutTerminationMode warn();
    Code:
       0: getstatic     #26                 // Field akka/stream/StreamSubscriptionTimeoutTerminationMode$WarnTermination$.MODULE$:Lakka/stream/StreamSubscriptionTimeoutTerminationMode$WarnTermination$;
       3: areturn

  public akka.stream.StreamSubscriptionTimeoutTerminationMode cancel();
    Code:
       0: getstatic     #32                 // Field akka/stream/StreamSubscriptionTimeoutTerminationMode$CancelTermination$.MODULE$:Lakka/stream/StreamSubscriptionTimeoutTerminationMode$CancelTermination$;
       3: areturn

  private akka.stream.StreamSubscriptionTimeoutTerminationMode$();
    Code:
       0: aload_0
       1: invokespecial #33                 // Method java/lang/Object."<init>":()V
       4: aload_0
       5: putstatic     #35                 // Field MODULE$:Lakka/stream/StreamSubscriptionTimeoutTerminationMode$;
       8: return
}
