Compiled from "ThrottleMode.scala"
public abstract class akka.stream.ThrottleMode {
  public static akka.stream.ThrottleMode$Enforcing$ enforcing();
    Code:
       0: getstatic     #16                 // Field akka/stream/ThrottleMode$.MODULE$:Lakka/stream/ThrottleMode$;
       3: invokevirtual #18                 // Method akka/stream/ThrottleMode$.enforcing:()Lakka/stream/ThrottleMode$Enforcing$;
       6: areturn

  public static akka.stream.ThrottleMode$Shaping$ shaping();
    Code:
       0: getstatic     #16                 // Field akka/stream/ThrottleMode$.MODULE$:Lakka/stream/ThrottleMode$;
       3: invokevirtual #22                 // Method akka/stream/ThrottleMode$.shaping:()Lakka/stream/ThrottleMode$Shaping$;
       6: areturn

  public akka.stream.ThrottleMode();
    Code:
       0: aload_0
       1: invokespecial #26                 // Method java/lang/Object."<init>":()V
       4: return
}
