Compiled from "Base64EncodingOutputStream.java"
public class org.apache.axiom.util.base64.Base64EncodingOutputStream extends org.apache.axiom.util.base64.AbstractBase64EncodingOutputStream {
  private final java.io.OutputStream parent;

  private final byte[] buffer;

  private int len;

  public org.apache.axiom.util.base64.Base64EncodingOutputStream(java.io.OutputStream, int);
    Code:
       0: aload_0
       1: invokespecial #1                  // Method org/apache/axiom/util/base64/AbstractBase64EncodingOutputStream."<init>":()V
       4: aload_0
       5: aload_1
       6: putfield      #2                  // Field parent:Ljava/io/OutputStream;
       9: aload_0
      10: iload_2
      11: newarray       byte
      13: putfield      #3                  // Field buffer:[B
      16: return

  public org.apache.axiom.util.base64.Base64EncodingOutputStream(java.io.OutputStream);
    Code:
       0: aload_0
       1: aload_1
       2: sipush        4096
       5: invokespecial #4                  // Method "<init>":(Ljava/io/OutputStream;I)V
       8: return

  protected void doWrite(byte[]) throws java.io.IOException;
    Code:
       0: aload_0
       1: getfield      #3                  // Field buffer:[B
       4: arraylength
       5: aload_0
       6: getfield      #5                  // Field len:I
       9: isub
      10: iconst_4
      11: if_icmpge     18
      14: aload_0
      15: invokevirtual #6                  // Method flushBuffer:()V
      18: aload_1
      19: iconst_0
      20: aload_0
      21: getfield      #3                  // Field buffer:[B
      24: aload_0
      25: getfield      #5                  // Field len:I
      28: iconst_4
      29: invokestatic  #7                  // Method java/lang/System.arraycopy:(Ljava/lang/Object;ILjava/lang/Object;II)V
      32: aload_0
      33: dup
      34: getfield      #5                  // Field len:I
      37: iconst_4
      38: iadd
      39: putfield      #5                  // Field len:I
      42: return

  protected void flushBuffer() throws java.io.IOException;
    Code:
       0: aload_0
       1: getfield      #2                  // Field parent:Ljava/io/OutputStream;
       4: aload_0
       5: getfield      #3                  // Field buffer:[B
       8: iconst_0
       9: aload_0
      10: getfield      #5                  // Field len:I
      13: invokevirtual #8                  // Method java/io/OutputStream.write:([BII)V
      16: aload_0
      17: iconst_0
      18: putfield      #5                  // Field len:I
      21: return

  protected void doFlush() throws java.io.IOException;
    Code:
       0: aload_0
       1: getfield      #2                  // Field parent:Ljava/io/OutputStream;
       4: invokevirtual #9                  // Method java/io/OutputStream.flush:()V
       7: return

  protected void doClose() throws java.io.IOException;
    Code:
       0: aload_0
       1: getfield      #2                  // Field parent:Ljava/io/OutputStream;
       4: invokevirtual #10                 // Method java/io/OutputStream.close:()V
       7: return
}
