Compiled from "MessageSourceResourceBundle.java"
public class org.springframework.context.support.MessageSourceResourceBundle extends java.util.ResourceBundle {
  private final org.springframework.context.MessageSource messageSource;

  private final java.util.Locale locale;

  public org.springframework.context.support.MessageSourceResourceBundle(org.springframework.context.MessageSource, java.util.Locale);
    Code:
       0: aload_0
       1: invokespecial #1                  // Method java/util/ResourceBundle."<init>":()V
       4: aload_1
       5: ldc           #2                  // String MessageSource must not be null
       7: invokestatic  #3                  // Method org/springframework/util/Assert.notNull:(Ljava/lang/Object;Ljava/lang/String;)V
      10: aload_0
      11: aload_1
      12: putfield      #4                  // Field messageSource:Lorg/springframework/context/MessageSource;
      15: aload_0
      16: aload_2
      17: putfield      #5                  // Field locale:Ljava/util/Locale;
      20: return

  public org.springframework.context.support.MessageSourceResourceBundle(org.springframework.context.MessageSource, java.util.Locale, java.util.ResourceBundle);
    Code:
       0: aload_0
       1: aload_1
       2: aload_2
       3: invokespecial #6                  // Method "<init>":(Lorg/springframework/context/MessageSource;Ljava/util/Locale;)V
       6: aload_0
       7: aload_3
       8: invokevirtual #7                  // Method setParent:(Ljava/util/ResourceBundle;)V
      11: return

  protected java.lang.Object handleGetObject(java.lang.String);
    Code:
       0: aload_0
       1: getfield      #4                  // Field messageSource:Lorg/springframework/context/MessageSource;
       4: aload_1
       5: aconst_null
       6: aload_0
       7: getfield      #5                  // Field locale:Ljava/util/Locale;
      10: invokeinterface #8,  4            // InterfaceMethod org/springframework/context/MessageSource.getMessage:(Ljava/lang/String;[Ljava/lang/Object;Ljava/util/Locale;)Ljava/lang/String;
      15: areturn
      16: astore_2
      17: aconst_null
      18: areturn
    Exception table:
       from    to  target type
           0    15    16   Class org/springframework/context/NoSuchMessageException

  public boolean containsKey(java.lang.String);
    Code:
       0: aload_0
       1: getfield      #4                  // Field messageSource:Lorg/springframework/context/MessageSource;
       4: aload_1
       5: aconst_null
       6: aload_0
       7: getfield      #5                  // Field locale:Ljava/util/Locale;
      10: invokeinterface #8,  4            // InterfaceMethod org/springframework/context/MessageSource.getMessage:(Ljava/lang/String;[Ljava/lang/Object;Ljava/util/Locale;)Ljava/lang/String;
      15: pop
      16: iconst_1
      17: ireturn
      18: astore_2
      19: iconst_0
      20: ireturn
    Exception table:
       from    to  target type
           0    17    18   Class org/springframework/context/NoSuchMessageException

  public java.util.Enumeration<java.lang.String> getKeys();
    Code:
       0: new           #10                 // class java/lang/UnsupportedOperationException
       3: dup
       4: ldc           #11                 // String MessageSourceResourceBundle does not support enumerating its keys
       6: invokespecial #12                 // Method java/lang/UnsupportedOperationException."<init>":(Ljava/lang/String;)V
       9: athrow

  public java.util.Locale getLocale();
    Code:
       0: aload_0
       1: getfield      #5                  // Field locale:Ljava/util/Locale;
       4: areturn
}
