Compiled from "KeyAffinityServiceFactory.java"
public class org.infinispan.affinity.KeyAffinityServiceFactory {
  public org.infinispan.affinity.KeyAffinityServiceFactory();
    Code:
       0: aload_0
       1: invokespecial #1                  // Method java/lang/Object."<init>":()V
       4: return

  public static <K, V> org.infinispan.affinity.KeyAffinityService<K> newKeyAffinityService(org.infinispan.Cache<K, V>, java.util.concurrent.Executor, org.infinispan.affinity.KeyGenerator<K>, int, boolean);
    Code:
       0: new           #2                  // class org/infinispan/affinity/impl/KeyAffinityServiceImpl
       3: dup
       4: aload_1
       5: aload_0
       6: aload_2
       7: iload_3
       8: aconst_null
       9: iload         4
      11: invokespecial #3                  // Method org/infinispan/affinity/impl/KeyAffinityServiceImpl."<init>":(Ljava/util/concurrent/Executor;Lorg/infinispan/Cache;Lorg/infinispan/affinity/KeyGenerator;ILjava/util/Collection;Z)V
      14: areturn

  public static <K, V> org.infinispan.affinity.KeyAffinityService<K> newKeyAffinityService(org.infinispan.Cache<K, V>, java.util.concurrent.Executor, org.infinispan.affinity.KeyGenerator<K>, int);
    Code:
       0: aload_0
       1: aload_1
       2: aload_2
       3: iload_3
       4: iconst_1
       5: invokestatic  #4                  // Method newKeyAffinityService:(Lorg/infinispan/Cache;Ljava/util/concurrent/Executor;Lorg/infinispan/affinity/KeyGenerator;IZ)Lorg/infinispan/affinity/KeyAffinityService;
       8: areturn

  public static <K, V> org.infinispan.affinity.KeyAffinityService<K> newKeyAffinityService(org.infinispan.Cache<K, V>, java.util.Collection<org.infinispan.remoting.transport.Address>, org.infinispan.affinity.KeyGenerator<K>, java.util.concurrent.Executor, int, boolean);
    Code:
       0: new           #2                  // class org/infinispan/affinity/impl/KeyAffinityServiceImpl
       3: dup
       4: aload_3
       5: aload_0
       6: aload_2
       7: iload         4
       9: aload_1
      10: iload         5
      12: invokespecial #3                  // Method org/infinispan/affinity/impl/KeyAffinityServiceImpl."<init>":(Ljava/util/concurrent/Executor;Lorg/infinispan/Cache;Lorg/infinispan/affinity/KeyGenerator;ILjava/util/Collection;Z)V
      15: areturn

  public static <K, V> org.infinispan.affinity.KeyAffinityService<K> newKeyAffinityService(org.infinispan.Cache<K, V>, java.util.Collection<org.infinispan.remoting.transport.Address>, org.infinispan.affinity.KeyGenerator<K>, java.util.concurrent.Executor, int);
    Code:
       0: aload_0
       1: aload_1
       2: aload_2
       3: aload_3
       4: iload         4
       6: iconst_1
       7: invokestatic  #5                  // Method newKeyAffinityService:(Lorg/infinispan/Cache;Ljava/util/Collection;Lorg/infinispan/affinity/KeyGenerator;Ljava/util/concurrent/Executor;IZ)Lorg/infinispan/affinity/KeyAffinityService;
      10: areturn

  public static <K, V> org.infinispan.affinity.KeyAffinityService<K> newLocalKeyAffinityService(org.infinispan.Cache<K, V>, org.infinispan.affinity.KeyGenerator<K>, java.util.concurrent.Executor, int, boolean);
    Code:
       0: aload_0
       1: invokeinterface #6,  1            // InterfaceMethod org/infinispan/Cache.getAdvancedCache:()Lorg/infinispan/AdvancedCache;
       6: invokeinterface #7,  1            // InterfaceMethod org/infinispan/AdvancedCache.getRpcManager:()Lorg/infinispan/remoting/rpc/RpcManager;
      11: invokeinterface #8,  1            // InterfaceMethod org/infinispan/remoting/rpc/RpcManager.getTransport:()Lorg/infinispan/remoting/transport/Transport;
      16: invokeinterface #9,  1            // InterfaceMethod org/infinispan/remoting/transport/Transport.getAddress:()Lorg/infinispan/remoting/transport/Address;
      21: astore        5
      23: aload         5
      25: invokestatic  #10                 // Method java/util/Collections.singletonList:(Ljava/lang/Object;)Ljava/util/List;
      28: astore        6
      30: aload_0
      31: aload         6
      33: aload_1
      34: aload_2
      35: iload_3
      36: iload         4
      38: invokestatic  #5                  // Method newKeyAffinityService:(Lorg/infinispan/Cache;Ljava/util/Collection;Lorg/infinispan/affinity/KeyGenerator;Ljava/util/concurrent/Executor;IZ)Lorg/infinispan/affinity/KeyAffinityService;
      41: areturn

  public static <K, V> org.infinispan.affinity.KeyAffinityService<K> newLocalKeyAffinityService(org.infinispan.Cache<K, V>, org.infinispan.affinity.KeyGenerator<K>, java.util.concurrent.Executor, int);
    Code:
       0: aload_0
       1: aload_1
       2: aload_2
       3: iload_3
       4: iconst_1
       5: invokestatic  #11                 // Method newLocalKeyAffinityService:(Lorg/infinispan/Cache;Lorg/infinispan/affinity/KeyGenerator;Ljava/util/concurrent/Executor;IZ)Lorg/infinispan/affinity/KeyAffinityService;
       8: areturn
}
