Compiled from "PackageType.java"
public final class org.apache.pulsar.packages.management.core.common.PackageType extends java.lang.Enum<org.apache.pulsar.packages.management.core.common.PackageType> {
  public static final org.apache.pulsar.packages.management.core.common.PackageType FUNCTION;

  public static final org.apache.pulsar.packages.management.core.common.PackageType SINK;

  public static final org.apache.pulsar.packages.management.core.common.PackageType SOURCE;

  private final java.lang.String value;

  private static final org.apache.pulsar.packages.management.core.common.PackageType[] $VALUES;

  public static org.apache.pulsar.packages.management.core.common.PackageType[] values();
    Code:
       0: getstatic     #1                  // Field $VALUES:[Lorg/apache/pulsar/packages/management/core/common/PackageType;
       3: invokevirtual #2                  // Method "[Lorg/apache/pulsar/packages/management/core/common/PackageType;".clone:()Ljava/lang/Object;
       6: checkcast     #3                  // class "[Lorg/apache/pulsar/packages/management/core/common/PackageType;"
       9: areturn

  public static org.apache.pulsar.packages.management.core.common.PackageType valueOf(java.lang.String);
    Code:
       0: ldc           #4                  // class org/apache/pulsar/packages/management/core/common/PackageType
       2: aload_0
       3: invokestatic  #5                  // Method java/lang/Enum.valueOf:(Ljava/lang/Class;Ljava/lang/String;)Ljava/lang/Enum;
       6: checkcast     #4                  // class org/apache/pulsar/packages/management/core/common/PackageType
       9: areturn

  private org.apache.pulsar.packages.management.core.common.PackageType(java.lang.String);
    Code:
       0: aload_0
       1: aload_1
       2: iload_2
       3: invokespecial #6                  // Method java/lang/Enum."<init>":(Ljava/lang/String;I)V
       6: aload_0
       7: aload_3
       8: putfield      #7                  // Field value:Ljava/lang/String;
      11: return

  public java.lang.String value();
    Code:
       0: aload_0
       1: getfield      #7                  // Field value:Ljava/lang/String;
       4: areturn

  public static org.apache.pulsar.packages.management.core.common.PackageType getEnum(java.lang.String);
    Code:
       0: invokestatic  #8                  // Method values:()[Lorg/apache/pulsar/packages/management/core/common/PackageType;
       3: astore_1
       4: aload_1
       5: arraylength
       6: istore_2
       7: iconst_0
       8: istore_3
       9: iload_3
      10: iload_2
      11: if_icmpge     40
      14: aload_1
      15: iload_3
      16: aaload
      17: astore        4
      19: aload         4
      21: getfield      #7                  // Field value:Ljava/lang/String;
      24: aload_0
      25: invokevirtual #9                  // Method java/lang/String.equalsIgnoreCase:(Ljava/lang/String;)Z
      28: ifeq          34
      31: aload         4
      33: areturn
      34: iinc          3, 1
      37: goto          9
      40: new           #10                 // class java/lang/IllegalArgumentException
      43: dup
      44: new           #11                 // class java/lang/StringBuilder
      47: dup
      48: invokespecial #12                 // Method java/lang/StringBuilder."<init>":()V
      51: ldc           #13                 // String Invalid package domain: \'
      53: invokevirtual #14                 // Method java/lang/StringBuilder.append:(Ljava/lang/String;)Ljava/lang/StringBuilder;
      56: aload_0
      57: invokevirtual #14                 // Method java/lang/StringBuilder.append:(Ljava/lang/String;)Ljava/lang/StringBuilder;
      60: ldc           #15                 // String \'
      62: invokevirtual #14                 // Method java/lang/StringBuilder.append:(Ljava/lang/String;)Ljava/lang/StringBuilder;
      65: invokevirtual #16                 // Method java/lang/StringBuilder.toString:()Ljava/lang/String;
      68: invokespecial #17                 // Method java/lang/IllegalArgumentException."<init>":(Ljava/lang/String;)V
      71: athrow

  public java.lang.String toString();
    Code:
       0: aload_0
       1: getfield      #7                  // Field value:Ljava/lang/String;
       4: areturn

  static {};
    Code:
       0: new           #4                  // class org/apache/pulsar/packages/management/core/common/PackageType
       3: dup
       4: ldc           #18                 // String FUNCTION
       6: iconst_0
       7: ldc           #19                 // String function
       9: invokespecial #20                 // Method "<init>":(Ljava/lang/String;ILjava/lang/String;)V
      12: putstatic     #21                 // Field FUNCTION:Lorg/apache/pulsar/packages/management/core/common/PackageType;
      15: new           #4                  // class org/apache/pulsar/packages/management/core/common/PackageType
      18: dup
      19: ldc           #22                 // String SINK
      21: iconst_1
      22: ldc           #23                 // String sink
      24: invokespecial #20                 // Method "<init>":(Ljava/lang/String;ILjava/lang/String;)V
      27: putstatic     #24                 // Field SINK:Lorg/apache/pulsar/packages/management/core/common/PackageType;
      30: new           #4                  // class org/apache/pulsar/packages/management/core/common/PackageType
      33: dup
      34: ldc           #25                 // String SOURCE
      36: iconst_2
      37: ldc           #26                 // String source
      39: invokespecial #20                 // Method "<init>":(Ljava/lang/String;ILjava/lang/String;)V
      42: putstatic     #27                 // Field SOURCE:Lorg/apache/pulsar/packages/management/core/common/PackageType;
      45: iconst_3
      46: anewarray     #4                  // class org/apache/pulsar/packages/management/core/common/PackageType
      49: dup
      50: iconst_0
      51: getstatic     #21                 // Field FUNCTION:Lorg/apache/pulsar/packages/management/core/common/PackageType;
      54: aastore
      55: dup
      56: iconst_1
      57: getstatic     #24                 // Field SINK:Lorg/apache/pulsar/packages/management/core/common/PackageType;
      60: aastore
      61: dup
      62: iconst_2
      63: getstatic     #27                 // Field SOURCE:Lorg/apache/pulsar/packages/management/core/common/PackageType;
      66: aastore
      67: putstatic     #1                  // Field $VALUES:[Lorg/apache/pulsar/packages/management/core/common/PackageType;
      70: return
}
