Compiled from "CompositeFunctionMapper.java"
public final class jnr.ffi.mapper.CompositeFunctionMapper implements jnr.ffi.mapper.FunctionMapper {
  private final java.util.Collection<jnr.ffi.mapper.FunctionMapper> functionMappers;

  public jnr.ffi.mapper.CompositeFunctionMapper(java.util.Collection<jnr.ffi.mapper.FunctionMapper>);
    Code:
       0: aload_0
       1: invokespecial #1                  // Method java/lang/Object."<init>":()V
       4: aload_0
       5: new           #2                  // class java/util/ArrayList
       8: dup
       9: aload_1
      10: invokespecial #3                  // Method java/util/ArrayList."<init>":(Ljava/util/Collection;)V
      13: invokestatic  #4                  // Method java/util/Collections.unmodifiableList:(Ljava/util/List;)Ljava/util/List;
      16: putfield      #5                  // Field functionMappers:Ljava/util/Collection;
      19: return

  public java.lang.String mapFunctionName(java.lang.String, jnr.ffi.mapper.FunctionMapper$Context);
    Code:
       0: aload_0
       1: getfield      #5                  // Field functionMappers:Ljava/util/Collection;
       4: invokeinterface #6,  1            // InterfaceMethod java/util/Collection.iterator:()Ljava/util/Iterator;
       9: astore_3
      10: aload_3
      11: invokeinterface #7,  1            // InterfaceMethod java/util/Iterator.hasNext:()Z
      16: ifeq          53
      19: aload_3
      20: invokeinterface #8,  1            // InterfaceMethod java/util/Iterator.next:()Ljava/lang/Object;
      25: checkcast     #9                  // class jnr/ffi/mapper/FunctionMapper
      28: astore        4
      30: aload         4
      32: aload_1
      33: aload_2
      34: invokeinterface #10,  3           // InterfaceMethod jnr/ffi/mapper/FunctionMapper.mapFunctionName:(Ljava/lang/String;Ljnr/ffi/mapper/FunctionMapper$Context;)Ljava/lang/String;
      39: astore        5
      41: aload         5
      43: aload_1
      44: if_acmpeq     50
      47: aload         5
      49: areturn
      50: goto          10
      53: aload_1
      54: areturn
}
