Compiled from "ZipArchiveInputStream.java"
public class org.apache.commons.compress.archivers.zip.ZipArchiveInputStream extends org.apache.commons.compress.archivers.ArchiveInputStream implements org.apache.commons.compress.utils.InputStreamStatistics {
  private final org.apache.commons.compress.archivers.zip.ZipEncoding zipEncoding;

  final java.lang.String encoding;

  private final boolean useUnicodeExtraFields;

  private final java.io.InputStream in;

  private final java.util.zip.Inflater inf;

  private final java.nio.ByteBuffer buf;

  private org.apache.commons.compress.archivers.zip.ZipArchiveInputStream$CurrentEntry current;

  private boolean closed;

  private boolean hitCentralDirectory;

  private java.io.ByteArrayInputStream lastStoredEntry;

  private boolean allowStoredEntriesWithDataDescriptor;

  private long uncompressedCount;

  private final boolean skipSplitSig;

  private static final int LFH_LEN;

  private static final int CFH_LEN;

  private static final long TWO_EXP_32;

  private final byte[] lfhBuf;

  private final byte[] skipBuf;

  private final byte[] shortBuf;

  private final byte[] wordBuf;

  private final byte[] twoDwordBuf;

  private int entriesRead;

  private static final java.lang.String USE_ZIPFILE_INSTEAD_OF_STREAM_DISCLAIMER;

  private static final byte[] LFH;

  private static final byte[] CFH;

  private static final byte[] DD;

  private static final byte[] APK_SIGNING_BLOCK_MAGIC;

  private static final java.math.BigInteger LONG_MAX;

  public org.apache.commons.compress.archivers.zip.ZipArchiveInputStream(java.io.InputStream);
    Code:
       0: aload_0
       1: aload_1
       2: ldc           #5                  // String UTF8
       4: invokespecial #6                  // Method "<init>":(Ljava/io/InputStream;Ljava/lang/String;)V
       7: return

  public org.apache.commons.compress.archivers.zip.ZipArchiveInputStream(java.io.InputStream, java.lang.String);
    Code:
       0: aload_0
       1: aload_1
       2: aload_2
       3: iconst_1
       4: invokespecial #7                  // Method "<init>":(Ljava/io/InputStream;Ljava/lang/String;Z)V
       7: return

  public org.apache.commons.compress.archivers.zip.ZipArchiveInputStream(java.io.InputStream, java.lang.String, boolean);
    Code:
       0: aload_0
       1: aload_1
       2: aload_2
       3: iload_3
       4: iconst_0
       5: invokespecial #8                  // Method "<init>":(Ljava/io/InputStream;Ljava/lang/String;ZZ)V
       8: return

  public org.apache.commons.compress.archivers.zip.ZipArchiveInputStream(java.io.InputStream, java.lang.String, boolean, boolean);
    Code:
       0: aload_0
       1: aload_1
       2: aload_2
       3: iload_3
       4: iload         4
       6: iconst_0
       7: invokespecial #9                  // Method "<init>":(Ljava/io/InputStream;Ljava/lang/String;ZZZ)V
      10: return

  public org.apache.commons.compress.archivers.zip.ZipArchiveInputStream(java.io.InputStream, java.lang.String, boolean, boolean, boolean);
    Code:
       0: aload_0
       1: invokespecial #10                 // Method org/apache/commons/compress/archivers/ArchiveInputStream."<init>":()V
       4: aload_0
       5: new           #11                 // class java/util/zip/Inflater
       8: dup
       9: iconst_1
      10: invokespecial #12                 // Method java/util/zip/Inflater."<init>":(Z)V
      13: putfield      #13                 // Field inf:Ljava/util/zip/Inflater;
      16: aload_0
      17: sipush        512
      20: invokestatic  #15                 // Method java/nio/ByteBuffer.allocate:(I)Ljava/nio/ByteBuffer;
      23: putfield      #16                 // Field buf:Ljava/nio/ByteBuffer;
      26: aload_0
      27: bipush        30
      29: newarray       byte
      31: putfield      #18                 // Field lfhBuf:[B
      34: aload_0
      35: sipush        1024
      38: newarray       byte
      40: putfield      #19                 // Field skipBuf:[B
      43: aload_0
      44: iconst_2
      45: newarray       byte
      47: putfield      #20                 // Field shortBuf:[B
      50: aload_0
      51: iconst_4
      52: newarray       byte
      54: putfield      #21                 // Field wordBuf:[B
      57: aload_0
      58: bipush        16
      60: newarray       byte
      62: putfield      #22                 // Field twoDwordBuf:[B
      65: aload_0
      66: aload_2
      67: putfield      #23                 // Field encoding:Ljava/lang/String;
      70: aload_0
      71: aload_2
      72: invokestatic  #24                 // Method org/apache/commons/compress/archivers/zip/ZipEncodingHelper.getZipEncoding:(Ljava/lang/String;)Lorg/apache/commons/compress/archivers/zip/ZipEncoding;
      75: putfield      #25                 // Field zipEncoding:Lorg/apache/commons/compress/archivers/zip/ZipEncoding;
      78: aload_0
      79: iload_3
      80: putfield      #26                 // Field useUnicodeExtraFields:Z
      83: aload_0
      84: new           #27                 // class java/io/PushbackInputStream
      87: dup
      88: aload_1
      89: aload_0
      90: getfield      #16                 // Field buf:Ljava/nio/ByteBuffer;
      93: invokevirtual #28                 // Method java/nio/ByteBuffer.capacity:()I
      96: invokespecial #29                 // Method java/io/PushbackInputStream."<init>":(Ljava/io/InputStream;I)V
      99: putfield      #30                 // Field in:Ljava/io/InputStream;
     102: aload_0
     103: iload         4
     105: putfield      #31                 // Field allowStoredEntriesWithDataDescriptor:Z
     108: aload_0
     109: iload         5
     111: putfield      #32                 // Field skipSplitSig:Z
     114: aload_0
     115: getfield      #16                 // Field buf:Ljava/nio/ByteBuffer;
     118: iconst_0
     119: invokevirtual #33                 // Method java/nio/ByteBuffer.limit:(I)Ljava/nio/Buffer;
     122: pop
     123: return

  public org.apache.commons.compress.archivers.zip.ZipArchiveEntry getNextZipEntry() throws java.io.IOException;
    Code:
       0: aload_0
       1: lconst_0
       2: putfield      #34                 // Field uncompressedCount:J
       5: iconst_1
       6: istore_1
       7: aload_0
       8: getfield      #35                 // Field closed:Z
      11: ifne          21
      14: aload_0
      15: getfield      #36                 // Field hitCentralDirectory:Z
      18: ifeq          23
      21: aconst_null
      22: areturn
      23: aload_0
      24: getfield      #3                  // Field current:Lorg/apache/commons/compress/archivers/zip/ZipArchiveInputStream$CurrentEntry;
      27: ifnull        36
      30: aload_0
      31: invokespecial #37                 // Method closeEntry:()V
      34: iconst_0
      35: istore_1
      36: aload_0
      37: invokevirtual #38                 // Method getBytesRead:()J
      40: lstore_2
      41: iload_1
      42: ifeq          52
      45: aload_0
      46: invokespecial #39                 // Method readFirstLocalFileHeader:()V
      49: goto          60
      52: aload_0
      53: aload_0
      54: getfield      #18                 // Field lfhBuf:[B
      57: invokespecial #40                 // Method readFully:([B)V
      60: goto          67
      63: astore        4
      65: aconst_null
      66: areturn
      67: new           #42                 // class org/apache/commons/compress/archivers/zip/ZipLong
      70: dup
      71: aload_0
      72: getfield      #18                 // Field lfhBuf:[B
      75: invokespecial #43                 // Method org/apache/commons/compress/archivers/zip/ZipLong."<init>":([B)V
      78: astore        4
      80: aload         4
      82: getstatic     #44                 // Field org/apache/commons/compress/archivers/zip/ZipLong.LFH_SIG:Lorg/apache/commons/compress/archivers/zip/ZipLong;
      85: invokevirtual #45                 // Method org/apache/commons/compress/archivers/zip/ZipLong.equals:(Ljava/lang/Object;)Z
      88: ifne          163
      91: aload         4
      93: getstatic     #46                 // Field org/apache/commons/compress/archivers/zip/ZipLong.CFH_SIG:Lorg/apache/commons/compress/archivers/zip/ZipLong;
      96: invokevirtual #45                 // Method org/apache/commons/compress/archivers/zip/ZipLong.equals:(Ljava/lang/Object;)Z
      99: ifne          124
     102: aload         4
     104: getstatic     #47                 // Field org/apache/commons/compress/archivers/zip/ZipLong.AED_SIG:Lorg/apache/commons/compress/archivers/zip/ZipLong;
     107: invokevirtual #45                 // Method org/apache/commons/compress/archivers/zip/ZipLong.equals:(Ljava/lang/Object;)Z
     110: ifne          124
     113: aload_0
     114: aload_0
     115: getfield      #18                 // Field lfhBuf:[B
     118: invokespecial #48                 // Method isApkSigningBlock:([B)Z
     121: ifeq          135
     124: aload_0
     125: iconst_1
     126: putfield      #36                 // Field hitCentralDirectory:Z
     129: aload_0
     130: invokespecial #49                 // Method skipRemainderOfArchive:()V
     133: aconst_null
     134: areturn
     135: new           #50                 // class java/util/zip/ZipException
     138: dup
     139: ldc           #51                 // String Unexpected record signature: 0X%X
     141: iconst_1
     142: anewarray     #52                 // class java/lang/Object
     145: dup
     146: iconst_0
     147: aload         4
     149: invokevirtual #53                 // Method org/apache/commons/compress/archivers/zip/ZipLong.getValue:()J
     152: invokestatic  #54                 // Method java/lang/Long.valueOf:(J)Ljava/lang/Long;
     155: aastore
     156: invokestatic  #55                 // Method java/lang/String.format:(Ljava/lang/String;[Ljava/lang/Object;)Ljava/lang/String;
     159: invokespecial #56                 // Method java/util/zip/ZipException."<init>":(Ljava/lang/String;)V
     162: athrow
     163: iconst_4
     164: istore        5
     166: aload_0
     167: new           #57                 // class org/apache/commons/compress/archivers/zip/ZipArchiveInputStream$CurrentEntry
     170: dup
     171: aconst_null
     172: invokespecial #58                 // Method org/apache/commons/compress/archivers/zip/ZipArchiveInputStream$CurrentEntry."<init>":(Lorg/apache/commons/compress/archivers/zip/ZipArchiveInputStream$1;)V
     175: putfield      #3                  // Field current:Lorg/apache/commons/compress/archivers/zip/ZipArchiveInputStream$CurrentEntry;
     178: aload_0
     179: getfield      #18                 // Field lfhBuf:[B
     182: iload         5
     184: invokestatic  #59                 // Method org/apache/commons/compress/archivers/zip/ZipShort.getValue:([BI)I
     187: istore        6
     189: iinc          5, 2
     192: aload_0
     193: getfield      #3                  // Field current:Lorg/apache/commons/compress/archivers/zip/ZipArchiveInputStream$CurrentEntry;
     196: invokestatic  #60                 // Method org/apache/commons/compress/archivers/zip/ZipArchiveInputStream$CurrentEntry.access$100:(Lorg/apache/commons/compress/archivers/zip/ZipArchiveInputStream$CurrentEntry;)Lorg/apache/commons/compress/archivers/zip/ZipArchiveEntry;
     199: iload         6
     201: bipush        8
     203: ishr
     204: bipush        15
     206: iand
     207: invokevirtual #62                 // Method org/apache/commons/compress/archivers/zip/ZipArchiveEntry.setPlatform:(I)V
     210: aload_0
     211: getfield      #18                 // Field lfhBuf:[B
     214: iload         5
     216: invokestatic  #63                 // Method org/apache/commons/compress/archivers/zip/GeneralPurposeBit.parse:([BI)Lorg/apache/commons/compress/archivers/zip/GeneralPurposeBit;
     219: astore        7
     221: aload         7
     223: invokevirtual #64                 // Method org/apache/commons/compress/archivers/zip/GeneralPurposeBit.usesUTF8ForNames:()Z
     226: istore        8
     228: iload         8
     230: ifeq          239
     233: getstatic     #65                 // Field org/apache/commons/compress/archivers/zip/ZipEncodingHelper.UTF8_ZIP_ENCODING:Lorg/apache/commons/compress/archivers/zip/ZipEncoding;
     236: goto          243
     239: aload_0
     240: getfield      #25                 // Field zipEncoding:Lorg/apache/commons/compress/archivers/zip/ZipEncoding;
     243: astore        9
     245: aload_0
     246: getfield      #3                  // Field current:Lorg/apache/commons/compress/archivers/zip/ZipArchiveInputStream$CurrentEntry;
     249: aload         7
     251: invokevirtual #66                 // Method org/apache/commons/compress/archivers/zip/GeneralPurposeBit.usesDataDescriptor:()Z
     254: invokestatic  #67                 // Method org/apache/commons/compress/archivers/zip/ZipArchiveInputStream$CurrentEntry.access$202:(Lorg/apache/commons/compress/archivers/zip/ZipArchiveInputStream$CurrentEntry;Z)Z
     257: pop
     258: aload_0
     259: getfield      #3                  // Field current:Lorg/apache/commons/compress/archivers/zip/ZipArchiveInputStream$CurrentEntry;
     262: invokestatic  #60                 // Method org/apache/commons/compress/archivers/zip/ZipArchiveInputStream$CurrentEntry.access$100:(Lorg/apache/commons/compress/archivers/zip/ZipArchiveInputStream$CurrentEntry;)Lorg/apache/commons/compress/archivers/zip/ZipArchiveEntry;
     265: aload         7
     267: invokevirtual #68                 // Method org/apache/commons/compress/archivers/zip/ZipArchiveEntry.setGeneralPurposeBit:(Lorg/apache/commons/compress/archivers/zip/GeneralPurposeBit;)V
     270: iinc          5, 2
     273: aload_0
     274: getfield      #3                  // Field current:Lorg/apache/commons/compress/archivers/zip/ZipArchiveInputStream$CurrentEntry;
     277: invokestatic  #60                 // Method org/apache/commons/compress/archivers/zip/ZipArchiveInputStream$CurrentEntry.access$100:(Lorg/apache/commons/compress/archivers/zip/ZipArchiveInputStream$CurrentEntry;)Lorg/apache/commons/compress/archivers/zip/ZipArchiveEntry;
     280: aload_0
     281: getfield      #18                 // Field lfhBuf:[B
     284: iload         5
     286: invokestatic  #59                 // Method org/apache/commons/compress/archivers/zip/ZipShort.getValue:([BI)I
     289: invokevirtual #69                 // Method org/apache/commons/compress/archivers/zip/ZipArchiveEntry.setMethod:(I)V
     292: iinc          5, 2
     295: aload_0
     296: getfield      #18                 // Field lfhBuf:[B
     299: iload         5
     301: invokestatic  #70                 // Method org/apache/commons/compress/archivers/zip/ZipLong.getValue:([BI)J
     304: invokestatic  #71                 // Method org/apache/commons/compress/archivers/zip/ZipUtil.dosToJavaTime:(J)J
     307: lstore        10
     309: aload_0
     310: getfield      #3                  // Field current:Lorg/apache/commons/compress/archivers/zip/ZipArchiveInputStream$CurrentEntry;
     313: invokestatic  #60                 // Method org/apache/commons/compress/archivers/zip/ZipArchiveInputStream$CurrentEntry.access$100:(Lorg/apache/commons/compress/archivers/zip/ZipArchiveInputStream$CurrentEntry;)Lorg/apache/commons/compress/archivers/zip/ZipArchiveEntry;
     316: lload         10
     318: invokevirtual #72                 // Method org/apache/commons/compress/archivers/zip/ZipArchiveEntry.setTime:(J)V
     321: iinc          5, 4
     324: aconst_null
     325: astore        12
     327: aconst_null
     328: astore        13
     330: aload_0
     331: getfield      #3                  // Field current:Lorg/apache/commons/compress/archivers/zip/ZipArchiveInputStream$CurrentEntry;
     334: invokestatic  #73                 // Method org/apache/commons/compress/archivers/zip/ZipArchiveInputStream$CurrentEntry.access$200:(Lorg/apache/commons/compress/archivers/zip/ZipArchiveInputStream$CurrentEntry;)Z
     337: ifne          401
     340: aload_0
     341: getfield      #3                  // Field current:Lorg/apache/commons/compress/archivers/zip/ZipArchiveInputStream$CurrentEntry;
     344: invokestatic  #60                 // Method org/apache/commons/compress/archivers/zip/ZipArchiveInputStream$CurrentEntry.access$100:(Lorg/apache/commons/compress/archivers/zip/ZipArchiveInputStream$CurrentEntry;)Lorg/apache/commons/compress/archivers/zip/ZipArchiveEntry;
     347: aload_0
     348: getfield      #18                 // Field lfhBuf:[B
     351: iload         5
     353: invokestatic  #70                 // Method org/apache/commons/compress/archivers/zip/ZipLong.getValue:([BI)J
     356: invokevirtual #74                 // Method org/apache/commons/compress/archivers/zip/ZipArchiveEntry.setCrc:(J)V
     359: iinc          5, 4
     362: new           #42                 // class org/apache/commons/compress/archivers/zip/ZipLong
     365: dup
     366: aload_0
     367: getfield      #18                 // Field lfhBuf:[B
     370: iload         5
     372: invokespecial #75                 // Method org/apache/commons/compress/archivers/zip/ZipLong."<init>":([BI)V
     375: astore        13
     377: iinc          5, 4
     380: new           #42                 // class org/apache/commons/compress/archivers/zip/ZipLong
     383: dup
     384: aload_0
     385: getfield      #18                 // Field lfhBuf:[B
     388: iload         5
     390: invokespecial #75                 // Method org/apache/commons/compress/archivers/zip/ZipLong."<init>":([BI)V
     393: astore        12
     395: iinc          5, 4
     398: goto          404
     401: iinc          5, 12
     404: aload_0
     405: getfield      #18                 // Field lfhBuf:[B
     408: iload         5
     410: invokestatic  #59                 // Method org/apache/commons/compress/archivers/zip/ZipShort.getValue:([BI)I
     413: istore        14
     415: iinc          5, 2
     418: aload_0
     419: getfield      #18                 // Field lfhBuf:[B
     422: iload         5
     424: invokestatic  #59                 // Method org/apache/commons/compress/archivers/zip/ZipShort.getValue:([BI)I
     427: istore        15
     429: iinc          5, 2
     432: aload_0
     433: iload         14
     435: invokespecial #76                 // Method readRange:(I)[B
     438: astore        16
     440: aload_0
     441: getfield      #3                  // Field current:Lorg/apache/commons/compress/archivers/zip/ZipArchiveInputStream$CurrentEntry;
     444: invokestatic  #60                 // Method org/apache/commons/compress/archivers/zip/ZipArchiveInputStream$CurrentEntry.access$100:(Lorg/apache/commons/compress/archivers/zip/ZipArchiveInputStream$CurrentEntry;)Lorg/apache/commons/compress/archivers/zip/ZipArchiveEntry;
     447: aload         9
     449: aload         16
     451: invokeinterface #77,  2           // InterfaceMethod org/apache/commons/compress/archivers/zip/ZipEncoding.decode:([B)Ljava/lang/String;
     456: aload         16
     458: invokevirtual #78                 // Method org/apache/commons/compress/archivers/zip/ZipArchiveEntry.setName:(Ljava/lang/String;[B)V
     461: iload         8
     463: ifeq          479
     466: aload_0
     467: getfield      #3                  // Field current:Lorg/apache/commons/compress/archivers/zip/ZipArchiveInputStream$CurrentEntry;
     470: invokestatic  #60                 // Method org/apache/commons/compress/archivers/zip/ZipArchiveInputStream$CurrentEntry.access$100:(Lorg/apache/commons/compress/archivers/zip/ZipArchiveInputStream$CurrentEntry;)Lorg/apache/commons/compress/archivers/zip/ZipArchiveEntry;
     473: getstatic     #79                 // Field org/apache/commons/compress/archivers/zip/ZipArchiveEntry$NameSource.NAME_WITH_EFS_FLAG:Lorg/apache/commons/compress/archivers/zip/ZipArchiveEntry$NameSource;
     476: invokevirtual #80                 // Method org/apache/commons/compress/archivers/zip/ZipArchiveEntry.setNameSource:(Lorg/apache/commons/compress/archivers/zip/ZipArchiveEntry$NameSource;)V
     479: aload_0
     480: iload         15
     482: invokespecial #76                 // Method readRange:(I)[B
     485: astore        17
     487: aload_0
     488: getfield      #3                  // Field current:Lorg/apache/commons/compress/archivers/zip/ZipArchiveInputStream$CurrentEntry;
     491: invokestatic  #60                 // Method org/apache/commons/compress/archivers/zip/ZipArchiveInputStream$CurrentEntry.access$100:(Lorg/apache/commons/compress/archivers/zip/ZipArchiveInputStream$CurrentEntry;)Lorg/apache/commons/compress/archivers/zip/ZipArchiveEntry;
     494: aload         17
     496: invokevirtual #81                 // Method org/apache/commons/compress/archivers/zip/ZipArchiveEntry.setExtra:([B)V
     499: goto          552
     502: astore        18
     504: new           #50                 // class java/util/zip/ZipException
     507: dup
     508: new           #83                 // class java/lang/StringBuilder
     511: dup
     512: invokespecial #84                 // Method java/lang/StringBuilder."<init>":()V
     515: ldc           #85                 // String Invalid extra data in entry
     517: invokevirtual #86                 // Method java/lang/StringBuilder.append:(Ljava/lang/String;)Ljava/lang/StringBuilder;
     520: aload_0
     521: getfield      #3                  // Field current:Lorg/apache/commons/compress/archivers/zip/ZipArchiveInputStream$CurrentEntry;
     524: invokestatic  #60                 // Method org/apache/commons/compress/archivers/zip/ZipArchiveInputStream$CurrentEntry.access$100:(Lorg/apache/commons/compress/archivers/zip/ZipArchiveInputStream$CurrentEntry;)Lorg/apache/commons/compress/archivers/zip/ZipArchiveEntry;
     527: invokevirtual #87                 // Method org/apache/commons/compress/archivers/zip/ZipArchiveEntry.getName:()Ljava/lang/String;
     530: invokevirtual #86                 // Method java/lang/StringBuilder.append:(Ljava/lang/String;)Ljava/lang/StringBuilder;
     533: invokevirtual #88                 // Method java/lang/StringBuilder.toString:()Ljava/lang/String;
     536: invokespecial #56                 // Method java/util/zip/ZipException."<init>":(Ljava/lang/String;)V
     539: astore        19
     541: aload         19
     543: aload         18
     545: invokevirtual #89                 // Method java/util/zip/ZipException.initCause:(Ljava/lang/Throwable;)Ljava/lang/Throwable;
     548: pop
     549: aload         19
     551: athrow
     552: iload         8
     554: ifne          577
     557: aload_0
     558: getfield      #26                 // Field useUnicodeExtraFields:Z
     561: ifeq          577
     564: aload_0
     565: getfield      #3                  // Field current:Lorg/apache/commons/compress/archivers/zip/ZipArchiveInputStream$CurrentEntry;
     568: invokestatic  #60                 // Method org/apache/commons/compress/archivers/zip/ZipArchiveInputStream$CurrentEntry.access$100:(Lorg/apache/commons/compress/archivers/zip/ZipArchiveInputStream$CurrentEntry;)Lorg/apache/commons/compress/archivers/zip/ZipArchiveEntry;
     571: aload         16
     573: aconst_null
     574: invokestatic  #90                 // Method org/apache/commons/compress/archivers/zip/ZipUtil.setNameAndCommentFromExtraFields:(Lorg/apache/commons/compress/archivers/zip/ZipArchiveEntry;[B[B)V
     577: aload_0
     578: aload         12
     580: aload         13
     582: invokespecial #91                 // Method processZip64Extra:(Lorg/apache/commons/compress/archivers/zip/ZipLong;Lorg/apache/commons/compress/archivers/zip/ZipLong;)V
     585: aload_0
     586: getfield      #3                  // Field current:Lorg/apache/commons/compress/archivers/zip/ZipArchiveInputStream$CurrentEntry;
     589: invokestatic  #60                 // Method org/apache/commons/compress/archivers/zip/ZipArchiveInputStream$CurrentEntry.access$100:(Lorg/apache/commons/compress/archivers/zip/ZipArchiveInputStream$CurrentEntry;)Lorg/apache/commons/compress/archivers/zip/ZipArchiveEntry;
     592: lload_2
     593: invokevirtual #92                 // Method org/apache/commons/compress/archivers/zip/ZipArchiveEntry.setLocalHeaderOffset:(J)V
     596: aload_0
     597: getfield      #3                  // Field current:Lorg/apache/commons/compress/archivers/zip/ZipArchiveInputStream$CurrentEntry;
     600: invokestatic  #60                 // Method org/apache/commons/compress/archivers/zip/ZipArchiveInputStream$CurrentEntry.access$100:(Lorg/apache/commons/compress/archivers/zip/ZipArchiveInputStream$CurrentEntry;)Lorg/apache/commons/compress/archivers/zip/ZipArchiveEntry;
     603: aload_0
     604: invokevirtual #38                 // Method getBytesRead:()J
     607: invokevirtual #93                 // Method org/apache/commons/compress/archivers/zip/ZipArchiveEntry.setDataOffset:(J)V
     610: aload_0
     611: getfield      #3                  // Field current:Lorg/apache/commons/compress/archivers/zip/ZipArchiveInputStream$CurrentEntry;
     614: invokestatic  #60                 // Method org/apache/commons/compress/archivers/zip/ZipArchiveInputStream$CurrentEntry.access$100:(Lorg/apache/commons/compress/archivers/zip/ZipArchiveInputStream$CurrentEntry;)Lorg/apache/commons/compress/archivers/zip/ZipArchiveEntry;
     617: iconst_1
     618: invokevirtual #94                 // Method org/apache/commons/compress/archivers/zip/ZipArchiveEntry.setStreamContiguous:(Z)V
     621: aload_0
     622: getfield      #3                  // Field current:Lorg/apache/commons/compress/archivers/zip/ZipArchiveInputStream$CurrentEntry;
     625: invokestatic  #60                 // Method org/apache/commons/compress/archivers/zip/ZipArchiveInputStream$CurrentEntry.access$100:(Lorg/apache/commons/compress/archivers/zip/ZipArchiveInputStream$CurrentEntry;)Lorg/apache/commons/compress/archivers/zip/ZipArchiveEntry;
     628: invokevirtual #95                 // Method org/apache/commons/compress/archivers/zip/ZipArchiveEntry.getMethod:()I
     631: invokestatic  #96                 // Method org/apache/commons/compress/archivers/zip/ZipMethod.getMethodByCode:(I)Lorg/apache/commons/compress/archivers/zip/ZipMethod;
     634: astore        18
     636: aload_0
     637: getfield      #3                  // Field current:Lorg/apache/commons/compress/archivers/zip/ZipArchiveInputStream$CurrentEntry;
     640: invokestatic  #60                 // Method org/apache/commons/compress/archivers/zip/ZipArchiveInputStream$CurrentEntry.access$100:(Lorg/apache/commons/compress/archivers/zip/ZipArchiveInputStream$CurrentEntry;)Lorg/apache/commons/compress/archivers/zip/ZipArchiveEntry;
     643: invokevirtual #97                 // Method org/apache/commons/compress/archivers/zip/ZipArchiveEntry.getCompressedSize:()J
     646: ldc2_w        #99                 // long -1l
     649: lcmp
     650: ifeq          867
     653: aload_0
     654: getfield      #3                  // Field current:Lorg/apache/commons/compress/archivers/zip/ZipArchiveInputStream$CurrentEntry;
     657: invokestatic  #60                 // Method org/apache/commons/compress/archivers/zip/ZipArchiveInputStream$CurrentEntry.access$100:(Lorg/apache/commons/compress/archivers/zip/ZipArchiveInputStream$CurrentEntry;)Lorg/apache/commons/compress/archivers/zip/ZipArchiveEntry;
     660: invokestatic  #101                // Method org/apache/commons/compress/archivers/zip/ZipUtil.canHandleEntryData:(Lorg/apache/commons/compress/archivers/zip/ZipArchiveEntry;)Z
     663: ifeq          894
     666: aload         18
     668: getstatic     #102                // Field org/apache/commons/compress/archivers/zip/ZipMethod.STORED:Lorg/apache/commons/compress/archivers/zip/ZipMethod;
     671: if_acmpeq     894
     674: aload         18
     676: getstatic     #103                // Field org/apache/commons/compress/archivers/zip/ZipMethod.DEFLATED:Lorg/apache/commons/compress/archivers/zip/ZipMethod;
     679: if_acmpeq     894
     682: new           #104                // class org/apache/commons/compress/archivers/zip/ZipArchiveInputStream$BoundedInputStream
     685: dup
     686: aload_0
     687: aload_0
     688: getfield      #30                 // Field in:Ljava/io/InputStream;
     691: aload_0
     692: getfield      #3                  // Field current:Lorg/apache/commons/compress/archivers/zip/ZipArchiveInputStream$CurrentEntry;
     695: invokestatic  #60                 // Method org/apache/commons/compress/archivers/zip/ZipArchiveInputStream$CurrentEntry.access$100:(Lorg/apache/commons/compress/archivers/zip/ZipArchiveInputStream$CurrentEntry;)Lorg/apache/commons/compress/archivers/zip/ZipArchiveEntry;
     698: invokevirtual #97                 // Method org/apache/commons/compress/archivers/zip/ZipArchiveEntry.getCompressedSize:()J
     701: invokespecial #105                // Method org/apache/commons/compress/archivers/zip/ZipArchiveInputStream$BoundedInputStream."<init>":(Lorg/apache/commons/compress/archivers/zip/ZipArchiveInputStream;Ljava/io/InputStream;J)V
     704: astore        19
     706: getstatic     #106                // Field org/apache/commons/compress/archivers/zip/ZipArchiveInputStream$1.$SwitchMap$org$apache$commons$compress$archivers$zip$ZipMethod:[I
     709: aload         18
     711: invokevirtual #107                // Method org/apache/commons/compress/archivers/zip/ZipMethod.ordinal:()I
     714: iaload
     715: tableswitch   { // 1 to 4
                     1: 744
                     2: 764
                     3: 824
                     4: 844
               default: 864
          }
     744: aload_0
     745: getfield      #3                  // Field current:Lorg/apache/commons/compress/archivers/zip/ZipArchiveInputStream$CurrentEntry;
     748: new           #108                // class org/apache/commons/compress/archivers/zip/UnshrinkingInputStream
     751: dup
     752: aload         19
     754: invokespecial #109                // Method org/apache/commons/compress/archivers/zip/UnshrinkingInputStream."<init>":(Ljava/io/InputStream;)V
     757: invokestatic  #110                // Method org/apache/commons/compress/archivers/zip/ZipArchiveInputStream$CurrentEntry.access$302:(Lorg/apache/commons/compress/archivers/zip/ZipArchiveInputStream$CurrentEntry;Ljava/io/InputStream;)Ljava/io/InputStream;
     760: pop
     761: goto          864
     764: aload_0
     765: getfield      #3                  // Field current:Lorg/apache/commons/compress/archivers/zip/ZipArchiveInputStream$CurrentEntry;
     768: new           #111                // class org/apache/commons/compress/archivers/zip/ExplodingInputStream
     771: dup
     772: aload_0
     773: getfield      #3                  // Field current:Lorg/apache/commons/compress/archivers/zip/ZipArchiveInputStream$CurrentEntry;
     776: invokestatic  #60                 // Method org/apache/commons/compress/archivers/zip/ZipArchiveInputStream$CurrentEntry.access$100:(Lorg/apache/commons/compress/archivers/zip/ZipArchiveInputStream$CurrentEntry;)Lorg/apache/commons/compress/archivers/zip/ZipArchiveEntry;
     779: invokevirtual #112                // Method org/apache/commons/compress/archivers/zip/ZipArchiveEntry.getGeneralPurposeBit:()Lorg/apache/commons/compress/archivers/zip/GeneralPurposeBit;
     782: invokevirtual #113                // Method org/apache/commons/compress/archivers/zip/GeneralPurposeBit.getSlidingDictionarySize:()I
     785: aload_0
     786: getfield      #3                  // Field current:Lorg/apache/commons/compress/archivers/zip/ZipArchiveInputStream$CurrentEntry;
     789: invokestatic  #60                 // Method org/apache/commons/compress/archivers/zip/ZipArchiveInputStream$CurrentEntry.access$100:(Lorg/apache/commons/compress/archivers/zip/ZipArchiveInputStream$CurrentEntry;)Lorg/apache/commons/compress/archivers/zip/ZipArchiveEntry;
     792: invokevirtual #112                // Method org/apache/commons/compress/archivers/zip/ZipArchiveEntry.getGeneralPurposeBit:()Lorg/apache/commons/compress/archivers/zip/GeneralPurposeBit;
     795: invokevirtual #114                // Method org/apache/commons/compress/archivers/zip/GeneralPurposeBit.getNumberOfShannonFanoTrees:()I
     798: aload         19
     800: invokespecial #115                // Method org/apache/commons/compress/archivers/zip/ExplodingInputStream."<init>":(IILjava/io/InputStream;)V
     803: invokestatic  #110                // Method org/apache/commons/compress/archivers/zip/ZipArchiveInputStream$CurrentEntry.access$302:(Lorg/apache/commons/compress/archivers/zip/ZipArchiveInputStream$CurrentEntry;Ljava/io/InputStream;)Ljava/io/InputStream;
     806: pop
     807: goto          864
     810: astore        20
     812: new           #117                // class java/io/IOException
     815: dup
     816: ldc           #118                // String bad IMPLODE data
     818: aload         20
     820: invokespecial #119                // Method java/io/IOException."<init>":(Ljava/lang/String;Ljava/lang/Throwable;)V
     823: athrow
     824: aload_0
     825: getfield      #3                  // Field current:Lorg/apache/commons/compress/archivers/zip/ZipArchiveInputStream$CurrentEntry;
     828: new           #120                // class org/apache/commons/compress/compressors/bzip2/BZip2CompressorInputStream
     831: dup
     832: aload         19
     834: invokespecial #121                // Method org/apache/commons/compress/compressors/bzip2/BZip2CompressorInputStream."<init>":(Ljava/io/InputStream;)V
     837: invokestatic  #110                // Method org/apache/commons/compress/archivers/zip/ZipArchiveInputStream$CurrentEntry.access$302:(Lorg/apache/commons/compress/archivers/zip/ZipArchiveInputStream$CurrentEntry;Ljava/io/InputStream;)Ljava/io/InputStream;
     840: pop
     841: goto          864
     844: aload_0
     845: getfield      #3                  // Field current:Lorg/apache/commons/compress/archivers/zip/ZipArchiveInputStream$CurrentEntry;
     848: new           #122                // class org/apache/commons/compress/compressors/deflate64/Deflate64CompressorInputStream
     851: dup
     852: aload         19
     854: invokespecial #123                // Method org/apache/commons/compress/compressors/deflate64/Deflate64CompressorInputStream."<init>":(Ljava/io/InputStream;)V
     857: invokestatic  #110                // Method org/apache/commons/compress/archivers/zip/ZipArchiveInputStream$CurrentEntry.access$302:(Lorg/apache/commons/compress/archivers/zip/ZipArchiveInputStream$CurrentEntry;Ljava/io/InputStream;)Ljava/io/InputStream;
     860: pop
     861: goto          864
     864: goto          894
     867: aload         18
     869: getstatic     #124                // Field org/apache/commons/compress/archivers/zip/ZipMethod.ENHANCED_DEFLATED:Lorg/apache/commons/compress/archivers/zip/ZipMethod;
     872: if_acmpne     894
     875: aload_0
     876: getfield      #3                  // Field current:Lorg/apache/commons/compress/archivers/zip/ZipArchiveInputStream$CurrentEntry;
     879: new           #122                // class org/apache/commons/compress/compressors/deflate64/Deflate64CompressorInputStream
     882: dup
     883: aload_0
     884: getfield      #30                 // Field in:Ljava/io/InputStream;
     887: invokespecial #123                // Method org/apache/commons/compress/compressors/deflate64/Deflate64CompressorInputStream."<init>":(Ljava/io/InputStream;)V
     890: invokestatic  #110                // Method org/apache/commons/compress/archivers/zip/ZipArchiveInputStream$CurrentEntry.access$302:(Lorg/apache/commons/compress/archivers/zip/ZipArchiveInputStream$CurrentEntry;Ljava/io/InputStream;)Ljava/io/InputStream;
     893: pop
     894: aload_0
     895: dup
     896: getfield      #125                // Field entriesRead:I
     899: iconst_1
     900: iadd
     901: putfield      #125                // Field entriesRead:I
     904: aload_0
     905: getfield      #3                  // Field current:Lorg/apache/commons/compress/archivers/zip/ZipArchiveInputStream$CurrentEntry;
     908: invokestatic  #60                 // Method org/apache/commons/compress/archivers/zip/ZipArchiveInputStream$CurrentEntry.access$100:(Lorg/apache/commons/compress/archivers/zip/ZipArchiveInputStream$CurrentEntry;)Lorg/apache/commons/compress/archivers/zip/ZipArchiveEntry;
     911: areturn
    Exception table:
       from    to  target type
          41    60    63   Class java/io/EOFException
         487   499   502   Class java/lang/RuntimeException
         764   807   810   Class java/lang/IllegalArgumentException

  private void readFirstLocalFileHeader() throws java.io.IOException;
    Code:
       0: aload_0
       1: aload_0
       2: getfield      #18                 // Field lfhBuf:[B
       5: invokespecial #40                 // Method readFully:([B)V
       8: new           #42                 // class org/apache/commons/compress/archivers/zip/ZipLong
      11: dup
      12: aload_0
      13: getfield      #18                 // Field lfhBuf:[B
      16: invokespecial #43                 // Method org/apache/commons/compress/archivers/zip/ZipLong."<init>":([B)V
      19: astore_1
      20: aload_0
      21: getfield      #32                 // Field skipSplitSig:Z
      24: ifne          48
      27: aload_1
      28: getstatic     #126                // Field org/apache/commons/compress/archivers/zip/ZipLong.DD_SIG:Lorg/apache/commons/compress/archivers/zip/ZipLong;
      31: invokevirtual #45                 // Method org/apache/commons/compress/archivers/zip/ZipLong.equals:(Ljava/lang/Object;)Z
      34: ifeq          48
      37: new           #127                // class org/apache/commons/compress/archivers/zip/UnsupportedZipFeatureException
      40: dup
      41: getstatic     #128                // Field org/apache/commons/compress/archivers/zip/UnsupportedZipFeatureException$Feature.SPLITTING:Lorg/apache/commons/compress/archivers/zip/UnsupportedZipFeatureException$Feature;
      44: invokespecial #129                // Method org/apache/commons/compress/archivers/zip/UnsupportedZipFeatureException."<init>":(Lorg/apache/commons/compress/archivers/zip/UnsupportedZipFeatureException$Feature;)V
      47: athrow
      48: aload_1
      49: getstatic     #130                // Field org/apache/commons/compress/archivers/zip/ZipLong.SINGLE_SEGMENT_SPLIT_MARKER:Lorg/apache/commons/compress/archivers/zip/ZipLong;
      52: invokevirtual #45                 // Method org/apache/commons/compress/archivers/zip/ZipLong.equals:(Ljava/lang/Object;)Z
      55: ifne          68
      58: aload_1
      59: getstatic     #126                // Field org/apache/commons/compress/archivers/zip/ZipLong.DD_SIG:Lorg/apache/commons/compress/archivers/zip/ZipLong;
      62: invokevirtual #45                 // Method org/apache/commons/compress/archivers/zip/ZipLong.equals:(Ljava/lang/Object;)Z
      65: ifeq          104
      68: iconst_4
      69: newarray       byte
      71: astore_2
      72: aload_0
      73: aload_2
      74: invokespecial #40                 // Method readFully:([B)V
      77: aload_0
      78: getfield      #18                 // Field lfhBuf:[B
      81: iconst_4
      82: aload_0
      83: getfield      #18                 // Field lfhBuf:[B
      86: iconst_0
      87: bipush        26
      89: invokestatic  #131                // Method java/lang/System.arraycopy:(Ljava/lang/Object;ILjava/lang/Object;II)V
      92: aload_2
      93: iconst_0
      94: aload_0
      95: getfield      #18                 // Field lfhBuf:[B
      98: bipush        26
     100: iconst_4
     101: invokestatic  #131                // Method java/lang/System.arraycopy:(Ljava/lang/Object;ILjava/lang/Object;II)V
     104: return

  private void processZip64Extra(org.apache.commons.compress.archivers.zip.ZipLong, org.apache.commons.compress.archivers.zip.ZipLong) throws java.util.zip.ZipException;
    Code:
       0: aload_0
       1: getfield      #3                  // Field current:Lorg/apache/commons/compress/archivers/zip/ZipArchiveInputStream$CurrentEntry;
       4: invokestatic  #60                 // Method org/apache/commons/compress/archivers/zip/ZipArchiveInputStream$CurrentEntry.access$100:(Lorg/apache/commons/compress/archivers/zip/ZipArchiveInputStream$CurrentEntry;)Lorg/apache/commons/compress/archivers/zip/ZipArchiveEntry;
       7: getstatic     #132                // Field org/apache/commons/compress/archivers/zip/Zip64ExtendedInformationExtraField.HEADER_ID:Lorg/apache/commons/compress/archivers/zip/ZipShort;
      10: invokevirtual #133                // Method org/apache/commons/compress/archivers/zip/ZipArchiveEntry.getExtraField:(Lorg/apache/commons/compress/archivers/zip/ZipShort;)Lorg/apache/commons/compress/archivers/zip/ZipExtraField;
      13: astore_3
      14: aload_3
      15: ifnull        35
      18: aload_3
      19: instanceof    #134                // class org/apache/commons/compress/archivers/zip/Zip64ExtendedInformationExtraField
      22: ifne          35
      25: new           #50                 // class java/util/zip/ZipException
      28: dup
      29: ldc           #135                // String archive contains unparseable zip64 extra field
      31: invokespecial #56                 // Method java/util/zip/ZipException."<init>":(Ljava/lang/String;)V
      34: athrow
      35: aload_3
      36: checkcast     #134                // class org/apache/commons/compress/archivers/zip/Zip64ExtendedInformationExtraField
      39: astore        4
      41: aload_0
      42: getfield      #3                  // Field current:Lorg/apache/commons/compress/archivers/zip/ZipArchiveInputStream$CurrentEntry;
      45: aload         4
      47: ifnull        54
      50: iconst_1
      51: goto          55
      54: iconst_0
      55: invokestatic  #136                // Method org/apache/commons/compress/archivers/zip/ZipArchiveInputStream$CurrentEntry.access$402:(Lorg/apache/commons/compress/archivers/zip/ZipArchiveInputStream$CurrentEntry;Z)Z
      58: pop
      59: aload_0
      60: getfield      #3                  // Field current:Lorg/apache/commons/compress/archivers/zip/ZipArchiveInputStream$CurrentEntry;
      63: invokestatic  #73                 // Method org/apache/commons/compress/archivers/zip/ZipArchiveInputStream$CurrentEntry.access$200:(Lorg/apache/commons/compress/archivers/zip/ZipArchiveInputStream$CurrentEntry;)Z
      66: ifne          275
      69: aload         4
      71: ifnull        201
      74: getstatic     #137                // Field org/apache/commons/compress/archivers/zip/ZipLong.ZIP64_MAGIC:Lorg/apache/commons/compress/archivers/zip/ZipLong;
      77: aload_2
      78: invokevirtual #45                 // Method org/apache/commons/compress/archivers/zip/ZipLong.equals:(Ljava/lang/Object;)Z
      81: ifne          94
      84: getstatic     #137                // Field org/apache/commons/compress/archivers/zip/ZipLong.ZIP64_MAGIC:Lorg/apache/commons/compress/archivers/zip/ZipLong;
      87: aload_1
      88: invokevirtual #45                 // Method org/apache/commons/compress/archivers/zip/ZipLong.equals:(Ljava/lang/Object;)Z
      91: ifeq          201
      94: aload         4
      96: invokevirtual #138                // Method org/apache/commons/compress/archivers/zip/Zip64ExtendedInformationExtraField.getCompressedSize:()Lorg/apache/commons/compress/archivers/zip/ZipEightByteInteger;
      99: ifnull        110
     102: aload         4
     104: invokevirtual #139                // Method org/apache/commons/compress/archivers/zip/Zip64ExtendedInformationExtraField.getSize:()Lorg/apache/commons/compress/archivers/zip/ZipEightByteInteger;
     107: ifnonnull     120
     110: new           #50                 // class java/util/zip/ZipException
     113: dup
     114: ldc           #140                // String archive contains corrupted zip64 extra field
     116: invokespecial #56                 // Method java/util/zip/ZipException."<init>":(Ljava/lang/String;)V
     119: athrow
     120: aload         4
     122: invokevirtual #138                // Method org/apache/commons/compress/archivers/zip/Zip64ExtendedInformationExtraField.getCompressedSize:()Lorg/apache/commons/compress/archivers/zip/ZipEightByteInteger;
     125: invokevirtual #141                // Method org/apache/commons/compress/archivers/zip/ZipEightByteInteger.getLongValue:()J
     128: lstore        5
     130: lload         5
     132: lconst_0
     133: lcmp
     134: ifge          147
     137: new           #50                 // class java/util/zip/ZipException
     140: dup
     141: ldc           #142                // String broken archive, entry with negative compressed size
     143: invokespecial #56                 // Method java/util/zip/ZipException."<init>":(Ljava/lang/String;)V
     146: athrow
     147: aload_0
     148: getfield      #3                  // Field current:Lorg/apache/commons/compress/archivers/zip/ZipArchiveInputStream$CurrentEntry;
     151: invokestatic  #60                 // Method org/apache/commons/compress/archivers/zip/ZipArchiveInputStream$CurrentEntry.access$100:(Lorg/apache/commons/compress/archivers/zip/ZipArchiveInputStream$CurrentEntry;)Lorg/apache/commons/compress/archivers/zip/ZipArchiveEntry;
     154: lload         5
     156: invokevirtual #143                // Method org/apache/commons/compress/archivers/zip/ZipArchiveEntry.setCompressedSize:(J)V
     159: aload         4
     161: invokevirtual #139                // Method org/apache/commons/compress/archivers/zip/Zip64ExtendedInformationExtraField.getSize:()Lorg/apache/commons/compress/archivers/zip/ZipEightByteInteger;
     164: invokevirtual #141                // Method org/apache/commons/compress/archivers/zip/ZipEightByteInteger.getLongValue:()J
     167: lstore        5
     169: lload         5
     171: lconst_0
     172: lcmp
     173: ifge          186
     176: new           #50                 // class java/util/zip/ZipException
     179: dup
     180: ldc           #144                // String broken archive, entry with negative size
     182: invokespecial #56                 // Method java/util/zip/ZipException."<init>":(Ljava/lang/String;)V
     185: athrow
     186: aload_0
     187: getfield      #3                  // Field current:Lorg/apache/commons/compress/archivers/zip/ZipArchiveInputStream$CurrentEntry;
     190: invokestatic  #60                 // Method org/apache/commons/compress/archivers/zip/ZipArchiveInputStream$CurrentEntry.access$100:(Lorg/apache/commons/compress/archivers/zip/ZipArchiveInputStream$CurrentEntry;)Lorg/apache/commons/compress/archivers/zip/ZipArchiveEntry;
     193: lload         5
     195: invokevirtual #145                // Method org/apache/commons/compress/archivers/zip/ZipArchiveEntry.setSize:(J)V
     198: goto          275
     201: aload_2
     202: ifnull        275
     205: aload_1
     206: ifnull        275
     209: aload_2
     210: invokevirtual #53                 // Method org/apache/commons/compress/archivers/zip/ZipLong.getValue:()J
     213: lconst_0
     214: lcmp
     215: ifge          228
     218: new           #50                 // class java/util/zip/ZipException
     221: dup
     222: ldc           #142                // String broken archive, entry with negative compressed size
     224: invokespecial #56                 // Method java/util/zip/ZipException."<init>":(Ljava/lang/String;)V
     227: athrow
     228: aload_0
     229: getfield      #3                  // Field current:Lorg/apache/commons/compress/archivers/zip/ZipArchiveInputStream$CurrentEntry;
     232: invokestatic  #60                 // Method org/apache/commons/compress/archivers/zip/ZipArchiveInputStream$CurrentEntry.access$100:(Lorg/apache/commons/compress/archivers/zip/ZipArchiveInputStream$CurrentEntry;)Lorg/apache/commons/compress/archivers/zip/ZipArchiveEntry;
     235: aload_2
     236: invokevirtual #53                 // Method org/apache/commons/compress/archivers/zip/ZipLong.getValue:()J
     239: invokevirtual #143                // Method org/apache/commons/compress/archivers/zip/ZipArchiveEntry.setCompressedSize:(J)V
     242: aload_1
     243: invokevirtual #53                 // Method org/apache/commons/compress/archivers/zip/ZipLong.getValue:()J
     246: lconst_0
     247: lcmp
     248: ifge          261
     251: new           #50                 // class java/util/zip/ZipException
     254: dup
     255: ldc           #144                // String broken archive, entry with negative size
     257: invokespecial #56                 // Method java/util/zip/ZipException."<init>":(Ljava/lang/String;)V
     260: athrow
     261: aload_0
     262: getfield      #3                  // Field current:Lorg/apache/commons/compress/archivers/zip/ZipArchiveInputStream$CurrentEntry;
     265: invokestatic  #60                 // Method org/apache/commons/compress/archivers/zip/ZipArchiveInputStream$CurrentEntry.access$100:(Lorg/apache/commons/compress/archivers/zip/ZipArchiveInputStream$CurrentEntry;)Lorg/apache/commons/compress/archivers/zip/ZipArchiveEntry;
     268: aload_1
     269: invokevirtual #53                 // Method org/apache/commons/compress/archivers/zip/ZipLong.getValue:()J
     272: invokevirtual #145                // Method org/apache/commons/compress/archivers/zip/ZipArchiveEntry.setSize:(J)V
     275: return

  public org.apache.commons.compress.archivers.ArchiveEntry getNextEntry() throws java.io.IOException;
    Code:
       0: aload_0
       1: invokevirtual #146                // Method getNextZipEntry:()Lorg/apache/commons/compress/archivers/zip/ZipArchiveEntry;
       4: areturn

  public boolean canReadEntryData(org.apache.commons.compress.archivers.ArchiveEntry);
    Code:
       0: aload_1
       1: instanceof    #147                // class org/apache/commons/compress/archivers/zip/ZipArchiveEntry
       4: ifeq          41
       7: aload_1
       8: checkcast     #147                // class org/apache/commons/compress/archivers/zip/ZipArchiveEntry
      11: astore_2
      12: aload_2
      13: invokestatic  #101                // Method org/apache/commons/compress/archivers/zip/ZipUtil.canHandleEntryData:(Lorg/apache/commons/compress/archivers/zip/ZipArchiveEntry;)Z
      16: ifeq          39
      19: aload_0
      20: aload_2
      21: invokespecial #148                // Method supportsDataDescriptorFor:(Lorg/apache/commons/compress/archivers/zip/ZipArchiveEntry;)Z
      24: ifeq          39
      27: aload_0
      28: aload_2
      29: invokespecial #149                // Method supportsCompressedSizeFor:(Lorg/apache/commons/compress/archivers/zip/ZipArchiveEntry;)Z
      32: ifeq          39
      35: iconst_1
      36: goto          40
      39: iconst_0
      40: ireturn
      41: iconst_0
      42: ireturn

  public int read(byte[], int, int) throws java.io.IOException;
    Code:
       0: iload_3
       1: ifne          6
       4: iconst_0
       5: ireturn
       6: aload_0
       7: getfield      #35                 // Field closed:Z
      10: ifeq          23
      13: new           #117                // class java/io/IOException
      16: dup
      17: ldc           #150                // String The stream is closed
      19: invokespecial #151                // Method java/io/IOException."<init>":(Ljava/lang/String;)V
      22: athrow
      23: aload_0
      24: getfield      #3                  // Field current:Lorg/apache/commons/compress/archivers/zip/ZipArchiveInputStream$CurrentEntry;
      27: ifnonnull     32
      30: iconst_m1
      31: ireturn
      32: iload_2
      33: aload_1
      34: arraylength
      35: if_icmpgt     54
      38: iload_3
      39: iflt          54
      42: iload_2
      43: iflt          54
      46: aload_1
      47: arraylength
      48: iload_2
      49: isub
      50: iload_3
      51: if_icmpge     62
      54: new           #152                // class java/lang/ArrayIndexOutOfBoundsException
      57: dup
      58: invokespecial #153                // Method java/lang/ArrayIndexOutOfBoundsException."<init>":()V
      61: athrow
      62: aload_0
      63: getfield      #3                  // Field current:Lorg/apache/commons/compress/archivers/zip/ZipArchiveInputStream$CurrentEntry;
      66: invokestatic  #60                 // Method org/apache/commons/compress/archivers/zip/ZipArchiveInputStream$CurrentEntry.access$100:(Lorg/apache/commons/compress/archivers/zip/ZipArchiveInputStream$CurrentEntry;)Lorg/apache/commons/compress/archivers/zip/ZipArchiveEntry;
      69: invokestatic  #154                // Method org/apache/commons/compress/archivers/zip/ZipUtil.checkRequestedFeatures:(Lorg/apache/commons/compress/archivers/zip/ZipArchiveEntry;)V
      72: aload_0
      73: aload_0
      74: getfield      #3                  // Field current:Lorg/apache/commons/compress/archivers/zip/ZipArchiveInputStream$CurrentEntry;
      77: invokestatic  #60                 // Method org/apache/commons/compress/archivers/zip/ZipArchiveInputStream$CurrentEntry.access$100:(Lorg/apache/commons/compress/archivers/zip/ZipArchiveInputStream$CurrentEntry;)Lorg/apache/commons/compress/archivers/zip/ZipArchiveEntry;
      80: invokespecial #148                // Method supportsDataDescriptorFor:(Lorg/apache/commons/compress/archivers/zip/ZipArchiveEntry;)Z
      83: ifne          104
      86: new           #127                // class org/apache/commons/compress/archivers/zip/UnsupportedZipFeatureException
      89: dup
      90: getstatic     #155                // Field org/apache/commons/compress/archivers/zip/UnsupportedZipFeatureException$Feature.DATA_DESCRIPTOR:Lorg/apache/commons/compress/archivers/zip/UnsupportedZipFeatureException$Feature;
      93: aload_0
      94: getfield      #3                  // Field current:Lorg/apache/commons/compress/archivers/zip/ZipArchiveInputStream$CurrentEntry;
      97: invokestatic  #60                 // Method org/apache/commons/compress/archivers/zip/ZipArchiveInputStream$CurrentEntry.access$100:(Lorg/apache/commons/compress/archivers/zip/ZipArchiveInputStream$CurrentEntry;)Lorg/apache/commons/compress/archivers/zip/ZipArchiveEntry;
     100: invokespecial #156                // Method org/apache/commons/compress/archivers/zip/UnsupportedZipFeatureException."<init>":(Lorg/apache/commons/compress/archivers/zip/UnsupportedZipFeatureException$Feature;Lorg/apache/commons/compress/archivers/zip/ZipArchiveEntry;)V
     103: athrow
     104: aload_0
     105: aload_0
     106: getfield      #3                  // Field current:Lorg/apache/commons/compress/archivers/zip/ZipArchiveInputStream$CurrentEntry;
     109: invokestatic  #60                 // Method org/apache/commons/compress/archivers/zip/ZipArchiveInputStream$CurrentEntry.access$100:(Lorg/apache/commons/compress/archivers/zip/ZipArchiveInputStream$CurrentEntry;)Lorg/apache/commons/compress/archivers/zip/ZipArchiveEntry;
     112: invokespecial #149                // Method supportsCompressedSizeFor:(Lorg/apache/commons/compress/archivers/zip/ZipArchiveEntry;)Z
     115: ifne          136
     118: new           #127                // class org/apache/commons/compress/archivers/zip/UnsupportedZipFeatureException
     121: dup
     122: getstatic     #157                // Field org/apache/commons/compress/archivers/zip/UnsupportedZipFeatureException$Feature.UNKNOWN_COMPRESSED_SIZE:Lorg/apache/commons/compress/archivers/zip/UnsupportedZipFeatureException$Feature;
     125: aload_0
     126: getfield      #3                  // Field current:Lorg/apache/commons/compress/archivers/zip/ZipArchiveInputStream$CurrentEntry;
     129: invokestatic  #60                 // Method org/apache/commons/compress/archivers/zip/ZipArchiveInputStream$CurrentEntry.access$100:(Lorg/apache/commons/compress/archivers/zip/ZipArchiveInputStream$CurrentEntry;)Lorg/apache/commons/compress/archivers/zip/ZipArchiveEntry;
     132: invokespecial #156                // Method org/apache/commons/compress/archivers/zip/UnsupportedZipFeatureException."<init>":(Lorg/apache/commons/compress/archivers/zip/UnsupportedZipFeatureException$Feature;Lorg/apache/commons/compress/archivers/zip/ZipArchiveEntry;)V
     135: athrow
     136: aload_0
     137: getfield      #3                  // Field current:Lorg/apache/commons/compress/archivers/zip/ZipArchiveInputStream$CurrentEntry;
     140: invokestatic  #60                 // Method org/apache/commons/compress/archivers/zip/ZipArchiveInputStream$CurrentEntry.access$100:(Lorg/apache/commons/compress/archivers/zip/ZipArchiveInputStream$CurrentEntry;)Lorg/apache/commons/compress/archivers/zip/ZipArchiveEntry;
     143: invokevirtual #95                 // Method org/apache/commons/compress/archivers/zip/ZipArchiveEntry.getMethod:()I
     146: ifne          161
     149: aload_0
     150: aload_1
     151: iload_2
     152: iload_3
     153: invokespecial #158                // Method readStored:([BII)I
     156: istore        4
     158: goto          310
     161: aload_0
     162: getfield      #3                  // Field current:Lorg/apache/commons/compress/archivers/zip/ZipArchiveInputStream$CurrentEntry;
     165: invokestatic  #60                 // Method org/apache/commons/compress/archivers/zip/ZipArchiveInputStream$CurrentEntry.access$100:(Lorg/apache/commons/compress/archivers/zip/ZipArchiveInputStream$CurrentEntry;)Lorg/apache/commons/compress/archivers/zip/ZipArchiveEntry;
     168: invokevirtual #95                 // Method org/apache/commons/compress/archivers/zip/ZipArchiveEntry.getMethod:()I
     171: bipush        8
     173: if_icmpne     188
     176: aload_0
     177: aload_1
     178: iload_2
     179: iload_3
     180: invokespecial #159                // Method readDeflated:([BII)I
     183: istore        4
     185: goto          310
     188: aload_0
     189: getfield      #3                  // Field current:Lorg/apache/commons/compress/archivers/zip/ZipArchiveInputStream$CurrentEntry;
     192: invokestatic  #60                 // Method org/apache/commons/compress/archivers/zip/ZipArchiveInputStream$CurrentEntry.access$100:(Lorg/apache/commons/compress/archivers/zip/ZipArchiveInputStream$CurrentEntry;)Lorg/apache/commons/compress/archivers/zip/ZipArchiveEntry;
     195: invokevirtual #95                 // Method org/apache/commons/compress/archivers/zip/ZipArchiveEntry.getMethod:()I
     198: getstatic     #160                // Field org/apache/commons/compress/archivers/zip/ZipMethod.UNSHRINKING:Lorg/apache/commons/compress/archivers/zip/ZipMethod;
     201: invokevirtual #161                // Method org/apache/commons/compress/archivers/zip/ZipMethod.getCode:()I
     204: if_icmpeq     264
     207: aload_0
     208: getfield      #3                  // Field current:Lorg/apache/commons/compress/archivers/zip/ZipArchiveInputStream$CurrentEntry;
     211: invokestatic  #60                 // Method org/apache/commons/compress/archivers/zip/ZipArchiveInputStream$CurrentEntry.access$100:(Lorg/apache/commons/compress/archivers/zip/ZipArchiveInputStream$CurrentEntry;)Lorg/apache/commons/compress/archivers/zip/ZipArchiveEntry;
     214: invokevirtual #95                 // Method org/apache/commons/compress/archivers/zip/ZipArchiveEntry.getMethod:()I
     217: getstatic     #162                // Field org/apache/commons/compress/archivers/zip/ZipMethod.IMPLODING:Lorg/apache/commons/compress/archivers/zip/ZipMethod;
     220: invokevirtual #161                // Method org/apache/commons/compress/archivers/zip/ZipMethod.getCode:()I
     223: if_icmpeq     264
     226: aload_0
     227: getfield      #3                  // Field current:Lorg/apache/commons/compress/archivers/zip/ZipArchiveInputStream$CurrentEntry;
     230: invokestatic  #60                 // Method org/apache/commons/compress/archivers/zip/ZipArchiveInputStream$CurrentEntry.access$100:(Lorg/apache/commons/compress/archivers/zip/ZipArchiveInputStream$CurrentEntry;)Lorg/apache/commons/compress/archivers/zip/ZipArchiveEntry;
     233: invokevirtual #95                 // Method org/apache/commons/compress/archivers/zip/ZipArchiveEntry.getMethod:()I
     236: getstatic     #124                // Field org/apache/commons/compress/archivers/zip/ZipMethod.ENHANCED_DEFLATED:Lorg/apache/commons/compress/archivers/zip/ZipMethod;
     239: invokevirtual #161                // Method org/apache/commons/compress/archivers/zip/ZipMethod.getCode:()I
     242: if_icmpeq     264
     245: aload_0
     246: getfield      #3                  // Field current:Lorg/apache/commons/compress/archivers/zip/ZipArchiveInputStream$CurrentEntry;
     249: invokestatic  #60                 // Method org/apache/commons/compress/archivers/zip/ZipArchiveInputStream$CurrentEntry.access$100:(Lorg/apache/commons/compress/archivers/zip/ZipArchiveInputStream$CurrentEntry;)Lorg/apache/commons/compress/archivers/zip/ZipArchiveEntry;
     252: invokevirtual #95                 // Method org/apache/commons/compress/archivers/zip/ZipArchiveEntry.getMethod:()I
     255: getstatic     #163                // Field org/apache/commons/compress/archivers/zip/ZipMethod.BZIP2:Lorg/apache/commons/compress/archivers/zip/ZipMethod;
     258: invokevirtual #161                // Method org/apache/commons/compress/archivers/zip/ZipMethod.getCode:()I
     261: if_icmpne     282
     264: aload_0
     265: getfield      #3                  // Field current:Lorg/apache/commons/compress/archivers/zip/ZipArchiveInputStream$CurrentEntry;
     268: invokestatic  #164                // Method org/apache/commons/compress/archivers/zip/ZipArchiveInputStream$CurrentEntry.access$300:(Lorg/apache/commons/compress/archivers/zip/ZipArchiveInputStream$CurrentEntry;)Ljava/io/InputStream;
     271: aload_1
     272: iload_2
     273: iload_3
     274: invokevirtual #165                // Method java/io/InputStream.read:([BII)I
     277: istore        4
     279: goto          310
     282: new           #127                // class org/apache/commons/compress/archivers/zip/UnsupportedZipFeatureException
     285: dup
     286: aload_0
     287: getfield      #3                  // Field current:Lorg/apache/commons/compress/archivers/zip/ZipArchiveInputStream$CurrentEntry;
     290: invokestatic  #60                 // Method org/apache/commons/compress/archivers/zip/ZipArchiveInputStream$CurrentEntry.access$100:(Lorg/apache/commons/compress/archivers/zip/ZipArchiveInputStream$CurrentEntry;)Lorg/apache/commons/compress/archivers/zip/ZipArchiveEntry;
     293: invokevirtual #95                 // Method org/apache/commons/compress/archivers/zip/ZipArchiveEntry.getMethod:()I
     296: invokestatic  #96                 // Method org/apache/commons/compress/archivers/zip/ZipMethod.getMethodByCode:(I)Lorg/apache/commons/compress/archivers/zip/ZipMethod;
     299: aload_0
     300: getfield      #3                  // Field current:Lorg/apache/commons/compress/archivers/zip/ZipArchiveInputStream$CurrentEntry;
     303: invokestatic  #60                 // Method org/apache/commons/compress/archivers/zip/ZipArchiveInputStream$CurrentEntry.access$100:(Lorg/apache/commons/compress/archivers/zip/ZipArchiveInputStream$CurrentEntry;)Lorg/apache/commons/compress/archivers/zip/ZipArchiveEntry;
     306: invokespecial #166                // Method org/apache/commons/compress/archivers/zip/UnsupportedZipFeatureException."<init>":(Lorg/apache/commons/compress/archivers/zip/ZipMethod;Lorg/apache/commons/compress/archivers/zip/ZipArchiveEntry;)V
     309: athrow
     310: iload         4
     312: iflt          341
     315: aload_0
     316: getfield      #3                  // Field current:Lorg/apache/commons/compress/archivers/zip/ZipArchiveInputStream$CurrentEntry;
     319: invokestatic  #167                // Method org/apache/commons/compress/archivers/zip/ZipArchiveInputStream$CurrentEntry.access$500:(Lorg/apache/commons/compress/archivers/zip/ZipArchiveInputStream$CurrentEntry;)Ljava/util/zip/CRC32;
     322: aload_1
     323: iload_2
     324: iload         4
     326: invokevirtual #168                // Method java/util/zip/CRC32.update:([BII)V
     329: aload_0
     330: dup
     331: getfield      #34                 // Field uncompressedCount:J
     334: iload         4
     336: i2l
     337: ladd
     338: putfield      #34                 // Field uncompressedCount:J
     341: iload         4
     343: ireturn

  public long getCompressedCount();
    Code:
       0: aload_0
       1: getfield      #3                  // Field current:Lorg/apache/commons/compress/archivers/zip/ZipArchiveInputStream$CurrentEntry;
       4: invokestatic  #60                 // Method org/apache/commons/compress/archivers/zip/ZipArchiveInputStream$CurrentEntry.access$100:(Lorg/apache/commons/compress/archivers/zip/ZipArchiveInputStream$CurrentEntry;)Lorg/apache/commons/compress/archivers/zip/ZipArchiveEntry;
       7: invokevirtual #95                 // Method org/apache/commons/compress/archivers/zip/ZipArchiveEntry.getMethod:()I
      10: ifne          21
      13: aload_0
      14: getfield      #3                  // Field current:Lorg/apache/commons/compress/archivers/zip/ZipArchiveInputStream$CurrentEntry;
      17: invokestatic  #169                // Method org/apache/commons/compress/archivers/zip/ZipArchiveInputStream$CurrentEntry.access$600:(Lorg/apache/commons/compress/archivers/zip/ZipArchiveInputStream$CurrentEntry;)J
      20: lreturn
      21: aload_0
      22: getfield      #3                  // Field current:Lorg/apache/commons/compress/archivers/zip/ZipArchiveInputStream$CurrentEntry;
      25: invokestatic  #60                 // Method org/apache/commons/compress/archivers/zip/ZipArchiveInputStream$CurrentEntry.access$100:(Lorg/apache/commons/compress/archivers/zip/ZipArchiveInputStream$CurrentEntry;)Lorg/apache/commons/compress/archivers/zip/ZipArchiveEntry;
      28: invokevirtual #95                 // Method org/apache/commons/compress/archivers/zip/ZipArchiveEntry.getMethod:()I
      31: bipush        8
      33: if_icmpne     41
      36: aload_0
      37: invokespecial #170                // Method getBytesInflated:()J
      40: lreturn
      41: aload_0
      42: getfield      #3                  // Field current:Lorg/apache/commons/compress/archivers/zip/ZipArchiveInputStream$CurrentEntry;
      45: invokestatic  #60                 // Method org/apache/commons/compress/archivers/zip/ZipArchiveInputStream$CurrentEntry.access$100:(Lorg/apache/commons/compress/archivers/zip/ZipArchiveInputStream$CurrentEntry;)Lorg/apache/commons/compress/archivers/zip/ZipArchiveEntry;
      48: invokevirtual #95                 // Method org/apache/commons/compress/archivers/zip/ZipArchiveEntry.getMethod:()I
      51: getstatic     #160                // Field org/apache/commons/compress/archivers/zip/ZipMethod.UNSHRINKING:Lorg/apache/commons/compress/archivers/zip/ZipMethod;
      54: invokevirtual #161                // Method org/apache/commons/compress/archivers/zip/ZipMethod.getCode:()I
      57: if_icmpne     74
      60: aload_0
      61: getfield      #3                  // Field current:Lorg/apache/commons/compress/archivers/zip/ZipArchiveInputStream$CurrentEntry;
      64: invokestatic  #164                // Method org/apache/commons/compress/archivers/zip/ZipArchiveInputStream$CurrentEntry.access$300:(Lorg/apache/commons/compress/archivers/zip/ZipArchiveInputStream$CurrentEntry;)Ljava/io/InputStream;
      67: checkcast     #108                // class org/apache/commons/compress/archivers/zip/UnshrinkingInputStream
      70: invokevirtual #171                // Method org/apache/commons/compress/archivers/zip/UnshrinkingInputStream.getCompressedCount:()J
      73: lreturn
      74: aload_0
      75: getfield      #3                  // Field current:Lorg/apache/commons/compress/archivers/zip/ZipArchiveInputStream$CurrentEntry;
      78: invokestatic  #60                 // Method org/apache/commons/compress/archivers/zip/ZipArchiveInputStream$CurrentEntry.access$100:(Lorg/apache/commons/compress/archivers/zip/ZipArchiveInputStream$CurrentEntry;)Lorg/apache/commons/compress/archivers/zip/ZipArchiveEntry;
      81: invokevirtual #95                 // Method org/apache/commons/compress/archivers/zip/ZipArchiveEntry.getMethod:()I
      84: getstatic     #162                // Field org/apache/commons/compress/archivers/zip/ZipMethod.IMPLODING:Lorg/apache/commons/compress/archivers/zip/ZipMethod;
      87: invokevirtual #161                // Method org/apache/commons/compress/archivers/zip/ZipMethod.getCode:()I
      90: if_icmpne     107
      93: aload_0
      94: getfield      #3                  // Field current:Lorg/apache/commons/compress/archivers/zip/ZipArchiveInputStream$CurrentEntry;
      97: invokestatic  #164                // Method org/apache/commons/compress/archivers/zip/ZipArchiveInputStream$CurrentEntry.access$300:(Lorg/apache/commons/compress/archivers/zip/ZipArchiveInputStream$CurrentEntry;)Ljava/io/InputStream;
     100: checkcast     #111                // class org/apache/commons/compress/archivers/zip/ExplodingInputStream
     103: invokevirtual #172                // Method org/apache/commons/compress/archivers/zip/ExplodingInputStream.getCompressedCount:()J
     106: lreturn
     107: aload_0
     108: getfield      #3                  // Field current:Lorg/apache/commons/compress/archivers/zip/ZipArchiveInputStream$CurrentEntry;
     111: invokestatic  #60                 // Method org/apache/commons/compress/archivers/zip/ZipArchiveInputStream$CurrentEntry.access$100:(Lorg/apache/commons/compress/archivers/zip/ZipArchiveInputStream$CurrentEntry;)Lorg/apache/commons/compress/archivers/zip/ZipArchiveEntry;
     114: invokevirtual #95                 // Method org/apache/commons/compress/archivers/zip/ZipArchiveEntry.getMethod:()I
     117: getstatic     #124                // Field org/apache/commons/compress/archivers/zip/ZipMethod.ENHANCED_DEFLATED:Lorg/apache/commons/compress/archivers/zip/ZipMethod;
     120: invokevirtual #161                // Method org/apache/commons/compress/archivers/zip/ZipMethod.getCode:()I
     123: if_icmpne     140
     126: aload_0
     127: getfield      #3                  // Field current:Lorg/apache/commons/compress/archivers/zip/ZipArchiveInputStream$CurrentEntry;
     130: invokestatic  #164                // Method org/apache/commons/compress/archivers/zip/ZipArchiveInputStream$CurrentEntry.access$300:(Lorg/apache/commons/compress/archivers/zip/ZipArchiveInputStream$CurrentEntry;)Ljava/io/InputStream;
     133: checkcast     #122                // class org/apache/commons/compress/compressors/deflate64/Deflate64CompressorInputStream
     136: invokevirtual #173                // Method org/apache/commons/compress/compressors/deflate64/Deflate64CompressorInputStream.getCompressedCount:()J
     139: lreturn
     140: aload_0
     141: getfield      #3                  // Field current:Lorg/apache/commons/compress/archivers/zip/ZipArchiveInputStream$CurrentEntry;
     144: invokestatic  #60                 // Method org/apache/commons/compress/archivers/zip/ZipArchiveInputStream$CurrentEntry.access$100:(Lorg/apache/commons/compress/archivers/zip/ZipArchiveInputStream$CurrentEntry;)Lorg/apache/commons/compress/archivers/zip/ZipArchiveEntry;
     147: invokevirtual #95                 // Method org/apache/commons/compress/archivers/zip/ZipArchiveEntry.getMethod:()I
     150: getstatic     #163                // Field org/apache/commons/compress/archivers/zip/ZipMethod.BZIP2:Lorg/apache/commons/compress/archivers/zip/ZipMethod;
     153: invokevirtual #161                // Method org/apache/commons/compress/archivers/zip/ZipMethod.getCode:()I
     156: if_icmpne     173
     159: aload_0
     160: getfield      #3                  // Field current:Lorg/apache/commons/compress/archivers/zip/ZipArchiveInputStream$CurrentEntry;
     163: invokestatic  #164                // Method org/apache/commons/compress/archivers/zip/ZipArchiveInputStream$CurrentEntry.access$300:(Lorg/apache/commons/compress/archivers/zip/ZipArchiveInputStream$CurrentEntry;)Ljava/io/InputStream;
     166: checkcast     #120                // class org/apache/commons/compress/compressors/bzip2/BZip2CompressorInputStream
     169: invokevirtual #174                // Method org/apache/commons/compress/compressors/bzip2/BZip2CompressorInputStream.getCompressedCount:()J
     172: lreturn
     173: ldc2_w        #99                 // long -1l
     176: lreturn

  public long getUncompressedCount();
    Code:
       0: aload_0
       1: getfield      #34                 // Field uncompressedCount:J
       4: lreturn

  private int readStored(byte[], int, int) throws java.io.IOException;
    Code:
       0: aload_0
       1: getfield      #3                  // Field current:Lorg/apache/commons/compress/archivers/zip/ZipArchiveInputStream$CurrentEntry;
       4: invokestatic  #73                 // Method org/apache/commons/compress/archivers/zip/ZipArchiveInputStream$CurrentEntry.access$200:(Lorg/apache/commons/compress/archivers/zip/ZipArchiveInputStream$CurrentEntry;)Z
       7: ifeq          32
      10: aload_0
      11: getfield      #175                // Field lastStoredEntry:Ljava/io/ByteArrayInputStream;
      14: ifnonnull     21
      17: aload_0
      18: invokespecial #176                // Method readStoredEntry:()V
      21: aload_0
      22: getfield      #175                // Field lastStoredEntry:Ljava/io/ByteArrayInputStream;
      25: aload_1
      26: iload_2
      27: iload_3
      28: invokevirtual #177                // Method java/io/ByteArrayInputStream.read:([BII)I
      31: ireturn
      32: aload_0
      33: getfield      #3                  // Field current:Lorg/apache/commons/compress/archivers/zip/ZipArchiveInputStream$CurrentEntry;
      36: invokestatic  #60                 // Method org/apache/commons/compress/archivers/zip/ZipArchiveInputStream$CurrentEntry.access$100:(Lorg/apache/commons/compress/archivers/zip/ZipArchiveInputStream$CurrentEntry;)Lorg/apache/commons/compress/archivers/zip/ZipArchiveEntry;
      39: invokevirtual #178                // Method org/apache/commons/compress/archivers/zip/ZipArchiveEntry.getSize:()J
      42: lstore        4
      44: aload_0
      45: getfield      #3                  // Field current:Lorg/apache/commons/compress/archivers/zip/ZipArchiveInputStream$CurrentEntry;
      48: invokestatic  #169                // Method org/apache/commons/compress/archivers/zip/ZipArchiveInputStream$CurrentEntry.access$600:(Lorg/apache/commons/compress/archivers/zip/ZipArchiveInputStream$CurrentEntry;)J
      51: lload         4
      53: lcmp
      54: iflt          59
      57: iconst_m1
      58: ireturn
      59: aload_0
      60: getfield      #16                 // Field buf:Ljava/nio/ByteBuffer;
      63: invokevirtual #179                // Method java/nio/ByteBuffer.position:()I
      66: aload_0
      67: getfield      #16                 // Field buf:Ljava/nio/ByteBuffer;
      70: invokevirtual #180                // Method java/nio/ByteBuffer.limit:()I
      73: if_icmplt     163
      76: aload_0
      77: getfield      #16                 // Field buf:Ljava/nio/ByteBuffer;
      80: iconst_0
      81: invokevirtual #181                // Method java/nio/ByteBuffer.position:(I)Ljava/nio/Buffer;
      84: pop
      85: aload_0
      86: getfield      #30                 // Field in:Ljava/io/InputStream;
      89: aload_0
      90: getfield      #16                 // Field buf:Ljava/nio/ByteBuffer;
      93: invokevirtual #182                // Method java/nio/ByteBuffer.array:()[B
      96: invokevirtual #183                // Method java/io/InputStream.read:([B)I
      99: istore        6
     101: iload         6
     103: iconst_m1
     104: if_icmpne     126
     107: aload_0
     108: getfield      #16                 // Field buf:Ljava/nio/ByteBuffer;
     111: iconst_0
     112: invokevirtual #33                 // Method java/nio/ByteBuffer.limit:(I)Ljava/nio/Buffer;
     115: pop
     116: new           #117                // class java/io/IOException
     119: dup
     120: ldc           #184                // String Truncated ZIP file
     122: invokespecial #151                // Method java/io/IOException."<init>":(Ljava/lang/String;)V
     125: athrow
     126: aload_0
     127: getfield      #16                 // Field buf:Ljava/nio/ByteBuffer;
     130: iload         6
     132: invokevirtual #33                 // Method java/nio/ByteBuffer.limit:(I)Ljava/nio/Buffer;
     135: pop
     136: aload_0
     137: iload         6
     139: invokevirtual #2                  // Method count:(I)V
     142: aload_0
     143: getfield      #3                  // Field current:Lorg/apache/commons/compress/archivers/zip/ZipArchiveInputStream$CurrentEntry;
     146: astore        7
     148: aload         7
     150: aload         7
     152: invokestatic  #185                // Method org/apache/commons/compress/archivers/zip/ZipArchiveInputStream$CurrentEntry.access$700:(Lorg/apache/commons/compress/archivers/zip/ZipArchiveInputStream$CurrentEntry;)J
     155: iload         6
     157: i2l
     158: ladd
     159: invokestatic  #186                // Method org/apache/commons/compress/archivers/zip/ZipArchiveInputStream$CurrentEntry.access$702:(Lorg/apache/commons/compress/archivers/zip/ZipArchiveInputStream$CurrentEntry;J)J
     162: pop2
     163: aload_0
     164: getfield      #16                 // Field buf:Ljava/nio/ByteBuffer;
     167: invokevirtual #187                // Method java/nio/ByteBuffer.remaining:()I
     170: iload_3
     171: invokestatic  #188                // Method java/lang/Math.min:(II)I
     174: istore        6
     176: lload         4
     178: aload_0
     179: getfield      #3                  // Field current:Lorg/apache/commons/compress/archivers/zip/ZipArchiveInputStream$CurrentEntry;
     182: invokestatic  #169                // Method org/apache/commons/compress/archivers/zip/ZipArchiveInputStream$CurrentEntry.access$600:(Lorg/apache/commons/compress/archivers/zip/ZipArchiveInputStream$CurrentEntry;)J
     185: lsub
     186: iload         6
     188: i2l
     189: lcmp
     190: ifge          206
     193: lload         4
     195: aload_0
     196: getfield      #3                  // Field current:Lorg/apache/commons/compress/archivers/zip/ZipArchiveInputStream$CurrentEntry;
     199: invokestatic  #169                // Method org/apache/commons/compress/archivers/zip/ZipArchiveInputStream$CurrentEntry.access$600:(Lorg/apache/commons/compress/archivers/zip/ZipArchiveInputStream$CurrentEntry;)J
     202: lsub
     203: l2i
     204: istore        6
     206: aload_0
     207: getfield      #16                 // Field buf:Ljava/nio/ByteBuffer;
     210: aload_1
     211: iload_2
     212: iload         6
     214: invokevirtual #189                // Method java/nio/ByteBuffer.get:([BII)Ljava/nio/ByteBuffer;
     217: pop
     218: aload_0
     219: getfield      #3                  // Field current:Lorg/apache/commons/compress/archivers/zip/ZipArchiveInputStream$CurrentEntry;
     222: astore        7
     224: aload         7
     226: aload         7
     228: invokestatic  #169                // Method org/apache/commons/compress/archivers/zip/ZipArchiveInputStream$CurrentEntry.access$600:(Lorg/apache/commons/compress/archivers/zip/ZipArchiveInputStream$CurrentEntry;)J
     231: iload         6
     233: i2l
     234: ladd
     235: invokestatic  #190                // Method org/apache/commons/compress/archivers/zip/ZipArchiveInputStream$CurrentEntry.access$602:(Lorg/apache/commons/compress/archivers/zip/ZipArchiveInputStream$CurrentEntry;J)J
     238: pop2
     239: iload         6
     241: ireturn

  private int readDeflated(byte[], int, int) throws java.io.IOException;
    Code:
       0: aload_0
       1: aload_1
       2: iload_2
       3: iload_3
       4: invokespecial #191                // Method readFromInflater:([BII)I
       7: istore        4
       9: iload         4
      11: ifgt          62
      14: aload_0
      15: getfield      #13                 // Field inf:Ljava/util/zip/Inflater;
      18: invokevirtual #192                // Method java/util/zip/Inflater.finished:()Z
      21: ifeq          26
      24: iconst_m1
      25: ireturn
      26: aload_0
      27: getfield      #13                 // Field inf:Ljava/util/zip/Inflater;
      30: invokevirtual #193                // Method java/util/zip/Inflater.needsDictionary:()Z
      33: ifeq          46
      36: new           #50                 // class java/util/zip/ZipException
      39: dup
      40: ldc           #194                // String This archive needs a preset dictionary which is not supported by Commons Compress.
      42: invokespecial #56                 // Method java/util/zip/ZipException."<init>":(Ljava/lang/String;)V
      45: athrow
      46: iload         4
      48: iconst_m1
      49: if_icmpne     62
      52: new           #117                // class java/io/IOException
      55: dup
      56: ldc           #184                // String Truncated ZIP file
      58: invokespecial #151                // Method java/io/IOException."<init>":(Ljava/lang/String;)V
      61: athrow
      62: iload         4
      64: ireturn

  private int readFromInflater(byte[], int, int) throws java.io.IOException;
    Code:
       0: iconst_0
       1: istore        4
       3: aload_0
       4: getfield      #13                 // Field inf:Ljava/util/zip/Inflater;
       7: invokevirtual #195                // Method java/util/zip/Inflater.needsInput:()Z
      10: ifeq          61
      13: aload_0
      14: invokespecial #196                // Method fill:()I
      17: istore        5
      19: iload         5
      21: ifle          53
      24: aload_0
      25: getfield      #3                  // Field current:Lorg/apache/commons/compress/archivers/zip/ZipArchiveInputStream$CurrentEntry;
      28: astore        6
      30: aload         6
      32: aload         6
      34: invokestatic  #185                // Method org/apache/commons/compress/archivers/zip/ZipArchiveInputStream$CurrentEntry.access$700:(Lorg/apache/commons/compress/archivers/zip/ZipArchiveInputStream$CurrentEntry;)J
      37: aload_0
      38: getfield      #16                 // Field buf:Ljava/nio/ByteBuffer;
      41: invokevirtual #180                // Method java/nio/ByteBuffer.limit:()I
      44: i2l
      45: ladd
      46: invokestatic  #186                // Method org/apache/commons/compress/archivers/zip/ZipArchiveInputStream$CurrentEntry.access$702:(Lorg/apache/commons/compress/archivers/zip/ZipArchiveInputStream$CurrentEntry;J)J
      49: pop2
      50: goto          61
      53: iload         5
      55: iconst_m1
      56: if_icmpne     114
      59: iconst_m1
      60: ireturn
      61: aload_0
      62: getfield      #13                 // Field inf:Ljava/util/zip/Inflater;
      65: aload_1
      66: iload_2
      67: iload_3
      68: invokevirtual #197                // Method java/util/zip/Inflater.inflate:([BII)I
      71: istore        4
      73: goto          99
      76: astore        5
      78: new           #50                 // class java/util/zip/ZipException
      81: dup
      82: aload         5
      84: invokevirtual #199                // Method java/util/zip/DataFormatException.getMessage:()Ljava/lang/String;
      87: invokespecial #56                 // Method java/util/zip/ZipException."<init>":(Ljava/lang/String;)V
      90: aload         5
      92: invokevirtual #89                 // Method java/util/zip/ZipException.initCause:(Ljava/lang/Throwable;)Ljava/lang/Throwable;
      95: checkcast     #117                // class java/io/IOException
      98: athrow
      99: iload         4
     101: ifne          114
     104: aload_0
     105: getfield      #13                 // Field inf:Ljava/util/zip/Inflater;
     108: invokevirtual #195                // Method java/util/zip/Inflater.needsInput:()Z
     111: ifne          3
     114: iload         4
     116: ireturn
    Exception table:
       from    to  target type
          61    73    76   Class java/util/zip/DataFormatException

  public void close() throws java.io.IOException;
    Code:
       0: aload_0
       1: getfield      #35                 // Field closed:Z
       4: ifne          39
       7: aload_0
       8: iconst_1
       9: putfield      #35                 // Field closed:Z
      12: aload_0
      13: getfield      #30                 // Field in:Ljava/io/InputStream;
      16: invokevirtual #200                // Method java/io/InputStream.close:()V
      19: aload_0
      20: getfield      #13                 // Field inf:Ljava/util/zip/Inflater;
      23: invokevirtual #201                // Method java/util/zip/Inflater.end:()V
      26: goto          39
      29: astore_1
      30: aload_0
      31: getfield      #13                 // Field inf:Ljava/util/zip/Inflater;
      34: invokevirtual #201                // Method java/util/zip/Inflater.end:()V
      37: aload_1
      38: athrow
      39: return
    Exception table:
       from    to  target type
          12    19    29   any

  public long skip(long) throws java.io.IOException;
    Code:
       0: lload_1
       1: lconst_0
       2: lcmp
       3: iflt          73
       6: lconst_0
       7: lstore_3
       8: lload_3
       9: lload_1
      10: lcmp
      11: ifge          71
      14: lload_1
      15: lload_3
      16: lsub
      17: lstore        5
      19: aload_0
      20: aload_0
      21: getfield      #19                 // Field skipBuf:[B
      24: iconst_0
      25: aload_0
      26: getfield      #19                 // Field skipBuf:[B
      29: arraylength
      30: i2l
      31: lload         5
      33: lcmp
      34: ifle          42
      37: lload         5
      39: goto          48
      42: aload_0
      43: getfield      #19                 // Field skipBuf:[B
      46: arraylength
      47: i2l
      48: l2i
      49: invokevirtual #202                // Method read:([BII)I
      52: istore        7
      54: iload         7
      56: iconst_m1
      57: if_icmpne     62
      60: lload_3
      61: lreturn
      62: lload_3
      63: iload         7
      65: i2l
      66: ladd
      67: lstore_3
      68: goto          8
      71: lload_3
      72: lreturn
      73: new           #116                // class java/lang/IllegalArgumentException
      76: dup
      77: invokespecial #203                // Method java/lang/IllegalArgumentException."<init>":()V
      80: athrow

  public static boolean matches(byte[], int);
    Code:
       0: iload_1
       1: getstatic     #204                // Field org/apache/commons/compress/archivers/zip/ZipArchiveOutputStream.LFH_SIG:[B
       4: arraylength
       5: if_icmpge     10
       8: iconst_0
       9: ireturn
      10: aload_0
      11: getstatic     #204                // Field org/apache/commons/compress/archivers/zip/ZipArchiveOutputStream.LFH_SIG:[B
      14: invokestatic  #205                // Method checksig:([B[B)Z
      17: ifne          53
      20: aload_0
      21: getstatic     #206                // Field org/apache/commons/compress/archivers/zip/ZipArchiveOutputStream.EOCD_SIG:[B
      24: invokestatic  #205                // Method checksig:([B[B)Z
      27: ifne          53
      30: aload_0
      31: getstatic     #207                // Field org/apache/commons/compress/archivers/zip/ZipArchiveOutputStream.DD_SIG:[B
      34: invokestatic  #205                // Method checksig:([B[B)Z
      37: ifne          53
      40: aload_0
      41: getstatic     #130                // Field org/apache/commons/compress/archivers/zip/ZipLong.SINGLE_SEGMENT_SPLIT_MARKER:Lorg/apache/commons/compress/archivers/zip/ZipLong;
      44: invokevirtual #208                // Method org/apache/commons/compress/archivers/zip/ZipLong.getBytes:()[B
      47: invokestatic  #205                // Method checksig:([B[B)Z
      50: ifeq          57
      53: iconst_1
      54: goto          58
      57: iconst_0
      58: ireturn

  private static boolean checksig(byte[], byte[]);
    Code:
       0: iconst_0
       1: istore_2
       2: iload_2
       3: aload_1
       4: arraylength
       5: if_icmpge     25
       8: aload_0
       9: iload_2
      10: baload
      11: aload_1
      12: iload_2
      13: baload
      14: if_icmpeq     19
      17: iconst_0
      18: ireturn
      19: iinc          2, 1
      22: goto          2
      25: iconst_1
      26: ireturn

  private void closeEntry() throws java.io.IOException;
    Code:
       0: aload_0
       1: getfield      #35                 // Field closed:Z
       4: ifeq          17
       7: new           #117                // class java/io/IOException
      10: dup
      11: ldc           #150                // String The stream is closed
      13: invokespecial #151                // Method java/io/IOException."<init>":(Ljava/lang/String;)V
      16: athrow
      17: aload_0
      18: getfield      #3                  // Field current:Lorg/apache/commons/compress/archivers/zip/ZipArchiveInputStream$CurrentEntry;
      21: ifnonnull     25
      24: return
      25: aload_0
      26: invokespecial #209                // Method currentEntryHasOutstandingBytes:()Z
      29: ifeq          39
      32: aload_0
      33: invokespecial #210                // Method drainCurrentEntryData:()V
      36: goto          144
      39: aload_0
      40: ldc2_w        #212                // long 9223372036854775807l
      43: invokevirtual #214                // Method skip:(J)J
      46: pop2
      47: aload_0
      48: getfield      #3                  // Field current:Lorg/apache/commons/compress/archivers/zip/ZipArchiveInputStream$CurrentEntry;
      51: invokestatic  #60                 // Method org/apache/commons/compress/archivers/zip/ZipArchiveInputStream$CurrentEntry.access$100:(Lorg/apache/commons/compress/archivers/zip/ZipArchiveInputStream$CurrentEntry;)Lorg/apache/commons/compress/archivers/zip/ZipArchiveEntry;
      54: invokevirtual #95                 // Method org/apache/commons/compress/archivers/zip/ZipArchiveEntry.getMethod:()I
      57: bipush        8
      59: if_icmpne     69
      62: aload_0
      63: invokespecial #170                // Method getBytesInflated:()J
      66: goto          76
      69: aload_0
      70: getfield      #3                  // Field current:Lorg/apache/commons/compress/archivers/zip/ZipArchiveInputStream$CurrentEntry;
      73: invokestatic  #169                // Method org/apache/commons/compress/archivers/zip/ZipArchiveInputStream$CurrentEntry.access$600:(Lorg/apache/commons/compress/archivers/zip/ZipArchiveInputStream$CurrentEntry;)J
      76: lstore_1
      77: aload_0
      78: getfield      #3                  // Field current:Lorg/apache/commons/compress/archivers/zip/ZipArchiveInputStream$CurrentEntry;
      81: invokestatic  #185                // Method org/apache/commons/compress/archivers/zip/ZipArchiveInputStream$CurrentEntry.access$700:(Lorg/apache/commons/compress/archivers/zip/ZipArchiveInputStream$CurrentEntry;)J
      84: lload_1
      85: lsub
      86: l2i
      87: istore_3
      88: iload_3
      89: ifle          133
      92: aload_0
      93: aload_0
      94: getfield      #16                 // Field buf:Ljava/nio/ByteBuffer;
      97: invokevirtual #182                // Method java/nio/ByteBuffer.array:()[B
     100: aload_0
     101: getfield      #16                 // Field buf:Ljava/nio/ByteBuffer;
     104: invokevirtual #180                // Method java/nio/ByteBuffer.limit:()I
     107: iload_3
     108: isub
     109: iload_3
     110: invokespecial #215                // Method pushback:([BII)V
     113: aload_0
     114: getfield      #3                  // Field current:Lorg/apache/commons/compress/archivers/zip/ZipArchiveInputStream$CurrentEntry;
     117: astore        4
     119: aload         4
     121: aload         4
     123: invokestatic  #185                // Method org/apache/commons/compress/archivers/zip/ZipArchiveInputStream$CurrentEntry.access$700:(Lorg/apache/commons/compress/archivers/zip/ZipArchiveInputStream$CurrentEntry;)J
     126: iload_3
     127: i2l
     128: lsub
     129: invokestatic  #186                // Method org/apache/commons/compress/archivers/zip/ZipArchiveInputStream$CurrentEntry.access$702:(Lorg/apache/commons/compress/archivers/zip/ZipArchiveInputStream$CurrentEntry;J)J
     132: pop2
     133: aload_0
     134: invokespecial #209                // Method currentEntryHasOutstandingBytes:()Z
     137: ifeq          144
     140: aload_0
     141: invokespecial #210                // Method drainCurrentEntryData:()V
     144: aload_0
     145: getfield      #175                // Field lastStoredEntry:Ljava/io/ByteArrayInputStream;
     148: ifnonnull     165
     151: aload_0
     152: getfield      #3                  // Field current:Lorg/apache/commons/compress/archivers/zip/ZipArchiveInputStream$CurrentEntry;
     155: invokestatic  #73                 // Method org/apache/commons/compress/archivers/zip/ZipArchiveInputStream$CurrentEntry.access$200:(Lorg/apache/commons/compress/archivers/zip/ZipArchiveInputStream$CurrentEntry;)Z
     158: ifeq          165
     161: aload_0
     162: invokespecial #216                // Method readDataDescriptor:()V
     165: aload_0
     166: getfield      #13                 // Field inf:Ljava/util/zip/Inflater;
     169: invokevirtual #217                // Method java/util/zip/Inflater.reset:()V
     172: aload_0
     173: getfield      #16                 // Field buf:Ljava/nio/ByteBuffer;
     176: invokevirtual #218                // Method java/nio/ByteBuffer.clear:()Ljava/nio/Buffer;
     179: invokevirtual #219                // Method java/nio/Buffer.flip:()Ljava/nio/Buffer;
     182: pop
     183: aload_0
     184: aconst_null
     185: putfield      #3                  // Field current:Lorg/apache/commons/compress/archivers/zip/ZipArchiveInputStream$CurrentEntry;
     188: aload_0
     189: aconst_null
     190: putfield      #175                // Field lastStoredEntry:Ljava/io/ByteArrayInputStream;
     193: return

  private boolean currentEntryHasOutstandingBytes();
    Code:
       0: aload_0
       1: getfield      #3                  // Field current:Lorg/apache/commons/compress/archivers/zip/ZipArchiveInputStream$CurrentEntry;
       4: invokestatic  #185                // Method org/apache/commons/compress/archivers/zip/ZipArchiveInputStream$CurrentEntry.access$700:(Lorg/apache/commons/compress/archivers/zip/ZipArchiveInputStream$CurrentEntry;)J
       7: aload_0
       8: getfield      #3                  // Field current:Lorg/apache/commons/compress/archivers/zip/ZipArchiveInputStream$CurrentEntry;
      11: invokestatic  #60                 // Method org/apache/commons/compress/archivers/zip/ZipArchiveInputStream$CurrentEntry.access$100:(Lorg/apache/commons/compress/archivers/zip/ZipArchiveInputStream$CurrentEntry;)Lorg/apache/commons/compress/archivers/zip/ZipArchiveEntry;
      14: invokevirtual #97                 // Method org/apache/commons/compress/archivers/zip/ZipArchiveEntry.getCompressedSize:()J
      17: lcmp
      18: ifgt          35
      21: aload_0
      22: getfield      #3                  // Field current:Lorg/apache/commons/compress/archivers/zip/ZipArchiveInputStream$CurrentEntry;
      25: invokestatic  #73                 // Method org/apache/commons/compress/archivers/zip/ZipArchiveInputStream$CurrentEntry.access$200:(Lorg/apache/commons/compress/archivers/zip/ZipArchiveInputStream$CurrentEntry;)Z
      28: ifne          35
      31: iconst_1
      32: goto          36
      35: iconst_0
      36: ireturn

  private void drainCurrentEntryData() throws java.io.IOException;
    Code:
       0: aload_0
       1: getfield      #3                  // Field current:Lorg/apache/commons/compress/archivers/zip/ZipArchiveInputStream$CurrentEntry;
       4: invokestatic  #60                 // Method org/apache/commons/compress/archivers/zip/ZipArchiveInputStream$CurrentEntry.access$100:(Lorg/apache/commons/compress/archivers/zip/ZipArchiveInputStream$CurrentEntry;)Lorg/apache/commons/compress/archivers/zip/ZipArchiveEntry;
       7: invokevirtual #97                 // Method org/apache/commons/compress/archivers/zip/ZipArchiveEntry.getCompressedSize:()J
      10: aload_0
      11: getfield      #3                  // Field current:Lorg/apache/commons/compress/archivers/zip/ZipArchiveInputStream$CurrentEntry;
      14: invokestatic  #185                // Method org/apache/commons/compress/archivers/zip/ZipArchiveInputStream$CurrentEntry.access$700:(Lorg/apache/commons/compress/archivers/zip/ZipArchiveInputStream$CurrentEntry;)J
      17: lsub
      18: lstore_1
      19: lload_1
      20: lconst_0
      21: lcmp
      22: ifle          112
      25: aload_0
      26: getfield      #30                 // Field in:Ljava/io/InputStream;
      29: aload_0
      30: getfield      #16                 // Field buf:Ljava/nio/ByteBuffer;
      33: invokevirtual #182                // Method java/nio/ByteBuffer.array:()[B
      36: iconst_0
      37: aload_0
      38: getfield      #16                 // Field buf:Ljava/nio/ByteBuffer;
      41: invokevirtual #28                 // Method java/nio/ByteBuffer.capacity:()I
      44: i2l
      45: lload_1
      46: invokestatic  #220                // Method java/lang/Math.min:(JJ)J
      49: l2i
      50: invokevirtual #165                // Method java/io/InputStream.read:([BII)I
      53: i2l
      54: lstore_3
      55: lload_3
      56: lconst_0
      57: lcmp
      58: ifge          100
      61: new           #41                 // class java/io/EOFException
      64: dup
      65: new           #83                 // class java/lang/StringBuilder
      68: dup
      69: invokespecial #84                 // Method java/lang/StringBuilder."<init>":()V
      72: ldc           #221                // String Truncated ZIP entry:
      74: invokevirtual #86                 // Method java/lang/StringBuilder.append:(Ljava/lang/String;)Ljava/lang/StringBuilder;
      77: aload_0
      78: getfield      #3                  // Field current:Lorg/apache/commons/compress/archivers/zip/ZipArchiveInputStream$CurrentEntry;
      81: invokestatic  #60                 // Method org/apache/commons/compress/archivers/zip/ZipArchiveInputStream$CurrentEntry.access$100:(Lorg/apache/commons/compress/archivers/zip/ZipArchiveInputStream$CurrentEntry;)Lorg/apache/commons/compress/archivers/zip/ZipArchiveEntry;
      84: invokevirtual #87                 // Method org/apache/commons/compress/archivers/zip/ZipArchiveEntry.getName:()Ljava/lang/String;
      87: invokestatic  #222                // Method org/apache/commons/compress/utils/ArchiveUtils.sanitize:(Ljava/lang/String;)Ljava/lang/String;
      90: invokevirtual #86                 // Method java/lang/StringBuilder.append:(Ljava/lang/String;)Ljava/lang/StringBuilder;
      93: invokevirtual #88                 // Method java/lang/StringBuilder.toString:()Ljava/lang/String;
      96: invokespecial #223                // Method java/io/EOFException."<init>":(Ljava/lang/String;)V
      99: athrow
     100: aload_0
     101: lload_3
     102: invokevirtual #224                // Method count:(J)V
     105: lload_1
     106: lload_3
     107: lsub
     108: lstore_1
     109: goto          19
     112: return

  private long getBytesInflated();
    Code:
       0: aload_0
       1: getfield      #13                 // Field inf:Ljava/util/zip/Inflater;
       4: invokevirtual #225                // Method java/util/zip/Inflater.getBytesRead:()J
       7: lstore_1
       8: aload_0
       9: getfield      #3                  // Field current:Lorg/apache/commons/compress/archivers/zip/ZipArchiveInputStream$CurrentEntry;
      12: invokestatic  #185                // Method org/apache/commons/compress/archivers/zip/ZipArchiveInputStream$CurrentEntry.access$700:(Lorg/apache/commons/compress/archivers/zip/ZipArchiveInputStream$CurrentEntry;)J
      15: ldc2_w        #226                // long 4294967296l
      18: lcmp
      19: iflt          47
      22: lload_1
      23: ldc2_w        #226                // long 4294967296l
      26: ladd
      27: aload_0
      28: getfield      #3                  // Field current:Lorg/apache/commons/compress/archivers/zip/ZipArchiveInputStream$CurrentEntry;
      31: invokestatic  #185                // Method org/apache/commons/compress/archivers/zip/ZipArchiveInputStream$CurrentEntry.access$700:(Lorg/apache/commons/compress/archivers/zip/ZipArchiveInputStream$CurrentEntry;)J
      34: lcmp
      35: ifgt          47
      38: lload_1
      39: ldc2_w        #226                // long 4294967296l
      42: ladd
      43: lstore_1
      44: goto          22
      47: lload_1
      48: lreturn

  private int fill() throws java.io.IOException;
    Code:
       0: aload_0
       1: getfield      #35                 // Field closed:Z
       4: ifeq          17
       7: new           #117                // class java/io/IOException
      10: dup
      11: ldc           #150                // String The stream is closed
      13: invokespecial #151                // Method java/io/IOException."<init>":(Ljava/lang/String;)V
      16: athrow
      17: aload_0
      18: getfield      #30                 // Field in:Ljava/io/InputStream;
      21: aload_0
      22: getfield      #16                 // Field buf:Ljava/nio/ByteBuffer;
      25: invokevirtual #182                // Method java/nio/ByteBuffer.array:()[B
      28: invokevirtual #183                // Method java/io/InputStream.read:([B)I
      31: istore_1
      32: iload_1
      33: ifle          78
      36: aload_0
      37: getfield      #16                 // Field buf:Ljava/nio/ByteBuffer;
      40: iload_1
      41: invokevirtual #33                 // Method java/nio/ByteBuffer.limit:(I)Ljava/nio/Buffer;
      44: pop
      45: aload_0
      46: aload_0
      47: getfield      #16                 // Field buf:Ljava/nio/ByteBuffer;
      50: invokevirtual #180                // Method java/nio/ByteBuffer.limit:()I
      53: invokevirtual #2                  // Method count:(I)V
      56: aload_0
      57: getfield      #13                 // Field inf:Ljava/util/zip/Inflater;
      60: aload_0
      61: getfield      #16                 // Field buf:Ljava/nio/ByteBuffer;
      64: invokevirtual #182                // Method java/nio/ByteBuffer.array:()[B
      67: iconst_0
      68: aload_0
      69: getfield      #16                 // Field buf:Ljava/nio/ByteBuffer;
      72: invokevirtual #180                // Method java/nio/ByteBuffer.limit:()I
      75: invokevirtual #228                // Method java/util/zip/Inflater.setInput:([BII)V
      78: iload_1
      79: ireturn

  private void readFully(byte[]) throws java.io.IOException;
    Code:
       0: aload_0
       1: aload_1
       2: iconst_0
       3: invokespecial #229                // Method readFully:([BI)V
       6: return

  private void readFully(byte[], int) throws java.io.IOException;
    Code:
       0: aload_1
       1: arraylength
       2: iload_2
       3: isub
       4: istore_3
       5: aload_0
       6: getfield      #30                 // Field in:Ljava/io/InputStream;
       9: aload_1
      10: iload_2
      11: iload_3
      12: invokestatic  #230                // Method org/apache/commons/compress/utils/IOUtils.readFully:(Ljava/io/InputStream;[BII)I
      15: istore        4
      17: aload_0
      18: iload         4
      20: invokevirtual #2                  // Method count:(I)V
      23: iload         4
      25: iload_3
      26: if_icmpge     37
      29: new           #41                 // class java/io/EOFException
      32: dup
      33: invokespecial #231                // Method java/io/EOFException."<init>":()V
      36: athrow
      37: return

  private byte[] readRange(int) throws java.io.IOException;
    Code:
       0: aload_0
       1: getfield      #30                 // Field in:Ljava/io/InputStream;
       4: iload_1
       5: invokestatic  #232                // Method org/apache/commons/compress/utils/IOUtils.readRange:(Ljava/io/InputStream;I)[B
       8: astore_2
       9: aload_0
      10: aload_2
      11: arraylength
      12: invokevirtual #2                  // Method count:(I)V
      15: aload_2
      16: arraylength
      17: iload_1
      18: if_icmpge     29
      21: new           #41                 // class java/io/EOFException
      24: dup
      25: invokespecial #231                // Method java/io/EOFException."<init>":()V
      28: athrow
      29: aload_2
      30: areturn

  private void readDataDescriptor() throws java.io.IOException;
    Code:
       0: aload_0
       1: aload_0
       2: getfield      #21                 // Field wordBuf:[B
       5: invokespecial #40                 // Method readFully:([B)V
       8: new           #42                 // class org/apache/commons/compress/archivers/zip/ZipLong
      11: dup
      12: aload_0
      13: getfield      #21                 // Field wordBuf:[B
      16: invokespecial #43                 // Method org/apache/commons/compress/archivers/zip/ZipLong."<init>":([B)V
      19: astore_1
      20: getstatic     #126                // Field org/apache/commons/compress/archivers/zip/ZipLong.DD_SIG:Lorg/apache/commons/compress/archivers/zip/ZipLong;
      23: aload_1
      24: invokevirtual #45                 // Method org/apache/commons/compress/archivers/zip/ZipLong.equals:(Ljava/lang/Object;)Z
      27: ifeq          50
      30: aload_0
      31: aload_0
      32: getfield      #21                 // Field wordBuf:[B
      35: invokespecial #40                 // Method readFully:([B)V
      38: new           #42                 // class org/apache/commons/compress/archivers/zip/ZipLong
      41: dup
      42: aload_0
      43: getfield      #21                 // Field wordBuf:[B
      46: invokespecial #43                 // Method org/apache/commons/compress/archivers/zip/ZipLong."<init>":([B)V
      49: astore_1
      50: aload_0
      51: getfield      #3                  // Field current:Lorg/apache/commons/compress/archivers/zip/ZipArchiveInputStream$CurrentEntry;
      54: invokestatic  #60                 // Method org/apache/commons/compress/archivers/zip/ZipArchiveInputStream$CurrentEntry.access$100:(Lorg/apache/commons/compress/archivers/zip/ZipArchiveInputStream$CurrentEntry;)Lorg/apache/commons/compress/archivers/zip/ZipArchiveEntry;
      57: aload_1
      58: invokevirtual #53                 // Method org/apache/commons/compress/archivers/zip/ZipLong.getValue:()J
      61: invokevirtual #74                 // Method org/apache/commons/compress/archivers/zip/ZipArchiveEntry.setCrc:(J)V
      64: aload_0
      65: aload_0
      66: getfield      #22                 // Field twoDwordBuf:[B
      69: invokespecial #40                 // Method readFully:([B)V
      72: new           #42                 // class org/apache/commons/compress/archivers/zip/ZipLong
      75: dup
      76: aload_0
      77: getfield      #22                 // Field twoDwordBuf:[B
      80: bipush        8
      82: invokespecial #75                 // Method org/apache/commons/compress/archivers/zip/ZipLong."<init>":([BI)V
      85: astore_2
      86: aload_2
      87: getstatic     #46                 // Field org/apache/commons/compress/archivers/zip/ZipLong.CFH_SIG:Lorg/apache/commons/compress/archivers/zip/ZipLong;
      90: invokevirtual #45                 // Method org/apache/commons/compress/archivers/zip/ZipLong.equals:(Ljava/lang/Object;)Z
      93: ifne          106
      96: aload_2
      97: getstatic     #44                 // Field org/apache/commons/compress/archivers/zip/ZipLong.LFH_SIG:Lorg/apache/commons/compress/archivers/zip/ZipLong;
     100: invokevirtual #45                 // Method org/apache/commons/compress/archivers/zip/ZipLong.equals:(Ljava/lang/Object;)Z
     103: ifeq          192
     106: aload_0
     107: aload_0
     108: getfield      #22                 // Field twoDwordBuf:[B
     111: bipush        8
     113: bipush        8
     115: invokespecial #215                // Method pushback:([BII)V
     118: aload_0
     119: getfield      #22                 // Field twoDwordBuf:[B
     122: invokestatic  #233                // Method org/apache/commons/compress/archivers/zip/ZipLong.getValue:([B)J
     125: lstore_3
     126: lload_3
     127: lconst_0
     128: lcmp
     129: ifge          142
     132: new           #50                 // class java/util/zip/ZipException
     135: dup
     136: ldc           #142                // String broken archive, entry with negative compressed size
     138: invokespecial #56                 // Method java/util/zip/ZipException."<init>":(Ljava/lang/String;)V
     141: athrow
     142: aload_0
     143: getfield      #3                  // Field current:Lorg/apache/commons/compress/archivers/zip/ZipArchiveInputStream$CurrentEntry;
     146: invokestatic  #60                 // Method org/apache/commons/compress/archivers/zip/ZipArchiveInputStream$CurrentEntry.access$100:(Lorg/apache/commons/compress/archivers/zip/ZipArchiveInputStream$CurrentEntry;)Lorg/apache/commons/compress/archivers/zip/ZipArchiveEntry;
     149: lload_3
     150: invokevirtual #143                // Method org/apache/commons/compress/archivers/zip/ZipArchiveEntry.setCompressedSize:(J)V
     153: aload_0
     154: getfield      #22                 // Field twoDwordBuf:[B
     157: iconst_4
     158: invokestatic  #70                 // Method org/apache/commons/compress/archivers/zip/ZipLong.getValue:([BI)J
     161: lstore_3
     162: lload_3
     163: lconst_0
     164: lcmp
     165: ifge          178
     168: new           #50                 // class java/util/zip/ZipException
     171: dup
     172: ldc           #144                // String broken archive, entry with negative size
     174: invokespecial #56                 // Method java/util/zip/ZipException."<init>":(Ljava/lang/String;)V
     177: athrow
     178: aload_0
     179: getfield      #3                  // Field current:Lorg/apache/commons/compress/archivers/zip/ZipArchiveInputStream$CurrentEntry;
     182: invokestatic  #60                 // Method org/apache/commons/compress/archivers/zip/ZipArchiveInputStream$CurrentEntry.access$100:(Lorg/apache/commons/compress/archivers/zip/ZipArchiveInputStream$CurrentEntry;)Lorg/apache/commons/compress/archivers/zip/ZipArchiveEntry;
     185: lload_3
     186: invokevirtual #145                // Method org/apache/commons/compress/archivers/zip/ZipArchiveEntry.setSize:(J)V
     189: goto          264
     192: aload_0
     193: getfield      #22                 // Field twoDwordBuf:[B
     196: invokestatic  #234                // Method org/apache/commons/compress/archivers/zip/ZipEightByteInteger.getLongValue:([B)J
     199: lstore_3
     200: lload_3
     201: lconst_0
     202: lcmp
     203: ifge          216
     206: new           #50                 // class java/util/zip/ZipException
     209: dup
     210: ldc           #142                // String broken archive, entry with negative compressed size
     212: invokespecial #56                 // Method java/util/zip/ZipException."<init>":(Ljava/lang/String;)V
     215: athrow
     216: aload_0
     217: getfield      #3                  // Field current:Lorg/apache/commons/compress/archivers/zip/ZipArchiveInputStream$CurrentEntry;
     220: invokestatic  #60                 // Method org/apache/commons/compress/archivers/zip/ZipArchiveInputStream$CurrentEntry.access$100:(Lorg/apache/commons/compress/archivers/zip/ZipArchiveInputStream$CurrentEntry;)Lorg/apache/commons/compress/archivers/zip/ZipArchiveEntry;
     223: lload_3
     224: invokevirtual #143                // Method org/apache/commons/compress/archivers/zip/ZipArchiveEntry.setCompressedSize:(J)V
     227: aload_0
     228: getfield      #22                 // Field twoDwordBuf:[B
     231: bipush        8
     233: invokestatic  #235                // Method org/apache/commons/compress/archivers/zip/ZipEightByteInteger.getLongValue:([BI)J
     236: lstore_3
     237: lload_3
     238: lconst_0
     239: lcmp
     240: ifge          253
     243: new           #50                 // class java/util/zip/ZipException
     246: dup
     247: ldc           #144                // String broken archive, entry with negative size
     249: invokespecial #56                 // Method java/util/zip/ZipException."<init>":(Ljava/lang/String;)V
     252: athrow
     253: aload_0
     254: getfield      #3                  // Field current:Lorg/apache/commons/compress/archivers/zip/ZipArchiveInputStream$CurrentEntry;
     257: invokestatic  #60                 // Method org/apache/commons/compress/archivers/zip/ZipArchiveInputStream$CurrentEntry.access$100:(Lorg/apache/commons/compress/archivers/zip/ZipArchiveInputStream$CurrentEntry;)Lorg/apache/commons/compress/archivers/zip/ZipArchiveEntry;
     260: lload_3
     261: invokevirtual #145                // Method org/apache/commons/compress/archivers/zip/ZipArchiveEntry.setSize:(J)V
     264: return

  private boolean supportsDataDescriptorFor(org.apache.commons.compress.archivers.zip.ZipArchiveEntry);
    Code:
       0: aload_1
       1: invokevirtual #112                // Method org/apache/commons/compress/archivers/zip/ZipArchiveEntry.getGeneralPurposeBit:()Lorg/apache/commons/compress/archivers/zip/GeneralPurposeBit;
       4: invokevirtual #66                 // Method org/apache/commons/compress/archivers/zip/GeneralPurposeBit.usesDataDescriptor:()Z
       7: ifeq          46
      10: aload_0
      11: getfield      #31                 // Field allowStoredEntriesWithDataDescriptor:Z
      14: ifeq          24
      17: aload_1
      18: invokevirtual #95                 // Method org/apache/commons/compress/archivers/zip/ZipArchiveEntry.getMethod:()I
      21: ifeq          46
      24: aload_1
      25: invokevirtual #95                 // Method org/apache/commons/compress/archivers/zip/ZipArchiveEntry.getMethod:()I
      28: bipush        8
      30: if_icmpeq     46
      33: aload_1
      34: invokevirtual #95                 // Method org/apache/commons/compress/archivers/zip/ZipArchiveEntry.getMethod:()I
      37: getstatic     #124                // Field org/apache/commons/compress/archivers/zip/ZipMethod.ENHANCED_DEFLATED:Lorg/apache/commons/compress/archivers/zip/ZipMethod;
      40: invokevirtual #161                // Method org/apache/commons/compress/archivers/zip/ZipMethod.getCode:()I
      43: if_icmpne     50
      46: iconst_1
      47: goto          51
      50: iconst_0
      51: ireturn

  private boolean supportsCompressedSizeFor(org.apache.commons.compress.archivers.zip.ZipArchiveEntry);
    Code:
       0: aload_1
       1: invokevirtual #97                 // Method org/apache/commons/compress/archivers/zip/ZipArchiveEntry.getCompressedSize:()J
       4: ldc2_w        #99                 // long -1l
       7: lcmp
       8: ifne          57
      11: aload_1
      12: invokevirtual #95                 // Method org/apache/commons/compress/archivers/zip/ZipArchiveEntry.getMethod:()I
      15: bipush        8
      17: if_icmpeq     57
      20: aload_1
      21: invokevirtual #95                 // Method org/apache/commons/compress/archivers/zip/ZipArchiveEntry.getMethod:()I
      24: getstatic     #124                // Field org/apache/commons/compress/archivers/zip/ZipMethod.ENHANCED_DEFLATED:Lorg/apache/commons/compress/archivers/zip/ZipMethod;
      27: invokevirtual #161                // Method org/apache/commons/compress/archivers/zip/ZipMethod.getCode:()I
      30: if_icmpeq     57
      33: aload_1
      34: invokevirtual #112                // Method org/apache/commons/compress/archivers/zip/ZipArchiveEntry.getGeneralPurposeBit:()Lorg/apache/commons/compress/archivers/zip/GeneralPurposeBit;
      37: invokevirtual #66                 // Method org/apache/commons/compress/archivers/zip/GeneralPurposeBit.usesDataDescriptor:()Z
      40: ifeq          61
      43: aload_0
      44: getfield      #31                 // Field allowStoredEntriesWithDataDescriptor:Z
      47: ifeq          61
      50: aload_1
      51: invokevirtual #95                 // Method org/apache/commons/compress/archivers/zip/ZipArchiveEntry.getMethod:()I
      54: ifne          61
      57: iconst_1
      58: goto          62
      61: iconst_0
      62: ireturn

  private void readStoredEntry() throws java.io.IOException;
    Code:
       0: new           #237                // class java/io/ByteArrayOutputStream
       3: dup
       4: invokespecial #238                // Method java/io/ByteArrayOutputStream."<init>":()V
       7: astore_1
       8: iconst_0
       9: istore_2
      10: iconst_0
      11: istore_3
      12: aload_0
      13: getfield      #3                  // Field current:Lorg/apache/commons/compress/archivers/zip/ZipArchiveInputStream$CurrentEntry;
      16: invokestatic  #239                // Method org/apache/commons/compress/archivers/zip/ZipArchiveInputStream$CurrentEntry.access$400:(Lorg/apache/commons/compress/archivers/zip/ZipArchiveInputStream$CurrentEntry;)Z
      19: ifeq          27
      22: bipush        20
      24: goto          29
      27: bipush        12
      29: istore        4
      31: iload_3
      32: ifne          117
      35: aload_0
      36: getfield      #30                 // Field in:Ljava/io/InputStream;
      39: aload_0
      40: getfield      #16                 // Field buf:Ljava/nio/ByteBuffer;
      43: invokevirtual #182                // Method java/nio/ByteBuffer.array:()[B
      46: iload_2
      47: sipush        512
      50: iload_2
      51: isub
      52: invokevirtual #165                // Method java/io/InputStream.read:([BII)I
      55: istore        5
      57: iload         5
      59: ifgt          72
      62: new           #117                // class java/io/IOException
      65: dup
      66: ldc           #184                // String Truncated ZIP file
      68: invokespecial #151                // Method java/io/IOException."<init>":(Ljava/lang/String;)V
      71: athrow
      72: iload         5
      74: iload_2
      75: iadd
      76: iconst_4
      77: if_icmpge     88
      80: iload_2
      81: iload         5
      83: iadd
      84: istore_2
      85: goto          31
      88: aload_0
      89: aload_1
      90: iload_2
      91: iload         5
      93: iload         4
      95: invokespecial #240                // Method bufferContainsSignature:(Ljava/io/ByteArrayOutputStream;III)Z
      98: istore_3
      99: iload_3
     100: ifne          114
     103: aload_0
     104: aload_1
     105: iload_2
     106: iload         5
     108: iload         4
     110: invokespecial #241                // Method cacheBytesRead:(Ljava/io/ByteArrayOutputStream;III)I
     113: istore_2
     114: goto          31
     117: aload_0
     118: getfield      #3                  // Field current:Lorg/apache/commons/compress/archivers/zip/ZipArchiveInputStream$CurrentEntry;
     121: invokestatic  #60                 // Method org/apache/commons/compress/archivers/zip/ZipArchiveInputStream$CurrentEntry.access$100:(Lorg/apache/commons/compress/archivers/zip/ZipArchiveInputStream$CurrentEntry;)Lorg/apache/commons/compress/archivers/zip/ZipArchiveEntry;
     124: invokevirtual #97                 // Method org/apache/commons/compress/archivers/zip/ZipArchiveEntry.getCompressedSize:()J
     127: aload_0
     128: getfield      #3                  // Field current:Lorg/apache/commons/compress/archivers/zip/ZipArchiveInputStream$CurrentEntry;
     131: invokestatic  #60                 // Method org/apache/commons/compress/archivers/zip/ZipArchiveInputStream$CurrentEntry.access$100:(Lorg/apache/commons/compress/archivers/zip/ZipArchiveInputStream$CurrentEntry;)Lorg/apache/commons/compress/archivers/zip/ZipArchiveEntry;
     134: invokevirtual #178                // Method org/apache/commons/compress/archivers/zip/ZipArchiveEntry.getSize:()J
     137: lcmp
     138: ifeq          151
     141: new           #50                 // class java/util/zip/ZipException
     144: dup
     145: ldc           #242                // String compressed and uncompressed size don\'t match while reading a stored entry using data descriptor. Either the archive is broken or it can not be read using ZipArchiveInputStream and you must use ZipFile. A common cause for this is a ZIP archive containing a ZIP archive. See http://commons.apache.org/proper/commons-compress/zip.html#ZipArchiveInputStream_vs_ZipFile
     147: invokespecial #56                 // Method java/util/zip/ZipException."<init>":(Ljava/lang/String;)V
     150: athrow
     151: aload_1
     152: invokevirtual #243                // Method java/io/ByteArrayOutputStream.toByteArray:()[B
     155: astore        5
     157: aload         5
     159: arraylength
     160: i2l
     161: aload_0
     162: getfield      #3                  // Field current:Lorg/apache/commons/compress/archivers/zip/ZipArchiveInputStream$CurrentEntry;
     165: invokestatic  #60                 // Method org/apache/commons/compress/archivers/zip/ZipArchiveInputStream$CurrentEntry.access$100:(Lorg/apache/commons/compress/archivers/zip/ZipArchiveInputStream$CurrentEntry;)Lorg/apache/commons/compress/archivers/zip/ZipArchiveEntry;
     168: invokevirtual #178                // Method org/apache/commons/compress/archivers/zip/ZipArchiveEntry.getSize:()J
     171: lcmp
     172: ifeq          185
     175: new           #50                 // class java/util/zip/ZipException
     178: dup
     179: ldc           #244                // String actual and claimed size don\'t match while reading a stored entry using data descriptor. Either the archive is broken or it can not be read using ZipArchiveInputStream and you must use ZipFile. A common cause for this is a ZIP archive containing a ZIP archive. See http://commons.apache.org/proper/commons-compress/zip.html#ZipArchiveInputStream_vs_ZipFile
     181: invokespecial #56                 // Method java/util/zip/ZipException."<init>":(Ljava/lang/String;)V
     184: athrow
     185: aload_0
     186: new           #245                // class java/io/ByteArrayInputStream
     189: dup
     190: aload         5
     192: invokespecial #246                // Method java/io/ByteArrayInputStream."<init>":([B)V
     195: putfield      #175                // Field lastStoredEntry:Ljava/io/ByteArrayInputStream;
     198: return

  private boolean bufferContainsSignature(java.io.ByteArrayOutputStream, int, int, int) throws java.io.IOException;
    Code:
       0: iconst_0
       1: istore        5
       3: iconst_0
       4: istore        6
       6: iload         5
       8: ifne          254
      11: iload         6
      13: iload_2
      14: iload_3
      15: iadd
      16: iconst_4
      17: isub
      18: if_icmpge     254
      21: aload_0
      22: getfield      #16                 // Field buf:Ljava/nio/ByteBuffer;
      25: invokevirtual #182                // Method java/nio/ByteBuffer.array:()[B
      28: iload         6
      30: baload
      31: getstatic     #247                // Field LFH:[B
      34: iconst_0
      35: baload
      36: if_icmpne     248
      39: aload_0
      40: getfield      #16                 // Field buf:Ljava/nio/ByteBuffer;
      43: invokevirtual #182                // Method java/nio/ByteBuffer.array:()[B
      46: iload         6
      48: iconst_1
      49: iadd
      50: baload
      51: getstatic     #247                // Field LFH:[B
      54: iconst_1
      55: baload
      56: if_icmpne     248
      59: iload         6
      61: istore        7
      63: iload         6
      65: iload         4
      67: if_icmplt     110
      70: aload_0
      71: getfield      #16                 // Field buf:Ljava/nio/ByteBuffer;
      74: invokevirtual #182                // Method java/nio/ByteBuffer.array:()[B
      77: iload         6
      79: iconst_2
      80: iadd
      81: baload
      82: getstatic     #247                // Field LFH:[B
      85: iconst_2
      86: baload
      87: if_icmpne     110
      90: aload_0
      91: getfield      #16                 // Field buf:Ljava/nio/ByteBuffer;
      94: invokevirtual #182                // Method java/nio/ByteBuffer.array:()[B
      97: iload         6
      99: iconst_3
     100: iadd
     101: baload
     102: getstatic     #247                // Field LFH:[B
     105: iconst_3
     106: baload
     107: if_icmpeq     150
     110: aload_0
     111: getfield      #16                 // Field buf:Ljava/nio/ByteBuffer;
     114: invokevirtual #182                // Method java/nio/ByteBuffer.array:()[B
     117: iload         6
     119: iconst_2
     120: iadd
     121: baload
     122: getstatic     #248                // Field CFH:[B
     125: iconst_2
     126: baload
     127: if_icmpne     163
     130: aload_0
     131: getfield      #16                 // Field buf:Ljava/nio/ByteBuffer;
     134: invokevirtual #182                // Method java/nio/ByteBuffer.array:()[B
     137: iload         6
     139: iconst_3
     140: iadd
     141: baload
     142: getstatic     #248                // Field CFH:[B
     145: iconst_3
     146: baload
     147: if_icmpne     163
     150: iload         6
     152: iload         4
     154: isub
     155: istore        7
     157: iconst_1
     158: istore        5
     160: goto          206
     163: aload_0
     164: getfield      #16                 // Field buf:Ljava/nio/ByteBuffer;
     167: invokevirtual #182                // Method java/nio/ByteBuffer.array:()[B
     170: iload         6
     172: iconst_2
     173: iadd
     174: baload
     175: getstatic     #249                // Field DD:[B
     178: iconst_2
     179: baload
     180: if_icmpne     206
     183: aload_0
     184: getfield      #16                 // Field buf:Ljava/nio/ByteBuffer;
     187: invokevirtual #182                // Method java/nio/ByteBuffer.array:()[B
     190: iload         6
     192: iconst_3
     193: iadd
     194: baload
     195: getstatic     #249                // Field DD:[B
     198: iconst_3
     199: baload
     200: if_icmpne     206
     203: iconst_1
     204: istore        5
     206: iload         5
     208: ifeq          248
     211: aload_0
     212: aload_0
     213: getfield      #16                 // Field buf:Ljava/nio/ByteBuffer;
     216: invokevirtual #182                // Method java/nio/ByteBuffer.array:()[B
     219: iload         7
     221: iload_2
     222: iload_3
     223: iadd
     224: iload         7
     226: isub
     227: invokespecial #215                // Method pushback:([BII)V
     230: aload_1
     231: aload_0
     232: getfield      #16                 // Field buf:Ljava/nio/ByteBuffer;
     235: invokevirtual #182                // Method java/nio/ByteBuffer.array:()[B
     238: iconst_0
     239: iload         7
     241: invokevirtual #250                // Method java/io/ByteArrayOutputStream.write:([BII)V
     244: aload_0
     245: invokespecial #216                // Method readDataDescriptor:()V
     248: iinc          6, 1
     251: goto          6
     254: iload         5
     256: ireturn

  private int cacheBytesRead(java.io.ByteArrayOutputStream, int, int, int);
    Code:
       0: iload_2
       1: iload_3
       2: iadd
       3: iload         4
       5: isub
       6: iconst_3
       7: isub
       8: istore        5
      10: iload         5
      12: ifle          61
      15: aload_1
      16: aload_0
      17: getfield      #16                 // Field buf:Ljava/nio/ByteBuffer;
      20: invokevirtual #182                // Method java/nio/ByteBuffer.array:()[B
      23: iconst_0
      24: iload         5
      26: invokevirtual #250                // Method java/io/ByteArrayOutputStream.write:([BII)V
      29: aload_0
      30: getfield      #16                 // Field buf:Ljava/nio/ByteBuffer;
      33: invokevirtual #182                // Method java/nio/ByteBuffer.array:()[B
      36: iload         5
      38: aload_0
      39: getfield      #16                 // Field buf:Ljava/nio/ByteBuffer;
      42: invokevirtual #182                // Method java/nio/ByteBuffer.array:()[B
      45: iconst_0
      46: iload         4
      48: iconst_3
      49: iadd
      50: invokestatic  #131                // Method java/lang/System.arraycopy:(Ljava/lang/Object;ILjava/lang/Object;II)V
      53: iload         4
      55: iconst_3
      56: iadd
      57: istore_2
      58: goto          65
      61: iload_2
      62: iload_3
      63: iadd
      64: istore_2
      65: iload_2
      66: ireturn

  private void pushback(byte[], int, int) throws java.io.IOException;
    Code:
       0: aload_0
       1: getfield      #30                 // Field in:Ljava/io/InputStream;
       4: checkcast     #27                 // class java/io/PushbackInputStream
       7: aload_1
       8: iload_2
       9: iload_3
      10: invokevirtual #251                // Method java/io/PushbackInputStream.unread:([BII)V
      13: aload_0
      14: iload_3
      15: i2l
      16: invokevirtual #252                // Method pushedBackBytes:(J)V
      19: return

  private void skipRemainderOfArchive() throws java.io.IOException;
    Code:
       0: aload_0
       1: getfield      #125                // Field entriesRead:I
       4: ifle          67
       7: aload_0
       8: aload_0
       9: getfield      #125                // Field entriesRead:I
      12: i2l
      13: ldc2_w        #253                // long 46l
      16: lmul
      17: ldc2_w        #255                // long 30l
      20: lsub
      21: invokespecial #257                // Method realSkip:(J)V
      24: aload_0
      25: invokespecial #258                // Method findEocdRecord:()Z
      28: istore_1
      29: iload_1
      30: ifeq          67
      33: aload_0
      34: ldc2_w        #259                // long 16l
      37: invokespecial #257                // Method realSkip:(J)V
      40: aload_0
      41: aload_0
      42: getfield      #20                 // Field shortBuf:[B
      45: invokespecial #40                 // Method readFully:([B)V
      48: aload_0
      49: getfield      #20                 // Field shortBuf:[B
      52: invokestatic  #261                // Method org/apache/commons/compress/archivers/zip/ZipShort.getValue:([B)I
      55: istore_2
      56: iload_2
      57: iflt          67
      60: aload_0
      61: iload_2
      62: i2l
      63: invokespecial #257                // Method realSkip:(J)V
      66: return
      67: new           #117                // class java/io/IOException
      70: dup
      71: ldc           #184                // String Truncated ZIP file
      73: invokespecial #151                // Method java/io/IOException."<init>":(Ljava/lang/String;)V
      76: athrow

  private boolean findEocdRecord() throws java.io.IOException;
    Code:
       0: iconst_m1
       1: istore_1
       2: iconst_0
       3: istore_2
       4: iload_2
       5: ifne          18
       8: aload_0
       9: invokespecial #262                // Method readOneByte:()I
      12: dup
      13: istore_1
      14: iconst_m1
      15: if_icmple     126
      18: iconst_0
      19: istore_2
      20: aload_0
      21: iload_1
      22: invokespecial #263                // Method isFirstByteOfEocdSig:(I)Z
      25: ifne          31
      28: goto          4
      31: aload_0
      32: invokespecial #262                // Method readOneByte:()I
      35: istore_1
      36: iload_1
      37: getstatic     #206                // Field org/apache/commons/compress/archivers/zip/ZipArchiveOutputStream.EOCD_SIG:[B
      40: iconst_1
      41: baload
      42: if_icmpeq     62
      45: iload_1
      46: iconst_m1
      47: if_icmpne     53
      50: goto          126
      53: aload_0
      54: iload_1
      55: invokespecial #263                // Method isFirstByteOfEocdSig:(I)Z
      58: istore_2
      59: goto          4
      62: aload_0
      63: invokespecial #262                // Method readOneByte:()I
      66: istore_1
      67: iload_1
      68: getstatic     #206                // Field org/apache/commons/compress/archivers/zip/ZipArchiveOutputStream.EOCD_SIG:[B
      71: iconst_2
      72: baload
      73: if_icmpeq     93
      76: iload_1
      77: iconst_m1
      78: if_icmpne     84
      81: goto          126
      84: aload_0
      85: iload_1
      86: invokespecial #263                // Method isFirstByteOfEocdSig:(I)Z
      89: istore_2
      90: goto          4
      93: aload_0
      94: invokespecial #262                // Method readOneByte:()I
      97: istore_1
      98: iload_1
      99: iconst_m1
     100: if_icmpne     106
     103: goto          126
     106: iload_1
     107: getstatic     #206                // Field org/apache/commons/compress/archivers/zip/ZipArchiveOutputStream.EOCD_SIG:[B
     110: iconst_3
     111: baload
     112: if_icmpne     117
     115: iconst_1
     116: ireturn
     117: aload_0
     118: iload_1
     119: invokespecial #263                // Method isFirstByteOfEocdSig:(I)Z
     122: istore_2
     123: goto          4
     126: iconst_0
     127: ireturn

  private void realSkip(long) throws java.io.IOException;
    Code:
       0: lload_1
       1: lconst_0
       2: lcmp
       3: iflt          80
       6: lconst_0
       7: lstore_3
       8: lload_3
       9: lload_1
      10: lcmp
      11: ifge          79
      14: lload_1
      15: lload_3
      16: lsub
      17: lstore        5
      19: aload_0
      20: getfield      #30                 // Field in:Ljava/io/InputStream;
      23: aload_0
      24: getfield      #19                 // Field skipBuf:[B
      27: iconst_0
      28: aload_0
      29: getfield      #19                 // Field skipBuf:[B
      32: arraylength
      33: i2l
      34: lload         5
      36: lcmp
      37: ifle          45
      40: lload         5
      42: goto          51
      45: aload_0
      46: getfield      #19                 // Field skipBuf:[B
      49: arraylength
      50: i2l
      51: l2i
      52: invokevirtual #165                // Method java/io/InputStream.read:([BII)I
      55: istore        7
      57: iload         7
      59: iconst_m1
      60: if_icmpne     64
      63: return
      64: aload_0
      65: iload         7
      67: invokevirtual #2                  // Method count:(I)V
      70: lload_3
      71: iload         7
      73: i2l
      74: ladd
      75: lstore_3
      76: goto          8
      79: return
      80: new           #116                // class java/lang/IllegalArgumentException
      83: dup
      84: invokespecial #203                // Method java/lang/IllegalArgumentException."<init>":()V
      87: athrow

  private int readOneByte() throws java.io.IOException;
    Code:
       0: aload_0
       1: getfield      #30                 // Field in:Ljava/io/InputStream;
       4: invokevirtual #264                // Method java/io/InputStream.read:()I
       7: istore_1
       8: iload_1
       9: iconst_m1
      10: if_icmpeq     18
      13: aload_0
      14: iconst_1
      15: invokevirtual #2                  // Method count:(I)V
      18: iload_1
      19: ireturn

  private boolean isFirstByteOfEocdSig(int);
    Code:
       0: iload_1
       1: getstatic     #206                // Field org/apache/commons/compress/archivers/zip/ZipArchiveOutputStream.EOCD_SIG:[B
       4: iconst_0
       5: baload
       6: if_icmpne     13
       9: iconst_1
      10: goto          14
      13: iconst_0
      14: ireturn

  private boolean isApkSigningBlock(byte[]) throws java.io.IOException;
    Code:
       0: aload_1
       1: invokestatic  #265                // Method org/apache/commons/compress/archivers/zip/ZipEightByteInteger.getValue:([B)Ljava/math/BigInteger;
       4: astore_2
       5: aload_2
       6: bipush        8
       8: aload_1
       9: arraylength
      10: isub
      11: i2l
      12: getstatic     #266                // Field APK_SIGNING_BLOCK_MAGIC:[B
      15: arraylength
      16: i2l
      17: lsub
      18: invokestatic  #267                // Method java/math/BigInteger.valueOf:(J)Ljava/math/BigInteger;
      21: invokevirtual #268                // Method java/math/BigInteger.add:(Ljava/math/BigInteger;)Ljava/math/BigInteger;
      24: astore_3
      25: getstatic     #266                // Field APK_SIGNING_BLOCK_MAGIC:[B
      28: arraylength
      29: newarray       byte
      31: astore        4
      33: aload_3
      34: invokevirtual #269                // Method java/math/BigInteger.signum:()I
      37: ifge          103
      40: aload_1
      41: arraylength
      42: aload_3
      43: invokevirtual #270                // Method java/math/BigInteger.intValue:()I
      46: iadd
      47: istore        5
      49: iload         5
      51: bipush        8
      53: if_icmpge     58
      56: iconst_0
      57: ireturn
      58: aload_3
      59: invokevirtual #270                // Method java/math/BigInteger.intValue:()I
      62: invokestatic  #271                // Method java/lang/Math.abs:(I)I
      65: istore        6
      67: aload_1
      68: iload         5
      70: aload         4
      72: iconst_0
      73: iload         6
      75: aload         4
      77: arraylength
      78: invokestatic  #188                // Method java/lang/Math.min:(II)I
      81: invokestatic  #131                // Method java/lang/System.arraycopy:(Ljava/lang/Object;ILjava/lang/Object;II)V
      84: iload         6
      86: aload         4
      88: arraylength
      89: if_icmpge     100
      92: aload_0
      93: aload         4
      95: iload         6
      97: invokespecial #229                // Method readFully:([BI)V
     100: goto          148
     103: aload_3
     104: getstatic     #272                // Field LONG_MAX:Ljava/math/BigInteger;
     107: invokevirtual #273                // Method java/math/BigInteger.compareTo:(Ljava/math/BigInteger;)I
     110: ifle          134
     113: aload_0
     114: ldc2_w        #212                // long 9223372036854775807l
     117: invokespecial #257                // Method realSkip:(J)V
     120: aload_3
     121: getstatic     #272                // Field LONG_MAX:Ljava/math/BigInteger;
     124: invokevirtual #274                // Method java/math/BigInteger.negate:()Ljava/math/BigInteger;
     127: invokevirtual #268                // Method java/math/BigInteger.add:(Ljava/math/BigInteger;)Ljava/math/BigInteger;
     130: astore_3
     131: goto          103
     134: aload_0
     135: aload_3
     136: invokevirtual #275                // Method java/math/BigInteger.longValue:()J
     139: invokespecial #257                // Method realSkip:(J)V
     142: aload_0
     143: aload         4
     145: invokespecial #40                 // Method readFully:([B)V
     148: goto          155
     151: astore        5
     153: iconst_0
     154: ireturn
     155: aload         4
     157: getstatic     #266                // Field APK_SIGNING_BLOCK_MAGIC:[B
     160: invokestatic  #276                // Method java/util/Arrays.equals:([B[B)Z
     163: ireturn
    Exception table:
       from    to  target type
          33    57   151   Class java/io/EOFException
          58   148   151   Class java/io/EOFException

  static void access$800(org.apache.commons.compress.archivers.zip.ZipArchiveInputStream, int);
    Code:
       0: aload_0
       1: iload_1
       2: invokevirtual #2                  // Method count:(I)V
       5: return

  static org.apache.commons.compress.archivers.zip.ZipArchiveInputStream$CurrentEntry access$900(org.apache.commons.compress.archivers.zip.ZipArchiveInputStream);
    Code:
       0: aload_0
       1: getfield      #3                  // Field current:Lorg/apache/commons/compress/archivers/zip/ZipArchiveInputStream$CurrentEntry;
       4: areturn

  static void access$1000(org.apache.commons.compress.archivers.zip.ZipArchiveInputStream, int);
    Code:
       0: aload_0
       1: iload_1
       2: invokevirtual #2                  // Method count:(I)V
       5: return

  static {};
    Code:
       0: getstatic     #44                 // Field org/apache/commons/compress/archivers/zip/ZipLong.LFH_SIG:Lorg/apache/commons/compress/archivers/zip/ZipLong;
       3: invokevirtual #208                // Method org/apache/commons/compress/archivers/zip/ZipLong.getBytes:()[B
       6: putstatic     #247                // Field LFH:[B
       9: getstatic     #46                 // Field org/apache/commons/compress/archivers/zip/ZipLong.CFH_SIG:Lorg/apache/commons/compress/archivers/zip/ZipLong;
      12: invokevirtual #208                // Method org/apache/commons/compress/archivers/zip/ZipLong.getBytes:()[B
      15: putstatic     #248                // Field CFH:[B
      18: getstatic     #126                // Field org/apache/commons/compress/archivers/zip/ZipLong.DD_SIG:Lorg/apache/commons/compress/archivers/zip/ZipLong;
      21: invokevirtual #208                // Method org/apache/commons/compress/archivers/zip/ZipLong.getBytes:()[B
      24: putstatic     #249                // Field DD:[B
      27: bipush        16
      29: newarray       byte
      31: dup
      32: iconst_0
      33: bipush        65
      35: bastore
      36: dup
      37: iconst_1
      38: bipush        80
      40: bastore
      41: dup
      42: iconst_2
      43: bipush        75
      45: bastore
      46: dup
      47: iconst_3
      48: bipush        32
      50: bastore
      51: dup
      52: iconst_4
      53: bipush        83
      55: bastore
      56: dup
      57: iconst_5
      58: bipush        105
      60: bastore
      61: dup
      62: bipush        6
      64: bipush        103
      66: bastore
      67: dup
      68: bipush        7
      70: bipush        32
      72: bastore
      73: dup
      74: bipush        8
      76: bipush        66
      78: bastore
      79: dup
      80: bipush        9
      82: bipush        108
      84: bastore
      85: dup
      86: bipush        10
      88: bipush        111
      90: bastore
      91: dup
      92: bipush        11
      94: bipush        99
      96: bastore
      97: dup
      98: bipush        12
     100: bipush        107
     102: bastore
     103: dup
     104: bipush        13
     106: bipush        32
     108: bastore
     109: dup
     110: bipush        14
     112: bipush        52
     114: bastore
     115: dup
     116: bipush        15
     118: bipush        50
     120: bastore
     121: putstatic     #266                // Field APK_SIGNING_BLOCK_MAGIC:[B
     124: ldc2_w        #212                // long 9223372036854775807l
     127: invokestatic  #267                // Method java/math/BigInteger.valueOf:(J)Ljava/math/BigInteger;
     130: putstatic     #272                // Field LONG_MAX:Ljava/math/BigInteger;
     133: return
}
