public class org.bouncycastle.asn1.cmc.EncryptedPOP extends org.bouncycastle.asn1.ASN1Object {
  private final org.bouncycastle.asn1.cmc.TaggedRequest request;

  private final org.bouncycastle.asn1.cms.ContentInfo cms;

  private final org.bouncycastle.asn1.x509.AlgorithmIdentifier thePOPAlgID;

  private final org.bouncycastle.asn1.x509.AlgorithmIdentifier witnessAlgID;

  private final byte[] witness;

  private org.bouncycastle.asn1.cmc.EncryptedPOP(org.bouncycastle.asn1.ASN1Sequence);
    Code:
       0: aload_0
       1: invokespecial #100                // Method org/bouncycastle/asn1/ASN1Object."<init>":()V
       4: aload_1
       5: invokevirtual #103                // Method org/bouncycastle/asn1/ASN1Sequence.size:()I
       8: iconst_5
       9: if_icmpeq     22
      12: new           #40                 // class java/lang/IllegalArgumentException
      15: dup
      16: ldc           #1                  // String incorrect sequence size
      18: invokespecial #97                 // Method java/lang/IllegalArgumentException."<init>":(Ljava/lang/String;)V
      21: athrow
      22: aload_0
      23: aload_1
      24: iconst_0
      25: invokevirtual #104                // Method org/bouncycastle/asn1/ASN1Sequence.getObjectAt:(I)Lorg/bouncycastle/asn1/ASN1Encodable;
      28: invokestatic  #109                // Method org/bouncycastle/asn1/cmc/TaggedRequest.getInstance:(Ljava/lang/Object;)Lorg/bouncycastle/asn1/cmc/TaggedRequest;
      31: putfield      #93                 // Field request:Lorg/bouncycastle/asn1/cmc/TaggedRequest;
      34: aload_0
      35: aload_1
      36: iconst_1
      37: invokevirtual #104                // Method org/bouncycastle/asn1/ASN1Sequence.getObjectAt:(I)Lorg/bouncycastle/asn1/ASN1Encodable;
      40: invokestatic  #110                // Method org/bouncycastle/asn1/cms/ContentInfo.getInstance:(Ljava/lang/Object;)Lorg/bouncycastle/asn1/cms/ContentInfo;
      43: putfield      #94                 // Field cms:Lorg/bouncycastle/asn1/cms/ContentInfo;
      46: aload_0
      47: aload_1
      48: iconst_2
      49: invokevirtual #104                // Method org/bouncycastle/asn1/ASN1Sequence.getObjectAt:(I)Lorg/bouncycastle/asn1/ASN1Encodable;
      52: invokestatic  #111                // Method org/bouncycastle/asn1/x509/AlgorithmIdentifier.getInstance:(Ljava/lang/Object;)Lorg/bouncycastle/asn1/x509/AlgorithmIdentifier;
      55: putfield      #95                 // Field thePOPAlgID:Lorg/bouncycastle/asn1/x509/AlgorithmIdentifier;
      58: aload_0
      59: aload_1
      60: iconst_3
      61: invokevirtual #104                // Method org/bouncycastle/asn1/ASN1Sequence.getObjectAt:(I)Lorg/bouncycastle/asn1/ASN1Encodable;
      64: invokestatic  #111                // Method org/bouncycastle/asn1/x509/AlgorithmIdentifier.getInstance:(Ljava/lang/Object;)Lorg/bouncycastle/asn1/x509/AlgorithmIdentifier;
      67: putfield      #96                 // Field witnessAlgID:Lorg/bouncycastle/asn1/x509/AlgorithmIdentifier;
      70: aload_0
      71: aload_1
      72: iconst_4
      73: invokevirtual #104                // Method org/bouncycastle/asn1/ASN1Sequence.getObjectAt:(I)Lorg/bouncycastle/asn1/ASN1Encodable;
      76: invokestatic  #102                // Method org/bouncycastle/asn1/ASN1OctetString.getInstance:(Ljava/lang/Object;)Lorg/bouncycastle/asn1/ASN1OctetString;
      79: invokevirtual #101                // Method org/bouncycastle/asn1/ASN1OctetString.getOctets:()[B
      82: invokestatic  #112                // Method org/bouncycastle/util/Arrays.clone:([B)[B
      85: putfield      #92                 // Field witness:[B
      88: return

  public org.bouncycastle.asn1.cmc.EncryptedPOP(org.bouncycastle.asn1.cmc.TaggedRequest, org.bouncycastle.asn1.cms.ContentInfo, org.bouncycastle.asn1.x509.AlgorithmIdentifier, org.bouncycastle.asn1.x509.AlgorithmIdentifier, byte[]);
    Code:
       0: aload_0
       1: invokespecial #100                // Method org/bouncycastle/asn1/ASN1Object."<init>":()V
       4: aload_0
       5: aload_1
       6: putfield      #93                 // Field request:Lorg/bouncycastle/asn1/cmc/TaggedRequest;
       9: aload_0
      10: aload_2
      11: putfield      #94                 // Field cms:Lorg/bouncycastle/asn1/cms/ContentInfo;
      14: aload_0
      15: aload_3
      16: putfield      #95                 // Field thePOPAlgID:Lorg/bouncycastle/asn1/x509/AlgorithmIdentifier;
      19: aload_0
      20: aload         4
      22: putfield      #96                 // Field witnessAlgID:Lorg/bouncycastle/asn1/x509/AlgorithmIdentifier;
      25: aload_0
      26: aload         5
      28: invokestatic  #112                // Method org/bouncycastle/util/Arrays.clone:([B)[B
      31: putfield      #92                 // Field witness:[B
      34: return

  public static org.bouncycastle.asn1.cmc.EncryptedPOP getInstance(java.lang.Object);
    Code:
       0: aload_0
       1: instanceof    #47                 // class org/bouncycastle/asn1/cmc/EncryptedPOP
       4: ifeq          12
       7: aload_0
       8: checkcast     #47                 // class org/bouncycastle/asn1/cmc/EncryptedPOP
      11: areturn
      12: aload_0
      13: ifnull        28
      16: new           #47                 // class org/bouncycastle/asn1/cmc/EncryptedPOP
      19: dup
      20: aload_0
      21: invokestatic  #105                // Method org/bouncycastle/asn1/ASN1Sequence.getInstance:(Ljava/lang/Object;)Lorg/bouncycastle/asn1/ASN1Sequence;
      24: invokespecial #108                // Method "<init>":(Lorg/bouncycastle/asn1/ASN1Sequence;)V
      27: areturn
      28: aconst_null
      29: areturn

  public org.bouncycastle.asn1.cmc.TaggedRequest getRequest();
    Code:
       0: aload_0
       1: getfield      #93                 // Field request:Lorg/bouncycastle/asn1/cmc/TaggedRequest;
       4: areturn

  public org.bouncycastle.asn1.cms.ContentInfo getCms();
    Code:
       0: aload_0
       1: getfield      #94                 // Field cms:Lorg/bouncycastle/asn1/cms/ContentInfo;
       4: areturn

  public org.bouncycastle.asn1.x509.AlgorithmIdentifier getThePOPAlgID();
    Code:
       0: aload_0
       1: getfield      #95                 // Field thePOPAlgID:Lorg/bouncycastle/asn1/x509/AlgorithmIdentifier;
       4: areturn

  public org.bouncycastle.asn1.x509.AlgorithmIdentifier getWitnessAlgID();
    Code:
       0: aload_0
       1: getfield      #96                 // Field witnessAlgID:Lorg/bouncycastle/asn1/x509/AlgorithmIdentifier;
       4: areturn

  public byte[] getWitness();
    Code:
       0: aload_0
       1: getfield      #92                 // Field witness:[B
       4: invokestatic  #112                // Method org/bouncycastle/util/Arrays.clone:([B)[B
       7: areturn

  public org.bouncycastle.asn1.ASN1Primitive toASN1Primitive();
    Code:
       0: new           #41                 // class org/bouncycastle/asn1/ASN1EncodableVector
       3: dup
       4: iconst_5
       5: invokespecial #98                 // Method org/bouncycastle/asn1/ASN1EncodableVector."<init>":(I)V
       8: astore_1
       9: aload_1
      10: aload_0
      11: getfield      #93                 // Field request:Lorg/bouncycastle/asn1/cmc/TaggedRequest;
      14: invokevirtual #99                 // Method org/bouncycastle/asn1/ASN1EncodableVector.add:(Lorg/bouncycastle/asn1/ASN1Encodable;)V
      17: aload_1
      18: aload_0
      19: getfield      #94                 // Field cms:Lorg/bouncycastle/asn1/cms/ContentInfo;
      22: invokevirtual #99                 // Method org/bouncycastle/asn1/ASN1EncodableVector.add:(Lorg/bouncycastle/asn1/ASN1Encodable;)V
      25: aload_1
      26: aload_0
      27: getfield      #95                 // Field thePOPAlgID:Lorg/bouncycastle/asn1/x509/AlgorithmIdentifier;
      30: invokevirtual #99                 // Method org/bouncycastle/asn1/ASN1EncodableVector.add:(Lorg/bouncycastle/asn1/ASN1Encodable;)V
      33: aload_1
      34: aload_0
      35: getfield      #96                 // Field witnessAlgID:Lorg/bouncycastle/asn1/x509/AlgorithmIdentifier;
      38: invokevirtual #99                 // Method org/bouncycastle/asn1/ASN1EncodableVector.add:(Lorg/bouncycastle/asn1/ASN1Encodable;)V
      41: aload_1
      42: new           #45                 // class org/bouncycastle/asn1/DEROctetString
      45: dup
      46: aload_0
      47: getfield      #92                 // Field witness:[B
      50: invokespecial #106                // Method org/bouncycastle/asn1/DEROctetString."<init>":([B)V
      53: invokevirtual #99                 // Method org/bouncycastle/asn1/ASN1EncodableVector.add:(Lorg/bouncycastle/asn1/ASN1Encodable;)V
      56: new           #46                 // class org/bouncycastle/asn1/DERSequence
      59: dup
      60: aload_1
      61: invokespecial #107                // Method org/bouncycastle/asn1/DERSequence."<init>":(Lorg/bouncycastle/asn1/ASN1EncodableVector;)V
      64: areturn
}
