Compiled from "HttpMethodHelper.java"
public final class org.apache.camel.component.http4.helper.HttpMethodHelper {
  private org.apache.camel.component.http4.helper.HttpMethodHelper();
    Code:
       0: aload_0
       1: invokespecial #1                  // Method java/lang/Object."<init>":()V
       4: return

  public static org.apache.camel.component.http4.HttpMethods createMethod(org.apache.camel.Exchange, org.apache.camel.component.http4.HttpEndpoint, boolean) throws java.net.URISyntaxException;
    Code:
       0: aload_0
       1: invokeinterface #2,  1            // InterfaceMethod org/apache/camel/Exchange.getIn:()Lorg/apache/camel/Message;
       6: ldc           #4                  // String CamelHttpQuery
       8: ldc           #5                  // class java/lang/String
      10: invokeinterface #6,  3            // InterfaceMethod org/apache/camel/Message.getHeader:(Ljava/lang/String;Ljava/lang/Class;)Ljava/lang/Object;
      15: checkcast     #5                  // class java/lang/String
      18: astore_3
      19: aload_0
      20: invokeinterface #2,  1            // InterfaceMethod org/apache/camel/Exchange.getIn:()Lorg/apache/camel/Message;
      25: ldc           #7                  // String CamelHttpUri
      27: ldc           #5                  // class java/lang/String
      29: invokeinterface #6,  3            // InterfaceMethod org/apache/camel/Message.getHeader:(Ljava/lang/String;Ljava/lang/Class;)Ljava/lang/Object;
      34: checkcast     #5                  // class java/lang/String
      37: astore        4
      39: aload_0
      40: invokeinterface #8,  1            // InterfaceMethod org/apache/camel/Exchange.getContext:()Lorg/apache/camel/CamelContext;
      45: aload         4
      47: invokeinterface #9,  2            // InterfaceMethod org/apache/camel/CamelContext.resolvePropertyPlaceholders:(Ljava/lang/String;)Ljava/lang/String;
      52: astore        4
      54: goto          90
      57: astore        5
      59: new           #11                 // class org/apache/camel/RuntimeExchangeException
      62: dup
      63: new           #12                 // class java/lang/StringBuilder
      66: dup
      67: invokespecial #13                 // Method java/lang/StringBuilder."<init>":()V
      70: ldc           #14                 // String Cannot resolve property placeholders with uri:
      72: invokevirtual #15                 // Method java/lang/StringBuilder.append:(Ljava/lang/String;)Ljava/lang/StringBuilder;
      75: aload         4
      77: invokevirtual #15                 // Method java/lang/StringBuilder.append:(Ljava/lang/String;)Ljava/lang/StringBuilder;
      80: invokevirtual #16                 // Method java/lang/StringBuilder.toString:()Ljava/lang/String;
      83: aload_0
      84: aload         5
      86: invokespecial #17                 // Method org/apache/camel/RuntimeExchangeException."<init>":(Ljava/lang/String;Lorg/apache/camel/Exchange;Ljava/lang/Throwable;)V
      89: athrow
      90: aload         4
      92: ifnull        119
      95: aload         4
      97: invokestatic  #18                 // Method org/apache/camel/util/UnsafeUriCharactersEncoder.encodeHttpURI:(Ljava/lang/String;)Ljava/lang/String;
     100: astore        4
     102: new           #19                 // class java/net/URI
     105: dup
     106: aload         4
     108: invokespecial #20                 // Method java/net/URI."<init>":(Ljava/lang/String;)V
     111: astore        5
     113: aload         5
     115: invokevirtual #21                 // Method java/net/URI.getQuery:()Ljava/lang/String;
     118: astore_3
     119: aload_3
     120: ifnonnull     131
     123: aload_1
     124: invokevirtual #22                 // Method org/apache/camel/component/http4/HttpEndpoint.getHttpUri:()Ljava/net/URI;
     127: invokevirtual #23                 // Method java/net/URI.getRawQuery:()Ljava/lang/String;
     130: astore_3
     131: aload_0
     132: invokeinterface #2,  1            // InterfaceMethod org/apache/camel/Exchange.getIn:()Lorg/apache/camel/Message;
     137: ldc           #24                 // String CamelHttpMethod
     139: ldc           #25                 // class org/apache/camel/component/http4/HttpMethods
     141: invokeinterface #6,  3            // InterfaceMethod org/apache/camel/Message.getHeader:(Ljava/lang/String;Ljava/lang/Class;)Ljava/lang/Object;
     146: checkcast     #25                 // class org/apache/camel/component/http4/HttpMethods
     149: astore        6
     151: aload         6
     153: ifnull        163
     156: aload         6
     158: astore        5
     160: goto          190
     163: aload_3
     164: ifnull        175
     167: getstatic     #26                 // Field org/apache/camel/component/http4/HttpMethods.GET:Lorg/apache/camel/component/http4/HttpMethods;
     170: astore        5
     172: goto          190
     175: iload_2
     176: ifeq          185
     179: getstatic     #27                 // Field org/apache/camel/component/http4/HttpMethods.POST:Lorg/apache/camel/component/http4/HttpMethods;
     182: goto          188
     185: getstatic     #26                 // Field org/apache/camel/component/http4/HttpMethods.GET:Lorg/apache/camel/component/http4/HttpMethods;
     188: astore        5
     190: aload         5
     192: areturn
    Exception table:
       from    to  target type
          39    54    57   Class java/lang/Exception
}
