Compiled from "WstxSAXParser.java"
public class com.ctc.wstx.sax.WstxSAXParser extends javax.xml.parsers.SAXParser implements org.xml.sax.Parser,org.xml.sax.XMLReader,org.xml.sax.ext.Attributes2,org.xml.sax.ext.Locator2,com.ctc.wstx.dtd.DTDEventListener {
  static final boolean FEAT_DEFAULT_NS_PREFIXES;

  protected final com.ctc.wstx.stax.WstxInputFactory mStaxFactory;

  protected final com.ctc.wstx.api.ReaderConfig mConfig;

  protected boolean mFeatNsPrefixes;

  protected com.ctc.wstx.sr.BasicStreamReader mScanner;

  protected com.ctc.wstx.sr.AttributeCollector mAttrCollector;

  protected com.ctc.wstx.sr.InputElementStack mElemStack;

  protected java.lang.String mEncoding;

  protected java.lang.String mXmlVersion;

  protected boolean mStandalone;

  protected org.xml.sax.ContentHandler mContentHandler;

  protected org.xml.sax.DTDHandler mDTDHandler;

  private org.xml.sax.EntityResolver mEntityResolver;

  private org.xml.sax.ErrorHandler mErrorHandler;

  private org.xml.sax.ext.LexicalHandler mLexicalHandler;

  private org.xml.sax.ext.DeclHandler mDeclHandler;

  protected int mAttrCount;

  protected int mNsCount;

  public com.ctc.wstx.sax.WstxSAXParser(com.ctc.wstx.stax.WstxInputFactory, boolean);
    Code:
       0: aload_0
       1: invokespecial #2                  // Method javax/xml/parsers/SAXParser."<init>":()V
       4: aload_0
       5: iconst_0
       6: putfield      #3                  // Field mNsCount:I
       9: aload_0
      10: aload_1
      11: putfield      #4                  // Field mStaxFactory:Lcom/ctc/wstx/stax/WstxInputFactory;
      14: aload_0
      15: iload_2
      16: putfield      #5                  // Field mFeatNsPrefixes:Z
      19: aload_0
      20: aload_1
      21: invokevirtual #6                  // Method com/ctc/wstx/stax/WstxInputFactory.createPrivateConfig:()Lcom/ctc/wstx/api/ReaderConfig;
      24: putfield      #7                  // Field mConfig:Lcom/ctc/wstx/api/ReaderConfig;
      27: aload_0
      28: getfield      #7                  // Field mConfig:Lcom/ctc/wstx/api/ReaderConfig;
      31: iconst_1
      32: invokevirtual #8                  // Method com/ctc/wstx/api/ReaderConfig.doSupportDTDs:(Z)V
      35: new           #9                  // class com/ctc/wstx/sax/WstxSAXParser$ResolverProxy
      38: dup
      39: aload_0
      40: invokespecial #10                 // Method com/ctc/wstx/sax/WstxSAXParser$ResolverProxy."<init>":(Lcom/ctc/wstx/sax/WstxSAXParser;)V
      43: astore_3
      44: aload_0
      45: getfield      #7                  // Field mConfig:Lcom/ctc/wstx/api/ReaderConfig;
      48: aload_3
      49: invokevirtual #11                 // Method com/ctc/wstx/api/ReaderConfig.setDtdResolver:(Ljavax/xml/stream/XMLResolver;)V
      52: aload_0
      53: getfield      #7                  // Field mConfig:Lcom/ctc/wstx/api/ReaderConfig;
      56: aload_3
      57: invokevirtual #12                 // Method com/ctc/wstx/api/ReaderConfig.setEntityResolver:(Ljavax/xml/stream/XMLResolver;)V
      60: aload_0
      61: getfield      #7                  // Field mConfig:Lcom/ctc/wstx/api/ReaderConfig;
      64: aload_0
      65: invokevirtual #13                 // Method com/ctc/wstx/api/ReaderConfig.setDTDEventListener:(Lcom/ctc/wstx/dtd/DTDEventListener;)V
      68: return

  public com.ctc.wstx.sax.WstxSAXParser();
    Code:
       0: aload_0
       1: new           #14                 // class com/ctc/wstx/stax/WstxInputFactory
       4: dup
       5: invokespecial #15                 // Method com/ctc/wstx/stax/WstxInputFactory."<init>":()V
       8: iconst_0
       9: invokespecial #17                 // Method "<init>":(Lcom/ctc/wstx/stax/WstxInputFactory;Z)V
      12: return

  public final org.xml.sax.Parser getParser();
    Code:
       0: aload_0
       1: areturn

  public final org.xml.sax.XMLReader getXMLReader();
    Code:
       0: aload_0
       1: areturn

  public final com.ctc.wstx.api.ReaderConfig getStaxConfig();
    Code:
       0: aload_0
       1: getfield      #7                  // Field mConfig:Lcom/ctc/wstx/api/ReaderConfig;
       4: areturn

  public boolean isNamespaceAware();
    Code:
       0: aload_0
       1: getfield      #7                  // Field mConfig:Lcom/ctc/wstx/api/ReaderConfig;
       4: invokevirtual #18                 // Method com/ctc/wstx/api/ReaderConfig.willSupportNamespaces:()Z
       7: ireturn

  public boolean isValidating();
    Code:
       0: aload_0
       1: getfield      #7                  // Field mConfig:Lcom/ctc/wstx/api/ReaderConfig;
       4: invokevirtual #19                 // Method com/ctc/wstx/api/ReaderConfig.willValidateWithDTD:()Z
       7: ireturn

  public java.lang.Object getProperty(java.lang.String) throws org.xml.sax.SAXNotRecognizedException, org.xml.sax.SAXNotSupportedException;
    Code:
       0: aload_1
       1: invokestatic  #20                 // Method com/ctc/wstx/sax/SAXProperty.findByUri:(Ljava/lang/String;)Lcom/ctc/wstx/sax/SAXProperty;
       4: astore_2
       5: aload_2
       6: getstatic     #21                 // Field com/ctc/wstx/sax/SAXProperty.DECLARATION_HANDLER:Lcom/ctc/wstx/sax/SAXProperty;
       9: if_acmpne     17
      12: aload_0
      13: getfield      #22                 // Field mDeclHandler:Lorg/xml/sax/ext/DeclHandler;
      16: areturn
      17: aload_2
      18: getstatic     #23                 // Field com/ctc/wstx/sax/SAXProperty.DOCUMENT_XML_VERSION:Lcom/ctc/wstx/sax/SAXProperty;
      21: if_acmpne     29
      24: aload_0
      25: getfield      #24                 // Field mXmlVersion:Ljava/lang/String;
      28: areturn
      29: aload_2
      30: getstatic     #25                 // Field com/ctc/wstx/sax/SAXProperty.DOM_NODE:Lcom/ctc/wstx/sax/SAXProperty;
      33: if_acmpne     38
      36: aconst_null
      37: areturn
      38: aload_2
      39: getstatic     #26                 // Field com/ctc/wstx/sax/SAXProperty.LEXICAL_HANDLER:Lcom/ctc/wstx/sax/SAXProperty;
      42: if_acmpne     50
      45: aload_0
      46: getfield      #27                 // Field mLexicalHandler:Lorg/xml/sax/ext/LexicalHandler;
      49: areturn
      50: aload_2
      51: getstatic     #28                 // Field com/ctc/wstx/sax/SAXProperty.XML_STRING:Lcom/ctc/wstx/sax/SAXProperty;
      54: if_acmpne     59
      57: aconst_null
      58: areturn
      59: new           #29                 // class org/xml/sax/SAXNotRecognizedException
      62: dup
      63: new           #30                 // class java/lang/StringBuilder
      66: dup
      67: invokespecial #31                 // Method java/lang/StringBuilder."<init>":()V
      70: ldc           #32                 // String Property \'
      72: invokevirtual #33                 // Method java/lang/StringBuilder.append:(Ljava/lang/String;)Ljava/lang/StringBuilder;
      75: aload_1
      76: invokevirtual #33                 // Method java/lang/StringBuilder.append:(Ljava/lang/String;)Ljava/lang/StringBuilder;
      79: ldc           #34                 // String \' not recognized
      81: invokevirtual #33                 // Method java/lang/StringBuilder.append:(Ljava/lang/String;)Ljava/lang/StringBuilder;
      84: invokevirtual #35                 // Method java/lang/StringBuilder.toString:()Ljava/lang/String;
      87: invokespecial #36                 // Method org/xml/sax/SAXNotRecognizedException."<init>":(Ljava/lang/String;)V
      90: athrow

  public void setProperty(java.lang.String, java.lang.Object) throws org.xml.sax.SAXNotRecognizedException, org.xml.sax.SAXNotSupportedException;
    Code:
       0: aload_1
       1: invokestatic  #20                 // Method com/ctc/wstx/sax/SAXProperty.findByUri:(Ljava/lang/String;)Lcom/ctc/wstx/sax/SAXProperty;
       4: astore_3
       5: aload_3
       6: getstatic     #21                 // Field com/ctc/wstx/sax/SAXProperty.DECLARATION_HANDLER:Lcom/ctc/wstx/sax/SAXProperty;
       9: if_acmpne     21
      12: aload_0
      13: aload_2
      14: checkcast     #37                 // class org/xml/sax/ext/DeclHandler
      17: putfield      #22                 // Field mDeclHandler:Lorg/xml/sax/ext/DeclHandler;
      20: return
      21: aload_3
      22: getstatic     #23                 // Field com/ctc/wstx/sax/SAXProperty.DOCUMENT_XML_VERSION:Lcom/ctc/wstx/sax/SAXProperty;
      25: if_acmpne     31
      28: goto          99
      31: aload_3
      32: getstatic     #25                 // Field com/ctc/wstx/sax/SAXProperty.DOM_NODE:Lcom/ctc/wstx/sax/SAXProperty;
      35: if_acmpne     41
      38: goto          99
      41: aload_3
      42: getstatic     #26                 // Field com/ctc/wstx/sax/SAXProperty.LEXICAL_HANDLER:Lcom/ctc/wstx/sax/SAXProperty;
      45: if_acmpne     57
      48: aload_0
      49: aload_2
      50: checkcast     #38                 // class org/xml/sax/ext/LexicalHandler
      53: putfield      #27                 // Field mLexicalHandler:Lorg/xml/sax/ext/LexicalHandler;
      56: return
      57: aload_3
      58: getstatic     #28                 // Field com/ctc/wstx/sax/SAXProperty.XML_STRING:Lcom/ctc/wstx/sax/SAXProperty;
      61: if_acmpne     67
      64: goto          99
      67: new           #29                 // class org/xml/sax/SAXNotRecognizedException
      70: dup
      71: new           #30                 // class java/lang/StringBuilder
      74: dup
      75: invokespecial #31                 // Method java/lang/StringBuilder."<init>":()V
      78: ldc           #32                 // String Property \'
      80: invokevirtual #33                 // Method java/lang/StringBuilder.append:(Ljava/lang/String;)Ljava/lang/StringBuilder;
      83: aload_1
      84: invokevirtual #33                 // Method java/lang/StringBuilder.append:(Ljava/lang/String;)Ljava/lang/StringBuilder;
      87: ldc           #34                 // String \' not recognized
      89: invokevirtual #33                 // Method java/lang/StringBuilder.append:(Ljava/lang/String;)Ljava/lang/StringBuilder;
      92: invokevirtual #35                 // Method java/lang/StringBuilder.toString:()Ljava/lang/String;
      95: invokespecial #36                 // Method org/xml/sax/SAXNotRecognizedException."<init>":(Ljava/lang/String;)V
      98: athrow
      99: new           #39                 // class org/xml/sax/SAXNotSupportedException
     102: dup
     103: new           #30                 // class java/lang/StringBuilder
     106: dup
     107: invokespecial #31                 // Method java/lang/StringBuilder."<init>":()V
     110: ldc           #32                 // String Property \'
     112: invokevirtual #33                 // Method java/lang/StringBuilder.append:(Ljava/lang/String;)Ljava/lang/StringBuilder;
     115: aload_1
     116: invokevirtual #33                 // Method java/lang/StringBuilder.append:(Ljava/lang/String;)Ljava/lang/StringBuilder;
     119: ldc           #40                 // String \' is read-only, can not be modified
     121: invokevirtual #33                 // Method java/lang/StringBuilder.append:(Ljava/lang/String;)Ljava/lang/StringBuilder;
     124: invokevirtual #35                 // Method java/lang/StringBuilder.toString:()Ljava/lang/String;
     127: invokespecial #41                 // Method org/xml/sax/SAXNotSupportedException."<init>":(Ljava/lang/String;)V
     130: athrow

  public void parse(org.xml.sax.InputSource, org.xml.sax.HandlerBase) throws org.xml.sax.SAXException, java.io.IOException;
    Code:
       0: aload_2
       1: ifnull        52
       4: aload_0
       5: getfield      #42                 // Field mContentHandler:Lorg/xml/sax/ContentHandler;
       8: ifnonnull     16
      11: aload_0
      12: aload_2
      13: invokevirtual #43                 // Method setDocumentHandler:(Lorg/xml/sax/DocumentHandler;)V
      16: aload_0
      17: getfield      #1                  // Field mEntityResolver:Lorg/xml/sax/EntityResolver;
      20: ifnonnull     28
      23: aload_0
      24: aload_2
      25: invokevirtual #44                 // Method setEntityResolver:(Lorg/xml/sax/EntityResolver;)V
      28: aload_0
      29: getfield      #45                 // Field mErrorHandler:Lorg/xml/sax/ErrorHandler;
      32: ifnonnull     40
      35: aload_0
      36: aload_2
      37: invokevirtual #46                 // Method setErrorHandler:(Lorg/xml/sax/ErrorHandler;)V
      40: aload_0
      41: getfield      #47                 // Field mDTDHandler:Lorg/xml/sax/DTDHandler;
      44: ifnonnull     52
      47: aload_0
      48: aload_2
      49: invokevirtual #48                 // Method setDTDHandler:(Lorg/xml/sax/DTDHandler;)V
      52: aload_0
      53: aload_1
      54: invokevirtual #49                 // Method parse:(Lorg/xml/sax/InputSource;)V
      57: return

  public void parse(org.xml.sax.InputSource, org.xml.sax.helpers.DefaultHandler) throws org.xml.sax.SAXException, java.io.IOException;
    Code:
       0: aload_2
       1: ifnull        52
       4: aload_0
       5: getfield      #42                 // Field mContentHandler:Lorg/xml/sax/ContentHandler;
       8: ifnonnull     16
      11: aload_0
      12: aload_2
      13: invokevirtual #50                 // Method setContentHandler:(Lorg/xml/sax/ContentHandler;)V
      16: aload_0
      17: getfield      #1                  // Field mEntityResolver:Lorg/xml/sax/EntityResolver;
      20: ifnonnull     28
      23: aload_0
      24: aload_2
      25: invokevirtual #44                 // Method setEntityResolver:(Lorg/xml/sax/EntityResolver;)V
      28: aload_0
      29: getfield      #45                 // Field mErrorHandler:Lorg/xml/sax/ErrorHandler;
      32: ifnonnull     40
      35: aload_0
      36: aload_2
      37: invokevirtual #46                 // Method setErrorHandler:(Lorg/xml/sax/ErrorHandler;)V
      40: aload_0
      41: getfield      #47                 // Field mDTDHandler:Lorg/xml/sax/DTDHandler;
      44: ifnonnull     52
      47: aload_0
      48: aload_2
      49: invokevirtual #48                 // Method setDTDHandler:(Lorg/xml/sax/DTDHandler;)V
      52: aload_0
      53: aload_1
      54: invokevirtual #49                 // Method parse:(Lorg/xml/sax/InputSource;)V
      57: return

  public org.xml.sax.ContentHandler getContentHandler();
    Code:
       0: aload_0
       1: getfield      #42                 // Field mContentHandler:Lorg/xml/sax/ContentHandler;
       4: areturn

  public org.xml.sax.DTDHandler getDTDHandler();
    Code:
       0: aload_0
       1: getfield      #47                 // Field mDTDHandler:Lorg/xml/sax/DTDHandler;
       4: areturn

  public org.xml.sax.EntityResolver getEntityResolver();
    Code:
       0: aload_0
       1: getfield      #1                  // Field mEntityResolver:Lorg/xml/sax/EntityResolver;
       4: areturn

  public org.xml.sax.ErrorHandler getErrorHandler();
    Code:
       0: aload_0
       1: getfield      #45                 // Field mErrorHandler:Lorg/xml/sax/ErrorHandler;
       4: areturn

  public boolean getFeature(java.lang.String) throws org.xml.sax.SAXNotRecognizedException;
    Code:
       0: aload_1
       1: invokestatic  #51                 // Method com/ctc/wstx/sax/SAXFeature.findByUri:(Ljava/lang/String;)Lcom/ctc/wstx/sax/SAXFeature;
       4: astore_2
       5: aload_2
       6: getstatic     #52                 // Field com/ctc/wstx/sax/SAXFeature.EXTERNAL_GENERAL_ENTITIES:Lcom/ctc/wstx/sax/SAXFeature;
       9: if_acmpne     20
      12: aload_0
      13: getfield      #7                  // Field mConfig:Lcom/ctc/wstx/api/ReaderConfig;
      16: invokevirtual #53                 // Method com/ctc/wstx/api/ReaderConfig.willSupportExternalEntities:()Z
      19: ireturn
      20: aload_2
      21: getstatic     #54                 // Field com/ctc/wstx/sax/SAXFeature.EXTERNAL_PARAMETER_ENTITIES:Lcom/ctc/wstx/sax/SAXFeature;
      24: if_acmpne     35
      27: aload_0
      28: getfield      #7                  // Field mConfig:Lcom/ctc/wstx/api/ReaderConfig;
      31: invokevirtual #53                 // Method com/ctc/wstx/api/ReaderConfig.willSupportExternalEntities:()Z
      34: ireturn
      35: aload_2
      36: getstatic     #55                 // Field com/ctc/wstx/sax/SAXFeature.IS_STANDALONE:Lcom/ctc/wstx/sax/SAXFeature;
      39: if_acmpne     47
      42: aload_0
      43: getfield      #56                 // Field mStandalone:Z
      46: ireturn
      47: aload_2
      48: getstatic     #57                 // Field com/ctc/wstx/sax/SAXFeature.LEXICAL_HANDLER_PARAMETER_ENTITIES:Lcom/ctc/wstx/sax/SAXFeature;
      51: if_acmpne     56
      54: iconst_0
      55: ireturn
      56: aload_2
      57: getstatic     #58                 // Field com/ctc/wstx/sax/SAXFeature.NAMESPACES:Lcom/ctc/wstx/sax/SAXFeature;
      60: if_acmpne     71
      63: aload_0
      64: getfield      #7                  // Field mConfig:Lcom/ctc/wstx/api/ReaderConfig;
      67: invokevirtual #18                 // Method com/ctc/wstx/api/ReaderConfig.willSupportNamespaces:()Z
      70: ireturn
      71: aload_2
      72: getstatic     #59                 // Field com/ctc/wstx/sax/SAXFeature.NAMESPACE_PREFIXES:Lcom/ctc/wstx/sax/SAXFeature;
      75: if_acmpne     94
      78: aload_0
      79: getfield      #7                  // Field mConfig:Lcom/ctc/wstx/api/ReaderConfig;
      82: invokevirtual #18                 // Method com/ctc/wstx/api/ReaderConfig.willSupportNamespaces:()Z
      85: ifne          92
      88: iconst_1
      89: goto          93
      92: iconst_0
      93: ireturn
      94: aload_2
      95: getstatic     #60                 // Field com/ctc/wstx/sax/SAXFeature.RESOLVE_DTD_URIS:Lcom/ctc/wstx/sax/SAXFeature;
      98: if_acmpne     103
     101: iconst_0
     102: ireturn
     103: aload_2
     104: getstatic     #61                 // Field com/ctc/wstx/sax/SAXFeature.STRING_INTERNING:Lcom/ctc/wstx/sax/SAXFeature;
     107: if_acmpne     112
     110: iconst_1
     111: ireturn
     112: aload_2
     113: getstatic     #62                 // Field com/ctc/wstx/sax/SAXFeature.UNICODE_NORMALIZATION_CHECKING:Lcom/ctc/wstx/sax/SAXFeature;
     116: if_acmpne     121
     119: iconst_0
     120: ireturn
     121: aload_2
     122: getstatic     #63                 // Field com/ctc/wstx/sax/SAXFeature.USE_ATTRIBUTES2:Lcom/ctc/wstx/sax/SAXFeature;
     125: if_acmpne     130
     128: iconst_1
     129: ireturn
     130: aload_2
     131: getstatic     #64                 // Field com/ctc/wstx/sax/SAXFeature.USE_LOCATOR2:Lcom/ctc/wstx/sax/SAXFeature;
     134: if_acmpne     139
     137: iconst_1
     138: ireturn
     139: aload_2
     140: getstatic     #65                 // Field com/ctc/wstx/sax/SAXFeature.USE_ENTITY_RESOLVER2:Lcom/ctc/wstx/sax/SAXFeature;
     143: if_acmpne     148
     146: iconst_1
     147: ireturn
     148: aload_2
     149: getstatic     #66                 // Field com/ctc/wstx/sax/SAXFeature.VALIDATION:Lcom/ctc/wstx/sax/SAXFeature;
     152: if_acmpne     163
     155: aload_0
     156: getfield      #7                  // Field mConfig:Lcom/ctc/wstx/api/ReaderConfig;
     159: invokevirtual #19                 // Method com/ctc/wstx/api/ReaderConfig.willValidateWithDTD:()Z
     162: ireturn
     163: aload_2
     164: getstatic     #67                 // Field com/ctc/wstx/sax/SAXFeature.XMLNS_URIS:Lcom/ctc/wstx/sax/SAXFeature;
     167: if_acmpne     172
     170: iconst_1
     171: ireturn
     172: aload_2
     173: getstatic     #68                 // Field com/ctc/wstx/sax/SAXFeature.XML_1_1:Lcom/ctc/wstx/sax/SAXFeature;
     176: if_acmpne     181
     179: iconst_1
     180: ireturn
     181: new           #29                 // class org/xml/sax/SAXNotRecognizedException
     184: dup
     185: new           #30                 // class java/lang/StringBuilder
     188: dup
     189: invokespecial #31                 // Method java/lang/StringBuilder."<init>":()V
     192: ldc           #69                 // String Feature \'
     194: invokevirtual #33                 // Method java/lang/StringBuilder.append:(Ljava/lang/String;)Ljava/lang/StringBuilder;
     197: aload_1
     198: invokevirtual #33                 // Method java/lang/StringBuilder.append:(Ljava/lang/String;)Ljava/lang/StringBuilder;
     201: ldc           #34                 // String \' not recognized
     203: invokevirtual #33                 // Method java/lang/StringBuilder.append:(Ljava/lang/String;)Ljava/lang/StringBuilder;
     206: invokevirtual #35                 // Method java/lang/StringBuilder.toString:()Ljava/lang/String;
     209: invokespecial #36                 // Method org/xml/sax/SAXNotRecognizedException."<init>":(Ljava/lang/String;)V
     212: athrow

  public void setContentHandler(org.xml.sax.ContentHandler);
    Code:
       0: aload_0
       1: aload_1
       2: putfield      #42                 // Field mContentHandler:Lorg/xml/sax/ContentHandler;
       5: return

  public void setDTDHandler(org.xml.sax.DTDHandler);
    Code:
       0: aload_0
       1: aload_1
       2: putfield      #47                 // Field mDTDHandler:Lorg/xml/sax/DTDHandler;
       5: return

  public void setEntityResolver(org.xml.sax.EntityResolver);
    Code:
       0: aload_0
       1: aload_1
       2: putfield      #1                  // Field mEntityResolver:Lorg/xml/sax/EntityResolver;
       5: return

  public void setErrorHandler(org.xml.sax.ErrorHandler);
    Code:
       0: aload_0
       1: aload_1
       2: putfield      #45                 // Field mErrorHandler:Lorg/xml/sax/ErrorHandler;
       5: return

  public void setFeature(java.lang.String, boolean) throws org.xml.sax.SAXNotRecognizedException, org.xml.sax.SAXNotSupportedException;
    Code:
       0: iconst_0
       1: istore_3
       2: iconst_0
       3: istore        4
       5: aload_1
       6: invokestatic  #51                 // Method com/ctc/wstx/sax/SAXFeature.findByUri:(Ljava/lang/String;)Lcom/ctc/wstx/sax/SAXFeature;
       9: astore        5
      11: aload         5
      13: getstatic     #52                 // Field com/ctc/wstx/sax/SAXFeature.EXTERNAL_GENERAL_ENTITIES:Lcom/ctc/wstx/sax/SAXFeature;
      16: if_acmpne     30
      19: aload_0
      20: getfield      #7                  // Field mConfig:Lcom/ctc/wstx/api/ReaderConfig;
      23: iload_2
      24: invokevirtual #70                 // Method com/ctc/wstx/api/ReaderConfig.doSupportExternalEntities:(Z)V
      27: goto          274
      30: aload         5
      32: getstatic     #54                 // Field com/ctc/wstx/sax/SAXFeature.EXTERNAL_PARAMETER_ENTITIES:Lcom/ctc/wstx/sax/SAXFeature;
      35: if_acmpne     41
      38: goto          274
      41: aload         5
      43: getstatic     #55                 // Field com/ctc/wstx/sax/SAXFeature.IS_STANDALONE:Lcom/ctc/wstx/sax/SAXFeature;
      46: if_acmpne     55
      49: iconst_1
      50: istore        4
      52: goto          274
      55: aload         5
      57: getstatic     #57                 // Field com/ctc/wstx/sax/SAXFeature.LEXICAL_HANDLER_PARAMETER_ENTITIES:Lcom/ctc/wstx/sax/SAXFeature;
      60: if_acmpne     66
      63: goto          274
      66: aload         5
      68: getstatic     #58                 // Field com/ctc/wstx/sax/SAXFeature.NAMESPACES:Lcom/ctc/wstx/sax/SAXFeature;
      71: if_acmpne     85
      74: aload_0
      75: getfield      #7                  // Field mConfig:Lcom/ctc/wstx/api/ReaderConfig;
      78: iload_2
      79: invokevirtual #71                 // Method com/ctc/wstx/api/ReaderConfig.doSupportNamespaces:(Z)V
      82: goto          274
      85: aload         5
      87: getstatic     #59                 // Field com/ctc/wstx/sax/SAXFeature.NAMESPACE_PREFIXES:Lcom/ctc/wstx/sax/SAXFeature;
      90: if_acmpne     101
      93: aload_0
      94: iload_2
      95: putfield      #5                  // Field mFeatNsPrefixes:Z
      98: goto          274
     101: aload         5
     103: getstatic     #60                 // Field com/ctc/wstx/sax/SAXFeature.RESOLVE_DTD_URIS:Lcom/ctc/wstx/sax/SAXFeature;
     106: if_acmpne     112
     109: goto          274
     112: aload         5
     114: getstatic     #61                 // Field com/ctc/wstx/sax/SAXFeature.STRING_INTERNING:Lcom/ctc/wstx/sax/SAXFeature;
     117: if_acmpne     133
     120: iload_2
     121: ifne          128
     124: iconst_1
     125: goto          129
     128: iconst_0
     129: istore_3
     130: goto          274
     133: aload         5
     135: getstatic     #62                 // Field com/ctc/wstx/sax/SAXFeature.UNICODE_NORMALIZATION_CHECKING:Lcom/ctc/wstx/sax/SAXFeature;
     138: if_acmpne     146
     141: iload_2
     142: istore_3
     143: goto          274
     146: aload         5
     148: getstatic     #63                 // Field com/ctc/wstx/sax/SAXFeature.USE_ATTRIBUTES2:Lcom/ctc/wstx/sax/SAXFeature;
     151: if_acmpne     160
     154: iconst_1
     155: istore        4
     157: goto          274
     160: aload         5
     162: getstatic     #64                 // Field com/ctc/wstx/sax/SAXFeature.USE_LOCATOR2:Lcom/ctc/wstx/sax/SAXFeature;
     165: if_acmpne     174
     168: iconst_1
     169: istore        4
     171: goto          274
     174: aload         5
     176: getstatic     #65                 // Field com/ctc/wstx/sax/SAXFeature.USE_ENTITY_RESOLVER2:Lcom/ctc/wstx/sax/SAXFeature;
     179: if_acmpne     188
     182: iconst_1
     183: istore        4
     185: goto          274
     188: aload         5
     190: getstatic     #66                 // Field com/ctc/wstx/sax/SAXFeature.VALIDATION:Lcom/ctc/wstx/sax/SAXFeature;
     193: if_acmpne     207
     196: aload_0
     197: getfield      #7                  // Field mConfig:Lcom/ctc/wstx/api/ReaderConfig;
     200: iload_2
     201: invokevirtual #72                 // Method com/ctc/wstx/api/ReaderConfig.doValidateWithDTD:(Z)V
     204: goto          274
     207: aload         5
     209: getstatic     #67                 // Field com/ctc/wstx/sax/SAXFeature.XMLNS_URIS:Lcom/ctc/wstx/sax/SAXFeature;
     212: if_acmpne     228
     215: iload_2
     216: ifne          223
     219: iconst_1
     220: goto          224
     223: iconst_0
     224: istore_3
     225: goto          274
     228: aload         5
     230: getstatic     #68                 // Field com/ctc/wstx/sax/SAXFeature.XML_1_1:Lcom/ctc/wstx/sax/SAXFeature;
     233: if_acmpne     242
     236: iconst_1
     237: istore        4
     239: goto          274
     242: new           #29                 // class org/xml/sax/SAXNotRecognizedException
     245: dup
     246: new           #30                 // class java/lang/StringBuilder
     249: dup
     250: invokespecial #31                 // Method java/lang/StringBuilder."<init>":()V
     253: ldc           #69                 // String Feature \'
     255: invokevirtual #33                 // Method java/lang/StringBuilder.append:(Ljava/lang/String;)Ljava/lang/StringBuilder;
     258: aload_1
     259: invokevirtual #33                 // Method java/lang/StringBuilder.append:(Ljava/lang/String;)Ljava/lang/StringBuilder;
     262: ldc           #34                 // String \' not recognized
     264: invokevirtual #33                 // Method java/lang/StringBuilder.append:(Ljava/lang/String;)Ljava/lang/StringBuilder;
     267: invokevirtual #35                 // Method java/lang/StringBuilder.toString:()Ljava/lang/String;
     270: invokespecial #36                 // Method org/xml/sax/SAXNotRecognizedException."<init>":(Ljava/lang/String;)V
     273: athrow
     274: iload         4
     276: ifeq          311
     279: new           #39                 // class org/xml/sax/SAXNotSupportedException
     282: dup
     283: new           #30                 // class java/lang/StringBuilder
     286: dup
     287: invokespecial #31                 // Method java/lang/StringBuilder."<init>":()V
     290: ldc           #69                 // String Feature \'
     292: invokevirtual #33                 // Method java/lang/StringBuilder.append:(Ljava/lang/String;)Ljava/lang/StringBuilder;
     295: aload_1
     296: invokevirtual #33                 // Method java/lang/StringBuilder.append:(Ljava/lang/String;)Ljava/lang/StringBuilder;
     299: ldc           #40                 // String \' is read-only, can not be modified
     301: invokevirtual #33                 // Method java/lang/StringBuilder.append:(Ljava/lang/String;)Ljava/lang/StringBuilder;
     304: invokevirtual #35                 // Method java/lang/StringBuilder.toString:()Ljava/lang/String;
     307: invokespecial #41                 // Method org/xml/sax/SAXNotSupportedException."<init>":(Ljava/lang/String;)V
     310: athrow
     311: iload_3
     312: ifeq          356
     315: new           #39                 // class org/xml/sax/SAXNotSupportedException
     318: dup
     319: new           #30                 // class java/lang/StringBuilder
     322: dup
     323: invokespecial #31                 // Method java/lang/StringBuilder."<init>":()V
     326: ldc           #73                 // String Trying to set invalid value for feature \'
     328: invokevirtual #33                 // Method java/lang/StringBuilder.append:(Ljava/lang/String;)Ljava/lang/StringBuilder;
     331: aload_1
     332: invokevirtual #33                 // Method java/lang/StringBuilder.append:(Ljava/lang/String;)Ljava/lang/StringBuilder;
     335: ldc           #74                 // String \', \'
     337: invokevirtual #33                 // Method java/lang/StringBuilder.append:(Ljava/lang/String;)Ljava/lang/StringBuilder;
     340: iload_2
     341: invokevirtual #75                 // Method java/lang/StringBuilder.append:(Z)Ljava/lang/StringBuilder;
     344: ldc           #76                 // String \'
     346: invokevirtual #33                 // Method java/lang/StringBuilder.append:(Ljava/lang/String;)Ljava/lang/StringBuilder;
     349: invokevirtual #35                 // Method java/lang/StringBuilder.toString:()Ljava/lang/String;
     352: invokespecial #41                 // Method org/xml/sax/SAXNotSupportedException."<init>":(Ljava/lang/String;)V
     355: athrow
     356: return

  public void parse(org.xml.sax.InputSource) throws org.xml.sax.SAXException;
    Code:
       0: aload_0
       1: aconst_null
       2: putfield      #77                 // Field mScanner:Lcom/ctc/wstx/sr/BasicStreamReader;
       5: aload_1
       6: invokevirtual #78                 // Method org/xml/sax/InputSource.getSystemId:()Ljava/lang/String;
       9: astore_2
      10: aload_0
      11: getfield      #7                  // Field mConfig:Lcom/ctc/wstx/api/ReaderConfig;
      14: astore_3
      15: aconst_null
      16: astore        4
      18: aconst_null
      19: astore        5
      21: aload_1
      22: invokevirtual #79                 // Method org/xml/sax/InputSource.getCharacterStream:()Ljava/io/Reader;
      25: astore        6
      27: aload         6
      29: ifnonnull     96
      32: aload_1
      33: invokevirtual #80                 // Method org/xml/sax/InputSource.getByteStream:()Ljava/io/InputStream;
      36: astore        5
      38: aload         5
      40: ifnonnull     96
      43: aload_2
      44: ifnonnull     57
      47: new           #81                 // class org/xml/sax/SAXException
      50: dup
      51: ldc           #82                 // String Invalid InputSource passed: neither character or byte stream passed, nor system id specified
      53: invokespecial #83                 // Method org/xml/sax/SAXException."<init>":(Ljava/lang/String;)V
      56: athrow
      57: aload_2
      58: invokestatic  #84                 // Method com/ctc/wstx/util/URLUtil.urlFromSystemId:(Ljava/lang/String;)Ljava/net/URL;
      61: astore        4
      63: aload         4
      65: invokestatic  #85                 // Method com/ctc/wstx/util/URLUtil.inputStreamFromURL:(Ljava/net/URL;)Ljava/io/InputStream;
      68: astore        5
      70: goto          96
      73: astore        7
      75: new           #81                 // class org/xml/sax/SAXException
      78: dup
      79: aload         7
      81: invokespecial #87                 // Method org/xml/sax/SAXException."<init>":(Ljava/lang/Exception;)V
      84: astore        8
      86: aload         8
      88: aload         7
      90: invokestatic  #88                 // Method com/ctc/wstx/util/ExceptionUtil.setInitCause:(Ljava/lang/Throwable;Ljava/lang/Throwable;)V
      93: aload         8
      95: athrow
      96: aload_0
      97: getfield      #42                 // Field mContentHandler:Lorg/xml/sax/ContentHandler;
     100: ifnull        122
     103: aload_0
     104: getfield      #42                 // Field mContentHandler:Lorg/xml/sax/ContentHandler;
     107: aload_0
     108: invokeinterface #89,  2           // InterfaceMethod org/xml/sax/ContentHandler.setDocumentLocator:(Lorg/xml/sax/Locator;)V
     113: aload_0
     114: getfield      #42                 // Field mContentHandler:Lorg/xml/sax/ContentHandler;
     117: invokeinterface #90,  1           // InterfaceMethod org/xml/sax/ContentHandler.startDocument:()V
     122: aload_3
     123: invokevirtual #91                 // Method com/ctc/wstx/api/ReaderConfig.resetState:()V
     126: aload_1
     127: invokevirtual #92                 // Method org/xml/sax/InputSource.getEncoding:()Ljava/lang/String;
     130: astore        7
     132: aload_1
     133: invokevirtual #93                 // Method org/xml/sax/InputSource.getPublicId:()Ljava/lang/String;
     136: astore        8
     138: aload         6
     140: ifnonnull     167
     143: aload         7
     145: ifnull        167
     148: aload         7
     150: invokevirtual #94                 // Method java/lang/String.length:()I
     153: ifle          167
     156: aload_3
     157: aload         5
     159: iconst_0
     160: aload         7
     162: invokestatic  #95                 // Method com/ctc/wstx/io/DefaultInputResolver.constructOptimizedReader:(Lcom/ctc/wstx/api/ReaderConfig;Ljava/io/InputStream;ZLjava/lang/String;)Ljava/io/Reader;
     165: astore        6
     167: aload_2
     168: aload         4
     170: invokestatic  #96                 // Method com/ctc/wstx/io/SystemId.construct:(Ljava/lang/String;Ljava/net/URL;)Lcom/ctc/wstx/io/SystemId;
     173: astore        10
     175: aload         6
     177: ifnull        217
     180: aload         8
     182: aload         10
     184: aload         6
     186: aload         7
     188: invokestatic  #97                 // Method com/ctc/wstx/io/ReaderBootstrapper.getInstance:(Ljava/lang/String;Lcom/ctc/wstx/io/SystemId;Ljava/io/Reader;Ljava/lang/String;)Lcom/ctc/wstx/io/ReaderBootstrapper;
     191: astore        9
     193: aload_0
     194: aload_0
     195: getfield      #4                  // Field mStaxFactory:Lcom/ctc/wstx/stax/WstxInputFactory;
     198: aload_3
     199: aload         10
     201: aload         9
     203: iconst_0
     204: iconst_0
     205: invokevirtual #98                 // Method com/ctc/wstx/stax/WstxInputFactory.createSR:(Lcom/ctc/wstx/api/ReaderConfig;Lcom/ctc/wstx/io/SystemId;Lcom/ctc/wstx/io/InputBootstrapper;ZZ)Lorg/codehaus/stax2/XMLStreamReader2;
     208: checkcast     #99                 // class com/ctc/wstx/sr/BasicStreamReader
     211: putfield      #77                 // Field mScanner:Lcom/ctc/wstx/sr/BasicStreamReader;
     214: goto          249
     217: aload         8
     219: aload         10
     221: aload         5
     223: invokestatic  #100                // Method com/ctc/wstx/io/StreamBootstrapper.getInstance:(Ljava/lang/String;Lcom/ctc/wstx/io/SystemId;Ljava/io/InputStream;)Lcom/ctc/wstx/io/StreamBootstrapper;
     226: astore        9
     228: aload_0
     229: aload_0
     230: getfield      #4                  // Field mStaxFactory:Lcom/ctc/wstx/stax/WstxInputFactory;
     233: aload_3
     234: aload         10
     236: aload         9
     238: iconst_0
     239: iconst_0
     240: invokevirtual #98                 // Method com/ctc/wstx/stax/WstxInputFactory.createSR:(Lcom/ctc/wstx/api/ReaderConfig;Lcom/ctc/wstx/io/SystemId;Lcom/ctc/wstx/io/InputBootstrapper;ZZ)Lorg/codehaus/stax2/XMLStreamReader2;
     243: checkcast     #99                 // class com/ctc/wstx/sr/BasicStreamReader
     246: putfield      #77                 // Field mScanner:Lcom/ctc/wstx/sr/BasicStreamReader;
     249: aload_0
     250: getfield      #77                 // Field mScanner:Lcom/ctc/wstx/sr/BasicStreamReader;
     253: invokevirtual #101                // Method com/ctc/wstx/sr/BasicStreamReader.getEncoding:()Ljava/lang/String;
     256: astore        11
     258: aload         11
     260: ifnonnull     272
     263: aload_0
     264: getfield      #77                 // Field mScanner:Lcom/ctc/wstx/sr/BasicStreamReader;
     267: invokevirtual #102                // Method com/ctc/wstx/sr/BasicStreamReader.getCharacterEncodingScheme:()Ljava/lang/String;
     270: astore        11
     272: aload_0
     273: aload         11
     275: putfield      #103                // Field mEncoding:Ljava/lang/String;
     278: aload_0
     279: aload_0
     280: getfield      #77                 // Field mScanner:Lcom/ctc/wstx/sr/BasicStreamReader;
     283: invokevirtual #104                // Method com/ctc/wstx/sr/BasicStreamReader.getVersion:()Ljava/lang/String;
     286: putfield      #24                 // Field mXmlVersion:Ljava/lang/String;
     289: aload_0
     290: aload_0
     291: getfield      #77                 // Field mScanner:Lcom/ctc/wstx/sr/BasicStreamReader;
     294: invokevirtual #105                // Method com/ctc/wstx/sr/BasicStreamReader.standaloneSet:()Z
     297: putfield      #56                 // Field mStandalone:Z
     300: aload_0
     301: aload_0
     302: getfield      #77                 // Field mScanner:Lcom/ctc/wstx/sr/BasicStreamReader;
     305: invokevirtual #106                // Method com/ctc/wstx/sr/BasicStreamReader.getAttributeCollector:()Lcom/ctc/wstx/sr/AttributeCollector;
     308: putfield      #107                // Field mAttrCollector:Lcom/ctc/wstx/sr/AttributeCollector;
     311: aload_0
     312: aload_0
     313: getfield      #77                 // Field mScanner:Lcom/ctc/wstx/sr/BasicStreamReader;
     316: invokevirtual #108                // Method com/ctc/wstx/sr/BasicStreamReader.getInputElementStack:()Lcom/ctc/wstx/sr/InputElementStack;
     319: putfield      #109                // Field mElemStack:Lcom/ctc/wstx/sr/InputElementStack;
     322: aload_0
     323: invokespecial #110                // Method fireEvents:()V
     326: aload_0
     327: getfield      #42                 // Field mContentHandler:Lorg/xml/sax/ContentHandler;
     330: ifnull        342
     333: aload_0
     334: getfield      #42                 // Field mContentHandler:Lorg/xml/sax/ContentHandler;
     337: invokeinterface #111,  1          // InterfaceMethod org/xml/sax/ContentHandler.endDocument:()V
     342: aload_0
     343: getfield      #77                 // Field mScanner:Lcom/ctc/wstx/sr/BasicStreamReader;
     346: ifnull        370
     349: aload_0
     350: getfield      #77                 // Field mScanner:Lcom/ctc/wstx/sr/BasicStreamReader;
     353: astore        7
     355: aload_0
     356: aconst_null
     357: putfield      #77                 // Field mScanner:Lcom/ctc/wstx/sr/BasicStreamReader;
     360: aload         7
     362: invokevirtual #112                // Method com/ctc/wstx/sr/BasicStreamReader.close:()V
     365: goto          370
     368: astore        8
     370: aload         6
     372: ifnull        385
     375: aload         6
     377: invokevirtual #114                // Method java/io/Reader.close:()V
     380: goto          385
     383: astore        7
     385: aload         5
     387: ifnull        652
     390: aload         5
     392: invokevirtual #115                // Method java/io/InputStream.close:()V
     395: goto          652
     398: astore        7
     400: goto          652
     403: astore        7
     405: aload_0
     406: aload         7
     408: invokespecial #116                // Method throwSaxException:(Ljava/lang/Exception;)V
     411: aload_0
     412: getfield      #42                 // Field mContentHandler:Lorg/xml/sax/ContentHandler;
     415: ifnull        427
     418: aload_0
     419: getfield      #42                 // Field mContentHandler:Lorg/xml/sax/ContentHandler;
     422: invokeinterface #111,  1          // InterfaceMethod org/xml/sax/ContentHandler.endDocument:()V
     427: aload_0
     428: getfield      #77                 // Field mScanner:Lcom/ctc/wstx/sr/BasicStreamReader;
     431: ifnull        455
     434: aload_0
     435: getfield      #77                 // Field mScanner:Lcom/ctc/wstx/sr/BasicStreamReader;
     438: astore        7
     440: aload_0
     441: aconst_null
     442: putfield      #77                 // Field mScanner:Lcom/ctc/wstx/sr/BasicStreamReader;
     445: aload         7
     447: invokevirtual #112                // Method com/ctc/wstx/sr/BasicStreamReader.close:()V
     450: goto          455
     453: astore        8
     455: aload         6
     457: ifnull        470
     460: aload         6
     462: invokevirtual #114                // Method java/io/Reader.close:()V
     465: goto          470
     468: astore        7
     470: aload         5
     472: ifnull        652
     475: aload         5
     477: invokevirtual #115                // Method java/io/InputStream.close:()V
     480: goto          652
     483: astore        7
     485: goto          652
     488: astore        7
     490: aload_0
     491: aload         7
     493: invokespecial #116                // Method throwSaxException:(Ljava/lang/Exception;)V
     496: aload_0
     497: getfield      #42                 // Field mContentHandler:Lorg/xml/sax/ContentHandler;
     500: ifnull        512
     503: aload_0
     504: getfield      #42                 // Field mContentHandler:Lorg/xml/sax/ContentHandler;
     507: invokeinterface #111,  1          // InterfaceMethod org/xml/sax/ContentHandler.endDocument:()V
     512: aload_0
     513: getfield      #77                 // Field mScanner:Lcom/ctc/wstx/sr/BasicStreamReader;
     516: ifnull        540
     519: aload_0
     520: getfield      #77                 // Field mScanner:Lcom/ctc/wstx/sr/BasicStreamReader;
     523: astore        7
     525: aload_0
     526: aconst_null
     527: putfield      #77                 // Field mScanner:Lcom/ctc/wstx/sr/BasicStreamReader;
     530: aload         7
     532: invokevirtual #112                // Method com/ctc/wstx/sr/BasicStreamReader.close:()V
     535: goto          540
     538: astore        8
     540: aload         6
     542: ifnull        555
     545: aload         6
     547: invokevirtual #114                // Method java/io/Reader.close:()V
     550: goto          555
     553: astore        7
     555: aload         5
     557: ifnull        652
     560: aload         5
     562: invokevirtual #115                // Method java/io/InputStream.close:()V
     565: goto          652
     568: astore        7
     570: goto          652
     573: astore        12
     575: aload_0
     576: getfield      #42                 // Field mContentHandler:Lorg/xml/sax/ContentHandler;
     579: ifnull        591
     582: aload_0
     583: getfield      #42                 // Field mContentHandler:Lorg/xml/sax/ContentHandler;
     586: invokeinterface #111,  1          // InterfaceMethod org/xml/sax/ContentHandler.endDocument:()V
     591: aload_0
     592: getfield      #77                 // Field mScanner:Lcom/ctc/wstx/sr/BasicStreamReader;
     595: ifnull        619
     598: aload_0
     599: getfield      #77                 // Field mScanner:Lcom/ctc/wstx/sr/BasicStreamReader;
     602: astore        13
     604: aload_0
     605: aconst_null
     606: putfield      #77                 // Field mScanner:Lcom/ctc/wstx/sr/BasicStreamReader;
     609: aload         13
     611: invokevirtual #112                // Method com/ctc/wstx/sr/BasicStreamReader.close:()V
     614: goto          619
     617: astore        14
     619: aload         6
     621: ifnull        634
     624: aload         6
     626: invokevirtual #114                // Method java/io/Reader.close:()V
     629: goto          634
     632: astore        13
     634: aload         5
     636: ifnull        649
     639: aload         5
     641: invokevirtual #115                // Method java/io/InputStream.close:()V
     644: goto          649
     647: astore        13
     649: aload         12
     651: athrow
     652: return
    Exception table:
       from    to  target type
          57    70    73   Class java/io/IOException
         360   365   368   Class javax/xml/stream/XMLStreamException
         375   380   383   Class java/io/IOException
         390   395   398   Class java/io/IOException
         126   326   403   Class java/io/IOException
         445   450   453   Class javax/xml/stream/XMLStreamException
         460   465   468   Class java/io/IOException
         475   480   483   Class java/io/IOException
         126   326   488   Class javax/xml/stream/XMLStreamException
         530   535   538   Class javax/xml/stream/XMLStreamException
         545   550   553   Class java/io/IOException
         560   565   568   Class java/io/IOException
         126   326   573   any
         403   411   573   any
         488   496   573   any
         609   614   617   Class javax/xml/stream/XMLStreamException
         624   629   632   Class java/io/IOException
         639   644   647   Class java/io/IOException
         573   575   573   any

  public void parse(java.lang.String) throws org.xml.sax.SAXException;
    Code:
       0: new           #117                // class org/xml/sax/InputSource
       3: dup
       4: aload_1
       5: invokespecial #118                // Method org/xml/sax/InputSource."<init>":(Ljava/lang/String;)V
       8: astore_2
       9: aload_0
      10: aload_2
      11: invokevirtual #49                 // Method parse:(Lorg/xml/sax/InputSource;)V
      14: return

  private final void fireEvents() throws java.io.IOException, org.xml.sax.SAXException, javax.xml.stream.XMLStreamException;
    Code:
       0: aload_0
       1: getfield      #7                  // Field mConfig:Lcom/ctc/wstx/api/ReaderConfig;
       4: iconst_0
       5: invokevirtual #119                // Method com/ctc/wstx/api/ReaderConfig.doParseLazily:(Z)V
       8: aload_0
       9: getfield      #77                 // Field mScanner:Lcom/ctc/wstx/sr/BasicStreamReader;
      12: invokevirtual #120                // Method com/ctc/wstx/sr/BasicStreamReader.next:()I
      15: dup
      16: istore_1
      17: iconst_1
      18: if_icmpeq     30
      21: aload_0
      22: iload_1
      23: iconst_0
      24: invokespecial #122                // Method fireAuxEvent:(IZ)V
      27: goto          8
      30: aload_0
      31: invokespecial #123                // Method fireStartTag:()V
      34: iconst_1
      35: istore_2
      36: aload_0
      37: getfield      #77                 // Field mScanner:Lcom/ctc/wstx/sr/BasicStreamReader;
      40: invokevirtual #120                // Method com/ctc/wstx/sr/BasicStreamReader.next:()I
      43: istore_1
      44: iload_1
      45: iconst_1
      46: if_icmpne     59
      49: aload_0
      50: invokespecial #123                // Method fireStartTag:()V
      53: iinc          2, 1
      56: goto          36
      59: iload_1
      60: iconst_2
      61: if_icmpne     86
      64: aload_0
      65: getfield      #77                 // Field mScanner:Lcom/ctc/wstx/sr/BasicStreamReader;
      68: aload_0
      69: getfield      #42                 // Field mContentHandler:Lorg/xml/sax/ContentHandler;
      72: invokevirtual #124                // Method com/ctc/wstx/sr/BasicStreamReader.fireSaxEndElement:(Lorg/xml/sax/ContentHandler;)V
      75: iinc          2, -1
      78: iload_2
      79: iconst_1
      80: if_icmpge     36
      83: goto          114
      86: iload_1
      87: iconst_4
      88: if_icmpne     105
      91: aload_0
      92: getfield      #77                 // Field mScanner:Lcom/ctc/wstx/sr/BasicStreamReader;
      95: aload_0
      96: getfield      #42                 // Field mContentHandler:Lorg/xml/sax/ContentHandler;
      99: invokevirtual #125                // Method com/ctc/wstx/sr/BasicStreamReader.fireSaxCharacterEvents:(Lorg/xml/sax/ContentHandler;)V
     102: goto          36
     105: aload_0
     106: iload_1
     107: iconst_1
     108: invokespecial #122                // Method fireAuxEvent:(IZ)V
     111: goto          36
     114: aload_0
     115: getfield      #77                 // Field mScanner:Lcom/ctc/wstx/sr/BasicStreamReader;
     118: invokevirtual #120                // Method com/ctc/wstx/sr/BasicStreamReader.next:()I
     121: istore_1
     122: iload_1
     123: bipush        8
     125: if_icmpne     131
     128: goto          149
     131: iload_1
     132: bipush        6
     134: if_icmpne     140
     137: goto          114
     140: aload_0
     141: iload_1
     142: iconst_0
     143: invokespecial #122                // Method fireAuxEvent:(IZ)V
     146: goto          114
     149: return

  private final void fireAuxEvent(int, boolean) throws java.io.IOException, org.xml.sax.SAXException, javax.xml.stream.XMLStreamException;
    Code:
       0: iload_1
       1: tableswitch   { // 3 to 12
                     3: 201
                     4: 259
                     5: 56
                     6: 215
                     7: 259
                     8: 259
                     9: 233
                    10: 259
                    11: 123
                    12: 70
               default: 259
          }
      56: aload_0
      57: getfield      #77                 // Field mScanner:Lcom/ctc/wstx/sr/BasicStreamReader;
      60: aload_0
      61: getfield      #27                 // Field mLexicalHandler:Lorg/xml/sax/ext/LexicalHandler;
      64: invokevirtual #126                // Method com/ctc/wstx/sr/BasicStreamReader.fireSaxCommentEvent:(Lorg/xml/sax/ext/LexicalHandler;)V
      67: goto          325
      70: aload_0
      71: getfield      #27                 // Field mLexicalHandler:Lorg/xml/sax/ext/LexicalHandler;
      74: ifnull        109
      77: aload_0
      78: getfield      #27                 // Field mLexicalHandler:Lorg/xml/sax/ext/LexicalHandler;
      81: invokeinterface #127,  1          // InterfaceMethod org/xml/sax/ext/LexicalHandler.startCDATA:()V
      86: aload_0
      87: getfield      #77                 // Field mScanner:Lcom/ctc/wstx/sr/BasicStreamReader;
      90: aload_0
      91: getfield      #42                 // Field mContentHandler:Lorg/xml/sax/ContentHandler;
      94: invokevirtual #125                // Method com/ctc/wstx/sr/BasicStreamReader.fireSaxCharacterEvents:(Lorg/xml/sax/ContentHandler;)V
      97: aload_0
      98: getfield      #27                 // Field mLexicalHandler:Lorg/xml/sax/ext/LexicalHandler;
     101: invokeinterface #128,  1          // InterfaceMethod org/xml/sax/ext/LexicalHandler.endCDATA:()V
     106: goto          325
     109: aload_0
     110: getfield      #77                 // Field mScanner:Lcom/ctc/wstx/sr/BasicStreamReader;
     113: aload_0
     114: getfield      #42                 // Field mContentHandler:Lorg/xml/sax/ContentHandler;
     117: invokevirtual #125                // Method com/ctc/wstx/sr/BasicStreamReader.fireSaxCharacterEvents:(Lorg/xml/sax/ContentHandler;)V
     120: goto          325
     123: aload_0
     124: getfield      #27                 // Field mLexicalHandler:Lorg/xml/sax/ext/LexicalHandler;
     127: ifnull        325
     130: aload_0
     131: getfield      #77                 // Field mScanner:Lcom/ctc/wstx/sr/BasicStreamReader;
     134: invokevirtual #129                // Method com/ctc/wstx/sr/BasicStreamReader.getDTDRootName:()Ljava/lang/String;
     137: astore_3
     138: aload_0
     139: getfield      #77                 // Field mScanner:Lcom/ctc/wstx/sr/BasicStreamReader;
     142: invokevirtual #130                // Method com/ctc/wstx/sr/BasicStreamReader.getDTDSystemId:()Ljava/lang/String;
     145: astore        4
     147: aload_0
     148: getfield      #77                 // Field mScanner:Lcom/ctc/wstx/sr/BasicStreamReader;
     151: invokevirtual #131                // Method com/ctc/wstx/sr/BasicStreamReader.getDTDPublicId:()Ljava/lang/String;
     154: astore        5
     156: aload_0
     157: getfield      #27                 // Field mLexicalHandler:Lorg/xml/sax/ext/LexicalHandler;
     160: aload_3
     161: aload         5
     163: aload         4
     165: invokeinterface #132,  4          // InterfaceMethod org/xml/sax/ext/LexicalHandler.startDTD:(Ljava/lang/String;Ljava/lang/String;Ljava/lang/String;)V
     170: aload_0
     171: getfield      #77                 // Field mScanner:Lcom/ctc/wstx/sr/BasicStreamReader;
     174: invokevirtual #133                // Method com/ctc/wstx/sr/BasicStreamReader.getDTDInfo:()Lorg/codehaus/stax2/DTDInfo;
     177: pop
     178: goto          189
     181: astore        6
     183: aload         6
     185: invokevirtual #135                // Method com/ctc/wstx/sax/WrappedSaxException.getSaxException:()Lorg/xml/sax/SAXException;
     188: athrow
     189: aload_0
     190: getfield      #27                 // Field mLexicalHandler:Lorg/xml/sax/ext/LexicalHandler;
     193: invokeinterface #136,  1          // InterfaceMethod org/xml/sax/ext/LexicalHandler.endDTD:()V
     198: goto          325
     201: aload_0
     202: getfield      #77                 // Field mScanner:Lcom/ctc/wstx/sr/BasicStreamReader;
     205: aload_0
     206: getfield      #42                 // Field mContentHandler:Lorg/xml/sax/ContentHandler;
     209: invokevirtual #137                // Method com/ctc/wstx/sr/BasicStreamReader.fireSaxPIEvent:(Lorg/xml/sax/ContentHandler;)V
     212: goto          325
     215: iload_2
     216: ifeq          325
     219: aload_0
     220: getfield      #77                 // Field mScanner:Lcom/ctc/wstx/sr/BasicStreamReader;
     223: aload_0
     224: getfield      #42                 // Field mContentHandler:Lorg/xml/sax/ContentHandler;
     227: invokevirtual #138                // Method com/ctc/wstx/sr/BasicStreamReader.fireSaxSpaceEvents:(Lorg/xml/sax/ContentHandler;)V
     230: goto          325
     233: aload_0
     234: getfield      #42                 // Field mContentHandler:Lorg/xml/sax/ContentHandler;
     237: ifnull        325
     240: aload_0
     241: getfield      #42                 // Field mContentHandler:Lorg/xml/sax/ContentHandler;
     244: aload_0
     245: getfield      #77                 // Field mScanner:Lcom/ctc/wstx/sr/BasicStreamReader;
     248: invokevirtual #139                // Method com/ctc/wstx/sr/BasicStreamReader.getLocalName:()Ljava/lang/String;
     251: invokeinterface #140,  2          // InterfaceMethod org/xml/sax/ContentHandler.skippedEntity:(Ljava/lang/String;)V
     256: goto          325
     259: iload_1
     260: bipush        8
     262: if_icmpne     298
     265: aload_0
     266: new           #30                 // class java/lang/StringBuilder
     269: dup
     270: invokespecial #31                 // Method java/lang/StringBuilder."<init>":()V
     273: ldc           #141                // String Unexpected end-of-input in
     275: invokevirtual #33                 // Method java/lang/StringBuilder.append:(Ljava/lang/String;)Ljava/lang/StringBuilder;
     278: iload_2
     279: ifeq          287
     282: ldc           #142                // String tree
     284: goto          289
     287: ldc           #143                // String prolog
     289: invokevirtual #33                 // Method java/lang/StringBuilder.append:(Ljava/lang/String;)Ljava/lang/StringBuilder;
     292: invokevirtual #35                 // Method java/lang/StringBuilder.toString:()Ljava/lang/String;
     295: invokespecial #144                // Method throwSaxException:(Ljava/lang/String;)V
     298: new           #145                // class java/lang/RuntimeException
     301: dup
     302: new           #30                 // class java/lang/StringBuilder
     305: dup
     306: invokespecial #31                 // Method java/lang/StringBuilder."<init>":()V
     309: ldc           #146                // String Internal error: unexpected type,
     311: invokevirtual #33                 // Method java/lang/StringBuilder.append:(Ljava/lang/String;)Ljava/lang/StringBuilder;
     314: iload_1
     315: invokevirtual #147                // Method java/lang/StringBuilder.append:(I)Ljava/lang/StringBuilder;
     318: invokevirtual #35                 // Method java/lang/StringBuilder.toString:()Ljava/lang/String;
     321: invokespecial #148                // Method java/lang/RuntimeException."<init>":(Ljava/lang/String;)V
     324: athrow
     325: return
    Exception table:
       from    to  target type
         170   178   181   Class com/ctc/wstx/sax/WrappedSaxException

  private final void fireStartTag() throws org.xml.sax.SAXException;
    Code:
       0: aload_0
       1: aload_0
       2: getfield      #107                // Field mAttrCollector:Lcom/ctc/wstx/sr/AttributeCollector;
       5: invokevirtual #149                // Method com/ctc/wstx/sr/AttributeCollector.getCount:()I
       8: putfield      #150                // Field mAttrCount:I
      11: aload_0
      12: getfield      #5                  // Field mFeatNsPrefixes:Z
      15: ifeq          29
      18: aload_0
      19: aload_0
      20: getfield      #109                // Field mElemStack:Lcom/ctc/wstx/sr/InputElementStack;
      23: invokevirtual #151                // Method com/ctc/wstx/sr/InputElementStack.getCurrentNsCount:()I
      26: putfield      #3                  // Field mNsCount:I
      29: aload_0
      30: getfield      #77                 // Field mScanner:Lcom/ctc/wstx/sr/BasicStreamReader;
      33: aload_0
      34: getfield      #42                 // Field mContentHandler:Lorg/xml/sax/ContentHandler;
      37: aload_0
      38: invokevirtual #152                // Method com/ctc/wstx/sr/BasicStreamReader.fireSaxStartElement:(Lorg/xml/sax/ContentHandler;Lorg/xml/sax/Attributes;)V
      41: return

  public void setDocumentHandler(org.xml.sax.DocumentHandler);
    Code:
       0: aload_0
       1: new           #153                // class com/ctc/wstx/sax/WstxSAXParser$DocHandlerWrapper
       4: dup
       5: aload_1
       6: invokespecial #154                // Method com/ctc/wstx/sax/WstxSAXParser$DocHandlerWrapper."<init>":(Lorg/xml/sax/DocumentHandler;)V
       9: invokevirtual #50                 // Method setContentHandler:(Lorg/xml/sax/ContentHandler;)V
      12: return

  public void setLocale(java.util.Locale);
    Code:
       0: return

  public int getIndex(java.lang.String);
    Code:
       0: aload_0
       1: getfield      #109                // Field mElemStack:Lcom/ctc/wstx/sr/InputElementStack;
       4: ifnonnull     9
       7: iconst_m1
       8: ireturn
       9: aload_0
      10: getfield      #109                // Field mElemStack:Lcom/ctc/wstx/sr/InputElementStack;
      13: aconst_null
      14: aload_1
      15: invokevirtual #155                // Method com/ctc/wstx/sr/InputElementStack.findAttributeIndex:(Ljava/lang/String;Ljava/lang/String;)I
      18: istore_2
      19: iload_2
      20: ireturn

  public int getIndex(java.lang.String, java.lang.String);
    Code:
       0: aload_0
       1: getfield      #109                // Field mElemStack:Lcom/ctc/wstx/sr/InputElementStack;
       4: ifnonnull     9
       7: iconst_m1
       8: ireturn
       9: aload_0
      10: getfield      #109                // Field mElemStack:Lcom/ctc/wstx/sr/InputElementStack;
      13: aload_1
      14: aload_2
      15: invokevirtual #155                // Method com/ctc/wstx/sr/InputElementStack.findAttributeIndex:(Ljava/lang/String;Ljava/lang/String;)I
      18: istore_3
      19: iload_3
      20: ireturn

  public int getLength();
    Code:
       0: aload_0
       1: getfield      #150                // Field mAttrCount:I
       4: aload_0
       5: getfield      #3                  // Field mNsCount:I
       8: iadd
       9: ireturn

  public java.lang.String getLocalName(int);
    Code:
       0: iload_1
       1: aload_0
       2: getfield      #150                // Field mAttrCount:I
       5: if_icmpge     25
       8: iload_1
       9: ifge          16
      12: aconst_null
      13: goto          24
      16: aload_0
      17: getfield      #107                // Field mAttrCollector:Lcom/ctc/wstx/sr/AttributeCollector;
      20: iload_1
      21: invokevirtual #156                // Method com/ctc/wstx/sr/AttributeCollector.getLocalName:(I)Ljava/lang/String;
      24: areturn
      25: iload_1
      26: aload_0
      27: getfield      #150                // Field mAttrCount:I
      30: isub
      31: istore_1
      32: iload_1
      33: aload_0
      34: getfield      #3                  // Field mNsCount:I
      37: if_icmpge     67
      40: aload_0
      41: getfield      #109                // Field mElemStack:Lcom/ctc/wstx/sr/InputElementStack;
      44: iload_1
      45: invokevirtual #157                // Method com/ctc/wstx/sr/InputElementStack.getLocalNsPrefix:(I)Ljava/lang/String;
      48: astore_2
      49: aload_2
      50: ifnull        60
      53: aload_2
      54: invokevirtual #94                 // Method java/lang/String.length:()I
      57: ifne          65
      60: ldc           #158                // String xmlns
      62: goto          66
      65: aload_2
      66: areturn
      67: aconst_null
      68: areturn

  public java.lang.String getQName(int);
    Code:
       0: iload_1
       1: aload_0
       2: getfield      #150                // Field mAttrCount:I
       5: if_icmpge     71
       8: iload_1
       9: ifge          14
      12: aconst_null
      13: areturn
      14: aload_0
      15: getfield      #107                // Field mAttrCollector:Lcom/ctc/wstx/sr/AttributeCollector;
      18: iload_1
      19: invokevirtual #159                // Method com/ctc/wstx/sr/AttributeCollector.getPrefix:(I)Ljava/lang/String;
      22: astore_2
      23: aload_0
      24: getfield      #107                // Field mAttrCollector:Lcom/ctc/wstx/sr/AttributeCollector;
      27: iload_1
      28: invokevirtual #156                // Method com/ctc/wstx/sr/AttributeCollector.getLocalName:(I)Ljava/lang/String;
      31: astore_3
      32: aload_2
      33: ifnull        43
      36: aload_2
      37: invokevirtual #94                 // Method java/lang/String.length:()I
      40: ifne          47
      43: aload_3
      44: goto          70
      47: new           #30                 // class java/lang/StringBuilder
      50: dup
      51: invokespecial #31                 // Method java/lang/StringBuilder."<init>":()V
      54: aload_2
      55: invokevirtual #33                 // Method java/lang/StringBuilder.append:(Ljava/lang/String;)Ljava/lang/StringBuilder;
      58: ldc           #160                // String :
      60: invokevirtual #33                 // Method java/lang/StringBuilder.append:(Ljava/lang/String;)Ljava/lang/StringBuilder;
      63: aload_3
      64: invokevirtual #33                 // Method java/lang/StringBuilder.append:(Ljava/lang/String;)Ljava/lang/StringBuilder;
      67: invokevirtual #35                 // Method java/lang/StringBuilder.toString:()Ljava/lang/String;
      70: areturn
      71: iload_1
      72: aload_0
      73: getfield      #150                // Field mAttrCount:I
      76: isub
      77: istore_1
      78: iload_1
      79: aload_0
      80: getfield      #3                  // Field mNsCount:I
      83: if_icmpge     129
      86: aload_0
      87: getfield      #109                // Field mElemStack:Lcom/ctc/wstx/sr/InputElementStack;
      90: iload_1
      91: invokevirtual #157                // Method com/ctc/wstx/sr/InputElementStack.getLocalNsPrefix:(I)Ljava/lang/String;
      94: astore_2
      95: aload_2
      96: ifnull        106
      99: aload_2
     100: invokevirtual #94                 // Method java/lang/String.length:()I
     103: ifne          109
     106: ldc           #158                // String xmlns
     108: areturn
     109: new           #30                 // class java/lang/StringBuilder
     112: dup
     113: invokespecial #31                 // Method java/lang/StringBuilder."<init>":()V
     116: ldc           #161                // String xmlns:
     118: invokevirtual #33                 // Method java/lang/StringBuilder.append:(Ljava/lang/String;)Ljava/lang/StringBuilder;
     121: aload_2
     122: invokevirtual #33                 // Method java/lang/StringBuilder.append:(Ljava/lang/String;)Ljava/lang/StringBuilder;
     125: invokevirtual #35                 // Method java/lang/StringBuilder.toString:()Ljava/lang/String;
     128: areturn
     129: aconst_null
     130: areturn

  public java.lang.String getType(int);
    Code:
       0: iload_1
       1: aload_0
       2: getfield      #150                // Field mAttrCount:I
       5: if_icmpge     34
       8: iload_1
       9: ifge          14
      12: aconst_null
      13: areturn
      14: aload_0
      15: getfield      #109                // Field mElemStack:Lcom/ctc/wstx/sr/InputElementStack;
      18: iload_1
      19: invokevirtual #162                // Method com/ctc/wstx/sr/InputElementStack.getAttributeType:(I)Ljava/lang/String;
      22: astore_2
      23: aload_2
      24: ldc           #163                // String ENUMERATED
      26: if_acmpne     32
      29: ldc           #164                // String NMTOKEN
      31: astore_2
      32: aload_2
      33: areturn
      34: iload_1
      35: aload_0
      36: getfield      #150                // Field mAttrCount:I
      39: isub
      40: istore_1
      41: iload_1
      42: aload_0
      43: getfield      #3                  // Field mNsCount:I
      46: if_icmpge     52
      49: ldc           #165                // String CDATA
      51: areturn
      52: aconst_null
      53: areturn

  public java.lang.String getType(java.lang.String);
    Code:
       0: aload_0
       1: aload_0
       2: aload_1
       3: invokevirtual #166                // Method getIndex:(Ljava/lang/String;)I
       6: invokevirtual #167                // Method getType:(I)Ljava/lang/String;
       9: areturn

  public java.lang.String getType(java.lang.String, java.lang.String);
    Code:
       0: aload_0
       1: aload_0
       2: aload_1
       3: aload_2
       4: invokevirtual #168                // Method getIndex:(Ljava/lang/String;Ljava/lang/String;)I
       7: invokevirtual #167                // Method getType:(I)Ljava/lang/String;
      10: areturn

  public java.lang.String getURI(int);
    Code:
       0: iload_1
       1: aload_0
       2: getfield      #150                // Field mAttrCount:I
       5: if_icmpge     34
       8: iload_1
       9: ifge          14
      12: aconst_null
      13: areturn
      14: aload_0
      15: getfield      #107                // Field mAttrCollector:Lcom/ctc/wstx/sr/AttributeCollector;
      18: iload_1
      19: invokevirtual #169                // Method com/ctc/wstx/sr/AttributeCollector.getURI:(I)Ljava/lang/String;
      22: astore_2
      23: aload_2
      24: ifnonnull     32
      27: ldc           #170                // String
      29: goto          33
      32: aload_2
      33: areturn
      34: iload_1
      35: aload_0
      36: getfield      #150                // Field mAttrCount:I
      39: isub
      40: aload_0
      41: getfield      #3                  // Field mNsCount:I
      44: if_icmpge     50
      47: ldc           #172                // String http://www.w3.org/2000/xmlns/
      49: areturn
      50: aconst_null
      51: areturn

  public java.lang.String getValue(int);
    Code:
       0: iload_1
       1: aload_0
       2: getfield      #150                // Field mAttrCount:I
       5: if_icmpge     25
       8: iload_1
       9: ifge          16
      12: aconst_null
      13: goto          24
      16: aload_0
      17: getfield      #107                // Field mAttrCollector:Lcom/ctc/wstx/sr/AttributeCollector;
      20: iload_1
      21: invokevirtual #173                // Method com/ctc/wstx/sr/AttributeCollector.getValue:(I)Ljava/lang/String;
      24: areturn
      25: iload_1
      26: aload_0
      27: getfield      #150                // Field mAttrCount:I
      30: isub
      31: istore_1
      32: iload_1
      33: aload_0
      34: getfield      #3                  // Field mNsCount:I
      37: if_icmpge     60
      40: aload_0
      41: getfield      #109                // Field mElemStack:Lcom/ctc/wstx/sr/InputElementStack;
      44: iload_1
      45: invokevirtual #174                // Method com/ctc/wstx/sr/InputElementStack.getLocalNsURI:(I)Ljava/lang/String;
      48: astore_2
      49: aload_2
      50: ifnonnull     58
      53: ldc           #170                // String
      55: goto          59
      58: aload_2
      59: areturn
      60: aconst_null
      61: areturn

  public java.lang.String getValue(java.lang.String);
    Code:
       0: aload_0
       1: aload_0
       2: aload_1
       3: invokevirtual #166                // Method getIndex:(Ljava/lang/String;)I
       6: invokevirtual #175                // Method getValue:(I)Ljava/lang/String;
       9: areturn

  public java.lang.String getValue(java.lang.String, java.lang.String);
    Code:
       0: aload_0
       1: aload_0
       2: aload_1
       3: aload_2
       4: invokevirtual #168                // Method getIndex:(Ljava/lang/String;Ljava/lang/String;)I
       7: invokevirtual #175                // Method getValue:(I)Ljava/lang/String;
      10: areturn

  public boolean isDeclared(int);
    Code:
       0: iload_1
       1: aload_0
       2: getfield      #150                // Field mAttrCount:I
       5: if_icmpge     14
       8: iload_1
       9: iflt          31
      12: iconst_1
      13: ireturn
      14: iload_1
      15: aload_0
      16: getfield      #150                // Field mAttrCount:I
      19: isub
      20: istore_1
      21: iload_1
      22: aload_0
      23: getfield      #3                  // Field mNsCount:I
      26: if_icmpge     31
      29: iconst_1
      30: ireturn
      31: aload_0
      32: iload_1
      33: invokespecial #176                // Method throwNoSuchAttribute:(I)V
      36: iconst_0
      37: ireturn

  public boolean isDeclared(java.lang.String);
    Code:
       0: iconst_0
       1: ireturn

  public boolean isDeclared(java.lang.String, java.lang.String);
    Code:
       0: iconst_0
       1: ireturn

  public boolean isSpecified(int);
    Code:
       0: iload_1
       1: aload_0
       2: getfield      #150                // Field mAttrCount:I
       5: if_icmpge     21
       8: iload_1
       9: iflt          38
      12: aload_0
      13: getfield      #107                // Field mAttrCollector:Lcom/ctc/wstx/sr/AttributeCollector;
      16: iload_1
      17: invokevirtual #177                // Method com/ctc/wstx/sr/AttributeCollector.isSpecified:(I)Z
      20: ireturn
      21: iload_1
      22: aload_0
      23: getfield      #150                // Field mAttrCount:I
      26: isub
      27: istore_1
      28: iload_1
      29: aload_0
      30: getfield      #3                  // Field mNsCount:I
      33: if_icmpge     38
      36: iconst_1
      37: ireturn
      38: aload_0
      39: iload_1
      40: invokespecial #176                // Method throwNoSuchAttribute:(I)V
      43: iconst_0
      44: ireturn

  public boolean isSpecified(java.lang.String);
    Code:
       0: aload_0
       1: aload_1
       2: invokevirtual #166                // Method getIndex:(Ljava/lang/String;)I
       5: istore_2
       6: iload_2
       7: ifge          42
      10: new           #178                // class java/lang/IllegalArgumentException
      13: dup
      14: new           #30                 // class java/lang/StringBuilder
      17: dup
      18: invokespecial #31                 // Method java/lang/StringBuilder."<init>":()V
      21: ldc           #179                // String No attribute with qName \'
      23: invokevirtual #33                 // Method java/lang/StringBuilder.append:(Ljava/lang/String;)Ljava/lang/StringBuilder;
      26: aload_1
      27: invokevirtual #33                 // Method java/lang/StringBuilder.append:(Ljava/lang/String;)Ljava/lang/StringBuilder;
      30: ldc           #76                 // String \'
      32: invokevirtual #33                 // Method java/lang/StringBuilder.append:(Ljava/lang/String;)Ljava/lang/StringBuilder;
      35: invokevirtual #35                 // Method java/lang/StringBuilder.toString:()Ljava/lang/String;
      38: invokespecial #180                // Method java/lang/IllegalArgumentException."<init>":(Ljava/lang/String;)V
      41: athrow
      42: aload_0
      43: iload_2
      44: invokevirtual #181                // Method isSpecified:(I)Z
      47: ireturn

  public boolean isSpecified(java.lang.String, java.lang.String);
    Code:
       0: aload_0
       1: aload_1
       2: aload_2
       3: invokevirtual #168                // Method getIndex:(Ljava/lang/String;Ljava/lang/String;)I
       6: istore_3
       7: iload_3
       8: ifge          52
      11: new           #178                // class java/lang/IllegalArgumentException
      14: dup
      15: new           #30                 // class java/lang/StringBuilder
      18: dup
      19: invokespecial #31                 // Method java/lang/StringBuilder."<init>":()V
      22: ldc           #182                // String No attribute with uri
      24: invokevirtual #33                 // Method java/lang/StringBuilder.append:(Ljava/lang/String;)Ljava/lang/StringBuilder;
      27: aload_1
      28: invokevirtual #33                 // Method java/lang/StringBuilder.append:(Ljava/lang/String;)Ljava/lang/StringBuilder;
      31: ldc           #183                // String , local name \'
      33: invokevirtual #33                 // Method java/lang/StringBuilder.append:(Ljava/lang/String;)Ljava/lang/StringBuilder;
      36: aload_2
      37: invokevirtual #33                 // Method java/lang/StringBuilder.append:(Ljava/lang/String;)Ljava/lang/StringBuilder;
      40: ldc           #76                 // String \'
      42: invokevirtual #33                 // Method java/lang/StringBuilder.append:(Ljava/lang/String;)Ljava/lang/StringBuilder;
      45: invokevirtual #35                 // Method java/lang/StringBuilder.toString:()Ljava/lang/String;
      48: invokespecial #180                // Method java/lang/IllegalArgumentException."<init>":(Ljava/lang/String;)V
      51: athrow
      52: aload_0
      53: iload_3
      54: invokevirtual #181                // Method isSpecified:(I)Z
      57: ireturn

  public int getColumnNumber();
    Code:
       0: aload_0
       1: getfield      #77                 // Field mScanner:Lcom/ctc/wstx/sr/BasicStreamReader;
       4: ifnull        22
       7: aload_0
       8: getfield      #77                 // Field mScanner:Lcom/ctc/wstx/sr/BasicStreamReader;
      11: invokevirtual #184                // Method com/ctc/wstx/sr/BasicStreamReader.getLocation:()Ljavax/xml/stream/Location;
      14: astore_1
      15: aload_1
      16: invokeinterface #185,  1          // InterfaceMethod javax/xml/stream/Location.getColumnNumber:()I
      21: ireturn
      22: iconst_m1
      23: ireturn

  public int getLineNumber();
    Code:
       0: aload_0
       1: getfield      #77                 // Field mScanner:Lcom/ctc/wstx/sr/BasicStreamReader;
       4: ifnull        22
       7: aload_0
       8: getfield      #77                 // Field mScanner:Lcom/ctc/wstx/sr/BasicStreamReader;
      11: invokevirtual #184                // Method com/ctc/wstx/sr/BasicStreamReader.getLocation:()Ljavax/xml/stream/Location;
      14: astore_1
      15: aload_1
      16: invokeinterface #186,  1          // InterfaceMethod javax/xml/stream/Location.getLineNumber:()I
      21: ireturn
      22: iconst_m1
      23: ireturn

  public java.lang.String getPublicId();
    Code:
       0: aload_0
       1: getfield      #77                 // Field mScanner:Lcom/ctc/wstx/sr/BasicStreamReader;
       4: ifnull        22
       7: aload_0
       8: getfield      #77                 // Field mScanner:Lcom/ctc/wstx/sr/BasicStreamReader;
      11: invokevirtual #184                // Method com/ctc/wstx/sr/BasicStreamReader.getLocation:()Ljavax/xml/stream/Location;
      14: astore_1
      15: aload_1
      16: invokeinterface #187,  1          // InterfaceMethod javax/xml/stream/Location.getPublicId:()Ljava/lang/String;
      21: areturn
      22: aconst_null
      23: areturn

  public java.lang.String getSystemId();
    Code:
       0: aload_0
       1: getfield      #77                 // Field mScanner:Lcom/ctc/wstx/sr/BasicStreamReader;
       4: ifnull        22
       7: aload_0
       8: getfield      #77                 // Field mScanner:Lcom/ctc/wstx/sr/BasicStreamReader;
      11: invokevirtual #184                // Method com/ctc/wstx/sr/BasicStreamReader.getLocation:()Ljavax/xml/stream/Location;
      14: astore_1
      15: aload_1
      16: invokeinterface #188,  1          // InterfaceMethod javax/xml/stream/Location.getSystemId:()Ljava/lang/String;
      21: areturn
      22: aconst_null
      23: areturn

  public java.lang.String getEncoding();
    Code:
       0: aload_0
       1: getfield      #103                // Field mEncoding:Ljava/lang/String;
       4: areturn

  public java.lang.String getXMLVersion();
    Code:
       0: aload_0
       1: getfield      #24                 // Field mXmlVersion:Ljava/lang/String;
       4: areturn

  public boolean dtdReportComments();
    Code:
       0: aload_0
       1: getfield      #27                 // Field mLexicalHandler:Lorg/xml/sax/ext/LexicalHandler;
       4: ifnull        11
       7: iconst_1
       8: goto          12
      11: iconst_0
      12: ireturn

  public void dtdComment(char[], int, int);
    Code:
       0: aload_0
       1: getfield      #27                 // Field mLexicalHandler:Lorg/xml/sax/ext/LexicalHandler;
       4: ifnull        34
       7: aload_0
       8: getfield      #27                 // Field mLexicalHandler:Lorg/xml/sax/ext/LexicalHandler;
      11: aload_1
      12: iload_2
      13: iload_3
      14: invokeinterface #189,  4          // InterfaceMethod org/xml/sax/ext/LexicalHandler.comment:([CII)V
      19: goto          34
      22: astore        4
      24: new           #134                // class com/ctc/wstx/sax/WrappedSaxException
      27: dup
      28: aload         4
      30: invokespecial #190                // Method com/ctc/wstx/sax/WrappedSaxException."<init>":(Lorg/xml/sax/SAXException;)V
      33: athrow
      34: return
    Exception table:
       from    to  target type
           7    19    22   Class org/xml/sax/SAXException

  public void dtdProcessingInstruction(java.lang.String, java.lang.String);
    Code:
       0: aload_0
       1: getfield      #42                 // Field mContentHandler:Lorg/xml/sax/ContentHandler;
       4: ifnull        31
       7: aload_0
       8: getfield      #42                 // Field mContentHandler:Lorg/xml/sax/ContentHandler;
      11: aload_1
      12: aload_2
      13: invokeinterface #191,  3          // InterfaceMethod org/xml/sax/ContentHandler.processingInstruction:(Ljava/lang/String;Ljava/lang/String;)V
      18: goto          31
      21: astore_3
      22: new           #134                // class com/ctc/wstx/sax/WrappedSaxException
      25: dup
      26: aload_3
      27: invokespecial #190                // Method com/ctc/wstx/sax/WrappedSaxException."<init>":(Lorg/xml/sax/SAXException;)V
      30: athrow
      31: return
    Exception table:
       from    to  target type
           7    18    21   Class org/xml/sax/SAXException

  public void dtdSkippedEntity(java.lang.String);
    Code:
       0: aload_0
       1: getfield      #42                 // Field mContentHandler:Lorg/xml/sax/ContentHandler;
       4: ifnull        30
       7: aload_0
       8: getfield      #42                 // Field mContentHandler:Lorg/xml/sax/ContentHandler;
      11: aload_1
      12: invokeinterface #140,  2          // InterfaceMethod org/xml/sax/ContentHandler.skippedEntity:(Ljava/lang/String;)V
      17: goto          30
      20: astore_2
      21: new           #134                // class com/ctc/wstx/sax/WrappedSaxException
      24: dup
      25: aload_2
      26: invokespecial #190                // Method com/ctc/wstx/sax/WrappedSaxException."<init>":(Lorg/xml/sax/SAXException;)V
      29: athrow
      30: return
    Exception table:
       from    to  target type
           7    17    20   Class org/xml/sax/SAXException

  public void dtdNotationDecl(java.lang.String, java.lang.String, java.lang.String, java.net.URL) throws javax.xml.stream.XMLStreamException;
    Code:
       0: aload_0
       1: getfield      #47                 // Field mDTDHandler:Lorg/xml/sax/DTDHandler;
       4: ifnull        72
       7: aload_3
       8: ifnull        45
      11: aload_3
      12: bipush        58
      14: invokevirtual #192                // Method java/lang/String.indexOf:(I)I
      17: ifge          45
      20: aload_3
      21: aload         4
      23: invokestatic  #193                // Method com/ctc/wstx/util/URLUtil.urlFromSystemId:(Ljava/lang/String;Ljava/net/URL;)Ljava/net/URL;
      26: invokevirtual #194                // Method java/net/URL.toExternalForm:()Ljava/lang/String;
      29: astore_3
      30: goto          45
      33: astore        5
      35: new           #195                // class com/ctc/wstx/exc/WstxIOException
      38: dup
      39: aload         5
      41: invokespecial #196                // Method com/ctc/wstx/exc/WstxIOException."<init>":(Ljava/io/IOException;)V
      44: athrow
      45: aload_0
      46: getfield      #47                 // Field mDTDHandler:Lorg/xml/sax/DTDHandler;
      49: aload_1
      50: aload_2
      51: aload_3
      52: invokeinterface #197,  4          // InterfaceMethod org/xml/sax/DTDHandler.notationDecl:(Ljava/lang/String;Ljava/lang/String;Ljava/lang/String;)V
      57: goto          72
      60: astore        5
      62: new           #134                // class com/ctc/wstx/sax/WrappedSaxException
      65: dup
      66: aload         5
      68: invokespecial #190                // Method com/ctc/wstx/sax/WrappedSaxException."<init>":(Lorg/xml/sax/SAXException;)V
      71: athrow
      72: return
    Exception table:
       from    to  target type
          20    30    33   Class java/io/IOException
          45    57    60   Class org/xml/sax/SAXException

  public void dtdUnparsedEntityDecl(java.lang.String, java.lang.String, java.lang.String, java.lang.String, java.net.URL) throws javax.xml.stream.XMLStreamException;
    Code:
       0: aload_0
       1: getfield      #47                 // Field mDTDHandler:Lorg/xml/sax/DTDHandler;
       4: ifnull        70
       7: aload_3
       8: bipush        58
      10: invokevirtual #192                // Method java/lang/String.indexOf:(I)I
      13: ifge          41
      16: aload_3
      17: aload         5
      19: invokestatic  #193                // Method com/ctc/wstx/util/URLUtil.urlFromSystemId:(Ljava/lang/String;Ljava/net/URL;)Ljava/net/URL;
      22: invokevirtual #194                // Method java/net/URL.toExternalForm:()Ljava/lang/String;
      25: astore_3
      26: goto          41
      29: astore        6
      31: new           #195                // class com/ctc/wstx/exc/WstxIOException
      34: dup
      35: aload         6
      37: invokespecial #196                // Method com/ctc/wstx/exc/WstxIOException."<init>":(Ljava/io/IOException;)V
      40: athrow
      41: aload_0
      42: getfield      #47                 // Field mDTDHandler:Lorg/xml/sax/DTDHandler;
      45: aload_1
      46: aload_2
      47: aload_3
      48: aload         4
      50: invokeinterface #198,  5          // InterfaceMethod org/xml/sax/DTDHandler.unparsedEntityDecl:(Ljava/lang/String;Ljava/lang/String;Ljava/lang/String;Ljava/lang/String;)V
      55: goto          70
      58: astore        6
      60: new           #134                // class com/ctc/wstx/sax/WrappedSaxException
      63: dup
      64: aload         6
      66: invokespecial #190                // Method com/ctc/wstx/sax/WrappedSaxException."<init>":(Lorg/xml/sax/SAXException;)V
      69: athrow
      70: return
    Exception table:
       from    to  target type
          16    26    29   Class java/io/IOException
          41    55    58   Class org/xml/sax/SAXException

  public void attributeDecl(java.lang.String, java.lang.String, java.lang.String, java.lang.String, java.lang.String);
    Code:
       0: aload_0
       1: getfield      #22                 // Field mDeclHandler:Lorg/xml/sax/ext/DeclHandler;
       4: ifnull        38
       7: aload_0
       8: getfield      #22                 // Field mDeclHandler:Lorg/xml/sax/ext/DeclHandler;
      11: aload_1
      12: aload_2
      13: aload_3
      14: aload         4
      16: aload         5
      18: invokeinterface #199,  6          // InterfaceMethod org/xml/sax/ext/DeclHandler.attributeDecl:(Ljava/lang/String;Ljava/lang/String;Ljava/lang/String;Ljava/lang/String;Ljava/lang/String;)V
      23: goto          38
      26: astore        6
      28: new           #134                // class com/ctc/wstx/sax/WrappedSaxException
      31: dup
      32: aload         6
      34: invokespecial #190                // Method com/ctc/wstx/sax/WrappedSaxException."<init>":(Lorg/xml/sax/SAXException;)V
      37: athrow
      38: return
    Exception table:
       from    to  target type
           7    23    26   Class org/xml/sax/SAXException

  public void dtdElementDecl(java.lang.String, java.lang.String);
    Code:
       0: aload_0
       1: getfield      #22                 // Field mDeclHandler:Lorg/xml/sax/ext/DeclHandler;
       4: ifnull        31
       7: aload_0
       8: getfield      #22                 // Field mDeclHandler:Lorg/xml/sax/ext/DeclHandler;
      11: aload_1
      12: aload_2
      13: invokeinterface #200,  3          // InterfaceMethod org/xml/sax/ext/DeclHandler.elementDecl:(Ljava/lang/String;Ljava/lang/String;)V
      18: goto          31
      21: astore_3
      22: new           #134                // class com/ctc/wstx/sax/WrappedSaxException
      25: dup
      26: aload_3
      27: invokespecial #190                // Method com/ctc/wstx/sax/WrappedSaxException."<init>":(Lorg/xml/sax/SAXException;)V
      30: athrow
      31: return
    Exception table:
       from    to  target type
           7    18    21   Class org/xml/sax/SAXException

  public void dtdExternalEntityDecl(java.lang.String, java.lang.String, java.lang.String);
    Code:
       0: aload_0
       1: getfield      #22                 // Field mDeclHandler:Lorg/xml/sax/ext/DeclHandler;
       4: ifnull        34
       7: aload_0
       8: getfield      #22                 // Field mDeclHandler:Lorg/xml/sax/ext/DeclHandler;
      11: aload_1
      12: aload_2
      13: aload_3
      14: invokeinterface #201,  4          // InterfaceMethod org/xml/sax/ext/DeclHandler.externalEntityDecl:(Ljava/lang/String;Ljava/lang/String;Ljava/lang/String;)V
      19: goto          34
      22: astore        4
      24: new           #134                // class com/ctc/wstx/sax/WrappedSaxException
      27: dup
      28: aload         4
      30: invokespecial #190                // Method com/ctc/wstx/sax/WrappedSaxException."<init>":(Lorg/xml/sax/SAXException;)V
      33: athrow
      34: return
    Exception table:
       from    to  target type
           7    19    22   Class org/xml/sax/SAXException

  public void dtdInternalEntityDecl(java.lang.String, java.lang.String);
    Code:
       0: aload_0
       1: getfield      #22                 // Field mDeclHandler:Lorg/xml/sax/ext/DeclHandler;
       4: ifnull        31
       7: aload_0
       8: getfield      #22                 // Field mDeclHandler:Lorg/xml/sax/ext/DeclHandler;
      11: aload_1
      12: aload_2
      13: invokeinterface #202,  3          // InterfaceMethod org/xml/sax/ext/DeclHandler.internalEntityDecl:(Ljava/lang/String;Ljava/lang/String;)V
      18: goto          31
      21: astore_3
      22: new           #134                // class com/ctc/wstx/sax/WrappedSaxException
      25: dup
      26: aload_3
      27: invokespecial #190                // Method com/ctc/wstx/sax/WrappedSaxException."<init>":(Lorg/xml/sax/SAXException;)V
      30: athrow
      31: return
    Exception table:
       from    to  target type
           7    18    21   Class org/xml/sax/SAXException

  private void throwSaxException(java.lang.Exception) throws org.xml.sax.SAXException;
    Code:
       0: new           #203                // class org/xml/sax/SAXParseException
       3: dup
       4: aload_1
       5: invokevirtual #204                // Method java/lang/Exception.getMessage:()Ljava/lang/String;
       8: aload_0
       9: aload_1
      10: invokespecial #205                // Method org/xml/sax/SAXParseException."<init>":(Ljava/lang/String;Lorg/xml/sax/Locator;Ljava/lang/Exception;)V
      13: astore_2
      14: aload_2
      15: aload_1
      16: invokestatic  #88                 // Method com/ctc/wstx/util/ExceptionUtil.setInitCause:(Ljava/lang/Throwable;Ljava/lang/Throwable;)V
      19: aload_0
      20: getfield      #45                 // Field mErrorHandler:Lorg/xml/sax/ErrorHandler;
      23: ifnull        36
      26: aload_0
      27: getfield      #45                 // Field mErrorHandler:Lorg/xml/sax/ErrorHandler;
      30: aload_2
      31: invokeinterface #206,  2          // InterfaceMethod org/xml/sax/ErrorHandler.fatalError:(Lorg/xml/sax/SAXParseException;)V
      36: aload_2
      37: athrow

  private void throwSaxException(java.lang.String) throws org.xml.sax.SAXException;
    Code:
       0: new           #203                // class org/xml/sax/SAXParseException
       3: dup
       4: aload_1
       5: aload_0
       6: invokespecial #207                // Method org/xml/sax/SAXParseException."<init>":(Ljava/lang/String;Lorg/xml/sax/Locator;)V
       9: astore_2
      10: aload_0
      11: getfield      #45                 // Field mErrorHandler:Lorg/xml/sax/ErrorHandler;
      14: ifnull        27
      17: aload_0
      18: getfield      #45                 // Field mErrorHandler:Lorg/xml/sax/ErrorHandler;
      21: aload_2
      22: invokeinterface #206,  2          // InterfaceMethod org/xml/sax/ErrorHandler.fatalError:(Lorg/xml/sax/SAXParseException;)V
      27: aload_2
      28: athrow

  private void throwNoSuchAttribute(int);
    Code:
       0: new           #178                // class java/lang/IllegalArgumentException
       3: dup
       4: new           #30                 // class java/lang/StringBuilder
       7: dup
       8: invokespecial #31                 // Method java/lang/StringBuilder."<init>":()V
      11: ldc           #208                // String No attribute with index
      13: invokevirtual #33                 // Method java/lang/StringBuilder.append:(Ljava/lang/String;)Ljava/lang/StringBuilder;
      16: iload_1
      17: invokevirtual #147                // Method java/lang/StringBuilder.append:(I)Ljava/lang/StringBuilder;
      20: ldc           #209                // String  (have
      22: invokevirtual #33                 // Method java/lang/StringBuilder.append:(Ljava/lang/String;)Ljava/lang/StringBuilder;
      25: aload_0
      26: getfield      #150                // Field mAttrCount:I
      29: aload_0
      30: getfield      #3                  // Field mNsCount:I
      33: iadd
      34: invokevirtual #147                // Method java/lang/StringBuilder.append:(I)Ljava/lang/StringBuilder;
      37: ldc           #210                // String  attributes)
      39: invokevirtual #33                 // Method java/lang/StringBuilder.append:(Ljava/lang/String;)Ljava/lang/StringBuilder;
      42: invokevirtual #35                 // Method java/lang/StringBuilder.toString:()Ljava/lang/String;
      45: invokespecial #180                // Method java/lang/IllegalArgumentException."<init>":(Ljava/lang/String;)V
      48: athrow

  static org.xml.sax.EntityResolver access$000(com.ctc.wstx.sax.WstxSAXParser);
    Code:
       0: aload_0
       1: getfield      #1                  // Field mEntityResolver:Lorg/xml/sax/EntityResolver;
       4: areturn
}
