Compiled from "MultipartFormDataParserTestCase.java"
final class io.undertow.server.handlers.form.MultipartFormDataParserTestCase$1 implements io.undertow.server.HttpHandler {
  io.undertow.server.handlers.form.MultipartFormDataParserTestCase$1();
    Code:
       0: aload_0
       1: invokespecial #1                  // Method java/lang/Object."<init>":()V
       4: return

  public void handleRequest(io.undertow.server.HttpServerExchange) throws java.lang.Exception;
    Code:
       0: getstatic     #2                  // Field java/lang/System.out:Ljava/io/PrintStream;
       3: ldc           #3                  // String In handler
       5: invokevirtual #4                  // Method java/io/PrintStream.println:(Ljava/lang/String;)V
       8: invokestatic  #5                  // Method io/undertow/server/handlers/form/FormParserFactory.builder:()Lio/undertow/server/handlers/form/FormParserFactory$Builder;
      11: invokevirtual #6                  // Method io/undertow/server/handlers/form/FormParserFactory$Builder.build:()Lio/undertow/server/handlers/form/FormParserFactory;
      14: aload_1
      15: invokevirtual #7                  // Method io/undertow/server/handlers/form/FormParserFactory.createParser:(Lio/undertow/server/HttpServerExchange;)Lio/undertow/server/handlers/form/FormDataParser;
      18: astore_2
      19: getstatic     #2                  // Field java/lang/System.out:Ljava/io/PrintStream;
      22: ldc           #8                  // String Created parser
      24: invokevirtual #4                  // Method java/io/PrintStream.println:(Ljava/lang/String;)V
      27: aload_2
      28: invokeinterface #9,  1            // InterfaceMethod io/undertow/server/handlers/form/FormDataParser.parseBlocking:()Lio/undertow/server/handlers/form/FormData;
      33: astore_3
      34: getstatic     #2                  // Field java/lang/System.out:Ljava/io/PrintStream;
      37: ldc           #10                 // String done parsing
      39: invokevirtual #4                  // Method java/io/PrintStream.println:(Ljava/lang/String;)V
      42: aload_1
      43: sipush        500
      46: invokevirtual #12                 // Method io/undertow/server/HttpServerExchange.setStatusCode:(I)Lio/undertow/server/HttpServerExchange;
      49: pop
      50: aload_3
      51: ldc           #13                 // String formValue
      53: invokevirtual #14                 // Method io/undertow/server/handlers/form/FormData.getFirst:(Ljava/lang/String;)Lio/undertow/server/handlers/form/FormData$FormValue;
      56: invokeinterface #15,  1           // InterfaceMethod io/undertow/server/handlers/form/FormData$FormValue.getValue:()Ljava/lang/String;
      61: ldc           #16                 // String myValue
      63: invokevirtual #17                 // Method java/lang/String.equals:(Ljava/lang/Object;)Z
      66: ifeq          130
      69: aload_3
      70: ldc           #18                 // String file
      72: invokevirtual #14                 // Method io/undertow/server/handlers/form/FormData.getFirst:(Ljava/lang/String;)Lio/undertow/server/handlers/form/FormData$FormValue;
      75: astore        4
      77: aload         4
      79: invokeinterface #19,  1           // InterfaceMethod io/undertow/server/handlers/form/FormData$FormValue.isFile:()Z
      84: ifeq          130
      87: aload         4
      89: invokeinterface #20,  1           // InterfaceMethod io/undertow/server/handlers/form/FormData$FormValue.getPath:()Ljava/nio/file/Path;
      94: ifnull        130
      97: new           #21                 // class java/lang/String
     100: dup
     101: aload         4
     103: invokeinterface #20,  1           // InterfaceMethod io/undertow/server/handlers/form/FormData$FormValue.getPath:()Ljava/nio/file/Path;
     108: invokestatic  #22                 // Method java/nio/file/Files.readAllBytes:(Ljava/nio/file/Path;)[B
     111: invokespecial #23                 // Method java/lang/String."<init>":([B)V
     114: ldc           #24                 // String file contents
     116: invokevirtual #25                 // Method java/lang/String.startsWith:(Ljava/lang/String;)Z
     119: ifeq          130
     122: aload_1
     123: sipush        200
     126: invokevirtual #12                 // Method io/undertow/server/HttpServerExchange.setStatusCode:(I)Lio/undertow/server/HttpServerExchange;
     129: pop
     130: aload_1
     131: invokevirtual #26                 // Method io/undertow/server/HttpServerExchange.endExchange:()Lio/undertow/server/HttpServerExchange;
     134: pop
     135: aload_2
     136: invokestatic  #27                 // Method org/xnio/IoUtils.safeClose:(Ljava/io/Closeable;)V
     139: goto          176
     142: astore_3
     143: aload_3
     144: invokevirtual #29                 // Method java/lang/Throwable.printStackTrace:()V
     147: aload_1
     148: sipush        500
     151: invokevirtual #12                 // Method io/undertow/server/HttpServerExchange.setStatusCode:(I)Lio/undertow/server/HttpServerExchange;
     154: pop
     155: aload_1
     156: invokevirtual #26                 // Method io/undertow/server/HttpServerExchange.endExchange:()Lio/undertow/server/HttpServerExchange;
     159: pop
     160: aload_2
     161: invokestatic  #27                 // Method org/xnio/IoUtils.safeClose:(Ljava/io/Closeable;)V
     164: goto          176
     167: astore        5
     169: aload_2
     170: invokestatic  #27                 // Method org/xnio/IoUtils.safeClose:(Ljava/io/Closeable;)V
     173: aload         5
     175: athrow
     176: return
    Exception table:
       from    to  target type
          27   135   142   Class java/lang/Throwable
          27   135   167   any
         142   160   167   any
         167   169   167   any
}
