Compiled from "BytecodeReadingParanamer.java"
final class org.sonarsource.sonarlint.shaded.org.picocontainer.paranamer.BytecodeReadingParanamer$1 extends java.util.HashMap<java.lang.String, java.lang.String> {
  org.sonarsource.sonarlint.shaded.org.picocontainer.paranamer.BytecodeReadingParanamer$1();
    Code:
       0: aload_0
       1: invokespecial #12                 // Method java/util/HashMap."<init>":()V
       4: aload_0
       5: ldc           #14                 // String int
       7: ldc           #16                 // String I
       9: invokevirtual #20                 // Method put:(Ljava/lang/Object;Ljava/lang/Object;)Ljava/lang/Object;
      12: pop
      13: aload_0
      14: ldc           #22                 // String boolean
      16: ldc           #24                 // String Z
      18: invokevirtual #20                 // Method put:(Ljava/lang/Object;Ljava/lang/Object;)Ljava/lang/Object;
      21: pop
      22: aload_0
      23: ldc           #26                 // String char
      25: ldc           #28                 // String C
      27: invokevirtual #20                 // Method put:(Ljava/lang/Object;Ljava/lang/Object;)Ljava/lang/Object;
      30: pop
      31: aload_0
      32: ldc           #30                 // String short
      34: ldc           #32                 // String S
      36: invokevirtual #20                 // Method put:(Ljava/lang/Object;Ljava/lang/Object;)Ljava/lang/Object;
      39: pop
      40: aload_0
      41: ldc           #34                 // String float
      43: ldc           #36                 // String F
      45: invokevirtual #20                 // Method put:(Ljava/lang/Object;Ljava/lang/Object;)Ljava/lang/Object;
      48: pop
      49: aload_0
      50: ldc           #38                 // String long
      52: ldc           #40                 // String J
      54: invokevirtual #20                 // Method put:(Ljava/lang/Object;Ljava/lang/Object;)Ljava/lang/Object;
      57: pop
      58: aload_0
      59: ldc           #42                 // String double
      61: ldc           #44                 // String D
      63: invokevirtual #20                 // Method put:(Ljava/lang/Object;Ljava/lang/Object;)Ljava/lang/Object;
      66: pop
      67: return
}
