Compiled from "AnsiPropertySource.java"
class org.springframework.boot.ansi.AnsiPropertySource$Ansi8BitColorMapping extends org.springframework.boot.ansi.AnsiPropertySource$Mapping {
  private final java.util.function.IntFunction<org.springframework.boot.ansi.Ansi8BitColor> factory;

  org.springframework.boot.ansi.AnsiPropertySource$Ansi8BitColorMapping(java.lang.String, java.util.function.IntFunction<org.springframework.boot.ansi.Ansi8BitColor>);
    Code:
       0: aload_0
       1: aload_1
       2: invokespecial #1                  // Method org/springframework/boot/ansi/AnsiPropertySource$Mapping."<init>":(Ljava/lang/String;)V
       5: aload_0
       6: aload_2
       7: putfield      #2                  // Field factory:Ljava/util/function/IntFunction;
      10: return

  org.springframework.boot.ansi.AnsiElement getElement(java.lang.String);
    Code:
       0: aload_0
       1: aload_1
       2: invokespecial #3                  // Method containsOnlyDigits:(Ljava/lang/String;)Z
       5: ifeq          26
       8: aload_0
       9: getfield      #2                  // Field factory:Ljava/util/function/IntFunction;
      12: aload_1
      13: invokestatic  #4                  // Method java/lang/Integer.parseInt:(Ljava/lang/String;)I
      16: invokeinterface #5,  2            // InterfaceMethod java/util/function/IntFunction.apply:(I)Ljava/lang/Object;
      21: checkcast     #6                  // class org/springframework/boot/ansi/AnsiElement
      24: areturn
      25: astore_2
      26: aconst_null
      27: areturn
    Exception table:
       from    to  target type
           8    24    25   Class java/lang/IllegalArgumentException

  private boolean containsOnlyDigits(java.lang.String);
    Code:
       0: iconst_0
       1: istore_2
       2: iload_2
       3: aload_1
       4: invokevirtual #8                  // Method java/lang/String.length:()I
       7: if_icmpge     29
      10: aload_1
      11: iload_2
      12: invokevirtual #9                  // Method java/lang/String.charAt:(I)C
      15: invokestatic  #10                 // Method java/lang/Character.isDigit:(C)Z
      18: ifne          23
      21: iconst_0
      22: ireturn
      23: iinc          2, 1
      26: goto          2
      29: aload_1
      30: invokevirtual #11                 // Method java/lang/String.isEmpty:()Z
      33: ifne          40
      36: iconst_1
      37: goto          41
      40: iconst_0
      41: ireturn
}
