Compiled from "ResourceRecordSetStaxUnmarshaller.java"
public class com.amazonaws.services.route53.model.transform.ResourceRecordSetStaxUnmarshaller implements com.amazonaws.transform.Unmarshaller<com.amazonaws.services.route53.model.ResourceRecordSet, com.amazonaws.transform.StaxUnmarshallerContext> {
  private static com.amazonaws.services.route53.model.transform.ResourceRecordSetStaxUnmarshaller instance;

  public com.amazonaws.services.route53.model.transform.ResourceRecordSetStaxUnmarshaller();
    Code:
       0: aload_0
       1: invokespecial #1                  // Method java/lang/Object."<init>":()V
       4: return

  public com.amazonaws.services.route53.model.ResourceRecordSet unmarshall(com.amazonaws.transform.StaxUnmarshallerContext) throws java.lang.Exception;
    Code:
       0: new           #2                  // class com/amazonaws/services/route53/model/ResourceRecordSet
       3: dup
       4: invokespecial #3                  // Method com/amazonaws/services/route53/model/ResourceRecordSet."<init>":()V
       7: astore_2
       8: aload_1
       9: invokevirtual #4                  // Method com/amazonaws/transform/StaxUnmarshallerContext.getCurrentDepth:()I
      12: istore_3
      13: iload_3
      14: iconst_1
      15: iadd
      16: istore        4
      18: aload_1
      19: invokevirtual #5                  // Method com/amazonaws/transform/StaxUnmarshallerContext.isStartOfDocument:()Z
      22: ifeq          28
      25: iinc          4, 1
      28: aload_1
      29: invokevirtual #6                  // Method com/amazonaws/transform/StaxUnmarshallerContext.nextEvent:()Ljavax/xml/stream/events/XMLEvent;
      32: astore        5
      34: aload         5
      36: invokeinterface #7,  1            // InterfaceMethod javax/xml/stream/events/XMLEvent.isEndDocument:()Z
      41: ifeq          46
      44: aload_2
      45: areturn
      46: aload         5
      48: invokeinterface #8,  1            // InterfaceMethod javax/xml/stream/events/XMLEvent.isAttribute:()Z
      53: ifne          66
      56: aload         5
      58: invokeinterface #9,  1            // InterfaceMethod javax/xml/stream/events/XMLEvent.isStartElement:()Z
      63: ifeq          374
      66: aload_1
      67: ldc           #10                 // String Name
      69: iload         4
      71: invokevirtual #11                 // Method com/amazonaws/transform/StaxUnmarshallerContext.testExpression:(Ljava/lang/String;I)Z
      74: ifeq          91
      77: aload_2
      78: invokestatic  #12                 // Method com/amazonaws/transform/SimpleTypeStaxUnmarshallers$StringStaxUnmarshaller.getInstance:()Lcom/amazonaws/transform/SimpleTypeStaxUnmarshallers$StringStaxUnmarshaller;
      81: aload_1
      82: invokevirtual #13                 // Method com/amazonaws/transform/SimpleTypeStaxUnmarshallers$StringStaxUnmarshaller.unmarshall:(Lcom/amazonaws/transform/StaxUnmarshallerContext;)Ljava/lang/String;
      85: invokevirtual #14                 // Method com/amazonaws/services/route53/model/ResourceRecordSet.setName:(Ljava/lang/String;)V
      88: goto          28
      91: aload_1
      92: ldc           #15                 // String Type
      94: iload         4
      96: invokevirtual #11                 // Method com/amazonaws/transform/StaxUnmarshallerContext.testExpression:(Ljava/lang/String;I)Z
      99: ifeq          116
     102: aload_2
     103: invokestatic  #12                 // Method com/amazonaws/transform/SimpleTypeStaxUnmarshallers$StringStaxUnmarshaller.getInstance:()Lcom/amazonaws/transform/SimpleTypeStaxUnmarshallers$StringStaxUnmarshaller;
     106: aload_1
     107: invokevirtual #13                 // Method com/amazonaws/transform/SimpleTypeStaxUnmarshallers$StringStaxUnmarshaller.unmarshall:(Lcom/amazonaws/transform/StaxUnmarshallerContext;)Ljava/lang/String;
     110: invokevirtual #16                 // Method com/amazonaws/services/route53/model/ResourceRecordSet.setType:(Ljava/lang/String;)V
     113: goto          28
     116: aload_1
     117: ldc           #17                 // String SetIdentifier
     119: iload         4
     121: invokevirtual #11                 // Method com/amazonaws/transform/StaxUnmarshallerContext.testExpression:(Ljava/lang/String;I)Z
     124: ifeq          141
     127: aload_2
     128: invokestatic  #12                 // Method com/amazonaws/transform/SimpleTypeStaxUnmarshallers$StringStaxUnmarshaller.getInstance:()Lcom/amazonaws/transform/SimpleTypeStaxUnmarshallers$StringStaxUnmarshaller;
     131: aload_1
     132: invokevirtual #13                 // Method com/amazonaws/transform/SimpleTypeStaxUnmarshallers$StringStaxUnmarshaller.unmarshall:(Lcom/amazonaws/transform/StaxUnmarshallerContext;)Ljava/lang/String;
     135: invokevirtual #18                 // Method com/amazonaws/services/route53/model/ResourceRecordSet.setSetIdentifier:(Ljava/lang/String;)V
     138: goto          28
     141: aload_1
     142: ldc           #19                 // String Weight
     144: iload         4
     146: invokevirtual #11                 // Method com/amazonaws/transform/StaxUnmarshallerContext.testExpression:(Ljava/lang/String;I)Z
     149: ifeq          166
     152: aload_2
     153: invokestatic  #20                 // Method com/amazonaws/transform/SimpleTypeStaxUnmarshallers$LongStaxUnmarshaller.getInstance:()Lcom/amazonaws/transform/SimpleTypeStaxUnmarshallers$LongStaxUnmarshaller;
     156: aload_1
     157: invokevirtual #21                 // Method com/amazonaws/transform/SimpleTypeStaxUnmarshallers$LongStaxUnmarshaller.unmarshall:(Lcom/amazonaws/transform/StaxUnmarshallerContext;)Ljava/lang/Long;
     160: invokevirtual #22                 // Method com/amazonaws/services/route53/model/ResourceRecordSet.setWeight:(Ljava/lang/Long;)V
     163: goto          28
     166: aload_1
     167: ldc           #23                 // String Region
     169: iload         4
     171: invokevirtual #11                 // Method com/amazonaws/transform/StaxUnmarshallerContext.testExpression:(Ljava/lang/String;I)Z
     174: ifeq          191
     177: aload_2
     178: invokestatic  #12                 // Method com/amazonaws/transform/SimpleTypeStaxUnmarshallers$StringStaxUnmarshaller.getInstance:()Lcom/amazonaws/transform/SimpleTypeStaxUnmarshallers$StringStaxUnmarshaller;
     181: aload_1
     182: invokevirtual #13                 // Method com/amazonaws/transform/SimpleTypeStaxUnmarshallers$StringStaxUnmarshaller.unmarshall:(Lcom/amazonaws/transform/StaxUnmarshallerContext;)Ljava/lang/String;
     185: invokevirtual #24                 // Method com/amazonaws/services/route53/model/ResourceRecordSet.setRegion:(Ljava/lang/String;)V
     188: goto          28
     191: aload_1
     192: ldc           #25                 // String GeoLocation
     194: iload         4
     196: invokevirtual #11                 // Method com/amazonaws/transform/StaxUnmarshallerContext.testExpression:(Ljava/lang/String;I)Z
     199: ifeq          216
     202: aload_2
     203: invokestatic  #26                 // Method com/amazonaws/services/route53/model/transform/GeoLocationStaxUnmarshaller.getInstance:()Lcom/amazonaws/services/route53/model/transform/GeoLocationStaxUnmarshaller;
     206: aload_1
     207: invokevirtual #27                 // Method com/amazonaws/services/route53/model/transform/GeoLocationStaxUnmarshaller.unmarshall:(Lcom/amazonaws/transform/StaxUnmarshallerContext;)Lcom/amazonaws/services/route53/model/GeoLocation;
     210: invokevirtual #28                 // Method com/amazonaws/services/route53/model/ResourceRecordSet.setGeoLocation:(Lcom/amazonaws/services/route53/model/GeoLocation;)V
     213: goto          28
     216: aload_1
     217: ldc           #29                 // String Failover
     219: iload         4
     221: invokevirtual #11                 // Method com/amazonaws/transform/StaxUnmarshallerContext.testExpression:(Ljava/lang/String;I)Z
     224: ifeq          241
     227: aload_2
     228: invokestatic  #12                 // Method com/amazonaws/transform/SimpleTypeStaxUnmarshallers$StringStaxUnmarshaller.getInstance:()Lcom/amazonaws/transform/SimpleTypeStaxUnmarshallers$StringStaxUnmarshaller;
     231: aload_1
     232: invokevirtual #13                 // Method com/amazonaws/transform/SimpleTypeStaxUnmarshallers$StringStaxUnmarshaller.unmarshall:(Lcom/amazonaws/transform/StaxUnmarshallerContext;)Ljava/lang/String;
     235: invokevirtual #30                 // Method com/amazonaws/services/route53/model/ResourceRecordSet.setFailover:(Ljava/lang/String;)V
     238: goto          28
     241: aload_1
     242: ldc           #31                 // String TTL
     244: iload         4
     246: invokevirtual #11                 // Method com/amazonaws/transform/StaxUnmarshallerContext.testExpression:(Ljava/lang/String;I)Z
     249: ifeq          266
     252: aload_2
     253: invokestatic  #20                 // Method com/amazonaws/transform/SimpleTypeStaxUnmarshallers$LongStaxUnmarshaller.getInstance:()Lcom/amazonaws/transform/SimpleTypeStaxUnmarshallers$LongStaxUnmarshaller;
     256: aload_1
     257: invokevirtual #21                 // Method com/amazonaws/transform/SimpleTypeStaxUnmarshallers$LongStaxUnmarshaller.unmarshall:(Lcom/amazonaws/transform/StaxUnmarshallerContext;)Ljava/lang/Long;
     260: invokevirtual #32                 // Method com/amazonaws/services/route53/model/ResourceRecordSet.setTTL:(Ljava/lang/Long;)V
     263: goto          28
     266: aload_1
     267: ldc           #33                 // String ResourceRecords/ResourceRecord
     269: iload         4
     271: invokevirtual #11                 // Method com/amazonaws/transform/StaxUnmarshallerContext.testExpression:(Ljava/lang/String;I)Z
     274: ifeq          299
     277: aload_2
     278: iconst_1
     279: anewarray     #34                 // class com/amazonaws/services/route53/model/ResourceRecord
     282: dup
     283: iconst_0
     284: invokestatic  #35                 // Method com/amazonaws/services/route53/model/transform/ResourceRecordStaxUnmarshaller.getInstance:()Lcom/amazonaws/services/route53/model/transform/ResourceRecordStaxUnmarshaller;
     287: aload_1
     288: invokevirtual #36                 // Method com/amazonaws/services/route53/model/transform/ResourceRecordStaxUnmarshaller.unmarshall:(Lcom/amazonaws/transform/StaxUnmarshallerContext;)Lcom/amazonaws/services/route53/model/ResourceRecord;
     291: aastore
     292: invokevirtual #37                 // Method com/amazonaws/services/route53/model/ResourceRecordSet.withResourceRecords:([Lcom/amazonaws/services/route53/model/ResourceRecord;)Lcom/amazonaws/services/route53/model/ResourceRecordSet;
     295: pop
     296: goto          28
     299: aload_1
     300: ldc           #38                 // String AliasTarget
     302: iload         4
     304: invokevirtual #11                 // Method com/amazonaws/transform/StaxUnmarshallerContext.testExpression:(Ljava/lang/String;I)Z
     307: ifeq          324
     310: aload_2
     311: invokestatic  #39                 // Method com/amazonaws/services/route53/model/transform/AliasTargetStaxUnmarshaller.getInstance:()Lcom/amazonaws/services/route53/model/transform/AliasTargetStaxUnmarshaller;
     314: aload_1
     315: invokevirtual #40                 // Method com/amazonaws/services/route53/model/transform/AliasTargetStaxUnmarshaller.unmarshall:(Lcom/amazonaws/transform/StaxUnmarshallerContext;)Lcom/amazonaws/services/route53/model/AliasTarget;
     318: invokevirtual #41                 // Method com/amazonaws/services/route53/model/ResourceRecordSet.setAliasTarget:(Lcom/amazonaws/services/route53/model/AliasTarget;)V
     321: goto          28
     324: aload_1
     325: ldc           #42                 // String HealthCheckId
     327: iload         4
     329: invokevirtual #11                 // Method com/amazonaws/transform/StaxUnmarshallerContext.testExpression:(Ljava/lang/String;I)Z
     332: ifeq          349
     335: aload_2
     336: invokestatic  #12                 // Method com/amazonaws/transform/SimpleTypeStaxUnmarshallers$StringStaxUnmarshaller.getInstance:()Lcom/amazonaws/transform/SimpleTypeStaxUnmarshallers$StringStaxUnmarshaller;
     339: aload_1
     340: invokevirtual #13                 // Method com/amazonaws/transform/SimpleTypeStaxUnmarshallers$StringStaxUnmarshaller.unmarshall:(Lcom/amazonaws/transform/StaxUnmarshallerContext;)Ljava/lang/String;
     343: invokevirtual #43                 // Method com/amazonaws/services/route53/model/ResourceRecordSet.setHealthCheckId:(Ljava/lang/String;)V
     346: goto          28
     349: aload_1
     350: ldc           #44                 // String TrafficPolicyInstanceId
     352: iload         4
     354: invokevirtual #11                 // Method com/amazonaws/transform/StaxUnmarshallerContext.testExpression:(Ljava/lang/String;I)Z
     357: ifeq          394
     360: aload_2
     361: invokestatic  #12                 // Method com/amazonaws/transform/SimpleTypeStaxUnmarshallers$StringStaxUnmarshaller.getInstance:()Lcom/amazonaws/transform/SimpleTypeStaxUnmarshallers$StringStaxUnmarshaller;
     364: aload_1
     365: invokevirtual #13                 // Method com/amazonaws/transform/SimpleTypeStaxUnmarshallers$StringStaxUnmarshaller.unmarshall:(Lcom/amazonaws/transform/StaxUnmarshallerContext;)Ljava/lang/String;
     368: invokevirtual #45                 // Method com/amazonaws/services/route53/model/ResourceRecordSet.setTrafficPolicyInstanceId:(Ljava/lang/String;)V
     371: goto          28
     374: aload         5
     376: invokeinterface #46,  1           // InterfaceMethod javax/xml/stream/events/XMLEvent.isEndElement:()Z
     381: ifeq          394
     384: aload_1
     385: invokevirtual #4                  // Method com/amazonaws/transform/StaxUnmarshallerContext.getCurrentDepth:()I
     388: iload_3
     389: if_icmpge     394
     392: aload_2
     393: areturn
     394: goto          28

  public static com.amazonaws.services.route53.model.transform.ResourceRecordSetStaxUnmarshaller getInstance();
    Code:
       0: getstatic     #47                 // Field instance:Lcom/amazonaws/services/route53/model/transform/ResourceRecordSetStaxUnmarshaller;
       3: ifnonnull     16
       6: new           #48                 // class com/amazonaws/services/route53/model/transform/ResourceRecordSetStaxUnmarshaller
       9: dup
      10: invokespecial #49                 // Method "<init>":()V
      13: putstatic     #47                 // Field instance:Lcom/amazonaws/services/route53/model/transform/ResourceRecordSetStaxUnmarshaller;
      16: getstatic     #47                 // Field instance:Lcom/amazonaws/services/route53/model/transform/ResourceRecordSetStaxUnmarshaller;
      19: areturn

  public java.lang.Object unmarshall(java.lang.Object) throws java.lang.Exception;
    Code:
       0: aload_0
       1: aload_1
       2: checkcast     #50                 // class com/amazonaws/transform/StaxUnmarshallerContext
       5: invokevirtual #51                 // Method unmarshall:(Lcom/amazonaws/transform/StaxUnmarshallerContext;)Lcom/amazonaws/services/route53/model/ResourceRecordSet;
       8: areturn
}
