Compiled from "DescribeProtectionResponse.java"
public interface software.amazon.awssdk.services.shield.model.DescribeProtectionResponse$Builder extends software.amazon.awssdk.services.shield.model.ShieldResponse$Builder, software.amazon.awssdk.core.SdkPojo, software.amazon.awssdk.utils.builder.CopyableBuilder<software.amazon.awssdk.services.shield.model.DescribeProtectionResponse$Builder, software.amazon.awssdk.services.shield.model.DescribeProtectionResponse> {
  public abstract software.amazon.awssdk.services.shield.model.DescribeProtectionResponse$Builder protection(software.amazon.awssdk.services.shield.model.Protection);

  public default software.amazon.awssdk.services.shield.model.DescribeProtectionResponse$Builder protection(java.util.function.Consumer<software.amazon.awssdk.services.shield.model.Protection$Builder>);
    Code:
       0: aload_0
       1: invokestatic  #1                  // Method software/amazon/awssdk/services/shield/model/Protection.builder:()Lsoftware/amazon/awssdk/services/shield/model/Protection$Builder;
       4: aload_1
       5: invokeinterface #2,  2            // InterfaceMethod software/amazon/awssdk/services/shield/model/Protection$Builder.applyMutation:(Ljava/util/function/Consumer;)Lsoftware/amazon/awssdk/utils/builder/SdkBuilder;
      10: checkcast     #3                  // class software/amazon/awssdk/services/shield/model/Protection$Builder
      13: invokeinterface #4,  1            // InterfaceMethod software/amazon/awssdk/services/shield/model/Protection$Builder.build:()Ljava/lang/Object;
      18: checkcast     #5                  // class software/amazon/awssdk/services/shield/model/Protection
      21: invokeinterface #6,  2            // InterfaceMethod protection:(Lsoftware/amazon/awssdk/services/shield/model/Protection;)Lsoftware/amazon/awssdk/services/shield/model/DescribeProtectionResponse$Builder;
      26: areturn
}
