Compiled from "StreamELResolverImpl.java"
public class org.apache.el.stream.StreamELResolverImpl extends javax.el.ELResolver {
  public org.apache.el.stream.StreamELResolverImpl();
    Code:
       0: aload_0
       1: invokespecial #1                  // Method javax/el/ELResolver."<init>":()V
       4: return

  public java.lang.Object getValue(javax.el.ELContext, java.lang.Object, java.lang.Object);
    Code:
       0: aconst_null
       1: areturn

  public java.lang.Class<?> getType(javax.el.ELContext, java.lang.Object, java.lang.Object);
    Code:
       0: aconst_null
       1: areturn

  public void setValue(javax.el.ELContext, java.lang.Object, java.lang.Object, java.lang.Object);
    Code:
       0: return

  public boolean isReadOnly(javax.el.ELContext, java.lang.Object, java.lang.Object);
    Code:
       0: iconst_0
       1: ireturn

  public java.util.Iterator<java.beans.FeatureDescriptor> getFeatureDescriptors(javax.el.ELContext, java.lang.Object);
    Code:
       0: aconst_null
       1: areturn

  public java.lang.Class<?> getCommonPropertyType(javax.el.ELContext, java.lang.Object);
    Code:
       0: aconst_null
       1: areturn

  public java.lang.Object invoke(javax.el.ELContext, java.lang.Object, java.lang.Object, java.lang.Class<?>[], java.lang.Object[]);
    Code:
       0: ldc           #2                  // String stream
       2: aload_3
       3: invokevirtual #3                  // Method java/lang/String.equals:(Ljava/lang/Object;)Z
       6: ifeq          79
       9: aload         5
      11: arraylength
      12: ifne          79
      15: aload_2
      16: invokevirtual #4                  // Method java/lang/Object.getClass:()Ljava/lang/Class;
      19: invokevirtual #5                  // Method java/lang/Class.isArray:()Z
      22: ifeq          46
      25: aload_1
      26: iconst_1
      27: invokevirtual #6                  // Method javax/el/ELContext.setPropertyResolved:(Z)V
      30: new           #7                  // class org/apache/el/stream/Stream
      33: dup
      34: new           #8                  // class org/apache/el/stream/StreamELResolverImpl$ArrayIterator
      37: dup
      38: aload_2
      39: invokespecial #9                  // Method org/apache/el/stream/StreamELResolverImpl$ArrayIterator."<init>":(Ljava/lang/Object;)V
      42: invokespecial #10                 // Method org/apache/el/stream/Stream."<init>":(Ljava/util/Iterator;)V
      45: areturn
      46: aload_2
      47: instanceof    #11                 // class java/util/Collection
      50: ifeq          79
      53: aload_1
      54: iconst_1
      55: invokevirtual #6                  // Method javax/el/ELContext.setPropertyResolved:(Z)V
      58: aload_2
      59: checkcast     #11                 // class java/util/Collection
      62: astore        6
      64: new           #7                  // class org/apache/el/stream/Stream
      67: dup
      68: aload         6
      70: invokeinterface #12,  1           // InterfaceMethod java/util/Collection.iterator:()Ljava/util/Iterator;
      75: invokespecial #10                 // Method org/apache/el/stream/Stream."<init>":(Ljava/util/Iterator;)V
      78: areturn
      79: aconst_null
      80: areturn
}
