Compiled from "AbstractBindHandler.java"
public abstract class org.springframework.boot.context.properties.bind.AbstractBindHandler implements org.springframework.boot.context.properties.bind.BindHandler {
  private final org.springframework.boot.context.properties.bind.BindHandler parent;

  public org.springframework.boot.context.properties.bind.AbstractBindHandler();
    Code:
       0: aload_0
       1: getstatic     #1                  // Field org/springframework/boot/context/properties/bind/BindHandler.DEFAULT:Lorg/springframework/boot/context/properties/bind/BindHandler;
       4: invokespecial #2                  // Method "<init>":(Lorg/springframework/boot/context/properties/bind/BindHandler;)V
       7: return

  public org.springframework.boot.context.properties.bind.AbstractBindHandler(org.springframework.boot.context.properties.bind.BindHandler);
    Code:
       0: aload_0
       1: invokespecial #3                  // Method java/lang/Object."<init>":()V
       4: aload_1
       5: ldc           #4                  // String Parent must not be null
       7: invokestatic  #5                  // Method org/springframework/util/Assert.notNull:(Ljava/lang/Object;Ljava/lang/String;)V
      10: aload_0
      11: aload_1
      12: putfield      #6                  // Field parent:Lorg/springframework/boot/context/properties/bind/BindHandler;
      15: return

  public <T> org.springframework.boot.context.properties.bind.Bindable<T> onStart(org.springframework.boot.context.properties.source.ConfigurationPropertyName, org.springframework.boot.context.properties.bind.Bindable<T>, org.springframework.boot.context.properties.bind.BindContext);
    Code:
       0: aload_0
       1: getfield      #6                  // Field parent:Lorg/springframework/boot/context/properties/bind/BindHandler;
       4: aload_1
       5: aload_2
       6: aload_3
       7: invokeinterface #7,  4            // InterfaceMethod org/springframework/boot/context/properties/bind/BindHandler.onStart:(Lorg/springframework/boot/context/properties/source/ConfigurationPropertyName;Lorg/springframework/boot/context/properties/bind/Bindable;Lorg/springframework/boot/context/properties/bind/BindContext;)Lorg/springframework/boot/context/properties/bind/Bindable;
      12: areturn

  public java.lang.Object onSuccess(org.springframework.boot.context.properties.source.ConfigurationPropertyName, org.springframework.boot.context.properties.bind.Bindable<?>, org.springframework.boot.context.properties.bind.BindContext, java.lang.Object);
    Code:
       0: aload_0
       1: getfield      #6                  // Field parent:Lorg/springframework/boot/context/properties/bind/BindHandler;
       4: aload_1
       5: aload_2
       6: aload_3
       7: aload         4
       9: invokeinterface #8,  5            // InterfaceMethod org/springframework/boot/context/properties/bind/BindHandler.onSuccess:(Lorg/springframework/boot/context/properties/source/ConfigurationPropertyName;Lorg/springframework/boot/context/properties/bind/Bindable;Lorg/springframework/boot/context/properties/bind/BindContext;Ljava/lang/Object;)Ljava/lang/Object;
      14: areturn

  public java.lang.Object onFailure(org.springframework.boot.context.properties.source.ConfigurationPropertyName, org.springframework.boot.context.properties.bind.Bindable<?>, org.springframework.boot.context.properties.bind.BindContext, java.lang.Exception) throws java.lang.Exception;
    Code:
       0: aload_0
       1: getfield      #6                  // Field parent:Lorg/springframework/boot/context/properties/bind/BindHandler;
       4: aload_1
       5: aload_2
       6: aload_3
       7: aload         4
       9: invokeinterface #9,  5            // InterfaceMethod org/springframework/boot/context/properties/bind/BindHandler.onFailure:(Lorg/springframework/boot/context/properties/source/ConfigurationPropertyName;Lorg/springframework/boot/context/properties/bind/Bindable;Lorg/springframework/boot/context/properties/bind/BindContext;Ljava/lang/Exception;)Ljava/lang/Object;
      14: areturn

  public void onFinish(org.springframework.boot.context.properties.source.ConfigurationPropertyName, org.springframework.boot.context.properties.bind.Bindable<?>, org.springframework.boot.context.properties.bind.BindContext, java.lang.Object) throws java.lang.Exception;
    Code:
       0: aload_0
       1: getfield      #6                  // Field parent:Lorg/springframework/boot/context/properties/bind/BindHandler;
       4: aload_1
       5: aload_2
       6: aload_3
       7: aload         4
       9: invokeinterface #10,  5           // InterfaceMethod org/springframework/boot/context/properties/bind/BindHandler.onFinish:(Lorg/springframework/boot/context/properties/source/ConfigurationPropertyName;Lorg/springframework/boot/context/properties/bind/Bindable;Lorg/springframework/boot/context/properties/bind/BindContext;Ljava/lang/Object;)V
      14: return
}
