Compiled from "AudioCue.scala"
public interface de.sciss.proc.AudioCue$Obj$LongOpImpl<T extends de.sciss.lucre.Txn<T>> extends de.sciss.lucre.impl.ExprNodeImpl<T, de.sciss.proc.AudioCue>, de.sciss.proc.AudioCue$Obj<T> {
  public static void $init$(de.sciss.proc.AudioCue$Obj$LongOpImpl);
    Code:
       0: return

  public abstract de.sciss.proc.AudioCue$Obj<T> peer();

  public abstract de.sciss.lucre.LongObj<T> num();

  public abstract int opId();

  public abstract de.sciss.proc.AudioCue mapNum(de.sciss.proc.AudioCue, long);

  public static de.sciss.lucre.Obj$Type tpe$(de.sciss.proc.AudioCue$Obj$LongOpImpl);
    Code:
       0: aload_0
       1: invokespecial #47                 // InterfaceMethod tpe:()Lde/sciss/lucre/Obj$Type;
       4: areturn

  public default de.sciss.lucre.Obj$Type tpe();
    Code:
       0: getstatic     #51                 // Field de/sciss/proc/AudioCue$Obj$.MODULE$:Lde/sciss/proc/AudioCue$Obj$;
       3: areturn

  public static de.sciss.audiofile.AudioFileSpec spec$(de.sciss.proc.AudioCue$Obj$LongOpImpl, de.sciss.lucre.Txn);
    Code:
       0: aload_0
       1: aload_1
       2: invokespecial #59                 // InterfaceMethod spec:(Lde/sciss/lucre/Txn;)Lde/sciss/audiofile/AudioFileSpec;
       5: areturn

  public default de.sciss.audiofile.AudioFileSpec spec(T);
    Code:
       0: aload_0
       1: invokeinterface #63,  1           // InterfaceMethod peer:()Lde/sciss/proc/AudioCue$Obj;
       6: aload_1
       7: invokeinterface #64,  2           // InterfaceMethod de/sciss/proc/AudioCue$Obj.spec:(Lde/sciss/lucre/Txn;)Lde/sciss/audiofile/AudioFileSpec;
      12: areturn

  public static de.sciss.proc.AudioCue value$(de.sciss.proc.AudioCue$Obj$LongOpImpl, de.sciss.lucre.Txn);
    Code:
       0: aload_0
       1: aload_1
       2: invokespecial #70                 // InterfaceMethod value:(Lde/sciss/lucre/Txn;)Lde/sciss/proc/AudioCue;
       5: areturn

  public default de.sciss.proc.AudioCue value(T);
    Code:
       0: aload_0
       1: invokeinterface #63,  1           // InterfaceMethod peer:()Lde/sciss/proc/AudioCue$Obj;
       6: aload_1
       7: invokeinterface #74,  2           // InterfaceMethod de/sciss/proc/AudioCue$Obj.value:(Lde/sciss/lucre/Exec;)Ljava/lang/Object;
      12: checkcast     #17                 // class de/sciss/proc/AudioCue
      15: astore_2
      16: aload_0
      17: invokeinterface #76,  1           // InterfaceMethod num:()Lde/sciss/lucre/LongObj;
      22: aload_1
      23: invokeinterface #79,  2           // InterfaceMethod de/sciss/lucre/LongObj.value:(Lde/sciss/lucre/Exec;)Ljava/lang/Object;
      28: invokestatic  #85                 // Method scala/runtime/BoxesRunTime.unboxToLong:(Ljava/lang/Object;)J
      31: lstore_3
      32: aload_0
      33: aload_2
      34: lload_3
      35: invokeinterface #87,  4           // InterfaceMethod mapNum:(Lde/sciss/proc/AudioCue;J)Lde/sciss/proc/AudioCue;
      40: areturn

  public static de.sciss.proc.AudioCue$Obj$LongOpImpl<T>.changed$ changed$(de.sciss.proc.AudioCue$Obj$LongOpImpl);
    Code:
       0: aload_0
       1: invokespecial #95                 // InterfaceMethod changed:()Lde/sciss/proc/AudioCue$Obj$LongOpImpl$changed$;
       4: areturn

  public default de.sciss.proc.AudioCue$Obj$LongOpImpl$changed$ changed();
    Code:
       0: new           #24                 // class de/sciss/proc/AudioCue$Obj$LongOpImpl$changed$
       3: dup
       4: aload_0
       5: invokespecial #98                 // Method de/sciss/proc/AudioCue$Obj$LongOpImpl$changed$."<init>":(Lde/sciss/proc/AudioCue$Obj$LongOpImpl;)V
       8: areturn

  public static de.sciss.proc.AudioCue$Obj$LongOpImpl connect$(de.sciss.proc.AudioCue$Obj$LongOpImpl, de.sciss.lucre.Txn);
    Code:
       0: aload_0
       1: aload_1
       2: invokespecial #104                // InterfaceMethod connect:(Lde/sciss/lucre/Txn;)Lde/sciss/proc/AudioCue$Obj$LongOpImpl;
       5: areturn

  public default de.sciss.proc.AudioCue$Obj$LongOpImpl connect(T);
    Code:
       0: aload_0
       1: invokeinterface #63,  1           // InterfaceMethod peer:()Lde/sciss/proc/AudioCue$Obj;
       6: invokeinterface #108,  1          // InterfaceMethod de/sciss/proc/AudioCue$Obj.changed:()Lde/sciss/lucre/EventLike;
      11: aload_0
      12: invokeinterface #95,  1           // InterfaceMethod changed:()Lde/sciss/proc/AudioCue$Obj$LongOpImpl$changed$;
      17: aload_1
      18: invokeinterface #114,  3          // InterfaceMethod de/sciss/lucre/EventLike.$minus$minus$minus$greater:(Lde/sciss/lucre/Event;Lde/sciss/lucre/Txn;)V
      23: aload_0
      24: invokeinterface #76,  1           // InterfaceMethod num:()Lde/sciss/lucre/LongObj;
      29: invokeinterface #115,  1          // InterfaceMethod de/sciss/lucre/LongObj.changed:()Lde/sciss/lucre/EventLike;
      34: aload_0
      35: invokeinterface #95,  1           // InterfaceMethod changed:()Lde/sciss/proc/AudioCue$Obj$LongOpImpl$changed$;
      40: aload_1
      41: invokeinterface #114,  3          // InterfaceMethod de/sciss/lucre/EventLike.$minus$minus$minus$greater:(Lde/sciss/lucre/Event;Lde/sciss/lucre/Txn;)V
      46: aload_0
      47: areturn

  private void disconnect(T);
    Code:
       0: aload_0
       1: invokeinterface #63,  1           // InterfaceMethod peer:()Lde/sciss/proc/AudioCue$Obj;
       6: invokeinterface #108,  1          // InterfaceMethod de/sciss/proc/AudioCue$Obj.changed:()Lde/sciss/lucre/EventLike;
      11: aload_0
      12: invokeinterface #95,  1           // InterfaceMethod changed:()Lde/sciss/proc/AudioCue$Obj$LongOpImpl$changed$;
      17: aload_1
      18: invokeinterface #121,  3          // InterfaceMethod de/sciss/lucre/EventLike.$minus$div$minus$greater:(Lde/sciss/lucre/Event;Lde/sciss/lucre/Txn;)V
      23: aload_0
      24: invokeinterface #76,  1           // InterfaceMethod num:()Lde/sciss/lucre/LongObj;
      29: invokeinterface #115,  1          // InterfaceMethod de/sciss/lucre/LongObj.changed:()Lde/sciss/lucre/EventLike;
      34: aload_0
      35: invokeinterface #95,  1           // InterfaceMethod changed:()Lde/sciss/proc/AudioCue$Obj$LongOpImpl$changed$;
      40: aload_1
      41: invokeinterface #121,  3          // InterfaceMethod de/sciss/lucre/EventLike.$minus$div$minus$greater:(Lde/sciss/lucre/Event;Lde/sciss/lucre/Txn;)V
      46: return

  public static void writeData$(de.sciss.proc.AudioCue$Obj$LongOpImpl, de.sciss.serial.DataOutput);
    Code:
       0: aload_0
       1: aload_1
       2: invokespecial #128                // InterfaceMethod writeData:(Lde/sciss/serial/DataOutput;)V
       5: return

  public default void writeData(de.sciss.serial.DataOutput);
    Code:
       0: aload_1
       1: iconst_1
       2: invokeinterface #135,  2          // InterfaceMethod de/sciss/serial/DataOutput.writeByte:(I)V
       7: aload_1
       8: aload_0
       9: invokeinterface #137,  1          // InterfaceMethod opId:()I
      14: invokeinterface #140,  2          // InterfaceMethod de/sciss/serial/DataOutput.writeInt:(I)V
      19: aload_0
      20: invokeinterface #63,  1           // InterfaceMethod peer:()Lde/sciss/proc/AudioCue$Obj;
      25: aload_1
      26: invokeinterface #143,  2          // InterfaceMethod de/sciss/proc/AudioCue$Obj.write:(Lde/sciss/serial/DataOutput;)V
      31: aload_0
      32: invokeinterface #76,  1           // InterfaceMethod num:()Lde/sciss/lucre/LongObj;
      37: aload_1
      38: invokeinterface #144,  2          // InterfaceMethod de/sciss/lucre/LongObj.write:(Lde/sciss/serial/DataOutput;)V
      43: return

  public static void disposeData$(de.sciss.proc.AudioCue$Obj$LongOpImpl, de.sciss.lucre.Txn);
    Code:
       0: aload_0
       1: aload_1
       2: invokespecial #149                // InterfaceMethod disposeData:(Lde/sciss/lucre/Txn;)V
       5: return

  public default void disposeData(T);
    Code:
       0: aload_0
       1: aload_1
       2: invokespecial #151                // InterfaceMethod disconnect:(Lde/sciss/lucre/Txn;)V
       5: return
}
