Compiled from "AuralObj.scala"
public final class de.sciss.proc.AuralObj$TargetPlaying$ implements scala.deriving.Mirror$Product,java.io.Serializable {
  public static final de.sciss.proc.AuralObj$TargetPlaying$ MODULE$;

  public de.sciss.proc.AuralObj$TargetPlaying$();
    Code:
       0: aload_0
       1: invokespecial #24                 // Method java/lang/Object."<init>":()V
       4: return

  public static {};
    Code:
       0: new           #2                  // class de/sciss/proc/AuralObj$TargetPlaying$
       3: dup
       4: invokespecial #27                 // Method "<init>":()V
       7: putstatic     #29                 // Field MODULE$:Lde/sciss/proc/AuralObj$TargetPlaying$;
      10: return

  private java.lang.Object writeReplace();
    Code:
       0: new           #33                 // class scala/runtime/ModuleSerializationProxy
       3: dup
       4: ldc           #2                  // class de/sciss/proc/AuralObj$TargetPlaying$
       6: invokespecial #36                 // Method scala/runtime/ModuleSerializationProxy."<init>":(Ljava/lang/Class;)V
       9: areturn

  public de.sciss.proc.AuralObj$TargetPlaying apply(long, de.sciss.proc.TimeRef);
    Code:
       0: new           #11                 // class de/sciss/proc/AuralObj$TargetPlaying
       3: dup
       4: lload_1
       5: aload_3
       6: invokespecial #43                 // Method de/sciss/proc/AuralObj$TargetPlaying."<init>":(JLde/sciss/proc/TimeRef;)V
       9: areturn

  public de.sciss.proc.AuralObj$TargetPlaying unapply(de.sciss.proc.AuralObj$TargetPlaying);
    Code:
       0: aload_1
       1: areturn

  public java.lang.String toString();
    Code:
       0: ldc           #52                 // String TargetPlaying
       2: areturn

  public de.sciss.proc.AuralObj$TargetPlaying fromProduct(scala.Product);
    Code:
       0: new           #11                 // class de/sciss/proc/AuralObj$TargetPlaying
       3: dup
       4: aload_1
       5: iconst_0
       6: invokeinterface #61,  2           // InterfaceMethod scala/Product.productElement:(I)Ljava/lang/Object;
      11: invokestatic  #67                 // Method scala/runtime/BoxesRunTime.unboxToLong:(Ljava/lang/Object;)J
      14: aload_1
      15: iconst_1
      16: invokeinterface #61,  2           // InterfaceMethod scala/Product.productElement:(I)Ljava/lang/Object;
      21: checkcast     #69                 // class de/sciss/proc/TimeRef
      24: invokespecial #43                 // Method de/sciss/proc/AuralObj$TargetPlaying."<init>":(JLde/sciss/proc/TimeRef;)V
      27: areturn

  public java.lang.Object fromProduct(scala.Product);
    Code:
       0: aload_0
       1: aload_1
       2: invokevirtual #74                 // Method fromProduct:(Lscala/Product;)Lde/sciss/proc/AuralObj$TargetPlaying;
       5: areturn
}
