Compiled from "AuralObj.scala"
public final class de.sciss.proc.AuralObj$Proc$AttrRemoved<T extends de.sciss.lucre.Txn<T>> implements de.sciss.proc.AuralObj$Proc$AttrUpdate<T>, scala.Product, java.io.Serializable {
  private final de.sciss.proc.AuralObj$Proc proc;

  private final de.sciss.proc.AuralAttribute attr;

  public static <T extends de.sciss.lucre.Txn<T>> de.sciss.proc.AuralObj$Proc$AttrRemoved<T> apply(de.sciss.proc.AuralObj$Proc<T>, de.sciss.proc.AuralAttribute<T>);
    Code:
       0: getstatic     #36                 // Field de/sciss/proc/AuralObj$Proc$AttrRemoved$.MODULE$:Lde/sciss/proc/AuralObj$Proc$AttrRemoved$;
       3: aload_0
       4: aload_1
       5: invokevirtual #38                 // Method de/sciss/proc/AuralObj$Proc$AttrRemoved$.apply:(Lde/sciss/proc/AuralObj$Proc;Lde/sciss/proc/AuralAttribute;)Lde/sciss/proc/AuralObj$Proc$AttrRemoved;
       8: areturn

  public static de.sciss.proc.AuralObj$Proc$AttrRemoved fromProduct(scala.Product);
    Code:
       0: getstatic     #36                 // Field de/sciss/proc/AuralObj$Proc$AttrRemoved$.MODULE$:Lde/sciss/proc/AuralObj$Proc$AttrRemoved$;
       3: aload_0
       4: invokevirtual #42                 // Method de/sciss/proc/AuralObj$Proc$AttrRemoved$.fromProduct:(Lscala/Product;)Lde/sciss/proc/AuralObj$Proc$AttrRemoved;
       7: areturn

  public static <T extends de.sciss.lucre.Txn<T>> de.sciss.proc.AuralObj$Proc$AttrRemoved<T> unapply(de.sciss.proc.AuralObj$Proc$AttrRemoved<T>);
    Code:
       0: getstatic     #36                 // Field de/sciss/proc/AuralObj$Proc$AttrRemoved$.MODULE$:Lde/sciss/proc/AuralObj$Proc$AttrRemoved$;
       3: aload_0
       4: invokevirtual #47                 // Method de/sciss/proc/AuralObj$Proc$AttrRemoved$.unapply:(Lde/sciss/proc/AuralObj$Proc$AttrRemoved;)Lde/sciss/proc/AuralObj$Proc$AttrRemoved;
       7: areturn

  public de.sciss.proc.AuralObj$Proc$AttrRemoved(de.sciss.proc.AuralObj$Proc<T>, de.sciss.proc.AuralAttribute<T>);
    Code:
       0: aload_0
       1: aload_1
       2: putfield      #52                 // Field proc:Lde/sciss/proc/AuralObj$Proc;
       5: aload_0
       6: aload_2
       7: putfield      #54                 // Field attr:Lde/sciss/proc/AuralAttribute;
      10: aload_0
      11: invokespecial #57                 // Method java/lang/Object."<init>":()V
      14: return

  public java.lang.String key();
    Code:
       0: aload_0
       1: invokestatic  #65                 // InterfaceMethod de/sciss/proc/AuralObj$Proc$AttrUpdate.key$:(Lde/sciss/proc/AuralObj$Proc$AttrUpdate;)Ljava/lang/String;
       4: areturn

  public scala.collection.Iterator productIterator();
    Code:
       0: aload_0
       1: invokestatic  #71                 // InterfaceMethod scala/Product.productIterator$:(Lscala/Product;)Lscala/collection/Iterator;
       4: areturn

  public scala.collection.Iterator productElementNames();
    Code:
       0: aload_0
       1: invokestatic  #75                 // InterfaceMethod scala/Product.productElementNames$:(Lscala/Product;)Lscala/collection/Iterator;
       4: areturn

  public int hashCode();
    Code:
       0: getstatic     #82                 // Field scala/runtime/ScalaRunTime$.MODULE$:Lscala/runtime/ScalaRunTime$;
       3: aload_0
       4: invokevirtual #86                 // Method scala/runtime/ScalaRunTime$._hashCode:(Lscala/Product;)I
       7: ireturn

  public boolean equals(java.lang.Object);
    Code:
       0: aload_0
       1: aload_1
       2: if_acmpeq     96
       5: aload_1
       6: astore_2
       7: aload_2
       8: instanceof    #2                  // class de/sciss/proc/AuralObj$Proc$AttrRemoved
      11: ifeq          89
      14: aload_2
      15: checkcast     #2                  // class de/sciss/proc/AuralObj$Proc$AttrRemoved
      18: astore_3
      19: aload_0
      20: invokevirtual #92                 // Method proc:()Lde/sciss/proc/AuralObj$Proc;
      23: aload_3
      24: invokevirtual #92                 // Method proc:()Lde/sciss/proc/AuralObj$Proc;
      27: astore        4
      29: dup
      30: ifnonnull     42
      33: pop
      34: aload         4
      36: ifnull        50
      39: goto          85
      42: aload         4
      44: invokevirtual #94                 // Method java/lang/Object.equals:(Ljava/lang/Object;)Z
      47: ifeq          85
      50: aload_0
      51: invokevirtual #97                 // Method attr:()Lde/sciss/proc/AuralAttribute;
      54: aload_3
      55: invokevirtual #97                 // Method attr:()Lde/sciss/proc/AuralAttribute;
      58: astore        5
      60: dup
      61: ifnonnull     73
      64: pop
      65: aload         5
      67: ifnull        81
      70: goto          85
      73: aload         5
      75: invokevirtual #94                 // Method java/lang/Object.equals:(Ljava/lang/Object;)Z
      78: ifeq          85
      81: iconst_1
      82: goto          86
      85: iconst_0
      86: goto          93
      89: iconst_0
      90: goto          93
      93: ifeq          100
      96: iconst_1
      97: goto          101
     100: iconst_0
     101: ireturn

  public java.lang.String toString();
    Code:
       0: getstatic     #82                 // Field scala/runtime/ScalaRunTime$.MODULE$:Lscala/runtime/ScalaRunTime$;
       3: aload_0
       4: invokevirtual #105                // Method scala/runtime/ScalaRunTime$._toString:(Lscala/Product;)Ljava/lang/String;
       7: areturn

  public boolean canEqual(java.lang.Object);
    Code:
       0: aload_1
       1: instanceof    #2                  // class de/sciss/proc/AuralObj$Proc$AttrRemoved
       4: ireturn

  public int productArity();
    Code:
       0: iconst_2
       1: ireturn

  public java.lang.String productPrefix();
    Code:
       0: ldc           #110                // String AttrRemoved
       2: areturn

  public java.lang.Object productElement(int);
    Code:
       0: iload_1
       1: istore_2
       2: iconst_0
       3: iload_2
       4: if_icmpne     14
       7: aload_0
       8: invokevirtual #116                // Method _1:()Lde/sciss/proc/AuralObj$Proc;
      11: goto          41
      14: iconst_1
      15: iload_2
      16: if_icmpne     26
      19: aload_0
      20: invokevirtual #119                // Method _2:()Lde/sciss/proc/AuralAttribute;
      23: goto          41
      26: new           #121                // class java/lang/IndexOutOfBoundsException
      29: dup
      30: iload_1
      31: invokestatic  #127                // Method scala/runtime/BoxesRunTime.boxToInteger:(I)Ljava/lang/Integer;
      34: invokevirtual #131                // Method java/lang/Integer.toString:()Ljava/lang/String;
      37: invokespecial #134                // Method java/lang/IndexOutOfBoundsException."<init>":(Ljava/lang/String;)V
      40: athrow
      41: areturn

  public java.lang.String productElementName(int);
    Code:
       0: iload_1
       1: istore_2
       2: iconst_0
       3: iload_2
       4: if_icmpne     12
       7: ldc           #138                // String proc
       9: goto          37
      12: iconst_1
      13: iload_2
      14: if_icmpne     22
      17: ldc           #139                // String attr
      19: goto          37
      22: new           #121                // class java/lang/IndexOutOfBoundsException
      25: dup
      26: iload_1
      27: invokestatic  #127                // Method scala/runtime/BoxesRunTime.boxToInteger:(I)Ljava/lang/Integer;
      30: invokevirtual #131                // Method java/lang/Integer.toString:()Ljava/lang/String;
      33: invokespecial #134                // Method java/lang/IndexOutOfBoundsException."<init>":(Ljava/lang/String;)V
      36: athrow
      37: areturn

  public de.sciss.proc.AuralObj$Proc<T> proc();
    Code:
       0: aload_0
       1: getfield      #52                 // Field proc:Lde/sciss/proc/AuralObj$Proc;
       4: areturn

  public de.sciss.proc.AuralAttribute<T> attr();
    Code:
       0: aload_0
       1: getfield      #54                 // Field attr:Lde/sciss/proc/AuralAttribute;
       4: areturn

  public <T extends de.sciss.lucre.Txn<T>> de.sciss.proc.AuralObj$Proc$AttrRemoved<T> copy(de.sciss.proc.AuralObj$Proc<T>, de.sciss.proc.AuralAttribute<T>);
    Code:
       0: new           #2                  // class de/sciss/proc/AuralObj$Proc$AttrRemoved
       3: dup
       4: aload_1
       5: aload_2
       6: invokespecial #146                // Method "<init>":(Lde/sciss/proc/AuralObj$Proc;Lde/sciss/proc/AuralAttribute;)V
       9: areturn

  public <T extends de.sciss.lucre.Txn<T>> de.sciss.proc.AuralObj$Proc<T> copy$default$1();
    Code:
       0: aload_0
       1: invokevirtual #92                 // Method proc:()Lde/sciss/proc/AuralObj$Proc;
       4: areturn

  public <T extends de.sciss.lucre.Txn<T>> de.sciss.proc.AuralAttribute<T> copy$default$2();
    Code:
       0: aload_0
       1: invokevirtual #97                 // Method attr:()Lde/sciss/proc/AuralAttribute;
       4: areturn

  public de.sciss.proc.AuralObj$Proc<T> _1();
    Code:
       0: aload_0
       1: invokevirtual #92                 // Method proc:()Lde/sciss/proc/AuralObj$Proc;
       4: areturn

  public de.sciss.proc.AuralAttribute<T> _2();
    Code:
       0: aload_0
       1: invokevirtual #97                 // Method attr:()Lde/sciss/proc/AuralAttribute;
       4: areturn
}
