Compiled from "Color.scala"
public final class de.sciss.proc.Color$ implements scala.deriving.Mirror$Sum,java.io.Serializable {
  public static final de.sciss.proc.Color$format$ format;

  public static final de.sciss.proc.Color$Obj$ Obj;

  private static final de.sciss.proc.Color Black;

  private static final de.sciss.proc.Color White;

  private static final scala.collection.immutable.IndexedSeq Palette;

  public static final de.sciss.proc.Color$Predefined$ Predefined;

  public static final de.sciss.proc.Color$User$ User;

  public static final de.sciss.proc.Color$ExOps$ ExOps;

  public static final de.sciss.proc.Color$ExValue$ ExValue;

  public static final de.sciss.proc.Color$ MODULE$;

  private de.sciss.proc.Color$();
    Code:
       0: aload_0
       1: invokespecial #63                 // Method java/lang/Object."<init>":()V
       4: return

  public static {};
    Code:
       0: new           #2                  // class de/sciss/proc/Color$
       3: dup
       4: invokespecial #66                 // Method "<init>":()V
       7: putstatic     #68                 // Field MODULE$:Lde/sciss/proc/Color$;
      10: sipush        17263
      13: istore_0
      14: getstatic     #70                 // Field de/sciss/proc/Color$Predefined$.MODULE$:Lde/sciss/proc/Color$Predefined$;
      17: bipush        13
      19: ldc           #71                 // String Black
      21: ldc           #72                 // int -16777216
      23: invokevirtual #76                 // Method de/sciss/proc/Color$Predefined$.apply:(ILjava/lang/String;I)Lde/sciss/proc/Color$Predefined;
      26: putstatic     #78                 // Field Black:Lde/sciss/proc/Color;
      29: getstatic     #70                 // Field de/sciss/proc/Color$Predefined$.MODULE$:Lde/sciss/proc/Color$Predefined$;
      32: bipush        15
      34: ldc           #79                 // String White
      36: iconst_m1
      37: invokevirtual #76                 // Method de/sciss/proc/Color$Predefined$.apply:(ILjava/lang/String;I)Lde/sciss/proc/Color$Predefined;
      40: putstatic     #81                 // Field White:Lde/sciss/proc/Color;
      43: getstatic     #86                 // Field scala/package$.MODULE$:Lscala/package$;
      46: invokevirtual #90                 // Method scala/package$.Vector:()Lscala/collection/immutable/Vector$;
      49: getstatic     #95                 // Field scala/runtime/ScalaRunTime$.MODULE$:Lscala/runtime/ScalaRunTime$;
      52: bipush        16
      54: anewarray     #13                 // class de/sciss/proc/Color
      57: dup
      58: iconst_0
      59: getstatic     #70                 // Field de/sciss/proc/Color$Predefined$.MODULE$:Lde/sciss/proc/Color$Predefined$;
      62: iconst_0
      63: ldc           #97                 // String Dark Blue
      65: ldc           #98                 // int -16768164
      67: invokevirtual #76                 // Method de/sciss/proc/Color$Predefined$.apply:(ILjava/lang/String;I)Lde/sciss/proc/Color$Predefined;
      70: aastore
      71: dup
      72: iconst_1
      73: getstatic     #70                 // Field de/sciss/proc/Color$Predefined$.MODULE$:Lde/sciss/proc/Color$Predefined$;
      76: iconst_1
      77: ldc           #100                // String Light Blue
      79: ldc           #101                // int -16744710
      81: invokevirtual #76                 // Method de/sciss/proc/Color$Predefined$.apply:(ILjava/lang/String;I)Lde/sciss/proc/Color$Predefined;
      84: aastore
      85: dup
      86: iconst_2
      87: getstatic     #70                 // Field de/sciss/proc/Color$Predefined$.MODULE$:Lde/sciss/proc/Color$Predefined$;
      90: iconst_2
      91: ldc           #103                // String Cyan
      93: ldc           #104                // int -10292491
      95: invokevirtual #76                 // Method de/sciss/proc/Color$Predefined$.apply:(ILjava/lang/String;I)Lde/sciss/proc/Color$Predefined;
      98: aastore
      99: dup
     100: iconst_3
     101: getstatic     #70                 // Field de/sciss/proc/Color$Predefined$.MODULE$:Lde/sciss/proc/Color$Predefined$;
     104: iconst_3
     105: ldc           #106                // String Mint
     107: ldc           #107                // int -13325199
     109: invokevirtual #76                 // Method de/sciss/proc/Color$Predefined$.apply:(ILjava/lang/String;I)Lde/sciss/proc/Color$Predefined;
     112: aastore
     113: dup
     114: iconst_4
     115: getstatic     #70                 // Field de/sciss/proc/Color$Predefined$.MODULE$:Lde/sciss/proc/Color$Predefined$;
     118: iconst_4
     119: ldc           #109                // String Green
     121: ldc           #110                // int -12785093
     123: invokevirtual #76                 // Method de/sciss/proc/Color$Predefined$.apply:(ILjava/lang/String;I)Lde/sciss/proc/Color$Predefined;
     126: aastore
     127: dup
     128: iconst_5
     129: getstatic     #70                 // Field de/sciss/proc/Color$Predefined$.MODULE$:Lde/sciss/proc/Color$Predefined$;
     132: iconst_5
     133: ldc           #112                // String Yellow
     135: ldc           #113                // int -1114368
     137: invokevirtual #76                 // Method de/sciss/proc/Color$Predefined$.apply:(ILjava/lang/String;I)Lde/sciss/proc/Color$Predefined;
     140: aastore
     141: dup
     142: bipush        6
     144: getstatic     #70                 // Field de/sciss/proc/Color$Predefined$.MODULE$:Lde/sciss/proc/Color$Predefined$;
     147: bipush        6
     149: ldc           #115                // String Dark Beige
     151: ldc           #116                // int -8559285
     153: invokevirtual #76                 // Method de/sciss/proc/Color$Predefined$.apply:(ILjava/lang/String;I)Lde/sciss/proc/Color$Predefined;
     156: aastore
     157: dup
     158: bipush        7
     160: getstatic     #70                 // Field de/sciss/proc/Color$Predefined$.MODULE$:Lde/sciss/proc/Color$Predefined$;
     163: bipush        7
     165: ldc           #118                // String Light Beige
     167: ldc           #119                // int -5596302
     169: invokevirtual #76                 // Method de/sciss/proc/Color$Predefined$.apply:(ILjava/lang/String;I)Lde/sciss/proc/Color$Predefined;
     172: aastore
     173: dup
     174: bipush        8
     176: getstatic     #70                 // Field de/sciss/proc/Color$Predefined$.MODULE$:Lde/sciss/proc/Color$Predefined$;
     179: bipush        8
     181: ldc           #121                // String Orange
     183: sipush        -27891
     186: invokevirtual #76                 // Method de/sciss/proc/Color$Predefined$.apply:(ILjava/lang/String;I)Lde/sciss/proc/Color$Predefined;
     189: aastore
     190: dup
     191: bipush        9
     193: getstatic     #70                 // Field de/sciss/proc/Color$Predefined$.MODULE$:Lde/sciss/proc/Color$Predefined$;
     196: bipush        9
     198: ldc           #123                // String Red
     200: ldc           #124                // int -49106
     202: invokevirtual #76                 // Method de/sciss/proc/Color$Predefined$.apply:(ILjava/lang/String;I)Lde/sciss/proc/Color$Predefined;
     205: aastore
     206: dup
     207: bipush        10
     209: getstatic     #70                 // Field de/sciss/proc/Color$Predefined$.MODULE$:Lde/sciss/proc/Color$Predefined$;
     212: bipush        10
     214: ldc           #126                // String Maroon
     216: ldc           #127                // int -7534263
     218: invokevirtual #76                 // Method de/sciss/proc/Color$Predefined$.apply:(ILjava/lang/String;I)Lde/sciss/proc/Color$Predefined;
     221: aastore
     222: dup
     223: bipush        11
     225: getstatic     #70                 // Field de/sciss/proc/Color$Predefined$.MODULE$:Lde/sciss/proc/Color$Predefined$;
     228: bipush        11
     230: ldc           #129                // String Fuchsia
     232: ldc           #130                // int -63784
     234: invokevirtual #76                 // Method de/sciss/proc/Color$Predefined$.apply:(ILjava/lang/String;I)Lde/sciss/proc/Color$Predefined;
     237: aastore
     238: dup
     239: bipush        12
     241: getstatic     #70                 // Field de/sciss/proc/Color$Predefined$.MODULE$:Lde/sciss/proc/Color$Predefined$;
     244: bipush        12
     246: ldc           #132                // String Purple
     248: ldc           #133                // int -4456218
     250: invokevirtual #76                 // Method de/sciss/proc/Color$Predefined$.apply:(ILjava/lang/String;I)Lde/sciss/proc/Color$Predefined;
     253: aastore
     254: dup
     255: bipush        13
     257: getstatic     #68                 // Field MODULE$:Lde/sciss/proc/Color$;
     260: invokevirtual #136                // Method Black:()Lde/sciss/proc/Color;
     263: aastore
     264: dup
     265: bipush        14
     267: getstatic     #70                 // Field de/sciss/proc/Color$Predefined$.MODULE$:Lde/sciss/proc/Color$Predefined$;
     270: bipush        14
     272: ldc           #138                // String Silver
     274: ldc           #139                // int -5653568
     276: invokevirtual #76                 // Method de/sciss/proc/Color$Predefined$.apply:(ILjava/lang/String;I)Lde/sciss/proc/Color$Predefined;
     279: aastore
     280: dup
     281: bipush        15
     283: getstatic     #68                 // Field MODULE$:Lde/sciss/proc/Color$;
     286: invokevirtual #141                // Method White:()Lde/sciss/proc/Color;
     289: aastore
     290: invokevirtual #145                // Method scala/runtime/ScalaRunTime$.wrapRefArray:([Ljava/lang/Object;)Lscala/collection/immutable/ArraySeq;
     293: invokevirtual #150                // Method scala/collection/immutable/Vector$.apply:(Lscala/collection/immutable/Seq;)Ljava/lang/Object;
     296: checkcast     #152                // class scala/collection/immutable/IndexedSeq
     299: putstatic     #154                // Field Palette:Lscala/collection/immutable/IndexedSeq;
     302: return

  private java.lang.Object writeReplace();
    Code:
       0: new           #160                // class scala/runtime/ModuleSerializationProxy
       3: dup
       4: ldc           #2                  // class de/sciss/proc/Color$
       6: invokespecial #163                // Method scala/runtime/ModuleSerializationProxy."<init>":(Ljava/lang/Class;)V
       9: areturn

  public final int typeId();
    Code:
       0: bipush        22
       2: ireturn

  public void init();
    Code:
       0: getstatic     #168                // Field de/sciss/proc/Color$Obj$.MODULE$:Lde/sciss/proc/Color$Obj$;
       3: invokevirtual #170                // Method de/sciss/proc/Color$Obj$.init:()V
       6: return

  public de.sciss.proc.Color Black();
    Code:
       0: getstatic     #78                 // Field Black:Lde/sciss/proc/Color;
       3: areturn

  public de.sciss.proc.Color White();
    Code:
       0: getstatic     #81                 // Field White:Lde/sciss/proc/Color;
       3: areturn

  public scala.collection.immutable.IndexedSeq<de.sciss.proc.Color> Palette();
    Code:
       0: getstatic     #154                // Field Palette:Lscala/collection/immutable/IndexedSeq;
       3: areturn

  public final de.sciss.lucre.expr.graph.Ex ExOps(de.sciss.lucre.expr.graph.Ex<de.sciss.proc.Color>);
    Code:
       0: aload_1
       1: areturn

  public int ordinal(de.sciss.proc.Color);
    Code:
       0: aload_1
       1: astore_2
       2: aload_2
       3: instanceof    #28                 // class de/sciss/proc/Color$Predefined
       6: ifeq          13
       9: iconst_0
      10: goto          33
      13: aload_2
      14: instanceof    #34                 // class de/sciss/proc/Color$User
      17: ifeq          24
      20: iconst_1
      21: goto          33
      24: new           #181                // class scala/MatchError
      27: dup
      28: aload_2
      29: invokespecial #184                // Method scala/MatchError."<init>":(Ljava/lang/Object;)V
      32: athrow
      33: ireturn

  public int ordinal(java.lang.Object);
    Code:
       0: aload_0
       1: aload_1
       2: checkcast     #13                 // class de/sciss/proc/Color
       5: invokevirtual #187                // Method ordinal:(Lde/sciss/proc/Color;)I
       8: ireturn
}
