Compiled from "Implicits.scala"
public final class de.sciss.proc.Implicits$ObjAttrMapOps<T extends de.sciss.lucre.Txn<T>> {
  private final de.sciss.lucre.MapObj$Modifiable this;

  public static <R extends de.sciss.lucre.Obj<de.sciss.lucre.Txn>, T extends de.sciss.lucre.Txn<T>> de.sciss.lucre.Obj<T> $bang$extension(de.sciss.lucre.MapObj$Modifiable, java.lang.String, T, scala.reflect.ClassTag<de.sciss.lucre.Obj<T>>);
    Code:
       0: getstatic     #26                 // Field de/sciss/proc/Implicits$ObjAttrMapOps$.MODULE$:Lde/sciss/proc/Implicits$ObjAttrMapOps$;
       3: aload_0
       4: aload_1
       5: aload_2
       6: aload_3
       7: invokevirtual #28                 // Method de/sciss/proc/Implicits$ObjAttrMapOps$.$bang$extension:(Lde/sciss/lucre/MapObj$Modifiable;Ljava/lang/String;Lde/sciss/lucre/Txn;Lscala/reflect/ClassTag;)Lde/sciss/lucre/Obj;
      10: areturn

  public static <T extends de.sciss.lucre.Txn<T>> boolean equals$extension(de.sciss.lucre.MapObj$Modifiable, java.lang.Object);
    Code:
       0: getstatic     #26                 // Field de/sciss/proc/Implicits$ObjAttrMapOps$.MODULE$:Lde/sciss/proc/Implicits$ObjAttrMapOps$;
       3: aload_0
       4: aload_1
       5: invokevirtual #33                 // Method de/sciss/proc/Implicits$ObjAttrMapOps$.equals$extension:(Lde/sciss/lucre/MapObj$Modifiable;Ljava/lang/Object;)Z
       8: ireturn

  public static <T extends de.sciss.lucre.Txn<T>> int hashCode$extension(de.sciss.lucre.MapObj$Modifiable);
    Code:
       0: getstatic     #26                 // Field de/sciss/proc/Implicits$ObjAttrMapOps$.MODULE$:Lde/sciss/proc/Implicits$ObjAttrMapOps$;
       3: aload_0
       4: invokevirtual #38                 // Method de/sciss/proc/Implicits$ObjAttrMapOps$.hashCode$extension:(Lde/sciss/lucre/MapObj$Modifiable;)I
       7: ireturn

  public de.sciss.proc.Implicits$ObjAttrMapOps(de.sciss.lucre.MapObj$Modifiable<T, java.lang.String, de.sciss.lucre.Obj>);
    Code:
       0: aload_0
       1: aload_1
       2: putfield      #43                 // Field this:Lde/sciss/lucre/MapObj$Modifiable;
       5: aload_0
       6: invokespecial #46                 // Method java/lang/Object."<init>":()V
       9: return

  public int hashCode();
    Code:
       0: getstatic     #26                 // Field de/sciss/proc/Implicits$ObjAttrMapOps$.MODULE$:Lde/sciss/proc/Implicits$ObjAttrMapOps$;
       3: aload_0
       4: invokevirtual #52                 // Method this:()Lde/sciss/lucre/MapObj$Modifiable;
       7: invokevirtual #38                 // Method de/sciss/proc/Implicits$ObjAttrMapOps$.hashCode$extension:(Lde/sciss/lucre/MapObj$Modifiable;)I
      10: ireturn

  public boolean equals(java.lang.Object);
    Code:
       0: getstatic     #26                 // Field de/sciss/proc/Implicits$ObjAttrMapOps$.MODULE$:Lde/sciss/proc/Implicits$ObjAttrMapOps$;
       3: aload_0
       4: invokevirtual #52                 // Method this:()Lde/sciss/lucre/MapObj$Modifiable;
       7: aload_1
       8: invokevirtual #33                 // Method de/sciss/proc/Implicits$ObjAttrMapOps$.equals$extension:(Lde/sciss/lucre/MapObj$Modifiable;Ljava/lang/Object;)Z
      11: ireturn

  public de.sciss.lucre.MapObj$Modifiable<T, java.lang.String, de.sciss.lucre.Obj> this();
    Code:
       0: aload_0
       1: getfield      #43                 // Field this:Lde/sciss/lucre/MapObj$Modifiable;
       4: areturn

  public <R extends de.sciss.lucre.Obj<de.sciss.lucre.Txn>> de.sciss.lucre.Obj<T> $bang(java.lang.String, T, scala.reflect.ClassTag<de.sciss.lucre.Obj<T>>);
    Code:
       0: getstatic     #26                 // Field de/sciss/proc/Implicits$ObjAttrMapOps$.MODULE$:Lde/sciss/proc/Implicits$ObjAttrMapOps$;
       3: aload_0
       4: invokevirtual #52                 // Method this:()Lde/sciss/lucre/MapObj$Modifiable;
       7: aload_1
       8: aload_2
       9: aload_3
      10: invokevirtual #28                 // Method de/sciss/proc/Implicits$ObjAttrMapOps$.$bang$extension:(Lde/sciss/lucre/MapObj$Modifiable;Ljava/lang/String;Lde/sciss/lucre/Txn;Lscala/reflect/ClassTag;)Lde/sciss/lucre/Obj;
      13: areturn
}
