Compiled from "Runner.scala"
public final class de.sciss.proc.Runner$RunnerOps<T extends de.sciss.lucre.Txn<T>> {
  private final de.sciss.proc.Runner r;

  public static <T extends de.sciss.lucre.Txn<T>> boolean equals$extension(de.sciss.proc.Runner, java.lang.Object);
    Code:
       0: getstatic     #21                 // Field de/sciss/proc/Runner$RunnerOps$.MODULE$:Lde/sciss/proc/Runner$RunnerOps$;
       3: aload_0
       4: aload_1
       5: invokevirtual #23                 // Method de/sciss/proc/Runner$RunnerOps$.equals$extension:(Lde/sciss/proc/Runner;Ljava/lang/Object;)Z
       8: ireturn

  public static <T extends de.sciss.lucre.Txn<T>> int hashCode$extension(de.sciss.proc.Runner);
    Code:
       0: getstatic     #21                 // Field de/sciss/proc/Runner$RunnerOps$.MODULE$:Lde/sciss/proc/Runner$RunnerOps$;
       3: aload_0
       4: invokevirtual #28                 // Method de/sciss/proc/Runner$RunnerOps$.hashCode$extension:(Lde/sciss/proc/Runner;)I
       7: ireturn

  public static <T extends de.sciss.lucre.Txn<T>> void runAndDispose$extension(de.sciss.proc.Runner, T);
    Code:
       0: getstatic     #21                 // Field de/sciss/proc/Runner$RunnerOps$.MODULE$:Lde/sciss/proc/Runner$RunnerOps$;
       3: aload_0
       4: aload_1
       5: invokevirtual #33                 // Method de/sciss/proc/Runner$RunnerOps$.runAndDispose$extension:(Lde/sciss/proc/Runner;Lde/sciss/lucre/Txn;)V
       8: return

  public de.sciss.proc.Runner$RunnerOps(de.sciss.proc.Runner<T>);
    Code:
       0: aload_0
       1: aload_1
       2: putfield      #38                 // Field r:Lde/sciss/proc/Runner;
       5: aload_0
       6: invokespecial #41                 // Method java/lang/Object."<init>":()V
       9: return

  public int hashCode();
    Code:
       0: getstatic     #21                 // Field de/sciss/proc/Runner$RunnerOps$.MODULE$:Lde/sciss/proc/Runner$RunnerOps$;
       3: aload_0
       4: invokevirtual #49                 // Method de$sciss$proc$Runner$RunnerOps$$r:()Lde/sciss/proc/Runner;
       7: invokevirtual #28                 // Method de/sciss/proc/Runner$RunnerOps$.hashCode$extension:(Lde/sciss/proc/Runner;)I
      10: ireturn

  public boolean equals(java.lang.Object);
    Code:
       0: getstatic     #21                 // Field de/sciss/proc/Runner$RunnerOps$.MODULE$:Lde/sciss/proc/Runner$RunnerOps$;
       3: aload_0
       4: invokevirtual #49                 // Method de$sciss$proc$Runner$RunnerOps$$r:()Lde/sciss/proc/Runner;
       7: aload_1
       8: invokevirtual #23                 // Method de/sciss/proc/Runner$RunnerOps$.equals$extension:(Lde/sciss/proc/Runner;Ljava/lang/Object;)Z
      11: ireturn

  public de.sciss.proc.Runner<T> de$sciss$proc$Runner$RunnerOps$$r();
    Code:
       0: aload_0
       1: getfield      #38                 // Field r:Lde/sciss/proc/Runner;
       4: areturn

  public void runAndDispose(T);
    Code:
       0: getstatic     #21                 // Field de/sciss/proc/Runner$RunnerOps$.MODULE$:Lde/sciss/proc/Runner$RunnerOps$;
       3: aload_0
       4: invokevirtual #49                 // Method de$sciss$proc$Runner$RunnerOps$$r:()Lde/sciss/proc/Runner;
       7: aload_1
       8: invokevirtual #33                 // Method de/sciss/proc/Runner$RunnerOps$.runAndDispose$extension:(Lde/sciss/proc/Runner;Lde/sciss/lucre/Txn;)V
      11: return
}
