Compiled from "Runner.scala"
public final class de.sciss.proc.Runner$ implements java.io.Serializable {
  public long 0bitmap$2;

  public static final de.sciss.proc.Runner$Stopped$ Stopped;

  public static final de.sciss.proc.Runner$Preparing$ Preparing;

  public static final de.sciss.proc.Runner$Prepared$ Prepared;

  public static final de.sciss.proc.Runner$Running$ Running;

  public static final de.sciss.proc.Runner$Done$ Done;

  public static final de.sciss.proc.Runner$Failed$ Failed;

  public static final de.sciss.proc.Runner$Mutable$ Mutable;

  public static final de.sciss.proc.Runner$Control$ Control;

  public static final de.sciss.proc.Runner$Action$ Action;

  public static final de.sciss.proc.Runner$Proc$ Proc;

  public static final de.sciss.proc.Runner$Folder$ Folder;

  public static final de.sciss.proc.Runner$Timeline$ Timeline;

  private static java.text.SimpleDateFormat fmtMessageDate$lzy1;

  public static final de.sciss.proc.Runner$Message$ Message;

  public static final de.sciss.proc.Runner$RunnerOps$ RunnerOps;

  public static final de.sciss.proc.Runner$ MODULE$;

  private de.sciss.proc.Runner$();
    Code:
       0: aload_0
       1: invokespecial #117                // Method java/lang/Object."<init>":()V
       4: return

  public static {};
    Code:
       0: new           #2                  // class de/sciss/proc/Runner$
       3: dup
       4: invokespecial #120                // Method "<init>":()V
       7: putstatic     #122                // Field MODULE$:Lde/sciss/proc/Runner$;
      10: return

  private java.lang.Object writeReplace();
    Code:
       0: new           #126                // class scala/runtime/ModuleSerializationProxy
       3: dup
       4: ldc           #2                  // class de/sciss/proc/Runner$
       6: invokespecial #129                // Method scala/runtime/ModuleSerializationProxy."<init>":(Ljava/lang/Class;)V
       9: areturn

  public <T extends de.sciss.lucre.Txn<T>> de.sciss.lucre.MapObjLike<T, java.lang.String, de.sciss.lucre.Form<T>> emptyAttr();
    Code:
       0: getstatic     #137                // Field de/sciss/lucre/expr/Context$.MODULE$:Lde/sciss/lucre/expr/Context$;
       3: invokevirtual #139                // Method de/sciss/lucre/expr/Context$.emptyAttr:()Lde/sciss/lucre/MapObjLike;
       6: areturn

  public void addFactory(de.sciss.proc.Runner$Factory);
    Code:
       0: getstatic     #147                // Field de/sciss/proc/impl/RunnerUniverseImpl$.MODULE$:Lde/sciss/proc/impl/RunnerUniverseImpl$;
       3: aload_1
       4: invokevirtual #149                // Method de/sciss/proc/impl/RunnerUniverseImpl$.addFactory:(Lde/sciss/proc/Runner$Factory;)V
       7: return

  public scala.Option<de.sciss.proc.Runner$Factory> getFactory(de.sciss.lucre.Obj$Type);
    Code:
       0: getstatic     #147                // Field de/sciss/proc/impl/RunnerUniverseImpl$.MODULE$:Lde/sciss/proc/impl/RunnerUniverseImpl$;
       3: aload_1
       4: invokevirtual #156                // Method de/sciss/proc/impl/RunnerUniverseImpl$.getFactory:(Lde/sciss/lucre/Obj$Type;)Lscala/Option;
       7: areturn

  public scala.collection.Iterable<de.sciss.proc.Runner$Factory> factories();
    Code:
       0: getstatic     #147                // Field de/sciss/proc/impl/RunnerUniverseImpl$.MODULE$:Lde/sciss/proc/impl/RunnerUniverseImpl$;
       3: invokevirtual #162                // Method de/sciss/proc/impl/RunnerUniverseImpl$.factories:()Lscala/collection/Iterable;
       6: areturn

  public <T extends de.sciss.lucre.Txn<T>> scala.Option<de.sciss.proc.Runner<T>> get(de.sciss.lucre.Obj<T>, T, de.sciss.proc.Universe<T>);
    Code:
       0: aload_3
       1: aload_1
       2: aload_2
       3: invokeinterface #174,  3          // InterfaceMethod de/sciss/proc/Universe.mkRunner:(Lde/sciss/lucre/Obj;Lde/sciss/lucre/Txn;)Lscala/Option;
       8: areturn

  public <T extends de.sciss.lucre.Txn<T>> de.sciss.proc.Runner<T> apply(de.sciss.lucre.Obj<T>, T, de.sciss.proc.Universe<T>);
    Code:
       0: aload_0
       1: aload_1
       2: aload_2
       3: aload_3
       4: invokevirtual #182                // Method get:(Lde/sciss/lucre/Obj;Lde/sciss/lucre/Txn;Lde/sciss/proc/Universe;)Lscala/Option;
       7: aload_0
       8: aload_1
       9: invokedynamic #202,  0            // InvokeDynamic #0:apply:(Lde/sciss/proc/Runner$;Lde/sciss/lucre/Obj;)Lscala/Function0;
      14: invokevirtual #208                // Method scala/Option.getOrElse:(Lscala/Function0;)Ljava/lang/Object;
      17: checkcast     #16                 // class de/sciss/proc/Runner
      20: areturn

  public java.text.SimpleDateFormat de$sciss$proc$Runner$$$fmtMessageDate();
    Code:
       0: getstatic     #217                // Field scala/runtime/LazyVals$.MODULE$:Lscala/runtime/LazyVals$;
       3: aload_0
       4: getstatic     #220                // Field de/sciss/proc/Runner.OFFSET$_m_0:J
       7: invokevirtual #223                // Method scala/runtime/LazyVals$.get:(Ljava/lang/Object;J)J
      10: lstore_1
      11: getstatic     #217                // Field scala/runtime/LazyVals$.MODULE$:Lscala/runtime/LazyVals$;
      14: lload_1
      15: iconst_0
      16: invokevirtual #227                // Method scala/runtime/LazyVals$.STATE:(JI)J
      19: lstore_3
      20: lload_3
      21: ldc2_w        #228                // long 3l
      24: lcmp
      25: ifne          35
      28: getstatic     #231                // Field fmtMessageDate$lzy1:Ljava/text/SimpleDateFormat;
      31: areturn
      32: nop
      33: nop
      34: athrow
      35: lload_3
      36: lconst_0
      37: lcmp
      38: ifne          118
      41: getstatic     #217                // Field scala/runtime/LazyVals$.MODULE$:Lscala/runtime/LazyVals$;
      44: aload_0
      45: getstatic     #220                // Field de/sciss/proc/Runner.OFFSET$_m_0:J
      48: lload_1
      49: iconst_1
      50: iconst_0
      51: invokevirtual #235                // Method scala/runtime/LazyVals$.CAS:(Ljava/lang/Object;JJII)Z
      54: ifeq          115
      57: new           #237                // class java/text/SimpleDateFormat
      60: dup
      61: ldc           #239                // String [HH:mm\'\'ss.SSS]
      63: getstatic     #245                // Field java/util/Locale.US:Ljava/util/Locale;
      66: invokespecial #248                // Method java/text/SimpleDateFormat."<init>":(Ljava/lang/String;Ljava/util/Locale;)V
      69: astore        5
      71: aload         5
      73: putstatic     #231                // Field fmtMessageDate$lzy1:Ljava/text/SimpleDateFormat;
      76: getstatic     #217                // Field scala/runtime/LazyVals$.MODULE$:Lscala/runtime/LazyVals$;
      79: aload_0
      80: getstatic     #220                // Field de/sciss/proc/Runner.OFFSET$_m_0:J
      83: iconst_3
      84: iconst_0
      85: invokevirtual #252                // Method scala/runtime/LazyVals$.setFlag:(Ljava/lang/Object;JII)V
      88: aload         5
      90: areturn
      91: nop
      92: nop
      93: athrow
      94: astore        6
      96: getstatic     #217                // Field scala/runtime/LazyVals$.MODULE$:Lscala/runtime/LazyVals$;
      99: aload_0
     100: getstatic     #220                // Field de/sciss/proc/Runner.OFFSET$_m_0:J
     103: iconst_0
     104: iconst_0
     105: invokevirtual #252                // Method scala/runtime/LazyVals$.setFlag:(Ljava/lang/Object;JII)V
     108: aload         6
     110: athrow
     111: nop
     112: nop
     113: athrow
     114: athrow
     115: goto          130
     118: getstatic     #217                // Field scala/runtime/LazyVals$.MODULE$:Lscala/runtime/LazyVals$;
     121: aload_0
     122: getstatic     #220                // Field de/sciss/proc/Runner.OFFSET$_m_0:J
     125: lload_1
     126: iconst_0
     127: invokevirtual #256                // Method scala/runtime/LazyVals$.wait4Notification:(Ljava/lang/Object;JJI)V
     130: goto          0
     133: nop
     134: athrow
    Exception table:
       from    to  target type
          57    91    94   Class java/lang/Throwable

  public final <T extends de.sciss.lucre.Txn<T>> de.sciss.proc.Runner RunnerOps(de.sciss.proc.Runner<T>);
    Code:
       0: aload_1
       1: areturn

  private final de.sciss.proc.Runner apply$$anonfun$1(de.sciss.lucre.Obj);
    Code:
       0: new           #263                // class java/lang/IllegalArgumentException
       3: dup
       4: new           #265                // class java/lang/StringBuilder
       7: dup
       8: ldc_w         #266                // int 22
      11: invokespecial #269                // Method java/lang/StringBuilder."<init>":(I)V
      14: ldc_w         #271                // String No runner factory for
      17: invokevirtual #275                // Method java/lang/StringBuilder.append:(Ljava/lang/String;)Ljava/lang/StringBuilder;
      20: aload_1
      21: invokeinterface #278,  1          // InterfaceMethod de/sciss/lucre/Obj.tpe:()Lde/sciss/lucre/Obj$Type;
      26: invokevirtual #281                // Method java/lang/StringBuilder.append:(Ljava/lang/Object;)Ljava/lang/StringBuilder;
      29: invokevirtual #285                // Method java/lang/StringBuilder.toString:()Ljava/lang/String;
      32: invokespecial #288                // Method java/lang/IllegalArgumentException."<init>":(Ljava/lang/String;)V
      35: athrow

  private static java.lang.Object $deserializeLambda$(java.lang.invoke.SerializedLambda);
    Code:
       0: aload_0
       1: invokedynamic #300,  0            // InvokeDynamic #1:lambdaDeserialize:(Ljava/lang/invoke/SerializedLambda;)Ljava/lang/Object;
       6: areturn
}
