Compiled from "UGenGraphBuilder.scala"
public final class de.sciss.proc.UGenGraphBuilder$Input$BufferGen$ implements scala.deriving.Mirror$Product,java.io.Serializable {
  public static final de.sciss.proc.UGenGraphBuilder$Input$BufferGen$Value$ Value;

  public static final de.sciss.proc.UGenGraphBuilder$Input$BufferGen$ MODULE$;

  public de.sciss.proc.UGenGraphBuilder$Input$BufferGen$();
    Code:
       0: aload_0
       1: invokespecial #39                 // Method java/lang/Object."<init>":()V
       4: return

  public static {};
    Code:
       0: new           #2                  // class de/sciss/proc/UGenGraphBuilder$Input$BufferGen$
       3: dup
       4: invokespecial #42                 // Method "<init>":()V
       7: putstatic     #44                 // Field MODULE$:Lde/sciss/proc/UGenGraphBuilder$Input$BufferGen$;
      10: return

  private java.lang.Object writeReplace();
    Code:
       0: new           #48                 // class scala/runtime/ModuleSerializationProxy
       3: dup
       4: ldc           #2                  // class de/sciss/proc/UGenGraphBuilder$Input$BufferGen$
       6: invokespecial #51                 // Method scala/runtime/ModuleSerializationProxy."<init>":(Ljava/lang/Class;)V
       9: areturn

  public de.sciss.proc.UGenGraphBuilder$Input$BufferGen apply(de.sciss.synth.message.BufferGen$Command, int, int);
    Code:
       0: new           #16                 // class de/sciss/proc/UGenGraphBuilder$Input$BufferGen
       3: dup
       4: aload_1
       5: iload_2
       6: iload_3
       7: invokespecial #59                 // Method de/sciss/proc/UGenGraphBuilder$Input$BufferGen."<init>":(Lde/sciss/synth/message/BufferGen$Command;II)V
      10: areturn

  public de.sciss.proc.UGenGraphBuilder$Input$BufferGen unapply(de.sciss.proc.UGenGraphBuilder$Input$BufferGen);
    Code:
       0: aload_1
       1: areturn

  public java.lang.String toString();
    Code:
       0: ldc           #68                 // String BufferGen
       2: areturn

  public de.sciss.proc.UGenGraphBuilder$Input$BufferGen fromProduct(scala.Product);
    Code:
       0: new           #16                 // class de/sciss/proc/UGenGraphBuilder$Input$BufferGen
       3: dup
       4: aload_1
       5: iconst_0
       6: invokeinterface #77,  2           // InterfaceMethod scala/Product.productElement:(I)Ljava/lang/Object;
      11: checkcast     #26                 // class de/sciss/synth/message/BufferGen$Command
      14: aload_1
      15: iconst_1
      16: invokeinterface #77,  2           // InterfaceMethod scala/Product.productElement:(I)Ljava/lang/Object;
      21: invokestatic  #83                 // Method scala/runtime/BoxesRunTime.unboxToInt:(Ljava/lang/Object;)I
      24: aload_1
      25: iconst_2
      26: invokeinterface #77,  2           // InterfaceMethod scala/Product.productElement:(I)Ljava/lang/Object;
      31: invokestatic  #83                 // Method scala/runtime/BoxesRunTime.unboxToInt:(Ljava/lang/Object;)I
      34: invokespecial #59                 // Method de/sciss/proc/UGenGraphBuilder$Input$BufferGen."<init>":(Lde/sciss/synth/message/BufferGen$Command;II)V
      37: areturn

  public java.lang.Object fromProduct(scala.Product);
    Code:
       0: aload_0
       1: aload_1
       2: invokevirtual #88                 // Method fromProduct:(Lscala/Product;)Lde/sciss/proc/UGenGraphBuilder$Input$BufferGen;
       5: areturn
}
