Compiled from "UGenGraphBuilder.scala"
public final class de.sciss.proc.UGenGraphBuilder$Input$Buffer$Value implements de.sciss.proc.UGenGraphBuilder$Value,scala.Product,java.io.Serializable {
  private final long numFrames;

  private final int numChannels;

  private final boolean async;

  public static de.sciss.proc.UGenGraphBuilder$Input$Buffer$Value apply(long, int, boolean);
    Code:
       0: getstatic     #35                 // Field de/sciss/proc/UGenGraphBuilder$Input$Buffer$Value$.MODULE$:Lde/sciss/proc/UGenGraphBuilder$Input$Buffer$Value$;
       3: lload_0
       4: iload_2
       5: iload_3
       6: invokevirtual #37                 // Method de/sciss/proc/UGenGraphBuilder$Input$Buffer$Value$.apply:(JIZ)Lde/sciss/proc/UGenGraphBuilder$Input$Buffer$Value;
       9: areturn

  public static de.sciss.proc.UGenGraphBuilder$Input$Buffer$Value fromProduct(scala.Product);
    Code:
       0: getstatic     #35                 // Field de/sciss/proc/UGenGraphBuilder$Input$Buffer$Value$.MODULE$:Lde/sciss/proc/UGenGraphBuilder$Input$Buffer$Value$;
       3: aload_0
       4: invokevirtual #41                 // Method de/sciss/proc/UGenGraphBuilder$Input$Buffer$Value$.fromProduct:(Lscala/Product;)Lde/sciss/proc/UGenGraphBuilder$Input$Buffer$Value;
       7: areturn

  public static de.sciss.proc.UGenGraphBuilder$Input$Buffer$Value unapply(de.sciss.proc.UGenGraphBuilder$Input$Buffer$Value);
    Code:
       0: getstatic     #35                 // Field de/sciss/proc/UGenGraphBuilder$Input$Buffer$Value$.MODULE$:Lde/sciss/proc/UGenGraphBuilder$Input$Buffer$Value$;
       3: aload_0
       4: invokevirtual #45                 // Method de/sciss/proc/UGenGraphBuilder$Input$Buffer$Value$.unapply:(Lde/sciss/proc/UGenGraphBuilder$Input$Buffer$Value;)Lde/sciss/proc/UGenGraphBuilder$Input$Buffer$Value;
       7: areturn

  public de.sciss.proc.UGenGraphBuilder$Input$Buffer$Value(long, int, boolean);
    Code:
       0: aload_0
       1: lload_1
       2: putfield      #49                 // Field numFrames:J
       5: aload_0
       6: iload_3
       7: putfield      #51                 // Field numChannels:I
      10: aload_0
      11: iload         4
      13: putfield      #53                 // Field async:Z
      16: aload_0
      17: invokespecial #56                 // Method java/lang/Object."<init>":()V
      20: return

  public scala.collection.Iterator productIterator();
    Code:
       0: aload_0
       1: invokestatic  #64                 // InterfaceMethod scala/Product.productIterator$:(Lscala/Product;)Lscala/collection/Iterator;
       4: areturn

  public scala.collection.Iterator productElementNames();
    Code:
       0: aload_0
       1: invokestatic  #68                 // InterfaceMethod scala/Product.productElementNames$:(Lscala/Product;)Lscala/collection/Iterator;
       4: areturn

  public int hashCode();
    Code:
       0: ldc           #71                 // int -889275714
       2: istore_1
       3: iload_1
       4: aload_0
       5: invokevirtual #75                 // Method productPrefix:()Ljava/lang/String;
       8: invokevirtual #79                 // Method java/lang/String.hashCode:()I
      11: invokestatic  #85                 // Method scala/runtime/Statics.mix:(II)I
      14: istore_1
      15: iload_1
      16: aload_0
      17: invokevirtual #88                 // Method numFrames:()J
      20: invokestatic  #92                 // Method scala/runtime/Statics.longHash:(J)I
      23: invokestatic  #85                 // Method scala/runtime/Statics.mix:(II)I
      26: istore_1
      27: iload_1
      28: aload_0
      29: invokevirtual #94                 // Method numChannels:()I
      32: invokestatic  #85                 // Method scala/runtime/Statics.mix:(II)I
      35: istore_1
      36: iload_1
      37: aload_0
      38: invokevirtual #97                 // Method async:()Z
      41: ifeq          50
      44: sipush        1231
      47: goto          53
      50: sipush        1237
      53: invokestatic  #85                 // Method scala/runtime/Statics.mix:(II)I
      56: istore_1
      57: iload_1
      58: iconst_3
      59: invokestatic  #100                // Method scala/runtime/Statics.finalizeHash:(II)I
      62: ireturn

  public boolean equals(java.lang.Object);
    Code:
       0: aload_0
       1: aload_1
       2: if_acmpeq     68
       5: aload_1
       6: astore_2
       7: aload_2
       8: instanceof    #2                  // class de/sciss/proc/UGenGraphBuilder$Input$Buffer$Value
      11: ifeq          61
      14: aload_2
      15: checkcast     #2                  // class de/sciss/proc/UGenGraphBuilder$Input$Buffer$Value
      18: astore_3
      19: aload_0
      20: invokevirtual #88                 // Method numFrames:()J
      23: aload_3
      24: invokevirtual #88                 // Method numFrames:()J
      27: lcmp
      28: ifne          57
      31: aload_0
      32: invokevirtual #94                 // Method numChannels:()I
      35: aload_3
      36: invokevirtual #94                 // Method numChannels:()I
      39: if_icmpne     57
      42: aload_0
      43: invokevirtual #97                 // Method async:()Z
      46: aload_3
      47: invokevirtual #97                 // Method async:()Z
      50: if_icmpne     57
      53: iconst_1
      54: goto          58
      57: iconst_0
      58: goto          65
      61: iconst_0
      62: goto          65
      65: ifeq          72
      68: iconst_1
      69: goto          73
      72: iconst_0
      73: ireturn

  public boolean canEqual(java.lang.Object);
    Code:
       0: aload_1
       1: instanceof    #2                  // class de/sciss/proc/UGenGraphBuilder$Input$Buffer$Value
       4: ireturn

  public int productArity();
    Code:
       0: iconst_3
       1: ireturn

  public java.lang.Object productElement(int);
    Code:
       0: iload_1
       1: istore_2
       2: iload_2
       3: tableswitch   { // 0 to 2
                     0: 28
                     1: 41
                     2: 54
               default: 67
          }
      28: aload_0
      29: invokevirtual #113                // Method _1:()J
      32: invokestatic  #119                // Method scala/runtime/BoxesRunTime.boxToLong:(J)Ljava/lang/Long;
      35: goto          86
      38: nop
      39: nop
      40: athrow
      41: aload_0
      42: invokevirtual #122                // Method _2:()I
      45: invokestatic  #126                // Method scala/runtime/BoxesRunTime.boxToInteger:(I)Ljava/lang/Integer;
      48: goto          86
      51: nop
      52: nop
      53: athrow
      54: aload_0
      55: invokevirtual #129                // Method _3:()Z
      58: invokestatic  #133                // Method scala/runtime/BoxesRunTime.boxToBoolean:(Z)Ljava/lang/Boolean;
      61: goto          86
      64: nop
      65: nop
      66: athrow
      67: new           #135                // class java/lang/IndexOutOfBoundsException
      70: dup
      71: iload_1
      72: invokestatic  #126                // Method scala/runtime/BoxesRunTime.boxToInteger:(I)Ljava/lang/Integer;
      75: invokevirtual #140                // Method java/lang/Integer.toString:()Ljava/lang/String;
      78: invokespecial #143                // Method java/lang/IndexOutOfBoundsException."<init>":(Ljava/lang/String;)V
      81: athrow
      82: nop
      83: nop
      84: athrow
      85: athrow
      86: areturn

  public java.lang.String productElementName(int);
    Code:
       0: iload_1
       1: istore_2
       2: iload_2
       3: tableswitch   { // 0 to 2
                     0: 28
                     1: 36
                     2: 44
               default: 52
          }
      28: ldc           #148                // String numFrames
      30: goto          71
      33: nop
      34: nop
      35: athrow
      36: ldc           #149                // String numChannels
      38: goto          71
      41: nop
      42: nop
      43: athrow
      44: ldc           #150                // String async
      46: goto          71
      49: nop
      50: nop
      51: athrow
      52: new           #135                // class java/lang/IndexOutOfBoundsException
      55: dup
      56: iload_1
      57: invokestatic  #126                // Method scala/runtime/BoxesRunTime.boxToInteger:(I)Ljava/lang/Integer;
      60: invokevirtual #140                // Method java/lang/Integer.toString:()Ljava/lang/String;
      63: invokespecial #143                // Method java/lang/IndexOutOfBoundsException."<init>":(Ljava/lang/String;)V
      66: athrow
      67: nop
      68: nop
      69: athrow
      70: athrow
      71: areturn

  public long numFrames();
    Code:
       0: aload_0
       1: getfield      #49                 // Field numFrames:J
       4: lreturn

  public int numChannels();
    Code:
       0: aload_0
       1: getfield      #51                 // Field numChannels:I
       4: ireturn

  public boolean async();
    Code:
       0: aload_0
       1: getfield      #53                 // Field async:Z
       4: ireturn

  public java.lang.String productPrefix();
    Code:
       0: ldc           #152                // String Input.Buffer.Value
       2: areturn

  public java.lang.String toString();
    Code:
       0: new           #154                // class java/lang/StringBuilder
       3: dup
       4: ldc           #155                // int 40
       6: invokespecial #158                // Method java/lang/StringBuilder."<init>":(I)V
       9: aload_0
      10: invokevirtual #75                 // Method productPrefix:()Ljava/lang/String;
      13: invokevirtual #162                // Method java/lang/StringBuilder.append:(Ljava/lang/String;)Ljava/lang/StringBuilder;
      16: ldc           #164                // String (numFrames =
      18: invokevirtual #162                // Method java/lang/StringBuilder.append:(Ljava/lang/String;)Ljava/lang/StringBuilder;
      21: aload_0
      22: invokevirtual #88                 // Method numFrames:()J
      25: invokevirtual #167                // Method java/lang/StringBuilder.append:(J)Ljava/lang/StringBuilder;
      28: ldc           #169                // String , numChannels =
      30: invokevirtual #162                // Method java/lang/StringBuilder.append:(Ljava/lang/String;)Ljava/lang/StringBuilder;
      33: aload_0
      34: invokevirtual #94                 // Method numChannels:()I
      37: invokevirtual #172                // Method java/lang/StringBuilder.append:(I)Ljava/lang/StringBuilder;
      40: ldc           #174                // String , async =
      42: invokevirtual #162                // Method java/lang/StringBuilder.append:(Ljava/lang/String;)Ljava/lang/StringBuilder;
      45: aload_0
      46: invokevirtual #97                 // Method async:()Z
      49: invokevirtual #177                // Method java/lang/StringBuilder.append:(Z)Ljava/lang/StringBuilder;
      52: ldc           #179                // String )
      54: invokevirtual #162                // Method java/lang/StringBuilder.append:(Ljava/lang/String;)Ljava/lang/StringBuilder;
      57: invokevirtual #180                // Method java/lang/StringBuilder.toString:()Ljava/lang/String;
      60: areturn

  public long numSamples();
    Code:
       0: aload_0
       1: invokevirtual #88                 // Method numFrames:()J
       4: aload_0
       5: invokevirtual #94                 // Method numChannels:()I
       8: i2l
       9: lmul
      10: lreturn

  public de.sciss.proc.UGenGraphBuilder$Input$Buffer$Value copy(long, int, boolean);
    Code:
       0: new           #2                  // class de/sciss/proc/UGenGraphBuilder$Input$Buffer$Value
       3: dup
       4: lload_1
       5: iload_3
       6: iload         4
       8: invokespecial #184                // Method "<init>":(JIZ)V
      11: areturn

  public long copy$default$1();
    Code:
       0: aload_0
       1: invokevirtual #88                 // Method numFrames:()J
       4: lreturn

  public int copy$default$2();
    Code:
       0: aload_0
       1: invokevirtual #94                 // Method numChannels:()I
       4: ireturn

  public boolean copy$default$3();
    Code:
       0: aload_0
       1: invokevirtual #97                 // Method async:()Z
       4: ireturn

  public long _1();
    Code:
       0: aload_0
       1: invokevirtual #88                 // Method numFrames:()J
       4: lreturn

  public int _2();
    Code:
       0: aload_0
       1: invokevirtual #94                 // Method numChannels:()I
       4: ireturn

  public boolean _3();
    Code:
       0: aload_0
       1: invokevirtual #97                 // Method async:()Z
       4: ireturn
}
