Compiled from "PatchingAssert.java"
public class org.jboss.as.patching.runner.PatchingAssert {
  public org.jboss.as.patching.runner.PatchingAssert();
    Code:
       0: aload_0
       1: invokespecial #1                  // Method java/lang/Object."<init>":()V
       4: return

  public static void assertContains(java.io.File, java.io.File...);
    Code:
       0: aload_1
       1: invokestatic  #2                  // Method java/util/Arrays.asList:([Ljava/lang/Object;)Ljava/util/List;
       4: astore_2
       5: new           #3                  // class java/lang/StringBuilder
       8: dup
       9: invokespecial #4                  // Method java/lang/StringBuilder."<init>":()V
      12: aload_0
      13: invokevirtual #5                  // Method java/lang/StringBuilder.append:(Ljava/lang/Object;)Ljava/lang/StringBuilder;
      16: ldc           #6                  // String  not found in
      18: invokevirtual #7                  // Method java/lang/StringBuilder.append:(Ljava/lang/String;)Ljava/lang/StringBuilder;
      21: aload_2
      22: invokevirtual #5                  // Method java/lang/StringBuilder.append:(Ljava/lang/Object;)Ljava/lang/StringBuilder;
      25: invokevirtual #8                  // Method java/lang/StringBuilder.toString:()Ljava/lang/String;
      28: aload_2
      29: aload_0
      30: invokeinterface #9,  2            // InterfaceMethod java/util/List.contains:(Ljava/lang/Object;)Z
      35: invokestatic  #10                 // Method org/junit/Assert.assertTrue:(Ljava/lang/String;Z)V
      38: return

  public static java.io.File assertDirExists(java.io.File, java.lang.String...);
    Code:
       0: iconst_1
       1: aload_0
       2: aload_1
       3: invokestatic  #11                 // Method assertFileExists:(ZLjava/io/File;[Ljava/lang/String;)Ljava/io/File;
       6: areturn

  public static void assertDirDoesNotExist(java.io.File, java.lang.String...);
    Code:
       0: aload_0
       1: aload_1
       2: invokestatic  #12                 // Method assertFileDoesNotExist:(Ljava/io/File;[Ljava/lang/String;)V
       5: return

  public static java.io.File assertFileExists(java.io.File, java.lang.String...);
    Code:
       0: iconst_0
       1: aload_0
       2: aload_1
       3: invokestatic  #11                 // Method assertFileExists:(ZLjava/io/File;[Ljava/lang/String;)Ljava/io/File;
       6: areturn

  private static java.io.File assertFileExists(boolean, java.io.File, java.lang.String...);
    Code:
       0: new           #3                  // class java/lang/StringBuilder
       3: dup
       4: invokespecial #4                  // Method java/lang/StringBuilder."<init>":()V
       7: aload_1
       8: invokevirtual #5                  // Method java/lang/StringBuilder.append:(Ljava/lang/Object;)Ljava/lang/StringBuilder;
      11: ldc           #13                 // String  does not exist
      13: invokevirtual #7                  // Method java/lang/StringBuilder.append:(Ljava/lang/String;)Ljava/lang/StringBuilder;
      16: invokevirtual #8                  // Method java/lang/StringBuilder.toString:()Ljava/lang/String;
      19: aload_1
      20: invokevirtual #14                 // Method java/io/File.exists:()Z
      23: invokestatic  #10                 // Method org/junit/Assert.assertTrue:(Ljava/lang/String;Z)V
      26: aload_1
      27: astore_3
      28: aload_2
      29: astore        4
      31: aload         4
      33: arraylength
      34: istore        5
      36: iconst_0
      37: istore        6
      39: iload         6
      41: iload         5
      43: if_icmpge     96
      46: aload         4
      48: iload         6
      50: aaload
      51: astore        7
      53: new           #15                 // class java/io/File
      56: dup
      57: aload_3
      58: aload         7
      60: invokespecial #16                 // Method java/io/File."<init>":(Ljava/io/File;Ljava/lang/String;)V
      63: astore_3
      64: new           #3                  // class java/lang/StringBuilder
      67: dup
      68: invokespecial #4                  // Method java/lang/StringBuilder."<init>":()V
      71: aload_3
      72: invokevirtual #5                  // Method java/lang/StringBuilder.append:(Ljava/lang/Object;)Ljava/lang/StringBuilder;
      75: ldc           #13                 // String  does not exist
      77: invokevirtual #7                  // Method java/lang/StringBuilder.append:(Ljava/lang/String;)Ljava/lang/StringBuilder;
      80: invokevirtual #8                  // Method java/lang/StringBuilder.toString:()Ljava/lang/String;
      83: aload_3
      84: invokevirtual #14                 // Method java/io/File.exists:()Z
      87: invokestatic  #10                 // Method org/junit/Assert.assertTrue:(Ljava/lang/String;Z)V
      90: iinc          6, 1
      93: goto          39
      96: new           #3                  // class java/lang/StringBuilder
      99: dup
     100: invokespecial #4                  // Method java/lang/StringBuilder."<init>":()V
     103: aload_3
     104: invokevirtual #5                  // Method java/lang/StringBuilder.append:(Ljava/lang/Object;)Ljava/lang/StringBuilder;
     107: ldc           #17                 // String  is
     109: invokevirtual #7                  // Method java/lang/StringBuilder.append:(Ljava/lang/String;)Ljava/lang/StringBuilder;
     112: iload_0
     113: ifeq          121
     116: ldc           #18                 // String not
     118: goto          123
     121: ldc           #19                 // String
     123: invokevirtual #7                  // Method java/lang/StringBuilder.append:(Ljava/lang/String;)Ljava/lang/StringBuilder;
     126: ldc           #20                 // String  a directory
     128: invokevirtual #7                  // Method java/lang/StringBuilder.append:(Ljava/lang/String;)Ljava/lang/StringBuilder;
     131: invokevirtual #8                  // Method java/lang/StringBuilder.toString:()Ljava/lang/String;
     134: iload_0
     135: aload_3
     136: invokevirtual #21                 // Method java/io/File.isDirectory:()Z
     139: invokestatic  #22                 // Method junit/framework/Assert.assertEquals:(Ljava/lang/String;ZZ)V
     142: aload_3
     143: areturn

  public static void assertFileDoesNotExist(java.io.File, java.lang.String...);
    Code:
       0: aload_0
       1: aload_1
       2: invokestatic  #23                 // Method org/jboss/as/patching/IoUtils.newFile:(Ljava/io/File;[Ljava/lang/String;)Ljava/io/File;
       5: astore_2
       6: new           #3                  // class java/lang/StringBuilder
       9: dup
      10: invokespecial #4                  // Method java/lang/StringBuilder."<init>":()V
      13: aload_2
      14: invokevirtual #5                  // Method java/lang/StringBuilder.append:(Ljava/lang/Object;)Ljava/lang/StringBuilder;
      17: ldc           #24                 // String  exists
      19: invokevirtual #7                  // Method java/lang/StringBuilder.append:(Ljava/lang/String;)Ljava/lang/StringBuilder;
      22: invokevirtual #8                  // Method java/lang/StringBuilder.toString:()Ljava/lang/String;
      25: aload_2
      26: invokevirtual #14                 // Method java/io/File.exists:()Z
      29: invokestatic  #25                 // Method org/junit/Assert.assertFalse:(Ljava/lang/String;Z)V
      32: return

  public static void assertFileContent(byte[], java.io.File) throws java.lang.Exception;
    Code:
       0: aconst_null
       1: aload_0
       2: aload_1
       3: invokestatic  #26                 // Method assertFileContent:(Ljava/lang/String;[BLjava/io/File;)V
       6: return

  public static void assertFileContent(java.lang.String, byte[], java.io.File) throws java.lang.Exception;
    Code:
       0: aload_0
       1: aload_1
       2: invokestatic  #27                 // Method org/jboss/as/patching/HashUtils.bytesToHexString:([B)Ljava/lang/String;
       5: aload_2
       6: invokestatic  #28                 // Method org/jboss/as/patching/HashUtils.hashFile:(Ljava/io/File;)[B
       9: invokestatic  #27                 // Method org/jboss/as/patching/HashUtils.bytesToHexString:([B)Ljava/lang/String;
      12: invokestatic  #29                 // Method junit/framework/Assert.assertEquals:(Ljava/lang/String;Ljava/lang/String;Ljava/lang/String;)V
      15: return

  public static void assertDefinedModule(java.io.File[], java.lang.String, byte[]) throws java.lang.Exception;
    Code:
       0: aload_0
       1: astore_3
       2: aload_3
       3: arraylength
       4: istore        4
       6: iconst_0
       7: istore        5
       9: iload         5
      11: iload         4
      13: if_icmpge     90
      16: aload_3
      17: iload         5
      19: aaload
      20: astore        6
      22: aload         6
      24: aload_1
      25: ldc           #30                 // String main
      27: invokestatic  #31                 // Method org/jboss/as/patching/runner/PatchContentLoader.getModulePath:(Ljava/io/File;Ljava/lang/String;Ljava/lang/String;)Ljava/io/File;
      30: astore        7
      32: new           #15                 // class java/io/File
      35: dup
      36: aload         7
      38: ldc           #32                 // String module.xml
      40: invokespecial #16                 // Method java/io/File."<init>":(Ljava/io/File;Ljava/lang/String;)V
      43: astore        8
      45: aload         8
      47: invokevirtual #14                 // Method java/io/File.exists:()Z
      50: ifeq          84
      53: aload         8
      55: aload_1
      56: ldc           #33                 // String <module
      58: invokestatic  #34                 // Method assertDefinedModuleWithRootElement:(Ljava/io/File;Ljava/lang/String;Ljava/lang/String;)V
      61: aload_2
      62: ifnull        83
      65: aload         7
      67: invokestatic  #28                 // Method org/jboss/as/patching/HashUtils.hashFile:(Ljava/io/File;)[B
      70: astore        9
      72: ldc           #35                 // String content of module differs
      74: aload_2
      75: aload         9
      77: invokestatic  #36                 // Method java/util/Arrays.equals:([B[B)Z
      80: invokestatic  #10                 // Method org/junit/Assert.assertTrue:(Ljava/lang/String;Z)V
      83: return
      84: iinc          5, 1
      87: goto          9
      90: new           #3                  // class java/lang/StringBuilder
      93: dup
      94: invokespecial #4                  // Method java/lang/StringBuilder."<init>":()V
      97: ldc           #37                 // String count not find module for
      99: invokevirtual #7                  // Method java/lang/StringBuilder.append:(Ljava/lang/String;)Ljava/lang/StringBuilder;
     102: aload_1
     103: invokevirtual #7                  // Method java/lang/StringBuilder.append:(Ljava/lang/String;)Ljava/lang/StringBuilder;
     106: ldc           #38                 // String  in
     108: invokevirtual #7                  // Method java/lang/StringBuilder.append:(Ljava/lang/String;)Ljava/lang/StringBuilder;
     111: aload_0
     112: invokestatic  #2                  // Method java/util/Arrays.asList:([Ljava/lang/Object;)Ljava/util/List;
     115: invokevirtual #5                  // Method java/lang/StringBuilder.append:(Ljava/lang/Object;)Ljava/lang/StringBuilder;
     118: invokevirtual #8                  // Method java/lang/StringBuilder.toString:()Ljava/lang/String;
     121: invokestatic  #39                 // Method org/junit/Assert.fail:(Ljava/lang/String;)V
     124: return

  public static void assertDefinedModule(java.io.File, java.lang.String, byte[]) throws java.lang.Exception;
    Code:
       0: aload_0
       1: aload_1
       2: ldc           #30                 // String main
       4: invokestatic  #31                 // Method org/jboss/as/patching/runner/PatchContentLoader.getModulePath:(Ljava/io/File;Ljava/lang/String;Ljava/lang/String;)Ljava/io/File;
       7: astore_3
       8: new           #15                 // class java/io/File
      11: dup
      12: aload_3
      13: ldc           #32                 // String module.xml
      15: invokespecial #16                 // Method java/io/File."<init>":(Ljava/io/File;Ljava/lang/String;)V
      18: astore        4
      20: aload         4
      22: invokevirtual #14                 // Method java/io/File.exists:()Z
      25: ifeq          58
      28: aload         4
      30: aload_1
      31: ldc           #33                 // String <module
      33: invokestatic  #34                 // Method assertDefinedModuleWithRootElement:(Ljava/io/File;Ljava/lang/String;Ljava/lang/String;)V
      36: aload_2
      37: ifnull        57
      40: aload_3
      41: invokestatic  #28                 // Method org/jboss/as/patching/HashUtils.hashFile:(Ljava/io/File;)[B
      44: astore        5
      46: ldc           #35                 // String content of module differs
      48: aload_2
      49: aload         5
      51: invokestatic  #36                 // Method java/util/Arrays.equals:([B[B)Z
      54: invokestatic  #10                 // Method org/junit/Assert.assertTrue:(Ljava/lang/String;Z)V
      57: return
      58: new           #3                  // class java/lang/StringBuilder
      61: dup
      62: invokespecial #4                  // Method java/lang/StringBuilder."<init>":()V
      65: ldc           #37                 // String count not find module for
      67: invokevirtual #7                  // Method java/lang/StringBuilder.append:(Ljava/lang/String;)Ljava/lang/StringBuilder;
      70: aload_1
      71: invokevirtual #7                  // Method java/lang/StringBuilder.append:(Ljava/lang/String;)Ljava/lang/StringBuilder;
      74: ldc           #38                 // String  in
      76: invokevirtual #7                  // Method java/lang/StringBuilder.append:(Ljava/lang/String;)Ljava/lang/StringBuilder;
      79: aload_0
      80: invokevirtual #5                  // Method java/lang/StringBuilder.append:(Ljava/lang/Object;)Ljava/lang/StringBuilder;
      83: invokevirtual #8                  // Method java/lang/StringBuilder.toString:()Ljava/lang/String;
      86: invokestatic  #39                 // Method org/junit/Assert.fail:(Ljava/lang/String;)V
      89: return

  static void assertDefinedBundle(java.io.File[], java.lang.String, byte[]) throws java.lang.Exception;
    Code:
       0: aload_0
       1: astore_3
       2: aload_3
       3: arraylength
       4: istore        4
       6: iconst_0
       7: istore        5
       9: iload         5
      11: iload         4
      13: if_icmpge     69
      16: aload_3
      17: iload         5
      19: aaload
      20: astore        6
      22: aload         6
      24: aload_1
      25: ldc           #30                 // String main
      27: invokestatic  #31                 // Method org/jboss/as/patching/runner/PatchContentLoader.getModulePath:(Ljava/io/File;Ljava/lang/String;Ljava/lang/String;)Ljava/io/File;
      30: astore        7
      32: aload         7
      34: invokevirtual #14                 // Method java/io/File.exists:()Z
      37: ifeq          63
      40: aload_2
      41: ifnull        62
      44: aload         7
      46: invokestatic  #28                 // Method org/jboss/as/patching/HashUtils.hashFile:(Ljava/io/File;)[B
      49: astore        8
      51: ldc           #40                 // String content of bundle differs
      53: aload_2
      54: aload         8
      56: invokestatic  #36                 // Method java/util/Arrays.equals:([B[B)Z
      59: invokestatic  #10                 // Method org/junit/Assert.assertTrue:(Ljava/lang/String;Z)V
      62: return
      63: iinc          5, 1
      66: goto          9
      69: new           #3                  // class java/lang/StringBuilder
      72: dup
      73: invokespecial #4                  // Method java/lang/StringBuilder."<init>":()V
      76: ldc           #41                 // String content not found bundle for
      78: invokevirtual #7                  // Method java/lang/StringBuilder.append:(Ljava/lang/String;)Ljava/lang/StringBuilder;
      81: aload_1
      82: invokevirtual #7                  // Method java/lang/StringBuilder.append:(Ljava/lang/String;)Ljava/lang/StringBuilder;
      85: ldc           #38                 // String  in
      87: invokevirtual #7                  // Method java/lang/StringBuilder.append:(Ljava/lang/String;)Ljava/lang/StringBuilder;
      90: aload_0
      91: invokestatic  #2                  // Method java/util/Arrays.asList:([Ljava/lang/Object;)Ljava/util/List;
      94: invokevirtual #5                  // Method java/lang/StringBuilder.append:(Ljava/lang/Object;)Ljava/lang/StringBuilder;
      97: invokevirtual #8                  // Method java/lang/StringBuilder.toString:()Ljava/lang/String;
     100: invokestatic  #39                 // Method org/junit/Assert.fail:(Ljava/lang/String;)V
     103: return

  static void assertDefinedBundle(java.io.File, java.lang.String, byte[]) throws java.lang.Exception;
    Code:
       0: aload_0
       1: aload_1
       2: ldc           #30                 // String main
       4: invokestatic  #31                 // Method org/jboss/as/patching/runner/PatchContentLoader.getModulePath:(Ljava/io/File;Ljava/lang/String;Ljava/lang/String;)Ljava/io/File;
       7: astore_3
       8: aload_3
       9: invokevirtual #14                 // Method java/io/File.exists:()Z
      12: ifeq          39
      15: aload_2
      16: ifnull        70
      19: aload_3
      20: invokestatic  #28                 // Method org/jboss/as/patching/HashUtils.hashFile:(Ljava/io/File;)[B
      23: astore        4
      25: ldc           #40                 // String content of bundle differs
      27: aload_2
      28: aload         4
      30: invokestatic  #36                 // Method java/util/Arrays.equals:([B[B)Z
      33: invokestatic  #10                 // Method org/junit/Assert.assertTrue:(Ljava/lang/String;Z)V
      36: goto          70
      39: new           #3                  // class java/lang/StringBuilder
      42: dup
      43: invokespecial #4                  // Method java/lang/StringBuilder."<init>":()V
      46: ldc           #41                 // String content not found bundle for
      48: invokevirtual #7                  // Method java/lang/StringBuilder.append:(Ljava/lang/String;)Ljava/lang/StringBuilder;
      51: aload_1
      52: invokevirtual #7                  // Method java/lang/StringBuilder.append:(Ljava/lang/String;)Ljava/lang/StringBuilder;
      55: ldc           #38                 // String  in
      57: invokevirtual #7                  // Method java/lang/StringBuilder.append:(Ljava/lang/String;)Ljava/lang/StringBuilder;
      60: aload_0
      61: invokevirtual #5                  // Method java/lang/StringBuilder.append:(Ljava/lang/Object;)Ljava/lang/StringBuilder;
      64: invokevirtual #8                  // Method java/lang/StringBuilder.toString:()Ljava/lang/String;
      67: invokestatic  #39                 // Method org/junit/Assert.fail:(Ljava/lang/String;)V
      70: return

  static void assertDefinedAbsentBundle(java.io.File[], java.lang.String) throws java.lang.Exception;
    Code:
       0: aload_0
       1: astore_2
       2: aload_2
       3: arraylength
       4: istore_3
       5: iconst_0
       6: istore        4
       8: iload         4
      10: iload_3
      11: if_icmpge     58
      14: aload_2
      15: iload         4
      17: aaload
      18: astore        5
      20: aload         5
      22: aload_1
      23: ldc           #30                 // String main
      25: invokestatic  #31                 // Method org/jboss/as/patching/runner/PatchContentLoader.getModulePath:(Ljava/io/File;Ljava/lang/String;Ljava/lang/String;)Ljava/io/File;
      28: astore        6
      30: aload         6
      32: invokevirtual #14                 // Method java/io/File.exists:()Z
      35: ifeq          52
      38: aload         6
      40: invokevirtual #42                 // Method java/io/File.listFiles:()[Ljava/io/File;
      43: astore        7
      45: aload         7
      47: arraylength
      48: ifne          52
      51: return
      52: iinc          4, 1
      55: goto          8
      58: new           #3                  // class java/lang/StringBuilder
      61: dup
      62: invokespecial #4                  // Method java/lang/StringBuilder."<init>":()V
      65: ldc           #41                 // String content not found bundle for
      67: invokevirtual #7                  // Method java/lang/StringBuilder.append:(Ljava/lang/String;)Ljava/lang/StringBuilder;
      70: aload_1
      71: invokevirtual #7                  // Method java/lang/StringBuilder.append:(Ljava/lang/String;)Ljava/lang/StringBuilder;
      74: ldc           #38                 // String  in
      76: invokevirtual #7                  // Method java/lang/StringBuilder.append:(Ljava/lang/String;)Ljava/lang/StringBuilder;
      79: aload_0
      80: invokestatic  #2                  // Method java/util/Arrays.asList:([Ljava/lang/Object;)Ljava/util/List;
      83: invokevirtual #5                  // Method java/lang/StringBuilder.append:(Ljava/lang/Object;)Ljava/lang/StringBuilder;
      86: invokevirtual #8                  // Method java/lang/StringBuilder.toString:()Ljava/lang/String;
      89: invokestatic  #39                 // Method org/junit/Assert.fail:(Ljava/lang/String;)V
      92: return

  static void assertDefinedAbsentBundle(java.io.File, java.lang.String) throws java.lang.Exception;
    Code:
       0: aload_0
       1: aload_1
       2: ldc           #30                 // String main
       4: invokestatic  #31                 // Method org/jboss/as/patching/runner/PatchContentLoader.getModulePath:(Ljava/io/File;Ljava/lang/String;Ljava/lang/String;)Ljava/io/File;
       7: astore_2
       8: aload_2
       9: invokevirtual #14                 // Method java/io/File.exists:()Z
      12: ifeq          26
      15: aload_2
      16: invokevirtual #42                 // Method java/io/File.listFiles:()[Ljava/io/File;
      19: astore_3
      20: aload_3
      21: arraylength
      22: ifne          26
      25: return
      26: new           #3                  // class java/lang/StringBuilder
      29: dup
      30: invokespecial #4                  // Method java/lang/StringBuilder."<init>":()V
      33: ldc           #43                 // String content found for
      35: invokevirtual #7                  // Method java/lang/StringBuilder.append:(Ljava/lang/String;)Ljava/lang/StringBuilder;
      38: aload_1
      39: invokevirtual #7                  // Method java/lang/StringBuilder.append:(Ljava/lang/String;)Ljava/lang/StringBuilder;
      42: ldc           #38                 // String  in
      44: invokevirtual #7                  // Method java/lang/StringBuilder.append:(Ljava/lang/String;)Ljava/lang/StringBuilder;
      47: aload_0
      48: invokevirtual #5                  // Method java/lang/StringBuilder.append:(Ljava/lang/Object;)Ljava/lang/StringBuilder;
      51: invokevirtual #8                  // Method java/lang/StringBuilder.toString:()Ljava/lang/String;
      54: invokestatic  #39                 // Method org/junit/Assert.fail:(Ljava/lang/String;)V
      57: return

  static void assertDefinedAbsentModule(java.io.File[], java.lang.String) throws java.lang.Exception;
    Code:
       0: aload_0
       1: astore_2
       2: aload_2
       3: arraylength
       4: istore_3
       5: iconst_0
       6: istore        4
       8: iload         4
      10: iload_3
      11: if_icmpge     66
      14: aload_2
      15: iload         4
      17: aaload
      18: astore        5
      20: aload         5
      22: aload_1
      23: ldc           #30                 // String main
      25: invokestatic  #31                 // Method org/jboss/as/patching/runner/PatchContentLoader.getModulePath:(Ljava/io/File;Ljava/lang/String;Ljava/lang/String;)Ljava/io/File;
      28: astore        6
      30: new           #15                 // class java/io/File
      33: dup
      34: aload         6
      36: ldc           #32                 // String module.xml
      38: invokespecial #16                 // Method java/io/File."<init>":(Ljava/io/File;Ljava/lang/String;)V
      41: astore        7
      43: aload         7
      45: invokevirtual #14                 // Method java/io/File.exists:()Z
      48: ifeq          60
      51: aload         7
      53: aload_1
      54: ldc           #44                 // String <module-absent
      56: invokestatic  #34                 // Method assertDefinedModuleWithRootElement:(Ljava/io/File;Ljava/lang/String;Ljava/lang/String;)V
      59: return
      60: iinc          4, 1
      63: goto          8
      66: new           #3                  // class java/lang/StringBuilder
      69: dup
      70: invokespecial #4                  // Method java/lang/StringBuilder."<init>":()V
      73: ldc           #45                 // String count not found module for
      75: invokevirtual #7                  // Method java/lang/StringBuilder.append:(Ljava/lang/String;)Ljava/lang/StringBuilder;
      78: aload_1
      79: invokevirtual #7                  // Method java/lang/StringBuilder.append:(Ljava/lang/String;)Ljava/lang/StringBuilder;
      82: ldc           #38                 // String  in
      84: invokevirtual #7                  // Method java/lang/StringBuilder.append:(Ljava/lang/String;)Ljava/lang/StringBuilder;
      87: aload_0
      88: invokestatic  #2                  // Method java/util/Arrays.asList:([Ljava/lang/Object;)Ljava/util/List;
      91: invokevirtual #5                  // Method java/lang/StringBuilder.append:(Ljava/lang/Object;)Ljava/lang/StringBuilder;
      94: invokevirtual #8                  // Method java/lang/StringBuilder.toString:()Ljava/lang/String;
      97: invokestatic  #39                 // Method org/junit/Assert.fail:(Ljava/lang/String;)V
     100: return

  static void assertDefinedAbsentModule(java.io.File, java.lang.String) throws java.lang.Exception;
    Code:
       0: aload_0
       1: aload_1
       2: ldc           #30                 // String main
       4: invokestatic  #31                 // Method org/jboss/as/patching/runner/PatchContentLoader.getModulePath:(Ljava/io/File;Ljava/lang/String;Ljava/lang/String;)Ljava/io/File;
       7: astore_2
       8: new           #15                 // class java/io/File
      11: dup
      12: aload_2
      13: ldc           #32                 // String module.xml
      15: invokespecial #16                 // Method java/io/File."<init>":(Ljava/io/File;Ljava/lang/String;)V
      18: astore_3
      19: aload_3
      20: invokevirtual #14                 // Method java/io/File.exists:()Z
      23: ifeq          36
      26: aload_3
      27: aload_1
      28: ldc           #44                 // String <module-absent
      30: invokestatic  #34                 // Method assertDefinedModuleWithRootElement:(Ljava/io/File;Ljava/lang/String;Ljava/lang/String;)V
      33: goto          67
      36: new           #3                  // class java/lang/StringBuilder
      39: dup
      40: invokespecial #4                  // Method java/lang/StringBuilder."<init>":()V
      43: ldc           #45                 // String count not found module for
      45: invokevirtual #7                  // Method java/lang/StringBuilder.append:(Ljava/lang/String;)Ljava/lang/StringBuilder;
      48: aload_1
      49: invokevirtual #7                  // Method java/lang/StringBuilder.append:(Ljava/lang/String;)Ljava/lang/StringBuilder;
      52: ldc           #38                 // String  in
      54: invokevirtual #7                  // Method java/lang/StringBuilder.append:(Ljava/lang/String;)Ljava/lang/StringBuilder;
      57: aload_0
      58: invokevirtual #5                  // Method java/lang/StringBuilder.append:(Ljava/lang/Object;)Ljava/lang/StringBuilder;
      61: invokevirtual #8                  // Method java/lang/StringBuilder.toString:()Ljava/lang/String;
      64: invokestatic  #39                 // Method org/junit/Assert.fail:(Ljava/lang/String;)V
      67: return

  private static void assertDefinedModuleWithRootElement(java.io.File, java.lang.String, java.lang.String) throws java.lang.Exception;
    Code:
       0: aload_0
       1: iconst_0
       2: anewarray     #46                 // class java/lang/String
       5: invokestatic  #47                 // Method assertFileExists:(Ljava/io/File;[Ljava/lang/String;)Ljava/io/File;
       8: pop
       9: aload_0
      10: aload_2
      11: invokestatic  #48                 // Method assertFileContains:(Ljava/io/File;Ljava/lang/String;)V
      14: aload_0
      15: ldc           #49                 // String name=\"%s\"
      17: iconst_1
      18: anewarray     #50                 // class java/lang/Object
      21: dup
      22: iconst_0
      23: aload_1
      24: aastore
      25: invokestatic  #51                 // Method java/lang/String.format:(Ljava/lang/String;[Ljava/lang/Object;)Ljava/lang/String;
      28: invokestatic  #48                 // Method assertFileContains:(Ljava/io/File;Ljava/lang/String;)V
      31: return

  private static void assertFileContains(java.io.File, java.lang.String) throws java.lang.Exception;
    Code:
       0: new           #52                 // class java/util/Scanner
       3: dup
       4: aload_0
       5: ldc           #53                 // String UTF-8
       7: invokespecial #54                 // Method java/util/Scanner."<init>":(Ljava/io/File;Ljava/lang/String;)V
      10: ldc           #55                 // String \\Z
      12: invokevirtual #56                 // Method java/util/Scanner.useDelimiter:(Ljava/lang/String;)Ljava/util/Scanner;
      15: invokevirtual #57                 // Method java/util/Scanner.next:()Ljava/lang/String;
      18: astore_2
      19: new           #3                  // class java/lang/StringBuilder
      22: dup
      23: invokespecial #4                  // Method java/lang/StringBuilder."<init>":()V
      26: aload_1
      27: invokevirtual #7                  // Method java/lang/StringBuilder.append:(Ljava/lang/String;)Ljava/lang/StringBuilder;
      30: ldc           #6                  // String  not found in
      32: invokevirtual #7                  // Method java/lang/StringBuilder.append:(Ljava/lang/String;)Ljava/lang/StringBuilder;
      35: aload_0
      36: invokevirtual #5                  // Method java/lang/StringBuilder.append:(Ljava/lang/Object;)Ljava/lang/StringBuilder;
      39: ldc           #58                 // String  with content=
      41: invokevirtual #7                  // Method java/lang/StringBuilder.append:(Ljava/lang/String;)Ljava/lang/StringBuilder;
      44: aload_2
      45: invokevirtual #7                  // Method java/lang/StringBuilder.append:(Ljava/lang/String;)Ljava/lang/StringBuilder;
      48: invokevirtual #8                  // Method java/lang/StringBuilder.toString:()Ljava/lang/String;
      51: aload_2
      52: aload_1
      53: invokevirtual #59                 // Method java/lang/String.contains:(Ljava/lang/CharSequence;)Z
      56: invokestatic  #10                 // Method org/junit/Assert.assertTrue:(Ljava/lang/String;Z)V
      59: return

  public static void assertPatchHasBeenApplied(org.jboss.as.patching.tool.PatchingResult, org.jboss.as.patching.metadata.Patch);
    Code:
       0: getstatic     #60                 // Field org/jboss/as/patching/metadata/Patch$PatchType.CUMULATIVE:Lorg/jboss/as/patching/metadata/Patch$PatchType;
       3: aload_1
       4: invokeinterface #61,  1           // InterfaceMethod org/jboss/as/patching/metadata/Patch.getIdentity:()Lorg/jboss/as/patching/metadata/Identity;
       9: invokeinterface #62,  1           // InterfaceMethod org/jboss/as/patching/metadata/Identity.getPatchType:()Lorg/jboss/as/patching/metadata/Patch$PatchType;
      14: if_acmpne     98
      17: aload_1
      18: invokeinterface #63,  1           // InterfaceMethod org/jboss/as/patching/metadata/Patch.getPatchId:()Ljava/lang/String;
      23: aload_0
      24: invokeinterface #64,  1           // InterfaceMethod org/jboss/as/patching/tool/PatchingResult.getPatchInfo:()Lorg/jboss/as/patching/PatchInfo;
      29: invokeinterface #65,  1           // InterfaceMethod org/jboss/as/patching/PatchInfo.getCumulativePatchID:()Ljava/lang/String;
      34: invokestatic  #66                 // Method junit/framework/Assert.assertEquals:(Ljava/lang/String;Ljava/lang/String;)V
      37: aload_0
      38: invokeinterface #64,  1           // InterfaceMethod org/jboss/as/patching/tool/PatchingResult.getPatchInfo:()Lorg/jboss/as/patching/PatchInfo;
      43: invokeinterface #67,  1           // InterfaceMethod org/jboss/as/patching/PatchInfo.getPatchIDs:()Ljava/util/List;
      48: invokeinterface #68,  1           // InterfaceMethod java/util/List.isEmpty:()Z
      53: invokestatic  #69                 // Method org/junit/Assert.assertTrue:(Z)V
      56: aload_1
      57: invokeinterface #61,  1           // InterfaceMethod org/jboss/as/patching/metadata/Patch.getIdentity:()Lorg/jboss/as/patching/metadata/Identity;
      62: getstatic     #60                 // Field org/jboss/as/patching/metadata/Patch$PatchType.CUMULATIVE:Lorg/jboss/as/patching/metadata/Patch$PatchType;
      65: ldc_w         #70                 // class org/jboss/as/patching/metadata/Identity$IdentityUpgrade
      68: invokeinterface #71,  3           // InterfaceMethod org/jboss/as/patching/metadata/Identity.forType:(Lorg/jboss/as/patching/metadata/Patch$PatchType;Ljava/lang/Class;)Lorg/jboss/as/patching/metadata/Identity;
      73: checkcast     #70                 // class org/jboss/as/patching/metadata/Identity$IdentityUpgrade
      76: invokeinterface #72,  1           // InterfaceMethod org/jboss/as/patching/metadata/Identity$IdentityUpgrade.getResultingVersion:()Ljava/lang/String;
      81: aload_0
      82: invokeinterface #64,  1           // InterfaceMethod org/jboss/as/patching/tool/PatchingResult.getPatchInfo:()Lorg/jboss/as/patching/PatchInfo;
      87: invokeinterface #73,  1           // InterfaceMethod org/jboss/as/patching/PatchInfo.getVersion:()Ljava/lang/String;
      92: invokestatic  #66                 // Method junit/framework/Assert.assertEquals:(Ljava/lang/String;Ljava/lang/String;)V
      95: goto          152
      98: aload_0
      99: invokeinterface #64,  1           // InterfaceMethod org/jboss/as/patching/tool/PatchingResult.getPatchInfo:()Lorg/jboss/as/patching/PatchInfo;
     104: invokeinterface #67,  1           // InterfaceMethod org/jboss/as/patching/PatchInfo.getPatchIDs:()Ljava/util/List;
     109: aload_1
     110: invokeinterface #63,  1           // InterfaceMethod org/jboss/as/patching/metadata/Patch.getPatchId:()Ljava/lang/String;
     115: invokeinterface #9,  2            // InterfaceMethod java/util/List.contains:(Ljava/lang/Object;)Z
     120: invokestatic  #69                 // Method org/junit/Assert.assertTrue:(Z)V
     123: aload_1
     124: invokeinterface #63,  1           // InterfaceMethod org/jboss/as/patching/metadata/Patch.getPatchId:()Ljava/lang/String;
     129: aload_0
     130: invokeinterface #64,  1           // InterfaceMethod org/jboss/as/patching/tool/PatchingResult.getPatchInfo:()Lorg/jboss/as/patching/PatchInfo;
     135: invokeinterface #67,  1           // InterfaceMethod org/jboss/as/patching/PatchInfo.getPatchIDs:()Ljava/util/List;
     140: iconst_0
     141: invokeinterface #74,  2           // InterfaceMethod java/util/List.get:(I)Ljava/lang/Object;
     146: checkcast     #46                 // class java/lang/String
     149: invokestatic  #66                 // Method junit/framework/Assert.assertEquals:(Ljava/lang/String;Ljava/lang/String;)V
     152: return

  static void assertPatchHasNotBeenApplied(org.jboss.as.patching.ContentConflictsException, org.jboss.as.patching.metadata.Patch, org.jboss.as.patching.metadata.ContentItem, org.jboss.as.patching.DirectoryStructure);
    Code:
       0: ldc           #75                 // String patch should have failed
       2: aload_0
       3: invokevirtual #76                 // Method org/jboss/as/patching/ContentConflictsException.getConflicts:()Ljava/util/Collection;
       6: invokeinterface #77,  1           // InterfaceMethod java/util/Collection.isEmpty:()Z
      11: invokestatic  #25                 // Method org/junit/Assert.assertFalse:(Ljava/lang/String;Z)V
      14: new           #3                  // class java/lang/StringBuilder
      17: dup
      18: invokespecial #4                  // Method java/lang/StringBuilder."<init>":()V
      21: aload_2
      22: invokevirtual #5                  // Method java/lang/StringBuilder.append:(Ljava/lang/Object;)Ljava/lang/StringBuilder;
      25: ldc           #78                 // String  is not reported in the problems
      27: invokevirtual #7                  // Method java/lang/StringBuilder.append:(Ljava/lang/String;)Ljava/lang/StringBuilder;
      30: aload_0
      31: invokevirtual #76                 // Method org/jboss/as/patching/ContentConflictsException.getConflicts:()Ljava/util/Collection;
      34: invokevirtual #5                  // Method java/lang/StringBuilder.append:(Ljava/lang/Object;)Ljava/lang/StringBuilder;
      37: invokevirtual #8                  // Method java/lang/StringBuilder.toString:()Ljava/lang/String;
      40: aload_0
      41: invokevirtual #76                 // Method org/jboss/as/patching/ContentConflictsException.getConflicts:()Ljava/util/Collection;
      44: aload_2
      45: invokeinterface #79,  2           // InterfaceMethod java/util/Collection.contains:(Ljava/lang/Object;)Z
      50: invokestatic  #10                 // Method org/junit/Assert.assertTrue:(Ljava/lang/String;Z)V
      53: aload_3
      54: invokevirtual #80                 // Method org/jboss/as/patching/DirectoryStructure.getInstalledImage:()Lorg/jboss/as/patching/installation/InstalledImage;
      57: aload_1
      58: invokeinterface #63,  1           // InterfaceMethod org/jboss/as/patching/metadata/Patch.getPatchId:()Ljava/lang/String;
      63: invokeinterface #81,  2           // InterfaceMethod org/jboss/as/patching/installation/InstalledImage.getPatchHistoryDir:(Ljava/lang/String;)Ljava/io/File;
      68: iconst_0
      69: anewarray     #46                 // class java/lang/String
      72: invokestatic  #82                 // Method assertDirDoesNotExist:(Ljava/io/File;[Ljava/lang/String;)V
      75: return

  public static void assertPatchHasBeenRolledBack(org.jboss.as.patching.tool.PatchingResult, org.jboss.as.patching.metadata.Patch, org.jboss.as.patching.PatchInfo);
    Code:
       0: aload_2
       1: invokeinterface #73,  1           // InterfaceMethod org/jboss/as/patching/PatchInfo.getVersion:()Ljava/lang/String;
       6: aload_0
       7: invokeinterface #64,  1           // InterfaceMethod org/jboss/as/patching/tool/PatchingResult.getPatchInfo:()Lorg/jboss/as/patching/PatchInfo;
      12: invokeinterface #73,  1           // InterfaceMethod org/jboss/as/patching/PatchInfo.getVersion:()Ljava/lang/String;
      17: invokestatic  #66                 // Method junit/framework/Assert.assertEquals:(Ljava/lang/String;Ljava/lang/String;)V
      20: aload_2
      21: invokeinterface #65,  1           // InterfaceMethod org/jboss/as/patching/PatchInfo.getCumulativePatchID:()Ljava/lang/String;
      26: aload_0
      27: invokeinterface #64,  1           // InterfaceMethod org/jboss/as/patching/tool/PatchingResult.getPatchInfo:()Lorg/jboss/as/patching/PatchInfo;
      32: invokeinterface #65,  1           // InterfaceMethod org/jboss/as/patching/PatchInfo.getCumulativePatchID:()Ljava/lang/String;
      37: invokestatic  #66                 // Method junit/framework/Assert.assertEquals:(Ljava/lang/String;Ljava/lang/String;)V
      40: aload_2
      41: invokeinterface #67,  1           // InterfaceMethod org/jboss/as/patching/PatchInfo.getPatchIDs:()Ljava/util/List;
      46: aload_0
      47: invokeinterface #64,  1           // InterfaceMethod org/jboss/as/patching/tool/PatchingResult.getPatchInfo:()Lorg/jboss/as/patching/PatchInfo;
      52: invokeinterface #67,  1           // InterfaceMethod org/jboss/as/patching/PatchInfo.getPatchIDs:()Ljava/util/List;
      57: invokestatic  #83                 // Method junit/framework/Assert.assertEquals:(Ljava/lang/Object;Ljava/lang/Object;)V
      60: return

  public static void assertPatchHasBeenRolledBack(org.jboss.as.patching.tool.PatchingResult, org.jboss.as.patching.metadata.Patch, org.jboss.as.patching.installation.PatchableTarget$TargetInfo);
    Code:
       0: aload_2
       1: invokeinterface #84,  1           // InterfaceMethod org/jboss/as/patching/installation/PatchableTarget$TargetInfo.getCumulativePatchID:()Ljava/lang/String;
       6: aload_0
       7: invokeinterface #64,  1           // InterfaceMethod org/jboss/as/patching/tool/PatchingResult.getPatchInfo:()Lorg/jboss/as/patching/PatchInfo;
      12: invokeinterface #65,  1           // InterfaceMethod org/jboss/as/patching/PatchInfo.getCumulativePatchID:()Ljava/lang/String;
      17: invokestatic  #66                 // Method junit/framework/Assert.assertEquals:(Ljava/lang/String;Ljava/lang/String;)V
      20: aload_2
      21: invokeinterface #85,  1           // InterfaceMethod org/jboss/as/patching/installation/PatchableTarget$TargetInfo.getPatchIDs:()Ljava/util/List;
      26: aload_0
      27: invokeinterface #64,  1           // InterfaceMethod org/jboss/as/patching/tool/PatchingResult.getPatchInfo:()Lorg/jboss/as/patching/PatchInfo;
      32: invokeinterface #67,  1           // InterfaceMethod org/jboss/as/patching/PatchInfo.getPatchIDs:()Ljava/util/List;
      37: invokestatic  #83                 // Method junit/framework/Assert.assertEquals:(Ljava/lang/Object;Ljava/lang/Object;)V
      40: return

  public static void assertPatchHasBeenRolledBack(org.jboss.as.patching.tool.PatchingResult, org.jboss.as.patching.installation.Identity) throws java.io.IOException;
    Code:
       0: aload_1
       1: invokeinterface #86,  1           // InterfaceMethod org/jboss/as/patching/installation/Identity.getVersion:()Ljava/lang/String;
       6: aload_0
       7: invokeinterface #64,  1           // InterfaceMethod org/jboss/as/patching/tool/PatchingResult.getPatchInfo:()Lorg/jboss/as/patching/PatchInfo;
      12: invokeinterface #73,  1           // InterfaceMethod org/jboss/as/patching/PatchInfo.getVersion:()Ljava/lang/String;
      17: invokestatic  #66                 // Method junit/framework/Assert.assertEquals:(Ljava/lang/String;Ljava/lang/String;)V
      20: aload_1
      21: invokeinterface #87,  1           // InterfaceMethod org/jboss/as/patching/installation/Identity.loadTargetInfo:()Lorg/jboss/as/patching/installation/PatchableTarget$TargetInfo;
      26: invokeinterface #84,  1           // InterfaceMethod org/jboss/as/patching/installation/PatchableTarget$TargetInfo.getCumulativePatchID:()Ljava/lang/String;
      31: aload_0
      32: invokeinterface #64,  1           // InterfaceMethod org/jboss/as/patching/tool/PatchingResult.getPatchInfo:()Lorg/jboss/as/patching/PatchInfo;
      37: invokeinterface #65,  1           // InterfaceMethod org/jboss/as/patching/PatchInfo.getCumulativePatchID:()Ljava/lang/String;
      42: invokestatic  #66                 // Method junit/framework/Assert.assertEquals:(Ljava/lang/String;Ljava/lang/String;)V
      45: aload_1
      46: invokeinterface #87,  1           // InterfaceMethod org/jboss/as/patching/installation/Identity.loadTargetInfo:()Lorg/jboss/as/patching/installation/PatchableTarget$TargetInfo;
      51: invokeinterface #85,  1           // InterfaceMethod org/jboss/as/patching/installation/PatchableTarget$TargetInfo.getPatchIDs:()Ljava/util/List;
      56: aload_0
      57: invokeinterface #64,  1           // InterfaceMethod org/jboss/as/patching/tool/PatchingResult.getPatchInfo:()Lorg/jboss/as/patching/PatchInfo;
      62: invokeinterface #67,  1           // InterfaceMethod org/jboss/as/patching/PatchInfo.getPatchIDs:()Ljava/util/List;
      67: invokestatic  #83                 // Method junit/framework/Assert.assertEquals:(Ljava/lang/Object;Ljava/lang/Object;)V
      70: return

  static void assertNoResourcesForPatch(org.jboss.as.patching.DirectoryStructure, org.jboss.as.patching.metadata.Patch);
    Code:
       0: aload_0
       1: aload_1
       2: invokeinterface #63,  1           // InterfaceMethod org/jboss/as/patching/metadata/Patch.getPatchId:()Ljava/lang/String;
       7: invokevirtual #88                 // Method org/jboss/as/patching/DirectoryStructure.getModulePatchDirectory:(Ljava/lang/String;)Ljava/io/File;
      10: iconst_0
      11: anewarray     #46                 // class java/lang/String
      14: invokestatic  #82                 // Method assertDirDoesNotExist:(Ljava/io/File;[Ljava/lang/String;)V
      17: aload_0
      18: aload_1
      19: invokeinterface #63,  1           // InterfaceMethod org/jboss/as/patching/metadata/Patch.getPatchId:()Ljava/lang/String;
      24: invokevirtual #89                 // Method org/jboss/as/patching/DirectoryStructure.getBundlesPatchDirectory:(Ljava/lang/String;)Ljava/io/File;
      27: iconst_0
      28: anewarray     #46                 // class java/lang/String
      31: invokestatic  #82                 // Method assertDirDoesNotExist:(Ljava/io/File;[Ljava/lang/String;)V
      34: aload_0
      35: invokevirtual #80                 // Method org/jboss/as/patching/DirectoryStructure.getInstalledImage:()Lorg/jboss/as/patching/installation/InstalledImage;
      38: aload_1
      39: invokeinterface #63,  1           // InterfaceMethod org/jboss/as/patching/metadata/Patch.getPatchId:()Ljava/lang/String;
      44: invokeinterface #81,  2           // InterfaceMethod org/jboss/as/patching/installation/InstalledImage.getPatchHistoryDir:(Ljava/lang/String;)Ljava/io/File;
      49: iconst_0
      50: anewarray     #46                 // class java/lang/String
      53: invokestatic  #82                 // Method assertDirDoesNotExist:(Ljava/io/File;[Ljava/lang/String;)V
      56: return

  public static void assertInstallationIsPatched(org.jboss.as.patching.metadata.Patch, org.jboss.as.patching.installation.PatchableTarget$TargetInfo);
    Code:
       0: getstatic     #60                 // Field org/jboss/as/patching/metadata/Patch$PatchType.CUMULATIVE:Lorg/jboss/as/patching/metadata/Patch$PatchType;
       3: aload_0
       4: invokeinterface #61,  1           // InterfaceMethod org/jboss/as/patching/metadata/Patch.getIdentity:()Lorg/jboss/as/patching/metadata/Identity;
       9: invokeinterface #62,  1           // InterfaceMethod org/jboss/as/patching/metadata/Identity.getPatchType:()Lorg/jboss/as/patching/metadata/Patch$PatchType;
      14: if_acmpne     35
      17: aload_0
      18: invokeinterface #63,  1           // InterfaceMethod org/jboss/as/patching/metadata/Patch.getPatchId:()Ljava/lang/String;
      23: aload_1
      24: invokeinterface #84,  1           // InterfaceMethod org/jboss/as/patching/installation/PatchableTarget$TargetInfo.getCumulativePatchID:()Ljava/lang/String;
      29: invokestatic  #66                 // Method junit/framework/Assert.assertEquals:(Ljava/lang/String;Ljava/lang/String;)V
      32: goto          79
      35: aload_1
      36: invokeinterface #85,  1           // InterfaceMethod org/jboss/as/patching/installation/PatchableTarget$TargetInfo.getPatchIDs:()Ljava/util/List;
      41: aload_0
      42: invokeinterface #63,  1           // InterfaceMethod org/jboss/as/patching/metadata/Patch.getPatchId:()Ljava/lang/String;
      47: invokeinterface #9,  2            // InterfaceMethod java/util/List.contains:(Ljava/lang/Object;)Z
      52: invokestatic  #90                 // Method junit/framework/Assert.assertTrue:(Z)V
      55: aload_0
      56: invokeinterface #63,  1           // InterfaceMethod org/jboss/as/patching/metadata/Patch.getPatchId:()Ljava/lang/String;
      61: aload_1
      62: invokeinterface #85,  1           // InterfaceMethod org/jboss/as/patching/installation/PatchableTarget$TargetInfo.getPatchIDs:()Ljava/util/List;
      67: iconst_0
      68: invokeinterface #74,  2           // InterfaceMethod java/util/List.get:(I)Ljava/lang/Object;
      73: checkcast     #46                 // class java/lang/String
      76: invokestatic  #66                 // Method junit/framework/Assert.assertEquals:(Ljava/lang/String;Ljava/lang/String;)V
      79: return
}
