Compiled from "JNDIUtil.java"
public class org.hornetq.utils.JNDIUtil {
  public org.hornetq.utils.JNDIUtil();
    Code:
       0: aload_0
       1: invokespecial #1                  // Method java/lang/Object."<init>":()V
       4: return

  public static javax.naming.Context createContext(javax.naming.Context, java.lang.String) throws javax.naming.NamingException;
    Code:
       0: aload_0
       1: astore_2
       2: new           #2                  // class java/util/StringTokenizer
       5: dup
       6: aload_1
       7: ldc           #3                  // String /
       9: invokespecial #4                  // Method java/util/StringTokenizer."<init>":(Ljava/lang/String;Ljava/lang/String;)V
      12: astore_3
      13: aload_3
      14: invokevirtual #5                  // Method java/util/StringTokenizer.hasMoreTokens:()Z
      17: ifeq          99
      20: aload_3
      21: invokevirtual #6                  // Method java/util/StringTokenizer.nextToken:()Ljava/lang/String;
      24: astore        4
      26: aload_2
      27: aload         4
      29: invokeinterface #7,  2            // InterfaceMethod javax/naming/Context.lookup:(Ljava/lang/String;)Ljava/lang/Object;
      34: astore        5
      36: aload         5
      38: instanceof    #8                  // class javax/naming/Context
      41: ifne          76
      44: new           #9                  // class javax/naming/NamingException
      47: dup
      48: new           #10                 // class java/lang/StringBuilder
      51: dup
      52: invokespecial #11                 // Method java/lang/StringBuilder."<init>":()V
      55: ldc           #12                 // String Path
      57: invokevirtual #13                 // Method java/lang/StringBuilder.append:(Ljava/lang/String;)Ljava/lang/StringBuilder;
      60: aload_1
      61: invokevirtual #13                 // Method java/lang/StringBuilder.append:(Ljava/lang/String;)Ljava/lang/StringBuilder;
      64: ldc           #14                 // String  overwrites and already bound object
      66: invokevirtual #13                 // Method java/lang/StringBuilder.append:(Ljava/lang/String;)Ljava/lang/StringBuilder;
      69: invokevirtual #15                 // Method java/lang/StringBuilder.toString:()Ljava/lang/String;
      72: invokespecial #16                 // Method javax/naming/NamingException."<init>":(Ljava/lang/String;)V
      75: athrow
      76: aload         5
      78: checkcast     #8                  // class javax/naming/Context
      81: astore_2
      82: goto          13
      85: astore        5
      87: aload_2
      88: aload         4
      90: invokeinterface #18,  2           // InterfaceMethod javax/naming/Context.createSubcontext:(Ljava/lang/String;)Ljavax/naming/Context;
      95: astore_2
      96: goto          13
      99: aload_2
     100: areturn
    Exception table:
       from    to  target type
          26    82    85   Class javax/naming/NameNotFoundException

  public static void tearDownRecursively(javax.naming.Context) throws java.lang.Exception;
    Code:
       0: aload_0
       1: ldc           #19                 // String
       3: invokeinterface #20,  2           // InterfaceMethod javax/naming/Context.listBindings:(Ljava/lang/String;)Ljavax/naming/NamingEnumeration;
       8: astore_1
       9: aload_1
      10: invokeinterface #21,  1           // InterfaceMethod javax/naming/NamingEnumeration.hasMore:()Z
      15: ifeq          65
      18: aload_1
      19: invokeinterface #22,  1           // InterfaceMethod javax/naming/NamingEnumeration.next:()Ljava/lang/Object;
      24: checkcast     #23                 // class javax/naming/Binding
      27: astore_2
      28: aload_2
      29: invokevirtual #24                 // Method javax/naming/Binding.getName:()Ljava/lang/String;
      32: astore_3
      33: aload_2
      34: invokevirtual #25                 // Method javax/naming/Binding.getObject:()Ljava/lang/Object;
      37: astore        4
      39: aload         4
      41: instanceof    #8                  // class javax/naming/Context
      44: ifeq          55
      47: aload         4
      49: checkcast     #8                  // class javax/naming/Context
      52: invokestatic  #26                 // Method tearDownRecursively:(Ljavax/naming/Context;)V
      55: aload_0
      56: aload_3
      57: invokeinterface #27,  2           // InterfaceMethod javax/naming/Context.unbind:(Ljava/lang/String;)V
      62: goto          9
      65: return

  public static void rebind(javax.naming.Context, java.lang.String, java.lang.Object) throws javax.naming.NamingException;
    Code:
       0: aload_0
       1: astore_3
       2: aload_1
       3: astore        4
       5: aload_1
       6: bipush        47
       8: invokevirtual #28                 // Method java/lang/String.lastIndexOf:(I)I
      11: istore        5
      13: iload         5
      15: iconst_m1
      16: if_icmpeq     41
      19: aload_0
      20: aload_1
      21: iconst_0
      22: iload         5
      24: invokevirtual #29                 // Method java/lang/String.substring:(II)Ljava/lang/String;
      27: invokestatic  #30                 // Method createContext:(Ljavax/naming/Context;Ljava/lang/String;)Ljavax/naming/Context;
      30: astore_3
      31: aload_1
      32: iload         5
      34: iconst_1
      35: iadd
      36: invokevirtual #31                 // Method java/lang/String.substring:(I)Ljava/lang/String;
      39: astore        4
      41: iconst_0
      42: istore        6
      44: aload_3
      45: aload         4
      47: aload_2
      48: invokeinterface #32,  3           // InterfaceMethod javax/naming/Context.rebind:(Ljava/lang/String;Ljava/lang/Object;)V
      53: goto          61
      56: astore        7
      58: iconst_1
      59: istore        6
      61: iload         6
      63: ifeq          75
      66: aload_3
      67: aload         4
      69: aload_2
      70: invokeinterface #34,  3           // InterfaceMethod javax/naming/Context.bind:(Ljava/lang/String;Ljava/lang/Object;)V
      75: return
    Exception table:
       from    to  target type
          44    53    56   Class java/lang/Exception
}
