Compiled from "AbstractStructSchema.java"
class org.apache.pulsar.client.impl.schema.AbstractStructSchema$WrappedVersionedSchema<T> extends org.apache.pulsar.client.impl.schema.AbstractStructSchema<T> {
  private final byte[] schemaVersion;

  private final org.apache.pulsar.client.impl.schema.AbstractStructSchema<T> parent;

  public org.apache.pulsar.client.impl.schema.AbstractStructSchema$WrappedVersionedSchema(org.apache.pulsar.common.schema.SchemaInfo, byte[], org.apache.pulsar.client.impl.schema.AbstractStructSchema<T>);
    Code:
       0: aload_0
       1: aload_1
       2: invokespecial #1                  // Method org/apache/pulsar/client/impl/schema/AbstractStructSchema."<init>":(Lorg/apache/pulsar/common/schema/SchemaInfo;)V
       5: aload_0
       6: aload_2
       7: putfield      #2                  // Field schemaVersion:[B
      10: aload_0
      11: aconst_null
      12: putfield      #3                  // Field writer:Lorg/apache/pulsar/client/api/schema/SchemaWriter;
      15: aload_0
      16: aload_3
      17: getfield      #4                  // Field org/apache/pulsar/client/impl/schema/AbstractStructSchema.reader:Lorg/apache/pulsar/client/api/schema/SchemaReader;
      20: putfield      #5                  // Field reader:Lorg/apache/pulsar/client/api/schema/SchemaReader;
      23: aload_0
      24: aload_3
      25: getfield      #6                  // Field org/apache/pulsar/client/impl/schema/AbstractStructSchema.schemaInfoProvider:Lorg/apache/pulsar/client/api/schema/SchemaInfoProvider;
      28: putfield      #7                  // Field schemaInfoProvider:Lorg/apache/pulsar/client/api/schema/SchemaInfoProvider;
      31: aload_0
      32: aload_3
      33: putfield      #8                  // Field parent:Lorg/apache/pulsar/client/impl/schema/AbstractStructSchema;
      36: return

  public boolean requireFetchingSchemaInfo();
    Code:
       0: iconst_1
       1: ireturn

  public T decode(byte[]);
    Code:
       0: aload_0
       1: aload_1
       2: aload_0
       3: getfield      #2                  // Field schemaVersion:[B
       6: invokevirtual #9                  // Method decode:([B[B)Ljava/lang/Object;
       9: areturn

  public T decode(io.netty.buffer.ByteBuf);
    Code:
       0: aload_0
       1: aload_1
       2: aload_0
       3: getfield      #2                  // Field schemaVersion:[B
       6: invokevirtual #10                 // Method decode:(Lio/netty/buffer/ByteBuf;[B)Ljava/lang/Object;
       9: areturn

  public byte[] encode(T);
    Code:
       0: new           #11                 // class java/lang/UnsupportedOperationException
       3: dup
       4: ldc           #12                 // String This schema is not meant to be used for encoding
       6: invokespecial #13                 // Method java/lang/UnsupportedOperationException."<init>":(Ljava/lang/String;)V
       9: athrow

  public java.util.Optional<java.lang.Object> getNativeSchema();
    Code:
       0: aload_0
       1: getfield      #5                  // Field reader:Lorg/apache/pulsar/client/api/schema/SchemaReader;
       4: instanceof    #14                 // class org/apache/pulsar/client/impl/schema/reader/AbstractMultiVersionReader
       7: ifeq          47
      10: aload_0
      11: getfield      #5                  // Field reader:Lorg/apache/pulsar/client/api/schema/SchemaReader;
      14: checkcast     #14                 // class org/apache/pulsar/client/impl/schema/reader/AbstractMultiVersionReader
      17: astore_1
      18: aload_1
      19: aload_0
      20: getfield      #2                  // Field schemaVersion:[B
      23: invokevirtual #15                 // Method org/apache/pulsar/client/impl/schema/reader/AbstractMultiVersionReader.getSchemaReader:([B)Lorg/apache/pulsar/client/api/schema/SchemaReader;
      26: astore_2
      27: aload_2
      28: invokeinterface #16,  1           // InterfaceMethod org/apache/pulsar/client/api/schema/SchemaReader.getNativeSchema:()Ljava/util/Optional;
      33: areturn
      34: astore_2
      35: new           #18                 // class java/lang/RuntimeException
      38: dup
      39: aload_2
      40: invokevirtual #19                 // Method java/util/concurrent/ExecutionException.getCause:()Ljava/lang/Throwable;
      43: invokespecial #20                 // Method java/lang/RuntimeException."<init>":(Ljava/lang/Throwable;)V
      46: athrow
      47: invokestatic  #21                 // Method java/util/Optional.empty:()Ljava/util/Optional;
      50: areturn
    Exception table:
       from    to  target type
          18    33    34   Class java/util/concurrent/ExecutionException

  public java.lang.String toString();
    Code:
       0: new           #22                 // class java/lang/StringBuilder
       3: dup
       4: invokespecial #23                 // Method java/lang/StringBuilder."<init>":()V
       7: ldc           #24                 // String VersionedSchema(type=
       9: invokevirtual #25                 // Method java/lang/StringBuilder.append:(Ljava/lang/String;)Ljava/lang/StringBuilder;
      12: aload_0
      13: getfield      #26                 // Field schemaInfo:Lorg/apache/pulsar/common/schema/SchemaInfo;
      16: invokeinterface #27,  1           // InterfaceMethod org/apache/pulsar/common/schema/SchemaInfo.getType:()Lorg/apache/pulsar/common/schema/SchemaType;
      21: invokevirtual #28                 // Method java/lang/StringBuilder.append:(Ljava/lang/Object;)Ljava/lang/StringBuilder;
      24: ldc           #29                 // String ,schemaVersion=
      26: invokevirtual #25                 // Method java/lang/StringBuilder.append:(Ljava/lang/String;)Ljava/lang/StringBuilder;
      29: aload_0
      30: getfield      #2                  // Field schemaVersion:[B
      33: invokestatic  #30                 // Method org/apache/pulsar/common/protocol/schema/BytesSchemaVersion.of:([B)Lorg/apache/pulsar/common/protocol/schema/BytesSchemaVersion;
      36: invokevirtual #28                 // Method java/lang/StringBuilder.append:(Ljava/lang/Object;)Ljava/lang/StringBuilder;
      39: ldc           #31                 // String ,name=
      41: invokevirtual #25                 // Method java/lang/StringBuilder.append:(Ljava/lang/String;)Ljava/lang/StringBuilder;
      44: aload_0
      45: getfield      #26                 // Field schemaInfo:Lorg/apache/pulsar/common/schema/SchemaInfo;
      48: invokeinterface #32,  1           // InterfaceMethod org/apache/pulsar/common/schema/SchemaInfo.getName:()Ljava/lang/String;
      53: invokevirtual #25                 // Method java/lang/StringBuilder.append:(Ljava/lang/String;)Ljava/lang/StringBuilder;
      56: ldc           #33                 // String )
      58: invokevirtual #25                 // Method java/lang/StringBuilder.append:(Ljava/lang/String;)Ljava/lang/StringBuilder;
      61: invokevirtual #34                 // Method java/lang/StringBuilder.toString:()Ljava/lang/String;
      64: areturn
}
