Compiled from "AvroSchema.java"
public class org.apache.pulsar.client.impl.schema.AvroSchema$TimestampConversion extends org.apache.avro.Conversion<org.joda.time.DateTime> {
  public org.apache.pulsar.client.impl.schema.AvroSchema$TimestampConversion();
    Code:
       0: aload_0
       1: invokespecial #1                  // Method org/apache/avro/Conversion."<init>":()V
       4: return

  public java.lang.Class<org.joda.time.DateTime> getConvertedType();
    Code:
       0: ldc           #2                  // class org/joda/time/DateTime
       2: areturn

  public java.lang.String getLogicalTypeName();
    Code:
       0: ldc           #3                  // String timestamp-millis
       2: areturn

  public org.joda.time.DateTime fromLong(java.lang.Long, org.apache.avro.Schema, org.apache.avro.LogicalType);
    Code:
       0: new           #2                  // class org/joda/time/DateTime
       3: dup
       4: aload_1
       5: getstatic     #4                  // Field org/joda/time/DateTimeZone.UTC:Lorg/joda/time/DateTimeZone;
       8: invokespecial #5                  // Method org/joda/time/DateTime."<init>":(Ljava/lang/Object;Lorg/joda/time/DateTimeZone;)V
      11: areturn

  public java.lang.Long toLong(org.joda.time.DateTime, org.apache.avro.Schema, org.apache.avro.LogicalType);
    Code:
       0: aload_1
       1: invokevirtual #6                  // Method org/joda/time/DateTime.getMillis:()J
       4: invokestatic  #7                  // Method java/lang/Long.valueOf:(J)Ljava/lang/Long;
       7: areturn

  public org.apache.avro.Schema getRecommendedSchema();
    Code:
       0: invokestatic  #8                  // Method org/apache/avro/LogicalTypes.timestampMillis:()Lorg/apache/avro/LogicalTypes$TimestampMillis;
       3: getstatic     #9                  // Field org/apache/avro/Schema$Type.LONG:Lorg/apache/avro/Schema$Type;
       6: invokestatic  #10                 // Method org/apache/avro/Schema.create:(Lorg/apache/avro/Schema$Type;)Lorg/apache/avro/Schema;
       9: invokevirtual #11                 // Method org/apache/avro/LogicalTypes$TimestampMillis.addToSchema:(Lorg/apache/avro/Schema;)Lorg/apache/avro/Schema;
      12: areturn

  public java.lang.Long toLong(java.lang.Object, org.apache.avro.Schema, org.apache.avro.LogicalType);
    Code:
       0: aload_0
       1: aload_1
       2: checkcast     #2                  // class org/joda/time/DateTime
       5: aload_2
       6: aload_3
       7: invokevirtual #12                 // Method toLong:(Lorg/joda/time/DateTime;Lorg/apache/avro/Schema;Lorg/apache/avro/LogicalType;)Ljava/lang/Long;
      10: areturn

  public java.lang.Object fromLong(java.lang.Long, org.apache.avro.Schema, org.apache.avro.LogicalType);
    Code:
       0: aload_0
       1: aload_1
       2: aload_2
       3: aload_3
       4: invokevirtual #13                 // Method fromLong:(Ljava/lang/Long;Lorg/apache/avro/Schema;Lorg/apache/avro/LogicalType;)Lorg/joda/time/DateTime;
       7: areturn
}
