Compiled from "IterationEvent.java"
public class org.apache.commons.math3.util.IterationEvent extends java.util.EventObject {
  private static final long serialVersionUID;

  private final int iterations;

  public org.apache.commons.math3.util.IterationEvent(java.lang.Object, int);
    Code:
       0: aload_0
       1: aload_1
       2: invokespecial #1                  // Method java/util/EventObject."<init>":(Ljava/lang/Object;)V
       5: aload_0
       6: iload_2
       7: putfield      #2                  // Field iterations:I
      10: return

  public int getIterations();
    Code:
       0: aload_0
       1: getfield      #2                  // Field iterations:I
       4: ireturn
}
