Compiled from "NettyBodyBody.java"
public class org.asynchttpclient.netty.request.body.NettyBodyBody implements org.asynchttpclient.netty.request.body.NettyBody {
  private final org.asynchttpclient.request.body.Body body;

  private final org.asynchttpclient.AsyncHttpClientConfig config;

  public org.asynchttpclient.netty.request.body.NettyBodyBody(org.asynchttpclient.request.body.Body, org.asynchttpclient.AsyncHttpClientConfig);
    Code:
       0: aload_0
       1: invokespecial #2                  // Method java/lang/Object."<init>":()V
       4: aload_0
       5: aload_1
       6: putfield      #1                  // Field body:Lorg/asynchttpclient/request/body/Body;
       9: aload_0
      10: aload_2
      11: putfield      #3                  // Field config:Lorg/asynchttpclient/AsyncHttpClientConfig;
      14: return

  public org.asynchttpclient.request.body.Body getBody();
    Code:
       0: aload_0
       1: getfield      #1                  // Field body:Lorg/asynchttpclient/request/body/Body;
       4: areturn

  public long getContentLength();
    Code:
       0: aload_0
       1: getfield      #1                  // Field body:Lorg/asynchttpclient/request/body/Body;
       4: invokeinterface #4,  1            // InterfaceMethod org/asynchttpclient/request/body/Body.getContentLength:()J
       9: lreturn

  public void write(io.netty.channel.Channel, org.asynchttpclient.netty.NettyResponseFuture<?>);
    Code:
       0: aload_0
       1: getfield      #1                  // Field body:Lorg/asynchttpclient/request/body/Body;
       4: instanceof    #5                  // class org/asynchttpclient/request/body/RandomAccessBody
       7: ifeq          61
      10: aload_1
      11: invokeinterface #6,  1            // InterfaceMethod io/netty/channel/Channel.pipeline:()Lio/netty/channel/ChannelPipeline;
      16: invokestatic  #7                  // Method org/asynchttpclient/netty/channel/ChannelManager.isSslHandlerConfigured:(Lio/netty/channel/ChannelPipeline;)Z
      19: ifne          61
      22: aload_0
      23: getfield      #3                  // Field config:Lorg/asynchttpclient/AsyncHttpClientConfig;
      26: invokeinterface #8,  1            // InterfaceMethod org/asynchttpclient/AsyncHttpClientConfig.isDisableZeroCopy:()Z
      31: ifne          61
      34: aload_0
      35: invokevirtual #9                  // Method getContentLength:()J
      38: lconst_0
      39: lcmp
      40: ifle          61
      43: new           #10                 // class org/asynchttpclient/netty/request/body/BodyFileRegion
      46: dup
      47: aload_0
      48: getfield      #1                  // Field body:Lorg/asynchttpclient/request/body/Body;
      51: checkcast     #5                  // class org/asynchttpclient/request/body/RandomAccessBody
      54: invokespecial #11                 // Method org/asynchttpclient/netty/request/body/BodyFileRegion."<init>":(Lorg/asynchttpclient/request/body/RandomAccessBody;)V
      57: astore_3
      58: goto          143
      61: new           #12                 // class org/asynchttpclient/netty/request/body/BodyChunkedInput
      64: dup
      65: aload_0
      66: getfield      #1                  // Field body:Lorg/asynchttpclient/request/body/Body;
      69: invokespecial #13                 // Method org/asynchttpclient/netty/request/body/BodyChunkedInput."<init>":(Lorg/asynchttpclient/request/body/Body;)V
      72: astore_3
      73: aload_2
      74: invokevirtual #14                 // Method org/asynchttpclient/netty/NettyResponseFuture.getTargetRequest:()Lorg/asynchttpclient/Request;
      77: invokeinterface #15,  1           // InterfaceMethod org/asynchttpclient/Request.getBodyGenerator:()Lorg/asynchttpclient/request/body/generator/BodyGenerator;
      82: astore        4
      84: aload         4
      86: instanceof    #16                 // class org/asynchttpclient/request/body/generator/FeedableBodyGenerator
      89: ifeq          143
      92: aload         4
      94: instanceof    #17                 // class org/asynchttpclient/request/body/generator/ReactiveStreamsBodyGenerator
      97: ifne          143
     100: aload_1
     101: invokeinterface #6,  1            // InterfaceMethod io/netty/channel/Channel.pipeline:()Lio/netty/channel/ChannelPipeline;
     106: ldc           #18                 // class io/netty/handler/stream/ChunkedWriteHandler
     108: invokeinterface #19,  2           // InterfaceMethod io/netty/channel/ChannelPipeline.get:(Ljava/lang/Class;)Lio/netty/channel/ChannelHandler;
     113: checkcast     #18                 // class io/netty/handler/stream/ChunkedWriteHandler
     116: astore        5
     118: ldc           #16                 // class org/asynchttpclient/request/body/generator/FeedableBodyGenerator
     120: aload         4
     122: invokevirtual #20                 // Method java/lang/Class.cast:(Ljava/lang/Object;)Ljava/lang/Object;
     125: checkcast     #16                 // class org/asynchttpclient/request/body/generator/FeedableBodyGenerator
     128: new           #21                 // class org/asynchttpclient/netty/request/body/NettyBodyBody$1
     131: dup
     132: aload_0
     133: aload         5
     135: invokespecial #22                 // Method org/asynchttpclient/netty/request/body/NettyBodyBody$1."<init>":(Lorg/asynchttpclient/netty/request/body/NettyBodyBody;Lio/netty/handler/stream/ChunkedWriteHandler;)V
     138: invokeinterface #23,  2           // InterfaceMethod org/asynchttpclient/request/body/generator/FeedableBodyGenerator.setListener:(Lorg/asynchttpclient/request/body/generator/FeedListener;)V
     143: aload_1
     144: aload_3
     145: aload_1
     146: invokeinterface #24,  1           // InterfaceMethod io/netty/channel/Channel.newProgressivePromise:()Lio/netty/channel/ChannelProgressivePromise;
     151: invokeinterface #25,  3           // InterfaceMethod io/netty/channel/Channel.write:(Ljava/lang/Object;Lio/netty/channel/ChannelPromise;)Lio/netty/channel/ChannelFuture;
     156: new           #26                 // class org/asynchttpclient/netty/request/body/NettyBodyBody$2
     159: dup
     160: aload_0
     161: aload_2
     162: iconst_0
     163: aload_0
     164: invokevirtual #9                  // Method getContentLength:()J
     167: invokespecial #27                 // Method org/asynchttpclient/netty/request/body/NettyBodyBody$2."<init>":(Lorg/asynchttpclient/netty/request/body/NettyBodyBody;Lorg/asynchttpclient/netty/NettyResponseFuture;ZJ)V
     170: invokeinterface #28,  2           // InterfaceMethod io/netty/channel/ChannelFuture.addListener:(Lio/netty/util/concurrent/GenericFutureListener;)Lio/netty/channel/ChannelFuture;
     175: pop
     176: aload_1
     177: getstatic     #29                 // Field io/netty/handler/codec/http/LastHttpContent.EMPTY_LAST_CONTENT:Lio/netty/handler/codec/http/LastHttpContent;
     180: aload_1
     181: invokeinterface #30,  1           // InterfaceMethod io/netty/channel/Channel.voidPromise:()Lio/netty/channel/ChannelPromise;
     186: invokeinterface #31,  3           // InterfaceMethod io/netty/channel/Channel.writeAndFlush:(Ljava/lang/Object;Lio/netty/channel/ChannelPromise;)Lio/netty/channel/ChannelFuture;
     191: pop
     192: return

  static org.asynchttpclient.request.body.Body access$000(org.asynchttpclient.netty.request.body.NettyBodyBody);
    Code:
       0: aload_0
       1: getfield      #1                  // Field body:Lorg/asynchttpclient/request/body/Body;
       4: areturn
}
