Compiled from "StandardCache.java"
final class org.thymeleaf.cache.StandardCache$CacheDataContainer<K, V> {
  private final java.lang.String name;

  private final boolean sizeLimit;

  private final int maxSize;

  private final boolean traceExecution;

  private final org.slf4j.Logger logger;

  private final java.util.concurrent.ConcurrentHashMap<K, org.thymeleaf.cache.StandardCache$CacheEntry<V>> container;

  private final java.lang.Object[] fifo;

  private int fifoPointer;

  org.thymeleaf.cache.StandardCache$CacheDataContainer(java.lang.String, int, int, boolean, org.slf4j.Logger);
    Code:
       0: aload_0
       1: invokespecial #1                  // Method java/lang/Object."<init>":()V
       4: aload_0
       5: aload_1
       6: putfield      #2                  // Field name:Ljava/lang/String;
       9: aload_0
      10: new           #3                  // class java/util/concurrent/ConcurrentHashMap
      13: dup
      14: iload_2
      15: ldc           #4                  // float 0.9f
      17: iconst_2
      18: invokespecial #5                  // Method java/util/concurrent/ConcurrentHashMap."<init>":(IFI)V
      21: putfield      #6                  // Field container:Ljava/util/concurrent/ConcurrentHashMap;
      24: aload_0
      25: iload_3
      26: putfield      #7                  // Field maxSize:I
      29: aload_0
      30: iload_3
      31: iflt          38
      34: iconst_1
      35: goto          39
      38: iconst_0
      39: putfield      #8                  // Field sizeLimit:Z
      42: aload_0
      43: getfield      #8                  // Field sizeLimit:Z
      46: ifeq          71
      49: aload_0
      50: aload_0
      51: getfield      #7                  // Field maxSize:I
      54: anewarray     #9                  // class java/lang/Object
      57: putfield      #10                 // Field fifo:[Ljava/lang/Object;
      60: aload_0
      61: getfield      #10                 // Field fifo:[Ljava/lang/Object;
      64: aconst_null
      65: invokestatic  #11                 // Method java/util/Arrays.fill:([Ljava/lang/Object;Ljava/lang/Object;)V
      68: goto          76
      71: aload_0
      72: aconst_null
      73: putfield      #10                 // Field fifo:[Ljava/lang/Object;
      76: aload_0
      77: iconst_0
      78: putfield      #12                 // Field fifoPointer:I
      81: aload_0
      82: iload         4
      84: putfield      #13                 // Field traceExecution:Z
      87: aload_0
      88: aload         5
      90: putfield      #14                 // Field logger:Lorg/slf4j/Logger;
      93: return

  public org.thymeleaf.cache.StandardCache$CacheEntry<V> get(java.lang.Object);
    Code:
       0: aload_0
       1: getfield      #6                  // Field container:Ljava/util/concurrent/ConcurrentHashMap;
       4: aload_1
       5: invokevirtual #15                 // Method java/util/concurrent/ConcurrentHashMap.get:(Ljava/lang/Object;)Ljava/lang/Object;
       8: checkcast     #16                 // class org/thymeleaf/cache/StandardCache$CacheEntry
      11: areturn

  public java.util.Set<K> keySet();
    Code:
       0: aload_0
       1: getfield      #6                  // Field container:Ljava/util/concurrent/ConcurrentHashMap;
       4: invokeinterface #17,  1           // InterfaceMethod java/util/Map.keySet:()Ljava/util/Set;
       9: areturn

  public int put(K, org.thymeleaf.cache.StandardCache$CacheEntry<V>);
    Code:
       0: aload_0
       1: getfield      #13                 // Field traceExecution:Z
       4: ifeq          14
       7: aload_0
       8: aload_1
       9: aload_2
      10: invokespecial #18                 // Method putWithTracing:(Ljava/lang/Object;Lorg/thymeleaf/cache/StandardCache$CacheEntry;)I
      13: ireturn
      14: aload_0
      15: aload_1
      16: aload_2
      17: invokespecial #19                 // Method putWithoutTracing:(Ljava/lang/Object;Lorg/thymeleaf/cache/StandardCache$CacheEntry;)I
      20: ireturn

  private int putWithoutTracing(K, org.thymeleaf.cache.StandardCache$CacheEntry<V>);
    Code:
       0: aload_0
       1: getfield      #6                  // Field container:Ljava/util/concurrent/ConcurrentHashMap;
       4: aload_1
       5: aload_2
       6: invokevirtual #20                 // Method java/util/concurrent/ConcurrentHashMap.putIfAbsent:(Ljava/lang/Object;Ljava/lang/Object;)Ljava/lang/Object;
       9: checkcast     #16                 // class org/thymeleaf/cache/StandardCache$CacheEntry
      12: astore_3
      13: aload_3
      14: ifnull        19
      17: iconst_m1
      18: ireturn
      19: aload_0
      20: getfield      #8                  // Field sizeLimit:Z
      23: ifeq          99
      26: aload_0
      27: getfield      #10                 // Field fifo:[Ljava/lang/Object;
      30: dup
      31: astore        4
      33: monitorenter
      34: aload_0
      35: getfield      #10                 // Field fifo:[Ljava/lang/Object;
      38: aload_0
      39: getfield      #12                 // Field fifoPointer:I
      42: aaload
      43: astore        5
      45: aload         5
      47: ifnull        60
      50: aload_0
      51: getfield      #6                  // Field container:Ljava/util/concurrent/ConcurrentHashMap;
      54: aload         5
      56: invokevirtual #21                 // Method java/util/concurrent/ConcurrentHashMap.remove:(Ljava/lang/Object;)Ljava/lang/Object;
      59: pop
      60: aload_0
      61: getfield      #10                 // Field fifo:[Ljava/lang/Object;
      64: aload_0
      65: getfield      #12                 // Field fifoPointer:I
      68: aload_1
      69: aastore
      70: aload_0
      71: aload_0
      72: getfield      #12                 // Field fifoPointer:I
      75: iconst_1
      76: iadd
      77: aload_0
      78: getfield      #7                  // Field maxSize:I
      81: irem
      82: putfield      #12                 // Field fifoPointer:I
      85: aload         4
      87: monitorexit
      88: goto          99
      91: astore        6
      93: aload         4
      95: monitorexit
      96: aload         6
      98: athrow
      99: iconst_m1
     100: ireturn
    Exception table:
       from    to  target type
          34    88    91   any
          91    96    91   any

  private synchronized int putWithTracing(K, org.thymeleaf.cache.StandardCache$CacheEntry<V>);
    Code:
       0: aload_0
       1: getfield      #6                  // Field container:Ljava/util/concurrent/ConcurrentHashMap;
       4: aload_1
       5: aload_2
       6: invokevirtual #20                 // Method java/util/concurrent/ConcurrentHashMap.putIfAbsent:(Ljava/lang/Object;Ljava/lang/Object;)Ljava/lang/Object;
       9: checkcast     #16                 // class org/thymeleaf/cache/StandardCache$CacheEntry
      12: astore_3
      13: aload_3
      14: ifnonnull     147
      17: aload_0
      18: getfield      #8                  // Field sizeLimit:Z
      21: ifeq          147
      24: aload_0
      25: getfield      #10                 // Field fifo:[Ljava/lang/Object;
      28: aload_0
      29: getfield      #12                 // Field fifoPointer:I
      32: aaload
      33: astore        4
      35: aload         4
      37: ifnull        122
      40: aload_0
      41: getfield      #6                  // Field container:Ljava/util/concurrent/ConcurrentHashMap;
      44: aload         4
      46: invokevirtual #21                 // Method java/util/concurrent/ConcurrentHashMap.remove:(Ljava/lang/Object;)Ljava/lang/Object;
      49: checkcast     #16                 // class org/thymeleaf/cache/StandardCache$CacheEntry
      52: astore        5
      54: aload         5
      56: ifnull        122
      59: aload_0
      60: getfield      #6                  // Field container:Ljava/util/concurrent/ConcurrentHashMap;
      63: invokevirtual #22                 // Method java/util/concurrent/ConcurrentHashMap.size:()I
      66: invokestatic  #23                 // Method java/lang/Integer.valueOf:(I)Ljava/lang/Integer;
      69: astore        6
      71: aload_0
      72: getfield      #14                 // Field logger:Lorg/slf4j/Logger;
      75: ldc           #24                 // String [THYMELEAF][{}][{}][CACHE_REMOVE][{}] Max size exceeded for cache \"{}\". Removing entry for key \"{}\". New size is {}.
      77: bipush        6
      79: anewarray     #9                  // class java/lang/Object
      82: dup
      83: iconst_0
      84: invokestatic  #25                 // Method org/thymeleaf/TemplateEngine.threadIndex:()Ljava/lang/String;
      87: aastore
      88: dup
      89: iconst_1
      90: aload_0
      91: getfield      #2                  // Field name:Ljava/lang/String;
      94: aastore
      95: dup
      96: iconst_2
      97: aload         6
      99: aastore
     100: dup
     101: iconst_3
     102: aload_0
     103: getfield      #2                  // Field name:Ljava/lang/String;
     106: aastore
     107: dup
     108: iconst_4
     109: aload         4
     111: aastore
     112: dup
     113: iconst_5
     114: aload         6
     116: aastore
     117: invokeinterface #26,  3           // InterfaceMethod org/slf4j/Logger.trace:(Ljava/lang/String;[Ljava/lang/Object;)V
     122: aload_0
     123: getfield      #10                 // Field fifo:[Ljava/lang/Object;
     126: aload_0
     127: getfield      #12                 // Field fifoPointer:I
     130: aload_1
     131: aastore
     132: aload_0
     133: aload_0
     134: getfield      #12                 // Field fifoPointer:I
     137: iconst_1
     138: iadd
     139: aload_0
     140: getfield      #7                  // Field maxSize:I
     143: irem
     144: putfield      #12                 // Field fifoPointer:I
     147: aload_0
     148: getfield      #6                  // Field container:Ljava/util/concurrent/ConcurrentHashMap;
     151: invokevirtual #22                 // Method java/util/concurrent/ConcurrentHashMap.size:()I
     154: ireturn

  public int remove(K);
    Code:
       0: aload_0
       1: getfield      #13                 // Field traceExecution:Z
       4: ifeq          13
       7: aload_0
       8: aload_1
       9: invokespecial #27                 // Method removeWithTracing:(Ljava/lang/Object;)I
      12: ireturn
      13: aload_0
      14: aload_1
      15: invokespecial #28                 // Method removeWithoutTracing:(Ljava/lang/Object;)I
      18: ireturn

  private int removeWithoutTracing(K);
    Code:
       0: aload_0
       1: getfield      #6                  // Field container:Ljava/util/concurrent/ConcurrentHashMap;
       4: aload_1
       5: invokevirtual #21                 // Method java/util/concurrent/ConcurrentHashMap.remove:(Ljava/lang/Object;)Ljava/lang/Object;
       8: checkcast     #16                 // class org/thymeleaf/cache/StandardCache$CacheEntry
      11: astore_2
      12: aload_2
      13: ifnull        66
      16: aload_0
      17: getfield      #8                  // Field sizeLimit:Z
      20: ifeq          66
      23: aload_1
      24: ifnull        66
      27: iconst_0
      28: istore_3
      29: iload_3
      30: aload_0
      31: getfield      #7                  // Field maxSize:I
      34: if_icmpge     66
      37: aload_1
      38: aload_0
      39: getfield      #10                 // Field fifo:[Ljava/lang/Object;
      42: iload_3
      43: aaload
      44: invokevirtual #29                 // Method java/lang/Object.equals:(Ljava/lang/Object;)Z
      47: ifeq          60
      50: aload_0
      51: getfield      #10                 // Field fifo:[Ljava/lang/Object;
      54: iload_3
      55: aconst_null
      56: aastore
      57: goto          66
      60: iinc          3, 1
      63: goto          29
      66: iconst_m1
      67: ireturn

  private synchronized int removeWithTracing(K);
    Code:
       0: aload_0
       1: getfield      #6                  // Field container:Ljava/util/concurrent/ConcurrentHashMap;
       4: aload_1
       5: invokevirtual #21                 // Method java/util/concurrent/ConcurrentHashMap.remove:(Ljava/lang/Object;)Ljava/lang/Object;
       8: checkcast     #16                 // class org/thymeleaf/cache/StandardCache$CacheEntry
      11: astore_2
      12: aload_2
      13: ifnonnull     18
      16: iconst_m1
      17: ireturn
      18: aload_0
      19: getfield      #8                  // Field sizeLimit:Z
      22: ifeq          68
      25: aload_1
      26: ifnull        68
      29: iconst_0
      30: istore_3
      31: iload_3
      32: aload_0
      33: getfield      #7                  // Field maxSize:I
      36: if_icmpge     68
      39: aload_1
      40: aload_0
      41: getfield      #10                 // Field fifo:[Ljava/lang/Object;
      44: iload_3
      45: aaload
      46: invokevirtual #29                 // Method java/lang/Object.equals:(Ljava/lang/Object;)Z
      49: ifeq          62
      52: aload_0
      53: getfield      #10                 // Field fifo:[Ljava/lang/Object;
      56: iload_3
      57: aconst_null
      58: aastore
      59: goto          68
      62: iinc          3, 1
      65: goto          31
      68: aload_0
      69: getfield      #6                  // Field container:Ljava/util/concurrent/ConcurrentHashMap;
      72: invokevirtual #22                 // Method java/util/concurrent/ConcurrentHashMap.size:()I
      75: ireturn

  public void clear();
    Code:
       0: aload_0
       1: getfield      #6                  // Field container:Ljava/util/concurrent/ConcurrentHashMap;
       4: invokevirtual #30                 // Method java/util/concurrent/ConcurrentHashMap.clear:()V
       7: return

  public int size();
    Code:
       0: aload_0
       1: getfield      #6                  // Field container:Ljava/util/concurrent/ConcurrentHashMap;
       4: invokevirtual #22                 // Method java/util/concurrent/ConcurrentHashMap.size:()I
       7: ireturn
}
