Compiled from "SearchConfig.java"
public class cc.zuv.web.support.search.SearchConfig$Lucene {
  private java.lang.String indexpath;

  public cc.zuv.web.support.search.SearchConfig$Lucene();
    Code:
       0: aload_0
       1: invokespecial #1                  // Method java/lang/Object."<init>":()V
       4: return

  public java.lang.String getIndexpath();
    Code:
       0: aload_0
       1: getfield      #2                  // Field indexpath:Ljava/lang/String;
       4: areturn

  public void setIndexpath(java.lang.String);
    Code:
       0: aload_0
       1: aload_1
       2: putfield      #2                  // Field indexpath:Ljava/lang/String;
       5: return
}
