Compiled from "ResourceAddress.java"
public class org.wildfly.swarm.config.runtime.model.ResourceAddress extends org.jboss.dmr.ModelNode {
  public static final org.wildfly.swarm.config.runtime.model.ResourceAddress ROOT;

  public org.wildfly.swarm.config.runtime.model.ResourceAddress();
    Code:
       0: aload_0
       1: invokespecial #1                  // Method org/jboss/dmr/ModelNode."<init>":()V
       4: return

  public org.wildfly.swarm.config.runtime.model.ResourceAddress(org.jboss.dmr.ModelNode);
    Code:
       0: aload_0
       1: invokespecial #1                  // Method org/jboss/dmr/ModelNode."<init>":()V
       4: aload_0
       5: aload_1
       6: invokevirtual #2                  // Method set:(Lorg/jboss/dmr/ModelNode;)Lorg/jboss/dmr/ModelNode;
       9: pop
      10: return

  public org.wildfly.swarm.config.runtime.model.ResourceAddress add(java.lang.String, java.lang.String);
    Code:
       0: aload_0
       1: invokevirtual #3                  // Method add:()Lorg/jboss/dmr/ModelNode;
       4: aload_1
       5: aload_2
       6: invokevirtual #4                  // Method org/jboss/dmr/ModelNode.set:(Ljava/lang/String;Ljava/lang/String;)Lorg/jboss/dmr/ModelNode;
       9: pop
      10: aload_0
      11: areturn

  public org.jboss.dmr.ModelNode add(java.lang.String, java.lang.String);
    Code:
       0: aload_0
       1: aload_1
       2: aload_2
       3: invokevirtual #5                  // Method add:(Ljava/lang/String;Ljava/lang/String;)Lorg/wildfly/swarm/config/runtime/model/ResourceAddress;
       6: areturn

  static {};
    Code:
       0: new           #6                  // class org/wildfly/swarm/config/runtime/model/ResourceAddress
       3: dup
       4: invokespecial #7                  // Method "<init>":()V
       7: putstatic     #8                  // Field ROOT:Lorg/wildfly/swarm/config/runtime/model/ResourceAddress;
      10: return
}
