Compiled from "UTCUtil.java"
public class sop.util.UTCUtil {
  public static final java.text.SimpleDateFormat UTC_FORMATTER;

  public static final java.text.SimpleDateFormat[] UTC_PARSERS;

  public sop.util.UTCUtil();
    Code:
       0: aload_0
       1: invokespecial #1                  // Method java/lang/Object."<init>":()V
       4: return

  public static java.util.Date parseUTCDate(java.lang.String);
    Code:
       0: getstatic     #7                  // Field UTC_PARSERS:[Ljava/text/SimpleDateFormat;
       3: astore_1
       4: aload_1
       5: arraylength
       6: istore_2
       7: iconst_0
       8: istore_3
       9: iload_3
      10: iload_2
      11: if_icmpge     34
      14: aload_1
      15: iload_3
      16: aaload
      17: astore        4
      19: aload         4
      21: aload_0
      22: invokevirtual #13                 // Method java/text/SimpleDateFormat.parse:(Ljava/lang/String;)Ljava/util/Date;
      25: areturn
      26: astore        5
      28: iinc          3, 1
      31: goto          9
      34: aconst_null
      35: areturn
    Exception table:
       from    to  target type
          19    25    26   Class java/text/ParseException

  public static java.lang.String formatUTCDate(java.util.Date);
    Code:
       0: getstatic     #21                 // Field UTC_FORMATTER:Ljava/text/SimpleDateFormat;
       3: aload_0
       4: invokevirtual #25                 // Method java/text/SimpleDateFormat.format:(Ljava/util/Date;)Ljava/lang/String;
       7: areturn

  static {};
    Code:
       0: new           #14                 // class java/text/SimpleDateFormat
       3: dup
       4: ldc           #29                 // String yyyy-MM-dd\'T\'HH:mm:ss\'Z\'
       6: invokespecial #31                 // Method java/text/SimpleDateFormat."<init>":(Ljava/lang/String;)V
       9: putstatic     #21                 // Field UTC_FORMATTER:Ljava/text/SimpleDateFormat;
      12: iconst_4
      13: anewarray     #14                 // class java/text/SimpleDateFormat
      16: dup
      17: iconst_0
      18: getstatic     #21                 // Field UTC_FORMATTER:Ljava/text/SimpleDateFormat;
      21: aastore
      22: dup
      23: iconst_1
      24: new           #14                 // class java/text/SimpleDateFormat
      27: dup
      28: ldc           #34                 // String yyyy-MM-dd\'T\'HH:mm:ssX
      30: invokespecial #31                 // Method java/text/SimpleDateFormat."<init>":(Ljava/lang/String;)V
      33: aastore
      34: dup
      35: iconst_2
      36: new           #14                 // class java/text/SimpleDateFormat
      39: dup
      40: ldc           #36                 // String yyyyMMdd\'T\'HHmmss\'Z\'
      42: invokespecial #31                 // Method java/text/SimpleDateFormat."<init>":(Ljava/lang/String;)V
      45: aastore
      46: dup
      47: iconst_3
      48: new           #14                 // class java/text/SimpleDateFormat
      51: dup
      52: ldc           #38                 // String yyyy-MM-dd\'T\'HH:mm\'Z\'
      54: invokespecial #31                 // Method java/text/SimpleDateFormat."<init>":(Ljava/lang/String;)V
      57: aastore
      58: putstatic     #7                  // Field UTC_PARSERS:[Ljava/text/SimpleDateFormat;
      61: getstatic     #7                  // Field UTC_PARSERS:[Ljava/text/SimpleDateFormat;
      64: astore_0
      65: aload_0
      66: arraylength
      67: istore_1
      68: iconst_0
      69: istore_2
      70: iload_2
      71: iload_1
      72: if_icmpge     94
      75: aload_0
      76: iload_2
      77: aaload
      78: astore_3
      79: aload_3
      80: ldc           #40                 // String UTC
      82: invokestatic  #42                 // Method java/util/TimeZone.getTimeZone:(Ljava/lang/String;)Ljava/util/TimeZone;
      85: invokevirtual #48                 // Method java/text/SimpleDateFormat.setTimeZone:(Ljava/util/TimeZone;)V
      88: iinc          2, 1
      91: goto          70
      94: return
}
