Compiled from "CycleDetectingLockFactory.java"
class com.google.common.util.concurrent.CycleDetectingLockFactory$CycleDetectingReentrantReadLock extends java.util.concurrent.locks.ReentrantReadWriteLock$ReadLock {
  final com.google.common.util.concurrent.CycleDetectingLockFactory$CycleDetectingReentrantReadWriteLock readWriteLock;

  final com.google.common.util.concurrent.CycleDetectingLockFactory this$0;

  com.google.common.util.concurrent.CycleDetectingLockFactory$CycleDetectingReentrantReadLock(com.google.common.util.concurrent.CycleDetectingLockFactory, com.google.common.util.concurrent.CycleDetectingLockFactory$CycleDetectingReentrantReadWriteLock);
    Code:
       0: aload_0
       1: aload_1
       2: putfield      #1                  // Field this$0:Lcom/google/common/util/concurrent/CycleDetectingLockFactory;
       5: aload_0
       6: aload_2
       7: invokespecial #2                  // Method java/util/concurrent/locks/ReentrantReadWriteLock$ReadLock."<init>":(Ljava/util/concurrent/locks/ReentrantReadWriteLock;)V
      10: aload_0
      11: aload_2
      12: putfield      #3                  // Field readWriteLock:Lcom/google/common/util/concurrent/CycleDetectingLockFactory$CycleDetectingReentrantReadWriteLock;
      15: return

  public void lock();
    Code:
       0: aload_0
       1: getfield      #1                  // Field this$0:Lcom/google/common/util/concurrent/CycleDetectingLockFactory;
       4: aload_0
       5: getfield      #3                  // Field readWriteLock:Lcom/google/common/util/concurrent/CycleDetectingLockFactory$CycleDetectingReentrantReadWriteLock;
       8: invokestatic  #4                  // Method com/google/common/util/concurrent/CycleDetectingLockFactory.access$600:(Lcom/google/common/util/concurrent/CycleDetectingLockFactory;Lcom/google/common/util/concurrent/CycleDetectingLockFactory$CycleDetectingLock;)V
      11: aload_0
      12: invokespecial #5                  // Method java/util/concurrent/locks/ReentrantReadWriteLock$ReadLock.lock:()V
      15: aload_0
      16: getfield      #3                  // Field readWriteLock:Lcom/google/common/util/concurrent/CycleDetectingLockFactory$CycleDetectingReentrantReadWriteLock;
      19: invokestatic  #6                  // Method com/google/common/util/concurrent/CycleDetectingLockFactory.access$700:(Lcom/google/common/util/concurrent/CycleDetectingLockFactory$CycleDetectingLock;)V
      22: goto          35
      25: astore_1
      26: aload_0
      27: getfield      #3                  // Field readWriteLock:Lcom/google/common/util/concurrent/CycleDetectingLockFactory$CycleDetectingReentrantReadWriteLock;
      30: invokestatic  #6                  // Method com/google/common/util/concurrent/CycleDetectingLockFactory.access$700:(Lcom/google/common/util/concurrent/CycleDetectingLockFactory$CycleDetectingLock;)V
      33: aload_1
      34: athrow
      35: return
    Exception table:
       from    to  target type
          11    15    25   any

  public void lockInterruptibly() throws java.lang.InterruptedException;
    Code:
       0: aload_0
       1: getfield      #1                  // Field this$0:Lcom/google/common/util/concurrent/CycleDetectingLockFactory;
       4: aload_0
       5: getfield      #3                  // Field readWriteLock:Lcom/google/common/util/concurrent/CycleDetectingLockFactory$CycleDetectingReentrantReadWriteLock;
       8: invokestatic  #4                  // Method com/google/common/util/concurrent/CycleDetectingLockFactory.access$600:(Lcom/google/common/util/concurrent/CycleDetectingLockFactory;Lcom/google/common/util/concurrent/CycleDetectingLockFactory$CycleDetectingLock;)V
      11: aload_0
      12: invokespecial #7                  // Method java/util/concurrent/locks/ReentrantReadWriteLock$ReadLock.lockInterruptibly:()V
      15: aload_0
      16: getfield      #3                  // Field readWriteLock:Lcom/google/common/util/concurrent/CycleDetectingLockFactory$CycleDetectingReentrantReadWriteLock;
      19: invokestatic  #6                  // Method com/google/common/util/concurrent/CycleDetectingLockFactory.access$700:(Lcom/google/common/util/concurrent/CycleDetectingLockFactory$CycleDetectingLock;)V
      22: goto          35
      25: astore_1
      26: aload_0
      27: getfield      #3                  // Field readWriteLock:Lcom/google/common/util/concurrent/CycleDetectingLockFactory$CycleDetectingReentrantReadWriteLock;
      30: invokestatic  #6                  // Method com/google/common/util/concurrent/CycleDetectingLockFactory.access$700:(Lcom/google/common/util/concurrent/CycleDetectingLockFactory$CycleDetectingLock;)V
      33: aload_1
      34: athrow
      35: return
    Exception table:
       from    to  target type
          11    15    25   any

  public boolean tryLock();
    Code:
       0: aload_0
       1: getfield      #1                  // Field this$0:Lcom/google/common/util/concurrent/CycleDetectingLockFactory;
       4: aload_0
       5: getfield      #3                  // Field readWriteLock:Lcom/google/common/util/concurrent/CycleDetectingLockFactory$CycleDetectingReentrantReadWriteLock;
       8: invokestatic  #4                  // Method com/google/common/util/concurrent/CycleDetectingLockFactory.access$600:(Lcom/google/common/util/concurrent/CycleDetectingLockFactory;Lcom/google/common/util/concurrent/CycleDetectingLockFactory$CycleDetectingLock;)V
      11: aload_0
      12: invokespecial #8                  // Method java/util/concurrent/locks/ReentrantReadWriteLock$ReadLock.tryLock:()Z
      15: istore_1
      16: aload_0
      17: getfield      #3                  // Field readWriteLock:Lcom/google/common/util/concurrent/CycleDetectingLockFactory$CycleDetectingReentrantReadWriteLock;
      20: invokestatic  #6                  // Method com/google/common/util/concurrent/CycleDetectingLockFactory.access$700:(Lcom/google/common/util/concurrent/CycleDetectingLockFactory$CycleDetectingLock;)V
      23: iload_1
      24: ireturn
      25: astore_2
      26: aload_0
      27: getfield      #3                  // Field readWriteLock:Lcom/google/common/util/concurrent/CycleDetectingLockFactory$CycleDetectingReentrantReadWriteLock;
      30: invokestatic  #6                  // Method com/google/common/util/concurrent/CycleDetectingLockFactory.access$700:(Lcom/google/common/util/concurrent/CycleDetectingLockFactory$CycleDetectingLock;)V
      33: aload_2
      34: athrow
    Exception table:
       from    to  target type
          11    16    25   any

  public boolean tryLock(long, java.util.concurrent.TimeUnit) throws java.lang.InterruptedException;
    Code:
       0: aload_0
       1: getfield      #1                  // Field this$0:Lcom/google/common/util/concurrent/CycleDetectingLockFactory;
       4: aload_0
       5: getfield      #3                  // Field readWriteLock:Lcom/google/common/util/concurrent/CycleDetectingLockFactory$CycleDetectingReentrantReadWriteLock;
       8: invokestatic  #4                  // Method com/google/common/util/concurrent/CycleDetectingLockFactory.access$600:(Lcom/google/common/util/concurrent/CycleDetectingLockFactory;Lcom/google/common/util/concurrent/CycleDetectingLockFactory$CycleDetectingLock;)V
      11: aload_0
      12: lload_1
      13: aload_3
      14: invokespecial #9                  // Method java/util/concurrent/locks/ReentrantReadWriteLock$ReadLock.tryLock:(JLjava/util/concurrent/TimeUnit;)Z
      17: istore        4
      19: aload_0
      20: getfield      #3                  // Field readWriteLock:Lcom/google/common/util/concurrent/CycleDetectingLockFactory$CycleDetectingReentrantReadWriteLock;
      23: invokestatic  #6                  // Method com/google/common/util/concurrent/CycleDetectingLockFactory.access$700:(Lcom/google/common/util/concurrent/CycleDetectingLockFactory$CycleDetectingLock;)V
      26: iload         4
      28: ireturn
      29: astore        5
      31: aload_0
      32: getfield      #3                  // Field readWriteLock:Lcom/google/common/util/concurrent/CycleDetectingLockFactory$CycleDetectingReentrantReadWriteLock;
      35: invokestatic  #6                  // Method com/google/common/util/concurrent/CycleDetectingLockFactory.access$700:(Lcom/google/common/util/concurrent/CycleDetectingLockFactory$CycleDetectingLock;)V
      38: aload         5
      40: athrow
    Exception table:
       from    to  target type
          11    19    29   any
          29    31    29   any

  public void unlock();
    Code:
       0: aload_0
       1: invokespecial #10                 // Method java/util/concurrent/locks/ReentrantReadWriteLock$ReadLock.unlock:()V
       4: aload_0
       5: getfield      #3                  // Field readWriteLock:Lcom/google/common/util/concurrent/CycleDetectingLockFactory$CycleDetectingReentrantReadWriteLock;
       8: invokestatic  #6                  // Method com/google/common/util/concurrent/CycleDetectingLockFactory.access$700:(Lcom/google/common/util/concurrent/CycleDetectingLockFactory$CycleDetectingLock;)V
      11: goto          24
      14: astore_1
      15: aload_0
      16: getfield      #3                  // Field readWriteLock:Lcom/google/common/util/concurrent/CycleDetectingLockFactory$CycleDetectingReentrantReadWriteLock;
      19: invokestatic  #6                  // Method com/google/common/util/concurrent/CycleDetectingLockFactory.access$700:(Lcom/google/common/util/concurrent/CycleDetectingLockFactory$CycleDetectingLock;)V
      22: aload_1
      23: athrow
      24: return
    Exception table:
       from    to  target type
           0     4    14   any
}
