Compiled from "ForwardingFluentFuture.java"
final class com.google.common.util.concurrent.ForwardingFluentFuture<V> extends com.google.common.util.concurrent.FluentFuture<V> {
  private final com.google.common.util.concurrent.ListenableFuture<V> delegate;

  com.google.common.util.concurrent.ForwardingFluentFuture(com.google.common.util.concurrent.ListenableFuture<V>);
    Code:
       0: aload_0
       1: invokespecial #1                  // Method com/google/common/util/concurrent/FluentFuture."<init>":()V
       4: aload_0
       5: aload_1
       6: invokestatic  #2                  // Method com/google/common/base/Preconditions.checkNotNull:(Ljava/lang/Object;)Ljava/lang/Object;
       9: checkcast     #3                  // class com/google/common/util/concurrent/ListenableFuture
      12: putfield      #4                  // Field delegate:Lcom/google/common/util/concurrent/ListenableFuture;
      15: return

  public void addListener(java.lang.Runnable, java.util.concurrent.Executor);
    Code:
       0: aload_0
       1: getfield      #4                  // Field delegate:Lcom/google/common/util/concurrent/ListenableFuture;
       4: aload_1
       5: aload_2
       6: invokeinterface #5,  3            // InterfaceMethod com/google/common/util/concurrent/ListenableFuture.addListener:(Ljava/lang/Runnable;Ljava/util/concurrent/Executor;)V
      11: return

  public boolean cancel(boolean);
    Code:
       0: aload_0
       1: getfield      #4                  // Field delegate:Lcom/google/common/util/concurrent/ListenableFuture;
       4: iload_1
       5: invokeinterface #6,  2            // InterfaceMethod com/google/common/util/concurrent/ListenableFuture.cancel:(Z)Z
      10: ireturn

  public boolean isCancelled();
    Code:
       0: aload_0
       1: getfield      #4                  // Field delegate:Lcom/google/common/util/concurrent/ListenableFuture;
       4: invokeinterface #7,  1            // InterfaceMethod com/google/common/util/concurrent/ListenableFuture.isCancelled:()Z
       9: ireturn

  public boolean isDone();
    Code:
       0: aload_0
       1: getfield      #4                  // Field delegate:Lcom/google/common/util/concurrent/ListenableFuture;
       4: invokeinterface #8,  1            // InterfaceMethod com/google/common/util/concurrent/ListenableFuture.isDone:()Z
       9: ireturn

  public V get() throws java.lang.InterruptedException, java.util.concurrent.ExecutionException;
    Code:
       0: aload_0
       1: getfield      #4                  // Field delegate:Lcom/google/common/util/concurrent/ListenableFuture;
       4: invokeinterface #9,  1            // InterfaceMethod com/google/common/util/concurrent/ListenableFuture.get:()Ljava/lang/Object;
       9: areturn

  public V get(long, java.util.concurrent.TimeUnit) throws java.lang.InterruptedException, java.util.concurrent.ExecutionException, java.util.concurrent.TimeoutException;
    Code:
       0: aload_0
       1: getfield      #4                  // Field delegate:Lcom/google/common/util/concurrent/ListenableFuture;
       4: lload_1
       5: aload_3
       6: invokeinterface #10,  4           // InterfaceMethod com/google/common/util/concurrent/ListenableFuture.get:(JLjava/util/concurrent/TimeUnit;)Ljava/lang/Object;
      11: areturn
}
