Compiled from "ChildrenCache.java"
class org.apache.curator.framework.recipes.queue.ChildrenCache$2 implements org.apache.curator.framework.api.BackgroundCallback {
  final org.apache.curator.framework.recipes.queue.ChildrenCache this$0;

  org.apache.curator.framework.recipes.queue.ChildrenCache$2(org.apache.curator.framework.recipes.queue.ChildrenCache);
    Code:
       0: aload_0
       1: aload_1
       2: putfield      #20                 // Field this$0:Lorg/apache/curator/framework/recipes/queue/ChildrenCache;
       5: aload_0
       6: invokespecial #23                 // Method java/lang/Object."<init>":()V
       9: return

  public void processResult(org.apache.curator.framework.CuratorFramework, org.apache.curator.framework.api.CuratorEvent) throws java.lang.Exception;
    Code:
       0: aload_2
       1: invokeinterface #35,  1           // InterfaceMethod org/apache/curator/framework/api/CuratorEvent.getResultCode:()I
       6: getstatic     #39                 // Field org/apache/zookeeper/KeeperException$Code.OK:Lorg/apache/zookeeper/KeeperException$Code;
       9: invokevirtual #42                 // Method org/apache/zookeeper/KeeperException$Code.intValue:()I
      12: if_icmpne     28
      15: aload_0
      16: getfield      #20                 // Field this$0:Lorg/apache/curator/framework/recipes/queue/ChildrenCache;
      19: aload_2
      20: invokeinterface #46,  1           // InterfaceMethod org/apache/curator/framework/api/CuratorEvent.getChildren:()Ljava/util/List;
      25: invokestatic  #50                 // Method org/apache/curator/framework/recipes/queue/ChildrenCache.access$300:(Lorg/apache/curator/framework/recipes/queue/ChildrenCache;Ljava/util/List;)V
      28: return
}
