Compiled from "DistributedIdQueue.java"
class org.apache.curator.framework.recipes.queue.DistributedIdQueue$2 implements java.util.Comparator<java.lang.String> {
  final org.apache.curator.framework.recipes.queue.DistributedIdQueue this$0;

  org.apache.curator.framework.recipes.queue.DistributedIdQueue$2(org.apache.curator.framework.recipes.queue.DistributedIdQueue);
    Code:
       0: aload_0
       1: aload_1
       2: putfield      #22                 // Field this$0:Lorg/apache/curator/framework/recipes/queue/DistributedIdQueue;
       5: aload_0
       6: invokespecial #25                 // Method java/lang/Object."<init>":()V
       9: return

  public int compare(java.lang.String, java.lang.String);
    Code:
       0: aload_0
       1: getfield      #22                 // Field this$0:Lorg/apache/curator/framework/recipes/queue/DistributedIdQueue;
       4: aload_1
       5: invokestatic  #33                 // Method org/apache/curator/framework/recipes/queue/DistributedIdQueue.access$100:(Lorg/apache/curator/framework/recipes/queue/DistributedIdQueue;Ljava/lang/String;)Lorg/apache/curator/framework/recipes/queue/DistributedIdQueue$Parts;
       8: getfield      #37                 // Field org/apache/curator/framework/recipes/queue/DistributedIdQueue$Parts.cleaned:Ljava/lang/String;
      11: aload_0
      12: getfield      #22                 // Field this$0:Lorg/apache/curator/framework/recipes/queue/DistributedIdQueue;
      15: aload_2
      16: invokestatic  #33                 // Method org/apache/curator/framework/recipes/queue/DistributedIdQueue.access$100:(Lorg/apache/curator/framework/recipes/queue/DistributedIdQueue;Ljava/lang/String;)Lorg/apache/curator/framework/recipes/queue/DistributedIdQueue$Parts;
      19: getfield      #37                 // Field org/apache/curator/framework/recipes/queue/DistributedIdQueue$Parts.cleaned:Ljava/lang/String;
      22: invokevirtual #43                 // Method java/lang/String.compareTo:(Ljava/lang/String;)I
      25: ireturn

  public int compare(java.lang.Object, java.lang.Object);
    Code:
       0: aload_0
       1: aload_1
       2: checkcast     #39                 // class java/lang/String
       5: aload_2
       6: checkcast     #39                 // class java/lang/String
       9: invokevirtual #48                 // Method compare:(Ljava/lang/String;Ljava/lang/String;)I
      12: ireturn
}
