Compiled from "EncoderUtil.java"
public class org.apache.james.mime4j.codec.EncoderUtil {
  private static final byte[] BASE64_TABLE;

  private static final char BASE64_PAD;

  private static final java.util.BitSet Q_REGULAR_CHARS;

  private static final java.util.BitSet Q_RESTRICTED_CHARS;

  private static final int MAX_USED_CHARACTERS;

  private static final java.lang.String ENC_WORD_PREFIX;

  private static final java.lang.String ENC_WORD_SUFFIX;

  private static final int ENCODED_WORD_MAX_LENGTH;

  private static final java.util.BitSet TOKEN_CHARS;

  private static final java.util.BitSet ATEXT_CHARS;

  private static java.util.BitSet initChars(java.lang.String);
    Code:
       0: new           #1                  // class java/util/BitSet
       3: dup
       4: sipush        128
       7: invokespecial #2                  // Method java/util/BitSet."<init>":(I)V
      10: astore_1
      11: bipush        33
      13: istore_2
      14: iload_2
      15: bipush        127
      17: if_icmpge     42
      20: aload_0
      21: iload_2
      22: invokevirtual #3                  // Method java/lang/String.indexOf:(I)I
      25: iconst_m1
      26: if_icmpne     34
      29: aload_1
      30: iload_2
      31: invokevirtual #4                  // Method java/util/BitSet.set:(I)V
      34: iload_2
      35: iconst_1
      36: iadd
      37: i2c
      38: istore_2
      39: goto          14
      42: aload_1
      43: areturn

  private org.apache.james.mime4j.codec.EncoderUtil();
    Code:
       0: aload_0
       1: invokespecial #5                  // Method java/lang/Object."<init>":()V
       4: return

  public static java.lang.String encodeAddressDisplayName(java.lang.String);
    Code:
       0: aload_0
       1: invokestatic  #6                  // Method isAtomPhrase:(Ljava/lang/String;)Z
       4: ifeq          9
       7: aload_0
       8: areturn
       9: aload_0
      10: iconst_0
      11: invokestatic  #7                  // Method hasToBeEncoded:(Ljava/lang/String;I)Z
      14: ifeq          25
      17: aload_0
      18: getstatic     #8                  // Field org/apache/james/mime4j/codec/EncoderUtil$Usage.WORD_ENTITY:Lorg/apache/james/mime4j/codec/EncoderUtil$Usage;
      21: invokestatic  #9                  // Method encodeEncodedWord:(Ljava/lang/String;Lorg/apache/james/mime4j/codec/EncoderUtil$Usage;)Ljava/lang/String;
      24: areturn
      25: aload_0
      26: invokestatic  #10                 // Method quote:(Ljava/lang/String;)Ljava/lang/String;
      29: areturn

  public static java.lang.String encodeAddressLocalPart(java.lang.String);
    Code:
       0: aload_0
       1: invokestatic  #11                 // Method isDotAtomText:(Ljava/lang/String;)Z
       4: ifeq          9
       7: aload_0
       8: areturn
       9: aload_0
      10: invokestatic  #10                 // Method quote:(Ljava/lang/String;)Ljava/lang/String;
      13: areturn

  public static java.lang.String encodeHeaderParameter(java.lang.String, java.lang.String);
    Code:
       0: aload_0
       1: getstatic     #12                 // Field java/util/Locale.US:Ljava/util/Locale;
       4: invokevirtual #13                 // Method java/lang/String.toLowerCase:(Ljava/util/Locale;)Ljava/lang/String;
       7: astore_0
       8: aload_1
       9: invokestatic  #14                 // Method isToken:(Ljava/lang/String;)Z
      12: ifeq          39
      15: new           #15                 // class java/lang/StringBuilder
      18: dup
      19: invokespecial #16                 // Method java/lang/StringBuilder."<init>":()V
      22: aload_0
      23: invokevirtual #17                 // Method java/lang/StringBuilder.append:(Ljava/lang/String;)Ljava/lang/StringBuilder;
      26: ldc           #18                 // String =
      28: invokevirtual #17                 // Method java/lang/StringBuilder.append:(Ljava/lang/String;)Ljava/lang/StringBuilder;
      31: aload_1
      32: invokevirtual #17                 // Method java/lang/StringBuilder.append:(Ljava/lang/String;)Ljava/lang/StringBuilder;
      35: invokevirtual #19                 // Method java/lang/StringBuilder.toString:()Ljava/lang/String;
      38: areturn
      39: new           #15                 // class java/lang/StringBuilder
      42: dup
      43: invokespecial #16                 // Method java/lang/StringBuilder."<init>":()V
      46: aload_0
      47: invokevirtual #17                 // Method java/lang/StringBuilder.append:(Ljava/lang/String;)Ljava/lang/StringBuilder;
      50: ldc           #18                 // String =
      52: invokevirtual #17                 // Method java/lang/StringBuilder.append:(Ljava/lang/String;)Ljava/lang/StringBuilder;
      55: aload_1
      56: invokestatic  #10                 // Method quote:(Ljava/lang/String;)Ljava/lang/String;
      59: invokevirtual #17                 // Method java/lang/StringBuilder.append:(Ljava/lang/String;)Ljava/lang/StringBuilder;
      62: invokevirtual #19                 // Method java/lang/StringBuilder.toString:()Ljava/lang/String;
      65: areturn

  public static java.lang.String encodeIfNecessary(java.lang.String, org.apache.james.mime4j.codec.EncoderUtil$Usage, int);
    Code:
       0: aload_0
       1: iload_2
       2: invokestatic  #7                  // Method hasToBeEncoded:(Ljava/lang/String;I)Z
       5: ifeq          15
       8: aload_0
       9: aload_1
      10: iload_2
      11: invokestatic  #20                 // Method encodeEncodedWord:(Ljava/lang/String;Lorg/apache/james/mime4j/codec/EncoderUtil$Usage;I)Ljava/lang/String;
      14: areturn
      15: aload_0
      16: areturn

  public static boolean hasToBeEncoded(java.lang.String, int);
    Code:
       0: aload_0
       1: ifnonnull     12
       4: new           #21                 // class java/lang/IllegalArgumentException
       7: dup
       8: invokespecial #22                 // Method java/lang/IllegalArgumentException."<init>":()V
      11: athrow
      12: iload_1
      13: iflt          22
      16: iload_1
      17: bipush        50
      19: if_icmple     30
      22: new           #21                 // class java/lang/IllegalArgumentException
      25: dup
      26: invokespecial #22                 // Method java/lang/IllegalArgumentException."<init>":()V
      29: athrow
      30: iload_1
      31: istore_2
      32: iconst_0
      33: istore_3
      34: iload_3
      35: aload_0
      36: invokevirtual #23                 // Method java/lang/String.length:()I
      39: if_icmpge     101
      42: aload_0
      43: iload_3
      44: invokevirtual #24                 // Method java/lang/String.charAt:(I)C
      47: istore        4
      49: iload         4
      51: bipush        9
      53: if_icmpeq     63
      56: iload         4
      58: bipush        32
      60: if_icmpne     68
      63: iconst_0
      64: istore_2
      65: goto          95
      68: iinc          2, 1
      71: iload_2
      72: bipush        77
      74: if_icmple     79
      77: iconst_1
      78: ireturn
      79: iload         4
      81: bipush        32
      83: if_icmplt     93
      86: iload         4
      88: bipush        127
      90: if_icmplt     95
      93: iconst_1
      94: ireturn
      95: iinc          3, 1
      98: goto          34
     101: iconst_0
     102: ireturn

  public static java.lang.String encodeEncodedWord(java.lang.String, org.apache.james.mime4j.codec.EncoderUtil$Usage);
    Code:
       0: aload_0
       1: aload_1
       2: iconst_0
       3: aconst_null
       4: aconst_null
       5: invokestatic  #25                 // Method encodeEncodedWord:(Ljava/lang/String;Lorg/apache/james/mime4j/codec/EncoderUtil$Usage;ILjava/nio/charset/Charset;Lorg/apache/james/mime4j/codec/EncoderUtil$Encoding;)Ljava/lang/String;
       8: areturn

  public static java.lang.String encodeEncodedWord(java.lang.String, org.apache.james.mime4j.codec.EncoderUtil$Usage, int);
    Code:
       0: aload_0
       1: aload_1
       2: iload_2
       3: aconst_null
       4: aconst_null
       5: invokestatic  #25                 // Method encodeEncodedWord:(Ljava/lang/String;Lorg/apache/james/mime4j/codec/EncoderUtil$Usage;ILjava/nio/charset/Charset;Lorg/apache/james/mime4j/codec/EncoderUtil$Encoding;)Ljava/lang/String;
       8: areturn

  public static java.lang.String encodeEncodedWord(java.lang.String, org.apache.james.mime4j.codec.EncoderUtil$Usage, int, java.nio.charset.Charset, org.apache.james.mime4j.codec.EncoderUtil$Encoding);
    Code:
       0: aload_0
       1: ifnonnull     12
       4: new           #21                 // class java/lang/IllegalArgumentException
       7: dup
       8: invokespecial #22                 // Method java/lang/IllegalArgumentException."<init>":()V
      11: athrow
      12: iload_2
      13: iflt          22
      16: iload_2
      17: bipush        50
      19: if_icmple     30
      22: new           #21                 // class java/lang/IllegalArgumentException
      25: dup
      26: invokespecial #22                 // Method java/lang/IllegalArgumentException."<init>":()V
      29: athrow
      30: aload_3
      31: ifnonnull     39
      34: aload_0
      35: invokestatic  #26                 // Method determineCharset:(Ljava/lang/String;)Ljava/nio/charset/Charset;
      38: astore_3
      39: aload_3
      40: invokevirtual #27                 // Method java/nio/charset/Charset.name:()Ljava/lang/String;
      43: invokestatic  #28                 // Method org/apache/james/mime4j/util/CharsetUtil.toMimeCharset:(Ljava/lang/String;)Ljava/lang/String;
      46: astore        5
      48: aload         5
      50: ifnonnull     63
      53: new           #21                 // class java/lang/IllegalArgumentException
      56: dup
      57: ldc           #29                 // String Unsupported charset
      59: invokespecial #30                 // Method java/lang/IllegalArgumentException."<init>":(Ljava/lang/String;)V
      62: athrow
      63: aload_0
      64: aload_3
      65: invokestatic  #31                 // Method encode:(Ljava/lang/String;Ljava/nio/charset/Charset;)[B
      68: astore        6
      70: aload         4
      72: ifnonnull     83
      75: aload         6
      77: aload_1
      78: invokestatic  #32                 // Method determineEncoding:([BLorg/apache/james/mime4j/codec/EncoderUtil$Usage;)Lorg/apache/james/mime4j/codec/EncoderUtil$Encoding;
      81: astore        4
      83: aload         4
      85: getstatic     #33                 // Field org/apache/james/mime4j/codec/EncoderUtil$Encoding.B:Lorg/apache/james/mime4j/codec/EncoderUtil$Encoding;
      88: if_acmpne     129
      91: new           #15                 // class java/lang/StringBuilder
      94: dup
      95: invokespecial #16                 // Method java/lang/StringBuilder."<init>":()V
      98: ldc           #34                 // String =?
     100: invokevirtual #17                 // Method java/lang/StringBuilder.append:(Ljava/lang/String;)Ljava/lang/StringBuilder;
     103: aload         5
     105: invokevirtual #17                 // Method java/lang/StringBuilder.append:(Ljava/lang/String;)Ljava/lang/StringBuilder;
     108: ldc           #35                 // String ?B?
     110: invokevirtual #17                 // Method java/lang/StringBuilder.append:(Ljava/lang/String;)Ljava/lang/StringBuilder;
     113: invokevirtual #19                 // Method java/lang/StringBuilder.toString:()Ljava/lang/String;
     116: astore        7
     118: aload         7
     120: aload_0
     121: iload_2
     122: aload_3
     123: aload         6
     125: invokestatic  #36                 // Method encodeB:(Ljava/lang/String;Ljava/lang/String;ILjava/nio/charset/Charset;[B)Ljava/lang/String;
     128: areturn
     129: new           #15                 // class java/lang/StringBuilder
     132: dup
     133: invokespecial #16                 // Method java/lang/StringBuilder."<init>":()V
     136: ldc           #34                 // String =?
     138: invokevirtual #17                 // Method java/lang/StringBuilder.append:(Ljava/lang/String;)Ljava/lang/StringBuilder;
     141: aload         5
     143: invokevirtual #17                 // Method java/lang/StringBuilder.append:(Ljava/lang/String;)Ljava/lang/StringBuilder;
     146: ldc           #37                 // String ?Q?
     148: invokevirtual #17                 // Method java/lang/StringBuilder.append:(Ljava/lang/String;)Ljava/lang/StringBuilder;
     151: invokevirtual #19                 // Method java/lang/StringBuilder.toString:()Ljava/lang/String;
     154: astore        7
     156: aload         7
     158: aload_0
     159: aload_1
     160: iload_2
     161: aload_3
     162: aload         6
     164: invokestatic  #38                 // Method encodeQ:(Ljava/lang/String;Ljava/lang/String;Lorg/apache/james/mime4j/codec/EncoderUtil$Usage;ILjava/nio/charset/Charset;[B)Ljava/lang/String;
     167: areturn

  public static java.lang.String encodeB(byte[]);
    Code:
       0: new           #15                 // class java/lang/StringBuilder
       3: dup
       4: invokespecial #16                 // Method java/lang/StringBuilder."<init>":()V
       7: astore_1
       8: iconst_0
       9: istore_2
      10: aload_0
      11: arraylength
      12: istore_3
      13: iload_2
      14: iload_3
      15: iconst_2
      16: isub
      17: if_icmpge     130
      20: aload_0
      21: iload_2
      22: baload
      23: sipush        255
      26: iand
      27: bipush        16
      29: ishl
      30: aload_0
      31: iload_2
      32: iconst_1
      33: iadd
      34: baload
      35: sipush        255
      38: iand
      39: bipush        8
      41: ishl
      42: ior
      43: aload_0
      44: iload_2
      45: iconst_2
      46: iadd
      47: baload
      48: sipush        255
      51: iand
      52: ior
      53: istore        4
      55: aload_1
      56: getstatic     #39                 // Field BASE64_TABLE:[B
      59: iload         4
      61: bipush        18
      63: ishr
      64: bipush        63
      66: iand
      67: baload
      68: i2c
      69: invokevirtual #40                 // Method java/lang/StringBuilder.append:(C)Ljava/lang/StringBuilder;
      72: pop
      73: aload_1
      74: getstatic     #39                 // Field BASE64_TABLE:[B
      77: iload         4
      79: bipush        12
      81: ishr
      82: bipush        63
      84: iand
      85: baload
      86: i2c
      87: invokevirtual #40                 // Method java/lang/StringBuilder.append:(C)Ljava/lang/StringBuilder;
      90: pop
      91: aload_1
      92: getstatic     #39                 // Field BASE64_TABLE:[B
      95: iload         4
      97: bipush        6
      99: ishr
     100: bipush        63
     102: iand
     103: baload
     104: i2c
     105: invokevirtual #40                 // Method java/lang/StringBuilder.append:(C)Ljava/lang/StringBuilder;
     108: pop
     109: aload_1
     110: getstatic     #39                 // Field BASE64_TABLE:[B
     113: iload         4
     115: bipush        63
     117: iand
     118: baload
     119: i2c
     120: invokevirtual #40                 // Method java/lang/StringBuilder.append:(C)Ljava/lang/StringBuilder;
     123: pop
     124: iinc          2, 3
     127: goto          13
     130: iload_2
     131: iload_3
     132: iconst_2
     133: isub
     134: if_icmpne     226
     137: aload_0
     138: iload_2
     139: baload
     140: sipush        255
     143: iand
     144: bipush        16
     146: ishl
     147: aload_0
     148: iload_2
     149: iconst_1
     150: iadd
     151: baload
     152: sipush        255
     155: iand
     156: bipush        8
     158: ishl
     159: ior
     160: istore        4
     162: aload_1
     163: getstatic     #39                 // Field BASE64_TABLE:[B
     166: iload         4
     168: bipush        18
     170: ishr
     171: bipush        63
     173: iand
     174: baload
     175: i2c
     176: invokevirtual #40                 // Method java/lang/StringBuilder.append:(C)Ljava/lang/StringBuilder;
     179: pop
     180: aload_1
     181: getstatic     #39                 // Field BASE64_TABLE:[B
     184: iload         4
     186: bipush        12
     188: ishr
     189: bipush        63
     191: iand
     192: baload
     193: i2c
     194: invokevirtual #40                 // Method java/lang/StringBuilder.append:(C)Ljava/lang/StringBuilder;
     197: pop
     198: aload_1
     199: getstatic     #39                 // Field BASE64_TABLE:[B
     202: iload         4
     204: bipush        6
     206: ishr
     207: bipush        63
     209: iand
     210: baload
     211: i2c
     212: invokevirtual #40                 // Method java/lang/StringBuilder.append:(C)Ljava/lang/StringBuilder;
     215: pop
     216: aload_1
     217: bipush        61
     219: invokevirtual #40                 // Method java/lang/StringBuilder.append:(C)Ljava/lang/StringBuilder;
     222: pop
     223: goto          295
     226: iload_2
     227: iload_3
     228: iconst_1
     229: isub
     230: if_icmpne     295
     233: aload_0
     234: iload_2
     235: baload
     236: sipush        255
     239: iand
     240: bipush        16
     242: ishl
     243: istore        4
     245: aload_1
     246: getstatic     #39                 // Field BASE64_TABLE:[B
     249: iload         4
     251: bipush        18
     253: ishr
     254: bipush        63
     256: iand
     257: baload
     258: i2c
     259: invokevirtual #40                 // Method java/lang/StringBuilder.append:(C)Ljava/lang/StringBuilder;
     262: pop
     263: aload_1
     264: getstatic     #39                 // Field BASE64_TABLE:[B
     267: iload         4
     269: bipush        12
     271: ishr
     272: bipush        63
     274: iand
     275: baload
     276: i2c
     277: invokevirtual #40                 // Method java/lang/StringBuilder.append:(C)Ljava/lang/StringBuilder;
     280: pop
     281: aload_1
     282: bipush        61
     284: invokevirtual #40                 // Method java/lang/StringBuilder.append:(C)Ljava/lang/StringBuilder;
     287: pop
     288: aload_1
     289: bipush        61
     291: invokevirtual #40                 // Method java/lang/StringBuilder.append:(C)Ljava/lang/StringBuilder;
     294: pop
     295: aload_1
     296: invokevirtual #19                 // Method java/lang/StringBuilder.toString:()Ljava/lang/String;
     299: areturn

  public static java.lang.String encodeQ(byte[], org.apache.james.mime4j.codec.EncoderUtil$Usage);
    Code:
       0: aload_1
       1: getstatic     #41                 // Field org/apache/james/mime4j/codec/EncoderUtil$Usage.TEXT_TOKEN:Lorg/apache/james/mime4j/codec/EncoderUtil$Usage;
       4: if_acmpne     13
       7: getstatic     #42                 // Field Q_REGULAR_CHARS:Ljava/util/BitSet;
      10: goto          16
      13: getstatic     #43                 // Field Q_RESTRICTED_CHARS:Ljava/util/BitSet;
      16: astore_2
      17: new           #15                 // class java/lang/StringBuilder
      20: dup
      21: invokespecial #16                 // Method java/lang/StringBuilder."<init>":()V
      24: astore_3
      25: aload_0
      26: arraylength
      27: istore        4
      29: iconst_0
      30: istore        5
      32: iload         5
      34: iload         4
      36: if_icmpge     124
      39: aload_0
      40: iload         5
      42: baload
      43: sipush        255
      46: iand
      47: istore        6
      49: iload         6
      51: bipush        32
      53: if_icmpne     66
      56: aload_3
      57: bipush        95
      59: invokevirtual #40                 // Method java/lang/StringBuilder.append:(C)Ljava/lang/StringBuilder;
      62: pop
      63: goto          118
      66: aload_2
      67: iload         6
      69: invokevirtual #44                 // Method java/util/BitSet.get:(I)Z
      72: ifne          110
      75: aload_3
      76: bipush        61
      78: invokevirtual #40                 // Method java/lang/StringBuilder.append:(C)Ljava/lang/StringBuilder;
      81: pop
      82: aload_3
      83: iload         6
      85: iconst_4
      86: iushr
      87: invokestatic  #45                 // Method hexDigit:(I)C
      90: invokevirtual #40                 // Method java/lang/StringBuilder.append:(C)Ljava/lang/StringBuilder;
      93: pop
      94: aload_3
      95: iload         6
      97: bipush        15
      99: iand
     100: invokestatic  #45                 // Method hexDigit:(I)C
     103: invokevirtual #40                 // Method java/lang/StringBuilder.append:(C)Ljava/lang/StringBuilder;
     106: pop
     107: goto          118
     110: aload_3
     111: iload         6
     113: i2c
     114: invokevirtual #40                 // Method java/lang/StringBuilder.append:(C)Ljava/lang/StringBuilder;
     117: pop
     118: iinc          5, 1
     121: goto          32
     124: aload_3
     125: invokevirtual #19                 // Method java/lang/StringBuilder.toString:()Ljava/lang/String;
     128: areturn

  public static boolean isToken(java.lang.String);
    Code:
       0: aload_0
       1: invokevirtual #23                 // Method java/lang/String.length:()I
       4: istore_1
       5: iload_1
       6: ifne          11
       9: iconst_0
      10: ireturn
      11: iconst_0
      12: istore_2
      13: iload_2
      14: iload_1
      15: if_icmpge     42
      18: aload_0
      19: iload_2
      20: invokevirtual #24                 // Method java/lang/String.charAt:(I)C
      23: istore_3
      24: getstatic     #46                 // Field TOKEN_CHARS:Ljava/util/BitSet;
      27: iload_3
      28: invokevirtual #44                 // Method java/util/BitSet.get:(I)Z
      31: ifne          36
      34: iconst_0
      35: ireturn
      36: iinc          2, 1
      39: goto          13
      42: iconst_1
      43: ireturn

  private static boolean isAtomPhrase(java.lang.String);
    Code:
       0: iconst_0
       1: istore_1
       2: aload_0
       3: invokevirtual #23                 // Method java/lang/String.length:()I
       6: istore_2
       7: iconst_0
       8: istore_3
       9: iload_3
      10: iload_2
      11: if_icmpge     53
      14: aload_0
      15: iload_3
      16: invokevirtual #24                 // Method java/lang/String.charAt:(I)C
      19: istore        4
      21: getstatic     #47                 // Field ATEXT_CHARS:Ljava/util/BitSet;
      24: iload         4
      26: invokevirtual #44                 // Method java/util/BitSet.get:(I)Z
      29: ifeq          37
      32: iconst_1
      33: istore_1
      34: goto          47
      37: iload         4
      39: invokestatic  #48                 // Method org/apache/james/mime4j/util/CharsetUtil.isWhitespace:(C)Z
      42: ifne          47
      45: iconst_0
      46: ireturn
      47: iinc          3, 1
      50: goto          9
      53: iload_1
      54: ireturn

  private static boolean isDotAtomText(java.lang.String);
    Code:
       0: bipush        46
       2: istore_1
       3: aload_0
       4: invokevirtual #23                 // Method java/lang/String.length:()I
       7: istore_2
       8: iload_2
       9: ifne          14
      12: iconst_0
      13: ireturn
      14: iconst_0
      15: istore_3
      16: iload_3
      17: iload_2
      18: if_icmpge     72
      21: aload_0
      22: iload_3
      23: invokevirtual #24                 // Method java/lang/String.charAt:(I)C
      26: istore        4
      28: iload         4
      30: bipush        46
      32: if_icmpne     50
      35: iload_1
      36: bipush        46
      38: if_icmpeq     48
      41: iload_3
      42: iload_2
      43: iconst_1
      44: isub
      45: if_icmpne     63
      48: iconst_0
      49: ireturn
      50: getstatic     #47                 // Field ATEXT_CHARS:Ljava/util/BitSet;
      53: iload         4
      55: invokevirtual #44                 // Method java/util/BitSet.get:(I)Z
      58: ifne          63
      61: iconst_0
      62: ireturn
      63: iload         4
      65: istore_1
      66: iinc          3, 1
      69: goto          16
      72: iconst_1
      73: ireturn

  private static java.lang.String quote(java.lang.String);
    Code:
       0: aload_0
       1: ldc           #49                 // String [\\\\\"]
       3: ldc           #50                 // String \\\\$0
       5: invokevirtual #51                 // Method java/lang/String.replaceAll:(Ljava/lang/String;Ljava/lang/String;)Ljava/lang/String;
       8: astore_1
       9: new           #15                 // class java/lang/StringBuilder
      12: dup
      13: invokespecial #16                 // Method java/lang/StringBuilder."<init>":()V
      16: ldc           #52                 // String \"
      18: invokevirtual #17                 // Method java/lang/StringBuilder.append:(Ljava/lang/String;)Ljava/lang/StringBuilder;
      21: aload_1
      22: invokevirtual #17                 // Method java/lang/StringBuilder.append:(Ljava/lang/String;)Ljava/lang/StringBuilder;
      25: ldc           #52                 // String \"
      27: invokevirtual #17                 // Method java/lang/StringBuilder.append:(Ljava/lang/String;)Ljava/lang/StringBuilder;
      30: invokevirtual #19                 // Method java/lang/StringBuilder.toString:()Ljava/lang/String;
      33: areturn

  private static java.lang.String encodeB(java.lang.String, java.lang.String, int, java.nio.charset.Charset, byte[]);
    Code:
       0: aload         4
       2: invokestatic  #53                 // Method bEncodedLength:([B)I
       5: istore        5
       7: aload_0
       8: invokevirtual #23                 // Method java/lang/String.length:()I
      11: iload         5
      13: iadd
      14: ldc           #54                 // String ?=
      16: invokevirtual #23                 // Method java/lang/String.length:()I
      19: iadd
      20: istore        6
      22: iload         6
      24: bipush        75
      26: iload_2
      27: isub
      28: if_icmpgt     59
      31: new           #15                 // class java/lang/StringBuilder
      34: dup
      35: invokespecial #16                 // Method java/lang/StringBuilder."<init>":()V
      38: aload_0
      39: invokevirtual #17                 // Method java/lang/StringBuilder.append:(Ljava/lang/String;)Ljava/lang/StringBuilder;
      42: aload         4
      44: invokestatic  #55                 // Method encodeB:([B)Ljava/lang/String;
      47: invokevirtual #17                 // Method java/lang/StringBuilder.append:(Ljava/lang/String;)Ljava/lang/StringBuilder;
      50: ldc           #54                 // String ?=
      52: invokevirtual #17                 // Method java/lang/StringBuilder.append:(Ljava/lang/String;)Ljava/lang/StringBuilder;
      55: invokevirtual #19                 // Method java/lang/StringBuilder.toString:()Ljava/lang/String;
      58: areturn
      59: aload_1
      60: iconst_0
      61: aload_1
      62: invokevirtual #23                 // Method java/lang/String.length:()I
      65: iconst_2
      66: idiv
      67: invokevirtual #56                 // Method java/lang/String.substring:(II)Ljava/lang/String;
      70: astore        7
      72: aload         7
      74: aload_3
      75: invokestatic  #31                 // Method encode:(Ljava/lang/String;Ljava/nio/charset/Charset;)[B
      78: astore        8
      80: aload_0
      81: aload         7
      83: iload_2
      84: aload_3
      85: aload         8
      87: invokestatic  #36                 // Method encodeB:(Ljava/lang/String;Ljava/lang/String;ILjava/nio/charset/Charset;[B)Ljava/lang/String;
      90: astore        9
      92: aload_1
      93: aload_1
      94: invokevirtual #23                 // Method java/lang/String.length:()I
      97: iconst_2
      98: idiv
      99: invokevirtual #57                 // Method java/lang/String.substring:(I)Ljava/lang/String;
     102: astore        10
     104: aload         10
     106: aload_3
     107: invokestatic  #31                 // Method encode:(Ljava/lang/String;Ljava/nio/charset/Charset;)[B
     110: astore        11
     112: aload_0
     113: aload         10
     115: iconst_0
     116: aload_3
     117: aload         11
     119: invokestatic  #36                 // Method encodeB:(Ljava/lang/String;Ljava/lang/String;ILjava/nio/charset/Charset;[B)Ljava/lang/String;
     122: astore        12
     124: new           #15                 // class java/lang/StringBuilder
     127: dup
     128: invokespecial #16                 // Method java/lang/StringBuilder."<init>":()V
     131: aload         9
     133: invokevirtual #17                 // Method java/lang/StringBuilder.append:(Ljava/lang/String;)Ljava/lang/StringBuilder;
     136: ldc           #58                 // String
     138: invokevirtual #17                 // Method java/lang/StringBuilder.append:(Ljava/lang/String;)Ljava/lang/StringBuilder;
     141: aload         12
     143: invokevirtual #17                 // Method java/lang/StringBuilder.append:(Ljava/lang/String;)Ljava/lang/StringBuilder;
     146: invokevirtual #19                 // Method java/lang/StringBuilder.toString:()Ljava/lang/String;
     149: areturn

  private static int bEncodedLength(byte[]);
    Code:
       0: aload_0
       1: arraylength
       2: iconst_2
       3: iadd
       4: iconst_3
       5: idiv
       6: iconst_4
       7: imul
       8: ireturn

  private static java.lang.String encodeQ(java.lang.String, java.lang.String, org.apache.james.mime4j.codec.EncoderUtil$Usage, int, java.nio.charset.Charset, byte[]);
    Code:
       0: aload         5
       2: aload_2
       3: invokestatic  #59                 // Method qEncodedLength:([BLorg/apache/james/mime4j/codec/EncoderUtil$Usage;)I
       6: istore        6
       8: aload_0
       9: invokevirtual #23                 // Method java/lang/String.length:()I
      12: iload         6
      14: iadd
      15: ldc           #54                 // String ?=
      17: invokevirtual #23                 // Method java/lang/String.length:()I
      20: iadd
      21: istore        7
      23: iload         7
      25: bipush        75
      27: iload_3
      28: isub
      29: if_icmpgt     61
      32: new           #15                 // class java/lang/StringBuilder
      35: dup
      36: invokespecial #16                 // Method java/lang/StringBuilder."<init>":()V
      39: aload_0
      40: invokevirtual #17                 // Method java/lang/StringBuilder.append:(Ljava/lang/String;)Ljava/lang/StringBuilder;
      43: aload         5
      45: aload_2
      46: invokestatic  #60                 // Method encodeQ:([BLorg/apache/james/mime4j/codec/EncoderUtil$Usage;)Ljava/lang/String;
      49: invokevirtual #17                 // Method java/lang/StringBuilder.append:(Ljava/lang/String;)Ljava/lang/StringBuilder;
      52: ldc           #54                 // String ?=
      54: invokevirtual #17                 // Method java/lang/StringBuilder.append:(Ljava/lang/String;)Ljava/lang/StringBuilder;
      57: invokevirtual #19                 // Method java/lang/StringBuilder.toString:()Ljava/lang/String;
      60: areturn
      61: aload_1
      62: iconst_0
      63: aload_1
      64: invokevirtual #23                 // Method java/lang/String.length:()I
      67: iconst_2
      68: idiv
      69: invokevirtual #56                 // Method java/lang/String.substring:(II)Ljava/lang/String;
      72: astore        8
      74: aload         8
      76: aload         4
      78: invokestatic  #31                 // Method encode:(Ljava/lang/String;Ljava/nio/charset/Charset;)[B
      81: astore        9
      83: aload_0
      84: aload         8
      86: aload_2
      87: iload_3
      88: aload         4
      90: aload         9
      92: invokestatic  #38                 // Method encodeQ:(Ljava/lang/String;Ljava/lang/String;Lorg/apache/james/mime4j/codec/EncoderUtil$Usage;ILjava/nio/charset/Charset;[B)Ljava/lang/String;
      95: astore        10
      97: aload_1
      98: aload_1
      99: invokevirtual #23                 // Method java/lang/String.length:()I
     102: iconst_2
     103: idiv
     104: invokevirtual #57                 // Method java/lang/String.substring:(I)Ljava/lang/String;
     107: astore        11
     109: aload         11
     111: aload         4
     113: invokestatic  #31                 // Method encode:(Ljava/lang/String;Ljava/nio/charset/Charset;)[B
     116: astore        12
     118: aload_0
     119: aload         11
     121: aload_2
     122: iconst_0
     123: aload         4
     125: aload         12
     127: invokestatic  #38                 // Method encodeQ:(Ljava/lang/String;Ljava/lang/String;Lorg/apache/james/mime4j/codec/EncoderUtil$Usage;ILjava/nio/charset/Charset;[B)Ljava/lang/String;
     130: astore        13
     132: new           #15                 // class java/lang/StringBuilder
     135: dup
     136: invokespecial #16                 // Method java/lang/StringBuilder."<init>":()V
     139: aload         10
     141: invokevirtual #17                 // Method java/lang/StringBuilder.append:(Ljava/lang/String;)Ljava/lang/StringBuilder;
     144: ldc           #58                 // String
     146: invokevirtual #17                 // Method java/lang/StringBuilder.append:(Ljava/lang/String;)Ljava/lang/StringBuilder;
     149: aload         13
     151: invokevirtual #17                 // Method java/lang/StringBuilder.append:(Ljava/lang/String;)Ljava/lang/StringBuilder;
     154: invokevirtual #19                 // Method java/lang/StringBuilder.toString:()Ljava/lang/String;
     157: areturn

  private static int qEncodedLength(byte[], org.apache.james.mime4j.codec.EncoderUtil$Usage);
    Code:
       0: aload_1
       1: getstatic     #41                 // Field org/apache/james/mime4j/codec/EncoderUtil$Usage.TEXT_TOKEN:Lorg/apache/james/mime4j/codec/EncoderUtil$Usage;
       4: if_acmpne     13
       7: getstatic     #42                 // Field Q_REGULAR_CHARS:Ljava/util/BitSet;
      10: goto          16
      13: getstatic     #43                 // Field Q_RESTRICTED_CHARS:Ljava/util/BitSet;
      16: astore_2
      17: iconst_0
      18: istore_3
      19: iconst_0
      20: istore        4
      22: iload         4
      24: aload_0
      25: arraylength
      26: if_icmpge     76
      29: aload_0
      30: iload         4
      32: baload
      33: sipush        255
      36: iand
      37: istore        5
      39: iload         5
      41: bipush        32
      43: if_icmpne     52
      46: iinc          3, 1
      49: goto          70
      52: aload_2
      53: iload         5
      55: invokevirtual #44                 // Method java/util/BitSet.get:(I)Z
      58: ifne          67
      61: iinc          3, 3
      64: goto          70
      67: iinc          3, 1
      70: iinc          4, 1
      73: goto          22
      76: iload_3
      77: ireturn

  private static byte[] encode(java.lang.String, java.nio.charset.Charset);
    Code:
       0: aload_1
       1: aload_0
       2: invokevirtual #61                 // Method java/nio/charset/Charset.encode:(Ljava/lang/String;)Ljava/nio/ByteBuffer;
       5: astore_2
       6: aload_2
       7: invokevirtual #62                 // Method java/nio/ByteBuffer.limit:()I
      10: newarray       byte
      12: astore_3
      13: aload_2
      14: aload_3
      15: invokevirtual #63                 // Method java/nio/ByteBuffer.get:([B)Ljava/nio/ByteBuffer;
      18: pop
      19: aload_3
      20: areturn

  private static java.nio.charset.Charset determineCharset(java.lang.String);
    Code:
       0: iconst_1
       1: istore_1
       2: aload_0
       3: invokevirtual #23                 // Method java/lang/String.length:()I
       6: istore_2
       7: iconst_0
       8: istore_3
       9: iload_3
      10: iload_2
      11: if_icmpge     48
      14: aload_0
      15: iload_3
      16: invokevirtual #24                 // Method java/lang/String.charAt:(I)C
      19: istore        4
      21: iload         4
      23: sipush        255
      26: if_icmple     33
      29: getstatic     #64                 // Field org/apache/james/mime4j/util/CharsetUtil.UTF_8:Ljava/nio/charset/Charset;
      32: areturn
      33: iload         4
      35: bipush        127
      37: if_icmple     42
      40: iconst_0
      41: istore_1
      42: iinc          3, 1
      45: goto          9
      48: iload_1
      49: ifeq          58
      52: getstatic     #65                 // Field org/apache/james/mime4j/util/CharsetUtil.US_ASCII:Ljava/nio/charset/Charset;
      55: goto          61
      58: getstatic     #66                 // Field org/apache/james/mime4j/util/CharsetUtil.ISO_8859_1:Ljava/nio/charset/Charset;
      61: areturn

  private static org.apache.james.mime4j.codec.EncoderUtil$Encoding determineEncoding(byte[], org.apache.james.mime4j.codec.EncoderUtil$Usage);
    Code:
       0: aload_0
       1: arraylength
       2: ifne          9
       5: getstatic     #67                 // Field org/apache/james/mime4j/codec/EncoderUtil$Encoding.Q:Lorg/apache/james/mime4j/codec/EncoderUtil$Encoding;
       8: areturn
       9: aload_1
      10: getstatic     #41                 // Field org/apache/james/mime4j/codec/EncoderUtil$Usage.TEXT_TOKEN:Lorg/apache/james/mime4j/codec/EncoderUtil$Usage;
      13: if_acmpne     22
      16: getstatic     #42                 // Field Q_REGULAR_CHARS:Ljava/util/BitSet;
      19: goto          25
      22: getstatic     #43                 // Field Q_RESTRICTED_CHARS:Ljava/util/BitSet;
      25: astore_2
      26: iconst_0
      27: istore_3
      28: iconst_0
      29: istore        4
      31: iload         4
      33: aload_0
      34: arraylength
      35: if_icmpge     73
      38: aload_0
      39: iload         4
      41: baload
      42: sipush        255
      45: iand
      46: istore        5
      48: iload         5
      50: bipush        32
      52: if_icmpeq     67
      55: aload_2
      56: iload         5
      58: invokevirtual #44                 // Method java/util/BitSet.get:(I)Z
      61: ifne          67
      64: iinc          3, 1
      67: iinc          4, 1
      70: goto          31
      73: iload_3
      74: bipush        100
      76: imul
      77: aload_0
      78: arraylength
      79: idiv
      80: istore        4
      82: iload         4
      84: bipush        30
      86: if_icmple     95
      89: getstatic     #33                 // Field org/apache/james/mime4j/codec/EncoderUtil$Encoding.B:Lorg/apache/james/mime4j/codec/EncoderUtil$Encoding;
      92: goto          98
      95: getstatic     #67                 // Field org/apache/james/mime4j/codec/EncoderUtil$Encoding.Q:Lorg/apache/james/mime4j/codec/EncoderUtil$Encoding;
      98: areturn

  private static char hexDigit(int);
    Code:
       0: iload_0
       1: bipush        10
       3: if_icmpge     14
       6: iload_0
       7: bipush        48
       9: iadd
      10: i2c
      11: goto          22
      14: iload_0
      15: bipush        10
      17: isub
      18: bipush        65
      20: iadd
      21: i2c
      22: ireturn

  static {};
    Code:
       0: getstatic     #68                 // Field org/apache/james/mime4j/codec/Base64OutputStream.BASE64_TABLE:[B
       3: putstatic     #39                 // Field BASE64_TABLE:[B
       6: ldc           #69                 // String =_?
       8: invokestatic  #70                 // Method initChars:(Ljava/lang/String;)Ljava/util/BitSet;
      11: putstatic     #42                 // Field Q_REGULAR_CHARS:Ljava/util/BitSet;
      14: ldc           #71                 // String =_?\"#$%&\'(),.:;<>@[\\]^`{|}~
      16: invokestatic  #70                 // Method initChars:(Ljava/lang/String;)Ljava/util/BitSet;
      19: putstatic     #43                 // Field Q_RESTRICTED_CHARS:Ljava/util/BitSet;
      22: ldc           #72                 // String ()<>@,;:\\\"/[]?=
      24: invokestatic  #70                 // Method initChars:(Ljava/lang/String;)Ljava/util/BitSet;
      27: putstatic     #46                 // Field TOKEN_CHARS:Ljava/util/BitSet;
      30: ldc           #73                 // String ()<>@.,;:\\\"[]
      32: invokestatic  #70                 // Method initChars:(Ljava/lang/String;)Ljava/util/BitSet;
      35: putstatic     #47                 // Field ATEXT_CHARS:Ljava/util/BitSet;
      38: return
}
