Compiled from "LabelSelector.java"
public class io.kubernetes.client.util.labels.LabelSelector implements io.kubernetes.client.fluent.Predicate<java.util.Map<java.lang.String, java.lang.String>> {
  private io.kubernetes.client.util.labels.LabelMatcher[] labelMatchers;

  io.kubernetes.client.util.labels.LabelSelector(io.kubernetes.client.util.labels.LabelMatcher...);
    Code:
       0: aload_0
       1: invokespecial #1                  // Method java/lang/Object."<init>":()V
       4: aload_0
       5: aload_1
       6: putfield      #2                  // Field labelMatchers:[Lio/kubernetes/client/util/labels/LabelMatcher;
       9: return

  public static io.kubernetes.client.util.labels.LabelSelector and(io.kubernetes.client.util.labels.LabelMatcher...);
    Code:
       0: new           #3                  // class io/kubernetes/client/util/labels/LabelSelector
       3: dup
       4: aload_0
       5: invokespecial #4                  // Method "<init>":([Lio/kubernetes/client/util/labels/LabelMatcher;)V
       8: areturn

  public static io.kubernetes.client.util.labels.LabelSelector empty();
    Code:
       0: iconst_0
       1: anewarray     #5                  // class io/kubernetes/client/util/labels/LabelMatcher
       4: invokestatic  #6                  // Method and:([Lio/kubernetes/client/util/labels/LabelMatcher;)Lio/kubernetes/client/util/labels/LabelSelector;
       7: areturn

  public java.lang.Boolean apply(java.util.Map<java.lang.String, java.lang.String>);
    Code:
       0: aload_0
       1: getfield      #2                  // Field labelMatchers:[Lio/kubernetes/client/util/labels/LabelMatcher;
       4: invokestatic  #7                  // Method java/util/Arrays.stream:([Ljava/lang/Object;)Ljava/util/stream/Stream;
       7: aload_1
       8: invokedynamic #8,  0              // InvokeDynamic #0:test:(Ljava/util/Map;)Ljava/util/function/Predicate;
      13: invokeinterface #9,  2            // InterfaceMethod java/util/stream/Stream.allMatch:(Ljava/util/function/Predicate;)Z
      18: invokestatic  #10                 // Method java/lang/Boolean.valueOf:(Z)Ljava/lang/Boolean;
      21: areturn

  public java.lang.String toString();
    Code:
       0: aload_0
       1: getfield      #2                  // Field labelMatchers:[Lio/kubernetes/client/util/labels/LabelMatcher;
       4: invokestatic  #7                  // Method java/util/Arrays.stream:([Ljava/lang/Object;)Ljava/util/stream/Stream;
       7: invokedynamic #11,  0             // InvokeDynamic #1:apply:()Ljava/util/function/Function;
      12: invokeinterface #12,  2           // InterfaceMethod java/util/stream/Stream.map:(Ljava/util/function/Function;)Ljava/util/stream/Stream;
      17: ldc           #13                 // String ,
      19: invokestatic  #14                 // Method java/util/stream/Collectors.joining:(Ljava/lang/CharSequence;)Ljava/util/stream/Collector;
      22: invokeinterface #15,  2           // InterfaceMethod java/util/stream/Stream.collect:(Ljava/util/stream/Collector;)Ljava/lang/Object;
      27: checkcast     #16                 // class java/lang/String
      30: areturn

  public java.lang.Boolean apply(java.lang.Object);
    Code:
       0: aload_0
       1: aload_1
       2: checkcast     #17                 // class java/util/Map
       5: invokevirtual #18                 // Method apply:(Ljava/util/Map;)Ljava/lang/Boolean;
       8: areturn

  private static java.lang.String lambda$toString$1(io.kubernetes.client.util.labels.LabelMatcher);
    Code:
       0: aload_0
       1: invokevirtual #19                 // Method java/lang/Object.toString:()Ljava/lang/String;
       4: areturn

  private static boolean lambda$apply$0(java.util.Map, io.kubernetes.client.util.labels.LabelMatcher);
    Code:
       0: aload_1
       1: aload_0
       2: aload_1
       3: invokeinterface #20,  1           // InterfaceMethod io/kubernetes/client/util/labels/LabelMatcher.getKey:()Ljava/lang/String;
       8: invokeinterface #21,  2           // InterfaceMethod java/util/Map.get:(Ljava/lang/Object;)Ljava/lang/Object;
      13: checkcast     #16                 // class java/lang/String
      16: invokeinterface #22,  2           // InterfaceMethod io/kubernetes/client/util/labels/LabelMatcher.test:(Ljava/lang/String;)Z
      21: ireturn
}
