Compiled from "EngineConfiguration.java"
public class org.thymeleaf.EngineConfiguration implements org.thymeleaf.IEngineConfiguration {
  private final org.thymeleaf.DialectSetConfiguration dialectSetConfiguration;

  private final java.util.Set<org.thymeleaf.templateresolver.ITemplateResolver> templateResolvers;

  private final java.util.Set<org.thymeleaf.messageresolver.IMessageResolver> messageResolvers;

  private final java.util.Set<org.thymeleaf.linkbuilder.ILinkBuilder> linkBuilders;

  private final org.thymeleaf.cache.ICacheManager cacheManager;

  private final org.thymeleaf.context.IEngineContextFactory engineContextFactory;

  private final org.thymeleaf.templateparser.markup.decoupled.IDecoupledTemplateLogicResolver decoupledTemplateLogicResolver;

  private org.thymeleaf.engine.TemplateManager templateManager;

  private final java.util.concurrent.ConcurrentHashMap<org.thymeleaf.templatemode.TemplateMode, org.thymeleaf.model.IModelFactory> modelFactories;

  org.thymeleaf.EngineConfiguration(java.util.Set<org.thymeleaf.templateresolver.ITemplateResolver>, java.util.Set<org.thymeleaf.messageresolver.IMessageResolver>, java.util.Set<org.thymeleaf.linkbuilder.ILinkBuilder>, java.util.Set<org.thymeleaf.DialectConfiguration>, org.thymeleaf.cache.ICacheManager, org.thymeleaf.context.IEngineContextFactory, org.thymeleaf.templateparser.markup.decoupled.IDecoupledTemplateLogicResolver);
    Code:
       0: aload_0
       1: invokespecial #2                  // Method java/lang/Object."<init>":()V
       4: aload_1
       5: ldc           #3                  // String Template Resolver set cannot be null
       7: invokestatic  #4                  // Method org/thymeleaf/util/Validate.notNull:(Ljava/lang/Object;Ljava/lang/String;)V
      10: aload_1
      11: invokeinterface #5,  1            // InterfaceMethod java/util/Set.size:()I
      16: ifle          23
      19: iconst_1
      20: goto          24
      23: iconst_0
      24: ldc           #6                  // String Template Resolver set cannot be empty
      26: invokestatic  #7                  // Method org/thymeleaf/util/Validate.isTrue:(ZLjava/lang/String;)V
      29: aload_1
      30: ldc           #8                  // String Template Resolver set cannot contain any nulls
      32: invokestatic  #9                  // Method org/thymeleaf/util/Validate.containsNoNulls:(Ljava/lang/Iterable;Ljava/lang/String;)V
      35: aload_2
      36: ldc           #10                 // String Message Resolver set cannot be null
      38: invokestatic  #4                  // Method org/thymeleaf/util/Validate.notNull:(Ljava/lang/Object;Ljava/lang/String;)V
      41: aload         4
      43: ldc           #11                 // String Dialect configuration set cannot be null
      45: invokestatic  #4                  // Method org/thymeleaf/util/Validate.notNull:(Ljava/lang/Object;Ljava/lang/String;)V
      48: aload         6
      50: ldc           #12                 // String Engine Context Factory cannot be null
      52: invokestatic  #4                  // Method org/thymeleaf/util/Validate.notNull:(Ljava/lang/Object;Ljava/lang/String;)V
      55: aload         7
      57: ldc           #13                 // String Decoupled Template Logic Resolver cannot be null
      59: invokestatic  #4                  // Method org/thymeleaf/util/Validate.notNull:(Ljava/lang/Object;Ljava/lang/String;)V
      62: new           #14                 // class java/util/ArrayList
      65: dup
      66: aload_1
      67: invokespecial #15                 // Method java/util/ArrayList."<init>":(Ljava/util/Collection;)V
      70: astore        8
      72: aload         8
      74: invokestatic  #16                 // Method org/thymeleaf/EngineConfiguration$TemplateResolverComparator.access$000:()Lorg/thymeleaf/EngineConfiguration$TemplateResolverComparator;
      77: invokestatic  #17                 // Method java/util/Collections.sort:(Ljava/util/List;Ljava/util/Comparator;)V
      80: aload_0
      81: new           #18                 // class java/util/LinkedHashSet
      84: dup
      85: aload         8
      87: invokespecial #19                 // Method java/util/LinkedHashSet."<init>":(Ljava/util/Collection;)V
      90: invokestatic  #20                 // Method java/util/Collections.unmodifiableSet:(Ljava/util/Set;)Ljava/util/Set;
      93: putfield      #21                 // Field templateResolvers:Ljava/util/Set;
      96: new           #14                 // class java/util/ArrayList
      99: dup
     100: aload_2
     101: invokespecial #15                 // Method java/util/ArrayList."<init>":(Ljava/util/Collection;)V
     104: astore        9
     106: aload         9
     108: invokestatic  #22                 // Method org/thymeleaf/EngineConfiguration$MessageResolverComparator.access$100:()Lorg/thymeleaf/EngineConfiguration$MessageResolverComparator;
     111: invokestatic  #17                 // Method java/util/Collections.sort:(Ljava/util/List;Ljava/util/Comparator;)V
     114: aload_0
     115: new           #18                 // class java/util/LinkedHashSet
     118: dup
     119: aload         9
     121: invokespecial #19                 // Method java/util/LinkedHashSet."<init>":(Ljava/util/Collection;)V
     124: invokestatic  #20                 // Method java/util/Collections.unmodifiableSet:(Ljava/util/Set;)Ljava/util/Set;
     127: putfield      #23                 // Field messageResolvers:Ljava/util/Set;
     130: new           #14                 // class java/util/ArrayList
     133: dup
     134: aload_3
     135: invokespecial #15                 // Method java/util/ArrayList."<init>":(Ljava/util/Collection;)V
     138: astore        10
     140: aload         10
     142: invokestatic  #24                 // Method org/thymeleaf/EngineConfiguration$LinkBuilderComparator.access$200:()Lorg/thymeleaf/EngineConfiguration$LinkBuilderComparator;
     145: invokestatic  #17                 // Method java/util/Collections.sort:(Ljava/util/List;Ljava/util/Comparator;)V
     148: aload_0
     149: new           #18                 // class java/util/LinkedHashSet
     152: dup
     153: aload         10
     155: invokespecial #19                 // Method java/util/LinkedHashSet."<init>":(Ljava/util/Collection;)V
     158: invokestatic  #20                 // Method java/util/Collections.unmodifiableSet:(Ljava/util/Set;)Ljava/util/Set;
     161: putfield      #25                 // Field linkBuilders:Ljava/util/Set;
     164: aload_0
     165: aload         5
     167: putfield      #26                 // Field cacheManager:Lorg/thymeleaf/cache/ICacheManager;
     170: aload_0
     171: aload         6
     173: putfield      #27                 // Field engineContextFactory:Lorg/thymeleaf/context/IEngineContextFactory;
     176: aload_0
     177: aload         7
     179: putfield      #28                 // Field decoupledTemplateLogicResolver:Lorg/thymeleaf/templateparser/markup/decoupled/IDecoupledTemplateLogicResolver;
     182: aload_0
     183: aload         4
     185: invokestatic  #29                 // Method org/thymeleaf/DialectSetConfiguration.build:(Ljava/util/Set;)Lorg/thymeleaf/DialectSetConfiguration;
     188: putfield      #30                 // Field dialectSetConfiguration:Lorg/thymeleaf/DialectSetConfiguration;
     191: aload_0
     192: new           #31                 // class java/util/concurrent/ConcurrentHashMap
     195: dup
     196: bipush        6
     198: fconst_1
     199: iconst_1
     200: invokespecial #32                 // Method java/util/concurrent/ConcurrentHashMap."<init>":(IFI)V
     203: putfield      #33                 // Field modelFactories:Ljava/util/concurrent/ConcurrentHashMap;
     206: return

  void initialize();
    Code:
       0: aload_0
       1: new           #34                 // class org/thymeleaf/engine/TemplateManager
       4: dup
       5: aload_0
       6: invokespecial #35                 // Method org/thymeleaf/engine/TemplateManager."<init>":(Lorg/thymeleaf/IEngineConfiguration;)V
       9: putfield      #36                 // Field templateManager:Lorg/thymeleaf/engine/TemplateManager;
      12: return

  public java.util.Set<org.thymeleaf.templateresolver.ITemplateResolver> getTemplateResolvers();
    Code:
       0: aload_0
       1: getfield      #21                 // Field templateResolvers:Ljava/util/Set;
       4: areturn

  public java.util.Set<org.thymeleaf.messageresolver.IMessageResolver> getMessageResolvers();
    Code:
       0: aload_0
       1: getfield      #23                 // Field messageResolvers:Ljava/util/Set;
       4: areturn

  public java.util.Set<org.thymeleaf.linkbuilder.ILinkBuilder> getLinkBuilders();
    Code:
       0: aload_0
       1: getfield      #25                 // Field linkBuilders:Ljava/util/Set;
       4: areturn

  public org.thymeleaf.cache.ICacheManager getCacheManager();
    Code:
       0: aload_0
       1: getfield      #26                 // Field cacheManager:Lorg/thymeleaf/cache/ICacheManager;
       4: areturn

  public org.thymeleaf.context.IEngineContextFactory getEngineContextFactory();
    Code:
       0: aload_0
       1: getfield      #27                 // Field engineContextFactory:Lorg/thymeleaf/context/IEngineContextFactory;
       4: areturn

  public org.thymeleaf.templateparser.markup.decoupled.IDecoupledTemplateLogicResolver getDecoupledTemplateLogicResolver();
    Code:
       0: aload_0
       1: getfield      #28                 // Field decoupledTemplateLogicResolver:Lorg/thymeleaf/templateparser/markup/decoupled/IDecoupledTemplateLogicResolver;
       4: areturn

  public java.util.Set<org.thymeleaf.DialectConfiguration> getDialectConfigurations();
    Code:
       0: aload_0
       1: getfield      #30                 // Field dialectSetConfiguration:Lorg/thymeleaf/DialectSetConfiguration;
       4: invokevirtual #37                 // Method org/thymeleaf/DialectSetConfiguration.getDialectConfigurations:()Ljava/util/Set;
       7: areturn

  public java.util.Set<org.thymeleaf.dialect.IDialect> getDialects();
    Code:
       0: aload_0
       1: getfield      #30                 // Field dialectSetConfiguration:Lorg/thymeleaf/DialectSetConfiguration;
       4: invokevirtual #38                 // Method org/thymeleaf/DialectSetConfiguration.getDialects:()Ljava/util/Set;
       7: areturn

  public boolean isStandardDialectPresent();
    Code:
       0: aload_0
       1: getfield      #30                 // Field dialectSetConfiguration:Lorg/thymeleaf/DialectSetConfiguration;
       4: invokevirtual #39                 // Method org/thymeleaf/DialectSetConfiguration.isStandardDialectPresent:()Z
       7: ireturn

  public java.lang.String getStandardDialectPrefix();
    Code:
       0: aload_0
       1: getfield      #30                 // Field dialectSetConfiguration:Lorg/thymeleaf/DialectSetConfiguration;
       4: invokevirtual #40                 // Method org/thymeleaf/DialectSetConfiguration.getStandardDialectPrefix:()Ljava/lang/String;
       7: areturn

  public org.thymeleaf.engine.ElementDefinitions getElementDefinitions();
    Code:
       0: aload_0
       1: getfield      #30                 // Field dialectSetConfiguration:Lorg/thymeleaf/DialectSetConfiguration;
       4: invokevirtual #41                 // Method org/thymeleaf/DialectSetConfiguration.getElementDefinitions:()Lorg/thymeleaf/engine/ElementDefinitions;
       7: areturn

  public org.thymeleaf.engine.AttributeDefinitions getAttributeDefinitions();
    Code:
       0: aload_0
       1: getfield      #30                 // Field dialectSetConfiguration:Lorg/thymeleaf/DialectSetConfiguration;
       4: invokevirtual #42                 // Method org/thymeleaf/DialectSetConfiguration.getAttributeDefinitions:()Lorg/thymeleaf/engine/AttributeDefinitions;
       7: areturn

  public java.util.Set<org.thymeleaf.processor.templateboundaries.ITemplateBoundariesProcessor> getTemplateBoundariesProcessors(org.thymeleaf.templatemode.TemplateMode);
    Code:
       0: aload_0
       1: getfield      #30                 // Field dialectSetConfiguration:Lorg/thymeleaf/DialectSetConfiguration;
       4: aload_1
       5: invokevirtual #43                 // Method org/thymeleaf/DialectSetConfiguration.getTemplateBoundariesProcessors:(Lorg/thymeleaf/templatemode/TemplateMode;)Ljava/util/Set;
       8: areturn

  public java.util.Set<org.thymeleaf.processor.cdatasection.ICDATASectionProcessor> getCDATASectionProcessors(org.thymeleaf.templatemode.TemplateMode);
    Code:
       0: aload_0
       1: getfield      #30                 // Field dialectSetConfiguration:Lorg/thymeleaf/DialectSetConfiguration;
       4: aload_1
       5: invokevirtual #44                 // Method org/thymeleaf/DialectSetConfiguration.getCDATASectionProcessors:(Lorg/thymeleaf/templatemode/TemplateMode;)Ljava/util/Set;
       8: areturn

  public java.util.Set<org.thymeleaf.processor.comment.ICommentProcessor> getCommentProcessors(org.thymeleaf.templatemode.TemplateMode);
    Code:
       0: aload_0
       1: getfield      #30                 // Field dialectSetConfiguration:Lorg/thymeleaf/DialectSetConfiguration;
       4: aload_1
       5: invokevirtual #45                 // Method org/thymeleaf/DialectSetConfiguration.getCommentProcessors:(Lorg/thymeleaf/templatemode/TemplateMode;)Ljava/util/Set;
       8: areturn

  public java.util.Set<org.thymeleaf.processor.doctype.IDocTypeProcessor> getDocTypeProcessors(org.thymeleaf.templatemode.TemplateMode);
    Code:
       0: aload_0
       1: getfield      #30                 // Field dialectSetConfiguration:Lorg/thymeleaf/DialectSetConfiguration;
       4: aload_1
       5: invokevirtual #46                 // Method org/thymeleaf/DialectSetConfiguration.getDocTypeProcessors:(Lorg/thymeleaf/templatemode/TemplateMode;)Ljava/util/Set;
       8: areturn

  public java.util.Set<org.thymeleaf.processor.element.IElementProcessor> getElementProcessors(org.thymeleaf.templatemode.TemplateMode);
    Code:
       0: aload_0
       1: getfield      #30                 // Field dialectSetConfiguration:Lorg/thymeleaf/DialectSetConfiguration;
       4: aload_1
       5: invokevirtual #47                 // Method org/thymeleaf/DialectSetConfiguration.getElementProcessors:(Lorg/thymeleaf/templatemode/TemplateMode;)Ljava/util/Set;
       8: areturn

  public java.util.Set<org.thymeleaf.processor.text.ITextProcessor> getTextProcessors(org.thymeleaf.templatemode.TemplateMode);
    Code:
       0: aload_0
       1: getfield      #30                 // Field dialectSetConfiguration:Lorg/thymeleaf/DialectSetConfiguration;
       4: aload_1
       5: invokevirtual #48                 // Method org/thymeleaf/DialectSetConfiguration.getTextProcessors:(Lorg/thymeleaf/templatemode/TemplateMode;)Ljava/util/Set;
       8: areturn

  public java.util.Set<org.thymeleaf.processor.processinginstruction.IProcessingInstructionProcessor> getProcessingInstructionProcessors(org.thymeleaf.templatemode.TemplateMode);
    Code:
       0: aload_0
       1: getfield      #30                 // Field dialectSetConfiguration:Lorg/thymeleaf/DialectSetConfiguration;
       4: aload_1
       5: invokevirtual #49                 // Method org/thymeleaf/DialectSetConfiguration.getProcessingInstructionProcessors:(Lorg/thymeleaf/templatemode/TemplateMode;)Ljava/util/Set;
       8: areturn

  public java.util.Set<org.thymeleaf.processor.xmldeclaration.IXMLDeclarationProcessor> getXMLDeclarationProcessors(org.thymeleaf.templatemode.TemplateMode);
    Code:
       0: aload_0
       1: getfield      #30                 // Field dialectSetConfiguration:Lorg/thymeleaf/DialectSetConfiguration;
       4: aload_1
       5: invokevirtual #50                 // Method org/thymeleaf/DialectSetConfiguration.getXMLDeclarationProcessors:(Lorg/thymeleaf/templatemode/TemplateMode;)Ljava/util/Set;
       8: areturn

  public java.util.Set<org.thymeleaf.preprocessor.IPreProcessor> getPreProcessors(org.thymeleaf.templatemode.TemplateMode);
    Code:
       0: aload_0
       1: getfield      #30                 // Field dialectSetConfiguration:Lorg/thymeleaf/DialectSetConfiguration;
       4: aload_1
       5: invokevirtual #51                 // Method org/thymeleaf/DialectSetConfiguration.getPreProcessors:(Lorg/thymeleaf/templatemode/TemplateMode;)Ljava/util/Set;
       8: areturn

  public java.util.Set<org.thymeleaf.postprocessor.IPostProcessor> getPostProcessors(org.thymeleaf.templatemode.TemplateMode);
    Code:
       0: aload_0
       1: getfield      #30                 // Field dialectSetConfiguration:Lorg/thymeleaf/DialectSetConfiguration;
       4: aload_1
       5: invokevirtual #52                 // Method org/thymeleaf/DialectSetConfiguration.getPostProcessors:(Lorg/thymeleaf/templatemode/TemplateMode;)Ljava/util/Set;
       8: areturn

  public java.util.Map<java.lang.String, java.lang.Object> getExecutionAttributes();
    Code:
       0: aload_0
       1: getfield      #30                 // Field dialectSetConfiguration:Lorg/thymeleaf/DialectSetConfiguration;
       4: invokevirtual #53                 // Method org/thymeleaf/DialectSetConfiguration.getExecutionAttributes:()Ljava/util/Map;
       7: areturn

  public org.thymeleaf.expression.IExpressionObjectFactory getExpressionObjectFactory();
    Code:
       0: aload_0
       1: getfield      #30                 // Field dialectSetConfiguration:Lorg/thymeleaf/DialectSetConfiguration;
       4: invokevirtual #54                 // Method org/thymeleaf/DialectSetConfiguration.getExpressionObjectFactory:()Lorg/thymeleaf/expression/IExpressionObjectFactory;
       7: areturn

  public org.thymeleaf.engine.TemplateManager getTemplateManager();
    Code:
       0: aload_0
       1: getfield      #36                 // Field templateManager:Lorg/thymeleaf/engine/TemplateManager;
       4: areturn

  public org.thymeleaf.model.IModelFactory getModelFactory(org.thymeleaf.templatemode.TemplateMode);
    Code:
       0: aload_0
       1: getfield      #33                 // Field modelFactories:Ljava/util/concurrent/ConcurrentHashMap;
       4: aload_1
       5: invokevirtual #55                 // Method java/util/concurrent/ConcurrentHashMap.containsKey:(Ljava/lang/Object;)Z
       8: ifeq          23
      11: aload_0
      12: getfield      #33                 // Field modelFactories:Ljava/util/concurrent/ConcurrentHashMap;
      15: aload_1
      16: invokevirtual #56                 // Method java/util/concurrent/ConcurrentHashMap.get:(Ljava/lang/Object;)Ljava/lang/Object;
      19: checkcast     #57                 // class org/thymeleaf/model/IModelFactory
      22: areturn
      23: new           #58                 // class org/thymeleaf/engine/StandardModelFactory
      26: dup
      27: aload_0
      28: aload_1
      29: invokespecial #59                 // Method org/thymeleaf/engine/StandardModelFactory."<init>":(Lorg/thymeleaf/IEngineConfiguration;Lorg/thymeleaf/templatemode/TemplateMode;)V
      32: astore_2
      33: aload_0
      34: getfield      #33                 // Field modelFactories:Ljava/util/concurrent/ConcurrentHashMap;
      37: aload_1
      38: aload_2
      39: invokevirtual #60                 // Method java/util/concurrent/ConcurrentHashMap.putIfAbsent:(Ljava/lang/Object;Ljava/lang/Object;)Ljava/lang/Object;
      42: pop
      43: aload_0
      44: getfield      #33                 // Field modelFactories:Ljava/util/concurrent/ConcurrentHashMap;
      47: aload_1
      48: invokevirtual #56                 // Method java/util/concurrent/ConcurrentHashMap.get:(Ljava/lang/Object;)Ljava/lang/Object;
      51: checkcast     #57                 // class org/thymeleaf/model/IModelFactory
      54: areturn

  public boolean isModelReshapeable(org.thymeleaf.templatemode.TemplateMode);
    Code:
       0: aload_0
       1: getfield      #30                 // Field dialectSetConfiguration:Lorg/thymeleaf/DialectSetConfiguration;
       4: invokevirtual #39                 // Method org/thymeleaf/DialectSetConfiguration.isStandardDialectPresent:()Z
       7: ifne          12
      10: iconst_0
      11: ireturn
      12: aload_0
      13: getfield      #30                 // Field dialectSetConfiguration:Lorg/thymeleaf/DialectSetConfiguration;
      16: aload_1
      17: invokevirtual #48                 // Method org/thymeleaf/DialectSetConfiguration.getTextProcessors:(Lorg/thymeleaf/templatemode/TemplateMode;)Ljava/util/Set;
      20: astore_2
      21: aload_2
      22: invokeinterface #5,  1            // InterfaceMethod java/util/Set.size:()I
      27: iconst_1
      28: if_icmple     33
      31: iconst_0
      32: ireturn
      33: aload_1
      34: invokevirtual #61                 // Method org/thymeleaf/templatemode/TemplateMode.isMarkup:()Z
      37: ifeq          95
      40: aload_0
      41: getfield      #30                 // Field dialectSetConfiguration:Lorg/thymeleaf/DialectSetConfiguration;
      44: aload_1
      45: invokevirtual #45                 // Method org/thymeleaf/DialectSetConfiguration.getCommentProcessors:(Lorg/thymeleaf/templatemode/TemplateMode;)Ljava/util/Set;
      48: astore_3
      49: aload_3
      50: invokeinterface #5,  1            // InterfaceMethod java/util/Set.size:()I
      55: aload_1
      56: getstatic     #62                 // Field org/thymeleaf/templatemode/TemplateMode.HTML:Lorg/thymeleaf/templatemode/TemplateMode;
      59: if_acmpne     66
      62: iconst_2
      63: goto          67
      66: iconst_1
      67: if_icmple     72
      70: iconst_0
      71: ireturn
      72: aload_0
      73: getfield      #30                 // Field dialectSetConfiguration:Lorg/thymeleaf/DialectSetConfiguration;
      76: aload_1
      77: invokevirtual #44                 // Method org/thymeleaf/DialectSetConfiguration.getCDATASectionProcessors:(Lorg/thymeleaf/templatemode/TemplateMode;)Ljava/util/Set;
      80: astore        4
      82: aload         4
      84: invokeinterface #5,  1            // InterfaceMethod java/util/Set.size:()I
      89: iconst_1
      90: if_icmple     95
      93: iconst_0
      94: ireturn
      95: aload_0
      96: getfield      #30                 // Field dialectSetConfiguration:Lorg/thymeleaf/DialectSetConfiguration;
      99: aload_1
     100: invokevirtual #51                 // Method org/thymeleaf/DialectSetConfiguration.getPreProcessors:(Lorg/thymeleaf/templatemode/TemplateMode;)Ljava/util/Set;
     103: invokeinterface #63,  1           // InterfaceMethod java/util/Set.isEmpty:()Z
     108: ifne          113
     111: iconst_0
     112: ireturn
     113: aload_0
     114: getfield      #30                 // Field dialectSetConfiguration:Lorg/thymeleaf/DialectSetConfiguration;
     117: aload_1
     118: invokevirtual #52                 // Method org/thymeleaf/DialectSetConfiguration.getPostProcessors:(Lorg/thymeleaf/templatemode/TemplateMode;)Ljava/util/Set;
     121: invokeinterface #63,  1           // InterfaceMethod java/util/Set.isEmpty:()Z
     126: ireturn

  private static int nullSafeIntegerComparison(java.lang.Integer, java.lang.Integer);
    Code:
       0: aload_0
       1: ifnull        20
       4: aload_1
       5: ifnull        16
       8: aload_0
       9: aload_1
      10: invokevirtual #64                 // Method java/lang/Integer.compareTo:(Ljava/lang/Integer;)I
      13: goto          29
      16: iconst_m1
      17: goto          29
      20: aload_1
      21: ifnull        28
      24: iconst_1
      25: goto          29
      28: iconst_0
      29: ireturn

  static int access$300(java.lang.Integer, java.lang.Integer);
    Code:
       0: aload_0
       1: aload_1
       2: invokestatic  #1                  // Method nullSafeIntegerComparison:(Ljava/lang/Integer;Ljava/lang/Integer;)I
       5: ireturn
}
