Compiled from "SimpleCacheKeysFactory.java"
public class org.hibernate.cache.internal.SimpleCacheKeysFactory implements org.hibernate.cache.spi.CacheKeysFactory {
  public static org.hibernate.cache.spi.CacheKeysFactory INSTANCE;

  public org.hibernate.cache.internal.SimpleCacheKeysFactory();
    Code:
       0: aload_0
       1: invokespecial #1                  // Method java/lang/Object."<init>":()V
       4: return

  public java.lang.Object createCollectionKey(java.lang.Object, org.hibernate.persister.collection.CollectionPersister, org.hibernate.engine.spi.SessionFactoryImplementor, java.lang.String);
    Code:
       0: aload_1
       1: areturn

  public java.lang.Object createEntityKey(java.lang.Object, org.hibernate.persister.entity.EntityPersister, org.hibernate.engine.spi.SessionFactoryImplementor, java.lang.String);
    Code:
       0: aload_1
       1: areturn

  public java.lang.Object createNaturalIdKey(java.lang.Object[], org.hibernate.persister.entity.EntityPersister, org.hibernate.engine.spi.SessionImplementor);
    Code:
       0: new           #2                  // class org/hibernate/cache/internal/OldNaturalIdCacheKey
       3: dup
       4: aload_1
       5: aload_2
       6: invokeinterface #3,  1            // InterfaceMethod org/hibernate/persister/entity/EntityPersister.getPropertyTypes:()[Lorg/hibernate/type/Type;
      11: aload_2
      12: invokeinterface #4,  1            // InterfaceMethod org/hibernate/persister/entity/EntityPersister.getNaturalIdentifierProperties:()[I
      17: aconst_null
      18: aload_3
      19: invokespecial #5                  // Method org/hibernate/cache/internal/OldNaturalIdCacheKey."<init>":([Ljava/lang/Object;[Lorg/hibernate/type/Type;[ILjava/lang/String;Lorg/hibernate/engine/spi/SessionImplementor;)V
      22: areturn

  public java.lang.Object getEntityId(java.lang.Object);
    Code:
       0: aload_1
       1: areturn

  public java.lang.Object getCollectionId(java.lang.Object);
    Code:
       0: aload_1
       1: areturn

  public java.lang.Object[] getNaturalIdValues(java.lang.Object);
    Code:
       0: aload_1
       1: checkcast     #2                  // class org/hibernate/cache/internal/OldNaturalIdCacheKey
       4: invokevirtual #6                  // Method org/hibernate/cache/internal/OldNaturalIdCacheKey.getNaturalIdValues:()[Ljava/io/Serializable;
       7: areturn

  static {};
    Code:
       0: new           #7                  // class org/hibernate/cache/internal/SimpleCacheKeysFactory
       3: dup
       4: invokespecial #8                  // Method "<init>":()V
       7: putstatic     #9                  // Field INSTANCE:Lorg/hibernate/cache/spi/CacheKeysFactory;
      10: return
}
