Compiled from "CSFile.java"
public class org.hl7.fhir.utilities.CSFile extends java.io.File {
  private static final long serialVersionUID;

  public org.hl7.fhir.utilities.CSFile(java.lang.String) throws java.io.IOException;
    Code:
       0: aload_0
       1: aload_1
       2: invokespecial #1                  // Method java/io/File."<init>":(Ljava/lang/String;)V
       5: aload_0
       6: invokevirtual #2                  // Method exists:()Z
       9: ifeq          71
      12: aload_0
      13: invokevirtual #3                  // Method getCanonicalFile:()Ljava/io/File;
      16: invokevirtual #4                  // Method java/io/File.getName:()Ljava/lang/String;
      19: aload_0
      20: invokevirtual #5                  // Method getName:()Ljava/lang/String;
      23: invokevirtual #6                  // Method java/lang/String.equals:(Ljava/lang/Object;)Z
      26: ifne          71
      29: new           #7                  // class java/lang/Error
      32: dup
      33: new           #8                  // class java/lang/StringBuilder
      36: dup
      37: invokespecial #9                  // Method java/lang/StringBuilder."<init>":()V
      40: ldc           #10                 // String Case mismatch of file
      42: invokevirtual #11                 // Method java/lang/StringBuilder.append:(Ljava/lang/String;)Ljava/lang/StringBuilder;
      45: aload_1
      46: invokevirtual #11                 // Method java/lang/StringBuilder.append:(Ljava/lang/String;)Ljava/lang/StringBuilder;
      49: ldc           #12                 // String : found
      51: invokevirtual #11                 // Method java/lang/StringBuilder.append:(Ljava/lang/String;)Ljava/lang/StringBuilder;
      54: aload_0
      55: invokevirtual #3                  // Method getCanonicalFile:()Ljava/io/File;
      58: invokevirtual #4                  // Method java/io/File.getName:()Ljava/lang/String;
      61: invokevirtual #11                 // Method java/lang/StringBuilder.append:(Ljava/lang/String;)Ljava/lang/StringBuilder;
      64: invokevirtual #13                 // Method java/lang/StringBuilder.toString:()Ljava/lang/String;
      67: invokespecial #14                 // Method java/lang/Error."<init>":(Ljava/lang/String;)V
      70: athrow
      71: return
}
