Compiled from "ZipURIResolver.java"
public class org.hl7.fhir.utilities.ZipURIResolver implements javax.xml.transform.URIResolver {
  private java.util.Map<java.lang.String, byte[]> files;

  public org.hl7.fhir.utilities.ZipURIResolver(java.util.Map<java.lang.String, byte[]>);
    Code:
       0: aload_0
       1: invokespecial #1                  // Method java/lang/Object."<init>":()V
       4: aload_0
       5: aload_1
       6: putfield      #2                  // Field files:Ljava/util/Map;
       9: return

  public javax.xml.transform.Source resolve(java.lang.String, java.lang.String) throws javax.xml.transform.TransformerException;
    Code:
       0: aload_0
       1: getfield      #2                  // Field files:Ljava/util/Map;
       4: aload_1
       5: invokeinterface #3,  2            // InterfaceMethod java/util/Map.get:(Ljava/lang/Object;)Ljava/lang/Object;
      10: checkcast     #4                  // class "[B"
      13: astore_3
      14: new           #5                  // class javax/xml/transform/stream/StreamSource
      17: dup
      18: new           #6                  // class java/io/ByteArrayInputStream
      21: dup
      22: aload_3
      23: invokespecial #7                  // Method java/io/ByteArrayInputStream."<init>":([B)V
      26: invokespecial #8                  // Method javax/xml/transform/stream/StreamSource."<init>":(Ljava/io/InputStream;)V
      29: areturn
      30: astore_3
      31: new           #10                 // class javax/xml/transform/TransformerException
      34: dup
      35: aload_3
      36: invokespecial #11                 // Method javax/xml/transform/TransformerException."<init>":(Ljava/lang/Throwable;)V
      39: athrow
    Exception table:
       from    to  target type
           0    29    30   Class java/lang/Exception
}
