Compiled from "auth.kt"
public abstract class net.mamoe.mirai.api.http.adapter.internal.dto.AuthedDTO implements net.mamoe.mirai.api.http.adapter.internal.dto.DTO {
  public static final net.mamoe.mirai.api.http.adapter.internal.dto.AuthedDTO$Companion Companion;

  private final java.lang.String sessionKey;

  public net.mamoe.mirai.api.http.context.session.Session session;

  private static final kotlin.Lazy<kotlinx.serialization.KSerializer<java.lang.Object>> $cachedSerializer$delegate;

  public net.mamoe.mirai.api.http.adapter.internal.dto.AuthedDTO();
    Code:
       0: aload_0
       1: invokespecial #10                 // Method java/lang/Object."<init>":()V
       4: aload_0
       5: ldc           #12                 // String SINGLE_SESSION
       7: putfield      #16                 // Field sessionKey:Ljava/lang/String;
      10: return

  public final java.lang.String getSessionKey();
    Code:
       0: aload_0
       1: getfield      #16                 // Field sessionKey:Ljava/lang/String;
       4: areturn

  public net.mamoe.mirai.api.http.context.session.Session getSession();
    Code:
       0: aload_0
       1: getfield      #27                 // Field session:Lnet/mamoe/mirai/api/http/context/session/Session;
       4: astore_1
       5: aload_1
       6: ifnull        11
       9: aload_1
      10: areturn
      11: ldc           #28                 // String session
      13: invokestatic  #34                 // Method kotlin/jvm/internal/Intrinsics.throwUninitializedPropertyAccessException:(Ljava/lang/String;)V
      16: aconst_null
      17: areturn

  public void setSession(net.mamoe.mirai.api.http.context.session.Session);
    Code:
       0: aload_1
       1: ldc           #40                 // String <set-?>
       3: invokestatic  #44                 // Method kotlin/jvm/internal/Intrinsics.checkNotNullParameter:(Ljava/lang/Object;Ljava/lang/String;)V
       6: aload_0
       7: aload_1
       8: putfield      #27                 // Field session:Lnet/mamoe/mirai/api/http/context/session/Session;
      11: return

  public static void getSession$annotations();
    Code:
       0: return

  public static final void write$Self(net.mamoe.mirai.api.http.adapter.internal.dto.AuthedDTO, kotlinx.serialization.encoding.CompositeEncoder, kotlinx.serialization.descriptors.SerialDescriptor);
    Code:
       0: aload_0
       1: ldc           #51                 // String self
       3: invokestatic  #44                 // Method kotlin/jvm/internal/Intrinsics.checkNotNullParameter:(Ljava/lang/Object;Ljava/lang/String;)V
       6: aload_1
       7: ldc           #53                 // String output
       9: invokestatic  #44                 // Method kotlin/jvm/internal/Intrinsics.checkNotNullParameter:(Ljava/lang/Object;Ljava/lang/String;)V
      12: aload_2
      13: ldc           #55                 // String serialDesc
      15: invokestatic  #44                 // Method kotlin/jvm/internal/Intrinsics.checkNotNullParameter:(Ljava/lang/Object;Ljava/lang/String;)V
      18: aload_1
      19: aload_2
      20: iconst_0
      21: invokeinterface #61,  3           // InterfaceMethod kotlinx/serialization/encoding/CompositeEncoder.shouldEncodeElementDefault:(Lkotlinx/serialization/descriptors/SerialDescriptor;I)Z
      26: ifeq          33
      29: iconst_1
      30: goto          50
      33: aload_0
      34: getfield      #16                 // Field sessionKey:Ljava/lang/String;
      37: ldc           #12                 // String SINGLE_SESSION
      39: invokestatic  #65                 // Method kotlin/jvm/internal/Intrinsics.areEqual:(Ljava/lang/Object;Ljava/lang/Object;)Z
      42: ifne          49
      45: iconst_1
      46: goto          50
      49: iconst_0
      50: ifeq          65
      53: aload_1
      54: aload_2
      55: iconst_0
      56: aload_0
      57: getfield      #16                 // Field sessionKey:Ljava/lang/String;
      60: invokeinterface #69,  4           // InterfaceMethod kotlinx/serialization/encoding/CompositeEncoder.encodeStringElement:(Lkotlinx/serialization/descriptors/SerialDescriptor;ILjava/lang/String;)V
      65: return

  public net.mamoe.mirai.api.http.adapter.internal.dto.AuthedDTO(int, java.lang.String, kotlinx.serialization.internal.SerializationConstructorMarker);
    Code:
       0: aload_0
       1: invokespecial #10                 // Method java/lang/Object."<init>":()V
       4: iload_1
       5: iconst_1
       6: iand
       7: ifne          19
      10: aload_0
      11: ldc           #12                 // String SINGLE_SESSION
      13: putfield      #16                 // Field sessionKey:Ljava/lang/String;
      16: goto          24
      19: aload_0
      20: aload_2
      21: putfield      #16                 // Field sessionKey:Ljava/lang/String;
      24: return

  public static final kotlin.Lazy access$get$cachedSerializer$delegate$cp();
    Code:
       0: getstatic     #97                 // Field $cachedSerializer$delegate:Lkotlin/Lazy;
       3: areturn

  static {};
    Code:
       0: new           #100                // class net/mamoe/mirai/api/http/adapter/internal/dto/AuthedDTO$Companion
       3: dup
       4: aconst_null
       5: invokespecial #103                // Method net/mamoe/mirai/api/http/adapter/internal/dto/AuthedDTO$Companion."<init>":(Lkotlin/jvm/internal/DefaultConstructorMarker;)V
       8: putstatic     #107                // Field Companion:Lnet/mamoe/mirai/api/http/adapter/internal/dto/AuthedDTO$Companion;
      11: getstatic     #113                // Field kotlin/LazyThreadSafetyMode.PUBLICATION:Lkotlin/LazyThreadSafetyMode;
      14: getstatic     #119                // Field net/mamoe/mirai/api/http/adapter/internal/dto/AuthedDTO$Companion$$cachedSerializer$delegate$1.INSTANCE:Lnet/mamoe/mirai/api/http/adapter/internal/dto/AuthedDTO$Companion$$cachedSerializer$delegate$1;
      17: checkcast     #121                // class kotlin/jvm/functions/Function0
      20: invokestatic  #127                // Method kotlin/LazyKt.lazy:(Lkotlin/LazyThreadSafetyMode;Lkotlin/jvm/functions/Function0;)Lkotlin/Lazy;
      23: putstatic     #97                 // Field $cachedSerializer$delegate:Lkotlin/Lazy;
      26: return
}
