Compiled from "event.kt"
public abstract class net.mamoe.mirai.api.http.adapter.internal.dto.BotEventDTO extends net.mamoe.mirai.api.http.adapter.internal.dto.EventDTO {
  public static final net.mamoe.mirai.api.http.adapter.internal.dto.BotEventDTO$Companion Companion;

  private static final kotlin.Lazy<kotlinx.serialization.KSerializer<java.lang.Object>> $cachedSerializer$delegate;

  private net.mamoe.mirai.api.http.adapter.internal.dto.BotEventDTO();
    Code:
       0: aload_0
       1: invokespecial #8                  // Method net/mamoe/mirai/api/http/adapter/internal/dto/EventDTO."<init>":()V
       4: return

  public static final void write$Self(net.mamoe.mirai.api.http.adapter.internal.dto.BotEventDTO, kotlinx.serialization.encoding.CompositeEncoder, kotlinx.serialization.descriptors.SerialDescriptor);
    Code:
       0: aload_0
       1: ldc           #16                 // String self
       3: invokestatic  #22                 // Method kotlin/jvm/internal/Intrinsics.checkNotNullParameter:(Ljava/lang/Object;Ljava/lang/String;)V
       6: aload_1
       7: ldc           #24                 // String output
       9: invokestatic  #22                 // Method kotlin/jvm/internal/Intrinsics.checkNotNullParameter:(Ljava/lang/Object;Ljava/lang/String;)V
      12: aload_2
      13: ldc           #26                 // String serialDesc
      15: invokestatic  #22                 // Method kotlin/jvm/internal/Intrinsics.checkNotNullParameter:(Ljava/lang/Object;Ljava/lang/String;)V
      18: aload_0
      19: checkcast     #4                  // class net/mamoe/mirai/api/http/adapter/internal/dto/EventDTO
      22: aload_1
      23: aload_2
      24: invokestatic  #29                 // Method net/mamoe/mirai/api/http/adapter/internal/dto/EventDTO.write$Self:(Lnet/mamoe/mirai/api/http/adapter/internal/dto/EventDTO;Lkotlinx/serialization/encoding/CompositeEncoder;Lkotlinx/serialization/descriptors/SerialDescriptor;)V
      27: return

  public net.mamoe.mirai.api.http.adapter.internal.dto.BotEventDTO(int, kotlinx.serialization.internal.SerializationConstructorMarker);
    Code:
       0: aload_0
       1: iload_1
       2: aload_2
       3: invokespecial #45                 // Method net/mamoe/mirai/api/http/adapter/internal/dto/EventDTO."<init>":(ILkotlinx/serialization/internal/SerializationConstructorMarker;)V
       6: return

  public net.mamoe.mirai.api.http.adapter.internal.dto.BotEventDTO(kotlin.jvm.internal.DefaultConstructorMarker);
    Code:
       0: aload_0
       1: invokespecial #51                 // Method "<init>":()V
       4: return

  public static final kotlin.Lazy access$get$cachedSerializer$delegate$cp();
    Code:
       0: getstatic     #59                 // Field $cachedSerializer$delegate:Lkotlin/Lazy;
       3: areturn

  static {};
    Code:
       0: new           #62                 // class net/mamoe/mirai/api/http/adapter/internal/dto/BotEventDTO$Companion
       3: dup
       4: aconst_null
       5: invokespecial #64                 // Method net/mamoe/mirai/api/http/adapter/internal/dto/BotEventDTO$Companion."<init>":(Lkotlin/jvm/internal/DefaultConstructorMarker;)V
       8: putstatic     #68                 // Field Companion:Lnet/mamoe/mirai/api/http/adapter/internal/dto/BotEventDTO$Companion;
      11: getstatic     #74                 // Field kotlin/LazyThreadSafetyMode.PUBLICATION:Lkotlin/LazyThreadSafetyMode;
      14: getstatic     #80                 // Field net/mamoe/mirai/api/http/adapter/internal/dto/BotEventDTO$Companion$$cachedSerializer$delegate$1.INSTANCE:Lnet/mamoe/mirai/api/http/adapter/internal/dto/BotEventDTO$Companion$$cachedSerializer$delegate$1;
      17: checkcast     #82                 // class kotlin/jvm/functions/Function0
      20: invokestatic  #88                 // Method kotlin/LazyKt.lazy:(Lkotlin/LazyThreadSafetyMode;Lkotlin/jvm/functions/Function0;)Lkotlin/Lazy;
      23: putstatic     #59                 // Field $cachedSerializer$delegate:Lkotlin/Lazy;
      26: return
}
