Compiled from "HashProbeTable.java"
class org.apache.jena.sparql.engine.join.HashProbeTable {
  long s_count;

  long s_bucketCount;

  long s_maxBucketSize;

  long s_noKeyBucketSize;

  long s_maxMatchGroup;

  long s_countScanMiss;

  private final java.util.List<org.apache.jena.sparql.engine.binding.Binding> noKeyBucket;

  private final org.apache.jena.ext.com.google.common.collect.Multimap<java.lang.Object, org.apache.jena.sparql.engine.binding.Binding> buckets;

  private final org.apache.jena.sparql.engine.join.JoinKey joinKey;

  org.apache.jena.sparql.engine.join.HashProbeTable(org.apache.jena.sparql.engine.join.JoinKey);
    Code:
       0: aload_0
       1: invokespecial #1                  // Method java/lang/Object."<init>":()V
       4: aload_0
       5: lconst_0
       6: putfield      #2                  // Field s_count:J
       9: aload_0
      10: lconst_0
      11: putfield      #3                  // Field s_bucketCount:J
      14: aload_0
      15: lconst_0
      16: putfield      #4                  // Field s_maxBucketSize:J
      19: aload_0
      20: lconst_0
      21: putfield      #5                  // Field s_noKeyBucketSize:J
      24: aload_0
      25: lconst_0
      26: putfield      #6                  // Field s_maxMatchGroup:J
      29: aload_0
      30: lconst_0
      31: putfield      #7                  // Field s_countScanMiss:J
      34: aload_0
      35: new           #8                  // class java/util/ArrayList
      38: dup
      39: invokespecial #9                  // Method java/util/ArrayList."<init>":()V
      42: putfield      #10                 // Field noKeyBucket:Ljava/util/List;
      45: aload_0
      46: aload_1
      47: putfield      #11                 // Field joinKey:Lorg/apache/jena/sparql/engine/join/JoinKey;
      50: aload_0
      51: invokestatic  #12                 // Method org/apache/jena/ext/com/google/common/collect/ArrayListMultimap.create:()Lorg/apache/jena/ext/com/google/common/collect/ArrayListMultimap;
      54: putfield      #13                 // Field buckets:Lorg/apache/jena/ext/com/google/common/collect/Multimap;
      57: return

  public void put(org.apache.jena.sparql.engine.binding.Binding);
    Code:
       0: aload_0
       1: dup
       2: getfield      #2                  // Field s_count:J
       5: lconst_1
       6: ladd
       7: putfield      #2                  // Field s_count:J
      10: aload_0
      11: getfield      #11                 // Field joinKey:Lorg/apache/jena/sparql/engine/join/JoinKey;
      14: aload_1
      15: invokestatic  #14                 // Method org/apache/jena/sparql/engine/join/JoinLib.hash:(Lorg/apache/jena/sparql/engine/join/JoinKey;Lorg/apache/jena/sparql/engine/binding/Binding;)Ljava/lang/Object;
      18: astore_2
      19: aload_2
      20: getstatic     #15                 // Field org/apache/jena/sparql/engine/join/JoinLib.noKeyHash:Ljava/lang/Object;
      23: if_acmpne     38
      26: aload_0
      27: getfield      #10                 // Field noKeyBucket:Ljava/util/List;
      30: aload_1
      31: invokeinterface #16,  2           // InterfaceMethod java/util/List.add:(Ljava/lang/Object;)Z
      36: pop
      37: return
      38: aload_0
      39: getfield      #13                 // Field buckets:Lorg/apache/jena/ext/com/google/common/collect/Multimap;
      42: aload_2
      43: aload_1
      44: invokeinterface #17,  3           // InterfaceMethod org/apache/jena/ext/com/google/common/collect/Multimap.put:(Ljava/lang/Object;Ljava/lang/Object;)Z
      49: pop
      50: return

  public java.util.Iterator<org.apache.jena.sparql.engine.binding.Binding> getCandidates(org.apache.jena.sparql.engine.binding.Binding);
    Code:
       0: aconst_null
       1: astore_2
       2: aload_0
       3: getfield      #11                 // Field joinKey:Lorg/apache/jena/sparql/engine/join/JoinKey;
       6: aload_1
       7: invokestatic  #14                 // Method org/apache/jena/sparql/engine/join/JoinLib.hash:(Lorg/apache/jena/sparql/engine/join/JoinKey;Lorg/apache/jena/sparql/engine/binding/Binding;)Ljava/lang/Object;
      10: astore_3
      11: aload_3
      12: getstatic     #15                 // Field org/apache/jena/sparql/engine/join/JoinLib.noKeyHash:Ljava/lang/Object;
      15: if_acmpne     36
      18: aload_0
      19: getfield      #13                 // Field buckets:Lorg/apache/jena/ext/com/google/common/collect/Multimap;
      22: invokeinterface #18,  1           // InterfaceMethod org/apache/jena/ext/com/google/common/collect/Multimap.values:()Ljava/util/Collection;
      27: invokeinterface #19,  1           // InterfaceMethod java/util/Collection.iterator:()Ljava/util/Iterator;
      32: astore_2
      33: goto          93
      36: aload_0
      37: getfield      #13                 // Field buckets:Lorg/apache/jena/ext/com/google/common/collect/Multimap;
      40: aload_3
      41: invokeinterface #20,  2           // InterfaceMethod org/apache/jena/ext/com/google/common/collect/Multimap.get:(Ljava/lang/Object;)Ljava/util/Collection;
      46: astore        4
      48: aload         4
      50: ifnull        83
      53: aload_0
      54: aload_0
      55: getfield      #6                  // Field s_maxMatchGroup:J
      58: aload         4
      60: invokeinterface #21,  1           // InterfaceMethod java/util/Collection.size:()I
      65: i2l
      66: invokestatic  #22                 // Method java/lang/Math.max:(JJ)J
      69: putfield      #6                  // Field s_maxMatchGroup:J
      72: aload         4
      74: invokeinterface #19,  1           // InterfaceMethod java/util/Collection.iterator:()Ljava/util/Iterator;
      79: astore_2
      80: goto          93
      83: aload_0
      84: dup
      85: getfield      #7                  // Field s_countScanMiss:J
      88: lconst_1
      89: ladd
      90: putfield      #7                  // Field s_countScanMiss:J
      93: aload_0
      94: getfield      #10                 // Field noKeyBucket:Ljava/util/List;
      97: ifnull        114
     100: aload_2
     101: aload_0
     102: getfield      #10                 // Field noKeyBucket:Ljava/util/List;
     105: invokeinterface #23,  1           // InterfaceMethod java/util/List.iterator:()Ljava/util/Iterator;
     110: invokestatic  #24                 // Method org/apache/jena/atlas/iterator/Iter.concat:(Ljava/util/Iterator;Ljava/util/Iterator;)Ljava/util/Iterator;
     113: astore_2
     114: aload_2
     115: areturn

  public void stats();
    Code:
       0: lconst_0
       1: lstore_1
       2: aload_0
       3: getfield      #13                 // Field buckets:Lorg/apache/jena/ext/com/google/common/collect/Multimap;
       6: invokeinterface #25,  1           // InterfaceMethod org/apache/jena/ext/com/google/common/collect/Multimap.keys:()Lorg/apache/jena/ext/com/google/common/collect/Multiset;
      11: invokeinterface #26,  1           // InterfaceMethod org/apache/jena/ext/com/google/common/collect/Multiset.iterator:()Ljava/util/Iterator;
      16: astore_3
      17: aload_3
      18: invokeinterface #27,  1           // InterfaceMethod java/util/Iterator.hasNext:()Z
      23: ifeq          63
      26: aload_3
      27: invokeinterface #28,  1           // InterfaceMethod java/util/Iterator.next:()Ljava/lang/Object;
      32: astore        4
      34: aload_0
      35: getfield      #13                 // Field buckets:Lorg/apache/jena/ext/com/google/common/collect/Multimap;
      38: aload         4
      40: invokeinterface #20,  2           // InterfaceMethod org/apache/jena/ext/com/google/common/collect/Multimap.get:(Ljava/lang/Object;)Ljava/util/Collection;
      45: invokeinterface #21,  1           // InterfaceMethod java/util/Collection.size:()I
      50: i2l
      51: lstore        5
      53: lload_1
      54: lload         5
      56: invokestatic  #22                 // Method java/lang/Math.max:(JJ)J
      59: lstore_1
      60: goto          17
      63: aload_0
      64: lload_1
      65: putfield      #4                  // Field s_maxBucketSize:J
      68: aload_0
      69: aload_0
      70: getfield      #13                 // Field buckets:Lorg/apache/jena/ext/com/google/common/collect/Multimap;
      73: invokeinterface #25,  1           // InterfaceMethod org/apache/jena/ext/com/google/common/collect/Multimap.keys:()Lorg/apache/jena/ext/com/google/common/collect/Multiset;
      78: invokeinterface #29,  1           // InterfaceMethod org/apache/jena/ext/com/google/common/collect/Multiset.size:()I
      83: i2l
      84: putfield      #3                  // Field s_bucketCount:J
      87: aload_0
      88: aload_0
      89: getfield      #10                 // Field noKeyBucket:Ljava/util/List;
      92: ifnonnull     99
      95: lconst_0
      96: goto          109
      99: aload_0
     100: getfield      #10                 // Field noKeyBucket:Ljava/util/List;
     103: invokeinterface #30,  1           // InterfaceMethod java/util/List.size:()I
     108: i2l
     109: putfield      #5                  // Field s_noKeyBucketSize:J
     112: return

  public java.util.Collection<org.apache.jena.sparql.engine.binding.Binding> getNoKey$();
    Code:
       0: aload_0
       1: getfield      #10                 // Field noKeyBucket:Ljava/util/List;
       4: ifnonnull     9
       7: aconst_null
       8: areturn
       9: aload_0
      10: getfield      #10                 // Field noKeyBucket:Ljava/util/List;
      13: areturn

  public java.util.Collection<org.apache.jena.sparql.engine.binding.Binding> getHashMatch$(org.apache.jena.sparql.engine.binding.Binding);
    Code:
       0: aload_0
       1: getfield      #11                 // Field joinKey:Lorg/apache/jena/sparql/engine/join/JoinKey;
       4: aload_1
       5: invokestatic  #14                 // Method org/apache/jena/sparql/engine/join/JoinLib.hash:(Lorg/apache/jena/sparql/engine/join/JoinKey;Lorg/apache/jena/sparql/engine/binding/Binding;)Ljava/lang/Object;
       8: astore_2
       9: aload_2
      10: getstatic     #15                 // Field org/apache/jena/sparql/engine/join/JoinLib.noKeyHash:Ljava/lang/Object;
      13: if_acmpne     21
      16: aload_0
      17: getfield      #10                 // Field noKeyBucket:Ljava/util/List;
      20: areturn
      21: aload_0
      22: getfield      #13                 // Field buckets:Lorg/apache/jena/ext/com/google/common/collect/Multimap;
      25: aload_2
      26: invokeinterface #20,  2           // InterfaceMethod org/apache/jena/ext/com/google/common/collect/Multimap.get:(Ljava/lang/Object;)Ljava/util/Collection;
      31: astore_3
      32: aload_3
      33: areturn

  public java.util.Iterator<org.apache.jena.sparql.engine.binding.Binding> values();
    Code:
       0: aload_0
       1: getfield      #13                 // Field buckets:Lorg/apache/jena/ext/com/google/common/collect/Multimap;
       4: invokeinterface #18,  1           // InterfaceMethod org/apache/jena/ext/com/google/common/collect/Multimap.values:()Ljava/util/Collection;
       9: invokeinterface #19,  1           // InterfaceMethod java/util/Collection.iterator:()Ljava/util/Iterator;
      14: aload_0
      15: getfield      #10                 // Field noKeyBucket:Ljava/util/List;
      18: invokeinterface #23,  1           // InterfaceMethod java/util/List.iterator:()Ljava/util/Iterator;
      23: invokestatic  #24                 // Method org/apache/jena/atlas/iterator/Iter.concat:(Ljava/util/Iterator;Ljava/util/Iterator;)Ljava/util/Iterator;
      26: areturn

  public void clear();
    Code:
       0: aload_0
       1: getfield      #13                 // Field buckets:Lorg/apache/jena/ext/com/google/common/collect/Multimap;
       4: invokeinterface #31,  1           // InterfaceMethod org/apache/jena/ext/com/google/common/collect/Multimap.clear:()V
       9: return
}
