Compiled from "ContentPackV1.java"
public abstract class org.graylog2.contentpacks.model.ContentPackV1 implements org.graylog2.contentpacks.model.ContentPack {
  static final java.lang.String VERSION;

  static final java.lang.String FIELD_NAME;

  static final java.lang.String FIELD_SUMMARY;

  static final java.lang.String FIELD_DESCRIPTION;

  static final java.lang.String FIELD_VENDOR;

  static final java.lang.String FIELD_URL;

  static final java.lang.String FIELD_PARAMETERS;

  static final java.lang.String FIELD_ENTITIES;

  static final java.lang.String FIELD_CREATED_AT;

  static final java.lang.String FIELD_SERVER_VERSION;

  static final java.lang.String FIELD_DB_ID;

  public org.graylog2.contentpacks.model.ContentPackV1();
    Code:
       0: aload_0
       1: invokespecial #1                  // Method java/lang/Object."<init>":()V
       4: return

  public abstract org.bson.types.ObjectId _id();

  public abstract java.lang.String name();

  public abstract java.lang.String summary();

  public abstract java.lang.String description();

  public abstract java.lang.String vendor();

  public abstract java.net.URI url();

  public abstract org.joda.time.DateTime createdAt();

  public abstract com.github.zafarkhaja.semver.Version serverVersion();

  public abstract com.google.common.collect.ImmutableSet<org.graylog2.contentpacks.model.parameters.Parameter> parameters();

  public abstract com.google.common.collect.ImmutableSet<org.graylog2.contentpacks.model.entities.Entity> entities();

  public static org.graylog2.contentpacks.model.ContentPackV1$Builder builder();
    Code:
       0: invokestatic  #2                  // Method org/graylog2/contentpacks/model/ContentPackV1$Builder.create:()Lorg/graylog2/contentpacks/model/ContentPackV1$Builder;
       3: areturn

  public java.util.Set<org.graylog2.contentpacks.model.constraints.Constraint> constraints();
    Code:
       0: aload_0
       1: invokevirtual #3                  // Method entities:()Lcom/google/common/collect/ImmutableSet;
       4: invokevirtual #4                  // Method com/google/common/collect/ImmutableSet.asList:()Lcom/google/common/collect/ImmutableList;
       7: invokevirtual #5                  // Method com/google/common/collect/ImmutableList.stream:()Ljava/util/stream/Stream;
      10: invokedynamic #6,  0              // InvokeDynamic #0:test:()Ljava/util/function/Predicate;
      15: invokeinterface #7,  2            // InterfaceMethod java/util/stream/Stream.filter:(Ljava/util/function/Predicate;)Ljava/util/stream/Stream;
      20: invokedynamic #8,  0              // InvokeDynamic #1:apply:()Ljava/util/function/Function;
      25: invokeinterface #9,  2            // InterfaceMethod java/util/stream/Stream.map:(Ljava/util/function/Function;)Ljava/util/stream/Stream;
      30: invokedynamic #10,  0             // InvokeDynamic #2:apply:()Ljava/util/function/Function;
      35: invokeinterface #9,  2            // InterfaceMethod java/util/stream/Stream.map:(Ljava/util/function/Function;)Ljava/util/stream/Stream;
      40: invokedynamic #11,  0             // InvokeDynamic #3:apply:()Ljava/util/function/Function;
      45: invokeinterface #12,  2           // InterfaceMethod java/util/stream/Stream.flatMap:(Ljava/util/function/Function;)Ljava/util/stream/Stream;
      50: invokestatic  #13                 // Method java/util/stream/Collectors.toSet:()Ljava/util/stream/Collector;
      53: invokeinterface #14,  2           // InterfaceMethod java/util/stream/Stream.collect:(Ljava/util/stream/Collector;)Ljava/lang/Object;
      58: checkcast     #15                 // class java/util/Set
      61: areturn

  private static org.graylog2.contentpacks.model.entities.EntityV1 lambda$constraints$1(org.graylog2.contentpacks.model.entities.Entity);
    Code:
       0: aload_0
       1: checkcast     #16                 // class org/graylog2/contentpacks/model/entities/EntityV1
       4: areturn

  private static boolean lambda$constraints$0(org.graylog2.contentpacks.model.entities.Entity);
    Code:
       0: aload_0
       1: instanceof    #16                 // class org/graylog2/contentpacks/model/entities/EntityV1
       4: ireturn
}
