Compiled from "ClassEditor.java"
public class org.jboss.common.beans.property.ClassEditor extends org.jboss.common.beans.property.PropertyEditorSupport<java.lang.Class> {
  public org.jboss.common.beans.property.ClassEditor();
    Code:
       0: aload_0
       1: ldc_w         #1                  // class java/lang/Class
       4: invokespecial #2                  // Method org/jboss/common/beans/property/PropertyEditorSupport."<init>":(Ljava/lang/Class;)V
       7: return

  public void setAsText(java.lang.String);
    Code:
       0: aload_1
       1: invokestatic  #3                  // Method org/jboss/common/beans/property/BeanUtils.isNull:(Ljava/lang/String;)Z
       4: ifeq          15
       7: aload_0
       8: aconst_null
       9: invokevirtual #4                  // Method setValue:(Ljava/lang/Object;)V
      12: goto          52
      15: invokestatic  #5                  // Method java/lang/Thread.currentThread:()Ljava/lang/Thread;
      18: invokevirtual #6                  // Method java/lang/Thread.getContextClassLoader:()Ljava/lang/ClassLoader;
      21: astore_2
      22: aload_2
      23: aload_1
      24: invokevirtual #7                  // Method java/lang/ClassLoader.loadClass:(Ljava/lang/String;)Ljava/lang/Class;
      27: astore_3
      28: aload_0
      29: aload_3
      30: invokevirtual #4                  // Method setValue:(Ljava/lang/Object;)V
      33: goto          52
      36: astore_2
      37: aload_2
      38: invokevirtual #9                  // Method java/lang/Exception.printStackTrace:()V
      41: new           #10                 // class java/lang/IllegalArgumentException
      44: dup
      45: ldc           #11                 // String Failed to parse to Class!
      47: aload_2
      48: invokespecial #12                 // Method java/lang/IllegalArgumentException."<init>":(Ljava/lang/String;Ljava/lang/Throwable;)V
      51: athrow
      52: return
    Exception table:
       from    to  target type
          15    33    36   Class java/lang/Exception

  public java.lang.String getAsText();
    Code:
       0: aload_0
       1: invokevirtual #13                 // Method getValue:()Ljava/lang/Object;
       4: checkcast     #1                  // class java/lang/Class
       7: astore_1
       8: aload_1
       9: ifnonnull     14
      12: aconst_null
      13: areturn
      14: aload_1
      15: invokevirtual #14                 // Method java/lang/Class.getName:()Ljava/lang/String;
      18: areturn
}
