Compiled from "DOMWriter.java"
public class org.jboss.common.beans.property.DOMWriter {
  private java.io.PrintWriter out;

  private boolean canonical;

  private boolean prettyprint;

  private boolean writeXMLDeclaration;

  private boolean ignoreWhitespace;

  private java.lang.String charsetName;

  private int prettyIndent;

  private boolean wroteXMLDeclaration;

  private org.w3c.dom.Node rootNode;

  private boolean completeNamespaces;

  private java.lang.String currentDefaultNamespace;

  public org.jboss.common.beans.property.DOMWriter(java.io.Writer);
    Code:
       0: aload_0
       1: invokespecial #1                  // Method java/lang/Object."<init>":()V
       4: aload_0
       5: iconst_1
       6: putfield      #2                  // Field completeNamespaces:Z
       9: aload_0
      10: new           #3                  // class java/io/PrintWriter
      13: dup
      14: aload_1
      15: invokespecial #4                  // Method java/io/PrintWriter."<init>":(Ljava/io/Writer;)V
      18: putfield      #5                  // Field out:Ljava/io/PrintWriter;
      21: return

  public org.jboss.common.beans.property.DOMWriter(java.io.Writer, java.lang.String);
    Code:
       0: aload_0
       1: invokespecial #1                  // Method java/lang/Object."<init>":()V
       4: aload_0
       5: iconst_1
       6: putfield      #2                  // Field completeNamespaces:Z
       9: aload_0
      10: new           #3                  // class java/io/PrintWriter
      13: dup
      14: aload_1
      15: invokespecial #4                  // Method java/io/PrintWriter."<init>":(Ljava/io/Writer;)V
      18: putfield      #5                  // Field out:Ljava/io/PrintWriter;
      21: aload_0
      22: aload_2
      23: putfield      #6                  // Field charsetName:Ljava/lang/String;
      26: aload_0
      27: iconst_1
      28: putfield      #7                  // Field writeXMLDeclaration:Z
      31: return

  public org.jboss.common.beans.property.DOMWriter(java.io.OutputStream);
    Code:
       0: aload_0
       1: invokespecial #1                  // Method java/lang/Object."<init>":()V
       4: aload_0
       5: iconst_1
       6: putfield      #2                  // Field completeNamespaces:Z
       9: aload_0
      10: new           #3                  // class java/io/PrintWriter
      13: dup
      14: new           #8                  // class java/io/OutputStreamWriter
      17: dup
      18: aload_1
      19: ldc           #9                  // String UTF-8
      21: invokespecial #10                 // Method java/io/OutputStreamWriter."<init>":(Ljava/io/OutputStream;Ljava/lang/String;)V
      24: invokespecial #4                  // Method java/io/PrintWriter."<init>":(Ljava/io/Writer;)V
      27: putfield      #5                  // Field out:Ljava/io/PrintWriter;
      30: goto          34
      33: astore_2
      34: return
    Exception table:
       from    to  target type
           9    30    33   Class java/io/UnsupportedEncodingException

  public org.jboss.common.beans.property.DOMWriter(java.io.OutputStream, java.lang.String);
    Code:
       0: aload_0
       1: invokespecial #1                  // Method java/lang/Object."<init>":()V
       4: aload_0
       5: iconst_1
       6: putfield      #2                  // Field completeNamespaces:Z
       9: aload_0
      10: new           #3                  // class java/io/PrintWriter
      13: dup
      14: new           #8                  // class java/io/OutputStreamWriter
      17: dup
      18: aload_1
      19: aload_2
      20: invokespecial #10                 // Method java/io/OutputStreamWriter."<init>":(Ljava/io/OutputStream;Ljava/lang/String;)V
      23: invokespecial #4                  // Method java/io/PrintWriter."<init>":(Ljava/io/Writer;)V
      26: putfield      #5                  // Field out:Ljava/io/PrintWriter;
      29: aload_0
      30: aload_2
      31: putfield      #6                  // Field charsetName:Ljava/lang/String;
      34: aload_0
      35: iconst_1
      36: putfield      #7                  // Field writeXMLDeclaration:Z
      39: goto          70
      42: astore_3
      43: new           #12                 // class java/lang/IllegalArgumentException
      46: dup
      47: new           #13                 // class java/lang/StringBuilder
      50: dup
      51: invokespecial #14                 // Method java/lang/StringBuilder."<init>":()V
      54: ldc           #15                 // String Unsupported encoding:
      56: invokevirtual #16                 // Method java/lang/StringBuilder.append:(Ljava/lang/String;)Ljava/lang/StringBuilder;
      59: aload_2
      60: invokevirtual #16                 // Method java/lang/StringBuilder.append:(Ljava/lang/String;)Ljava/lang/StringBuilder;
      63: invokevirtual #17                 // Method java/lang/StringBuilder.toString:()Ljava/lang/String;
      66: invokespecial #18                 // Method java/lang/IllegalArgumentException."<init>":(Ljava/lang/String;)V
      69: athrow
      70: return
    Exception table:
       from    to  target type
           9    39    42   Class java/io/UnsupportedEncodingException

  public static java.lang.String printNode(org.w3c.dom.Node, boolean);
    Code:
       0: new           #19                 // class java/io/StringWriter
       3: dup
       4: invokespecial #20                 // Method java/io/StringWriter."<init>":()V
       7: astore_2
       8: new           #21                 // class org/jboss/common/beans/property/DOMWriter
      11: dup
      12: aload_2
      13: invokespecial #22                 // Method "<init>":(Ljava/io/Writer;)V
      16: iload_1
      17: invokevirtual #23                 // Method setPrettyprint:(Z)Lorg/jboss/common/beans/property/DOMWriter;
      20: aload_0
      21: invokevirtual #24                 // Method print:(Lorg/w3c/dom/Node;)V
      24: aload_2
      25: invokevirtual #25                 // Method java/io/StringWriter.toString:()Ljava/lang/String;
      28: areturn

  public boolean isCanonical();
    Code:
       0: aload_0
       1: getfield      #26                 // Field canonical:Z
       4: ireturn

  public org.jboss.common.beans.property.DOMWriter setCanonical(boolean);
    Code:
       0: aload_0
       1: iload_1
       2: putfield      #26                 // Field canonical:Z
       5: aload_0
       6: areturn

  public boolean isIgnoreWhitespace();
    Code:
       0: aload_0
       1: getfield      #27                 // Field ignoreWhitespace:Z
       4: ireturn

  public org.jboss.common.beans.property.DOMWriter setIgnoreWhitespace(boolean);
    Code:
       0: aload_0
       1: iload_1
       2: putfield      #27                 // Field ignoreWhitespace:Z
       5: aload_0
       6: areturn

  public org.jboss.common.beans.property.DOMWriter setCompleteNamespaces(boolean);
    Code:
       0: aload_0
       1: iload_1
       2: putfield      #2                  // Field completeNamespaces:Z
       5: aload_0
       6: areturn

  public boolean isPrettyprint();
    Code:
       0: aload_0
       1: getfield      #28                 // Field prettyprint:Z
       4: ireturn

  public org.jboss.common.beans.property.DOMWriter setPrettyprint(boolean);
    Code:
       0: aload_0
       1: iload_1
       2: putfield      #28                 // Field prettyprint:Z
       5: aload_0
       6: areturn

  public boolean isWriteXMLDeclaration();
    Code:
       0: aload_0
       1: getfield      #7                  // Field writeXMLDeclaration:Z
       4: ireturn

  public org.jboss.common.beans.property.DOMWriter setWriteXMLDeclaration(boolean);
    Code:
       0: aload_0
       1: iload_1
       2: putfield      #7                  // Field writeXMLDeclaration:Z
       5: aload_0
       6: areturn

  public void print(org.w3c.dom.Node);
    Code:
       0: aload_0
       1: getfield      #28                 // Field prettyprint:Z
       4: ifeq          24
       7: aload_0
       8: getfield      #27                 // Field ignoreWhitespace:Z
      11: ifeq          24
      14: new           #29                 // class java/lang/IllegalStateException
      17: dup
      18: ldc           #30                 // String Cannot pretty print and ignore whitespace
      20: invokespecial #31                 // Method java/lang/IllegalStateException."<init>":(Ljava/lang/String;)V
      23: athrow
      24: aload_0
      25: aload_1
      26: putfield      #32                 // Field rootNode:Lorg/w3c/dom/Node;
      29: aload_0
      30: aload_1
      31: iconst_0
      32: invokespecial #33                 // Method printInternal:(Lorg/w3c/dom/Node;Z)V
      35: return

  private void printInternal(org.w3c.dom.Node, boolean);
    Code:
       0: aload_1
       1: ifnonnull     5
       4: return
       5: aload_0
       6: getfield      #34                 // Field wroteXMLDeclaration:Z
       9: ifne          105
      12: aload_0
      13: getfield      #7                  // Field writeXMLDeclaration:Z
      16: iconst_1
      17: if_icmpne     105
      20: aload_0
      21: getfield      #26                 // Field canonical:Z
      24: ifne          105
      27: aload_0
      28: getfield      #5                  // Field out:Ljava/io/PrintWriter;
      31: ldc           #35                 // String <?xml version=\'1.0\'
      33: invokevirtual #36                 // Method java/io/PrintWriter.print:(Ljava/lang/String;)V
      36: aload_0
      37: getfield      #6                  // Field charsetName:Ljava/lang/String;
      40: ifnull        77
      43: aload_0
      44: getfield      #5                  // Field out:Ljava/io/PrintWriter;
      47: new           #13                 // class java/lang/StringBuilder
      50: dup
      51: invokespecial #14                 // Method java/lang/StringBuilder."<init>":()V
      54: ldc           #37                 // String  encoding=\'
      56: invokevirtual #16                 // Method java/lang/StringBuilder.append:(Ljava/lang/String;)Ljava/lang/StringBuilder;
      59: aload_0
      60: getfield      #6                  // Field charsetName:Ljava/lang/String;
      63: invokevirtual #16                 // Method java/lang/StringBuilder.append:(Ljava/lang/String;)Ljava/lang/StringBuilder;
      66: ldc           #38                 // String \'
      68: invokevirtual #16                 // Method java/lang/StringBuilder.append:(Ljava/lang/String;)Ljava/lang/StringBuilder;
      71: invokevirtual #17                 // Method java/lang/StringBuilder.toString:()Ljava/lang/String;
      74: invokevirtual #36                 // Method java/io/PrintWriter.print:(Ljava/lang/String;)V
      77: aload_0
      78: getfield      #5                  // Field out:Ljava/io/PrintWriter;
      81: ldc           #39                 // String ?>
      83: invokevirtual #36                 // Method java/io/PrintWriter.print:(Ljava/lang/String;)V
      86: aload_0
      87: getfield      #28                 // Field prettyprint:Z
      90: ifeq          100
      93: aload_0
      94: getfield      #5                  // Field out:Ljava/io/PrintWriter;
      97: invokevirtual #40                 // Method java/io/PrintWriter.println:()V
     100: aload_0
     101: iconst_1
     102: putfield      #34                 // Field wroteXMLDeclaration:Z
     105: aload_1
     106: invokeinterface #41,  1           // InterfaceMethod org/w3c/dom/Node.getNodeType:()S
     111: istore_3
     112: aload_1
     113: invokeinterface #42,  1           // InterfaceMethod org/w3c/dom/Node.getChildNodes:()Lorg/w3c/dom/NodeList;
     118: invokeinterface #43,  1           // InterfaceMethod org/w3c/dom/NodeList.getLength:()I
     123: ifle          130
     126: iconst_1
     127: goto          131
     130: iconst_0
     131: istore        4
     133: aload_1
     134: invokeinterface #44,  1           // InterfaceMethod org/w3c/dom/Node.getNodeName:()Ljava/lang/String;
     139: astore        5
     141: iload_3
     142: tableswitch   { // 1 to 9
                     1: 245
                     2: 1312
                     3: 1093
                     4: 1029
                     5: 937
                     6: 1312
                     7: 1157
                     8: 1226
                     9: 192
               default: 1312
          }
     192: aload_1
     193: invokeinterface #42,  1           // InterfaceMethod org/w3c/dom/Node.getChildNodes:()Lorg/w3c/dom/NodeList;
     198: astore        6
     200: iconst_0
     201: istore        7
     203: iload         7
     205: aload         6
     207: invokeinterface #43,  1           // InterfaceMethod org/w3c/dom/NodeList.getLength:()I
     212: if_icmpge     235
     215: aload_0
     216: aload         6
     218: iload         7
     220: invokeinterface #45,  2           // InterfaceMethod org/w3c/dom/NodeList.item:(I)Lorg/w3c/dom/Node;
     225: iconst_0
     226: invokespecial #33                 // Method printInternal:(Lorg/w3c/dom/Node;Z)V
     229: iinc          7, 1
     232: goto          203
     235: aload_0
     236: getfield      #5                  // Field out:Ljava/io/PrintWriter;
     239: invokevirtual #46                 // Method java/io/PrintWriter.flush:()V
     242: goto          1312
     245: aload_1
     246: checkcast     #47                 // class org/w3c/dom/Element
     249: astore        6
     251: aload_0
     252: getfield      #28                 // Field prettyprint:Z
     255: ifeq          295
     258: iconst_0
     259: istore        7
     261: iload         7
     263: aload_0
     264: getfield      #48                 // Field prettyIndent:I
     267: if_icmpge     285
     270: aload_0
     271: getfield      #5                  // Field out:Ljava/io/PrintWriter;
     274: bipush        32
     276: invokevirtual #49                 // Method java/io/PrintWriter.print:(C)V
     279: iinc          7, 1
     282: goto          261
     285: aload_0
     286: dup
     287: getfield      #48                 // Field prettyIndent:I
     290: iconst_1
     291: iadd
     292: putfield      #48                 // Field prettyIndent:I
     295: aload_0
     296: getfield      #5                  // Field out:Ljava/io/PrintWriter;
     299: bipush        60
     301: invokevirtual #49                 // Method java/io/PrintWriter.print:(C)V
     304: aload_0
     305: getfield      #5                  // Field out:Ljava/io/PrintWriter;
     308: aload         5
     310: invokevirtual #36                 // Method java/io/PrintWriter.print:(Ljava/lang/String;)V
     313: new           #50                 // class java/util/HashMap
     316: dup
     317: invokespecial #51                 // Method java/util/HashMap."<init>":()V
     320: astore        7
     322: aload_1
     323: invokeinterface #52,  1           // InterfaceMethod org/w3c/dom/Node.getPrefix:()Ljava/lang/String;
     328: astore        8
     330: aload_1
     331: invokeinterface #53,  1           // InterfaceMethod org/w3c/dom/Node.getNamespaceURI:()Ljava/lang/String;
     336: astore        9
     338: aload         8
     340: ifnull        369
     343: aload_0
     344: aload         8
     346: aload         6
     348: aload_0
     349: getfield      #32                 // Field rootNode:Lorg/w3c/dom/Node;
     352: invokespecial #54                 // Method getNamespaceURI:(Ljava/lang/String;Lorg/w3c/dom/Element;Lorg/w3c/dom/Node;)Ljava/lang/String;
     355: astore        10
     357: aload         7
     359: aload         8
     361: aload         10
     363: invokeinterface #55,  3           // InterfaceMethod java/util/Map.put:(Ljava/lang/Object;Ljava/lang/Object;)Ljava/lang/Object;
     368: pop
     369: aload_0
     370: aload_1
     371: invokeinterface #56,  1           // InterfaceMethod org/w3c/dom/Node.getAttributes:()Lorg/w3c/dom/NamedNodeMap;
     376: invokespecial #57                 // Method sortAttributes:(Lorg/w3c/dom/NamedNodeMap;)[Lorg/w3c/dom/Attr;
     379: astore        10
     381: iconst_0
     382: istore        11
     384: iload         11
     386: aload         10
     388: arraylength
     389: if_icmpge     653
     392: aload         10
     394: iload         11
     396: aaload
     397: astore        12
     399: aload         12
     401: invokeinterface #58,  1           // InterfaceMethod org/w3c/dom/Attr.getPrefix:()Ljava/lang/String;
     406: astore        13
     408: aload         12
     410: invokeinterface #59,  1           // InterfaceMethod org/w3c/dom/Attr.getNodeName:()Ljava/lang/String;
     415: astore        14
     417: aload         12
     419: invokeinterface #60,  1           // InterfaceMethod org/w3c/dom/Attr.getNodeValue:()Ljava/lang/String;
     424: aload_0
     425: getfield      #26                 // Field canonical:Z
     428: invokestatic  #61                 // Method normalize:(Ljava/lang/String;Z)Ljava/lang/String;
     431: astore        15
     433: aload         14
     435: ldc           #62                 // String xmlns
     437: invokevirtual #63                 // Method java/lang/String.equals:(Ljava/lang/Object;)Z
     440: ifeq          449
     443: aload_0
     444: aload         15
     446: putfield      #64                 // Field currentDefaultNamespace:Ljava/lang/String;
     449: aload         13
     451: ifnull        605
     454: aload         13
     456: ldc           #62                 // String xmlns
     458: invokevirtual #63                 // Method java/lang/String.equals:(Ljava/lang/Object;)Z
     461: ifne          605
     464: aload         13
     466: ldc           #65                 // String xml
     468: invokevirtual #63                 // Method java/lang/String.equals:(Ljava/lang/Object;)Z
     471: ifne          605
     474: aload_0
     475: aload         13
     477: aload         6
     479: aload_0
     480: getfield      #32                 // Field rootNode:Lorg/w3c/dom/Node;
     483: invokespecial #54                 // Method getNamespaceURI:(Ljava/lang/String;Lorg/w3c/dom/Element;Lorg/w3c/dom/Node;)Ljava/lang/String;
     486: astore        16
     488: aload         7
     490: aload         13
     492: aload         16
     494: invokeinterface #55,  3           // InterfaceMethod java/util/Map.put:(Ljava/lang/Object;Ljava/lang/Object;)Ljava/lang/Object;
     499: pop
     500: aload         14
     502: new           #13                 // class java/lang/StringBuilder
     505: dup
     506: invokespecial #14                 // Method java/lang/StringBuilder."<init>":()V
     509: aload         13
     511: invokevirtual #16                 // Method java/lang/StringBuilder.append:(Ljava/lang/String;)Ljava/lang/StringBuilder;
     514: ldc           #66                 // String :type
     516: invokevirtual #16                 // Method java/lang/StringBuilder.append:(Ljava/lang/String;)Ljava/lang/StringBuilder;
     519: invokevirtual #17                 // Method java/lang/StringBuilder.toString:()Ljava/lang/String;
     522: invokevirtual #63                 // Method java/lang/String.equals:(Ljava/lang/Object;)Z
     525: ifeq          605
     528: aload         15
     530: ldc           #67                 // String :
     532: invokevirtual #68                 // Method java/lang/String.indexOf:(Ljava/lang/String;)I
     535: ifle          605
     538: aload         16
     540: ifnonnull     554
     543: aload_0
     544: aload         13
     546: aload         6
     548: aconst_null
     549: invokespecial #54                 // Method getNamespaceURI:(Ljava/lang/String;Lorg/w3c/dom/Element;Lorg/w3c/dom/Node;)Ljava/lang/String;
     552: astore        16
     554: ldc           #69                 // String http://www.w3.org/2001/XMLSchema-instance
     556: aload         16
     558: invokevirtual #63                 // Method java/lang/String.equals:(Ljava/lang/Object;)Z
     561: ifeq          605
     564: aload         15
     566: iconst_0
     567: aload         15
     569: ldc           #67                 // String :
     571: invokevirtual #68                 // Method java/lang/String.indexOf:(Ljava/lang/String;)I
     574: invokevirtual #70                 // Method java/lang/String.substring:(II)Ljava/lang/String;
     577: astore        17
     579: aload_0
     580: aload         17
     582: aload         6
     584: aload_0
     585: getfield      #32                 // Field rootNode:Lorg/w3c/dom/Node;
     588: invokespecial #54                 // Method getNamespaceURI:(Ljava/lang/String;Lorg/w3c/dom/Element;Lorg/w3c/dom/Node;)Ljava/lang/String;
     591: astore        18
     593: aload         7
     595: aload         17
     597: aload         18
     599: invokeinterface #55,  3           // InterfaceMethod java/util/Map.put:(Ljava/lang/Object;Ljava/lang/Object;)Ljava/lang/Object;
     604: pop
     605: aload_0
     606: getfield      #5                  // Field out:Ljava/io/PrintWriter;
     609: new           #13                 // class java/lang/StringBuilder
     612: dup
     613: invokespecial #14                 // Method java/lang/StringBuilder."<init>":()V
     616: ldc           #71                 // String
     618: invokevirtual #16                 // Method java/lang/StringBuilder.append:(Ljava/lang/String;)Ljava/lang/StringBuilder;
     621: aload         14
     623: invokevirtual #16                 // Method java/lang/StringBuilder.append:(Ljava/lang/String;)Ljava/lang/StringBuilder;
     626: ldc           #72                 // String =\'
     628: invokevirtual #16                 // Method java/lang/StringBuilder.append:(Ljava/lang/String;)Ljava/lang/StringBuilder;
     631: aload         15
     633: invokevirtual #16                 // Method java/lang/StringBuilder.append:(Ljava/lang/String;)Ljava/lang/StringBuilder;
     636: ldc           #38                 // String \'
     638: invokevirtual #16                 // Method java/lang/StringBuilder.append:(Ljava/lang/String;)Ljava/lang/StringBuilder;
     641: invokevirtual #17                 // Method java/lang/StringBuilder.toString:()Ljava/lang/String;
     644: invokevirtual #36                 // Method java/io/PrintWriter.print:(Ljava/lang/String;)V
     647: iinc          11, 1
     650: goto          384
     653: aload_0
     654: getfield      #2                  // Field completeNamespaces:Z
     657: ifeq          771
     660: aload         7
     662: invokeinterface #73,  1           // InterfaceMethod java/util/Map.keySet:()Ljava/util/Set;
     667: invokeinterface #74,  1           // InterfaceMethod java/util/Set.iterator:()Ljava/util/Iterator;
     672: astore        11
     674: aload         11
     676: invokeinterface #75,  1           // InterfaceMethod java/util/Iterator.hasNext:()Z
     681: ifeq          771
     684: aload         11
     686: invokeinterface #76,  1           // InterfaceMethod java/util/Iterator.next:()Ljava/lang/Object;
     691: checkcast     #77                 // class java/lang/String
     694: astore        12
     696: aload         7
     698: aload         12
     700: invokeinterface #78,  2           // InterfaceMethod java/util/Map.get:(Ljava/lang/Object;)Ljava/lang/Object;
     705: checkcast     #77                 // class java/lang/String
     708: astore        13
     710: aload         13
     712: ifnonnull     768
     715: aload_0
     716: aload         12
     718: aload         6
     720: aconst_null
     721: invokespecial #54                 // Method getNamespaceURI:(Ljava/lang/String;Lorg/w3c/dom/Element;Lorg/w3c/dom/Node;)Ljava/lang/String;
     724: astore        13
     726: aload_0
     727: getfield      #5                  // Field out:Ljava/io/PrintWriter;
     730: new           #13                 // class java/lang/StringBuilder
     733: dup
     734: invokespecial #14                 // Method java/lang/StringBuilder."<init>":()V
     737: ldc           #79                 // String  xmlns:
     739: invokevirtual #16                 // Method java/lang/StringBuilder.append:(Ljava/lang/String;)Ljava/lang/StringBuilder;
     742: aload         12
     744: invokevirtual #16                 // Method java/lang/StringBuilder.append:(Ljava/lang/String;)Ljava/lang/StringBuilder;
     747: ldc           #72                 // String =\'
     749: invokevirtual #16                 // Method java/lang/StringBuilder.append:(Ljava/lang/String;)Ljava/lang/StringBuilder;
     752: aload         13
     754: invokevirtual #16                 // Method java/lang/StringBuilder.append:(Ljava/lang/String;)Ljava/lang/StringBuilder;
     757: ldc           #38                 // String \'
     759: invokevirtual #16                 // Method java/lang/StringBuilder.append:(Ljava/lang/String;)Ljava/lang/StringBuilder;
     762: invokevirtual #17                 // Method java/lang/StringBuilder.toString:()Ljava/lang/String;
     765: invokevirtual #36                 // Method java/io/PrintWriter.print:(Ljava/lang/String;)V
     768: goto          674
     771: aload         8
     773: ifnonnull     850
     776: aload         9
     778: ifnull        850
     781: aload         6
     783: ldc           #62                 // String xmlns
     785: invokeinterface #80,  2           // InterfaceMethod org/w3c/dom/Element.getAttribute:(Ljava/lang/String;)Ljava/lang/String;
     790: astore        11
     792: aload         11
     794: invokevirtual #81                 // Method java/lang/String.length:()I
     797: ifne          850
     800: aload         9
     802: aload_0
     803: getfield      #64                 // Field currentDefaultNamespace:Ljava/lang/String;
     806: invokevirtual #63                 // Method java/lang/String.equals:(Ljava/lang/Object;)Z
     809: ifne          850
     812: aload_0
     813: getfield      #5                  // Field out:Ljava/io/PrintWriter;
     816: new           #13                 // class java/lang/StringBuilder
     819: dup
     820: invokespecial #14                 // Method java/lang/StringBuilder."<init>":()V
     823: ldc           #82                 // String  xmlns=\'
     825: invokevirtual #16                 // Method java/lang/StringBuilder.append:(Ljava/lang/String;)Ljava/lang/StringBuilder;
     828: aload         9
     830: invokevirtual #16                 // Method java/lang/StringBuilder.append:(Ljava/lang/String;)Ljava/lang/StringBuilder;
     833: ldc           #38                 // String \'
     835: invokevirtual #16                 // Method java/lang/StringBuilder.append:(Ljava/lang/String;)Ljava/lang/StringBuilder;
     838: invokevirtual #17                 // Method java/lang/StringBuilder.toString:()Ljava/lang/String;
     841: invokevirtual #36                 // Method java/io/PrintWriter.print:(Ljava/lang/String;)V
     844: aload_0
     845: aload         9
     847: putfield      #64                 // Field currentDefaultNamespace:Ljava/lang/String;
     850: iload         4
     852: ifeq          864
     855: aload_0
     856: getfield      #5                  // Field out:Ljava/io/PrintWriter;
     859: bipush        62
     861: invokevirtual #49                 // Method java/io/PrintWriter.print:(C)V
     864: aload_0
     865: aload_1
     866: invokespecial #83                 // Method isEndMarkerIndented:(Lorg/w3c/dom/Node;)Z
     869: istore_2
     870: iload_2
     871: ifeq          883
     874: aload_0
     875: getfield      #5                  // Field out:Ljava/io/PrintWriter;
     878: bipush        10
     880: invokevirtual #49                 // Method java/io/PrintWriter.print:(C)V
     883: aload_1
     884: invokeinterface #42,  1           // InterfaceMethod org/w3c/dom/Node.getChildNodes:()Lorg/w3c/dom/NodeList;
     889: astore        11
     891: aload         11
     893: invokeinterface #43,  1           // InterfaceMethod org/w3c/dom/NodeList.getLength:()I
     898: istore        12
     900: iconst_0
     901: istore        13
     903: iload         13
     905: iload         12
     907: if_icmpge     934
     910: aload         11
     912: iload         13
     914: invokeinterface #45,  2           // InterfaceMethod org/w3c/dom/NodeList.item:(I)Lorg/w3c/dom/Node;
     919: astore        14
     921: aload_0
     922: aload         14
     924: iconst_0
     925: invokespecial #33                 // Method printInternal:(Lorg/w3c/dom/Node;Z)V
     928: iinc          13, 1
     931: goto          903
     934: goto          1312
     937: aload_0
     938: getfield      #26                 // Field canonical:Z
     941: ifeq          999
     944: aload_1
     945: invokeinterface #42,  1           // InterfaceMethod org/w3c/dom/Node.getChildNodes:()Lorg/w3c/dom/NodeList;
     950: astore        6
     952: aload         6
     954: ifnull        996
     957: aload         6
     959: invokeinterface #43,  1           // InterfaceMethod org/w3c/dom/NodeList.getLength:()I
     964: istore        7
     966: iconst_0
     967: istore        8
     969: iload         8
     971: iload         7
     973: if_icmpge     996
     976: aload_0
     977: aload         6
     979: iload         8
     981: invokeinterface #45,  2           // InterfaceMethod org/w3c/dom/NodeList.item:(I)Lorg/w3c/dom/Node;
     986: iconst_0
     987: invokespecial #33                 // Method printInternal:(Lorg/w3c/dom/Node;Z)V
     990: iinc          8, 1
     993: goto          969
     996: goto          1312
     999: aload_0
    1000: getfield      #5                  // Field out:Ljava/io/PrintWriter;
    1003: bipush        38
    1005: invokevirtual #49                 // Method java/io/PrintWriter.print:(C)V
    1008: aload_0
    1009: getfield      #5                  // Field out:Ljava/io/PrintWriter;
    1012: aload         5
    1014: invokevirtual #36                 // Method java/io/PrintWriter.print:(Ljava/lang/String;)V
    1017: aload_0
    1018: getfield      #5                  // Field out:Ljava/io/PrintWriter;
    1021: bipush        59
    1023: invokevirtual #49                 // Method java/io/PrintWriter.print:(C)V
    1026: goto          1312
    1029: aload_0
    1030: getfield      #26                 // Field canonical:Z
    1033: ifeq          1059
    1036: aload_0
    1037: getfield      #5                  // Field out:Ljava/io/PrintWriter;
    1040: aload_1
    1041: invokeinterface #84,  1           // InterfaceMethod org/w3c/dom/Node.getNodeValue:()Ljava/lang/String;
    1046: aload_0
    1047: getfield      #26                 // Field canonical:Z
    1050: invokestatic  #61                 // Method normalize:(Ljava/lang/String;Z)Ljava/lang/String;
    1053: invokevirtual #36                 // Method java/io/PrintWriter.print:(Ljava/lang/String;)V
    1056: goto          1312
    1059: aload_0
    1060: getfield      #5                  // Field out:Ljava/io/PrintWriter;
    1063: ldc           #85                 // String <![CDATA[
    1065: invokevirtual #36                 // Method java/io/PrintWriter.print:(Ljava/lang/String;)V
    1068: aload_0
    1069: getfield      #5                  // Field out:Ljava/io/PrintWriter;
    1072: aload_1
    1073: invokeinterface #84,  1           // InterfaceMethod org/w3c/dom/Node.getNodeValue:()Ljava/lang/String;
    1078: invokevirtual #36                 // Method java/io/PrintWriter.print:(Ljava/lang/String;)V
    1081: aload_0
    1082: getfield      #5                  // Field out:Ljava/io/PrintWriter;
    1085: ldc           #86                 // String ]]>
    1087: invokevirtual #36                 // Method java/io/PrintWriter.print:(Ljava/lang/String;)V
    1090: goto          1312
    1093: aload_1
    1094: invokeinterface #84,  1           // InterfaceMethod org/w3c/dom/Node.getNodeValue:()Ljava/lang/String;
    1099: aload_0
    1100: getfield      #26                 // Field canonical:Z
    1103: invokestatic  #61                 // Method normalize:(Ljava/lang/String;Z)Ljava/lang/String;
    1106: astore        6
    1108: aload         6
    1110: invokevirtual #87                 // Method java/lang/String.trim:()Ljava/lang/String;
    1113: invokevirtual #81                 // Method java/lang/String.length:()I
    1116: ifle          1131
    1119: aload_0
    1120: getfield      #5                  // Field out:Ljava/io/PrintWriter;
    1123: aload         6
    1125: invokevirtual #36                 // Method java/io/PrintWriter.print:(Ljava/lang/String;)V
    1128: goto          1312
    1131: aload_0
    1132: getfield      #28                 // Field prettyprint:Z
    1135: ifne          1312
    1138: aload_0
    1139: getfield      #27                 // Field ignoreWhitespace:Z
    1142: ifne          1312
    1145: aload_0
    1146: getfield      #5                  // Field out:Ljava/io/PrintWriter;
    1149: aload         6
    1151: invokevirtual #36                 // Method java/io/PrintWriter.print:(Ljava/lang/String;)V
    1154: goto          1312
    1157: aload_0
    1158: getfield      #5                  // Field out:Ljava/io/PrintWriter;
    1161: ldc           #88                 // String <?
    1163: invokevirtual #36                 // Method java/io/PrintWriter.print:(Ljava/lang/String;)V
    1166: aload_0
    1167: getfield      #5                  // Field out:Ljava/io/PrintWriter;
    1170: aload         5
    1172: invokevirtual #36                 // Method java/io/PrintWriter.print:(Ljava/lang/String;)V
    1175: aload_1
    1176: invokeinterface #84,  1           // InterfaceMethod org/w3c/dom/Node.getNodeValue:()Ljava/lang/String;
    1181: astore        6
    1183: aload         6
    1185: ifnull        1214
    1188: aload         6
    1190: invokevirtual #81                 // Method java/lang/String.length:()I
    1193: ifle          1214
    1196: aload_0
    1197: getfield      #5                  // Field out:Ljava/io/PrintWriter;
    1200: bipush        32
    1202: invokevirtual #49                 // Method java/io/PrintWriter.print:(C)V
    1205: aload_0
    1206: getfield      #5                  // Field out:Ljava/io/PrintWriter;
    1209: aload         6
    1211: invokevirtual #36                 // Method java/io/PrintWriter.print:(Ljava/lang/String;)V
    1214: aload_0
    1215: getfield      #5                  // Field out:Ljava/io/PrintWriter;
    1218: ldc           #39                 // String ?>
    1220: invokevirtual #36                 // Method java/io/PrintWriter.print:(Ljava/lang/String;)V
    1223: goto          1312
    1226: iconst_0
    1227: istore        6
    1229: iload         6
    1231: aload_0
    1232: getfield      #48                 // Field prettyIndent:I
    1235: if_icmpge     1253
    1238: aload_0
    1239: getfield      #5                  // Field out:Ljava/io/PrintWriter;
    1242: bipush        32
    1244: invokevirtual #49                 // Method java/io/PrintWriter.print:(C)V
    1247: iinc          6, 1
    1250: goto          1229
    1253: aload_0
    1254: getfield      #5                  // Field out:Ljava/io/PrintWriter;
    1257: ldc           #89                 // String <!--
    1259: invokevirtual #36                 // Method java/io/PrintWriter.print:(Ljava/lang/String;)V
    1262: aload_1
    1263: invokeinterface #84,  1           // InterfaceMethod org/w3c/dom/Node.getNodeValue:()Ljava/lang/String;
    1268: astore        6
    1270: aload         6
    1272: ifnull        1284
    1275: aload_0
    1276: getfield      #5                  // Field out:Ljava/io/PrintWriter;
    1279: aload         6
    1281: invokevirtual #36                 // Method java/io/PrintWriter.print:(Ljava/lang/String;)V
    1284: aload_0
    1285: getfield      #5                  // Field out:Ljava/io/PrintWriter;
    1288: ldc           #90                 // String -->
    1290: invokevirtual #36                 // Method java/io/PrintWriter.print:(Ljava/lang/String;)V
    1293: aload_0
    1294: getfield      #28                 // Field prettyprint:Z
    1297: ifeq          1312
    1300: aload_0
    1301: getfield      #5                  // Field out:Ljava/io/PrintWriter;
    1304: bipush        10
    1306: invokevirtual #49                 // Method java/io/PrintWriter.print:(C)V
    1309: goto          1312
    1312: iload_3
    1313: iconst_1
    1314: if_icmpne     1425
    1317: aload_0
    1318: getfield      #28                 // Field prettyprint:Z
    1321: ifeq          1334
    1324: aload_0
    1325: dup
    1326: getfield      #48                 // Field prettyIndent:I
    1329: iconst_1
    1330: isub
    1331: putfield      #48                 // Field prettyIndent:I
    1334: iload         4
    1336: ifne          1351
    1339: aload_0
    1340: getfield      #5                  // Field out:Ljava/io/PrintWriter;
    1343: ldc           #91                 // String />
    1345: invokevirtual #36                 // Method java/io/PrintWriter.print:(Ljava/lang/String;)V
    1348: goto          1409
    1351: iload_2
    1352: ifeq          1382
    1355: iconst_0
    1356: istore        6
    1358: iload         6
    1360: aload_0
    1361: getfield      #48                 // Field prettyIndent:I
    1364: if_icmpge     1382
    1367: aload_0
    1368: getfield      #5                  // Field out:Ljava/io/PrintWriter;
    1371: bipush        32
    1373: invokevirtual #49                 // Method java/io/PrintWriter.print:(C)V
    1376: iinc          6, 1
    1379: goto          1358
    1382: aload_0
    1383: getfield      #5                  // Field out:Ljava/io/PrintWriter;
    1386: ldc           #92                 // String </
    1388: invokevirtual #36                 // Method java/io/PrintWriter.print:(Ljava/lang/String;)V
    1391: aload_0
    1392: getfield      #5                  // Field out:Ljava/io/PrintWriter;
    1395: aload         5
    1397: invokevirtual #36                 // Method java/io/PrintWriter.print:(Ljava/lang/String;)V
    1400: aload_0
    1401: getfield      #5                  // Field out:Ljava/io/PrintWriter;
    1404: bipush        62
    1406: invokevirtual #49                 // Method java/io/PrintWriter.print:(C)V
    1409: aload_0
    1410: getfield      #48                 // Field prettyIndent:I
    1413: ifle          1425
    1416: aload_0
    1417: getfield      #5                  // Field out:Ljava/io/PrintWriter;
    1420: bipush        10
    1422: invokevirtual #49                 // Method java/io/PrintWriter.print:(C)V
    1425: aload_0
    1426: getfield      #5                  // Field out:Ljava/io/PrintWriter;
    1429: invokevirtual #46                 // Method java/io/PrintWriter.flush:()V
    1432: return

  private java.lang.String getNamespaceURI(java.lang.String, org.w3c.dom.Element, org.w3c.dom.Node);
    Code:
       0: aload_2
       1: invokeinterface #93,  1           // InterfaceMethod org/w3c/dom/Element.getParentNode:()Lorg/w3c/dom/Node;
       6: astore        4
       8: aload_2
       9: new           #13                 // class java/lang/StringBuilder
      12: dup
      13: invokespecial #14                 // Method java/lang/StringBuilder."<init>":()V
      16: ldc           #94                 // String xmlns:
      18: invokevirtual #16                 // Method java/lang/StringBuilder.append:(Ljava/lang/String;)Ljava/lang/StringBuilder;
      21: aload_1
      22: invokevirtual #16                 // Method java/lang/StringBuilder.append:(Ljava/lang/String;)Ljava/lang/StringBuilder;
      25: invokevirtual #17                 // Method java/lang/StringBuilder.toString:()Ljava/lang/String;
      28: invokeinterface #80,  2           // InterfaceMethod org/w3c/dom/Element.getAttribute:(Ljava/lang/String;)Ljava/lang/String;
      33: astore        5
      35: aload         5
      37: invokevirtual #81                 // Method java/lang/String.length:()I
      40: ifne          68
      43: aload_2
      44: aload_3
      45: if_acmpeq     68
      48: aload         4
      50: instanceof    #47                 // class org/w3c/dom/Element
      53: ifeq          68
      56: aload_0
      57: aload_1
      58: aload         4
      60: checkcast     #47                 // class org/w3c/dom/Element
      63: aload_3
      64: invokespecial #54                 // Method getNamespaceURI:(Ljava/lang/String;Lorg/w3c/dom/Element;Lorg/w3c/dom/Node;)Ljava/lang/String;
      67: areturn
      68: aload         5
      70: invokevirtual #81                 // Method java/lang/String.length:()I
      73: ifle          81
      76: aload         5
      78: goto          82
      81: aconst_null
      82: areturn

  private boolean isEndMarkerIndented(org.w3c.dom.Node);
    Code:
       0: aload_0
       1: getfield      #28                 // Field prettyprint:Z
       4: ifeq          59
       7: aload_1
       8: invokeinterface #42,  1           // InterfaceMethod org/w3c/dom/Node.getChildNodes:()Lorg/w3c/dom/NodeList;
      13: astore_2
      14: aload_2
      15: invokeinterface #43,  1           // InterfaceMethod org/w3c/dom/NodeList.getLength:()I
      20: istore_3
      21: iconst_0
      22: istore        4
      24: iload         4
      26: iload_3
      27: if_icmpge     59
      30: aload_2
      31: iload         4
      33: invokeinterface #45,  2           // InterfaceMethod org/w3c/dom/NodeList.item:(I)Lorg/w3c/dom/Node;
      38: astore        5
      40: aload         5
      42: invokeinterface #41,  1           // InterfaceMethod org/w3c/dom/Node.getNodeType:()S
      47: iconst_1
      48: if_icmpne     53
      51: iconst_1
      52: ireturn
      53: iinc          4, 1
      56: goto          24
      59: iconst_0
      60: ireturn

  private org.w3c.dom.Attr[] sortAttributes(org.w3c.dom.NamedNodeMap);
    Code:
       0: aload_1
       1: ifnull        13
       4: aload_1
       5: invokeinterface #95,  1           // InterfaceMethod org/w3c/dom/NamedNodeMap.getLength:()I
      10: goto          14
      13: iconst_0
      14: istore_2
      15: iload_2
      16: anewarray     #96                 // class org/w3c/dom/Attr
      19: astore_3
      20: iconst_0
      21: istore        4
      23: iload         4
      25: iload_2
      26: if_icmpge     50
      29: aload_3
      30: iload         4
      32: aload_1
      33: iload         4
      35: invokeinterface #97,  2           // InterfaceMethod org/w3c/dom/NamedNodeMap.item:(I)Lorg/w3c/dom/Node;
      40: checkcast     #96                 // class org/w3c/dom/Attr
      43: aastore
      44: iinc          4, 1
      47: goto          23
      50: iconst_0
      51: istore        4
      53: iload         4
      55: iload_2
      56: iconst_1
      57: isub
      58: if_icmpge     156
      61: aload_3
      62: iload         4
      64: aaload
      65: invokeinterface #59,  1           // InterfaceMethod org/w3c/dom/Attr.getNodeName:()Ljava/lang/String;
      70: astore        5
      72: iload         4
      74: istore        6
      76: iload         4
      78: iconst_1
      79: iadd
      80: istore        7
      82: iload         7
      84: iload_2
      85: if_icmpge     123
      88: aload_3
      89: iload         7
      91: aaload
      92: invokeinterface #59,  1           // InterfaceMethod org/w3c/dom/Attr.getNodeName:()Ljava/lang/String;
      97: astore        8
      99: aload         8
     101: aload         5
     103: invokevirtual #98                 // Method java/lang/String.compareTo:(Ljava/lang/String;)I
     106: ifge          117
     109: aload         8
     111: astore        5
     113: iload         7
     115: istore        6
     117: iinc          7, 1
     120: goto          82
     123: iload         6
     125: iload         4
     127: if_icmpeq     150
     130: aload_3
     131: iload         4
     133: aaload
     134: astore        7
     136: aload_3
     137: iload         4
     139: aload_3
     140: iload         6
     142: aaload
     143: aastore
     144: aload_3
     145: iload         6
     147: aload         7
     149: aastore
     150: iinc          4, 1
     153: goto          53
     156: aload_3
     157: areturn

  public static java.lang.String normalize(java.lang.String, boolean);
    Code:
       0: new           #99                 // class java/lang/StringBuffer
       3: dup
       4: invokespecial #100                // Method java/lang/StringBuffer."<init>":()V
       7: astore_2
       8: aload_0
       9: ifnull        19
      12: aload_0
      13: invokevirtual #81                 // Method java/lang/String.length:()I
      16: goto          20
      19: iconst_0
      20: istore_3
      21: iconst_0
      22: istore        4
      24: iload         4
      26: iload_3
      27: if_icmpge     202
      30: aload_0
      31: iload         4
      33: invokevirtual #101                // Method java/lang/String.charAt:(I)C
      36: istore        5
      38: iload         5
      40: lookupswitch  { // 7
                    10: 158
                    13: 158
                    34: 138
                    38: 128
                    39: 148
                    60: 108
                    62: 118
               default: 189
          }
     108: aload_2
     109: ldc           #102                // String &lt;
     111: invokevirtual #103                // Method java/lang/StringBuffer.append:(Ljava/lang/String;)Ljava/lang/StringBuffer;
     114: pop
     115: goto          196
     118: aload_2
     119: ldc           #104                // String &gt;
     121: invokevirtual #103                // Method java/lang/StringBuffer.append:(Ljava/lang/String;)Ljava/lang/StringBuffer;
     124: pop
     125: goto          196
     128: aload_2
     129: ldc           #105                // String &amp;
     131: invokevirtual #103                // Method java/lang/StringBuffer.append:(Ljava/lang/String;)Ljava/lang/StringBuffer;
     134: pop
     135: goto          196
     138: aload_2
     139: ldc           #106                // String &quot;
     141: invokevirtual #103                // Method java/lang/StringBuffer.append:(Ljava/lang/String;)Ljava/lang/StringBuffer;
     144: pop
     145: goto          196
     148: aload_2
     149: ldc           #107                // String &apos;
     151: invokevirtual #103                // Method java/lang/StringBuffer.append:(Ljava/lang/String;)Ljava/lang/StringBuffer;
     154: pop
     155: goto          196
     158: iload_1
     159: ifeq          189
     162: aload_2
     163: ldc           #108                // String &#
     165: invokevirtual #103                // Method java/lang/StringBuffer.append:(Ljava/lang/String;)Ljava/lang/StringBuffer;
     168: pop
     169: aload_2
     170: iload         5
     172: invokestatic  #109                // Method java/lang/Integer.toString:(I)Ljava/lang/String;
     175: invokevirtual #103                // Method java/lang/StringBuffer.append:(Ljava/lang/String;)Ljava/lang/StringBuffer;
     178: pop
     179: aload_2
     180: bipush        59
     182: invokevirtual #110                // Method java/lang/StringBuffer.append:(C)Ljava/lang/StringBuffer;
     185: pop
     186: goto          196
     189: aload_2
     190: iload         5
     192: invokevirtual #110                // Method java/lang/StringBuffer.append:(C)Ljava/lang/StringBuffer;
     195: pop
     196: iinc          4, 1
     199: goto          24
     202: aload_2
     203: invokevirtual #111                // Method java/lang/StringBuffer.toString:()Ljava/lang/String;
     206: areturn
}
