Compiled from "ElementEditor.java"
public class org.jboss.common.beans.property.ElementEditor extends org.jboss.common.beans.property.XMLEditorSupport<org.w3c.dom.Element> {
  public org.jboss.common.beans.property.ElementEditor();
    Code:
       0: aload_0
       1: ldc_w         #1                  // class org/w3c/dom/Element
       4: invokespecial #2                  // Method org/jboss/common/beans/property/XMLEditorSupport."<init>":(Ljava/lang/Class;)V
       7: return

  public void setAsText(java.lang.String);
    Code:
       0: aload_1
       1: invokestatic  #3                  // Method org/jboss/common/beans/property/BeanUtils.isNull:(Ljava/lang/String;)Z
       4: ifeq          13
       7: aload_0
       8: aconst_null
       9: invokevirtual #4                  // Method setValue:(Ljava/lang/Object;)V
      12: return
      13: aload_0
      14: aload_0
      15: aload_1
      16: invokevirtual #5                  // Method getAsDocument:(Ljava/lang/String;)Lorg/w3c/dom/Document;
      19: invokeinterface #6,  1            // InterfaceMethod org/w3c/dom/Document.getDocumentElement:()Lorg/w3c/dom/Element;
      24: invokevirtual #4                  // Method setValue:(Ljava/lang/Object;)V
      27: return
}
