Compiled from "NoneTlsKeyManagersProvider.java"
public final class software.amazon.awssdk.internal.http.NoneTlsKeyManagersProvider implements software.amazon.awssdk.http.TlsKeyManagersProvider {
  private static final software.amazon.awssdk.internal.http.NoneTlsKeyManagersProvider INSTANCE;

  private software.amazon.awssdk.internal.http.NoneTlsKeyManagersProvider();
    Code:
       0: aload_0
       1: invokespecial #1                  // Method java/lang/Object."<init>":()V
       4: return

  public javax.net.ssl.KeyManager[] keyManagers();
    Code:
       0: aconst_null
       1: areturn

  public static software.amazon.awssdk.internal.http.NoneTlsKeyManagersProvider getInstance();
    Code:
       0: getstatic     #2                  // Field INSTANCE:Lsoftware/amazon/awssdk/internal/http/NoneTlsKeyManagersProvider;
       3: areturn

  static {};
    Code:
       0: new           #3                  // class software/amazon/awssdk/internal/http/NoneTlsKeyManagersProvider
       3: dup
       4: invokespecial #4                  // Method "<init>":()V
       7: putstatic     #2                  // Field INSTANCE:Lsoftware/amazon/awssdk/internal/http/NoneTlsKeyManagersProvider;
      10: return
}
