Compiled from "SAAJUtils.java"
public final class org.apache.cxf.binding.soap.saaj.SAAJUtils {
  private org.apache.cxf.binding.soap.saaj.SAAJUtils();
    Code:
       0: aload_0
       1: invokespecial #1                  // Method java/lang/Object."<init>":()V
       4: return

  public static javax.xml.soap.SOAPHeader getHeader(javax.xml.soap.SOAPMessage) throws javax.xml.soap.SOAPException;
    Code:
       0: aload_0
       1: invokevirtual #2                  // Method javax/xml/soap/SOAPMessage.getSOAPHeader:()Ljavax/xml/soap/SOAPHeader;
       4: areturn
       5: astore_1
       6: aload_0
       7: invokevirtual #4                  // Method javax/xml/soap/SOAPMessage.getSOAPPart:()Ljavax/xml/soap/SOAPPart;
      10: invokevirtual #5                  // Method javax/xml/soap/SOAPPart.getEnvelope:()Ljavax/xml/soap/SOAPEnvelope;
      13: invokeinterface #6,  1            // InterfaceMethod javax/xml/soap/SOAPEnvelope.getHeader:()Ljavax/xml/soap/SOAPHeader;
      18: areturn
    Exception table:
       from    to  target type
           0     4     5   Class java/lang/UnsupportedOperationException

  public static javax.xml.soap.SOAPBody getBody(javax.xml.soap.SOAPMessage) throws javax.xml.soap.SOAPException;
    Code:
       0: aload_0
       1: invokevirtual #7                  // Method javax/xml/soap/SOAPMessage.getSOAPBody:()Ljavax/xml/soap/SOAPBody;
       4: areturn
       5: astore_1
       6: aload_0
       7: invokevirtual #4                  // Method javax/xml/soap/SOAPMessage.getSOAPPart:()Ljavax/xml/soap/SOAPPart;
      10: invokevirtual #5                  // Method javax/xml/soap/SOAPPart.getEnvelope:()Ljavax/xml/soap/SOAPEnvelope;
      13: invokeinterface #8,  1            // InterfaceMethod javax/xml/soap/SOAPEnvelope.getBody:()Ljavax/xml/soap/SOAPBody;
      18: areturn
    Exception table:
       from    to  target type
           0     4     5   Class java/lang/UnsupportedOperationException

  public static void setFaultCode(javax.xml.soap.SOAPFault, javax.xml.namespace.QName) throws javax.xml.soap.SOAPException;
    Code:
       0: aload_0
       1: aload_1
       2: invokeinterface #9,  2            // InterfaceMethod javax/xml/soap/SOAPFault.setFaultCode:(Ljavax/xml/namespace/QName;)V
       7: goto          104
      10: astore_2
      11: iconst_1
      12: istore_3
      13: ldc           #11                 // String fc1
      15: astore        4
      17: aload_0
      18: aload         4
      20: invokeinterface #12,  2           // InterfaceMethod javax/xml/soap/SOAPFault.getNamespaceURI:(Ljava/lang/String;)Ljava/lang/String;
      25: invokestatic  #13                 // Method org/apache/cxf/common/util/StringUtils.isEmpty:(Ljava/lang/String;)Z
      28: ifne          58
      31: iinc          3, 1
      34: new           #14                 // class java/lang/StringBuilder
      37: dup
      38: invokespecial #15                 // Method java/lang/StringBuilder."<init>":()V
      41: ldc           #16                 // String fc
      43: invokevirtual #17                 // Method java/lang/StringBuilder.append:(Ljava/lang/String;)Ljava/lang/StringBuilder;
      46: iload_3
      47: invokevirtual #18                 // Method java/lang/StringBuilder.append:(I)Ljava/lang/StringBuilder;
      50: invokevirtual #19                 // Method java/lang/StringBuilder.toString:()Ljava/lang/String;
      53: astore        4
      55: goto          17
      58: aload_0
      59: aload         4
      61: aload_1
      62: invokevirtual #20                 // Method javax/xml/namespace/QName.getNamespaceURI:()Ljava/lang/String;
      65: invokeinterface #21,  3           // InterfaceMethod javax/xml/soap/SOAPFault.addNamespaceDeclaration:(Ljava/lang/String;Ljava/lang/String;)Ljavax/xml/soap/SOAPElement;
      70: pop
      71: aload_0
      72: new           #14                 // class java/lang/StringBuilder
      75: dup
      76: invokespecial #15                 // Method java/lang/StringBuilder."<init>":()V
      79: aload         4
      81: invokevirtual #17                 // Method java/lang/StringBuilder.append:(Ljava/lang/String;)Ljava/lang/StringBuilder;
      84: ldc           #22                 // String :
      86: invokevirtual #17                 // Method java/lang/StringBuilder.append:(Ljava/lang/String;)Ljava/lang/StringBuilder;
      89: aload_1
      90: invokevirtual #23                 // Method javax/xml/namespace/QName.getLocalPart:()Ljava/lang/String;
      93: invokevirtual #17                 // Method java/lang/StringBuilder.append:(Ljava/lang/String;)Ljava/lang/StringBuilder;
      96: invokevirtual #19                 // Method java/lang/StringBuilder.toString:()Ljava/lang/String;
      99: invokeinterface #24,  2           // InterfaceMethod javax/xml/soap/SOAPFault.setFaultCode:(Ljava/lang/String;)V
     104: return
    Exception table:
       from    to  target type
           0     7    10   Class java/lang/Throwable
}
