Compiled from "DescribeFileSystemPolicyResponse.java"
final class software.amazon.awssdk.services.efs.model.DescribeFileSystemPolicyResponse$BuilderImpl extends software.amazon.awssdk.services.efs.model.EfsResponse$BuilderImpl implements software.amazon.awssdk.services.efs.model.DescribeFileSystemPolicyResponse$Builder {
  private java.lang.String fileSystemId;

  private java.lang.String policy;

  private software.amazon.awssdk.services.efs.model.DescribeFileSystemPolicyResponse$BuilderImpl();
    Code:
       0: aload_0
       1: invokespecial #5                  // Method software/amazon/awssdk/services/efs/model/EfsResponse$BuilderImpl."<init>":()V
       4: return

  private software.amazon.awssdk.services.efs.model.DescribeFileSystemPolicyResponse$BuilderImpl(software.amazon.awssdk.services.efs.model.DescribeFileSystemPolicyResponse);
    Code:
       0: aload_0
       1: aload_1
       2: invokespecial #6                  // Method software/amazon/awssdk/services/efs/model/EfsResponse$BuilderImpl."<init>":(Lsoftware/amazon/awssdk/services/efs/model/EfsResponse;)V
       5: aload_0
       6: aload_1
       7: invokestatic  #7                  // Method software/amazon/awssdk/services/efs/model/DescribeFileSystemPolicyResponse.access$400:(Lsoftware/amazon/awssdk/services/efs/model/DescribeFileSystemPolicyResponse;)Ljava/lang/String;
      10: invokevirtual #8                  // Method fileSystemId:(Ljava/lang/String;)Lsoftware/amazon/awssdk/services/efs/model/DescribeFileSystemPolicyResponse$Builder;
      13: pop
      14: aload_0
      15: aload_1
      16: invokestatic  #9                  // Method software/amazon/awssdk/services/efs/model/DescribeFileSystemPolicyResponse.access$500:(Lsoftware/amazon/awssdk/services/efs/model/DescribeFileSystemPolicyResponse;)Ljava/lang/String;
      19: invokevirtual #10                 // Method policy:(Ljava/lang/String;)Lsoftware/amazon/awssdk/services/efs/model/DescribeFileSystemPolicyResponse$Builder;
      22: pop
      23: return

  public final java.lang.String getFileSystemId();
    Code:
       0: aload_0
       1: getfield      #4                  // Field fileSystemId:Ljava/lang/String;
       4: areturn

  public final void setFileSystemId(java.lang.String);
    Code:
       0: aload_0
       1: aload_1
       2: putfield      #4                  // Field fileSystemId:Ljava/lang/String;
       5: return

  public final software.amazon.awssdk.services.efs.model.DescribeFileSystemPolicyResponse$Builder fileSystemId(java.lang.String);
    Code:
       0: aload_0
       1: aload_1
       2: putfield      #4                  // Field fileSystemId:Ljava/lang/String;
       5: aload_0
       6: areturn

  public final java.lang.String getPolicy();
    Code:
       0: aload_0
       1: getfield      #3                  // Field policy:Ljava/lang/String;
       4: areturn

  public final void setPolicy(java.lang.String);
    Code:
       0: aload_0
       1: aload_1
       2: putfield      #3                  // Field policy:Ljava/lang/String;
       5: return

  public final software.amazon.awssdk.services.efs.model.DescribeFileSystemPolicyResponse$Builder policy(java.lang.String);
    Code:
       0: aload_0
       1: aload_1
       2: putfield      #3                  // Field policy:Ljava/lang/String;
       5: aload_0
       6: areturn

  public software.amazon.awssdk.services.efs.model.DescribeFileSystemPolicyResponse build();
    Code:
       0: new           #11                 // class software/amazon/awssdk/services/efs/model/DescribeFileSystemPolicyResponse
       3: dup
       4: aload_0
       5: aconst_null
       6: invokespecial #12                 // Method software/amazon/awssdk/services/efs/model/DescribeFileSystemPolicyResponse."<init>":(Lsoftware/amazon/awssdk/services/efs/model/DescribeFileSystemPolicyResponse$BuilderImpl;Lsoftware/amazon/awssdk/services/efs/model/DescribeFileSystemPolicyResponse$1;)V
       9: areturn

  public java.util.List<software.amazon.awssdk.core.SdkField<?>> sdkFields();
    Code:
       0: invokestatic  #13                 // Method software/amazon/awssdk/services/efs/model/DescribeFileSystemPolicyResponse.access$700:()Ljava/util/List;
       3: areturn

  public software.amazon.awssdk.services.efs.model.EfsResponse build();
    Code:
       0: aload_0
       1: invokevirtual #14                 // Method build:()Lsoftware/amazon/awssdk/services/efs/model/DescribeFileSystemPolicyResponse;
       4: areturn

  public software.amazon.awssdk.awscore.AwsResponse build();
    Code:
       0: aload_0
       1: invokevirtual #14                 // Method build:()Lsoftware/amazon/awssdk/services/efs/model/DescribeFileSystemPolicyResponse;
       4: areturn

  public software.amazon.awssdk.core.SdkResponse build();
    Code:
       0: aload_0
       1: invokevirtual #14                 // Method build:()Lsoftware/amazon/awssdk/services/efs/model/DescribeFileSystemPolicyResponse;
       4: areturn

  public java.lang.Object build();
    Code:
       0: aload_0
       1: invokevirtual #14                 // Method build:()Lsoftware/amazon/awssdk/services/efs/model/DescribeFileSystemPolicyResponse;
       4: areturn

  static java.lang.String access$000(software.amazon.awssdk.services.efs.model.DescribeFileSystemPolicyResponse$BuilderImpl);
    Code:
       0: aload_0
       1: getfield      #4                  // Field fileSystemId:Ljava/lang/String;
       4: areturn

  static java.lang.String access$100(software.amazon.awssdk.services.efs.model.DescribeFileSystemPolicyResponse$BuilderImpl);
    Code:
       0: aload_0
       1: getfield      #3                  // Field policy:Ljava/lang/String;
       4: areturn

  software.amazon.awssdk.services.efs.model.DescribeFileSystemPolicyResponse$BuilderImpl(software.amazon.awssdk.services.efs.model.DescribeFileSystemPolicyResponse, software.amazon.awssdk.services.efs.model.DescribeFileSystemPolicyResponse$1);
    Code:
       0: aload_0
       1: aload_1
       2: invokespecial #2                  // Method "<init>":(Lsoftware/amazon/awssdk/services/efs/model/DescribeFileSystemPolicyResponse;)V
       5: return

  software.amazon.awssdk.services.efs.model.DescribeFileSystemPolicyResponse$BuilderImpl(software.amazon.awssdk.services.efs.model.DescribeFileSystemPolicyResponse$1);
    Code:
       0: aload_0
       1: invokespecial #1                  // Method "<init>":()V
       4: return
}
