Compiled from "FileSystemDescription.java"
public interface software.amazon.awssdk.services.efs.model.FileSystemDescription$Builder extends software.amazon.awssdk.core.SdkPojo, software.amazon.awssdk.utils.builder.CopyableBuilder<software.amazon.awssdk.services.efs.model.FileSystemDescription$Builder, software.amazon.awssdk.services.efs.model.FileSystemDescription> {
  public abstract software.amazon.awssdk.services.efs.model.FileSystemDescription$Builder ownerId(java.lang.String);

  public abstract software.amazon.awssdk.services.efs.model.FileSystemDescription$Builder creationToken(java.lang.String);

  public abstract software.amazon.awssdk.services.efs.model.FileSystemDescription$Builder fileSystemId(java.lang.String);

  public abstract software.amazon.awssdk.services.efs.model.FileSystemDescription$Builder fileSystemArn(java.lang.String);

  public abstract software.amazon.awssdk.services.efs.model.FileSystemDescription$Builder creationTime(java.time.Instant);

  public abstract software.amazon.awssdk.services.efs.model.FileSystemDescription$Builder lifeCycleState(java.lang.String);

  public abstract software.amazon.awssdk.services.efs.model.FileSystemDescription$Builder lifeCycleState(software.amazon.awssdk.services.efs.model.LifeCycleState);

  public abstract software.amazon.awssdk.services.efs.model.FileSystemDescription$Builder name(java.lang.String);

  public abstract software.amazon.awssdk.services.efs.model.FileSystemDescription$Builder numberOfMountTargets(java.lang.Integer);

  public abstract software.amazon.awssdk.services.efs.model.FileSystemDescription$Builder sizeInBytes(software.amazon.awssdk.services.efs.model.FileSystemSize);

  public default software.amazon.awssdk.services.efs.model.FileSystemDescription$Builder sizeInBytes(java.util.function.Consumer<software.amazon.awssdk.services.efs.model.FileSystemSize$Builder>);
    Code:
       0: aload_0
       1: invokestatic  #1                  // Method software/amazon/awssdk/services/efs/model/FileSystemSize.builder:()Lsoftware/amazon/awssdk/services/efs/model/FileSystemSize$Builder;
       4: aload_1
       5: invokeinterface #2,  2            // InterfaceMethod software/amazon/awssdk/services/efs/model/FileSystemSize$Builder.applyMutation:(Ljava/util/function/Consumer;)Lsoftware/amazon/awssdk/utils/builder/SdkBuilder;
      10: checkcast     #3                  // class software/amazon/awssdk/services/efs/model/FileSystemSize$Builder
      13: invokeinterface #4,  1            // InterfaceMethod software/amazon/awssdk/services/efs/model/FileSystemSize$Builder.build:()Ljava/lang/Object;
      18: checkcast     #5                  // class software/amazon/awssdk/services/efs/model/FileSystemSize
      21: invokeinterface #6,  2            // InterfaceMethod sizeInBytes:(Lsoftware/amazon/awssdk/services/efs/model/FileSystemSize;)Lsoftware/amazon/awssdk/services/efs/model/FileSystemDescription$Builder;
      26: areturn

  public abstract software.amazon.awssdk.services.efs.model.FileSystemDescription$Builder performanceMode(java.lang.String);

  public abstract software.amazon.awssdk.services.efs.model.FileSystemDescription$Builder performanceMode(software.amazon.awssdk.services.efs.model.PerformanceMode);

  public abstract software.amazon.awssdk.services.efs.model.FileSystemDescription$Builder encrypted(java.lang.Boolean);

  public abstract software.amazon.awssdk.services.efs.model.FileSystemDescription$Builder kmsKeyId(java.lang.String);

  public abstract software.amazon.awssdk.services.efs.model.FileSystemDescription$Builder throughputMode(java.lang.String);

  public abstract software.amazon.awssdk.services.efs.model.FileSystemDescription$Builder throughputMode(software.amazon.awssdk.services.efs.model.ThroughputMode);

  public abstract software.amazon.awssdk.services.efs.model.FileSystemDescription$Builder provisionedThroughputInMibps(java.lang.Double);

  public abstract software.amazon.awssdk.services.efs.model.FileSystemDescription$Builder availabilityZoneName(java.lang.String);

  public abstract software.amazon.awssdk.services.efs.model.FileSystemDescription$Builder availabilityZoneId(java.lang.String);

  public abstract software.amazon.awssdk.services.efs.model.FileSystemDescription$Builder tags(java.util.Collection<software.amazon.awssdk.services.efs.model.Tag>);

  public abstract software.amazon.awssdk.services.efs.model.FileSystemDescription$Builder tags(software.amazon.awssdk.services.efs.model.Tag...);

  public abstract software.amazon.awssdk.services.efs.model.FileSystemDescription$Builder tags(java.util.function.Consumer<software.amazon.awssdk.services.efs.model.Tag$Builder>...);
}
