Compiled from "PersistentList.java"
final class org.hibernate.collection.internal.PersistentList$Clear implements org.hibernate.collection.internal.AbstractPersistentCollection$DelayedOperation {
  final org.hibernate.collection.internal.PersistentList this$0;

  org.hibernate.collection.internal.PersistentList$Clear(org.hibernate.collection.internal.PersistentList);
    Code:
       0: aload_0
       1: aload_1
       2: putfield      #1                  // Field this$0:Lorg/hibernate/collection/internal/PersistentList;
       5: aload_0
       6: invokespecial #2                  // Method java/lang/Object."<init>":()V
       9: return

  public void operate();
    Code:
       0: aload_0
       1: getfield      #1                  // Field this$0:Lorg/hibernate/collection/internal/PersistentList;
       4: getfield      #3                  // Field org/hibernate/collection/internal/PersistentList.list:Ljava/util/List;
       7: invokeinterface #4,  1            // InterfaceMethod java/util/List.clear:()V
      12: return

  public java.lang.Object getAddedInstance();
    Code:
       0: aconst_null
       1: areturn

  public java.lang.Object getOrphan();
    Code:
       0: new           #5                  // class java/lang/UnsupportedOperationException
       3: dup
       4: ldc           #6                  // String queued clear cannot be used with orphan delete
       6: invokespecial #7                  // Method java/lang/UnsupportedOperationException."<init>":(Ljava/lang/String;)V
       9: athrow
}
