Compiled from "JDKValueInstantiators.java"
class io.dekorate.deps.jackson.databind.deser.impl.JDKValueInstantiators$ConstantValueInstantiator extends io.dekorate.deps.jackson.databind.deser.ValueInstantiator$Base implements java.io.Serializable {
  private static final long serialVersionUID;

  protected final java.lang.Object _value;

  public io.dekorate.deps.jackson.databind.deser.impl.JDKValueInstantiators$ConstantValueInstantiator(java.lang.Object);
    Code:
       0: aload_0
       1: aload_1
       2: invokevirtual #27                 // Method java/lang/Object.getClass:()Ljava/lang/Class;
       5: invokespecial #30                 // Method io/dekorate/deps/jackson/databind/deser/ValueInstantiator$Base."<init>":(Ljava/lang/Class;)V
       8: aload_0
       9: aload_1
      10: putfield      #32                 // Field _value:Ljava/lang/Object;
      13: return

  public boolean canInstantiate();
    Code:
       0: iconst_1
       1: ireturn

  public boolean canCreateUsingDefault();
    Code:
       0: iconst_1
       1: ireturn

  public java.lang.Object createUsingDefault(io.dekorate.deps.jackson.databind.DeserializationContext) throws java.io.IOException;
    Code:
       0: aload_0
       1: getfield      #32                 // Field _value:Ljava/lang/Object;
       4: areturn
}
