Compiled from "RevisionPropertyPropertyName.java"
public class org.hibernate.envers.query.internal.property.RevisionPropertyPropertyName implements org.hibernate.envers.query.internal.property.PropertyNameGetter {
  private final java.lang.String propertyName;

  public org.hibernate.envers.query.internal.property.RevisionPropertyPropertyName(java.lang.String);
    Code:
       0: aload_0
       1: invokespecial #1                  // Method java/lang/Object."<init>":()V
       4: aload_0
       5: aload_1
       6: putfield      #2                  // Field propertyName:Ljava/lang/String;
       9: return

  public java.lang.String get(org.hibernate.envers.boot.internal.EnversService);
    Code:
       0: aload_1
       1: invokeinterface #3,  1            // InterfaceMethod org/hibernate/envers/boot/internal/EnversService.getAuditEntitiesConfiguration:()Lorg/hibernate/envers/configuration/internal/AuditEntitiesConfiguration;
       6: aload_0
       7: getfield      #2                  // Field propertyName:Ljava/lang/String;
      10: invokevirtual #4                  // Method org/hibernate/envers/configuration/internal/AuditEntitiesConfiguration.getRevisionPropPath:(Ljava/lang/String;)Ljava/lang/String;
      13: areturn
}
