Compiled from "DistributionRatio.java"
public class org.apache.camel.processor.loadbalancer.DistributionRatio {
  private int processorPosition;

  private int distributionWeight;

  private int runtimeWeight;

  public org.apache.camel.processor.loadbalancer.DistributionRatio(int, int);
    Code:
       0: aload_0
       1: iload_1
       2: iload_2
       3: iload_2
       4: invokespecial #14                 // Method "<init>":(III)V
       7: return

  public org.apache.camel.processor.loadbalancer.DistributionRatio(int, int, int);
    Code:
       0: aload_0
       1: invokespecial #19                 // Method java/lang/Object."<init>":()V
       4: aload_0
       5: iload_1
       6: putfield      #21                 // Field processorPosition:I
       9: aload_0
      10: iload_2
      11: putfield      #23                 // Field distributionWeight:I
      14: aload_0
      15: iload_3
      16: putfield      #25                 // Field runtimeWeight:I
      19: return

  public int getProcessorPosition();
    Code:
       0: aload_0
       1: getfield      #21                 // Field processorPosition:I
       4: ireturn

  public void setProcessorPosition(int);
    Code:
       0: aload_0
       1: iload_1
       2: putfield      #21                 // Field processorPosition:I
       5: return

  public int getDistributionWeight();
    Code:
       0: aload_0
       1: getfield      #23                 // Field distributionWeight:I
       4: ireturn

  public void setDistributionWeight(int);
    Code:
       0: aload_0
       1: iload_1
       2: putfield      #23                 // Field distributionWeight:I
       5: return

  public int getRuntimeWeight();
    Code:
       0: aload_0
       1: getfield      #25                 // Field runtimeWeight:I
       4: ireturn

  public void setRuntimeWeight(int);
    Code:
       0: aload_0
       1: iload_1
       2: putfield      #25                 // Field runtimeWeight:I
       5: return
}
