Compiled from "HotSwappableTargetSource.java"
public class org.springframework.aop.target.HotSwappableTargetSource implements org.springframework.aop.TargetSource,java.io.Serializable {
  private static final long serialVersionUID;

  private java.lang.Object target;

  public org.springframework.aop.target.HotSwappableTargetSource(java.lang.Object);
    Code:
       0: aload_0
       1: invokespecial #1                  // Method java/lang/Object."<init>":()V
       4: aload_1
       5: ldc           #2                  // String Target object must not be null
       7: invokestatic  #3                  // Method org/springframework/util/Assert.notNull:(Ljava/lang/Object;Ljava/lang/String;)V
      10: aload_0
      11: aload_1
      12: putfield      #4                  // Field target:Ljava/lang/Object;
      15: return

  public synchronized java.lang.Class<?> getTargetClass();
    Code:
       0: aload_0
       1: getfield      #4                  // Field target:Ljava/lang/Object;
       4: invokevirtual #5                  // Method java/lang/Object.getClass:()Ljava/lang/Class;
       7: areturn

  public final boolean isStatic();
    Code:
       0: iconst_0
       1: ireturn

  public synchronized java.lang.Object getTarget();
    Code:
       0: aload_0
       1: getfield      #4                  // Field target:Ljava/lang/Object;
       4: areturn

  public void releaseTarget(java.lang.Object);
    Code:
       0: return

  public synchronized java.lang.Object swap(java.lang.Object) throws java.lang.IllegalArgumentException;
    Code:
       0: aload_1
       1: ldc           #2                  // String Target object must not be null
       3: invokestatic  #3                  // Method org/springframework/util/Assert.notNull:(Ljava/lang/Object;Ljava/lang/String;)V
       6: aload_0
       7: getfield      #4                  // Field target:Ljava/lang/Object;
      10: astore_2
      11: aload_0
      12: aload_1
      13: putfield      #4                  // Field target:Ljava/lang/Object;
      16: aload_2
      17: areturn

  public boolean equals(java.lang.Object);
    Code:
       0: aload_0
       1: aload_1
       2: if_acmpeq     29
       5: aload_1
       6: instanceof    #6                  // class org/springframework/aop/target/HotSwappableTargetSource
       9: ifeq          33
      12: aload_0
      13: getfield      #4                  // Field target:Ljava/lang/Object;
      16: aload_1
      17: checkcast     #6                  // class org/springframework/aop/target/HotSwappableTargetSource
      20: getfield      #4                  // Field target:Ljava/lang/Object;
      23: invokevirtual #7                  // Method java/lang/Object.equals:(Ljava/lang/Object;)Z
      26: ifeq          33
      29: iconst_1
      30: goto          34
      33: iconst_0
      34: ireturn

  public int hashCode();
    Code:
       0: ldc           #6                  // class org/springframework/aop/target/HotSwappableTargetSource
       2: invokevirtual #8                  // Method java/lang/Object.hashCode:()I
       5: ireturn

  public java.lang.String toString();
    Code:
       0: new           #9                  // class java/lang/StringBuilder
       3: dup
       4: invokespecial #10                 // Method java/lang/StringBuilder."<init>":()V
       7: ldc           #11                 // String HotSwappableTargetSource for target:
       9: invokevirtual #12                 // Method java/lang/StringBuilder.append:(Ljava/lang/String;)Ljava/lang/StringBuilder;
      12: aload_0
      13: getfield      #4                  // Field target:Ljava/lang/Object;
      16: invokevirtual #13                 // Method java/lang/StringBuilder.append:(Ljava/lang/Object;)Ljava/lang/StringBuilder;
      19: invokevirtual #14                 // Method java/lang/StringBuilder.toString:()Ljava/lang/String;
      22: areturn
}
