Compiled from "InitializationService.java"
public class org.opensaml.core.config.InitializationService {
  protected org.opensaml.core.config.InitializationService();
    Code:
       0: aload_0
       1: invokespecial #1                  // Method java/lang/Object."<init>":()V
       4: return

  public static synchronized void initialize() throws org.opensaml.core.config.InitializationException;
    Code:
       0: invokestatic  #2                  // Method getLogger:()Lorg/slf4j/Logger;
       3: astore_0
       4: aload_0
       5: ldc           #3                  // String Initializing OpenSAML using the Java Services API
       7: invokeinterface #4,  2            // InterfaceMethod org/slf4j/Logger.info:(Ljava/lang/String;)V
      12: invokestatic  #5                  // Method getServiceLoader:()Ljava/util/ServiceLoader;
      15: astore_1
      16: aload_1
      17: invokevirtual #6                  // Method java/util/ServiceLoader.iterator:()Ljava/util/Iterator;
      20: astore_2
      21: aload_2
      22: invokeinterface #7,  1            // InterfaceMethod java/util/Iterator.hasNext:()Z
      27: ifeq          82
      30: aload_2
      31: invokeinterface #8,  1            // InterfaceMethod java/util/Iterator.next:()Ljava/lang/Object;
      36: checkcast     #9                  // class org/opensaml/core/config/Initializer
      39: astore_3
      40: aload_0
      41: ldc           #10                 // String Initializing module initializer implementation: {}
      43: aload_3
      44: invokevirtual #11                 // Method java/lang/Object.getClass:()Ljava/lang/Class;
      47: invokevirtual #12                 // Method java/lang/Class.getName:()Ljava/lang/String;
      50: invokeinterface #13,  3           // InterfaceMethod org/slf4j/Logger.debug:(Ljava/lang/String;Ljava/lang/Object;)V
      55: aload_3
      56: invokeinterface #14,  1           // InterfaceMethod org/opensaml/core/config/Initializer.init:()V
      61: goto          79
      64: astore        4
      66: aload_0
      67: ldc           #16                 // String Error initializing module
      69: aload         4
      71: invokeinterface #17,  3           // InterfaceMethod org/slf4j/Logger.error:(Ljava/lang/String;Ljava/lang/Throwable;)V
      76: aload         4
      78: athrow
      79: goto          21
      82: return
    Exception table:
       from    to  target type
          55    61    64   Class org/opensaml/core/config/InitializationException

  private static java.util.ServiceLoader<org.opensaml.core.config.Initializer> getServiceLoader();
    Code:
       0: ldc_w         #9                  // class org/opensaml/core/config/Initializer
       3: invokestatic  #18                 // Method java/util/ServiceLoader.load:(Ljava/lang/Class;)Ljava/util/ServiceLoader;
       6: areturn

  private static org.slf4j.Logger getLogger();
    Code:
       0: ldc_w         #19                 // class org/opensaml/core/config/InitializationService
       3: invokestatic  #20                 // Method org/slf4j/LoggerFactory.getLogger:(Ljava/lang/Class;)Lorg/slf4j/Logger;
       6: areturn
}
