Compiled from "SafeRepresenter.java"
public class io.dekorate.deps.snakeyaml.representer.SafeRepresenter$RepresentByteArray implements io.dekorate.deps.snakeyaml.representer.Represent {
  final io.dekorate.deps.snakeyaml.representer.SafeRepresenter this$0;

  protected io.dekorate.deps.snakeyaml.representer.SafeRepresenter$RepresentByteArray(io.dekorate.deps.snakeyaml.representer.SafeRepresenter);
    Code:
       0: aload_0
       1: aload_1
       2: putfield      #21                 // Field this$0:Lio/dekorate/deps/snakeyaml/representer/SafeRepresenter;
       5: aload_0
       6: invokespecial #24                 // Method java/lang/Object."<init>":()V
       9: return

  public io.dekorate.deps.snakeyaml.nodes.Node representData(java.lang.Object);
    Code:
       0: aload_1
       1: checkcast     #30                 // class "[B"
       4: checkcast     #30                 // class "[B"
       7: invokestatic  #36                 // Method io/dekorate/deps/snakeyaml/external/biz/base64Coder/Base64Coder.encode:([B)[C
      10: astore_2
      11: aload_0
      12: getfield      #21                 // Field this$0:Lio/dekorate/deps/snakeyaml/representer/SafeRepresenter;
      15: getstatic     #42                 // Field io/dekorate/deps/snakeyaml/nodes/Tag.BINARY:Lio/dekorate/deps/snakeyaml/nodes/Tag;
      18: aload_2
      19: invokestatic  #48                 // Method java/lang/String.valueOf:([C)Ljava/lang/String;
      22: getstatic     #52                 // Field io/dekorate/deps/snakeyaml/DumperOptions$ScalarStyle.LITERAL:Lio/dekorate/deps/snakeyaml/DumperOptions$ScalarStyle;
      25: invokevirtual #56                 // Method io/dekorate/deps/snakeyaml/representer/SafeRepresenter.representScalar:(Lio/dekorate/deps/snakeyaml/nodes/Tag;Ljava/lang/String;Lio/dekorate/deps/snakeyaml/DumperOptions$ScalarStyle;)Lio/dekorate/deps/snakeyaml/nodes/Node;
      28: areturn
}
