Compiled from "IO_JenaWriters.java"
public class org.apache.jena.riot.system.IO_JenaWriters {
  private static boolean isWiredIn;

  public org.apache.jena.riot.system.IO_JenaWriters();
    Code:
       0: aload_0
       1: invokespecial #1                  // Method java/lang/Object."<init>":()V
       4: return

  public static void wireIntoJena();
    Code:
       0: getstatic     #2                  // Field isWiredIn:Z
       3: ifeq          7
       6: return
       7: iconst_1
       8: putstatic     #2                  // Field isWiredIn:Z
      11: new           #3                  // class org/apache/jena/riot/adapters/RDFWriterFactoryRIOT
      14: dup
      15: invokespecial #4                  // Method org/apache/jena/riot/adapters/RDFWriterFactoryRIOT."<init>":()V
      18: invokestatic  #5                  // Method org/apache/jena/rdf/model/impl/RDFWriterFImpl.alternative:(Lorg/apache/jena/rdf/model/RDFWriterF;)V
      21: return

  public static void resetJena();
    Code:
       0: getstatic     #2                  // Field isWiredIn:Z
       3: ifne          7
       6: return
       7: iconst_0
       8: putstatic     #2                  // Field isWiredIn:Z
      11: aconst_null
      12: invokestatic  #5                  // Method org/apache/jena/rdf/model/impl/RDFWriterFImpl.alternative:(Lorg/apache/jena/rdf/model/RDFWriterF;)V
      15: return

  public static void registerForModelWrite(java.lang.String, java.lang.Class<?>);
    Code:
       0: aload_0
       1: aload_1
       2: invokevirtual #6                  // Method java/lang/Class.getName:()Ljava/lang/String;
       5: invokestatic  #7                  // Method org/apache/jena/rdf/model/impl/RDFWriterFImpl.setBaseWriterClassName:(Ljava/lang/String;Ljava/lang/String;)Ljava/lang/String;
       8: pop
       9: return

  static {};
    Code:
       0: iconst_0
       1: putstatic     #2                  // Field isWiredIn:Z
       4: return
}
