Compiled from "HpccErrorBlock.java"
public class org.hpccsystems.commons.errors.HpccErrorBlock {
  private final java.util.concurrent.CopyOnWriteArraySet<org.hpccsystems.commons.errors.HpccError> he;

  public org.hpccsystems.commons.errors.HpccErrorBlock();
    Code:
       0: aload_0
       1: invokespecial #1                  // Method java/lang/Object."<init>":()V
       4: aload_0
       5: new           #2                  // class java/util/concurrent/CopyOnWriteArraySet
       8: dup
       9: invokespecial #3                  // Method java/util/concurrent/CopyOnWriteArraySet."<init>":()V
      12: putfield      #4                  // Field he:Ljava/util/concurrent/CopyOnWriteArraySet;
      15: return

  public java.lang.String toString();
    Code:
       0: new           #5                  // class java/lang/StringBuilder
       3: dup
       4: invokespecial #6                  // Method java/lang/StringBuilder."<init>":()V
       7: astore_1
       8: aload_0
       9: getfield      #4                  // Field he:Ljava/util/concurrent/CopyOnWriteArraySet;
      12: invokevirtual #7                  // Method java/util/concurrent/CopyOnWriteArraySet.iterator:()Ljava/util/Iterator;
      15: astore_2
      16: aload_2
      17: invokeinterface #8,  1            // InterfaceMethod java/util/Iterator.hasNext:()Z
      22: ifeq          52
      25: aload_2
      26: invokeinterface #9,  1            // InterfaceMethod java/util/Iterator.next:()Ljava/lang/Object;
      31: checkcast     #10                 // class org/hpccsystems/commons/errors/HpccError
      34: astore_3
      35: aload_1
      36: aload_3
      37: invokevirtual #11                 // Method org/hpccsystems/commons/errors/HpccError.toString:()Ljava/lang/String;
      40: invokevirtual #12                 // Method java/lang/StringBuilder.append:(Ljava/lang/String;)Ljava/lang/StringBuilder;
      43: ldc           #13                 // String \n
      45: invokevirtual #12                 // Method java/lang/StringBuilder.append:(Ljava/lang/String;)Ljava/lang/StringBuilder;
      48: pop
      49: goto          16
      52: aload_1
      53: invokevirtual #14                 // Method java/lang/StringBuilder.toString:()Ljava/lang/String;
      56: areturn

  public void addAll(org.hpccsystems.commons.errors.HpccErrorBlock);
    Code:
       0: aload_0
       1: getfield      #4                  // Field he:Ljava/util/concurrent/CopyOnWriteArraySet;
       4: aload_1
       5: getfield      #4                  // Field he:Ljava/util/concurrent/CopyOnWriteArraySet;
       8: invokevirtual #15                 // Method java/util/concurrent/CopyOnWriteArraySet.addAll:(Ljava/util/Collection;)Z
      11: pop
      12: return

  public java.util.List<org.hpccsystems.commons.errors.HpccError> getErrors(org.hpccsystems.commons.errors.IErrorCode);
    Code:
       0: aload_0
       1: getstatic     #16                 // Field org/hpccsystems/commons/errors/HpccErrorLevel.ERROR:Lorg/hpccsystems/commons/errors/HpccErrorLevel;
       4: aload_1
       5: invokevirtual #17                 // Method getItems:(Lorg/hpccsystems/commons/errors/HpccErrorLevel;Lorg/hpccsystems/commons/errors/IErrorCode;)Ljava/util/List;
       8: astore_2
       9: aload_2
      10: aload_0
      11: getstatic     #18                 // Field org/hpccsystems/commons/errors/HpccErrorLevel.FATAL:Lorg/hpccsystems/commons/errors/HpccErrorLevel;
      14: aload_1
      15: invokevirtual #17                 // Method getItems:(Lorg/hpccsystems/commons/errors/HpccErrorLevel;Lorg/hpccsystems/commons/errors/IErrorCode;)Ljava/util/List;
      18: invokeinterface #19,  2           // InterfaceMethod java/util/List.addAll:(Ljava/util/Collection;)Z
      23: pop
      24: aload_2
      25: areturn

  public java.util.List<org.hpccsystems.commons.errors.HpccError> getErrors();
    Code:
       0: aload_0
       1: getstatic     #16                 // Field org/hpccsystems/commons/errors/HpccErrorLevel.ERROR:Lorg/hpccsystems/commons/errors/HpccErrorLevel;
       4: aconst_null
       5: invokevirtual #17                 // Method getItems:(Lorg/hpccsystems/commons/errors/HpccErrorLevel;Lorg/hpccsystems/commons/errors/IErrorCode;)Ljava/util/List;
       8: astore_1
       9: aload_1
      10: aload_0
      11: getstatic     #18                 // Field org/hpccsystems/commons/errors/HpccErrorLevel.FATAL:Lorg/hpccsystems/commons/errors/HpccErrorLevel;
      14: aconst_null
      15: invokevirtual #17                 // Method getItems:(Lorg/hpccsystems/commons/errors/HpccErrorLevel;Lorg/hpccsystems/commons/errors/IErrorCode;)Ljava/util/List;
      18: invokeinterface #19,  2           // InterfaceMethod java/util/List.addAll:(Ljava/util/Collection;)Z
      23: pop
      24: aload_1
      25: areturn

  public java.util.List<org.hpccsystems.commons.errors.HpccError> getWarnings();
    Code:
       0: aload_0
       1: getstatic     #20                 // Field org/hpccsystems/commons/errors/HpccErrorLevel.WARNING:Lorg/hpccsystems/commons/errors/HpccErrorLevel;
       4: aconst_null
       5: invokevirtual #17                 // Method getItems:(Lorg/hpccsystems/commons/errors/HpccErrorLevel;Lorg/hpccsystems/commons/errors/IErrorCode;)Ljava/util/List;
       8: areturn

  public java.util.List<org.hpccsystems.commons.errors.HpccError> getInfos();
    Code:
       0: aload_0
       1: getstatic     #21                 // Field org/hpccsystems/commons/errors/HpccErrorLevel.INFO:Lorg/hpccsystems/commons/errors/HpccErrorLevel;
       4: aconst_null
       5: invokevirtual #17                 // Method getItems:(Lorg/hpccsystems/commons/errors/HpccErrorLevel;Lorg/hpccsystems/commons/errors/IErrorCode;)Ljava/util/List;
       8: areturn

  public java.util.List<org.hpccsystems.commons.errors.HpccError> getItems(org.hpccsystems.commons.errors.HpccErrorLevel, org.hpccsystems.commons.errors.IErrorCode);
    Code:
       0: new           #22                 // class java/util/ArrayList
       3: dup
       4: invokespecial #23                 // Method java/util/ArrayList."<init>":()V
       7: astore_3
       8: aload_0
       9: getfield      #4                  // Field he:Ljava/util/concurrent/CopyOnWriteArraySet;
      12: invokevirtual #7                  // Method java/util/concurrent/CopyOnWriteArraySet.iterator:()Ljava/util/Iterator;
      15: astore        4
      17: aload         4
      19: invokeinterface #8,  1            // InterfaceMethod java/util/Iterator.hasNext:()Z
      24: ifeq          83
      27: aload         4
      29: invokeinterface #9,  1            // InterfaceMethod java/util/Iterator.next:()Ljava/lang/Object;
      34: checkcast     #10                 // class org/hpccsystems/commons/errors/HpccError
      37: astore        5
      39: aload_1
      40: ifnull        55
      43: aload_1
      44: aload         5
      46: invokevirtual #24                 // Method org/hpccsystems/commons/errors/HpccError.getErrorLevel:()Lorg/hpccsystems/commons/errors/HpccErrorLevel;
      49: invokevirtual #25                 // Method org/hpccsystems/commons/errors/HpccErrorLevel.equals:(Ljava/lang/Object;)Z
      52: ifeq          80
      55: aload_2
      56: ifnull        71
      59: aload_2
      60: aload         5
      62: invokevirtual #26                 // Method org/hpccsystems/commons/errors/HpccError.getErrorCode:()Lorg/hpccsystems/commons/errors/IErrorCode;
      65: invokevirtual #27                 // Method java/lang/Object.equals:(Ljava/lang/Object;)Z
      68: ifeq          80
      71: aload_3
      72: aload         5
      74: invokeinterface #28,  2           // InterfaceMethod java/util/List.add:(Ljava/lang/Object;)Z
      79: pop
      80: goto          17
      83: aload_3
      84: areturn

  public void add(org.hpccsystems.commons.errors.HpccError);
    Code:
       0: aload_1
       1: ifnonnull     5
       4: return
       5: aload_0
       6: getfield      #4                  // Field he:Ljava/util/concurrent/CopyOnWriteArraySet;
       9: dup
      10: astore_2
      11: monitorenter
      12: aload_0
      13: getfield      #4                  // Field he:Ljava/util/concurrent/CopyOnWriteArraySet;
      16: aload_1
      17: invokevirtual #29                 // Method java/util/concurrent/CopyOnWriteArraySet.add:(Ljava/lang/Object;)Z
      20: pop
      21: aload_2
      22: monitorexit
      23: goto          31
      26: astore_3
      27: aload_2
      28: monitorexit
      29: aload_3
      30: athrow
      31: return
    Exception table:
       from    to  target type
          12    23    26   any
          26    29    26   any

  public java.lang.String toEclIdeString();
    Code:
       0: new           #5                  // class java/lang/StringBuilder
       3: dup
       4: invokespecial #6                  // Method java/lang/StringBuilder."<init>":()V
       7: astore_1
       8: aload_0
       9: invokevirtual #30                 // Method getErrors:()Ljava/util/List;
      12: invokeinterface #31,  1           // InterfaceMethod java/util/List.iterator:()Ljava/util/Iterator;
      17: astore_2
      18: aload_2
      19: invokeinterface #8,  1            // InterfaceMethod java/util/Iterator.hasNext:()Z
      24: ifeq          49
      27: aload_2
      28: invokeinterface #9,  1            // InterfaceMethod java/util/Iterator.next:()Ljava/lang/Object;
      33: checkcast     #10                 // class org/hpccsystems/commons/errors/HpccError
      36: astore_3
      37: aload_1
      38: aload_3
      39: invokevirtual #32                 // Method org/hpccsystems/commons/errors/HpccError.toEclIdeString:()Ljava/lang/String;
      42: invokevirtual #12                 // Method java/lang/StringBuilder.append:(Ljava/lang/String;)Ljava/lang/StringBuilder;
      45: pop
      46: goto          18
      49: aload_1
      50: invokevirtual #14                 // Method java/lang/StringBuilder.toString:()Ljava/lang/String;
      53: areturn

  public void clear();
    Code:
       0: aload_0
       1: getfield      #4                  // Field he:Ljava/util/concurrent/CopyOnWriteArraySet;
       4: invokevirtual #33                 // Method java/util/concurrent/CopyOnWriteArraySet.clear:()V
       7: return

  public int size();
    Code:
       0: aload_0
       1: getfield      #4                  // Field he:Ljava/util/concurrent/CopyOnWriteArraySet;
       4: invokevirtual #34                 // Method java/util/concurrent/CopyOnWriteArraySet.size:()I
       7: ireturn

  public java.util.Set<org.hpccsystems.commons.errors.HpccError> asSet();
    Code:
       0: aload_0
       1: getfield      #4                  // Field he:Ljava/util/concurrent/CopyOnWriteArraySet;
       4: areturn

  public boolean isEmpty();
    Code:
       0: aload_0
       1: getfield      #4                  // Field he:Ljava/util/concurrent/CopyOnWriteArraySet;
       4: invokevirtual #35                 // Method java/util/concurrent/CopyOnWriteArraySet.isEmpty:()Z
       7: ireturn
}
