Compiled from "CreateInstanceExportTaskRequestMarshaller.java"
public class com.amazonaws.services.ec2.model.transform.CreateInstanceExportTaskRequestMarshaller implements com.amazonaws.transform.Marshaller<com.amazonaws.Request<com.amazonaws.services.ec2.model.CreateInstanceExportTaskRequest>, com.amazonaws.services.ec2.model.CreateInstanceExportTaskRequest> {
  public com.amazonaws.services.ec2.model.transform.CreateInstanceExportTaskRequestMarshaller();
    Code:
       0: aload_0
       1: invokespecial #1                  // Method java/lang/Object."<init>":()V
       4: return

  public com.amazonaws.Request<com.amazonaws.services.ec2.model.CreateInstanceExportTaskRequest> marshall(com.amazonaws.services.ec2.model.CreateInstanceExportTaskRequest);
    Code:
       0: aload_1
       1: ifnonnull     14
       4: new           #2                  // class com/amazonaws/AmazonClientException
       7: dup
       8: ldc           #3                  // String Invalid argument passed to marshall(...)
      10: invokespecial #4                  // Method com/amazonaws/AmazonClientException."<init>":(Ljava/lang/String;)V
      13: athrow
      14: new           #5                  // class com/amazonaws/DefaultRequest
      17: dup
      18: aload_1
      19: ldc           #6                  // String AmazonEC2
      21: invokespecial #7                  // Method com/amazonaws/DefaultRequest."<init>":(Lcom/amazonaws/AmazonWebServiceRequest;Ljava/lang/String;)V
      24: astore_2
      25: aload_2
      26: ldc           #8                  // String Action
      28: ldc           #9                  // String CreateInstanceExportTask
      30: invokeinterface #10,  3           // InterfaceMethod com/amazonaws/Request.addParameter:(Ljava/lang/String;Ljava/lang/String;)V
      35: aload_2
      36: ldc           #11                 // String Version
      38: ldc           #12                 // String 2016-04-01
      40: invokeinterface #10,  3           // InterfaceMethod com/amazonaws/Request.addParameter:(Ljava/lang/String;Ljava/lang/String;)V
      45: aload_2
      46: getstatic     #13                 // Field com/amazonaws/http/HttpMethodName.POST:Lcom/amazonaws/http/HttpMethodName;
      49: invokeinterface #14,  2           // InterfaceMethod com/amazonaws/Request.setHttpMethod:(Lcom/amazonaws/http/HttpMethodName;)V
      54: aload_1
      55: invokevirtual #15                 // Method com/amazonaws/services/ec2/model/CreateInstanceExportTaskRequest.getDescription:()Ljava/lang/String;
      58: ifnull        76
      61: aload_2
      62: ldc           #16                 // String Description
      64: aload_1
      65: invokevirtual #15                 // Method com/amazonaws/services/ec2/model/CreateInstanceExportTaskRequest.getDescription:()Ljava/lang/String;
      68: invokestatic  #17                 // Method com/amazonaws/util/StringUtils.fromString:(Ljava/lang/String;)Ljava/lang/String;
      71: invokeinterface #10,  3           // InterfaceMethod com/amazonaws/Request.addParameter:(Ljava/lang/String;Ljava/lang/String;)V
      76: aload_1
      77: invokevirtual #18                 // Method com/amazonaws/services/ec2/model/CreateInstanceExportTaskRequest.getInstanceId:()Ljava/lang/String;
      80: ifnull        98
      83: aload_2
      84: ldc           #19                 // String InstanceId
      86: aload_1
      87: invokevirtual #18                 // Method com/amazonaws/services/ec2/model/CreateInstanceExportTaskRequest.getInstanceId:()Ljava/lang/String;
      90: invokestatic  #17                 // Method com/amazonaws/util/StringUtils.fromString:(Ljava/lang/String;)Ljava/lang/String;
      93: invokeinterface #10,  3           // InterfaceMethod com/amazonaws/Request.addParameter:(Ljava/lang/String;Ljava/lang/String;)V
      98: aload_1
      99: invokevirtual #20                 // Method com/amazonaws/services/ec2/model/CreateInstanceExportTaskRequest.getTargetEnvironment:()Ljava/lang/String;
     102: ifnull        120
     105: aload_2
     106: ldc           #21                 // String TargetEnvironment
     108: aload_1
     109: invokevirtual #20                 // Method com/amazonaws/services/ec2/model/CreateInstanceExportTaskRequest.getTargetEnvironment:()Ljava/lang/String;
     112: invokestatic  #17                 // Method com/amazonaws/util/StringUtils.fromString:(Ljava/lang/String;)Ljava/lang/String;
     115: invokeinterface #10,  3           // InterfaceMethod com/amazonaws/Request.addParameter:(Ljava/lang/String;Ljava/lang/String;)V
     120: aload_1
     121: invokevirtual #22                 // Method com/amazonaws/services/ec2/model/CreateInstanceExportTaskRequest.getExportToS3Task:()Lcom/amazonaws/services/ec2/model/ExportToS3TaskSpecification;
     124: astore_3
     125: aload_3
     126: ifnull        217
     129: aload_3
     130: invokevirtual #23                 // Method com/amazonaws/services/ec2/model/ExportToS3TaskSpecification.getDiskImageFormat:()Ljava/lang/String;
     133: ifnull        151
     136: aload_2
     137: ldc           #24                 // String ExportToS3.DiskImageFormat
     139: aload_3
     140: invokevirtual #23                 // Method com/amazonaws/services/ec2/model/ExportToS3TaskSpecification.getDiskImageFormat:()Ljava/lang/String;
     143: invokestatic  #17                 // Method com/amazonaws/util/StringUtils.fromString:(Ljava/lang/String;)Ljava/lang/String;
     146: invokeinterface #10,  3           // InterfaceMethod com/amazonaws/Request.addParameter:(Ljava/lang/String;Ljava/lang/String;)V
     151: aload_3
     152: invokevirtual #25                 // Method com/amazonaws/services/ec2/model/ExportToS3TaskSpecification.getContainerFormat:()Ljava/lang/String;
     155: ifnull        173
     158: aload_2
     159: ldc           #26                 // String ExportToS3.ContainerFormat
     161: aload_3
     162: invokevirtual #25                 // Method com/amazonaws/services/ec2/model/ExportToS3TaskSpecification.getContainerFormat:()Ljava/lang/String;
     165: invokestatic  #17                 // Method com/amazonaws/util/StringUtils.fromString:(Ljava/lang/String;)Ljava/lang/String;
     168: invokeinterface #10,  3           // InterfaceMethod com/amazonaws/Request.addParameter:(Ljava/lang/String;Ljava/lang/String;)V
     173: aload_3
     174: invokevirtual #27                 // Method com/amazonaws/services/ec2/model/ExportToS3TaskSpecification.getS3Bucket:()Ljava/lang/String;
     177: ifnull        195
     180: aload_2
     181: ldc           #28                 // String ExportToS3.S3Bucket
     183: aload_3
     184: invokevirtual #27                 // Method com/amazonaws/services/ec2/model/ExportToS3TaskSpecification.getS3Bucket:()Ljava/lang/String;
     187: invokestatic  #17                 // Method com/amazonaws/util/StringUtils.fromString:(Ljava/lang/String;)Ljava/lang/String;
     190: invokeinterface #10,  3           // InterfaceMethod com/amazonaws/Request.addParameter:(Ljava/lang/String;Ljava/lang/String;)V
     195: aload_3
     196: invokevirtual #29                 // Method com/amazonaws/services/ec2/model/ExportToS3TaskSpecification.getS3Prefix:()Ljava/lang/String;
     199: ifnull        217
     202: aload_2
     203: ldc           #30                 // String ExportToS3.S3Prefix
     205: aload_3
     206: invokevirtual #29                 // Method com/amazonaws/services/ec2/model/ExportToS3TaskSpecification.getS3Prefix:()Ljava/lang/String;
     209: invokestatic  #17                 // Method com/amazonaws/util/StringUtils.fromString:(Ljava/lang/String;)Ljava/lang/String;
     212: invokeinterface #10,  3           // InterfaceMethod com/amazonaws/Request.addParameter:(Ljava/lang/String;Ljava/lang/String;)V
     217: aload_2
     218: areturn

  public java.lang.Object marshall(java.lang.Object) throws java.lang.Exception;
    Code:
       0: aload_0
       1: aload_1
       2: checkcast     #31                 // class com/amazonaws/services/ec2/model/CreateInstanceExportTaskRequest
       5: invokevirtual #32                 // Method marshall:(Lcom/amazonaws/services/ec2/model/CreateInstanceExportTaskRequest;)Lcom/amazonaws/Request;
       8: areturn
}
