Compiled from "RunScheduledInstancesRequestMarshaller.java"
public class com.amazonaws.services.ec2.model.transform.RunScheduledInstancesRequestMarshaller implements com.amazonaws.transform.Marshaller<com.amazonaws.Request<com.amazonaws.services.ec2.model.RunScheduledInstancesRequest>, com.amazonaws.services.ec2.model.RunScheduledInstancesRequest> {
  public com.amazonaws.services.ec2.model.transform.RunScheduledInstancesRequestMarshaller();
    Code:
       0: aload_0
       1: invokespecial #1                  // Method java/lang/Object."<init>":()V
       4: return

  public com.amazonaws.Request<com.amazonaws.services.ec2.model.RunScheduledInstancesRequest> marshall(com.amazonaws.services.ec2.model.RunScheduledInstancesRequest);
    Code:
       0: aload_1
       1: ifnonnull     14
       4: new           #2                  // class com/amazonaws/AmazonClientException
       7: dup
       8: ldc           #3                  // String Invalid argument passed to marshall(...)
      10: invokespecial #4                  // Method com/amazonaws/AmazonClientException."<init>":(Ljava/lang/String;)V
      13: athrow
      14: new           #5                  // class com/amazonaws/DefaultRequest
      17: dup
      18: aload_1
      19: ldc           #6                  // String AmazonEC2
      21: invokespecial #7                  // Method com/amazonaws/DefaultRequest."<init>":(Lcom/amazonaws/AmazonWebServiceRequest;Ljava/lang/String;)V
      24: astore_2
      25: aload_2
      26: ldc           #8                  // String Action
      28: ldc           #9                  // String RunScheduledInstances
      30: invokeinterface #10,  3           // InterfaceMethod com/amazonaws/Request.addParameter:(Ljava/lang/String;Ljava/lang/String;)V
      35: aload_2
      36: ldc           #11                 // String Version
      38: ldc           #12                 // String 2016-04-01
      40: invokeinterface #10,  3           // InterfaceMethod com/amazonaws/Request.addParameter:(Ljava/lang/String;Ljava/lang/String;)V
      45: aload_2
      46: getstatic     #13                 // Field com/amazonaws/http/HttpMethodName.POST:Lcom/amazonaws/http/HttpMethodName;
      49: invokeinterface #14,  2           // InterfaceMethod com/amazonaws/Request.setHttpMethod:(Lcom/amazonaws/http/HttpMethodName;)V
      54: aload_2
      55: ldc           #15                 // String ClientToken
      57: aload_1
      58: invokevirtual #16                 // Method com/amazonaws/services/ec2/model/RunScheduledInstancesRequest.getClientToken:()Ljava/lang/String;
      61: invokestatic  #17                 // Method com/amazonaws/util/IdempotentUtils.resolveString:(Ljava/lang/String;)Ljava/lang/String;
      64: invokeinterface #10,  3           // InterfaceMethod com/amazonaws/Request.addParameter:(Ljava/lang/String;Ljava/lang/String;)V
      69: aload_1
      70: invokevirtual #18                 // Method com/amazonaws/services/ec2/model/RunScheduledInstancesRequest.getInstanceCount:()Ljava/lang/Integer;
      73: ifnull        91
      76: aload_2
      77: ldc           #19                 // String InstanceCount
      79: aload_1
      80: invokevirtual #18                 // Method com/amazonaws/services/ec2/model/RunScheduledInstancesRequest.getInstanceCount:()Ljava/lang/Integer;
      83: invokestatic  #20                 // Method com/amazonaws/util/StringUtils.fromInteger:(Ljava/lang/Integer;)Ljava/lang/String;
      86: invokeinterface #10,  3           // InterfaceMethod com/amazonaws/Request.addParameter:(Ljava/lang/String;Ljava/lang/String;)V
      91: aload_1
      92: invokevirtual #21                 // Method com/amazonaws/services/ec2/model/RunScheduledInstancesRequest.getScheduledInstanceId:()Ljava/lang/String;
      95: ifnull        113
      98: aload_2
      99: ldc           #22                 // String ScheduledInstanceId
     101: aload_1
     102: invokevirtual #21                 // Method com/amazonaws/services/ec2/model/RunScheduledInstancesRequest.getScheduledInstanceId:()Ljava/lang/String;
     105: invokestatic  #23                 // Method com/amazonaws/util/StringUtils.fromString:(Ljava/lang/String;)Ljava/lang/String;
     108: invokeinterface #10,  3           // InterfaceMethod com/amazonaws/Request.addParameter:(Ljava/lang/String;Ljava/lang/String;)V
     113: aload_1
     114: invokevirtual #24                 // Method com/amazonaws/services/ec2/model/RunScheduledInstancesRequest.getLaunchSpecification:()Lcom/amazonaws/services/ec2/model/ScheduledInstancesLaunchSpecification;
     117: astore_3
     118: aload_3
     119: ifnull        1775
     122: aload_3
     123: invokevirtual #25                 // Method com/amazonaws/services/ec2/model/ScheduledInstancesLaunchSpecification.getImageId:()Ljava/lang/String;
     126: ifnull        144
     129: aload_2
     130: ldc           #26                 // String LaunchSpecification.ImageId
     132: aload_3
     133: invokevirtual #25                 // Method com/amazonaws/services/ec2/model/ScheduledInstancesLaunchSpecification.getImageId:()Ljava/lang/String;
     136: invokestatic  #23                 // Method com/amazonaws/util/StringUtils.fromString:(Ljava/lang/String;)Ljava/lang/String;
     139: invokeinterface #10,  3           // InterfaceMethod com/amazonaws/Request.addParameter:(Ljava/lang/String;Ljava/lang/String;)V
     144: aload_3
     145: invokevirtual #27                 // Method com/amazonaws/services/ec2/model/ScheduledInstancesLaunchSpecification.getKeyName:()Ljava/lang/String;
     148: ifnull        166
     151: aload_2
     152: ldc           #28                 // String LaunchSpecification.KeyName
     154: aload_3
     155: invokevirtual #27                 // Method com/amazonaws/services/ec2/model/ScheduledInstancesLaunchSpecification.getKeyName:()Ljava/lang/String;
     158: invokestatic  #23                 // Method com/amazonaws/util/StringUtils.fromString:(Ljava/lang/String;)Ljava/lang/String;
     161: invokeinterface #10,  3           // InterfaceMethod com/amazonaws/Request.addParameter:(Ljava/lang/String;Ljava/lang/String;)V
     166: aload_3
     167: invokevirtual #29                 // Method com/amazonaws/services/ec2/model/ScheduledInstancesLaunchSpecification.getSecurityGroupIds:()Ljava/util/List;
     170: checkcast     #30                 // class com/amazonaws/internal/SdkInternalList
     173: astore        4
     175: aload         4
     177: invokevirtual #31                 // Method com/amazonaws/internal/SdkInternalList.isEmpty:()Z
     180: ifeq          191
     183: aload         4
     185: invokevirtual #32                 // Method com/amazonaws/internal/SdkInternalList.isAutoConstruct:()Z
     188: ifne          265
     191: iconst_1
     192: istore        5
     194: aload         4
     196: invokevirtual #33                 // Method com/amazonaws/internal/SdkInternalList.iterator:()Ljava/util/Iterator;
     199: astore        6
     201: aload         6
     203: invokeinterface #34,  1           // InterfaceMethod java/util/Iterator.hasNext:()Z
     208: ifeq          265
     211: aload         6
     213: invokeinterface #35,  1           // InterfaceMethod java/util/Iterator.next:()Ljava/lang/Object;
     218: checkcast     #36                 // class java/lang/String
     221: astore        7
     223: aload         7
     225: ifnull        259
     228: aload_2
     229: new           #37                 // class java/lang/StringBuilder
     232: dup
     233: invokespecial #38                 // Method java/lang/StringBuilder."<init>":()V
     236: ldc           #39                 // String LaunchSpecification.SecurityGroupId.
     238: invokevirtual #40                 // Method java/lang/StringBuilder.append:(Ljava/lang/String;)Ljava/lang/StringBuilder;
     241: iload         5
     243: invokevirtual #41                 // Method java/lang/StringBuilder.append:(I)Ljava/lang/StringBuilder;
     246: invokevirtual #42                 // Method java/lang/StringBuilder.toString:()Ljava/lang/String;
     249: aload         7
     251: invokestatic  #23                 // Method com/amazonaws/util/StringUtils.fromString:(Ljava/lang/String;)Ljava/lang/String;
     254: invokeinterface #10,  3           // InterfaceMethod com/amazonaws/Request.addParameter:(Ljava/lang/String;Ljava/lang/String;)V
     259: iinc          5, 1
     262: goto          201
     265: aload_3
     266: invokevirtual #43                 // Method com/amazonaws/services/ec2/model/ScheduledInstancesLaunchSpecification.getUserData:()Ljava/lang/String;
     269: ifnull        287
     272: aload_2
     273: ldc           #44                 // String LaunchSpecification.UserData
     275: aload_3
     276: invokevirtual #43                 // Method com/amazonaws/services/ec2/model/ScheduledInstancesLaunchSpecification.getUserData:()Ljava/lang/String;
     279: invokestatic  #23                 // Method com/amazonaws/util/StringUtils.fromString:(Ljava/lang/String;)Ljava/lang/String;
     282: invokeinterface #10,  3           // InterfaceMethod com/amazonaws/Request.addParameter:(Ljava/lang/String;Ljava/lang/String;)V
     287: aload_3
     288: invokevirtual #45                 // Method com/amazonaws/services/ec2/model/ScheduledInstancesLaunchSpecification.getPlacement:()Lcom/amazonaws/services/ec2/model/ScheduledInstancesPlacement;
     291: astore        5
     293: aload         5
     295: ifnull        346
     298: aload         5
     300: invokevirtual #46                 // Method com/amazonaws/services/ec2/model/ScheduledInstancesPlacement.getAvailabilityZone:()Ljava/lang/String;
     303: ifnull        322
     306: aload_2
     307: ldc           #47                 // String LaunchSpecification.Placement.AvailabilityZone
     309: aload         5
     311: invokevirtual #46                 // Method com/amazonaws/services/ec2/model/ScheduledInstancesPlacement.getAvailabilityZone:()Ljava/lang/String;
     314: invokestatic  #23                 // Method com/amazonaws/util/StringUtils.fromString:(Ljava/lang/String;)Ljava/lang/String;
     317: invokeinterface #10,  3           // InterfaceMethod com/amazonaws/Request.addParameter:(Ljava/lang/String;Ljava/lang/String;)V
     322: aload         5
     324: invokevirtual #48                 // Method com/amazonaws/services/ec2/model/ScheduledInstancesPlacement.getGroupName:()Ljava/lang/String;
     327: ifnull        346
     330: aload_2
     331: ldc           #49                 // String LaunchSpecification.Placement.GroupName
     333: aload         5
     335: invokevirtual #48                 // Method com/amazonaws/services/ec2/model/ScheduledInstancesPlacement.getGroupName:()Ljava/lang/String;
     338: invokestatic  #23                 // Method com/amazonaws/util/StringUtils.fromString:(Ljava/lang/String;)Ljava/lang/String;
     341: invokeinterface #10,  3           // InterfaceMethod com/amazonaws/Request.addParameter:(Ljava/lang/String;Ljava/lang/String;)V
     346: aload_3
     347: invokevirtual #50                 // Method com/amazonaws/services/ec2/model/ScheduledInstancesLaunchSpecification.getKernelId:()Ljava/lang/String;
     350: ifnull        368
     353: aload_2
     354: ldc           #51                 // String LaunchSpecification.KernelId
     356: aload_3
     357: invokevirtual #50                 // Method com/amazonaws/services/ec2/model/ScheduledInstancesLaunchSpecification.getKernelId:()Ljava/lang/String;
     360: invokestatic  #23                 // Method com/amazonaws/util/StringUtils.fromString:(Ljava/lang/String;)Ljava/lang/String;
     363: invokeinterface #10,  3           // InterfaceMethod com/amazonaws/Request.addParameter:(Ljava/lang/String;Ljava/lang/String;)V
     368: aload_3
     369: invokevirtual #52                 // Method com/amazonaws/services/ec2/model/ScheduledInstancesLaunchSpecification.getInstanceType:()Ljava/lang/String;
     372: ifnull        390
     375: aload_2
     376: ldc           #53                 // String LaunchSpecification.InstanceType
     378: aload_3
     379: invokevirtual #52                 // Method com/amazonaws/services/ec2/model/ScheduledInstancesLaunchSpecification.getInstanceType:()Ljava/lang/String;
     382: invokestatic  #23                 // Method com/amazonaws/util/StringUtils.fromString:(Ljava/lang/String;)Ljava/lang/String;
     385: invokeinterface #10,  3           // InterfaceMethod com/amazonaws/Request.addParameter:(Ljava/lang/String;Ljava/lang/String;)V
     390: aload_3
     391: invokevirtual #54                 // Method com/amazonaws/services/ec2/model/ScheduledInstancesLaunchSpecification.getRamdiskId:()Ljava/lang/String;
     394: ifnull        412
     397: aload_2
     398: ldc           #55                 // String LaunchSpecification.RamdiskId
     400: aload_3
     401: invokevirtual #54                 // Method com/amazonaws/services/ec2/model/ScheduledInstancesLaunchSpecification.getRamdiskId:()Ljava/lang/String;
     404: invokestatic  #23                 // Method com/amazonaws/util/StringUtils.fromString:(Ljava/lang/String;)Ljava/lang/String;
     407: invokeinterface #10,  3           // InterfaceMethod com/amazonaws/Request.addParameter:(Ljava/lang/String;Ljava/lang/String;)V
     412: aload_3
     413: invokevirtual #56                 // Method com/amazonaws/services/ec2/model/ScheduledInstancesLaunchSpecification.getBlockDeviceMappings:()Ljava/util/List;
     416: checkcast     #30                 // class com/amazonaws/internal/SdkInternalList
     419: astore        6
     421: aload         6
     423: invokevirtual #31                 // Method com/amazonaws/internal/SdkInternalList.isEmpty:()Z
     426: ifeq          437
     429: aload         6
     431: invokevirtual #32                 // Method com/amazonaws/internal/SdkInternalList.isAutoConstruct:()Z
     434: ifne          910
     437: iconst_1
     438: istore        7
     440: aload         6
     442: invokevirtual #33                 // Method com/amazonaws/internal/SdkInternalList.iterator:()Ljava/util/Iterator;
     445: astore        8
     447: aload         8
     449: invokeinterface #34,  1           // InterfaceMethod java/util/Iterator.hasNext:()Z
     454: ifeq          910
     457: aload         8
     459: invokeinterface #35,  1           // InterfaceMethod java/util/Iterator.next:()Ljava/lang/Object;
     464: checkcast     #57                 // class com/amazonaws/services/ec2/model/ScheduledInstancesBlockDeviceMapping
     467: astore        9
     469: aload         9
     471: invokevirtual #58                 // Method com/amazonaws/services/ec2/model/ScheduledInstancesBlockDeviceMapping.getDeviceName:()Ljava/lang/String;
     474: ifnull        516
     477: aload_2
     478: new           #37                 // class java/lang/StringBuilder
     481: dup
     482: invokespecial #38                 // Method java/lang/StringBuilder."<init>":()V
     485: ldc           #59                 // String LaunchSpecification.BlockDeviceMapping.
     487: invokevirtual #40                 // Method java/lang/StringBuilder.append:(Ljava/lang/String;)Ljava/lang/StringBuilder;
     490: iload         7
     492: invokevirtual #41                 // Method java/lang/StringBuilder.append:(I)Ljava/lang/StringBuilder;
     495: ldc           #60                 // String .DeviceName
     497: invokevirtual #40                 // Method java/lang/StringBuilder.append:(Ljava/lang/String;)Ljava/lang/StringBuilder;
     500: invokevirtual #42                 // Method java/lang/StringBuilder.toString:()Ljava/lang/String;
     503: aload         9
     505: invokevirtual #58                 // Method com/amazonaws/services/ec2/model/ScheduledInstancesBlockDeviceMapping.getDeviceName:()Ljava/lang/String;
     508: invokestatic  #23                 // Method com/amazonaws/util/StringUtils.fromString:(Ljava/lang/String;)Ljava/lang/String;
     511: invokeinterface #10,  3           // InterfaceMethod com/amazonaws/Request.addParameter:(Ljava/lang/String;Ljava/lang/String;)V
     516: aload         9
     518: invokevirtual #61                 // Method com/amazonaws/services/ec2/model/ScheduledInstancesBlockDeviceMapping.getNoDevice:()Ljava/lang/String;
     521: ifnull        563
     524: aload_2
     525: new           #37                 // class java/lang/StringBuilder
     528: dup
     529: invokespecial #38                 // Method java/lang/StringBuilder."<init>":()V
     532: ldc           #59                 // String LaunchSpecification.BlockDeviceMapping.
     534: invokevirtual #40                 // Method java/lang/StringBuilder.append:(Ljava/lang/String;)Ljava/lang/StringBuilder;
     537: iload         7
     539: invokevirtual #41                 // Method java/lang/StringBuilder.append:(I)Ljava/lang/StringBuilder;
     542: ldc           #62                 // String .NoDevice
     544: invokevirtual #40                 // Method java/lang/StringBuilder.append:(Ljava/lang/String;)Ljava/lang/StringBuilder;
     547: invokevirtual #42                 // Method java/lang/StringBuilder.toString:()Ljava/lang/String;
     550: aload         9
     552: invokevirtual #61                 // Method com/amazonaws/services/ec2/model/ScheduledInstancesBlockDeviceMapping.getNoDevice:()Ljava/lang/String;
     555: invokestatic  #23                 // Method com/amazonaws/util/StringUtils.fromString:(Ljava/lang/String;)Ljava/lang/String;
     558: invokeinterface #10,  3           // InterfaceMethod com/amazonaws/Request.addParameter:(Ljava/lang/String;Ljava/lang/String;)V
     563: aload         9
     565: invokevirtual #63                 // Method com/amazonaws/services/ec2/model/ScheduledInstancesBlockDeviceMapping.getVirtualName:()Ljava/lang/String;
     568: ifnull        610
     571: aload_2
     572: new           #37                 // class java/lang/StringBuilder
     575: dup
     576: invokespecial #38                 // Method java/lang/StringBuilder."<init>":()V
     579: ldc           #59                 // String LaunchSpecification.BlockDeviceMapping.
     581: invokevirtual #40                 // Method java/lang/StringBuilder.append:(Ljava/lang/String;)Ljava/lang/StringBuilder;
     584: iload         7
     586: invokevirtual #41                 // Method java/lang/StringBuilder.append:(I)Ljava/lang/StringBuilder;
     589: ldc           #64                 // String .VirtualName
     591: invokevirtual #40                 // Method java/lang/StringBuilder.append:(Ljava/lang/String;)Ljava/lang/StringBuilder;
     594: invokevirtual #42                 // Method java/lang/StringBuilder.toString:()Ljava/lang/String;
     597: aload         9
     599: invokevirtual #63                 // Method com/amazonaws/services/ec2/model/ScheduledInstancesBlockDeviceMapping.getVirtualName:()Ljava/lang/String;
     602: invokestatic  #23                 // Method com/amazonaws/util/StringUtils.fromString:(Ljava/lang/String;)Ljava/lang/String;
     605: invokeinterface #10,  3           // InterfaceMethod com/amazonaws/Request.addParameter:(Ljava/lang/String;Ljava/lang/String;)V
     610: aload         9
     612: invokevirtual #65                 // Method com/amazonaws/services/ec2/model/ScheduledInstancesBlockDeviceMapping.getEbs:()Lcom/amazonaws/services/ec2/model/ScheduledInstancesEbs;
     615: astore        10
     617: aload         10
     619: ifnull        904
     622: aload         10
     624: invokevirtual #66                 // Method com/amazonaws/services/ec2/model/ScheduledInstancesEbs.getSnapshotId:()Ljava/lang/String;
     627: ifnull        669
     630: aload_2
     631: new           #37                 // class java/lang/StringBuilder
     634: dup
     635: invokespecial #38                 // Method java/lang/StringBuilder."<init>":()V
     638: ldc           #59                 // String LaunchSpecification.BlockDeviceMapping.
     640: invokevirtual #40                 // Method java/lang/StringBuilder.append:(Ljava/lang/String;)Ljava/lang/StringBuilder;
     643: iload         7
     645: invokevirtual #41                 // Method java/lang/StringBuilder.append:(I)Ljava/lang/StringBuilder;
     648: ldc           #67                 // String .Ebs.SnapshotId
     650: invokevirtual #40                 // Method java/lang/StringBuilder.append:(Ljava/lang/String;)Ljava/lang/StringBuilder;
     653: invokevirtual #42                 // Method java/lang/StringBuilder.toString:()Ljava/lang/String;
     656: aload         10
     658: invokevirtual #66                 // Method com/amazonaws/services/ec2/model/ScheduledInstancesEbs.getSnapshotId:()Ljava/lang/String;
     661: invokestatic  #23                 // Method com/amazonaws/util/StringUtils.fromString:(Ljava/lang/String;)Ljava/lang/String;
     664: invokeinterface #10,  3           // InterfaceMethod com/amazonaws/Request.addParameter:(Ljava/lang/String;Ljava/lang/String;)V
     669: aload         10
     671: invokevirtual #68                 // Method com/amazonaws/services/ec2/model/ScheduledInstancesEbs.getVolumeSize:()Ljava/lang/Integer;
     674: ifnull        716
     677: aload_2
     678: new           #37                 // class java/lang/StringBuilder
     681: dup
     682: invokespecial #38                 // Method java/lang/StringBuilder."<init>":()V
     685: ldc           #59                 // String LaunchSpecification.BlockDeviceMapping.
     687: invokevirtual #40                 // Method java/lang/StringBuilder.append:(Ljava/lang/String;)Ljava/lang/StringBuilder;
     690: iload         7
     692: invokevirtual #41                 // Method java/lang/StringBuilder.append:(I)Ljava/lang/StringBuilder;
     695: ldc           #69                 // String .Ebs.VolumeSize
     697: invokevirtual #40                 // Method java/lang/StringBuilder.append:(Ljava/lang/String;)Ljava/lang/StringBuilder;
     700: invokevirtual #42                 // Method java/lang/StringBuilder.toString:()Ljava/lang/String;
     703: aload         10
     705: invokevirtual #68                 // Method com/amazonaws/services/ec2/model/ScheduledInstancesEbs.getVolumeSize:()Ljava/lang/Integer;
     708: invokestatic  #20                 // Method com/amazonaws/util/StringUtils.fromInteger:(Ljava/lang/Integer;)Ljava/lang/String;
     711: invokeinterface #10,  3           // InterfaceMethod com/amazonaws/Request.addParameter:(Ljava/lang/String;Ljava/lang/String;)V
     716: aload         10
     718: invokevirtual #70                 // Method com/amazonaws/services/ec2/model/ScheduledInstancesEbs.getDeleteOnTermination:()Ljava/lang/Boolean;
     721: ifnull        763
     724: aload_2
     725: new           #37                 // class java/lang/StringBuilder
     728: dup
     729: invokespecial #38                 // Method java/lang/StringBuilder."<init>":()V
     732: ldc           #59                 // String LaunchSpecification.BlockDeviceMapping.
     734: invokevirtual #40                 // Method java/lang/StringBuilder.append:(Ljava/lang/String;)Ljava/lang/StringBuilder;
     737: iload         7
     739: invokevirtual #41                 // Method java/lang/StringBuilder.append:(I)Ljava/lang/StringBuilder;
     742: ldc           #71                 // String .Ebs.DeleteOnTermination
     744: invokevirtual #40                 // Method java/lang/StringBuilder.append:(Ljava/lang/String;)Ljava/lang/StringBuilder;
     747: invokevirtual #42                 // Method java/lang/StringBuilder.toString:()Ljava/lang/String;
     750: aload         10
     752: invokevirtual #70                 // Method com/amazonaws/services/ec2/model/ScheduledInstancesEbs.getDeleteOnTermination:()Ljava/lang/Boolean;
     755: invokestatic  #72                 // Method com/amazonaws/util/StringUtils.fromBoolean:(Ljava/lang/Boolean;)Ljava/lang/String;
     758: invokeinterface #10,  3           // InterfaceMethod com/amazonaws/Request.addParameter:(Ljava/lang/String;Ljava/lang/String;)V
     763: aload         10
     765: invokevirtual #73                 // Method com/amazonaws/services/ec2/model/ScheduledInstancesEbs.getVolumeType:()Ljava/lang/String;
     768: ifnull        810
     771: aload_2
     772: new           #37                 // class java/lang/StringBuilder
     775: dup
     776: invokespecial #38                 // Method java/lang/StringBuilder."<init>":()V
     779: ldc           #59                 // String LaunchSpecification.BlockDeviceMapping.
     781: invokevirtual #40                 // Method java/lang/StringBuilder.append:(Ljava/lang/String;)Ljava/lang/StringBuilder;
     784: iload         7
     786: invokevirtual #41                 // Method java/lang/StringBuilder.append:(I)Ljava/lang/StringBuilder;
     789: ldc           #74                 // String .Ebs.VolumeType
     791: invokevirtual #40                 // Method java/lang/StringBuilder.append:(Ljava/lang/String;)Ljava/lang/StringBuilder;
     794: invokevirtual #42                 // Method java/lang/StringBuilder.toString:()Ljava/lang/String;
     797: aload         10
     799: invokevirtual #73                 // Method com/amazonaws/services/ec2/model/ScheduledInstancesEbs.getVolumeType:()Ljava/lang/String;
     802: invokestatic  #23                 // Method com/amazonaws/util/StringUtils.fromString:(Ljava/lang/String;)Ljava/lang/String;
     805: invokeinterface #10,  3           // InterfaceMethod com/amazonaws/Request.addParameter:(Ljava/lang/String;Ljava/lang/String;)V
     810: aload         10
     812: invokevirtual #75                 // Method com/amazonaws/services/ec2/model/ScheduledInstancesEbs.getIops:()Ljava/lang/Integer;
     815: ifnull        857
     818: aload_2
     819: new           #37                 // class java/lang/StringBuilder
     822: dup
     823: invokespecial #38                 // Method java/lang/StringBuilder."<init>":()V
     826: ldc           #59                 // String LaunchSpecification.BlockDeviceMapping.
     828: invokevirtual #40                 // Method java/lang/StringBuilder.append:(Ljava/lang/String;)Ljava/lang/StringBuilder;
     831: iload         7
     833: invokevirtual #41                 // Method java/lang/StringBuilder.append:(I)Ljava/lang/StringBuilder;
     836: ldc           #76                 // String .Ebs.Iops
     838: invokevirtual #40                 // Method java/lang/StringBuilder.append:(Ljava/lang/String;)Ljava/lang/StringBuilder;
     841: invokevirtual #42                 // Method java/lang/StringBuilder.toString:()Ljava/lang/String;
     844: aload         10
     846: invokevirtual #75                 // Method com/amazonaws/services/ec2/model/ScheduledInstancesEbs.getIops:()Ljava/lang/Integer;
     849: invokestatic  #20                 // Method com/amazonaws/util/StringUtils.fromInteger:(Ljava/lang/Integer;)Ljava/lang/String;
     852: invokeinterface #10,  3           // InterfaceMethod com/amazonaws/Request.addParameter:(Ljava/lang/String;Ljava/lang/String;)V
     857: aload         10
     859: invokevirtual #77                 // Method com/amazonaws/services/ec2/model/ScheduledInstancesEbs.getEncrypted:()Ljava/lang/Boolean;
     862: ifnull        904
     865: aload_2
     866: new           #37                 // class java/lang/StringBuilder
     869: dup
     870: invokespecial #38                 // Method java/lang/StringBuilder."<init>":()V
     873: ldc           #59                 // String LaunchSpecification.BlockDeviceMapping.
     875: invokevirtual #40                 // Method java/lang/StringBuilder.append:(Ljava/lang/String;)Ljava/lang/StringBuilder;
     878: iload         7
     880: invokevirtual #41                 // Method java/lang/StringBuilder.append:(I)Ljava/lang/StringBuilder;
     883: ldc           #78                 // String .Ebs.Encrypted
     885: invokevirtual #40                 // Method java/lang/StringBuilder.append:(Ljava/lang/String;)Ljava/lang/StringBuilder;
     888: invokevirtual #42                 // Method java/lang/StringBuilder.toString:()Ljava/lang/String;
     891: aload         10
     893: invokevirtual #77                 // Method com/amazonaws/services/ec2/model/ScheduledInstancesEbs.getEncrypted:()Ljava/lang/Boolean;
     896: invokestatic  #72                 // Method com/amazonaws/util/StringUtils.fromBoolean:(Ljava/lang/Boolean;)Ljava/lang/String;
     899: invokeinterface #10,  3           // InterfaceMethod com/amazonaws/Request.addParameter:(Ljava/lang/String;Ljava/lang/String;)V
     904: iinc          7, 1
     907: goto          447
     910: aload_3
     911: invokevirtual #79                 // Method com/amazonaws/services/ec2/model/ScheduledInstancesLaunchSpecification.getMonitoring:()Lcom/amazonaws/services/ec2/model/ScheduledInstancesMonitoring;
     914: astore        7
     916: aload         7
     918: ifnull        945
     921: aload         7
     923: invokevirtual #80                 // Method com/amazonaws/services/ec2/model/ScheduledInstancesMonitoring.getEnabled:()Ljava/lang/Boolean;
     926: ifnull        945
     929: aload_2
     930: ldc           #81                 // String LaunchSpecification.Monitoring.Enabled
     932: aload         7
     934: invokevirtual #80                 // Method com/amazonaws/services/ec2/model/ScheduledInstancesMonitoring.getEnabled:()Ljava/lang/Boolean;
     937: invokestatic  #72                 // Method com/amazonaws/util/StringUtils.fromBoolean:(Ljava/lang/Boolean;)Ljava/lang/String;
     940: invokeinterface #10,  3           // InterfaceMethod com/amazonaws/Request.addParameter:(Ljava/lang/String;Ljava/lang/String;)V
     945: aload_3
     946: invokevirtual #82                 // Method com/amazonaws/services/ec2/model/ScheduledInstancesLaunchSpecification.getSubnetId:()Ljava/lang/String;
     949: ifnull        967
     952: aload_2
     953: ldc           #83                 // String LaunchSpecification.SubnetId
     955: aload_3
     956: invokevirtual #82                 // Method com/amazonaws/services/ec2/model/ScheduledInstancesLaunchSpecification.getSubnetId:()Ljava/lang/String;
     959: invokestatic  #23                 // Method com/amazonaws/util/StringUtils.fromString:(Ljava/lang/String;)Ljava/lang/String;
     962: invokeinterface #10,  3           // InterfaceMethod com/amazonaws/Request.addParameter:(Ljava/lang/String;Ljava/lang/String;)V
     967: aload_3
     968: invokevirtual #84                 // Method com/amazonaws/services/ec2/model/ScheduledInstancesLaunchSpecification.getNetworkInterfaces:()Ljava/util/List;
     971: checkcast     #30                 // class com/amazonaws/internal/SdkInternalList
     974: astore        8
     976: aload         8
     978: invokevirtual #31                 // Method com/amazonaws/internal/SdkInternalList.isEmpty:()Z
     981: ifeq          992
     984: aload         8
     986: invokevirtual #32                 // Method com/amazonaws/internal/SdkInternalList.isAutoConstruct:()Z
     989: ifne          1694
     992: iconst_1
     993: istore        9
     995: aload         8
     997: invokevirtual #33                 // Method com/amazonaws/internal/SdkInternalList.iterator:()Ljava/util/Iterator;
    1000: astore        10
    1002: aload         10
    1004: invokeinterface #34,  1           // InterfaceMethod java/util/Iterator.hasNext:()Z
    1009: ifeq          1694
    1012: aload         10
    1014: invokeinterface #35,  1           // InterfaceMethod java/util/Iterator.next:()Ljava/lang/Object;
    1019: checkcast     #85                 // class com/amazonaws/services/ec2/model/ScheduledInstancesNetworkInterface
    1022: astore        11
    1024: aload         11
    1026: invokevirtual #86                 // Method com/amazonaws/services/ec2/model/ScheduledInstancesNetworkInterface.getNetworkInterfaceId:()Ljava/lang/String;
    1029: ifnull        1071
    1032: aload_2
    1033: new           #37                 // class java/lang/StringBuilder
    1036: dup
    1037: invokespecial #38                 // Method java/lang/StringBuilder."<init>":()V
    1040: ldc           #87                 // String LaunchSpecification.NetworkInterface.
    1042: invokevirtual #40                 // Method java/lang/StringBuilder.append:(Ljava/lang/String;)Ljava/lang/StringBuilder;
    1045: iload         9
    1047: invokevirtual #41                 // Method java/lang/StringBuilder.append:(I)Ljava/lang/StringBuilder;
    1050: ldc           #88                 // String .NetworkInterfaceId
    1052: invokevirtual #40                 // Method java/lang/StringBuilder.append:(Ljava/lang/String;)Ljava/lang/StringBuilder;
    1055: invokevirtual #42                 // Method java/lang/StringBuilder.toString:()Ljava/lang/String;
    1058: aload         11
    1060: invokevirtual #86                 // Method com/amazonaws/services/ec2/model/ScheduledInstancesNetworkInterface.getNetworkInterfaceId:()Ljava/lang/String;
    1063: invokestatic  #23                 // Method com/amazonaws/util/StringUtils.fromString:(Ljava/lang/String;)Ljava/lang/String;
    1066: invokeinterface #10,  3           // InterfaceMethod com/amazonaws/Request.addParameter:(Ljava/lang/String;Ljava/lang/String;)V
    1071: aload         11
    1073: invokevirtual #89                 // Method com/amazonaws/services/ec2/model/ScheduledInstancesNetworkInterface.getDeviceIndex:()Ljava/lang/Integer;
    1076: ifnull        1118
    1079: aload_2
    1080: new           #37                 // class java/lang/StringBuilder
    1083: dup
    1084: invokespecial #38                 // Method java/lang/StringBuilder."<init>":()V
    1087: ldc           #87                 // String LaunchSpecification.NetworkInterface.
    1089: invokevirtual #40                 // Method java/lang/StringBuilder.append:(Ljava/lang/String;)Ljava/lang/StringBuilder;
    1092: iload         9
    1094: invokevirtual #41                 // Method java/lang/StringBuilder.append:(I)Ljava/lang/StringBuilder;
    1097: ldc           #90                 // String .DeviceIndex
    1099: invokevirtual #40                 // Method java/lang/StringBuilder.append:(Ljava/lang/String;)Ljava/lang/StringBuilder;
    1102: invokevirtual #42                 // Method java/lang/StringBuilder.toString:()Ljava/lang/String;
    1105: aload         11
    1107: invokevirtual #89                 // Method com/amazonaws/services/ec2/model/ScheduledInstancesNetworkInterface.getDeviceIndex:()Ljava/lang/Integer;
    1110: invokestatic  #20                 // Method com/amazonaws/util/StringUtils.fromInteger:(Ljava/lang/Integer;)Ljava/lang/String;
    1113: invokeinterface #10,  3           // InterfaceMethod com/amazonaws/Request.addParameter:(Ljava/lang/String;Ljava/lang/String;)V
    1118: aload         11
    1120: invokevirtual #91                 // Method com/amazonaws/services/ec2/model/ScheduledInstancesNetworkInterface.getSubnetId:()Ljava/lang/String;
    1123: ifnull        1165
    1126: aload_2
    1127: new           #37                 // class java/lang/StringBuilder
    1130: dup
    1131: invokespecial #38                 // Method java/lang/StringBuilder."<init>":()V
    1134: ldc           #87                 // String LaunchSpecification.NetworkInterface.
    1136: invokevirtual #40                 // Method java/lang/StringBuilder.append:(Ljava/lang/String;)Ljava/lang/StringBuilder;
    1139: iload         9
    1141: invokevirtual #41                 // Method java/lang/StringBuilder.append:(I)Ljava/lang/StringBuilder;
    1144: ldc           #92                 // String .SubnetId
    1146: invokevirtual #40                 // Method java/lang/StringBuilder.append:(Ljava/lang/String;)Ljava/lang/StringBuilder;
    1149: invokevirtual #42                 // Method java/lang/StringBuilder.toString:()Ljava/lang/String;
    1152: aload         11
    1154: invokevirtual #91                 // Method com/amazonaws/services/ec2/model/ScheduledInstancesNetworkInterface.getSubnetId:()Ljava/lang/String;
    1157: invokestatic  #23                 // Method com/amazonaws/util/StringUtils.fromString:(Ljava/lang/String;)Ljava/lang/String;
    1160: invokeinterface #10,  3           // InterfaceMethod com/amazonaws/Request.addParameter:(Ljava/lang/String;Ljava/lang/String;)V
    1165: aload         11
    1167: invokevirtual #93                 // Method com/amazonaws/services/ec2/model/ScheduledInstancesNetworkInterface.getDescription:()Ljava/lang/String;
    1170: ifnull        1212
    1173: aload_2
    1174: new           #37                 // class java/lang/StringBuilder
    1177: dup
    1178: invokespecial #38                 // Method java/lang/StringBuilder."<init>":()V
    1181: ldc           #87                 // String LaunchSpecification.NetworkInterface.
    1183: invokevirtual #40                 // Method java/lang/StringBuilder.append:(Ljava/lang/String;)Ljava/lang/StringBuilder;
    1186: iload         9
    1188: invokevirtual #41                 // Method java/lang/StringBuilder.append:(I)Ljava/lang/StringBuilder;
    1191: ldc           #94                 // String .Description
    1193: invokevirtual #40                 // Method java/lang/StringBuilder.append:(Ljava/lang/String;)Ljava/lang/StringBuilder;
    1196: invokevirtual #42                 // Method java/lang/StringBuilder.toString:()Ljava/lang/String;
    1199: aload         11
    1201: invokevirtual #93                 // Method com/amazonaws/services/ec2/model/ScheduledInstancesNetworkInterface.getDescription:()Ljava/lang/String;
    1204: invokestatic  #23                 // Method com/amazonaws/util/StringUtils.fromString:(Ljava/lang/String;)Ljava/lang/String;
    1207: invokeinterface #10,  3           // InterfaceMethod com/amazonaws/Request.addParameter:(Ljava/lang/String;Ljava/lang/String;)V
    1212: aload         11
    1214: invokevirtual #95                 // Method com/amazonaws/services/ec2/model/ScheduledInstancesNetworkInterface.getPrivateIpAddress:()Ljava/lang/String;
    1217: ifnull        1259
    1220: aload_2
    1221: new           #37                 // class java/lang/StringBuilder
    1224: dup
    1225: invokespecial #38                 // Method java/lang/StringBuilder."<init>":()V
    1228: ldc           #87                 // String LaunchSpecification.NetworkInterface.
    1230: invokevirtual #40                 // Method java/lang/StringBuilder.append:(Ljava/lang/String;)Ljava/lang/StringBuilder;
    1233: iload         9
    1235: invokevirtual #41                 // Method java/lang/StringBuilder.append:(I)Ljava/lang/StringBuilder;
    1238: ldc           #96                 // String .PrivateIpAddress
    1240: invokevirtual #40                 // Method java/lang/StringBuilder.append:(Ljava/lang/String;)Ljava/lang/StringBuilder;
    1243: invokevirtual #42                 // Method java/lang/StringBuilder.toString:()Ljava/lang/String;
    1246: aload         11
    1248: invokevirtual #95                 // Method com/amazonaws/services/ec2/model/ScheduledInstancesNetworkInterface.getPrivateIpAddress:()Ljava/lang/String;
    1251: invokestatic  #23                 // Method com/amazonaws/util/StringUtils.fromString:(Ljava/lang/String;)Ljava/lang/String;
    1254: invokeinterface #10,  3           // InterfaceMethod com/amazonaws/Request.addParameter:(Ljava/lang/String;Ljava/lang/String;)V
    1259: aload         11
    1261: invokevirtual #97                 // Method com/amazonaws/services/ec2/model/ScheduledInstancesNetworkInterface.getPrivateIpAddressConfigs:()Ljava/util/List;
    1264: checkcast     #30                 // class com/amazonaws/internal/SdkInternalList
    1267: astore        12
    1269: aload         12
    1271: invokevirtual #31                 // Method com/amazonaws/internal/SdkInternalList.isEmpty:()Z
    1274: ifeq          1285
    1277: aload         12
    1279: invokevirtual #32                 // Method com/amazonaws/internal/SdkInternalList.isAutoConstruct:()Z
    1282: ifne          1437
    1285: iconst_1
    1286: istore        13
    1288: aload         12
    1290: invokevirtual #33                 // Method com/amazonaws/internal/SdkInternalList.iterator:()Ljava/util/Iterator;
    1293: astore        14
    1295: aload         14
    1297: invokeinterface #34,  1           // InterfaceMethod java/util/Iterator.hasNext:()Z
    1302: ifeq          1437
    1305: aload         14
    1307: invokeinterface #35,  1           // InterfaceMethod java/util/Iterator.next:()Ljava/lang/Object;
    1312: checkcast     #98                 // class com/amazonaws/services/ec2/model/ScheduledInstancesPrivateIpAddressConfig
    1315: astore        15
    1317: aload         15
    1319: invokevirtual #99                 // Method com/amazonaws/services/ec2/model/ScheduledInstancesPrivateIpAddressConfig.getPrivateIpAddress:()Ljava/lang/String;
    1322: ifnull        1374
    1325: aload_2
    1326: new           #37                 // class java/lang/StringBuilder
    1329: dup
    1330: invokespecial #38                 // Method java/lang/StringBuilder."<init>":()V
    1333: ldc           #87                 // String LaunchSpecification.NetworkInterface.
    1335: invokevirtual #40                 // Method java/lang/StringBuilder.append:(Ljava/lang/String;)Ljava/lang/StringBuilder;
    1338: iload         9
    1340: invokevirtual #41                 // Method java/lang/StringBuilder.append:(I)Ljava/lang/StringBuilder;
    1343: ldc           #100                // String .PrivateIpAddressConfig.
    1345: invokevirtual #40                 // Method java/lang/StringBuilder.append:(Ljava/lang/String;)Ljava/lang/StringBuilder;
    1348: iload         13
    1350: invokevirtual #41                 // Method java/lang/StringBuilder.append:(I)Ljava/lang/StringBuilder;
    1353: ldc           #96                 // String .PrivateIpAddress
    1355: invokevirtual #40                 // Method java/lang/StringBuilder.append:(Ljava/lang/String;)Ljava/lang/StringBuilder;
    1358: invokevirtual #42                 // Method java/lang/StringBuilder.toString:()Ljava/lang/String;
    1361: aload         15
    1363: invokevirtual #99                 // Method com/amazonaws/services/ec2/model/ScheduledInstancesPrivateIpAddressConfig.getPrivateIpAddress:()Ljava/lang/String;
    1366: invokestatic  #23                 // Method com/amazonaws/util/StringUtils.fromString:(Ljava/lang/String;)Ljava/lang/String;
    1369: invokeinterface #10,  3           // InterfaceMethod com/amazonaws/Request.addParameter:(Ljava/lang/String;Ljava/lang/String;)V
    1374: aload         15
    1376: invokevirtual #101                // Method com/amazonaws/services/ec2/model/ScheduledInstancesPrivateIpAddressConfig.getPrimary:()Ljava/lang/Boolean;
    1379: ifnull        1431
    1382: aload_2
    1383: new           #37                 // class java/lang/StringBuilder
    1386: dup
    1387: invokespecial #38                 // Method java/lang/StringBuilder."<init>":()V
    1390: ldc           #87                 // String LaunchSpecification.NetworkInterface.
    1392: invokevirtual #40                 // Method java/lang/StringBuilder.append:(Ljava/lang/String;)Ljava/lang/StringBuilder;
    1395: iload         9
    1397: invokevirtual #41                 // Method java/lang/StringBuilder.append:(I)Ljava/lang/StringBuilder;
    1400: ldc           #100                // String .PrivateIpAddressConfig.
    1402: invokevirtual #40                 // Method java/lang/StringBuilder.append:(Ljava/lang/String;)Ljava/lang/StringBuilder;
    1405: iload         13
    1407: invokevirtual #41                 // Method java/lang/StringBuilder.append:(I)Ljava/lang/StringBuilder;
    1410: ldc           #102                // String .Primary
    1412: invokevirtual #40                 // Method java/lang/StringBuilder.append:(Ljava/lang/String;)Ljava/lang/StringBuilder;
    1415: invokevirtual #42                 // Method java/lang/StringBuilder.toString:()Ljava/lang/String;
    1418: aload         15
    1420: invokevirtual #101                // Method com/amazonaws/services/ec2/model/ScheduledInstancesPrivateIpAddressConfig.getPrimary:()Ljava/lang/Boolean;
    1423: invokestatic  #72                 // Method com/amazonaws/util/StringUtils.fromBoolean:(Ljava/lang/Boolean;)Ljava/lang/String;
    1426: invokeinterface #10,  3           // InterfaceMethod com/amazonaws/Request.addParameter:(Ljava/lang/String;Ljava/lang/String;)V
    1431: iinc          13, 1
    1434: goto          1295
    1437: aload         11
    1439: invokevirtual #103                // Method com/amazonaws/services/ec2/model/ScheduledInstancesNetworkInterface.getSecondaryPrivateIpAddressCount:()Ljava/lang/Integer;
    1442: ifnull        1484
    1445: aload_2
    1446: new           #37                 // class java/lang/StringBuilder
    1449: dup
    1450: invokespecial #38                 // Method java/lang/StringBuilder."<init>":()V
    1453: ldc           #87                 // String LaunchSpecification.NetworkInterface.
    1455: invokevirtual #40                 // Method java/lang/StringBuilder.append:(Ljava/lang/String;)Ljava/lang/StringBuilder;
    1458: iload         9
    1460: invokevirtual #41                 // Method java/lang/StringBuilder.append:(I)Ljava/lang/StringBuilder;
    1463: ldc           #104                // String .SecondaryPrivateIpAddressCount
    1465: invokevirtual #40                 // Method java/lang/StringBuilder.append:(Ljava/lang/String;)Ljava/lang/StringBuilder;
    1468: invokevirtual #42                 // Method java/lang/StringBuilder.toString:()Ljava/lang/String;
    1471: aload         11
    1473: invokevirtual #103                // Method com/amazonaws/services/ec2/model/ScheduledInstancesNetworkInterface.getSecondaryPrivateIpAddressCount:()Ljava/lang/Integer;
    1476: invokestatic  #20                 // Method com/amazonaws/util/StringUtils.fromInteger:(Ljava/lang/Integer;)Ljava/lang/String;
    1479: invokeinterface #10,  3           // InterfaceMethod com/amazonaws/Request.addParameter:(Ljava/lang/String;Ljava/lang/String;)V
    1484: aload         11
    1486: invokevirtual #105                // Method com/amazonaws/services/ec2/model/ScheduledInstancesNetworkInterface.getAssociatePublicIpAddress:()Ljava/lang/Boolean;
    1489: ifnull        1531
    1492: aload_2
    1493: new           #37                 // class java/lang/StringBuilder
    1496: dup
    1497: invokespecial #38                 // Method java/lang/StringBuilder."<init>":()V
    1500: ldc           #87                 // String LaunchSpecification.NetworkInterface.
    1502: invokevirtual #40                 // Method java/lang/StringBuilder.append:(Ljava/lang/String;)Ljava/lang/StringBuilder;
    1505: iload         9
    1507: invokevirtual #41                 // Method java/lang/StringBuilder.append:(I)Ljava/lang/StringBuilder;
    1510: ldc           #106                // String .AssociatePublicIpAddress
    1512: invokevirtual #40                 // Method java/lang/StringBuilder.append:(Ljava/lang/String;)Ljava/lang/StringBuilder;
    1515: invokevirtual #42                 // Method java/lang/StringBuilder.toString:()Ljava/lang/String;
    1518: aload         11
    1520: invokevirtual #105                // Method com/amazonaws/services/ec2/model/ScheduledInstancesNetworkInterface.getAssociatePublicIpAddress:()Ljava/lang/Boolean;
    1523: invokestatic  #72                 // Method com/amazonaws/util/StringUtils.fromBoolean:(Ljava/lang/Boolean;)Ljava/lang/String;
    1526: invokeinterface #10,  3           // InterfaceMethod com/amazonaws/Request.addParameter:(Ljava/lang/String;Ljava/lang/String;)V
    1531: aload         11
    1533: invokevirtual #107                // Method com/amazonaws/services/ec2/model/ScheduledInstancesNetworkInterface.getGroups:()Ljava/util/List;
    1536: checkcast     #30                 // class com/amazonaws/internal/SdkInternalList
    1539: astore        13
    1541: aload         13
    1543: invokevirtual #31                 // Method com/amazonaws/internal/SdkInternalList.isEmpty:()Z
    1546: ifeq          1557
    1549: aload         13
    1551: invokevirtual #32                 // Method com/amazonaws/internal/SdkInternalList.isAutoConstruct:()Z
    1554: ifne          1641
    1557: iconst_1
    1558: istore        14
    1560: aload         13
    1562: invokevirtual #33                 // Method com/amazonaws/internal/SdkInternalList.iterator:()Ljava/util/Iterator;
    1565: astore        15
    1567: aload         15
    1569: invokeinterface #34,  1           // InterfaceMethod java/util/Iterator.hasNext:()Z
    1574: ifeq          1641
    1577: aload         15
    1579: invokeinterface #35,  1           // InterfaceMethod java/util/Iterator.next:()Ljava/lang/Object;
    1584: checkcast     #36                 // class java/lang/String
    1587: astore        16
    1589: aload         16
    1591: ifnull        1635
    1594: aload_2
    1595: new           #37                 // class java/lang/StringBuilder
    1598: dup
    1599: invokespecial #38                 // Method java/lang/StringBuilder."<init>":()V
    1602: ldc           #87                 // String LaunchSpecification.NetworkInterface.
    1604: invokevirtual #40                 // Method java/lang/StringBuilder.append:(Ljava/lang/String;)Ljava/lang/StringBuilder;
    1607: iload         9
    1609: invokevirtual #41                 // Method java/lang/StringBuilder.append:(I)Ljava/lang/StringBuilder;
    1612: ldc           #108                // String .Group.
    1614: invokevirtual #40                 // Method java/lang/StringBuilder.append:(Ljava/lang/String;)Ljava/lang/StringBuilder;
    1617: iload         14
    1619: invokevirtual #41                 // Method java/lang/StringBuilder.append:(I)Ljava/lang/StringBuilder;
    1622: invokevirtual #42                 // Method java/lang/StringBuilder.toString:()Ljava/lang/String;
    1625: aload         16
    1627: invokestatic  #23                 // Method com/amazonaws/util/StringUtils.fromString:(Ljava/lang/String;)Ljava/lang/String;
    1630: invokeinterface #10,  3           // InterfaceMethod com/amazonaws/Request.addParameter:(Ljava/lang/String;Ljava/lang/String;)V
    1635: iinc          14, 1
    1638: goto          1567
    1641: aload         11
    1643: invokevirtual #109                // Method com/amazonaws/services/ec2/model/ScheduledInstancesNetworkInterface.getDeleteOnTermination:()Ljava/lang/Boolean;
    1646: ifnull        1688
    1649: aload_2
    1650: new           #37                 // class java/lang/StringBuilder
    1653: dup
    1654: invokespecial #38                 // Method java/lang/StringBuilder."<init>":()V
    1657: ldc           #87                 // String LaunchSpecification.NetworkInterface.
    1659: invokevirtual #40                 // Method java/lang/StringBuilder.append:(Ljava/lang/String;)Ljava/lang/StringBuilder;
    1662: iload         9
    1664: invokevirtual #41                 // Method java/lang/StringBuilder.append:(I)Ljava/lang/StringBuilder;
    1667: ldc           #110                // String .DeleteOnTermination
    1669: invokevirtual #40                 // Method java/lang/StringBuilder.append:(Ljava/lang/String;)Ljava/lang/StringBuilder;
    1672: invokevirtual #42                 // Method java/lang/StringBuilder.toString:()Ljava/lang/String;
    1675: aload         11
    1677: invokevirtual #109                // Method com/amazonaws/services/ec2/model/ScheduledInstancesNetworkInterface.getDeleteOnTermination:()Ljava/lang/Boolean;
    1680: invokestatic  #72                 // Method com/amazonaws/util/StringUtils.fromBoolean:(Ljava/lang/Boolean;)Ljava/lang/String;
    1683: invokeinterface #10,  3           // InterfaceMethod com/amazonaws/Request.addParameter:(Ljava/lang/String;Ljava/lang/String;)V
    1688: iinc          9, 1
    1691: goto          1002
    1694: aload_3
    1695: invokevirtual #111                // Method com/amazonaws/services/ec2/model/ScheduledInstancesLaunchSpecification.getIamInstanceProfile:()Lcom/amazonaws/services/ec2/model/ScheduledInstancesIamInstanceProfile;
    1698: astore        9
    1700: aload         9
    1702: ifnull        1753
    1705: aload         9
    1707: invokevirtual #112                // Method com/amazonaws/services/ec2/model/ScheduledInstancesIamInstanceProfile.getArn:()Ljava/lang/String;
    1710: ifnull        1729
    1713: aload_2
    1714: ldc           #113                // String LaunchSpecification.IamInstanceProfile.Arn
    1716: aload         9
    1718: invokevirtual #112                // Method com/amazonaws/services/ec2/model/ScheduledInstancesIamInstanceProfile.getArn:()Ljava/lang/String;
    1721: invokestatic  #23                 // Method com/amazonaws/util/StringUtils.fromString:(Ljava/lang/String;)Ljava/lang/String;
    1724: invokeinterface #10,  3           // InterfaceMethod com/amazonaws/Request.addParameter:(Ljava/lang/String;Ljava/lang/String;)V
    1729: aload         9
    1731: invokevirtual #114                // Method com/amazonaws/services/ec2/model/ScheduledInstancesIamInstanceProfile.getName:()Ljava/lang/String;
    1734: ifnull        1753
    1737: aload_2
    1738: ldc           #115                // String LaunchSpecification.IamInstanceProfile.Name
    1740: aload         9
    1742: invokevirtual #114                // Method com/amazonaws/services/ec2/model/ScheduledInstancesIamInstanceProfile.getName:()Ljava/lang/String;
    1745: invokestatic  #23                 // Method com/amazonaws/util/StringUtils.fromString:(Ljava/lang/String;)Ljava/lang/String;
    1748: invokeinterface #10,  3           // InterfaceMethod com/amazonaws/Request.addParameter:(Ljava/lang/String;Ljava/lang/String;)V
    1753: aload_3
    1754: invokevirtual #116                // Method com/amazonaws/services/ec2/model/ScheduledInstancesLaunchSpecification.getEbsOptimized:()Ljava/lang/Boolean;
    1757: ifnull        1775
    1760: aload_2
    1761: ldc           #117                // String LaunchSpecification.EbsOptimized
    1763: aload_3
    1764: invokevirtual #116                // Method com/amazonaws/services/ec2/model/ScheduledInstancesLaunchSpecification.getEbsOptimized:()Ljava/lang/Boolean;
    1767: invokestatic  #72                 // Method com/amazonaws/util/StringUtils.fromBoolean:(Ljava/lang/Boolean;)Ljava/lang/String;
    1770: invokeinterface #10,  3           // InterfaceMethod com/amazonaws/Request.addParameter:(Ljava/lang/String;Ljava/lang/String;)V
    1775: aload_2
    1776: areturn

  public java.lang.Object marshall(java.lang.Object) throws java.lang.Exception;
    Code:
       0: aload_0
       1: aload_1
       2: checkcast     #118                // class com/amazonaws/services/ec2/model/RunScheduledInstancesRequest
       5: invokevirtual #119                // Method marshall:(Lcom/amazonaws/services/ec2/model/RunScheduledInstancesRequest;)Lcom/amazonaws/Request;
       8: areturn
}
