Compiled from "VolumeStaxUnmarshaller.java"
public class com.amazonaws.services.ec2.model.transform.VolumeStaxUnmarshaller implements com.amazonaws.transform.Unmarshaller<com.amazonaws.services.ec2.model.Volume, com.amazonaws.transform.StaxUnmarshallerContext> {
  private static com.amazonaws.services.ec2.model.transform.VolumeStaxUnmarshaller instance;

  public com.amazonaws.services.ec2.model.transform.VolumeStaxUnmarshaller();
    Code:
       0: aload_0
       1: invokespecial #1                  // Method java/lang/Object."<init>":()V
       4: return

  public com.amazonaws.services.ec2.model.Volume unmarshall(com.amazonaws.transform.StaxUnmarshallerContext) throws java.lang.Exception;
    Code:
       0: new           #2                  // class com/amazonaws/services/ec2/model/Volume
       3: dup
       4: invokespecial #3                  // Method com/amazonaws/services/ec2/model/Volume."<init>":()V
       7: astore_2
       8: aload_1
       9: invokevirtual #4                  // Method com/amazonaws/transform/StaxUnmarshallerContext.getCurrentDepth:()I
      12: istore_3
      13: iload_3
      14: iconst_1
      15: iadd
      16: istore        4
      18: aload_1
      19: invokevirtual #5                  // Method com/amazonaws/transform/StaxUnmarshallerContext.isStartOfDocument:()Z
      22: ifeq          28
      25: iinc          4, 1
      28: aload_1
      29: invokevirtual #6                  // Method com/amazonaws/transform/StaxUnmarshallerContext.nextEvent:()Ljavax/xml/stream/events/XMLEvent;
      32: astore        5
      34: aload         5
      36: invokeinterface #7,  1            // InterfaceMethod javax/xml/stream/events/XMLEvent.isEndDocument:()Z
      41: ifeq          46
      44: aload_2
      45: areturn
      46: aload         5
      48: invokeinterface #8,  1            // InterfaceMethod javax/xml/stream/events/XMLEvent.isAttribute:()Z
      53: ifne          66
      56: aload         5
      58: invokeinterface #9,  1            // InterfaceMethod javax/xml/stream/events/XMLEvent.isStartElement:()Z
      63: ifeq          382
      66: aload_1
      67: ldc           #10                 // String volumeId
      69: iload         4
      71: invokevirtual #11                 // Method com/amazonaws/transform/StaxUnmarshallerContext.testExpression:(Ljava/lang/String;I)Z
      74: ifeq          91
      77: aload_2
      78: invokestatic  #12                 // Method com/amazonaws/transform/SimpleTypeStaxUnmarshallers$StringStaxUnmarshaller.getInstance:()Lcom/amazonaws/transform/SimpleTypeStaxUnmarshallers$StringStaxUnmarshaller;
      81: aload_1
      82: invokevirtual #13                 // Method com/amazonaws/transform/SimpleTypeStaxUnmarshallers$StringStaxUnmarshaller.unmarshall:(Lcom/amazonaws/transform/StaxUnmarshallerContext;)Ljava/lang/String;
      85: invokevirtual #14                 // Method com/amazonaws/services/ec2/model/Volume.setVolumeId:(Ljava/lang/String;)V
      88: goto          28
      91: aload_1
      92: ldc           #15                 // String size
      94: iload         4
      96: invokevirtual #11                 // Method com/amazonaws/transform/StaxUnmarshallerContext.testExpression:(Ljava/lang/String;I)Z
      99: ifeq          116
     102: aload_2
     103: invokestatic  #16                 // Method com/amazonaws/transform/SimpleTypeStaxUnmarshallers$IntegerStaxUnmarshaller.getInstance:()Lcom/amazonaws/transform/SimpleTypeStaxUnmarshallers$IntegerStaxUnmarshaller;
     106: aload_1
     107: invokevirtual #17                 // Method com/amazonaws/transform/SimpleTypeStaxUnmarshallers$IntegerStaxUnmarshaller.unmarshall:(Lcom/amazonaws/transform/StaxUnmarshallerContext;)Ljava/lang/Integer;
     110: invokevirtual #18                 // Method com/amazonaws/services/ec2/model/Volume.setSize:(Ljava/lang/Integer;)V
     113: goto          28
     116: aload_1
     117: ldc           #19                 // String snapshotId
     119: iload         4
     121: invokevirtual #11                 // Method com/amazonaws/transform/StaxUnmarshallerContext.testExpression:(Ljava/lang/String;I)Z
     124: ifeq          141
     127: aload_2
     128: invokestatic  #12                 // Method com/amazonaws/transform/SimpleTypeStaxUnmarshallers$StringStaxUnmarshaller.getInstance:()Lcom/amazonaws/transform/SimpleTypeStaxUnmarshallers$StringStaxUnmarshaller;
     131: aload_1
     132: invokevirtual #13                 // Method com/amazonaws/transform/SimpleTypeStaxUnmarshallers$StringStaxUnmarshaller.unmarshall:(Lcom/amazonaws/transform/StaxUnmarshallerContext;)Ljava/lang/String;
     135: invokevirtual #20                 // Method com/amazonaws/services/ec2/model/Volume.setSnapshotId:(Ljava/lang/String;)V
     138: goto          28
     141: aload_1
     142: ldc           #21                 // String availabilityZone
     144: iload         4
     146: invokevirtual #11                 // Method com/amazonaws/transform/StaxUnmarshallerContext.testExpression:(Ljava/lang/String;I)Z
     149: ifeq          166
     152: aload_2
     153: invokestatic  #12                 // Method com/amazonaws/transform/SimpleTypeStaxUnmarshallers$StringStaxUnmarshaller.getInstance:()Lcom/amazonaws/transform/SimpleTypeStaxUnmarshallers$StringStaxUnmarshaller;
     156: aload_1
     157: invokevirtual #13                 // Method com/amazonaws/transform/SimpleTypeStaxUnmarshallers$StringStaxUnmarshaller.unmarshall:(Lcom/amazonaws/transform/StaxUnmarshallerContext;)Ljava/lang/String;
     160: invokevirtual #22                 // Method com/amazonaws/services/ec2/model/Volume.setAvailabilityZone:(Ljava/lang/String;)V
     163: goto          28
     166: aload_1
     167: ldc           #23                 // String status
     169: iload         4
     171: invokevirtual #11                 // Method com/amazonaws/transform/StaxUnmarshallerContext.testExpression:(Ljava/lang/String;I)Z
     174: ifeq          191
     177: aload_2
     178: invokestatic  #12                 // Method com/amazonaws/transform/SimpleTypeStaxUnmarshallers$StringStaxUnmarshaller.getInstance:()Lcom/amazonaws/transform/SimpleTypeStaxUnmarshallers$StringStaxUnmarshaller;
     181: aload_1
     182: invokevirtual #13                 // Method com/amazonaws/transform/SimpleTypeStaxUnmarshallers$StringStaxUnmarshaller.unmarshall:(Lcom/amazonaws/transform/StaxUnmarshallerContext;)Ljava/lang/String;
     185: invokevirtual #24                 // Method com/amazonaws/services/ec2/model/Volume.setState:(Ljava/lang/String;)V
     188: goto          28
     191: aload_1
     192: ldc           #25                 // String createTime
     194: iload         4
     196: invokevirtual #11                 // Method com/amazonaws/transform/StaxUnmarshallerContext.testExpression:(Ljava/lang/String;I)Z
     199: ifeq          216
     202: aload_2
     203: invokestatic  #26                 // Method com/amazonaws/transform/SimpleTypeStaxUnmarshallers$DateStaxUnmarshaller.getInstance:()Lcom/amazonaws/transform/SimpleTypeStaxUnmarshallers$DateStaxUnmarshaller;
     206: aload_1
     207: invokevirtual #27                 // Method com/amazonaws/transform/SimpleTypeStaxUnmarshallers$DateStaxUnmarshaller.unmarshall:(Lcom/amazonaws/transform/StaxUnmarshallerContext;)Ljava/util/Date;
     210: invokevirtual #28                 // Method com/amazonaws/services/ec2/model/Volume.setCreateTime:(Ljava/util/Date;)V
     213: goto          28
     216: aload_1
     217: ldc           #29                 // String attachmentSet/item
     219: iload         4
     221: invokevirtual #11                 // Method com/amazonaws/transform/StaxUnmarshallerContext.testExpression:(Ljava/lang/String;I)Z
     224: ifeq          249
     227: aload_2
     228: iconst_1
     229: anewarray     #30                 // class com/amazonaws/services/ec2/model/VolumeAttachment
     232: dup
     233: iconst_0
     234: invokestatic  #31                 // Method com/amazonaws/services/ec2/model/transform/VolumeAttachmentStaxUnmarshaller.getInstance:()Lcom/amazonaws/services/ec2/model/transform/VolumeAttachmentStaxUnmarshaller;
     237: aload_1
     238: invokevirtual #32                 // Method com/amazonaws/services/ec2/model/transform/VolumeAttachmentStaxUnmarshaller.unmarshall:(Lcom/amazonaws/transform/StaxUnmarshallerContext;)Lcom/amazonaws/services/ec2/model/VolumeAttachment;
     241: aastore
     242: invokevirtual #33                 // Method com/amazonaws/services/ec2/model/Volume.withAttachments:([Lcom/amazonaws/services/ec2/model/VolumeAttachment;)Lcom/amazonaws/services/ec2/model/Volume;
     245: pop
     246: goto          28
     249: aload_1
     250: ldc           #34                 // String tagSet/item
     252: iload         4
     254: invokevirtual #11                 // Method com/amazonaws/transform/StaxUnmarshallerContext.testExpression:(Ljava/lang/String;I)Z
     257: ifeq          282
     260: aload_2
     261: iconst_1
     262: anewarray     #35                 // class com/amazonaws/services/ec2/model/Tag
     265: dup
     266: iconst_0
     267: invokestatic  #36                 // Method com/amazonaws/services/ec2/model/transform/TagStaxUnmarshaller.getInstance:()Lcom/amazonaws/services/ec2/model/transform/TagStaxUnmarshaller;
     270: aload_1
     271: invokevirtual #37                 // Method com/amazonaws/services/ec2/model/transform/TagStaxUnmarshaller.unmarshall:(Lcom/amazonaws/transform/StaxUnmarshallerContext;)Lcom/amazonaws/services/ec2/model/Tag;
     274: aastore
     275: invokevirtual #38                 // Method com/amazonaws/services/ec2/model/Volume.withTags:([Lcom/amazonaws/services/ec2/model/Tag;)Lcom/amazonaws/services/ec2/model/Volume;
     278: pop
     279: goto          28
     282: aload_1
     283: ldc           #39                 // String volumeType
     285: iload         4
     287: invokevirtual #11                 // Method com/amazonaws/transform/StaxUnmarshallerContext.testExpression:(Ljava/lang/String;I)Z
     290: ifeq          307
     293: aload_2
     294: invokestatic  #12                 // Method com/amazonaws/transform/SimpleTypeStaxUnmarshallers$StringStaxUnmarshaller.getInstance:()Lcom/amazonaws/transform/SimpleTypeStaxUnmarshallers$StringStaxUnmarshaller;
     297: aload_1
     298: invokevirtual #13                 // Method com/amazonaws/transform/SimpleTypeStaxUnmarshallers$StringStaxUnmarshaller.unmarshall:(Lcom/amazonaws/transform/StaxUnmarshallerContext;)Ljava/lang/String;
     301: invokevirtual #40                 // Method com/amazonaws/services/ec2/model/Volume.setVolumeType:(Ljava/lang/String;)V
     304: goto          28
     307: aload_1
     308: ldc           #41                 // String iops
     310: iload         4
     312: invokevirtual #11                 // Method com/amazonaws/transform/StaxUnmarshallerContext.testExpression:(Ljava/lang/String;I)Z
     315: ifeq          332
     318: aload_2
     319: invokestatic  #16                 // Method com/amazonaws/transform/SimpleTypeStaxUnmarshallers$IntegerStaxUnmarshaller.getInstance:()Lcom/amazonaws/transform/SimpleTypeStaxUnmarshallers$IntegerStaxUnmarshaller;
     322: aload_1
     323: invokevirtual #17                 // Method com/amazonaws/transform/SimpleTypeStaxUnmarshallers$IntegerStaxUnmarshaller.unmarshall:(Lcom/amazonaws/transform/StaxUnmarshallerContext;)Ljava/lang/Integer;
     326: invokevirtual #42                 // Method com/amazonaws/services/ec2/model/Volume.setIops:(Ljava/lang/Integer;)V
     329: goto          28
     332: aload_1
     333: ldc           #43                 // String encrypted
     335: iload         4
     337: invokevirtual #11                 // Method com/amazonaws/transform/StaxUnmarshallerContext.testExpression:(Ljava/lang/String;I)Z
     340: ifeq          357
     343: aload_2
     344: invokestatic  #44                 // Method com/amazonaws/transform/SimpleTypeStaxUnmarshallers$BooleanStaxUnmarshaller.getInstance:()Lcom/amazonaws/transform/SimpleTypeStaxUnmarshallers$BooleanStaxUnmarshaller;
     347: aload_1
     348: invokevirtual #45                 // Method com/amazonaws/transform/SimpleTypeStaxUnmarshallers$BooleanStaxUnmarshaller.unmarshall:(Lcom/amazonaws/transform/StaxUnmarshallerContext;)Ljava/lang/Boolean;
     351: invokevirtual #46                 // Method com/amazonaws/services/ec2/model/Volume.setEncrypted:(Ljava/lang/Boolean;)V
     354: goto          28
     357: aload_1
     358: ldc           #47                 // String kmsKeyId
     360: iload         4
     362: invokevirtual #11                 // Method com/amazonaws/transform/StaxUnmarshallerContext.testExpression:(Ljava/lang/String;I)Z
     365: ifeq          402
     368: aload_2
     369: invokestatic  #12                 // Method com/amazonaws/transform/SimpleTypeStaxUnmarshallers$StringStaxUnmarshaller.getInstance:()Lcom/amazonaws/transform/SimpleTypeStaxUnmarshallers$StringStaxUnmarshaller;
     372: aload_1
     373: invokevirtual #13                 // Method com/amazonaws/transform/SimpleTypeStaxUnmarshallers$StringStaxUnmarshaller.unmarshall:(Lcom/amazonaws/transform/StaxUnmarshallerContext;)Ljava/lang/String;
     376: invokevirtual #48                 // Method com/amazonaws/services/ec2/model/Volume.setKmsKeyId:(Ljava/lang/String;)V
     379: goto          28
     382: aload         5
     384: invokeinterface #49,  1           // InterfaceMethod javax/xml/stream/events/XMLEvent.isEndElement:()Z
     389: ifeq          402
     392: aload_1
     393: invokevirtual #4                  // Method com/amazonaws/transform/StaxUnmarshallerContext.getCurrentDepth:()I
     396: iload_3
     397: if_icmpge     402
     400: aload_2
     401: areturn
     402: goto          28

  public static com.amazonaws.services.ec2.model.transform.VolumeStaxUnmarshaller getInstance();
    Code:
       0: getstatic     #50                 // Field instance:Lcom/amazonaws/services/ec2/model/transform/VolumeStaxUnmarshaller;
       3: ifnonnull     16
       6: new           #51                 // class com/amazonaws/services/ec2/model/transform/VolumeStaxUnmarshaller
       9: dup
      10: invokespecial #52                 // Method "<init>":()V
      13: putstatic     #50                 // Field instance:Lcom/amazonaws/services/ec2/model/transform/VolumeStaxUnmarshaller;
      16: getstatic     #50                 // Field instance:Lcom/amazonaws/services/ec2/model/transform/VolumeStaxUnmarshaller;
      19: areturn

  public java.lang.Object unmarshall(java.lang.Object) throws java.lang.Exception;
    Code:
       0: aload_0
       1: aload_1
       2: checkcast     #53                 // class com/amazonaws/transform/StaxUnmarshallerContext
       5: invokevirtual #54                 // Method unmarshall:(Lcom/amazonaws/transform/StaxUnmarshallerContext;)Lcom/amazonaws/services/ec2/model/Volume;
       8: areturn
}
