Compiled from "ParsedRaDeploymentProcessor.java"
public class org.jboss.as.connector.deployers.ra.processors.ParsedRaDeploymentProcessor implements org.jboss.as.server.deployment.DeploymentUnitProcessor {
  public org.jboss.as.connector.deployers.ra.processors.ParsedRaDeploymentProcessor();
    Code:
       0: aload_0
       1: invokespecial #1                  // Method java/lang/Object."<init>":()V
       4: return

  public void deploy(org.jboss.as.server.deployment.DeploymentPhaseContext) throws org.jboss.as.server.deployment.DeploymentUnitProcessingException;
    Code:
       0: aload_1
       1: invokeinterface #2,  1            // InterfaceMethod org/jboss/as/server/deployment/DeploymentPhaseContext.getDeploymentUnit:()Lorg/jboss/as/server/deployment/DeploymentUnit;
       6: getstatic     #3                  // Field org/jboss/as/connector/metadata/xmldescriptors/ConnectorXmlDescriptor.ATTACHMENT_KEY:Lorg/jboss/as/server/deployment/AttachmentKey;
       9: invokeinterface #4,  2            // InterfaceMethod org/jboss/as/server/deployment/DeploymentUnit.getAttachment:(Lorg/jboss/as/server/deployment/AttachmentKey;)Ljava/lang/Object;
      14: checkcast     #5                  // class org/jboss/as/connector/metadata/xmldescriptors/ConnectorXmlDescriptor
      17: astore_2
      18: aload_1
      19: invokeinterface #2,  1            // InterfaceMethod org/jboss/as/server/deployment/DeploymentPhaseContext.getDeploymentUnit:()Lorg/jboss/as/server/deployment/DeploymentUnit;
      24: getstatic     #6                  // Field org/jboss/as/server/deployment/DeploymentModelUtils.MUTABLE_REGISTRATION_ATTACHMENT:Lorg/jboss/as/server/deployment/AttachmentKey;
      27: invokeinterface #4,  2            // InterfaceMethod org/jboss/as/server/deployment/DeploymentUnit.getAttachment:(Lorg/jboss/as/server/deployment/AttachmentKey;)Ljava/lang/Object;
      32: checkcast     #7                  // class org/jboss/as/controller/registry/ManagementResourceRegistration
      35: astore        4
      37: aload_1
      38: invokeinterface #2,  1            // InterfaceMethod org/jboss/as/server/deployment/DeploymentPhaseContext.getDeploymentUnit:()Lorg/jboss/as/server/deployment/DeploymentUnit;
      43: getstatic     #8                  // Field org/jboss/as/server/deployment/DeploymentModelUtils.DEPLOYMENT_RESOURCE:Lorg/jboss/as/server/deployment/AttachmentKey;
      46: invokeinterface #4,  2            // InterfaceMethod org/jboss/as/server/deployment/DeploymentUnit.getAttachment:(Lorg/jboss/as/server/deployment/AttachmentKey;)Ljava/lang/Object;
      51: checkcast     #9                  // class org/jboss/as/controller/registry/Resource
      54: astore        5
      56: aload_2
      57: ifnonnull     61
      60: return
      61: aload_1
      62: invokeinterface #10,  1           // InterfaceMethod org/jboss/as/server/deployment/DeploymentPhaseContext.getServiceTarget:()Lorg/jboss/msc/service/ServiceTarget;
      67: astore        6
      69: aload_1
      70: invokeinterface #2,  1            // InterfaceMethod org/jboss/as/server/deployment/DeploymentPhaseContext.getDeploymentUnit:()Lorg/jboss/as/server/deployment/DeploymentUnit;
      75: astore        7
      77: aload         7
      79: invokeinterface #11,  1           // InterfaceMethod org/jboss/as/server/deployment/DeploymentUnit.getParent:()Lorg/jboss/as/server/deployment/DeploymentUnit;
      84: ifnull        113
      87: aload         4
      89: iconst_1
      90: anewarray     #12                 // class org/jboss/as/controller/PathElement
      93: dup
      94: iconst_0
      95: ldc           #13                 // String subdeployment
      97: invokestatic  #14                 // Method org/jboss/as/controller/PathElement.pathElement:(Ljava/lang/String;)Lorg/jboss/as/controller/PathElement;
     100: aastore
     101: invokestatic  #15                 // Method org/jboss/as/controller/PathAddress.pathAddress:([Lorg/jboss/as/controller/PathElement;)Lorg/jboss/as/controller/PathAddress;
     104: invokeinterface #16,  2           // InterfaceMethod org/jboss/as/controller/registry/ManagementResourceRegistration.getSubModel:(Lorg/jboss/as/controller/PathAddress;)Lorg/jboss/as/controller/registry/ManagementResourceRegistration;
     109: astore_3
     110: goto          116
     113: aload         4
     115: astore_3
     116: aload         7
     118: getstatic     #17                 // Field org/jboss/as/connector/metadata/xmldescriptors/IronJacamarXmlDescriptor.ATTACHMENT_KEY:Lorg/jboss/as/server/deployment/AttachmentKey;
     121: invokeinterface #4,  2            // InterfaceMethod org/jboss/as/server/deployment/DeploymentUnit.getAttachment:(Lorg/jboss/as/server/deployment/AttachmentKey;)Ljava/lang/Object;
     126: checkcast     #18                 // class org/jboss/as/connector/metadata/xmldescriptors/IronJacamarXmlDescriptor
     129: astore        8
     131: aload         7
     133: getstatic     #19                 // Field org/jboss/as/server/deployment/Attachments.MODULE:Lorg/jboss/as/server/deployment/AttachmentKey;
     136: invokeinterface #4,  2            // InterfaceMethod org/jboss/as/server/deployment/DeploymentUnit.getAttachment:(Lorg/jboss/as/server/deployment/AttachmentKey;)Ljava/lang/Object;
     141: checkcast     #20                 // class org/jboss/modules/Module
     144: astore        9
     146: aload         9
     148: ifnonnull     166
     151: getstatic     #21                 // Field org/jboss/as/connector/logging/ConnectorLogger.ROOT_LOGGER:Lorg/jboss/as/connector/logging/ConnectorLogger;
     154: aload_1
     155: invokeinterface #2,  1            // InterfaceMethod org/jboss/as/server/deployment/DeploymentPhaseContext.getDeploymentUnit:()Lorg/jboss/as/server/deployment/DeploymentUnit;
     160: invokeinterface #22,  2           // InterfaceMethod org/jboss/as/connector/logging/ConnectorLogger.failedToGetModuleAttachment:(Lorg/jboss/as/server/deployment/DeploymentUnit;)Lorg/jboss/as/server/deployment/DeploymentUnitProcessingException;
     165: athrow
     166: getstatic     #23                 // Field org/jboss/as/connector/logging/ConnectorLogger.DEPLOYMENT_CONNECTOR_LOGGER:Lorg/jboss/as/connector/logging/ConnectorLogger;
     169: ldc           #24                 // String ParsedRaDeploymentProcessor: Processing=%s
     171: aload         7
     173: invokeinterface #25,  3           // InterfaceMethod org/jboss/as/connector/logging/ConnectorLogger.debugf:(Ljava/lang/String;Ljava/lang/Object;)V
     178: aload         9
     180: invokevirtual #26                 // Method org/jboss/modules/Module.getClassLoader:()Lorg/jboss/modules/ModuleClassLoader;
     183: astore        10
     185: aload         7
     187: invokestatic  #27                 // Method org/jboss/as/server/deployment/annotation/AnnotationIndexUtils.getAnnotationIndexes:(Lorg/jboss/as/server/deployment/DeploymentUnit;)Ljava/util/Map;
     190: astore        11
     192: aload_2
     193: aload         8
     195: aload         10
     197: aload         6
     199: aload         11
     201: aload         7
     203: invokeinterface #28,  1           // InterfaceMethod org/jboss/as/server/deployment/DeploymentUnit.getServiceName:()Lorg/jboss/msc/service/ServiceName;
     208: aload_3
     209: aload         5
     211: invokestatic  #29                 // Method process:(Lorg/jboss/as/connector/metadata/xmldescriptors/ConnectorXmlDescriptor;Lorg/jboss/as/connector/metadata/xmldescriptors/IronJacamarXmlDescriptor;Ljava/lang/ClassLoader;Lorg/jboss/msc/service/ServiceTarget;Ljava/util/Map;Lorg/jboss/msc/service/ServiceName;Lorg/jboss/as/controller/registry/ManagementResourceRegistration;Lorg/jboss/as/controller/registry/Resource;)Lorg/jboss/msc/service/ServiceBuilder;
     214: astore        12
     216: aload         12
     218: ifnull        334
     221: aconst_null
     222: astore        13
     224: aload         8
     226: ifnull        262
     229: aload         8
     231: invokevirtual #30                 // Method org/jboss/as/connector/metadata/xmldescriptors/IronJacamarXmlDescriptor.getIronJacamar:()Lorg/jboss/jca/common/api/metadata/resourceadapter/Activation;
     234: ifnull        262
     237: aload         8
     239: invokevirtual #30                 // Method org/jboss/as/connector/metadata/xmldescriptors/IronJacamarXmlDescriptor.getIronJacamar:()Lorg/jboss/jca/common/api/metadata/resourceadapter/Activation;
     242: invokeinterface #31,  1           // InterfaceMethod org/jboss/jca/common/api/metadata/resourceadapter/Activation.getBootstrapContext:()Ljava/lang/String;
     247: ifnull        262
     250: aload         8
     252: invokevirtual #30                 // Method org/jboss/as/connector/metadata/xmldescriptors/IronJacamarXmlDescriptor.getIronJacamar:()Lorg/jboss/jca/common/api/metadata/resourceadapter/Activation;
     255: invokeinterface #31,  1           // InterfaceMethod org/jboss/jca/common/api/metadata/resourceadapter/Activation.getBootstrapContext:()Ljava/lang/String;
     260: astore        13
     262: aload         13
     264: ifnonnull     271
     267: ldc           #32                 // String default
     269: astore        13
     271: aload_3
     272: invokeinterface #33,  1           // InterfaceMethod org/jboss/as/controller/registry/ManagementResourceRegistration.isAllowsOverride:()Z
     277: ifeq          318
     280: aload_3
     281: aload         7
     283: invokeinterface #34,  1           // InterfaceMethod org/jboss/as/server/deployment/DeploymentUnit.getName:()Ljava/lang/String;
     288: invokeinterface #35,  2           // InterfaceMethod org/jboss/as/controller/registry/ManagementResourceRegistration.getOverrideModel:(Ljava/lang/String;)Lorg/jboss/as/controller/registry/ManagementResourceRegistration;
     293: ifnonnull     318
     296: aload_3
     297: aload         7
     299: invokeinterface #34,  1           // InterfaceMethod org/jboss/as/server/deployment/DeploymentUnit.getName:()Ljava/lang/String;
     304: new           #36                 // class org/jboss/as/connector/deployers/ra/processors/ParsedRaDeploymentProcessor$1
     307: dup
     308: aload_0
     309: invokespecial #37                 // Method org/jboss/as/connector/deployers/ra/processors/ParsedRaDeploymentProcessor$1."<init>":(Lorg/jboss/as/connector/deployers/ra/processors/ParsedRaDeploymentProcessor;)V
     312: invokeinterface #38,  3           // InterfaceMethod org/jboss/as/controller/registry/ManagementResourceRegistration.registerOverrideModel:(Ljava/lang/String;Lorg/jboss/as/controller/descriptions/OverrideDescriptionProvider;)Lorg/jboss/as/controller/registry/ManagementResourceRegistration;
     317: pop
     318: aload         12
     320: getstatic     #39                 // Field org/jboss/msc/service/ServiceController$Mode.ACTIVE:Lorg/jboss/msc/service/ServiceController$Mode;
     323: invokeinterface #40,  2           // InterfaceMethod org/jboss/msc/service/ServiceBuilder.setInitialMode:(Lorg/jboss/msc/service/ServiceController$Mode;)Lorg/jboss/msc/service/ServiceBuilder;
     328: invokeinterface #41,  1           // InterfaceMethod org/jboss/msc/service/ServiceBuilder.install:()Lorg/jboss/msc/service/ServiceController;
     333: pop
     334: return

  public static org.jboss.msc.service.ServiceBuilder process(org.jboss.as.connector.metadata.xmldescriptors.ConnectorXmlDescriptor, org.jboss.as.connector.metadata.xmldescriptors.IronJacamarXmlDescriptor, java.lang.ClassLoader, org.jboss.msc.service.ServiceTarget, java.util.Map<org.jboss.as.server.deployment.module.ResourceRoot, org.jboss.jandex.Index>, org.jboss.msc.service.ServiceName, org.jboss.as.controller.registry.ManagementResourceRegistration, org.jboss.as.controller.registry.Resource) throws org.jboss.as.server.deployment.DeploymentUnitProcessingException;
    Code:
       0: aload_0
       1: ifnull        11
       4: aload_0
       5: invokevirtual #42                 // Method org/jboss/as/connector/metadata/xmldescriptors/ConnectorXmlDescriptor.getConnector:()Lorg/jboss/jca/common/api/metadata/spec/Connector;
       8: goto          12
      11: aconst_null
      12: astore        8
      14: aload_1
      15: ifnull        25
      18: aload_1
      19: invokevirtual #30                 // Method org/jboss/as/connector/metadata/xmldescriptors/IronJacamarXmlDescriptor.getIronJacamar:()Lorg/jboss/jca/common/api/metadata/resourceadapter/Activation;
      22: goto          26
      25: aconst_null
      26: astore        9
      28: new           #43                 // class org/jboss/jca/common/annotations/Annotations
      31: dup
      32: invokespecial #44                 // Method org/jboss/jca/common/annotations/Annotations."<init>":()V
      35: astore        10
      37: aload         4
      39: ifnull        165
      42: aload         4
      44: invokeinterface #45,  1           // InterfaceMethod java/util/Map.size:()I
      49: ifle          165
      52: getstatic     #23                 // Field org/jboss/as/connector/logging/ConnectorLogger.DEPLOYMENT_CONNECTOR_LOGGER:Lorg/jboss/as/connector/logging/ConnectorLogger;
      55: ldc           #46                 // String ParsedRaDeploymentProcessor: Found %d annotationIndexes
      57: aload         4
      59: invokeinterface #45,  1           // InterfaceMethod java/util/Map.size:()I
      64: invokeinterface #47,  3           // InterfaceMethod org/jboss/as/connector/logging/ConnectorLogger.debugf:(Ljava/lang/String;I)V
      69: aload         4
      71: invokeinterface #48,  1           // InterfaceMethod java/util/Map.values:()Ljava/util/Collection;
      76: invokeinterface #49,  1           // InterfaceMethod java/util/Collection.iterator:()Ljava/util/Iterator;
      81: astore        11
      83: aload         11
      85: invokeinterface #50,  1           // InterfaceMethod java/util/Iterator.hasNext:()Z
      90: ifeq          165
      93: aload         11
      95: invokeinterface #51,  1           // InterfaceMethod java/util/Iterator.next:()Ljava/lang/Object;
     100: checkcast     #52                 // class org/jboss/jandex/Index
     103: astore        12
     105: aload         12
     107: invokevirtual #53                 // Method org/jboss/jandex/Index.getKnownClasses:()Ljava/util/Collection;
     110: ifnull        162
     113: aload         12
     115: invokevirtual #53                 // Method org/jboss/jandex/Index.getKnownClasses:()Ljava/util/Collection;
     118: invokeinterface #54,  1           // InterfaceMethod java/util/Collection.size:()I
     123: ifle          162
     126: new           #55                 // class org/jboss/as/connector/annotations/repository/jandex/JandexAnnotationRepositoryImpl
     129: dup
     130: aload         12
     132: aload_2
     133: invokespecial #56                 // Method org/jboss/as/connector/annotations/repository/jandex/JandexAnnotationRepositoryImpl."<init>":(Lorg/jboss/jandex/Index;Ljava/lang/ClassLoader;)V
     136: astore        13
     138: aload         10
     140: aload         8
     142: aload         13
     144: aload_2
     145: invokevirtual #57                 // Method org/jboss/jca/common/annotations/Annotations.merge:(Lorg/jboss/jca/common/api/metadata/spec/Connector;Lorg/jboss/jca/common/spi/annotations/repository/AnnotationRepository;Ljava/lang/ClassLoader;)Lorg/jboss/jca/common/api/metadata/spec/Connector;
     148: astore        8
     150: getstatic     #23                 // Field org/jboss/as/connector/logging/ConnectorLogger.DEPLOYMENT_CONNECTOR_LOGGER:Lorg/jboss/as/connector/logging/ConnectorLogger;
     153: ldc           #58                 // String ParsedRaDeploymentProcessor: CMD=%s
     155: aload         8
     157: invokeinterface #25,  3           // InterfaceMethod org/jboss/as/connector/logging/ConnectorLogger.debugf:(Ljava/lang/String;Ljava/lang/Object;)V
     162: goto          83
     165: aload         4
     167: ifnull        180
     170: aload         4
     172: invokeinterface #45,  1           // InterfaceMethod java/util/Map.size:()I
     177: ifne          194
     180: getstatic     #23                 // Field org/jboss/as/connector/logging/ConnectorLogger.DEPLOYMENT_CONNECTOR_LOGGER:Lorg/jboss/as/connector/logging/ConnectorLogger;
     183: ldc           #59                 // String ParsedRaDeploymentProcessor: Found 0 annotationIndexes
     185: iconst_0
     186: anewarray     #60                 // class java/lang/Object
     189: invokeinterface #61,  3           // InterfaceMethod org/jboss/as/connector/logging/ConnectorLogger.debugf:(Ljava/lang/String;[Ljava/lang/Object;)V
     194: aload         8
     196: ifnull        222
     199: aload         8
     201: invokeinterface #62,  1           // InterfaceMethod org/jboss/jca/common/api/metadata/spec/Connector.validate:()V
     206: new           #63                 // class org/jboss/jca/common/metadata/merge/Merger
     209: dup
     210: invokespecial #64                 // Method org/jboss/jca/common/metadata/merge/Merger."<init>":()V
     213: aload         9
     215: aload         8
     217: invokevirtual #65                 // Method org/jboss/jca/common/metadata/merge/Merger.mergeConnectorWithCommonIronJacamar:(Lorg/jboss/jca/common/api/metadata/resourceadapter/Activation;Lorg/jboss/jca/common/api/metadata/spec/Connector;)Lorg/jboss/jca/common/api/metadata/spec/Connector;
     220: astore        8
     222: getstatic     #66                 // Field org/jboss/as/connector/util/ConnectorServices.RESOURCE_ADAPTER_DEPLOYER_SERVICE_PREFIX:Lorg/jboss/msc/service/ServiceName;
     225: iconst_1
     226: anewarray     #67                 // class java/lang/String
     229: dup
     230: iconst_0
     231: aload_0
     232: invokevirtual #68                 // Method org/jboss/as/connector/metadata/xmldescriptors/ConnectorXmlDescriptor.getDeploymentName:()Ljava/lang/String;
     235: aastore
     236: invokevirtual #69                 // Method org/jboss/msc/service/ServiceName.append:([Ljava/lang/String;)Lorg/jboss/msc/service/ServiceName;
     239: astore        11
     241: new           #70                 // class org/jboss/as/connector/services/resourceadapters/deployment/ResourceAdapterDeploymentService
     244: dup
     245: aload_0
     246: aload         8
     248: aload         9
     250: aload_2
     251: aload         11
     253: aload         5
     255: aload         6
     257: aload         7
     259: invokespecial #71                 // Method org/jboss/as/connector/services/resourceadapters/deployment/ResourceAdapterDeploymentService."<init>":(Lorg/jboss/as/connector/metadata/xmldescriptors/ConnectorXmlDescriptor;Lorg/jboss/jca/common/api/metadata/spec/Connector;Lorg/jboss/jca/common/api/metadata/resourceadapter/Activation;Ljava/lang/ClassLoader;Lorg/jboss/msc/service/ServiceName;Lorg/jboss/msc/service/ServiceName;Lorg/jboss/as/controller/registry/ManagementResourceRegistration;Lorg/jboss/as/controller/registry/Resource;)V
     262: astore        12
     264: aload_3
     265: aload         11
     267: aload         12
     269: invokeinterface #72,  3           // InterfaceMethod org/jboss/msc/service/ServiceTarget.addService:(Lorg/jboss/msc/service/ServiceName;Lorg/jboss/msc/service/Service;)Lorg/jboss/msc/service/ServiceBuilder;
     274: aload         12
     276: invokevirtual #73                 // Method org/jboss/as/connector/services/resourceadapters/deployment/ResourceAdapterDeploymentService.getExecutorServiceInjector:()Lorg/jboss/msc/inject/Injector;
     279: iconst_0
     280: invokestatic  #74                 // Method org/jboss/as/server/Services.addServerExecutorDependency:(Lorg/jboss/msc/service/ServiceBuilder;Lorg/jboss/msc/inject/Injector;Z)Lorg/jboss/msc/service/ServiceBuilder;
     283: getstatic     #75                 // Field org/jboss/as/connector/util/ConnectorServices.IRONJACAMAR_MDR:Lorg/jboss/msc/service/ServiceName;
     286: ldc           #76                 // class org/jboss/as/connector/services/mdr/AS7MetadataRepository
     288: aload         12
     290: invokevirtual #77                 // Method org/jboss/as/connector/services/resourceadapters/deployment/ResourceAdapterDeploymentService.getMdrInjector:()Lorg/jboss/msc/inject/Injector;
     293: invokeinterface #78,  4           // InterfaceMethod org/jboss/msc/service/ServiceBuilder.addDependency:(Lorg/jboss/msc/service/ServiceName;Ljava/lang/Class;Lorg/jboss/msc/inject/Injector;)Lorg/jboss/msc/service/ServiceBuilder;
     298: getstatic     #79                 // Field org/jboss/as/connector/util/ConnectorServices.RA_REPOSITORY_SERVICE:Lorg/jboss/msc/service/ServiceName;
     301: ldc           #80                 // class org/jboss/jca/core/spi/rar/ResourceAdapterRepository
     303: aload         12
     305: invokevirtual #81                 // Method org/jboss/as/connector/services/resourceadapters/deployment/ResourceAdapterDeploymentService.getRaRepositoryInjector:()Lorg/jboss/msc/inject/Injector;
     308: invokeinterface #78,  4           // InterfaceMethod org/jboss/msc/service/ServiceBuilder.addDependency:(Lorg/jboss/msc/service/ServiceName;Ljava/lang/Class;Lorg/jboss/msc/inject/Injector;)Lorg/jboss/msc/service/ServiceBuilder;
     313: getstatic     #82                 // Field org/jboss/as/connector/util/ConnectorServices.MANAGEMENT_REPOSITORY_SERVICE:Lorg/jboss/msc/service/ServiceName;
     316: ldc           #83                 // class org/jboss/jca/core/api/management/ManagementRepository
     318: aload         12
     320: invokevirtual #84                 // Method org/jboss/as/connector/services/resourceadapters/deployment/ResourceAdapterDeploymentService.getManagementRepositoryInjector:()Lorg/jboss/msc/inject/Injector;
     323: invokeinterface #78,  4           // InterfaceMethod org/jboss/msc/service/ServiceBuilder.addDependency:(Lorg/jboss/msc/service/ServiceName;Ljava/lang/Class;Lorg/jboss/msc/inject/Injector;)Lorg/jboss/msc/service/ServiceBuilder;
     328: getstatic     #85                 // Field org/jboss/as/connector/util/ConnectorServices.RESOURCE_ADAPTER_REGISTRY_SERVICE:Lorg/jboss/msc/service/ServiceName;
     331: ldc           #86                 // class org/jboss/as/connector/services/resourceadapters/deployment/registry/ResourceAdapterDeploymentRegistry
     333: aload         12
     335: invokevirtual #87                 // Method org/jboss/as/connector/services/resourceadapters/deployment/ResourceAdapterDeploymentService.getRegistryInjector:()Lorg/jboss/msc/inject/Injector;
     338: invokeinterface #78,  4           // InterfaceMethod org/jboss/msc/service/ServiceBuilder.addDependency:(Lorg/jboss/msc/service/ServiceName;Ljava/lang/Class;Lorg/jboss/msc/inject/Injector;)Lorg/jboss/msc/service/ServiceBuilder;
     343: getstatic     #88                 // Field org/jboss/as/connector/util/ConnectorServices.TRANSACTION_INTEGRATION_SERVICE:Lorg/jboss/msc/service/ServiceName;
     346: ldc           #89                 // class org/jboss/jca/core/spi/transaction/TransactionIntegration
     348: aload         12
     350: invokevirtual #90                 // Method org/jboss/as/connector/services/resourceadapters/deployment/ResourceAdapterDeploymentService.getTxIntegrationInjector:()Lorg/jboss/msc/inject/Injector;
     353: invokeinterface #78,  4           // InterfaceMethod org/jboss/msc/service/ServiceBuilder.addDependency:(Lorg/jboss/msc/service/ServiceName;Ljava/lang/Class;Lorg/jboss/msc/inject/Injector;)Lorg/jboss/msc/service/ServiceBuilder;
     358: getstatic     #91                 // Field org/jboss/as/connector/util/ConnectorServices.CONNECTOR_CONFIG_SERVICE:Lorg/jboss/msc/service/ServiceName;
     361: ldc           #92                 // class org/jboss/as/connector/subsystems/jca/JcaSubsystemConfiguration
     363: aload         12
     365: invokevirtual #93                 // Method org/jboss/as/connector/services/resourceadapters/deployment/ResourceAdapterDeploymentService.getConfigInjector:()Lorg/jboss/msc/inject/Injector;
     368: invokeinterface #78,  4           // InterfaceMethod org/jboss/msc/service/ServiceBuilder.addDependency:(Lorg/jboss/msc/service/ServiceName;Ljava/lang/Class;Lorg/jboss/msc/inject/Injector;)Lorg/jboss/msc/service/ServiceBuilder;
     373: getstatic     #94                 // Field org/jboss/as/security/service/SubjectFactoryService.SERVICE_NAME:Lorg/jboss/msc/service/ServiceName;
     376: ldc           #95                 // class org/jboss/security/SubjectFactory
     378: aload         12
     380: invokevirtual #96                 // Method org/jboss/as/connector/services/resourceadapters/deployment/ResourceAdapterDeploymentService.getSubjectFactoryInjector:()Lorg/jboss/msc/inject/Injector;
     383: invokeinterface #78,  4           // InterfaceMethod org/jboss/msc/service/ServiceBuilder.addDependency:(Lorg/jboss/msc/service/ServiceName;Ljava/lang/Class;Lorg/jboss/msc/inject/Injector;)Lorg/jboss/msc/service/ServiceBuilder;
     388: getstatic     #97                 // Field org/jboss/as/connector/util/ConnectorServices.CCM_SERVICE:Lorg/jboss/msc/service/ServiceName;
     391: ldc           #98                 // class org/jboss/jca/core/api/connectionmanager/ccm/CachedConnectionManager
     393: aload         12
     395: invokevirtual #99                 // Method org/jboss/as/connector/services/resourceadapters/deployment/ResourceAdapterDeploymentService.getCcmInjector:()Lorg/jboss/msc/inject/Injector;
     398: invokeinterface #78,  4           // InterfaceMethod org/jboss/msc/service/ServiceBuilder.addDependency:(Lorg/jboss/msc/service/ServiceName;Ljava/lang/Class;Lorg/jboss/msc/inject/Injector;)Lorg/jboss/msc/service/ServiceBuilder;
     403: getstatic     #100                // Field org/jboss/as/connector/util/ConnectorServices.IDLE_REMOVER_SERVICE:Lorg/jboss/msc/service/ServiceName;
     406: invokeinterface #101,  2          // InterfaceMethod org/jboss/msc/service/ServiceBuilder.addDependency:(Lorg/jboss/msc/service/ServiceName;)Lorg/jboss/msc/service/ServiceBuilder;
     411: getstatic     #102                // Field org/jboss/as/connector/util/ConnectorServices.CONNECTION_VALIDATOR_SERVICE:Lorg/jboss/msc/service/ServiceName;
     414: invokeinterface #101,  2          // InterfaceMethod org/jboss/msc/service/ServiceBuilder.addDependency:(Lorg/jboss/msc/service/ServiceName;)Lorg/jboss/msc/service/ServiceBuilder;
     419: getstatic     #103                // Field org/jboss/as/naming/service/NamingService.SERVICE_NAME:Lorg/jboss/msc/service/ServiceName;
     422: invokeinterface #101,  2          // InterfaceMethod org/jboss/msc/service/ServiceBuilder.addDependency:(Lorg/jboss/msc/service/ServiceName;)Lorg/jboss/msc/service/ServiceBuilder;
     427: areturn
     428: astore        10
     430: new           #105                // class org/jboss/as/server/deployment/DeploymentUnitProcessingException
     433: dup
     434: aload         10
     436: invokespecial #106                // Method org/jboss/as/server/deployment/DeploymentUnitProcessingException."<init>":(Ljava/lang/Throwable;)V
     439: athrow
    Exception table:
       from    to  target type
          28   427   428   Class java/lang/Throwable

  public void undeploy(org.jboss.as.server.deployment.DeploymentUnit);
    Code:
       0: return
}
