Compiled from "DescribeUsersPublisher.java"
class software.amazon.awssdk.services.workdocs.paginators.DescribeUsersPublisher$DescribeUsersResponseFetcher implements software.amazon.awssdk.core.pagination.async.AsyncPageFetcher<software.amazon.awssdk.services.workdocs.model.DescribeUsersResponse> {
  final software.amazon.awssdk.services.workdocs.paginators.DescribeUsersPublisher this$0;

  private software.amazon.awssdk.services.workdocs.paginators.DescribeUsersPublisher$DescribeUsersResponseFetcher(software.amazon.awssdk.services.workdocs.paginators.DescribeUsersPublisher);
    Code:
       0: aload_0
       1: aload_1
       2: putfield      #2                  // Field this$0:Lsoftware/amazon/awssdk/services/workdocs/paginators/DescribeUsersPublisher;
       5: aload_0
       6: invokespecial #3                  // Method java/lang/Object."<init>":()V
       9: return

  public boolean hasNextPage(software.amazon.awssdk.services.workdocs.model.DescribeUsersResponse);
    Code:
       0: aload_1
       1: invokevirtual #4                  // Method software/amazon/awssdk/services/workdocs/model/DescribeUsersResponse.marker:()Ljava/lang/String;
       4: invokestatic  #5                  // Method software/amazon/awssdk/core/util/PaginatorUtils.isOutputTokenAvailable:(Ljava/lang/Object;)Z
       7: ireturn

  public java.util.concurrent.CompletableFuture<software.amazon.awssdk.services.workdocs.model.DescribeUsersResponse> nextPage(software.amazon.awssdk.services.workdocs.model.DescribeUsersResponse);
    Code:
       0: aload_1
       1: ifnonnull     24
       4: aload_0
       5: getfield      #2                  // Field this$0:Lsoftware/amazon/awssdk/services/workdocs/paginators/DescribeUsersPublisher;
       8: invokestatic  #6                  // Method software/amazon/awssdk/services/workdocs/paginators/DescribeUsersPublisher.access$200:(Lsoftware/amazon/awssdk/services/workdocs/paginators/DescribeUsersPublisher;)Lsoftware/amazon/awssdk/services/workdocs/WorkDocsAsyncClient;
      11: aload_0
      12: getfield      #2                  // Field this$0:Lsoftware/amazon/awssdk/services/workdocs/paginators/DescribeUsersPublisher;
      15: invokestatic  #7                  // Method software/amazon/awssdk/services/workdocs/paginators/DescribeUsersPublisher.access$100:(Lsoftware/amazon/awssdk/services/workdocs/paginators/DescribeUsersPublisher;)Lsoftware/amazon/awssdk/services/workdocs/model/DescribeUsersRequest;
      18: invokeinterface #8,  2            // InterfaceMethod software/amazon/awssdk/services/workdocs/WorkDocsAsyncClient.describeUsers:(Lsoftware/amazon/awssdk/services/workdocs/model/DescribeUsersRequest;)Ljava/util/concurrent/CompletableFuture;
      23: areturn
      24: aload_0
      25: getfield      #2                  // Field this$0:Lsoftware/amazon/awssdk/services/workdocs/paginators/DescribeUsersPublisher;
      28: invokestatic  #6                  // Method software/amazon/awssdk/services/workdocs/paginators/DescribeUsersPublisher.access$200:(Lsoftware/amazon/awssdk/services/workdocs/paginators/DescribeUsersPublisher;)Lsoftware/amazon/awssdk/services/workdocs/WorkDocsAsyncClient;
      31: aload_0
      32: getfield      #2                  // Field this$0:Lsoftware/amazon/awssdk/services/workdocs/paginators/DescribeUsersPublisher;
      35: invokestatic  #7                  // Method software/amazon/awssdk/services/workdocs/paginators/DescribeUsersPublisher.access$100:(Lsoftware/amazon/awssdk/services/workdocs/paginators/DescribeUsersPublisher;)Lsoftware/amazon/awssdk/services/workdocs/model/DescribeUsersRequest;
      38: invokevirtual #9                  // Method software/amazon/awssdk/services/workdocs/model/DescribeUsersRequest.toBuilder:()Lsoftware/amazon/awssdk/services/workdocs/model/DescribeUsersRequest$Builder;
      41: aload_1
      42: invokevirtual #4                  // Method software/amazon/awssdk/services/workdocs/model/DescribeUsersResponse.marker:()Ljava/lang/String;
      45: invokeinterface #10,  2           // InterfaceMethod software/amazon/awssdk/services/workdocs/model/DescribeUsersRequest$Builder.marker:(Ljava/lang/String;)Lsoftware/amazon/awssdk/services/workdocs/model/DescribeUsersRequest$Builder;
      50: invokeinterface #11,  1           // InterfaceMethod software/amazon/awssdk/services/workdocs/model/DescribeUsersRequest$Builder.build:()Ljava/lang/Object;
      55: checkcast     #12                 // class software/amazon/awssdk/services/workdocs/model/DescribeUsersRequest
      58: invokeinterface #8,  2            // InterfaceMethod software/amazon/awssdk/services/workdocs/WorkDocsAsyncClient.describeUsers:(Lsoftware/amazon/awssdk/services/workdocs/model/DescribeUsersRequest;)Ljava/util/concurrent/CompletableFuture;
      63: areturn

  public java.util.concurrent.CompletableFuture nextPage(java.lang.Object);
    Code:
       0: aload_0
       1: aload_1
       2: checkcast     #13                 // class software/amazon/awssdk/services/workdocs/model/DescribeUsersResponse
       5: invokevirtual #14                 // Method nextPage:(Lsoftware/amazon/awssdk/services/workdocs/model/DescribeUsersResponse;)Ljava/util/concurrent/CompletableFuture;
       8: areturn

  public boolean hasNextPage(java.lang.Object);
    Code:
       0: aload_0
       1: aload_1
       2: checkcast     #13                 // class software/amazon/awssdk/services/workdocs/model/DescribeUsersResponse
       5: invokevirtual #15                 // Method hasNextPage:(Lsoftware/amazon/awssdk/services/workdocs/model/DescribeUsersResponse;)Z
       8: ireturn

  software.amazon.awssdk.services.workdocs.paginators.DescribeUsersPublisher$DescribeUsersResponseFetcher(software.amazon.awssdk.services.workdocs.paginators.DescribeUsersPublisher, software.amazon.awssdk.services.workdocs.paginators.DescribeUsersPublisher$1);
    Code:
       0: aload_0
       1: aload_1
       2: invokespecial #1                  // Method "<init>":(Lsoftware/amazon/awssdk/services/workdocs/paginators/DescribeUsersPublisher;)V
       5: return
}
