Compiled from "User.java"
public final class org.elasticsearch.client.security.user.User {
  private final java.lang.String username;

  private final java.util.Set<java.lang.String> roles;

  private final java.util.Map<java.lang.String, java.lang.Object> metadata;

  private final java.lang.String fullName;

  private final java.lang.String email;

  public org.elasticsearch.client.security.user.User(java.lang.String, java.util.Collection<java.lang.String>, java.util.Map<java.lang.String, java.lang.Object>, java.lang.String, java.lang.String);
    Code:
       0: aload_0
       1: invokespecial #1                  // Method java/lang/Object."<init>":()V
       4: aload_0
       5: aload_1
       6: ldc           #2                  // String `username` is required, cannot be null
       8: invokestatic  #3                  // Method java/util/Objects.requireNonNull:(Ljava/lang/Object;Ljava/lang/String;)Ljava/lang/Object;
      11: checkcast     #4                  // class java/lang/String
      14: dup
      15: astore_1
      16: putfield      #5                  // Field username:Ljava/lang/String;
      19: aload_0
      20: new           #6                  // class java/util/HashSet
      23: dup
      24: aload_2
      25: ldc           #7                  // String `roles` is required, cannot be null. Pass an empty Collection instead.
      27: invokestatic  #3                  // Method java/util/Objects.requireNonNull:(Ljava/lang/Object;Ljava/lang/String;)Ljava/lang/Object;
      30: checkcast     #8                  // class java/util/Collection
      33: invokespecial #9                  // Method java/util/HashSet."<init>":(Ljava/util/Collection;)V
      36: invokestatic  #10                 // Method java/util/Collections.unmodifiableSet:(Ljava/util/Set;)Ljava/util/Set;
      39: putfield      #11                 // Field roles:Ljava/util/Set;
      42: aload_0
      43: aload_3
      44: ldc           #12                 // String `metadata` is required, cannot be null. Pass an empty map instead.
      46: invokestatic  #3                  // Method java/util/Objects.requireNonNull:(Ljava/lang/Object;Ljava/lang/String;)Ljava/lang/Object;
      49: checkcast     #13                 // class java/util/Map
      52: invokestatic  #14                 // Method java/util/Collections.unmodifiableMap:(Ljava/util/Map;)Ljava/util/Map;
      55: putfield      #15                 // Field metadata:Ljava/util/Map;
      58: aload_0
      59: aload         4
      61: putfield      #16                 // Field fullName:Ljava/lang/String;
      64: aload_0
      65: aload         5
      67: putfield      #17                 // Field email:Ljava/lang/String;
      70: return

  public org.elasticsearch.client.security.user.User(java.lang.String, java.util.Collection<java.lang.String>);
    Code:
       0: aload_0
       1: aload_1
       2: aload_2
       3: invokestatic  #18                 // Method java/util/Collections.emptyMap:()Ljava/util/Map;
       6: aconst_null
       7: aconst_null
       8: invokespecial #19                 // Method "<init>":(Ljava/lang/String;Ljava/util/Collection;Ljava/util/Map;Ljava/lang/String;Ljava/lang/String;)V
      11: return

  public java.lang.String getUsername();
    Code:
       0: aload_0
       1: getfield      #5                  // Field username:Ljava/lang/String;
       4: areturn

  public java.util.Set<java.lang.String> getRoles();
    Code:
       0: aload_0
       1: getfield      #11                 // Field roles:Ljava/util/Set;
       4: areturn

  public java.util.Map<java.lang.String, java.lang.Object> getMetadata();
    Code:
       0: aload_0
       1: getfield      #15                 // Field metadata:Ljava/util/Map;
       4: areturn

  public java.lang.String getFullName();
    Code:
       0: aload_0
       1: getfield      #16                 // Field fullName:Ljava/lang/String;
       4: areturn

  public java.lang.String getEmail();
    Code:
       0: aload_0
       1: getfield      #17                 // Field email:Ljava/lang/String;
       4: areturn

  public java.lang.String toString();
    Code:
       0: new           #20                 // class java/lang/StringBuilder
       3: dup
       4: invokespecial #21                 // Method java/lang/StringBuilder."<init>":()V
       7: astore_1
       8: aload_1
       9: ldc           #22                 // String User[username=
      11: invokevirtual #23                 // Method java/lang/StringBuilder.append:(Ljava/lang/String;)Ljava/lang/StringBuilder;
      14: aload_0
      15: getfield      #5                  // Field username:Ljava/lang/String;
      18: invokevirtual #23                 // Method java/lang/StringBuilder.append:(Ljava/lang/String;)Ljava/lang/StringBuilder;
      21: pop
      22: aload_1
      23: ldc           #24                 // String ,roles=[
      25: invokevirtual #23                 // Method java/lang/StringBuilder.append:(Ljava/lang/String;)Ljava/lang/StringBuilder;
      28: aload_0
      29: getfield      #11                 // Field roles:Ljava/util/Set;
      32: invokestatic  #25                 // Method org/elasticsearch/common/Strings.collectionToCommaDelimitedString:(Ljava/lang/Iterable;)Ljava/lang/String;
      35: invokevirtual #23                 // Method java/lang/StringBuilder.append:(Ljava/lang/String;)Ljava/lang/StringBuilder;
      38: ldc           #26                 // String ]
      40: invokevirtual #23                 // Method java/lang/StringBuilder.append:(Ljava/lang/String;)Ljava/lang/StringBuilder;
      43: pop
      44: aload_1
      45: ldc           #27                 // String ,metadata=
      47: invokevirtual #23                 // Method java/lang/StringBuilder.append:(Ljava/lang/String;)Ljava/lang/StringBuilder;
      50: aload_0
      51: getfield      #15                 // Field metadata:Ljava/util/Map;
      54: invokevirtual #28                 // Method java/lang/StringBuilder.append:(Ljava/lang/Object;)Ljava/lang/StringBuilder;
      57: pop
      58: aload_1
      59: ldc           #29                 // String ,fullName=
      61: invokevirtual #23                 // Method java/lang/StringBuilder.append:(Ljava/lang/String;)Ljava/lang/StringBuilder;
      64: aload_0
      65: getfield      #16                 // Field fullName:Ljava/lang/String;
      68: invokevirtual #23                 // Method java/lang/StringBuilder.append:(Ljava/lang/String;)Ljava/lang/StringBuilder;
      71: pop
      72: aload_1
      73: ldc           #30                 // String ,email=
      75: invokevirtual #23                 // Method java/lang/StringBuilder.append:(Ljava/lang/String;)Ljava/lang/StringBuilder;
      78: aload_0
      79: getfield      #17                 // Field email:Ljava/lang/String;
      82: invokevirtual #23                 // Method java/lang/StringBuilder.append:(Ljava/lang/String;)Ljava/lang/StringBuilder;
      85: pop
      86: aload_1
      87: ldc           #26                 // String ]
      89: invokevirtual #23                 // Method java/lang/StringBuilder.append:(Ljava/lang/String;)Ljava/lang/StringBuilder;
      92: pop
      93: aload_1
      94: invokevirtual #31                 // Method java/lang/StringBuilder.toString:()Ljava/lang/String;
      97: areturn

  public boolean equals(java.lang.Object);
    Code:
       0: aload_0
       1: aload_1
       2: if_acmpne     7
       5: iconst_1
       6: ireturn
       7: aload_1
       8: ifnull        22
      11: aload_0
      12: invokevirtual #32                 // Method java/lang/Object.getClass:()Ljava/lang/Class;
      15: aload_1
      16: invokevirtual #32                 // Method java/lang/Object.getClass:()Ljava/lang/Class;
      19: if_acmpeq     24
      22: iconst_0
      23: ireturn
      24: aload_1
      25: checkcast     #33                 // class org/elasticsearch/client/security/user/User
      28: astore_2
      29: aload_0
      30: getfield      #5                  // Field username:Ljava/lang/String;
      33: aload_2
      34: getfield      #5                  // Field username:Ljava/lang/String;
      37: invokestatic  #34                 // Method java/util/Objects.equals:(Ljava/lang/Object;Ljava/lang/Object;)Z
      40: ifeq          103
      43: aload_0
      44: getfield      #11                 // Field roles:Ljava/util/Set;
      47: aload_2
      48: getfield      #11                 // Field roles:Ljava/util/Set;
      51: invokestatic  #34                 // Method java/util/Objects.equals:(Ljava/lang/Object;Ljava/lang/Object;)Z
      54: ifeq          103
      57: aload_0
      58: getfield      #15                 // Field metadata:Ljava/util/Map;
      61: aload_2
      62: getfield      #15                 // Field metadata:Ljava/util/Map;
      65: invokestatic  #34                 // Method java/util/Objects.equals:(Ljava/lang/Object;Ljava/lang/Object;)Z
      68: ifeq          103
      71: aload_0
      72: getfield      #16                 // Field fullName:Ljava/lang/String;
      75: aload_2
      76: getfield      #16                 // Field fullName:Ljava/lang/String;
      79: invokestatic  #34                 // Method java/util/Objects.equals:(Ljava/lang/Object;Ljava/lang/Object;)Z
      82: ifeq          103
      85: aload_0
      86: getfield      #17                 // Field email:Ljava/lang/String;
      89: aload_2
      90: getfield      #17                 // Field email:Ljava/lang/String;
      93: invokestatic  #34                 // Method java/util/Objects.equals:(Ljava/lang/Object;Ljava/lang/Object;)Z
      96: ifeq          103
      99: iconst_1
     100: goto          104
     103: iconst_0
     104: ireturn

  public int hashCode();
    Code:
       0: iconst_5
       1: anewarray     #35                 // class java/lang/Object
       4: dup
       5: iconst_0
       6: aload_0
       7: getfield      #5                  // Field username:Ljava/lang/String;
      10: aastore
      11: dup
      12: iconst_1
      13: aload_0
      14: getfield      #11                 // Field roles:Ljava/util/Set;
      17: aastore
      18: dup
      19: iconst_2
      20: aload_0
      21: getfield      #15                 // Field metadata:Ljava/util/Map;
      24: aastore
      25: dup
      26: iconst_3
      27: aload_0
      28: getfield      #16                 // Field fullName:Ljava/lang/String;
      31: aastore
      32: dup
      33: iconst_4
      34: aload_0
      35: getfield      #17                 // Field email:Ljava/lang/String;
      38: aastore
      39: invokestatic  #36                 // Method java/util/Objects.hash:([Ljava/lang/Object;)I
      42: ireturn
}
