Compiled from "WorkbenchAdapter.java"
public abstract class org.eclipse.ui.model.WorkbenchAdapter implements org.eclipse.ui.model.IWorkbenchAdapter,org.eclipse.ui.model.IWorkbenchAdapter2,org.eclipse.ui.model.IWorkbenchAdapter3 {
  protected static final java.lang.Object[] NO_CHILDREN;

  static {};
    Code:
       0: iconst_0
       1: anewarray     #27                 // class java/lang/Object
       4: putstatic     #50                 // Field NO_CHILDREN:[Ljava/lang/Object;
       7: return

  public org.eclipse.ui.model.WorkbenchAdapter();
    Code:
       0: aload_0
       1: invokespecial #51                 // Method java/lang/Object."<init>":()V
       4: return

  public java.lang.Object[] getChildren(java.lang.Object);
    Code:
       0: getstatic     #50                 // Field NO_CHILDREN:[Ljava/lang/Object;
       3: areturn

  public org.eclipse.jface.resource.ImageDescriptor getImageDescriptor(java.lang.Object);
    Code:
       0: aconst_null
       1: areturn

  public java.lang.String getLabel(java.lang.Object);
    Code:
       0: aload_1
       1: ifnonnull     9
       4: ldc           #1                  // String
       6: goto          13
       9: aload_1
      10: invokevirtual #52                 // Method java/lang/Object.toString:()Ljava/lang/String;
      13: areturn

  public java.lang.Object getParent(java.lang.Object);
    Code:
       0: aconst_null
       1: areturn

  public org.eclipse.swt.graphics.RGB getBackground(java.lang.Object);
    Code:
       0: aconst_null
       1: areturn

  public org.eclipse.swt.graphics.RGB getForeground(java.lang.Object);
    Code:
       0: aconst_null
       1: areturn

  public org.eclipse.swt.graphics.FontData getFont(java.lang.Object);
    Code:
       0: aconst_null
       1: areturn

  public org.eclipse.jface.viewers.StyledString getStyledText(java.lang.Object);
    Code:
       0: new           #29                 // class org/eclipse/jface/viewers/StyledString
       3: dup
       4: aload_0
       5: aload_1
       6: invokevirtual #54                 // Method getLabel:(Ljava/lang/Object;)Ljava/lang/String;
       9: invokespecial #53                 // Method org/eclipse/jface/viewers/StyledString."<init>":(Ljava/lang/String;)V
      12: areturn
}
