Compiled from "ChannelManager.java"
class org.asynchttpclient.netty.channel.ChannelManager$3 extends io.netty.handler.codec.http.HttpContentDecompressor {
  final org.asynchttpclient.netty.channel.ChannelManager this$0;

  org.asynchttpclient.netty.channel.ChannelManager$3(org.asynchttpclient.netty.channel.ChannelManager);
    Code:
       0: aload_0
       1: aload_1
       2: putfield      #1                  // Field this$0:Lorg/asynchttpclient/netty/channel/ChannelManager;
       5: aload_0
       6: invokespecial #2                  // Method io/netty/handler/codec/http/HttpContentDecompressor."<init>":()V
       9: return

  protected java.lang.String getTargetContentEncoding(java.lang.String);
    Code:
       0: aload_1
       1: areturn
}
