Compiled from "RPCMessageReceiver.java"
public class org.apache.axis2.rpc.receivers.RPCMessageReceiver extends org.apache.axis2.receivers.AbstractInOutMessageReceiver {
  private static org.apache.commons.logging.Log log;

  public org.apache.axis2.rpc.receivers.RPCMessageReceiver();
    Code:
       0: aload_0
       1: invokespecial #1                  // Method org/apache/axis2/receivers/AbstractInOutMessageReceiver."<init>":()V
       4: return

  public void invokeBusinessLogic(org.apache.axis2.context.MessageContext, org.apache.axis2.context.MessageContext) throws org.apache.axis2.AxisFault;
    Code:
       0: aconst_null
       1: astore_3
       2: aload_0
       3: aload_1
       4: invokevirtual #2                  // Method getTheImplementationObject:(Lorg/apache/axis2/context/MessageContext;)Ljava/lang/Object;
       7: astore        4
       9: aload         4
      11: invokevirtual #3                  // Method java/lang/Object.getClass:()Ljava/lang/Class;
      14: astore        5
      16: aload_1
      17: invokevirtual #4                  // Method org/apache/axis2/context/MessageContext.getOperationContext:()Lorg/apache/axis2/context/OperationContext;
      20: invokevirtual #5                  // Method org/apache/axis2/context/OperationContext.getAxisOperation:()Lorg/apache/axis2/description/AxisOperation;
      23: astore        6
      25: aload         6
      27: ldc           #6                  // String myMethod
      29: invokevirtual #7                  // Method org/apache/axis2/description/AxisOperation.getParameterValue:(Ljava/lang/String;)Ljava/lang/Object;
      32: checkcast     #8                  // class java/lang/reflect/Method
      35: checkcast     #8                  // class java/lang/reflect/Method
      38: astore_3
      39: aload_3
      40: ifnull        54
      43: aload_3
      44: invokevirtual #9                  // Method java/lang/reflect/Method.getDeclaringClass:()Ljava/lang/Class;
      47: aload         5
      49: if_acmpeq     54
      52: aconst_null
      53: astore_3
      54: aload_1
      55: invokevirtual #10                 // Method org/apache/axis2/context/MessageContext.getAxisService:()Lorg/apache/axis2/description/AxisService;
      58: astore        7
      60: aload_1
      61: invokevirtual #11                 // Method org/apache/axis2/context/MessageContext.getEnvelope:()Lorg/apache/axiom/soap/SOAPEnvelope;
      64: invokeinterface #12,  1           // InterfaceMethod org/apache/axiom/soap/SOAPEnvelope.getBody:()Lorg/apache/axiom/soap/SOAPBody;
      69: astore        8
      71: aload         8
      73: ifnonnull     86
      76: new           #13                 // class org/apache/axis2/AxisFault
      79: dup
      80: ldc           #14                 // String SOAP body is missing in the request
      82: invokespecial #15                 // Method org/apache/axis2/AxisFault."<init>":(Ljava/lang/String;)V
      85: athrow
      86: aload         8
      88: invokeinterface #16,  1           // InterfaceMethod org/apache/axiom/soap/SOAPBody.getFirstElement:()Lorg/apache/axiom/om/OMElement;
      93: astore        9
      95: aload         6
      97: ldc           #18                 // String In
      99: invokevirtual #19                 // Method org/apache/axis2/description/AxisOperation.getMessage:(Ljava/lang/String;)Lorg/apache/axis2/description/AxisMessage;
     102: astore        10
     104: aconst_null
     105: astore        11
     107: aload_3
     108: ifnonnull     243
     111: aload         6
     113: invokevirtual #20                 // Method org/apache/axis2/description/AxisOperation.getName:()Ljavax/xml/namespace/QName;
     116: invokevirtual #21                 // Method javax/xml/namespace/QName.getLocalPart:()Ljava/lang/String;
     119: astore        12
     121: aload         5
     123: invokevirtual #22                 // Method java/lang/Class.getMethods:()[Ljava/lang/reflect/Method;
     126: astore        13
     128: aload         13
     130: astore        14
     132: aload         14
     134: arraylength
     135: istore        15
     137: iconst_0
     138: istore        16
     140: iload         16
     142: iload         15
     144: if_icmpge     198
     147: aload         14
     149: iload         16
     151: aaload
     152: astore        17
     154: aload         17
     156: invokevirtual #23                 // Method java/lang/reflect/Method.isBridge:()Z
     159: ifeq          165
     162: goto          192
     165: aload         17
     167: invokevirtual #24                 // Method java/lang/reflect/Method.getName:()Ljava/lang/String;
     170: aload         12
     172: invokevirtual #25                 // Method java/lang/String.equals:(Ljava/lang/Object;)Z
     175: ifeq          192
     178: aload         17
     180: astore_3
     181: aload         6
     183: ldc           #6                  // String myMethod
     185: aload_3
     186: invokevirtual #26                 // Method org/apache/axis2/description/AxisOperation.addParameter:(Ljava/lang/String;Ljava/lang/Object;)V
     189: goto          198
     192: iinc          16, 1
     195: goto          140
     198: aload_3
     199: ifnonnull     243
     202: new           #13                 // class org/apache/axis2/AxisFault
     205: dup
     206: new           #27                 // class java/lang/StringBuilder
     209: dup
     210: invokespecial #28                 // Method java/lang/StringBuilder."<init>":()V
     213: ldc           #29                 // String No such method \'
     215: invokevirtual #30                 // Method java/lang/StringBuilder.append:(Ljava/lang/String;)Ljava/lang/StringBuilder;
     218: aload         12
     220: invokevirtual #30                 // Method java/lang/StringBuilder.append:(Ljava/lang/String;)Ljava/lang/StringBuilder;
     223: ldc           #31                 // String \' in class
     225: invokevirtual #30                 // Method java/lang/StringBuilder.append:(Ljava/lang/String;)Ljava/lang/StringBuilder;
     228: aload         5
     230: invokevirtual #32                 // Method java/lang/Class.getName:()Ljava/lang/String;
     233: invokevirtual #30                 // Method java/lang/StringBuilder.append:(Ljava/lang/String;)Ljava/lang/StringBuilder;
     236: invokevirtual #33                 // Method java/lang/StringBuilder.toString:()Ljava/lang/String;
     239: invokespecial #15                 // Method org/apache/axis2/AxisFault."<init>":(Ljava/lang/String;)V
     242: athrow
     243: aconst_null
     244: astore        12
     246: aload         10
     248: ifnull        266
     251: aload         10
     253: aload_3
     254: aload         4
     256: aload         11
     258: aload         9
     260: aload_1
     261: invokestatic  #34                 // Method org/apache/axis2/rpc/receivers/RPCUtil.invokeServiceClass:(Lorg/apache/axis2/description/AxisMessage;Ljava/lang/reflect/Method;Ljava/lang/Object;Ljava/lang/String;Lorg/apache/axiom/om/OMElement;Lorg/apache/axis2/context/MessageContext;)Ljava/lang/Object;
     264: astore        12
     266: aload_0
     267: aload_1
     268: invokevirtual #35                 // Method getSOAPFactory:(Lorg/apache/axis2/context/MessageContext;)Lorg/apache/axiom/soap/SOAPFactory;
     271: astore        13
     273: aload         6
     275: ldc           #36                 // String Out
     277: invokevirtual #19                 // Method org/apache/axis2/description/AxisOperation.getMessage:(Ljava/lang/String;)Lorg/apache/axis2/description/AxisMessage;
     280: astore        14
     282: aload         14
     284: ifnull        308
     287: aload         14
     289: invokevirtual #37                 // Method org/apache/axis2/description/AxisMessage.getElementQName:()Ljavax/xml/namespace/QName;
     292: ifnull        308
     295: aload         14
     297: invokevirtual #37                 // Method org/apache/axis2/description/AxisMessage.getElementQName:()Ljavax/xml/namespace/QName;
     300: invokevirtual #38                 // Method javax/xml/namespace/QName.getNamespaceURI:()Ljava/lang/String;
     303: astore        11
     305: goto          315
     308: aload         7
     310: invokevirtual #39                 // Method org/apache/axis2/description/AxisService.getTargetNamespace:()Ljava/lang/String;
     313: astore        11
     315: aload         13
     317: aload         11
     319: aload         7
     321: invokevirtual #40                 // Method org/apache/axis2/description/AxisService.getSchemaTargetNamespacePrefix:()Ljava/lang/String;
     324: invokeinterface #41,  3           // InterfaceMethod org/apache/axiom/soap/SOAPFactory.createOMNamespace:(Ljava/lang/String;Ljava/lang/String;)Lorg/apache/axiom/om/OMNamespace;
     329: astore        15
     331: aload         13
     333: invokeinterface #42,  1           // InterfaceMethod org/apache/axiom/soap/SOAPFactory.getDefaultEnvelope:()Lorg/apache/axiom/soap/SOAPEnvelope;
     338: astore        16
     340: aconst_null
     341: astore        17
     343: ldc           #44                 // String http://www.w3.org/ns/wsdl/robust-in-only
     345: aload         6
     347: invokevirtual #45                 // Method org/apache/axis2/description/AxisOperation.getMessageExchangePattern:()Ljava/lang/String;
     350: invokevirtual #25                 // Method java/lang/String.equals:(Ljava/lang/Object;)Z
     353: ifeq          405
     356: aload_2
     357: invokevirtual #46                 // Method org/apache/axis2/context/MessageContext.getAxisMessage:()Lorg/apache/axis2/description/AxisMessage;
     360: invokevirtual #47                 // Method org/apache/axis2/description/AxisMessage.getName:()Ljava/lang/String;
     363: ifnull        398
     366: aload         13
     368: aload_2
     369: invokevirtual #46                 // Method org/apache/axis2/context/MessageContext.getAxisMessage:()Lorg/apache/axis2/description/AxisMessage;
     372: invokevirtual #47                 // Method org/apache/axis2/description/AxisMessage.getName:()Ljava/lang/String;
     375: aload         15
     377: invokeinterface #48,  3           // InterfaceMethod org/apache/axiom/soap/SOAPFactory.createOMElement:(Ljava/lang/String;Lorg/apache/axiom/om/OMNamespace;)Lorg/apache/axiom/om/OMElement;
     382: astore        18
     384: aload         16
     386: invokeinterface #12,  1           // InterfaceMethod org/apache/axiom/soap/SOAPEnvelope.getBody:()Lorg/apache/axiom/soap/SOAPBody;
     391: aload         18
     393: invokeinterface #49,  2           // InterfaceMethod org/apache/axiom/soap/SOAPBody.addChild:(Lorg/apache/axiom/om/OMNode;)V
     398: aload_2
     399: aload         16
     401: invokevirtual #50                 // Method org/apache/axis2/context/MessageContext.setEnvelope:(Lorg/apache/axiom/soap/SOAPEnvelope;)V
     404: return
     405: aload         7
     407: ldc           #52                 // String doclitBare
     409: invokevirtual #53                 // Method org/apache/axis2/description/AxisService.getParameter:(Ljava/lang/String;)Lorg/apache/axis2/description/Parameter;
     412: astore        18
     414: aload         18
     416: ifnull        452
     419: ldc           #54                 // String true
     421: aload         18
     423: invokevirtual #55                 // Method org/apache/axis2/description/Parameter.getValue:()Ljava/lang/Object;
     426: invokevirtual #25                 // Method java/lang/String.equals:(Ljava/lang/Object;)Z
     429: ifeq          452
     432: aload         12
     434: aload         7
     436: aload_3
     437: aload         16
     439: aload         13
     441: aload         15
     443: aload         17
     445: aload_2
     446: invokestatic  #56                 // Method org/apache/axis2/rpc/receivers/RPCUtil.processResonseAsDocLitBare:(Ljava/lang/Object;Lorg/apache/axis2/description/AxisService;Ljava/lang/reflect/Method;Lorg/apache/axiom/soap/SOAPEnvelope;Lorg/apache/axiom/soap/SOAPFactory;Lorg/apache/axiom/om/OMNamespace;Lorg/apache/axiom/om/OMElement;Lorg/apache/axis2/context/MessageContext;)V
     449: goto          469
     452: aload         12
     454: aload         7
     456: aload_3
     457: aload         16
     459: aload         13
     461: aload         15
     463: aload         17
     465: aload_2
     466: invokestatic  #57                 // Method org/apache/axis2/rpc/receivers/RPCUtil.processResponseAsDocLitWrapped:(Ljava/lang/Object;Lorg/apache/axis2/description/AxisService;Ljava/lang/reflect/Method;Lorg/apache/axiom/soap/SOAPEnvelope;Lorg/apache/axiom/soap/SOAPFactory;Lorg/apache/axiom/om/OMNamespace;Lorg/apache/axiom/om/OMElement;Lorg/apache/axis2/context/MessageContext;)V
     469: aload_2
     470: aload         16
     472: invokevirtual #50                 // Method org/apache/axis2/context/MessageContext.setEnvelope:(Lorg/apache/axiom/soap/SOAPEnvelope;)V
     475: goto          976
     478: astore        4
     480: aconst_null
     481: astore        5
     483: aload         4
     485: invokevirtual #59                 // Method java/lang/reflect/InvocationTargetException.getCause:()Ljava/lang/Throwable;
     488: astore        6
     490: aload         6
     492: ifnull        502
     495: aload         6
     497: invokevirtual #60                 // Method java/lang/Throwable.getMessage:()Ljava/lang/String;
     500: astore        5
     502: aload         5
     504: ifnonnull     540
     507: new           #27                 // class java/lang/StringBuilder
     510: dup
     511: invokespecial #28                 // Method java/lang/StringBuilder."<init>":()V
     514: ldc           #61                 // String Exception occurred while trying to invoke service method
     516: invokevirtual #30                 // Method java/lang/StringBuilder.append:(Ljava/lang/String;)Ljava/lang/StringBuilder;
     519: aload_3
     520: ifnull        530
     523: aload_3
     524: invokevirtual #24                 // Method java/lang/reflect/Method.getName:()Ljava/lang/String;
     527: goto          532
     530: ldc           #62                 // String null
     532: invokevirtual #30                 // Method java/lang/StringBuilder.append:(Ljava/lang/String;)Ljava/lang/StringBuilder;
     535: invokevirtual #33                 // Method java/lang/StringBuilder.toString:()Ljava/lang/String;
     538: astore        5
     540: aload         6
     542: instanceof    #13                 // class org/apache/axis2/AxisFault
     545: ifeq          566
     548: getstatic     #63                 // Field log:Lorg/apache/commons/logging/Log;
     551: aload         5
     553: aload         6
     555: invokeinterface #64,  3           // InterfaceMethod org/apache/commons/logging/Log.debug:(Ljava/lang/Object;Ljava/lang/Throwable;)V
     560: aload         6
     562: checkcast     #13                 // class org/apache/axis2/AxisFault
     565: athrow
     566: aload_3
     567: invokevirtual #65                 // Method java/lang/reflect/Method.getExceptionTypes:()[Ljava/lang/Class;
     570: astore        7
     572: aload         7
     574: astore        8
     576: aload         8
     578: arraylength
     579: istore        9
     581: iconst_0
     582: istore        10
     584: iload         10
     586: iload         9
     588: if_icmpge     876
     591: aload         8
     593: iload         10
     595: aaload
     596: astore        11
     598: aload         6
     600: ifnull        870
     603: aload         11
     605: invokevirtual #32                 // Method java/lang/Class.getName:()Ljava/lang/String;
     608: aload         6
     610: invokevirtual #3                  // Method java/lang/Object.getClass:()Ljava/lang/Class;
     613: invokevirtual #32                 // Method java/lang/Class.getName:()Ljava/lang/String;
     616: invokevirtual #25                 // Method java/lang/String.equals:(Ljava/lang/Object;)Z
     619: ifeq          870
     622: new           #27                 // class java/lang/StringBuilder
     625: dup
     626: invokespecial #28                 // Method java/lang/StringBuilder."<init>":()V
     629: aload_1
     630: invokevirtual #10                 // Method org/apache/axis2/context/MessageContext.getAxisService:()Lorg/apache/axis2/description/AxisService;
     633: invokevirtual #66                 // Method org/apache/axis2/description/AxisService.getName:()Ljava/lang/String;
     636: invokevirtual #30                 // Method java/lang/StringBuilder.append:(Ljava/lang/String;)Ljava/lang/StringBuilder;
     639: aload_0
     640: aload         11
     642: invokespecial #67                 // Method getSimpleClassName:(Ljava/lang/Class;)Ljava/lang/String;
     645: invokevirtual #30                 // Method java/lang/StringBuilder.append:(Ljava/lang/String;)Ljava/lang/StringBuilder;
     648: invokevirtual #33                 // Method java/lang/StringBuilder.toString:()Ljava/lang/String;
     651: astore        12
     653: aload_1
     654: invokevirtual #10                 // Method org/apache/axis2/context/MessageContext.getAxisService:()Lorg/apache/axis2/description/AxisService;
     657: invokevirtual #68                 // Method org/apache/axis2/description/AxisService.getTypeTable:()Lorg/apache/axis2/description/java2wsdl/TypeTable;
     660: astore        13
     662: aload         13
     664: aload         12
     666: invokevirtual #69                 // Method org/apache/axis2/description/java2wsdl/TypeTable.getQNamefortheType:(Ljava/lang/String;)Ljavax/xml/namespace/QName;
     669: astore        14
     671: aload_0
     672: aload_1
     673: invokevirtual #35                 // Method getSOAPFactory:(Lorg/apache/axis2/context/MessageContext;)Lorg/apache/axiom/soap/SOAPFactory;
     676: astore        15
     678: aload         15
     680: aload         14
     682: invokeinterface #70,  2           // InterfaceMethod org/apache/axiom/soap/SOAPFactory.createOMElement:(Ljavax/xml/namespace/QName;)Lorg/apache/axiom/om/OMElement;
     687: astore        16
     689: aload         11
     691: invokevirtual #32                 // Method java/lang/Class.getName:()Ljava/lang/String;
     694: ldc           #71                 // class java/lang/Exception
     696: invokevirtual #32                 // Method java/lang/Class.getName:()Ljava/lang/String;
     699: invokevirtual #25                 // Method java/lang/String.equals:(Ljava/lang/Object;)Z
     702: ifeq          768
     705: aload         15
     707: aload         14
     709: invokeinterface #70,  2           // InterfaceMethod org/apache/axiom/soap/SOAPFactory.createOMElement:(Ljavax/xml/namespace/QName;)Lorg/apache/axiom/om/OMElement;
     714: astore        17
     716: aload         15
     718: ldc           #72                 // String Message
     720: aload_1
     721: invokevirtual #10                 // Method org/apache/axis2/context/MessageContext.getAxisService:()Lorg/apache/axis2/description/AxisService;
     724: invokevirtual #39                 // Method org/apache/axis2/description/AxisService.getTargetNamespace:()Ljava/lang/String;
     727: aconst_null
     728: invokeinterface #73,  4           // InterfaceMethod org/apache/axiom/soap/SOAPFactory.createOMElement:(Ljava/lang/String;Ljava/lang/String;Ljava/lang/String;)Lorg/apache/axiom/om/OMElement;
     733: astore        18
     735: aload         18
     737: aload         6
     739: invokevirtual #60                 // Method java/lang/Throwable.getMessage:()Ljava/lang/String;
     742: invokeinterface #74,  2           // InterfaceMethod org/apache/axiom/om/OMElement.setText:(Ljava/lang/String;)V
     747: aload         17
     749: aload         18
     751: invokeinterface #75,  2           // InterfaceMethod org/apache/axiom/om/OMElement.addChild:(Lorg/apache/axiom/om/OMNode;)V
     756: aload         16
     758: aload         17
     760: invokeinterface #75,  2           // InterfaceMethod org/apache/axiom/om/OMElement.addChild:(Lorg/apache/axiom/om/OMNode;)V
     765: goto          846
     768: aload         6
     770: instanceof    #76                 // class java/lang/RuntimeException
     773: ifne          846
     776: new           #77                 // class javax/xml/namespace/QName
     779: dup
     780: aload         14
     782: invokevirtual #38                 // Method javax/xml/namespace/QName.getNamespaceURI:()Ljava/lang/String;
     785: aload_0
     786: aload         11
     788: invokespecial #67                 // Method getSimpleClassName:(Ljava/lang/Class;)Ljava/lang/String;
     791: invokespecial #78                 // Method javax/xml/namespace/QName."<init>":(Ljava/lang/String;Ljava/lang/String;)V
     794: astore        17
     796: aload         6
     798: aload         17
     800: aload         13
     802: iconst_1
     803: iconst_0
     804: invokestatic  #79                 // Method org/apache/axis2/databinding/utils/BeanUtil.getPullParser:(Ljava/lang/Object;Ljavax/xml/namespace/QName;Lorg/apache/axis2/description/java2wsdl/TypeTable;ZZ)Ljavax/xml/stream/XMLStreamReader;
     807: astore        18
     809: new           #80                 // class org/apache/axiom/om/impl/builder/StAXOMBuilder
     812: dup
     813: invokestatic  #81                 // Method org/apache/axiom/om/OMAbstractFactory.getOMFactory:()Lorg/apache/axiom/om/OMFactory;
     816: new           #82                 // class org/apache/axis2/util/StreamWrapper
     819: dup
     820: aload         18
     822: invokespecial #83                 // Method org/apache/axis2/util/StreamWrapper."<init>":(Ljavax/xml/stream/XMLStreamReader;)V
     825: invokespecial #84                 // Method org/apache/axiom/om/impl/builder/StAXOMBuilder."<init>":(Lorg/apache/axiom/om/OMFactory;Ljavax/xml/stream/XMLStreamReader;)V
     828: astore        19
     830: aload         19
     832: invokevirtual #85                 // Method org/apache/axiom/om/impl/builder/StAXOMBuilder.getDocumentElement:()Lorg/apache/axiom/om/OMElement;
     835: astore        20
     837: aload         16
     839: aload         20
     841: invokeinterface #75,  2           // InterfaceMethod org/apache/axiom/om/OMElement.addChild:(Lorg/apache/axiom/om/OMNode;)V
     846: new           #13                 // class org/apache/axis2/AxisFault
     849: dup
     850: aload         6
     852: invokevirtual #60                 // Method java/lang/Throwable.getMessage:()Ljava/lang/String;
     855: invokespecial #15                 // Method org/apache/axis2/AxisFault."<init>":(Ljava/lang/String;)V
     858: astore        17
     860: aload         17
     862: aload         16
     864: invokevirtual #86                 // Method org/apache/axis2/AxisFault.setDetail:(Lorg/apache/axiom/om/OMElement;)V
     867: aload         17
     869: athrow
     870: iinc          10, 1
     873: goto          584
     876: getstatic     #63                 // Field log:Lorg/apache/commons/logging/Log;
     879: aload         5
     881: aload         4
     883: invokeinterface #87,  3           // InterfaceMethod org/apache/commons/logging/Log.error:(Ljava/lang/Object;Ljava/lang/Throwable;)V
     888: new           #13                 // class org/apache/axis2/AxisFault
     891: dup
     892: aload         5
     894: aload         4
     896: invokespecial #88                 // Method org/apache/axis2/AxisFault."<init>":(Ljava/lang/String;Ljava/lang/Throwable;)V
     899: athrow
     900: astore        4
     902: getstatic     #63                 // Field log:Lorg/apache/commons/logging/Log;
     905: aload         4
     907: invokevirtual #89                 // Method java/lang/RuntimeException.getMessage:()Ljava/lang/String;
     910: aload         4
     912: invokeinterface #87,  3           // InterfaceMethod org/apache/commons/logging/Log.error:(Ljava/lang/Object;Ljava/lang/Throwable;)V
     917: aload         4
     919: invokestatic  #90                 // Method org/apache/axis2/AxisFault.makeFault:(Ljava/lang/Throwable;)Lorg/apache/axis2/AxisFault;
     922: athrow
     923: astore        4
     925: new           #27                 // class java/lang/StringBuilder
     928: dup
     929: invokespecial #28                 // Method java/lang/StringBuilder."<init>":()V
     932: ldc           #61                 // String Exception occurred while trying to invoke service method
     934: invokevirtual #30                 // Method java/lang/StringBuilder.append:(Ljava/lang/String;)Ljava/lang/StringBuilder;
     937: aload_3
     938: ifnull        948
     941: aload_3
     942: invokevirtual #24                 // Method java/lang/reflect/Method.getName:()Ljava/lang/String;
     945: goto          950
     948: ldc           #62                 // String null
     950: invokevirtual #30                 // Method java/lang/StringBuilder.append:(Ljava/lang/String;)Ljava/lang/StringBuilder;
     953: invokevirtual #33                 // Method java/lang/StringBuilder.toString:()Ljava/lang/String;
     956: astore        5
     958: getstatic     #63                 // Field log:Lorg/apache/commons/logging/Log;
     961: aload         5
     963: aload         4
     965: invokeinterface #87,  3           // InterfaceMethod org/apache/commons/logging/Log.error:(Ljava/lang/Object;Ljava/lang/Throwable;)V
     970: aload         4
     972: invokestatic  #90                 // Method org/apache/axis2/AxisFault.makeFault:(Ljava/lang/Throwable;)Lorg/apache/axis2/AxisFault;
     975: athrow
     976: return
    Exception table:
       from    to  target type
           2   404   478   Class java/lang/reflect/InvocationTargetException
         405   475   478   Class java/lang/reflect/InvocationTargetException
           2   404   900   Class java/lang/RuntimeException
         405   475   900   Class java/lang/RuntimeException
           2   404   923   Class java/lang/Exception
         405   475   923   Class java/lang/Exception

  private java.lang.String getSimpleClassName(java.lang.Class<?>);
    Code:
       0: aload_1
       1: invokevirtual #32                 // Method java/lang/Class.getName:()Ljava/lang/String;
       4: astore_2
       5: aload_2
       6: bipush        46
       8: invokevirtual #91                 // Method java/lang/String.lastIndexOf:(I)I
      11: istore_3
      12: iload_3
      13: iconst_m1
      14: if_icmpeq     35
      17: iload_3
      18: aload_2
      19: invokevirtual #92                 // Method java/lang/String.length:()I
      22: iconst_1
      23: isub
      24: if_icmpge     35
      27: aload_2
      28: iload_3
      29: iconst_1
      30: iadd
      31: invokevirtual #93                 // Method java/lang/String.substring:(I)Ljava/lang/String;
      34: astore_2
      35: aload_2
      36: bipush        36
      38: bipush        95
      40: invokevirtual #94                 // Method java/lang/String.replace:(CC)Ljava/lang/String;
      43: areturn

  static {};
    Code:
       0: ldc           #95                 // class org/apache/axis2/rpc/receivers/RPCMessageReceiver
       2: invokestatic  #96                 // Method org/apache/commons/logging/LogFactory.getLog:(Ljava/lang/Class;)Lorg/apache/commons/logging/Log;
       5: putstatic     #63                 // Field log:Lorg/apache/commons/logging/Log;
       8: return
}
