Compiled from "CombinedTrackable.java"
class org.sonarsource.sonarlint.core.issuetracking.CombinedTrackable extends org.sonarsource.sonarlint.core.issuetracking.AbstractTrackable {
  org.sonarsource.sonarlint.core.issuetracking.CombinedTrackable(org.sonarsource.sonarlint.core.issuetracking.Trackable, org.sonarsource.sonarlint.core.issuetracking.Trackable, boolean);
    Code:
       0: aload_0
       1: aload_2
       2: invokespecial #10                 // Method org/sonarsource/sonarlint/core/issuetracking/AbstractTrackable."<init>":(Lorg/sonarsource/sonarlint/core/issuetracking/Trackable;)V
       5: aload_0
       6: aload_1
       7: invokeinterface #16,  1           // InterfaceMethod org/sonarsource/sonarlint/core/issuetracking/Trackable.getCreationDate:()Ljava/lang/Long;
      12: putfield      #20                 // Field creationDate:Ljava/lang/Long;
      15: aload_0
      16: aload_1
      17: invokeinterface #24,  1           // InterfaceMethod org/sonarsource/sonarlint/core/issuetracking/Trackable.getServerIssueKey:()Ljava/lang/String;
      22: putfield      #28                 // Field serverIssueKey:Ljava/lang/String;
      25: aload_0
      26: aload_1
      27: invokeinterface #32,  1           // InterfaceMethod org/sonarsource/sonarlint/core/issuetracking/Trackable.isResolved:()Z
      32: putfield      #36                 // Field resolved:Z
      35: aload_0
      36: aload_1
      37: invokeinterface #39,  1           // InterfaceMethod org/sonarsource/sonarlint/core/issuetracking/Trackable.getAssignee:()Ljava/lang/String;
      42: putfield      #42                 // Field assignee:Ljava/lang/String;
      45: iload_3
      46: ifeq          78
      49: aload_0
      50: aload_1
      51: invokeinterface #45,  1           // InterfaceMethod org/sonarsource/sonarlint/core/issuetracking/Trackable.getSeverity:()Ljava/lang/String;
      56: putfield      #48                 // Field severity:Ljava/lang/String;
      59: aload_1
      60: invokeinterface #51,  1           // InterfaceMethod org/sonarsource/sonarlint/core/issuetracking/Trackable.getType:()Ljava/lang/String;
      65: ifnull        78
      68: aload_0
      69: aload_1
      70: invokeinterface #51,  1           // InterfaceMethod org/sonarsource/sonarlint/core/issuetracking/Trackable.getType:()Ljava/lang/String;
      75: putfield      #54                 // Field type:Ljava/lang/String;
      78: return
}
