Compiled from "AbstractEmptinessExpression.java"
public abstract class org.hibernate.criterion.AbstractEmptinessExpression implements org.hibernate.criterion.Criterion {
  private static final org.hibernate.engine.spi.TypedValue[] NO_VALUES;

  protected final java.lang.String propertyName;

  protected org.hibernate.criterion.AbstractEmptinessExpression(java.lang.String);
    Code:
       0: aload_0
       1: invokespecial #1                  // Method java/lang/Object."<init>":()V
       4: aload_0
       5: aload_1
       6: putfield      #2                  // Field propertyName:Ljava/lang/String;
       9: return

  protected abstract boolean excludeEmpty();

  public final java.lang.String toSqlString(org.hibernate.Criteria, org.hibernate.criterion.CriteriaQuery) throws org.hibernate.HibernateException;
    Code:
       0: aload_2
       1: aload_1
       2: aload_0
       3: getfield      #2                  // Field propertyName:Ljava/lang/String;
       6: invokeinterface #3,  3            // InterfaceMethod org/hibernate/criterion/CriteriaQuery.getEntityName:(Lorg/hibernate/Criteria;Ljava/lang/String;)Ljava/lang/String;
      11: astore_3
      12: aload_2
      13: aload_0
      14: getfield      #2                  // Field propertyName:Ljava/lang/String;
      17: invokeinterface #4,  2            // InterfaceMethod org/hibernate/criterion/CriteriaQuery.getPropertyName:(Ljava/lang/String;)Ljava/lang/String;
      22: astore        4
      24: aload_2
      25: aload_1
      26: aload_0
      27: getfield      #2                  // Field propertyName:Ljava/lang/String;
      30: invokeinterface #5,  3            // InterfaceMethod org/hibernate/criterion/CriteriaQuery.getSQLAlias:(Lorg/hibernate/Criteria;Ljava/lang/String;)Ljava/lang/String;
      35: astore        5
      37: aload_2
      38: invokeinterface #6,  1            // InterfaceMethod org/hibernate/criterion/CriteriaQuery.getFactory:()Lorg/hibernate/engine/spi/SessionFactoryImplementor;
      43: astore        6
      45: aload_0
      46: aload_3
      47: aload         4
      49: aload         6
      51: invokevirtual #7                  // Method getQueryableCollection:(Ljava/lang/String;Ljava/lang/String;Lorg/hibernate/engine/spi/SessionFactoryImplementor;)Lorg/hibernate/persister/collection/QueryableCollection;
      54: astore        7
      56: aload         7
      58: invokeinterface #8,  1            // InterfaceMethod org/hibernate/persister/collection/QueryableCollection.getKeyColumnNames:()[Ljava/lang/String;
      63: astore        8
      65: aload         6
      67: aload_3
      68: invokeinterface #9,  2            // InterfaceMethod org/hibernate/engine/spi/SessionFactoryImplementor.getEntityPersister:(Ljava/lang/String;)Lorg/hibernate/persister/entity/EntityPersister;
      73: checkcast     #10                 // class org/hibernate/persister/entity/Loadable
      76: invokeinterface #11,  1           // InterfaceMethod org/hibernate/persister/entity/Loadable.getIdentifierColumnNames:()[Ljava/lang/String;
      81: astore        9
      83: new           #12                 // class java/lang/StringBuilder
      86: dup
      87: invokespecial #13                 // Method java/lang/StringBuilder."<init>":()V
      90: ldc           #14                 // String (select 1 from
      92: invokevirtual #15                 // Method java/lang/StringBuilder.append:(Ljava/lang/String;)Ljava/lang/StringBuilder;
      95: aload         7
      97: invokeinterface #16,  1           // InterfaceMethod org/hibernate/persister/collection/QueryableCollection.getTableName:()Ljava/lang/String;
     102: invokevirtual #15                 // Method java/lang/StringBuilder.append:(Ljava/lang/String;)Ljava/lang/StringBuilder;
     105: ldc           #17                 // String  where
     107: invokevirtual #15                 // Method java/lang/StringBuilder.append:(Ljava/lang/String;)Ljava/lang/StringBuilder;
     110: new           #18                 // class org/hibernate/sql/ConditionFragment
     113: dup
     114: invokespecial #19                 // Method org/hibernate/sql/ConditionFragment."<init>":()V
     117: aload         5
     119: invokevirtual #20                 // Method org/hibernate/sql/ConditionFragment.setTableAlias:(Ljava/lang/String;)Lorg/hibernate/sql/ConditionFragment;
     122: aload         9
     124: aload         8
     126: invokevirtual #21                 // Method org/hibernate/sql/ConditionFragment.setCondition:([Ljava/lang/String;[Ljava/lang/String;)Lorg/hibernate/sql/ConditionFragment;
     129: invokevirtual #22                 // Method org/hibernate/sql/ConditionFragment.toFragmentString:()Ljava/lang/String;
     132: invokevirtual #15                 // Method java/lang/StringBuilder.append:(Ljava/lang/String;)Ljava/lang/StringBuilder;
     135: ldc           #23                 // String )
     137: invokevirtual #15                 // Method java/lang/StringBuilder.append:(Ljava/lang/String;)Ljava/lang/StringBuilder;
     140: invokevirtual #24                 // Method java/lang/StringBuilder.toString:()Ljava/lang/String;
     143: astore        10
     145: aload_0
     146: invokevirtual #25                 // Method excludeEmpty:()Z
     149: ifeq          175
     152: new           #12                 // class java/lang/StringBuilder
     155: dup
     156: invokespecial #13                 // Method java/lang/StringBuilder."<init>":()V
     159: ldc           #26                 // String exists
     161: invokevirtual #15                 // Method java/lang/StringBuilder.append:(Ljava/lang/String;)Ljava/lang/StringBuilder;
     164: aload         10
     166: invokevirtual #15                 // Method java/lang/StringBuilder.append:(Ljava/lang/String;)Ljava/lang/StringBuilder;
     169: invokevirtual #24                 // Method java/lang/StringBuilder.toString:()Ljava/lang/String;
     172: goto          195
     175: new           #12                 // class java/lang/StringBuilder
     178: dup
     179: invokespecial #13                 // Method java/lang/StringBuilder."<init>":()V
     182: ldc           #27                 // String not exists
     184: invokevirtual #15                 // Method java/lang/StringBuilder.append:(Ljava/lang/String;)Ljava/lang/StringBuilder;
     187: aload         10
     189: invokevirtual #15                 // Method java/lang/StringBuilder.append:(Ljava/lang/String;)Ljava/lang/StringBuilder;
     192: invokevirtual #24                 // Method java/lang/StringBuilder.toString:()Ljava/lang/String;
     195: areturn

  protected org.hibernate.persister.collection.QueryableCollection getQueryableCollection(java.lang.String, java.lang.String, org.hibernate.engine.spi.SessionFactoryImplementor) throws org.hibernate.HibernateException;
    Code:
       0: aload_3
       1: aload_1
       2: invokeinterface #9,  2            // InterfaceMethod org/hibernate/engine/spi/SessionFactoryImplementor.getEntityPersister:(Ljava/lang/String;)Lorg/hibernate/persister/entity/EntityPersister;
       7: checkcast     #28                 // class org/hibernate/persister/entity/PropertyMapping
      10: astore        4
      12: aload         4
      14: aload_2
      15: invokeinterface #29,  2           // InterfaceMethod org/hibernate/persister/entity/PropertyMapping.toType:(Ljava/lang/String;)Lorg/hibernate/type/Type;
      20: astore        5
      22: aload         5
      24: invokeinterface #30,  1           // InterfaceMethod org/hibernate/type/Type.isCollectionType:()Z
      29: ifne          73
      32: new           #31                 // class org/hibernate/MappingException
      35: dup
      36: new           #12                 // class java/lang/StringBuilder
      39: dup
      40: invokespecial #13                 // Method java/lang/StringBuilder."<init>":()V
      43: ldc           #32                 // String Property path [
      45: invokevirtual #15                 // Method java/lang/StringBuilder.append:(Ljava/lang/String;)Ljava/lang/StringBuilder;
      48: aload_1
      49: invokevirtual #15                 // Method java/lang/StringBuilder.append:(Ljava/lang/String;)Ljava/lang/StringBuilder;
      52: ldc           #33                 // String .
      54: invokevirtual #15                 // Method java/lang/StringBuilder.append:(Ljava/lang/String;)Ljava/lang/StringBuilder;
      57: aload_2
      58: invokevirtual #15                 // Method java/lang/StringBuilder.append:(Ljava/lang/String;)Ljava/lang/StringBuilder;
      61: ldc           #34                 // String ] does not reference a collection
      63: invokevirtual #15                 // Method java/lang/StringBuilder.append:(Ljava/lang/String;)Ljava/lang/StringBuilder;
      66: invokevirtual #24                 // Method java/lang/StringBuilder.toString:()Ljava/lang/String;
      69: invokespecial #35                 // Method org/hibernate/MappingException."<init>":(Ljava/lang/String;)V
      72: athrow
      73: aload         5
      75: checkcast     #36                 // class org/hibernate/type/CollectionType
      78: invokevirtual #37                 // Method org/hibernate/type/CollectionType.getRole:()Ljava/lang/String;
      81: astore        6
      83: aload_3
      84: aload         6
      86: invokeinterface #38,  2           // InterfaceMethod org/hibernate/engine/spi/SessionFactoryImplementor.getCollectionPersister:(Ljava/lang/String;)Lorg/hibernate/persister/collection/CollectionPersister;
      91: checkcast     #39                 // class org/hibernate/persister/collection/QueryableCollection
      94: areturn
      95: astore        7
      97: new           #41                 // class org/hibernate/QueryException
     100: dup
     101: new           #12                 // class java/lang/StringBuilder
     104: dup
     105: invokespecial #13                 // Method java/lang/StringBuilder."<init>":()V
     108: ldc           #42                 // String collection role is not queryable:
     110: invokevirtual #15                 // Method java/lang/StringBuilder.append:(Ljava/lang/String;)Ljava/lang/StringBuilder;
     113: aload         6
     115: invokevirtual #15                 // Method java/lang/StringBuilder.append:(Ljava/lang/String;)Ljava/lang/StringBuilder;
     118: invokevirtual #24                 // Method java/lang/StringBuilder.toString:()Ljava/lang/String;
     121: invokespecial #43                 // Method org/hibernate/QueryException."<init>":(Ljava/lang/String;)V
     124: athrow
     125: astore        7
     127: new           #41                 // class org/hibernate/QueryException
     130: dup
     131: new           #12                 // class java/lang/StringBuilder
     134: dup
     135: invokespecial #13                 // Method java/lang/StringBuilder."<init>":()V
     138: ldc           #45                 // String collection role not found:
     140: invokevirtual #15                 // Method java/lang/StringBuilder.append:(Ljava/lang/String;)Ljava/lang/StringBuilder;
     143: aload         6
     145: invokevirtual #15                 // Method java/lang/StringBuilder.append:(Ljava/lang/String;)Ljava/lang/StringBuilder;
     148: invokevirtual #24                 // Method java/lang/StringBuilder.toString:()Ljava/lang/String;
     151: invokespecial #43                 // Method org/hibernate/QueryException."<init>":(Ljava/lang/String;)V
     154: athrow
    Exception table:
       from    to  target type
          83    94    95   Class java/lang/ClassCastException
          83    94   125   Class java/lang/Exception

  public final org.hibernate.engine.spi.TypedValue[] getTypedValues(org.hibernate.Criteria, org.hibernate.criterion.CriteriaQuery) throws org.hibernate.HibernateException;
    Code:
       0: getstatic     #46                 // Field NO_VALUES:[Lorg/hibernate/engine/spi/TypedValue;
       3: areturn

  public final java.lang.String toString();
    Code:
       0: new           #12                 // class java/lang/StringBuilder
       3: dup
       4: invokespecial #13                 // Method java/lang/StringBuilder."<init>":()V
       7: aload_0
       8: getfield      #2                  // Field propertyName:Ljava/lang/String;
      11: invokevirtual #15                 // Method java/lang/StringBuilder.append:(Ljava/lang/String;)Ljava/lang/StringBuilder;
      14: aload_0
      15: invokevirtual #25                 // Method excludeEmpty:()Z
      18: ifeq          26
      21: ldc           #47                 // String  is not empty
      23: goto          28
      26: ldc           #48                 // String  is empty
      28: invokevirtual #15                 // Method java/lang/StringBuilder.append:(Ljava/lang/String;)Ljava/lang/StringBuilder;
      31: invokevirtual #24                 // Method java/lang/StringBuilder.toString:()Ljava/lang/String;
      34: areturn

  static {};
    Code:
       0: iconst_0
       1: anewarray     #49                 // class org/hibernate/engine/spi/TypedValue
       4: putstatic     #46                 // Field NO_VALUES:[Lorg/hibernate/engine/spi/TypedValue;
       7: return
}
