Compiled from "SQLCriterion.java"
public class org.hibernate.criterion.SQLCriterion implements org.hibernate.criterion.Criterion {
  private final java.lang.String sql;

  private final org.hibernate.engine.spi.TypedValue[] typedValues;

  protected org.hibernate.criterion.SQLCriterion(java.lang.String, java.lang.Object[], org.hibernate.type.Type[]);
    Code:
       0: aload_0
       1: invokespecial #1                  // Method java/lang/Object."<init>":()V
       4: aload_0
       5: aload_1
       6: putfield      #2                  // Field sql:Ljava/lang/String;
       9: aload_0
      10: aload_2
      11: arraylength
      12: anewarray     #3                  // class org/hibernate/engine/spi/TypedValue
      15: putfield      #4                  // Field typedValues:[Lorg/hibernate/engine/spi/TypedValue;
      18: iconst_0
      19: istore        4
      21: iload         4
      23: aload_0
      24: getfield      #4                  // Field typedValues:[Lorg/hibernate/engine/spi/TypedValue;
      27: arraylength
      28: if_icmpge     59
      31: aload_0
      32: getfield      #4                  // Field typedValues:[Lorg/hibernate/engine/spi/TypedValue;
      35: iload         4
      37: new           #3                  // class org/hibernate/engine/spi/TypedValue
      40: dup
      41: aload_3
      42: iload         4
      44: aaload
      45: aload_2
      46: iload         4
      48: aaload
      49: invokespecial #5                  // Method org/hibernate/engine/spi/TypedValue."<init>":(Lorg/hibernate/type/Type;Ljava/lang/Object;)V
      52: aastore
      53: iinc          4, 1
      56: goto          21
      59: return

  protected org.hibernate.criterion.SQLCriterion(java.lang.String, java.lang.Object, org.hibernate.type.Type);
    Code:
       0: aload_0
       1: invokespecial #1                  // Method java/lang/Object."<init>":()V
       4: aload_0
       5: aload_1
       6: putfield      #2                  // Field sql:Ljava/lang/String;
       9: aload_0
      10: iconst_1
      11: anewarray     #3                  // class org/hibernate/engine/spi/TypedValue
      14: dup
      15: iconst_0
      16: new           #3                  // class org/hibernate/engine/spi/TypedValue
      19: dup
      20: aload_3
      21: aload_2
      22: invokespecial #5                  // Method org/hibernate/engine/spi/TypedValue."<init>":(Lorg/hibernate/type/Type;Ljava/lang/Object;)V
      25: aastore
      26: putfield      #4                  // Field typedValues:[Lorg/hibernate/engine/spi/TypedValue;
      29: return

  protected org.hibernate.criterion.SQLCriterion(java.lang.String);
    Code:
       0: aload_0
       1: invokespecial #1                  // Method java/lang/Object."<init>":()V
       4: aload_0
       5: aload_1
       6: putfield      #2                  // Field sql:Ljava/lang/String;
       9: aload_0
      10: iconst_0
      11: anewarray     #3                  // class org/hibernate/engine/spi/TypedValue
      14: putfield      #4                  // Field typedValues:[Lorg/hibernate/engine/spi/TypedValue;
      17: return

  public java.lang.String toSqlString(org.hibernate.Criteria, org.hibernate.criterion.CriteriaQuery);
    Code:
       0: aload_0
       1: getfield      #2                  // Field sql:Ljava/lang/String;
       4: ldc           #6                  // String {alias}
       6: aload_2
       7: aload_1
       8: invokeinterface #7,  2            // InterfaceMethod org/hibernate/criterion/CriteriaQuery.getSQLAlias:(Lorg/hibernate/Criteria;)Ljava/lang/String;
      13: invokestatic  #8                  // Method org/hibernate/internal/util/StringHelper.replace:(Ljava/lang/String;Ljava/lang/String;Ljava/lang/String;)Ljava/lang/String;
      16: areturn

  public org.hibernate.engine.spi.TypedValue[] getTypedValues(org.hibernate.Criteria, org.hibernate.criterion.CriteriaQuery);
    Code:
       0: aload_0
       1: getfield      #4                  // Field typedValues:[Lorg/hibernate/engine/spi/TypedValue;
       4: areturn

  public java.lang.String toString();
    Code:
       0: aload_0
       1: getfield      #2                  // Field sql:Ljava/lang/String;
       4: areturn
}
