Compiled from "SubqueryExpression.java"
public abstract class org.hibernate.criterion.SubqueryExpression implements org.hibernate.criterion.Criterion {
  private org.hibernate.internal.CriteriaImpl criteriaImpl;

  private java.lang.String quantifier;

  private java.lang.String op;

  private org.hibernate.engine.spi.QueryParameters params;

  private org.hibernate.type.Type[] types;

  private org.hibernate.loader.criteria.CriteriaQueryTranslator innerQuery;

  protected org.hibernate.criterion.SubqueryExpression(java.lang.String, java.lang.String, org.hibernate.criterion.DetachedCriteria);
    Code:
       0: aload_0
       1: invokespecial #1                  // Method java/lang/Object."<init>":()V
       4: aload_0
       5: aload_3
       6: invokevirtual #2                  // Method org/hibernate/criterion/DetachedCriteria.getCriteriaImpl:()Lorg/hibernate/internal/CriteriaImpl;
       9: putfield      #3                  // Field criteriaImpl:Lorg/hibernate/internal/CriteriaImpl;
      12: aload_0
      13: aload_2
      14: putfield      #4                  // Field quantifier:Ljava/lang/String;
      17: aload_0
      18: aload_1
      19: putfield      #5                  // Field op:Ljava/lang/String;
      22: return

  protected org.hibernate.type.Type[] getTypes();
    Code:
       0: aload_0
       1: getfield      #6                  // Field types:[Lorg/hibernate/type/Type;
       4: areturn

  protected abstract java.lang.String toLeftSqlString(org.hibernate.Criteria, org.hibernate.criterion.CriteriaQuery);

  public java.lang.String toSqlString(org.hibernate.Criteria, org.hibernate.criterion.CriteriaQuery) throws org.hibernate.HibernateException;
    Code:
       0: new           #7                  // class java/lang/StringBuilder
       3: dup
       4: aload_0
       5: aload_1
       6: aload_2
       7: invokevirtual #8                  // Method toLeftSqlString:(Lorg/hibernate/Criteria;Lorg/hibernate/criterion/CriteriaQuery;)Ljava/lang/String;
      10: invokespecial #9                  // Method java/lang/StringBuilder."<init>":(Ljava/lang/String;)V
      13: astore_3
      14: aload_0
      15: getfield      #5                  // Field op:Ljava/lang/String;
      18: ifnull        40
      21: aload_3
      22: bipush        32
      24: invokevirtual #10                 // Method java/lang/StringBuilder.append:(C)Ljava/lang/StringBuilder;
      27: aload_0
      28: getfield      #5                  // Field op:Ljava/lang/String;
      31: invokevirtual #11                 // Method java/lang/StringBuilder.append:(Ljava/lang/String;)Ljava/lang/StringBuilder;
      34: bipush        32
      36: invokevirtual #10                 // Method java/lang/StringBuilder.append:(C)Ljava/lang/StringBuilder;
      39: pop
      40: aload_0
      41: getfield      #4                  // Field quantifier:Ljava/lang/String;
      44: ifnull        61
      47: aload_3
      48: aload_0
      49: getfield      #4                  // Field quantifier:Ljava/lang/String;
      52: invokevirtual #11                 // Method java/lang/StringBuilder.append:(Ljava/lang/String;)Ljava/lang/StringBuilder;
      55: bipush        32
      57: invokevirtual #10                 // Method java/lang/StringBuilder.append:(C)Ljava/lang/StringBuilder;
      60: pop
      61: aload_2
      62: invokeinterface #12,  1           // InterfaceMethod org/hibernate/criterion/CriteriaQuery.getFactory:()Lorg/hibernate/engine/spi/SessionFactoryImplementor;
      67: astore        4
      69: aload         4
      71: invokeinterface #13,  1           // InterfaceMethod org/hibernate/engine/spi/SessionFactoryImplementor.getMetamodel:()Lorg/hibernate/metamodel/spi/MetamodelImplementor;
      76: aload_0
      77: getfield      #3                  // Field criteriaImpl:Lorg/hibernate/internal/CriteriaImpl;
      80: invokevirtual #14                 // Method org/hibernate/internal/CriteriaImpl.getEntityOrClassName:()Ljava/lang/String;
      83: invokeinterface #15,  2           // InterfaceMethod org/hibernate/metamodel/spi/MetamodelImplementor.entityPersister:(Ljava/lang/String;)Lorg/hibernate/persister/entity/EntityPersister;
      88: checkcast     #16                 // class org/hibernate/persister/entity/OuterJoinLoadable
      91: astore        5
      93: aload_0
      94: aload_2
      95: aload         4
      97: invokespecial #17                 // Method createAndSetInnerQuery:(Lorg/hibernate/criterion/CriteriaQuery;Lorg/hibernate/engine/spi/SessionFactoryImplementor;)V
     100: aload_0
     101: getfield      #3                  // Field criteriaImpl:Lorg/hibernate/internal/CriteriaImpl;
     104: aload_0
     105: aload_1
     106: invokespecial #18                 // Method deriveRootSession:(Lorg/hibernate/Criteria;)Lorg/hibernate/engine/spi/SharedSessionContractImplementor;
     109: invokevirtual #19                 // Method org/hibernate/internal/CriteriaImpl.setSession:(Lorg/hibernate/engine/spi/SharedSessionContractImplementor;)V
     112: new           #20                 // class org/hibernate/loader/criteria/CriteriaJoinWalker
     115: dup
     116: aload         5
     118: aload_0
     119: getfield      #21                 // Field innerQuery:Lorg/hibernate/loader/criteria/CriteriaQueryTranslator;
     122: aload         4
     124: aload_0
     125: getfield      #3                  // Field criteriaImpl:Lorg/hibernate/internal/CriteriaImpl;
     128: aload_0
     129: getfield      #3                  // Field criteriaImpl:Lorg/hibernate/internal/CriteriaImpl;
     132: invokevirtual #14                 // Method org/hibernate/internal/CriteriaImpl.getEntityOrClassName:()Ljava/lang/String;
     135: aload_0
     136: getfield      #3                  // Field criteriaImpl:Lorg/hibernate/internal/CriteriaImpl;
     139: invokevirtual #22                 // Method org/hibernate/internal/CriteriaImpl.getSession:()Lorg/hibernate/engine/spi/SharedSessionContractImplementor;
     142: invokeinterface #23,  1           // InterfaceMethod org/hibernate/engine/spi/SharedSessionContractImplementor.getLoadQueryInfluencers:()Lorg/hibernate/engine/spi/LoadQueryInfluencers;
     147: aload_0
     148: getfield      #21                 // Field innerQuery:Lorg/hibernate/loader/criteria/CriteriaQueryTranslator;
     151: invokevirtual #24                 // Method org/hibernate/loader/criteria/CriteriaQueryTranslator.getRootSQLALias:()Ljava/lang/String;
     154: invokespecial #25                 // Method org/hibernate/loader/criteria/CriteriaJoinWalker."<init>":(Lorg/hibernate/persister/entity/OuterJoinLoadable;Lorg/hibernate/loader/criteria/CriteriaQueryTranslator;Lorg/hibernate/engine/spi/SessionFactoryImplementor;Lorg/hibernate/internal/CriteriaImpl;Ljava/lang/String;Lorg/hibernate/engine/spi/LoadQueryInfluencers;Ljava/lang/String;)V
     157: astore        6
     159: aload_3
     160: bipush        40
     162: invokevirtual #10                 // Method java/lang/StringBuilder.append:(C)Ljava/lang/StringBuilder;
     165: aload         6
     167: invokevirtual #26                 // Method org/hibernate/loader/criteria/CriteriaJoinWalker.getSQLString:()Ljava/lang/String;
     170: invokevirtual #11                 // Method java/lang/StringBuilder.append:(Ljava/lang/String;)Ljava/lang/StringBuilder;
     173: bipush        41
     175: invokevirtual #10                 // Method java/lang/StringBuilder.append:(C)Ljava/lang/StringBuilder;
     178: invokevirtual #27                 // Method java/lang/StringBuilder.toString:()Ljava/lang/String;
     181: areturn

  private org.hibernate.engine.spi.SharedSessionContractImplementor deriveRootSession(org.hibernate.Criteria);
    Code:
       0: aload_1
       1: instanceof    #28                 // class org/hibernate/internal/CriteriaImpl
       4: ifeq          15
       7: aload_1
       8: checkcast     #28                 // class org/hibernate/internal/CriteriaImpl
      11: invokevirtual #22                 // Method org/hibernate/internal/CriteriaImpl.getSession:()Lorg/hibernate/engine/spi/SharedSessionContractImplementor;
      14: areturn
      15: aload_1
      16: instanceof    #29                 // class org/hibernate/internal/CriteriaImpl$Subcriteria
      19: ifeq          34
      22: aload_0
      23: aload_1
      24: checkcast     #29                 // class org/hibernate/internal/CriteriaImpl$Subcriteria
      27: invokevirtual #30                 // Method org/hibernate/internal/CriteriaImpl$Subcriteria.getParent:()Lorg/hibernate/Criteria;
      30: invokespecial #18                 // Method deriveRootSession:(Lorg/hibernate/Criteria;)Lorg/hibernate/engine/spi/SharedSessionContractImplementor;
      33: areturn
      34: aconst_null
      35: areturn

  public org.hibernate.engine.spi.TypedValue[] getTypedValues(org.hibernate.Criteria, org.hibernate.criterion.CriteriaQuery) throws org.hibernate.HibernateException;
    Code:
       0: aload_2
       1: invokeinterface #12,  1           // InterfaceMethod org/hibernate/criterion/CriteriaQuery.getFactory:()Lorg/hibernate/engine/spi/SessionFactoryImplementor;
       6: astore_3
       7: aload_0
       8: aload_2
       9: aload_3
      10: invokespecial #17                 // Method createAndSetInnerQuery:(Lorg/hibernate/criterion/CriteriaQuery;Lorg/hibernate/engine/spi/SessionFactoryImplementor;)V
      13: aload_0
      14: getfield      #31                 // Field params:Lorg/hibernate/engine/spi/QueryParameters;
      17: invokevirtual #32                 // Method org/hibernate/engine/spi/QueryParameters.getPositionalParameterTypes:()[Lorg/hibernate/type/Type;
      20: astore        4
      22: aload_0
      23: getfield      #31                 // Field params:Lorg/hibernate/engine/spi/QueryParameters;
      26: invokevirtual #33                 // Method org/hibernate/engine/spi/QueryParameters.getPositionalParameterValues:()[Ljava/lang/Object;
      29: astore        5
      31: aload         4
      33: arraylength
      34: anewarray     #34                 // class org/hibernate/engine/spi/TypedValue
      37: astore        6
      39: iconst_0
      40: istore        7
      42: iload         7
      44: aload         4
      46: arraylength
      47: if_icmpge     78
      50: aload         6
      52: iload         7
      54: new           #34                 // class org/hibernate/engine/spi/TypedValue
      57: dup
      58: aload         4
      60: iload         7
      62: aaload
      63: aload         5
      65: iload         7
      67: aaload
      68: invokespecial #35                 // Method org/hibernate/engine/spi/TypedValue."<init>":(Lorg/hibernate/type/Type;Ljava/lang/Object;)V
      71: aastore
      72: iinc          7, 1
      75: goto          42
      78: aload         6
      80: areturn

  private void createAndSetInnerQuery(org.hibernate.criterion.CriteriaQuery, org.hibernate.engine.spi.SessionFactoryImplementor);
    Code:
       0: aload_0
       1: getfield      #21                 // Field innerQuery:Lorg/hibernate/loader/criteria/CriteriaQueryTranslator;
       4: ifnonnull     100
       7: aload_0
       8: getfield      #3                  // Field criteriaImpl:Lorg/hibernate/internal/CriteriaImpl;
      11: invokevirtual #36                 // Method org/hibernate/internal/CriteriaImpl.getAlias:()Ljava/lang/String;
      14: ifnonnull     27
      17: aload_1
      18: invokeinterface #37,  1           // InterfaceMethod org/hibernate/criterion/CriteriaQuery.generateSQLAlias:()Ljava/lang/String;
      23: astore_3
      24: goto          53
      27: new           #7                  // class java/lang/StringBuilder
      30: dup
      31: invokespecial #38                 // Method java/lang/StringBuilder."<init>":()V
      34: aload_0
      35: getfield      #3                  // Field criteriaImpl:Lorg/hibernate/internal/CriteriaImpl;
      38: invokevirtual #36                 // Method org/hibernate/internal/CriteriaImpl.getAlias:()Ljava/lang/String;
      41: invokevirtual #11                 // Method java/lang/StringBuilder.append:(Ljava/lang/String;)Ljava/lang/StringBuilder;
      44: ldc           #39                 // String _
      46: invokevirtual #11                 // Method java/lang/StringBuilder.append:(Ljava/lang/String;)Ljava/lang/StringBuilder;
      49: invokevirtual #27                 // Method java/lang/StringBuilder.toString:()Ljava/lang/String;
      52: astore_3
      53: aload_0
      54: new           #40                 // class org/hibernate/loader/criteria/CriteriaQueryTranslator
      57: dup
      58: aload_2
      59: aload_0
      60: getfield      #3                  // Field criteriaImpl:Lorg/hibernate/internal/CriteriaImpl;
      63: aload_0
      64: getfield      #3                  // Field criteriaImpl:Lorg/hibernate/internal/CriteriaImpl;
      67: invokevirtual #14                 // Method org/hibernate/internal/CriteriaImpl.getEntityOrClassName:()Ljava/lang/String;
      70: aload_3
      71: aload_1
      72: invokespecial #41                 // Method org/hibernate/loader/criteria/CriteriaQueryTranslator."<init>":(Lorg/hibernate/engine/spi/SessionFactoryImplementor;Lorg/hibernate/internal/CriteriaImpl;Ljava/lang/String;Ljava/lang/String;Lorg/hibernate/criterion/CriteriaQuery;)V
      75: putfield      #21                 // Field innerQuery:Lorg/hibernate/loader/criteria/CriteriaQueryTranslator;
      78: aload_0
      79: aload_0
      80: getfield      #21                 // Field innerQuery:Lorg/hibernate/loader/criteria/CriteriaQueryTranslator;
      83: invokevirtual #42                 // Method org/hibernate/loader/criteria/CriteriaQueryTranslator.getQueryParameters:()Lorg/hibernate/engine/spi/QueryParameters;
      86: putfield      #31                 // Field params:Lorg/hibernate/engine/spi/QueryParameters;
      89: aload_0
      90: aload_0
      91: getfield      #21                 // Field innerQuery:Lorg/hibernate/loader/criteria/CriteriaQueryTranslator;
      94: invokevirtual #43                 // Method org/hibernate/loader/criteria/CriteriaQueryTranslator.getProjectedTypes:()[Lorg/hibernate/type/Type;
      97: putfield      #6                  // Field types:[Lorg/hibernate/type/Type;
     100: return
}
