Compiled from "FeatureMatcher.java"
public abstract class org.hamcrest.FeatureMatcher<T, U> extends org.hamcrest.TypeSafeDiagnosingMatcher<T> {
  private static final org.hamcrest.internal.ReflectiveTypeFinder TYPE_FINDER;

  private final org.hamcrest.Matcher<? super U> subMatcher;

  private final java.lang.String featureDescription;

  private final java.lang.String featureName;

  public org.hamcrest.FeatureMatcher(org.hamcrest.Matcher<? super U>, java.lang.String, java.lang.String);
    Code:
       0: aload_0
       1: getstatic     #1                  // Field TYPE_FINDER:Lorg/hamcrest/internal/ReflectiveTypeFinder;
       4: invokespecial #2                  // Method org/hamcrest/TypeSafeDiagnosingMatcher."<init>":(Lorg/hamcrest/internal/ReflectiveTypeFinder;)V
       7: aload_0
       8: aload_1
       9: putfield      #3                  // Field subMatcher:Lorg/hamcrest/Matcher;
      12: aload_0
      13: aload_2
      14: putfield      #4                  // Field featureDescription:Ljava/lang/String;
      17: aload_0
      18: aload_3
      19: putfield      #5                  // Field featureName:Ljava/lang/String;
      22: return

  protected abstract U featureValueOf(T);

  protected boolean matchesSafely(T, org.hamcrest.Description);
    Code:
       0: aload_0
       1: aload_1
       2: invokevirtual #6                  // Method featureValueOf:(Ljava/lang/Object;)Ljava/lang/Object;
       5: astore_3
       6: aload_0
       7: getfield      #3                  // Field subMatcher:Lorg/hamcrest/Matcher;
      10: aload_3
      11: invokeinterface #7,  2            // InterfaceMethod org/hamcrest/Matcher.matches:(Ljava/lang/Object;)Z
      16: ifne          50
      19: aload_2
      20: aload_0
      21: getfield      #5                  // Field featureName:Ljava/lang/String;
      24: invokeinterface #8,  2            // InterfaceMethod org/hamcrest/Description.appendText:(Ljava/lang/String;)Lorg/hamcrest/Description;
      29: ldc           #9                  // String
      31: invokeinterface #8,  2            // InterfaceMethod org/hamcrest/Description.appendText:(Ljava/lang/String;)Lorg/hamcrest/Description;
      36: pop
      37: aload_0
      38: getfield      #3                  // Field subMatcher:Lorg/hamcrest/Matcher;
      41: aload_3
      42: aload_2
      43: invokeinterface #10,  3           // InterfaceMethod org/hamcrest/Matcher.describeMismatch:(Ljava/lang/Object;Lorg/hamcrest/Description;)V
      48: iconst_0
      49: ireturn
      50: iconst_1
      51: ireturn

  public final void describeTo(org.hamcrest.Description);
    Code:
       0: aload_1
       1: aload_0
       2: getfield      #4                  // Field featureDescription:Ljava/lang/String;
       5: invokeinterface #8,  2            // InterfaceMethod org/hamcrest/Description.appendText:(Ljava/lang/String;)Lorg/hamcrest/Description;
      10: ldc           #9                  // String
      12: invokeinterface #8,  2            // InterfaceMethod org/hamcrest/Description.appendText:(Ljava/lang/String;)Lorg/hamcrest/Description;
      17: aload_0
      18: getfield      #3                  // Field subMatcher:Lorg/hamcrest/Matcher;
      21: invokeinterface #11,  2           // InterfaceMethod org/hamcrest/Description.appendDescriptionOf:(Lorg/hamcrest/SelfDescribing;)Lorg/hamcrest/Description;
      26: pop
      27: return

  static {};
    Code:
       0: new           #12                 // class org/hamcrest/internal/ReflectiveTypeFinder
       3: dup
       4: ldc           #13                 // String featureValueOf
       6: iconst_1
       7: iconst_0
       8: invokespecial #14                 // Method org/hamcrest/internal/ReflectiveTypeFinder."<init>":(Ljava/lang/String;II)V
      11: putstatic     #1                  // Field TYPE_FINDER:Lorg/hamcrest/internal/ReflectiveTypeFinder;
      14: return
}
