Compiled from "AnnotationMetadataSourceProcessorImpl.java"
public class org.hibernate.boot.model.source.internal.annotations.AnnotationMetadataSourceProcessorImpl implements org.hibernate.boot.model.source.spi.MetadataSourceProcessor {
  private static final org.jboss.logging.Logger log;

  private final org.hibernate.boot.internal.MetadataBuildingContextRootImpl rootMetadataBuildingContext;

  private final org.jboss.jandex.IndexView jandexView;

  private final org.hibernate.annotations.common.reflection.ReflectionManager reflectionManager;

  private final java.util.LinkedHashSet<java.lang.String> annotatedPackages;

  private final java.util.List<org.hibernate.annotations.common.reflection.XClass> xClasses;

  public org.hibernate.boot.model.source.internal.annotations.AnnotationMetadataSourceProcessorImpl(org.hibernate.boot.model.process.spi.ManagedResources, org.hibernate.boot.internal.MetadataBuildingContextRootImpl, org.jboss.jandex.IndexView);
    Code:
       0: aload_0
       1: invokespecial #2                  // Method java/lang/Object."<init>":()V
       4: aload_0
       5: new           #3                  // class java/util/LinkedHashSet
       8: dup
       9: invokespecial #4                  // Method java/util/LinkedHashSet."<init>":()V
      12: putfield      #5                  // Field annotatedPackages:Ljava/util/LinkedHashSet;
      15: aload_0
      16: new           #6                  // class java/util/ArrayList
      19: dup
      20: invokespecial #7                  // Method java/util/ArrayList."<init>":()V
      23: putfield      #8                  // Field xClasses:Ljava/util/List;
      26: aload_0
      27: aload_2
      28: putfield      #9                  // Field rootMetadataBuildingContext:Lorg/hibernate/boot/internal/MetadataBuildingContextRootImpl;
      31: aload_0
      32: aload_3
      33: putfield      #10                 // Field jandexView:Lorg/jboss/jandex/IndexView;
      36: aload_0
      37: aload_2
      38: invokevirtual #11                 // Method org/hibernate/boot/internal/MetadataBuildingContextRootImpl.getBuildingOptions:()Lorg/hibernate/boot/spi/MetadataBuildingOptions;
      41: invokeinterface #12,  1           // InterfaceMethod org/hibernate/boot/spi/MetadataBuildingOptions.getReflectionManager:()Lorg/hibernate/annotations/common/reflection/ReflectionManager;
      46: putfield      #1                  // Field reflectionManager:Lorg/hibernate/annotations/common/reflection/ReflectionManager;
      49: aload_1
      50: invokeinterface #13,  1           // InterfaceMethod org/hibernate/boot/model/process/spi/ManagedResources.getAnnotatedPackageNames:()Ljava/util/Collection;
      55: invokestatic  #14                 // Method org/hibernate/internal/util/collections/CollectionHelper.isNotEmpty:(Ljava/util/Collection;)Z
      58: ifeq          75
      61: aload_0
      62: getfield      #5                  // Field annotatedPackages:Ljava/util/LinkedHashSet;
      65: aload_1
      66: invokeinterface #13,  1           // InterfaceMethod org/hibernate/boot/model/process/spi/ManagedResources.getAnnotatedPackageNames:()Ljava/util/Collection;
      71: invokevirtual #15                 // Method java/util/LinkedHashSet.addAll:(Ljava/util/Collection;)Z
      74: pop
      75: new           #16                 // class org/hibernate/boot/model/source/internal/annotations/AnnotationMetadataSourceProcessorImpl$AttributeConverterManager
      78: dup
      79: aload_2
      80: invokespecial #17                 // Method org/hibernate/boot/model/source/internal/annotations/AnnotationMetadataSourceProcessorImpl$AttributeConverterManager."<init>":(Lorg/hibernate/boot/internal/MetadataBuildingContextRootImpl;)V
      83: astore        4
      85: aload_0
      86: getfield      #1                  // Field reflectionManager:Lorg/hibernate/annotations/common/reflection/ReflectionManager;
      89: checkcast     #18                 // class org/hibernate/annotations/common/reflection/MetadataProviderInjector
      92: invokeinterface #19,  1           // InterfaceMethod org/hibernate/annotations/common/reflection/MetadataProviderInjector.getMetadataProvider:()Lorg/hibernate/annotations/common/reflection/MetadataProvider;
      97: checkcast     #20                 // class org/hibernate/cfg/annotations/reflection/JPAMetadataProvider
     100: astore        5
     102: aload_1
     103: invokeinterface #21,  1           // InterfaceMethod org/hibernate/boot/model/process/spi/ManagedResources.getXmlMappingBindings:()Ljava/util/Collection;
     108: invokeinterface #22,  1           // InterfaceMethod java/util/Collection.iterator:()Ljava/util/Iterator;
     113: astore        6
     115: aload         6
     117: invokeinterface #23,  1           // InterfaceMethod java/util/Iterator.hasNext:()Z
     122: ifeq          232
     125: aload         6
     127: invokeinterface #24,  1           // InterfaceMethod java/util/Iterator.next:()Ljava/lang/Object;
     132: checkcast     #25                 // class org/hibernate/boot/jaxb/spi/Binding
     135: astore        7
     137: ldc           #26                 // class org/dom4j/Document
     139: aload         7
     141: invokevirtual #27                 // Method org/hibernate/boot/jaxb/spi/Binding.getRoot:()Ljava/lang/Object;
     144: invokevirtual #28                 // Method java/lang/Class.isInstance:(Ljava/lang/Object;)Z
     147: ifne          153
     150: goto          115
     153: aload         7
     155: invokevirtual #27                 // Method org/hibernate/boot/jaxb/spi/Binding.getRoot:()Ljava/lang/Object;
     158: checkcast     #26                 // class org/dom4j/Document
     161: astore        8
     163: aload         5
     165: invokevirtual #29                 // Method org/hibernate/cfg/annotations/reflection/JPAMetadataProvider.getXMLContext:()Lorg/hibernate/cfg/annotations/reflection/XMLContext;
     168: aload         8
     170: invokevirtual #30                 // Method org/hibernate/cfg/annotations/reflection/XMLContext.addDocument:(Lorg/dom4j/Document;)Ljava/util/List;
     173: astore        9
     175: aload         9
     177: invokeinterface #31,  1           // InterfaceMethod java/util/List.iterator:()Ljava/util/Iterator;
     182: astore        10
     184: aload         10
     186: invokeinterface #23,  1           // InterfaceMethod java/util/Iterator.hasNext:()Z
     191: ifeq          229
     194: aload         10
     196: invokeinterface #24,  1           // InterfaceMethod java/util/Iterator.next:()Ljava/lang/Object;
     201: checkcast     #32                 // class java/lang/String
     204: astore        11
     206: aload_0
     207: getfield      #8                  // Field xClasses:Ljava/util/List;
     210: aload_0
     211: aload         11
     213: aload_0
     214: getfield      #1                  // Field reflectionManager:Lorg/hibernate/annotations/common/reflection/ReflectionManager;
     217: invokespecial #33                 // Method toXClass:(Ljava/lang/String;Lorg/hibernate/annotations/common/reflection/ReflectionManager;)Lorg/hibernate/annotations/common/reflection/XClass;
     220: invokeinterface #34,  2           // InterfaceMethod java/util/List.add:(Ljava/lang/Object;)Z
     225: pop
     226: goto          184
     229: goto          115
     232: aload         5
     234: invokevirtual #29                 // Method org/hibernate/cfg/annotations/reflection/JPAMetadataProvider.getXMLContext:()Lorg/hibernate/cfg/annotations/reflection/XMLContext;
     237: aload         4
     239: invokevirtual #35                 // Method org/hibernate/cfg/annotations/reflection/XMLContext.applyDiscoveredAttributeConverters:(Lorg/hibernate/cfg/annotations/reflection/AttributeConverterDefinitionCollector;)V
     242: aload_2
     243: invokevirtual #11                 // Method org/hibernate/boot/internal/MetadataBuildingContextRootImpl.getBuildingOptions:()Lorg/hibernate/boot/spi/MetadataBuildingOptions;
     246: invokeinterface #36,  1           // InterfaceMethod org/hibernate/boot/spi/MetadataBuildingOptions.getServiceRegistry:()Lorg/hibernate/boot/registry/StandardServiceRegistry;
     251: ldc           #37                 // class org/hibernate/boot/registry/classloading/spi/ClassLoaderService
     253: invokeinterface #38,  2           // InterfaceMethod org/hibernate/boot/registry/StandardServiceRegistry.getService:(Ljava/lang/Class;)Lorg/hibernate/service/Service;
     258: checkcast     #37                 // class org/hibernate/boot/registry/classloading/spi/ClassLoaderService
     261: astore        6
     263: aload_1
     264: invokeinterface #39,  1           // InterfaceMethod org/hibernate/boot/model/process/spi/ManagedResources.getAnnotatedClassNames:()Ljava/util/Collection;
     269: invokeinterface #22,  1           // InterfaceMethod java/util/Collection.iterator:()Ljava/util/Iterator;
     274: astore        7
     276: aload         7
     278: invokeinterface #23,  1           // InterfaceMethod java/util/Iterator.hasNext:()Z
     283: ifeq          320
     286: aload         7
     288: invokeinterface #24,  1           // InterfaceMethod java/util/Iterator.next:()Ljava/lang/Object;
     293: checkcast     #32                 // class java/lang/String
     296: astore        8
     298: aload         6
     300: aload         8
     302: invokeinterface #40,  2           // InterfaceMethod org/hibernate/boot/registry/classloading/spi/ClassLoaderService.classForName:(Ljava/lang/String;)Ljava/lang/Class;
     307: astore        9
     309: aload_0
     310: aload         9
     312: aload         4
     314: invokespecial #41                 // Method categorizeAnnotatedClass:(Ljava/lang/Class;Lorg/hibernate/boot/model/source/internal/annotations/AnnotationMetadataSourceProcessorImpl$AttributeConverterManager;)V
     317: goto          276
     320: aload_1
     321: invokeinterface #42,  1           // InterfaceMethod org/hibernate/boot/model/process/spi/ManagedResources.getAnnotatedClassReferences:()Ljava/util/Collection;
     326: invokeinterface #22,  1           // InterfaceMethod java/util/Collection.iterator:()Ljava/util/Iterator;
     331: astore        7
     333: aload         7
     335: invokeinterface #23,  1           // InterfaceMethod java/util/Iterator.hasNext:()Z
     340: ifeq          366
     343: aload         7
     345: invokeinterface #24,  1           // InterfaceMethod java/util/Iterator.next:()Ljava/lang/Object;
     350: checkcast     #43                 // class java/lang/Class
     353: astore        8
     355: aload_0
     356: aload         8
     358: aload         4
     360: invokespecial #41                 // Method categorizeAnnotatedClass:(Ljava/lang/Class;Lorg/hibernate/boot/model/source/internal/annotations/AnnotationMetadataSourceProcessorImpl$AttributeConverterManager;)V
     363: goto          333
     366: return

  private void categorizeAnnotatedClass(java.lang.Class, org.hibernate.boot.model.source.internal.annotations.AnnotationMetadataSourceProcessorImpl$AttributeConverterManager);
    Code:
       0: aload_0
       1: getfield      #1                  // Field reflectionManager:Lorg/hibernate/annotations/common/reflection/ReflectionManager;
       4: aload_1
       5: invokeinterface #44,  2           // InterfaceMethod org/hibernate/annotations/common/reflection/ReflectionManager.toXClass:(Ljava/lang/Class;)Lorg/hibernate/annotations/common/reflection/XClass;
      10: astore_3
      11: aload_3
      12: ldc           #45                 // class javax/persistence/Converter
      14: invokeinterface #46,  2           // InterfaceMethod org/hibernate/annotations/common/reflection/XClass.isAnnotationPresent:(Ljava/lang/Class;)Z
      19: ifeq          30
      22: aload_2
      23: aload_1
      24: invokevirtual #47                 // Method org/hibernate/boot/model/source/internal/annotations/AnnotationMetadataSourceProcessorImpl$AttributeConverterManager.addAttributeConverter:(Ljava/lang/Class;)V
      27: goto          78
      30: aload_3
      31: ldc           #48                 // class javax/persistence/Entity
      33: invokeinterface #46,  2           // InterfaceMethod org/hibernate/annotations/common/reflection/XClass.isAnnotationPresent:(Ljava/lang/Class;)Z
      38: ifne          52
      41: aload_3
      42: ldc           #49                 // class javax/persistence/MappedSuperclass
      44: invokeinterface #46,  2           // InterfaceMethod org/hibernate/annotations/common/reflection/XClass.isAnnotationPresent:(Ljava/lang/Class;)Z
      49: ifeq          66
      52: aload_0
      53: getfield      #8                  // Field xClasses:Ljava/util/List;
      56: aload_3
      57: invokeinterface #34,  2           // InterfaceMethod java/util/List.add:(Ljava/lang/Object;)Z
      62: pop
      63: goto          78
      66: getstatic     #50                 // Field log:Lorg/jboss/logging/Logger;
      69: ldc           #51                 // String Encountered a non-categorized annotated class [%s]; ignoring
      71: aload_1
      72: invokevirtual #52                 // Method java/lang/Class.getName:()Ljava/lang/String;
      75: invokevirtual #53                 // Method org/jboss/logging/Logger.debugf:(Ljava/lang/String;Ljava/lang/Object;)V
      78: return

  private org.hibernate.annotations.common.reflection.XClass toXClass(java.lang.String, org.hibernate.annotations.common.reflection.ReflectionManager);
    Code:
       0: aload_2
       1: aload_1
       2: invokeinterface #54,  2           // InterfaceMethod org/hibernate/annotations/common/reflection/ReflectionManager.classForName:(Ljava/lang/String;)Lorg/hibernate/annotations/common/reflection/XClass;
       7: areturn
       8: astore_3
       9: new           #56                 // class org/hibernate/AnnotationException
      12: dup
      13: new           #57                 // class java/lang/StringBuilder
      16: dup
      17: invokespecial #58                 // Method java/lang/StringBuilder."<init>":()V
      20: ldc           #59                 // String Unable to load class defined in XML:
      22: invokevirtual #60                 // Method java/lang/StringBuilder.append:(Ljava/lang/String;)Ljava/lang/StringBuilder;
      25: aload_1
      26: invokevirtual #60                 // Method java/lang/StringBuilder.append:(Ljava/lang/String;)Ljava/lang/StringBuilder;
      29: invokevirtual #61                 // Method java/lang/StringBuilder.toString:()Ljava/lang/String;
      32: aload_3
      33: invokespecial #62                 // Method org/hibernate/AnnotationException."<init>":(Ljava/lang/String;Ljava/lang/Throwable;)V
      36: athrow
    Exception table:
       from    to  target type
           0     7     8   Class org/hibernate/annotations/common/reflection/ClassLoadingException

  public void prepare();
    Code:
       0: aload_0
       1: getfield      #9                  // Field rootMetadataBuildingContext:Lorg/hibernate/boot/internal/MetadataBuildingContextRootImpl;
       4: invokevirtual #11                 // Method org/hibernate/boot/internal/MetadataBuildingContextRootImpl.getBuildingOptions:()Lorg/hibernate/boot/spi/MetadataBuildingOptions;
       7: checkcast     #63                 // class org/hibernate/boot/spi/JpaOrmXmlPersistenceUnitDefaultAware
      10: new           #64                 // class org/hibernate/boot/model/source/internal/annotations/AnnotationMetadataSourceProcessorImpl$1
      13: dup
      14: aload_0
      15: invokespecial #65                 // Method org/hibernate/boot/model/source/internal/annotations/AnnotationMetadataSourceProcessorImpl$1."<init>":(Lorg/hibernate/boot/model/source/internal/annotations/AnnotationMetadataSourceProcessorImpl;)V
      18: invokeinterface #66,  2           // InterfaceMethod org/hibernate/boot/spi/JpaOrmXmlPersistenceUnitDefaultAware.apply:(Lorg/hibernate/boot/spi/JpaOrmXmlPersistenceUnitDefaultAware$JpaOrmXmlPersistenceUnitDefaults;)V
      23: aload_0
      24: getfield      #9                  // Field rootMetadataBuildingContext:Lorg/hibernate/boot/internal/MetadataBuildingContextRootImpl;
      27: invokevirtual #67                 // Method org/hibernate/boot/internal/MetadataBuildingContextRootImpl.getMetadataCollector:()Lorg/hibernate/boot/spi/InFlightMetadataCollector;
      30: invokeinterface #68,  1           // InterfaceMethod org/hibernate/boot/spi/InFlightMetadataCollector.getDatabase:()Lorg/hibernate/boot/model/relational/Database;
      35: aload_0
      36: getfield      #9                  // Field rootMetadataBuildingContext:Lorg/hibernate/boot/internal/MetadataBuildingContextRootImpl;
      39: invokevirtual #11                 // Method org/hibernate/boot/internal/MetadataBuildingContextRootImpl.getBuildingOptions:()Lorg/hibernate/boot/spi/MetadataBuildingOptions;
      42: invokeinterface #69,  1           // InterfaceMethod org/hibernate/boot/spi/MetadataBuildingOptions.getMappingDefaults:()Lorg/hibernate/boot/spi/MappingDefaults;
      47: invokeinterface #70,  1           // InterfaceMethod org/hibernate/boot/spi/MappingDefaults.getImplicitCatalogName:()Ljava/lang/String;
      52: aload_0
      53: getfield      #9                  // Field rootMetadataBuildingContext:Lorg/hibernate/boot/internal/MetadataBuildingContextRootImpl;
      56: invokevirtual #11                 // Method org/hibernate/boot/internal/MetadataBuildingContextRootImpl.getBuildingOptions:()Lorg/hibernate/boot/spi/MetadataBuildingOptions;
      59: invokeinterface #69,  1           // InterfaceMethod org/hibernate/boot/spi/MetadataBuildingOptions.getMappingDefaults:()Lorg/hibernate/boot/spi/MappingDefaults;
      64: invokeinterface #71,  1           // InterfaceMethod org/hibernate/boot/spi/MappingDefaults.getImplicitSchemaName:()Ljava/lang/String;
      69: invokevirtual #72                 // Method org/hibernate/boot/model/relational/Database.adjustDefaultNamespace:(Ljava/lang/String;Ljava/lang/String;)Lorg/hibernate/boot/model/relational/Namespace;
      72: pop
      73: aload_0
      74: getfield      #9                  // Field rootMetadataBuildingContext:Lorg/hibernate/boot/internal/MetadataBuildingContextRootImpl;
      77: invokestatic  #73                 // Method org/hibernate/cfg/AnnotationBinder.bindDefaults:(Lorg/hibernate/boot/spi/MetadataBuildingContext;)V
      80: aload_0
      81: getfield      #5                  // Field annotatedPackages:Ljava/util/LinkedHashSet;
      84: invokevirtual #74                 // Method java/util/LinkedHashSet.iterator:()Ljava/util/Iterator;
      87: astore_1
      88: aload_1
      89: invokeinterface #23,  1           // InterfaceMethod java/util/Iterator.hasNext:()Z
      94: ifeq          118
      97: aload_1
      98: invokeinterface #24,  1           // InterfaceMethod java/util/Iterator.next:()Ljava/lang/Object;
     103: checkcast     #32                 // class java/lang/String
     106: astore_2
     107: aload_2
     108: aload_0
     109: getfield      #9                  // Field rootMetadataBuildingContext:Lorg/hibernate/boot/internal/MetadataBuildingContextRootImpl;
     112: invokestatic  #75                 // Method org/hibernate/cfg/AnnotationBinder.bindPackage:(Ljava/lang/String;Lorg/hibernate/boot/spi/MetadataBuildingContext;)V
     115: goto          88
     118: return

  public void processTypeDefinitions();
    Code:
       0: return

  public void processQueryRenames();
    Code:
       0: return

  public void processNamedQueries();
    Code:
       0: return

  public void processAuxiliaryDatabaseObjectDefinitions();
    Code:
       0: return

  public void processIdentifierGenerators();
    Code:
       0: return

  public void processFilterDefinitions();
    Code:
       0: return

  public void processFetchProfiles();
    Code:
       0: return

  public void prepareForEntityHierarchyProcessing();
    Code:
       0: return

  public void processEntityHierarchies(java.util.Set<java.lang.String>);
    Code:
       0: aload_0
       1: aload_0
       2: getfield      #8                  // Field xClasses:Ljava/util/List;
       5: invokespecial #76                 // Method orderAndFillHierarchy:(Ljava/util/List;)Ljava/util/List;
       8: astore_2
       9: aload_2
      10: aload_0
      11: getfield      #9                  // Field rootMetadataBuildingContext:Lorg/hibernate/boot/internal/MetadataBuildingContextRootImpl;
      14: invokestatic  #77                 // Method org/hibernate/cfg/AnnotationBinder.buildInheritanceStates:(Ljava/util/List;Lorg/hibernate/boot/spi/MetadataBuildingContext;)Ljava/util/Map;
      17: astore_3
      18: aload_2
      19: invokeinterface #31,  1           // InterfaceMethod java/util/List.iterator:()Ljava/util/Iterator;
      24: astore        4
      26: aload         4
      28: invokeinterface #23,  1           // InterfaceMethod java/util/Iterator.hasNext:()Z
      33: ifeq          104
      36: aload         4
      38: invokeinterface #24,  1           // InterfaceMethod java/util/Iterator.next:()Ljava/lang/Object;
      43: checkcast     #78                 // class org/hibernate/annotations/common/reflection/XClass
      46: astore        5
      48: aload_1
      49: aload         5
      51: invokeinterface #79,  1           // InterfaceMethod org/hibernate/annotations/common/reflection/XClass.getName:()Ljava/lang/String;
      56: invokeinterface #80,  2           // InterfaceMethod java/util/Set.contains:(Ljava/lang/Object;)Z
      61: ifeq          77
      64: getstatic     #50                 // Field log:Lorg/jboss/logging/Logger;
      67: ldc           #81                 // String Skipping annotated class processing of entity [%s], as it has already been processed
      69: aload         5
      71: invokevirtual #53                 // Method org/jboss/logging/Logger.debugf:(Ljava/lang/String;Ljava/lang/Object;)V
      74: goto          26
      77: aload         5
      79: aload_3
      80: aload_0
      81: getfield      #9                  // Field rootMetadataBuildingContext:Lorg/hibernate/boot/internal/MetadataBuildingContextRootImpl;
      84: invokestatic  #82                 // Method org/hibernate/cfg/AnnotationBinder.bindClass:(Lorg/hibernate/annotations/common/reflection/XClass;Ljava/util/Map;Lorg/hibernate/boot/spi/MetadataBuildingContext;)V
      87: aload_1
      88: aload         5
      90: invokeinterface #79,  1           // InterfaceMethod org/hibernate/annotations/common/reflection/XClass.getName:()Ljava/lang/String;
      95: invokeinterface #83,  2           // InterfaceMethod java/util/Set.add:(Ljava/lang/Object;)Z
     100: pop
     101: goto          26
     104: return

  private java.util.List<org.hibernate.annotations.common.reflection.XClass> orderAndFillHierarchy(java.util.List<org.hibernate.annotations.common.reflection.XClass>);
    Code:
       0: new           #6                  // class java/util/ArrayList
       3: dup
       4: aload_1
       5: invokespecial #84                 // Method java/util/ArrayList."<init>":(Ljava/util/Collection;)V
       8: astore_2
       9: aload_0
      10: aload_1
      11: aload_2
      12: invokespecial #85                 // Method insertMappedSuperclasses:(Ljava/util/List;Ljava/util/List;)V
      15: new           #6                  // class java/util/ArrayList
      18: dup
      19: aload_2
      20: invokespecial #84                 // Method java/util/ArrayList."<init>":(Ljava/util/Collection;)V
      23: astore_3
      24: new           #6                  // class java/util/ArrayList
      27: dup
      28: aload_2
      29: invokeinterface #86,  1           // InterfaceMethod java/util/List.size:()I
      34: invokespecial #87                 // Method java/util/ArrayList."<init>":(I)V
      37: astore        4
      39: aload_3
      40: invokeinterface #86,  1           // InterfaceMethod java/util/List.size:()I
      45: ifle          73
      48: aload_3
      49: iconst_0
      50: invokeinterface #88,  2           // InterfaceMethod java/util/List.get:(I)Ljava/lang/Object;
      55: checkcast     #78                 // class org/hibernate/annotations/common/reflection/XClass
      58: astore        5
      60: aload_0
      61: aload_3
      62: aload         4
      64: aload_2
      65: aload         5
      67: invokespecial #89                 // Method orderHierarchy:(Ljava/util/List;Ljava/util/List;Ljava/util/List;Lorg/hibernate/annotations/common/reflection/XClass;)V
      70: goto          39
      73: aload         4
      75: areturn

  private void insertMappedSuperclasses(java.util.List<org.hibernate.annotations.common.reflection.XClass>, java.util.List<org.hibernate.annotations.common.reflection.XClass>);
    Code:
       0: aload_1
       1: invokeinterface #31,  1           // InterfaceMethod java/util/List.iterator:()Ljava/util/Iterator;
       6: astore_3
       7: aload_3
       8: invokeinterface #23,  1           // InterfaceMethod java/util/Iterator.hasNext:()Z
      13: ifeq          116
      16: aload_3
      17: invokeinterface #24,  1           // InterfaceMethod java/util/Iterator.next:()Ljava/lang/Object;
      22: checkcast     #78                 // class org/hibernate/annotations/common/reflection/XClass
      25: astore        4
      27: aload         4
      29: invokeinterface #90,  1           // InterfaceMethod org/hibernate/annotations/common/reflection/XClass.getSuperclass:()Lorg/hibernate/annotations/common/reflection/XClass;
      34: astore        5
      36: aload         5
      38: ifnull        113
      41: aload_0
      42: getfield      #1                  // Field reflectionManager:Lorg/hibernate/annotations/common/reflection/ReflectionManager;
      45: aload         5
      47: ldc           #91                 // class java/lang/Object
      49: invokeinterface #92,  3           // InterfaceMethod org/hibernate/annotations/common/reflection/ReflectionManager.equals:(Lorg/hibernate/annotations/common/reflection/XClass;Ljava/lang/Class;)Z
      54: ifne          113
      57: aload_2
      58: aload         5
      60: invokeinterface #93,  2           // InterfaceMethod java/util/List.contains:(Ljava/lang/Object;)Z
      65: ifne          113
      68: aload         5
      70: ldc           #48                 // class javax/persistence/Entity
      72: invokeinterface #46,  2           // InterfaceMethod org/hibernate/annotations/common/reflection/XClass.isAnnotationPresent:(Ljava/lang/Class;)Z
      77: ifne          92
      80: aload         5
      82: ldc           #49                 // class javax/persistence/MappedSuperclass
      84: invokeinterface #46,  2           // InterfaceMethod org/hibernate/annotations/common/reflection/XClass.isAnnotationPresent:(Ljava/lang/Class;)Z
      89: ifeq          101
      92: aload_2
      93: aload         5
      95: invokeinterface #34,  2           // InterfaceMethod java/util/List.add:(Ljava/lang/Object;)Z
     100: pop
     101: aload         5
     103: invokeinterface #90,  1           // InterfaceMethod org/hibernate/annotations/common/reflection/XClass.getSuperclass:()Lorg/hibernate/annotations/common/reflection/XClass;
     108: astore        5
     110: goto          36
     113: goto          7
     116: return

  private void orderHierarchy(java.util.List<org.hibernate.annotations.common.reflection.XClass>, java.util.List<org.hibernate.annotations.common.reflection.XClass>, java.util.List<org.hibernate.annotations.common.reflection.XClass>, org.hibernate.annotations.common.reflection.XClass);
    Code:
       0: aload         4
       2: ifnull        21
       5: aload_0
       6: getfield      #1                  // Field reflectionManager:Lorg/hibernate/annotations/common/reflection/ReflectionManager;
       9: aload         4
      11: ldc           #91                 // class java/lang/Object
      13: invokeinterface #92,  3           // InterfaceMethod org/hibernate/annotations/common/reflection/ReflectionManager.equals:(Lorg/hibernate/annotations/common/reflection/XClass;Ljava/lang/Class;)Z
      18: ifeq          22
      21: return
      22: aload_0
      23: aload_1
      24: aload_2
      25: aload_3
      26: aload         4
      28: invokeinterface #90,  1           // InterfaceMethod org/hibernate/annotations/common/reflection/XClass.getSuperclass:()Lorg/hibernate/annotations/common/reflection/XClass;
      33: invokespecial #89                 // Method orderHierarchy:(Ljava/util/List;Ljava/util/List;Ljava/util/List;Lorg/hibernate/annotations/common/reflection/XClass;)V
      36: aload_3
      37: aload         4
      39: invokeinterface #93,  2           // InterfaceMethod java/util/List.contains:(Ljava/lang/Object;)Z
      44: ifeq          76
      47: aload_2
      48: aload         4
      50: invokeinterface #93,  2           // InterfaceMethod java/util/List.contains:(Ljava/lang/Object;)Z
      55: ifne          67
      58: aload_2
      59: aload         4
      61: invokeinterface #34,  2           // InterfaceMethod java/util/List.add:(Ljava/lang/Object;)Z
      66: pop
      67: aload_1
      68: aload         4
      70: invokeinterface #94,  2           // InterfaceMethod java/util/List.remove:(Ljava/lang/Object;)Z
      75: pop
      76: return

  public void postProcessEntityHierarchies();
    Code:
       0: return

  public void processResultSetMappings();
    Code:
       0: return

  public void finishUp();
    Code:
       0: return

  static org.hibernate.annotations.common.reflection.ReflectionManager access$000(org.hibernate.boot.model.source.internal.annotations.AnnotationMetadataSourceProcessorImpl);
    Code:
       0: aload_0
       1: getfield      #1                  // Field reflectionManager:Lorg/hibernate/annotations/common/reflection/ReflectionManager;
       4: areturn

  static {};
    Code:
       0: ldc           #95                 // class org/hibernate/boot/model/source/internal/annotations/AnnotationMetadataSourceProcessorImpl
       2: invokestatic  #96                 // Method org/jboss/logging/Logger.getLogger:(Ljava/lang/Class;)Lorg/jboss/logging/Logger;
       5: putstatic     #50                 // Field log:Lorg/jboss/logging/Logger;
       8: return
}
