Compiled from "E_StrSubstring.java"
public class org.apache.jena.sparql.expr.E_StrSubstring extends org.apache.jena.sparql.expr.ExprFunctionN {
  private static final java.lang.String symbol;

  public org.apache.jena.sparql.expr.E_StrSubstring(org.apache.jena.sparql.expr.Expr, org.apache.jena.sparql.expr.Expr, org.apache.jena.sparql.expr.Expr);
    Code:
       0: aload_0
       1: ldc           #3                  // String substr
       3: iconst_3
       4: anewarray     #4                  // class org/apache/jena/sparql/expr/Expr
       7: dup
       8: iconst_0
       9: aload_1
      10: aastore
      11: dup
      12: iconst_1
      13: aload_2
      14: aastore
      15: dup
      16: iconst_2
      17: aload_3
      18: aastore
      19: invokespecial #5                  // Method org/apache/jena/sparql/expr/ExprFunctionN."<init>":(Ljava/lang/String;[Lorg/apache/jena/sparql/expr/Expr;)V
      22: return

  public org.apache.jena.sparql.expr.NodeValue eval(java.util.List<org.apache.jena.sparql.expr.NodeValue>);
    Code:
       0: aload_1
       1: invokeinterface #6,  1            // InterfaceMethod java/util/List.size:()I
       6: iconst_2
       7: if_icmpne     34
      10: aload_1
      11: iconst_0
      12: invokeinterface #7,  2            // InterfaceMethod java/util/List.get:(I)Ljava/lang/Object;
      17: checkcast     #8                  // class org/apache/jena/sparql/expr/NodeValue
      20: aload_1
      21: iconst_1
      22: invokeinterface #7,  2            // InterfaceMethod java/util/List.get:(I)Ljava/lang/Object;
      27: checkcast     #8                  // class org/apache/jena/sparql/expr/NodeValue
      30: invokestatic  #9                  // Method org/apache/jena/sparql/expr/nodevalue/XSDFuncOp.substring:(Lorg/apache/jena/sparql/expr/NodeValue;Lorg/apache/jena/sparql/expr/NodeValue;)Lorg/apache/jena/sparql/expr/NodeValue;
      33: areturn
      34: aload_1
      35: iconst_0
      36: invokeinterface #7,  2            // InterfaceMethod java/util/List.get:(I)Ljava/lang/Object;
      41: checkcast     #8                  // class org/apache/jena/sparql/expr/NodeValue
      44: aload_1
      45: iconst_1
      46: invokeinterface #7,  2            // InterfaceMethod java/util/List.get:(I)Ljava/lang/Object;
      51: checkcast     #8                  // class org/apache/jena/sparql/expr/NodeValue
      54: aload_1
      55: iconst_2
      56: invokeinterface #7,  2            // InterfaceMethod java/util/List.get:(I)Ljava/lang/Object;
      61: checkcast     #8                  // class org/apache/jena/sparql/expr/NodeValue
      64: invokestatic  #10                 // Method org/apache/jena/sparql/expr/nodevalue/XSDFuncOp.substring:(Lorg/apache/jena/sparql/expr/NodeValue;Lorg/apache/jena/sparql/expr/NodeValue;Lorg/apache/jena/sparql/expr/NodeValue;)Lorg/apache/jena/sparql/expr/NodeValue;
      67: areturn

  public org.apache.jena.sparql.expr.Expr copy(org.apache.jena.sparql.expr.ExprList);
    Code:
       0: aload_1
       1: invokevirtual #11                 // Method org/apache/jena/sparql/expr/ExprList.size:()I
       4: iconst_2
       5: if_icmpne     27
       8: new           #2                  // class org/apache/jena/sparql/expr/E_StrSubstring
      11: dup
      12: aload_1
      13: iconst_0
      14: invokevirtual #12                 // Method org/apache/jena/sparql/expr/ExprList.get:(I)Lorg/apache/jena/sparql/expr/Expr;
      17: aload_1
      18: iconst_1
      19: invokevirtual #12                 // Method org/apache/jena/sparql/expr/ExprList.get:(I)Lorg/apache/jena/sparql/expr/Expr;
      22: aconst_null
      23: invokespecial #13                 // Method "<init>":(Lorg/apache/jena/sparql/expr/Expr;Lorg/apache/jena/sparql/expr/Expr;Lorg/apache/jena/sparql/expr/Expr;)V
      26: areturn
      27: new           #2                  // class org/apache/jena/sparql/expr/E_StrSubstring
      30: dup
      31: aload_1
      32: iconst_0
      33: invokevirtual #12                 // Method org/apache/jena/sparql/expr/ExprList.get:(I)Lorg/apache/jena/sparql/expr/Expr;
      36: aload_1
      37: iconst_1
      38: invokevirtual #12                 // Method org/apache/jena/sparql/expr/ExprList.get:(I)Lorg/apache/jena/sparql/expr/Expr;
      41: aload_1
      42: iconst_2
      43: invokevirtual #12                 // Method org/apache/jena/sparql/expr/ExprList.get:(I)Lorg/apache/jena/sparql/expr/Expr;
      46: invokespecial #13                 // Method "<init>":(Lorg/apache/jena/sparql/expr/Expr;Lorg/apache/jena/sparql/expr/Expr;Lorg/apache/jena/sparql/expr/Expr;)V
      49: areturn
}
