Compiled from "ThreadCache.java"
class org.apache.kafka.streams.state.internals.ThreadCache$DirtyEntry {
  private final org.apache.kafka.common.utils.Bytes key;

  private final byte[] newValue;

  private final org.apache.kafka.streams.state.internals.LRUCacheEntry recordContext;

  org.apache.kafka.streams.state.internals.ThreadCache$DirtyEntry(org.apache.kafka.common.utils.Bytes, byte[], org.apache.kafka.streams.state.internals.LRUCacheEntry);
    Code:
       0: aload_0
       1: invokespecial #1                  // Method java/lang/Object."<init>":()V
       4: aload_0
       5: aload_1
       6: putfield      #2                  // Field key:Lorg/apache/kafka/common/utils/Bytes;
       9: aload_0
      10: aload_2
      11: putfield      #3                  // Field newValue:[B
      14: aload_0
      15: aload_3
      16: putfield      #4                  // Field recordContext:Lorg/apache/kafka/streams/state/internals/LRUCacheEntry;
      19: return

  public org.apache.kafka.common.utils.Bytes key();
    Code:
       0: aload_0
       1: getfield      #2                  // Field key:Lorg/apache/kafka/common/utils/Bytes;
       4: areturn

  public byte[] newValue();
    Code:
       0: aload_0
       1: getfield      #3                  // Field newValue:[B
       4: areturn

  public org.apache.kafka.streams.state.internals.LRUCacheEntry entry();
    Code:
       0: aload_0
       1: getfield      #4                  // Field recordContext:Lorg/apache/kafka/streams/state/internals/LRUCacheEntry;
       4: areturn
}
