Compiled from "AbstractReadOnlyDecorator.java"
class org.apache.kafka.streams.processor.internals.AbstractReadOnlyDecorator$TimestampedKeyValueStoreReadOnlyDecorator<K, V> extends org.apache.kafka.streams.processor.internals.AbstractReadOnlyDecorator$KeyValueStoreReadOnlyDecorator<K, org.apache.kafka.streams.state.ValueAndTimestamp<V>> implements org.apache.kafka.streams.state.TimestampedKeyValueStore<K, V> {
  private org.apache.kafka.streams.processor.internals.AbstractReadOnlyDecorator$TimestampedKeyValueStoreReadOnlyDecorator(org.apache.kafka.streams.state.TimestampedKeyValueStore<K, V>);
    Code:
       0: aload_0
       1: aload_1
       2: aconst_null
       3: invokespecial #2                  // Method org/apache/kafka/streams/processor/internals/AbstractReadOnlyDecorator$KeyValueStoreReadOnlyDecorator."<init>":(Lorg/apache/kafka/streams/state/KeyValueStore;Lorg/apache/kafka/streams/processor/internals/AbstractReadOnlyDecorator$1;)V
       6: return

  org.apache.kafka.streams.processor.internals.AbstractReadOnlyDecorator$TimestampedKeyValueStoreReadOnlyDecorator(org.apache.kafka.streams.state.TimestampedKeyValueStore, org.apache.kafka.streams.processor.internals.AbstractReadOnlyDecorator$1);
    Code:
       0: aload_0
       1: aload_1
       2: invokespecial #1                  // Method "<init>":(Lorg/apache/kafka/streams/state/TimestampedKeyValueStore;)V
       5: return
}
