Compiled from "PartitionGroup.java"
public class org.apache.kafka.streams.processor.internals.PartitionGroup {
  private final java.util.Map<org.apache.kafka.common.TopicPartition, org.apache.kafka.streams.processor.internals.RecordQueue> partitionQueues;

  private final org.apache.kafka.common.metrics.Sensor recordLatenessSensor;

  private final java.util.PriorityQueue<org.apache.kafka.streams.processor.internals.RecordQueue> nonEmptyQueuesByTime;

  private long streamTime;

  private int totalBuffered;

  private boolean allBuffered;

  org.apache.kafka.streams.processor.internals.PartitionGroup(java.util.Map<org.apache.kafka.common.TopicPartition, org.apache.kafka.streams.processor.internals.RecordQueue>, org.apache.kafka.common.metrics.Sensor);
    Code:
       0: aload_0
       1: invokespecial #1                  // Method java/lang/Object."<init>":()V
       4: aload_0
       5: new           #2                  // class java/util/PriorityQueue
       8: dup
       9: aload_1
      10: invokeinterface #3,  1            // InterfaceMethod java/util/Map.size:()I
      15: invokedynamic #4,  0              // InvokeDynamic #0:applyAsLong:()Ljava/util/function/ToLongFunction;
      20: invokestatic  #5                  // InterfaceMethod java/util/Comparator.comparingLong:(Ljava/util/function/ToLongFunction;)Ljava/util/Comparator;
      23: invokespecial #6                  // Method java/util/PriorityQueue."<init>":(ILjava/util/Comparator;)V
      26: putfield      #7                  // Field nonEmptyQueuesByTime:Ljava/util/PriorityQueue;
      29: aload_0
      30: aload_1
      31: putfield      #8                  // Field partitionQueues:Ljava/util/Map;
      34: aload_0
      35: aload_2
      36: putfield      #9                  // Field recordLatenessSensor:Lorg/apache/kafka/common/metrics/Sensor;
      39: aload_0
      40: iconst_0
      41: putfield      #10                 // Field totalBuffered:I
      44: aload_0
      45: iconst_0
      46: putfield      #11                 // Field allBuffered:Z
      49: aload_0
      50: ldc2_w        #13                 // long -1l
      53: putfield      #15                 // Field streamTime:J
      56: return

  long partitionTimestamp(org.apache.kafka.common.TopicPartition);
    Code:
       0: aload_0
       1: getfield      #8                  // Field partitionQueues:Ljava/util/Map;
       4: aload_1
       5: invokeinterface #16,  2           // InterfaceMethod java/util/Map.get:(Ljava/lang/Object;)Ljava/lang/Object;
      10: checkcast     #12                 // class org/apache/kafka/streams/processor/internals/RecordQueue
      13: astore_2
      14: aload_2
      15: ifnonnull     50
      18: new           #17                 // class java/lang/IllegalStateException
      21: dup
      22: new           #18                 // class java/lang/StringBuilder
      25: dup
      26: invokespecial #19                 // Method java/lang/StringBuilder."<init>":()V
      29: ldc           #20                 // String Partition
      31: invokevirtual #21                 // Method java/lang/StringBuilder.append:(Ljava/lang/String;)Ljava/lang/StringBuilder;
      34: aload_1
      35: invokevirtual #22                 // Method java/lang/StringBuilder.append:(Ljava/lang/Object;)Ljava/lang/StringBuilder;
      38: ldc           #23                 // String  not found.
      40: invokevirtual #21                 // Method java/lang/StringBuilder.append:(Ljava/lang/String;)Ljava/lang/StringBuilder;
      43: invokevirtual #24                 // Method java/lang/StringBuilder.toString:()Ljava/lang/String;
      46: invokespecial #25                 // Method java/lang/IllegalStateException."<init>":(Ljava/lang/String;)V
      49: athrow
      50: aload_2
      51: invokevirtual #26                 // Method org/apache/kafka/streams/processor/internals/RecordQueue.partitionTime:()J
      54: lreturn

  void updatePartitions(java.util.Set<org.apache.kafka.common.TopicPartition>, java.util.function.Function<org.apache.kafka.common.TopicPartition, org.apache.kafka.streams.processor.internals.RecordQueue>);
    Code:
       0: new           #27                 // class java/util/HashSet
       3: dup
       4: invokespecial #28                 // Method java/util/HashSet."<init>":()V
       7: astore_3
       8: aload_0
       9: getfield      #8                  // Field partitionQueues:Ljava/util/Map;
      12: invokeinterface #29,  1           // InterfaceMethod java/util/Map.entrySet:()Ljava/util/Set;
      17: invokeinterface #30,  1           // InterfaceMethod java/util/Set.iterator:()Ljava/util/Iterator;
      22: astore        4
      24: aload         4
      26: invokeinterface #31,  1           // InterfaceMethod java/util/Iterator.hasNext:()Z
      31: ifeq          119
      34: aload         4
      36: invokeinterface #32,  1           // InterfaceMethod java/util/Iterator.next:()Ljava/lang/Object;
      41: checkcast     #33                 // class java/util/Map$Entry
      44: astore        5
      46: aload         5
      48: invokeinterface #34,  1           // InterfaceMethod java/util/Map$Entry.getKey:()Ljava/lang/Object;
      53: checkcast     #35                 // class org/apache/kafka/common/TopicPartition
      56: astore        6
      58: aload_1
      59: aload         6
      61: invokeinterface #36,  2           // InterfaceMethod java/util/Set.contains:(Ljava/lang/Object;)Z
      66: ifne          107
      69: aload_0
      70: dup
      71: getfield      #10                 // Field totalBuffered:I
      74: aload         5
      76: invokeinterface #37,  1           // InterfaceMethod java/util/Map$Entry.getValue:()Ljava/lang/Object;
      81: checkcast     #12                 // class org/apache/kafka/streams/processor/internals/RecordQueue
      84: invokevirtual #38                 // Method org/apache/kafka/streams/processor/internals/RecordQueue.size:()I
      87: isub
      88: putfield      #10                 // Field totalBuffered:I
      91: aload         4
      93: invokeinterface #39,  1           // InterfaceMethod java/util/Iterator.remove:()V
      98: aload_3
      99: aload         6
     101: invokeinterface #40,  2           // InterfaceMethod java/util/Set.add:(Ljava/lang/Object;)Z
     106: pop
     107: aload_1
     108: aload         6
     110: invokeinterface #41,  2           // InterfaceMethod java/util/Set.remove:(Ljava/lang/Object;)Z
     115: pop
     116: goto          24
     119: aload_1
     120: invokeinterface #30,  1           // InterfaceMethod java/util/Set.iterator:()Ljava/util/Iterator;
     125: astore        5
     127: aload         5
     129: invokeinterface #31,  1           // InterfaceMethod java/util/Iterator.hasNext:()Z
     134: ifeq          172
     137: aload         5
     139: invokeinterface #32,  1           // InterfaceMethod java/util/Iterator.next:()Ljava/lang/Object;
     144: checkcast     #35                 // class org/apache/kafka/common/TopicPartition
     147: astore        6
     149: aload_0
     150: getfield      #8                  // Field partitionQueues:Ljava/util/Map;
     153: aload         6
     155: aload_2
     156: aload         6
     158: invokeinterface #42,  2           // InterfaceMethod java/util/function/Function.apply:(Ljava/lang/Object;)Ljava/lang/Object;
     163: invokeinterface #43,  3           // InterfaceMethod java/util/Map.put:(Ljava/lang/Object;Ljava/lang/Object;)Ljava/lang/Object;
     168: pop
     169: goto          127
     172: aload_0
     173: getfield      #7                  // Field nonEmptyQueuesByTime:Ljava/util/PriorityQueue;
     176: aload_3
     177: invokedynamic #44,  0             // InvokeDynamic #1:test:(Ljava/util/Set;)Ljava/util/function/Predicate;
     182: invokevirtual #45                 // Method java/util/PriorityQueue.removeIf:(Ljava/util/function/Predicate;)Z
     185: pop
     186: aload_0
     187: aload_0
     188: getfield      #11                 // Field allBuffered:Z
     191: ifeq          207
     194: aload_1
     195: invokeinterface #46,  1           // InterfaceMethod java/util/Set.isEmpty:()Z
     200: ifeq          207
     203: iconst_1
     204: goto          208
     207: iconst_0
     208: putfield      #11                 // Field allBuffered:Z
     211: return

  void setPartitionTime(org.apache.kafka.common.TopicPartition, long);
    Code:
       0: aload_0
       1: getfield      #8                  // Field partitionQueues:Ljava/util/Map;
       4: aload_1
       5: invokeinterface #16,  2           // InterfaceMethod java/util/Map.get:(Ljava/lang/Object;)Ljava/lang/Object;
      10: checkcast     #12                 // class org/apache/kafka/streams/processor/internals/RecordQueue
      13: astore        4
      15: aload         4
      17: ifnonnull     52
      20: new           #17                 // class java/lang/IllegalStateException
      23: dup
      24: new           #18                 // class java/lang/StringBuilder
      27: dup
      28: invokespecial #19                 // Method java/lang/StringBuilder."<init>":()V
      31: ldc           #20                 // String Partition
      33: invokevirtual #21                 // Method java/lang/StringBuilder.append:(Ljava/lang/String;)Ljava/lang/StringBuilder;
      36: aload_1
      37: invokevirtual #22                 // Method java/lang/StringBuilder.append:(Ljava/lang/Object;)Ljava/lang/StringBuilder;
      40: ldc           #23                 // String  not found.
      42: invokevirtual #21                 // Method java/lang/StringBuilder.append:(Ljava/lang/String;)Ljava/lang/StringBuilder;
      45: invokevirtual #24                 // Method java/lang/StringBuilder.toString:()Ljava/lang/String;
      48: invokespecial #25                 // Method java/lang/IllegalStateException."<init>":(Ljava/lang/String;)V
      51: athrow
      52: aload_0
      53: getfield      #15                 // Field streamTime:J
      56: lload_2
      57: lcmp
      58: ifge          66
      61: aload_0
      62: lload_2
      63: putfield      #15                 // Field streamTime:J
      66: aload         4
      68: lload_2
      69: invokevirtual #47                 // Method org/apache/kafka/streams/processor/internals/RecordQueue.setPartitionTime:(J)V
      72: return

  org.apache.kafka.streams.processor.internals.StampedRecord nextRecord(org.apache.kafka.streams.processor.internals.PartitionGroup$RecordInfo, long);
    Code:
       0: aconst_null
       1: astore        4
       3: aload_0
       4: getfield      #7                  // Field nonEmptyQueuesByTime:Ljava/util/PriorityQueue;
       7: invokevirtual #48                 // Method java/util/PriorityQueue.poll:()Ljava/lang/Object;
      10: checkcast     #12                 // class org/apache/kafka/streams/processor/internals/RecordQueue
      13: astore        5
      15: aload_1
      16: aload         5
      18: putfield      #49                 // Field org/apache/kafka/streams/processor/internals/PartitionGroup$RecordInfo.queue:Lorg/apache/kafka/streams/processor/internals/RecordQueue;
      21: aload         5
      23: ifnull        127
      26: aload         5
      28: invokevirtual #50                 // Method org/apache/kafka/streams/processor/internals/RecordQueue.poll:()Lorg/apache/kafka/streams/processor/internals/StampedRecord;
      31: astore        4
      33: aload         4
      35: ifnull        127
      38: aload_0
      39: dup
      40: getfield      #10                 // Field totalBuffered:I
      43: iconst_1
      44: isub
      45: putfield      #10                 // Field totalBuffered:I
      48: aload         5
      50: invokevirtual #51                 // Method org/apache/kafka/streams/processor/internals/RecordQueue.isEmpty:()Z
      53: ifeq          64
      56: aload_0
      57: iconst_0
      58: putfield      #11                 // Field allBuffered:Z
      61: goto          74
      64: aload_0
      65: getfield      #7                  // Field nonEmptyQueuesByTime:Ljava/util/PriorityQueue;
      68: aload         5
      70: invokevirtual #52                 // Method java/util/PriorityQueue.offer:(Ljava/lang/Object;)Z
      73: pop
      74: aload         4
      76: getfield      #53                 // Field org/apache/kafka/streams/processor/internals/StampedRecord.timestamp:J
      79: aload_0
      80: getfield      #15                 // Field streamTime:J
      83: lcmp
      84: ifle          108
      87: aload_0
      88: aload         4
      90: getfield      #53                 // Field org/apache/kafka/streams/processor/internals/StampedRecord.timestamp:J
      93: putfield      #15                 // Field streamTime:J
      96: aload_0
      97: getfield      #9                  // Field recordLatenessSensor:Lorg/apache/kafka/common/metrics/Sensor;
     100: dconst_0
     101: lload_2
     102: invokevirtual #54                 // Method org/apache/kafka/common/metrics/Sensor.record:(DJ)V
     105: goto          127
     108: aload_0
     109: getfield      #9                  // Field recordLatenessSensor:Lorg/apache/kafka/common/metrics/Sensor;
     112: aload_0
     113: getfield      #15                 // Field streamTime:J
     116: aload         4
     118: getfield      #53                 // Field org/apache/kafka/streams/processor/internals/StampedRecord.timestamp:J
     121: lsub
     122: l2d
     123: lload_2
     124: invokevirtual #54                 // Method org/apache/kafka/common/metrics/Sensor.record:(DJ)V
     127: aload         4
     129: areturn

  int addRawRecords(org.apache.kafka.common.TopicPartition, java.lang.Iterable<org.apache.kafka.clients.consumer.ConsumerRecord<byte[], byte[]>>);
    Code:
       0: aload_0
       1: getfield      #8                  // Field partitionQueues:Ljava/util/Map;
       4: aload_1
       5: invokeinterface #16,  2           // InterfaceMethod java/util/Map.get:(Ljava/lang/Object;)Ljava/lang/Object;
      10: checkcast     #12                 // class org/apache/kafka/streams/processor/internals/RecordQueue
      13: astore_3
      14: aload_3
      15: ifnonnull     50
      18: new           #17                 // class java/lang/IllegalStateException
      21: dup
      22: new           #18                 // class java/lang/StringBuilder
      25: dup
      26: invokespecial #19                 // Method java/lang/StringBuilder."<init>":()V
      29: ldc           #20                 // String Partition
      31: invokevirtual #21                 // Method java/lang/StringBuilder.append:(Ljava/lang/String;)Ljava/lang/StringBuilder;
      34: aload_1
      35: invokevirtual #22                 // Method java/lang/StringBuilder.append:(Ljava/lang/Object;)Ljava/lang/StringBuilder;
      38: ldc           #23                 // String  not found.
      40: invokevirtual #21                 // Method java/lang/StringBuilder.append:(Ljava/lang/String;)Ljava/lang/StringBuilder;
      43: invokevirtual #24                 // Method java/lang/StringBuilder.toString:()Ljava/lang/String;
      46: invokespecial #25                 // Method java/lang/IllegalStateException."<init>":(Ljava/lang/String;)V
      49: athrow
      50: aload_3
      51: invokevirtual #38                 // Method org/apache/kafka/streams/processor/internals/RecordQueue.size:()I
      54: istore        4
      56: aload_3
      57: aload_2
      58: invokevirtual #55                 // Method org/apache/kafka/streams/processor/internals/RecordQueue.addRawRecords:(Ljava/lang/Iterable;)I
      61: istore        5
      63: iload         4
      65: ifne          106
      68: iload         5
      70: ifle          106
      73: aload_0
      74: getfield      #7                  // Field nonEmptyQueuesByTime:Ljava/util/PriorityQueue;
      77: aload_3
      78: invokevirtual #52                 // Method java/util/PriorityQueue.offer:(Ljava/lang/Object;)Z
      81: pop
      82: aload_0
      83: getfield      #7                  // Field nonEmptyQueuesByTime:Ljava/util/PriorityQueue;
      86: invokevirtual #56                 // Method java/util/PriorityQueue.size:()I
      89: aload_0
      90: getfield      #8                  // Field partitionQueues:Ljava/util/Map;
      93: invokeinterface #3,  1            // InterfaceMethod java/util/Map.size:()I
      98: if_icmpne     106
     101: aload_0
     102: iconst_1
     103: putfield      #11                 // Field allBuffered:Z
     106: aload_0
     107: dup
     108: getfield      #10                 // Field totalBuffered:I
     111: iload         5
     113: iload         4
     115: isub
     116: iadd
     117: putfield      #10                 // Field totalBuffered:I
     120: iload         5
     122: ireturn

  java.util.Set<org.apache.kafka.common.TopicPartition> partitions();
    Code:
       0: aload_0
       1: getfield      #8                  // Field partitionQueues:Ljava/util/Map;
       4: invokeinterface #57,  1           // InterfaceMethod java/util/Map.keySet:()Ljava/util/Set;
       9: invokestatic  #58                 // Method java/util/Collections.unmodifiableSet:(Ljava/util/Set;)Ljava/util/Set;
      12: areturn

  long streamTime();
    Code:
       0: aload_0
       1: getfield      #15                 // Field streamTime:J
       4: lreturn

  java.lang.Long headRecordOffset(org.apache.kafka.common.TopicPartition);
    Code:
       0: aload_0
       1: getfield      #8                  // Field partitionQueues:Ljava/util/Map;
       4: aload_1
       5: invokeinterface #16,  2           // InterfaceMethod java/util/Map.get:(Ljava/lang/Object;)Ljava/lang/Object;
      10: checkcast     #12                 // class org/apache/kafka/streams/processor/internals/RecordQueue
      13: astore_2
      14: aload_2
      15: ifnonnull     50
      18: new           #17                 // class java/lang/IllegalStateException
      21: dup
      22: new           #18                 // class java/lang/StringBuilder
      25: dup
      26: invokespecial #19                 // Method java/lang/StringBuilder."<init>":()V
      29: ldc           #20                 // String Partition
      31: invokevirtual #21                 // Method java/lang/StringBuilder.append:(Ljava/lang/String;)Ljava/lang/StringBuilder;
      34: aload_1
      35: invokevirtual #22                 // Method java/lang/StringBuilder.append:(Ljava/lang/Object;)Ljava/lang/StringBuilder;
      38: ldc           #23                 // String  not found.
      40: invokevirtual #21                 // Method java/lang/StringBuilder.append:(Ljava/lang/String;)Ljava/lang/StringBuilder;
      43: invokevirtual #24                 // Method java/lang/StringBuilder.toString:()Ljava/lang/String;
      46: invokespecial #25                 // Method java/lang/IllegalStateException."<init>":(Ljava/lang/String;)V
      49: athrow
      50: aload_2
      51: invokevirtual #59                 // Method org/apache/kafka/streams/processor/internals/RecordQueue.headRecordOffset:()Ljava/lang/Long;
      54: areturn

  int numBuffered(org.apache.kafka.common.TopicPartition);
    Code:
       0: aload_0
       1: getfield      #8                  // Field partitionQueues:Ljava/util/Map;
       4: aload_1
       5: invokeinterface #16,  2           // InterfaceMethod java/util/Map.get:(Ljava/lang/Object;)Ljava/lang/Object;
      10: checkcast     #12                 // class org/apache/kafka/streams/processor/internals/RecordQueue
      13: astore_2
      14: aload_2
      15: ifnonnull     50
      18: new           #17                 // class java/lang/IllegalStateException
      21: dup
      22: new           #18                 // class java/lang/StringBuilder
      25: dup
      26: invokespecial #19                 // Method java/lang/StringBuilder."<init>":()V
      29: ldc           #20                 // String Partition
      31: invokevirtual #21                 // Method java/lang/StringBuilder.append:(Ljava/lang/String;)Ljava/lang/StringBuilder;
      34: aload_1
      35: invokevirtual #22                 // Method java/lang/StringBuilder.append:(Ljava/lang/Object;)Ljava/lang/StringBuilder;
      38: ldc           #23                 // String  not found.
      40: invokevirtual #21                 // Method java/lang/StringBuilder.append:(Ljava/lang/String;)Ljava/lang/StringBuilder;
      43: invokevirtual #24                 // Method java/lang/StringBuilder.toString:()Ljava/lang/String;
      46: invokespecial #25                 // Method java/lang/IllegalStateException."<init>":(Ljava/lang/String;)V
      49: athrow
      50: aload_2
      51: invokevirtual #38                 // Method org/apache/kafka/streams/processor/internals/RecordQueue.size:()I
      54: ireturn

  int numBuffered();
    Code:
       0: aload_0
       1: getfield      #10                 // Field totalBuffered:I
       4: ireturn

  boolean allPartitionsBuffered();
    Code:
       0: aload_0
       1: getfield      #11                 // Field allBuffered:Z
       4: ireturn

  void clear();
    Code:
       0: aload_0
       1: getfield      #8                  // Field partitionQueues:Ljava/util/Map;
       4: invokeinterface #60,  1           // InterfaceMethod java/util/Map.values:()Ljava/util/Collection;
       9: invokeinterface #61,  1           // InterfaceMethod java/util/Collection.iterator:()Ljava/util/Iterator;
      14: astore_1
      15: aload_1
      16: invokeinterface #31,  1           // InterfaceMethod java/util/Iterator.hasNext:()Z
      21: ifeq          41
      24: aload_1
      25: invokeinterface #32,  1           // InterfaceMethod java/util/Iterator.next:()Ljava/lang/Object;
      30: checkcast     #12                 // class org/apache/kafka/streams/processor/internals/RecordQueue
      33: astore_2
      34: aload_2
      35: invokevirtual #62                 // Method org/apache/kafka/streams/processor/internals/RecordQueue.clear:()V
      38: goto          15
      41: aload_0
      42: getfield      #7                  // Field nonEmptyQueuesByTime:Ljava/util/PriorityQueue;
      45: invokevirtual #63                 // Method java/util/PriorityQueue.clear:()V
      48: aload_0
      49: iconst_0
      50: putfield      #10                 // Field totalBuffered:I
      53: aload_0
      54: ldc2_w        #13                 // long -1l
      57: putfield      #15                 // Field streamTime:J
      60: return

  private static boolean lambda$updatePartitions$0(java.util.Set, org.apache.kafka.streams.processor.internals.RecordQueue);
    Code:
       0: aload_0
       1: aload_1
       2: invokevirtual #64                 // Method org/apache/kafka/streams/processor/internals/RecordQueue.partition:()Lorg/apache/kafka/common/TopicPartition;
       5: invokeinterface #36,  2           // InterfaceMethod java/util/Set.contains:(Ljava/lang/Object;)Z
      10: ireturn
}
