Compiled from "StreamsPartitionAssignor.java"
public class org.apache.kafka.streams.processor.internals.StreamsPartitionAssignor implements org.apache.kafka.clients.consumer.ConsumerPartitionAssignor,org.apache.kafka.common.Configurable {
  private org.slf4j.Logger log;

  private java.lang.String logPrefix;

  private static final java.util.UUID FUTURE_ID;

  protected static final java.util.Comparator<org.apache.kafka.common.TopicPartition> PARTITION_COMPARATOR;

  private java.lang.String userEndPoint;

  private org.apache.kafka.streams.processor.internals.assignment.AssignorConfiguration$AssignmentConfigs assignmentConfigs;

  private org.apache.kafka.streams.processor.internals.TaskManager taskManager;

  private org.apache.kafka.streams.processor.internals.StreamsMetadataState streamsMetadataState;

  private org.apache.kafka.streams.processor.PartitionGrouper partitionGrouper;

  private java.util.concurrent.atomic.AtomicInteger assignmentErrorCode;

  private java.util.concurrent.atomic.AtomicLong nextScheduledRebalanceMs;

  private org.apache.kafka.common.utils.Time time;

  protected int usedSubscriptionMetadataVersion;

  private org.apache.kafka.clients.admin.Admin adminClient;

  private org.apache.kafka.streams.processor.internals.InternalTopicManager internalTopicManager;

  private org.apache.kafka.streams.processor.internals.assignment.CopartitionedTopicsEnforcer copartitionedTopicsEnforcer;

  private org.apache.kafka.clients.consumer.ConsumerPartitionAssignor$RebalanceProtocol rebalanceProtocol;

  private org.apache.kafka.streams.processor.internals.assignment.AssignorConfiguration$AssignmentListener assignmentListener;

  private java.util.function.Supplier<org.apache.kafka.streams.processor.internals.assignment.TaskAssignor> taskAssignorSupplier;

  public org.apache.kafka.streams.processor.internals.StreamsPartitionAssignor();
    Code:
       0: aload_0
       1: invokespecial #3                  // Method java/lang/Object."<init>":()V
       4: aload_0
       5: bipush        7
       7: putfield      #4                  // Field usedSubscriptionMetadataVersion:I
      10: return

  public void configure(java.util.Map<java.lang.String, ?>);
    Code:
       0: new           #5                  // class org/apache/kafka/streams/processor/internals/assignment/AssignorConfiguration
       3: dup
       4: aload_1
       5: invokespecial #6                  // Method org/apache/kafka/streams/processor/internals/assignment/AssignorConfiguration."<init>":(Ljava/util/Map;)V
       8: astore_2
       9: aload_0
      10: aload_2
      11: invokevirtual #7                  // Method org/apache/kafka/streams/processor/internals/assignment/AssignorConfiguration.logPrefix:()Ljava/lang/String;
      14: putfield      #8                  // Field logPrefix:Ljava/lang/String;
      17: aload_0
      18: new           #9                  // class org/apache/kafka/common/utils/LogContext
      21: dup
      22: aload_0
      23: getfield      #8                  // Field logPrefix:Ljava/lang/String;
      26: invokespecial #10                 // Method org/apache/kafka/common/utils/LogContext."<init>":(Ljava/lang/String;)V
      29: aload_0
      30: invokevirtual #11                 // Method java/lang/Object.getClass:()Ljava/lang/Class;
      33: invokevirtual #12                 // Method org/apache/kafka/common/utils/LogContext.logger:(Ljava/lang/Class;)Lorg/slf4j/Logger;
      36: putfield      #13                 // Field log:Lorg/slf4j/Logger;
      39: aload_0
      40: aload_2
      41: aload_0
      42: getfield      #4                  // Field usedSubscriptionMetadataVersion:I
      45: invokevirtual #14                 // Method org/apache/kafka/streams/processor/internals/assignment/AssignorConfiguration.configuredMetadataVersion:(I)I
      48: putfield      #4                  // Field usedSubscriptionMetadataVersion:I
      51: aload_0
      52: aload_2
      53: invokevirtual #15                 // Method org/apache/kafka/streams/processor/internals/assignment/AssignorConfiguration.taskManager:()Lorg/apache/kafka/streams/processor/internals/TaskManager;
      56: putfield      #16                 // Field taskManager:Lorg/apache/kafka/streams/processor/internals/TaskManager;
      59: aload_0
      60: aload_2
      61: invokevirtual #17                 // Method org/apache/kafka/streams/processor/internals/assignment/AssignorConfiguration.streamsMetadataState:()Lorg/apache/kafka/streams/processor/internals/StreamsMetadataState;
      64: putfield      #18                 // Field streamsMetadataState:Lorg/apache/kafka/streams/processor/internals/StreamsMetadataState;
      67: aload_0
      68: aload_2
      69: invokevirtual #19                 // Method org/apache/kafka/streams/processor/internals/assignment/AssignorConfiguration.assignmentErrorCode:()Ljava/util/concurrent/atomic/AtomicInteger;
      72: putfield      #20                 // Field assignmentErrorCode:Ljava/util/concurrent/atomic/AtomicInteger;
      75: aload_0
      76: aload_2
      77: invokevirtual #21                 // Method org/apache/kafka/streams/processor/internals/assignment/AssignorConfiguration.nextScheduledRebalanceMs:()Ljava/util/concurrent/atomic/AtomicLong;
      80: putfield      #22                 // Field nextScheduledRebalanceMs:Ljava/util/concurrent/atomic/AtomicLong;
      83: aload_0
      84: aload_2
      85: invokevirtual #23                 // Method org/apache/kafka/streams/processor/internals/assignment/AssignorConfiguration.time:()Lorg/apache/kafka/common/utils/Time;
      88: putfield      #24                 // Field time:Lorg/apache/kafka/common/utils/Time;
      91: aload_0
      92: aload_2
      93: invokevirtual #25                 // Method org/apache/kafka/streams/processor/internals/assignment/AssignorConfiguration.assignmentConfigs:()Lorg/apache/kafka/streams/processor/internals/assignment/AssignorConfiguration$AssignmentConfigs;
      96: putfield      #26                 // Field assignmentConfigs:Lorg/apache/kafka/streams/processor/internals/assignment/AssignorConfiguration$AssignmentConfigs;
      99: aload_0
     100: aload_2
     101: invokevirtual #27                 // Method org/apache/kafka/streams/processor/internals/assignment/AssignorConfiguration.partitionGrouper:()Lorg/apache/kafka/streams/processor/PartitionGrouper;
     104: putfield      #28                 // Field partitionGrouper:Lorg/apache/kafka/streams/processor/PartitionGrouper;
     107: aload_0
     108: aload_2
     109: invokevirtual #29                 // Method org/apache/kafka/streams/processor/internals/assignment/AssignorConfiguration.userEndPoint:()Ljava/lang/String;
     112: putfield      #30                 // Field userEndPoint:Ljava/lang/String;
     115: aload_0
     116: aload_2
     117: invokevirtual #31                 // Method org/apache/kafka/streams/processor/internals/assignment/AssignorConfiguration.adminClient:()Lorg/apache/kafka/clients/admin/Admin;
     120: putfield      #32                 // Field adminClient:Lorg/apache/kafka/clients/admin/Admin;
     123: aload_0
     124: aload_2
     125: invokevirtual #33                 // Method org/apache/kafka/streams/processor/internals/assignment/AssignorConfiguration.internalTopicManager:()Lorg/apache/kafka/streams/processor/internals/InternalTopicManager;
     128: putfield      #34                 // Field internalTopicManager:Lorg/apache/kafka/streams/processor/internals/InternalTopicManager;
     131: aload_0
     132: aload_2
     133: invokevirtual #35                 // Method org/apache/kafka/streams/processor/internals/assignment/AssignorConfiguration.copartitionedTopicsEnforcer:()Lorg/apache/kafka/streams/processor/internals/assignment/CopartitionedTopicsEnforcer;
     136: putfield      #36                 // Field copartitionedTopicsEnforcer:Lorg/apache/kafka/streams/processor/internals/assignment/CopartitionedTopicsEnforcer;
     139: aload_0
     140: aload_2
     141: invokevirtual #37                 // Method org/apache/kafka/streams/processor/internals/assignment/AssignorConfiguration.rebalanceProtocol:()Lorg/apache/kafka/clients/consumer/ConsumerPartitionAssignor$RebalanceProtocol;
     144: putfield      #38                 // Field rebalanceProtocol:Lorg/apache/kafka/clients/consumer/ConsumerPartitionAssignor$RebalanceProtocol;
     147: aload_0
     148: aload_2
     149: dup
     150: invokevirtual #11                 // Method java/lang/Object.getClass:()Ljava/lang/Class;
     153: pop
     154: invokedynamic #39,  0             // InvokeDynamic #0:get:(Lorg/apache/kafka/streams/processor/internals/assignment/AssignorConfiguration;)Ljava/util/function/Supplier;
     159: putfield      #40                 // Field taskAssignorSupplier:Ljava/util/function/Supplier;
     162: aload_0
     163: aload_2
     164: invokevirtual #41                 // Method org/apache/kafka/streams/processor/internals/assignment/AssignorConfiguration.assignmentListener:()Lorg/apache/kafka/streams/processor/internals/assignment/AssignorConfiguration$AssignmentListener;
     167: putfield      #42                 // Field assignmentListener:Lorg/apache/kafka/streams/processor/internals/assignment/AssignorConfiguration$AssignmentListener;
     170: return

  public java.lang.String name();
    Code:
       0: ldc           #43                 // String stream
       2: areturn

  public java.util.List<org.apache.kafka.clients.consumer.ConsumerPartitionAssignor$RebalanceProtocol> supportedProtocols();
    Code:
       0: new           #44                 // class java/util/ArrayList
       3: dup
       4: invokespecial #45                 // Method java/util/ArrayList."<init>":()V
       7: astore_1
       8: aload_1
       9: getstatic     #46                 // Field org/apache/kafka/clients/consumer/ConsumerPartitionAssignor$RebalanceProtocol.EAGER:Lorg/apache/kafka/clients/consumer/ConsumerPartitionAssignor$RebalanceProtocol;
      12: invokeinterface #47,  2           // InterfaceMethod java/util/List.add:(Ljava/lang/Object;)Z
      17: pop
      18: aload_0
      19: getfield      #38                 // Field rebalanceProtocol:Lorg/apache/kafka/clients/consumer/ConsumerPartitionAssignor$RebalanceProtocol;
      22: getstatic     #48                 // Field org/apache/kafka/clients/consumer/ConsumerPartitionAssignor$RebalanceProtocol.COOPERATIVE:Lorg/apache/kafka/clients/consumer/ConsumerPartitionAssignor$RebalanceProtocol;
      25: if_acmpne     39
      28: aload_1
      29: aload_0
      30: getfield      #38                 // Field rebalanceProtocol:Lorg/apache/kafka/clients/consumer/ConsumerPartitionAssignor$RebalanceProtocol;
      33: invokeinterface #47,  2           // InterfaceMethod java/util/List.add:(Ljava/lang/Object;)Z
      38: pop
      39: aload_1
      40: areturn

  public java.nio.ByteBuffer subscriptionUserData(java.util.Set<java.lang.String>);
    Code:
       0: aload_0
       1: aload_1
       2: invokevirtual #49                 // Method handleRebalanceStart:(Ljava/util/Set;)V
       5: new           #1                  // class org/apache/kafka/streams/processor/internals/assignment/SubscriptionInfo
       8: dup
       9: aload_0
      10: getfield      #4                  // Field usedSubscriptionMetadataVersion:I
      13: bipush        7
      15: aload_0
      16: getfield      #16                 // Field taskManager:Lorg/apache/kafka/streams/processor/internals/TaskManager;
      19: invokevirtual #50                 // Method org/apache/kafka/streams/processor/internals/TaskManager.processId:()Ljava/util/UUID;
      22: aload_0
      23: getfield      #30                 // Field userEndPoint:Ljava/lang/String;
      26: aload_0
      27: getfield      #16                 // Field taskManager:Lorg/apache/kafka/streams/processor/internals/TaskManager;
      30: invokevirtual #51                 // Method org/apache/kafka/streams/processor/internals/TaskManager.getTaskOffsetSums:()Ljava/util/Map;
      33: invokespecial #52                 // Method org/apache/kafka/streams/processor/internals/assignment/SubscriptionInfo."<init>":(IILjava/util/UUID;Ljava/lang/String;Ljava/util/Map;)V
      36: invokevirtual #53                 // Method org/apache/kafka/streams/processor/internals/assignment/SubscriptionInfo.encode:()Ljava/nio/ByteBuffer;
      39: areturn

  private java.util.Map<java.lang.String, org.apache.kafka.clients.consumer.ConsumerPartitionAssignor$Assignment> errorAssignment(java.util.Map<java.util.UUID, org.apache.kafka.streams.processor.internals.StreamsPartitionAssignor$ClientMetadata>, int);
    Code:
       0: new           #54                 // class java/util/HashMap
       3: dup
       4: invokespecial #55                 // Method java/util/HashMap."<init>":()V
       7: astore_3
       8: aload_1
       9: invokeinterface #56,  1           // InterfaceMethod java/util/Map.values:()Ljava/util/Collection;
      14: invokeinterface #57,  1           // InterfaceMethod java/util/Collection.iterator:()Ljava/util/Iterator;
      19: astore        4
      21: aload         4
      23: invokeinterface #58,  1           // InterfaceMethod java/util/Iterator.hasNext:()Z
      28: ifeq          127
      31: aload         4
      33: invokeinterface #59,  1           // InterfaceMethod java/util/Iterator.next:()Ljava/lang/Object;
      38: checkcast     #60                 // class org/apache/kafka/streams/processor/internals/StreamsPartitionAssignor$ClientMetadata
      41: astore        5
      43: aload         5
      45: invokestatic  #61                 // Method org/apache/kafka/streams/processor/internals/StreamsPartitionAssignor$ClientMetadata.access$000:(Lorg/apache/kafka/streams/processor/internals/StreamsPartitionAssignor$ClientMetadata;)Ljava/util/SortedSet;
      48: invokeinterface #62,  1           // InterfaceMethod java/util/SortedSet.iterator:()Ljava/util/Iterator;
      53: astore        6
      55: aload         6
      57: invokeinterface #58,  1           // InterfaceMethod java/util/Iterator.hasNext:()Z
      62: ifeq          124
      65: aload         6
      67: invokeinterface #59,  1           // InterfaceMethod java/util/Iterator.next:()Ljava/lang/Object;
      72: checkcast     #63                 // class java/lang/String
      75: astore        7
      77: aload_3
      78: aload         7
      80: new           #64                 // class org/apache/kafka/clients/consumer/ConsumerPartitionAssignor$Assignment
      83: dup
      84: invokestatic  #65                 // Method java/util/Collections.emptyList:()Ljava/util/List;
      87: new           #66                 // class org/apache/kafka/streams/processor/internals/assignment/AssignmentInfo
      90: dup
      91: bipush        7
      93: invokestatic  #65                 // Method java/util/Collections.emptyList:()Ljava/util/List;
      96: invokestatic  #67                 // Method java/util/Collections.emptyMap:()Ljava/util/Map;
      99: invokestatic  #67                 // Method java/util/Collections.emptyMap:()Ljava/util/Map;
     102: invokestatic  #67                 // Method java/util/Collections.emptyMap:()Ljava/util/Map;
     105: iload_2
     106: invokespecial #68                 // Method org/apache/kafka/streams/processor/internals/assignment/AssignmentInfo."<init>":(ILjava/util/List;Ljava/util/Map;Ljava/util/Map;Ljava/util/Map;I)V
     109: invokevirtual #69                 // Method org/apache/kafka/streams/processor/internals/assignment/AssignmentInfo.encode:()Ljava/nio/ByteBuffer;
     112: invokespecial #70                 // Method org/apache/kafka/clients/consumer/ConsumerPartitionAssignor$Assignment."<init>":(Ljava/util/List;Ljava/nio/ByteBuffer;)V
     115: invokeinterface #71,  3           // InterfaceMethod java/util/Map.put:(Ljava/lang/Object;Ljava/lang/Object;)Ljava/lang/Object;
     120: pop
     121: goto          55
     124: goto          21
     127: aload_3
     128: areturn

  public org.apache.kafka.clients.consumer.ConsumerPartitionAssignor$GroupAssignment assign(org.apache.kafka.common.Cluster, org.apache.kafka.clients.consumer.ConsumerPartitionAssignor$GroupSubscription);
    Code:
       0: aload_2
       1: invokevirtual #72                 // Method org/apache/kafka/clients/consumer/ConsumerPartitionAssignor$GroupSubscription.groupSubscription:()Ljava/util/Map;
       4: astore_3
       5: new           #54                 // class java/util/HashMap
       8: dup
       9: invokespecial #55                 // Method java/util/HashMap."<init>":()V
      12: astore        4
      14: new           #73                 // class java/util/HashSet
      17: dup
      18: invokespecial #74                 // Method java/util/HashSet."<init>":()V
      21: astore        5
      23: bipush        7
      25: istore        6
      27: bipush        7
      29: istore        7
      31: iconst_m1
      32: istore        8
      34: aload_3
      35: invokeinterface #75,  1           // InterfaceMethod java/util/Map.entrySet:()Ljava/util/Set;
      40: invokeinterface #76,  1           // InterfaceMethod java/util/Set.iterator:()Ljava/util/Iterator;
      45: astore        9
      47: aload         9
      49: invokeinterface #58,  1           // InterfaceMethod java/util/Iterator.hasNext:()Z
      54: ifeq          279
      57: aload         9
      59: invokeinterface #59,  1           // InterfaceMethod java/util/Iterator.next:()Ljava/lang/Object;
      64: checkcast     #77                 // class java/util/Map$Entry
      67: astore        10
      69: aload         10
      71: invokeinterface #78,  1           // InterfaceMethod java/util/Map$Entry.getKey:()Ljava/lang/Object;
      76: checkcast     #63                 // class java/lang/String
      79: astore        11
      81: aload         10
      83: invokeinterface #79,  1           // InterfaceMethod java/util/Map$Entry.getValue:()Ljava/lang/Object;
      88: checkcast     #80                 // class org/apache/kafka/clients/consumer/ConsumerPartitionAssignor$Subscription
      91: astore        12
      93: aload         12
      95: invokevirtual #81                 // Method org/apache/kafka/clients/consumer/ConsumerPartitionAssignor$Subscription.userData:()Ljava/nio/ByteBuffer;
      98: invokestatic  #82                 // Method org/apache/kafka/streams/processor/internals/assignment/SubscriptionInfo.decode:(Ljava/nio/ByteBuffer;)Lorg/apache/kafka/streams/processor/internals/assignment/SubscriptionInfo;
     101: astore        13
     103: aload         13
     105: invokevirtual #83                 // Method org/apache/kafka/streams/processor/internals/assignment/SubscriptionInfo.version:()I
     108: istore        14
     110: aload_0
     111: iload         14
     113: iload         6
     115: invokespecial #84                 // Method updateMinReceivedVersion:(II)I
     118: istore        6
     120: aload_0
     121: aload         13
     123: invokevirtual #85                 // Method org/apache/kafka/streams/processor/internals/assignment/SubscriptionInfo.latestSupportedVersion:()I
     126: iload         7
     128: invokespecial #86                 // Method updateMinSupportedVersion:(II)I
     131: istore        7
     133: iload         14
     135: bipush        7
     137: if_icmple     184
     140: iload         14
     142: istore        8
     144: getstatic     #87                 // Field FUTURE_ID:Ljava/util/UUID;
     147: astore        15
     149: aload         4
     151: getstatic     #87                 // Field FUTURE_ID:Ljava/util/UUID;
     154: invokeinterface #88,  2           // InterfaceMethod java/util/Map.containsKey:(Ljava/lang/Object;)Z
     159: ifne          191
     162: aload         4
     164: getstatic     #87                 // Field FUTURE_ID:Ljava/util/UUID;
     167: new           #60                 // class org/apache/kafka/streams/processor/internals/StreamsPartitionAssignor$ClientMetadata
     170: dup
     171: aconst_null
     172: invokespecial #89                 // Method org/apache/kafka/streams/processor/internals/StreamsPartitionAssignor$ClientMetadata."<init>":(Ljava/lang/String;)V
     175: invokeinterface #71,  3           // InterfaceMethod java/util/Map.put:(Ljava/lang/Object;Ljava/lang/Object;)Ljava/lang/Object;
     180: pop
     181: goto          191
     184: aload         13
     186: invokevirtual #90                 // Method org/apache/kafka/streams/processor/internals/assignment/SubscriptionInfo.processId:()Ljava/util/UUID;
     189: astore        15
     191: aload         4
     193: aload         15
     195: invokeinterface #91,  2           // InterfaceMethod java/util/Map.get:(Ljava/lang/Object;)Ljava/lang/Object;
     200: checkcast     #60                 // class org/apache/kafka/streams/processor/internals/StreamsPartitionAssignor$ClientMetadata
     203: astore        16
     205: aload         16
     207: ifnonnull     239
     210: new           #60                 // class org/apache/kafka/streams/processor/internals/StreamsPartitionAssignor$ClientMetadata
     213: dup
     214: aload         13
     216: invokevirtual #92                 // Method org/apache/kafka/streams/processor/internals/assignment/SubscriptionInfo.userEndPoint:()Ljava/lang/String;
     219: invokespecial #89                 // Method org/apache/kafka/streams/processor/internals/StreamsPartitionAssignor$ClientMetadata."<init>":(Ljava/lang/String;)V
     222: astore        16
     224: aload         4
     226: aload         13
     228: invokevirtual #90                 // Method org/apache/kafka/streams/processor/internals/assignment/SubscriptionInfo.processId:()Ljava/util/UUID;
     231: aload         16
     233: invokeinterface #71,  3           // InterfaceMethod java/util/Map.put:(Ljava/lang/Object;Ljava/lang/Object;)Ljava/lang/Object;
     238: pop
     239: aload         16
     241: aload         11
     243: aload         12
     245: invokevirtual #93                 // Method org/apache/kafka/clients/consumer/ConsumerPartitionAssignor$Subscription.ownedPartitions:()Ljava/util/List;
     248: invokevirtual #94                 // Method org/apache/kafka/streams/processor/internals/StreamsPartitionAssignor$ClientMetadata.addConsumer:(Ljava/lang/String;Ljava/util/List;)V
     251: aload         5
     253: aload         12
     255: invokevirtual #93                 // Method org/apache/kafka/clients/consumer/ConsumerPartitionAssignor$Subscription.ownedPartitions:()Ljava/util/List;
     258: invokeinterface #95,  2           // InterfaceMethod java/util/Set.addAll:(Ljava/util/Collection;)Z
     263: pop
     264: aload         16
     266: aload         11
     268: aload         13
     270: invokevirtual #96                 // Method org/apache/kafka/streams/processor/internals/assignment/SubscriptionInfo.taskOffsetSums:()Ljava/util/Map;
     273: invokevirtual #97                 // Method org/apache/kafka/streams/processor/internals/StreamsPartitionAssignor$ClientMetadata.addPreviousTasksAndOffsetSums:(Ljava/lang/String;Ljava/util/Map;)V
     276: goto          47
     279: aload_0
     280: iload         6
     282: iload         7
     284: iload         8
     286: invokespecial #98                 // Method checkMetadataVersions:(III)Z
     289: istore        9
     291: aload_0
     292: getfield      #13                 // Field log:Lorg/slf4j/Logger;
     295: ldc           #99                 // String Constructed client metadata {} from the member subscriptions.
     297: aload         4
     299: invokeinterface #100,  3          // InterfaceMethod org/slf4j/Logger.debug:(Ljava/lang/String;Ljava/lang/Object;)V
     304: aload_0
     305: getfield      #16                 // Field taskManager:Lorg/apache/kafka/streams/processor/internals/TaskManager;
     308: invokevirtual #101                // Method org/apache/kafka/streams/processor/internals/TaskManager.builder:()Lorg/apache/kafka/streams/processor/internals/InternalTopologyBuilder;
     311: invokevirtual #102                // Method org/apache/kafka/streams/processor/internals/InternalTopologyBuilder.topicGroups:()Ljava/util/Map;
     314: astore        10
     316: aload_0
     317: aload         10
     319: aload_1
     320: invokespecial #103                // Method prepareRepartitionTopics:(Ljava/util/Map;Lorg/apache/kafka/common/Cluster;)Ljava/util/Map;
     323: astore        11
     325: goto          350
     328: astore        12
     330: new           #105                // class org/apache/kafka/clients/consumer/ConsumerPartitionAssignor$GroupAssignment
     333: dup
     334: aload_0
     335: aload         4
     337: getstatic     #106                // Field org/apache/kafka/streams/processor/internals/assignment/AssignorError.INCOMPLETE_SOURCE_TOPIC_METADATA:Lorg/apache/kafka/streams/processor/internals/assignment/AssignorError;
     340: invokevirtual #107                // Method org/apache/kafka/streams/processor/internals/assignment/AssignorError.code:()I
     343: invokespecial #108                // Method errorAssignment:(Ljava/util/Map;I)Ljava/util/Map;
     346: invokespecial #109                // Method org/apache/kafka/clients/consumer/ConsumerPartitionAssignor$GroupAssignment."<init>":(Ljava/util/Map;)V
     349: areturn
     350: aload_1
     351: aload         11
     353: invokevirtual #110                // Method org/apache/kafka/common/Cluster.withPartitions:(Ljava/util/Map;)Lorg/apache/kafka/common/Cluster;
     356: astore        12
     358: aload_0
     359: getfield      #13                 // Field log:Lorg/slf4j/Logger;
     362: ldc           #111                // String Created repartition topics {} from the parsed topology.
     364: aload         11
     366: invokeinterface #56,  1           // InterfaceMethod java/util/Map.values:()Ljava/util/Collection;
     371: invokeinterface #100,  3          // InterfaceMethod org/slf4j/Logger.debug:(Ljava/lang/String;Ljava/lang/Object;)V
     376: new           #73                 // class java/util/HashSet
     379: dup
     380: invokespecial #74                 // Method java/util/HashSet."<init>":()V
     383: astore        13
     385: new           #54                 // class java/util/HashMap
     388: dup
     389: invokespecial #55                 // Method java/util/HashMap."<init>":()V
     392: astore        14
     394: aload         10
     396: invokeinterface #75,  1           // InterfaceMethod java/util/Map.entrySet:()Ljava/util/Set;
     401: invokeinterface #76,  1           // InterfaceMethod java/util/Set.iterator:()Ljava/util/Iterator;
     406: astore        15
     408: aload         15
     410: invokeinterface #58,  1           // InterfaceMethod java/util/Iterator.hasNext:()Z
     415: ifeq          482
     418: aload         15
     420: invokeinterface #59,  1           // InterfaceMethod java/util/Iterator.next:()Ljava/lang/Object;
     425: checkcast     #77                 // class java/util/Map$Entry
     428: astore        16
     430: aload         13
     432: aload         16
     434: invokeinterface #79,  1           // InterfaceMethod java/util/Map$Entry.getValue:()Ljava/lang/Object;
     439: checkcast     #112                // class org/apache/kafka/streams/processor/internals/InternalTopologyBuilder$TopicsInfo
     442: getfield      #113                // Field org/apache/kafka/streams/processor/internals/InternalTopologyBuilder$TopicsInfo.sourceTopics:Ljava/util/Set;
     445: invokeinterface #95,  2           // InterfaceMethod java/util/Set.addAll:(Ljava/util/Collection;)Z
     450: pop
     451: aload         14
     453: aload         16
     455: invokeinterface #78,  1           // InterfaceMethod java/util/Map$Entry.getKey:()Ljava/lang/Object;
     460: aload         16
     462: invokeinterface #79,  1           // InterfaceMethod java/util/Map$Entry.getValue:()Ljava/lang/Object;
     467: checkcast     #112                // class org/apache/kafka/streams/processor/internals/InternalTopologyBuilder$TopicsInfo
     470: getfield      #113                // Field org/apache/kafka/streams/processor/internals/InternalTopologyBuilder$TopicsInfo.sourceTopics:Ljava/util/Set;
     473: invokeinterface #71,  3           // InterfaceMethod java/util/Map.put:(Ljava/lang/Object;Ljava/lang/Object;)Ljava/lang/Object;
     478: pop
     479: goto          408
     482: aload_0
     483: getfield      #28                 // Field partitionGrouper:Lorg/apache/kafka/streams/processor/PartitionGrouper;
     486: aload         14
     488: aload         12
     490: invokeinterface #114,  3          // InterfaceMethod org/apache/kafka/streams/processor/PartitionGrouper.partitionGroups:(Ljava/util/Map;Lorg/apache/kafka/common/Cluster;)Ljava/util/Map;
     495: astore        15
     497: new           #73                 // class java/util/HashSet
     500: dup
     501: invokespecial #74                 // Method java/util/HashSet."<init>":()V
     504: astore        16
     506: aload_0
     507: aload         12
     509: aload         13
     511: aload         10
     513: aload         4
     515: aload         15
     517: aload         16
     519: invokespecial #115                // Method assignTasksToClients:(Lorg/apache/kafka/common/Cluster;Ljava/util/Set;Ljava/util/Map;Ljava/util/Map;Ljava/util/Map;Ljava/util/Set;)Z
     522: istore        17
     524: new           #54                 // class java/util/HashMap
     527: dup
     528: invokespecial #55                 // Method java/util/HashMap."<init>":()V
     531: astore        18
     533: new           #54                 // class java/util/HashMap
     536: dup
     537: invokespecial #55                 // Method java/util/HashMap."<init>":()V
     540: astore        19
     542: iload         6
     544: iconst_2
     545: if_icmplt     560
     548: aload_0
     549: aload         18
     551: aload         19
     553: aload         15
     555: aload         4
     557: invokespecial #116                // Method populatePartitionsByHostMaps:(Ljava/util/Map;Ljava/util/Map;Ljava/util/Map;Ljava/util/Map;)V
     560: aload_0
     561: getfield      #18                 // Field streamsMetadataState:Lorg/apache/kafka/streams/processor/internals/StreamsMetadataState;
     564: aload         18
     566: aload         19
     568: aload         12
     570: invokevirtual #117                // Method org/apache/kafka/streams/processor/internals/StreamsMetadataState.onChange:(Ljava/util/Map;Ljava/util/Map;Lorg/apache/kafka/common/Cluster;)V
     573: aload_0
     574: aload         16
     576: aload         4
     578: aload         15
     580: aload         18
     582: aload         19
     584: aload         5
     586: iload         6
     588: iload         7
     590: iload         9
     592: iload         17
     594: invokespecial #118                // Method computeNewAssignment:(Ljava/util/Set;Ljava/util/Map;Ljava/util/Map;Ljava/util/Map;Ljava/util/Map;Ljava/util/Set;IIZZ)Ljava/util/Map;
     597: astore        20
     599: new           #105                // class org/apache/kafka/clients/consumer/ConsumerPartitionAssignor$GroupAssignment
     602: dup
     603: aload         20
     605: invokespecial #109                // Method org/apache/kafka/clients/consumer/ConsumerPartitionAssignor$GroupAssignment."<init>":(Ljava/util/Map;)V
     608: areturn
    Exception table:
       from    to  target type
         316   325   328   Class org/apache/kafka/streams/errors/TaskAssignmentException

  private boolean checkMetadataVersions(int, int, int);
    Code:
       0: iload_3
       1: iconst_m1
       2: if_icmpne     11
       5: iconst_0
       6: istore        4
       8: goto          82
      11: iload_1
      12: iconst_3
      13: if_icmplt     41
      16: iconst_1
      17: istore        4
      19: aload_0
      20: getfield      #13                 // Field log:Lorg/slf4j/Logger;
      23: ldc           #119                // String Received a future (version probing) subscription (version: {}). Sending assignment back (with supported version {}).
      25: iload_3
      26: invokestatic  #120                // Method java/lang/Integer.valueOf:(I)Ljava/lang/Integer;
      29: iload_2
      30: invokestatic  #120                // Method java/lang/Integer.valueOf:(I)Ljava/lang/Integer;
      33: invokeinterface #121,  4          // InterfaceMethod org/slf4j/Logger.info:(Ljava/lang/String;Ljava/lang/Object;Ljava/lang/Object;)V
      38: goto          82
      41: new           #122                // class java/lang/IllegalStateException
      44: dup
      45: new           #123                // class java/lang/StringBuilder
      48: dup
      49: invokespecial #124                // Method java/lang/StringBuilder."<init>":()V
      52: ldc           #125                // String Received a future (version probing) subscription (version:
      54: invokevirtual #126                // Method java/lang/StringBuilder.append:(Ljava/lang/String;)Ljava/lang/StringBuilder;
      57: iload_3
      58: invokevirtual #127                // Method java/lang/StringBuilder.append:(I)Ljava/lang/StringBuilder;
      61: ldc           #128                // String ) and an incompatible pre Kafka 2.0 subscription (version:
      63: invokevirtual #126                // Method java/lang/StringBuilder.append:(Ljava/lang/String;)Ljava/lang/StringBuilder;
      66: iload_1
      67: invokevirtual #127                // Method java/lang/StringBuilder.append:(I)Ljava/lang/StringBuilder;
      70: ldc           #129                // String ) at the same time.
      72: invokevirtual #126                // Method java/lang/StringBuilder.append:(Ljava/lang/String;)Ljava/lang/StringBuilder;
      75: invokevirtual #130                // Method java/lang/StringBuilder.toString:()Ljava/lang/String;
      78: invokespecial #131                // Method java/lang/IllegalStateException."<init>":(Ljava/lang/String;)V
      81: athrow
      82: iload_1
      83: bipush        7
      85: if_icmpge     108
      88: aload_0
      89: getfield      #13                 // Field log:Lorg/slf4j/Logger;
      92: ldc           #132                // String Downgrade metadata to version {}. Latest supported version is {}.
      94: iload_1
      95: invokestatic  #120                // Method java/lang/Integer.valueOf:(I)Ljava/lang/Integer;
      98: bipush        7
     100: invokestatic  #120                // Method java/lang/Integer.valueOf:(I)Ljava/lang/Integer;
     103: invokeinterface #121,  4          // InterfaceMethod org/slf4j/Logger.info:(Ljava/lang/String;Ljava/lang/Object;Ljava/lang/Object;)V
     108: iload_2
     109: bipush        7
     111: if_icmpge     134
     114: aload_0
     115: getfield      #13                 // Field log:Lorg/slf4j/Logger;
     118: ldc           #133                // String Downgrade latest supported metadata to version {}. Latest supported version is {}.
     120: iload_2
     121: invokestatic  #120                // Method java/lang/Integer.valueOf:(I)Ljava/lang/Integer;
     124: bipush        7
     126: invokestatic  #120                // Method java/lang/Integer.valueOf:(I)Ljava/lang/Integer;
     129: invokeinterface #121,  4          // InterfaceMethod org/slf4j/Logger.info:(Ljava/lang/String;Ljava/lang/Object;Ljava/lang/Object;)V
     134: iload         4
     136: ireturn

  private java.util.Map<java.lang.String, org.apache.kafka.streams.processor.internals.InternalTopicConfig> computeRepartitionTopicMetadata(java.util.Map<java.lang.Integer, org.apache.kafka.streams.processor.internals.InternalTopologyBuilder$TopicsInfo>, org.apache.kafka.common.Cluster) throws org.apache.kafka.streams.errors.TaskAssignmentException;
    Code:
       0: new           #54                 // class java/util/HashMap
       3: dup
       4: invokespecial #55                 // Method java/util/HashMap."<init>":()V
       7: astore_3
       8: aload_1
       9: invokeinterface #56,  1           // InterfaceMethod java/util/Map.values:()Ljava/util/Collection;
      14: invokeinterface #57,  1           // InterfaceMethod java/util/Collection.iterator:()Ljava/util/Iterator;
      19: astore        4
      21: aload         4
      23: invokeinterface #58,  1           // InterfaceMethod java/util/Iterator.hasNext:()Z
      28: ifeq          197
      31: aload         4
      33: invokeinterface #59,  1           // InterfaceMethod java/util/Iterator.next:()Ljava/lang/Object;
      38: checkcast     #112                // class org/apache/kafka/streams/processor/internals/InternalTopologyBuilder$TopicsInfo
      41: astore        5
      43: aload         5
      45: getfield      #113                // Field org/apache/kafka/streams/processor/internals/InternalTopologyBuilder$TopicsInfo.sourceTopics:Ljava/util/Set;
      48: invokeinterface #76,  1           // InterfaceMethod java/util/Set.iterator:()Ljava/util/Iterator;
      53: astore        6
      55: aload         6
      57: invokeinterface #58,  1           // InterfaceMethod java/util/Iterator.hasNext:()Z
      62: ifeq          138
      65: aload         6
      67: invokeinterface #59,  1           // InterfaceMethod java/util/Iterator.next:()Ljava/lang/Object;
      72: checkcast     #63                 // class java/lang/String
      75: astore        7
      77: aload         5
      79: getfield      #134                // Field org/apache/kafka/streams/processor/internals/InternalTopologyBuilder$TopicsInfo.repartitionSourceTopics:Ljava/util/Map;
      82: aload         7
      84: invokeinterface #88,  2           // InterfaceMethod java/util/Map.containsKey:(Ljava/lang/Object;)Z
      89: ifne          135
      92: aload_2
      93: invokevirtual #135                // Method org/apache/kafka/common/Cluster.topics:()Ljava/util/Set;
      96: aload         7
      98: invokeinterface #136,  2          // InterfaceMethod java/util/Set.contains:(Ljava/lang/Object;)Z
     103: ifne          135
     106: aload_0
     107: getfield      #13                 // Field log:Lorg/slf4j/Logger;
     110: ldc           #137                // String Source topic {} is missing/unknown during rebalance, please make sure all source topics have been pre-created before starting the Streams application. Returning error {}
     112: aload         7
     114: getstatic     #106                // Field org/apache/kafka/streams/processor/internals/assignment/AssignorError.INCOMPLETE_SOURCE_TOPIC_METADATA:Lorg/apache/kafka/streams/processor/internals/assignment/AssignorError;
     117: invokevirtual #138                // Method org/apache/kafka/streams/processor/internals/assignment/AssignorError.name:()Ljava/lang/String;
     120: invokeinterface #139,  4          // InterfaceMethod org/slf4j/Logger.error:(Ljava/lang/String;Ljava/lang/Object;Ljava/lang/Object;)V
     125: new           #104                // class org/apache/kafka/streams/errors/TaskAssignmentException
     128: dup
     129: ldc           #140                // String Missing source topic during assignment.
     131: invokespecial #141                // Method org/apache/kafka/streams/errors/TaskAssignmentException."<init>":(Ljava/lang/String;)V
     134: athrow
     135: goto          55
     138: aload         5
     140: getfield      #134                // Field org/apache/kafka/streams/processor/internals/InternalTopologyBuilder$TopicsInfo.repartitionSourceTopics:Ljava/util/Map;
     143: invokeinterface #56,  1           // InterfaceMethod java/util/Map.values:()Ljava/util/Collection;
     148: invokeinterface #57,  1           // InterfaceMethod java/util/Collection.iterator:()Ljava/util/Iterator;
     153: astore        6
     155: aload         6
     157: invokeinterface #58,  1           // InterfaceMethod java/util/Iterator.hasNext:()Z
     162: ifeq          194
     165: aload         6
     167: invokeinterface #59,  1           // InterfaceMethod java/util/Iterator.next:()Ljava/lang/Object;
     172: checkcast     #142                // class org/apache/kafka/streams/processor/internals/InternalTopicConfig
     175: astore        7
     177: aload_3
     178: aload         7
     180: invokevirtual #143                // Method org/apache/kafka/streams/processor/internals/InternalTopicConfig.name:()Ljava/lang/String;
     183: aload         7
     185: invokeinterface #71,  3           // InterfaceMethod java/util/Map.put:(Ljava/lang/Object;Ljava/lang/Object;)Ljava/lang/Object;
     190: pop
     191: goto          155
     194: goto          21
     197: aload_3
     198: areturn

  private java.util.Map<org.apache.kafka.common.TopicPartition, org.apache.kafka.common.PartitionInfo> prepareRepartitionTopics(java.util.Map<java.lang.Integer, org.apache.kafka.streams.processor.internals.InternalTopologyBuilder$TopicsInfo>, org.apache.kafka.common.Cluster);
    Code:
       0: aload_0
       1: aload_1
       2: aload_2
       3: invokespecial #144                // Method computeRepartitionTopicMetadata:(Ljava/util/Map;Lorg/apache/kafka/common/Cluster;)Ljava/util/Map;
       6: astore_3
       7: aload_0
       8: aload_3
       9: aload_1
      10: aload_2
      11: invokespecial #145                // Method setRepartitionTopicMetadataNumberOfPartitions:(Ljava/util/Map;Ljava/util/Map;Lorg/apache/kafka/common/Cluster;)V
      14: aload_0
      15: aload_0
      16: getfield      #16                 // Field taskManager:Lorg/apache/kafka/streams/processor/internals/TaskManager;
      19: invokevirtual #101                // Method org/apache/kafka/streams/processor/internals/TaskManager.builder:()Lorg/apache/kafka/streams/processor/internals/InternalTopologyBuilder;
      22: invokevirtual #146                // Method org/apache/kafka/streams/processor/internals/InternalTopologyBuilder.copartitionGroups:()Ljava/util/Collection;
      25: aload_3
      26: aload_2
      27: invokespecial #147                // Method ensureCopartitioning:(Ljava/util/Collection;Ljava/util/Map;Lorg/apache/kafka/common/Cluster;)V
      30: aload_0
      31: getfield      #34                 // Field internalTopicManager:Lorg/apache/kafka/streams/processor/internals/InternalTopicManager;
      34: aload_3
      35: invokevirtual #148                // Method org/apache/kafka/streams/processor/internals/InternalTopicManager.makeReady:(Ljava/util/Map;)Ljava/util/Set;
      38: pop
      39: new           #54                 // class java/util/HashMap
      42: dup
      43: invokespecial #55                 // Method java/util/HashMap."<init>":()V
      46: astore        4
      48: aload_3
      49: invokeinterface #75,  1           // InterfaceMethod java/util/Map.entrySet:()Ljava/util/Set;
      54: invokeinterface #76,  1           // InterfaceMethod java/util/Set.iterator:()Ljava/util/Iterator;
      59: astore        5
      61: aload         5
      63: invokeinterface #58,  1           // InterfaceMethod java/util/Iterator.hasNext:()Z
      68: ifeq          181
      71: aload         5
      73: invokeinterface #59,  1           // InterfaceMethod java/util/Iterator.next:()Ljava/lang/Object;
      78: checkcast     #77                 // class java/util/Map$Entry
      81: astore        6
      83: aload         6
      85: invokeinterface #78,  1           // InterfaceMethod java/util/Map$Entry.getKey:()Ljava/lang/Object;
      90: checkcast     #63                 // class java/lang/String
      93: astore        7
      95: aload         6
      97: invokeinterface #79,  1           // InterfaceMethod java/util/Map$Entry.getValue:()Ljava/lang/Object;
     102: checkcast     #142                // class org/apache/kafka/streams/processor/internals/InternalTopicConfig
     105: invokevirtual #149                // Method org/apache/kafka/streams/processor/internals/InternalTopicConfig.numberOfPartitions:()Ljava/util/Optional;
     108: iconst_m1
     109: invokestatic  #120                // Method java/lang/Integer.valueOf:(I)Ljava/lang/Integer;
     112: invokevirtual #150                // Method java/util/Optional.orElse:(Ljava/lang/Object;)Ljava/lang/Object;
     115: checkcast     #151                // class java/lang/Integer
     118: invokevirtual #152                // Method java/lang/Integer.intValue:()I
     121: istore        8
     123: iconst_0
     124: istore        9
     126: iload         9
     128: iload         8
     130: if_icmpge     178
     133: aload         4
     135: new           #153                // class org/apache/kafka/common/TopicPartition
     138: dup
     139: aload         7
     141: iload         9
     143: invokespecial #154                // Method org/apache/kafka/common/TopicPartition."<init>":(Ljava/lang/String;I)V
     146: new           #155                // class org/apache/kafka/common/PartitionInfo
     149: dup
     150: aload         7
     152: iload         9
     154: aconst_null
     155: iconst_0
     156: anewarray     #156                // class org/apache/kafka/common/Node
     159: iconst_0
     160: anewarray     #156                // class org/apache/kafka/common/Node
     163: invokespecial #157                // Method org/apache/kafka/common/PartitionInfo."<init>":(Ljava/lang/String;ILorg/apache/kafka/common/Node;[Lorg/apache/kafka/common/Node;[Lorg/apache/kafka/common/Node;)V
     166: invokeinterface #71,  3           // InterfaceMethod java/util/Map.put:(Ljava/lang/Object;Ljava/lang/Object;)Ljava/lang/Object;
     171: pop
     172: iinc          9, 1
     175: goto          126
     178: goto          61
     181: aload         4
     183: areturn

  private void setRepartitionTopicMetadataNumberOfPartitions(java.util.Map<java.lang.String, org.apache.kafka.streams.processor.internals.InternalTopicConfig>, java.util.Map<java.lang.Integer, org.apache.kafka.streams.processor.internals.InternalTopologyBuilder$TopicsInfo>, org.apache.kafka.common.Cluster);
    Code:
       0: iconst_0
       1: istore        4
       3: aload_2
       4: invokeinterface #56,  1           // InterfaceMethod java/util/Map.values:()Ljava/util/Collection;
       9: invokeinterface #57,  1           // InterfaceMethod java/util/Collection.iterator:()Ljava/util/Iterator;
      14: astore        5
      16: aload         5
      18: invokeinterface #58,  1           // InterfaceMethod java/util/Iterator.hasNext:()Z
      23: ifeq          370
      26: aload         5
      28: invokeinterface #59,  1           // InterfaceMethod java/util/Iterator.next:()Ljava/lang/Object;
      33: checkcast     #112                // class org/apache/kafka/streams/processor/internals/InternalTopologyBuilder$TopicsInfo
      36: astore        6
      38: aload         6
      40: getfield      #134                // Field org/apache/kafka/streams/processor/internals/InternalTopologyBuilder$TopicsInfo.repartitionSourceTopics:Ljava/util/Map;
      43: invokeinterface #158,  1          // InterfaceMethod java/util/Map.keySet:()Ljava/util/Set;
      48: invokeinterface #76,  1           // InterfaceMethod java/util/Set.iterator:()Ljava/util/Iterator;
      53: astore        7
      55: aload         7
      57: invokeinterface #58,  1           // InterfaceMethod java/util/Iterator.hasNext:()Z
      62: ifeq          367
      65: aload         7
      67: invokeinterface #59,  1           // InterfaceMethod java/util/Iterator.next:()Ljava/lang/Object;
      72: checkcast     #63                 // class java/lang/String
      75: astore        8
      77: aload_1
      78: aload         8
      80: invokeinterface #91,  2           // InterfaceMethod java/util/Map.get:(Ljava/lang/Object;)Ljava/lang/Object;
      85: checkcast     #142                // class org/apache/kafka/streams/processor/internals/InternalTopicConfig
      88: invokevirtual #149                // Method org/apache/kafka/streams/processor/internals/InternalTopicConfig.numberOfPartitions:()Ljava/util/Optional;
      91: astore        9
      93: aconst_null
      94: astore        10
      96: aload         9
      98: invokevirtual #159                // Method java/util/Optional.isPresent:()Z
     101: ifne          364
     104: aload_2
     105: invokeinterface #56,  1           // InterfaceMethod java/util/Map.values:()Ljava/util/Collection;
     110: invokeinterface #57,  1           // InterfaceMethod java/util/Collection.iterator:()Ljava/util/Iterator;
     115: astore        11
     117: aload         11
     119: invokeinterface #58,  1           // InterfaceMethod java/util/Iterator.hasNext:()Z
     124: ifeq          334
     127: aload         11
     129: invokeinterface #59,  1           // InterfaceMethod java/util/Iterator.next:()Ljava/lang/Object;
     134: checkcast     #112                // class org/apache/kafka/streams/processor/internals/InternalTopologyBuilder$TopicsInfo
     137: astore        12
     139: aload         12
     141: getfield      #160                // Field org/apache/kafka/streams/processor/internals/InternalTopologyBuilder$TopicsInfo.sinkTopics:Ljava/util/Set;
     144: astore        13
     146: aload         13
     148: aload         8
     150: invokeinterface #136,  2          // InterfaceMethod java/util/Set.contains:(Ljava/lang/Object;)Z
     155: ifeq          331
     158: aload         12
     160: getfield      #113                // Field org/apache/kafka/streams/processor/internals/InternalTopologyBuilder$TopicsInfo.sourceTopics:Ljava/util/Set;
     163: invokeinterface #76,  1           // InterfaceMethod java/util/Set.iterator:()Ljava/util/Iterator;
     168: astore        14
     170: aload         14
     172: invokeinterface #58,  1           // InterfaceMethod java/util/Iterator.hasNext:()Z
     177: ifeq          331
     180: aload         14
     182: invokeinterface #59,  1           // InterfaceMethod java/util/Iterator.next:()Ljava/lang/Object;
     187: checkcast     #63                 // class java/lang/String
     190: astore        15
     192: aconst_null
     193: astore        16
     195: aload_1
     196: aload         15
     198: invokeinterface #88,  2           // InterfaceMethod java/util/Map.containsKey:(Ljava/lang/Object;)Z
     203: ifeq          251
     206: aload_1
     207: aload         15
     209: invokeinterface #91,  2           // InterfaceMethod java/util/Map.get:(Ljava/lang/Object;)Ljava/lang/Object;
     214: checkcast     #142                // class org/apache/kafka/streams/processor/internals/InternalTopicConfig
     217: invokevirtual #149                // Method org/apache/kafka/streams/processor/internals/InternalTopicConfig.numberOfPartitions:()Ljava/util/Optional;
     220: invokevirtual #159                // Method java/util/Optional.isPresent:()Z
     223: ifeq          301
     226: aload_1
     227: aload         15
     229: invokeinterface #91,  2           // InterfaceMethod java/util/Map.get:(Ljava/lang/Object;)Ljava/lang/Object;
     234: checkcast     #142                // class org/apache/kafka/streams/processor/internals/InternalTopicConfig
     237: invokevirtual #149                // Method org/apache/kafka/streams/processor/internals/InternalTopicConfig.numberOfPartitions:()Ljava/util/Optional;
     240: invokevirtual #161                // Method java/util/Optional.get:()Ljava/lang/Object;
     243: checkcast     #151                // class java/lang/Integer
     246: astore        16
     248: goto          301
     251: aload_3
     252: aload         15
     254: invokevirtual #162                // Method org/apache/kafka/common/Cluster.partitionCountForTopic:(Ljava/lang/String;)Ljava/lang/Integer;
     257: astore        17
     259: aload         17
     261: ifnonnull     297
     264: new           #122                // class java/lang/IllegalStateException
     267: dup
     268: new           #123                // class java/lang/StringBuilder
     271: dup
     272: invokespecial #124                // Method java/lang/StringBuilder."<init>":()V
     275: ldc           #163                // String No partition count found for source topic
     277: invokevirtual #126                // Method java/lang/StringBuilder.append:(Ljava/lang/String;)Ljava/lang/StringBuilder;
     280: aload         15
     282: invokevirtual #126                // Method java/lang/StringBuilder.append:(Ljava/lang/String;)Ljava/lang/StringBuilder;
     285: ldc           #164                // String , but it should have been.
     287: invokevirtual #126                // Method java/lang/StringBuilder.append:(Ljava/lang/String;)Ljava/lang/StringBuilder;
     290: invokevirtual #130                // Method java/lang/StringBuilder.toString:()Ljava/lang/String;
     293: invokespecial #131                // Method java/lang/IllegalStateException."<init>":(Ljava/lang/String;)V
     296: athrow
     297: aload         17
     299: astore        16
     301: aload         16
     303: ifnull        328
     306: aload         10
     308: ifnull        324
     311: aload         16
     313: invokevirtual #152                // Method java/lang/Integer.intValue:()I
     316: aload         10
     318: invokevirtual #152                // Method java/lang/Integer.intValue:()I
     321: if_icmple     328
     324: aload         16
     326: astore        10
     328: goto          170
     331: goto          117
     334: aload         10
     336: ifnonnull     345
     339: iconst_1
     340: istore        4
     342: goto          364
     345: aload_1
     346: aload         8
     348: invokeinterface #91,  2           // InterfaceMethod java/util/Map.get:(Ljava/lang/Object;)Ljava/lang/Object;
     353: checkcast     #142                // class org/apache/kafka/streams/processor/internals/InternalTopicConfig
     356: aload         10
     358: invokevirtual #152                // Method java/lang/Integer.intValue:()I
     361: invokevirtual #165                // Method org/apache/kafka/streams/processor/internals/InternalTopicConfig.setNumberOfPartitions:(I)V
     364: goto          55
     367: goto          16
     370: iload         4
     372: ifne          0
     375: return

  private void populateTasksForMaps(java.util.Map<org.apache.kafka.common.TopicPartition, org.apache.kafka.streams.processor.TaskId>, java.util.Map<java.lang.Integer, java.util.Set<org.apache.kafka.streams.processor.TaskId>>, java.util.Set<java.lang.String>, java.util.Map<org.apache.kafka.streams.processor.TaskId, java.util.Set<org.apache.kafka.common.TopicPartition>>, org.apache.kafka.common.Cluster);
    Code:
       0: new           #73                 // class java/util/HashSet
       3: dup
       4: invokespecial #74                 // Method java/util/HashSet."<init>":()V
       7: astore        6
       9: aload         4
      11: invokeinterface #75,  1           // InterfaceMethod java/util/Map.entrySet:()Ljava/util/Set;
      16: invokeinterface #76,  1           // InterfaceMethod java/util/Set.iterator:()Ljava/util/Iterator;
      21: astore        7
      23: aload         7
      25: invokeinterface #58,  1           // InterfaceMethod java/util/Iterator.hasNext:()Z
      30: ifeq          184
      33: aload         7
      35: invokeinterface #59,  1           // InterfaceMethod java/util/Iterator.next:()Ljava/lang/Object;
      40: checkcast     #77                 // class java/util/Map$Entry
      43: astore        8
      45: aload         8
      47: invokeinterface #78,  1           // InterfaceMethod java/util/Map$Entry.getKey:()Ljava/lang/Object;
      52: checkcast     #166                // class org/apache/kafka/streams/processor/TaskId
      55: astore        9
      57: aload         8
      59: invokeinterface #79,  1           // InterfaceMethod java/util/Map$Entry.getValue:()Ljava/lang/Object;
      64: checkcast     #167                // class java/util/Set
      67: astore        10
      69: aload         10
      71: invokeinterface #76,  1           // InterfaceMethod java/util/Set.iterator:()Ljava/util/Iterator;
      76: astore        11
      78: aload         11
      80: invokeinterface #58,  1           // InterfaceMethod java/util/Iterator.hasNext:()Z
      85: ifeq          141
      88: aload         11
      90: invokeinterface #59,  1           // InterfaceMethod java/util/Iterator.next:()Ljava/lang/Object;
      95: checkcast     #153                // class org/apache/kafka/common/TopicPartition
      98: astore        12
     100: aload_1
     101: aload         12
     103: aload         9
     105: invokeinterface #71,  3           // InterfaceMethod java/util/Map.put:(Ljava/lang/Object;Ljava/lang/Object;)Ljava/lang/Object;
     110: pop
     111: aload         6
     113: aload         12
     115: invokeinterface #136,  2          // InterfaceMethod java/util/Set.contains:(Ljava/lang/Object;)Z
     120: ifeq          138
     123: aload_0
     124: getfield      #13                 // Field log:Lorg/slf4j/Logger;
     127: ldc           #168                // String Partition {} is assigned to more than one tasks: {}
     129: aload         12
     131: aload         4
     133: invokeinterface #169,  4          // InterfaceMethod org/slf4j/Logger.warn:(Ljava/lang/String;Ljava/lang/Object;Ljava/lang/Object;)V
     138: goto          78
     141: aload         6
     143: aload         10
     145: invokeinterface #95,  2           // InterfaceMethod java/util/Set.addAll:(Ljava/util/Collection;)Z
     150: pop
     151: aload_2
     152: aload         9
     154: getfield      #170                // Field org/apache/kafka/streams/processor/TaskId.topicGroupId:I
     157: invokestatic  #120                // Method java/lang/Integer.valueOf:(I)Ljava/lang/Integer;
     160: invokedynamic #171,  0            // InvokeDynamic #1:apply:()Ljava/util/function/Function;
     165: invokeinterface #172,  3          // InterfaceMethod java/util/Map.computeIfAbsent:(Ljava/lang/Object;Ljava/util/function/Function;)Ljava/lang/Object;
     170: checkcast     #167                // class java/util/Set
     173: aload         9
     175: invokeinterface #173,  2          // InterfaceMethod java/util/Set.add:(Ljava/lang/Object;)Z
     180: pop
     181: goto          23
     184: aload_0
     185: aload_3
     186: aload         4
     188: aload         6
     190: aload         5
     192: invokespecial #174                // Method checkAllPartitions:(Ljava/util/Set;Ljava/util/Map;Ljava/util/Set;Lorg/apache/kafka/common/Cluster;)V
     195: return

  private void checkAllPartitions(java.util.Set<java.lang.String>, java.util.Map<org.apache.kafka.streams.processor.TaskId, java.util.Set<org.apache.kafka.common.TopicPartition>>, java.util.Set<org.apache.kafka.common.TopicPartition>, org.apache.kafka.common.Cluster);
    Code:
       0: aload_1
       1: invokeinterface #76,  1           // InterfaceMethod java/util/Set.iterator:()Ljava/util/Iterator;
       6: astore        5
       8: aload         5
      10: invokeinterface #58,  1           // InterfaceMethod java/util/Iterator.hasNext:()Z
      15: ifeq          146
      18: aload         5
      20: invokeinterface #59,  1           // InterfaceMethod java/util/Iterator.next:()Ljava/lang/Object;
      25: checkcast     #63                 // class java/lang/String
      28: astore        6
      30: aload         4
      32: aload         6
      34: invokevirtual #175                // Method org/apache/kafka/common/Cluster.partitionsForTopic:(Ljava/lang/String;)Ljava/util/List;
      37: astore        7
      39: aload         7
      41: invokeinterface #176,  1          // InterfaceMethod java/util/List.isEmpty:()Z
      46: ifeq          65
      49: aload_0
      50: getfield      #13                 // Field log:Lorg/slf4j/Logger;
      53: ldc           #177                // String No partitions found for topic {}
      55: aload         6
      57: invokeinterface #178,  3          // InterfaceMethod org/slf4j/Logger.warn:(Ljava/lang/String;Ljava/lang/Object;)V
      62: goto          143
      65: aload         7
      67: invokeinterface #179,  1          // InterfaceMethod java/util/List.iterator:()Ljava/util/Iterator;
      72: astore        8
      74: aload         8
      76: invokeinterface #58,  1           // InterfaceMethod java/util/Iterator.hasNext:()Z
      81: ifeq          143
      84: aload         8
      86: invokeinterface #59,  1           // InterfaceMethod java/util/Iterator.next:()Ljava/lang/Object;
      91: checkcast     #155                // class org/apache/kafka/common/PartitionInfo
      94: astore        9
      96: new           #153                // class org/apache/kafka/common/TopicPartition
      99: dup
     100: aload         9
     102: invokevirtual #180                // Method org/apache/kafka/common/PartitionInfo.topic:()Ljava/lang/String;
     105: aload         9
     107: invokevirtual #181                // Method org/apache/kafka/common/PartitionInfo.partition:()I
     110: invokespecial #154                // Method org/apache/kafka/common/TopicPartition."<init>":(Ljava/lang/String;I)V
     113: astore        10
     115: aload_3
     116: aload         10
     118: invokeinterface #136,  2          // InterfaceMethod java/util/Set.contains:(Ljava/lang/Object;)Z
     123: ifne          140
     126: aload_0
     127: getfield      #13                 // Field log:Lorg/slf4j/Logger;
     130: ldc           #182                // String Partition {} is not assigned to any tasks: {} Possible causes of a partition not getting assigned is that another topic defined in the topology has not been created when starting your streams application, resulting in no tasks created for this topology at all.
     132: aload         10
     134: aload_2
     135: invokeinterface #169,  4          // InterfaceMethod org/slf4j/Logger.warn:(Ljava/lang/String;Ljava/lang/Object;Ljava/lang/Object;)V
     140: goto          74
     143: goto          8
     146: return

  private java.util.Set<java.lang.String> prepareChangelogTopics(java.util.Map<java.lang.Integer, org.apache.kafka.streams.processor.internals.InternalTopologyBuilder$TopicsInfo>, java.util.Map<java.lang.Integer, java.util.Set<org.apache.kafka.streams.processor.TaskId>>, java.util.Map<org.apache.kafka.streams.processor.TaskId, java.util.Set<org.apache.kafka.common.TopicPartition>>, java.util.Set<java.lang.String>);
    Code:
       0: new           #54                 // class java/util/HashMap
       3: dup
       4: invokespecial #55                 // Method java/util/HashMap."<init>":()V
       7: astore        5
       9: aload_1
      10: invokeinterface #75,  1           // InterfaceMethod java/util/Map.entrySet:()Ljava/util/Set;
      15: invokeinterface #76,  1           // InterfaceMethod java/util/Set.iterator:()Ljava/util/Iterator;
      20: astore        6
      22: aload         6
      24: invokeinterface #58,  1           // InterfaceMethod java/util/Iterator.hasNext:()Z
      29: ifeq          338
      32: aload         6
      34: invokeinterface #59,  1           // InterfaceMethod java/util/Iterator.next:()Ljava/lang/Object;
      39: checkcast     #77                 // class java/util/Map$Entry
      42: astore        7
      44: aload         7
      46: invokeinterface #78,  1           // InterfaceMethod java/util/Map$Entry.getKey:()Ljava/lang/Object;
      51: checkcast     #151                // class java/lang/Integer
      54: invokevirtual #152                // Method java/lang/Integer.intValue:()I
      57: istore        8
      59: aload         7
      61: invokeinterface #79,  1           // InterfaceMethod java/util/Map$Entry.getValue:()Ljava/lang/Object;
      66: checkcast     #112                // class org/apache/kafka/streams/processor/internals/InternalTopologyBuilder$TopicsInfo
      69: astore        9
      71: aload_2
      72: iload         8
      74: invokestatic  #120                // Method java/lang/Integer.valueOf:(I)Ljava/lang/Integer;
      77: invokeinterface #91,  2           // InterfaceMethod java/util/Map.get:(Ljava/lang/Object;)Ljava/lang/Object;
      82: checkcast     #167                // class java/util/Set
      85: astore        10
      87: aload         10
      89: ifnonnull     111
      92: aload_0
      93: getfield      #13                 // Field log:Lorg/slf4j/Logger;
      96: ldc           #183                // String No tasks found for topic group {}
      98: iload         8
     100: invokestatic  #120                // Method java/lang/Integer.valueOf:(I)Ljava/lang/Integer;
     103: invokeinterface #100,  3          // InterfaceMethod org/slf4j/Logger.debug:(Ljava/lang/String;Ljava/lang/Object;)V
     108: goto          22
     111: aload         9
     113: getfield      #184                // Field org/apache/kafka/streams/processor/internals/InternalTopologyBuilder$TopicsInfo.stateChangelogTopics:Ljava/util/Map;
     116: invokeinterface #185,  1          // InterfaceMethod java/util/Map.isEmpty:()Z
     121: ifeq          127
     124: goto          22
     127: aload         10
     129: invokeinterface #76,  1           // InterfaceMethod java/util/Set.iterator:()Ljava/util/Iterator;
     134: astore        11
     136: aload         11
     138: invokeinterface #58,  1           // InterfaceMethod java/util/Iterator.hasNext:()Z
     143: ifeq          205
     146: aload         11
     148: invokeinterface #59,  1           // InterfaceMethod java/util/Iterator.next:()Ljava/lang/Object;
     153: checkcast     #166                // class org/apache/kafka/streams/processor/TaskId
     156: astore        12
     158: aload_3
     159: aload         12
     161: aload         9
     163: getfield      #184                // Field org/apache/kafka/streams/processor/internals/InternalTopologyBuilder$TopicsInfo.stateChangelogTopics:Ljava/util/Map;
     166: invokeinterface #158,  1          // InterfaceMethod java/util/Map.keySet:()Ljava/util/Set;
     171: invokeinterface #186,  1          // InterfaceMethod java/util/Set.stream:()Ljava/util/stream/Stream;
     176: aload         12
     178: invokedynamic #187,  0            // InvokeDynamic #2:apply:(Lorg/apache/kafka/streams/processor/TaskId;)Ljava/util/function/Function;
     183: invokeinterface #188,  2          // InterfaceMethod java/util/stream/Stream.map:(Ljava/util/function/Function;)Ljava/util/stream/Stream;
     188: invokestatic  #189                // Method java/util/stream/Collectors.toSet:()Ljava/util/stream/Collector;
     191: invokeinterface #190,  2          // InterfaceMethod java/util/stream/Stream.collect:(Ljava/util/stream/Collector;)Ljava/lang/Object;
     196: invokeinterface #71,  3           // InterfaceMethod java/util/Map.put:(Ljava/lang/Object;Ljava/lang/Object;)Ljava/lang/Object;
     201: pop
     202: goto          136
     205: aload         9
     207: invokevirtual #191                // Method org/apache/kafka/streams/processor/internals/InternalTopologyBuilder$TopicsInfo.nonSourceChangelogTopics:()Ljava/util/Set;
     210: invokeinterface #76,  1           // InterfaceMethod java/util/Set.iterator:()Ljava/util/Iterator;
     215: astore        11
     217: aload         11
     219: invokeinterface #58,  1           // InterfaceMethod java/util/Iterator.hasNext:()Z
     224: ifeq          322
     227: aload         11
     229: invokeinterface #59,  1           // InterfaceMethod java/util/Iterator.next:()Ljava/lang/Object;
     234: checkcast     #142                // class org/apache/kafka/streams/processor/internals/InternalTopicConfig
     237: astore        12
     239: iconst_m1
     240: istore        13
     242: aload         10
     244: invokeinterface #76,  1           // InterfaceMethod java/util/Set.iterator:()Ljava/util/Iterator;
     249: astore        14
     251: aload         14
     253: invokeinterface #58,  1           // InterfaceMethod java/util/Iterator.hasNext:()Z
     258: ifeq          297
     261: aload         14
     263: invokeinterface #59,  1           // InterfaceMethod java/util/Iterator.next:()Ljava/lang/Object;
     268: checkcast     #166                // class org/apache/kafka/streams/processor/TaskId
     271: astore        15
     273: iload         13
     275: aload         15
     277: getfield      #192                // Field org/apache/kafka/streams/processor/TaskId.partition:I
     280: iconst_1
     281: iadd
     282: if_icmpge     294
     285: aload         15
     287: getfield      #192                // Field org/apache/kafka/streams/processor/TaskId.partition:I
     290: iconst_1
     291: iadd
     292: istore        13
     294: goto          251
     297: aload         12
     299: iload         13
     301: invokevirtual #165                // Method org/apache/kafka/streams/processor/internals/InternalTopicConfig.setNumberOfPartitions:(I)V
     304: aload         5
     306: aload         12
     308: invokevirtual #143                // Method org/apache/kafka/streams/processor/internals/InternalTopicConfig.name:()Ljava/lang/String;
     311: aload         12
     313: invokeinterface #71,  3           // InterfaceMethod java/util/Map.put:(Ljava/lang/Object;Ljava/lang/Object;)Ljava/lang/Object;
     318: pop
     319: goto          217
     322: aload         4
     324: aload         9
     326: invokevirtual #193                // Method org/apache/kafka/streams/processor/internals/InternalTopologyBuilder$TopicsInfo.sourceTopicChangelogs:()Ljava/util/Set;
     329: invokeinterface #95,  2           // InterfaceMethod java/util/Set.addAll:(Ljava/util/Collection;)Z
     334: pop
     335: goto          22
     338: aload_0
     339: getfield      #34                 // Field internalTopicManager:Lorg/apache/kafka/streams/processor/internals/InternalTopicManager;
     342: aload         5
     344: invokevirtual #148                // Method org/apache/kafka/streams/processor/internals/InternalTopicManager.makeReady:(Ljava/util/Map;)Ljava/util/Set;
     347: astore        6
     349: aload_0
     350: getfield      #13                 // Field log:Lorg/slf4j/Logger;
     353: ldc           #194                // String Created state changelog topics {} from the parsed topology.
     355: aload         5
     357: invokeinterface #56,  1           // InterfaceMethod java/util/Map.values:()Ljava/util/Collection;
     362: invokeinterface #100,  3          // InterfaceMethod org/slf4j/Logger.debug:(Ljava/lang/String;Ljava/lang/Object;)V
     367: aload         6
     369: areturn

  private boolean assignTasksToClients(org.apache.kafka.common.Cluster, java.util.Set<java.lang.String>, java.util.Map<java.lang.Integer, org.apache.kafka.streams.processor.internals.InternalTopologyBuilder$TopicsInfo>, java.util.Map<java.util.UUID, org.apache.kafka.streams.processor.internals.StreamsPartitionAssignor$ClientMetadata>, java.util.Map<org.apache.kafka.streams.processor.TaskId, java.util.Set<org.apache.kafka.common.TopicPartition>>, java.util.Set<org.apache.kafka.streams.processor.TaskId>);
    Code:
       0: aload         6
       2: invokeinterface #195,  1          // InterfaceMethod java/util/Set.isEmpty:()Z
       7: ifne          20
      10: new           #196                // class java/lang/IllegalArgumentException
      13: dup
      14: ldc           #197                // String The stateful tasks should not be populated before assigning tasks to clients
      16: invokespecial #198                // Method java/lang/IllegalArgumentException."<init>":(Ljava/lang/String;)V
      19: athrow
      20: new           #54                 // class java/util/HashMap
      23: dup
      24: invokespecial #55                 // Method java/util/HashMap."<init>":()V
      27: astore        7
      29: new           #54                 // class java/util/HashMap
      32: dup
      33: invokespecial #55                 // Method java/util/HashMap."<init>":()V
      36: astore        8
      38: aload_0
      39: aload         7
      41: aload         8
      43: aload_2
      44: aload         5
      46: aload_1
      47: invokespecial #199                // Method populateTasksForMaps:(Ljava/util/Map;Ljava/util/Map;Ljava/util/Set;Ljava/util/Map;Lorg/apache/kafka/common/Cluster;)V
      50: new           #54                 // class java/util/HashMap
      53: dup
      54: invokespecial #55                 // Method java/util/HashMap."<init>":()V
      57: astore        9
      59: new           #73                 // class java/util/HashSet
      62: dup
      63: invokespecial #74                 // Method java/util/HashSet."<init>":()V
      66: astore        10
      68: aload_0
      69: aload_3
      70: aload         8
      72: aload         9
      74: aload         10
      76: invokespecial #200                // Method prepareChangelogTopics:(Ljava/util/Map;Ljava/util/Map;Ljava/util/Map;Ljava/util/Set;)Ljava/util/Set;
      79: astore        11
      81: new           #54                 // class java/util/HashMap
      84: dup
      85: invokespecial #55                 // Method java/util/HashMap."<init>":()V
      88: astore        12
      90: aload_0
      91: aload         12
      93: aload         4
      95: aload         7
      97: aload         9
      99: aload         11
     101: aload         10
     103: invokespecial #201                // Method populateClientStatesMap:(Ljava/util/Map;Ljava/util/Map;Ljava/util/Map;Ljava/util/Map;Ljava/util/Set;Ljava/util/Set;)Z
     106: istore        13
     108: aload         5
     110: invokeinterface #158,  1          // InterfaceMethod java/util/Map.keySet:()Ljava/util/Set;
     115: astore        14
     117: aload         6
     119: aload         9
     121: invokeinterface #158,  1          // InterfaceMethod java/util/Map.keySet:()Ljava/util/Set;
     126: invokeinterface #95,  2           // InterfaceMethod java/util/Set.addAll:(Ljava/util/Collection;)Z
     131: pop
     132: aload_0
     133: getfield      #13                 // Field log:Lorg/slf4j/Logger;
     136: ldc           #202                // String Assigning tasks {} to clients {} with number of replicas {}
     138: iconst_3
     139: anewarray     #203                // class java/lang/Object
     142: dup
     143: iconst_0
     144: aload         14
     146: aastore
     147: dup
     148: iconst_1
     149: aload         12
     151: aastore
     152: dup
     153: iconst_2
     154: aload_0
     155: invokevirtual #204                // Method numStandbyReplicas:()I
     158: invokestatic  #120                // Method java/lang/Integer.valueOf:(I)Ljava/lang/Integer;
     161: aastore
     162: invokeinterface #205,  3          // InterfaceMethod org/slf4j/Logger.debug:(Ljava/lang/String;[Ljava/lang/Object;)V
     167: aload_0
     168: iload         13
     170: invokespecial #206                // Method createTaskAssignor:(Z)Lorg/apache/kafka/streams/processor/internals/assignment/TaskAssignor;
     173: astore        15
     175: aload         15
     177: aload         12
     179: aload         14
     181: aload         6
     183: aload_0
     184: getfield      #26                 // Field assignmentConfigs:Lorg/apache/kafka/streams/processor/internals/assignment/AssignorConfiguration$AssignmentConfigs;
     187: invokeinterface #207,  5          // InterfaceMethod org/apache/kafka/streams/processor/internals/assignment/TaskAssignor.assign:(Ljava/util/Map;Ljava/util/Set;Ljava/util/Set;Lorg/apache/kafka/streams/processor/internals/assignment/AssignorConfiguration$AssignmentConfigs;)Z
     192: istore        16
     194: aload_0
     195: getfield      #13                 // Field log:Lorg/slf4j/Logger;
     198: ldc           #208                // String Assigned tasks to clients as {}{}.
     200: getstatic     #209                // Field org/apache/kafka/common/utils/Utils.NL:Ljava/lang/String;
     203: aload         12
     205: invokeinterface #75,  1           // InterfaceMethod java/util/Map.entrySet:()Ljava/util/Set;
     210: invokeinterface #186,  1          // InterfaceMethod java/util/Set.stream:()Ljava/util/stream/Stream;
     215: invokedynamic #210,  0            // InvokeDynamic #3:apply:()Ljava/util/function/Function;
     220: invokeinterface #188,  2          // InterfaceMethod java/util/stream/Stream.map:(Ljava/util/function/Function;)Ljava/util/stream/Stream;
     225: getstatic     #209                // Field org/apache/kafka/common/utils/Utils.NL:Ljava/lang/String;
     228: invokestatic  #211                // Method java/util/stream/Collectors.joining:(Ljava/lang/CharSequence;)Ljava/util/stream/Collector;
     231: invokeinterface #190,  2          // InterfaceMethod java/util/stream/Stream.collect:(Ljava/util/stream/Collector;)Ljava/lang/Object;
     236: invokeinterface #121,  4          // InterfaceMethod org/slf4j/Logger.info:(Ljava/lang/String;Ljava/lang/Object;Ljava/lang/Object;)V
     241: iload         16
     243: ireturn

  private org.apache.kafka.streams.processor.internals.assignment.TaskAssignor createTaskAssignor(boolean);
    Code:
       0: aload_0
       1: getfield      #40                 // Field taskAssignorSupplier:Ljava/util/function/Supplier;
       4: invokeinterface #212,  1          // InterfaceMethod java/util/function/Supplier.get:()Ljava/lang/Object;
       9: checkcast     #213                // class org/apache/kafka/streams/processor/internals/assignment/TaskAssignor
      12: astore_2
      13: aload_2
      14: instanceof    #214                // class org/apache/kafka/streams/processor/internals/assignment/StickyTaskAssignor
      17: ifeq          22
      20: aload_2
      21: areturn
      22: iload_1
      23: ifeq          28
      26: aload_2
      27: areturn
      28: aload_0
      29: getfield      #13                 // Field log:Lorg/slf4j/Logger;
      32: ldc           #215                // String Failed to fetch end offsets for changelogs, will return previous assignment to clients and trigger another rebalance to retry.
      34: invokeinterface #216,  2          // InterfaceMethod org/slf4j/Logger.info:(Ljava/lang/String;)V
      39: new           #217                // class org/apache/kafka/streams/processor/internals/assignment/FallbackPriorTaskAssignor
      42: dup
      43: invokespecial #218                // Method org/apache/kafka/streams/processor/internals/assignment/FallbackPriorTaskAssignor."<init>":()V
      46: areturn

  private boolean populateClientStatesMap(java.util.Map<java.util.UUID, org.apache.kafka.streams.processor.internals.assignment.ClientState>, java.util.Map<java.util.UUID, org.apache.kafka.streams.processor.internals.StreamsPartitionAssignor$ClientMetadata>, java.util.Map<org.apache.kafka.common.TopicPartition, org.apache.kafka.streams.processor.TaskId>, java.util.Map<org.apache.kafka.streams.processor.TaskId, java.util.Set<org.apache.kafka.common.TopicPartition>>, java.util.Set<java.lang.String>, java.util.Set<java.lang.String>);
    Code:
       0: aload         4
       2: invokeinterface #56,  1           // InterfaceMethod java/util/Map.values:()Ljava/util/Collection;
       7: invokeinterface #219,  1          // InterfaceMethod java/util/Collection.stream:()Ljava/util/stream/Stream;
      12: invokedynamic #220,  0            // InvokeDynamic #4:apply:()Ljava/util/function/Function;
      17: invokeinterface #221,  2          // InterfaceMethod java/util/stream/Stream.flatMap:(Ljava/util/function/Function;)Ljava/util/stream/Stream;
      22: invokestatic  #222                // Method java/util/stream/Collectors.toList:()Ljava/util/stream/Collector;
      25: invokeinterface #190,  2          // InterfaceMethod java/util/stream/Stream.collect:(Ljava/util/stream/Collector;)Ljava/lang/Object;
      30: checkcast     #223                // class java/util/Collection
      33: astore        9
      35: new           #73                 // class java/util/HashSet
      38: dup
      39: invokespecial #74                 // Method java/util/HashSet."<init>":()V
      42: astore        10
      44: new           #73                 // class java/util/HashSet
      47: dup
      48: invokespecial #74                 // Method java/util/HashSet."<init>":()V
      51: astore        11
      53: new           #73                 // class java/util/HashSet
      56: dup
      57: invokespecial #74                 // Method java/util/HashSet."<init>":()V
      60: astore        12
      62: aload         9
      64: invokeinterface #57,  1           // InterfaceMethod java/util/Collection.iterator:()Ljava/util/Iterator;
      69: astore        13
      71: aload         13
      73: invokeinterface #58,  1           // InterfaceMethod java/util/Iterator.hasNext:()Z
      78: ifeq          162
      81: aload         13
      83: invokeinterface #59,  1           // InterfaceMethod java/util/Iterator.next:()Ljava/lang/Object;
      88: checkcast     #153                // class org/apache/kafka/common/TopicPartition
      91: astore        14
      93: aload         5
      95: aload         14
      97: invokevirtual #224                // Method org/apache/kafka/common/TopicPartition.topic:()Ljava/lang/String;
     100: invokeinterface #136,  2          // InterfaceMethod java/util/Set.contains:(Ljava/lang/Object;)Z
     105: ifeq          121
     108: aload         12
     110: aload         14
     112: invokeinterface #173,  2          // InterfaceMethod java/util/Set.add:(Ljava/lang/Object;)Z
     117: pop
     118: goto          159
     121: aload         6
     123: aload         14
     125: invokevirtual #224                // Method org/apache/kafka/common/TopicPartition.topic:()Ljava/lang/String;
     128: invokeinterface #136,  2          // InterfaceMethod java/util/Set.contains:(Ljava/lang/Object;)Z
     133: ifeq          149
     136: aload         11
     138: aload         14
     140: invokeinterface #173,  2          // InterfaceMethod java/util/Set.add:(Ljava/lang/Object;)Z
     145: pop
     146: goto          159
     149: aload         10
     151: aload         14
     153: invokeinterface #173,  2          // InterfaceMethod java/util/Set.add:(Ljava/lang/Object;)Z
     158: pop
     159: goto          71
     162: aload         10
     164: aload_0
     165: getfield      #32                 // Field adminClient:Lorg/apache/kafka/clients/admin/Admin;
     168: invokestatic  #225                // Method org/apache/kafka/streams/processor/internals/ClientUtils.fetchEndOffsetsFuture:(Ljava/util/Collection;Lorg/apache/kafka/clients/admin/Admin;)Lorg/apache/kafka/common/KafkaFuture;
     171: astore        13
     173: aload         11
     175: aload_0
     176: getfield      #16                 // Field taskManager:Lorg/apache/kafka/streams/processor/internals/TaskManager;
     179: invokevirtual #226                // Method org/apache/kafka/streams/processor/internals/TaskManager.mainConsumer:()Lorg/apache/kafka/clients/consumer/Consumer;
     182: invokestatic  #227                // Method org/apache/kafka/streams/processor/internals/ClientUtils.fetchCommittedOffsets:(Ljava/util/Set;Lorg/apache/kafka/clients/consumer/Consumer;)Ljava/util/Map;
     185: astore        14
     187: aload         13
     189: invokestatic  #228                // Method org/apache/kafka/streams/processor/internals/ClientUtils.getEndOffsets:(Lorg/apache/kafka/common/KafkaFuture;)Ljava/util/Map;
     192: astore        15
     194: aload_0
     195: aload         4
     197: aload         15
     199: aload         14
     201: aload         12
     203: invokespecial #229                // Method computeEndOffsetSumsByTask:(Ljava/util/Map;Ljava/util/Map;Ljava/util/Map;Ljava/util/Collection;)Ljava/util/Map;
     206: astore        8
     208: iconst_1
     209: istore        7
     211: goto          254
     214: astore        9
     216: aload         4
     218: invokeinterface #158,  1          // InterfaceMethod java/util/Map.keySet:()Ljava/util/Set;
     223: invokeinterface #186,  1          // InterfaceMethod java/util/Set.stream:()Ljava/util/stream/Stream;
     228: invokedynamic #232,  0            // InvokeDynamic #5:apply:()Ljava/util/function/Function;
     233: invokedynamic #233,  0            // InvokeDynamic #6:apply:()Ljava/util/function/Function;
     238: invokestatic  #234                // Method java/util/stream/Collectors.toMap:(Ljava/util/function/Function;Ljava/util/function/Function;)Ljava/util/stream/Collector;
     241: invokeinterface #190,  2          // InterfaceMethod java/util/stream/Stream.collect:(Ljava/util/stream/Collector;)Ljava/lang/Object;
     246: checkcast     #235                // class java/util/Map
     249: astore        8
     251: iconst_0
     252: istore        7
     254: aload_2
     255: invokeinterface #75,  1           // InterfaceMethod java/util/Map.entrySet:()Ljava/util/Set;
     260: invokeinterface #76,  1           // InterfaceMethod java/util/Set.iterator:()Ljava/util/Iterator;
     265: astore        9
     267: aload         9
     269: invokeinterface #58,  1           // InterfaceMethod java/util/Iterator.hasNext:()Z
     274: ifeq          345
     277: aload         9
     279: invokeinterface #59,  1           // InterfaceMethod java/util/Iterator.next:()Ljava/lang/Object;
     284: checkcast     #77                 // class java/util/Map$Entry
     287: astore        10
     289: aload         10
     291: invokeinterface #78,  1           // InterfaceMethod java/util/Map$Entry.getKey:()Ljava/lang/Object;
     296: checkcast     #236                // class java/util/UUID
     299: astore        11
     301: aload         10
     303: invokeinterface #79,  1           // InterfaceMethod java/util/Map$Entry.getValue:()Ljava/lang/Object;
     308: checkcast     #60                 // class org/apache/kafka/streams/processor/internals/StreamsPartitionAssignor$ClientMetadata
     311: invokestatic  #237                // Method org/apache/kafka/streams/processor/internals/StreamsPartitionAssignor$ClientMetadata.access$100:(Lorg/apache/kafka/streams/processor/internals/StreamsPartitionAssignor$ClientMetadata;)Lorg/apache/kafka/streams/processor/internals/assignment/ClientState;
     314: astore        12
     316: aload         12
     318: aload_3
     319: invokevirtual #238                // Method org/apache/kafka/streams/processor/internals/assignment/ClientState.initializePrevTasks:(Ljava/util/Map;)V
     322: aload         12
     324: aload         11
     326: aload         8
     328: invokevirtual #239                // Method org/apache/kafka/streams/processor/internals/assignment/ClientState.computeTaskLags:(Ljava/util/UUID;Ljava/util/Map;)V
     331: aload_1
     332: aload         11
     334: aload         12
     336: invokeinterface #71,  3           // InterfaceMethod java/util/Map.put:(Ljava/lang/Object;Ljava/lang/Object;)Ljava/lang/Object;
     341: pop
     342: goto          267
     345: iload         7
     347: ireturn
    Exception table:
       from    to  target type
           0   211   214   Class org/apache/kafka/streams/errors/StreamsException
           0   211   214   Class org/apache/kafka/common/errors/TimeoutException

  private java.util.Map<org.apache.kafka.streams.processor.TaskId, java.lang.Long> computeEndOffsetSumsByTask(java.util.Map<org.apache.kafka.streams.processor.TaskId, java.util.Set<org.apache.kafka.common.TopicPartition>>, java.util.Map<org.apache.kafka.common.TopicPartition, org.apache.kafka.clients.admin.ListOffsetsResult$ListOffsetsResultInfo>, java.util.Map<org.apache.kafka.common.TopicPartition, java.lang.Long>, java.util.Collection<org.apache.kafka.common.TopicPartition>);
    Code:
       0: new           #54                 // class java/util/HashMap
       3: dup
       4: invokespecial #55                 // Method java/util/HashMap."<init>":()V
       7: astore        5
       9: aload_1
      10: invokeinterface #75,  1           // InterfaceMethod java/util/Map.entrySet:()Ljava/util/Set;
      15: invokeinterface #76,  1           // InterfaceMethod java/util/Set.iterator:()Ljava/util/Iterator;
      20: astore        6
      22: aload         6
      24: invokeinterface #58,  1           // InterfaceMethod java/util/Iterator.hasNext:()Z
      29: ifeq          301
      32: aload         6
      34: invokeinterface #59,  1           // InterfaceMethod java/util/Iterator.next:()Ljava/lang/Object;
      39: checkcast     #77                 // class java/util/Map$Entry
      42: astore        7
      44: aload         7
      46: invokeinterface #78,  1           // InterfaceMethod java/util/Map$Entry.getKey:()Ljava/lang/Object;
      51: checkcast     #166                // class org/apache/kafka/streams/processor/TaskId
      54: astore        8
      56: aload         7
      58: invokeinterface #79,  1           // InterfaceMethod java/util/Map$Entry.getValue:()Ljava/lang/Object;
      63: checkcast     #167                // class java/util/Set
      66: astore        9
      68: aload         5
      70: aload         8
      72: lconst_0
      73: invokestatic  #240                // Method java/lang/Long.valueOf:(J)Ljava/lang/Long;
      76: invokeinterface #71,  3           // InterfaceMethod java/util/Map.put:(Ljava/lang/Object;Ljava/lang/Object;)Ljava/lang/Object;
      81: pop
      82: aload         9
      84: invokeinterface #76,  1           // InterfaceMethod java/util/Set.iterator:()Ljava/util/Iterator;
      89: astore        10
      91: aload         10
      93: invokeinterface #58,  1           // InterfaceMethod java/util/Iterator.hasNext:()Z
      98: ifeq          298
     101: aload         10
     103: invokeinterface #59,  1           // InterfaceMethod java/util/Iterator.next:()Ljava/lang/Object;
     108: checkcast     #153                // class org/apache/kafka/common/TopicPartition
     111: astore        11
     113: aload         4
     115: aload         11
     117: invokeinterface #241,  2          // InterfaceMethod java/util/Collection.contains:(Ljava/lang/Object;)Z
     122: ifeq          131
     125: lconst_0
     126: lstore        12
     128: goto          234
     131: aload_3
     132: aload         11
     134: invokeinterface #88,  2           // InterfaceMethod java/util/Map.containsKey:(Ljava/lang/Object;)Z
     139: ifeq          161
     142: aload_3
     143: aload         11
     145: invokeinterface #91,  2           // InterfaceMethod java/util/Map.get:(Ljava/lang/Object;)Ljava/lang/Object;
     150: checkcast     #242                // class java/lang/Long
     153: invokevirtual #243                // Method java/lang/Long.longValue:()J
     156: lstore        12
     158: goto          234
     161: aload_2
     162: aload         11
     164: invokeinterface #88,  2           // InterfaceMethod java/util/Map.containsKey:(Ljava/lang/Object;)Z
     169: ifeq          191
     172: aload_2
     173: aload         11
     175: invokeinterface #91,  2           // InterfaceMethod java/util/Map.get:(Ljava/lang/Object;)Ljava/lang/Object;
     180: checkcast     #244                // class org/apache/kafka/clients/admin/ListOffsetsResult$ListOffsetsResultInfo
     183: invokevirtual #245                // Method org/apache/kafka/clients/admin/ListOffsetsResult$ListOffsetsResultInfo.offset:()J
     186: lstore        12
     188: goto          234
     191: aload_0
     192: getfield      #13                 // Field log:Lorg/slf4j/Logger;
     195: ldc           #246                // String Fetched offsets did not contain the changelog {} of task {}
     197: aload         11
     199: aload         8
     201: invokeinterface #247,  4          // InterfaceMethod org/slf4j/Logger.debug:(Ljava/lang/String;Ljava/lang/Object;Ljava/lang/Object;)V
     206: new           #122                // class java/lang/IllegalStateException
     209: dup
     210: new           #123                // class java/lang/StringBuilder
     213: dup
     214: invokespecial #124                // Method java/lang/StringBuilder."<init>":()V
     217: ldc           #248                // String Could not get end offset for
     219: invokevirtual #126                // Method java/lang/StringBuilder.append:(Ljava/lang/String;)Ljava/lang/StringBuilder;
     222: aload         11
     224: invokevirtual #249                // Method java/lang/StringBuilder.append:(Ljava/lang/Object;)Ljava/lang/StringBuilder;
     227: invokevirtual #130                // Method java/lang/StringBuilder.toString:()Ljava/lang/String;
     230: invokespecial #131                // Method java/lang/IllegalStateException."<init>":(Ljava/lang/String;)V
     233: athrow
     234: aload         5
     236: aload         8
     238: invokeinterface #91,  2           // InterfaceMethod java/util/Map.get:(Ljava/lang/Object;)Ljava/lang/Object;
     243: checkcast     #242                // class java/lang/Long
     246: invokevirtual #243                // Method java/lang/Long.longValue:()J
     249: lload         12
     251: ladd
     252: lstore        14
     254: lload         14
     256: lconst_0
     257: lcmp
     258: ifge          280
     261: aload         5
     263: aload         8
     265: ldc2_w        #250                // long 9223372036854775807l
     268: invokestatic  #240                // Method java/lang/Long.valueOf:(J)Ljava/lang/Long;
     271: invokeinterface #71,  3           // InterfaceMethod java/util/Map.put:(Ljava/lang/Object;Ljava/lang/Object;)Ljava/lang/Object;
     276: pop
     277: goto          298
     280: aload         5
     282: aload         8
     284: lload         14
     286: invokestatic  #240                // Method java/lang/Long.valueOf:(J)Ljava/lang/Long;
     289: invokeinterface #71,  3           // InterfaceMethod java/util/Map.put:(Ljava/lang/Object;Ljava/lang/Object;)Ljava/lang/Object;
     294: pop
     295: goto          91
     298: goto          22
     301: aload         5
     303: areturn

  private void populatePartitionsByHostMaps(java.util.Map<org.apache.kafka.streams.state.HostInfo, java.util.Set<org.apache.kafka.common.TopicPartition>>, java.util.Map<org.apache.kafka.streams.state.HostInfo, java.util.Set<org.apache.kafka.common.TopicPartition>>, java.util.Map<org.apache.kafka.streams.processor.TaskId, java.util.Set<org.apache.kafka.common.TopicPartition>>, java.util.Map<java.util.UUID, org.apache.kafka.streams.processor.internals.StreamsPartitionAssignor$ClientMetadata>);
    Code:
       0: aload         4
       2: invokeinterface #75,  1           // InterfaceMethod java/util/Map.entrySet:()Ljava/util/Set;
       7: invokeinterface #76,  1           // InterfaceMethod java/util/Set.iterator:()Ljava/util/Iterator;
      12: astore        5
      14: aload         5
      16: invokeinterface #58,  1           // InterfaceMethod java/util/Iterator.hasNext:()Z
      21: ifeq          226
      24: aload         5
      26: invokeinterface #59,  1           // InterfaceMethod java/util/Iterator.next:()Ljava/lang/Object;
      31: checkcast     #77                 // class java/util/Map$Entry
      34: astore        6
      36: aload         6
      38: invokeinterface #79,  1           // InterfaceMethod java/util/Map$Entry.getValue:()Ljava/lang/Object;
      43: checkcast     #60                 // class org/apache/kafka/streams/processor/internals/StreamsPartitionAssignor$ClientMetadata
      46: invokestatic  #252                // Method org/apache/kafka/streams/processor/internals/StreamsPartitionAssignor$ClientMetadata.access$200:(Lorg/apache/kafka/streams/processor/internals/StreamsPartitionAssignor$ClientMetadata;)Lorg/apache/kafka/streams/state/HostInfo;
      49: astore        7
      51: aload         7
      53: ifnull        223
      56: new           #73                 // class java/util/HashSet
      59: dup
      60: invokespecial #74                 // Method java/util/HashSet."<init>":()V
      63: astore        8
      65: new           #73                 // class java/util/HashSet
      68: dup
      69: invokespecial #74                 // Method java/util/HashSet."<init>":()V
      72: astore        9
      74: aload         6
      76: invokeinterface #79,  1           // InterfaceMethod java/util/Map$Entry.getValue:()Ljava/lang/Object;
      81: checkcast     #60                 // class org/apache/kafka/streams/processor/internals/StreamsPartitionAssignor$ClientMetadata
      84: invokestatic  #237                // Method org/apache/kafka/streams/processor/internals/StreamsPartitionAssignor$ClientMetadata.access$100:(Lorg/apache/kafka/streams/processor/internals/StreamsPartitionAssignor$ClientMetadata;)Lorg/apache/kafka/streams/processor/internals/assignment/ClientState;
      87: astore        10
      89: aload         10
      91: invokevirtual #253                // Method org/apache/kafka/streams/processor/internals/assignment/ClientState.activeTasks:()Ljava/util/Set;
      94: invokeinterface #76,  1           // InterfaceMethod java/util/Set.iterator:()Ljava/util/Iterator;
      99: astore        11
     101: aload         11
     103: invokeinterface #58,  1           // InterfaceMethod java/util/Iterator.hasNext:()Z
     108: ifeq          145
     111: aload         11
     113: invokeinterface #59,  1           // InterfaceMethod java/util/Iterator.next:()Ljava/lang/Object;
     118: checkcast     #166                // class org/apache/kafka/streams/processor/TaskId
     121: astore        12
     123: aload         8
     125: aload_3
     126: aload         12
     128: invokeinterface #91,  2           // InterfaceMethod java/util/Map.get:(Ljava/lang/Object;)Ljava/lang/Object;
     133: checkcast     #223                // class java/util/Collection
     136: invokeinterface #95,  2           // InterfaceMethod java/util/Set.addAll:(Ljava/util/Collection;)Z
     141: pop
     142: goto          101
     145: aload         10
     147: invokevirtual #254                // Method org/apache/kafka/streams/processor/internals/assignment/ClientState.standbyTasks:()Ljava/util/Set;
     150: invokeinterface #76,  1           // InterfaceMethod java/util/Set.iterator:()Ljava/util/Iterator;
     155: astore        11
     157: aload         11
     159: invokeinterface #58,  1           // InterfaceMethod java/util/Iterator.hasNext:()Z
     164: ifeq          201
     167: aload         11
     169: invokeinterface #59,  1           // InterfaceMethod java/util/Iterator.next:()Ljava/lang/Object;
     174: checkcast     #166                // class org/apache/kafka/streams/processor/TaskId
     177: astore        12
     179: aload         9
     181: aload_3
     182: aload         12
     184: invokeinterface #91,  2           // InterfaceMethod java/util/Map.get:(Ljava/lang/Object;)Ljava/lang/Object;
     189: checkcast     #223                // class java/util/Collection
     192: invokeinterface #95,  2           // InterfaceMethod java/util/Set.addAll:(Ljava/util/Collection;)Z
     197: pop
     198: goto          157
     201: aload_1
     202: aload         7
     204: aload         8
     206: invokeinterface #71,  3           // InterfaceMethod java/util/Map.put:(Ljava/lang/Object;Ljava/lang/Object;)Ljava/lang/Object;
     211: pop
     212: aload_2
     213: aload         7
     215: aload         9
     217: invokeinterface #71,  3           // InterfaceMethod java/util/Map.put:(Ljava/lang/Object;Ljava/lang/Object;)Ljava/lang/Object;
     222: pop
     223: goto          14
     226: return

  private java.util.Map<java.lang.String, org.apache.kafka.clients.consumer.ConsumerPartitionAssignor$Assignment> computeNewAssignment(java.util.Set<org.apache.kafka.streams.processor.TaskId>, java.util.Map<java.util.UUID, org.apache.kafka.streams.processor.internals.StreamsPartitionAssignor$ClientMetadata>, java.util.Map<org.apache.kafka.streams.processor.TaskId, java.util.Set<org.apache.kafka.common.TopicPartition>>, java.util.Map<org.apache.kafka.streams.state.HostInfo, java.util.Set<org.apache.kafka.common.TopicPartition>>, java.util.Map<org.apache.kafka.streams.state.HostInfo, java.util.Set<org.apache.kafka.common.TopicPartition>>, java.util.Set<org.apache.kafka.common.TopicPartition>, int, int, boolean, boolean);
    Code:
       0: iload         10
       2: ifne          10
       5: iload         9
       7: ifeq          14
      10: iconst_1
      11: goto          15
      14: iconst_0
      15: istore        11
      17: new           #54                 // class java/util/HashMap
      20: dup
      21: invokespecial #55                 // Method java/util/HashMap."<init>":()V
      24: astore        12
      26: aload_2
      27: invokeinterface #75,  1           // InterfaceMethod java/util/Map.entrySet:()Ljava/util/Set;
      32: invokeinterface #76,  1           // InterfaceMethod java/util/Set.iterator:()Ljava/util/Iterator;
      37: astore        13
      39: aload         13
      41: invokeinterface #58,  1           // InterfaceMethod java/util/Iterator.hasNext:()Z
      46: ifeq          220
      49: aload         13
      51: invokeinterface #59,  1           // InterfaceMethod java/util/Iterator.next:()Ljava/lang/Object;
      56: checkcast     #77                 // class java/util/Map$Entry
      59: astore        14
      61: aload         14
      63: invokeinterface #78,  1           // InterfaceMethod java/util/Map$Entry.getKey:()Ljava/lang/Object;
      68: checkcast     #236                // class java/util/UUID
      71: astore        15
      73: aload         14
      75: invokeinterface #79,  1           // InterfaceMethod java/util/Map$Entry.getValue:()Ljava/lang/Object;
      80: checkcast     #60                 // class org/apache/kafka/streams/processor/internals/StreamsPartitionAssignor$ClientMetadata
      83: astore        16
      85: aload         16
      87: invokestatic  #237                // Method org/apache/kafka/streams/processor/internals/StreamsPartitionAssignor$ClientMetadata.access$100:(Lorg/apache/kafka/streams/processor/internals/StreamsPartitionAssignor$ClientMetadata;)Lorg/apache/kafka/streams/processor/internals/assignment/ClientState;
      90: astore        17
      92: aload         16
      94: invokestatic  #61                 // Method org/apache/kafka/streams/processor/internals/StreamsPartitionAssignor$ClientMetadata.access$000:(Lorg/apache/kafka/streams/processor/internals/StreamsPartitionAssignor$ClientMetadata;)Ljava/util/SortedSet;
      97: astore        18
      99: aload         17
     101: invokevirtual #255                // Method org/apache/kafka/streams/processor/internals/assignment/ClientState.statefulActiveTasks:()Ljava/util/Set;
     104: aload         17
     106: invokevirtual #256                // Method org/apache/kafka/streams/processor/internals/assignment/ClientState.statelessActiveTasks:()Ljava/util/Set;
     109: aload         18
     111: aload         17
     113: invokestatic  #257                // Method assignTasksToThreads:(Ljava/util/Collection;Ljava/util/Collection;Ljava/util/SortedSet;Lorg/apache/kafka/streams/processor/internals/assignment/ClientState;)Ljava/util/Map;
     116: astore        19
     118: aload         17
     120: invokevirtual #254                // Method org/apache/kafka/streams/processor/internals/assignment/ClientState.standbyTasks:()Ljava/util/Set;
     123: invokestatic  #258                // Method java/util/Collections.emptySet:()Ljava/util/Set;
     126: aload         18
     128: aload         17
     130: invokestatic  #257                // Method assignTasksToThreads:(Ljava/util/Collection;Ljava/util/Collection;Ljava/util/SortedSet;Lorg/apache/kafka/streams/processor/internals/assignment/ClientState;)Ljava/util/Map;
     133: astore        20
     135: iload         10
     137: ifeq          159
     140: aload         15
     142: aload_0
     143: getfield      #16                 // Field taskManager:Lorg/apache/kafka/streams/processor/internals/TaskManager;
     146: invokevirtual #50                 // Method org/apache/kafka/streams/processor/internals/TaskManager.processId:()Ljava/util/UUID;
     149: invokevirtual #259                // Method java/util/UUID.equals:(Ljava/lang/Object;)Z
     152: ifeq          159
     155: iconst_1
     156: goto          160
     159: iconst_0
     160: istore        21
     162: aload_0
     163: aload_1
     164: aload         12
     166: aload         16
     168: aload_3
     169: aload         4
     171: aload         5
     173: aload         6
     175: aload         19
     177: aload         20
     179: iload         7
     181: iload         8
     183: iload         21
     185: invokespecial #260                // Method addClientAssignments:(Ljava/util/Set;Ljava/util/Map;Lorg/apache/kafka/streams/processor/internals/StreamsPartitionAssignor$ClientMetadata;Ljava/util/Map;Ljava/util/Map;Ljava/util/Map;Ljava/util/Set;Ljava/util/Map;Ljava/util/Map;IIZ)Z
     188: istore        22
     190: iload         22
     192: ifne          200
     195: iload         21
     197: ifeq          217
     200: iconst_1
     201: istore        11
     203: aload_0
     204: getfield      #13                 // Field log:Lorg/slf4j/Logger;
     207: ldc_w         #261                // String Requested client {} to schedule a followup rebalance
     210: aload         15
     212: invokeinterface #100,  3          // InterfaceMethod org/slf4j/Logger.debug:(Ljava/lang/String;Ljava/lang/Object;)V
     217: goto          39
     220: iload         11
     222: ifeq          250
     225: aload_0
     226: getfield      #42                 // Field assignmentListener:Lorg/apache/kafka/streams/processor/internals/assignment/AssignorConfiguration$AssignmentListener;
     229: iconst_0
     230: invokeinterface #262,  2          // InterfaceMethod org/apache/kafka/streams/processor/internals/assignment/AssignorConfiguration$AssignmentListener.onAssignmentComplete:(Z)V
     235: aload_0
     236: getfield      #13                 // Field log:Lorg/slf4j/Logger;
     239: ldc_w         #263                // String Finished unstable assignment of tasks, a followup rebalance will be scheduled.
     242: invokeinterface #216,  2          // InterfaceMethod org/slf4j/Logger.info:(Ljava/lang/String;)V
     247: goto          272
     250: aload_0
     251: getfield      #42                 // Field assignmentListener:Lorg/apache/kafka/streams/processor/internals/assignment/AssignorConfiguration$AssignmentListener;
     254: iconst_1
     255: invokeinterface #262,  2          // InterfaceMethod org/apache/kafka/streams/processor/internals/assignment/AssignorConfiguration$AssignmentListener.onAssignmentComplete:(Z)V
     260: aload_0
     261: getfield      #13                 // Field log:Lorg/slf4j/Logger;
     264: ldc_w         #264                // String Finished stable assignment of tasks, no followup rebalances required.
     267: invokeinterface #216,  2          // InterfaceMethod org/slf4j/Logger.info:(Ljava/lang/String;)V
     272: aload         12
     274: areturn

  private boolean addClientAssignments(java.util.Set<org.apache.kafka.streams.processor.TaskId>, java.util.Map<java.lang.String, org.apache.kafka.clients.consumer.ConsumerPartitionAssignor$Assignment>, org.apache.kafka.streams.processor.internals.StreamsPartitionAssignor$ClientMetadata, java.util.Map<org.apache.kafka.streams.processor.TaskId, java.util.Set<org.apache.kafka.common.TopicPartition>>, java.util.Map<org.apache.kafka.streams.state.HostInfo, java.util.Set<org.apache.kafka.common.TopicPartition>>, java.util.Map<org.apache.kafka.streams.state.HostInfo, java.util.Set<org.apache.kafka.common.TopicPartition>>, java.util.Set<org.apache.kafka.common.TopicPartition>, java.util.Map<java.lang.String, java.util.List<org.apache.kafka.streams.processor.TaskId>>, java.util.Map<java.lang.String, java.util.List<org.apache.kafka.streams.processor.TaskId>>, int, int, boolean);
    Code:
       0: iconst_0
       1: istore        13
       3: iload         12
       5: istore        14
       7: aload_3
       8: invokestatic  #61                 // Method org/apache/kafka/streams/processor/internals/StreamsPartitionAssignor$ClientMetadata.access$000:(Lorg/apache/kafka/streams/processor/internals/StreamsPartitionAssignor$ClientMetadata;)Ljava/util/SortedSet;
      11: invokeinterface #62,  1           // InterfaceMethod java/util/SortedSet.iterator:()Ljava/util/Iterator;
      16: astore        15
      18: aload         15
      20: invokeinterface #58,  1           // InterfaceMethod java/util/Iterator.hasNext:()Z
      25: ifeq          261
      28: aload         15
      30: invokeinterface #59,  1           // InterfaceMethod java/util/Iterator.next:()Ljava/lang/Object;
      35: checkcast     #63                 // class java/lang/String
      38: astore        16
      40: aload         8
      42: aload         16
      44: invokeinterface #91,  2           // InterfaceMethod java/util/Map.get:(Ljava/lang/Object;)Ljava/lang/Object;
      49: checkcast     #265                // class java/util/List
      52: astore        17
      54: new           #44                 // class java/util/ArrayList
      57: dup
      58: invokespecial #45                 // Method java/util/ArrayList."<init>":()V
      61: astore        18
      63: new           #44                 // class java/util/ArrayList
      66: dup
      67: invokespecial #45                 // Method java/util/ArrayList."<init>":()V
      70: astore        19
      72: aload_0
      73: aload         18
      75: aload         19
      77: aload         16
      79: aload_3
      80: invokestatic  #237                // Method org/apache/kafka/streams/processor/internals/StreamsPartitionAssignor$ClientMetadata.access$100:(Lorg/apache/kafka/streams/processor/internals/StreamsPartitionAssignor$ClientMetadata;)Lorg/apache/kafka/streams/processor/internals/assignment/ClientState;
      83: aload         17
      85: aload         4
      87: aload         7
      89: invokespecial #266                // Method populateActiveTaskAndPartitionsLists:(Ljava/util/List;Ljava/util/List;Ljava/lang/String;Lorg/apache/kafka/streams/processor/internals/assignment/ClientState;Ljava/util/List;Ljava/util/Map;Ljava/util/Set;)Ljava/util/Set;
      92: astore        20
      94: aload_0
      95: aload         16
      97: aload         9
      99: aload         16
     101: invokeinterface #91,  2           // InterfaceMethod java/util/Map.get:(Ljava/lang/Object;)Ljava/lang/Object;
     106: checkcast     #267                // class java/lang/Iterable
     109: aload         20
     111: aload_1
     112: aload         4
     114: aload_3
     115: invokestatic  #237                // Method org/apache/kafka/streams/processor/internals/StreamsPartitionAssignor$ClientMetadata.access$100:(Lorg/apache/kafka/streams/processor/internals/StreamsPartitionAssignor$ClientMetadata;)Lorg/apache/kafka/streams/processor/internals/assignment/ClientState;
     118: invokespecial #268                // Method buildStandbyTaskMap:(Ljava/lang/String;Ljava/lang/Iterable;Ljava/lang/Iterable;Ljava/util/Set;Ljava/util/Map;Lorg/apache/kafka/streams/processor/internals/assignment/ClientState;)Ljava/util/Map;
     121: astore        21
     123: new           #66                 // class org/apache/kafka/streams/processor/internals/assignment/AssignmentInfo
     126: dup
     127: iload         10
     129: iload         11
     131: aload         19
     133: aload         21
     135: aload         5
     137: aload         6
     139: getstatic     #269                // Field org/apache/kafka/streams/processor/internals/assignment/AssignorError.NONE:Lorg/apache/kafka/streams/processor/internals/assignment/AssignorError;
     142: invokevirtual #107                // Method org/apache/kafka/streams/processor/internals/assignment/AssignorError.code:()I
     145: invokespecial #270                // Method org/apache/kafka/streams/processor/internals/assignment/AssignmentInfo."<init>":(IILjava/util/List;Ljava/util/Map;Ljava/util/Map;Ljava/util/Map;I)V
     148: astore        22
     150: aload         20
     152: invokeinterface #195,  1          // InterfaceMethod java/util/Set.isEmpty:()Z
     157: ifne          187
     160: aload_0
     161: getfield      #13                 // Field log:Lorg/slf4j/Logger;
     164: ldc_w         #271                // String Requesting followup rebalance be scheduled immediately due to tasks changing ownership.
     167: invokeinterface #216,  2          // InterfaceMethod org/slf4j/Logger.info:(Ljava/lang/String;)V
     172: aload         22
     174: lconst_0
     175: invokevirtual #272                // Method org/apache/kafka/streams/processor/internals/assignment/AssignmentInfo.setNextRebalanceTime:(J)V
     178: iconst_1
     179: istore        13
     181: iconst_0
     182: istore        14
     184: goto          235
     187: iload         14
     189: ifeq          235
     192: aload_0
     193: getfield      #24                 // Field time:Lorg/apache/kafka/common/utils/Time;
     196: invokeinterface #273,  1          // InterfaceMethod org/apache/kafka/common/utils/Time.milliseconds:()J
     201: aload_0
     202: invokevirtual #274                // Method probingRebalanceIntervalMs:()J
     205: ladd
     206: lstore        23
     208: aload_0
     209: getfield      #13                 // Field log:Lorg/slf4j/Logger;
     212: ldc_w         #275                // String Requesting followup rebalance be scheduled for {} ms to probe for caught-up replica tasks.
     215: lload         23
     217: invokestatic  #240                // Method java/lang/Long.valueOf:(J)Ljava/lang/Long;
     220: invokeinterface #276,  3          // InterfaceMethod org/slf4j/Logger.info:(Ljava/lang/String;Ljava/lang/Object;)V
     225: aload         22
     227: lload         23
     229: invokevirtual #272                // Method org/apache/kafka/streams/processor/internals/assignment/AssignmentInfo.setNextRebalanceTime:(J)V
     232: iconst_0
     233: istore        14
     235: aload_2
     236: aload         16
     238: new           #64                 // class org/apache/kafka/clients/consumer/ConsumerPartitionAssignor$Assignment
     241: dup
     242: aload         18
     244: aload         22
     246: invokevirtual #69                 // Method org/apache/kafka/streams/processor/internals/assignment/AssignmentInfo.encode:()Ljava/nio/ByteBuffer;
     249: invokespecial #70                 // Method org/apache/kafka/clients/consumer/ConsumerPartitionAssignor$Assignment."<init>":(Ljava/util/List;Ljava/nio/ByteBuffer;)V
     252: invokeinterface #71,  3           // InterfaceMethod java/util/Map.put:(Ljava/lang/Object;Ljava/lang/Object;)Ljava/lang/Object;
     257: pop
     258: goto          18
     261: iload         13
     263: ireturn

  private java.util.Set<org.apache.kafka.streams.processor.TaskId> populateActiveTaskAndPartitionsLists(java.util.List<org.apache.kafka.common.TopicPartition>, java.util.List<org.apache.kafka.streams.processor.TaskId>, java.lang.String, org.apache.kafka.streams.processor.internals.assignment.ClientState, java.util.List<org.apache.kafka.streams.processor.TaskId>, java.util.Map<org.apache.kafka.streams.processor.TaskId, java.util.Set<org.apache.kafka.common.TopicPartition>>, java.util.Set<org.apache.kafka.common.TopicPartition>);
    Code:
       0: new           #44                 // class java/util/ArrayList
       3: dup
       4: invokespecial #45                 // Method java/util/ArrayList."<init>":()V
       7: astore        8
       9: new           #277                // class java/util/TreeSet
      12: dup
      13: invokespecial #278                // Method java/util/TreeSet."<init>":()V
      16: astore        9
      18: aload         5
      20: invokeinterface #179,  1          // InterfaceMethod java/util/List.iterator:()Ljava/util/Iterator;
      25: astore        10
      27: aload         10
      29: invokeinterface #58,  1           // InterfaceMethod java/util/Iterator.hasNext:()Z
      34: ifeq          223
      37: aload         10
      39: invokeinterface #59,  1           // InterfaceMethod java/util/Iterator.next:()Ljava/lang/Object;
      44: checkcast     #166                // class org/apache/kafka/streams/processor/TaskId
      47: astore        11
      49: new           #44                 // class java/util/ArrayList
      52: dup
      53: invokespecial #45                 // Method java/util/ArrayList."<init>":()V
      56: astore        12
      58: aload         6
      60: aload         11
      62: invokeinterface #91,  2           // InterfaceMethod java/util/Map.get:(Ljava/lang/Object;)Ljava/lang/Object;
      67: checkcast     #167                // class java/util/Set
      70: invokeinterface #76,  1           // InterfaceMethod java/util/Set.iterator:()Ljava/util/Iterator;
      75: astore        13
      77: aload         13
      79: invokeinterface #58,  1           // InterfaceMethod java/util/Iterator.hasNext:()Z
      84: ifeq          210
      87: aload         13
      89: invokeinterface #59,  1           // InterfaceMethod java/util/Iterator.next:()Ljava/lang/Object;
      94: checkcast     #153                // class org/apache/kafka/common/TopicPartition
      97: astore        14
      99: aload         4
     101: aload         14
     103: invokevirtual #279                // Method org/apache/kafka/streams/processor/internals/assignment/ClientState.previousOwnerForPartition:(Lorg/apache/kafka/common/TopicPartition;)Ljava/lang/String;
     106: astore        15
     108: aload         15
     110: ifnull        122
     113: aload         15
     115: aload_3
     116: invokevirtual #280                // Method java/lang/String.equals:(Ljava/lang/Object;)Z
     119: ifne          126
     122: iconst_1
     123: goto          127
     126: iconst_0
     127: istore        16
     129: iload         16
     131: ifeq          188
     134: aload         7
     136: aload         14
     138: invokeinterface #136,  2          // InterfaceMethod java/util/Set.contains:(Ljava/lang/Object;)Z
     143: ifeq          188
     146: aload_0
     147: getfield      #13                 // Field log:Lorg/slf4j/Logger;
     150: ldc_w         #281                // String Removing task {} from {} active assignment until it is safely revoked in followup rebalance
     153: aload         11
     155: aload_3
     156: invokeinterface #121,  4          // InterfaceMethod org/slf4j/Logger.info:(Ljava/lang/String;Ljava/lang/Object;Ljava/lang/Object;)V
     161: aload         9
     163: aload         11
     165: invokeinterface #173,  2          // InterfaceMethod java/util/Set.add:(Ljava/lang/Object;)Z
     170: pop
     171: aload         12
     173: invokeinterface #282,  1          // InterfaceMethod java/util/List.clear:()V
     178: aload         4
     180: aload         11
     182: invokevirtual #283                // Method org/apache/kafka/streams/processor/internals/assignment/ClientState.unassignActive:(Lorg/apache/kafka/streams/processor/TaskId;)V
     185: goto          210
     188: aload         12
     190: new           #284                // class org/apache/kafka/streams/processor/internals/StreamsPartitionAssignor$AssignedPartition
     193: dup
     194: aload         11
     196: aload         14
     198: invokespecial #285                // Method org/apache/kafka/streams/processor/internals/StreamsPartitionAssignor$AssignedPartition."<init>":(Lorg/apache/kafka/streams/processor/TaskId;Lorg/apache/kafka/common/TopicPartition;)V
     201: invokeinterface #47,  2           // InterfaceMethod java/util/List.add:(Ljava/lang/Object;)Z
     206: pop
     207: goto          77
     210: aload         8
     212: aload         12
     214: invokeinterface #286,  2          // InterfaceMethod java/util/List.addAll:(Ljava/util/Collection;)Z
     219: pop
     220: goto          27
     223: aload         8
     225: invokestatic  #287                // Method java/util/Collections.sort:(Ljava/util/List;)V
     228: aload         8
     230: invokeinterface #179,  1          // InterfaceMethod java/util/List.iterator:()Ljava/util/Iterator;
     235: astore        10
     237: aload         10
     239: invokeinterface #58,  1           // InterfaceMethod java/util/Iterator.hasNext:()Z
     244: ifeq          286
     247: aload         10
     249: invokeinterface #59,  1           // InterfaceMethod java/util/Iterator.next:()Ljava/lang/Object;
     254: checkcast     #284                // class org/apache/kafka/streams/processor/internals/StreamsPartitionAssignor$AssignedPartition
     257: astore        11
     259: aload_2
     260: aload         11
     262: invokestatic  #288                // Method org/apache/kafka/streams/processor/internals/StreamsPartitionAssignor$AssignedPartition.access$300:(Lorg/apache/kafka/streams/processor/internals/StreamsPartitionAssignor$AssignedPartition;)Lorg/apache/kafka/streams/processor/TaskId;
     265: invokeinterface #47,  2           // InterfaceMethod java/util/List.add:(Ljava/lang/Object;)Z
     270: pop
     271: aload_1
     272: aload         11
     274: invokestatic  #289                // Method org/apache/kafka/streams/processor/internals/StreamsPartitionAssignor$AssignedPartition.access$400:(Lorg/apache/kafka/streams/processor/internals/StreamsPartitionAssignor$AssignedPartition;)Lorg/apache/kafka/common/TopicPartition;
     277: invokeinterface #47,  2           // InterfaceMethod java/util/List.add:(Ljava/lang/Object;)Z
     282: pop
     283: goto          237
     286: aload         9
     288: areturn

  private java.util.Map<org.apache.kafka.streams.processor.TaskId, java.util.Set<org.apache.kafka.common.TopicPartition>> buildStandbyTaskMap(java.lang.String, java.lang.Iterable<org.apache.kafka.streams.processor.TaskId>, java.lang.Iterable<org.apache.kafka.streams.processor.TaskId>, java.util.Set<org.apache.kafka.streams.processor.TaskId>, java.util.Map<org.apache.kafka.streams.processor.TaskId, java.util.Set<org.apache.kafka.common.TopicPartition>>, org.apache.kafka.streams.processor.internals.assignment.ClientState);
    Code:
       0: new           #54                 // class java/util/HashMap
       3: dup
       4: invokespecial #55                 // Method java/util/HashMap."<init>":()V
       7: astore        7
       9: aload_2
      10: invokeinterface #290,  1          // InterfaceMethod java/lang/Iterable.iterator:()Ljava/util/Iterator;
      15: astore        8
      17: aload         8
      19: invokeinterface #58,  1           // InterfaceMethod java/util/Iterator.hasNext:()Z
      24: ifeq          61
      27: aload         8
      29: invokeinterface #59,  1           // InterfaceMethod java/util/Iterator.next:()Ljava/lang/Object;
      34: checkcast     #166                // class org/apache/kafka/streams/processor/TaskId
      37: astore        9
      39: aload         7
      41: aload         9
      43: aload         5
      45: aload         9
      47: invokeinterface #91,  2           // InterfaceMethod java/util/Map.get:(Ljava/lang/Object;)Ljava/lang/Object;
      52: invokeinterface #71,  3           // InterfaceMethod java/util/Map.put:(Ljava/lang/Object;Ljava/lang/Object;)Ljava/lang/Object;
      57: pop
      58: goto          17
      61: aload_3
      62: invokeinterface #290,  1          // InterfaceMethod java/lang/Iterable.iterator:()Ljava/util/Iterator;
      67: astore        8
      69: aload         8
      71: invokeinterface #58,  1           // InterfaceMethod java/util/Iterator.hasNext:()Z
      76: ifeq          147
      79: aload         8
      81: invokeinterface #59,  1           // InterfaceMethod java/util/Iterator.next:()Ljava/lang/Object;
      86: checkcast     #166                // class org/apache/kafka/streams/processor/TaskId
      89: astore        9
      91: aload         4
      93: aload         9
      95: invokeinterface #136,  2          // InterfaceMethod java/util/Set.contains:(Ljava/lang/Object;)Z
     100: ifeq          144
     103: aload_0
     104: getfield      #13                 // Field log:Lorg/slf4j/Logger;
     107: ldc_w         #291                // String Adding removed stateful active task {} as a standby for {} before it is safely revoked in followup rebalance
     110: aload         9
     112: aload_1
     113: invokeinterface #121,  4          // InterfaceMethod org/slf4j/Logger.info:(Ljava/lang/String;Ljava/lang/Object;Ljava/lang/Object;)V
     118: aload         7
     120: aload         9
     122: aload         5
     124: aload         9
     126: invokeinterface #91,  2           // InterfaceMethod java/util/Map.get:(Ljava/lang/Object;)Ljava/lang/Object;
     131: invokeinterface #71,  3           // InterfaceMethod java/util/Map.put:(Ljava/lang/Object;Ljava/lang/Object;)Ljava/lang/Object;
     136: pop
     137: aload         6
     139: aload         9
     141: invokevirtual #292                // Method org/apache/kafka/streams/processor/internals/assignment/ClientState.assignStandby:(Lorg/apache/kafka/streams/processor/TaskId;)V
     144: goto          69
     147: aload         7
     149: areturn

  static java.util.Map<java.lang.String, java.util.List<org.apache.kafka.streams.processor.TaskId>> assignTasksToThreads(java.util.Collection<org.apache.kafka.streams.processor.TaskId>, java.util.Collection<org.apache.kafka.streams.processor.TaskId>, java.util.SortedSet<java.lang.String>, org.apache.kafka.streams.processor.internals.assignment.ClientState);
    Code:
       0: new           #54                 // class java/util/HashMap
       3: dup
       4: invokespecial #55                 // Method java/util/HashMap."<init>":()V
       7: astore        4
       9: aload_2
      10: invokeinterface #62,  1           // InterfaceMethod java/util/SortedSet.iterator:()Ljava/util/Iterator;
      15: astore        5
      17: aload         5
      19: invokeinterface #58,  1           // InterfaceMethod java/util/Iterator.hasNext:()Z
      24: ifeq          59
      27: aload         5
      29: invokeinterface #59,  1           // InterfaceMethod java/util/Iterator.next:()Ljava/lang/Object;
      34: checkcast     #63                 // class java/lang/String
      37: astore        6
      39: aload         4
      41: aload         6
      43: new           #44                 // class java/util/ArrayList
      46: dup
      47: invokespecial #45                 // Method java/util/ArrayList."<init>":()V
      50: invokeinterface #71,  3           // InterfaceMethod java/util/Map.put:(Ljava/lang/Object;Ljava/lang/Object;)Ljava/lang/Object;
      55: pop
      56: goto          17
      59: new           #44                 // class java/util/ArrayList
      62: dup
      63: aload_1
      64: invokespecial #293                // Method java/util/ArrayList."<init>":(Ljava/util/Collection;)V
      67: astore        5
      69: aload         5
      71: invokestatic  #287                // Method java/util/Collections.sort:(Ljava/util/List;)V
      74: aload         5
      76: invokeinterface #179,  1          // InterfaceMethod java/util/List.iterator:()Ljava/util/Iterator;
      81: astore        6
      83: aload_0
      84: invokeinterface #294,  1          // InterfaceMethod java/util/Collection.size:()I
      89: i2d
      90: aload_2
      91: invokeinterface #295,  1          // InterfaceMethod java/util/SortedSet.size:()I
      96: i2d
      97: ddiv
      98: invokestatic  #296                // Method java/lang/Math.floor:(D)D
     101: d2i
     102: istore        7
     104: new           #297                // class java/util/PriorityQueue
     107: dup
     108: aload_0
     109: invokespecial #298                // Method java/util/PriorityQueue."<init>":(Ljava/util/Collection;)V
     112: astore        8
     114: new           #299                // class java/util/LinkedList
     117: dup
     118: invokespecial #300                // Method java/util/LinkedList."<init>":()V
     121: astore        9
     123: new           #301                // class java/util/TreeMap
     126: dup
     127: invokespecial #302                // Method java/util/TreeMap."<init>":()V
     130: astore        10
     132: aload         8
     134: invokevirtual #303                // Method java/util/PriorityQueue.isEmpty:()Z
     137: ifne          679
     140: aload_2
     141: invokeinterface #62,  1           // InterfaceMethod java/util/SortedSet.iterator:()Ljava/util/Iterator;
     146: astore        11
     148: aload         11
     150: invokeinterface #58,  1           // InterfaceMethod java/util/Iterator.hasNext:()Z
     155: ifeq          302
     158: aload         11
     160: invokeinterface #59,  1           // InterfaceMethod java/util/Iterator.next:()Ljava/lang/Object;
     165: checkcast     #63                 // class java/lang/String
     168: astore        12
     170: aload         4
     172: aload         12
     174: invokeinterface #91,  2           // InterfaceMethod java/util/Map.get:(Ljava/lang/Object;)Ljava/lang/Object;
     179: checkcast     #265                // class java/util/List
     182: astore        13
     184: aload_3
     185: aload         12
     187: invokestatic  #304                // Method getPreviousTasksByLag:(Lorg/apache/kafka/streams/processor/internals/assignment/ClientState;Ljava/lang/String;)Ljava/util/SortedSet;
     190: invokeinterface #62,  1           // InterfaceMethod java/util/SortedSet.iterator:()Ljava/util/Iterator;
     195: astore        14
     197: aload         14
     199: invokeinterface #58,  1           // InterfaceMethod java/util/Iterator.hasNext:()Z
     204: ifeq          277
     207: aload         14
     209: invokeinterface #59,  1           // InterfaceMethod java/util/Iterator.next:()Ljava/lang/Object;
     214: checkcast     #166                // class org/apache/kafka/streams/processor/TaskId
     217: astore        15
     219: aload         8
     221: aload         15
     223: invokevirtual #305                // Method java/util/PriorityQueue.contains:(Ljava/lang/Object;)Z
     226: ifeq          274
     229: aload         13
     231: invokeinterface #306,  1          // InterfaceMethod java/util/List.size:()I
     236: iload         7
     238: if_icmpge     262
     241: aload         13
     243: aload         15
     245: invokeinterface #47,  2           // InterfaceMethod java/util/List.add:(Ljava/lang/Object;)Z
     250: pop
     251: aload         8
     253: aload         15
     255: invokevirtual #307                // Method java/util/PriorityQueue.remove:(Ljava/lang/Object;)Z
     258: pop
     259: goto          274
     262: aload         10
     264: aload         15
     266: aload         12
     268: invokeinterface #71,  3           // InterfaceMethod java/util/Map.put:(Ljava/lang/Object;Ljava/lang/Object;)Ljava/lang/Object;
     273: pop
     274: goto          197
     277: aload         13
     279: invokeinterface #306,  1          // InterfaceMethod java/util/List.size:()I
     284: iload         7
     286: if_icmpge     299
     289: aload         9
     291: aload         12
     293: invokeinterface #308,  2          // InterfaceMethod java/util/Queue.offer:(Ljava/lang/Object;)Z
     298: pop
     299: goto          148
     302: aload         9
     304: invokeinterface #309,  1          // InterfaceMethod java/util/Queue.isEmpty:()Z
     309: ifne          402
     312: aload         8
     314: invokevirtual #310                // Method java/util/PriorityQueue.poll:()Ljava/lang/Object;
     317: checkcast     #166                // class org/apache/kafka/streams/processor/TaskId
     320: astore        11
     322: aload         11
     324: ifnull        388
     327: aload         9
     329: invokeinterface #311,  1          // InterfaceMethod java/util/Queue.poll:()Ljava/lang/Object;
     334: checkcast     #63                 // class java/lang/String
     337: astore        12
     339: aload         4
     341: aload         12
     343: invokeinterface #91,  2           // InterfaceMethod java/util/Map.get:(Ljava/lang/Object;)Ljava/lang/Object;
     348: checkcast     #265                // class java/util/List
     351: astore        13
     353: aload         13
     355: aload         11
     357: invokeinterface #47,  2           // InterfaceMethod java/util/List.add:(Ljava/lang/Object;)Z
     362: pop
     363: aload         13
     365: invokeinterface #306,  1          // InterfaceMethod java/util/List.size:()I
     370: iload         7
     372: if_icmpge     385
     375: aload         9
     377: aload         12
     379: invokeinterface #308,  2          // InterfaceMethod java/util/Queue.offer:(Ljava/lang/Object;)Z
     384: pop
     385: goto          399
     388: new           #122                // class java/lang/IllegalStateException
     391: dup
     392: ldc_w         #312                // String Ran out of unassigned stateful tasks but some members were not at capacity
     395: invokespecial #131                // Method java/lang/IllegalStateException."<init>":(Ljava/lang/String;)V
     398: athrow
     399: goto          302
     402: aload         8
     404: invokevirtual #303                // Method java/util/PriorityQueue.isEmpty:()Z
     407: ifne          679
     410: aload         9
     412: aload_2
     413: invokeinterface #313,  2          // InterfaceMethod java/util/Queue.addAll:(Ljava/util/Collection;)Z
     418: pop
     419: aload         10
     421: invokeinterface #75,  1           // InterfaceMethod java/util/Map.entrySet:()Ljava/util/Set;
     426: invokeinterface #76,  1           // InterfaceMethod java/util/Set.iterator:()Ljava/util/Iterator;
     431: astore        11
     433: aload         11
     435: invokeinterface #58,  1           // InterfaceMethod java/util/Iterator.hasNext:()Z
     440: ifeq          542
     443: aload         11
     445: invokeinterface #59,  1           // InterfaceMethod java/util/Iterator.next:()Ljava/lang/Object;
     450: checkcast     #77                 // class java/util/Map$Entry
     453: astore        12
     455: aload         12
     457: invokeinterface #78,  1           // InterfaceMethod java/util/Map$Entry.getKey:()Ljava/lang/Object;
     462: checkcast     #166                // class org/apache/kafka/streams/processor/TaskId
     465: astore        13
     467: aload         12
     469: invokeinterface #79,  1           // InterfaceMethod java/util/Map$Entry.getValue:()Ljava/lang/Object;
     474: checkcast     #63                 // class java/lang/String
     477: astore        14
     479: aload         9
     481: aload         14
     483: invokeinterface #314,  2          // InterfaceMethod java/util/Queue.contains:(Ljava/lang/Object;)Z
     488: ifeq          539
     491: aload         8
     493: aload         13
     495: invokevirtual #305                // Method java/util/PriorityQueue.contains:(Ljava/lang/Object;)Z
     498: ifeq          539
     501: aload         4
     503: aload         14
     505: invokeinterface #91,  2           // InterfaceMethod java/util/Map.get:(Ljava/lang/Object;)Ljava/lang/Object;
     510: checkcast     #265                // class java/util/List
     513: aload         13
     515: invokeinterface #47,  2           // InterfaceMethod java/util/List.add:(Ljava/lang/Object;)Z
     520: pop
     521: aload         8
     523: aload         13
     525: invokevirtual #307                // Method java/util/PriorityQueue.remove:(Ljava/lang/Object;)Z
     528: pop
     529: aload         9
     531: aload         14
     533: invokeinterface #315,  2          // InterfaceMethod java/util/Queue.remove:(Ljava/lang/Object;)Z
     538: pop
     539: goto          433
     542: aload         8
     544: invokevirtual #316                // Method java/util/PriorityQueue.iterator:()Ljava/util/Iterator;
     547: astore        11
     549: aload         11
     551: invokeinterface #58,  1           // InterfaceMethod java/util/Iterator.hasNext:()Z
     556: ifeq          610
     559: aload         11
     561: invokeinterface #59,  1           // InterfaceMethod java/util/Iterator.next:()Ljava/lang/Object;
     566: checkcast     #166                // class org/apache/kafka/streams/processor/TaskId
     569: astore        12
     571: aload         9
     573: invokeinterface #311,  1          // InterfaceMethod java/util/Queue.poll:()Ljava/lang/Object;
     578: checkcast     #63                 // class java/lang/String
     581: astore        13
     583: aload         4
     585: aload         13
     587: invokeinterface #91,  2           // InterfaceMethod java/util/Map.get:(Ljava/lang/Object;)Ljava/lang/Object;
     592: checkcast     #265                // class java/util/List
     595: astore        14
     597: aload         14
     599: aload         12
     601: invokeinterface #47,  2           // InterfaceMethod java/util/List.add:(Ljava/lang/Object;)Z
     606: pop
     607: goto          549
     610: aload         6
     612: invokeinterface #58,  1           // InterfaceMethod java/util/Iterator.hasNext:()Z
     617: ifeq          679
     620: aload         9
     622: invokeinterface #311,  1          // InterfaceMethod java/util/Queue.poll:()Ljava/lang/Object;
     627: checkcast     #63                 // class java/lang/String
     630: astore        11
     632: aload         11
     634: ifnull        679
     637: aload         6
     639: invokeinterface #59,  1           // InterfaceMethod java/util/Iterator.next:()Ljava/lang/Object;
     644: checkcast     #166                // class org/apache/kafka/streams/processor/TaskId
     647: astore        12
     649: aload         6
     651: invokeinterface #317,  1          // InterfaceMethod java/util/Iterator.remove:()V
     656: aload         4
     658: aload         11
     660: invokeinterface #91,  2           // InterfaceMethod java/util/Map.get:(Ljava/lang/Object;)Ljava/lang/Object;
     665: checkcast     #265                // class java/util/List
     668: aload         12
     670: invokeinterface #47,  2           // InterfaceMethod java/util/List.add:(Ljava/lang/Object;)Z
     675: pop
     676: goto          610
     679: aload         9
     681: aload_2
     682: invokeinterface #313,  2          // InterfaceMethod java/util/Queue.addAll:(Ljava/util/Collection;)Z
     687: pop
     688: aload         6
     690: invokeinterface #58,  1           // InterfaceMethod java/util/Iterator.hasNext:()Z
     695: ifeq          755
     698: aload         6
     700: invokeinterface #59,  1           // InterfaceMethod java/util/Iterator.next:()Ljava/lang/Object;
     705: checkcast     #166                // class org/apache/kafka/streams/processor/TaskId
     708: astore        11
     710: aload         9
     712: invokeinterface #311,  1          // InterfaceMethod java/util/Queue.poll:()Ljava/lang/Object;
     717: checkcast     #63                 // class java/lang/String
     720: astore        12
     722: aload         4
     724: aload         12
     726: invokeinterface #91,  2           // InterfaceMethod java/util/Map.get:(Ljava/lang/Object;)Ljava/lang/Object;
     731: checkcast     #265                // class java/util/List
     734: aload         11
     736: invokeinterface #47,  2           // InterfaceMethod java/util/List.add:(Ljava/lang/Object;)Z
     741: pop
     742: aload         9
     744: aload         12
     746: invokeinterface #308,  2          // InterfaceMethod java/util/Queue.offer:(Ljava/lang/Object;)Z
     751: pop
     752: goto          688
     755: aload         4
     757: areturn

  private static java.util.SortedSet<org.apache.kafka.streams.processor.TaskId> getPreviousTasksByLag(org.apache.kafka.streams.processor.internals.assignment.ClientState, java.lang.String);
    Code:
       0: new           #277                // class java/util/TreeSet
       3: dup
       4: aload_0
       5: dup
       6: invokevirtual #11                 // Method java/lang/Object.getClass:()Ljava/lang/Class;
       9: pop
      10: invokedynamic #318,  0            // InvokeDynamic #7:applyAsLong:(Lorg/apache/kafka/streams/processor/internals/assignment/ClientState;)Ljava/util/function/ToLongFunction;
      15: invokestatic  #319                // InterfaceMethod java/util/Comparator.comparingLong:(Ljava/util/function/ToLongFunction;)Ljava/util/Comparator;
      18: invokedynamic #320,  0            // InvokeDynamic #8:compare:()Ljava/util/Comparator;
      23: invokeinterface #321,  2          // InterfaceMethod java/util/Comparator.thenComparing:(Ljava/util/Comparator;)Ljava/util/Comparator;
      28: invokespecial #322                // Method java/util/TreeSet."<init>":(Ljava/util/Comparator;)V
      31: astore_2
      32: aload_2
      33: aload_0
      34: aload_1
      35: invokevirtual #323                // Method org/apache/kafka/streams/processor/internals/assignment/ClientState.previousTasksForConsumer:(Ljava/lang/String;)Ljava/util/Set;
      38: invokeinterface #324,  2          // InterfaceMethod java/util/SortedSet.addAll:(Ljava/util/Collection;)Z
      43: pop
      44: aload_2
      45: areturn

  private void validateMetadataVersions(int, int);
    Code:
       0: iload_1
       1: aload_0
       2: getfield      #4                  // Field usedSubscriptionMetadataVersion:I
       5: if_icmple     78
       8: aload_0
       9: getfield      #13                 // Field log:Lorg/slf4j/Logger;
      12: ldc_w         #325                // String Leader sent back an assignment with version {} which was greater than our used version {}
      15: iload_1
      16: invokestatic  #120                // Method java/lang/Integer.valueOf:(I)Ljava/lang/Integer;
      19: aload_0
      20: getfield      #4                  // Field usedSubscriptionMetadataVersion:I
      23: invokestatic  #120                // Method java/lang/Integer.valueOf:(I)Ljava/lang/Integer;
      26: invokeinterface #139,  4          // InterfaceMethod org/slf4j/Logger.error:(Ljava/lang/String;Ljava/lang/Object;Ljava/lang/Object;)V
      31: new           #104                // class org/apache/kafka/streams/errors/TaskAssignmentException
      34: dup
      35: new           #123                // class java/lang/StringBuilder
      38: dup
      39: invokespecial #124                // Method java/lang/StringBuilder."<init>":()V
      42: ldc_w         #326                // String Sent a version
      45: invokevirtual #126                // Method java/lang/StringBuilder.append:(Ljava/lang/String;)Ljava/lang/StringBuilder;
      48: aload_0
      49: getfield      #4                  // Field usedSubscriptionMetadataVersion:I
      52: invokevirtual #127                // Method java/lang/StringBuilder.append:(I)Ljava/lang/StringBuilder;
      55: ldc_w         #327                // String  subscription but got an assignment with higher version
      58: invokevirtual #126                // Method java/lang/StringBuilder.append:(Ljava/lang/String;)Ljava/lang/StringBuilder;
      61: iload_1
      62: invokevirtual #127                // Method java/lang/StringBuilder.append:(I)Ljava/lang/StringBuilder;
      65: ldc_w         #328                // String .
      68: invokevirtual #126                // Method java/lang/StringBuilder.append:(Ljava/lang/String;)Ljava/lang/StringBuilder;
      71: invokevirtual #130                // Method java/lang/StringBuilder.toString:()Ljava/lang/String;
      74: invokespecial #141                // Method org/apache/kafka/streams/errors/TaskAssignmentException."<init>":(Ljava/lang/String;)V
      77: athrow
      78: iload_2
      79: bipush        7
      81: if_icmple     116
      84: aload_0
      85: getfield      #13                 // Field log:Lorg/slf4j/Logger;
      88: ldc_w         #329                // String Leader sent back assignment with commonly supported version {} that is greater than our actual latest supported version {}
      91: iload_2
      92: invokestatic  #120                // Method java/lang/Integer.valueOf:(I)Ljava/lang/Integer;
      95: bipush        7
      97: invokestatic  #120                // Method java/lang/Integer.valueOf:(I)Ljava/lang/Integer;
     100: invokeinterface #139,  4          // InterfaceMethod org/slf4j/Logger.error:(Ljava/lang/String;Ljava/lang/Object;Ljava/lang/Object;)V
     105: new           #104                // class org/apache/kafka/streams/errors/TaskAssignmentException
     108: dup
     109: ldc_w         #330                // String Can\'t upgrade to metadata version greater than we support
     112: invokespecial #141                // Method org/apache/kafka/streams/errors/TaskAssignmentException."<init>":(Ljava/lang/String;)V
     115: athrow
     116: return

  protected boolean maybeUpdateSubscriptionVersion(int, int);
    Code:
       0: iload_1
       1: iconst_3
       2: if_icmplt     115
       5: iload_2
       6: aload_0
       7: getfield      #4                  // Field usedSubscriptionMetadataVersion:I
      10: if_icmple     60
      13: aload_0
      14: getfield      #13                 // Field log:Lorg/slf4j/Logger;
      17: ldc_w         #331                // String Sent a version {} subscription and group\'s latest commonly supported version is {} (successful version probing and end of rolling upgrade). Upgrading subscription metadata version to {} for next rebalance.
      20: iconst_3
      21: anewarray     #203                // class java/lang/Object
      24: dup
      25: iconst_0
      26: aload_0
      27: getfield      #4                  // Field usedSubscriptionMetadataVersion:I
      30: invokestatic  #120                // Method java/lang/Integer.valueOf:(I)Ljava/lang/Integer;
      33: aastore
      34: dup
      35: iconst_1
      36: iload_2
      37: invokestatic  #120                // Method java/lang/Integer.valueOf:(I)Ljava/lang/Integer;
      40: aastore
      41: dup
      42: iconst_2
      43: iload_2
      44: invokestatic  #120                // Method java/lang/Integer.valueOf:(I)Ljava/lang/Integer;
      47: aastore
      48: invokeinterface #332,  3          // InterfaceMethod org/slf4j/Logger.info:(Ljava/lang/String;[Ljava/lang/Object;)V
      53: aload_0
      54: iload_2
      55: putfield      #4                  // Field usedSubscriptionMetadataVersion:I
      58: iconst_1
      59: ireturn
      60: iload_1
      61: aload_0
      62: getfield      #4                  // Field usedSubscriptionMetadataVersion:I
      65: if_icmpge     135
      68: aload_0
      69: getfield      #13                 // Field log:Lorg/slf4j/Logger;
      72: ldc_w         #333                // String Sent a version {} subscription and got version {} assignment back (successful version probing). Downgrade subscription metadata to commonly supported version {} and trigger new rebalance.
      75: iconst_3
      76: anewarray     #203                // class java/lang/Object
      79: dup
      80: iconst_0
      81: aload_0
      82: getfield      #4                  // Field usedSubscriptionMetadataVersion:I
      85: invokestatic  #120                // Method java/lang/Integer.valueOf:(I)Ljava/lang/Integer;
      88: aastore
      89: dup
      90: iconst_1
      91: iload_1
      92: invokestatic  #120                // Method java/lang/Integer.valueOf:(I)Ljava/lang/Integer;
      95: aastore
      96: dup
      97: iconst_2
      98: iload_2
      99: invokestatic  #120                // Method java/lang/Integer.valueOf:(I)Ljava/lang/Integer;
     102: aastore
     103: invokeinterface #332,  3          // InterfaceMethod org/slf4j/Logger.info:(Ljava/lang/String;[Ljava/lang/Object;)V
     108: aload_0
     109: iload_2
     110: putfield      #4                  // Field usedSubscriptionMetadataVersion:I
     113: iconst_1
     114: ireturn
     115: aload_0
     116: getfield      #13                 // Field log:Lorg/slf4j/Logger;
     119: ldc_w         #334                // String Received an assignment version {} that is less than the earliest version that allows version probing {}. If this is not during a rolling upgrade from version 2.0 or below, this is an error.
     122: iload_1
     123: invokestatic  #120                // Method java/lang/Integer.valueOf:(I)Ljava/lang/Integer;
     126: iconst_3
     127: invokestatic  #120                // Method java/lang/Integer.valueOf:(I)Ljava/lang/Integer;
     130: invokeinterface #247,  4          // InterfaceMethod org/slf4j/Logger.debug:(Ljava/lang/String;Ljava/lang/Object;Ljava/lang/Object;)V
     135: iconst_0
     136: ireturn

  public void onAssignment(org.apache.kafka.clients.consumer.ConsumerPartitionAssignor$Assignment, org.apache.kafka.clients.consumer.ConsumerGroupMetadata);
    Code:
       0: new           #44                 // class java/util/ArrayList
       3: dup
       4: aload_1
       5: invokevirtual #335                // Method org/apache/kafka/clients/consumer/ConsumerPartitionAssignor$Assignment.partitions:()Ljava/util/List;
       8: invokespecial #293                // Method java/util/ArrayList."<init>":(Ljava/util/Collection;)V
      11: astore_3
      12: aload_3
      13: getstatic     #336                // Field PARTITION_COMPARATOR:Ljava/util/Comparator;
      16: invokeinterface #337,  2          // InterfaceMethod java/util/List.sort:(Ljava/util/Comparator;)V
      21: aload_1
      22: invokevirtual #338                // Method org/apache/kafka/clients/consumer/ConsumerPartitionAssignor$Assignment.userData:()Ljava/nio/ByteBuffer;
      25: invokestatic  #339                // Method org/apache/kafka/streams/processor/internals/assignment/AssignmentInfo.decode:(Ljava/nio/ByteBuffer;)Lorg/apache/kafka/streams/processor/internals/assignment/AssignmentInfo;
      28: astore        4
      30: aload         4
      32: invokevirtual #340                // Method org/apache/kafka/streams/processor/internals/assignment/AssignmentInfo.errCode:()I
      35: getstatic     #269                // Field org/apache/kafka/streams/processor/internals/assignment/AssignorError.NONE:Lorg/apache/kafka/streams/processor/internals/assignment/AssignorError;
      38: invokevirtual #107                // Method org/apache/kafka/streams/processor/internals/assignment/AssignorError.code:()I
      41: if_icmpeq     57
      44: aload_0
      45: getfield      #20                 // Field assignmentErrorCode:Ljava/util/concurrent/atomic/AtomicInteger;
      48: aload         4
      50: invokevirtual #340                // Method org/apache/kafka/streams/processor/internals/assignment/AssignmentInfo.errCode:()I
      53: invokevirtual #341                // Method java/util/concurrent/atomic/AtomicInteger.set:(I)V
      56: return
      57: aload         4
      59: invokevirtual #342                // Method org/apache/kafka/streams/processor/internals/assignment/AssignmentInfo.version:()I
      62: istore        5
      64: aload         4
      66: invokevirtual #343                // Method org/apache/kafka/streams/processor/internals/assignment/AssignmentInfo.commonlySupportedVersion:()I
      69: istore        6
      71: aload_0
      72: iload         5
      74: iload         6
      76: invokespecial #344                // Method validateMetadataVersions:(II)V
      79: iload         5
      81: tableswitch   { // 1 to 7
                     1: 124
                     2: 165
                     3: 165
                     4: 165
                     5: 165
                     6: 210
                     7: 257
               default: 306
          }
     124: aload_3
     125: aload         4
     127: aload_0
     128: getfield      #8                  // Field logPrefix:Ljava/lang/String;
     131: invokestatic  #345                // Method validateActiveTaskEncoding:(Ljava/util/List;Lorg/apache/kafka/streams/processor/internals/assignment/AssignmentInfo;Ljava/lang/String;)V
     134: aload_3
     135: aload         4
     137: invokestatic  #346                // Method getActiveTasks:(Ljava/util/List;Lorg/apache/kafka/streams/processor/internals/assignment/AssignmentInfo;)Ljava/util/Map;
     140: astore        7
     142: invokestatic  #67                 // Method java/util/Collections.emptyMap:()Ljava/util/Map;
     145: astore        9
     147: invokestatic  #67                 // Method java/util/Collections.emptyMap:()Ljava/util/Map;
     150: astore        10
     152: invokestatic  #67                 // Method java/util/Collections.emptyMap:()Ljava/util/Map;
     155: astore        8
     157: ldc2_w        #250                // long 9223372036854775807l
     160: lstore        11
     162: goto          317
     165: aload_3
     166: aload         4
     168: aload_0
     169: getfield      #8                  // Field logPrefix:Ljava/lang/String;
     172: invokestatic  #345                // Method validateActiveTaskEncoding:(Ljava/util/List;Lorg/apache/kafka/streams/processor/internals/assignment/AssignmentInfo;Ljava/lang/String;)V
     175: aload_3
     176: aload         4
     178: invokestatic  #346                // Method getActiveTasks:(Ljava/util/List;Lorg/apache/kafka/streams/processor/internals/assignment/AssignmentInfo;)Ljava/util/Map;
     181: astore        7
     183: aload         4
     185: invokevirtual #347                // Method org/apache/kafka/streams/processor/internals/assignment/AssignmentInfo.partitionsByHost:()Ljava/util/Map;
     188: astore        9
     190: invokestatic  #67                 // Method java/util/Collections.emptyMap:()Ljava/util/Map;
     193: astore        10
     195: aload         9
     197: invokestatic  #348                // Method getTopicPartitionInfo:(Ljava/util/Map;)Ljava/util/Map;
     200: astore        8
     202: ldc2_w        #250                // long 9223372036854775807l
     205: lstore        11
     207: goto          317
     210: aload_3
     211: aload         4
     213: aload_0
     214: getfield      #8                  // Field logPrefix:Ljava/lang/String;
     217: invokestatic  #345                // Method validateActiveTaskEncoding:(Ljava/util/List;Lorg/apache/kafka/streams/processor/internals/assignment/AssignmentInfo;Ljava/lang/String;)V
     220: aload_3
     221: aload         4
     223: invokestatic  #346                // Method getActiveTasks:(Ljava/util/List;Lorg/apache/kafka/streams/processor/internals/assignment/AssignmentInfo;)Ljava/util/Map;
     226: astore        7
     228: aload         4
     230: invokevirtual #347                // Method org/apache/kafka/streams/processor/internals/assignment/AssignmentInfo.partitionsByHost:()Ljava/util/Map;
     233: astore        9
     235: aload         4
     237: invokevirtual #349                // Method org/apache/kafka/streams/processor/internals/assignment/AssignmentInfo.standbyPartitionByHost:()Ljava/util/Map;
     240: astore        10
     242: aload         9
     244: invokestatic  #348                // Method getTopicPartitionInfo:(Ljava/util/Map;)Ljava/util/Map;
     247: astore        8
     249: ldc2_w        #250                // long 9223372036854775807l
     252: lstore        11
     254: goto          317
     257: aload_3
     258: aload         4
     260: aload_0
     261: getfield      #8                  // Field logPrefix:Ljava/lang/String;
     264: invokestatic  #345                // Method validateActiveTaskEncoding:(Ljava/util/List;Lorg/apache/kafka/streams/processor/internals/assignment/AssignmentInfo;Ljava/lang/String;)V
     267: aload_3
     268: aload         4
     270: invokestatic  #346                // Method getActiveTasks:(Ljava/util/List;Lorg/apache/kafka/streams/processor/internals/assignment/AssignmentInfo;)Ljava/util/Map;
     273: astore        7
     275: aload         4
     277: invokevirtual #347                // Method org/apache/kafka/streams/processor/internals/assignment/AssignmentInfo.partitionsByHost:()Ljava/util/Map;
     280: astore        9
     282: aload         4
     284: invokevirtual #349                // Method org/apache/kafka/streams/processor/internals/assignment/AssignmentInfo.standbyPartitionByHost:()Ljava/util/Map;
     287: astore        10
     289: aload         9
     291: invokestatic  #348                // Method getTopicPartitionInfo:(Ljava/util/Map;)Ljava/util/Map;
     294: astore        8
     296: aload         4
     298: invokevirtual #350                // Method org/apache/kafka/streams/processor/internals/assignment/AssignmentInfo.nextRebalanceMs:()J
     301: lstore        11
     303: goto          317
     306: new           #122                // class java/lang/IllegalStateException
     309: dup
     310: ldc_w         #351                // String This code should never be reached. Please file a bug report at https://issues.apache.org/jira/projects/KAFKA/
     313: invokespecial #131                // Method java/lang/IllegalStateException."<init>":(Ljava/lang/String;)V
     316: athrow
     317: aload_0
     318: lload         11
     320: iload         5
     322: iload         6
     324: aload         9
     326: invokeinterface #158,  1          // InterfaceMethod java/util/Map.keySet:()Ljava/util/Set;
     331: invokespecial #352                // Method maybeScheduleFollowupRebalance:(JIILjava/util/Set;)V
     334: invokestatic  #353                // Method org/apache/kafka/common/Cluster.empty:()Lorg/apache/kafka/common/Cluster;
     337: aload         8
     339: invokevirtual #110                // Method org/apache/kafka/common/Cluster.withPartitions:(Ljava/util/Map;)Lorg/apache/kafka/common/Cluster;
     342: astore        13
     344: aload_0
     345: getfield      #18                 // Field streamsMetadataState:Lorg/apache/kafka/streams/processor/internals/StreamsMetadataState;
     348: aload         9
     350: aload         10
     352: aload         13
     354: invokevirtual #117                // Method org/apache/kafka/streams/processor/internals/StreamsMetadataState.onChange:(Ljava/util/Map;Ljava/util/Map;Lorg/apache/kafka/common/Cluster;)V
     357: aload_0
     358: getfield      #16                 // Field taskManager:Lorg/apache/kafka/streams/processor/internals/TaskManager;
     361: aload         7
     363: aload         4
     365: invokevirtual #354                // Method org/apache/kafka/streams/processor/internals/assignment/AssignmentInfo.standbyTasks:()Ljava/util/Map;
     368: invokevirtual #355                // Method org/apache/kafka/streams/processor/internals/TaskManager.handleAssignment:(Ljava/util/Map;Ljava/util/Map;)V
     371: return

  private void maybeScheduleFollowupRebalance(long, int, int, java.util.Set<org.apache.kafka.streams.state.HostInfo>);
    Code:
       0: aload_0
       1: iload_3
       2: iload         4
       4: invokevirtual #356                // Method maybeUpdateSubscriptionVersion:(II)Z
       7: ifeq          33
      10: aload_0
      11: getfield      #13                 // Field log:Lorg/slf4j/Logger;
      14: ldc_w         #357                // String Requested to schedule immediate rebalance due to version probing.
      17: invokeinterface #216,  2          // InterfaceMethod org/slf4j/Logger.info:(Ljava/lang/String;)V
      22: aload_0
      23: getfield      #22                 // Field nextScheduledRebalanceMs:Ljava/util/concurrent/atomic/AtomicLong;
      26: lconst_0
      27: invokevirtual #358                // Method java/util/concurrent/atomic/AtomicLong.set:(J)V
      30: goto          155
      33: aload_0
      34: aload         5
      36: invokespecial #359                // Method verifyHostInfo:(Ljava/util/Set;)Z
      39: ifne          69
      42: aload_0
      43: getfield      #13                 // Field log:Lorg/slf4j/Logger;
      46: ldc_w         #360                // String Requested to schedule immediate rebalance to update group with new host endpoint = {}.
      49: aload_0
      50: getfield      #30                 // Field userEndPoint:Ljava/lang/String;
      53: invokeinterface #276,  3          // InterfaceMethod org/slf4j/Logger.info:(Ljava/lang/String;Ljava/lang/Object;)V
      58: aload_0
      59: getfield      #22                 // Field nextScheduledRebalanceMs:Ljava/util/concurrent/atomic/AtomicLong;
      62: lconst_0
      63: invokevirtual #358                // Method java/util/concurrent/atomic/AtomicLong.set:(J)V
      66: goto          155
      69: lload_1
      70: lconst_0
      71: lcmp
      72: ifne          98
      75: aload_0
      76: getfield      #13                 // Field log:Lorg/slf4j/Logger;
      79: ldc_w         #361                // String Requested to schedule immediate rebalance for new tasks to be safely revoked from current owner.
      82: invokeinterface #216,  2          // InterfaceMethod org/slf4j/Logger.info:(Ljava/lang/String;)V
      87: aload_0
      88: getfield      #22                 // Field nextScheduledRebalanceMs:Ljava/util/concurrent/atomic/AtomicLong;
      91: lconst_0
      92: invokevirtual #358                // Method java/util/concurrent/atomic/AtomicLong.set:(J)V
      95: goto          155
      98: lload_1
      99: ldc2_w        #250                // long 9223372036854775807l
     102: lcmp
     103: ifge          133
     106: aload_0
     107: getfield      #13                 // Field log:Lorg/slf4j/Logger;
     110: ldc_w         #362                // String Requested to schedule probing rebalance for {} ms.
     113: lload_1
     114: invokestatic  #240                // Method java/lang/Long.valueOf:(J)Ljava/lang/Long;
     117: invokeinterface #276,  3          // InterfaceMethod org/slf4j/Logger.info:(Ljava/lang/String;Ljava/lang/Object;)V
     122: aload_0
     123: getfield      #22                 // Field nextScheduledRebalanceMs:Ljava/util/concurrent/atomic/AtomicLong;
     126: lload_1
     127: invokevirtual #358                // Method java/util/concurrent/atomic/AtomicLong.set:(J)V
     130: goto          155
     133: aload_0
     134: getfield      #13                 // Field log:Lorg/slf4j/Logger;
     137: ldc_w         #363                // String No followup rebalance was requested, resetting the rebalance schedule.
     140: invokeinterface #216,  2          // InterfaceMethod org/slf4j/Logger.info:(Ljava/lang/String;)V
     145: aload_0
     146: getfield      #22                 // Field nextScheduledRebalanceMs:Ljava/util/concurrent/atomic/AtomicLong;
     149: ldc2_w        #250                // long 9223372036854775807l
     152: invokevirtual #358                // Method java/util/concurrent/atomic/AtomicLong.set:(J)V
     155: return

  private boolean verifyHostInfo(java.util.Set<org.apache.kafka.streams.state.HostInfo>);
    Code:
       0: aload_0
       1: getfield      #30                 // Field userEndPoint:Ljava/lang/String;
       4: ifnull        32
       7: aload_1
       8: invokeinterface #195,  1          // InterfaceMethod java/util/Set.isEmpty:()Z
      13: ifne          32
      16: aload_0
      17: getfield      #30                 // Field userEndPoint:Ljava/lang/String;
      20: invokestatic  #364                // Method org/apache/kafka/streams/state/HostInfo.buildFromEndpoint:(Ljava/lang/String;)Lorg/apache/kafka/streams/state/HostInfo;
      23: astore_2
      24: aload_1
      25: aload_2
      26: invokeinterface #136,  2          // InterfaceMethod java/util/Set.contains:(Ljava/lang/Object;)Z
      31: ireturn
      32: iconst_1
      33: ireturn

  protected static java.util.Map<org.apache.kafka.streams.processor.TaskId, java.util.Set<org.apache.kafka.common.TopicPartition>> getActiveTasks(java.util.List<org.apache.kafka.common.TopicPartition>, org.apache.kafka.streams.processor.internals.assignment.AssignmentInfo);
    Code:
       0: new           #54                 // class java/util/HashMap
       3: dup
       4: invokespecial #55                 // Method java/util/HashMap."<init>":()V
       7: astore_2
       8: iconst_0
       9: istore_3
      10: iload_3
      11: aload_0
      12: invokeinterface #306,  1          // InterfaceMethod java/util/List.size:()I
      17: if_icmpge     77
      20: aload_0
      21: iload_3
      22: invokeinterface #365,  2          // InterfaceMethod java/util/List.get:(I)Ljava/lang/Object;
      27: checkcast     #153                // class org/apache/kafka/common/TopicPartition
      30: astore        4
      32: aload_1
      33: invokevirtual #366                // Method org/apache/kafka/streams/processor/internals/assignment/AssignmentInfo.activeTasks:()Ljava/util/List;
      36: iload_3
      37: invokeinterface #365,  2          // InterfaceMethod java/util/List.get:(I)Ljava/lang/Object;
      42: checkcast     #166                // class org/apache/kafka/streams/processor/TaskId
      45: astore        5
      47: aload_2
      48: aload         5
      50: invokedynamic #367,  0            // InvokeDynamic #9:apply:()Ljava/util/function/Function;
      55: invokeinterface #172,  3          // InterfaceMethod java/util/Map.computeIfAbsent:(Ljava/lang/Object;Ljava/util/function/Function;)Ljava/lang/Object;
      60: checkcast     #167                // class java/util/Set
      63: aload         4
      65: invokeinterface #173,  2          // InterfaceMethod java/util/Set.add:(Ljava/lang/Object;)Z
      70: pop
      71: iinc          3, 1
      74: goto          10
      77: aload_2
      78: areturn

  static java.util.Map<org.apache.kafka.common.TopicPartition, org.apache.kafka.common.PartitionInfo> getTopicPartitionInfo(java.util.Map<org.apache.kafka.streams.state.HostInfo, java.util.Set<org.apache.kafka.common.TopicPartition>>);
    Code:
       0: new           #54                 // class java/util/HashMap
       3: dup
       4: invokespecial #55                 // Method java/util/HashMap."<init>":()V
       7: astore_1
       8: aload_0
       9: invokeinterface #56,  1           // InterfaceMethod java/util/Map.values:()Ljava/util/Collection;
      14: invokeinterface #57,  1           // InterfaceMethod java/util/Collection.iterator:()Ljava/util/Iterator;
      19: astore_2
      20: aload_2
      21: invokeinterface #58,  1           // InterfaceMethod java/util/Iterator.hasNext:()Z
      26: ifeq          110
      29: aload_2
      30: invokeinterface #59,  1           // InterfaceMethod java/util/Iterator.next:()Ljava/lang/Object;
      35: checkcast     #167                // class java/util/Set
      38: astore_3
      39: aload_3
      40: invokeinterface #76,  1           // InterfaceMethod java/util/Set.iterator:()Ljava/util/Iterator;
      45: astore        4
      47: aload         4
      49: invokeinterface #58,  1           // InterfaceMethod java/util/Iterator.hasNext:()Z
      54: ifeq          107
      57: aload         4
      59: invokeinterface #59,  1           // InterfaceMethod java/util/Iterator.next:()Ljava/lang/Object;
      64: checkcast     #153                // class org/apache/kafka/common/TopicPartition
      67: astore        5
      69: aload_1
      70: aload         5
      72: new           #155                // class org/apache/kafka/common/PartitionInfo
      75: dup
      76: aload         5
      78: invokevirtual #224                // Method org/apache/kafka/common/TopicPartition.topic:()Ljava/lang/String;
      81: aload         5
      83: invokevirtual #368                // Method org/apache/kafka/common/TopicPartition.partition:()I
      86: aconst_null
      87: iconst_0
      88: anewarray     #156                // class org/apache/kafka/common/Node
      91: iconst_0
      92: anewarray     #156                // class org/apache/kafka/common/Node
      95: invokespecial #157                // Method org/apache/kafka/common/PartitionInfo."<init>":(Ljava/lang/String;ILorg/apache/kafka/common/Node;[Lorg/apache/kafka/common/Node;[Lorg/apache/kafka/common/Node;)V
      98: invokeinterface #71,  3           // InterfaceMethod java/util/Map.put:(Ljava/lang/Object;Ljava/lang/Object;)Ljava/lang/Object;
     103: pop
     104: goto          47
     107: goto          20
     110: aload_1
     111: areturn

  private static void validateActiveTaskEncoding(java.util.List<org.apache.kafka.common.TopicPartition>, org.apache.kafka.streams.processor.internals.assignment.AssignmentInfo, java.lang.String);
    Code:
       0: aload_0
       1: invokeinterface #306,  1          // InterfaceMethod java/util/List.size:()I
       6: aload_1
       7: invokevirtual #366                // Method org/apache/kafka/streams/processor/internals/assignment/AssignmentInfo.activeTasks:()Ljava/util/List;
      10: invokeinterface #306,  1          // InterfaceMethod java/util/List.size:()I
      15: if_icmpeq     74
      18: new           #104                // class org/apache/kafka/streams/errors/TaskAssignmentException
      21: dup
      22: ldc_w         #369                // String %sNumber of assigned partitions %d is not equal to the number of active taskIds %d, assignmentInfo=%s
      25: iconst_4
      26: anewarray     #203                // class java/lang/Object
      29: dup
      30: iconst_0
      31: aload_2
      32: aastore
      33: dup
      34: iconst_1
      35: aload_0
      36: invokeinterface #306,  1          // InterfaceMethod java/util/List.size:()I
      41: invokestatic  #120                // Method java/lang/Integer.valueOf:(I)Ljava/lang/Integer;
      44: aastore
      45: dup
      46: iconst_2
      47: aload_1
      48: invokevirtual #366                // Method org/apache/kafka/streams/processor/internals/assignment/AssignmentInfo.activeTasks:()Ljava/util/List;
      51: invokeinterface #306,  1          // InterfaceMethod java/util/List.size:()I
      56: invokestatic  #120                // Method java/lang/Integer.valueOf:(I)Ljava/lang/Integer;
      59: aastore
      60: dup
      61: iconst_3
      62: aload_1
      63: invokevirtual #370                // Method org/apache/kafka/streams/processor/internals/assignment/AssignmentInfo.toString:()Ljava/lang/String;
      66: aastore
      67: invokestatic  #371                // Method java/lang/String.format:(Ljava/lang/String;[Ljava/lang/Object;)Ljava/lang/String;
      70: invokespecial #141                // Method org/apache/kafka/streams/errors/TaskAssignmentException."<init>":(Ljava/lang/String;)V
      73: athrow
      74: return

  private void ensureCopartitioning(java.util.Collection<java.util.Set<java.lang.String>>, java.util.Map<java.lang.String, org.apache.kafka.streams.processor.internals.InternalTopicConfig>, org.apache.kafka.common.Cluster);
    Code:
       0: aload_1
       1: invokeinterface #57,  1           // InterfaceMethod java/util/Collection.iterator:()Ljava/util/Iterator;
       6: astore        4
       8: aload         4
      10: invokeinterface #58,  1           // InterfaceMethod java/util/Iterator.hasNext:()Z
      15: ifeq          44
      18: aload         4
      20: invokeinterface #59,  1           // InterfaceMethod java/util/Iterator.next:()Ljava/lang/Object;
      25: checkcast     #167                // class java/util/Set
      28: astore        5
      30: aload_0
      31: getfield      #36                 // Field copartitionedTopicsEnforcer:Lorg/apache/kafka/streams/processor/internals/assignment/CopartitionedTopicsEnforcer;
      34: aload         5
      36: aload_2
      37: aload_3
      38: invokevirtual #372                // Method org/apache/kafka/streams/processor/internals/assignment/CopartitionedTopicsEnforcer.enforce:(Ljava/util/Set;Ljava/util/Map;Lorg/apache/kafka/common/Cluster;)V
      41: goto          8
      44: return

  private int updateMinReceivedVersion(int, int);
    Code:
       0: iload_1
       1: iload_2
       2: invokestatic  #373                // Method java/lang/Math.min:(II)I
       5: ireturn

  private int updateMinSupportedVersion(int, int);
    Code:
       0: iload_1
       1: iload_2
       2: if_icmpge     27
       5: aload_0
       6: getfield      #13                 // Field log:Lorg/slf4j/Logger;
       9: ldc_w         #374                // String Downgrade the current minimum supported version {} to the smaller seen supported version {}
      12: iload_2
      13: invokestatic  #120                // Method java/lang/Integer.valueOf:(I)Ljava/lang/Integer;
      16: iload_1
      17: invokestatic  #120                // Method java/lang/Integer.valueOf:(I)Ljava/lang/Integer;
      20: invokeinterface #247,  4          // InterfaceMethod org/slf4j/Logger.debug:(Ljava/lang/String;Ljava/lang/Object;Ljava/lang/Object;)V
      25: iload_1
      26: ireturn
      27: aload_0
      28: getfield      #13                 // Field log:Lorg/slf4j/Logger;
      31: ldc_w         #375                // String Current minimum supported version remains at {}, last seen supported version was {}
      34: iload_2
      35: invokestatic  #120                // Method java/lang/Integer.valueOf:(I)Ljava/lang/Integer;
      38: iload_1
      39: invokestatic  #120                // Method java/lang/Integer.valueOf:(I)Ljava/lang/Integer;
      42: invokeinterface #247,  4          // InterfaceMethod org/slf4j/Logger.debug:(Ljava/lang/String;Ljava/lang/Object;Ljava/lang/Object;)V
      47: iload_2
      48: ireturn

  void setInternalTopicManager(org.apache.kafka.streams.processor.internals.InternalTopicManager);
    Code:
       0: aload_0
       1: aload_1
       2: putfield      #34                 // Field internalTopicManager:Lorg/apache/kafka/streams/processor/internals/InternalTopicManager;
       5: return

  org.apache.kafka.clients.consumer.ConsumerPartitionAssignor$RebalanceProtocol rebalanceProtocol();
    Code:
       0: aload_0
       1: getfield      #38                 // Field rebalanceProtocol:Lorg/apache/kafka/clients/consumer/ConsumerPartitionAssignor$RebalanceProtocol;
       4: areturn

  protected java.lang.String userEndPoint();
    Code:
       0: aload_0
       1: getfield      #30                 // Field userEndPoint:Ljava/lang/String;
       4: areturn

  protected org.apache.kafka.streams.processor.internals.TaskManager taskManager();
    Code:
       0: aload_0
       1: getfield      #16                 // Field taskManager:Lorg/apache/kafka/streams/processor/internals/TaskManager;
       4: areturn

  protected void handleRebalanceStart(java.util.Set<java.lang.String>);
    Code:
       0: aload_0
       1: getfield      #16                 // Field taskManager:Lorg/apache/kafka/streams/processor/internals/TaskManager;
       4: aload_1
       5: invokevirtual #376                // Method org/apache/kafka/streams/processor/internals/TaskManager.handleRebalanceStart:(Ljava/util/Set;)V
       8: return

  long acceptableRecoveryLag();
    Code:
       0: aload_0
       1: getfield      #26                 // Field assignmentConfigs:Lorg/apache/kafka/streams/processor/internals/assignment/AssignorConfiguration$AssignmentConfigs;
       4: getfield      #377                // Field org/apache/kafka/streams/processor/internals/assignment/AssignorConfiguration$AssignmentConfigs.acceptableRecoveryLag:J
       7: lreturn

  int maxWarmupReplicas();
    Code:
       0: aload_0
       1: getfield      #26                 // Field assignmentConfigs:Lorg/apache/kafka/streams/processor/internals/assignment/AssignorConfiguration$AssignmentConfigs;
       4: getfield      #378                // Field org/apache/kafka/streams/processor/internals/assignment/AssignorConfiguration$AssignmentConfigs.maxWarmupReplicas:I
       7: ireturn

  int numStandbyReplicas();
    Code:
       0: aload_0
       1: getfield      #26                 // Field assignmentConfigs:Lorg/apache/kafka/streams/processor/internals/assignment/AssignorConfiguration$AssignmentConfigs;
       4: getfield      #379                // Field org/apache/kafka/streams/processor/internals/assignment/AssignorConfiguration$AssignmentConfigs.numStandbyReplicas:I
       7: ireturn

  long probingRebalanceIntervalMs();
    Code:
       0: aload_0
       1: getfield      #26                 // Field assignmentConfigs:Lorg/apache/kafka/streams/processor/internals/assignment/AssignorConfiguration$AssignmentConfigs;
       4: getfield      #380                // Field org/apache/kafka/streams/processor/internals/assignment/AssignorConfiguration$AssignmentConfigs.probingRebalanceIntervalMs:J
       7: lreturn

  private static java.util.Set lambda$getActiveTasks$4(org.apache.kafka.streams.processor.TaskId);
    Code:
       0: new           #73                 // class java/util/HashSet
       3: dup
       4: invokespecial #74                 // Method java/util/HashSet."<init>":()V
       7: areturn

  private static java.lang.Long lambda$populateClientStatesMap$3(org.apache.kafka.streams.processor.TaskId);
    Code:
       0: ldc2_w        #381                // long -3l
       3: invokestatic  #240                // Method java/lang/Long.valueOf:(J)Ljava/lang/Long;
       6: areturn

  private static org.apache.kafka.streams.processor.TaskId lambda$populateClientStatesMap$2(org.apache.kafka.streams.processor.TaskId);
    Code:
       0: aload_0
       1: areturn

  private static org.apache.kafka.common.TopicPartition lambda$prepareChangelogTopics$1(org.apache.kafka.streams.processor.TaskId, java.lang.String);
    Code:
       0: new           #153                // class org/apache/kafka/common/TopicPartition
       3: dup
       4: aload_1
       5: aload_0
       6: getfield      #192                // Field org/apache/kafka/streams/processor/TaskId.partition:I
       9: invokespecial #154                // Method org/apache/kafka/common/TopicPartition."<init>":(Ljava/lang/String;I)V
      12: areturn

  private static java.util.Set lambda$populateTasksForMaps$0(java.lang.Integer);
    Code:
       0: new           #73                 // class java/util/HashSet
       3: dup
       4: invokespecial #74                 // Method java/util/HashSet."<init>":()V
       7: areturn

  static {};
    Code:
       0: invokestatic  #383                // Method java/util/UUID.randomUUID:()Ljava/util/UUID;
       3: putstatic     #87                 // Field FUTURE_ID:Ljava/util/UUID;
       6: invokedynamic #384,  0            // InvokeDynamic #10:apply:()Ljava/util/function/Function;
      11: invokestatic  #385                // InterfaceMethod java/util/Comparator.comparing:(Ljava/util/function/Function;)Ljava/util/Comparator;
      14: invokedynamic #386,  0            // InvokeDynamic #11:applyAsInt:()Ljava/util/function/ToIntFunction;
      19: invokeinterface #387,  2          // InterfaceMethod java/util/Comparator.thenComparingInt:(Ljava/util/function/ToIntFunction;)Ljava/util/Comparator;
      24: putstatic     #336                // Field PARTITION_COMPARATOR:Ljava/util/Comparator;
      27: return
}
