Compiled from "TypeBasedCandidateFilter.java"
public class org.mockito.internal.configuration.injection.filter.TypeBasedCandidateFilter implements org.mockito.internal.configuration.injection.filter.MockCandidateFilter {
  private final org.mockito.internal.configuration.injection.filter.MockCandidateFilter next;

  public org.mockito.internal.configuration.injection.filter.TypeBasedCandidateFilter(org.mockito.internal.configuration.injection.filter.MockCandidateFilter);
    Code:
       0: aload_0
       1: invokespecial #1                  // Method java/lang/Object."<init>":()V
       4: aload_0
       5: aload_1
       6: putfield      #2                  // Field next:Lorg/mockito/internal/configuration/injection/filter/MockCandidateFilter;
       9: return

  public org.mockito.internal.configuration.injection.filter.OngoingInjector filterCandidate(java.util.Collection<java.lang.Object>, java.lang.reflect.Field, java.util.List<java.lang.reflect.Field>, java.lang.Object);
    Code:
       0: new           #3                  // class java/util/ArrayList
       3: dup
       4: invokespecial #4                  // Method java/util/ArrayList."<init>":()V
       7: astore        5
       9: aload_1
      10: invokeinterface #5,  1            // InterfaceMethod java/util/Collection.iterator:()Ljava/util/Iterator;
      15: astore        6
      17: aload         6
      19: invokeinterface #6,  1            // InterfaceMethod java/util/Iterator.hasNext:()Z
      24: ifeq          64
      27: aload         6
      29: invokeinterface #7,  1            // InterfaceMethod java/util/Iterator.next:()Ljava/lang/Object;
      34: astore        7
      36: aload_2
      37: invokevirtual #8                  // Method java/lang/reflect/Field.getType:()Ljava/lang/Class;
      40: aload         7
      42: invokevirtual #9                  // Method java/lang/Object.getClass:()Ljava/lang/Class;
      45: invokevirtual #10                 // Method java/lang/Class.isAssignableFrom:(Ljava/lang/Class;)Z
      48: ifeq          61
      51: aload         5
      53: aload         7
      55: invokeinterface #11,  2           // InterfaceMethod java/util/List.add:(Ljava/lang/Object;)Z
      60: pop
      61: goto          17
      64: aload_0
      65: getfield      #2                  // Field next:Lorg/mockito/internal/configuration/injection/filter/MockCandidateFilter;
      68: aload         5
      70: aload_2
      71: aload_3
      72: aload         4
      74: invokeinterface #12,  5           // InterfaceMethod org/mockito/internal/configuration/injection/filter/MockCandidateFilter.filterCandidate:(Ljava/util/Collection;Ljava/lang/reflect/Field;Ljava/util/List;Ljava/lang/Object;)Lorg/mockito/internal/configuration/injection/filter/OngoingInjector;
      79: areturn
}
