Compiled from "AbstractAuthorizingInInterceptor.java"
public abstract class org.apache.cxf.interceptor.security.AbstractAuthorizingInInterceptor extends org.apache.cxf.phase.AbstractPhaseInterceptor<org.apache.cxf.message.Message> {
  private static final java.util.logging.Logger LOG;

  private static final java.lang.String ALL_ROLES;

  private boolean allowAnonymousUsers;

  public org.apache.cxf.interceptor.security.AbstractAuthorizingInInterceptor();
    Code:
       0: aload_0
       1: iconst_1
       2: invokespecial #1                  // Method "<init>":(Z)V
       5: return

  public org.apache.cxf.interceptor.security.AbstractAuthorizingInInterceptor(boolean);
    Code:
       0: aload_0
       1: aconst_null
       2: ldc           #2                  // String pre-invoke
       4: iload_1
       5: invokespecial #3                  // Method org/apache/cxf/phase/AbstractPhaseInterceptor."<init>":(Ljava/lang/String;Ljava/lang/String;Z)V
       8: aload_0
       9: iconst_1
      10: putfield      #4                  // Field allowAnonymousUsers:Z
      13: return

  public void handleMessage(org.apache.cxf.message.Message) throws org.apache.cxf.interceptor.Fault;
    Code:
       0: aload_0
       1: aload_1
       2: invokevirtual #5                  // Method getTargetMethod:(Lorg/apache/cxf/message/Message;)Ljava/lang/reflect/Method;
       5: astore_2
       6: aload_1
       7: ldc_w         #6                  // class org/apache/cxf/security/SecurityContext
      10: invokeinterface #7,  2            // InterfaceMethod org/apache/cxf/message/Message.get:(Ljava/lang/Class;)Ljava/lang/Object;
      15: checkcast     #6                  // class org/apache/cxf/security/SecurityContext
      18: astore_3
      19: aload_3
      20: ifnull        42
      23: aload_3
      24: invokeinterface #8,  1            // InterfaceMethod org/apache/cxf/security/SecurityContext.getUserPrincipal:()Ljava/security/Principal;
      29: ifnull        42
      32: aload_0
      33: aload_3
      34: aload_2
      35: invokevirtual #9                  // Method authorize:(Lorg/apache/cxf/security/SecurityContext;Ljava/lang/reflect/Method;)Z
      38: ifeq          58
      41: return
      42: aload_0
      43: aload_2
      44: invokevirtual #10                 // Method isMethodProtected:(Ljava/lang/reflect/Method;)Z
      47: ifne          58
      50: aload_0
      51: invokevirtual #11                 // Method isAllowAnonymousUsers:()Z
      54: ifeq          58
      57: return
      58: new           #12                 // class org/apache/cxf/interceptor/security/AccessDeniedException
      61: dup
      62: ldc           #13                 // String Unauthorized
      64: invokespecial #14                 // Method org/apache/cxf/interceptor/security/AccessDeniedException."<init>":(Ljava/lang/String;)V
      67: athrow

  protected java.lang.reflect.Method getTargetMethod(org.apache.cxf.message.Message);
    Code:
       0: aload_1
       1: invokeinterface #15,  1           // InterfaceMethod org/apache/cxf/message/Message.getExchange:()Lorg/apache/cxf/message/Exchange;
       6: invokeinterface #16,  1           // InterfaceMethod org/apache/cxf/message/Exchange.getBindingOperationInfo:()Lorg/apache/cxf/service/model/BindingOperationInfo;
      11: astore_2
      12: aload_2
      13: ifnull        50
      16: aload_1
      17: invokeinterface #15,  1           // InterfaceMethod org/apache/cxf/message/Message.getExchange:()Lorg/apache/cxf/message/Exchange;
      22: invokeinterface #17,  1           // InterfaceMethod org/apache/cxf/message/Exchange.getService:()Lorg/apache/cxf/service/Service;
      27: ldc_w         #18                 // class org/apache/cxf/service/invoker/MethodDispatcher
      30: invokevirtual #19                 // Method java/lang/Class.getName:()Ljava/lang/String;
      33: invokeinterface #20,  2           // InterfaceMethod org/apache/cxf/service/Service.get:(Ljava/lang/Object;)Ljava/lang/Object;
      38: checkcast     #18                 // class org/apache/cxf/service/invoker/MethodDispatcher
      41: astore_3
      42: aload_3
      43: aload_2
      44: invokeinterface #21,  2           // InterfaceMethod org/apache/cxf/service/invoker/MethodDispatcher.getMethod:(Lorg/apache/cxf/service/model/BindingOperationInfo;)Ljava/lang/reflect/Method;
      49: areturn
      50: aload_1
      51: ldc           #22                 // String org.apache.cxf.resource.method
      53: invokeinterface #23,  2           // InterfaceMethod org/apache/cxf/message/Message.get:(Ljava/lang/Object;)Ljava/lang/Object;
      58: checkcast     #24                 // class java/lang/reflect/Method
      61: astore_3
      62: aload_3
      63: ifnull        68
      66: aload_3
      67: areturn
      68: new           #12                 // class org/apache/cxf/interceptor/security/AccessDeniedException
      71: dup
      72: ldc           #25                 // String Method is not available : Unauthorized
      74: invokespecial #14                 // Method org/apache/cxf/interceptor/security/AccessDeniedException."<init>":(Ljava/lang/String;)V
      77: athrow

  protected boolean authorize(org.apache.cxf.security.SecurityContext, java.lang.reflect.Method);
    Code:
       0: aload_0
       1: aload_2
       2: invokevirtual #26                 // Method getExpectedRoles:(Ljava/lang/reflect/Method;)Ljava/util/List;
       5: astore_3
       6: aload_3
       7: invokeinterface #27,  1           // InterfaceMethod java/util/List.isEmpty:()Z
      12: ifeq          45
      15: aload_0
      16: aload_2
      17: invokevirtual #28                 // Method getDenyRoles:(Ljava/lang/reflect/Method;)Ljava/util/List;
      20: astore        4
      22: aload         4
      24: invokeinterface #27,  1           // InterfaceMethod java/util/List.isEmpty:()Z
      29: ifeq          36
      32: iconst_1
      33: goto          44
      36: aload_0
      37: aload_1
      38: aload         4
      40: iconst_1
      41: invokevirtual #29                 // Method isUserInRole:(Lorg/apache/cxf/security/SecurityContext;Ljava/util/List;Z)Z
      44: ireturn
      45: aload_0
      46: aload_1
      47: aload_3
      48: iconst_0
      49: invokevirtual #29                 // Method isUserInRole:(Lorg/apache/cxf/security/SecurityContext;Ljava/util/List;Z)Z
      52: ifeq          57
      55: iconst_1
      56: ireturn
      57: getstatic     #30                 // Field LOG:Ljava/util/logging/Logger;
      60: getstatic     #31                 // Field java/util/logging/Level.FINE:Ljava/util/logging/Level;
      63: invokevirtual #32                 // Method java/util/logging/Logger.isLoggable:(Ljava/util/logging/Level;)Z
      66: ifeq          104
      69: getstatic     #30                 // Field LOG:Ljava/util/logging/Logger;
      72: new           #33                 // class java/lang/StringBuilder
      75: dup
      76: invokespecial #34                 // Method java/lang/StringBuilder."<init>":()V
      79: aload_1
      80: invokeinterface #8,  1            // InterfaceMethod org/apache/cxf/security/SecurityContext.getUserPrincipal:()Ljava/security/Principal;
      85: invokeinterface #35,  1           // InterfaceMethod java/security/Principal.getName:()Ljava/lang/String;
      90: invokevirtual #36                 // Method java/lang/StringBuilder.append:(Ljava/lang/String;)Ljava/lang/StringBuilder;
      93: ldc           #37                 // String  is not authorized
      95: invokevirtual #36                 // Method java/lang/StringBuilder.append:(Ljava/lang/String;)Ljava/lang/StringBuilder;
      98: invokevirtual #38                 // Method java/lang/StringBuilder.toString:()Ljava/lang/String;
     101: invokevirtual #39                 // Method java/util/logging/Logger.fine:(Ljava/lang/String;)V
     104: iconst_0
     105: ireturn

  protected boolean isMethodProtected(java.lang.reflect.Method);
    Code:
       0: aload_0
       1: aload_1
       2: invokevirtual #26                 // Method getExpectedRoles:(Ljava/lang/reflect/Method;)Ljava/util/List;
       5: invokeinterface #27,  1           // InterfaceMethod java/util/List.isEmpty:()Z
      10: ifeq          26
      13: aload_0
      14: aload_1
      15: invokevirtual #28                 // Method getDenyRoles:(Ljava/lang/reflect/Method;)Ljava/util/List;
      18: invokeinterface #27,  1           // InterfaceMethod java/util/List.isEmpty:()Z
      23: ifne          30
      26: iconst_1
      27: goto          31
      30: iconst_0
      31: ireturn

  protected boolean isUserInRole(org.apache.cxf.security.SecurityContext, java.util.List<java.lang.String>, boolean);
    Code:
       0: aload_2
       1: invokeinterface #40,  1           // InterfaceMethod java/util/List.size:()I
       6: iconst_1
       7: if_icmpne     35
      10: ldc           #41                 // String *
      12: aload_2
      13: iconst_0
      14: invokeinterface #42,  2           // InterfaceMethod java/util/List.get:(I)Ljava/lang/Object;
      19: invokevirtual #43                 // Method java/lang/String.equals:(Ljava/lang/Object;)Z
      22: ifeq          35
      25: iload_3
      26: ifne          33
      29: iconst_1
      30: goto          34
      33: iconst_0
      34: ireturn
      35: aload_2
      36: invokeinterface #44,  1           // InterfaceMethod java/util/List.iterator:()Ljava/util/Iterator;
      41: astore        4
      43: aload         4
      45: invokeinterface #45,  1           // InterfaceMethod java/util/Iterator.hasNext:()Z
      50: ifeq          89
      53: aload         4
      55: invokeinterface #46,  1           // InterfaceMethod java/util/Iterator.next:()Ljava/lang/Object;
      60: checkcast     #47                 // class java/lang/String
      63: astore        5
      65: aload_1
      66: aload         5
      68: invokeinterface #48,  2           // InterfaceMethod org/apache/cxf/security/SecurityContext.isUserInRole:(Ljava/lang/String;)Z
      73: ifeq          86
      76: iload_3
      77: ifne          84
      80: iconst_1
      81: goto          85
      84: iconst_0
      85: ireturn
      86: goto          43
      89: iload_3
      90: ireturn

  protected abstract java.util.List<java.lang.String> getExpectedRoles(java.lang.reflect.Method);

  protected java.util.List<java.lang.String> getDenyRoles(java.lang.reflect.Method);
    Code:
       0: invokestatic  #49                 // Method java/util/Collections.emptyList:()Ljava/util/List;
       3: areturn

  public boolean isAllowAnonymousUsers();
    Code:
       0: aload_0
       1: getfield      #4                  // Field allowAnonymousUsers:Z
       4: ireturn

  public void setAllowAnonymousUsers(boolean);
    Code:
       0: aload_0
       1: iload_1
       2: putfield      #4                  // Field allowAnonymousUsers:Z
       5: return

  static {};
    Code:
       0: ldc_w         #50                 // class org/apache/cxf/interceptor/security/AbstractAuthorizingInInterceptor
       3: invokestatic  #51                 // Method org/apache/cxf/common/logging/LogUtils.getL7dLogger:(Ljava/lang/Class;)Ljava/util/logging/Logger;
       6: putstatic     #30                 // Field LOG:Ljava/util/logging/Logger;
       9: return
}
