Compiled from "ReconfigureOnChangeFilter.java"
class ch.qos.logback.classic.turbo.ReconfigureOnChangeFilter$ReconfiguringThread implements java.lang.Runnable {
  final ch.qos.logback.classic.turbo.ReconfigureOnChangeFilter this$0;

  ch.qos.logback.classic.turbo.ReconfigureOnChangeFilter$ReconfiguringThread(ch.qos.logback.classic.turbo.ReconfigureOnChangeFilter);
    Code:
       0: aload_0
       1: aload_1
       2: putfield      #1                  // Field this$0:Lch/qos/logback/classic/turbo/ReconfigureOnChangeFilter;
       5: aload_0
       6: invokespecial #2                  // Method java/lang/Object."<init>":()V
       9: return

  public void run();
    Code:
       0: aload_0
       1: getfield      #1                  // Field this$0:Lch/qos/logback/classic/turbo/ReconfigureOnChangeFilter;
       4: getfield      #3                  // Field ch/qos/logback/classic/turbo/ReconfigureOnChangeFilter.mainConfigurationURL:Ljava/net/URL;
       7: ifnonnull     20
      10: aload_0
      11: getfield      #1                  // Field this$0:Lch/qos/logback/classic/turbo/ReconfigureOnChangeFilter;
      14: ldc           #4                  // String Due to missing top level configuration file, skipping reconfiguration
      16: invokevirtual #5                  // Method ch/qos/logback/classic/turbo/ReconfigureOnChangeFilter.addInfo:(Ljava/lang/String;)V
      19: return
      20: aload_0
      21: getfield      #1                  // Field this$0:Lch/qos/logback/classic/turbo/ReconfigureOnChangeFilter;
      24: invokestatic  #6                  // Method ch/qos/logback/classic/turbo/ReconfigureOnChangeFilter.access$000:(Lch/qos/logback/classic/turbo/ReconfigureOnChangeFilter;)Lch/qos/logback/core/Context;
      27: checkcast     #7                  // class ch/qos/logback/classic/LoggerContext
      30: astore_1
      31: aload_0
      32: getfield      #1                  // Field this$0:Lch/qos/logback/classic/turbo/ReconfigureOnChangeFilter;
      35: new           #8                  // class java/lang/StringBuilder
      38: dup
      39: invokespecial #9                  // Method java/lang/StringBuilder."<init>":()V
      42: ldc           #10                 // String Will reset and reconfigure context named [
      44: invokevirtual #11                 // Method java/lang/StringBuilder.append:(Ljava/lang/String;)Ljava/lang/StringBuilder;
      47: aload_0
      48: getfield      #1                  // Field this$0:Lch/qos/logback/classic/turbo/ReconfigureOnChangeFilter;
      51: invokestatic  #12                 // Method ch/qos/logback/classic/turbo/ReconfigureOnChangeFilter.access$100:(Lch/qos/logback/classic/turbo/ReconfigureOnChangeFilter;)Lch/qos/logback/core/Context;
      54: invokeinterface #13,  1           // InterfaceMethod ch/qos/logback/core/Context.getName:()Ljava/lang/String;
      59: invokevirtual #11                 // Method java/lang/StringBuilder.append:(Ljava/lang/String;)Ljava/lang/StringBuilder;
      62: ldc           #14                 // String ]
      64: invokevirtual #11                 // Method java/lang/StringBuilder.append:(Ljava/lang/String;)Ljava/lang/StringBuilder;
      67: invokevirtual #15                 // Method java/lang/StringBuilder.toString:()Ljava/lang/String;
      70: invokevirtual #5                  // Method ch/qos/logback/classic/turbo/ReconfigureOnChangeFilter.addInfo:(Ljava/lang/String;)V
      73: aload_0
      74: getfield      #1                  // Field this$0:Lch/qos/logback/classic/turbo/ReconfigureOnChangeFilter;
      77: getfield      #3                  // Field ch/qos/logback/classic/turbo/ReconfigureOnChangeFilter.mainConfigurationURL:Ljava/net/URL;
      80: invokevirtual #16                 // Method java/net/URL.toString:()Ljava/lang/String;
      83: ldc           #17                 // String xml
      85: invokevirtual #18                 // Method java/lang/String.endsWith:(Ljava/lang/String;)Z
      88: ifeq          99
      91: aload_0
      92: aload_1
      93: invokespecial #19                 // Method performXMLConfiguration:(Lch/qos/logback/classic/LoggerContext;)V
      96: goto          151
      99: aload_0
     100: getfield      #1                  // Field this$0:Lch/qos/logback/classic/turbo/ReconfigureOnChangeFilter;
     103: getfield      #3                  // Field ch/qos/logback/classic/turbo/ReconfigureOnChangeFilter.mainConfigurationURL:Ljava/net/URL;
     106: invokevirtual #16                 // Method java/net/URL.toString:()Ljava/lang/String;
     109: ldc           #20                 // String groovy
     111: invokevirtual #18                 // Method java/lang/String.endsWith:(Ljava/lang/String;)Z
     114: ifeq          151
     117: invokestatic  #21                 // Method ch/qos/logback/classic/util/EnvUtil.isGroovyAvailable:()Z
     120: ifeq          142
     123: aload_1
     124: invokevirtual #22                 // Method ch/qos/logback/classic/LoggerContext.reset:()V
     127: aload_1
     128: aload_0
     129: aload_0
     130: getfield      #1                  // Field this$0:Lch/qos/logback/classic/turbo/ReconfigureOnChangeFilter;
     133: getfield      #3                  // Field ch/qos/logback/classic/turbo/ReconfigureOnChangeFilter.mainConfigurationURL:Ljava/net/URL;
     136: invokestatic  #23                 // Method ch/qos/logback/classic/gaffer/GafferUtil.runGafferConfiguratorOn:(Lch/qos/logback/classic/LoggerContext;Ljava/lang/Object;Ljava/net/URL;)V
     139: goto          151
     142: aload_0
     143: getfield      #1                  // Field this$0:Lch/qos/logback/classic/turbo/ReconfigureOnChangeFilter;
     146: ldc           #24                 // String Groovy classes are not available on the class path. ABORTING INITIALIZATION.
     148: invokevirtual #25                 // Method ch/qos/logback/classic/turbo/ReconfigureOnChangeFilter.addError:(Ljava/lang/String;)V
     151: return

  private void performXMLConfiguration(ch.qos.logback.classic.LoggerContext);
    Code:
       0: new           #26                 // class ch/qos/logback/classic/joran/JoranConfigurator
       3: dup
       4: invokespecial #27                 // Method ch/qos/logback/classic/joran/JoranConfigurator."<init>":()V
       7: astore_2
       8: aload_2
       9: aload_0
      10: getfield      #1                  // Field this$0:Lch/qos/logback/classic/turbo/ReconfigureOnChangeFilter;
      13: invokestatic  #28                 // Method ch/qos/logback/classic/turbo/ReconfigureOnChangeFilter.access$200:(Lch/qos/logback/classic/turbo/ReconfigureOnChangeFilter;)Lch/qos/logback/core/Context;
      16: invokevirtual #29                 // Method ch/qos/logback/classic/joran/JoranConfigurator.setContext:(Lch/qos/logback/core/Context;)V
      19: new           #30                 // class ch/qos/logback/core/status/StatusUtil
      22: dup
      23: aload_0
      24: getfield      #1                  // Field this$0:Lch/qos/logback/classic/turbo/ReconfigureOnChangeFilter;
      27: invokestatic  #31                 // Method ch/qos/logback/classic/turbo/ReconfigureOnChangeFilter.access$300:(Lch/qos/logback/classic/turbo/ReconfigureOnChangeFilter;)Lch/qos/logback/core/Context;
      30: invokespecial #32                 // Method ch/qos/logback/core/status/StatusUtil."<init>":(Lch/qos/logback/core/Context;)V
      33: astore_3
      34: aload_2
      35: invokevirtual #33                 // Method ch/qos/logback/classic/joran/JoranConfigurator.recallSafeConfiguration:()Ljava/util/List;
      38: astore        4
      40: aload_0
      41: getfield      #1                  // Field this$0:Lch/qos/logback/classic/turbo/ReconfigureOnChangeFilter;
      44: invokestatic  #34                 // Method ch/qos/logback/classic/turbo/ReconfigureOnChangeFilter.access$400:(Lch/qos/logback/classic/turbo/ReconfigureOnChangeFilter;)Lch/qos/logback/core/Context;
      47: invokestatic  #35                 // Method ch/qos/logback/core/joran/util/ConfigurationWatchListUtil.getMainWatchURL:(Lch/qos/logback/core/Context;)Ljava/net/URL;
      50: astore        5
      52: aload_1
      53: invokevirtual #22                 // Method ch/qos/logback/classic/LoggerContext.reset:()V
      56: invokestatic  #36                 // Method java/lang/System.currentTimeMillis:()J
      59: lstore        6
      61: aload_2
      62: aload_0
      63: getfield      #1                  // Field this$0:Lch/qos/logback/classic/turbo/ReconfigureOnChangeFilter;
      66: getfield      #3                  // Field ch/qos/logback/classic/turbo/ReconfigureOnChangeFilter.mainConfigurationURL:Ljava/net/URL;
      69: invokevirtual #37                 // Method ch/qos/logback/classic/joran/JoranConfigurator.doConfigure:(Ljava/net/URL;)V
      72: aload_3
      73: lload         6
      75: invokevirtual #38                 // Method ch/qos/logback/core/status/StatusUtil.hasXMLParsingErrors:(J)Z
      78: ifeq          90
      81: aload_0
      82: aload_1
      83: aload         4
      85: aload         5
      87: invokespecial #39                 // Method fallbackConfiguration:(Lch/qos/logback/classic/LoggerContext;Ljava/util/List;Ljava/net/URL;)V
      90: goto          104
      93: astore        8
      95: aload_0
      96: aload_1
      97: aload         4
      99: aload         5
     101: invokespecial #39                 // Method fallbackConfiguration:(Lch/qos/logback/classic/LoggerContext;Ljava/util/List;Ljava/net/URL;)V
     104: return
    Exception table:
       from    to  target type
          61    90    93   Class ch/qos/logback/core/joran/spi/JoranException

  private void fallbackConfiguration(ch.qos.logback.classic.LoggerContext, java.util.List<ch.qos.logback.core.joran.event.SaxEvent>, java.net.URL);
    Code:
       0: new           #26                 // class ch/qos/logback/classic/joran/JoranConfigurator
       3: dup
       4: invokespecial #27                 // Method ch/qos/logback/classic/joran/JoranConfigurator."<init>":()V
       7: astore        4
       9: aload         4
      11: aload_0
      12: getfield      #1                  // Field this$0:Lch/qos/logback/classic/turbo/ReconfigureOnChangeFilter;
      15: invokestatic  #41                 // Method ch/qos/logback/classic/turbo/ReconfigureOnChangeFilter.access$500:(Lch/qos/logback/classic/turbo/ReconfigureOnChangeFilter;)Lch/qos/logback/core/Context;
      18: invokevirtual #29                 // Method ch/qos/logback/classic/joran/JoranConfigurator.setContext:(Lch/qos/logback/core/Context;)V
      21: aload_2
      22: ifnull        91
      25: aload_0
      26: getfield      #1                  // Field this$0:Lch/qos/logback/classic/turbo/ReconfigureOnChangeFilter;
      29: ldc           #42                 // String Falling back to previously registered safe configuration.
      31: invokevirtual #43                 // Method ch/qos/logback/classic/turbo/ReconfigureOnChangeFilter.addWarn:(Ljava/lang/String;)V
      34: aload_1
      35: invokevirtual #22                 // Method ch/qos/logback/classic/LoggerContext.reset:()V
      38: aload         4
      40: pop
      41: aload_0
      42: getfield      #1                  // Field this$0:Lch/qos/logback/classic/turbo/ReconfigureOnChangeFilter;
      45: invokestatic  #44                 // Method ch/qos/logback/classic/turbo/ReconfigureOnChangeFilter.access$600:(Lch/qos/logback/classic/turbo/ReconfigureOnChangeFilter;)Lch/qos/logback/core/Context;
      48: aload_3
      49: invokestatic  #45                 // Method ch/qos/logback/classic/joran/JoranConfigurator.informContextOfURLUsedForConfiguration:(Lch/qos/logback/core/Context;Ljava/net/URL;)V
      52: aload         4
      54: aload_2
      55: invokevirtual #46                 // Method ch/qos/logback/classic/joran/JoranConfigurator.doConfigure:(Ljava/util/List;)V
      58: aload_0
      59: getfield      #1                  // Field this$0:Lch/qos/logback/classic/turbo/ReconfigureOnChangeFilter;
      62: ldc           #47                 // String Re-registering previous fallback configuration once more as a fallback configuration point
      64: invokevirtual #5                  // Method ch/qos/logback/classic/turbo/ReconfigureOnChangeFilter.addInfo:(Ljava/lang/String;)V
      67: aload         4
      69: invokevirtual #48                 // Method ch/qos/logback/classic/joran/JoranConfigurator.registerSafeConfiguration:()V
      72: goto          100
      75: astore        5
      77: aload_0
      78: getfield      #1                  // Field this$0:Lch/qos/logback/classic/turbo/ReconfigureOnChangeFilter;
      81: ldc           #49                 // String Unexpected exception thrown by a configuration considered safe.
      83: aload         5
      85: invokevirtual #50                 // Method ch/qos/logback/classic/turbo/ReconfigureOnChangeFilter.addError:(Ljava/lang/String;Ljava/lang/Throwable;)V
      88: goto          100
      91: aload_0
      92: getfield      #1                  // Field this$0:Lch/qos/logback/classic/turbo/ReconfigureOnChangeFilter;
      95: ldc           #51                 // String No previous configuration to fall back on.
      97: invokevirtual #43                 // Method ch/qos/logback/classic/turbo/ReconfigureOnChangeFilter.addWarn:(Ljava/lang/String;)V
     100: return
    Exception table:
       from    to  target type
          34    72    75   Class ch/qos/logback/core/joran/spi/JoranException
}
