Compiled from "ReconfigureOnChangeFilter.java"
public class ch.qos.logback.classic.turbo.ReconfigureOnChangeFilter extends ch.qos.logback.classic.turbo.TurboFilter {
  public static final long DEFAULT_REFRESH_PERIOD;

  long refreshPeriod;

  java.net.URL mainConfigurationURL;

  protected volatile long nextCheck;

  ch.qos.logback.core.joran.spi.ConfigurationWatchList configurationWatchList;

  private long invocationCounter;

  private volatile long mask;

  private volatile long lastMaskCheck;

  private static final int MAX_MASK;

  private static final long MASK_INCREASE_THRESHOLD;

  private static final long MASK_DECREASE_THRESHOLD;

  public ch.qos.logback.classic.turbo.ReconfigureOnChangeFilter();
    Code:
       0: aload_0
       1: invokespecial #2                  // Method ch/qos/logback/classic/turbo/TurboFilter."<init>":()V
       4: aload_0
       5: ldc2_w        #3                  // long 60000l
       8: putfield      #5                  // Field refreshPeriod:J
      11: aload_0
      12: lconst_0
      13: putfield      #6                  // Field invocationCounter:J
      16: aload_0
      17: ldc2_w        #7                  // long 15l
      20: putfield      #9                  // Field mask:J
      23: aload_0
      24: invokestatic  #10                 // Method java/lang/System.currentTimeMillis:()J
      27: putfield      #11                 // Field lastMaskCheck:J
      30: return

  public void start();
    Code:
       0: aload_0
       1: aload_0
       2: getfield      #1                  // Field context:Lch/qos/logback/core/Context;
       5: invokestatic  #12                 // Method ch/qos/logback/core/joran/util/ConfigurationWatchListUtil.getConfigurationWatchList:(Lch/qos/logback/core/Context;)Lch/qos/logback/core/joran/spi/ConfigurationWatchList;
       8: putfield      #13                 // Field configurationWatchList:Lch/qos/logback/core/joran/spi/ConfigurationWatchList;
      11: aload_0
      12: getfield      #13                 // Field configurationWatchList:Lch/qos/logback/core/joran/spi/ConfigurationWatchList;
      15: ifnull        133
      18: aload_0
      19: aload_0
      20: getfield      #13                 // Field configurationWatchList:Lch/qos/logback/core/joran/spi/ConfigurationWatchList;
      23: invokevirtual #14                 // Method ch/qos/logback/core/joran/spi/ConfigurationWatchList.getMainURL:()Ljava/net/URL;
      26: putfield      #15                 // Field mainConfigurationURL:Ljava/net/URL;
      29: aload_0
      30: getfield      #15                 // Field mainConfigurationURL:Ljava/net/URL;
      33: ifnonnull     43
      36: aload_0
      37: ldc           #16                 // String Due to missing top level configuration file, automatic reconfiguration is impossible.
      39: invokevirtual #17                 // Method addWarn:(Ljava/lang/String;)V
      42: return
      43: aload_0
      44: getfield      #13                 // Field configurationWatchList:Lch/qos/logback/core/joran/spi/ConfigurationWatchList;
      47: invokevirtual #18                 // Method ch/qos/logback/core/joran/spi/ConfigurationWatchList.getCopyOfFileWatchList:()Ljava/util/List;
      50: astore_1
      51: aload_0
      52: getfield      #5                  // Field refreshPeriod:J
      55: ldc2_w        #19                 // long 1000l
      58: ldiv
      59: lstore_2
      60: aload_0
      61: new           #21                 // class java/lang/StringBuilder
      64: dup
      65: invokespecial #22                 // Method java/lang/StringBuilder."<init>":()V
      68: ldc           #23                 // String Will scan for changes in [
      70: invokevirtual #24                 // Method java/lang/StringBuilder.append:(Ljava/lang/String;)Ljava/lang/StringBuilder;
      73: aload_1
      74: invokevirtual #25                 // Method java/lang/StringBuilder.append:(Ljava/lang/Object;)Ljava/lang/StringBuilder;
      77: ldc           #26                 // String ] every
      79: invokevirtual #24                 // Method java/lang/StringBuilder.append:(Ljava/lang/String;)Ljava/lang/StringBuilder;
      82: lload_2
      83: invokevirtual #27                 // Method java/lang/StringBuilder.append:(J)Ljava/lang/StringBuilder;
      86: ldc           #28                 // String  seconds.
      88: invokevirtual #24                 // Method java/lang/StringBuilder.append:(Ljava/lang/String;)Ljava/lang/StringBuilder;
      91: invokevirtual #29                 // Method java/lang/StringBuilder.toString:()Ljava/lang/String;
      94: invokevirtual #30                 // Method addInfo:(Ljava/lang/String;)V
      97: aload_0
      98: getfield      #13                 // Field configurationWatchList:Lch/qos/logback/core/joran/spi/ConfigurationWatchList;
     101: dup
     102: astore        4
     104: monitorenter
     105: aload_0
     106: invokestatic  #10                 // Method java/lang/System.currentTimeMillis:()J
     109: invokevirtual #31                 // Method updateNextCheck:(J)V
     112: aload         4
     114: monitorexit
     115: goto          126
     118: astore        5
     120: aload         4
     122: monitorexit
     123: aload         5
     125: athrow
     126: aload_0
     127: invokespecial #32                 // Method ch/qos/logback/classic/turbo/TurboFilter.start:()V
     130: goto          139
     133: aload_0
     134: ldc           #33                 // String Empty ConfigurationWatchList in context
     136: invokevirtual #17                 // Method addWarn:(Ljava/lang/String;)V
     139: return
    Exception table:
       from    to  target type
         105   115   118   any
         118   123   118   any

  public java.lang.String toString();
    Code:
       0: new           #21                 // class java/lang/StringBuilder
       3: dup
       4: invokespecial #22                 // Method java/lang/StringBuilder."<init>":()V
       7: ldc           #34                 // String ReconfigureOnChangeFilter{invocationCounter=
       9: invokevirtual #24                 // Method java/lang/StringBuilder.append:(Ljava/lang/String;)Ljava/lang/StringBuilder;
      12: aload_0
      13: getfield      #6                  // Field invocationCounter:J
      16: invokevirtual #27                 // Method java/lang/StringBuilder.append:(J)Ljava/lang/StringBuilder;
      19: bipush        125
      21: invokevirtual #35                 // Method java/lang/StringBuilder.append:(C)Ljava/lang/StringBuilder;
      24: invokevirtual #29                 // Method java/lang/StringBuilder.toString:()Ljava/lang/String;
      27: areturn

  public ch.qos.logback.core.spi.FilterReply decide(org.slf4j.Marker, ch.qos.logback.classic.Logger, ch.qos.logback.classic.Level, java.lang.String, java.lang.Object[], java.lang.Throwable);
    Code:
       0: aload_0
       1: invokevirtual #36                 // Method isStarted:()Z
       4: ifne          11
       7: getstatic     #37                 // Field ch/qos/logback/core/spi/FilterReply.NEUTRAL:Lch/qos/logback/core/spi/FilterReply;
      10: areturn
      11: aload_0
      12: dup
      13: getfield      #6                  // Field invocationCounter:J
      16: dup2_x1
      17: lconst_1
      18: ladd
      19: putfield      #6                  // Field invocationCounter:J
      22: aload_0
      23: getfield      #9                  // Field mask:J
      26: land
      27: aload_0
      28: getfield      #9                  // Field mask:J
      31: lcmp
      32: ifeq          39
      35: getstatic     #37                 // Field ch/qos/logback/core/spi/FilterReply.NEUTRAL:Lch/qos/logback/core/spi/FilterReply;
      38: areturn
      39: invokestatic  #10                 // Method java/lang/System.currentTimeMillis:()J
      42: lstore        7
      44: aload_0
      45: getfield      #13                 // Field configurationWatchList:Lch/qos/logback/core/joran/spi/ConfigurationWatchList;
      48: dup
      49: astore        9
      51: monitorenter
      52: aload_0
      53: lload         7
      55: invokespecial #38                 // Method updateMaskIfNecessary:(J)V
      58: aload_0
      59: lload         7
      61: invokevirtual #39                 // Method changeDetected:(J)Z
      64: ifeq          75
      67: aload_0
      68: invokevirtual #40                 // Method disableSubsequentReconfiguration:()V
      71: aload_0
      72: invokevirtual #41                 // Method detachReconfigurationToNewThread:()V
      75: aload         9
      77: monitorexit
      78: goto          89
      81: astore        10
      83: aload         9
      85: monitorexit
      86: aload         10
      88: athrow
      89: getstatic     #37                 // Field ch/qos/logback/core/spi/FilterReply.NEUTRAL:Lch/qos/logback/core/spi/FilterReply;
      92: areturn
    Exception table:
       from    to  target type
          52    78    81   any
          81    86    81   any

  private void updateMaskIfNecessary(long);
    Code:
       0: lload_1
       1: aload_0
       2: getfield      #11                 // Field lastMaskCheck:J
       5: lsub
       6: lstore_3
       7: aload_0
       8: lload_1
       9: putfield      #11                 // Field lastMaskCheck:J
      12: lload_3
      13: ldc2_w        #42                 // long 100l
      16: lcmp
      17: ifge          46
      20: aload_0
      21: getfield      #9                  // Field mask:J
      24: ldc2_w        #44                 // long 65535l
      27: lcmp
      28: ifge          46
      31: aload_0
      32: aload_0
      33: getfield      #9                  // Field mask:J
      36: iconst_1
      37: lshl
      38: lconst_1
      39: lor
      40: putfield      #9                  // Field mask:J
      43: goto          64
      46: lload_3
      47: ldc2_w        #46                 // long 800l
      50: lcmp
      51: ifle          64
      54: aload_0
      55: aload_0
      56: getfield      #9                  // Field mask:J
      59: iconst_2
      60: lushr
      61: putfield      #9                  // Field mask:J
      64: return

  void detachReconfigurationToNewThread();
    Code:
       0: aload_0
       1: new           #21                 // class java/lang/StringBuilder
       4: dup
       5: invokespecial #22                 // Method java/lang/StringBuilder."<init>":()V
       8: ldc           #48                 // String Detected change in [
      10: invokevirtual #24                 // Method java/lang/StringBuilder.append:(Ljava/lang/String;)Ljava/lang/StringBuilder;
      13: aload_0
      14: getfield      #13                 // Field configurationWatchList:Lch/qos/logback/core/joran/spi/ConfigurationWatchList;
      17: invokevirtual #18                 // Method ch/qos/logback/core/joran/spi/ConfigurationWatchList.getCopyOfFileWatchList:()Ljava/util/List;
      20: invokevirtual #25                 // Method java/lang/StringBuilder.append:(Ljava/lang/Object;)Ljava/lang/StringBuilder;
      23: ldc           #49                 // String ]
      25: invokevirtual #24                 // Method java/lang/StringBuilder.append:(Ljava/lang/String;)Ljava/lang/StringBuilder;
      28: invokevirtual #29                 // Method java/lang/StringBuilder.toString:()Ljava/lang/String;
      31: invokevirtual #30                 // Method addInfo:(Ljava/lang/String;)V
      34: aload_0
      35: getfield      #1                  // Field context:Lch/qos/logback/core/Context;
      38: invokeinterface #50,  1           // InterfaceMethod ch/qos/logback/core/Context.getExecutorService:()Ljava/util/concurrent/ExecutorService;
      43: new           #51                 // class ch/qos/logback/classic/turbo/ReconfigureOnChangeFilter$ReconfiguringThread
      46: dup
      47: aload_0
      48: invokespecial #52                 // Method ch/qos/logback/classic/turbo/ReconfigureOnChangeFilter$ReconfiguringThread."<init>":(Lch/qos/logback/classic/turbo/ReconfigureOnChangeFilter;)V
      51: invokeinterface #53,  2           // InterfaceMethod java/util/concurrent/ExecutorService.submit:(Ljava/lang/Runnable;)Ljava/util/concurrent/Future;
      56: pop
      57: return

  void updateNextCheck(long);
    Code:
       0: aload_0
       1: lload_1
       2: aload_0
       3: getfield      #5                  // Field refreshPeriod:J
       6: ladd
       7: putfield      #54                 // Field nextCheck:J
      10: return

  protected boolean changeDetected(long);
    Code:
       0: lload_1
       1: aload_0
       2: getfield      #54                 // Field nextCheck:J
       5: lcmp
       6: iflt          22
       9: aload_0
      10: lload_1
      11: invokevirtual #31                 // Method updateNextCheck:(J)V
      14: aload_0
      15: getfield      #13                 // Field configurationWatchList:Lch/qos/logback/core/joran/spi/ConfigurationWatchList;
      18: invokevirtual #55                 // Method ch/qos/logback/core/joran/spi/ConfigurationWatchList.changeDetected:()Z
      21: ireturn
      22: iconst_0
      23: ireturn

  void disableSubsequentReconfiguration();
    Code:
       0: aload_0
       1: ldc2_w        #56                 // long 9223372036854775807l
       4: putfield      #54                 // Field nextCheck:J
       7: return

  public long getRefreshPeriod();
    Code:
       0: aload_0
       1: getfield      #5                  // Field refreshPeriod:J
       4: lreturn

  public void setRefreshPeriod(long);
    Code:
       0: aload_0
       1: lload_1
       2: putfield      #5                  // Field refreshPeriod:J
       5: return

  static ch.qos.logback.core.Context access$000(ch.qos.logback.classic.turbo.ReconfigureOnChangeFilter);
    Code:
       0: aload_0
       1: getfield      #1                  // Field context:Lch/qos/logback/core/Context;
       4: areturn

  static ch.qos.logback.core.Context access$100(ch.qos.logback.classic.turbo.ReconfigureOnChangeFilter);
    Code:
       0: aload_0
       1: getfield      #1                  // Field context:Lch/qos/logback/core/Context;
       4: areturn

  static ch.qos.logback.core.Context access$200(ch.qos.logback.classic.turbo.ReconfigureOnChangeFilter);
    Code:
       0: aload_0
       1: getfield      #1                  // Field context:Lch/qos/logback/core/Context;
       4: areturn

  static ch.qos.logback.core.Context access$300(ch.qos.logback.classic.turbo.ReconfigureOnChangeFilter);
    Code:
       0: aload_0
       1: getfield      #1                  // Field context:Lch/qos/logback/core/Context;
       4: areturn

  static ch.qos.logback.core.Context access$400(ch.qos.logback.classic.turbo.ReconfigureOnChangeFilter);
    Code:
       0: aload_0
       1: getfield      #1                  // Field context:Lch/qos/logback/core/Context;
       4: areturn

  static ch.qos.logback.core.Context access$500(ch.qos.logback.classic.turbo.ReconfigureOnChangeFilter);
    Code:
       0: aload_0
       1: getfield      #1                  // Field context:Lch/qos/logback/core/Context;
       4: areturn

  static ch.qos.logback.core.Context access$600(ch.qos.logback.classic.turbo.ReconfigureOnChangeFilter);
    Code:
       0: aload_0
       1: getfield      #1                  // Field context:Lch/qos/logback/core/Context;
       4: areturn
}
