Compiled from "SimpleELContext.java"
final class org.hibernate.validator.internal.engine.messageinterpolation.el.SimpleELContext$1 extends javax.el.CompositeELResolver {
  org.hibernate.validator.internal.engine.messageinterpolation.el.SimpleELContext$1();
    Code:
       0: aload_0
       1: invokespecial #1                  // Method javax/el/CompositeELResolver."<init>":()V
       4: aload_0
       5: new           #2                  // class org/hibernate/validator/internal/engine/messageinterpolation/el/RootResolver
       8: dup
       9: invokespecial #3                  // Method org/hibernate/validator/internal/engine/messageinterpolation/el/RootResolver."<init>":()V
      12: invokevirtual #4                  // Method add:(Ljavax/el/ELResolver;)V
      15: aload_0
      16: new           #5                  // class javax/el/StaticFieldELResolver
      19: dup
      20: invokespecial #6                  // Method javax/el/StaticFieldELResolver."<init>":()V
      23: invokevirtual #4                  // Method add:(Ljavax/el/ELResolver;)V
      26: aload_0
      27: new           #7                  // class javax/el/ArrayELResolver
      30: dup
      31: iconst_1
      32: invokespecial #8                  // Method javax/el/ArrayELResolver."<init>":(Z)V
      35: invokevirtual #4                  // Method add:(Ljavax/el/ELResolver;)V
      38: aload_0
      39: new           #9                  // class javax/el/ListELResolver
      42: dup
      43: iconst_1
      44: invokespecial #10                 // Method javax/el/ListELResolver."<init>":(Z)V
      47: invokevirtual #4                  // Method add:(Ljavax/el/ELResolver;)V
      50: aload_0
      51: new           #11                 // class javax/el/MapELResolver
      54: dup
      55: iconst_1
      56: invokespecial #12                 // Method javax/el/MapELResolver."<init>":(Z)V
      59: invokevirtual #4                  // Method add:(Ljavax/el/ELResolver;)V
      62: aload_0
      63: new           #13                 // class javax/el/ResourceBundleELResolver
      66: dup
      67: invokespecial #14                 // Method javax/el/ResourceBundleELResolver."<init>":()V
      70: invokevirtual #4                  // Method add:(Ljavax/el/ELResolver;)V
      73: aload_0
      74: new           #15                 // class javax/el/BeanELResolver
      77: dup
      78: iconst_1
      79: invokespecial #16                 // Method javax/el/BeanELResolver."<init>":(Z)V
      82: invokevirtual #4                  // Method add:(Ljavax/el/ELResolver;)V
      85: return
}
