Compiled from "ConfigurationSupplier.java"
public class io.dekorate.config.ConfigurationSupplier<C> implements java.util.function.Supplier<C>, java.lang.Comparable<io.dekorate.config.ConfigurationSupplier<C>> {
  private final io.dekorate.deps.kubernetes.api.builder.VisitableBuilder<C, ?> builder;

  private final boolean explicit;

  public static io.dekorate.config.ConfigurationSupplier<?> empty();
    Code:
       0: new           #1                  // class io/dekorate/config/ConfigurationSupplier
       3: dup
       4: aconst_null
       5: invokespecial #2                  // Method "<init>":(Lio/dekorate/deps/kubernetes/api/builder/VisitableBuilder;)V
       8: areturn

  public io.dekorate.config.ConfigurationSupplier(io.dekorate.deps.kubernetes.api.builder.VisitableBuilder<C, ?>);
    Code:
       0: aload_0
       1: aload_1
       2: iconst_0
       3: invokespecial #3                  // Method "<init>":(Lio/dekorate/deps/kubernetes/api/builder/VisitableBuilder;Z)V
       6: return

  public io.dekorate.config.ConfigurationSupplier(io.dekorate.deps.kubernetes.api.builder.VisitableBuilder<C, ?>, boolean);
    Code:
       0: aload_0
       1: invokespecial #4                  // Method java/lang/Object."<init>":()V
       4: aload_0
       5: aload_1
       6: putfield      #5                  // Field builder:Lio/dekorate/deps/kubernetes/api/builder/VisitableBuilder;
       9: aload_0
      10: iload_2
      11: putfield      #6                  // Field explicit:Z
      14: return

  public boolean hasConfiguration();
    Code:
       0: aload_0
       1: getfield      #5                  // Field builder:Lio/dekorate/deps/kubernetes/api/builder/VisitableBuilder;
       4: ifnull        11
       7: iconst_1
       8: goto          12
      11: iconst_0
      12: ireturn

  public boolean isExplicit();
    Code:
       0: aload_0
       1: getfield      #6                  // Field explicit:Z
       4: ireturn

  private void checkBuilder();
    Code:
       0: aload_0
       1: getfield      #5                  // Field builder:Lio/dekorate/deps/kubernetes/api/builder/VisitableBuilder;
       4: ifnonnull     17
       7: new           #7                  // class java/lang/IllegalStateException
      10: dup
      11: ldc           #8                  // String ConfigurationSupplier is empty.
      13: invokespecial #9                  // Method java/lang/IllegalStateException."<init>":(Ljava/lang/String;)V
      16: athrow
      17: return

  public C get();
    Code:
       0: aload_0
       1: invokespecial #10                 // Method checkBuilder:()V
       4: aload_0
       5: getfield      #5                  // Field builder:Lio/dekorate/deps/kubernetes/api/builder/VisitableBuilder;
       8: invokeinterface #11,  1           // InterfaceMethod io/dekorate/deps/kubernetes/api/builder/VisitableBuilder.build:()Ljava/lang/Object;
      13: areturn

  public io.dekorate.config.ConfigurationSupplier<C> configure(java.lang.Iterable<io.dekorate.kubernetes.config.Configurator>);
    Code:
       0: aload_0
       1: invokespecial #10                 // Method checkBuilder:()V
       4: aload_1
       5: aload_0
       6: invokedynamic #12,  0             // InvokeDynamic #0:accept:(Lio/dekorate/config/ConfigurationSupplier;)Ljava/util/function/Consumer;
      11: invokeinterface #13,  2           // InterfaceMethod java/lang/Iterable.forEach:(Ljava/util/function/Consumer;)V
      16: aload_0
      17: areturn

  public io.dekorate.config.ConfigurationSupplier<C> configure(io.dekorate.kubernetes.config.Configurator);
    Code:
       0: aload_0
       1: invokespecial #10                 // Method checkBuilder:()V
       4: aload_0
       5: getfield      #5                  // Field builder:Lio/dekorate/deps/kubernetes/api/builder/VisitableBuilder;
       8: aload_1
       9: invokeinterface #14,  2           // InterfaceMethod io/dekorate/deps/kubernetes/api/builder/VisitableBuilder.accept:(Lio/dekorate/deps/kubernetes/api/builder/Visitor;)Ljava/lang/Object;
      14: pop
      15: aload_0
      16: areturn

  public java.lang.reflect.Type getType();
    Code:
       0: aload_0
       1: invokespecial #10                 // Method checkBuilder:()V
       4: aload_0
       5: getfield      #5                  // Field builder:Lio/dekorate/deps/kubernetes/api/builder/VisitableBuilder;
       8: invokevirtual #15                 // Method java/lang/Object.getClass:()Ljava/lang/Class;
      11: astore_1
      12: aload_1
      13: invokevirtual #16                 // Method java/lang/Class.getGenericSuperclass:()Ljava/lang/reflect/Type;
      16: checkcast     #17                 // class java/lang/reflect/ParameterizedType
      19: astore_2
      20: aload_2
      21: invokeinterface #18,  1           // InterfaceMethod java/lang/reflect/ParameterizedType.getActualTypeArguments:()[Ljava/lang/reflect/Type;
      26: iconst_0
      27: aaload
      28: areturn

  public int compareTo(io.dekorate.config.ConfigurationSupplier<C>);
    Code:
       0: iconst_0
       1: ireturn

  public int compareTo(java.lang.Object);
    Code:
       0: aload_0
       1: aload_1
       2: checkcast     #1                  // class io/dekorate/config/ConfigurationSupplier
       5: invokevirtual #19                 // Method compareTo:(Lio/dekorate/config/ConfigurationSupplier;)I
       8: ireturn

  private void lambda$configure$0(io.dekorate.kubernetes.config.Configurator);
    Code:
       0: aload_0
       1: getfield      #5                  // Field builder:Lio/dekorate/deps/kubernetes/api/builder/VisitableBuilder;
       4: aload_1
       5: invokeinterface #14,  2           // InterfaceMethod io/dekorate/deps/kubernetes/api/builder/VisitableBuilder.accept:(Lio/dekorate/deps/kubernetes/api/builder/Visitor;)Ljava/lang/Object;
      10: checkcast     #20                 // class io/dekorate/deps/kubernetes/api/builder/VisitableBuilder
      13: pop
      14: return
}
