Compiled from "SecurityProviderLoader.java"
public class org.owasp.esapi.crypto.SecurityProviderLoader {
  private static org.owasp.esapi.Logger logger;

  private static java.util.Hashtable<java.lang.String, java.lang.String> jceProviders;

  static final boolean $assertionsDisabled;

  public org.owasp.esapi.crypto.SecurityProviderLoader();
    Code:
       0: aload_0
       1: invokespecial #1                  // Method java/lang/Object."<init>":()V
       4: return

  public static int insertProviderAt(java.lang.String, int) throws java.security.NoSuchProviderException;
    Code:
       0: aconst_null
       1: astore_2
       2: aconst_null
       3: astore_3
       4: aconst_null
       5: astore        4
       7: getstatic     #2                  // Field $assertionsDisabled:Z
      10: ifne          33
      13: iload_1
      14: iconst_m1
      15: if_icmpeq     33
      18: iload_1
      19: iconst_1
      20: if_icmpge     33
      23: new           #3                  // class java/lang/AssertionError
      26: dup
      27: ldc           #4                  // String Position pos must be -1 or integer >= 1
      29: invokespecial #5                  // Method java/lang/AssertionError."<init>":(Ljava/lang/Object;)V
      32: athrow
      33: aload_0
      34: bipush        46
      36: invokevirtual #6                  // Method java/lang/String.indexOf:(I)I
      39: iconst_m1
      40: if_icmpeq     48
      43: aload_0
      44: astore_3
      45: goto          118
      48: getstatic     #7                  // Field jceProviders:Ljava/util/Hashtable;
      51: aload_0
      52: invokevirtual #8                  // Method java/util/Hashtable.containsKey:(Ljava/lang/Object;)Z
      55: ifeq          72
      58: getstatic     #7                  // Field jceProviders:Ljava/util/Hashtable;
      61: aload_0
      62: invokevirtual #9                  // Method java/util/Hashtable.get:(Ljava/lang/Object;)Ljava/lang/Object;
      65: checkcast     #10                 // class java/lang/String
      68: astore_3
      69: goto          118
      72: new           #11                 // class java/security/NoSuchProviderException
      75: dup
      76: new           #12                 // class java/lang/StringBuilder
      79: dup
      80: invokespecial #13                 // Method java/lang/StringBuilder."<init>":()V
      83: ldc           #14                 // String Unable to locate Provider class for provider
      85: invokevirtual #15                 // Method java/lang/StringBuilder.append:(Ljava/lang/String;)Ljava/lang/StringBuilder;
      88: aload_0
      89: invokevirtual #15                 // Method java/lang/StringBuilder.append:(Ljava/lang/String;)Ljava/lang/StringBuilder;
      92: ldc           #16                 // String . Try using fully qualified class name
      94: invokevirtual #15                 // Method java/lang/StringBuilder.append:(Ljava/lang/String;)Ljava/lang/StringBuilder;
      97: ldc           #17                 // String or check provider name for typos. Builtin provider names are:
      99: invokevirtual #15                 // Method java/lang/StringBuilder.append:(Ljava/lang/String;)Ljava/lang/StringBuilder;
     102: getstatic     #7                  // Field jceProviders:Ljava/util/Hashtable;
     105: invokevirtual #18                 // Method java/util/Hashtable.toString:()Ljava/lang/String;
     108: invokevirtual #15                 // Method java/lang/StringBuilder.append:(Ljava/lang/String;)Ljava/lang/StringBuilder;
     111: invokevirtual #19                 // Method java/lang/StringBuilder.toString:()Ljava/lang/String;
     114: invokespecial #20                 // Method java/security/NoSuchProviderException."<init>":(Ljava/lang/String;)V
     117: athrow
     118: aload_3
     119: invokestatic  #21                 // Method java/lang/Class.forName:(Ljava/lang/String;)Ljava/lang/Class;
     122: astore_2
     123: aload_2
     124: invokevirtual #22                 // Method java/lang/Class.newInstance:()Ljava/lang/Object;
     127: checkcast     #23                 // class java/security/Provider
     130: astore        4
     132: iload_1
     133: iconst_m1
     134: if_icmpne     147
     137: aload         4
     139: invokestatic  #24                 // Method java/security/Security.addProvider:(Ljava/security/Provider;)I
     142: istore        5
     144: goto          155
     147: aload         4
     149: iload_1
     150: invokestatic  #25                 // Method java/security/Security.insertProviderAt:(Ljava/security/Provider;I)I
     153: istore        5
     155: iload         5
     157: iconst_m1
     158: if_icmpne     255
     161: new           #12                 // class java/lang/StringBuilder
     164: dup
     165: invokespecial #13                 // Method java/lang/StringBuilder."<init>":()V
     168: ldc           #26                 // String JCE provider \'
     170: invokevirtual #15                 // Method java/lang/StringBuilder.append:(Ljava/lang/String;)Ljava/lang/StringBuilder;
     173: aload_0
     174: invokevirtual #15                 // Method java/lang/StringBuilder.append:(Ljava/lang/String;)Ljava/lang/StringBuilder;
     177: ldc           #27                 // String \' already loaded
     179: invokevirtual #15                 // Method java/lang/StringBuilder.append:(Ljava/lang/String;)Ljava/lang/StringBuilder;
     182: invokevirtual #19                 // Method java/lang/StringBuilder.toString:()Ljava/lang/String;
     185: astore        6
     187: iload_1
     188: iconst_m1
     189: if_icmpne     208
     192: getstatic     #28                 // Field logger:Lorg/owasp/esapi/Logger;
     195: getstatic     #29                 // Field org/owasp/esapi/Logger.SECURITY_SUCCESS:Lorg/owasp/esapi/Logger$EventType;
     198: aload         6
     200: invokeinterface #30,  3           // InterfaceMethod org/owasp/esapi/Logger.always:(Lorg/owasp/esapi/Logger$EventType;Ljava/lang/String;)V
     205: goto          252
     208: getstatic     #28                 // Field logger:Lorg/owasp/esapi/Logger;
     211: getstatic     #31                 // Field org/owasp/esapi/Logger.SECURITY_FAILURE:Lorg/owasp/esapi/Logger$EventType;
     214: aload         6
     216: invokeinterface #32,  3           // InterfaceMethod org/owasp/esapi/Logger.warning:(Lorg/owasp/esapi/Logger$EventType;Ljava/lang/String;)V
     221: getstatic     #28                 // Field logger:Lorg/owasp/esapi/Logger;
     224: getstatic     #31                 // Field org/owasp/esapi/Logger.SECURITY_FAILURE:Lorg/owasp/esapi/Logger$EventType;
     227: new           #12                 // class java/lang/StringBuilder
     230: dup
     231: invokespecial #13                 // Method java/lang/StringBuilder."<init>":()V
     234: ldc           #33                 // String (audit)
     236: invokevirtual #15                 // Method java/lang/StringBuilder.append:(Ljava/lang/String;)Ljava/lang/StringBuilder;
     239: aload         6
     241: invokevirtual #15                 // Method java/lang/StringBuilder.append:(Ljava/lang/String;)Ljava/lang/StringBuilder;
     244: invokevirtual #19                 // Method java/lang/StringBuilder.toString:()Ljava/lang/String;
     247: invokeinterface #30,  3           // InterfaceMethod org/owasp/esapi/Logger.always:(Lorg/owasp/esapi/Logger$EventType;Ljava/lang/String;)V
     252: goto          294
     255: getstatic     #28                 // Field logger:Lorg/owasp/esapi/Logger;
     258: getstatic     #34                 // Field org/owasp/esapi/Logger.SECURITY_AUDIT:Lorg/owasp/esapi/Logger$EventType;
     261: new           #12                 // class java/lang/StringBuilder
     264: dup
     265: invokespecial #13                 // Method java/lang/StringBuilder."<init>":()V
     268: ldc           #35                 // String Successfully loaded preferred JCE provider
     270: invokevirtual #15                 // Method java/lang/StringBuilder.append:(Ljava/lang/String;)Ljava/lang/StringBuilder;
     273: aload_0
     274: invokevirtual #15                 // Method java/lang/StringBuilder.append:(Ljava/lang/String;)Ljava/lang/StringBuilder;
     277: ldc           #36                 // String  at position
     279: invokevirtual #15                 // Method java/lang/StringBuilder.append:(Ljava/lang/String;)Ljava/lang/StringBuilder;
     282: iload_1
     283: invokevirtual #37                 // Method java/lang/StringBuilder.append:(I)Ljava/lang/StringBuilder;
     286: invokevirtual #19                 // Method java/lang/StringBuilder.toString:()Ljava/lang/String;
     289: invokeinterface #30,  3           // InterfaceMethod org/owasp/esapi/Logger.always:(Lorg/owasp/esapi/Logger$EventType;Ljava/lang/String;)V
     294: iload         5
     296: ireturn
     297: astore        5
     299: getstatic     #28                 // Field logger:Lorg/owasp/esapi/Logger;
     302: getstatic     #31                 // Field org/owasp/esapi/Logger.SECURITY_FAILURE:Lorg/owasp/esapi/Logger$EventType;
     305: new           #12                 // class java/lang/StringBuilder
     308: dup
     309: invokespecial #13                 // Method java/lang/StringBuilder."<init>":()V
     312: ldc           #39                 // String Failed to load preferred JCE provider
     314: invokevirtual #15                 // Method java/lang/StringBuilder.append:(Ljava/lang/String;)Ljava/lang/StringBuilder;
     317: aload_0
     318: invokevirtual #15                 // Method java/lang/StringBuilder.append:(Ljava/lang/String;)Ljava/lang/StringBuilder;
     321: ldc           #36                 // String  at position
     323: invokevirtual #15                 // Method java/lang/StringBuilder.append:(Ljava/lang/String;)Ljava/lang/StringBuilder;
     326: iload_1
     327: invokevirtual #37                 // Method java/lang/StringBuilder.append:(I)Ljava/lang/StringBuilder;
     330: invokevirtual #19                 // Method java/lang/StringBuilder.toString:()Ljava/lang/String;
     333: aload         5
     335: invokeinterface #40,  4           // InterfaceMethod org/owasp/esapi/Logger.always:(Lorg/owasp/esapi/Logger$EventType;Ljava/lang/String;Ljava/lang/Throwable;)V
     340: aload         5
     342: athrow
     343: astore        5
     345: getstatic     #28                 // Field logger:Lorg/owasp/esapi/Logger;
     348: getstatic     #42                 // Field org/owasp/esapi/Logger.EVENT_FAILURE:Lorg/owasp/esapi/Logger$EventType;
     351: new           #12                 // class java/lang/StringBuilder
     354: dup
     355: invokespecial #13                 // Method java/lang/StringBuilder."<init>":()V
     358: ldc           #43                 // String Failed to insert failed crypto  provider
     360: invokevirtual #15                 // Method java/lang/StringBuilder.append:(Ljava/lang/String;)Ljava/lang/StringBuilder;
     363: aload_0
     364: invokevirtual #15                 // Method java/lang/StringBuilder.append:(Ljava/lang/String;)Ljava/lang/StringBuilder;
     367: ldc           #36                 // String  at position
     369: invokevirtual #15                 // Method java/lang/StringBuilder.append:(Ljava/lang/String;)Ljava/lang/StringBuilder;
     372: iload_1
     373: invokevirtual #37                 // Method java/lang/StringBuilder.append:(I)Ljava/lang/StringBuilder;
     376: invokevirtual #19                 // Method java/lang/StringBuilder.toString:()Ljava/lang/String;
     379: aload         5
     381: invokeinterface #44,  4           // InterfaceMethod org/owasp/esapi/Logger.error:(Lorg/owasp/esapi/Logger$EventType;Ljava/lang/String;Ljava/lang/Throwable;)V
     386: new           #11                 // class java/security/NoSuchProviderException
     389: dup
     390: new           #12                 // class java/lang/StringBuilder
     393: dup
     394: invokespecial #13                 // Method java/lang/StringBuilder."<init>":()V
     397: ldc           #45                 // String Failed to insert crypto  provider for
     399: invokevirtual #15                 // Method java/lang/StringBuilder.append:(Ljava/lang/String;)Ljava/lang/StringBuilder;
     402: aload_0
     403: invokevirtual #15                 // Method java/lang/StringBuilder.append:(Ljava/lang/String;)Ljava/lang/StringBuilder;
     406: ldc           #46                 // String ; exception msg:
     408: invokevirtual #15                 // Method java/lang/StringBuilder.append:(Ljava/lang/String;)Ljava/lang/StringBuilder;
     411: aload         5
     413: invokevirtual #47                 // Method java/lang/Exception.toString:()Ljava/lang/String;
     416: invokevirtual #15                 // Method java/lang/StringBuilder.append:(Ljava/lang/String;)Ljava/lang/StringBuilder;
     419: invokevirtual #19                 // Method java/lang/StringBuilder.toString:()Ljava/lang/String;
     422: invokespecial #20                 // Method java/security/NoSuchProviderException."<init>":(Ljava/lang/String;)V
     425: athrow
    Exception table:
       from    to  target type
          33   296   297   Class java/lang/SecurityException
          33   296   343   Class java/lang/Exception

  public static int loadESAPIPreferredJCEProvider() throws java.security.NoSuchProviderException;
    Code:
       0: invokestatic  #48                 // Method org/owasp/esapi/ESAPI.securityConfiguration:()Lorg/owasp/esapi/SecurityConfiguration;
       3: invokeinterface #49,  1           // InterfaceMethod org/owasp/esapi/SecurityConfiguration.getPreferredJCEProvider:()Ljava/lang/String;
       8: astore_0
       9: aload_0
      10: ifnull        23
      13: aload_0
      14: invokevirtual #50                 // Method java/lang/String.trim:()Ljava/lang/String;
      17: invokevirtual #51                 // Method java/lang/String.length:()I
      20: ifne          38
      23: getstatic     #28                 // Field logger:Lorg/owasp/esapi/Logger;
      26: getstatic     #34                 // Field org/owasp/esapi/Logger.SECURITY_AUDIT:Lorg/owasp/esapi/Logger$EventType;
      29: ldc           #52                 // String No Encryptor.PreferredJCEProvider specified.
      31: invokeinterface #30,  3           // InterfaceMethod org/owasp/esapi/Logger.always:(Lorg/owasp/esapi/Logger$EventType;Ljava/lang/String;)V
      36: iconst_m1
      37: ireturn
      38: aload_0
      39: iconst_1
      40: invokestatic  #53                 // Method insertProviderAt:(Ljava/lang/String;I)I
      43: ireturn
      44: astore_1
      45: new           #12                 // class java/lang/StringBuilder
      48: dup
      49: invokespecial #13                 // Method java/lang/StringBuilder."<init>":()V
      52: ldc           #54                 // String failed to load *preferred* JCE crypto provider,
      54: invokevirtual #15                 // Method java/lang/StringBuilder.append:(Ljava/lang/String;)Ljava/lang/StringBuilder;
      57: aload_0
      58: invokevirtual #15                 // Method java/lang/StringBuilder.append:(Ljava/lang/String;)Ljava/lang/StringBuilder;
      61: invokevirtual #19                 // Method java/lang/StringBuilder.toString:()Ljava/lang/String;
      64: astore_2
      65: getstatic     #28                 // Field logger:Lorg/owasp/esapi/Logger;
      68: getstatic     #34                 // Field org/owasp/esapi/Logger.SECURITY_AUDIT:Lorg/owasp/esapi/Logger$EventType;
      71: aload_2
      72: invokeinterface #30,  3           // InterfaceMethod org/owasp/esapi/Logger.always:(Lorg/owasp/esapi/Logger$EventType;Ljava/lang/String;)V
      77: getstatic     #28                 // Field logger:Lorg/owasp/esapi/Logger;
      80: getstatic     #31                 // Field org/owasp/esapi/Logger.SECURITY_FAILURE:Lorg/owasp/esapi/Logger$EventType;
      83: aload_2
      84: invokeinterface #55,  3           // InterfaceMethod org/owasp/esapi/Logger.error:(Lorg/owasp/esapi/Logger$EventType;Ljava/lang/String;)V
      89: aload_1
      90: athrow
    Exception table:
       from    to  target type
           9    37    44   Class java/security/NoSuchProviderException
          38    43    44   Class java/security/NoSuchProviderException

  static {};
    Code:
       0: ldc_w         #56                 // class org/owasp/esapi/crypto/SecurityProviderLoader
       3: invokevirtual #57                 // Method java/lang/Class.desiredAssertionStatus:()Z
       6: ifne          13
       9: iconst_1
      10: goto          14
      13: iconst_0
      14: putstatic     #2                  // Field $assertionsDisabled:Z
      17: ldc           #58                 // String SecurityProviderLoader
      19: invokestatic  #59                 // Method org/owasp/esapi/ESAPI.getLogger:(Ljava/lang/String;)Lorg/owasp/esapi/Logger;
      22: putstatic     #28                 // Field logger:Lorg/owasp/esapi/Logger;
      25: new           #60                 // class java/util/Hashtable
      28: dup
      29: invokespecial #61                 // Method java/util/Hashtable."<init>":()V
      32: putstatic     #7                  // Field jceProviders:Ljava/util/Hashtable;
      35: getstatic     #7                  // Field jceProviders:Ljava/util/Hashtable;
      38: ldc           #62                 // String SunJCE
      40: ldc           #63                 // String com.sun.crypto.provider.SunJCE
      42: invokevirtual #64                 // Method java/util/Hashtable.put:(Ljava/lang/Object;Ljava/lang/Object;)Ljava/lang/Object;
      45: pop
      46: getstatic     #7                  // Field jceProviders:Ljava/util/Hashtable;
      49: ldc           #65                 // String IBMJCE
      51: ldc           #66                 // String com.ibm.crypto.provider.IBMJCE
      53: invokevirtual #64                 // Method java/util/Hashtable.put:(Ljava/lang/Object;Ljava/lang/Object;)Ljava/lang/Object;
      56: pop
      57: getstatic     #7                  // Field jceProviders:Ljava/util/Hashtable;
      60: ldc           #67                 // String GnuCrypto
      62: ldc           #68                 // String gnu.crypto.jce.GnuCrypto
      64: invokevirtual #64                 // Method java/util/Hashtable.put:(Ljava/lang/Object;Ljava/lang/Object;)Ljava/lang/Object;
      67: pop
      68: getstatic     #7                  // Field jceProviders:Ljava/util/Hashtable;
      71: ldc           #69                 // String BC
      73: ldc           #70                 // String org.bouncycastle.jce.provider.BouncyCastleProvider
      75: invokevirtual #64                 // Method java/util/Hashtable.put:(Ljava/lang/Object;Ljava/lang/Object;)Ljava/lang/Object;
      78: pop
      79: getstatic     #7                  // Field jceProviders:Ljava/util/Hashtable;
      82: ldc           #71                 // String IAIK
      84: ldc           #72                 // String iaik.security.provider.IAIK
      86: invokevirtual #64                 // Method java/util/Hashtable.put:(Ljava/lang/Object;Ljava/lang/Object;)Ljava/lang/Object;
      89: pop
      90: getstatic     #7                  // Field jceProviders:Ljava/util/Hashtable;
      93: ldc           #73                 // String CryptixCrypto
      95: ldc           #74                 // String cryptix.jce.provider.CryptixCrypto
      97: invokevirtual #64                 // Method java/util/Hashtable.put:(Ljava/lang/Object;Ljava/lang/Object;)Ljava/lang/Object;
     100: pop
     101: getstatic     #7                  // Field jceProviders:Ljava/util/Hashtable;
     104: ldc           #75                 // String Cryptix
     106: ldc           #74                 // String cryptix.jce.provider.CryptixCrypto
     108: invokevirtual #64                 // Method java/util/Hashtable.put:(Ljava/lang/Object;Ljava/lang/Object;)Ljava/lang/Object;
     111: pop
     112: getstatic     #7                  // Field jceProviders:Ljava/util/Hashtable;
     115: ldc           #76                 // String ABA
     117: ldc           #77                 // String au.net.aba.crypto.provider.ABAProvider
     119: invokevirtual #64                 // Method java/util/Hashtable.put:(Ljava/lang/Object;Ljava/lang/Object;)Ljava/lang/Object;
     122: pop
     123: return
}
