Compiled from "WatchResponse.java"
class io.etcd.jetcd.watch.WatchResponse$1 {
  static final int[] $SwitchMap$io$etcd$jetcd$api$Event$EventType;

  static {};
    Code:
       0: invokestatic  #1                  // Method io/etcd/jetcd/api/Event$EventType.values:()[Lio/etcd/jetcd/api/Event$EventType;
       3: arraylength
       4: newarray       int
       6: putstatic     #2                  // Field $SwitchMap$io$etcd$jetcd$api$Event$EventType:[I
       9: getstatic     #2                  // Field $SwitchMap$io$etcd$jetcd$api$Event$EventType:[I
      12: getstatic     #3                  // Field io/etcd/jetcd/api/Event$EventType.DELETE:Lio/etcd/jetcd/api/Event$EventType;
      15: invokevirtual #4                  // Method io/etcd/jetcd/api/Event$EventType.ordinal:()I
      18: iconst_1
      19: iastore
      20: goto          24
      23: astore_0
      24: getstatic     #2                  // Field $SwitchMap$io$etcd$jetcd$api$Event$EventType:[I
      27: getstatic     #6                  // Field io/etcd/jetcd/api/Event$EventType.PUT:Lio/etcd/jetcd/api/Event$EventType;
      30: invokevirtual #4                  // Method io/etcd/jetcd/api/Event$EventType.ordinal:()I
      33: iconst_2
      34: iastore
      35: goto          39
      38: astore_0
      39: return
    Exception table:
       from    to  target type
           9    20    23   Class java/lang/NoSuchFieldError
          24    35    38   Class java/lang/NoSuchFieldError
}
