Compiled from "TypeDescription.java"
public abstract class org.modelmapper.internal.bytebuddy.description.type.TypeDescription$Generic$Visitor$Substitutor$WithoutTypeSubstitution extends org.modelmapper.internal.bytebuddy.description.type.TypeDescription$Generic$Visitor$Substitutor {
  public org.modelmapper.internal.bytebuddy.description.type.TypeDescription$Generic$Visitor$Substitutor$WithoutTypeSubstitution();
    Code:
       0: aload_0
       1: invokespecial #19                 // Method org/modelmapper/internal/bytebuddy/description/type/TypeDescription$Generic$Visitor$Substitutor."<init>":()V
       4: return

  public org.modelmapper.internal.bytebuddy.description.type.TypeDescription$Generic onNonGenericType(org.modelmapper.internal.bytebuddy.description.type.TypeDescription$Generic);
    Code:
       0: aload_1
       1: areturn

  protected org.modelmapper.internal.bytebuddy.description.type.TypeDescription$Generic onSimpleType(org.modelmapper.internal.bytebuddy.description.type.TypeDescription$Generic);
    Code:
       0: aload_1
       1: areturn

  public java.lang.Object onNonGenericType(org.modelmapper.internal.bytebuddy.description.type.TypeDescription$Generic);
    Code:
       0: aload_0
       1: aload_1
       2: invokevirtual #29                 // Method onNonGenericType:(Lorg/modelmapper/internal/bytebuddy/description/type/TypeDescription$Generic;)Lorg/modelmapper/internal/bytebuddy/description/type/TypeDescription$Generic;
       5: areturn

  public java.lang.Object onParameterizedType(org.modelmapper.internal.bytebuddy.description.type.TypeDescription$Generic);
    Code:
       0: aload_0
       1: aload_1
       2: invokespecial #32                 // Method org/modelmapper/internal/bytebuddy/description/type/TypeDescription$Generic$Visitor$Substitutor.onParameterizedType:(Lorg/modelmapper/internal/bytebuddy/description/type/TypeDescription$Generic;)Lorg/modelmapper/internal/bytebuddy/description/type/TypeDescription$Generic;
       5: areturn

  public java.lang.Object onWildcard(org.modelmapper.internal.bytebuddy.description.type.TypeDescription$Generic);
    Code:
       0: aload_0
       1: aload_1
       2: invokespecial #35                 // Method org/modelmapper/internal/bytebuddy/description/type/TypeDescription$Generic$Visitor$Substitutor.onWildcard:(Lorg/modelmapper/internal/bytebuddy/description/type/TypeDescription$Generic;)Lorg/modelmapper/internal/bytebuddy/description/type/TypeDescription$Generic;
       5: areturn

  public java.lang.Object onGenericArray(org.modelmapper.internal.bytebuddy.description.type.TypeDescription$Generic);
    Code:
       0: aload_0
       1: aload_1
       2: invokespecial #38                 // Method org/modelmapper/internal/bytebuddy/description/type/TypeDescription$Generic$Visitor$Substitutor.onGenericArray:(Lorg/modelmapper/internal/bytebuddy/description/type/TypeDescription$Generic;)Lorg/modelmapper/internal/bytebuddy/description/type/TypeDescription$Generic;
       5: areturn
}
