Compiled from "TypeDescription.java"
public abstract class org.modelmapper.internal.bytebuddy.description.type.TypeDescription$Generic$Builder {
  private static final java.lang.reflect.Type UNDEFINED;

  protected final java.util.List<? extends org.modelmapper.internal.bytebuddy.description.annotation.AnnotationDescription> annotations;

  protected org.modelmapper.internal.bytebuddy.description.type.TypeDescription$Generic$Builder(java.util.List<? extends org.modelmapper.internal.bytebuddy.description.annotation.AnnotationDescription>);
    Code:
       0: aload_0
       1: invokespecial #80                 // Method java/lang/Object."<init>":()V
       4: aload_0
       5: aload_1
       6: putfield      #82                 // Field annotations:Ljava/util/List;
       9: return

  public static org.modelmapper.internal.bytebuddy.description.type.TypeDescription$Generic$Builder rawType(java.lang.Class<?>);
    Code:
       0: new           #31                 // class org/modelmapper/internal/bytebuddy/description/type/TypeDescription$ForLoadedType
       3: dup
       4: aload_0
       5: invokespecial #89                 // Method org/modelmapper/internal/bytebuddy/description/type/TypeDescription$ForLoadedType."<init>":(Ljava/lang/Class;)V
       8: invokestatic  #92                 // Method rawType:(Lorg/modelmapper/internal/bytebuddy/description/type/TypeDescription;)Lorg/modelmapper/internal/bytebuddy/description/type/TypeDescription$Generic$Builder;
      11: areturn

  public static org.modelmapper.internal.bytebuddy.description.type.TypeDescription$Generic$Builder rawType(org.modelmapper.internal.bytebuddy.description.type.TypeDescription);
    Code:
       0: new           #23                 // class org/modelmapper/internal/bytebuddy/description/type/TypeDescription$Generic$Builder$OfNonGenericType
       3: dup
       4: aload_0
       5: invokespecial #98                 // Method org/modelmapper/internal/bytebuddy/description/type/TypeDescription$Generic$Builder$OfNonGenericType."<init>":(Lorg/modelmapper/internal/bytebuddy/description/type/TypeDescription;)V
       8: areturn

  public static org.modelmapper.internal.bytebuddy.description.type.TypeDescription$Generic$Builder rawType(java.lang.Class<?>, org.modelmapper.internal.bytebuddy.description.type.TypeDescription$Generic);
    Code:
       0: new           #31                 // class org/modelmapper/internal/bytebuddy/description/type/TypeDescription$ForLoadedType
       3: dup
       4: aload_0
       5: invokespecial #89                 // Method org/modelmapper/internal/bytebuddy/description/type/TypeDescription$ForLoadedType."<init>":(Ljava/lang/Class;)V
       8: aload_1
       9: invokestatic  #103                // Method rawType:(Lorg/modelmapper/internal/bytebuddy/description/type/TypeDescription;Lorg/modelmapper/internal/bytebuddy/description/type/TypeDescription$Generic;)Lorg/modelmapper/internal/bytebuddy/description/type/TypeDescription$Generic$Builder;
      12: areturn

  public static org.modelmapper.internal.bytebuddy.description.type.TypeDescription$Generic$Builder rawType(org.modelmapper.internal.bytebuddy.description.type.TypeDescription, org.modelmapper.internal.bytebuddy.description.type.TypeDescription$Generic);
    Code:
       0: aload_0
       1: invokeinterface #109,  1          // InterfaceMethod org/modelmapper/internal/bytebuddy/description/type/TypeDescription.getDeclaringType:()Lorg/modelmapper/internal/bytebuddy/description/type/TypeDescription;
       6: astore_2
       7: aload_2
       8: ifnonnull     46
      11: aload_1
      12: ifnull        46
      15: new           #111                // class java/lang/IllegalArgumentException
      18: dup
      19: new           #113                // class java/lang/StringBuilder
      22: dup
      23: invokespecial #114                // Method java/lang/StringBuilder."<init>":()V
      26: aload_0
      27: invokevirtual #118                // Method java/lang/StringBuilder.append:(Ljava/lang/Object;)Ljava/lang/StringBuilder;
      30: ldc           #120                // String  does not have a declaring type:
      32: invokevirtual #123                // Method java/lang/StringBuilder.append:(Ljava/lang/String;)Ljava/lang/StringBuilder;
      35: aload_1
      36: invokevirtual #118                // Method java/lang/StringBuilder.append:(Ljava/lang/Object;)Ljava/lang/StringBuilder;
      39: invokevirtual #127                // Method java/lang/StringBuilder.toString:()Ljava/lang/String;
      42: invokespecial #130                // Method java/lang/IllegalArgumentException."<init>":(Ljava/lang/String;)V
      45: athrow
      46: aload_2
      47: ifnull        98
      50: aload_1
      51: ifnull        67
      54: aload_2
      55: aload_1
      56: invokeinterface #133,  1          // InterfaceMethod org/modelmapper/internal/bytebuddy/description/type/TypeDescription$Generic.asErasure:()Lorg/modelmapper/internal/bytebuddy/description/type/TypeDescription;
      61: invokevirtual #137                // Method java/lang/Object.equals:(Ljava/lang/Object;)Z
      64: ifne          98
      67: new           #111                // class java/lang/IllegalArgumentException
      70: dup
      71: new           #113                // class java/lang/StringBuilder
      74: dup
      75: invokespecial #114                // Method java/lang/StringBuilder."<init>":()V
      78: aload_1
      79: invokevirtual #118                // Method java/lang/StringBuilder.append:(Ljava/lang/Object;)Ljava/lang/StringBuilder;
      82: ldc           #139                // String  is not the declaring type of
      84: invokevirtual #123                // Method java/lang/StringBuilder.append:(Ljava/lang/String;)Ljava/lang/StringBuilder;
      87: aload_0
      88: invokevirtual #118                // Method java/lang/StringBuilder.append:(Ljava/lang/Object;)Ljava/lang/StringBuilder;
      91: invokevirtual #127                // Method java/lang/StringBuilder.toString:()Ljava/lang/String;
      94: invokespecial #130                // Method java/lang/IllegalArgumentException."<init>":(Ljava/lang/String;)V
      97: athrow
      98: new           #23                 // class org/modelmapper/internal/bytebuddy/description/type/TypeDescription$Generic$Builder$OfNonGenericType
     101: dup
     102: aload_0
     103: aload_1
     104: invokespecial #142                // Method org/modelmapper/internal/bytebuddy/description/type/TypeDescription$Generic$Builder$OfNonGenericType."<init>":(Lorg/modelmapper/internal/bytebuddy/description/type/TypeDescription;Lorg/modelmapper/internal/bytebuddy/description/type/TypeDescription$Generic;)V
     107: areturn

  public static org.modelmapper.internal.bytebuddy.description.type.TypeDescription$Generic unboundWildcard();
    Code:
       0: invokestatic  #151                // Method java/util/Collections.emptySet:()Ljava/util/Set;
       3: invokestatic  #154                // Method unboundWildcard:(Ljava/util/Collection;)Lorg/modelmapper/internal/bytebuddy/description/type/TypeDescription$Generic;
       6: areturn

  public static org.modelmapper.internal.bytebuddy.description.type.TypeDescription$Generic unboundWildcard(java.lang.annotation.Annotation...);
    Code:
       0: aload_0
       1: invokestatic  #161                // Method java/util/Arrays.asList:([Ljava/lang/Object;)Ljava/util/List;
       4: invokestatic  #164                // Method unboundWildcard:(Ljava/util/List;)Lorg/modelmapper/internal/bytebuddy/description/type/TypeDescription$Generic;
       7: areturn

  public static org.modelmapper.internal.bytebuddy.description.type.TypeDescription$Generic unboundWildcard(java.util.List<? extends java.lang.annotation.Annotation>);
    Code:
       0: new           #34                 // class org/modelmapper/internal/bytebuddy/description/annotation/AnnotationList$ForLoadedAnnotations
       3: dup
       4: aload_0
       5: invokespecial #168                // Method org/modelmapper/internal/bytebuddy/description/annotation/AnnotationList$ForLoadedAnnotations."<init>":(Ljava/util/List;)V
       8: invokestatic  #154                // Method unboundWildcard:(Ljava/util/Collection;)Lorg/modelmapper/internal/bytebuddy/description/type/TypeDescription$Generic;
      11: areturn

  public static org.modelmapper.internal.bytebuddy.description.type.TypeDescription$Generic unboundWildcard(org.modelmapper.internal.bytebuddy.description.annotation.AnnotationDescription...);
    Code:
       0: aload_0
       1: invokestatic  #161                // Method java/util/Arrays.asList:([Ljava/lang/Object;)Ljava/util/List;
       4: invokestatic  #154                // Method unboundWildcard:(Ljava/util/Collection;)Lorg/modelmapper/internal/bytebuddy/description/type/TypeDescription$Generic;
       7: areturn

  public static org.modelmapper.internal.bytebuddy.description.type.TypeDescription$Generic unboundWildcard(java.util.Collection<? extends org.modelmapper.internal.bytebuddy.description.annotation.AnnotationDescription>);
    Code:
       0: new           #39                 // class org/modelmapper/internal/bytebuddy/description/annotation/AnnotationSource$Explicit
       3: dup
       4: new           #173                // class java/util/ArrayList
       7: dup
       8: aload_0
       9: invokespecial #176                // Method java/util/ArrayList."<init>":(Ljava/util/Collection;)V
      12: invokespecial #177                // Method org/modelmapper/internal/bytebuddy/description/annotation/AnnotationSource$Explicit."<init>":(Ljava/util/List;)V
      15: invokestatic  #181                // Method org/modelmapper/internal/bytebuddy/description/type/TypeDescription$Generic$OfWildcardType$Latent.unbounded:(Lorg/modelmapper/internal/bytebuddy/description/annotation/AnnotationSource;)Lorg/modelmapper/internal/bytebuddy/description/type/TypeDescription$Generic;
      18: areturn

  public static org.modelmapper.internal.bytebuddy.description.type.TypeDescription$Generic$Builder typeVariable(java.lang.String);
    Code:
       0: new           #14                 // class org/modelmapper/internal/bytebuddy/description/type/TypeDescription$Generic$Builder$OfTypeVariable
       3: dup
       4: aload_0
       5: invokespecial #186                // Method org/modelmapper/internal/bytebuddy/description/type/TypeDescription$Generic$Builder$OfTypeVariable."<init>":(Ljava/lang/String;)V
       8: areturn

  public static org.modelmapper.internal.bytebuddy.description.type.TypeDescription$Generic$Builder parameterizedType(java.lang.Class<?>, java.lang.reflect.Type...);
    Code:
       0: aload_0
       1: aload_1
       2: invokestatic  #161                // Method java/util/Arrays.asList:([Ljava/lang/Object;)Ljava/util/List;
       5: invokestatic  #193                // Method parameterizedType:(Ljava/lang/Class;Ljava/util/List;)Lorg/modelmapper/internal/bytebuddy/description/type/TypeDescription$Generic$Builder;
       8: areturn

  public static org.modelmapper.internal.bytebuddy.description.type.TypeDescription$Generic$Builder parameterizedType(java.lang.Class<?>, java.util.List<? extends java.lang.reflect.Type>);
    Code:
       0: aload_0
       1: getstatic     #197                // Field UNDEFINED:Ljava/lang/reflect/Type;
       4: aload_1
       5: invokestatic  #200                // Method parameterizedType:(Ljava/lang/Class;Ljava/lang/reflect/Type;Ljava/util/List;)Lorg/modelmapper/internal/bytebuddy/description/type/TypeDescription$Generic$Builder;
       8: areturn

  public static org.modelmapper.internal.bytebuddy.description.type.TypeDescription$Generic$Builder parameterizedType(java.lang.Class<?>, java.lang.reflect.Type, java.util.List<? extends java.lang.reflect.Type>);
    Code:
       0: new           #31                 // class org/modelmapper/internal/bytebuddy/description/type/TypeDescription$ForLoadedType
       3: dup
       4: aload_0
       5: invokespecial #89                 // Method org/modelmapper/internal/bytebuddy/description/type/TypeDescription$ForLoadedType."<init>":(Ljava/lang/Class;)V
       8: aload_1
       9: ifnonnull     16
      12: aconst_null
      13: goto          20
      16: aload_1
      17: invokestatic  #206                // Method org/modelmapper/internal/bytebuddy/description/type/TypeDefinition$Sort.describe:(Ljava/lang/reflect/Type;)Lorg/modelmapper/internal/bytebuddy/description/type/TypeDescription$Generic;
      20: new           #48                 // class org/modelmapper/internal/bytebuddy/description/type/TypeList$Generic$ForLoadedTypes
      23: dup
      24: aload_2
      25: invokespecial #213                // Method org/modelmapper/internal/bytebuddy/description/type/TypeList$Generic$ForLoadedTypes."<init>":(Ljava/util/List;)V
      28: invokestatic  #216                // Method parameterizedType:(Lorg/modelmapper/internal/bytebuddy/description/type/TypeDescription;Lorg/modelmapper/internal/bytebuddy/description/type/TypeDescription$Generic;Ljava/util/Collection;)Lorg/modelmapper/internal/bytebuddy/description/type/TypeDescription$Generic$Builder;
      31: areturn

  public static org.modelmapper.internal.bytebuddy.description.type.TypeDescription$Generic$Builder parameterizedType(org.modelmapper.internal.bytebuddy.description.type.TypeDescription, org.modelmapper.internal.bytebuddy.description.type.TypeDefinition...);
    Code:
       0: aload_0
       1: aload_1
       2: invokestatic  #161                // Method java/util/Arrays.asList:([Ljava/lang/Object;)Ljava/util/List;
       5: invokestatic  #220                // Method parameterizedType:(Lorg/modelmapper/internal/bytebuddy/description/type/TypeDescription;Ljava/util/Collection;)Lorg/modelmapper/internal/bytebuddy/description/type/TypeDescription$Generic$Builder;
       8: areturn

  public static org.modelmapper.internal.bytebuddy.description.type.TypeDescription$Generic$Builder parameterizedType(org.modelmapper.internal.bytebuddy.description.type.TypeDescription, java.util.Collection<? extends org.modelmapper.internal.bytebuddy.description.type.TypeDefinition>);
    Code:
       0: aload_0
       1: getstatic     #223                // Field org/modelmapper/internal/bytebuddy/description/type/TypeDescription$Generic.UNDEFINED:Lorg/modelmapper/internal/bytebuddy/description/type/TypeDescription$Generic;
       4: aload_1
       5: invokestatic  #216                // Method parameterizedType:(Lorg/modelmapper/internal/bytebuddy/description/type/TypeDescription;Lorg/modelmapper/internal/bytebuddy/description/type/TypeDescription$Generic;Ljava/util/Collection;)Lorg/modelmapper/internal/bytebuddy/description/type/TypeDescription$Generic$Builder;
       8: areturn

  public static org.modelmapper.internal.bytebuddy.description.type.TypeDescription$Generic$Builder parameterizedType(org.modelmapper.internal.bytebuddy.description.type.TypeDescription, org.modelmapper.internal.bytebuddy.description.type.TypeDescription$Generic, java.util.Collection<? extends org.modelmapper.internal.bytebuddy.description.type.TypeDefinition>);
    Code:
       0: aload_0
       1: invokeinterface #109,  1          // InterfaceMethod org/modelmapper/internal/bytebuddy/description/type/TypeDescription.getDeclaringType:()Lorg/modelmapper/internal/bytebuddy/description/type/TypeDescription;
       6: astore_3
       7: aload_1
       8: ifnonnull     31
      11: aload_3
      12: ifnull        31
      15: aload_0
      16: invokeinterface #228,  1          // InterfaceMethod org/modelmapper/internal/bytebuddy/description/type/TypeDescription.isStatic:()Z
      21: ifeq          31
      24: aload_3
      25: invokeinterface #231,  1          // InterfaceMethod org/modelmapper/internal/bytebuddy/description/type/TypeDescription.asGenericType:()Lorg/modelmapper/internal/bytebuddy/description/type/TypeDescription$Generic;
      30: astore_1
      31: aload_0
      32: invokeinterface #234,  1          // InterfaceMethod org/modelmapper/internal/bytebuddy/description/type/TypeDescription.isGenerified:()Z
      37: ifne          67
      40: new           #111                // class java/lang/IllegalArgumentException
      43: dup
      44: new           #113                // class java/lang/StringBuilder
      47: dup
      48: invokespecial #114                // Method java/lang/StringBuilder."<init>":()V
      51: aload_0
      52: invokevirtual #118                // Method java/lang/StringBuilder.append:(Ljava/lang/Object;)Ljava/lang/StringBuilder;
      55: ldc           #236                // String  is not a parameterized type
      57: invokevirtual #123                // Method java/lang/StringBuilder.append:(Ljava/lang/String;)Ljava/lang/StringBuilder;
      60: invokevirtual #127                // Method java/lang/StringBuilder.toString:()Ljava/lang/String;
      63: invokespecial #130                // Method java/lang/IllegalArgumentException."<init>":(Ljava/lang/String;)V
      66: athrow
      67: aload_1
      68: ifnonnull     111
      71: aload_3
      72: ifnull        111
      75: aload_0
      76: invokeinterface #228,  1          // InterfaceMethod org/modelmapper/internal/bytebuddy/description/type/TypeDescription.isStatic:()Z
      81: ifne          111
      84: new           #111                // class java/lang/IllegalArgumentException
      87: dup
      88: new           #113                // class java/lang/StringBuilder
      91: dup
      92: invokespecial #114                // Method java/lang/StringBuilder."<init>":()V
      95: aload_0
      96: invokevirtual #118                // Method java/lang/StringBuilder.append:(Ljava/lang/Object;)Ljava/lang/StringBuilder;
      99: ldc           #238                // String  requires an owner type
     101: invokevirtual #123                // Method java/lang/StringBuilder.append:(Ljava/lang/String;)Ljava/lang/StringBuilder;
     104: invokevirtual #127                // Method java/lang/StringBuilder.toString:()Ljava/lang/String;
     107: invokespecial #130                // Method java/lang/IllegalArgumentException."<init>":(Ljava/lang/String;)V
     110: athrow
     111: aload_1
     112: ifnull        159
     115: aload_1
     116: invokeinterface #133,  1          // InterfaceMethod org/modelmapper/internal/bytebuddy/description/type/TypeDescription$Generic.asErasure:()Lorg/modelmapper/internal/bytebuddy/description/type/TypeDescription;
     121: aload_3
     122: invokevirtual #137                // Method java/lang/Object.equals:(Ljava/lang/Object;)Z
     125: ifne          159
     128: new           #111                // class java/lang/IllegalArgumentException
     131: dup
     132: new           #113                // class java/lang/StringBuilder
     135: dup
     136: invokespecial #114                // Method java/lang/StringBuilder."<init>":()V
     139: aload_1
     140: invokevirtual #118                // Method java/lang/StringBuilder.append:(Ljava/lang/Object;)Ljava/lang/StringBuilder;
     143: ldc           #240                // String  does not represent required owner for
     145: invokevirtual #123                // Method java/lang/StringBuilder.append:(Ljava/lang/String;)Ljava/lang/StringBuilder;
     148: aload_0
     149: invokevirtual #118                // Method java/lang/StringBuilder.append:(Ljava/lang/Object;)Ljava/lang/StringBuilder;
     152: invokevirtual #127                // Method java/lang/StringBuilder.toString:()Ljava/lang/String;
     155: invokespecial #130                // Method java/lang/IllegalArgumentException."<init>":(Ljava/lang/String;)V
     158: athrow
     159: aload_1
     160: ifnull        213
     163: aload_0
     164: invokeinterface #228,  1          // InterfaceMethod org/modelmapper/internal/bytebuddy/description/type/TypeDescription.isStatic:()Z
     169: aload_1
     170: invokeinterface #244,  1          // InterfaceMethod org/modelmapper/internal/bytebuddy/description/type/TypeDescription$Generic.getSort:()Lorg/modelmapper/internal/bytebuddy/description/type/TypeDefinition$Sort;
     175: invokevirtual #247                // Method org/modelmapper/internal/bytebuddy/description/type/TypeDefinition$Sort.isNonGeneric:()Z
     178: ixor
     179: ifeq          213
     182: new           #111                // class java/lang/IllegalArgumentException
     185: dup
     186: new           #113                // class java/lang/StringBuilder
     189: dup
     190: invokespecial #114                // Method java/lang/StringBuilder."<init>":()V
     193: aload_1
     194: invokevirtual #118                // Method java/lang/StringBuilder.append:(Ljava/lang/Object;)Ljava/lang/StringBuilder;
     197: ldc           #249                // String  does not define the correct parameters for owning
     199: invokevirtual #123                // Method java/lang/StringBuilder.append:(Ljava/lang/String;)Ljava/lang/StringBuilder;
     202: aload_0
     203: invokevirtual #118                // Method java/lang/StringBuilder.append:(Ljava/lang/Object;)Ljava/lang/StringBuilder;
     206: invokevirtual #127                // Method java/lang/StringBuilder.toString:()Ljava/lang/String;
     209: invokespecial #130                // Method java/lang/IllegalArgumentException."<init>":(Ljava/lang/String;)V
     212: athrow
     213: aload_0
     214: invokeinterface #253,  1          // InterfaceMethod org/modelmapper/internal/bytebuddy/description/type/TypeDescription.getTypeVariables:()Lorg/modelmapper/internal/bytebuddy/description/type/TypeList$Generic;
     219: invokeinterface #257,  1          // InterfaceMethod org/modelmapper/internal/bytebuddy/description/type/TypeList$Generic.size:()I
     224: aload_2
     225: invokeinterface #260,  1          // InterfaceMethod java/util/Collection.size:()I
     230: if_icmpeq     265
     233: new           #111                // class java/lang/IllegalArgumentException
     236: dup
     237: new           #113                // class java/lang/StringBuilder
     240: dup
     241: invokespecial #114                // Method java/lang/StringBuilder."<init>":()V
     244: aload_2
     245: invokevirtual #118                // Method java/lang/StringBuilder.append:(Ljava/lang/Object;)Ljava/lang/StringBuilder;
     248: ldc_w         #262                // String  does not contain number of required parameters for
     251: invokevirtual #123                // Method java/lang/StringBuilder.append:(Ljava/lang/String;)Ljava/lang/StringBuilder;
     254: aload_0
     255: invokevirtual #118                // Method java/lang/StringBuilder.append:(Ljava/lang/Object;)Ljava/lang/StringBuilder;
     258: invokevirtual #127                // Method java/lang/StringBuilder.toString:()Ljava/lang/String;
     261: invokespecial #130                // Method java/lang/IllegalArgumentException."<init>":(Ljava/lang/String;)V
     264: athrow
     265: new           #20                 // class org/modelmapper/internal/bytebuddy/description/type/TypeDescription$Generic$Builder$OfParameterizedType
     268: dup
     269: aload_0
     270: aload_1
     271: new           #51                 // class org/modelmapper/internal/bytebuddy/description/type/TypeList$Generic$Explicit
     274: dup
     275: new           #173                // class java/util/ArrayList
     278: dup
     279: aload_2
     280: invokespecial #176                // Method java/util/ArrayList."<init>":(Ljava/util/Collection;)V
     283: invokespecial #263                // Method org/modelmapper/internal/bytebuddy/description/type/TypeList$Generic$Explicit."<init>":(Ljava/util/List;)V
     286: invokespecial #266                // Method org/modelmapper/internal/bytebuddy/description/type/TypeDescription$Generic$Builder$OfParameterizedType."<init>":(Lorg/modelmapper/internal/bytebuddy/description/type/TypeDescription;Lorg/modelmapper/internal/bytebuddy/description/type/TypeDescription$Generic;Ljava/util/List;)V
     289: areturn

  public org.modelmapper.internal.bytebuddy.description.type.TypeDescription$Generic asWildcardUpperBound();
    Code:
       0: aload_0
       1: invokestatic  #151                // Method java/util/Collections.emptySet:()Ljava/util/Set;
       4: invokevirtual #269                // Method asWildcardUpperBound:(Ljava/util/Collection;)Lorg/modelmapper/internal/bytebuddy/description/type/TypeDescription$Generic;
       7: areturn

  public org.modelmapper.internal.bytebuddy.description.type.TypeDescription$Generic asWildcardUpperBound(java.lang.annotation.Annotation...);
    Code:
       0: aload_0
       1: aload_1
       2: invokestatic  #161                // Method java/util/Arrays.asList:([Ljava/lang/Object;)Ljava/util/List;
       5: invokevirtual #271                // Method asWildcardUpperBound:(Ljava/util/List;)Lorg/modelmapper/internal/bytebuddy/description/type/TypeDescription$Generic;
       8: areturn

  public org.modelmapper.internal.bytebuddy.description.type.TypeDescription$Generic asWildcardUpperBound(java.util.List<? extends java.lang.annotation.Annotation>);
    Code:
       0: aload_0
       1: new           #34                 // class org/modelmapper/internal/bytebuddy/description/annotation/AnnotationList$ForLoadedAnnotations
       4: dup
       5: aload_1
       6: invokespecial #168                // Method org/modelmapper/internal/bytebuddy/description/annotation/AnnotationList$ForLoadedAnnotations."<init>":(Ljava/util/List;)V
       9: invokevirtual #269                // Method asWildcardUpperBound:(Ljava/util/Collection;)Lorg/modelmapper/internal/bytebuddy/description/type/TypeDescription$Generic;
      12: areturn

  public org.modelmapper.internal.bytebuddy.description.type.TypeDescription$Generic asWildcardUpperBound(org.modelmapper.internal.bytebuddy.description.annotation.AnnotationDescription...);
    Code:
       0: aload_0
       1: aload_1
       2: invokestatic  #161                // Method java/util/Arrays.asList:([Ljava/lang/Object;)Ljava/util/List;
       5: invokevirtual #269                // Method asWildcardUpperBound:(Ljava/util/Collection;)Lorg/modelmapper/internal/bytebuddy/description/type/TypeDescription$Generic;
       8: areturn

  public org.modelmapper.internal.bytebuddy.description.type.TypeDescription$Generic asWildcardUpperBound(java.util.Collection<? extends org.modelmapper.internal.bytebuddy.description.annotation.AnnotationDescription>);
    Code:
       0: aload_0
       1: invokevirtual #274                // Method build:()Lorg/modelmapper/internal/bytebuddy/description/type/TypeDescription$Generic;
       4: new           #39                 // class org/modelmapper/internal/bytebuddy/description/annotation/AnnotationSource$Explicit
       7: dup
       8: new           #173                // class java/util/ArrayList
      11: dup
      12: aload_1
      13: invokespecial #176                // Method java/util/ArrayList."<init>":(Ljava/util/Collection;)V
      16: invokespecial #177                // Method org/modelmapper/internal/bytebuddy/description/annotation/AnnotationSource$Explicit."<init>":(Ljava/util/List;)V
      19: invokestatic  #278                // Method org/modelmapper/internal/bytebuddy/description/type/TypeDescription$Generic$OfWildcardType$Latent.boundedAbove:(Lorg/modelmapper/internal/bytebuddy/description/type/TypeDescription$Generic;Lorg/modelmapper/internal/bytebuddy/description/annotation/AnnotationSource;)Lorg/modelmapper/internal/bytebuddy/description/type/TypeDescription$Generic;
      22: areturn

  public org.modelmapper.internal.bytebuddy.description.type.TypeDescription$Generic asWildcardLowerBound();
    Code:
       0: aload_0
       1: invokestatic  #151                // Method java/util/Collections.emptySet:()Ljava/util/Set;
       4: invokevirtual #281                // Method asWildcardLowerBound:(Ljava/util/Collection;)Lorg/modelmapper/internal/bytebuddy/description/type/TypeDescription$Generic;
       7: areturn

  public org.modelmapper.internal.bytebuddy.description.type.TypeDescription$Generic asWildcardLowerBound(java.lang.annotation.Annotation...);
    Code:
       0: aload_0
       1: aload_1
       2: invokestatic  #161                // Method java/util/Arrays.asList:([Ljava/lang/Object;)Ljava/util/List;
       5: invokevirtual #283                // Method asWildcardLowerBound:(Ljava/util/List;)Lorg/modelmapper/internal/bytebuddy/description/type/TypeDescription$Generic;
       8: areturn

  public org.modelmapper.internal.bytebuddy.description.type.TypeDescription$Generic asWildcardLowerBound(java.util.List<? extends java.lang.annotation.Annotation>);
    Code:
       0: aload_0
       1: new           #34                 // class org/modelmapper/internal/bytebuddy/description/annotation/AnnotationList$ForLoadedAnnotations
       4: dup
       5: aload_1
       6: invokespecial #168                // Method org/modelmapper/internal/bytebuddy/description/annotation/AnnotationList$ForLoadedAnnotations."<init>":(Ljava/util/List;)V
       9: invokevirtual #281                // Method asWildcardLowerBound:(Ljava/util/Collection;)Lorg/modelmapper/internal/bytebuddy/description/type/TypeDescription$Generic;
      12: areturn

  public org.modelmapper.internal.bytebuddy.description.type.TypeDescription$Generic asWildcardLowerBound(org.modelmapper.internal.bytebuddy.description.annotation.AnnotationDescription...);
    Code:
       0: aload_0
       1: aload_1
       2: invokestatic  #161                // Method java/util/Arrays.asList:([Ljava/lang/Object;)Ljava/util/List;
       5: invokevirtual #281                // Method asWildcardLowerBound:(Ljava/util/Collection;)Lorg/modelmapper/internal/bytebuddy/description/type/TypeDescription$Generic;
       8: areturn

  public org.modelmapper.internal.bytebuddy.description.type.TypeDescription$Generic asWildcardLowerBound(java.util.Collection<? extends org.modelmapper.internal.bytebuddy.description.annotation.AnnotationDescription>);
    Code:
       0: aload_0
       1: invokevirtual #274                // Method build:()Lorg/modelmapper/internal/bytebuddy/description/type/TypeDescription$Generic;
       4: new           #39                 // class org/modelmapper/internal/bytebuddy/description/annotation/AnnotationSource$Explicit
       7: dup
       8: new           #173                // class java/util/ArrayList
      11: dup
      12: aload_1
      13: invokespecial #176                // Method java/util/ArrayList."<init>":(Ljava/util/Collection;)V
      16: invokespecial #177                // Method org/modelmapper/internal/bytebuddy/description/annotation/AnnotationSource$Explicit."<init>":(Ljava/util/List;)V
      19: invokestatic  #286                // Method org/modelmapper/internal/bytebuddy/description/type/TypeDescription$Generic$OfWildcardType$Latent.boundedBelow:(Lorg/modelmapper/internal/bytebuddy/description/type/TypeDescription$Generic;Lorg/modelmapper/internal/bytebuddy/description/annotation/AnnotationSource;)Lorg/modelmapper/internal/bytebuddy/description/type/TypeDescription$Generic;
      22: areturn

  public org.modelmapper.internal.bytebuddy.description.type.TypeDescription$Generic$Builder asArray();
    Code:
       0: aload_0
       1: iconst_1
       2: invokevirtual #291                // Method asArray:(I)Lorg/modelmapper/internal/bytebuddy/description/type/TypeDescription$Generic$Builder;
       5: areturn

  public org.modelmapper.internal.bytebuddy.description.type.TypeDescription$Generic$Builder asArray(int);
    Code:
       0: iload_1
       1: iconst_1
       2: if_icmpge     33
       5: new           #111                // class java/lang/IllegalArgumentException
       8: dup
       9: new           #113                // class java/lang/StringBuilder
      12: dup
      13: invokespecial #114                // Method java/lang/StringBuilder."<init>":()V
      16: ldc_w         #293                // String Cannot define an array of a non-positive arity:
      19: invokevirtual #123                // Method java/lang/StringBuilder.append:(Ljava/lang/String;)Ljava/lang/StringBuilder;
      22: iload_1
      23: invokevirtual #296                // Method java/lang/StringBuilder.append:(I)Ljava/lang/StringBuilder;
      26: invokevirtual #127                // Method java/lang/StringBuilder.toString:()Ljava/lang/String;
      29: invokespecial #130                // Method java/lang/IllegalArgumentException."<init>":(Ljava/lang/String;)V
      32: athrow
      33: aload_0
      34: invokevirtual #274                // Method build:()Lorg/modelmapper/internal/bytebuddy/description/type/TypeDescription$Generic;
      37: astore_2
      38: iinc          1, -1
      41: iload_1
      42: ifle          60
      45: new           #56                 // class org/modelmapper/internal/bytebuddy/description/type/TypeDescription$Generic$OfGenericArray$Latent
      48: dup
      49: aload_2
      50: getstatic     #300                // Field org/modelmapper/internal/bytebuddy/description/annotation/AnnotationSource$Empty.INSTANCE:Lorg/modelmapper/internal/bytebuddy/description/annotation/AnnotationSource$Empty;
      53: invokespecial #303                // Method org/modelmapper/internal/bytebuddy/description/type/TypeDescription$Generic$OfGenericArray$Latent."<init>":(Lorg/modelmapper/internal/bytebuddy/description/type/TypeDescription$Generic;Lorg/modelmapper/internal/bytebuddy/description/annotation/AnnotationSource;)V
      56: astore_2
      57: goto          38
      60: new           #17                 // class org/modelmapper/internal/bytebuddy/description/type/TypeDescription$Generic$Builder$OfGenericArrayType
      63: dup
      64: aload_2
      65: invokespecial #306                // Method org/modelmapper/internal/bytebuddy/description/type/TypeDescription$Generic$Builder$OfGenericArrayType."<init>":(Lorg/modelmapper/internal/bytebuddy/description/type/TypeDescription$Generic;)V
      68: areturn

  public org.modelmapper.internal.bytebuddy.description.type.TypeDescription$Generic$Builder annotate(java.lang.annotation.Annotation...);
    Code:
       0: aload_0
       1: aload_1
       2: invokestatic  #161                // Method java/util/Arrays.asList:([Ljava/lang/Object;)Ljava/util/List;
       5: invokevirtual #314                // Method annotate:(Ljava/util/List;)Lorg/modelmapper/internal/bytebuddy/description/type/TypeDescription$Generic$Builder;
       8: areturn

  public org.modelmapper.internal.bytebuddy.description.type.TypeDescription$Generic$Builder annotate(java.util.List<? extends java.lang.annotation.Annotation>);
    Code:
       0: aload_0
       1: new           #34                 // class org/modelmapper/internal/bytebuddy/description/annotation/AnnotationList$ForLoadedAnnotations
       4: dup
       5: aload_1
       6: invokespecial #168                // Method org/modelmapper/internal/bytebuddy/description/annotation/AnnotationList$ForLoadedAnnotations."<init>":(Ljava/util/List;)V
       9: invokevirtual #317                // Method annotate:(Ljava/util/Collection;)Lorg/modelmapper/internal/bytebuddy/description/type/TypeDescription$Generic$Builder;
      12: areturn

  public org.modelmapper.internal.bytebuddy.description.type.TypeDescription$Generic$Builder annotate(org.modelmapper.internal.bytebuddy.description.annotation.AnnotationDescription...);
    Code:
       0: aload_0
       1: aload_1
       2: invokestatic  #161                // Method java/util/Arrays.asList:([Ljava/lang/Object;)Ljava/util/List;
       5: invokevirtual #317                // Method annotate:(Ljava/util/Collection;)Lorg/modelmapper/internal/bytebuddy/description/type/TypeDescription$Generic$Builder;
       8: areturn

  public org.modelmapper.internal.bytebuddy.description.type.TypeDescription$Generic$Builder annotate(java.util.Collection<? extends org.modelmapper.internal.bytebuddy.description.annotation.AnnotationDescription>);
    Code:
       0: aload_0
       1: new           #173                // class java/util/ArrayList
       4: dup
       5: aload_1
       6: invokespecial #176                // Method java/util/ArrayList."<init>":(Ljava/util/Collection;)V
       9: invokevirtual #321                // Method doAnnotate:(Ljava/util/List;)Lorg/modelmapper/internal/bytebuddy/description/type/TypeDescription$Generic$Builder;
      12: areturn

  protected abstract org.modelmapper.internal.bytebuddy.description.type.TypeDescription$Generic$Builder doAnnotate(java.util.List<? extends org.modelmapper.internal.bytebuddy.description.annotation.AnnotationDescription>);

  public org.modelmapper.internal.bytebuddy.description.type.TypeDescription$Generic build();
    Code:
       0: aload_0
       1: invokevirtual #324                // Method doBuild:()Lorg/modelmapper/internal/bytebuddy/description/type/TypeDescription$Generic;
       4: areturn

  public org.modelmapper.internal.bytebuddy.description.type.TypeDescription$Generic build(java.lang.annotation.Annotation...);
    Code:
       0: aload_0
       1: aload_1
       2: invokestatic  #161                // Method java/util/Arrays.asList:([Ljava/lang/Object;)Ljava/util/List;
       5: invokevirtual #326                // Method build:(Ljava/util/List;)Lorg/modelmapper/internal/bytebuddy/description/type/TypeDescription$Generic;
       8: areturn

  public org.modelmapper.internal.bytebuddy.description.type.TypeDescription$Generic build(java.util.List<? extends java.lang.annotation.Annotation>);
    Code:
       0: aload_0
       1: new           #34                 // class org/modelmapper/internal/bytebuddy/description/annotation/AnnotationList$ForLoadedAnnotations
       4: dup
       5: aload_1
       6: invokespecial #168                // Method org/modelmapper/internal/bytebuddy/description/annotation/AnnotationList$ForLoadedAnnotations."<init>":(Ljava/util/List;)V
       9: invokevirtual #328                // Method build:(Ljava/util/Collection;)Lorg/modelmapper/internal/bytebuddy/description/type/TypeDescription$Generic;
      12: areturn

  public org.modelmapper.internal.bytebuddy.description.type.TypeDescription$Generic build(org.modelmapper.internal.bytebuddy.description.annotation.AnnotationDescription...);
    Code:
       0: aload_0
       1: aload_1
       2: invokestatic  #161                // Method java/util/Arrays.asList:([Ljava/lang/Object;)Ljava/util/List;
       5: invokevirtual #328                // Method build:(Ljava/util/Collection;)Lorg/modelmapper/internal/bytebuddy/description/type/TypeDescription$Generic;
       8: areturn

  public org.modelmapper.internal.bytebuddy.description.type.TypeDescription$Generic build(java.util.Collection<? extends org.modelmapper.internal.bytebuddy.description.annotation.AnnotationDescription>);
    Code:
       0: aload_0
       1: new           #173                // class java/util/ArrayList
       4: dup
       5: aload_1
       6: invokespecial #176                // Method java/util/ArrayList."<init>":(Ljava/util/Collection;)V
       9: invokevirtual #321                // Method doAnnotate:(Ljava/util/List;)Lorg/modelmapper/internal/bytebuddy/description/type/TypeDescription$Generic$Builder;
      12: invokevirtual #324                // Method doBuild:()Lorg/modelmapper/internal/bytebuddy/description/type/TypeDescription$Generic;
      15: areturn

  protected abstract org.modelmapper.internal.bytebuddy.description.type.TypeDescription$Generic doBuild();

  static {};
    Code:
       0: goto          8
       3: aconst_null
       4: putstatic     #197                // Field UNDEFINED:Ljava/lang/reflect/Type;
       7: return
       8: goto          3

  public boolean equals(java.lang.Object);
    Code:
       0: aload_0
       1: aload_1
       2: if_acmpne     7
       5: iconst_1
       6: ireturn
       7: aload_1
       8: ifnonnull     13
      11: iconst_0
      12: ireturn
      13: aload_0
      14: invokevirtual #333                // Method java/lang/Object.getClass:()Ljava/lang/Class;
      17: aload_1
      18: invokevirtual #333                // Method java/lang/Object.getClass:()Ljava/lang/Class;
      21: if_acmpeq     26
      24: iconst_0
      25: ireturn
      26: aload_0
      27: getfield      #82                 // Field annotations:Ljava/util/List;
      30: aload_1
      31: checkcast     #2                  // class org/modelmapper/internal/bytebuddy/description/type/TypeDescription$Generic$Builder
      34: getfield      #82                 // Field annotations:Ljava/util/List;
      37: invokeinterface #334,  2          // InterfaceMethod java/util/List.equals:(Ljava/lang/Object;)Z
      42: ifne          47
      45: iconst_0
      46: ireturn
      47: iconst_1
      48: ireturn

  public int hashCode();
    Code:
       0: bipush        17
       2: bipush        31
       4: imul
       5: aload_0
       6: getfield      #82                 // Field annotations:Ljava/util/List;
       9: invokeinterface #337,  1          // InterfaceMethod java/util/List.hashCode:()I
      14: iadd
      15: ireturn
}
