Compiled from "TypeDescription.java"
final class org.modelmapper.internal.bytebuddy.description.type.TypeDescription$Generic$Visitor$Reifying$1 extends org.modelmapper.internal.bytebuddy.description.type.TypeDescription$Generic$Visitor$Reifying {
  org.modelmapper.internal.bytebuddy.description.type.TypeDescription$Generic$Visitor$Reifying$1(java.lang.String, int);
    Code:
       0: aload_0
       1: aload_1
       2: iload_2
       3: aconst_null
       4: invokespecial #21                 // Method org/modelmapper/internal/bytebuddy/description/type/TypeDescription$Generic$Visitor$Reifying."<init>":(Ljava/lang/String;ILorg/modelmapper/internal/bytebuddy/description/type/TypeDescription$1;)V
       7: return

  public org.modelmapper.internal.bytebuddy.description.type.TypeDescription$Generic onParameterizedType(org.modelmapper.internal.bytebuddy.description.type.TypeDescription$Generic);
    Code:
       0: aload_1
       1: areturn

  public java.lang.Object onNonGenericType(org.modelmapper.internal.bytebuddy.description.type.TypeDescription$Generic);
    Code:
       0: aload_0
       1: aload_1
       2: invokespecial #31                 // Method org/modelmapper/internal/bytebuddy/description/type/TypeDescription$Generic$Visitor$Reifying.onNonGenericType:(Lorg/modelmapper/internal/bytebuddy/description/type/TypeDescription$Generic;)Lorg/modelmapper/internal/bytebuddy/description/type/TypeDescription$Generic;
       5: areturn

  public java.lang.Object onTypeVariable(org.modelmapper.internal.bytebuddy.description.type.TypeDescription$Generic);
    Code:
       0: aload_0
       1: aload_1
       2: invokespecial #34                 // Method org/modelmapper/internal/bytebuddy/description/type/TypeDescription$Generic$Visitor$Reifying.onTypeVariable:(Lorg/modelmapper/internal/bytebuddy/description/type/TypeDescription$Generic;)Lorg/modelmapper/internal/bytebuddy/description/type/TypeDescription$Generic;
       5: areturn

  public java.lang.Object onParameterizedType(org.modelmapper.internal.bytebuddy.description.type.TypeDescription$Generic);
    Code:
       0: aload_0
       1: aload_1
       2: invokevirtual #36                 // Method onParameterizedType:(Lorg/modelmapper/internal/bytebuddy/description/type/TypeDescription$Generic;)Lorg/modelmapper/internal/bytebuddy/description/type/TypeDescription$Generic;
       5: areturn

  public java.lang.Object onWildcard(org.modelmapper.internal.bytebuddy.description.type.TypeDescription$Generic);
    Code:
       0: aload_0
       1: aload_1
       2: invokespecial #39                 // Method org/modelmapper/internal/bytebuddy/description/type/TypeDescription$Generic$Visitor$Reifying.onWildcard:(Lorg/modelmapper/internal/bytebuddy/description/type/TypeDescription$Generic;)Lorg/modelmapper/internal/bytebuddy/description/type/TypeDescription$Generic;
       5: areturn

  public java.lang.Object onGenericArray(org.modelmapper.internal.bytebuddy.description.type.TypeDescription$Generic);
    Code:
       0: aload_0
       1: aload_1
       2: invokespecial #42                 // Method org/modelmapper/internal/bytebuddy/description/type/TypeDescription$Generic$Visitor$Reifying.onGenericArray:(Lorg/modelmapper/internal/bytebuddy/description/type/TypeDescription$Generic;)Lorg/modelmapper/internal/bytebuddy/description/type/TypeDescription$Generic;
       5: areturn
}
