Compiled from "TypeDescription.java"
public class org.modelmapper.internal.bytebuddy.description.type.TypeDescription$Generic$OfGenericArray$Latent extends org.modelmapper.internal.bytebuddy.description.type.TypeDescription$Generic$OfGenericArray {
  private final org.modelmapper.internal.bytebuddy.description.type.TypeDescription$Generic componentType;

  private final org.modelmapper.internal.bytebuddy.description.annotation.AnnotationSource annotationSource;

  public org.modelmapper.internal.bytebuddy.description.type.TypeDescription$Generic$OfGenericArray$Latent(org.modelmapper.internal.bytebuddy.description.type.TypeDescription$Generic, org.modelmapper.internal.bytebuddy.description.annotation.AnnotationSource);
    Code:
       0: aload_0
       1: invokespecial #21                 // Method org/modelmapper/internal/bytebuddy/description/type/TypeDescription$Generic$OfGenericArray."<init>":()V
       4: aload_0
       5: aload_1
       6: putfield      #23                 // Field componentType:Lorg/modelmapper/internal/bytebuddy/description/type/TypeDescription$Generic;
       9: aload_0
      10: aload_2
      11: putfield      #25                 // Field annotationSource:Lorg/modelmapper/internal/bytebuddy/description/annotation/AnnotationSource;
      14: return

  public org.modelmapper.internal.bytebuddy.description.type.TypeDescription$Generic getComponentType();
    Code:
       0: aload_0
       1: getfield      #23                 // Field componentType:Lorg/modelmapper/internal/bytebuddy/description/type/TypeDescription$Generic;
       4: areturn

  public org.modelmapper.internal.bytebuddy.description.annotation.AnnotationList getDeclaredAnnotations();
    Code:
       0: aload_0
       1: getfield      #25                 // Field annotationSource:Lorg/modelmapper/internal/bytebuddy/description/annotation/AnnotationSource;
       4: invokeinterface #35,  1           // InterfaceMethod org/modelmapper/internal/bytebuddy/description/annotation/AnnotationSource.getDeclaredAnnotations:()Lorg/modelmapper/internal/bytebuddy/description/annotation/AnnotationList;
       9: areturn

  public org.modelmapper.internal.bytebuddy.description.type.TypeDefinition getComponentType();
    Code:
       0: aload_0
       1: invokevirtual #38                 // Method getComponentType:()Lorg/modelmapper/internal/bytebuddy/description/type/TypeDescription$Generic;
       4: areturn
}
