Compiled from "AttributeList.java"
class org.jdom.AttributeList extends java.util.AbstractList implements java.util.List,java.io.Serializable {
  private static final java.lang.String CVS_ID;

  private static final int INITIAL_ARRAY_SIZE;

  private org.jdom.Attribute[] elementData;

  private int size;

  private org.jdom.Element parent;

  private org.jdom.AttributeList();
    Code:
       0: aload_0
       1: invokespecial #1                  // Method java/util/AbstractList."<init>":()V
       4: return

  org.jdom.AttributeList(org.jdom.Element);
    Code:
       0: aload_0
       1: invokespecial #1                  // Method java/util/AbstractList."<init>":()V
       4: aload_0
       5: aload_1
       6: putfield      #2                  // Field parent:Lorg/jdom/Element;
       9: return

  final void uncheckedAddAttribute(org.jdom.Attribute);
    Code:
       0: aload_1
       1: aload_0
       2: getfield      #2                  // Field parent:Lorg/jdom/Element;
       5: putfield      #3                  // Field org/jdom/Attribute.parent:Lorg/jdom/Element;
       8: aload_0
       9: aload_0
      10: getfield      #4                  // Field size:I
      13: iconst_1
      14: iadd
      15: invokespecial #5                  // Method ensureCapacity:(I)V
      18: aload_0
      19: getfield      #6                  // Field elementData:[Lorg/jdom/Attribute;
      22: aload_0
      23: dup
      24: getfield      #4                  // Field size:I
      27: dup_x1
      28: iconst_1
      29: iadd
      30: putfield      #4                  // Field size:I
      33: aload_1
      34: aastore
      35: aload_0
      36: dup
      37: getfield      #7                  // Field modCount:I
      40: iconst_1
      41: iadd
      42: putfield      #7                  // Field modCount:I
      45: return

  public boolean add(java.lang.Object);
    Code:
       0: aload_1
       1: instanceof    #8                  // class org/jdom/Attribute
       4: ifeq          44
       7: aload_1
       8: checkcast     #8                  // class org/jdom/Attribute
      11: astore_2
      12: aload_0
      13: aload_2
      14: invokespecial #9                  // Method indexOfDuplicate:(Lorg/jdom/Attribute;)I
      17: istore_3
      18: iload_3
      19: ifge          34
      22: aload_0
      23: aload_0
      24: invokevirtual #10                 // Method size:()I
      27: aload_2
      28: invokevirtual #11                 // Method add:(ILorg/jdom/Attribute;)V
      31: goto          41
      34: aload_0
      35: iload_3
      36: aload_2
      37: invokevirtual #12                 // Method set:(ILorg/jdom/Attribute;)Ljava/lang/Object;
      40: pop
      41: goto          96
      44: aload_1
      45: ifnonnull     58
      48: new           #13                 // class org/jdom/IllegalAddException
      51: dup
      52: ldc           #14                 // String Cannot add null attribute
      54: invokespecial #15                 // Method org/jdom/IllegalAddException."<init>":(Ljava/lang/String;)V
      57: athrow
      58: new           #13                 // class org/jdom/IllegalAddException
      61: dup
      62: new           #16                 // class java/lang/StringBuffer
      65: dup
      66: invokespecial #17                 // Method java/lang/StringBuffer."<init>":()V
      69: ldc           #18                 // String Class
      71: invokevirtual #19                 // Method java/lang/StringBuffer.append:(Ljava/lang/String;)Ljava/lang/StringBuffer;
      74: aload_1
      75: invokevirtual #20                 // Method java/lang/Object.getClass:()Ljava/lang/Class;
      78: invokevirtual #21                 // Method java/lang/Class.getName:()Ljava/lang/String;
      81: invokevirtual #19                 // Method java/lang/StringBuffer.append:(Ljava/lang/String;)Ljava/lang/StringBuffer;
      84: ldc           #22                 // String  is not an attribute
      86: invokevirtual #19                 // Method java/lang/StringBuffer.append:(Ljava/lang/String;)Ljava/lang/StringBuffer;
      89: invokevirtual #23                 // Method java/lang/StringBuffer.toString:()Ljava/lang/String;
      92: invokespecial #15                 // Method org/jdom/IllegalAddException."<init>":(Ljava/lang/String;)V
      95: athrow
      96: iconst_1
      97: ireturn

  public void add(int, java.lang.Object);
    Code:
       0: aload_2
       1: instanceof    #8                  // class org/jdom/Attribute
       4: ifeq          43
       7: aload_2
       8: checkcast     #8                  // class org/jdom/Attribute
      11: astore_3
      12: aload_0
      13: aload_3
      14: invokespecial #9                  // Method indexOfDuplicate:(Lorg/jdom/Attribute;)I
      17: istore        4
      19: iload         4
      21: iflt          34
      24: new           #13                 // class org/jdom/IllegalAddException
      27: dup
      28: ldc           #24                 // String Cannot add duplicate attribute
      30: invokespecial #15                 // Method org/jdom/IllegalAddException."<init>":(Ljava/lang/String;)V
      33: athrow
      34: aload_0
      35: iload_1
      36: aload_3
      37: invokevirtual #11                 // Method add:(ILorg/jdom/Attribute;)V
      40: goto          95
      43: aload_2
      44: ifnonnull     57
      47: new           #13                 // class org/jdom/IllegalAddException
      50: dup
      51: ldc           #14                 // String Cannot add null attribute
      53: invokespecial #15                 // Method org/jdom/IllegalAddException."<init>":(Ljava/lang/String;)V
      56: athrow
      57: new           #13                 // class org/jdom/IllegalAddException
      60: dup
      61: new           #16                 // class java/lang/StringBuffer
      64: dup
      65: invokespecial #17                 // Method java/lang/StringBuffer."<init>":()V
      68: ldc           #18                 // String Class
      70: invokevirtual #19                 // Method java/lang/StringBuffer.append:(Ljava/lang/String;)Ljava/lang/StringBuffer;
      73: aload_2
      74: invokevirtual #20                 // Method java/lang/Object.getClass:()Ljava/lang/Class;
      77: invokevirtual #21                 // Method java/lang/Class.getName:()Ljava/lang/String;
      80: invokevirtual #19                 // Method java/lang/StringBuffer.append:(Ljava/lang/String;)Ljava/lang/StringBuffer;
      83: ldc           #22                 // String  is not an attribute
      85: invokevirtual #19                 // Method java/lang/StringBuffer.append:(Ljava/lang/String;)Ljava/lang/StringBuffer;
      88: invokevirtual #23                 // Method java/lang/StringBuffer.toString:()Ljava/lang/String;
      91: invokespecial #15                 // Method org/jdom/IllegalAddException."<init>":(Ljava/lang/String;)V
      94: athrow
      95: aload_0
      96: dup
      97: getfield      #7                  // Field modCount:I
     100: iconst_1
     101: iadd
     102: putfield      #7                  // Field modCount:I
     105: return

  void add(int, org.jdom.Attribute);
    Code:
       0: aload_2
       1: invokevirtual #25                 // Method org/jdom/Attribute.getParent:()Lorg/jdom/Element;
       4: ifnull        45
       7: new           #13                 // class org/jdom/IllegalAddException
      10: dup
      11: new           #16                 // class java/lang/StringBuffer
      14: dup
      15: invokespecial #17                 // Method java/lang/StringBuffer."<init>":()V
      18: ldc           #26                 // String The attribute already has an existing parent \"
      20: invokevirtual #19                 // Method java/lang/StringBuffer.append:(Ljava/lang/String;)Ljava/lang/StringBuffer;
      23: aload_2
      24: invokevirtual #25                 // Method org/jdom/Attribute.getParent:()Lorg/jdom/Element;
      27: invokevirtual #27                 // Method org/jdom/Element.getQualifiedName:()Ljava/lang/String;
      30: invokevirtual #19                 // Method java/lang/StringBuffer.append:(Ljava/lang/String;)Ljava/lang/StringBuffer;
      33: ldc           #28                 // String \"
      35: invokevirtual #19                 // Method java/lang/StringBuffer.append:(Ljava/lang/String;)Ljava/lang/StringBuffer;
      38: invokevirtual #23                 // Method java/lang/StringBuffer.toString:()Ljava/lang/String;
      41: invokespecial #15                 // Method org/jdom/IllegalAddException."<init>":(Ljava/lang/String;)V
      44: athrow
      45: aload_2
      46: aload_0
      47: getfield      #2                  // Field parent:Lorg/jdom/Element;
      50: invokestatic  #29                 // Method org/jdom/Verifier.checkNamespaceCollision:(Lorg/jdom/Attribute;Lorg/jdom/Element;)Ljava/lang/String;
      53: astore_3
      54: aload_3
      55: ifnull        72
      58: new           #13                 // class org/jdom/IllegalAddException
      61: dup
      62: aload_0
      63: getfield      #2                  // Field parent:Lorg/jdom/Element;
      66: aload_2
      67: aload_3
      68: invokespecial #30                 // Method org/jdom/IllegalAddException."<init>":(Lorg/jdom/Element;Lorg/jdom/Attribute;Ljava/lang/String;)V
      71: athrow
      72: iload_1
      73: iflt          84
      76: iload_1
      77: aload_0
      78: getfield      #4                  // Field size:I
      81: if_icmple     123
      84: new           #31                 // class java/lang/IndexOutOfBoundsException
      87: dup
      88: new           #16                 // class java/lang/StringBuffer
      91: dup
      92: invokespecial #17                 // Method java/lang/StringBuffer."<init>":()V
      95: ldc           #32                 // String Index:
      97: invokevirtual #19                 // Method java/lang/StringBuffer.append:(Ljava/lang/String;)Ljava/lang/StringBuffer;
     100: iload_1
     101: invokevirtual #33                 // Method java/lang/StringBuffer.append:(I)Ljava/lang/StringBuffer;
     104: ldc           #34                 // String  Size:
     106: invokevirtual #19                 // Method java/lang/StringBuffer.append:(Ljava/lang/String;)Ljava/lang/StringBuffer;
     109: aload_0
     110: invokevirtual #10                 // Method size:()I
     113: invokevirtual #33                 // Method java/lang/StringBuffer.append:(I)Ljava/lang/StringBuffer;
     116: invokevirtual #23                 // Method java/lang/StringBuffer.toString:()Ljava/lang/String;
     119: invokespecial #35                 // Method java/lang/IndexOutOfBoundsException."<init>":(Ljava/lang/String;)V
     122: athrow
     123: aload_2
     124: aload_0
     125: getfield      #2                  // Field parent:Lorg/jdom/Element;
     128: invokevirtual #36                 // Method org/jdom/Attribute.setParent:(Lorg/jdom/Element;)Lorg/jdom/Attribute;
     131: pop
     132: aload_0
     133: aload_0
     134: getfield      #4                  // Field size:I
     137: iconst_1
     138: iadd
     139: invokespecial #5                  // Method ensureCapacity:(I)V
     142: iload_1
     143: aload_0
     144: getfield      #4                  // Field size:I
     147: if_icmpne     170
     150: aload_0
     151: getfield      #6                  // Field elementData:[Lorg/jdom/Attribute;
     154: aload_0
     155: dup
     156: getfield      #4                  // Field size:I
     159: dup_x1
     160: iconst_1
     161: iadd
     162: putfield      #4                  // Field size:I
     165: aload_2
     166: aastore
     167: goto          208
     170: aload_0
     171: getfield      #6                  // Field elementData:[Lorg/jdom/Attribute;
     174: iload_1
     175: aload_0
     176: getfield      #6                  // Field elementData:[Lorg/jdom/Attribute;
     179: iload_1
     180: iconst_1
     181: iadd
     182: aload_0
     183: getfield      #4                  // Field size:I
     186: iload_1
     187: isub
     188: invokestatic  #37                 // Method java/lang/System.arraycopy:(Ljava/lang/Object;ILjava/lang/Object;II)V
     191: aload_0
     192: getfield      #6                  // Field elementData:[Lorg/jdom/Attribute;
     195: iload_1
     196: aload_2
     197: aastore
     198: aload_0
     199: dup
     200: getfield      #4                  // Field size:I
     203: iconst_1
     204: iadd
     205: putfield      #4                  // Field size:I
     208: aload_0
     209: dup
     210: getfield      #7                  // Field modCount:I
     213: iconst_1
     214: iadd
     215: putfield      #7                  // Field modCount:I
     218: return

  public boolean addAll(java.util.Collection);
    Code:
       0: aload_0
       1: aload_0
       2: invokevirtual #10                 // Method size:()I
       5: aload_1
       6: invokevirtual #38                 // Method addAll:(ILjava/util/Collection;)Z
       9: ireturn

  public boolean addAll(int, java.util.Collection);
    Code:
       0: iload_1
       1: iflt          12
       4: iload_1
       5: aload_0
       6: getfield      #4                  // Field size:I
       9: if_icmple     51
      12: new           #31                 // class java/lang/IndexOutOfBoundsException
      15: dup
      16: new           #16                 // class java/lang/StringBuffer
      19: dup
      20: invokespecial #17                 // Method java/lang/StringBuffer."<init>":()V
      23: ldc           #32                 // String Index:
      25: invokevirtual #19                 // Method java/lang/StringBuffer.append:(Ljava/lang/String;)Ljava/lang/StringBuffer;
      28: iload_1
      29: invokevirtual #33                 // Method java/lang/StringBuffer.append:(I)Ljava/lang/StringBuffer;
      32: ldc           #34                 // String  Size:
      34: invokevirtual #19                 // Method java/lang/StringBuffer.append:(Ljava/lang/String;)Ljava/lang/StringBuffer;
      37: aload_0
      38: invokevirtual #10                 // Method size:()I
      41: invokevirtual #33                 // Method java/lang/StringBuffer.append:(I)Ljava/lang/StringBuffer;
      44: invokevirtual #23                 // Method java/lang/StringBuffer.toString:()Ljava/lang/String;
      47: invokespecial #35                 // Method java/lang/IndexOutOfBoundsException."<init>":(Ljava/lang/String;)V
      50: athrow
      51: aload_2
      52: ifnull        64
      55: aload_2
      56: invokeinterface #39,  1           // InterfaceMethod java/util/Collection.size:()I
      61: ifne          66
      64: iconst_0
      65: ireturn
      66: aload_0
      67: aload_0
      68: invokevirtual #10                 // Method size:()I
      71: aload_2
      72: invokeinterface #39,  1           // InterfaceMethod java/util/Collection.size:()I
      77: iadd
      78: invokespecial #5                  // Method ensureCapacity:(I)V
      81: iconst_0
      82: istore_3
      83: aload_2
      84: invokeinterface #40,  1           // InterfaceMethod java/util/Collection.iterator:()Ljava/util/Iterator;
      89: astore        4
      91: aload         4
      93: invokeinterface #41,  1           // InterfaceMethod java/util/Iterator.hasNext:()Z
      98: ifeq          125
     101: aload         4
     103: invokeinterface #42,  1           // InterfaceMethod java/util/Iterator.next:()Ljava/lang/Object;
     108: astore        5
     110: aload_0
     111: iload_1
     112: iload_3
     113: iadd
     114: aload         5
     116: invokevirtual #43                 // Method add:(ILjava/lang/Object;)V
     119: iinc          3, 1
     122: goto          91
     125: goto          154
     128: astore        4
     130: iconst_0
     131: istore        5
     133: iload         5
     135: iload_3
     136: if_icmpge     151
     139: aload_0
     140: iload_1
     141: invokevirtual #45                 // Method remove:(I)Ljava/lang/Object;
     144: pop
     145: iinc          5, 1
     148: goto          133
     151: aload         4
     153: athrow
     154: iconst_1
     155: ireturn
    Exception table:
       from    to  target type
          83   125   128   Class java/lang/RuntimeException

  public void clear();
    Code:
       0: aload_0
       1: getfield      #6                  // Field elementData:[Lorg/jdom/Attribute;
       4: ifnull        46
       7: iconst_0
       8: istore_1
       9: iload_1
      10: aload_0
      11: getfield      #4                  // Field size:I
      14: if_icmpge     36
      17: aload_0
      18: getfield      #6                  // Field elementData:[Lorg/jdom/Attribute;
      21: iload_1
      22: aaload
      23: astore_2
      24: aload_2
      25: aconst_null
      26: invokevirtual #36                 // Method org/jdom/Attribute.setParent:(Lorg/jdom/Element;)Lorg/jdom/Attribute;
      29: pop
      30: iinc          1, 1
      33: goto          9
      36: aload_0
      37: aconst_null
      38: putfield      #6                  // Field elementData:[Lorg/jdom/Attribute;
      41: aload_0
      42: iconst_0
      43: putfield      #4                  // Field size:I
      46: aload_0
      47: dup
      48: getfield      #7                  // Field modCount:I
      51: iconst_1
      52: iadd
      53: putfield      #7                  // Field modCount:I
      56: return

  void clearAndSet(java.util.Collection);
    Code:
       0: aload_0
       1: getfield      #6                  // Field elementData:[Lorg/jdom/Attribute;
       4: astore_2
       5: aload_0
       6: getfield      #4                  // Field size:I
       9: istore_3
      10: aload_0
      11: aconst_null
      12: putfield      #6                  // Field elementData:[Lorg/jdom/Attribute;
      15: aload_0
      16: iconst_0
      17: putfield      #4                  // Field size:I
      20: aload_1
      21: ifnull        68
      24: aload_1
      25: invokeinterface #39,  1           // InterfaceMethod java/util/Collection.size:()I
      30: ifeq          68
      33: aload_0
      34: aload_1
      35: invokeinterface #39,  1           // InterfaceMethod java/util/Collection.size:()I
      40: invokespecial #5                  // Method ensureCapacity:(I)V
      43: aload_0
      44: iconst_0
      45: aload_1
      46: invokevirtual #38                 // Method addAll:(ILjava/util/Collection;)Z
      49: pop
      50: goto          68
      53: astore        4
      55: aload_0
      56: aload_2
      57: putfield      #6                  // Field elementData:[Lorg/jdom/Attribute;
      60: aload_0
      61: iload_3
      62: putfield      #4                  // Field size:I
      65: aload         4
      67: athrow
      68: aload_2
      69: ifnull        100
      72: iconst_0
      73: istore        4
      75: iload         4
      77: iload_3
      78: if_icmpge     100
      81: aload_2
      82: iload         4
      84: aaload
      85: astore        5
      87: aload         5
      89: aconst_null
      90: invokevirtual #36                 // Method org/jdom/Attribute.setParent:(Lorg/jdom/Element;)Lorg/jdom/Attribute;
      93: pop
      94: iinc          4, 1
      97: goto          75
     100: aload_0
     101: dup
     102: getfield      #7                  // Field modCount:I
     105: iconst_1
     106: iadd
     107: putfield      #7                  // Field modCount:I
     110: return
    Exception table:
       from    to  target type
          43    50    53   Class java/lang/RuntimeException

  private void ensureCapacity(int);
    Code:
       0: aload_0
       1: getfield      #6                  // Field elementData:[Lorg/jdom/Attribute;
       4: ifnonnull     22
       7: aload_0
       8: iload_1
       9: iconst_5
      10: invokestatic  #46                 // Method java/lang/Math.max:(II)I
      13: anewarray     #8                  // class org/jdom/Attribute
      16: putfield      #6                  // Field elementData:[Lorg/jdom/Attribute;
      19: goto          79
      22: aload_0
      23: getfield      #6                  // Field elementData:[Lorg/jdom/Attribute;
      26: arraylength
      27: istore_2
      28: iload_1
      29: iload_2
      30: if_icmple     79
      33: aload_0
      34: getfield      #6                  // Field elementData:[Lorg/jdom/Attribute;
      37: astore_3
      38: iload_2
      39: iconst_3
      40: imul
      41: iconst_2
      42: idiv
      43: iconst_1
      44: iadd
      45: istore        4
      47: iload         4
      49: iload_1
      50: if_icmpge     56
      53: iload_1
      54: istore        4
      56: aload_0
      57: iload         4
      59: anewarray     #8                  // class org/jdom/Attribute
      62: putfield      #6                  // Field elementData:[Lorg/jdom/Attribute;
      65: aload_3
      66: iconst_0
      67: aload_0
      68: getfield      #6                  // Field elementData:[Lorg/jdom/Attribute;
      71: iconst_0
      72: aload_0
      73: getfield      #4                  // Field size:I
      76: invokestatic  #37                 // Method java/lang/System.arraycopy:(Ljava/lang/Object;ILjava/lang/Object;II)V
      79: return

  public java.lang.Object get(int);
    Code:
       0: iload_1
       1: iflt          12
       4: iload_1
       5: aload_0
       6: getfield      #4                  // Field size:I
       9: if_icmplt     51
      12: new           #31                 // class java/lang/IndexOutOfBoundsException
      15: dup
      16: new           #16                 // class java/lang/StringBuffer
      19: dup
      20: invokespecial #17                 // Method java/lang/StringBuffer."<init>":()V
      23: ldc           #32                 // String Index:
      25: invokevirtual #19                 // Method java/lang/StringBuffer.append:(Ljava/lang/String;)Ljava/lang/StringBuffer;
      28: iload_1
      29: invokevirtual #33                 // Method java/lang/StringBuffer.append:(I)Ljava/lang/StringBuffer;
      32: ldc           #34                 // String  Size:
      34: invokevirtual #19                 // Method java/lang/StringBuffer.append:(Ljava/lang/String;)Ljava/lang/StringBuffer;
      37: aload_0
      38: invokevirtual #10                 // Method size:()I
      41: invokevirtual #33                 // Method java/lang/StringBuffer.append:(I)Ljava/lang/StringBuffer;
      44: invokevirtual #23                 // Method java/lang/StringBuffer.toString:()Ljava/lang/String;
      47: invokespecial #35                 // Method java/lang/IndexOutOfBoundsException."<init>":(Ljava/lang/String;)V
      50: athrow
      51: aload_0
      52: getfield      #6                  // Field elementData:[Lorg/jdom/Attribute;
      55: iload_1
      56: aaload
      57: areturn

  java.lang.Object get(java.lang.String, org.jdom.Namespace);
    Code:
       0: aload_0
       1: aload_1
       2: aload_2
       3: invokevirtual #47                 // Method indexOf:(Ljava/lang/String;Lorg/jdom/Namespace;)I
       6: istore_3
       7: iload_3
       8: ifge          13
      11: aconst_null
      12: areturn
      13: aload_0
      14: getfield      #6                  // Field elementData:[Lorg/jdom/Attribute;
      17: iload_3
      18: aaload
      19: areturn

  int indexOf(java.lang.String, org.jdom.Namespace);
    Code:
       0: aload_2
       1: invokevirtual #48                 // Method org/jdom/Namespace.getURI:()Ljava/lang/String;
       4: astore_3
       5: aload_0
       6: getfield      #6                  // Field elementData:[Lorg/jdom/Attribute;
       9: ifnull        74
      12: iconst_0
      13: istore        4
      15: iload         4
      17: aload_0
      18: getfield      #4                  // Field size:I
      21: if_icmpge     74
      24: aload_0
      25: getfield      #6                  // Field elementData:[Lorg/jdom/Attribute;
      28: iload         4
      30: aaload
      31: astore        5
      33: aload         5
      35: invokevirtual #49                 // Method org/jdom/Attribute.getNamespaceURI:()Ljava/lang/String;
      38: astore        6
      40: aload         5
      42: invokevirtual #50                 // Method org/jdom/Attribute.getName:()Ljava/lang/String;
      45: astore        7
      47: aload         6
      49: aload_3
      50: invokevirtual #51                 // Method java/lang/String.equals:(Ljava/lang/Object;)Z
      53: ifeq          68
      56: aload         7
      58: aload_1
      59: invokevirtual #51                 // Method java/lang/String.equals:(Ljava/lang/Object;)Z
      62: ifeq          68
      65: iload         4
      67: ireturn
      68: iinc          4, 1
      71: goto          15
      74: iconst_m1
      75: ireturn

  public java.lang.Object remove(int);
    Code:
       0: iload_1
       1: iflt          12
       4: iload_1
       5: aload_0
       6: getfield      #4                  // Field size:I
       9: if_icmplt     51
      12: new           #31                 // class java/lang/IndexOutOfBoundsException
      15: dup
      16: new           #16                 // class java/lang/StringBuffer
      19: dup
      20: invokespecial #17                 // Method java/lang/StringBuffer."<init>":()V
      23: ldc           #32                 // String Index:
      25: invokevirtual #19                 // Method java/lang/StringBuffer.append:(Ljava/lang/String;)Ljava/lang/StringBuffer;
      28: iload_1
      29: invokevirtual #33                 // Method java/lang/StringBuffer.append:(I)Ljava/lang/StringBuffer;
      32: ldc           #34                 // String  Size:
      34: invokevirtual #19                 // Method java/lang/StringBuffer.append:(Ljava/lang/String;)Ljava/lang/StringBuffer;
      37: aload_0
      38: invokevirtual #10                 // Method size:()I
      41: invokevirtual #33                 // Method java/lang/StringBuffer.append:(I)Ljava/lang/StringBuffer;
      44: invokevirtual #23                 // Method java/lang/StringBuffer.toString:()Ljava/lang/String;
      47: invokespecial #35                 // Method java/lang/IndexOutOfBoundsException."<init>":(Ljava/lang/String;)V
      50: athrow
      51: aload_0
      52: getfield      #6                  // Field elementData:[Lorg/jdom/Attribute;
      55: iload_1
      56: aaload
      57: astore_2
      58: aload_2
      59: aconst_null
      60: invokevirtual #36                 // Method org/jdom/Attribute.setParent:(Lorg/jdom/Element;)Lorg/jdom/Attribute;
      63: pop
      64: aload_0
      65: getfield      #4                  // Field size:I
      68: iload_1
      69: isub
      70: iconst_1
      71: isub
      72: istore_3
      73: iload_3
      74: ifle          93
      77: aload_0
      78: getfield      #6                  // Field elementData:[Lorg/jdom/Attribute;
      81: iload_1
      82: iconst_1
      83: iadd
      84: aload_0
      85: getfield      #6                  // Field elementData:[Lorg/jdom/Attribute;
      88: iload_1
      89: iload_3
      90: invokestatic  #37                 // Method java/lang/System.arraycopy:(Ljava/lang/Object;ILjava/lang/Object;II)V
      93: aload_0
      94: getfield      #6                  // Field elementData:[Lorg/jdom/Attribute;
      97: aload_0
      98: dup
      99: getfield      #4                  // Field size:I
     102: iconst_1
     103: isub
     104: dup_x1
     105: putfield      #4                  // Field size:I
     108: aconst_null
     109: aastore
     110: aload_0
     111: dup
     112: getfield      #7                  // Field modCount:I
     115: iconst_1
     116: iadd
     117: putfield      #7                  // Field modCount:I
     120: aload_2
     121: areturn

  boolean remove(java.lang.String, org.jdom.Namespace);
    Code:
       0: aload_0
       1: aload_1
       2: aload_2
       3: invokevirtual #47                 // Method indexOf:(Ljava/lang/String;Lorg/jdom/Namespace;)I
       6: istore_3
       7: iload_3
       8: ifge          13
      11: iconst_0
      12: ireturn
      13: aload_0
      14: iload_3
      15: invokevirtual #45                 // Method remove:(I)Ljava/lang/Object;
      18: pop
      19: iconst_1
      20: ireturn

  public java.lang.Object set(int, java.lang.Object);
    Code:
       0: aload_2
       1: instanceof    #8                  // class org/jdom/Attribute
       4: ifeq          47
       7: aload_2
       8: checkcast     #8                  // class org/jdom/Attribute
      11: astore_3
      12: aload_0
      13: aload_3
      14: invokespecial #9                  // Method indexOfDuplicate:(Lorg/jdom/Attribute;)I
      17: istore        4
      19: iload         4
      21: iflt          40
      24: iload         4
      26: iload_1
      27: if_icmpeq     40
      30: new           #13                 // class org/jdom/IllegalAddException
      33: dup
      34: ldc           #52                 // String Cannot set duplicate attribute
      36: invokespecial #15                 // Method org/jdom/IllegalAddException."<init>":(Ljava/lang/String;)V
      39: athrow
      40: aload_0
      41: iload_1
      42: aload_3
      43: invokevirtual #12                 // Method set:(ILorg/jdom/Attribute;)Ljava/lang/Object;
      46: areturn
      47: aload_2
      48: ifnonnull     61
      51: new           #13                 // class org/jdom/IllegalAddException
      54: dup
      55: ldc           #14                 // String Cannot add null attribute
      57: invokespecial #15                 // Method org/jdom/IllegalAddException."<init>":(Ljava/lang/String;)V
      60: athrow
      61: new           #13                 // class org/jdom/IllegalAddException
      64: dup
      65: new           #16                 // class java/lang/StringBuffer
      68: dup
      69: invokespecial #17                 // Method java/lang/StringBuffer."<init>":()V
      72: ldc           #18                 // String Class
      74: invokevirtual #19                 // Method java/lang/StringBuffer.append:(Ljava/lang/String;)Ljava/lang/StringBuffer;
      77: aload_2
      78: invokevirtual #20                 // Method java/lang/Object.getClass:()Ljava/lang/Class;
      81: invokevirtual #21                 // Method java/lang/Class.getName:()Ljava/lang/String;
      84: invokevirtual #19                 // Method java/lang/StringBuffer.append:(Ljava/lang/String;)Ljava/lang/StringBuffer;
      87: ldc           #22                 // String  is not an attribute
      89: invokevirtual #19                 // Method java/lang/StringBuffer.append:(Ljava/lang/String;)Ljava/lang/StringBuffer;
      92: invokevirtual #23                 // Method java/lang/StringBuffer.toString:()Ljava/lang/String;
      95: invokespecial #15                 // Method org/jdom/IllegalAddException."<init>":(Ljava/lang/String;)V
      98: athrow

  java.lang.Object set(int, org.jdom.Attribute);
    Code:
       0: iload_1
       1: iflt          12
       4: iload_1
       5: aload_0
       6: getfield      #4                  // Field size:I
       9: if_icmplt     51
      12: new           #31                 // class java/lang/IndexOutOfBoundsException
      15: dup
      16: new           #16                 // class java/lang/StringBuffer
      19: dup
      20: invokespecial #17                 // Method java/lang/StringBuffer."<init>":()V
      23: ldc           #32                 // String Index:
      25: invokevirtual #19                 // Method java/lang/StringBuffer.append:(Ljava/lang/String;)Ljava/lang/StringBuffer;
      28: iload_1
      29: invokevirtual #33                 // Method java/lang/StringBuffer.append:(I)Ljava/lang/StringBuffer;
      32: ldc           #34                 // String  Size:
      34: invokevirtual #19                 // Method java/lang/StringBuffer.append:(Ljava/lang/String;)Ljava/lang/StringBuffer;
      37: aload_0
      38: invokevirtual #10                 // Method size:()I
      41: invokevirtual #33                 // Method java/lang/StringBuffer.append:(I)Ljava/lang/StringBuffer;
      44: invokevirtual #23                 // Method java/lang/StringBuffer.toString:()Ljava/lang/String;
      47: invokespecial #35                 // Method java/lang/IndexOutOfBoundsException."<init>":(Ljava/lang/String;)V
      50: athrow
      51: aload_2
      52: invokevirtual #25                 // Method org/jdom/Attribute.getParent:()Lorg/jdom/Element;
      55: ifnull        96
      58: new           #13                 // class org/jdom/IllegalAddException
      61: dup
      62: new           #16                 // class java/lang/StringBuffer
      65: dup
      66: invokespecial #17                 // Method java/lang/StringBuffer."<init>":()V
      69: ldc           #26                 // String The attribute already has an existing parent \"
      71: invokevirtual #19                 // Method java/lang/StringBuffer.append:(Ljava/lang/String;)Ljava/lang/StringBuffer;
      74: aload_2
      75: invokevirtual #25                 // Method org/jdom/Attribute.getParent:()Lorg/jdom/Element;
      78: invokevirtual #27                 // Method org/jdom/Element.getQualifiedName:()Ljava/lang/String;
      81: invokevirtual #19                 // Method java/lang/StringBuffer.append:(Ljava/lang/String;)Ljava/lang/StringBuffer;
      84: ldc           #28                 // String \"
      86: invokevirtual #19                 // Method java/lang/StringBuffer.append:(Ljava/lang/String;)Ljava/lang/StringBuffer;
      89: invokevirtual #23                 // Method java/lang/StringBuffer.toString:()Ljava/lang/String;
      92: invokespecial #15                 // Method org/jdom/IllegalAddException."<init>":(Ljava/lang/String;)V
      95: athrow
      96: aload_2
      97: aload_0
      98: getfield      #2                  // Field parent:Lorg/jdom/Element;
     101: invokestatic  #29                 // Method org/jdom/Verifier.checkNamespaceCollision:(Lorg/jdom/Attribute;Lorg/jdom/Element;)Ljava/lang/String;
     104: astore_3
     105: aload_3
     106: ifnull        123
     109: new           #13                 // class org/jdom/IllegalAddException
     112: dup
     113: aload_0
     114: getfield      #2                  // Field parent:Lorg/jdom/Element;
     117: aload_2
     118: aload_3
     119: invokespecial #30                 // Method org/jdom/IllegalAddException."<init>":(Lorg/jdom/Element;Lorg/jdom/Attribute;Ljava/lang/String;)V
     122: athrow
     123: aload_0
     124: getfield      #6                  // Field elementData:[Lorg/jdom/Attribute;
     127: iload_1
     128: aaload
     129: astore        4
     131: aload         4
     133: aconst_null
     134: invokevirtual #36                 // Method org/jdom/Attribute.setParent:(Lorg/jdom/Element;)Lorg/jdom/Attribute;
     137: pop
     138: aload_0
     139: getfield      #6                  // Field elementData:[Lorg/jdom/Attribute;
     142: iload_1
     143: aload_2
     144: aastore
     145: aload_2
     146: aload_0
     147: getfield      #2                  // Field parent:Lorg/jdom/Element;
     150: invokevirtual #36                 // Method org/jdom/Attribute.setParent:(Lorg/jdom/Element;)Lorg/jdom/Attribute;
     153: pop
     154: aload         4
     156: areturn

  private int indexOfDuplicate(org.jdom.Attribute);
    Code:
       0: iconst_m1
       1: istore_2
       2: aload_1
       3: invokevirtual #50                 // Method org/jdom/Attribute.getName:()Ljava/lang/String;
       6: astore_3
       7: aload_1
       8: invokevirtual #53                 // Method org/jdom/Attribute.getNamespace:()Lorg/jdom/Namespace;
      11: astore        4
      13: aload_0
      14: aload_3
      15: aload         4
      17: invokevirtual #47                 // Method indexOf:(Ljava/lang/String;Lorg/jdom/Namespace;)I
      20: istore_2
      21: iload_2
      22: ireturn

  public int size();
    Code:
       0: aload_0
       1: getfield      #4                  // Field size:I
       4: ireturn

  public java.lang.String toString();
    Code:
       0: aload_0
       1: invokespecial #54                 // Method java/util/AbstractList.toString:()Ljava/lang/String;
       4: areturn
}
