Compiled from "ContentList.java"
class org.jdom.ContentList$FilterListIterator implements java.util.ListIterator {
  org.jdom.filter.Filter filter;

  private boolean forward;

  private boolean canremove;

  private boolean canset;

  private int cursor;

  private int tmpcursor;

  private int index;

  private int expected;

  private int fsize;

  private final org.jdom.ContentList this$0;

  org.jdom.ContentList$FilterListIterator(org.jdom.ContentList, org.jdom.filter.Filter, int);
    Code:
       0: aload_0
       1: invokespecial #1                  // Method java/lang/Object."<init>":()V
       4: aload_0
       5: aload_1
       6: putfield      #2                  // Field this$0:Lorg/jdom/ContentList;
       9: aload_0
      10: iconst_0
      11: putfield      #3                  // Field forward:Z
      14: aload_0
      15: iconst_0
      16: putfield      #4                  // Field canremove:Z
      19: aload_0
      20: iconst_0
      21: putfield      #5                  // Field canset:Z
      24: aload_0
      25: iconst_m1
      26: putfield      #6                  // Field cursor:I
      29: aload_0
      30: iconst_m1
      31: putfield      #7                  // Field tmpcursor:I
      34: aload_0
      35: iconst_m1
      36: putfield      #8                  // Field index:I
      39: aload_0
      40: iconst_m1
      41: putfield      #9                  // Field expected:I
      44: aload_0
      45: iconst_0
      46: putfield      #10                 // Field fsize:I
      49: aload_0
      50: aload_2
      51: putfield      #11                 // Field filter:Lorg/jdom/filter/Filter;
      54: aload_0
      55: aload_1
      56: invokestatic  #12                 // Method org/jdom/ContentList.access$000:(Lorg/jdom/ContentList;)I
      59: putfield      #9                  // Field expected:I
      62: aload_0
      63: iconst_0
      64: putfield      #3                  // Field forward:Z
      67: iload_3
      68: ifge          98
      71: new           #13                 // class java/lang/IndexOutOfBoundsException
      74: dup
      75: new           #14                 // class java/lang/StringBuffer
      78: dup
      79: invokespecial #15                 // Method java/lang/StringBuffer."<init>":()V
      82: ldc           #16                 // String Index:
      84: invokevirtual #17                 // Method java/lang/StringBuffer.append:(Ljava/lang/String;)Ljava/lang/StringBuffer;
      87: iload_3
      88: invokevirtual #18                 // Method java/lang/StringBuffer.append:(I)Ljava/lang/StringBuffer;
      91: invokevirtual #19                 // Method java/lang/StringBuffer.toString:()Ljava/lang/String;
      94: invokespecial #20                 // Method java/lang/IndexOutOfBoundsException."<init>":(Ljava/lang/String;)V
      97: athrow
      98: aload_0
      99: iconst_0
     100: putfield      #10                 // Field fsize:I
     103: iconst_0
     104: istore        4
     106: iload         4
     108: aload_1
     109: invokevirtual #21                 // Method org/jdom/ContentList.size:()I
     112: if_icmpge     168
     115: aload_2
     116: aload_1
     117: iload         4
     119: invokevirtual #22                 // Method org/jdom/ContentList.get:(I)Ljava/lang/Object;
     122: invokeinterface #23,  2           // InterfaceMethod org/jdom/filter/Filter.matches:(Ljava/lang/Object;)Z
     127: ifeq          162
     130: iload_3
     131: aload_0
     132: getfield      #10                 // Field fsize:I
     135: if_icmpne     152
     138: aload_0
     139: iload         4
     141: putfield      #6                  // Field cursor:I
     144: aload_0
     145: aload_0
     146: getfield      #10                 // Field fsize:I
     149: putfield      #8                  // Field index:I
     152: aload_0
     153: dup
     154: getfield      #10                 // Field fsize:I
     157: iconst_1
     158: iadd
     159: putfield      #10                 // Field fsize:I
     162: iinc          4, 1
     165: goto          106
     168: iload_3
     169: aload_0
     170: getfield      #10                 // Field fsize:I
     173: if_icmple     215
     176: new           #13                 // class java/lang/IndexOutOfBoundsException
     179: dup
     180: new           #14                 // class java/lang/StringBuffer
     183: dup
     184: invokespecial #15                 // Method java/lang/StringBuffer."<init>":()V
     187: ldc           #16                 // String Index:
     189: invokevirtual #17                 // Method java/lang/StringBuffer.append:(Ljava/lang/String;)Ljava/lang/StringBuffer;
     192: iload_3
     193: invokevirtual #18                 // Method java/lang/StringBuffer.append:(I)Ljava/lang/StringBuffer;
     196: ldc           #24                 // String  Size:
     198: invokevirtual #17                 // Method java/lang/StringBuffer.append:(Ljava/lang/String;)Ljava/lang/StringBuffer;
     201: aload_0
     202: getfield      #10                 // Field fsize:I
     205: invokevirtual #18                 // Method java/lang/StringBuffer.append:(I)Ljava/lang/StringBuffer;
     208: invokevirtual #19                 // Method java/lang/StringBuffer.toString:()Ljava/lang/String;
     211: invokespecial #20                 // Method java/lang/IndexOutOfBoundsException."<init>":(Ljava/lang/String;)V
     214: athrow
     215: aload_0
     216: getfield      #6                  // Field cursor:I
     219: iconst_m1
     220: if_icmpne     239
     223: aload_0
     224: aload_1
     225: invokevirtual #21                 // Method org/jdom/ContentList.size:()I
     228: putfield      #6                  // Field cursor:I
     231: aload_0
     232: aload_0
     233: getfield      #10                 // Field fsize:I
     236: putfield      #8                  // Field index:I
     239: return

  public boolean hasNext();
    Code:
       0: aload_0
       1: invokevirtual #25                 // Method nextIndex:()I
       4: aload_0
       5: getfield      #10                 // Field fsize:I
       8: if_icmpge     15
      11: iconst_1
      12: goto          16
      15: iconst_0
      16: ireturn

  public java.lang.Object next();
    Code:
       0: aload_0
       1: invokevirtual #26                 // Method hasNext:()Z
       4: ifne          17
       7: new           #27                 // class java/util/NoSuchElementException
      10: dup
      11: ldc           #28                 // String next() is beyond the end of the Iterator
      13: invokespecial #29                 // Method java/util/NoSuchElementException."<init>":(Ljava/lang/String;)V
      16: athrow
      17: aload_0
      18: aload_0
      19: invokevirtual #25                 // Method nextIndex:()I
      22: putfield      #8                  // Field index:I
      25: aload_0
      26: aload_0
      27: getfield      #7                  // Field tmpcursor:I
      30: putfield      #6                  // Field cursor:I
      33: aload_0
      34: iconst_1
      35: putfield      #3                  // Field forward:Z
      38: aload_0
      39: iconst_1
      40: putfield      #4                  // Field canremove:Z
      43: aload_0
      44: iconst_1
      45: putfield      #5                  // Field canset:Z
      48: aload_0
      49: getfield      #2                  // Field this$0:Lorg/jdom/ContentList;
      52: aload_0
      53: getfield      #6                  // Field cursor:I
      56: invokevirtual #22                 // Method org/jdom/ContentList.get:(I)Ljava/lang/Object;
      59: areturn

  public boolean hasPrevious();
    Code:
       0: aload_0
       1: invokevirtual #30                 // Method previousIndex:()I
       4: iflt          11
       7: iconst_1
       8: goto          12
      11: iconst_0
      12: ireturn

  public java.lang.Object previous();
    Code:
       0: aload_0
       1: invokevirtual #31                 // Method hasPrevious:()Z
       4: ifne          17
       7: new           #27                 // class java/util/NoSuchElementException
      10: dup
      11: ldc           #32                 // String previous() is before the start of the Iterator
      13: invokespecial #29                 // Method java/util/NoSuchElementException."<init>":(Ljava/lang/String;)V
      16: athrow
      17: aload_0
      18: aload_0
      19: invokevirtual #30                 // Method previousIndex:()I
      22: putfield      #8                  // Field index:I
      25: aload_0
      26: aload_0
      27: getfield      #7                  // Field tmpcursor:I
      30: putfield      #6                  // Field cursor:I
      33: aload_0
      34: iconst_0
      35: putfield      #3                  // Field forward:Z
      38: aload_0
      39: iconst_1
      40: putfield      #4                  // Field canremove:Z
      43: aload_0
      44: iconst_1
      45: putfield      #5                  // Field canset:Z
      48: aload_0
      49: getfield      #2                  // Field this$0:Lorg/jdom/ContentList;
      52: aload_0
      53: getfield      #6                  // Field cursor:I
      56: invokevirtual #22                 // Method org/jdom/ContentList.get:(I)Ljava/lang/Object;
      59: areturn

  public int nextIndex();
    Code:
       0: aload_0
       1: invokespecial #33                 // Method checkConcurrentModification:()V
       4: aload_0
       5: getfield      #3                  // Field forward:Z
       8: ifeq          85
      11: aload_0
      12: getfield      #6                  // Field cursor:I
      15: iconst_1
      16: iadd
      17: istore_1
      18: iload_1
      19: aload_0
      20: getfield      #2                  // Field this$0:Lorg/jdom/ContentList;
      23: invokevirtual #21                 // Method org/jdom/ContentList.size:()I
      26: if_icmpge     67
      29: aload_0
      30: getfield      #11                 // Field filter:Lorg/jdom/filter/Filter;
      33: aload_0
      34: getfield      #2                  // Field this$0:Lorg/jdom/ContentList;
      37: iload_1
      38: invokevirtual #22                 // Method org/jdom/ContentList.get:(I)Ljava/lang/Object;
      41: invokeinterface #23,  2           // InterfaceMethod org/jdom/filter/Filter.matches:(Ljava/lang/Object;)Z
      46: ifeq          61
      49: aload_0
      50: iload_1
      51: putfield      #7                  // Field tmpcursor:I
      54: aload_0
      55: getfield      #8                  // Field index:I
      58: iconst_1
      59: iadd
      60: ireturn
      61: iinc          1, 1
      64: goto          18
      67: aload_0
      68: aload_0
      69: getfield      #2                  // Field this$0:Lorg/jdom/ContentList;
      72: invokevirtual #21                 // Method org/jdom/ContentList.size:()I
      75: putfield      #7                  // Field tmpcursor:I
      78: aload_0
      79: getfield      #8                  // Field index:I
      82: iconst_1
      83: iadd
      84: ireturn
      85: aload_0
      86: aload_0
      87: getfield      #6                  // Field cursor:I
      90: putfield      #7                  // Field tmpcursor:I
      93: aload_0
      94: getfield      #8                  // Field index:I
      97: ireturn

  public int previousIndex();
    Code:
       0: aload_0
       1: invokespecial #33                 // Method checkConcurrentModification:()V
       4: aload_0
       5: getfield      #3                  // Field forward:Z
       8: ifne          72
      11: aload_0
      12: getfield      #6                  // Field cursor:I
      15: iconst_1
      16: isub
      17: istore_1
      18: iload_1
      19: iflt          60
      22: aload_0
      23: getfield      #11                 // Field filter:Lorg/jdom/filter/Filter;
      26: aload_0
      27: getfield      #2                  // Field this$0:Lorg/jdom/ContentList;
      30: iload_1
      31: invokevirtual #22                 // Method org/jdom/ContentList.get:(I)Ljava/lang/Object;
      34: invokeinterface #23,  2           // InterfaceMethod org/jdom/filter/Filter.matches:(Ljava/lang/Object;)Z
      39: ifeq          54
      42: aload_0
      43: iload_1
      44: putfield      #7                  // Field tmpcursor:I
      47: aload_0
      48: getfield      #8                  // Field index:I
      51: iconst_1
      52: isub
      53: ireturn
      54: iinc          1, -1
      57: goto          18
      60: aload_0
      61: iconst_m1
      62: putfield      #7                  // Field tmpcursor:I
      65: aload_0
      66: getfield      #8                  // Field index:I
      69: iconst_1
      70: isub
      71: ireturn
      72: aload_0
      73: aload_0
      74: getfield      #6                  // Field cursor:I
      77: putfield      #7                  // Field tmpcursor:I
      80: aload_0
      81: getfield      #8                  // Field index:I
      84: ireturn

  public void add(java.lang.Object);
    Code:
       0: aload_0
       1: getfield      #11                 // Field filter:Lorg/jdom/filter/Filter;
       4: aload_1
       5: invokeinterface #23,  2           // InterfaceMethod org/jdom/filter/Filter.matches:(Ljava/lang/Object;)Z
      10: ifne          60
      13: new           #34                 // class org/jdom/IllegalAddException
      16: dup
      17: new           #14                 // class java/lang/StringBuffer
      20: dup
      21: invokespecial #15                 // Method java/lang/StringBuffer."<init>":()V
      24: ldc           #35                 // String Filter won\'t allow the
      26: invokevirtual #17                 // Method java/lang/StringBuffer.append:(Ljava/lang/String;)Ljava/lang/StringBuffer;
      29: aload_1
      30: invokevirtual #36                 // Method java/lang/Object.getClass:()Ljava/lang/Class;
      33: invokevirtual #37                 // Method java/lang/Class.getName:()Ljava/lang/String;
      36: invokevirtual #17                 // Method java/lang/StringBuffer.append:(Ljava/lang/String;)Ljava/lang/StringBuffer;
      39: ldc           #38                 // String  \'
      41: invokevirtual #17                 // Method java/lang/StringBuffer.append:(Ljava/lang/String;)Ljava/lang/StringBuffer;
      44: aload_1
      45: invokevirtual #39                 // Method java/lang/StringBuffer.append:(Ljava/lang/Object;)Ljava/lang/StringBuffer;
      48: ldc           #40                 // String \' to be added to the list
      50: invokevirtual #17                 // Method java/lang/StringBuffer.append:(Ljava/lang/String;)Ljava/lang/StringBuffer;
      53: invokevirtual #19                 // Method java/lang/StringBuffer.toString:()Ljava/lang/String;
      56: invokespecial #41                 // Method org/jdom/IllegalAddException."<init>":(Ljava/lang/String;)V
      59: athrow
      60: aload_0
      61: invokevirtual #25                 // Method nextIndex:()I
      64: pop
      65: aload_0
      66: getfield      #2                  // Field this$0:Lorg/jdom/ContentList;
      69: aload_0
      70: getfield      #7                  // Field tmpcursor:I
      73: aload_1
      74: invokevirtual #42                 // Method org/jdom/ContentList.add:(ILjava/lang/Object;)V
      77: aload_0
      78: aload_0
      79: getfield      #2                  // Field this$0:Lorg/jdom/ContentList;
      82: invokestatic  #12                 // Method org/jdom/ContentList.access$000:(Lorg/jdom/ContentList;)I
      85: putfield      #9                  // Field expected:I
      88: aload_0
      89: aload_0
      90: iconst_0
      91: dup_x1
      92: putfield      #5                  // Field canset:Z
      95: putfield      #4                  // Field canremove:Z
      98: aload_0
      99: getfield      #3                  // Field forward:Z
     102: ifeq          118
     105: aload_0
     106: dup
     107: getfield      #8                  // Field index:I
     110: iconst_1
     111: iadd
     112: putfield      #8                  // Field index:I
     115: goto          123
     118: aload_0
     119: iconst_1
     120: putfield      #3                  // Field forward:Z
     123: aload_0
     124: dup
     125: getfield      #10                 // Field fsize:I
     128: iconst_1
     129: iadd
     130: putfield      #10                 // Field fsize:I
     133: aload_0
     134: aload_0
     135: getfield      #7                  // Field tmpcursor:I
     138: putfield      #6                  // Field cursor:I
     141: return

  public void remove();
    Code:
       0: aload_0
       1: getfield      #4                  // Field canremove:Z
       4: ifne          17
       7: new           #43                 // class java/lang/IllegalStateException
      10: dup
      11: ldc           #44                 // String Can not remove an element unless either next() or previous() has been called since the last remove()
      13: invokespecial #45                 // Method java/lang/IllegalStateException."<init>":(Ljava/lang/String;)V
      16: athrow
      17: aload_0
      18: getfield      #3                  // Field forward:Z
      21: istore_1
      22: aload_0
      23: iconst_1
      24: putfield      #3                  // Field forward:Z
      27: aload_0
      28: invokevirtual #25                 // Method nextIndex:()I
      31: pop
      32: aload_0
      33: getfield      #2                  // Field this$0:Lorg/jdom/ContentList;
      36: aload_0
      37: getfield      #6                  // Field cursor:I
      40: invokevirtual #46                 // Method org/jdom/ContentList.remove:(I)Ljava/lang/Object;
      43: pop
      44: aload_0
      45: iload_1
      46: putfield      #3                  // Field forward:Z
      49: goto          60
      52: astore_2
      53: aload_0
      54: iload_1
      55: putfield      #3                  // Field forward:Z
      58: aload_2
      59: athrow
      60: aload_0
      61: aload_0
      62: getfield      #7                  // Field tmpcursor:I
      65: iconst_1
      66: isub
      67: putfield      #6                  // Field cursor:I
      70: aload_0
      71: aload_0
      72: getfield      #2                  // Field this$0:Lorg/jdom/ContentList;
      75: invokestatic  #12                 // Method org/jdom/ContentList.access$000:(Lorg/jdom/ContentList;)I
      78: putfield      #9                  // Field expected:I
      81: aload_0
      82: iconst_0
      83: putfield      #3                  // Field forward:Z
      86: aload_0
      87: iconst_0
      88: putfield      #4                  // Field canremove:Z
      91: aload_0
      92: iconst_0
      93: putfield      #5                  // Field canset:Z
      96: aload_0
      97: dup
      98: getfield      #10                 // Field fsize:I
     101: iconst_1
     102: isub
     103: putfield      #10                 // Field fsize:I
     106: return
    Exception table:
       from    to  target type
          27    44    52   any
          52    53    52   any

  public void set(java.lang.Object);
    Code:
       0: aload_0
       1: getfield      #5                  // Field canset:Z
       4: ifne          17
       7: new           #43                 // class java/lang/IllegalStateException
      10: dup
      11: ldc           #47                 // String Can not set an element unless either next() or previous() has been called since the last remove() or set()
      13: invokespecial #45                 // Method java/lang/IllegalStateException."<init>":(Ljava/lang/String;)V
      16: athrow
      17: aload_0
      18: invokespecial #33                 // Method checkConcurrentModification:()V
      21: aload_0
      22: getfield      #11                 // Field filter:Lorg/jdom/filter/Filter;
      25: aload_1
      26: invokeinterface #23,  2           // InterfaceMethod org/jdom/filter/Filter.matches:(Ljava/lang/Object;)Z
      31: ifne          79
      34: new           #34                 // class org/jdom/IllegalAddException
      37: dup
      38: new           #14                 // class java/lang/StringBuffer
      41: dup
      42: invokespecial #15                 // Method java/lang/StringBuffer."<init>":()V
      45: ldc           #48                 // String Filter won\'t allow index
      47: invokevirtual #17                 // Method java/lang/StringBuffer.append:(Ljava/lang/String;)Ljava/lang/StringBuffer;
      50: aload_0
      51: getfield      #8                  // Field index:I
      54: invokevirtual #18                 // Method java/lang/StringBuffer.append:(I)Ljava/lang/StringBuffer;
      57: ldc           #49                 // String  to be set to
      59: invokevirtual #17                 // Method java/lang/StringBuffer.append:(Ljava/lang/String;)Ljava/lang/StringBuffer;
      62: aload_1
      63: invokevirtual #36                 // Method java/lang/Object.getClass:()Ljava/lang/Class;
      66: invokevirtual #37                 // Method java/lang/Class.getName:()Ljava/lang/String;
      69: invokevirtual #17                 // Method java/lang/StringBuffer.append:(Ljava/lang/String;)Ljava/lang/StringBuffer;
      72: invokevirtual #19                 // Method java/lang/StringBuffer.toString:()Ljava/lang/String;
      75: invokespecial #41                 // Method org/jdom/IllegalAddException."<init>":(Ljava/lang/String;)V
      78: athrow
      79: aload_0
      80: getfield      #2                  // Field this$0:Lorg/jdom/ContentList;
      83: aload_0
      84: getfield      #6                  // Field cursor:I
      87: aload_1
      88: invokevirtual #50                 // Method org/jdom/ContentList.set:(ILjava/lang/Object;)Ljava/lang/Object;
      91: pop
      92: aload_0
      93: aload_0
      94: getfield      #2                  // Field this$0:Lorg/jdom/ContentList;
      97: invokestatic  #12                 // Method org/jdom/ContentList.access$000:(Lorg/jdom/ContentList;)I
     100: putfield      #9                  // Field expected:I
     103: return

  private void checkConcurrentModification();
    Code:
       0: aload_0
       1: getfield      #9                  // Field expected:I
       4: aload_0
       5: getfield      #2                  // Field this$0:Lorg/jdom/ContentList;
       8: invokestatic  #12                 // Method org/jdom/ContentList.access$000:(Lorg/jdom/ContentList;)I
      11: if_icmpeq     22
      14: new           #51                 // class java/util/ConcurrentModificationException
      17: dup
      18: invokespecial #52                 // Method java/util/ConcurrentModificationException."<init>":()V
      21: athrow
      22: return
}
