Compiled from "FilterIterator.java"
class org.jdom.FilterIterator implements java.util.Iterator {
  private java.util.Iterator iterator;

  private org.jdom.filter.Filter filter;

  private java.lang.Object nextObject;

  private static final java.lang.String CVS_ID;

  public org.jdom.FilterIterator(java.util.Iterator, org.jdom.filter.Filter);
    Code:
       0: aload_0
       1: invokespecial #1                  // Method java/lang/Object."<init>":()V
       4: aload_1
       5: ifnull        12
       8: aload_2
       9: ifnonnull     22
      12: new           #2                  // class java/lang/IllegalArgumentException
      15: dup
      16: ldc           #3                  // String null parameter
      18: invokespecial #4                  // Method java/lang/IllegalArgumentException."<init>":(Ljava/lang/String;)V
      21: athrow
      22: aload_0
      23: aload_1
      24: putfield      #5                  // Field iterator:Ljava/util/Iterator;
      27: aload_0
      28: aload_2
      29: putfield      #6                  // Field filter:Lorg/jdom/filter/Filter;
      32: return

  public boolean hasNext();
    Code:
       0: aload_0
       1: getfield      #7                  // Field nextObject:Ljava/lang/Object;
       4: ifnull        9
       7: iconst_1
       8: ireturn
       9: aload_0
      10: getfield      #5                  // Field iterator:Ljava/util/Iterator;
      13: invokeinterface #8,  1            // InterfaceMethod java/util/Iterator.hasNext:()Z
      18: ifeq          54
      21: aload_0
      22: getfield      #5                  // Field iterator:Ljava/util/Iterator;
      25: invokeinterface #9,  1            // InterfaceMethod java/util/Iterator.next:()Ljava/lang/Object;
      30: astore_1
      31: aload_0
      32: getfield      #6                  // Field filter:Lorg/jdom/filter/Filter;
      35: aload_1
      36: invokeinterface #10,  2           // InterfaceMethod org/jdom/filter/Filter.matches:(Ljava/lang/Object;)Z
      41: ifeq          51
      44: aload_0
      45: aload_1
      46: putfield      #7                  // Field nextObject:Ljava/lang/Object;
      49: iconst_1
      50: ireturn
      51: goto          9
      54: iconst_0
      55: ireturn

  public java.lang.Object next();
    Code:
       0: aload_0
       1: invokevirtual #11                 // Method hasNext:()Z
       4: ifne          15
       7: new           #12                 // class java/util/NoSuchElementException
      10: dup
      11: invokespecial #13                 // Method java/util/NoSuchElementException."<init>":()V
      14: athrow
      15: aload_0
      16: getfield      #7                  // Field nextObject:Ljava/lang/Object;
      19: astore_1
      20: aload_0
      21: aconst_null
      22: putfield      #7                  // Field nextObject:Ljava/lang/Object;
      25: aload_1
      26: areturn

  public void remove();
    Code:
       0: aload_0
       1: getfield      #5                  // Field iterator:Ljava/util/Iterator;
       4: invokeinterface #14,  1           // InterfaceMethod java/util/Iterator.remove:()V
       9: return
}
