Compiled from "JDOMException.java"
public class org.jdom.JDOMException extends java.lang.Exception {
  private static final java.lang.String CVS_ID;

  private java.lang.Throwable cause;

  public org.jdom.JDOMException();
    Code:
       0: aload_0
       1: ldc           #1                  // String Error occurred in JDOM application.
       3: invokespecial #2                  // Method java/lang/Exception."<init>":(Ljava/lang/String;)V
       6: return

  public org.jdom.JDOMException(java.lang.String);
    Code:
       0: aload_0
       1: aload_1
       2: invokespecial #2                  // Method java/lang/Exception."<init>":(Ljava/lang/String;)V
       5: return

  public org.jdom.JDOMException(java.lang.String, java.lang.Throwable);
    Code:
       0: aload_0
       1: aload_1
       2: invokespecial #2                  // Method java/lang/Exception."<init>":(Ljava/lang/String;)V
       5: aload_0
       6: aload_2
       7: putfield      #3                  // Field cause:Ljava/lang/Throwable;
      10: return

  public java.lang.Throwable initCause(java.lang.Throwable);
    Code:
       0: aload_0
       1: aload_1
       2: putfield      #3                  // Field cause:Ljava/lang/Throwable;
       5: aload_0
       6: areturn

  public java.lang.String getMessage();
    Code:
       0: aload_0
       1: invokespecial #4                  // Method java/lang/Exception.getMessage:()Ljava/lang/String;
       4: astore_1
       5: aload_0
       6: astore_2
       7: aload_2
       8: invokestatic  #5                  // Method getNestedException:(Ljava/lang/Throwable;)Ljava/lang/Throwable;
      11: dup
      12: astore_3
      13: ifnull        119
      16: aload_3
      17: invokevirtual #6                  // Method java/lang/Throwable.getMessage:()Ljava/lang/String;
      20: astore        4
      22: aload_3
      23: instanceof    #7                  // class org/xml/sax/SAXException
      26: ifeq          64
      29: aload_3
      30: checkcast     #7                  // class org/xml/sax/SAXException
      33: invokevirtual #8                  // Method org/xml/sax/SAXException.getException:()Ljava/lang/Exception;
      36: astore        5
      38: aload         5
      40: ifnull        64
      43: aload         4
      45: ifnull        64
      48: aload         4
      50: aload         5
      52: invokevirtual #6                  // Method java/lang/Throwable.getMessage:()Ljava/lang/String;
      55: invokevirtual #9                  // Method java/lang/String.equals:(Ljava/lang/Object;)Z
      58: ifeq          64
      61: aconst_null
      62: astore        4
      64: aload         4
      66: ifnull        104
      69: aload_1
      70: ifnull        101
      73: new           #10                 // class java/lang/StringBuffer
      76: dup
      77: invokespecial #11                 // Method java/lang/StringBuffer."<init>":()V
      80: aload_1
      81: invokevirtual #12                 // Method java/lang/StringBuffer.append:(Ljava/lang/String;)Ljava/lang/StringBuffer;
      84: ldc           #13                 // String :
      86: invokevirtual #12                 // Method java/lang/StringBuffer.append:(Ljava/lang/String;)Ljava/lang/StringBuffer;
      89: aload         4
      91: invokevirtual #12                 // Method java/lang/StringBuffer.append:(Ljava/lang/String;)Ljava/lang/StringBuffer;
      94: invokevirtual #14                 // Method java/lang/StringBuffer.toString:()Ljava/lang/String;
      97: astore_1
      98: goto          104
     101: aload         4
     103: astore_1
     104: aload_3
     105: instanceof    #15                 // class org/jdom/JDOMException
     108: ifeq          114
     111: goto          119
     114: aload_3
     115: astore_2
     116: goto          7
     119: aload_1
     120: areturn

  public void printStackTrace();
    Code:
       0: aload_0
       1: invokespecial #16                 // Method java/lang/Exception.printStackTrace:()V
       4: aload_0
       5: astore_1
       6: aload_1
       7: invokestatic  #5                  // Method getNestedException:(Ljava/lang/Throwable;)Ljava/lang/Throwable;
      10: dup
      11: astore_2
      12: ifnull        42
      15: getstatic     #17                 // Field java/lang/System.err:Ljava/io/PrintStream;
      18: ldc           #18                 // String Caused by:
      20: invokevirtual #19                 // Method java/io/PrintStream.print:(Ljava/lang/String;)V
      23: aload_2
      24: invokevirtual #20                 // Method java/lang/Throwable.printStackTrace:()V
      27: aload_2
      28: instanceof    #15                 // class org/jdom/JDOMException
      31: ifeq          37
      34: goto          42
      37: aload_2
      38: astore_1
      39: goto          6
      42: return

  public void printStackTrace(java.io.PrintStream);
    Code:
       0: aload_0
       1: aload_1
       2: invokespecial #21                 // Method java/lang/Exception.printStackTrace:(Ljava/io/PrintStream;)V
       5: aload_0
       6: astore_2
       7: aload_2
       8: invokestatic  #5                  // Method getNestedException:(Ljava/lang/Throwable;)Ljava/lang/Throwable;
      11: dup
      12: astore_3
      13: ifnull        42
      16: aload_1
      17: ldc           #18                 // String Caused by:
      19: invokevirtual #19                 // Method java/io/PrintStream.print:(Ljava/lang/String;)V
      22: aload_3
      23: aload_1
      24: invokevirtual #22                 // Method java/lang/Throwable.printStackTrace:(Ljava/io/PrintStream;)V
      27: aload_3
      28: instanceof    #15                 // class org/jdom/JDOMException
      31: ifeq          37
      34: goto          42
      37: aload_3
      38: astore_2
      39: goto          7
      42: return

  public void printStackTrace(java.io.PrintWriter);
    Code:
       0: aload_0
       1: aload_1
       2: invokespecial #23                 // Method java/lang/Exception.printStackTrace:(Ljava/io/PrintWriter;)V
       5: aload_0
       6: astore_2
       7: aload_2
       8: invokestatic  #5                  // Method getNestedException:(Ljava/lang/Throwable;)Ljava/lang/Throwable;
      11: dup
      12: astore_3
      13: ifnull        42
      16: aload_1
      17: ldc           #18                 // String Caused by:
      19: invokevirtual #24                 // Method java/io/PrintWriter.print:(Ljava/lang/String;)V
      22: aload_3
      23: aload_1
      24: invokevirtual #25                 // Method java/lang/Throwable.printStackTrace:(Ljava/io/PrintWriter;)V
      27: aload_3
      28: instanceof    #15                 // class org/jdom/JDOMException
      31: ifeq          37
      34: goto          42
      37: aload_3
      38: astore_2
      39: goto          7
      42: return

  public java.lang.Throwable getCause();
    Code:
       0: aload_0
       1: getfield      #3                  // Field cause:Ljava/lang/Throwable;
       4: areturn

  private static java.lang.Throwable getNestedException(java.lang.Throwable);
    Code:
       0: aload_0
       1: instanceof    #15                 // class org/jdom/JDOMException
       4: ifeq          15
       7: aload_0
       8: checkcast     #15                 // class org/jdom/JDOMException
      11: invokevirtual #26                 // Method getCause:()Ljava/lang/Throwable;
      14: areturn
      15: aload_0
      16: instanceof    #7                  // class org/xml/sax/SAXException
      19: ifeq          30
      22: aload_0
      23: checkcast     #7                  // class org/xml/sax/SAXException
      26: invokevirtual #8                  // Method org/xml/sax/SAXException.getException:()Ljava/lang/Exception;
      29: areturn
      30: aload_0
      31: instanceof    #27                 // class java/sql/SQLException
      34: ifeq          45
      37: aload_0
      38: checkcast     #27                 // class java/sql/SQLException
      41: invokevirtual #28                 // Method java/sql/SQLException.getNextException:()Ljava/sql/SQLException;
      44: areturn
      45: aload_0
      46: instanceof    #29                 // class java/lang/reflect/InvocationTargetException
      49: ifeq          60
      52: aload_0
      53: checkcast     #29                 // class java/lang/reflect/InvocationTargetException
      56: invokevirtual #30                 // Method java/lang/reflect/InvocationTargetException.getTargetException:()Ljava/lang/Throwable;
      59: areturn
      60: aload_0
      61: instanceof    #31                 // class java/lang/ExceptionInInitializerError
      64: ifeq          75
      67: aload_0
      68: checkcast     #31                 // class java/lang/ExceptionInInitializerError
      71: invokevirtual #32                 // Method java/lang/ExceptionInInitializerError.getException:()Ljava/lang/Throwable;
      74: areturn
      75: aload_0
      76: ldc           #33                 // String java.rmi.RemoteException
      78: ldc           #34                 // String detail
      80: invokestatic  #35                 // Method getNestedExceptionFromField:(Ljava/lang/Throwable;Ljava/lang/String;Ljava/lang/String;)Ljava/lang/Throwable;
      83: astore_1
      84: aload_1
      85: ifnull        90
      88: aload_1
      89: areturn
      90: aload_0
      91: ldc           #36                 // String javax.naming.NamingException
      93: ldc           #37                 // String getRootCause
      95: invokestatic  #38                 // Method getNestedException:(Ljava/lang/Throwable;Ljava/lang/String;Ljava/lang/String;)Ljava/lang/Throwable;
      98: astore_1
      99: aload_1
     100: ifnull        105
     103: aload_1
     104: areturn
     105: aload_0
     106: ldc           #39                 // String javax.servlet.ServletException
     108: ldc           #37                 // String getRootCause
     110: invokestatic  #38                 // Method getNestedException:(Ljava/lang/Throwable;Ljava/lang/String;Ljava/lang/String;)Ljava/lang/Throwable;
     113: astore_1
     114: aload_1
     115: ifnull        120
     118: aload_1
     119: areturn
     120: aconst_null
     121: areturn

  private static java.lang.Throwable getNestedException(java.lang.Throwable, java.lang.String, java.lang.String);
    Code:
       0: aload_1
       1: invokestatic  #40                 // Method java/lang/Class.forName:(Ljava/lang/String;)Ljava/lang/Class;
       4: astore_3
       5: aload_0
       6: invokevirtual #41                 // Method java/lang/Object.getClass:()Ljava/lang/Class;
       9: astore        4
      11: aload_3
      12: aload         4
      14: invokevirtual #42                 // Method java/lang/Class.isAssignableFrom:(Ljava/lang/Class;)Z
      17: ifeq          53
      20: iconst_0
      21: anewarray     #43                 // class java/lang/Class
      24: astore        5
      26: aload_3
      27: aload_2
      28: aload         5
      30: invokevirtual #44                 // Method java/lang/Class.getMethod:(Ljava/lang/String;[Ljava/lang/Class;)Ljava/lang/reflect/Method;
      33: astore        6
      35: iconst_0
      36: anewarray     #45                 // class java/lang/Object
      39: astore        7
      41: aload         6
      43: aload_0
      44: aload         7
      46: invokevirtual #46                 // Method java/lang/reflect/Method.invoke:(Ljava/lang/Object;[Ljava/lang/Object;)Ljava/lang/Object;
      49: checkcast     #47                 // class java/lang/Throwable
      52: areturn
      53: goto          57
      56: astore_3
      57: aconst_null
      58: areturn
    Exception table:
       from    to  target type
           0    52    56   Class java/lang/Exception

  private static java.lang.Throwable getNestedExceptionFromField(java.lang.Throwable, java.lang.String, java.lang.String);
    Code:
       0: aload_1
       1: invokestatic  #40                 // Method java/lang/Class.forName:(Ljava/lang/String;)Ljava/lang/Class;
       4: astore_3
       5: aload_0
       6: invokevirtual #41                 // Method java/lang/Object.getClass:()Ljava/lang/Class;
       9: astore        4
      11: aload_3
      12: aload         4
      14: invokevirtual #42                 // Method java/lang/Class.isAssignableFrom:(Ljava/lang/Class;)Z
      17: ifeq          43
      20: iconst_0
      21: anewarray     #43                 // class java/lang/Class
      24: astore        5
      26: aload_3
      27: aload_2
      28: invokevirtual #49                 // Method java/lang/Class.getField:(Ljava/lang/String;)Ljava/lang/reflect/Field;
      31: astore        6
      33: aload         6
      35: aload_0
      36: invokevirtual #50                 // Method java/lang/reflect/Field.get:(Ljava/lang/Object;)Ljava/lang/Object;
      39: checkcast     #47                 // class java/lang/Throwable
      42: areturn
      43: goto          47
      46: astore_3
      47: aconst_null
      48: areturn
    Exception table:
       from    to  target type
           0    42    46   Class java/lang/Exception
}
