Compiled from "QueryClauses.java"
public class io.manbang.ebatis.core.meta.QueryClauses {
  private io.manbang.ebatis.core.meta.QueryClauses();
    Code:
       0: aload_0
       1: invokespecial #1                  // Method java/lang/Object."<init>":()V
       4: new           #2                  // class java/lang/UnsupportedOperationException
       7: dup
       8: invokespecial #3                  // Method java/lang/UnsupportedOperationException."<init>":()V
      11: athrow

  public static java.lang.Class<? extends java.lang.annotation.Annotation> getQueryClauseClass(io.manbang.ebatis.core.meta.AnnotatedMeta<?>);
    Code:
       0: invokestatic  #4                  // Method io/manbang/ebatis/core/builder/QueryClauseType.values:()[Lio/manbang/ebatis/core/builder/QueryClauseType;
       3: astore_1
       4: aload_1
       5: arraylength
       6: istore_2
       7: iconst_0
       8: istore_3
       9: iload_3
      10: iload_2
      11: if_icmpge     46
      14: aload_1
      15: iload_3
      16: aaload
      17: astore        4
      19: aload         4
      21: invokevirtual #5                  // Method io/manbang/ebatis/core/builder/QueryClauseType.getQueryClauseClass:()Ljava/lang/Class;
      24: astore        5
      26: aload_0
      27: aload         5
      29: invokeinterface #6,  2            // InterfaceMethod io/manbang/ebatis/core/meta/AnnotatedMeta.isAnnotationPresent:(Ljava/lang/Class;)Z
      34: ifeq          40
      37: aload         5
      39: areturn
      40: iinc          3, 1
      43: goto          9
      46: ldc           #7                  // class io/manbang/ebatis/core/annotation/Must
      48: areturn

  public static java.util.Map<java.lang.Class<? extends java.lang.annotation.Annotation>, java.util.List<io.manbang.ebatis.core.meta.FieldMeta>> groupByQueryClause(java.lang.Class<?>);
    Code:
       0: aload_0
       1: invokevirtual #8                  // Method java/lang/Class.getFields:()[Ljava/lang/reflect/Field;
       4: invokestatic  #9                  // Method java/util/Arrays.stream:([Ljava/lang/Object;)Ljava/util/stream/Stream;
       7: invokedynamic #10,  0             // InvokeDynamic #0:test:()Ljava/util/function/Predicate;
      12: invokeinterface #11,  2           // InterfaceMethod java/util/stream/Stream.filter:(Ljava/util/function/Predicate;)Ljava/util/stream/Stream;
      17: invokedynamic #12,  0             // InvokeDynamic #1:apply:()Ljava/util/function/Function;
      22: invokeinterface #13,  2           // InterfaceMethod java/util/stream/Stream.map:(Ljava/util/function/Function;)Ljava/util/stream/Stream;
      27: invokedynamic #14,  0             // InvokeDynamic #2:apply:()Ljava/util/function/Function;
      32: invokestatic  #15                 // Method java/util/stream/Collectors.toList:()Ljava/util/stream/Collector;
      35: invokestatic  #16                 // Method java/util/stream/Collectors.groupingBy:(Ljava/util/function/Function;Ljava/util/stream/Collector;)Ljava/util/stream/Collector;
      38: invokeinterface #17,  2           // InterfaceMethod java/util/stream/Stream.collect:(Ljava/util/stream/Collector;)Ljava/lang/Object;
      43: checkcast     #18                 // class java/util/Map
      46: astore_1
      47: aload_1
      48: invokestatic  #19                 // Method java/util/Collections.unmodifiableMap:(Ljava/util/Map;)Ljava/util/Map;
      51: areturn

  public static boolean filterField(java.lang.reflect.Field);
    Code:
       0: aload_0
       1: invokevirtual #20                 // Method java/lang/reflect/Field.getModifiers:()I
       4: istore_1
       5: iload_1
       6: invokestatic  #21                 // Method java/lang/reflect/Modifier.isPrivate:(I)Z
       9: ifeq          39
      12: iload_1
      13: invokestatic  #22                 // Method java/lang/reflect/Modifier.isStatic:(I)Z
      16: ifne          39
      19: iload_1
      20: invokestatic  #23                 // Method java/lang/reflect/Modifier.isTransient:(I)Z
      23: ifne          39
      26: aload_0
      27: ldc           #24                 // class io/manbang/ebatis/core/annotation/Ignore
      29: invokevirtual #25                 // Method java/lang/reflect/Field.isAnnotationPresent:(Ljava/lang/Class;)Z
      32: ifne          39
      35: iconst_1
      36: goto          40
      39: iconst_0
      40: ireturn
}
