Compiled from "messages_sr.java"
public class org.postgresql.translation.messages_sr extends java.util.ResourceBundle {
  private static final java.util.Hashtable table;

  public org.postgresql.translation.messages_sr();
    Code:
       0: aload_0
       1: invokespecial #1                  // Method java/util/ResourceBundle."<init>":()V
       4: return

  public java.lang.Object handleGetObject(java.lang.String) throws java.util.MissingResourceException;
    Code:
       0: getstatic     #2                  // Field table:Ljava/util/Hashtable;
       3: aload_1
       4: invokevirtual #3                  // Method java/util/Hashtable.get:(Ljava/lang/Object;)Ljava/lang/Object;
       7: areturn

  public java.util.Enumeration getKeys();
    Code:
       0: getstatic     #2                  // Field table:Ljava/util/Hashtable;
       3: invokevirtual #4                  // Method java/util/Hashtable.keys:()Ljava/util/Enumeration;
       6: areturn

  public java.util.ResourceBundle getParent();
    Code:
       0: aload_0
       1: getfield      #5                  // Field java/util/ResourceBundle.parent:Ljava/util/ResourceBundle;
       4: areturn

  static {};
    Code:
       0: new           #6                  // class java/util/Hashtable
       3: dup
       4: invokespecial #7                  // Method java/util/Hashtable."<init>":()V
       7: astore_0
       8: aload_0
       9: ldc           #8                  // String
      11: ldc           #9                  // String Project-Id-Version: PostgreSQL 8.1\nReport-Msgid-Bugs-To: \nPOT-Creation-Date: 2015-11-25 15:14+0000\nPO-Revision-Date: 2009-05-26 11:13+0100\nLast-Translator: Bojan Škaljac <skaljac (at) gmail.com>\nLanguage-Team: Srpski <skaljac@gmail.com>\nLanguage: \nMIME-Version: 1.0\nContent-Type: text/plain; charset=UTF-8\nContent-Transfer-Encoding: 8bit\nX-Poedit-Language: Serbian\nX-Poedit-Country: YUGOSLAVIA\n
      13: invokevirtual #10                 // Method java/util/Hashtable.put:(Ljava/lang/Object;Ljava/lang/Object;)Ljava/lang/Object;
      16: pop
      17: aload_0
      18: ldc           #11                 // String Error loading default settings from driverconfig.properties
      20: ldc           #12                 // String Greška u čitanju standardnih podešavanja iz driverconfig.properties
      22: invokevirtual #10                 // Method java/util/Hashtable.put:(Ljava/lang/Object;Ljava/lang/Object;)Ljava/lang/Object;
      25: pop
      26: aload_0
      27: ldc           #13                 // String Your security policy has prevented the connection from being attempted.  You probably need to grant the connect java.net.SocketPermission to the database server host and port that you wish to connect to.
      29: ldc           #14                 // String Sigurnosna podešavanja su sprečila konekciju. Verovatno je potrebno da dozvolite konekciju klasi java.net.SocketPermission na bazu na serveru.
      31: invokevirtual #10                 // Method java/util/Hashtable.put:(Ljava/lang/Object;Ljava/lang/Object;)Ljava/lang/Object;
      34: pop
      35: aload_0
      36: ldc           #15                 // String Something unusual has occurred to cause the driver to fail. Please report this exception.
      38: ldc           #16                 // String Nešto neobično se dogodilo i drajver je zakazao. Molim prijavite ovaj izuzetak.
      40: invokevirtual #10                 // Method java/util/Hashtable.put:(Ljava/lang/Object;Ljava/lang/Object;)Ljava/lang/Object;
      43: pop
      44: aload_0
      45: ldc           #17                 // String Connection attempt timed out.
      47: ldc           #18                 // String Isteklo je vreme za pokušaj konektovanja.
      49: invokevirtual #10                 // Method java/util/Hashtable.put:(Ljava/lang/Object;Ljava/lang/Object;)Ljava/lang/Object;
      52: pop
      53: aload_0
      54: ldc           #19                 // String Interrupted while attempting to connect.
      56: ldc           #20                 // String Prekinut pokušaj konektovanja.
      58: invokevirtual #10                 // Method java/util/Hashtable.put:(Ljava/lang/Object;Ljava/lang/Object;)Ljava/lang/Object;
      61: pop
      62: aload_0
      63: ldc           #21                 // String Method {0} is not yet implemented.
      65: ldc           #22                 // String Metod {0} nije još impelemtiran.
      67: invokevirtual #10                 // Method java/util/Hashtable.put:(Ljava/lang/Object;Ljava/lang/Object;)Ljava/lang/Object;
      70: pop
      71: aload_0
      72: ldc           #23                 // String A connection could not be made using the requested protocol {0}.
      74: ldc           #24                 // String Konekciju nije moguće kreirati uz pomoć protokola {0}.
      76: invokevirtual #10                 // Method java/util/Hashtable.put:(Ljava/lang/Object;Ljava/lang/Object;)Ljava/lang/Object;
      79: pop
      80: aload_0
      81: ldc           #25                 // String Premature end of input stream, expected {0} bytes, but only read {1}.
      83: ldc           #26                 // String Prevremen završetak ulaznog toka podataka,očekivano {0} bajtova, a pročitano samo {1}.
      85: invokevirtual #10                 // Method java/util/Hashtable.put:(Ljava/lang/Object;Ljava/lang/Object;)Ljava/lang/Object;
      88: pop
      89: aload_0
      90: ldc           #27                 // String Expected an EOF from server, got: {0}
      92: ldc           #28                 // String Očekivan EOF od servera, a dobijeno: {0}
      94: invokevirtual #10                 // Method java/util/Hashtable.put:(Ljava/lang/Object;Ljava/lang/Object;)Ljava/lang/Object;
      97: pop
      98: aload_0
      99: ldc           #29                 // String Malformed function or procedure escape syntax at offset {0}.
     101: ldc           #30                 // String Pogrešna sintaksa u funkciji ili proceduri na poziciji {0}.
     103: invokevirtual #10                 // Method java/util/Hashtable.put:(Ljava/lang/Object;Ljava/lang/Object;)Ljava/lang/Object;
     106: pop
     107: aload_0
     108: ldc           #31                 // String An unexpected result was returned by a query.
     110: ldc           #32                 // String Nepredviđen rezultat je vraćen od strane upita.
     112: invokevirtual #10                 // Method java/util/Hashtable.put:(Ljava/lang/Object;Ljava/lang/Object;)Ljava/lang/Object;
     115: pop
     116: aload_0
     117: ldc           #33                 // String Illegal UTF-8 sequence: byte {0} of {1} byte sequence is not 10xxxxxx: {2}
     119: ldc           #34                 // String Ilegalna UTF-8 sekvenca: bajt {0} od {1} bajtova sekvence nije 10xxxxxx: {2}
     121: invokevirtual #10                 // Method java/util/Hashtable.put:(Ljava/lang/Object;Ljava/lang/Object;)Ljava/lang/Object;
     124: pop
     125: aload_0
     126: ldc           #35                 // String Illegal UTF-8 sequence: {0} bytes used to encode a {1} byte value: {2}
     128: ldc           #36                 // String Ilegalna UTF-8 sekvenca: {0} bytes used to encode a {1} byte value: {2}
     130: invokevirtual #10                 // Method java/util/Hashtable.put:(Ljava/lang/Object;Ljava/lang/Object;)Ljava/lang/Object;
     133: pop
     134: aload_0
     135: ldc           #37                 // String Illegal UTF-8 sequence: initial byte is {0}: {1}
     137: ldc           #38                 // String Ilegalna UTF-8 sekvenca: inicijalni bajt je {0}: {1}
     139: invokevirtual #10                 // Method java/util/Hashtable.put:(Ljava/lang/Object;Ljava/lang/Object;)Ljava/lang/Object;
     142: pop
     143: aload_0
     144: ldc           #39                 // String Illegal UTF-8 sequence: final value is out of range: {0}
     146: ldc           #40                 // String Ilegalna UTF-8 sekvenca: finalna vrednost je van opsega: {0}
     148: invokevirtual #10                 // Method java/util/Hashtable.put:(Ljava/lang/Object;Ljava/lang/Object;)Ljava/lang/Object;
     151: pop
     152: aload_0
     153: ldc           #41                 // String Illegal UTF-8 sequence: final value is a surrogate value: {0}
     155: ldc           #42                 // String Ilegalna UTF-8 sekvenca: finalna vrednost je zamena vrednosti: {0}
     157: invokevirtual #10                 // Method java/util/Hashtable.put:(Ljava/lang/Object;Ljava/lang/Object;)Ljava/lang/Object;
     160: pop
     161: aload_0
     162: ldc           #43                 // String Zero bytes may not occur in string parameters.
     164: ldc           #44                 // String Nula bajtovji se ne smeju pojavljivati u string parametrima.
     166: invokevirtual #10                 // Method java/util/Hashtable.put:(Ljava/lang/Object;Ljava/lang/Object;)Ljava/lang/Object;
     169: pop
     170: aload_0
     171: ldc           #45                 // String Zero bytes may not occur in identifiers.
     173: ldc           #46                 // String Nula bajtovji se ne smeju pojavljivati u identifikatorima.
     175: invokevirtual #10                 // Method java/util/Hashtable.put:(Ljava/lang/Object;Ljava/lang/Object;)Ljava/lang/Object;
     178: pop
     179: aload_0
     180: ldc           #47                 // String Connection refused. Check that the hostname and port are correct and that the postmaster is accepting TCP/IP connections.
     182: ldc           #48                 // String Konekcija odbijena. Proverite dali je ime domćina (host) koretno i da postmaster podržava TCP/IP konekcije.
     184: invokevirtual #10                 // Method java/util/Hashtable.put:(Ljava/lang/Object;Ljava/lang/Object;)Ljava/lang/Object;
     187: pop
     188: aload_0
     189: ldc           #49                 // String The connection attempt failed.
     191: ldc           #50                 // String Pokušaj konektovanja propao.
     193: invokevirtual #10                 // Method java/util/Hashtable.put:(Ljava/lang/Object;Ljava/lang/Object;)Ljava/lang/Object;
     196: pop
     197: aload_0
     198: ldc           #51                 // String The server does not support SSL.
     200: ldc           #52                 // String Server ne podržava SSL.
     202: invokevirtual #10                 // Method java/util/Hashtable.put:(Ljava/lang/Object;Ljava/lang/Object;)Ljava/lang/Object;
     205: pop
     206: aload_0
     207: ldc           #53                 // String An error occurred while setting up the SSL connection.
     209: ldc           #54                 // String Greška se dogodila prilikom podešavanja SSL konekcije.
     211: invokevirtual #10                 // Method java/util/Hashtable.put:(Ljava/lang/Object;Ljava/lang/Object;)Ljava/lang/Object;
     214: pop
     215: aload_0
     216: ldc           #55                 // String Connection rejected: {0}.
     218: ldc           #56                 // String Konekcija odbačena: {0}.
     220: invokevirtual #10                 // Method java/util/Hashtable.put:(Ljava/lang/Object;Ljava/lang/Object;)Ljava/lang/Object;
     223: pop
     224: aload_0
     225: ldc           #57                 // String The server requested password-based authentication, but no password was provided.
     227: ldc           #58                 // String Server zahteva autentifikaciju baziranu na šifri, ali šifra nije prosleđena.
     229: invokevirtual #10                 // Method java/util/Hashtable.put:(Ljava/lang/Object;Ljava/lang/Object;)Ljava/lang/Object;
     232: pop
     233: aload_0
     234: ldc           #59                 // String The authentication type {0} is not supported. Check that you have configured the pg_hba.conf file to include the client\'\'s IP address or subnet, and that it is using an authentication scheme supported by the driver.
     236: ldc           #60                 // String Tip autentifikacije {0} nije podržan. Proverite dali imate podešen pg_hba.conf fajl koji uključuje klijentovu IP adresu ili podmrežu, i da ta mreža koristi šemu autentifikacije koja je podržana od strane ovog drajvera.
     238: invokevirtual #10                 // Method java/util/Hashtable.put:(Ljava/lang/Object;Ljava/lang/Object;)Ljava/lang/Object;
     241: pop
     242: aload_0
     243: ldc           #61                 // String Protocol error.  Session setup failed.
     245: ldc           #62                 // String Greška protokola.  Zakazivanje sesije propalo.
     247: invokevirtual #10                 // Method java/util/Hashtable.put:(Ljava/lang/Object;Ljava/lang/Object;)Ljava/lang/Object;
     250: pop
     251: aload_0
     252: ldc           #63                 // String Backend start-up failed: {0}.
     254: ldc           #64                 // String Pozadinsko startovanje propalo: {0}.
     256: invokevirtual #10                 // Method java/util/Hashtable.put:(Ljava/lang/Object;Ljava/lang/Object;)Ljava/lang/Object;
     259: pop
     260: aload_0
     261: ldc           #65                 // String The column index is out of range: {0}, number of columns: {1}.
     263: ldc           #66                 // String Indeks kolone van osega: {0}, broj kolona: {1}.
     265: invokevirtual #10                 // Method java/util/Hashtable.put:(Ljava/lang/Object;Ljava/lang/Object;)Ljava/lang/Object;
     268: pop
     269: aload_0
     270: ldc           #67                 // String No value specified for parameter {0}.
     272: ldc           #68                 // String Nije zadata vrednost za parametar {0}.
     274: invokevirtual #10                 // Method java/util/Hashtable.put:(Ljava/lang/Object;Ljava/lang/Object;)Ljava/lang/Object;
     277: pop
     278: aload_0
     279: ldc           #69                 // String Expected command status BEGIN, got {0}.
     281: ldc           #70                 // String Očekivan status komande je BEGIN, a dobijeno je {0}.
     283: invokevirtual #10                 // Method java/util/Hashtable.put:(Ljava/lang/Object;Ljava/lang/Object;)Ljava/lang/Object;
     286: pop
     287: aload_0
     288: ldc           #71                 // String Unexpected command status: {0}.
     290: ldc           #72                 // String Neočekivan komandni status: {0}.
     292: invokevirtual #10                 // Method java/util/Hashtable.put:(Ljava/lang/Object;Ljava/lang/Object;)Ljava/lang/Object;
     295: pop
     296: aload_0
     297: ldc           #73                 // String Unknown Response Type {0}.
     299: ldc           #74                 // String Nepoznat tip odziva {0}.
     301: invokevirtual #10                 // Method java/util/Hashtable.put:(Ljava/lang/Object;Ljava/lang/Object;)Ljava/lang/Object;
     304: pop
     305: aload_0
     306: ldc           #75                 // String Ran out of memory retrieving query results.
     308: ldc           #76                 // String Nestalo je memorije prilikom preuzimanja rezultata upita.
     310: invokevirtual #10                 // Method java/util/Hashtable.put:(Ljava/lang/Object;Ljava/lang/Object;)Ljava/lang/Object;
     313: pop
     314: aload_0
     315: ldc           #77                 // String Unable to interpret the update count in command completion tag: {0}.
     317: ldc           #78                 // String Neuspešno prekidanje prebrojavanja ažurivanja u tagu zakompletiranje komandi: {0}.
     319: invokevirtual #10                 // Method java/util/Hashtable.put:(Ljava/lang/Object;Ljava/lang/Object;)Ljava/lang/Object;
     322: pop
     323: aload_0
     324: ldc           #79                 // String Unable to bind parameter values for statement.
     326: ldc           #80                 // String Nije moguće naći vrednost vezivnog parametra za izjavu (statement).
     328: invokevirtual #10                 // Method java/util/Hashtable.put:(Ljava/lang/Object;Ljava/lang/Object;)Ljava/lang/Object;
     331: pop
     332: aload_0
     333: ldc           #81                 // String The server\'\'s DateStyle parameter was changed to {0}. The JDBC driver requires DateStyle to begin with ISO for correct operation.
     335: ldc           #82                 // String Serverov DataStyle parametar promenjen u {0}. JDBC zahteva da DateStyle počinje sa ISO za uspešno završavanje operacije.
     337: invokevirtual #10                 // Method java/util/Hashtable.put:(Ljava/lang/Object;Ljava/lang/Object;)Ljava/lang/Object;
     340: pop
     341: aload_0
     342: ldc           #83                 // String The server\'\'s standard_conforming_strings parameter was reported as {0}. The JDBC driver expected on or off.
     344: ldc           #84                 // String Serverov standard_conforming_strings parametar javlja {0}. JDBC drajver ocekuje on ili off.
     346: invokevirtual #10                 // Method java/util/Hashtable.put:(Ljava/lang/Object;Ljava/lang/Object;)Ljava/lang/Object;
     349: pop
     350: aload_0
     351: ldc           #85                 // String Bind message length {0} too long.  This can be caused by very large or incorrect length specifications on InputStream parameters.
     353: ldc           #86                 // String Dužina vezivne poruke {0} prevelika.  Ovo je možda rezultat veoma velike ili pogrešne dužine specifikacije za InputStream parametre.
     355: invokevirtual #10                 // Method java/util/Hashtable.put:(Ljava/lang/Object;Ljava/lang/Object;)Ljava/lang/Object;
     358: pop
     359: aload_0
     360: ldc           #87                 // String The driver currently does not support COPY operations.
     362: ldc           #88                 // String Drajver trenutno ne podržava COPY operacije.
     364: invokevirtual #10                 // Method java/util/Hashtable.put:(Ljava/lang/Object;Ljava/lang/Object;)Ljava/lang/Object;
     367: pop
     368: aload_0
     369: ldc           #89                 // String This PooledConnection has already been closed.
     371: ldc           #90                 // String PooledConnection je već zatvoren.
     373: invokevirtual #10                 // Method java/util/Hashtable.put:(Ljava/lang/Object;Ljava/lang/Object;)Ljava/lang/Object;
     376: pop
     377: aload_0
     378: ldc           #91                 // String Connection has been closed automatically because a new connection was opened for the same PooledConnection or the PooledConnection has been closed.
     380: ldc           #92                 // String Konekcija je zatvorena automatski zato što je nova konekcija otvorena za isti PooledConnection ili je PooledConnection zatvoren.
     382: invokevirtual #10                 // Method java/util/Hashtable.put:(Ljava/lang/Object;Ljava/lang/Object;)Ljava/lang/Object;
     385: pop
     386: aload_0
     387: ldc           #93                 // String Connection has been closed.
     389: ldc           #94                 // String Konekcija je već zatvorena.
     391: invokevirtual #10                 // Method java/util/Hashtable.put:(Ljava/lang/Object;Ljava/lang/Object;)Ljava/lang/Object;
     394: pop
     395: aload_0
     396: ldc           #95                 // String Statement has been closed.
     398: ldc           #96                 // String Statemen je već zatvoren.
     400: invokevirtual #10                 // Method java/util/Hashtable.put:(Ljava/lang/Object;Ljava/lang/Object;)Ljava/lang/Object;
     403: pop
     404: aload_0
     405: ldc           #97                 // String DataSource has been closed.
     407: ldc           #98                 // String DataSource je zatvoren.
     409: invokevirtual #10                 // Method java/util/Hashtable.put:(Ljava/lang/Object;Ljava/lang/Object;)Ljava/lang/Object;
     412: pop
     413: aload_0
     414: ldc           #99                 // String Fastpath call {0} - No result was returned and we expected an integer.
     416: ldc           #100                // String Fastpath poziv {0} - Nikakav rezultat nije vraćen a očekivan je integer.
     418: invokevirtual #10                 // Method java/util/Hashtable.put:(Ljava/lang/Object;Ljava/lang/Object;)Ljava/lang/Object;
     421: pop
     422: aload_0
     423: ldc           #101                // String The fastpath function {0} is unknown.
     425: ldc           #102                // String Fastpath funkcija {0} je nepoznata.
     427: invokevirtual #10                 // Method java/util/Hashtable.put:(Ljava/lang/Object;Ljava/lang/Object;)Ljava/lang/Object;
     430: pop
     431: aload_0
     432: ldc           #103                // String Conversion to type {0} failed: {1}.
     434: ldc           #104                // String Konverzija u tip {0} propala: {1}.
     436: invokevirtual #10                 // Method java/util/Hashtable.put:(Ljava/lang/Object;Ljava/lang/Object;)Ljava/lang/Object;
     439: pop
     440: aload_0
     441: ldc           #105                // String Cannot tell if path is open or closed: {0}.
     443: ldc           #106                // String Nije moguće utvrditi dali je putanja otvorena ili zatvorena: {0}.
     445: invokevirtual #10                 // Method java/util/Hashtable.put:(Ljava/lang/Object;Ljava/lang/Object;)Ljava/lang/Object;
     448: pop
     449: aload_0
     450: ldc           #107                // String The array index is out of range: {0}
     452: ldc           #108                // String Indeks niza je van opsega: {0}
     454: invokevirtual #10                 // Method java/util/Hashtable.put:(Ljava/lang/Object;Ljava/lang/Object;)Ljava/lang/Object;
     457: pop
     458: aload_0
     459: ldc           #109                // String The array index is out of range: {0}, number of elements: {1}.
     461: ldc           #110                // String Indeks niza je van opsega: {0}, broj elemenata: {1}.
     463: invokevirtual #10                 // Method java/util/Hashtable.put:(Ljava/lang/Object;Ljava/lang/Object;)Ljava/lang/Object;
     466: pop
     467: aload_0
     468: ldc           #111                // String Invalid character data was found.  This is most likely caused by stored data containing characters that are invalid for the character set the database was created in.  The most common example of this is storing 8bit data in a SQL_ASCII database.
     470: ldc           #112                // String Pronađeni su nevažeći karakter podaci. Uzrok je najverovatnije to što pohranjeni podaci sadrže karaktere koji su nevažeći u setu karaktera sa kojima je baza kreirana.  Npr. Čuvanje 8bit podataka u SQL_ASCII bazi podataka.
     472: invokevirtual #10                 // Method java/util/Hashtable.put:(Ljava/lang/Object;Ljava/lang/Object;)Ljava/lang/Object;
     475: pop
     476: aload_0
     477: ldc           #113                // String Truncation of large objects is only implemented in 8.3 and later servers.
     479: ldc           #114                // String Skraćivanje velikih objekata je implementirano samo u 8.3 i novijim serverima.
     481: invokevirtual #10                 // Method java/util/Hashtable.put:(Ljava/lang/Object;Ljava/lang/Object;)Ljava/lang/Object;
     484: pop
     485: aload_0
     486: ldc           #115                // String PostgreSQL LOBs can only index to: {0}
     488: ldc           #116                // String PostgreSQL LOB mogu jedino da označavaju: {0}
     490: invokevirtual #10                 // Method java/util/Hashtable.put:(Ljava/lang/Object;Ljava/lang/Object;)Ljava/lang/Object;
     493: pop
     494: aload_0
     495: ldc           #117                // String LOB positioning offsets start at 1.
     497: ldc           #118                // String LOB pozicija ofset počinje kod 1.
     499: invokevirtual #10                 // Method java/util/Hashtable.put:(Ljava/lang/Object;Ljava/lang/Object;)Ljava/lang/Object;
     502: pop
     503: aload_0
     504: ldc           #119                // String free() was called on this LOB previously
     506: ldc           #120                // String free() je pozvan na ovom LOB-u prethodno
     508: invokevirtual #10                 // Method java/util/Hashtable.put:(Ljava/lang/Object;Ljava/lang/Object;)Ljava/lang/Object;
     511: pop
     512: aload_0
     513: ldc           #121                // String Unsupported value for stringtype parameter: {0}
     515: ldc           #122                // String Vrednost za parametar tipa string nije podržana: {0}
     517: invokevirtual #10                 // Method java/util/Hashtable.put:(Ljava/lang/Object;Ljava/lang/Object;)Ljava/lang/Object;
     520: pop
     521: aload_0
     522: ldc           #123                // String No results were returned by the query.
     524: ldc           #124                // String Nikakav rezultat nije vraćen od strane upita.
     526: invokevirtual #10                 // Method java/util/Hashtable.put:(Ljava/lang/Object;Ljava/lang/Object;)Ljava/lang/Object;
     529: pop
     530: aload_0
     531: ldc           #125                // String A result was returned when none was expected.
     533: ldc           #126                // String Rezultat vraćen ali nikakav rezultat nije očekivan.
     535: invokevirtual #10                 // Method java/util/Hashtable.put:(Ljava/lang/Object;Ljava/lang/Object;)Ljava/lang/Object;
     538: pop
     539: aload_0
     540: ldc           #127                // String Custom type maps are not supported.
     542: ldc           #128                // String Mape sa korisnički definisanim tipovima nisu podržane.
     544: invokevirtual #10                 // Method java/util/Hashtable.put:(Ljava/lang/Object;Ljava/lang/Object;)Ljava/lang/Object;
     547: pop
     548: aload_0
     549: ldc           #129                // String Failed to create object for: {0}.
     551: ldc           #130                // String Propao pokušaj kreiranja objekta za: {0}.
     553: invokevirtual #10                 // Method java/util/Hashtable.put:(Ljava/lang/Object;Ljava/lang/Object;)Ljava/lang/Object;
     556: pop
     557: aload_0
     558: ldc           #131                // String Unable to load the class {0} responsible for the datatype {1}
     560: ldc           #132                // String Nije moguće učitati kalsu {0} odgovornu za tip podataka {1}
     562: invokevirtual #10                 // Method java/util/Hashtable.put:(Ljava/lang/Object;Ljava/lang/Object;)Ljava/lang/Object;
     565: pop
     566: aload_0
     567: ldc           #133                // String Cannot change transaction read-only property in the middle of a transaction.
     569: ldc           #134                // String Nije moguće izmeniti read-only osobinu transakcije u sred izvršavanja transakcije.
     571: invokevirtual #10                 // Method java/util/Hashtable.put:(Ljava/lang/Object;Ljava/lang/Object;)Ljava/lang/Object;
     574: pop
     575: aload_0
     576: ldc           #135                // String Cannot change transaction isolation level in the middle of a transaction.
     578: ldc           #136                // String Nije moguće izmeniti nivo izolacije transakcije u sred izvršavanja transakcije.
     580: invokevirtual #10                 // Method java/util/Hashtable.put:(Ljava/lang/Object;Ljava/lang/Object;)Ljava/lang/Object;
     583: pop
     584: aload_0
     585: ldc           #137                // String Transaction isolation level {0} not supported.
     587: ldc           #138                // String Nivo izolacije transakcije {0} nije podržan.
     589: invokevirtual #10                 // Method java/util/Hashtable.put:(Ljava/lang/Object;Ljava/lang/Object;)Ljava/lang/Object;
     592: pop
     593: aload_0
     594: ldc           #139                // String Finalizing a Connection that was never closed:
     596: ldc           #140                // String Dovršavanje konekcije koja nikada nije zatvorena:
     598: invokevirtual #10                 // Method java/util/Hashtable.put:(Ljava/lang/Object;Ljava/lang/Object;)Ljava/lang/Object;
     601: pop
     602: aload_0
     603: ldc           #141                // String Unable to translate data into the desired encoding.
     605: ldc           #142                // String Nije moguće prevesti podatke u odabrani encoding format.
     607: invokevirtual #10                 // Method java/util/Hashtable.put:(Ljava/lang/Object;Ljava/lang/Object;)Ljava/lang/Object;
     610: pop
     611: aload_0
     612: ldc           #143                // String Fetch size must be a value greater to or equal to 0.
     614: ldc           #144                // String Doneta veličina mora biti vrednost veća ili jednaka 0.
     616: invokevirtual #10                 // Method java/util/Hashtable.put:(Ljava/lang/Object;Ljava/lang/Object;)Ljava/lang/Object;
     619: pop
     620: aload_0
     621: ldc           #145                // String Unable to determine a value for MaxIndexKeys due to missing system catalog data.
     623: ldc           #146                // String Nije moguće odrediti vrednost za MaxIndexKezs zbog nedostatka podataka u sistemskom katalogu.
     625: invokevirtual #10                 // Method java/util/Hashtable.put:(Ljava/lang/Object;Ljava/lang/Object;)Ljava/lang/Object;
     628: pop
     629: aload_0
     630: ldc           #147                // String Unable to find name datatype in the system catalogs.
     632: ldc           #148                // String Nije moguće pronaći ime tipa podatka u sistemskom katalogu.
     634: invokevirtual #10                 // Method java/util/Hashtable.put:(Ljava/lang/Object;Ljava/lang/Object;)Ljava/lang/Object;
     637: pop
     638: aload_0
     639: ldc           #149                // String Operation requires a scrollable ResultSet, but this ResultSet is FORWARD_ONLY.
     641: ldc           #150                // String Operacija zahteva skrolabilan ResultSet,ali ovaj ResultSet je FORWARD_ONLY.
     643: invokevirtual #10                 // Method java/util/Hashtable.put:(Ljava/lang/Object;Ljava/lang/Object;)Ljava/lang/Object;
     646: pop
     647: aload_0
     648: ldc           #151                // String Unexpected error while decoding character data from a large object.
     650: ldc           #152                // String Neočekivana greška prilikom dekodiranja karaktera iz velikog objekta.
     652: invokevirtual #10                 // Method java/util/Hashtable.put:(Ljava/lang/Object;Ljava/lang/Object;)Ljava/lang/Object;
     655: pop
     656: aload_0
     657: ldc           #153                // String Can\'\'t use relative move methods while on the insert row.
     659: ldc           #154                // String Ne može se koristiti metod relativnog pomeranja prilikom ubacivanja redova.
     661: invokevirtual #10                 // Method java/util/Hashtable.put:(Ljava/lang/Object;Ljava/lang/Object;)Ljava/lang/Object;
     664: pop
     665: aload_0
     666: ldc           #155                // String Invalid fetch direction constant: {0}.
     668: ldc           #156                // String Pogrešna konstanta za direkciju donošenja: {0}.
     670: invokevirtual #10                 // Method java/util/Hashtable.put:(Ljava/lang/Object;Ljava/lang/Object;)Ljava/lang/Object;
     673: pop
     674: aload_0
     675: ldc           #157                // String Cannot call cancelRowUpdates() when on the insert row.
     677: ldc           #158                // String Nije moguće pozvati cancelRowUpdates() prilikom ubacivanja redova.
     679: invokevirtual #10                 // Method java/util/Hashtable.put:(Ljava/lang/Object;Ljava/lang/Object;)Ljava/lang/Object;
     682: pop
     683: aload_0
     684: ldc           #159                // String Cannot call deleteRow() when on the insert row.
     686: ldc           #160                // String Nije moguće pozvati deleteRow() prilikom ubacivanja redova.
     688: invokevirtual #10                 // Method java/util/Hashtable.put:(Ljava/lang/Object;Ljava/lang/Object;)Ljava/lang/Object;
     691: pop
     692: aload_0
     693: ldc           #161                // String Currently positioned before the start of the ResultSet.  You cannot call deleteRow() here.
     695: ldc           #162                // String Trenutna pozicija pre početka ResultSet-a.  Ne možete pozvati deleteRow() na toj poziciji.
     697: invokevirtual #10                 // Method java/util/Hashtable.put:(Ljava/lang/Object;Ljava/lang/Object;)Ljava/lang/Object;
     700: pop
     701: aload_0
     702: ldc           #163                // String Currently positioned after the end of the ResultSet.  You cannot call deleteRow() here.
     704: ldc           #164                // String Trenutna pozicija posle kraja ResultSet-a.  Ne možete pozvati deleteRow() na toj poziciji.
     706: invokevirtual #10                 // Method java/util/Hashtable.put:(Ljava/lang/Object;Ljava/lang/Object;)Ljava/lang/Object;
     709: pop
     710: aload_0
     711: ldc           #165                // String There are no rows in this ResultSet.
     713: ldc           #166                // String U ResultSet-u nema redova.
     715: invokevirtual #10                 // Method java/util/Hashtable.put:(Ljava/lang/Object;Ljava/lang/Object;)Ljava/lang/Object;
     718: pop
     719: aload_0
     720: ldc           #167                // String Not on the insert row.
     722: ldc           #168                // String Nije mod ubacivanja redova.
     724: invokevirtual #10                 // Method java/util/Hashtable.put:(Ljava/lang/Object;Ljava/lang/Object;)Ljava/lang/Object;
     727: pop
     728: aload_0
     729: ldc           #169                // String You must specify at least one column value to insert a row.
     731: ldc           #170                // String Morate specificirati barem jednu vrednost za kolonu da bi ste ubacili red.
     733: invokevirtual #10                 // Method java/util/Hashtable.put:(Ljava/lang/Object;Ljava/lang/Object;)Ljava/lang/Object;
     736: pop
     737: aload_0
     738: ldc           #171                // String The JVM claims not to support the encoding: {0}
     740: ldc           #172                // String JVM tvrdi da ne podržava encoding: {0}
     742: invokevirtual #10                 // Method java/util/Hashtable.put:(Ljava/lang/Object;Ljava/lang/Object;)Ljava/lang/Object;
     745: pop
     746: aload_0
     747: ldc           #173                // String Provided InputStream failed.
     749: ldc           #174                // String Pribaljeni InputStream zakazao.
     751: invokevirtual #10                 // Method java/util/Hashtable.put:(Ljava/lang/Object;Ljava/lang/Object;)Ljava/lang/Object;
     754: pop
     755: aload_0
     756: ldc           #175                // String Provided Reader failed.
     758: ldc           #176                // String Pribavljeni čitač (Reader) zakazao.
     760: invokevirtual #10                 // Method java/util/Hashtable.put:(Ljava/lang/Object;Ljava/lang/Object;)Ljava/lang/Object;
     763: pop
     764: aload_0
     765: ldc           #177                // String Can\'\'t refresh the insert row.
     767: ldc           #178                // String Nije moguće osvežiti ubačeni red.
     769: invokevirtual #10                 // Method java/util/Hashtable.put:(Ljava/lang/Object;Ljava/lang/Object;)Ljava/lang/Object;
     772: pop
     773: aload_0
     774: ldc           #179                // String Cannot call updateRow() when on the insert row.
     776: ldc           #180                // String Nije moguće pozvati updateRow() prilikom ubacivanja redova.
     778: invokevirtual #10                 // Method java/util/Hashtable.put:(Ljava/lang/Object;Ljava/lang/Object;)Ljava/lang/Object;
     781: pop
     782: aload_0
     783: ldc           #181                // String Cannot update the ResultSet because it is either before the start or after the end of the results.
     785: ldc           #182                // String Nije moguće ažurirati ResultSet zato što je ili početak ili kraj rezultata.
     787: invokevirtual #10                 // Method java/util/Hashtable.put:(Ljava/lang/Object;Ljava/lang/Object;)Ljava/lang/Object;
     790: pop
     791: aload_0
     792: ldc           #183                // String ResultSets with concurrency CONCUR_READ_ONLY cannot be updated.
     794: ldc           #184                // String ResultSets sa osobinom CONCUR_READ_ONLY ne moeže biti ažuriran.
     796: invokevirtual #10                 // Method java/util/Hashtable.put:(Ljava/lang/Object;Ljava/lang/Object;)Ljava/lang/Object;
     799: pop
     800: aload_0
     801: ldc           #185                // String No primary key found for table {0}.
     803: ldc           #186                // String Nije pronađen ključ za tabelu {0}.
     805: invokevirtual #10                 // Method java/util/Hashtable.put:(Ljava/lang/Object;Ljava/lang/Object;)Ljava/lang/Object;
     808: pop
     809: aload_0
     810: ldc           #187                // String Bad value for type {0} : {1}
     812: ldc           #188                // String Pogrešna vrednost za tip {0} : {1}
     814: invokevirtual #10                 // Method java/util/Hashtable.put:(Ljava/lang/Object;Ljava/lang/Object;)Ljava/lang/Object;
     817: pop
     818: aload_0
     819: ldc           #189                // String The column name {0} was not found in this ResultSet.
     821: ldc           #190                // String Ime kolone {0} nije pronadjeno u ResultSet.
     823: invokevirtual #10                 // Method java/util/Hashtable.put:(Ljava/lang/Object;Ljava/lang/Object;)Ljava/lang/Object;
     826: pop
     827: aload_0
     828: ldc           #191                // String ResultSet is not updateable.  The query that generated this result set must select only one table, and must select all primary keys from that table. See the JDBC 2.1 API Specification, section 5.6 for more details.
     830: ldc           #192                // String ResultSet nije moguće ažurirati. Upit koji je generisao ovaj razultat mora selektoati jedino tabelu,i mora selektovati sve primrne ključeve iz te tabele. Pogledajte API specifikaciju za JDBC 2.1, sekciju 5.6 za više detalja.
     832: invokevirtual #10                 // Method java/util/Hashtable.put:(Ljava/lang/Object;Ljava/lang/Object;)Ljava/lang/Object;
     835: pop
     836: aload_0
     837: ldc           #193                // String This ResultSet is closed.
     839: ldc           #194                // String ResultSet je zatvoren.
     841: invokevirtual #10                 // Method java/util/Hashtable.put:(Ljava/lang/Object;Ljava/lang/Object;)Ljava/lang/Object;
     844: pop
     845: aload_0
     846: ldc           #195                // String ResultSet not positioned properly, perhaps you need to call next.
     848: ldc           #196                // String ResultSet nije pravilno pozicioniran, možda je potrebno da pozovete next.
     850: invokevirtual #10                 // Method java/util/Hashtable.put:(Ljava/lang/Object;Ljava/lang/Object;)Ljava/lang/Object;
     853: pop
     854: aload_0
     855: ldc           #197                // String Can\'\'t use query methods that take a query string on a PreparedStatement.
     857: ldc           #198                // String Ne možete da koristite metode za upit koji uzimaju string iz upita u PreparedStatement-u.
     859: invokevirtual #10                 // Method java/util/Hashtable.put:(Ljava/lang/Object;Ljava/lang/Object;)Ljava/lang/Object;
     862: pop
     863: aload_0
     864: ldc           #199                // String Multiple ResultSets were returned by the query.
     866: ldc           #200                // String Višestruki ResultSet-vi su vraćeni od strane upita.
     868: invokevirtual #10                 // Method java/util/Hashtable.put:(Ljava/lang/Object;Ljava/lang/Object;)Ljava/lang/Object;
     871: pop
     872: aload_0
     873: ldc           #201                // String A CallableStatement was executed with nothing returned.
     875: ldc           #202                // String CallableStatement je izvršen ali ništa nije vrećeno kao rezultat.
     877: invokevirtual #10                 // Method java/util/Hashtable.put:(Ljava/lang/Object;Ljava/lang/Object;)Ljava/lang/Object;
     880: pop
     881: aload_0
     882: ldc           #203                // String A CallableStatement was executed with an invalid number of parameters
     884: ldc           #204                // String CallableStatement je izvršen sa nevažećim brojem parametara
     886: invokevirtual #10                 // Method java/util/Hashtable.put:(Ljava/lang/Object;Ljava/lang/Object;)Ljava/lang/Object;
     889: pop
     890: aload_0
     891: ldc           #205                // String A CallableStatement function was executed and the out parameter {0} was of type {1} however type {2} was registered.
     893: ldc           #206                // String CallableStatement funkcija je izvršena dok je izlazni parametar {0} tipa {1} a tip {2} je registrovan kao izlazni parametar.
     895: invokevirtual #10                 // Method java/util/Hashtable.put:(Ljava/lang/Object;Ljava/lang/Object;)Ljava/lang/Object;
     898: pop
     899: aload_0
     900: ldc           #207                // String Maximum number of rows must be a value grater than or equal to 0.
     902: ldc           #208                // String Maksimalni broj redova mora biti vrednosti veće ili jednake 0.
     904: invokevirtual #10                 // Method java/util/Hashtable.put:(Ljava/lang/Object;Ljava/lang/Object;)Ljava/lang/Object;
     907: pop
     908: aload_0
     909: ldc           #209                // String Query timeout must be a value greater than or equals to 0.
     911: ldc           #210                // String Tajm-aut mora biti vrednost veća ili jednaka 0.
     913: invokevirtual #10                 // Method java/util/Hashtable.put:(Ljava/lang/Object;Ljava/lang/Object;)Ljava/lang/Object;
     916: pop
     917: aload_0
     918: ldc           #211                // String The maximum field size must be a value greater than or equal to 0.
     920: ldc           #212                // String Maksimalna vrednost veličine polja mora biti vrednost veća ili jednaka 0.
     922: invokevirtual #10                 // Method java/util/Hashtable.put:(Ljava/lang/Object;Ljava/lang/Object;)Ljava/lang/Object;
     925: pop
     926: aload_0
     927: ldc           #213                // String Unknown Types value.
     929: ldc           #214                // String Nepoznata vrednost za Types.
     931: invokevirtual #10                 // Method java/util/Hashtable.put:(Ljava/lang/Object;Ljava/lang/Object;)Ljava/lang/Object;
     934: pop
     935: aload_0
     936: ldc           #215                // String Invalid stream length {0}.
     938: ldc           #216                // String Nevažeća dužina toka {0}.
     940: invokevirtual #10                 // Method java/util/Hashtable.put:(Ljava/lang/Object;Ljava/lang/Object;)Ljava/lang/Object;
     943: pop
     944: aload_0
     945: ldc           #217                // String The JVM claims not to support the {0} encoding.
     947: ldc           #218                // String JVM tvrdi da ne podržava {0} encoding.
     949: invokevirtual #10                 // Method java/util/Hashtable.put:(Ljava/lang/Object;Ljava/lang/Object;)Ljava/lang/Object;
     952: pop
     953: aload_0
     954: ldc           #219                // String Unknown type {0}.
     956: ldc           #220                // String Nepoznat tip {0}.
     958: invokevirtual #10                 // Method java/util/Hashtable.put:(Ljava/lang/Object;Ljava/lang/Object;)Ljava/lang/Object;
     961: pop
     962: aload_0
     963: ldc           #221                // String Cannot cast an instance of {0} to type {1}
     965: ldc           #222                // String Nije moguće kastovati instancu {0} u tip {1}
     967: invokevirtual #10                 // Method java/util/Hashtable.put:(Ljava/lang/Object;Ljava/lang/Object;)Ljava/lang/Object;
     970: pop
     971: aload_0
     972: ldc           #223                // String Unsupported Types value: {0}
     974: ldc           #224                // String Za tip nije podržana vrednost: {0}
     976: invokevirtual #10                 // Method java/util/Hashtable.put:(Ljava/lang/Object;Ljava/lang/Object;)Ljava/lang/Object;
     979: pop
     980: aload_0
     981: ldc           #225                // String Cannot convert an instance of {0} to type {1}
     983: ldc           #226                // String Nije moguće konvertovati instancu {0} u tip {1}
     985: invokevirtual #10                 // Method java/util/Hashtable.put:(Ljava/lang/Object;Ljava/lang/Object;)Ljava/lang/Object;
     988: pop
     989: aload_0
     990: ldc           #227                // String Can\'\'t infer the SQL type to use for an instance of {0}. Use setObject() with an explicit Types value to specify the type to use.
     992: ldc           #228                // String Nije moguće zaključiti SQL tip koji bi se koristio sa instancom {0}. Koristite setObject() sa zadatim eksplicitnim tipom vrednosti.
     994: invokevirtual #10                 // Method java/util/Hashtable.put:(Ljava/lang/Object;Ljava/lang/Object;)Ljava/lang/Object;
     997: pop
     998: aload_0
     999: ldc           #229                // String This statement does not declare an OUT parameter.  Use \'{\' ?= call ... \'}\' to declare one.
    1001: ldc           #230                // String Izraz ne deklariše izlazni parametar. Koristite \'{\' ?= poziv ... \'}\' za deklarisanje.
    1003: invokevirtual #10                 // Method java/util/Hashtable.put:(Ljava/lang/Object;Ljava/lang/Object;)Ljava/lang/Object;
    1006: pop
    1007: aload_0
    1008: ldc           #231                // String wasNull cannot be call before fetching a result.
    1010: ldc           #232                // String wasNull nemože biti pozvan pre zahvatanja rezultata.
    1012: invokevirtual #10                 // Method java/util/Hashtable.put:(Ljava/lang/Object;Ljava/lang/Object;)Ljava/lang/Object;
    1015: pop
    1016: aload_0
    1017: ldc           #233                // String Parameter of type {0} was registered, but call to get{1} (sqltype={2}) was made.
    1019: ldc           #234                // String Parametar tipa {0} je registrovan,ali poziv za get{1} (sql tip={2}) je izvršen.
    1021: invokevirtual #10                 // Method java/util/Hashtable.put:(Ljava/lang/Object;Ljava/lang/Object;)Ljava/lang/Object;
    1024: pop
    1025: aload_0
    1026: ldc           #235                // String A CallableStatement was declared, but no call to registerOutParameter(1, <some type>) was made.
    1028: ldc           #236                // String CallableStatement jedeklarisan ali nije bilo poziva registerOutParameter (1, <neki_tip>).
    1030: invokevirtual #10                 // Method java/util/Hashtable.put:(Ljava/lang/Object;Ljava/lang/Object;)Ljava/lang/Object;
    1033: pop
    1034: aload_0
    1035: ldc           #237                // String No function outputs were registered.
    1037: ldc           #238                // String Nije registrovan nikakv izlaz iz funkcije.
    1039: invokevirtual #10                 // Method java/util/Hashtable.put:(Ljava/lang/Object;Ljava/lang/Object;)Ljava/lang/Object;
    1042: pop
    1043: aload_0
    1044: ldc           #239                // String Results cannot be retrieved from a CallableStatement before it is executed.
    1046: ldc           #240                // String Razultat nemože da se primi iz CallableStatement pre nego što se on izvrši.
    1048: invokevirtual #10                 // Method java/util/Hashtable.put:(Ljava/lang/Object;Ljava/lang/Object;)Ljava/lang/Object;
    1051: pop
    1052: aload_0
    1053: ldc           #241                // String This statement has been closed.
    1055: ldc           #242                // String Statement je zatvoren.
    1057: invokevirtual #10                 // Method java/util/Hashtable.put:(Ljava/lang/Object;Ljava/lang/Object;)Ljava/lang/Object;
    1060: pop
    1061: aload_0
    1062: ldc           #243                // String Too many update results were returned.
    1064: ldc           #244                // String Previše rezultata za ažuriranje je vraćeno.
    1066: invokevirtual #10                 // Method java/util/Hashtable.put:(Ljava/lang/Object;Ljava/lang/Object;)Ljava/lang/Object;
    1069: pop
    1070: aload_0
    1071: ldc           #245                // String Batch entry {0} {1} was aborted.  Call getNextException to see the cause.
    1073: ldc           #246                // String Smeša prijava {0} {1} je odbačena. Pozovite getNextException da proverite rezlog.
    1075: invokevirtual #10                 // Method java/util/Hashtable.put:(Ljava/lang/Object;Ljava/lang/Object;)Ljava/lang/Object;
    1078: pop
    1079: aload_0
    1080: ldc           #247                // String Unexpected error writing large object to database.
    1082: ldc           #248                // String Neočekivana greška prilikom upisa velikog objekta u bazu podataka.
    1084: invokevirtual #10                 // Method java/util/Hashtable.put:(Ljava/lang/Object;Ljava/lang/Object;)Ljava/lang/Object;
    1087: pop
    1088: aload_0
    1089: ldc           #249                // String {0} function takes one and only one argument.
    1091: ldc           #250                // String Funkcija {0} prima jedan i samo jedan parametar.
    1093: invokevirtual #10                 // Method java/util/Hashtable.put:(Ljava/lang/Object;Ljava/lang/Object;)Ljava/lang/Object;
    1096: pop
    1097: aload_0
    1098: ldc           #251                // String {0} function takes two and only two arguments.
    1100: ldc           #252                // String Funkcija {0} prima dva i samo dva parametra.
    1102: invokevirtual #10                 // Method java/util/Hashtable.put:(Ljava/lang/Object;Ljava/lang/Object;)Ljava/lang/Object;
    1105: pop
    1106: aload_0
    1107: ldc           #253                // String {0} function takes four and only four argument.
    1109: ldc           #254                // String Funkcija {0} prima četiri i samo četiri parametra.
    1111: invokevirtual #10                 // Method java/util/Hashtable.put:(Ljava/lang/Object;Ljava/lang/Object;)Ljava/lang/Object;
    1114: pop
    1115: aload_0
    1116: ldc           #255                // String {0} function takes two or three arguments.
    1118: ldc_w         #256                // String Funkcija {0} prima dva ili tri parametra.
    1121: invokevirtual #10                 // Method java/util/Hashtable.put:(Ljava/lang/Object;Ljava/lang/Object;)Ljava/lang/Object;
    1124: pop
    1125: aload_0
    1126: ldc_w         #257                // String {0} function doesn\'\'t take any argument.
    1129: ldc_w         #258                // String Funkcija {0} nema parametara.
    1132: invokevirtual #10                 // Method java/util/Hashtable.put:(Ljava/lang/Object;Ljava/lang/Object;)Ljava/lang/Object;
    1135: pop
    1136: aload_0
    1137: ldc_w         #259                // String {0} function takes three and only three arguments.
    1140: ldc_w         #260                // String Funkcija {0} prima tri i samo tri parametra.
    1143: invokevirtual #10                 // Method java/util/Hashtable.put:(Ljava/lang/Object;Ljava/lang/Object;)Ljava/lang/Object;
    1146: pop
    1147: aload_0
    1148: ldc_w         #261                // String Interval {0} not yet implemented
    1151: ldc_w         #262                // String Interval {0} još nije implementiran.
    1154: invokevirtual #10                 // Method java/util/Hashtable.put:(Ljava/lang/Object;Ljava/lang/Object;)Ljava/lang/Object;
    1157: pop
    1158: aload_0
    1159: ldc_w         #263                // String Infinite value found for timestamp/date. This cannot be represented as time.
    1162: ldc_w         #264                // String Beskonačna vrednost je pronađena za tipestamp/date. To se nemože predstaviti kao vreme.
    1165: invokevirtual #10                 // Method java/util/Hashtable.put:(Ljava/lang/Object;Ljava/lang/Object;)Ljava/lang/Object;
    1168: pop
    1169: aload_0
    1170: ldc_w         #265                // String The class {0} does not implement org.postgresql.util.PGobject.
    1173: ldc_w         #266                // String Klasa {0} ne implementira org.postgresql.util.PGobject.
    1176: invokevirtual #10                 // Method java/util/Hashtable.put:(Ljava/lang/Object;Ljava/lang/Object;)Ljava/lang/Object;
    1179: pop
    1180: aload_0
    1181: ldc_w         #267                // String Unknown ResultSet holdability setting: {0}.
    1184: ldc_w         #268                // String Nepoznata ResultSet podešavanja za mogućnost držanja (holdability): {0}.
    1187: invokevirtual #10                 // Method java/util/Hashtable.put:(Ljava/lang/Object;Ljava/lang/Object;)Ljava/lang/Object;
    1190: pop
    1191: aload_0
    1192: ldc_w         #269                // String Server versions prior to 8.0 do not support savepoints.
    1195: ldc_w         #270                // String Verzije servera manje od 8.0 ne podržavaju tačke snimanja.
    1198: invokevirtual #10                 // Method java/util/Hashtable.put:(Ljava/lang/Object;Ljava/lang/Object;)Ljava/lang/Object;
    1201: pop
    1202: aload_0
    1203: ldc_w         #271                // String Cannot establish a savepoint in auto-commit mode.
    1206: ldc_w         #272                // String U auto-commit modu nije moguće podešavanje tački snimanja.
    1209: invokevirtual #10                 // Method java/util/Hashtable.put:(Ljava/lang/Object;Ljava/lang/Object;)Ljava/lang/Object;
    1212: pop
    1213: aload_0
    1214: ldc_w         #273                // String Returning autogenerated keys is not supported.
    1217: ldc_w         #274                // String Vraćanje autogenerisanih ključeva nije podržano.
    1220: invokevirtual #10                 // Method java/util/Hashtable.put:(Ljava/lang/Object;Ljava/lang/Object;)Ljava/lang/Object;
    1223: pop
    1224: aload_0
    1225: ldc_w         #275                // String The parameter index is out of range: {0}, number of parameters: {1}.
    1228: ldc_w         #276                // String Index parametra je van opsega: {0}, broj parametara je: {1}.
    1231: invokevirtual #10                 // Method java/util/Hashtable.put:(Ljava/lang/Object;Ljava/lang/Object;)Ljava/lang/Object;
    1234: pop
    1235: aload_0
    1236: ldc_w         #277                // String Returning autogenerated keys is only supported for 8.2 and later servers.
    1239: ldc_w         #278                // String Vraćanje autogenerisanih ključeva je podržano samo za verzije servera od 8.2 pa na dalje.
    1242: invokevirtual #10                 // Method java/util/Hashtable.put:(Ljava/lang/Object;Ljava/lang/Object;)Ljava/lang/Object;
    1245: pop
    1246: aload_0
    1247: ldc_w         #279                // String Returning autogenerated keys by column index is not supported.
    1250: ldc_w         #280                // String Vraćanje autogenerisanih ključeva po kloloni nije podržano.
    1253: invokevirtual #10                 // Method java/util/Hashtable.put:(Ljava/lang/Object;Ljava/lang/Object;)Ljava/lang/Object;
    1256: pop
    1257: aload_0
    1258: ldc_w         #281                // String Cannot reference a savepoint after it has been released.
    1261: ldc_w         #282                // String Nije moguće referenciranje tačke snimanja nakon njenog oslobađanja.
    1264: invokevirtual #10                 // Method java/util/Hashtable.put:(Ljava/lang/Object;Ljava/lang/Object;)Ljava/lang/Object;
    1267: pop
    1268: aload_0
    1269: ldc_w         #283                // String Cannot retrieve the id of a named savepoint.
    1272: ldc_w         #284                // String Nije moguće primiti id imena tačke snimanja.
    1275: invokevirtual #10                 // Method java/util/Hashtable.put:(Ljava/lang/Object;Ljava/lang/Object;)Ljava/lang/Object;
    1278: pop
    1279: aload_0
    1280: ldc_w         #285                // String Cannot retrieve the name of an unnamed savepoint.
    1283: ldc_w         #286                // String Nije moguće izvaditi ime tačke snimanja koja nema ime.
    1286: invokevirtual #10                 // Method java/util/Hashtable.put:(Ljava/lang/Object;Ljava/lang/Object;)Ljava/lang/Object;
    1289: pop
    1290: aload_0
    1291: ldc_w         #287                // String Invalid UUID data.
    1294: ldc_w         #288                // String Nevažeća UUID podatak.
    1297: invokevirtual #10                 // Method java/util/Hashtable.put:(Ljava/lang/Object;Ljava/lang/Object;)Ljava/lang/Object;
    1300: pop
    1301: aload_0
    1302: ldc_w         #289                // String Unable to find server array type for provided name {0}.
    1305: ldc_w         #290                // String Neuspešno nalaženje liste servera za zadato ime {0}.
    1308: invokevirtual #10                 // Method java/util/Hashtable.put:(Ljava/lang/Object;Ljava/lang/Object;)Ljava/lang/Object;
    1311: pop
    1312: aload_0
    1313: ldc_w         #291                // String ClientInfo property not supported.
    1316: ldc_w         #292                // String ClientInfo property nije podržan.
    1319: invokevirtual #10                 // Method java/util/Hashtable.put:(Ljava/lang/Object;Ljava/lang/Object;)Ljava/lang/Object;
    1322: pop
    1323: aload_0
    1324: ldc_w         #293                // String Unable to decode xml data.
    1327: ldc_w         #294                // String Neuspešno dekodiranje XML podataka.
    1330: invokevirtual #10                 // Method java/util/Hashtable.put:(Ljava/lang/Object;Ljava/lang/Object;)Ljava/lang/Object;
    1333: pop
    1334: aload_0
    1335: ldc_w         #295                // String Unknown XML Source class: {0}
    1338: ldc_w         #296                // String Nepoznata XML ulazna klasa: {0}
    1341: invokevirtual #10                 // Method java/util/Hashtable.put:(Ljava/lang/Object;Ljava/lang/Object;)Ljava/lang/Object;
    1344: pop
    1345: aload_0
    1346: ldc_w         #297                // String Unable to create SAXResult for SQLXML.
    1349: ldc_w         #298                // String Nije moguće kreirati SAXResult za SQLXML.
    1352: invokevirtual #10                 // Method java/util/Hashtable.put:(Ljava/lang/Object;Ljava/lang/Object;)Ljava/lang/Object;
    1355: pop
    1356: aload_0
    1357: ldc_w         #299                // String Unable to create StAXResult for SQLXML
    1360: ldc_w         #300                // String Nije moguće kreirati StAXResult za SQLXML
    1363: invokevirtual #10                 // Method java/util/Hashtable.put:(Ljava/lang/Object;Ljava/lang/Object;)Ljava/lang/Object;
    1366: pop
    1367: aload_0
    1368: ldc_w         #301                // String Unknown XML Result class: {0}
    1371: ldc_w         #302                // String nepoznata XML klasa rezultata: {0}
    1374: invokevirtual #10                 // Method java/util/Hashtable.put:(Ljava/lang/Object;Ljava/lang/Object;)Ljava/lang/Object;
    1377: pop
    1378: aload_0
    1379: ldc_w         #303                // String This SQLXML object has already been freed.
    1382: ldc_w         #304                // String Ovaj SQLXML je već obrisan.
    1385: invokevirtual #10                 // Method java/util/Hashtable.put:(Ljava/lang/Object;Ljava/lang/Object;)Ljava/lang/Object;
    1388: pop
    1389: aload_0
    1390: ldc_w         #305                // String This SQLXML object has not been initialized, so you cannot retrieve data from it.
    1393: ldc_w         #306                // String SQLXML objekat nije inicijalizovan tako da nije moguće preuzimati podatke iz njega.
    1396: invokevirtual #10                 // Method java/util/Hashtable.put:(Ljava/lang/Object;Ljava/lang/Object;)Ljava/lang/Object;
    1399: pop
    1400: aload_0
    1401: ldc_w         #307                // String Failed to convert binary xml data to encoding: {0}.
    1404: ldc_w         #308                // String Neuspešno konvertovanje binarnih XML podataka u kodnu stranu: {0}.
    1407: invokevirtual #10                 // Method java/util/Hashtable.put:(Ljava/lang/Object;Ljava/lang/Object;)Ljava/lang/Object;
    1410: pop
    1411: aload_0
    1412: ldc_w         #309                // String Unable to convert DOMResult SQLXML data to a string.
    1415: ldc_w         #310                // String Nije moguće konvertovati DOMResult SQLXML podatke u string.
    1418: invokevirtual #10                 // Method java/util/Hashtable.put:(Ljava/lang/Object;Ljava/lang/Object;)Ljava/lang/Object;
    1421: pop
    1422: aload_0
    1423: ldc_w         #311                // String This SQLXML object has already been initialized, so you cannot manipulate it further.
    1426: ldc_w         #312                // String SQLXML objekat je već inicijalizovan, tako da ga nije moguće dodatno menjati.
    1429: invokevirtual #10                 // Method java/util/Hashtable.put:(Ljava/lang/Object;Ljava/lang/Object;)Ljava/lang/Object;
    1432: pop
    1433: aload_0
    1434: ldc_w         #313                // String Failed to initialize LargeObject API
    1437: ldc_w         #314                // String Propao pokušaj inicijalizacije LargeObject API-ja.
    1440: invokevirtual #10                 // Method java/util/Hashtable.put:(Ljava/lang/Object;Ljava/lang/Object;)Ljava/lang/Object;
    1443: pop
    1444: aload_0
    1445: ldc_w         #315                // String Large Objects may not be used in auto-commit mode.
    1448: ldc_w         #316                // String Veliki objekti (Large Object) se nemogu koristiti u auto-commit modu.
    1451: invokevirtual #10                 // Method java/util/Hashtable.put:(Ljava/lang/Object;Ljava/lang/Object;)Ljava/lang/Object;
    1454: pop
    1455: aload_0
    1456: ldc_w         #317                // String The SSLSocketFactory class provided {0} could not be instantiated.
    1459: ldc_w         #318                // String SSLSocketFactory klasa koju pruža {0} se nemože instancirati.
    1462: invokevirtual #10                 // Method java/util/Hashtable.put:(Ljava/lang/Object;Ljava/lang/Object;)Ljava/lang/Object;
    1465: pop
    1466: aload_0
    1467: ldc_w         #319                // String Conversion of interval failed
    1470: ldc_w         #320                // String Konverzija intervala propala.
    1473: invokevirtual #10                 // Method java/util/Hashtable.put:(Ljava/lang/Object;Ljava/lang/Object;)Ljava/lang/Object;
    1476: pop
    1477: aload_0
    1478: ldc_w         #321                // String Conversion of money failed.
    1481: ldc_w         #322                // String Konverzija novca (money) propala.
    1484: invokevirtual #10                 // Method java/util/Hashtable.put:(Ljava/lang/Object;Ljava/lang/Object;)Ljava/lang/Object;
    1487: pop
    1488: aload_0
    1489: ldc_w         #323                // String Detail: {0}
    1492: ldc_w         #324                // String Detalji: {0}
    1495: invokevirtual #10                 // Method java/util/Hashtable.put:(Ljava/lang/Object;Ljava/lang/Object;)Ljava/lang/Object;
    1498: pop
    1499: aload_0
    1500: ldc_w         #325                // String Hint: {0}
    1503: ldc_w         #326                // String Nagovest: {0}
    1506: invokevirtual #10                 // Method java/util/Hashtable.put:(Ljava/lang/Object;Ljava/lang/Object;)Ljava/lang/Object;
    1509: pop
    1510: aload_0
    1511: ldc_w         #327                // String Position: {0}
    1514: ldc_w         #328                // String Pozicija: {0}
    1517: invokevirtual #10                 // Method java/util/Hashtable.put:(Ljava/lang/Object;Ljava/lang/Object;)Ljava/lang/Object;
    1520: pop
    1521: aload_0
    1522: ldc_w         #329                // String Where: {0}
    1525: ldc_w         #330                // String Gde: {0}
    1528: invokevirtual #10                 // Method java/util/Hashtable.put:(Ljava/lang/Object;Ljava/lang/Object;)Ljava/lang/Object;
    1531: pop
    1532: aload_0
    1533: ldc_w         #331                // String Internal Query: {0}
    1536: ldc_w         #332                // String Interni upit: {0}
    1539: invokevirtual #10                 // Method java/util/Hashtable.put:(Ljava/lang/Object;Ljava/lang/Object;)Ljava/lang/Object;
    1542: pop
    1543: aload_0
    1544: ldc_w         #333                // String Internal Position: {0}
    1547: ldc_w         #334                // String Interna pozicija: {0}
    1550: invokevirtual #10                 // Method java/util/Hashtable.put:(Ljava/lang/Object;Ljava/lang/Object;)Ljava/lang/Object;
    1553: pop
    1554: aload_0
    1555: ldc_w         #335                // String Location: File: {0}, Routine: {1}, Line: {2}
    1558: ldc_w         #336                // String Lokacija: Fajl: {0}, Rutina: {1}, Linija: {2}
    1561: invokevirtual #10                 // Method java/util/Hashtable.put:(Ljava/lang/Object;Ljava/lang/Object;)Ljava/lang/Object;
    1564: pop
    1565: aload_0
    1566: ldc_w         #337                // String Server SQLState: {0}
    1569: ldc_w         #338                // String SQLState servera: {0}
    1572: invokevirtual #10                 // Method java/util/Hashtable.put:(Ljava/lang/Object;Ljava/lang/Object;)Ljava/lang/Object;
    1575: pop
    1576: aload_0
    1577: ldc_w         #339                // String Invalid flags
    1580: ldc_w         #340                // String Nevažeće zastavice
    1583: invokevirtual #10                 // Method java/util/Hashtable.put:(Ljava/lang/Object;Ljava/lang/Object;)Ljava/lang/Object;
    1586: pop
    1587: aload_0
    1588: ldc_w         #341                // String xid must not be null
    1591: ldc_w         #342                // String xid ne sme biti null
    1594: invokevirtual #10                 // Method java/util/Hashtable.put:(Ljava/lang/Object;Ljava/lang/Object;)Ljava/lang/Object;
    1597: pop
    1598: aload_0
    1599: ldc_w         #343                // String Connection is busy with another transaction
    1602: ldc_w         #344                // String Konekcija je zauzeta sa drugom transakciom.
    1605: invokevirtual #10                 // Method java/util/Hashtable.put:(Ljava/lang/Object;Ljava/lang/Object;)Ljava/lang/Object;
    1608: pop
    1609: aload_0
    1610: ldc_w         #345                // String suspend/resume not implemented
    1613: ldc_w         #346                // String obustavljanje/nastavljanje nije implementirano.
    1616: invokevirtual #10                 // Method java/util/Hashtable.put:(Ljava/lang/Object;Ljava/lang/Object;)Ljava/lang/Object;
    1619: pop
    1620: aload_0
    1621: ldc_w         #347                // String Transaction interleaving not implemented
    1624: ldc_w         #348                // String Preplitanje transakcija nije implementirano.
    1627: invokevirtual #10                 // Method java/util/Hashtable.put:(Ljava/lang/Object;Ljava/lang/Object;)Ljava/lang/Object;
    1630: pop
    1631: aload_0
    1632: ldc_w         #349                // String Error disabling autocommit
    1635: ldc_w         #350                // String Greška u isključivanju autokomita
    1638: invokevirtual #10                 // Method java/util/Hashtable.put:(Ljava/lang/Object;Ljava/lang/Object;)Ljava/lang/Object;
    1641: pop
    1642: aload_0
    1643: ldc_w         #351                // String tried to call end without corresponding start call
    1646: ldc_w         #352                // String Pokušaj pozivanja kraja pre odgovarajućeg početka.
    1649: invokevirtual #10                 // Method java/util/Hashtable.put:(Ljava/lang/Object;Ljava/lang/Object;)Ljava/lang/Object;
    1652: pop
    1653: aload_0
    1654: ldc_w         #353                // String Not implemented: Prepare must be issued using the same connection that started the transaction
    1657: ldc_w         #354                // String Nije implementirano: Spremanje mora biti pozvano uz korišćenje iste konekcije koja se koristi za startovanje transakcije.
    1660: invokevirtual #10                 // Method java/util/Hashtable.put:(Ljava/lang/Object;Ljava/lang/Object;)Ljava/lang/Object;
    1663: pop
    1664: aload_0
    1665: ldc_w         #355                // String Prepare called before end
    1668: ldc_w         #356                // String Pripremanje poziva pre kraja.
    1671: invokevirtual #10                 // Method java/util/Hashtable.put:(Ljava/lang/Object;Ljava/lang/Object;)Ljava/lang/Object;
    1674: pop
    1675: aload_0
    1676: ldc_w         #357                // String Server versions prior to 8.1 do not support two-phase commit.
    1679: ldc_w         #358                // String Verzije servera pre 8.1 verzije ne podržavaju commit iz dve faze.
    1682: invokevirtual #10                 // Method java/util/Hashtable.put:(Ljava/lang/Object;Ljava/lang/Object;)Ljava/lang/Object;
    1685: pop
    1686: aload_0
    1687: ldc_w         #359                // String Error preparing transaction
    1690: ldc_w         #360                // String Greška u pripremanju transakcije.
    1693: invokevirtual #10                 // Method java/util/Hashtable.put:(Ljava/lang/Object;Ljava/lang/Object;)Ljava/lang/Object;
    1696: pop
    1697: aload_0
    1698: ldc_w         #361                // String Invalid flag
    1701: ldc_w         #362                // String Nevažeća zastavica (flag)
    1704: invokevirtual #10                 // Method java/util/Hashtable.put:(Ljava/lang/Object;Ljava/lang/Object;)Ljava/lang/Object;
    1707: pop
    1708: aload_0
    1709: ldc_w         #363                // String Error during recover
    1712: ldc_w         #364                // String Greška prilikom oporavljanja.
    1715: invokevirtual #10                 // Method java/util/Hashtable.put:(Ljava/lang/Object;Ljava/lang/Object;)Ljava/lang/Object;
    1718: pop
    1719: aload_0
    1720: ldc_w         #365                // String Error rolling back prepared transaction
    1723: ldc_w         #366                // String Greška prilikom povratka na prethodo pripremljenu transakciju.
    1726: invokevirtual #10                 // Method java/util/Hashtable.put:(Ljava/lang/Object;Ljava/lang/Object;)Ljava/lang/Object;
    1729: pop
    1730: aload_0
    1731: ldc_w         #367                // String Not implemented: one-phase commit must be issued using the same connection that was used to start it
    1734: ldc_w         #368                // String Nije implementirano: Commit iz jedne faze mora biti izdat uz korištenje iste konekcije koja je korištena za startovanje.
    1737: invokevirtual #10                 // Method java/util/Hashtable.put:(Ljava/lang/Object;Ljava/lang/Object;)Ljava/lang/Object;
    1740: pop
    1741: aload_0
    1742: ldc_w         #369                // String commit called before end
    1745: ldc_w         #370                // String commit pozvan pre kraja.
    1748: invokevirtual #10                 // Method java/util/Hashtable.put:(Ljava/lang/Object;Ljava/lang/Object;)Ljava/lang/Object;
    1751: pop
    1752: aload_0
    1753: ldc_w         #371                // String Error during one-phase commit
    1756: ldc_w         #372                // String Kreška prilikom commit-a iz jedne faze.
    1759: invokevirtual #10                 // Method java/util/Hashtable.put:(Ljava/lang/Object;Ljava/lang/Object;)Ljava/lang/Object;
    1762: pop
    1763: aload_0
    1764: ldc_w         #373                // String Not implemented: 2nd phase commit must be issued using an idle connection
    1767: ldc_w         #374                // String Nije implementirano: Dvofazni commit mora biti izdat uz korištenje besposlene konekcije.
    1770: invokevirtual #10                 // Method java/util/Hashtable.put:(Ljava/lang/Object;Ljava/lang/Object;)Ljava/lang/Object;
    1773: pop
    1774: aload_0
    1775: ldc_w         #375                // String Heuristic commit/rollback not supported
    1778: ldc_w         #376                // String Heuristički commit/rollback nije podržan.
    1781: invokevirtual #10                 // Method java/util/Hashtable.put:(Ljava/lang/Object;Ljava/lang/Object;)Ljava/lang/Object;
    1784: pop
    1785: aload_0
    1786: putstatic     #2                  // Field table:Ljava/util/Hashtable;
    1789: return
}
