Compiled from "ColocFeature.java"
public class org.apache.cxf.binding.coloc.feature.ColocFeature extends org.apache.cxf.feature.AbstractFeature {
  public org.apache.cxf.binding.coloc.feature.ColocFeature();
    Code:
       0: aload_0
       1: invokespecial #1                  // Method org/apache/cxf/feature/AbstractFeature."<init>":()V
       4: return

  public void initialize(org.apache.cxf.endpoint.Client, org.apache.cxf.Bus);
    Code:
       0: new           #2                  // class org/apache/cxf/endpoint/DeferredConduitSelector
       3: dup
       4: invokespecial #3                  // Method org/apache/cxf/endpoint/DeferredConduitSelector."<init>":()V
       7: astore_3
       8: aload_3
       9: aload_1
      10: invokeinterface #4,  1            // InterfaceMethod org/apache/cxf/endpoint/Client.getEndpoint:()Lorg/apache/cxf/endpoint/Endpoint;
      15: invokeinterface #5,  2            // InterfaceMethod org/apache/cxf/endpoint/ConduitSelector.setEndpoint:(Lorg/apache/cxf/endpoint/Endpoint;)V
      20: aload_1
      21: aload_3
      22: invokeinterface #6,  2            // InterfaceMethod org/apache/cxf/endpoint/Client.setConduitSelector:(Lorg/apache/cxf/endpoint/ConduitSelector;)V
      27: aload_0
      28: aload_1
      29: aload_2
      30: invokevirtual #7                  // Method initializeProvider:(Lorg/apache/cxf/interceptor/InterceptorProvider;Lorg/apache/cxf/Bus;)V
      33: return

  protected void initializeProvider(org.apache.cxf.interceptor.InterceptorProvider, org.apache.cxf.Bus);
    Code:
       0: aload_1
       1: invokeinterface #8,  1            // InterfaceMethod org/apache/cxf/interceptor/InterceptorProvider.getInInterceptors:()Ljava/util/List;
       6: new           #9                  // class org/apache/cxf/binding/coloc/ColocInInterceptor
       9: dup
      10: invokespecial #10                 // Method org/apache/cxf/binding/coloc/ColocInInterceptor."<init>":()V
      13: invokeinterface #11,  2           // InterfaceMethod java/util/List.add:(Ljava/lang/Object;)Z
      18: pop
      19: aload_1
      20: invokeinterface #12,  1           // InterfaceMethod org/apache/cxf/interceptor/InterceptorProvider.getOutInterceptors:()Ljava/util/List;
      25: new           #13                 // class org/apache/cxf/binding/coloc/ColocOutInterceptor
      28: dup
      29: aload_2
      30: invokespecial #14                 // Method org/apache/cxf/binding/coloc/ColocOutInterceptor."<init>":(Lorg/apache/cxf/Bus;)V
      33: invokeinterface #11,  2           // InterfaceMethod java/util/List.add:(Ljava/lang/Object;)Z
      38: pop
      39: return
}
