Compiled from "Enums.java"
final class com.google.common.base.Enums$StringConverter<T extends java.lang.Enum<T>> extends com.google.common.base.Converter<java.lang.String, T> implements java.io.Serializable {
  private final java.lang.Class<T> enumClass;

  private static final long serialVersionUID;

  com.google.common.base.Enums$StringConverter(java.lang.Class<T>);
    Code:
       0: aload_0
       1: invokespecial #1                  // Method com/google/common/base/Converter."<init>":()V
       4: aload_0
       5: aload_1
       6: invokestatic  #2                  // Method com/google/common/base/Preconditions.checkNotNull:(Ljava/lang/Object;)Ljava/lang/Object;
       9: checkcast     #3                  // class java/lang/Class
      12: putfield      #4                  // Field enumClass:Ljava/lang/Class;
      15: return

  protected T doForward(java.lang.String);
    Code:
       0: aload_0
       1: getfield      #4                  // Field enumClass:Ljava/lang/Class;
       4: aload_1
       5: invokestatic  #5                  // Method java/lang/Enum.valueOf:(Ljava/lang/Class;Ljava/lang/String;)Ljava/lang/Enum;
       8: areturn

  protected java.lang.String doBackward(T);
    Code:
       0: aload_1
       1: invokevirtual #6                  // Method java/lang/Enum.name:()Ljava/lang/String;
       4: areturn

  public boolean equals(java.lang.Object);
    Code:
       0: aload_1
       1: instanceof    #7                  // class com/google/common/base/Enums$StringConverter
       4: ifeq          24
       7: aload_1
       8: checkcast     #7                  // class com/google/common/base/Enums$StringConverter
      11: astore_2
      12: aload_0
      13: getfield      #4                  // Field enumClass:Ljava/lang/Class;
      16: aload_2
      17: getfield      #4                  // Field enumClass:Ljava/lang/Class;
      20: invokevirtual #8                  // Method java/lang/Object.equals:(Ljava/lang/Object;)Z
      23: ireturn
      24: iconst_0
      25: ireturn

  public int hashCode();
    Code:
       0: aload_0
       1: getfield      #4                  // Field enumClass:Ljava/lang/Class;
       4: invokevirtual #9                  // Method java/lang/Object.hashCode:()I
       7: ireturn

  public java.lang.String toString();
    Code:
       0: aload_0
       1: getfield      #4                  // Field enumClass:Ljava/lang/Class;
       4: invokevirtual #10                 // Method java/lang/Class.getName:()Ljava/lang/String;
       7: invokestatic  #11                 // Method java/lang/String.valueOf:(Ljava/lang/Object;)Ljava/lang/String;
      10: invokestatic  #11                 // Method java/lang/String.valueOf:(Ljava/lang/Object;)Ljava/lang/String;
      13: astore_1
      14: new           #12                 // class java/lang/StringBuilder
      17: dup
      18: bipush        29
      20: aload_1
      21: invokevirtual #13                 // Method java/lang/String.length:()I
      24: iadd
      25: invokespecial #14                 // Method java/lang/StringBuilder."<init>":(I)V
      28: ldc           #15                 // String Enums.stringConverter(
      30: invokevirtual #16                 // Method java/lang/StringBuilder.append:(Ljava/lang/String;)Ljava/lang/StringBuilder;
      33: aload_1
      34: invokevirtual #16                 // Method java/lang/StringBuilder.append:(Ljava/lang/String;)Ljava/lang/StringBuilder;
      37: ldc           #17                 // String .class)
      39: invokevirtual #16                 // Method java/lang/StringBuilder.append:(Ljava/lang/String;)Ljava/lang/StringBuilder;
      42: invokevirtual #18                 // Method java/lang/StringBuilder.toString:()Ljava/lang/String;
      45: areturn

  protected java.lang.Object doBackward(java.lang.Object);
    Code:
       0: aload_0
       1: aload_1
       2: checkcast     #19                 // class java/lang/Enum
       5: invokevirtual #20                 // Method doBackward:(Ljava/lang/Enum;)Ljava/lang/String;
       8: areturn

  protected java.lang.Object doForward(java.lang.Object);
    Code:
       0: aload_0
       1: aload_1
       2: checkcast     #21                 // class java/lang/String
       5: invokevirtual #22                 // Method doForward:(Ljava/lang/String;)Ljava/lang/Enum;
       8: areturn
}
