Compiled from "AbstractCollection.kt"
public abstract class kotlin.collections.AbstractCollection<E> implements java.util.Collection<E>, kotlin.jvm.internal.markers.KMappedMarker {
  public abstract int getSize();

  public final int size();
    Code:
       0: aload_0
       1: invokevirtual #17                 // Method getSize:()I
       4: ireturn

  public abstract java.util.Iterator<E> iterator();

  public boolean contains(java.lang.Object);
    Code:
       0: aload_0
       1: astore_2
       2: aload_2
       3: instanceof    #7                  // class java/util/Collection
       6: ifeq          25
       9: aload_2
      10: checkcast     #7                  // class java/util/Collection
      13: invokeinterface #28,  1           // InterfaceMethod java/util/Collection.isEmpty:()Z
      18: ifeq          25
      21: iconst_0
      22: goto          70
      25: aload_2
      26: invokeinterface #32,  1           // InterfaceMethod java/lang/Iterable.iterator:()Ljava/util/Iterator;
      31: astore_3
      32: aload_3
      33: invokeinterface #37,  1           // InterfaceMethod java/util/Iterator.hasNext:()Z
      38: ifeq          69
      41: aload_3
      42: invokeinterface #41,  1           // InterfaceMethod java/util/Iterator.next:()Ljava/lang/Object;
      47: astore        4
      49: aload         4
      51: astore        5
      53: aload         5
      55: aload_1
      56: invokestatic  #47                 // Method kotlin/jvm/internal/Intrinsics.areEqual:(Ljava/lang/Object;Ljava/lang/Object;)Z
      59: ifeq          32
      62: iconst_1
      63: goto          70
      66: nop
      67: nop
      68: athrow
      69: iconst_0
      70: ireturn

  public boolean containsAll(java.util.Collection<? extends java.lang.Object>);
    Code:
       0: aload_1
       1: ldc           #62                 // String elements
       3: invokestatic  #66                 // Method kotlin/jvm/internal/Intrinsics.checkParameterIsNotNull:(Ljava/lang/Object;Ljava/lang/String;)V
       6: aload_1
       7: checkcast     #30                 // class java/lang/Iterable
      10: astore_2
      11: aload_2
      12: checkcast     #7                  // class java/util/Collection
      15: invokeinterface #28,  1           // InterfaceMethod java/util/Collection.isEmpty:()Z
      20: ifeq          27
      23: iconst_1
      24: goto          72
      27: aload_2
      28: invokeinterface #32,  1           // InterfaceMethod java/lang/Iterable.iterator:()Ljava/util/Iterator;
      33: astore_3
      34: aload_3
      35: invokeinterface #37,  1           // InterfaceMethod java/util/Iterator.hasNext:()Z
      40: ifeq          71
      43: aload_3
      44: invokeinterface #41,  1           // InterfaceMethod java/util/Iterator.next:()Ljava/lang/Object;
      49: astore        4
      51: aload         4
      53: astore        5
      55: aload_0
      56: aload         5
      58: invokevirtual #68                 // Method contains:(Ljava/lang/Object;)Z
      61: ifne          34
      64: iconst_0
      65: goto          72
      68: nop
      69: nop
      70: athrow
      71: iconst_1
      72: ireturn

  public boolean isEmpty();
    Code:
       0: aload_0
       1: invokevirtual #73                 // Method size:()I
       4: ifne          11
       7: iconst_1
       8: goto          12
      11: iconst_0
      12: ireturn

  public java.lang.String toString();
    Code:
       0: aload_0
       1: ldc           #77                 // String ,
       3: checkcast     #79                 // class java/lang/CharSequence
       6: ldc           #81                 // String [
       8: checkcast     #79                 // class java/lang/CharSequence
      11: ldc           #83                 // String ]
      13: checkcast     #79                 // class java/lang/CharSequence
      16: iconst_0
      17: aconst_null
      18: new           #85                 // class kotlin/collections/AbstractCollection$toString$1
      21: dup
      22: aload_0
      23: invokespecial #89                 // Method kotlin/collections/AbstractCollection$toString$1."<init>":(Lkotlin/collections/AbstractCollection;)V
      26: checkcast     #91                 // class kotlin/jvm/functions/Function1
      29: bipush        24
      31: aconst_null
      32: invokestatic  #97                 // Method kotlin/collections/CollectionsKt.joinToString$default:(Ljava/lang/Iterable;Ljava/lang/CharSequence;Ljava/lang/CharSequence;Ljava/lang/CharSequence;ILjava/lang/CharSequence;Lkotlin/jvm/functions/Function1;ILjava/lang/Object;)Ljava/lang/String;
      35: areturn

  public java.lang.Object[] toArray();
    Code:
       0: aload_0
       1: checkcast     #7                  // class java/util/Collection
       4: astore_1
       5: aload_1
       6: invokestatic  #104                // Method kotlin/jvm/internal/CollectionToArray.toArray:(Ljava/util/Collection;)[Ljava/lang/Object;
       9: areturn

  public <T> T[] toArray(T[]);
    Code:
       0: aload_1
       1: ldc           #107                // String array
       3: invokestatic  #66                 // Method kotlin/jvm/internal/Intrinsics.checkParameterIsNotNull:(Ljava/lang/Object;Ljava/lang/String;)V
       6: aload_0
       7: checkcast     #7                  // class java/util/Collection
      10: astore_2
      11: aload_2
      12: aload_1
      13: invokestatic  #110                // Method kotlin/jvm/internal/CollectionToArray.toArray:(Ljava/util/Collection;[Ljava/lang/Object;)[Ljava/lang/Object;
      16: dup
      17: ifnonnull     30
      20: new           #112                // class kotlin/TypeCastException
      23: dup
      24: ldc           #114                // String null cannot be cast to non-null type kotlin.Array<T>
      26: invokespecial #117                // Method kotlin/TypeCastException."<init>":(Ljava/lang/String;)V
      29: athrow
      30: areturn

  protected kotlin.collections.AbstractCollection();
    Code:
       0: aload_0
       1: invokespecial #122                // Method java/lang/Object."<init>":()V
       4: return

  public boolean add(E);
    Code:
       0: new           #125                // class java/lang/UnsupportedOperationException
       3: dup
       4: ldc           #127                // String Operation is not supported for read-only collection
       6: invokespecial #128                // Method java/lang/UnsupportedOperationException."<init>":(Ljava/lang/String;)V
       9: athrow

  public boolean addAll(java.util.Collection<? extends E>);
    Code:
       0: new           #125                // class java/lang/UnsupportedOperationException
       3: dup
       4: ldc           #127                // String Operation is not supported for read-only collection
       6: invokespecial #128                // Method java/lang/UnsupportedOperationException."<init>":(Ljava/lang/String;)V
       9: athrow

  public void clear();
    Code:
       0: new           #125                // class java/lang/UnsupportedOperationException
       3: dup
       4: ldc           #127                // String Operation is not supported for read-only collection
       6: invokespecial #128                // Method java/lang/UnsupportedOperationException."<init>":(Ljava/lang/String;)V
       9: athrow

  public boolean remove(java.lang.Object);
    Code:
       0: new           #125                // class java/lang/UnsupportedOperationException
       3: dup
       4: ldc           #127                // String Operation is not supported for read-only collection
       6: invokespecial #128                // Method java/lang/UnsupportedOperationException."<init>":(Ljava/lang/String;)V
       9: athrow

  public boolean removeAll(java.util.Collection<? extends java.lang.Object>);
    Code:
       0: new           #125                // class java/lang/UnsupportedOperationException
       3: dup
       4: ldc           #127                // String Operation is not supported for read-only collection
       6: invokespecial #128                // Method java/lang/UnsupportedOperationException."<init>":(Ljava/lang/String;)V
       9: athrow

  public boolean retainAll(java.util.Collection<? extends java.lang.Object>);
    Code:
       0: new           #125                // class java/lang/UnsupportedOperationException
       3: dup
       4: ldc           #127                // String Operation is not supported for read-only collection
       6: invokespecial #128                // Method java/lang/UnsupportedOperationException."<init>":(Ljava/lang/String;)V
       9: athrow
}
