Compiled from "Iterators.kt"
class kotlin.collections.CollectionsKt__IteratorsKt extends kotlin.collections.CollectionsKt__IteratorsJVMKt {
  private static final <T> java.util.Iterator<T> iterator(java.util.Iterator<? extends T>);
    Code:
       0: aload_0
       1: ldc           #10                 // String receiver$0
       3: invokestatic  #16                 // Method kotlin/jvm/internal/Intrinsics.checkParameterIsNotNull:(Ljava/lang/Object;Ljava/lang/String;)V
       6: aload_0
       7: areturn

  public static final <T> java.util.Iterator<kotlin.collections.IndexedValue<T>> withIndex(java.util.Iterator<? extends T>);
    Code:
       0: aload_0
       1: ldc           #10                 // String receiver$0
       3: invokestatic  #16                 // Method kotlin/jvm/internal/Intrinsics.checkParameterIsNotNull:(Ljava/lang/Object;Ljava/lang/String;)V
       6: new           #23                 // class kotlin/collections/IndexingIterator
       9: dup
      10: aload_0
      11: invokespecial #27                 // Method kotlin/collections/IndexingIterator."<init>":(Ljava/util/Iterator;)V
      14: checkcast     #29                 // class java/util/Iterator
      17: areturn

  public static final <T> void forEach(java.util.Iterator<? extends T>, kotlin.jvm.functions.Function1<? super T, kotlin.Unit>);
    Code:
       0: aload_0
       1: ldc           #10                 // String receiver$0
       3: invokestatic  #16                 // Method kotlin/jvm/internal/Intrinsics.checkParameterIsNotNull:(Ljava/lang/Object;Ljava/lang/String;)V
       6: aload_1
       7: ldc           #33                 // String operation
       9: invokestatic  #16                 // Method kotlin/jvm/internal/Intrinsics.checkParameterIsNotNull:(Ljava/lang/Object;Ljava/lang/String;)V
      12: aload_0
      13: astore        5
      15: aload         5
      17: astore        4
      19: aload         4
      21: invokeinterface #37,  1           // InterfaceMethod java/util/Iterator.hasNext:()Z
      26: ifeq          48
      29: aload         4
      31: invokeinterface #41,  1           // InterfaceMethod java/util/Iterator.next:()Ljava/lang/Object;
      36: astore_3
      37: aload_1
      38: aload_3
      39: invokeinterface #47,  2           // InterfaceMethod kotlin/jvm/functions/Function1.invoke:(Ljava/lang/Object;)Ljava/lang/Object;
      44: pop
      45: goto          19
      48: return

  public kotlin.collections.CollectionsKt__IteratorsKt();
    Code:
       0: aload_0
       1: invokespecial #75                 // Method kotlin/collections/CollectionsKt__IteratorsJVMKt."<init>":()V
       4: return
}
