Compiled from "SessionFactoryDelegatingImpl.java"
public class org.hibernate.engine.spi.SessionFactoryDelegatingImpl implements org.hibernate.engine.spi.SessionFactoryImplementor,org.hibernate.SessionFactory {
  private final org.hibernate.engine.spi.SessionFactoryImplementor delegate;

  public org.hibernate.engine.spi.SessionFactoryDelegatingImpl(org.hibernate.engine.spi.SessionFactoryImplementor);
    Code:
       0: aload_0
       1: invokespecial #1                  // Method java/lang/Object."<init>":()V
       4: aload_0
       5: aload_1
       6: putfield      #2                  // Field delegate:Lorg/hibernate/engine/spi/SessionFactoryImplementor;
       9: return

  public org.hibernate.boot.spi.SessionFactoryOptions getSessionFactoryOptions();
    Code:
       0: aload_0
       1: getfield      #2                  // Field delegate:Lorg/hibernate/engine/spi/SessionFactoryImplementor;
       4: invokeinterface #3,  1            // InterfaceMethod org/hibernate/engine/spi/SessionFactoryImplementor.getSessionFactoryOptions:()Lorg/hibernate/boot/spi/SessionFactoryOptions;
       9: areturn

  public org.hibernate.engine.spi.SessionBuilderImplementor withOptions();
    Code:
       0: aload_0
       1: getfield      #2                  // Field delegate:Lorg/hibernate/engine/spi/SessionFactoryImplementor;
       4: invokeinterface #4,  1            // InterfaceMethod org/hibernate/engine/spi/SessionFactoryImplementor.withOptions:()Lorg/hibernate/engine/spi/SessionBuilderImplementor;
       9: areturn

  public org.hibernate.Session openSession() throws org.hibernate.HibernateException;
    Code:
       0: aload_0
       1: getfield      #2                  // Field delegate:Lorg/hibernate/engine/spi/SessionFactoryImplementor;
       4: invokeinterface #5,  1            // InterfaceMethod org/hibernate/engine/spi/SessionFactoryImplementor.openSession:()Lorg/hibernate/Session;
       9: areturn

  public org.hibernate.Session getCurrentSession() throws org.hibernate.HibernateException;
    Code:
       0: aload_0
       1: getfield      #2                  // Field delegate:Lorg/hibernate/engine/spi/SessionFactoryImplementor;
       4: invokeinterface #6,  1            // InterfaceMethod org/hibernate/engine/spi/SessionFactoryImplementor.getCurrentSession:()Lorg/hibernate/Session;
       9: areturn

  public org.hibernate.StatelessSessionBuilder withStatelessOptions();
    Code:
       0: aload_0
       1: getfield      #2                  // Field delegate:Lorg/hibernate/engine/spi/SessionFactoryImplementor;
       4: invokeinterface #7,  1            // InterfaceMethod org/hibernate/engine/spi/SessionFactoryImplementor.withStatelessOptions:()Lorg/hibernate/StatelessSessionBuilder;
       9: areturn

  public org.hibernate.StatelessSession openStatelessSession();
    Code:
       0: aload_0
       1: getfield      #2                  // Field delegate:Lorg/hibernate/engine/spi/SessionFactoryImplementor;
       4: invokeinterface #8,  1            // InterfaceMethod org/hibernate/engine/spi/SessionFactoryImplementor.openStatelessSession:()Lorg/hibernate/StatelessSession;
       9: areturn

  public org.hibernate.StatelessSession openStatelessSession(java.sql.Connection);
    Code:
       0: aload_0
       1: getfield      #2                  // Field delegate:Lorg/hibernate/engine/spi/SessionFactoryImplementor;
       4: aload_1
       5: invokeinterface #9,  2            // InterfaceMethod org/hibernate/engine/spi/SessionFactoryImplementor.openStatelessSession:(Ljava/sql/Connection;)Lorg/hibernate/StatelessSession;
      10: areturn

  public org.hibernate.metadata.ClassMetadata getClassMetadata(java.lang.Class);
    Code:
       0: aload_0
       1: getfield      #2                  // Field delegate:Lorg/hibernate/engine/spi/SessionFactoryImplementor;
       4: aload_1
       5: invokeinterface #10,  2           // InterfaceMethod org/hibernate/engine/spi/SessionFactoryImplementor.getClassMetadata:(Ljava/lang/Class;)Lorg/hibernate/metadata/ClassMetadata;
      10: areturn

  public org.hibernate.metadata.ClassMetadata getClassMetadata(java.lang.String);
    Code:
       0: aload_0
       1: getfield      #2                  // Field delegate:Lorg/hibernate/engine/spi/SessionFactoryImplementor;
       4: aload_1
       5: invokeinterface #11,  2           // InterfaceMethod org/hibernate/engine/spi/SessionFactoryImplementor.getClassMetadata:(Ljava/lang/String;)Lorg/hibernate/metadata/ClassMetadata;
      10: areturn

  public org.hibernate.metadata.CollectionMetadata getCollectionMetadata(java.lang.String);
    Code:
       0: aload_0
       1: getfield      #2                  // Field delegate:Lorg/hibernate/engine/spi/SessionFactoryImplementor;
       4: aload_1
       5: invokeinterface #12,  2           // InterfaceMethod org/hibernate/engine/spi/SessionFactoryImplementor.getCollectionMetadata:(Ljava/lang/String;)Lorg/hibernate/metadata/CollectionMetadata;
      10: areturn

  public java.util.Map<java.lang.String, org.hibernate.metadata.ClassMetadata> getAllClassMetadata();
    Code:
       0: aload_0
       1: getfield      #2                  // Field delegate:Lorg/hibernate/engine/spi/SessionFactoryImplementor;
       4: invokeinterface #13,  1           // InterfaceMethod org/hibernate/engine/spi/SessionFactoryImplementor.getAllClassMetadata:()Ljava/util/Map;
       9: areturn

  public java.util.Map getAllCollectionMetadata();
    Code:
       0: aload_0
       1: getfield      #2                  // Field delegate:Lorg/hibernate/engine/spi/SessionFactoryImplementor;
       4: invokeinterface #14,  1           // InterfaceMethod org/hibernate/engine/spi/SessionFactoryImplementor.getAllCollectionMetadata:()Ljava/util/Map;
       9: areturn

  public org.hibernate.stat.spi.StatisticsImplementor getStatistics();
    Code:
       0: aload_0
       1: getfield      #2                  // Field delegate:Lorg/hibernate/engine/spi/SessionFactoryImplementor;
       4: invokeinterface #15,  1           // InterfaceMethod org/hibernate/engine/spi/SessionFactoryImplementor.getStatistics:()Lorg/hibernate/stat/spi/StatisticsImplementor;
       9: areturn

  public void close() throws org.hibernate.HibernateException;
    Code:
       0: aload_0
       1: getfield      #2                  // Field delegate:Lorg/hibernate/engine/spi/SessionFactoryImplementor;
       4: invokeinterface #16,  1           // InterfaceMethod org/hibernate/engine/spi/SessionFactoryImplementor.close:()V
       9: return

  public boolean isClosed();
    Code:
       0: aload_0
       1: getfield      #2                  // Field delegate:Lorg/hibernate/engine/spi/SessionFactoryImplementor;
       4: invokeinterface #17,  1           // InterfaceMethod org/hibernate/engine/spi/SessionFactoryImplementor.isClosed:()Z
       9: ireturn

  public org.hibernate.engine.spi.CacheImplementor getCache();
    Code:
       0: aload_0
       1: getfield      #2                  // Field delegate:Lorg/hibernate/engine/spi/SessionFactoryImplementor;
       4: invokeinterface #18,  1           // InterfaceMethod org/hibernate/engine/spi/SessionFactoryImplementor.getCache:()Lorg/hibernate/engine/spi/CacheImplementor;
       9: areturn

  public javax.persistence.PersistenceUnitUtil getPersistenceUnitUtil();
    Code:
       0: aconst_null
       1: areturn

  public void addNamedQuery(java.lang.String, javax.persistence.Query);
    Code:
       0: return

  public <T> T unwrap(java.lang.Class<T>);
    Code:
       0: aconst_null
       1: areturn

  public <T> void addNamedEntityGraph(java.lang.String, javax.persistence.EntityGraph<T>);
    Code:
       0: return

  public java.util.Set getDefinedFilterNames();
    Code:
       0: aload_0
       1: getfield      #2                  // Field delegate:Lorg/hibernate/engine/spi/SessionFactoryImplementor;
       4: invokeinterface #19,  1           // InterfaceMethod org/hibernate/engine/spi/SessionFactoryImplementor.getDefinedFilterNames:()Ljava/util/Set;
       9: areturn

  public org.hibernate.engine.spi.FilterDefinition getFilterDefinition(java.lang.String) throws org.hibernate.HibernateException;
    Code:
       0: aload_0
       1: getfield      #2                  // Field delegate:Lorg/hibernate/engine/spi/SessionFactoryImplementor;
       4: aload_1
       5: invokeinterface #20,  2           // InterfaceMethod org/hibernate/engine/spi/SessionFactoryImplementor.getFilterDefinition:(Ljava/lang/String;)Lorg/hibernate/engine/spi/FilterDefinition;
      10: areturn

  public boolean containsFetchProfileDefinition(java.lang.String);
    Code:
       0: aload_0
       1: getfield      #2                  // Field delegate:Lorg/hibernate/engine/spi/SessionFactoryImplementor;
       4: aload_1
       5: invokeinterface #21,  2           // InterfaceMethod org/hibernate/engine/spi/SessionFactoryImplementor.containsFetchProfileDefinition:(Ljava/lang/String;)Z
      10: ireturn

  public org.hibernate.TypeHelper getTypeHelper();
    Code:
       0: aload_0
       1: getfield      #2                  // Field delegate:Lorg/hibernate/engine/spi/SessionFactoryImplementor;
       4: invokeinterface #22,  1           // InterfaceMethod org/hibernate/engine/spi/SessionFactoryImplementor.getTypeHelper:()Lorg/hibernate/TypeHelper;
       9: areturn

  public org.hibernate.type.TypeResolver getTypeResolver();
    Code:
       0: aload_0
       1: getfield      #2                  // Field delegate:Lorg/hibernate/engine/spi/SessionFactoryImplementor;
       4: invokeinterface #23,  1           // InterfaceMethod org/hibernate/engine/spi/SessionFactoryImplementor.getTypeResolver:()Lorg/hibernate/type/TypeResolver;
       9: areturn

  public java.util.Map<java.lang.String, java.lang.Object> getProperties();
    Code:
       0: aload_0
       1: getfield      #2                  // Field delegate:Lorg/hibernate/engine/spi/SessionFactoryImplementor;
       4: invokeinterface #24,  1           // InterfaceMethod org/hibernate/engine/spi/SessionFactoryImplementor.getProperties:()Ljava/util/Map;
       9: areturn

  public org.hibernate.persister.entity.EntityPersister getEntityPersister(java.lang.String) throws org.hibernate.MappingException;
    Code:
       0: aload_0
       1: getfield      #2                  // Field delegate:Lorg/hibernate/engine/spi/SessionFactoryImplementor;
       4: aload_1
       5: invokeinterface #25,  2           // InterfaceMethod org/hibernate/engine/spi/SessionFactoryImplementor.getEntityPersister:(Ljava/lang/String;)Lorg/hibernate/persister/entity/EntityPersister;
      10: areturn

  public java.util.Map<java.lang.String, org.hibernate.persister.entity.EntityPersister> getEntityPersisters();
    Code:
       0: aload_0
       1: getfield      #2                  // Field delegate:Lorg/hibernate/engine/spi/SessionFactoryImplementor;
       4: invokeinterface #26,  1           // InterfaceMethod org/hibernate/engine/spi/SessionFactoryImplementor.getEntityPersisters:()Ljava/util/Map;
       9: areturn

  public org.hibernate.persister.collection.CollectionPersister getCollectionPersister(java.lang.String) throws org.hibernate.MappingException;
    Code:
       0: aload_0
       1: getfield      #2                  // Field delegate:Lorg/hibernate/engine/spi/SessionFactoryImplementor;
       4: aload_1
       5: invokeinterface #27,  2           // InterfaceMethod org/hibernate/engine/spi/SessionFactoryImplementor.getCollectionPersister:(Ljava/lang/String;)Lorg/hibernate/persister/collection/CollectionPersister;
      10: areturn

  public java.util.Map<java.lang.String, org.hibernate.persister.collection.CollectionPersister> getCollectionPersisters();
    Code:
       0: aload_0
       1: getfield      #2                  // Field delegate:Lorg/hibernate/engine/spi/SessionFactoryImplementor;
       4: invokeinterface #28,  1           // InterfaceMethod org/hibernate/engine/spi/SessionFactoryImplementor.getCollectionPersisters:()Ljava/util/Map;
       9: areturn

  public org.hibernate.engine.jdbc.spi.JdbcServices getJdbcServices();
    Code:
       0: aload_0
       1: getfield      #2                  // Field delegate:Lorg/hibernate/engine/spi/SessionFactoryImplementor;
       4: invokeinterface #29,  1           // InterfaceMethod org/hibernate/engine/spi/SessionFactoryImplementor.getJdbcServices:()Lorg/hibernate/engine/jdbc/spi/JdbcServices;
       9: areturn

  public org.hibernate.dialect.Dialect getDialect();
    Code:
       0: aload_0
       1: getfield      #2                  // Field delegate:Lorg/hibernate/engine/spi/SessionFactoryImplementor;
       4: invokeinterface #30,  1           // InterfaceMethod org/hibernate/engine/spi/SessionFactoryImplementor.getDialect:()Lorg/hibernate/dialect/Dialect;
       9: areturn

  public org.hibernate.Interceptor getInterceptor();
    Code:
       0: aload_0
       1: getfield      #2                  // Field delegate:Lorg/hibernate/engine/spi/SessionFactoryImplementor;
       4: invokeinterface #31,  1           // InterfaceMethod org/hibernate/engine/spi/SessionFactoryImplementor.getInterceptor:()Lorg/hibernate/Interceptor;
       9: areturn

  public org.hibernate.engine.query.spi.QueryPlanCache getQueryPlanCache();
    Code:
       0: aload_0
       1: getfield      #2                  // Field delegate:Lorg/hibernate/engine/spi/SessionFactoryImplementor;
       4: invokeinterface #32,  1           // InterfaceMethod org/hibernate/engine/spi/SessionFactoryImplementor.getQueryPlanCache:()Lorg/hibernate/engine/query/spi/QueryPlanCache;
       9: areturn

  public org.hibernate.type.Type[] getReturnTypes(java.lang.String) throws org.hibernate.HibernateException;
    Code:
       0: aload_0
       1: getfield      #2                  // Field delegate:Lorg/hibernate/engine/spi/SessionFactoryImplementor;
       4: aload_1
       5: invokeinterface #33,  2           // InterfaceMethod org/hibernate/engine/spi/SessionFactoryImplementor.getReturnTypes:(Ljava/lang/String;)[Lorg/hibernate/type/Type;
      10: areturn

  public java.lang.String[] getReturnAliases(java.lang.String) throws org.hibernate.HibernateException;
    Code:
       0: aload_0
       1: getfield      #2                  // Field delegate:Lorg/hibernate/engine/spi/SessionFactoryImplementor;
       4: aload_1
       5: invokeinterface #34,  2           // InterfaceMethod org/hibernate/engine/spi/SessionFactoryImplementor.getReturnAliases:(Ljava/lang/String;)[Ljava/lang/String;
      10: areturn

  public java.lang.String[] getImplementors(java.lang.String) throws org.hibernate.MappingException;
    Code:
       0: aload_0
       1: getfield      #2                  // Field delegate:Lorg/hibernate/engine/spi/SessionFactoryImplementor;
       4: aload_1
       5: invokeinterface #35,  2           // InterfaceMethod org/hibernate/engine/spi/SessionFactoryImplementor.getImplementors:(Ljava/lang/String;)[Ljava/lang/String;
      10: areturn

  public java.lang.String getImportedClassName(java.lang.String);
    Code:
       0: aload_0
       1: getfield      #2                  // Field delegate:Lorg/hibernate/engine/spi/SessionFactoryImplementor;
       4: aload_1
       5: invokeinterface #36,  2           // InterfaceMethod org/hibernate/engine/spi/SessionFactoryImplementor.getImportedClassName:(Ljava/lang/String;)Ljava/lang/String;
      10: areturn

  public javax.persistence.EntityGraph findEntityGraphByName(java.lang.String);
    Code:
       0: aload_0
       1: getfield      #2                  // Field delegate:Lorg/hibernate/engine/spi/SessionFactoryImplementor;
       4: aload_1
       5: invokeinterface #37,  2           // InterfaceMethod org/hibernate/engine/spi/SessionFactoryImplementor.findEntityGraphByName:(Ljava/lang/String;)Ljavax/persistence/EntityGraph;
      10: areturn

  public org.hibernate.cache.spi.QueryCache getQueryCache();
    Code:
       0: aload_0
       1: getfield      #2                  // Field delegate:Lorg/hibernate/engine/spi/SessionFactoryImplementor;
       4: invokeinterface #38,  1           // InterfaceMethod org/hibernate/engine/spi/SessionFactoryImplementor.getQueryCache:()Lorg/hibernate/cache/spi/QueryCache;
       9: areturn

  public org.hibernate.cache.spi.QueryCache getQueryCache(java.lang.String) throws org.hibernate.HibernateException;
    Code:
       0: aload_0
       1: getfield      #2                  // Field delegate:Lorg/hibernate/engine/spi/SessionFactoryImplementor;
       4: aload_1
       5: invokeinterface #39,  2           // InterfaceMethod org/hibernate/engine/spi/SessionFactoryImplementor.getQueryCache:(Ljava/lang/String;)Lorg/hibernate/cache/spi/QueryCache;
      10: areturn

  public org.hibernate.cache.spi.UpdateTimestampsCache getUpdateTimestampsCache();
    Code:
       0: aload_0
       1: getfield      #2                  // Field delegate:Lorg/hibernate/engine/spi/SessionFactoryImplementor;
       4: invokeinterface #40,  1           // InterfaceMethod org/hibernate/engine/spi/SessionFactoryImplementor.getUpdateTimestampsCache:()Lorg/hibernate/cache/spi/UpdateTimestampsCache;
       9: areturn

  public org.hibernate.stat.spi.StatisticsImplementor getStatisticsImplementor();
    Code:
       0: aload_0
       1: getfield      #2                  // Field delegate:Lorg/hibernate/engine/spi/SessionFactoryImplementor;
       4: invokeinterface #41,  1           // InterfaceMethod org/hibernate/engine/spi/SessionFactoryImplementor.getStatisticsImplementor:()Lorg/hibernate/stat/spi/StatisticsImplementor;
       9: areturn

  public org.hibernate.engine.spi.NamedQueryDefinition getNamedQuery(java.lang.String);
    Code:
       0: aload_0
       1: getfield      #2                  // Field delegate:Lorg/hibernate/engine/spi/SessionFactoryImplementor;
       4: aload_1
       5: invokeinterface #42,  2           // InterfaceMethod org/hibernate/engine/spi/SessionFactoryImplementor.getNamedQuery:(Ljava/lang/String;)Lorg/hibernate/engine/spi/NamedQueryDefinition;
      10: areturn

  public void registerNamedQueryDefinition(java.lang.String, org.hibernate.engine.spi.NamedQueryDefinition);
    Code:
       0: aload_0
       1: getfield      #2                  // Field delegate:Lorg/hibernate/engine/spi/SessionFactoryImplementor;
       4: aload_1
       5: aload_2
       6: invokeinterface #43,  3           // InterfaceMethod org/hibernate/engine/spi/SessionFactoryImplementor.registerNamedQueryDefinition:(Ljava/lang/String;Lorg/hibernate/engine/spi/NamedQueryDefinition;)V
      11: return

  public org.hibernate.engine.spi.NamedSQLQueryDefinition getNamedSQLQuery(java.lang.String);
    Code:
       0: aload_0
       1: getfield      #2                  // Field delegate:Lorg/hibernate/engine/spi/SessionFactoryImplementor;
       4: aload_1
       5: invokeinterface #44,  2           // InterfaceMethod org/hibernate/engine/spi/SessionFactoryImplementor.getNamedSQLQuery:(Ljava/lang/String;)Lorg/hibernate/engine/spi/NamedSQLQueryDefinition;
      10: areturn

  public void registerNamedSQLQueryDefinition(java.lang.String, org.hibernate.engine.spi.NamedSQLQueryDefinition);
    Code:
       0: aload_0
       1: getfield      #2                  // Field delegate:Lorg/hibernate/engine/spi/SessionFactoryImplementor;
       4: aload_1
       5: aload_2
       6: invokeinterface #45,  3           // InterfaceMethod org/hibernate/engine/spi/SessionFactoryImplementor.registerNamedSQLQueryDefinition:(Ljava/lang/String;Lorg/hibernate/engine/spi/NamedSQLQueryDefinition;)V
      11: return

  public org.hibernate.engine.ResultSetMappingDefinition getResultSetMapping(java.lang.String);
    Code:
       0: aload_0
       1: getfield      #2                  // Field delegate:Lorg/hibernate/engine/spi/SessionFactoryImplementor;
       4: aload_1
       5: invokeinterface #46,  2           // InterfaceMethod org/hibernate/engine/spi/SessionFactoryImplementor.getResultSetMapping:(Ljava/lang/String;)Lorg/hibernate/engine/ResultSetMappingDefinition;
      10: areturn

  public org.hibernate.id.IdentifierGenerator getIdentifierGenerator(java.lang.String);
    Code:
       0: aload_0
       1: getfield      #2                  // Field delegate:Lorg/hibernate/engine/spi/SessionFactoryImplementor;
       4: aload_1
       5: invokeinterface #47,  2           // InterfaceMethod org/hibernate/engine/spi/SessionFactoryImplementor.getIdentifierGenerator:(Ljava/lang/String;)Lorg/hibernate/id/IdentifierGenerator;
      10: areturn

  public org.hibernate.cache.spi.Region getSecondLevelCacheRegion(java.lang.String);
    Code:
       0: aload_0
       1: getfield      #2                  // Field delegate:Lorg/hibernate/engine/spi/SessionFactoryImplementor;
       4: aload_1
       5: invokeinterface #48,  2           // InterfaceMethod org/hibernate/engine/spi/SessionFactoryImplementor.getSecondLevelCacheRegion:(Ljava/lang/String;)Lorg/hibernate/cache/spi/Region;
      10: areturn

  public org.hibernate.cache.spi.access.RegionAccessStrategy getSecondLevelCacheRegionAccessStrategy(java.lang.String);
    Code:
       0: aload_0
       1: getfield      #2                  // Field delegate:Lorg/hibernate/engine/spi/SessionFactoryImplementor;
       4: aload_1
       5: invokeinterface #49,  2           // InterfaceMethod org/hibernate/engine/spi/SessionFactoryImplementor.getSecondLevelCacheRegionAccessStrategy:(Ljava/lang/String;)Lorg/hibernate/cache/spi/access/RegionAccessStrategy;
      10: areturn

  public org.hibernate.cache.spi.Region getNaturalIdCacheRegion(java.lang.String);
    Code:
       0: aload_0
       1: getfield      #2                  // Field delegate:Lorg/hibernate/engine/spi/SessionFactoryImplementor;
       4: aload_1
       5: invokeinterface #50,  2           // InterfaceMethod org/hibernate/engine/spi/SessionFactoryImplementor.getNaturalIdCacheRegion:(Ljava/lang/String;)Lorg/hibernate/cache/spi/Region;
      10: areturn

  public org.hibernate.cache.spi.access.RegionAccessStrategy getNaturalIdCacheRegionAccessStrategy(java.lang.String);
    Code:
       0: aload_0
       1: getfield      #2                  // Field delegate:Lorg/hibernate/engine/spi/SessionFactoryImplementor;
       4: aload_1
       5: invokeinterface #51,  2           // InterfaceMethod org/hibernate/engine/spi/SessionFactoryImplementor.getNaturalIdCacheRegionAccessStrategy:(Ljava/lang/String;)Lorg/hibernate/cache/spi/access/RegionAccessStrategy;
      10: areturn

  public java.util.Map getAllSecondLevelCacheRegions();
    Code:
       0: aload_0
       1: getfield      #2                  // Field delegate:Lorg/hibernate/engine/spi/SessionFactoryImplementor;
       4: invokeinterface #52,  1           // InterfaceMethod org/hibernate/engine/spi/SessionFactoryImplementor.getAllSecondLevelCacheRegions:()Ljava/util/Map;
       9: areturn

  public org.hibernate.exception.spi.SQLExceptionConverter getSQLExceptionConverter();
    Code:
       0: aload_0
       1: getfield      #2                  // Field delegate:Lorg/hibernate/engine/spi/SessionFactoryImplementor;
       4: invokeinterface #53,  1           // InterfaceMethod org/hibernate/engine/spi/SessionFactoryImplementor.getSQLExceptionConverter:()Lorg/hibernate/exception/spi/SQLExceptionConverter;
       9: areturn

  public org.hibernate.engine.jdbc.spi.SqlExceptionHelper getSQLExceptionHelper();
    Code:
       0: aload_0
       1: getfield      #2                  // Field delegate:Lorg/hibernate/engine/spi/SessionFactoryImplementor;
       4: invokeinterface #54,  1           // InterfaceMethod org/hibernate/engine/spi/SessionFactoryImplementor.getSQLExceptionHelper:()Lorg/hibernate/engine/jdbc/spi/SqlExceptionHelper;
       9: areturn

  public org.hibernate.cfg.Settings getSettings();
    Code:
       0: aload_0
       1: getfield      #2                  // Field delegate:Lorg/hibernate/engine/spi/SessionFactoryImplementor;
       4: invokeinterface #55,  1           // InterfaceMethod org/hibernate/engine/spi/SessionFactoryImplementor.getSettings:()Lorg/hibernate/cfg/Settings;
       9: areturn

  public org.hibernate.Session openTemporarySession() throws org.hibernate.HibernateException;
    Code:
       0: aload_0
       1: getfield      #2                  // Field delegate:Lorg/hibernate/engine/spi/SessionFactoryImplementor;
       4: invokeinterface #56,  1           // InterfaceMethod org/hibernate/engine/spi/SessionFactoryImplementor.openTemporarySession:()Lorg/hibernate/Session;
       9: areturn

  public java.util.Set<java.lang.String> getCollectionRolesByEntityParticipant(java.lang.String);
    Code:
       0: aload_0
       1: getfield      #2                  // Field delegate:Lorg/hibernate/engine/spi/SessionFactoryImplementor;
       4: aload_1
       5: invokeinterface #57,  2           // InterfaceMethod org/hibernate/engine/spi/SessionFactoryImplementor.getCollectionRolesByEntityParticipant:(Ljava/lang/String;)Ljava/util/Set;
      10: areturn

  public org.hibernate.proxy.EntityNotFoundDelegate getEntityNotFoundDelegate();
    Code:
       0: aload_0
       1: getfield      #2                  // Field delegate:Lorg/hibernate/engine/spi/SessionFactoryImplementor;
       4: invokeinterface #58,  1           // InterfaceMethod org/hibernate/engine/spi/SessionFactoryImplementor.getEntityNotFoundDelegate:()Lorg/hibernate/proxy/EntityNotFoundDelegate;
       9: areturn

  public org.hibernate.dialect.function.SQLFunctionRegistry getSqlFunctionRegistry();
    Code:
       0: aload_0
       1: getfield      #2                  // Field delegate:Lorg/hibernate/engine/spi/SessionFactoryImplementor;
       4: invokeinterface #59,  1           // InterfaceMethod org/hibernate/engine/spi/SessionFactoryImplementor.getSqlFunctionRegistry:()Lorg/hibernate/dialect/function/SQLFunctionRegistry;
       9: areturn

  public org.hibernate.engine.profile.FetchProfile getFetchProfile(java.lang.String);
    Code:
       0: aload_0
       1: getfield      #2                  // Field delegate:Lorg/hibernate/engine/spi/SessionFactoryImplementor;
       4: aload_1
       5: invokeinterface #60,  2           // InterfaceMethod org/hibernate/engine/spi/SessionFactoryImplementor.getFetchProfile:(Ljava/lang/String;)Lorg/hibernate/engine/profile/FetchProfile;
      10: areturn

  public org.hibernate.service.spi.ServiceRegistryImplementor getServiceRegistry();
    Code:
       0: aload_0
       1: getfield      #2                  // Field delegate:Lorg/hibernate/engine/spi/SessionFactoryImplementor;
       4: invokeinterface #61,  1           // InterfaceMethod org/hibernate/engine/spi/SessionFactoryImplementor.getServiceRegistry:()Lorg/hibernate/service/spi/ServiceRegistryImplementor;
       9: areturn

  public void addObserver(org.hibernate.SessionFactoryObserver);
    Code:
       0: aload_0
       1: getfield      #2                  // Field delegate:Lorg/hibernate/engine/spi/SessionFactoryImplementor;
       4: aload_1
       5: invokeinterface #62,  2           // InterfaceMethod org/hibernate/engine/spi/SessionFactoryImplementor.addObserver:(Lorg/hibernate/SessionFactoryObserver;)V
      10: return

  public org.hibernate.CustomEntityDirtinessStrategy getCustomEntityDirtinessStrategy();
    Code:
       0: aload_0
       1: getfield      #2                  // Field delegate:Lorg/hibernate/engine/spi/SessionFactoryImplementor;
       4: invokeinterface #63,  1           // InterfaceMethod org/hibernate/engine/spi/SessionFactoryImplementor.getCustomEntityDirtinessStrategy:()Lorg/hibernate/CustomEntityDirtinessStrategy;
       9: areturn

  public org.hibernate.context.spi.CurrentTenantIdentifierResolver getCurrentTenantIdentifierResolver();
    Code:
       0: aload_0
       1: getfield      #2                  // Field delegate:Lorg/hibernate/engine/spi/SessionFactoryImplementor;
       4: invokeinterface #64,  1           // InterfaceMethod org/hibernate/engine/spi/SessionFactoryImplementor.getCurrentTenantIdentifierResolver:()Lorg/hibernate/context/spi/CurrentTenantIdentifierResolver;
       9: areturn

  public org.hibernate.query.spi.NamedQueryRepository getNamedQueryRepository();
    Code:
       0: aload_0
       1: getfield      #2                  // Field delegate:Lorg/hibernate/engine/spi/SessionFactoryImplementor;
       4: invokeinterface #65,  1           // InterfaceMethod org/hibernate/engine/spi/SessionFactoryImplementor.getNamedQueryRepository:()Lorg/hibernate/query/spi/NamedQueryRepository;
       9: areturn

  public java.lang.Iterable<org.hibernate.EntityNameResolver> iterateEntityNameResolvers();
    Code:
       0: aload_0
       1: getfield      #2                  // Field delegate:Lorg/hibernate/engine/spi/SessionFactoryImplementor;
       4: invokeinterface #66,  1           // InterfaceMethod org/hibernate/engine/spi/SessionFactoryImplementor.iterateEntityNameResolvers:()Ljava/lang/Iterable;
       9: areturn

  public org.hibernate.persister.entity.EntityPersister locateEntityPersister(java.lang.Class);
    Code:
       0: aload_0
       1: getfield      #2                  // Field delegate:Lorg/hibernate/engine/spi/SessionFactoryImplementor;
       4: aload_1
       5: invokeinterface #67,  2           // InterfaceMethod org/hibernate/engine/spi/SessionFactoryImplementor.locateEntityPersister:(Ljava/lang/Class;)Lorg/hibernate/persister/entity/EntityPersister;
      10: areturn

  public org.hibernate.persister.entity.EntityPersister locateEntityPersister(java.lang.String);
    Code:
       0: aload_0
       1: getfield      #2                  // Field delegate:Lorg/hibernate/engine/spi/SessionFactoryImplementor;
       4: aload_1
       5: invokeinterface #68,  2           // InterfaceMethod org/hibernate/engine/spi/SessionFactoryImplementor.locateEntityPersister:(Ljava/lang/String;)Lorg/hibernate/persister/entity/EntityPersister;
      10: areturn

  public org.hibernate.engine.spi.SessionFactoryImplementor$DeserializationResolver getDeserializationResolver();
    Code:
       0: aload_0
       1: getfield      #2                  // Field delegate:Lorg/hibernate/engine/spi/SessionFactoryImplementor;
       4: invokeinterface #69,  1           // InterfaceMethod org/hibernate/engine/spi/SessionFactoryImplementor.getDeserializationResolver:()Lorg/hibernate/engine/spi/SessionFactoryImplementor$DeserializationResolver;
       9: areturn

  public org.hibernate.id.factory.IdentifierGeneratorFactory getIdentifierGeneratorFactory();
    Code:
       0: aload_0
       1: getfield      #2                  // Field delegate:Lorg/hibernate/engine/spi/SessionFactoryImplementor;
       4: invokeinterface #70,  1           // InterfaceMethod org/hibernate/engine/spi/SessionFactoryImplementor.getIdentifierGeneratorFactory:()Lorg/hibernate/id/factory/IdentifierGeneratorFactory;
       9: areturn

  public org.hibernate.type.Type getIdentifierType(java.lang.String) throws org.hibernate.MappingException;
    Code:
       0: aload_0
       1: getfield      #2                  // Field delegate:Lorg/hibernate/engine/spi/SessionFactoryImplementor;
       4: aload_1
       5: invokeinterface #71,  2           // InterfaceMethod org/hibernate/engine/spi/SessionFactoryImplementor.getIdentifierType:(Ljava/lang/String;)Lorg/hibernate/type/Type;
      10: areturn

  public java.lang.String getIdentifierPropertyName(java.lang.String) throws org.hibernate.MappingException;
    Code:
       0: aload_0
       1: getfield      #2                  // Field delegate:Lorg/hibernate/engine/spi/SessionFactoryImplementor;
       4: aload_1
       5: invokeinterface #72,  2           // InterfaceMethod org/hibernate/engine/spi/SessionFactoryImplementor.getIdentifierPropertyName:(Ljava/lang/String;)Ljava/lang/String;
      10: areturn

  public org.hibernate.type.Type getReferencedPropertyType(java.lang.String, java.lang.String) throws org.hibernate.MappingException;
    Code:
       0: aload_0
       1: getfield      #2                  // Field delegate:Lorg/hibernate/engine/spi/SessionFactoryImplementor;
       4: aload_1
       5: aload_2
       6: invokeinterface #73,  3           // InterfaceMethod org/hibernate/engine/spi/SessionFactoryImplementor.getReferencedPropertyType:(Ljava/lang/String;Ljava/lang/String;)Lorg/hibernate/type/Type;
      11: areturn

  public java.lang.String getUuid();
    Code:
       0: aload_0
       1: getfield      #2                  // Field delegate:Lorg/hibernate/engine/spi/SessionFactoryImplementor;
       4: invokeinterface #74,  1           // InterfaceMethod org/hibernate/engine/spi/SessionFactoryImplementor.getUuid:()Ljava/lang/String;
       9: areturn

  public java.lang.String getName();
    Code:
       0: aload_0
       1: getfield      #2                  // Field delegate:Lorg/hibernate/engine/spi/SessionFactoryImplementor;
       4: invokeinterface #75,  1           // InterfaceMethod org/hibernate/engine/spi/SessionFactoryImplementor.getName:()Ljava/lang/String;
       9: areturn

  public javax.naming.Reference getReference() throws javax.naming.NamingException;
    Code:
       0: aload_0
       1: getfield      #2                  // Field delegate:Lorg/hibernate/engine/spi/SessionFactoryImplementor;
       4: invokeinterface #76,  1           // InterfaceMethod org/hibernate/engine/spi/SessionFactoryImplementor.getReference:()Ljavax/naming/Reference;
       9: areturn

  public <T> java.util.List<javax.persistence.EntityGraph<? super T>> findEntityGraphsByType(java.lang.Class<T>);
    Code:
       0: aload_0
       1: getfield      #2                  // Field delegate:Lorg/hibernate/engine/spi/SessionFactoryImplementor;
       4: aload_1
       5: invokeinterface #77,  2           // InterfaceMethod org/hibernate/engine/spi/SessionFactoryImplementor.findEntityGraphsByType:(Ljava/lang/Class;)Ljava/util/List;
      10: areturn

  public javax.persistence.EntityManager createEntityManager();
    Code:
       0: aload_0
       1: getfield      #2                  // Field delegate:Lorg/hibernate/engine/spi/SessionFactoryImplementor;
       4: invokeinterface #78,  1           // InterfaceMethod org/hibernate/engine/spi/SessionFactoryImplementor.createEntityManager:()Ljavax/persistence/EntityManager;
       9: areturn

  public javax.persistence.EntityManager createEntityManager(java.util.Map);
    Code:
       0: aload_0
       1: getfield      #2                  // Field delegate:Lorg/hibernate/engine/spi/SessionFactoryImplementor;
       4: aload_1
       5: invokeinterface #79,  2           // InterfaceMethod org/hibernate/engine/spi/SessionFactoryImplementor.createEntityManager:(Ljava/util/Map;)Ljavax/persistence/EntityManager;
      10: areturn

  public javax.persistence.EntityManager createEntityManager(javax.persistence.SynchronizationType);
    Code:
       0: aload_0
       1: getfield      #2                  // Field delegate:Lorg/hibernate/engine/spi/SessionFactoryImplementor;
       4: aload_1
       5: invokeinterface #80,  2           // InterfaceMethod org/hibernate/engine/spi/SessionFactoryImplementor.createEntityManager:(Ljavax/persistence/SynchronizationType;)Ljavax/persistence/EntityManager;
      10: areturn

  public javax.persistence.EntityManager createEntityManager(javax.persistence.SynchronizationType, java.util.Map);
    Code:
       0: aload_0
       1: getfield      #2                  // Field delegate:Lorg/hibernate/engine/spi/SessionFactoryImplementor;
       4: aload_1
       5: aload_2
       6: invokeinterface #81,  3           // InterfaceMethod org/hibernate/engine/spi/SessionFactoryImplementor.createEntityManager:(Ljavax/persistence/SynchronizationType;Ljava/util/Map;)Ljavax/persistence/EntityManager;
      11: areturn

  public javax.persistence.criteria.CriteriaBuilder getCriteriaBuilder();
    Code:
       0: aload_0
       1: getfield      #2                  // Field delegate:Lorg/hibernate/engine/spi/SessionFactoryImplementor;
       4: invokeinterface #82,  1           // InterfaceMethod org/hibernate/engine/spi/SessionFactoryImplementor.getCriteriaBuilder:()Ljavax/persistence/criteria/CriteriaBuilder;
       9: areturn

  public org.hibernate.metamodel.spi.MetamodelImplementor getMetamodel();
    Code:
       0: aload_0
       1: getfield      #2                  // Field delegate:Lorg/hibernate/engine/spi/SessionFactoryImplementor;
       4: invokeinterface #83,  1           // InterfaceMethod org/hibernate/engine/spi/SessionFactoryImplementor.getMetamodel:()Lorg/hibernate/metamodel/spi/MetamodelImplementor;
       9: areturn

  public boolean isOpen();
    Code:
       0: aload_0
       1: getfield      #2                  // Field delegate:Lorg/hibernate/engine/spi/SessionFactoryImplementor;
       4: invokeinterface #84,  1           // InterfaceMethod org/hibernate/engine/spi/SessionFactoryImplementor.isOpen:()Z
       9: ireturn

  public org.hibernate.type.Type resolveParameterBindType(java.lang.Object);
    Code:
       0: aload_0
       1: getfield      #2                  // Field delegate:Lorg/hibernate/engine/spi/SessionFactoryImplementor;
       4: aload_1
       5: invokeinterface #85,  2           // InterfaceMethod org/hibernate/engine/spi/SessionFactoryImplementor.resolveParameterBindType:(Ljava/lang/Object;)Lorg/hibernate/type/Type;
      10: areturn

  public org.hibernate.type.Type resolveParameterBindType(java.lang.Class);
    Code:
       0: aload_0
       1: getfield      #2                  // Field delegate:Lorg/hibernate/engine/spi/SessionFactoryImplementor;
       4: aload_1
       5: invokeinterface #86,  2           // InterfaceMethod org/hibernate/engine/spi/SessionFactoryImplementor.resolveParameterBindType:(Ljava/lang/Class;)Lorg/hibernate/type/Type;
      10: areturn

  public org.hibernate.Cache getCache();
    Code:
       0: aload_0
       1: invokevirtual #87                 // Method getCache:()Lorg/hibernate/engine/spi/CacheImplementor;
       4: areturn

  public org.hibernate.stat.Statistics getStatistics();
    Code:
       0: aload_0
       1: invokevirtual #88                 // Method getStatistics:()Lorg/hibernate/stat/spi/StatisticsImplementor;
       4: areturn

  public org.hibernate.SessionBuilder withOptions();
    Code:
       0: aload_0
       1: invokevirtual #89                 // Method withOptions:()Lorg/hibernate/engine/spi/SessionBuilderImplementor;
       4: areturn

  public javax.persistence.Cache getCache();
    Code:
       0: aload_0
       1: invokevirtual #87                 // Method getCache:()Lorg/hibernate/engine/spi/CacheImplementor;
       4: areturn

  public javax.persistence.metamodel.Metamodel getMetamodel();
    Code:
       0: aload_0
       1: invokevirtual #90                 // Method getMetamodel:()Lorg/hibernate/metamodel/spi/MetamodelImplementor;
       4: areturn

  public org.hibernate.Metamodel getMetamodel();
    Code:
       0: aload_0
       1: invokevirtual #90                 // Method getMetamodel:()Lorg/hibernate/metamodel/spi/MetamodelImplementor;
       4: areturn
}
