Compiled from "IpcOrigin.java"
public class io.vertx.up.uca.micro.discovery.IpcOrigin extends io.vertx.up.uca.micro.discovery.ApiOrigin {
  public io.vertx.up.uca.micro.discovery.IpcOrigin();
    Code:
       0: aload_0
       1: invokespecial #1                  // Method io/vertx/up/uca/micro/discovery/ApiOrigin."<init>":()V
       4: return

  public java.util.concurrent.ConcurrentMap<java.lang.String, io.vertx.servicediscovery.Record> getRegistryData();
    Code:
       0: aload_0
       1: getstatic     #2                  // Field io/vertx/up/eon/em/EtcdPath.IPC:Lio/vertx/up/eon/em/EtcdPath;
       4: invokevirtual #3                  // Method readData:(Lio/vertx/up/eon/em/EtcdPath;)Ljava/util/concurrent/ConcurrentMap;
       7: astore_1
       8: aload_1
       9: invokeinterface #4,  1            // InterfaceMethod java/util/concurrent/ConcurrentMap.values:()Ljava/util/Collection;
      14: invokeinterface #5,  1            // InterfaceMethod java/util/Collection.iterator:()Ljava/util/Iterator;
      19: astore_2
      20: aload_2
      21: invokeinterface #6,  1            // InterfaceMethod java/util/Iterator.hasNext:()Z
      26: ifeq          70
      29: aload_2
      30: invokeinterface #7,  1            // InterfaceMethod java/util/Iterator.next:()Ljava/lang/Object;
      35: checkcast     #8                  // class io/vertx/servicediscovery/Record
      38: astore_3
      39: aload_3
      40: getstatic     #9                  // Field io/vertx/servicediscovery/Status.UP:Lio/vertx/servicediscovery/Status;
      43: invokevirtual #10                 // Method io/vertx/servicediscovery/Record.setStatus:(Lio/vertx/servicediscovery/Status;)Lio/vertx/servicediscovery/Record;
      46: pop
      47: aload_3
      48: ldc           #11                 // String IPC
      50: invokevirtual #12                 // Method io/vertx/servicediscovery/Record.setType:(Ljava/lang/String;)Lio/vertx/servicediscovery/Record;
      53: pop
      54: aload_3
      55: invokevirtual #13                 // Method io/vertx/servicediscovery/Record.getLocation:()Lio/vertx/core/json/JsonObject;
      58: ldc           #14                 // String ssl
      60: getstatic     #15                 // Field java/lang/Boolean.TRUE:Ljava/lang/Boolean;
      63: invokevirtual #16                 // Method io/vertx/core/json/JsonObject.put:(Ljava/lang/String;Ljava/lang/Boolean;)Lio/vertx/core/json/JsonObject;
      66: pop
      67: goto          20
      70: aload_1
      71: areturn

  public io.vertx.up.eon.em.EtcdPath getPath();
    Code:
       0: getstatic     #2                  // Field io/vertx/up/eon/em/EtcdPath.IPC:Lio/vertx/up/eon/em/EtcdPath;
       3: areturn
}
