Compiled from "State.java"
public final class org.sonatype.spice.zapper.internal.transport.State extends java.lang.Enum<org.sonatype.spice.zapper.internal.transport.State> {
  public static final org.sonatype.spice.zapper.internal.transport.State SUCCESS;

  public static final org.sonatype.spice.zapper.internal.transport.State FAILURE;

  private static final org.sonatype.spice.zapper.internal.transport.State[] $VALUES;

  public static org.sonatype.spice.zapper.internal.transport.State[] values();
    Code:
       0: getstatic     #1                  // Field $VALUES:[Lorg/sonatype/spice/zapper/internal/transport/State;
       3: invokevirtual #2                  // Method "[Lorg/sonatype/spice/zapper/internal/transport/State;".clone:()Ljava/lang/Object;
       6: checkcast     #3                  // class "[Lorg/sonatype/spice/zapper/internal/transport/State;"
       9: areturn

  public static org.sonatype.spice.zapper.internal.transport.State valueOf(java.lang.String);
    Code:
       0: ldc_w         #4                  // class org/sonatype/spice/zapper/internal/transport/State
       3: aload_0
       4: invokestatic  #5                  // Method java/lang/Enum.valueOf:(Ljava/lang/Class;Ljava/lang/String;)Ljava/lang/Enum;
       7: checkcast     #4                  // class org/sonatype/spice/zapper/internal/transport/State
      10: areturn

  private org.sonatype.spice.zapper.internal.transport.State();
    Code:
       0: aload_0
       1: aload_1
       2: iload_2
       3: invokespecial #6                  // Method java/lang/Enum."<init>":(Ljava/lang/String;I)V
       6: return

  static {};
    Code:
       0: new           #4                  // class org/sonatype/spice/zapper/internal/transport/State
       3: dup
       4: ldc           #7                  // String SUCCESS
       6: iconst_0
       7: invokespecial #8                  // Method "<init>":(Ljava/lang/String;I)V
      10: putstatic     #9                  // Field SUCCESS:Lorg/sonatype/spice/zapper/internal/transport/State;
      13: new           #4                  // class org/sonatype/spice/zapper/internal/transport/State
      16: dup
      17: ldc           #10                 // String FAILURE
      19: iconst_1
      20: invokespecial #8                  // Method "<init>":(Ljava/lang/String;I)V
      23: putstatic     #11                 // Field FAILURE:Lorg/sonatype/spice/zapper/internal/transport/State;
      26: iconst_2
      27: anewarray     #4                  // class org/sonatype/spice/zapper/internal/transport/State
      30: dup
      31: iconst_0
      32: getstatic     #9                  // Field SUCCESS:Lorg/sonatype/spice/zapper/internal/transport/State;
      35: aastore
      36: dup
      37: iconst_1
      38: getstatic     #11                 // Field FAILURE:Lorg/sonatype/spice/zapper/internal/transport/State;
      41: aastore
      42: putstatic     #1                  // Field $VALUES:[Lorg/sonatype/spice/zapper/internal/transport/State;
      45: return
}
