Compiled from "SearchResultsTableModel.java"
class org.protege.editor.owl.ui.search.SearchResultsTableModel$PlaceHolderRow extends org.protege.editor.owl.ui.search.SearchResultsTableModel$ResultsTableModelRow {
  final org.protege.editor.owl.ui.search.SearchResultsTableModel this$0;

  private org.protege.editor.owl.ui.search.SearchResultsTableModel$PlaceHolderRow(org.protege.editor.owl.ui.search.SearchResultsTableModel, int);
    Code:
       0: aload_0
       1: aload_1
       2: putfield      #2                  // Field this$0:Lorg/protege/editor/owl/ui/search/SearchResultsTableModel;
       5: aload_0
       6: aload_1
       7: aconst_null
       8: iconst_0
       9: iload_2
      10: aconst_null
      11: invokespecial #3                  // Method org/protege/editor/owl/ui/search/SearchResultsTableModel$ResultsTableModelRow."<init>":(Lorg/protege/editor/owl/ui/search/SearchResultsTableModel;Lorg/protege/editor/owl/model/search/SearchResult;IILorg/protege/editor/owl/ui/search/SearchResultsTableModel$1;)V
      14: return

  public boolean isFirstRowInCategory();
    Code:
       0: iconst_0
       1: ireturn

  public java.lang.Object getRenderableObject(int);
    Code:
       0: iload_1
       1: iconst_1
       2: if_icmpne     41
       5: new           #4                  // class java/lang/StringBuilder
       8: dup
       9: invokespecial #5                  // Method java/lang/StringBuilder."<init>":()V
      12: ldc           #6                  // String     +
      14: invokevirtual #7                  // Method java/lang/StringBuilder.append:(Ljava/lang/String;)Ljava/lang/StringBuilder;
      17: aload_0
      18: invokevirtual #8                  // Method getCategoryResultCount:()I
      21: aload_0
      22: getfield      #2                  // Field this$0:Lorg/protege/editor/owl/ui/search/SearchResultsTableModel;
      25: invokestatic  #9                  // Method org/protege/editor/owl/ui/search/SearchResultsTableModel.access$400:(Lorg/protege/editor/owl/ui/search/SearchResultsTableModel;)I
      28: isub
      29: invokevirtual #10                 // Method java/lang/StringBuilder.append:(I)Ljava/lang/StringBuilder;
      32: ldc           #11                 // String  more results...
      34: invokevirtual #7                  // Method java/lang/StringBuilder.append:(Ljava/lang/String;)Ljava/lang/StringBuilder;
      37: invokevirtual #12                 // Method java/lang/StringBuilder.toString:()Ljava/lang/String;
      40: areturn
      41: ldc           #13                 // String
      43: areturn

  org.protege.editor.owl.ui.search.SearchResultsTableModel$PlaceHolderRow(org.protege.editor.owl.ui.search.SearchResultsTableModel, int, org.protege.editor.owl.ui.search.SearchResultsTableModel$1);
    Code:
       0: aload_0
       1: aload_1
       2: iload_2
       3: invokespecial #1                  // Method "<init>":(Lorg/protege/editor/owl/ui/search/SearchResultsTableModel;I)V
       6: return
}
