Compiled from "SearchResultsPanel.java"
class org.protege.editor.owl.ui.search.SearchResultsPanel$EntityRenderer extends javax.swing.table.DefaultTableCellRenderer {
  private org.protege.editor.owl.ui.renderer.styledstring.StyledStringPanel styledStringPanel;

  final org.protege.editor.owl.ui.search.SearchResultsPanel this$0;

  private org.protege.editor.owl.ui.search.SearchResultsPanel$EntityRenderer(org.protege.editor.owl.ui.search.SearchResultsPanel);
    Code:
       0: aload_0
       1: aload_1
       2: putfield      #2                  // Field this$0:Lorg/protege/editor/owl/ui/search/SearchResultsPanel;
       5: aload_0
       6: invokespecial #3                  // Method javax/swing/table/DefaultTableCellRenderer."<init>":()V
       9: aload_0
      10: new           #4                  // class org/protege/editor/owl/ui/renderer/styledstring/StyledStringPanel
      13: dup
      14: invokespecial #5                  // Method org/protege/editor/owl/ui/renderer/styledstring/StyledStringPanel."<init>":()V
      17: putfield      #6                  // Field styledStringPanel:Lorg/protege/editor/owl/ui/renderer/styledstring/StyledStringPanel;
      20: return

  public java.awt.Component getTableCellRendererComponent(javax.swing.JTable, java.lang.Object, boolean, boolean, int, int);
    Code:
       0: aload_2
       1: instanceof    #7                  // class org/semanticweb/owlapi/model/OWLObject
       4: ifeq          364
       7: aload_2
       8: checkcast     #7                  // class org/semanticweb/owlapi/model/OWLObject
      11: astore        7
      13: new           #8                  // class org/protege/editor/owl/ui/renderer/context/OWLObjectRenderingContext
      16: dup
      17: new           #9                  // class org/protege/editor/owl/model/OWLEditorKitShortFormProvider
      20: dup
      21: aload_0
      22: getfield      #2                  // Field this$0:Lorg/protege/editor/owl/ui/search/SearchResultsPanel;
      25: invokestatic  #10                 // Method org/protege/editor/owl/ui/search/SearchResultsPanel.access$700:(Lorg/protege/editor/owl/ui/search/SearchResultsPanel;)Lorg/protege/editor/owl/OWLEditorKit;
      28: invokespecial #11                 // Method org/protege/editor/owl/model/OWLEditorKitShortFormProvider."<init>":(Lorg/protege/editor/owl/OWLEditorKit;)V
      31: new           #12                 // class org/protege/editor/owl/model/OWLEditorKitOntologyShortFormProvider
      34: dup
      35: aload_0
      36: getfield      #2                  // Field this$0:Lorg/protege/editor/owl/ui/search/SearchResultsPanel;
      39: invokestatic  #10                 // Method org/protege/editor/owl/ui/search/SearchResultsPanel.access$700:(Lorg/protege/editor/owl/ui/search/SearchResultsPanel;)Lorg/protege/editor/owl/OWLEditorKit;
      42: invokespecial #13                 // Method org/protege/editor/owl/model/OWLEditorKitOntologyShortFormProvider."<init>":(Lorg/protege/editor/owl/OWLEditorKit;)V
      45: invokespecial #14                 // Method org/protege/editor/owl/ui/renderer/context/OWLObjectRenderingContext."<init>":(Lorg/semanticweb/owlapi/util/ShortFormProvider;Lorg/semanticweb/owlapi/util/OntologyIRIShortFormProvider;)V
      48: astore        8
      50: new           #15                 // class org/protege/editor/owl/ui/renderer/styledstring/OWLObjectStyledStringRenderer
      53: dup
      54: aload         8
      56: invokespecial #16                 // Method org/protege/editor/owl/ui/renderer/styledstring/OWLObjectStyledStringRenderer."<init>":(Lorg/protege/editor/owl/ui/renderer/context/OWLObjectRenderingContext;)V
      59: astore        9
      61: aload         9
      63: aload         7
      65: invokevirtual #17                 // Method org/protege/editor/owl/ui/renderer/styledstring/OWLObjectStyledStringRenderer.getRendering:(Lorg/semanticweb/owlapi/model/OWLObject;)Lorg/protege/editor/owl/ui/renderer/styledstring/StyledString;
      68: astore        10
      70: aload         10
      72: invokevirtual #18                 // Method org/protege/editor/owl/ui/renderer/styledstring/StyledString.builder:()Lorg/protege/editor/owl/ui/renderer/styledstring/StyledString$Builder;
      75: astore        11
      77: aload_0
      78: getfield      #2                  // Field this$0:Lorg/protege/editor/owl/ui/search/SearchResultsPanel;
      81: invokestatic  #19                 // Method org/protege/editor/owl/ui/search/SearchResultsPanel.access$600:(Lorg/protege/editor/owl/ui/search/SearchResultsPanel;)Lorg/protege/editor/owl/ui/search/SearchResultsTableModel;
      84: iload         5
      86: invokevirtual #20                 // Method org/protege/editor/owl/ui/search/SearchResultsTableModel.getSearchResult:(I)Lorg/protege/editor/owl/model/search/SearchResult;
      89: astore        12
      91: aload         12
      93: invokevirtual #21                 // Method org/protege/editor/owl/model/search/SearchResult.getCategory:()Lorg/protege/editor/owl/model/search/SearchCategory;
      96: getstatic     #22                 // Field org/protege/editor/owl/model/search/SearchCategory.DISPLAY_NAME:Lorg/protege/editor/owl/model/search/SearchCategory;
      99: if_acmpne     170
     102: aload         12
     104: invokevirtual #23                 // Method org/protege/editor/owl/model/search/SearchResult.getMatches:()Lcom/google/common/collect/ImmutableList;
     107: invokevirtual #24                 // Method com/google/common/collect/ImmutableList.iterator:()Lcom/google/common/collect/UnmodifiableIterator;
     110: astore        13
     112: aload         13
     114: invokeinterface #25,  1           // InterfaceMethod java/util/Iterator.hasNext:()Z
     119: ifeq          170
     122: aload         13
     124: invokeinterface #26,  1           // InterfaceMethod java/util/Iterator.next:()Ljava/lang/Object;
     129: checkcast     #27                 // class org/protege/editor/owl/model/search/SearchResultMatch
     132: astore        14
     134: aload         14
     136: invokevirtual #28                 // Method org/protege/editor/owl/model/search/SearchResultMatch.getStart:()I
     139: istore        15
     141: aload         14
     143: invokevirtual #29                 // Method org/protege/editor/owl/model/search/SearchResultMatch.getEnd:()I
     146: istore        16
     148: aload         11
     150: iload         15
     152: iload         16
     154: iconst_1
     155: anewarray     #30                 // class org/protege/editor/owl/ui/renderer/styledstring/StyleAttribute
     158: dup
     159: iconst_0
     160: invokestatic  #31                 // Method org/protege/editor/owl/ui/renderer/styledstring/FontWeightAttribute.getBoldFontWeight:()Lorg/protege/editor/owl/ui/renderer/styledstring/FontWeightAttribute;
     163: aastore
     164: invokevirtual #32                 // Method org/protege/editor/owl/ui/renderer/styledstring/StyledString$Builder.applyStyleAttributes:(II[Lorg/protege/editor/owl/ui/renderer/styledstring/StyleAttribute;)V
     167: goto          112
     170: aload_0
     171: getfield      #2                  // Field this$0:Lorg/protege/editor/owl/ui/search/SearchResultsPanel;
     174: invokestatic  #10                 // Method org/protege/editor/owl/ui/search/SearchResultsPanel.access$700:(Lorg/protege/editor/owl/ui/search/SearchResultsPanel;)Lorg/protege/editor/owl/OWLEditorKit;
     177: invokevirtual #33                 // Method org/protege/editor/owl/OWLEditorKit.getOWLModelManager:()Lorg/protege/editor/owl/model/OWLModelManager;
     180: aload         7
     182: invokeinterface #34,  2           // InterfaceMethod org/protege/editor/owl/model/OWLModelManager.isDeprecated:(Lorg/semanticweb/owlapi/model/OWLObject;)Z
     187: ifeq          205
     190: aload         11
     192: iconst_1
     193: anewarray     #30                 // class org/protege/editor/owl/ui/renderer/styledstring/StyleAttribute
     196: dup
     197: iconst_0
     198: invokestatic  #35                 // Method org/protege/editor/owl/ui/renderer/styledstring/StrikeThroughAttribute.getSingle:()Lorg/protege/editor/owl/ui/renderer/styledstring/StrikeThroughAttribute;
     201: aastore
     202: invokevirtual #36                 // Method org/protege/editor/owl/ui/renderer/styledstring/StyledString$Builder.applyStyleAttributes:([Lorg/protege/editor/owl/ui/renderer/styledstring/StyleAttribute;)V
     205: iload_3
     206: ifeq          272
     209: aload_0
     210: getfield      #6                  // Field styledStringPanel:Lorg/protege/editor/owl/ui/renderer/styledstring/StyledStringPanel;
     213: iconst_0
     214: iconst_0
     215: iconst_0
     216: bipush        10
     218: aload_1
     219: invokevirtual #37                 // Method javax/swing/JTable.getSelectionBackground:()Ljava/awt/Color;
     222: invokestatic  #38                 // Method javax/swing/BorderFactory.createMatteBorder:(IIIILjava/awt/Color;)Ljavax/swing/border/MatteBorder;
     225: invokevirtual #39                 // Method org/protege/editor/owl/ui/renderer/styledstring/StyledStringPanel.setBorder:(Ljavax/swing/border/Border;)V
     228: aload_0
     229: getfield      #6                  // Field styledStringPanel:Lorg/protege/editor/owl/ui/renderer/styledstring/StyledStringPanel;
     232: aload_1
     233: invokevirtual #40                 // Method javax/swing/JTable.getSelectionForeground:()Ljava/awt/Color;
     236: invokevirtual #41                 // Method org/protege/editor/owl/ui/renderer/styledstring/StyledStringPanel.setForeground:(Ljava/awt/Color;)V
     239: aload_0
     240: getfield      #6                  // Field styledStringPanel:Lorg/protege/editor/owl/ui/renderer/styledstring/StyledStringPanel;
     243: aload_1
     244: invokevirtual #37                 // Method javax/swing/JTable.getSelectionBackground:()Ljava/awt/Color;
     247: invokevirtual #42                 // Method org/protege/editor/owl/ui/renderer/styledstring/StyledStringPanel.setBackground:(Ljava/awt/Color;)V
     250: aload         11
     252: iconst_1
     253: anewarray     #30                 // class org/protege/editor/owl/ui/renderer/styledstring/StyleAttribute
     256: dup
     257: iconst_0
     258: aload_1
     259: invokevirtual #40                 // Method javax/swing/JTable.getSelectionForeground:()Ljava/awt/Color;
     262: invokestatic  #43                 // Method org/protege/editor/owl/ui/renderer/styledstring/ForegroundAttribute.get:(Ljava/awt/Color;)Lorg/protege/editor/owl/ui/renderer/styledstring/ForegroundAttribute;
     265: aastore
     266: invokevirtual #36                 // Method org/protege/editor/owl/ui/renderer/styledstring/StyledString$Builder.applyStyleAttributes:([Lorg/protege/editor/owl/ui/renderer/styledstring/StyleAttribute;)V
     269: goto          307
     272: aload_0
     273: getfield      #6                  // Field styledStringPanel:Lorg/protege/editor/owl/ui/renderer/styledstring/StyledStringPanel;
     276: iconst_0
     277: iconst_0
     278: iconst_0
     279: bipush        10
     281: aload_1
     282: invokevirtual #44                 // Method javax/swing/JTable.getBackground:()Ljava/awt/Color;
     285: invokestatic  #38                 // Method javax/swing/BorderFactory.createMatteBorder:(IIIILjava/awt/Color;)Ljavax/swing/border/MatteBorder;
     288: invokevirtual #39                 // Method org/protege/editor/owl/ui/renderer/styledstring/StyledStringPanel.setBorder:(Ljavax/swing/border/Border;)V
     291: aload_0
     292: getfield      #6                  // Field styledStringPanel:Lorg/protege/editor/owl/ui/renderer/styledstring/StyledStringPanel;
     295: aconst_null
     296: invokevirtual #41                 // Method org/protege/editor/owl/ui/renderer/styledstring/StyledStringPanel.setForeground:(Ljava/awt/Color;)V
     299: aload_0
     300: getfield      #6                  // Field styledStringPanel:Lorg/protege/editor/owl/ui/renderer/styledstring/StyledStringPanel;
     303: aconst_null
     304: invokevirtual #42                 // Method org/protege/editor/owl/ui/renderer/styledstring/StyledStringPanel.setBackground:(Ljava/awt/Color;)V
     307: aload_0
     308: getfield      #6                  // Field styledStringPanel:Lorg/protege/editor/owl/ui/renderer/styledstring/StyledStringPanel;
     311: aload         11
     313: invokevirtual #45                 // Method org/protege/editor/owl/ui/renderer/styledstring/StyledString$Builder.build:()Lorg/protege/editor/owl/ui/renderer/styledstring/StyledString;
     316: invokevirtual #46                 // Method org/protege/editor/owl/ui/renderer/styledstring/StyledStringPanel.setStyledString:(Lorg/protege/editor/owl/ui/renderer/styledstring/StyledString;)V
     319: aload_0
     320: getfield      #6                  // Field styledStringPanel:Lorg/protege/editor/owl/ui/renderer/styledstring/StyledStringPanel;
     323: invokestatic  #47                 // Method org/protege/editor/owl/ui/renderer/OWLRendererPreferences.getInstance:()Lorg/protege/editor/owl/ui/renderer/OWLRendererPreferences;
     326: invokevirtual #48                 // Method org/protege/editor/owl/ui/renderer/OWLRendererPreferences.getFont:()Ljava/awt/Font;
     329: invokevirtual #49                 // Method org/protege/editor/owl/ui/renderer/styledstring/StyledStringPanel.setFont:(Ljava/awt/Font;)V
     332: aload_0
     333: getfield      #6                  // Field styledStringPanel:Lorg/protege/editor/owl/ui/renderer/styledstring/StyledStringPanel;
     336: aload_0
     337: getfield      #2                  // Field this$0:Lorg/protege/editor/owl/ui/search/SearchResultsPanel;
     340: invokestatic  #10                 // Method org/protege/editor/owl/ui/search/SearchResultsPanel.access$700:(Lorg/protege/editor/owl/ui/search/SearchResultsPanel;)Lorg/protege/editor/owl/OWLEditorKit;
     343: invokevirtual #50                 // Method org/protege/editor/owl/OWLEditorKit.getOWLWorkspace:()Lorg/protege/editor/owl/model/OWLWorkspace;
     346: invokevirtual #51                 // Method org/protege/editor/owl/model/OWLWorkspace.getOWLIconProvider:()Lorg/protege/editor/owl/ui/renderer/OWLIconProvider;
     349: aload         7
     351: invokeinterface #52,  2           // InterfaceMethod org/protege/editor/owl/ui/renderer/OWLIconProvider.getIcon:(Lorg/semanticweb/owlapi/model/OWLObject;)Ljavax/swing/Icon;
     356: invokevirtual #53                 // Method org/protege/editor/owl/ui/renderer/styledstring/StyledStringPanel.setIcon:(Ljavax/swing/Icon;)V
     359: aload_0
     360: getfield      #6                  // Field styledStringPanel:Lorg/protege/editor/owl/ui/renderer/styledstring/StyledStringPanel;
     363: areturn
     364: aload_0
     365: aload_1
     366: aload_2
     367: iload_3
     368: iload         4
     370: iload         5
     372: iload         6
     374: invokespecial #54                 // Method javax/swing/table/DefaultTableCellRenderer.getTableCellRendererComponent:(Ljavax/swing/JTable;Ljava/lang/Object;ZZII)Ljava/awt/Component;
     377: checkcast     #55                 // class javax/swing/JLabel
     380: astore        7
     382: aload         7
     384: aconst_null
     385: invokevirtual #56                 // Method javax/swing/JLabel.setIcon:(Ljavax/swing/Icon;)V
     388: iload_3
     389: ifne          400
     392: aload         7
     394: getstatic     #57                 // Field java/awt/Color.LIGHT_GRAY:Ljava/awt/Color;
     397: invokevirtual #58                 // Method javax/swing/JLabel.setForeground:(Ljava/awt/Color;)V
     400: aload         7
     402: areturn

  org.protege.editor.owl.ui.search.SearchResultsPanel$EntityRenderer(org.protege.editor.owl.ui.search.SearchResultsPanel, org.protege.editor.owl.ui.search.SearchResultsPanel$1);
    Code:
       0: aload_0
       1: aload_1
       2: invokespecial #1                  // Method "<init>":(Lorg/protege/editor/owl/ui/search/SearchResultsPanel;)V
       5: return
}
