Compiled from "SearchOptionsPanel.java"
class org.protege.editor.owl.ui.search.SearchOptionsPanel$2 extends javax.swing.AbstractAction {
  final org.protege.editor.owl.ui.search.SearchOptionsPanel this$0;

  org.protege.editor.owl.ui.search.SearchOptionsPanel$2(org.protege.editor.owl.ui.search.SearchOptionsPanel, java.lang.String);
    Code:
       0: aload_0
       1: aload_1
       2: putfield      #1                  // Field this$0:Lorg/protege/editor/owl/ui/search/SearchOptionsPanel;
       5: aload_0
       6: aload_2
       7: invokespecial #2                  // Method javax/swing/AbstractAction."<init>":(Ljava/lang/String;)V
      10: return

  public void actionPerformed(java.awt.event.ActionEvent);
    Code:
       0: invokestatic  #3                  // Method org/protege/editor/owl/model/find/OWLEntityFinderPreferences.getInstance:()Lorg/protege/editor/owl/model/find/OWLEntityFinderPreferences;
       3: aload_0
       4: getfield      #1                  // Field this$0:Lorg/protege/editor/owl/ui/search/SearchOptionsPanel;
       7: invokestatic  #4                  // Method org/protege/editor/owl/ui/search/SearchOptionsPanel.access$200:(Lorg/protege/editor/owl/ui/search/SearchOptionsPanel;)Ljavax/swing/JCheckBox;
      10: invokevirtual #5                  // Method javax/swing/JCheckBox.isSelected:()Z
      13: invokevirtual #6                  // Method org/protege/editor/owl/model/find/OWLEntityFinderPreferences.setCaseSensitive:(Z)V
      16: aload_0
      17: getfield      #1                  // Field this$0:Lorg/protege/editor/owl/ui/search/SearchOptionsPanel;
      20: invokestatic  #7                  // Method org/protege/editor/owl/ui/search/SearchOptionsPanel.access$300:(Lorg/protege/editor/owl/ui/search/SearchOptionsPanel;)V
      23: return
}
