Compiled from "MinValidatorForFloat.java"
public class org.hibernate.validator.internal.constraintvalidators.bv.number.bound.MinValidatorForFloat extends org.hibernate.validator.internal.constraintvalidators.bv.number.bound.AbstractMinValidator<java.lang.Float> {
  public org.hibernate.validator.internal.constraintvalidators.bv.number.bound.MinValidatorForFloat();
    Code:
       0: aload_0
       1: invokespecial #1                  // Method org/hibernate/validator/internal/constraintvalidators/bv/number/bound/AbstractMinValidator."<init>":()V
       4: return

  protected int compare(java.lang.Float);
    Code:
       0: aload_1
       1: aload_0
       2: getfield      #2                  // Field minValue:J
       5: getstatic     #3                  // Field org/hibernate/validator/internal/constraintvalidators/bv/number/InfinityNumberComparatorHelper.LESS_THAN:Ljava/util/OptionalInt;
       8: invokestatic  #4                  // Method org/hibernate/validator/internal/constraintvalidators/bv/number/bound/NumberComparatorHelper.compare:(Ljava/lang/Float;JLjava/util/OptionalInt;)I
      11: ireturn

  protected int compare(java.lang.Object);
    Code:
       0: aload_0
       1: aload_1
       2: checkcast     #5                  // class java/lang/Float
       5: invokevirtual #6                  // Method compare:(Ljava/lang/Float;)I
       8: ireturn
}
