Compiled from "SSLConfig.kt"
final class kweb.https.SSLConfig$1 extends kotlin.jvm.internal.Lambda implements kotlin.jvm.functions.Function0<char[]> {
  public static final kweb.https.SSLConfig$1 INSTANCE;

  kweb.https.SSLConfig$1();
    Code:
       0: aload_0
       1: iconst_0
       2: invokespecial #12                 // Method kotlin/jvm/internal/Lambda."<init>":(I)V
       5: return

  public final char[] invoke();
    Code:
       0: ldc           #19                 // String changeit
       2: invokevirtual #24                 // Method java/lang/String.toCharArray:()[C
       5: dup
       6: ldc           #26                 // String this as java.lang.String).toCharArray()
       8: invokestatic  #32                 // Method kotlin/jvm/internal/Intrinsics.checkNotNullExpressionValue:(Ljava/lang/Object;Ljava/lang/String;)V
      11: areturn

  public java.lang.Object invoke();
    Code:
       0: aload_0
       1: invokevirtual #35                 // Method invoke:()[C
       4: areturn

  static {};
    Code:
       0: new           #2                  // class kweb/https/SSLConfig$1
       3: dup
       4: invokespecial #38                 // Method "<init>":()V
       7: putstatic     #41                 // Field INSTANCE:Lkweb/https/SSLConfig$1;
      10: return
}
