Compiled from "AnonymousBackendTask.java"
public class net.serenitybdd.screenplay.AnonymousBackendTask extends net.serenitybdd.screenplay.AnonymousTask implements net.serenitybdd.markers.DisableScreenshots {
  public net.serenitybdd.screenplay.AnonymousBackendTask();
    Code:
       0: aload_0
       1: invokespecial #1                  // Method net/serenitybdd/screenplay/AnonymousTask."<init>":()V
       4: return

  public net.serenitybdd.screenplay.AnonymousBackendTask(java.lang.String, java.util.List<net.serenitybdd.screenplay.Performable>);
    Code:
       0: aload_0
       1: aload_1
       2: aload_2
       3: invokespecial #2                  // Method net/serenitybdd/screenplay/AnonymousTask."<init>":(Ljava/lang/String;Ljava/util/List;)V
       6: return
}
