Compiled from "KVar.kt"
final class kweb.state.KVarKt$combine$listener2$1 extends kotlin.jvm.internal.Lambda implements kotlin.jvm.functions.Function2<B, B, kotlin.Unit> {
  final kweb.state.KVar<kotlin.Pair<A, B>> $newKVar;

  final kotlin.Pair<kweb.state.KVar<A>, kweb.state.KVar<B>> $this_combine;

  kweb.state.KVarKt$combine$listener2$1(kweb.state.KVar<kotlin.Pair<A, B>>, kotlin.Pair<kweb.state.KVar<A>, kweb.state.KVar<B>>);
    Code:
       0: aload_0
       1: aload_1
       2: putfield      #14                 // Field $newKVar:Lkweb/state/KVar;
       5: aload_0
       6: aload_2
       7: putfield      #18                 // Field $this_combine:Lkotlin/Pair;
      10: aload_0
      11: iconst_2
      12: invokespecial #21                 // Method kotlin/jvm/internal/Lambda."<init>":(I)V
      15: return

  public final void invoke(B, B);
    Code:
       0: aload_0
       1: getfield      #14                 // Field $newKVar:Lkweb/state/KVar;
       4: aload_0
       5: getfield      #18                 // Field $this_combine:Lkotlin/Pair;
       8: invokevirtual #33                 // Method kotlin/Pair.getFirst:()Ljava/lang/Object;
      11: checkcast     #35                 // class kweb/state/KVar
      14: invokevirtual #38                 // Method kweb/state/KVar.getValue:()Ljava/lang/Object;
      17: aload_2
      18: invokestatic  #44                 // Method kotlin/TuplesKt.to:(Ljava/lang/Object;Ljava/lang/Object;)Lkotlin/Pair;
      21: invokevirtual #48                 // Method kweb/state/KVar.setValue:(Ljava/lang/Object;)V
      24: return

  public java.lang.Object invoke(java.lang.Object, java.lang.Object);
    Code:
       0: aload_0
       1: aload_1
       2: aload_2
       3: invokevirtual #53                 // Method invoke:(Ljava/lang/Object;Ljava/lang/Object;)V
       6: getstatic     #59                 // Field kotlin/Unit.INSTANCE:Lkotlin/Unit;
       9: areturn
}
