Compiled from "render.kt"
public final class kweb.state.RenderFragment {
  private final java.lang.String startId;

  private final java.lang.String endId;

  private final java.util.ArrayList<kotlin.jvm.functions.Function0<kotlin.Unit>> deletionListeners;

  public kweb.state.RenderFragment(java.lang.String, java.lang.String);
    Code:
       0: aload_1
       1: ldc           #9                  // String startId
       3: invokestatic  #15                 // Method kotlin/jvm/internal/Intrinsics.checkNotNullParameter:(Ljava/lang/Object;Ljava/lang/String;)V
       6: aload_2
       7: ldc           #17                 // String endId
       9: invokestatic  #15                 // Method kotlin/jvm/internal/Intrinsics.checkNotNullParameter:(Ljava/lang/Object;Ljava/lang/String;)V
      12: aload_0
      13: invokespecial #20                 // Method java/lang/Object."<init>":()V
      16: aload_0
      17: aload_1
      18: putfield      #23                 // Field startId:Ljava/lang/String;
      21: aload_0
      22: aload_2
      23: putfield      #25                 // Field endId:Ljava/lang/String;
      26: aload_0
      27: new           #27                 // class java/util/ArrayList
      30: dup
      31: invokespecial #28                 // Method java/util/ArrayList."<init>":()V
      34: putfield      #32                 // Field deletionListeners:Ljava/util/ArrayList;
      37: return

  public final java.lang.String getStartId();
    Code:
       0: aload_0
       1: getfield      #23                 // Field startId:Ljava/lang/String;
       4: areturn

  public final java.lang.String getEndId();
    Code:
       0: aload_0
       1: getfield      #25                 // Field endId:Ljava/lang/String;
       4: areturn

  public final void addDeletionListener$kweb_core(kotlin.jvm.functions.Function0<kotlin.Unit>);
    Code:
       0: aload_1
       1: ldc           #42                 // String listener
       3: invokestatic  #15                 // Method kotlin/jvm/internal/Intrinsics.checkNotNullParameter:(Ljava/lang/Object;Ljava/lang/String;)V
       6: aload_0
       7: getfield      #32                 // Field deletionListeners:Ljava/util/ArrayList;
      10: astore_2
      11: aload_2
      12: monitorenter
      13: nop
      14: iconst_0
      15: istore_3
      16: aload_0
      17: getfield      #32                 // Field deletionListeners:Ljava/util/ArrayList;
      20: checkcast     #44                 // class java/util/Collection
      23: aload_1
      24: invokeinterface #48,  2           // InterfaceMethod java/util/Collection.add:(Ljava/lang/Object;)Z
      29: pop
      30: nop
      31: getstatic     #54                 // Field kotlin/Unit.INSTANCE:Lkotlin/Unit;
      34: astore_3
      35: aload_2
      36: monitorexit
      37: goto          45
      40: astore_3
      41: aload_2
      42: monitorexit
      43: aload_3
      44: athrow
      45: return
    Exception table:
       from    to  target type
          13    35    40   any
          40    41    40   any

  public final void delete();
    Code:
       0: aload_0
       1: getfield      #32                 // Field deletionListeners:Ljava/util/ArrayList;
       4: astore_1
       5: aload_1
       6: monitorenter
       7: nop
       8: iconst_0
       9: istore_2
      10: aload_0
      11: getfield      #32                 // Field deletionListeners:Ljava/util/ArrayList;
      14: checkcast     #64                 // class java/lang/Iterable
      17: astore_3
      18: iconst_0
      19: istore        4
      21: aload_3
      22: invokeinterface #68,  1           // InterfaceMethod java/lang/Iterable.iterator:()Ljava/util/Iterator;
      27: astore        5
      29: aload         5
      31: invokeinterface #74,  1           // InterfaceMethod java/util/Iterator.hasNext:()Z
      36: ifeq          70
      39: aload         5
      41: invokeinterface #78,  1           // InterfaceMethod java/util/Iterator.next:()Ljava/lang/Object;
      46: astore        6
      48: aload         6
      50: checkcast     #59                 // class kotlin/jvm/functions/Function0
      53: astore        7
      55: iconst_0
      56: istore        8
      58: aload         7
      60: invokeinterface #81,  1           // InterfaceMethod kotlin/jvm/functions/Function0.invoke:()Ljava/lang/Object;
      65: pop
      66: nop
      67: goto          29
      70: nop
      71: nop
      72: getstatic     #54                 // Field kotlin/Unit.INSTANCE:Lkotlin/Unit;
      75: astore_2
      76: aload_1
      77: monitorexit
      78: goto          86
      81: astore_2
      82: aload_1
      83: monitorexit
      84: aload_2
      85: athrow
      86: return
    Exception table:
       from    to  target type
           7    76    81   any
          81    82    81   any
}
