Compiled from "LoadGraphLoadPlanBuildingStrategy.java"
public class org.hibernate.loader.plan.build.internal.LoadGraphLoadPlanBuildingStrategy extends org.hibernate.loader.plan.build.internal.AbstractEntityGraphVisitationStrategy {
  private final org.hibernate.graph.spi.GraphNodeImplementor rootEntityGraph;

  public org.hibernate.loader.plan.build.internal.LoadGraphLoadPlanBuildingStrategy(org.hibernate.engine.spi.SessionFactoryImplementor, org.hibernate.engine.spi.LoadQueryInfluencers, org.hibernate.LockMode);
    Code:
       0: aload_0
       1: aload_1
       2: aload_2
       3: aload_3
       4: invokespecial #1                  // Method org/hibernate/loader/plan/build/internal/AbstractEntityGraphVisitationStrategy."<init>":(Lorg/hibernate/engine/spi/SessionFactoryImplementor;Lorg/hibernate/engine/spi/LoadQueryInfluencers;Lorg/hibernate/LockMode;)V
       7: aload_0
       8: aload_2
       9: invokevirtual #2                  // Method org/hibernate/engine/spi/LoadQueryInfluencers.getLoadGraph:()Ljavax/persistence/EntityGraph;
      12: checkcast     #3                  // class org/hibernate/graph/spi/GraphNodeImplementor
      15: putfield      #4                  // Field rootEntityGraph:Lorg/hibernate/graph/spi/GraphNodeImplementor;
      18: return

  protected org.hibernate.graph.spi.GraphNodeImplementor getRootEntityGraph();
    Code:
       0: aload_0
       1: getfield      #4                  // Field rootEntityGraph:Lorg/hibernate/graph/spi/GraphNodeImplementor;
       4: areturn

  protected org.hibernate.engine.FetchStrategy resolveImplicitFetchStrategyFromEntityGraph(org.hibernate.persister.walking.spi.AssociationAttributeDefinition);
    Code:
       0: aload_1
       1: aload_0
       2: getfield      #5                  // Field loadQueryInfluencers:Lorg/hibernate/engine/spi/LoadQueryInfluencers;
       5: aload_0
       6: getfield      #6                  // Field currentPropertyPath:Lorg/hibernate/loader/PropertyPath;
       9: invokeinterface #7,  3            // InterfaceMethod org/hibernate/persister/walking/spi/AssociationAttributeDefinition.determineFetchPlan:(Lorg/hibernate/engine/spi/LoadQueryInfluencers;Lorg/hibernate/loader/PropertyPath;)Lorg/hibernate/engine/FetchStrategy;
      14: astore_2
      15: aload_2
      16: invokevirtual #8                  // Method org/hibernate/engine/FetchStrategy.getTiming:()Lorg/hibernate/engine/FetchTiming;
      19: getstatic     #9                  // Field org/hibernate/engine/FetchTiming.IMMEDIATE:Lorg/hibernate/engine/FetchTiming;
      22: if_acmpne     42
      25: aload_2
      26: invokevirtual #10                 // Method org/hibernate/engine/FetchStrategy.getStyle:()Lorg/hibernate/engine/FetchStyle;
      29: getstatic     #11                 // Field org/hibernate/engine/FetchStyle.JOIN:Lorg/hibernate/engine/FetchStyle;
      32: if_acmpne     42
      35: aload_0
      36: aload_1
      37: aload_2
      38: invokevirtual #12                 // Method adjustJoinFetchIfNeeded:(Lorg/hibernate/persister/walking/spi/AssociationAttributeDefinition;Lorg/hibernate/engine/FetchStrategy;)Lorg/hibernate/engine/FetchStrategy;
      41: astore_2
      42: aload_2
      43: areturn
}
