Compiled from "TomcatEmbeddedServletContainerFactory.java"
class org.springframework.boot.context.embedded.tomcat.TomcatEmbeddedServletContainerFactory$1 implements org.apache.catalina.LifecycleListener {
  final org.springframework.boot.context.embedded.tomcat.TomcatEmbeddedContext val$context;

  final org.springframework.boot.context.embedded.tomcat.TomcatEmbeddedServletContainerFactory this$0;

  org.springframework.boot.context.embedded.tomcat.TomcatEmbeddedServletContainerFactory$1(org.springframework.boot.context.embedded.tomcat.TomcatEmbeddedServletContainerFactory, org.springframework.boot.context.embedded.tomcat.TomcatEmbeddedContext);
    Code:
       0: aload_0
       1: aload_1
       2: putfield      #1                  // Field this$0:Lorg/springframework/boot/context/embedded/tomcat/TomcatEmbeddedServletContainerFactory;
       5: aload_0
       6: aload_2
       7: putfield      #2                  // Field val$context:Lorg/springframework/boot/context/embedded/tomcat/TomcatEmbeddedContext;
      10: aload_0
      11: invokespecial #3                  // Method java/lang/Object."<init>":()V
      14: return

  public void lifecycleEvent(org.apache.catalina.LifecycleEvent);
    Code:
       0: aload_1
       1: invokevirtual #4                  // Method org/apache/catalina/LifecycleEvent.getType:()Ljava/lang/String;
       4: ldc           #6                  // String configure_start
       6: invokevirtual #7                  // Method java/lang/String.equals:(Ljava/lang/Object;)Z
       9: ifeq          29
      12: aload_0
      13: getfield      #2                  // Field val$context:Lorg/springframework/boot/context/embedded/tomcat/TomcatEmbeddedContext;
      16: invokestatic  #8                  // Method org/springframework/boot/context/embedded/tomcat/TomcatResources.get:(Lorg/apache/catalina/Context;)Lorg/springframework/boot/context/embedded/tomcat/TomcatResources;
      19: aload_0
      20: getfield      #1                  // Field this$0:Lorg/springframework/boot/context/embedded/tomcat/TomcatEmbeddedServletContainerFactory;
      23: invokestatic  #9                  // Method org/springframework/boot/context/embedded/tomcat/TomcatEmbeddedServletContainerFactory.access$100:(Lorg/springframework/boot/context/embedded/tomcat/TomcatEmbeddedServletContainerFactory;)Ljava/util/List;
      26: invokevirtual #10                 // Method org/springframework/boot/context/embedded/tomcat/TomcatResources.addResourceJars:(Ljava/util/List;)V
      29: return
}
