Compiled from "CrossFadeSupport.scala"
public final class io.youi.app.screen.CrossFadeSupport$$anonfun$4 extends scala.runtime.AbstractFunction0$mcD$sp implements scala.Serializable {
  public static final long serialVersionUID;

  public final double apply();
    Code:
       0: aload_0
       1: invokevirtual #21                 // Method apply$mcD$sp:()D
       4: dreturn

  public double apply$mcD$sp();
    Code:
       0: dconst_1
       1: dreturn

  public final java.lang.Object apply();
    Code:
       0: aload_0
       1: invokevirtual #26                 // Method apply:()D
       4: invokestatic  #32                 // Method scala/runtime/BoxesRunTime.boxToDouble:(D)Ljava/lang/Double;
       7: areturn

  public io.youi.app.screen.CrossFadeSupport$$anonfun$4(io.youi.app.screen.CrossFadeSupport);
    Code:
       0: aload_0
       1: invokespecial #37                 // Method scala/runtime/AbstractFunction0$mcD$sp."<init>":()V
       4: return
}
