Compiled from "ScreenManager.scala"
public final class io.youi.app.screen.EmptyScreen$ implements io.youi.app.screen.Screen {
  public static final io.youi.app.screen.EmptyScreen$ MODULE$;

  private final reactify.Var<io.youi.app.screen.ScreenState> currentState;

  private final reactify.Val<io.youi.app.screen.ScreenState> state;

  public static {};
    Code:
       0: new           #2                  // class io/youi/app/screen/EmptyScreen$
       3: invokespecial #14                 // Method "<init>":()V
       6: return

  public reactify.Var<io.youi.app.screen.ScreenState> currentState();
    Code:
       0: aload_0
       1: getfield      #23                 // Field currentState:Lreactify/Var;
       4: areturn

  public reactify.Val<io.youi.app.screen.ScreenState> state();
    Code:
       0: aload_0
       1: getfield      #27                 // Field state:Lreactify/Val;
       4: areturn

  public void io$youi$app$screen$Screen$_setter_$currentState_$eq(reactify.Var);
    Code:
       0: aload_0
       1: aload_1
       2: putfield      #23                 // Field currentState:Lreactify/Var;
       5: return

  public void io$youi$app$screen$Screen$_setter_$state_$eq(reactify.Val);
    Code:
       0: aload_0
       1: aload_1
       2: putfield      #27                 // Field state:Lreactify/Val;
       5: return

  public java.lang.String title();
    Code:
       0: aload_0
       1: invokestatic  #39                 // Method io/youi/app/screen/Screen$class.title:(Lio/youi/app/screen/Screen;)Ljava/lang/String;
       4: areturn

  public scala.concurrent.Future<scala.runtime.BoxedUnit> init();
    Code:
       0: aload_0
       1: invokestatic  #44                 // Method io/youi/app/screen/Screen$class.init:(Lio/youi/app/screen/Screen;)Lscala/concurrent/Future;
       4: areturn

  public scala.concurrent.Future<scala.runtime.BoxedUnit> load();
    Code:
       0: aload_0
       1: invokestatic  #47                 // Method io/youi/app/screen/Screen$class.load:(Lio/youi/app/screen/Screen;)Lscala/concurrent/Future;
       4: areturn

  public scala.concurrent.Future<scala.runtime.BoxedUnit> activate();
    Code:
       0: aload_0
       1: invokestatic  #50                 // Method io/youi/app/screen/Screen$class.activate:(Lio/youi/app/screen/Screen;)Lscala/concurrent/Future;
       4: areturn

  public scala.concurrent.Future<scala.runtime.BoxedUnit> deactivate();
    Code:
       0: aload_0
       1: invokestatic  #53                 // Method io/youi/app/screen/Screen$class.deactivate:(Lio/youi/app/screen/Screen;)Lscala/concurrent/Future;
       4: areturn

  public scala.concurrent.Future<scala.runtime.BoxedUnit> dispose();
    Code:
       0: aload_0
       1: invokestatic  #56                 // Method io/youi/app/screen/Screen$class.dispose:(Lio/youi/app/screen/Screen;)Lscala/concurrent/Future;
       4: areturn

  private io.youi.app.screen.EmptyScreen$();
    Code:
       0: aload_0
       1: invokespecial #57                 // Method java/lang/Object."<init>":()V
       4: aload_0
       5: putstatic     #59                 // Field MODULE$:Lio/youi/app/screen/EmptyScreen$;
       8: aload_0
       9: invokestatic  #63                 // Method io/youi/app/screen/Screen$class.$init$:(Lio/youi/app/screen/Screen;)V
      12: return
}
