Compiled from "LoadingTransitionSupport.scala"
public abstract class io.youi.app.screen.LoadingTransitionSupport$class {
  public static scala.concurrent.Future beforeScreenChange(io.youi.app.screen.LoadingTransitionSupport, io.youi.app.screen.Screen, io.youi.app.screen.Screen);
    Code:
       0: getstatic     #13                 // Field scala/concurrent/Future$.MODULE$:Lscala/concurrent/Future$;
       3: new           #15                 // class io/youi/app/screen/LoadingTransitionSupport$$anonfun$beforeScreenChange$1
       6: dup
       7: aload_0
       8: invokespecial #19                 // Method io/youi/app/screen/LoadingTransitionSupport$$anonfun$beforeScreenChange$1."<init>":(Lio/youi/app/screen/LoadingTransitionSupport;)V
      11: getstatic     #24                 // Field scala/concurrent/ExecutionContext$Implicits$.MODULE$:Lscala/concurrent/ExecutionContext$Implicits$;
      14: invokevirtual #28                 // Method scala/concurrent/ExecutionContext$Implicits$.global:()Lscala/concurrent/ExecutionContextExecutor;
      17: invokevirtual #32                 // Method scala/concurrent/Future$.apply:(Lscala/Function0;Lscala/concurrent/ExecutionContext;)Lscala/concurrent/Future;
      20: areturn

  public static scala.concurrent.Future afterScreenChange(io.youi.app.screen.LoadingTransitionSupport, io.youi.app.screen.Screen, io.youi.app.screen.Screen);
    Code:
       0: getstatic     #13                 // Field scala/concurrent/Future$.MODULE$:Lscala/concurrent/Future$;
       3: new           #40                 // class io/youi/app/screen/LoadingTransitionSupport$$anonfun$afterScreenChange$1
       6: dup
       7: aload_0
       8: invokespecial #41                 // Method io/youi/app/screen/LoadingTransitionSupport$$anonfun$afterScreenChange$1."<init>":(Lio/youi/app/screen/LoadingTransitionSupport;)V
      11: getstatic     #24                 // Field scala/concurrent/ExecutionContext$Implicits$.MODULE$:Lscala/concurrent/ExecutionContext$Implicits$;
      14: invokevirtual #28                 // Method scala/concurrent/ExecutionContext$Implicits$.global:()Lscala/concurrent/ExecutionContextExecutor;
      17: invokevirtual #32                 // Method scala/concurrent/Future$.apply:(Lscala/Function0;Lscala/concurrent/ExecutionContext;)Lscala/concurrent/Future;
      20: areturn

  public static void $init$(io.youi.app.screen.LoadingTransitionSupport);
    Code:
       0: return
}
