Compiled from "ClassTo.java"
final class io.sundr.codegen.functions.ClassTo$6 implements io.sundr.Function<java.lang.reflect.Type, io.sundr.codegen.model.TypeParamDef> {
  io.sundr.codegen.functions.ClassTo$6();
    Code:
       0: aload_0
       1: invokespecial #1                  // Method java/lang/Object."<init>":()V
       4: return

  public io.sundr.codegen.model.TypeParamDef apply(java.lang.reflect.Type);
    Code:
       0: aload_1
       1: instanceof    #2                  // class java/lang/reflect/TypeVariable
       4: ifeq          126
       7: aload_1
       8: checkcast     #2                  // class java/lang/reflect/TypeVariable
      11: astore_2
      12: aload_2
      13: invokeinterface #3,  1            // InterfaceMethod java/lang/reflect/TypeVariable.getName:()Ljava/lang/String;
      18: astore_3
      19: new           #4                  // class java/util/ArrayList
      22: dup
      23: invokespecial #5                  // Method java/util/ArrayList."<init>":()V
      26: astore        4
      28: aload_2
      29: invokeinterface #6,  1            // InterfaceMethod java/lang/reflect/TypeVariable.getBounds:()[Ljava/lang/reflect/Type;
      34: astore        5
      36: aload         5
      38: arraylength
      39: istore        6
      41: iconst_0
      42: istore        7
      44: iload         7
      46: iload         6
      48: if_icmpge     100
      51: aload         5
      53: iload         7
      55: aaload
      56: astore        8
      58: aload         8
      60: instanceof    #7                  // class java/lang/Class
      63: ifeq          94
      66: aload         8
      68: checkcast     #7                  // class java/lang/Class
      71: astore        9
      73: aload         4
      75: getstatic     #8                  // Field io/sundr/codegen/functions/ClassTo.TYPEREF:Lio/sundr/Function;
      78: aload         9
      80: invokeinterface #9,  2            // InterfaceMethod io/sundr/Function.apply:(Ljava/lang/Object;)Ljava/lang/Object;
      85: checkcast     #10                 // class io/sundr/codegen/model/ClassRef
      88: invokeinterface #11,  2           // InterfaceMethod java/util/List.add:(Ljava/lang/Object;)Z
      93: pop
      94: iinc          7, 1
      97: goto          44
     100: new           #12                 // class io/sundr/codegen/model/TypeParamDefBuilder
     103: dup
     104: invokespecial #13                 // Method io/sundr/codegen/model/TypeParamDefBuilder."<init>":()V
     107: aload_3
     108: invokevirtual #14                 // Method io/sundr/codegen/model/TypeParamDefBuilder.withName:(Ljava/lang/String;)Lio/sundr/codegen/model/TypeParamDefFluent;
     111: checkcast     #12                 // class io/sundr/codegen/model/TypeParamDefBuilder
     114: aload         4
     116: invokevirtual #15                 // Method io/sundr/codegen/model/TypeParamDefBuilder.withBounds:(Ljava/util/List;)Lio/sundr/codegen/model/TypeParamDefFluent;
     119: checkcast     #12                 // class io/sundr/codegen/model/TypeParamDefBuilder
     122: invokevirtual #16                 // Method io/sundr/codegen/model/TypeParamDefBuilder.build:()Lio/sundr/codegen/model/EditableTypeParamDef;
     125: areturn
     126: aconst_null
     127: areturn

  public java.lang.Object apply(java.lang.Object);
    Code:
       0: aload_0
       1: aload_1
       2: checkcast     #17                 // class java/lang/reflect/Type
       5: invokevirtual #18                 // Method apply:(Ljava/lang/reflect/Type;)Lio/sundr/codegen/model/TypeParamDef;
       8: areturn
}
