Compiled from "CouponsIterator.java"
class com.yahoo.sketches.hll.CouponsIterator {
  private final int offset_;

  private final int maxEntries_;

  private final short[] couponsArr_;

  private int index_;

  com.yahoo.sketches.hll.CouponsIterator(short[], int, int);
    Code:
       0: aload_0
       1: invokespecial #1                  // Method java/lang/Object."<init>":()V
       4: aload_0
       5: iload_2
       6: putfield      #2                  // Field offset_:I
       9: aload_0
      10: iload_3
      11: putfield      #3                  // Field maxEntries_:I
      14: aload_0
      15: aload_1
      16: putfield      #4                  // Field couponsArr_:[S
      19: aload_0
      20: iconst_m1
      21: putfield      #5                  // Field index_:I
      24: return

  boolean next();
    Code:
       0: aload_0
       1: dup
       2: getfield      #5                  // Field index_:I
       5: iconst_1
       6: iadd
       7: putfield      #5                  // Field index_:I
      10: aload_0
      11: getfield      #5                  // Field index_:I
      14: aload_0
      15: getfield      #3                  // Field maxEntries_:I
      18: if_icmpge     53
      21: aload_0
      22: getfield      #4                  // Field couponsArr_:[S
      25: aload_0
      26: getfield      #2                  // Field offset_:I
      29: aload_0
      30: getfield      #5                  // Field index_:I
      33: iadd
      34: saload
      35: ifeq          40
      38: iconst_1
      39: ireturn
      40: aload_0
      41: dup
      42: getfield      #5                  // Field index_:I
      45: iconst_1
      46: iadd
      47: putfield      #5                  // Field index_:I
      50: goto          10
      53: iconst_0
      54: ireturn

  short getValue();
    Code:
       0: aload_0
       1: getfield      #4                  // Field couponsArr_:[S
       4: aload_0
       5: getfield      #2                  // Field offset_:I
       8: aload_0
       9: getfield      #5                  // Field index_:I
      12: iadd
      13: saload
      14: ireturn
}
