Compiled from "DenseCompressedFieldsFactory.java"
final class com.yahoo.sketches.hll.DenseCompressedFieldsFactory implements com.yahoo.sketches.hll.FieldsFactory {
  com.yahoo.sketches.hll.DenseCompressedFieldsFactory();
    Code:
       0: aload_0
       1: invokespecial #1                  // Method java/lang/Object."<init>":()V
       4: return

  public com.yahoo.sketches.hll.Fields make(com.yahoo.sketches.hll.Preamble);
    Code:
       0: new           #2                  // class com/yahoo/sketches/hll/OnHeapCompressedFields
       3: dup
       4: aload_1
       5: invokespecial #3                  // Method com/yahoo/sketches/hll/OnHeapCompressedFields."<init>":(Lcom/yahoo/sketches/hll/Preamble;)V
       8: areturn
}
