Compiled from "SchemaExport.java"
public class org.hibernate.tool.hbm2ddl.SchemaExport {
  private static final org.hibernate.internal.CoreMessageLogger LOG;

  boolean haltOnError;

  boolean format;

  boolean manageNamespaces;

  java.lang.String delimiter;

  java.lang.String outputFile;

  private java.lang.String importFiles;

  private final java.util.List<java.lang.Exception> exceptions;

  public org.hibernate.tool.hbm2ddl.SchemaExport();
    Code:
       0: aload_0
       1: invokespecial #2                  // Method java/lang/Object."<init>":()V
       4: aload_0
       5: iconst_0
       6: putfield      #3                  // Field haltOnError:Z
       9: aload_0
      10: iconst_0
      11: putfield      #4                  // Field format:Z
      14: aload_0
      15: iconst_0
      16: putfield      #5                  // Field manageNamespaces:Z
      19: aload_0
      20: aconst_null
      21: putfield      #6                  // Field delimiter:Ljava/lang/String;
      24: aload_0
      25: aconst_null
      26: putfield      #7                  // Field outputFile:Ljava/lang/String;
      29: aload_0
      30: new           #8                  // class java/util/ArrayList
      33: dup
      34: invokespecial #9                  // Method java/util/ArrayList."<init>":()V
      37: putfield      #10                 // Field exceptions:Ljava/util/List;
      40: return

  public org.hibernate.tool.hbm2ddl.SchemaExport setOutputFile(java.lang.String);
    Code:
       0: aload_0
       1: aload_1
       2: putfield      #7                  // Field outputFile:Ljava/lang/String;
       5: aload_0
       6: areturn

  public org.hibernate.tool.hbm2ddl.SchemaExport setImportFiles(java.lang.String);
    Code:
       0: aload_0
       1: aload_1
       2: putfield      #11                 // Field importFiles:Ljava/lang/String;
       5: aload_0
       6: areturn

  public org.hibernate.tool.hbm2ddl.SchemaExport setDelimiter(java.lang.String);
    Code:
       0: aload_0
       1: aload_1
       2: putfield      #6                  // Field delimiter:Ljava/lang/String;
       5: aload_0
       6: areturn

  public org.hibernate.tool.hbm2ddl.SchemaExport setFormat(boolean);
    Code:
       0: aload_0
       1: iload_1
       2: putfield      #4                  // Field format:Z
       5: aload_0
       6: areturn

  public org.hibernate.tool.hbm2ddl.SchemaExport setHaltOnError(boolean);
    Code:
       0: aload_0
       1: iload_1
       2: putfield      #3                  // Field haltOnError:Z
       5: aload_0
       6: areturn

  public org.hibernate.tool.hbm2ddl.SchemaExport setManageNamespaces(boolean);
    Code:
       0: aload_0
       1: iload_1
       2: putfield      #5                  // Field manageNamespaces:Z
       5: aload_0
       6: areturn

  public void drop(java.util.EnumSet<org.hibernate.tool.schema.TargetType>, org.hibernate.boot.Metadata);
    Code:
       0: aload_0
       1: aload_1
       2: getstatic     #12                 // Field org/hibernate/tool/hbm2ddl/SchemaExport$Action.DROP:Lorg/hibernate/tool/hbm2ddl/SchemaExport$Action;
       5: aload_2
       6: invokevirtual #13                 // Method execute:(Ljava/util/EnumSet;Lorg/hibernate/tool/hbm2ddl/SchemaExport$Action;Lorg/hibernate/boot/Metadata;)V
       9: return

  public void create(java.util.EnumSet<org.hibernate.tool.schema.TargetType>, org.hibernate.boot.Metadata);
    Code:
       0: aload_0
       1: aload_1
       2: getstatic     #14                 // Field org/hibernate/tool/hbm2ddl/SchemaExport$Action.BOTH:Lorg/hibernate/tool/hbm2ddl/SchemaExport$Action;
       5: aload_2
       6: invokevirtual #13                 // Method execute:(Ljava/util/EnumSet;Lorg/hibernate/tool/hbm2ddl/SchemaExport$Action;Lorg/hibernate/boot/Metadata;)V
       9: return

  public void createOnly(java.util.EnumSet<org.hibernate.tool.schema.TargetType>, org.hibernate.boot.Metadata);
    Code:
       0: aload_0
       1: aload_1
       2: getstatic     #15                 // Field org/hibernate/tool/hbm2ddl/SchemaExport$Action.CREATE:Lorg/hibernate/tool/hbm2ddl/SchemaExport$Action;
       5: aload_2
       6: invokevirtual #13                 // Method execute:(Ljava/util/EnumSet;Lorg/hibernate/tool/hbm2ddl/SchemaExport$Action;Lorg/hibernate/boot/Metadata;)V
       9: return

  public void execute(java.util.EnumSet<org.hibernate.tool.schema.TargetType>, org.hibernate.tool.hbm2ddl.SchemaExport$Action, org.hibernate.boot.Metadata);
    Code:
       0: aload_0
       1: aload_1
       2: aload_2
       3: aload_3
       4: aload_3
       5: checkcast     #16                 // class org/hibernate/boot/spi/MetadataImplementor
       8: invokeinterface #17,  1           // InterfaceMethod org/hibernate/boot/spi/MetadataImplementor.getMetadataBuildingOptions:()Lorg/hibernate/boot/spi/MetadataBuildingOptions;
      13: invokeinterface #18,  1           // InterfaceMethod org/hibernate/boot/spi/MetadataBuildingOptions.getServiceRegistry:()Lorg/hibernate/boot/registry/StandardServiceRegistry;
      18: invokevirtual #19                 // Method execute:(Ljava/util/EnumSet;Lorg/hibernate/tool/hbm2ddl/SchemaExport$Action;Lorg/hibernate/boot/Metadata;Lorg/hibernate/service/ServiceRegistry;)V
      21: return

  public void execute(java.util.EnumSet<org.hibernate.tool.schema.TargetType>, org.hibernate.tool.hbm2ddl.SchemaExport$Action, org.hibernate.boot.Metadata, org.hibernate.service.ServiceRegistry);
    Code:
       0: aload_2
       1: getstatic     #20                 // Field org/hibernate/tool/hbm2ddl/SchemaExport$Action.NONE:Lorg/hibernate/tool/hbm2ddl/SchemaExport$Action;
       4: if_acmpne     18
       7: getstatic     #1                  // Field LOG:Lorg/hibernate/internal/CoreMessageLogger;
      10: ldc           #21                 // String Skipping SchemaExport as Action.NONE was passed
      12: invokeinterface #22,  2           // InterfaceMethod org/hibernate/internal/CoreMessageLogger.debug:(Ljava/lang/Object;)V
      17: return
      18: aload_1
      19: invokevirtual #23                 // Method java/util/EnumSet.isEmpty:()Z
      22: ifeq          36
      25: getstatic     #1                  // Field LOG:Lorg/hibernate/internal/CoreMessageLogger;
      28: ldc           #24                 // String Skipping SchemaExport as no targets were specified
      30: invokeinterface #22,  2           // InterfaceMethod org/hibernate/internal/CoreMessageLogger.debug:(Ljava/lang/Object;)V
      35: return
      36: aload_0
      37: getfield      #10                 // Field exceptions:Ljava/util/List;
      40: invokeinterface #25,  1           // InterfaceMethod java/util/List.clear:()V
      45: getstatic     #1                  // Field LOG:Lorg/hibernate/internal/CoreMessageLogger;
      48: invokeinterface #26,  1           // InterfaceMethod org/hibernate/internal/CoreMessageLogger.runningHbm2ddlSchemaExport:()V
      53: aload_1
      54: aload_0
      55: getfield      #7                  // Field outputFile:Ljava/lang/String;
      58: aload         4
      60: invokestatic  #27                 // Method buildTargetDescriptor:(Ljava/util/EnumSet;Ljava/lang/String;Lorg/hibernate/service/ServiceRegistry;)Lorg/hibernate/tool/schema/spi/TargetDescriptor;
      63: astore        5
      65: aload_0
      66: aload_2
      67: aload_0
      68: aload_1
      69: invokespecial #28                 // Method needsJdbcConnection:(Ljava/util/EnumSet;)Z
      72: aload_3
      73: aload         4
      75: aload         5
      77: invokevirtual #29                 // Method doExecution:(Lorg/hibernate/tool/hbm2ddl/SchemaExport$Action;ZLorg/hibernate/boot/Metadata;Lorg/hibernate/service/ServiceRegistry;Lorg/hibernate/tool/schema/spi/TargetDescriptor;)V
      80: return

  public void doExecution(org.hibernate.tool.hbm2ddl.SchemaExport$Action, boolean, org.hibernate.boot.Metadata, org.hibernate.service.ServiceRegistry, org.hibernate.tool.schema.spi.TargetDescriptor);
    Code:
       0: new           #30                 // class java/util/HashMap
       3: dup
       4: invokespecial #31                 // Method java/util/HashMap."<init>":()V
       7: astore        6
       9: aload         6
      11: aload         4
      13: ldc           #32                 // class org/hibernate/engine/config/spi/ConfigurationService
      15: invokeinterface #33,  2           // InterfaceMethod org/hibernate/service/ServiceRegistry.getService:(Ljava/lang/Class;)Lorg/hibernate/service/Service;
      20: checkcast     #32                 // class org/hibernate/engine/config/spi/ConfigurationService
      23: invokeinterface #34,  1           // InterfaceMethod org/hibernate/engine/config/spi/ConfigurationService.getSettings:()Ljava/util/Map;
      28: invokeinterface #35,  2           // InterfaceMethod java/util/Map.putAll:(Ljava/util/Map;)V
      33: aload         6
      35: ldc           #37                 // String hibernate.hbm2ddl.delimiter
      37: aload_0
      38: getfield      #6                  // Field delimiter:Ljava/lang/String;
      41: invokeinterface #38,  3           // InterfaceMethod java/util/Map.put:(Ljava/lang/Object;Ljava/lang/Object;)Ljava/lang/Object;
      46: pop
      47: aload         6
      49: ldc           #39                 // String hibernate.format_sql
      51: aload_0
      52: getfield      #4                  // Field format:Z
      55: invokestatic  #40                 // Method java/lang/Boolean.valueOf:(Z)Ljava/lang/Boolean;
      58: invokeinterface #38,  3           // InterfaceMethod java/util/Map.put:(Ljava/lang/Object;Ljava/lang/Object;)Ljava/lang/Object;
      63: pop
      64: aload         6
      66: ldc           #41                 // String hibernate.hbm2ddl.import_files
      68: aload_0
      69: getfield      #11                 // Field importFiles:Ljava/lang/String;
      72: invokeinterface #38,  3           // InterfaceMethod java/util/Map.put:(Ljava/lang/Object;Ljava/lang/Object;)Ljava/lang/Object;
      77: pop
      78: aload         4
      80: ldc           #42                 // class org/hibernate/tool/schema/spi/SchemaManagementTool
      82: invokeinterface #33,  2           // InterfaceMethod org/hibernate/service/ServiceRegistry.getService:(Ljava/lang/Class;)Lorg/hibernate/service/Service;
      87: checkcast     #42                 // class org/hibernate/tool/schema/spi/SchemaManagementTool
      90: astore        7
      92: aload_0
      93: getfield      #3                  // Field haltOnError:Z
      96: ifeq          105
      99: getstatic     #43                 // Field org/hibernate/tool/schema/internal/ExceptionHandlerHaltImpl.INSTANCE:Lorg/hibernate/tool/schema/internal/ExceptionHandlerHaltImpl;
     102: goto          112
     105: new           #44                 // class org/hibernate/tool/schema/internal/ExceptionHandlerCollectingImpl
     108: dup
     109: invokespecial #45                 // Method org/hibernate/tool/schema/internal/ExceptionHandlerCollectingImpl."<init>":()V
     112: astore        8
     114: aload         6
     116: aload         8
     118: invokestatic  #46                 // Method org/hibernate/tool/schema/spi/SchemaManagementToolCoordinator.buildExecutionOptions:(Ljava/util/Map;Lorg/hibernate/tool/schema/spi/ExceptionHandler;)Lorg/hibernate/tool/schema/spi/ExecutionOptions;
     121: astore        9
     123: new           #47                 // class org/hibernate/tool/hbm2ddl/SchemaExport$1
     126: dup
     127: aload_0
     128: invokespecial #48                 // Method org/hibernate/tool/hbm2ddl/SchemaExport$1."<init>":(Lorg/hibernate/tool/hbm2ddl/SchemaExport;)V
     131: astore        10
     133: aload_1
     134: invokevirtual #49                 // Method org/hibernate/tool/hbm2ddl/SchemaExport$Action.doDrop:()Z
     137: ifeq          161
     140: aload         7
     142: aload         6
     144: invokeinterface #50,  2           // InterfaceMethod org/hibernate/tool/schema/spi/SchemaManagementTool.getSchemaDropper:(Ljava/util/Map;)Lorg/hibernate/tool/schema/spi/SchemaDropper;
     149: aload_3
     150: aload         9
     152: aload         10
     154: aload         5
     156: invokeinterface #51,  5           // InterfaceMethod org/hibernate/tool/schema/spi/SchemaDropper.doDrop:(Lorg/hibernate/boot/Metadata;Lorg/hibernate/tool/schema/spi/ExecutionOptions;Lorg/hibernate/tool/schema/spi/SourceDescriptor;Lorg/hibernate/tool/schema/spi/TargetDescriptor;)V
     161: aload_1
     162: invokevirtual #52                 // Method org/hibernate/tool/hbm2ddl/SchemaExport$Action.doCreate:()Z
     165: ifeq          189
     168: aload         7
     170: aload         6
     172: invokeinterface #53,  2           // InterfaceMethod org/hibernate/tool/schema/spi/SchemaManagementTool.getSchemaCreator:(Ljava/util/Map;)Lorg/hibernate/tool/schema/spi/SchemaCreator;
     177: aload_3
     178: aload         9
     180: aload         10
     182: aload         5
     184: invokeinterface #54,  5           // InterfaceMethod org/hibernate/tool/schema/spi/SchemaCreator.doCreation:(Lorg/hibernate/boot/Metadata;Lorg/hibernate/tool/schema/spi/ExecutionOptions;Lorg/hibernate/tool/schema/spi/SourceDescriptor;Lorg/hibernate/tool/schema/spi/TargetDescriptor;)V
     189: aload         8
     191: instanceof    #44                 // class org/hibernate/tool/schema/internal/ExceptionHandlerCollectingImpl
     194: ifeq          249
     197: aload_0
     198: getfield      #10                 // Field exceptions:Ljava/util/List;
     201: aload         8
     203: checkcast     #44                 // class org/hibernate/tool/schema/internal/ExceptionHandlerCollectingImpl
     206: invokevirtual #55                 // Method org/hibernate/tool/schema/internal/ExceptionHandlerCollectingImpl.getExceptions:()Ljava/util/List;
     209: invokeinterface #56,  2           // InterfaceMethod java/util/List.addAll:(Ljava/util/Collection;)Z
     214: pop
     215: goto          249
     218: astore        11
     220: aload         8
     222: instanceof    #44                 // class org/hibernate/tool/schema/internal/ExceptionHandlerCollectingImpl
     225: ifeq          246
     228: aload_0
     229: getfield      #10                 // Field exceptions:Ljava/util/List;
     232: aload         8
     234: checkcast     #44                 // class org/hibernate/tool/schema/internal/ExceptionHandlerCollectingImpl
     237: invokevirtual #55                 // Method org/hibernate/tool/schema/internal/ExceptionHandlerCollectingImpl.getExceptions:()Ljava/util/List;
     240: invokeinterface #56,  2           // InterfaceMethod java/util/List.addAll:(Ljava/util/Collection;)Z
     245: pop
     246: aload         11
     248: athrow
     249: return
    Exception table:
       from    to  target type
         133   189   218   any
         218   220   218   any

  private boolean needsJdbcConnection(java.util.EnumSet<org.hibernate.tool.schema.TargetType>);
    Code:
       0: aload_1
       1: getstatic     #57                 // Field org/hibernate/tool/schema/TargetType.DATABASE:Lorg/hibernate/tool/schema/TargetType;
       4: invokevirtual #58                 // Method java/util/EnumSet.contains:(Ljava/lang/Object;)Z
       7: ireturn

  public static org.hibernate.tool.schema.spi.TargetDescriptor buildTargetDescriptor(java.util.EnumSet<org.hibernate.tool.schema.TargetType>, java.lang.String, org.hibernate.service.ServiceRegistry);
    Code:
       0: aload_0
       1: getstatic     #59                 // Field org/hibernate/tool/schema/TargetType.SCRIPT:Lorg/hibernate/tool/schema/TargetType;
       4: invokevirtual #58                 // Method java/util/EnumSet.contains:(Ljava/lang/Object;)Z
       7: ifeq          69
      10: aload_1
      11: ifnonnull     24
      14: new           #60                 // class org/hibernate/tool/schema/spi/SchemaManagementException
      17: dup
      18: ldc           #61                 // String Writing to script was requested, but no script file was specified
      20: invokespecial #62                 // Method org/hibernate/tool/schema/spi/SchemaManagementException."<init>":(Ljava/lang/String;)V
      23: athrow
      24: aload_1
      25: aload_2
      26: ldc           #63                 // class org/hibernate/boot/registry/classloading/spi/ClassLoaderService
      28: invokeinterface #33,  2           // InterfaceMethod org/hibernate/service/ServiceRegistry.getService:(Ljava/lang/Class;)Lorg/hibernate/service/Service;
      33: checkcast     #63                 // class org/hibernate/boot/registry/classloading/spi/ClassLoaderService
      36: aload_2
      37: ldc           #32                 // class org/hibernate/engine/config/spi/ConfigurationService
      39: invokeinterface #33,  2           // InterfaceMethod org/hibernate/service/ServiceRegistry.getService:(Ljava/lang/Class;)Lorg/hibernate/service/Service;
      44: checkcast     #32                 // class org/hibernate/engine/config/spi/ConfigurationService
      47: invokeinterface #34,  1           // InterfaceMethod org/hibernate/engine/config/spi/ConfigurationService.getSettings:()Ljava/util/Map;
      52: ldc           #64                 // String hibernate.hbm2ddl.charset_name
      54: invokeinterface #65,  2           // InterfaceMethod java/util/Map.get:(Ljava/lang/Object;)Ljava/lang/Object;
      59: checkcast     #66                 // class java/lang/String
      62: invokestatic  #67                 // Method org/hibernate/tool/schema/internal/Helper.interpretScriptTargetSetting:(Ljava/lang/Object;Lorg/hibernate/boot/registry/classloading/spi/ClassLoaderService;Ljava/lang/String;)Lorg/hibernate/tool/schema/spi/ScriptTargetOutput;
      65: astore_3
      66: goto          71
      69: aconst_null
      70: astore_3
      71: new           #68                 // class org/hibernate/tool/hbm2ddl/SchemaExport$TargetDescriptorImpl
      74: dup
      75: aload_0
      76: aload_3
      77: invokespecial #69                 // Method org/hibernate/tool/hbm2ddl/SchemaExport$TargetDescriptorImpl."<init>":(Ljava/util/EnumSet;Lorg/hibernate/tool/schema/spi/ScriptTargetOutput;)V
      80: areturn

  public void perform(org.hibernate.tool.hbm2ddl.SchemaExport$Action, org.hibernate.boot.Metadata, org.hibernate.tool.schema.spi.ScriptTargetOutput);
    Code:
       0: aload_0
       1: aload_1
       2: iconst_0
       3: aload_2
       4: aload_2
       5: checkcast     #16                 // class org/hibernate/boot/spi/MetadataImplementor
       8: invokeinterface #17,  1           // InterfaceMethod org/hibernate/boot/spi/MetadataImplementor.getMetadataBuildingOptions:()Lorg/hibernate/boot/spi/MetadataBuildingOptions;
      13: invokeinterface #18,  1           // InterfaceMethod org/hibernate/boot/spi/MetadataBuildingOptions.getServiceRegistry:()Lorg/hibernate/boot/registry/StandardServiceRegistry;
      18: new           #68                 // class org/hibernate/tool/hbm2ddl/SchemaExport$TargetDescriptorImpl
      21: dup
      22: getstatic     #59                 // Field org/hibernate/tool/schema/TargetType.SCRIPT:Lorg/hibernate/tool/schema/TargetType;
      25: invokestatic  #70                 // Method java/util/EnumSet.of:(Ljava/lang/Enum;)Ljava/util/EnumSet;
      28: aload_3
      29: invokespecial #69                 // Method org/hibernate/tool/hbm2ddl/SchemaExport$TargetDescriptorImpl."<init>":(Ljava/util/EnumSet;Lorg/hibernate/tool/schema/spi/ScriptTargetOutput;)V
      32: invokevirtual #29                 // Method doExecution:(Lorg/hibernate/tool/hbm2ddl/SchemaExport$Action;ZLorg/hibernate/boot/Metadata;Lorg/hibernate/service/ServiceRegistry;Lorg/hibernate/tool/schema/spi/TargetDescriptor;)V
      35: return

  public static void main(java.lang.String[]);
    Code:
       0: aload_0
       1: invokestatic  #71                 // Method org/hibernate/tool/hbm2ddl/SchemaExport$CommandLineArgs.parseCommandLineArgs:([Ljava/lang/String;)Lorg/hibernate/tool/hbm2ddl/SchemaExport$CommandLineArgs;
       4: astore_1
       5: aload_1
       6: invokestatic  #72                 // Method execute:(Lorg/hibernate/tool/hbm2ddl/SchemaExport$CommandLineArgs;)V
       9: goto          26
      12: astore_1
      13: getstatic     #1                  // Field LOG:Lorg/hibernate/internal/CoreMessageLogger;
      16: aload_1
      17: invokeinterface #74,  2           // InterfaceMethod org/hibernate/internal/CoreMessageLogger.unableToCreateSchema:(Ljava/lang/Exception;)V
      22: aload_1
      23: invokevirtual #75                 // Method java/lang/Exception.printStackTrace:()V
      26: return
    Exception table:
       from    to  target type
           0     9    12   Class java/lang/Exception

  public static void execute(org.hibernate.tool.hbm2ddl.SchemaExport$CommandLineArgs) throws java.lang.Exception;
    Code:
       0: aload_0
       1: invokestatic  #76                 // Method buildStandardServiceRegistry:(Lorg/hibernate/tool/hbm2ddl/SchemaExport$CommandLineArgs;)Lorg/hibernate/boot/registry/StandardServiceRegistry;
       4: astore_1
       5: aload_0
       6: aload_1
       7: invokestatic  #77                 // Method buildMetadata:(Lorg/hibernate/tool/hbm2ddl/SchemaExport$CommandLineArgs;Lorg/hibernate/boot/registry/StandardServiceRegistry;)Lorg/hibernate/boot/spi/MetadataImplementor;
      10: astore_2
      11: new           #78                 // class org/hibernate/tool/hbm2ddl/SchemaExport
      14: dup
      15: invokespecial #79                 // Method "<init>":()V
      18: aload_0
      19: getfield      #80                 // Field org/hibernate/tool/hbm2ddl/SchemaExport$CommandLineArgs.halt:Z
      22: invokevirtual #81                 // Method setHaltOnError:(Z)Lorg/hibernate/tool/hbm2ddl/SchemaExport;
      25: aload_0
      26: getfield      #82                 // Field org/hibernate/tool/hbm2ddl/SchemaExport$CommandLineArgs.outputFile:Ljava/lang/String;
      29: invokevirtual #83                 // Method setOutputFile:(Ljava/lang/String;)Lorg/hibernate/tool/hbm2ddl/SchemaExport;
      32: aload_0
      33: getfield      #84                 // Field org/hibernate/tool/hbm2ddl/SchemaExport$CommandLineArgs.delimiter:Ljava/lang/String;
      36: invokevirtual #85                 // Method setDelimiter:(Ljava/lang/String;)Lorg/hibernate/tool/hbm2ddl/SchemaExport;
      39: aload_0
      40: getfield      #86                 // Field org/hibernate/tool/hbm2ddl/SchemaExport$CommandLineArgs.format:Z
      43: invokevirtual #87                 // Method setFormat:(Z)Lorg/hibernate/tool/hbm2ddl/SchemaExport;
      46: aload_0
      47: getfield      #88                 // Field org/hibernate/tool/hbm2ddl/SchemaExport$CommandLineArgs.manageNamespaces:Z
      50: invokevirtual #89                 // Method setManageNamespaces:(Z)Lorg/hibernate/tool/hbm2ddl/SchemaExport;
      53: aload_0
      54: getfield      #90                 // Field org/hibernate/tool/hbm2ddl/SchemaExport$CommandLineArgs.importFile:Ljava/lang/String;
      57: invokevirtual #91                 // Method setImportFiles:(Ljava/lang/String;)Lorg/hibernate/tool/hbm2ddl/SchemaExport;
      60: aload_0
      61: getfield      #92                 // Field org/hibernate/tool/hbm2ddl/SchemaExport$CommandLineArgs.targetTypes:Ljava/util/EnumSet;
      64: aload_0
      65: getfield      #93                 // Field org/hibernate/tool/hbm2ddl/SchemaExport$CommandLineArgs.action:Lorg/hibernate/tool/hbm2ddl/SchemaExport$Action;
      68: aload_2
      69: aload_1
      70: invokevirtual #19                 // Method execute:(Ljava/util/EnumSet;Lorg/hibernate/tool/hbm2ddl/SchemaExport$Action;Lorg/hibernate/boot/Metadata;Lorg/hibernate/service/ServiceRegistry;)V
      73: aload_1
      74: invokestatic  #94                 // Method org/hibernate/boot/registry/StandardServiceRegistryBuilder.destroy:(Lorg/hibernate/service/ServiceRegistry;)V
      77: goto          87
      80: astore_3
      81: aload_1
      82: invokestatic  #94                 // Method org/hibernate/boot/registry/StandardServiceRegistryBuilder.destroy:(Lorg/hibernate/service/ServiceRegistry;)V
      85: aload_3
      86: athrow
      87: return
    Exception table:
       from    to  target type
           5    73    80   any

  private static org.hibernate.boot.registry.StandardServiceRegistry buildStandardServiceRegistry(org.hibernate.tool.hbm2ddl.SchemaExport$CommandLineArgs) throws java.lang.Exception;
    Code:
       0: new           #95                 // class org/hibernate/boot/registry/BootstrapServiceRegistryBuilder
       3: dup
       4: invokespecial #96                 // Method org/hibernate/boot/registry/BootstrapServiceRegistryBuilder."<init>":()V
       7: invokevirtual #97                 // Method org/hibernate/boot/registry/BootstrapServiceRegistryBuilder.build:()Lorg/hibernate/boot/registry/BootstrapServiceRegistry;
      10: astore_1
      11: new           #98                 // class org/hibernate/boot/registry/StandardServiceRegistryBuilder
      14: dup
      15: aload_1
      16: invokespecial #99                 // Method org/hibernate/boot/registry/StandardServiceRegistryBuilder."<init>":(Lorg/hibernate/boot/registry/BootstrapServiceRegistry;)V
      19: astore_2
      20: aload_0
      21: getfield      #100                // Field org/hibernate/tool/hbm2ddl/SchemaExport$CommandLineArgs.cfgXmlFile:Ljava/lang/String;
      24: ifnull        36
      27: aload_2
      28: aload_0
      29: getfield      #100                // Field org/hibernate/tool/hbm2ddl/SchemaExport$CommandLineArgs.cfgXmlFile:Ljava/lang/String;
      32: invokevirtual #101                // Method org/hibernate/boot/registry/StandardServiceRegistryBuilder.configure:(Ljava/lang/String;)Lorg/hibernate/boot/registry/StandardServiceRegistryBuilder;
      35: pop
      36: new           #102                // class java/util/Properties
      39: dup
      40: invokespecial #103                // Method java/util/Properties."<init>":()V
      43: astore_3
      44: aload_0
      45: getfield      #104                // Field org/hibernate/tool/hbm2ddl/SchemaExport$CommandLineArgs.propertiesFile:Ljava/lang/String;
      48: ifnull        66
      51: aload_3
      52: new           #105                // class java/io/FileInputStream
      55: dup
      56: aload_0
      57: getfield      #104                // Field org/hibernate/tool/hbm2ddl/SchemaExport$CommandLineArgs.propertiesFile:Ljava/lang/String;
      60: invokespecial #106                // Method java/io/FileInputStream."<init>":(Ljava/lang/String;)V
      63: invokevirtual #107                // Method java/util/Properties.load:(Ljava/io/InputStream;)V
      66: aload_2
      67: aload_3
      68: invokevirtual #108                // Method org/hibernate/boot/registry/StandardServiceRegistryBuilder.applySettings:(Ljava/util/Map;)Lorg/hibernate/boot/registry/StandardServiceRegistryBuilder;
      71: pop
      72: aload_2
      73: invokevirtual #109                // Method org/hibernate/boot/registry/StandardServiceRegistryBuilder.build:()Lorg/hibernate/boot/registry/StandardServiceRegistry;
      76: areturn

  private static org.hibernate.boot.spi.MetadataImplementor buildMetadata(org.hibernate.tool.hbm2ddl.SchemaExport$CommandLineArgs, org.hibernate.boot.registry.StandardServiceRegistry) throws java.lang.Exception;
    Code:
       0: new           #110                // class org/hibernate/boot/MetadataSources
       3: dup
       4: aload_1
       5: invokespecial #111                // Method org/hibernate/boot/MetadataSources."<init>":(Lorg/hibernate/service/ServiceRegistry;)V
       8: astore_2
       9: aload_0
      10: getfield      #112                // Field org/hibernate/tool/hbm2ddl/SchemaExport$CommandLineArgs.hbmXmlFiles:Ljava/util/List;
      13: invokeinterface #113,  1          // InterfaceMethod java/util/List.iterator:()Ljava/util/Iterator;
      18: astore_3
      19: aload_3
      20: invokeinterface #114,  1          // InterfaceMethod java/util/Iterator.hasNext:()Z
      25: ifeq          49
      28: aload_3
      29: invokeinterface #115,  1          // InterfaceMethod java/util/Iterator.next:()Ljava/lang/Object;
      34: checkcast     #66                 // class java/lang/String
      37: astore        4
      39: aload_2
      40: aload         4
      42: invokevirtual #116                // Method org/hibernate/boot/MetadataSources.addFile:(Ljava/lang/String;)Lorg/hibernate/boot/MetadataSources;
      45: pop
      46: goto          19
      49: aload_0
      50: getfield      #117                // Field org/hibernate/tool/hbm2ddl/SchemaExport$CommandLineArgs.jarFiles:Ljava/util/List;
      53: invokeinterface #113,  1          // InterfaceMethod java/util/List.iterator:()Ljava/util/Iterator;
      58: astore_3
      59: aload_3
      60: invokeinterface #114,  1          // InterfaceMethod java/util/Iterator.hasNext:()Z
      65: ifeq          96
      68: aload_3
      69: invokeinterface #115,  1          // InterfaceMethod java/util/Iterator.next:()Ljava/lang/Object;
      74: checkcast     #66                 // class java/lang/String
      77: astore        4
      79: aload_2
      80: new           #118                // class java/io/File
      83: dup
      84: aload         4
      86: invokespecial #119                // Method java/io/File."<init>":(Ljava/lang/String;)V
      89: invokevirtual #120                // Method org/hibernate/boot/MetadataSources.addJar:(Ljava/io/File;)Lorg/hibernate/boot/MetadataSources;
      92: pop
      93: goto          59
      96: aload_2
      97: invokevirtual #121                // Method org/hibernate/boot/MetadataSources.getMetadataBuilder:()Lorg/hibernate/boot/MetadataBuilder;
     100: astore_3
     101: aload_1
     102: ldc           #122                // class org/hibernate/boot/registry/selector/spi/StrategySelector
     104: invokeinterface #123,  2          // InterfaceMethod org/hibernate/boot/registry/StandardServiceRegistry.getService:(Ljava/lang/Class;)Lorg/hibernate/service/Service;
     109: checkcast     #122                // class org/hibernate/boot/registry/selector/spi/StrategySelector
     112: astore        4
     114: aload_0
     115: getfield      #124                // Field org/hibernate/tool/hbm2ddl/SchemaExport$CommandLineArgs.implicitNamingStrategyImplName:Ljava/lang/String;
     118: ifnull        144
     121: aload_3
     122: aload         4
     124: ldc           #125                // class org/hibernate/boot/model/naming/ImplicitNamingStrategy
     126: aload_0
     127: getfield      #124                // Field org/hibernate/tool/hbm2ddl/SchemaExport$CommandLineArgs.implicitNamingStrategyImplName:Ljava/lang/String;
     130: invokeinterface #126,  3          // InterfaceMethod org/hibernate/boot/registry/selector/spi/StrategySelector.resolveStrategy:(Ljava/lang/Class;Ljava/lang/Object;)Ljava/lang/Object;
     135: checkcast     #125                // class org/hibernate/boot/model/naming/ImplicitNamingStrategy
     138: invokeinterface #127,  2          // InterfaceMethod org/hibernate/boot/MetadataBuilder.applyImplicitNamingStrategy:(Lorg/hibernate/boot/model/naming/ImplicitNamingStrategy;)Lorg/hibernate/boot/MetadataBuilder;
     143: pop
     144: aload_0
     145: getfield      #128                // Field org/hibernate/tool/hbm2ddl/SchemaExport$CommandLineArgs.physicalNamingStrategyImplName:Ljava/lang/String;
     148: ifnull        174
     151: aload_3
     152: aload         4
     154: ldc           #129                // class org/hibernate/boot/model/naming/PhysicalNamingStrategy
     156: aload_0
     157: getfield      #128                // Field org/hibernate/tool/hbm2ddl/SchemaExport$CommandLineArgs.physicalNamingStrategyImplName:Ljava/lang/String;
     160: invokeinterface #126,  3          // InterfaceMethod org/hibernate/boot/registry/selector/spi/StrategySelector.resolveStrategy:(Ljava/lang/Class;Ljava/lang/Object;)Ljava/lang/Object;
     165: checkcast     #129                // class org/hibernate/boot/model/naming/PhysicalNamingStrategy
     168: invokeinterface #130,  2          // InterfaceMethod org/hibernate/boot/MetadataBuilder.applyPhysicalNamingStrategy:(Lorg/hibernate/boot/model/naming/PhysicalNamingStrategy;)Lorg/hibernate/boot/MetadataBuilder;
     173: pop
     174: aload_3
     175: invokeinterface #131,  1          // InterfaceMethod org/hibernate/boot/MetadataBuilder.build:()Lorg/hibernate/boot/Metadata;
     180: checkcast     #16                 // class org/hibernate/boot/spi/MetadataImplementor
     183: areturn

  public static org.hibernate.boot.spi.MetadataImplementor buildMetadataFromMainArgs(java.lang.String[]) throws java.lang.Exception;
    Code:
       0: aload_0
       1: invokestatic  #71                 // Method org/hibernate/tool/hbm2ddl/SchemaExport$CommandLineArgs.parseCommandLineArgs:([Ljava/lang/String;)Lorg/hibernate/tool/hbm2ddl/SchemaExport$CommandLineArgs;
       4: astore_1
       5: aload_1
       6: invokestatic  #76                 // Method buildStandardServiceRegistry:(Lorg/hibernate/tool/hbm2ddl/SchemaExport$CommandLineArgs;)Lorg/hibernate/boot/registry/StandardServiceRegistry;
       9: astore_2
      10: aload_1
      11: aload_2
      12: invokestatic  #77                 // Method buildMetadata:(Lorg/hibernate/tool/hbm2ddl/SchemaExport$CommandLineArgs;Lorg/hibernate/boot/registry/StandardServiceRegistry;)Lorg/hibernate/boot/spi/MetadataImplementor;
      15: astore_3
      16: aload_2
      17: invokestatic  #94                 // Method org/hibernate/boot/registry/StandardServiceRegistryBuilder.destroy:(Lorg/hibernate/service/ServiceRegistry;)V
      20: aload_3
      21: areturn
      22: astore        4
      24: aload_2
      25: invokestatic  #94                 // Method org/hibernate/boot/registry/StandardServiceRegistryBuilder.destroy:(Lorg/hibernate/service/ServiceRegistry;)V
      28: aload         4
      30: athrow
    Exception table:
       from    to  target type
          10    16    22   any
          22    24    22   any

  public java.util.List getExceptions();
    Code:
       0: aload_0
       1: getfield      #10                 // Field exceptions:Ljava/util/List;
       4: areturn

  static org.hibernate.internal.CoreMessageLogger access$100();
    Code:
       0: getstatic     #1                  // Field LOG:Lorg/hibernate/internal/CoreMessageLogger;
       3: areturn

  static {};
    Code:
       0: ldc           #78                 // class org/hibernate/tool/hbm2ddl/SchemaExport
       2: invokestatic  #132                // Method org/hibernate/internal/CoreLogging.messageLogger:(Ljava/lang/Class;)Lorg/hibernate/internal/CoreMessageLogger;
       5: putstatic     #1                  // Field LOG:Lorg/hibernate/internal/CoreMessageLogger;
       8: return
}
