Compiled from "ScriptExporter.java"
class org.hibernate.tool.hbm2ddl.ScriptExporter implements org.hibernate.tool.hbm2ddl.Exporter {
  org.hibernate.tool.hbm2ddl.ScriptExporter();
    Code:
       0: aload_0
       1: invokespecial #1                  // Method java/lang/Object."<init>":()V
       4: return

  public boolean acceptsImportScripts();
    Code:
       0: iconst_0
       1: ireturn

  public void export(java.lang.String) throws java.lang.Exception;
    Code:
       0: getstatic     #2                  // Field java/lang/System.out:Ljava/io/PrintStream;
       3: aload_1
       4: invokevirtual #3                  // Method java/io/PrintStream.println:(Ljava/lang/String;)V
       7: return

  public void release() throws java.lang.Exception;
    Code:
       0: return
}
