Compiled from "AsExistingPropertyTypeSerializer.java"
public class io.dekorate.deps.jackson.databind.jsontype.impl.AsExistingPropertyTypeSerializer extends io.dekorate.deps.jackson.databind.jsontype.impl.AsPropertyTypeSerializer {
  public io.dekorate.deps.jackson.databind.jsontype.impl.AsExistingPropertyTypeSerializer(io.dekorate.deps.jackson.databind.jsontype.TypeIdResolver, io.dekorate.deps.jackson.databind.BeanProperty, java.lang.String);
    Code:
       0: aload_0
       1: aload_1
       2: aload_2
       3: aload_3
       4: invokespecial #14                 // Method io/dekorate/deps/jackson/databind/jsontype/impl/AsPropertyTypeSerializer."<init>":(Lio/dekorate/deps/jackson/databind/jsontype/TypeIdResolver;Lio/dekorate/deps/jackson/databind/BeanProperty;Ljava/lang/String;)V
       7: return

  public io.dekorate.deps.jackson.databind.jsontype.impl.AsExistingPropertyTypeSerializer forProperty(io.dekorate.deps.jackson.databind.BeanProperty);
    Code:
       0: aload_0
       1: getfield      #27                 // Field _property:Lio/dekorate/deps/jackson/databind/BeanProperty;
       4: aload_1
       5: if_acmpne     12
       8: aload_0
       9: goto          28
      12: new           #2                  // class io/dekorate/deps/jackson/databind/jsontype/impl/AsExistingPropertyTypeSerializer
      15: dup
      16: aload_0
      17: getfield      #30                 // Field _idResolver:Lio/dekorate/deps/jackson/databind/jsontype/TypeIdResolver;
      20: aload_1
      21: aload_0
      22: getfield      #33                 // Field _typePropertyName:Ljava/lang/String;
      25: invokespecial #34                 // Method "<init>":(Lio/dekorate/deps/jackson/databind/jsontype/TypeIdResolver;Lio/dekorate/deps/jackson/databind/BeanProperty;Ljava/lang/String;)V
      28: areturn

  public io.dekorate.deps.jackson.annotation.JsonTypeInfo$As getTypeInclusion();
    Code:
       0: getstatic     #41                 // Field io/dekorate/deps/jackson/annotation/JsonTypeInfo$As.EXISTING_PROPERTY:Lio/dekorate/deps/jackson/annotation/JsonTypeInfo$As;
       3: areturn

  public io.dekorate.deps.jackson.databind.jsontype.impl.AsPropertyTypeSerializer forProperty(io.dekorate.deps.jackson.databind.BeanProperty);
    Code:
       0: aload_0
       1: aload_1
       2: invokevirtual #44                 // Method forProperty:(Lio/dekorate/deps/jackson/databind/BeanProperty;)Lio/dekorate/deps/jackson/databind/jsontype/impl/AsExistingPropertyTypeSerializer;
       5: areturn

  public io.dekorate.deps.jackson.databind.jsontype.impl.AsArrayTypeSerializer forProperty(io.dekorate.deps.jackson.databind.BeanProperty);
    Code:
       0: aload_0
       1: aload_1
       2: invokevirtual #44                 // Method forProperty:(Lio/dekorate/deps/jackson/databind/BeanProperty;)Lio/dekorate/deps/jackson/databind/jsontype/impl/AsExistingPropertyTypeSerializer;
       5: areturn

  public io.dekorate.deps.jackson.databind.jsontype.TypeSerializer forProperty(io.dekorate.deps.jackson.databind.BeanProperty);
    Code:
       0: aload_0
       1: aload_1
       2: invokevirtual #44                 // Method forProperty:(Lio/dekorate/deps/jackson/databind/BeanProperty;)Lio/dekorate/deps/jackson/databind/jsontype/impl/AsExistingPropertyTypeSerializer;
       5: areturn
}
