Compiled from "FileFilterUtil.java"
public class ch.qos.logback.core.rolling.helper.FileFilterUtil {
  public ch.qos.logback.core.rolling.helper.FileFilterUtil();
    Code:
       0: aload_0
       1: invokespecial #1                  // Method java/lang/Object."<init>":()V
       4: return

  public static void sortFileArrayByName(java.io.File[]);
    Code:
       0: aload_0
       1: new           #2                  // class ch/qos/logback/core/rolling/helper/FileFilterUtil$1
       4: dup
       5: invokespecial #3                  // Method ch/qos/logback/core/rolling/helper/FileFilterUtil$1."<init>":()V
       8: invokestatic  #4                  // Method java/util/Arrays.sort:([Ljava/lang/Object;Ljava/util/Comparator;)V
      11: return

  public static void reverseSortFileArrayByName(java.io.File[]);
    Code:
       0: aload_0
       1: new           #5                  // class ch/qos/logback/core/rolling/helper/FileFilterUtil$2
       4: dup
       5: invokespecial #6                  // Method ch/qos/logback/core/rolling/helper/FileFilterUtil$2."<init>":()V
       8: invokestatic  #4                  // Method java/util/Arrays.sort:([Ljava/lang/Object;Ljava/util/Comparator;)V
      11: return

  public static java.lang.String afterLastSlash(java.lang.String);
    Code:
       0: aload_0
       1: bipush        47
       3: invokevirtual #7                  // Method java/lang/String.lastIndexOf:(I)I
       6: istore_1
       7: iload_1
       8: iconst_m1
       9: if_icmpne     14
      12: aload_0
      13: areturn
      14: aload_0
      15: iload_1
      16: iconst_1
      17: iadd
      18: invokevirtual #8                  // Method java/lang/String.substring:(I)Ljava/lang/String;
      21: areturn

  public static boolean isEmptyDirectory(java.io.File);
    Code:
       0: aload_0
       1: invokevirtual #9                  // Method java/io/File.isDirectory:()Z
       4: ifne          39
       7: new           #10                 // class java/lang/IllegalArgumentException
      10: dup
      11: new           #11                 // class java/lang/StringBuilder
      14: dup
      15: invokespecial #12                 // Method java/lang/StringBuilder."<init>":()V
      18: ldc           #13                 // String [
      20: invokevirtual #14                 // Method java/lang/StringBuilder.append:(Ljava/lang/String;)Ljava/lang/StringBuilder;
      23: aload_0
      24: invokevirtual #15                 // Method java/lang/StringBuilder.append:(Ljava/lang/Object;)Ljava/lang/StringBuilder;
      27: ldc           #16                 // String ] must be a directory
      29: invokevirtual #14                 // Method java/lang/StringBuilder.append:(Ljava/lang/String;)Ljava/lang/StringBuilder;
      32: invokevirtual #17                 // Method java/lang/StringBuilder.toString:()Ljava/lang/String;
      35: invokespecial #18                 // Method java/lang/IllegalArgumentException."<init>":(Ljava/lang/String;)V
      38: athrow
      39: aload_0
      40: invokevirtual #19                 // Method java/io/File.list:()[Ljava/lang/String;
      43: astore_1
      44: aload_1
      45: ifnull        53
      48: aload_1
      49: arraylength
      50: ifne          55
      53: iconst_1
      54: ireturn
      55: iconst_0
      56: ireturn

  public static java.io.File[] filesInFolderMatchingStemRegex(java.io.File, java.lang.String);
    Code:
       0: aload_0
       1: ifnonnull     9
       4: iconst_0
       5: anewarray     #20                 // class java/io/File
       8: areturn
       9: aload_0
      10: invokevirtual #21                 // Method java/io/File.exists:()Z
      13: ifeq          23
      16: aload_0
      17: invokevirtual #9                  // Method java/io/File.isDirectory:()Z
      20: ifne          28
      23: iconst_0
      24: anewarray     #20                 // class java/io/File
      27: areturn
      28: aload_0
      29: new           #22                 // class ch/qos/logback/core/rolling/helper/FileFilterUtil$3
      32: dup
      33: aload_1
      34: invokespecial #23                 // Method ch/qos/logback/core/rolling/helper/FileFilterUtil$3."<init>":(Ljava/lang/String;)V
      37: invokevirtual #24                 // Method java/io/File.listFiles:(Ljava/io/FilenameFilter;)[Ljava/io/File;
      40: areturn

  public static int findHighestCounter(java.io.File[], java.lang.String);
    Code:
       0: ldc           #25                 // int -2147483648
       2: istore_2
       3: aload_0
       4: astore_3
       5: aload_3
       6: arraylength
       7: istore        4
       9: iconst_0
      10: istore        5
      12: iload         5
      14: iload         4
      16: if_icmpge     48
      19: aload_3
      20: iload         5
      22: aaload
      23: astore        6
      25: aload         6
      27: aload_1
      28: invokestatic  #26                 // Method extractCounter:(Ljava/io/File;Ljava/lang/String;)I
      31: istore        7
      33: iload_2
      34: iload         7
      36: if_icmpge     42
      39: iload         7
      41: istore_2
      42: iinc          5, 1
      45: goto          12
      48: iload_2
      49: ireturn

  public static int extractCounter(java.io.File, java.lang.String);
    Code:
       0: aload_1
       1: invokestatic  #27                 // Method java/util/regex/Pattern.compile:(Ljava/lang/String;)Ljava/util/regex/Pattern;
       4: astore_2
       5: aload_0
       6: invokevirtual #28                 // Method java/io/File.getName:()Ljava/lang/String;
       9: astore_3
      10: aload_2
      11: aload_3
      12: invokevirtual #29                 // Method java/util/regex/Pattern.matcher:(Ljava/lang/CharSequence;)Ljava/util/regex/Matcher;
      15: astore        4
      17: aload         4
      19: invokevirtual #30                 // Method java/util/regex/Matcher.matches:()Z
      22: ifne          66
      25: new           #31                 // class java/lang/IllegalStateException
      28: dup
      29: new           #11                 // class java/lang/StringBuilder
      32: dup
      33: invokespecial #12                 // Method java/lang/StringBuilder."<init>":()V
      36: ldc           #32                 // String The regex [
      38: invokevirtual #14                 // Method java/lang/StringBuilder.append:(Ljava/lang/String;)Ljava/lang/StringBuilder;
      41: aload_1
      42: invokevirtual #14                 // Method java/lang/StringBuilder.append:(Ljava/lang/String;)Ljava/lang/StringBuilder;
      45: ldc           #33                 // String ] should match [
      47: invokevirtual #14                 // Method java/lang/StringBuilder.append:(Ljava/lang/String;)Ljava/lang/StringBuilder;
      50: aload_3
      51: invokevirtual #14                 // Method java/lang/StringBuilder.append:(Ljava/lang/String;)Ljava/lang/StringBuilder;
      54: ldc           #34                 // String ]
      56: invokevirtual #14                 // Method java/lang/StringBuilder.append:(Ljava/lang/String;)Ljava/lang/StringBuilder;
      59: invokevirtual #17                 // Method java/lang/StringBuilder.toString:()Ljava/lang/String;
      62: invokespecial #35                 // Method java/lang/IllegalStateException."<init>":(Ljava/lang/String;)V
      65: athrow
      66: aload         4
      68: iconst_1
      69: invokevirtual #36                 // Method java/util/regex/Matcher.group:(I)Ljava/lang/String;
      72: astore        5
      74: new           #37                 // class java/lang/Integer
      77: dup
      78: aload         5
      80: invokespecial #38                 // Method java/lang/Integer."<init>":(Ljava/lang/String;)V
      83: invokevirtual #39                 // Method java/lang/Integer.intValue:()I
      86: ireturn

  public static java.lang.String slashify(java.lang.String);
    Code:
       0: aload_0
       1: bipush        92
       3: bipush        47
       5: invokevirtual #40                 // Method java/lang/String.replace:(CC)Ljava/lang/String;
       8: areturn

  public static void removeEmptyParentDirectories(java.io.File, int);
    Code:
       0: iload_1
       1: iconst_3
       2: if_icmplt     6
       5: return
       6: aload_0
       7: invokevirtual #41                 // Method java/io/File.getParentFile:()Ljava/io/File;
      10: astore_2
      11: aload_2
      12: invokevirtual #9                  // Method java/io/File.isDirectory:()Z
      15: ifeq          37
      18: aload_2
      19: invokestatic  #42                 // Method isEmptyDirectory:(Ljava/io/File;)Z
      22: ifeq          37
      25: aload_2
      26: invokevirtual #43                 // Method java/io/File.delete:()Z
      29: pop
      30: aload_2
      31: iload_1
      32: iconst_1
      33: iadd
      34: invokestatic  #44                 // Method removeEmptyParentDirectories:(Ljava/io/File;I)V
      37: return
}
