Compiled from "JdbcTemplate.java"
public class org.springframework.jdbc.core.JdbcTemplate extends org.springframework.jdbc.support.JdbcAccessor implements org.springframework.jdbc.core.JdbcOperations {
  private static final java.lang.String RETURN_RESULT_SET_PREFIX;

  private static final java.lang.String RETURN_UPDATE_COUNT_PREFIX;

  private boolean ignoreWarnings;

  private int fetchSize;

  private int maxRows;

  private int queryTimeout;

  private boolean skipResultsProcessing;

  private boolean skipUndeclaredResults;

  private boolean resultsMapCaseInsensitive;

  public org.springframework.jdbc.core.JdbcTemplate();
    Code:
       0: aload_0
       1: invokespecial #2                  // Method org/springframework/jdbc/support/JdbcAccessor."<init>":()V
       4: aload_0
       5: iconst_1
       6: putfield      #3                  // Field ignoreWarnings:Z
       9: aload_0
      10: iconst_m1
      11: putfield      #4                  // Field fetchSize:I
      14: aload_0
      15: iconst_m1
      16: putfield      #5                  // Field maxRows:I
      19: aload_0
      20: iconst_m1
      21: putfield      #6                  // Field queryTimeout:I
      24: aload_0
      25: iconst_0
      26: putfield      #7                  // Field skipResultsProcessing:Z
      29: aload_0
      30: iconst_0
      31: putfield      #8                  // Field skipUndeclaredResults:Z
      34: aload_0
      35: iconst_0
      36: putfield      #9                  // Field resultsMapCaseInsensitive:Z
      39: return

  public org.springframework.jdbc.core.JdbcTemplate(javax.sql.DataSource);
    Code:
       0: aload_0
       1: invokespecial #2                  // Method org/springframework/jdbc/support/JdbcAccessor."<init>":()V
       4: aload_0
       5: iconst_1
       6: putfield      #3                  // Field ignoreWarnings:Z
       9: aload_0
      10: iconst_m1
      11: putfield      #4                  // Field fetchSize:I
      14: aload_0
      15: iconst_m1
      16: putfield      #5                  // Field maxRows:I
      19: aload_0
      20: iconst_m1
      21: putfield      #6                  // Field queryTimeout:I
      24: aload_0
      25: iconst_0
      26: putfield      #7                  // Field skipResultsProcessing:Z
      29: aload_0
      30: iconst_0
      31: putfield      #8                  // Field skipUndeclaredResults:Z
      34: aload_0
      35: iconst_0
      36: putfield      #9                  // Field resultsMapCaseInsensitive:Z
      39: aload_0
      40: aload_1
      41: invokevirtual #10                 // Method setDataSource:(Ljavax/sql/DataSource;)V
      44: aload_0
      45: invokevirtual #11                 // Method afterPropertiesSet:()V
      48: return

  public org.springframework.jdbc.core.JdbcTemplate(javax.sql.DataSource, boolean);
    Code:
       0: aload_0
       1: invokespecial #2                  // Method org/springframework/jdbc/support/JdbcAccessor."<init>":()V
       4: aload_0
       5: iconst_1
       6: putfield      #3                  // Field ignoreWarnings:Z
       9: aload_0
      10: iconst_m1
      11: putfield      #4                  // Field fetchSize:I
      14: aload_0
      15: iconst_m1
      16: putfield      #5                  // Field maxRows:I
      19: aload_0
      20: iconst_m1
      21: putfield      #6                  // Field queryTimeout:I
      24: aload_0
      25: iconst_0
      26: putfield      #7                  // Field skipResultsProcessing:Z
      29: aload_0
      30: iconst_0
      31: putfield      #8                  // Field skipUndeclaredResults:Z
      34: aload_0
      35: iconst_0
      36: putfield      #9                  // Field resultsMapCaseInsensitive:Z
      39: aload_0
      40: aload_1
      41: invokevirtual #10                 // Method setDataSource:(Ljavax/sql/DataSource;)V
      44: aload_0
      45: iload_2
      46: invokevirtual #12                 // Method setLazyInit:(Z)V
      49: aload_0
      50: invokevirtual #11                 // Method afterPropertiesSet:()V
      53: return

  public void setIgnoreWarnings(boolean);
    Code:
       0: aload_0
       1: iload_1
       2: putfield      #3                  // Field ignoreWarnings:Z
       5: return

  public boolean isIgnoreWarnings();
    Code:
       0: aload_0
       1: getfield      #3                  // Field ignoreWarnings:Z
       4: ireturn

  public void setFetchSize(int);
    Code:
       0: aload_0
       1: iload_1
       2: putfield      #4                  // Field fetchSize:I
       5: return

  public int getFetchSize();
    Code:
       0: aload_0
       1: getfield      #4                  // Field fetchSize:I
       4: ireturn

  public void setMaxRows(int);
    Code:
       0: aload_0
       1: iload_1
       2: putfield      #5                  // Field maxRows:I
       5: return

  public int getMaxRows();
    Code:
       0: aload_0
       1: getfield      #5                  // Field maxRows:I
       4: ireturn

  public void setQueryTimeout(int);
    Code:
       0: aload_0
       1: iload_1
       2: putfield      #6                  // Field queryTimeout:I
       5: return

  public int getQueryTimeout();
    Code:
       0: aload_0
       1: getfield      #6                  // Field queryTimeout:I
       4: ireturn

  public void setSkipResultsProcessing(boolean);
    Code:
       0: aload_0
       1: iload_1
       2: putfield      #7                  // Field skipResultsProcessing:Z
       5: return

  public boolean isSkipResultsProcessing();
    Code:
       0: aload_0
       1: getfield      #7                  // Field skipResultsProcessing:Z
       4: ireturn

  public void setSkipUndeclaredResults(boolean);
    Code:
       0: aload_0
       1: iload_1
       2: putfield      #8                  // Field skipUndeclaredResults:Z
       5: return

  public boolean isSkipUndeclaredResults();
    Code:
       0: aload_0
       1: getfield      #8                  // Field skipUndeclaredResults:Z
       4: ireturn

  public void setResultsMapCaseInsensitive(boolean);
    Code:
       0: aload_0
       1: iload_1
       2: putfield      #9                  // Field resultsMapCaseInsensitive:Z
       5: return

  public boolean isResultsMapCaseInsensitive();
    Code:
       0: aload_0
       1: getfield      #9                  // Field resultsMapCaseInsensitive:Z
       4: ireturn

  public <T> T execute(org.springframework.jdbc.core.ConnectionCallback<T>) throws org.springframework.dao.DataAccessException;
    Code:
       0: aload_1
       1: ldc           #13                 // String Callback object must not be null
       3: invokestatic  #14                 // Method org/springframework/util/Assert.notNull:(Ljava/lang/Object;Ljava/lang/String;)V
       6: aload_0
       7: invokevirtual #15                 // Method obtainDataSource:()Ljavax/sql/DataSource;
      10: invokestatic  #16                 // Method org/springframework/jdbc/datasource/DataSourceUtils.getConnection:(Ljavax/sql/DataSource;)Ljava/sql/Connection;
      13: astore_2
      14: aload_0
      15: aload_2
      16: invokevirtual #17                 // Method createConnectionProxy:(Ljava/sql/Connection;)Ljava/sql/Connection;
      19: astore_3
      20: aload_1
      21: aload_3
      22: invokeinterface #18,  2           // InterfaceMethod org/springframework/jdbc/core/ConnectionCallback.doInConnection:(Ljava/sql/Connection;)Ljava/lang/Object;
      27: astore        4
      29: aload_2
      30: aload_0
      31: invokevirtual #19                 // Method getDataSource:()Ljavax/sql/DataSource;
      34: invokestatic  #20                 // Method org/springframework/jdbc/datasource/DataSourceUtils.releaseConnection:(Ljava/sql/Connection;Ljavax/sql/DataSource;)V
      37: aload         4
      39: areturn
      40: astore_3
      41: aload_1
      42: invokestatic  #22                 // Method getSql:(Ljava/lang/Object;)Ljava/lang/String;
      45: astore        4
      47: aload_2
      48: aload_0
      49: invokevirtual #19                 // Method getDataSource:()Ljavax/sql/DataSource;
      52: invokestatic  #20                 // Method org/springframework/jdbc/datasource/DataSourceUtils.releaseConnection:(Ljava/sql/Connection;Ljavax/sql/DataSource;)V
      55: aconst_null
      56: astore_2
      57: aload_0
      58: ldc           #23                 // String ConnectionCallback
      60: aload         4
      62: aload_3
      63: invokevirtual #24                 // Method translateException:(Ljava/lang/String;Ljava/lang/String;Ljava/sql/SQLException;)Lorg/springframework/dao/DataAccessException;
      66: athrow
      67: astore        5
      69: aload_2
      70: aload_0
      71: invokevirtual #19                 // Method getDataSource:()Ljavax/sql/DataSource;
      74: invokestatic  #20                 // Method org/springframework/jdbc/datasource/DataSourceUtils.releaseConnection:(Ljava/sql/Connection;Ljavax/sql/DataSource;)V
      77: aload         5
      79: athrow
    Exception table:
       from    to  target type
          14    29    40   Class java/sql/SQLException
          14    29    67   any
          40    69    67   any

  protected java.sql.Connection createConnectionProxy(java.sql.Connection);
    Code:
       0: ldc           #25                 // class org/springframework/jdbc/datasource/ConnectionProxy
       2: invokevirtual #26                 // Method java/lang/Class.getClassLoader:()Ljava/lang/ClassLoader;
       5: iconst_1
       6: anewarray     #27                 // class java/lang/Class
       9: dup
      10: iconst_0
      11: ldc           #25                 // class org/springframework/jdbc/datasource/ConnectionProxy
      13: aastore
      14: new           #28                 // class org/springframework/jdbc/core/JdbcTemplate$CloseSuppressingInvocationHandler
      17: dup
      18: aload_0
      19: aload_1
      20: invokespecial #29                 // Method org/springframework/jdbc/core/JdbcTemplate$CloseSuppressingInvocationHandler."<init>":(Lorg/springframework/jdbc/core/JdbcTemplate;Ljava/sql/Connection;)V
      23: invokestatic  #30                 // Method java/lang/reflect/Proxy.newProxyInstance:(Ljava/lang/ClassLoader;[Ljava/lang/Class;Ljava/lang/reflect/InvocationHandler;)Ljava/lang/Object;
      26: checkcast     #31                 // class java/sql/Connection
      29: areturn

  public <T> T execute(org.springframework.jdbc.core.StatementCallback<T>) throws org.springframework.dao.DataAccessException;
    Code:
       0: aload_1
       1: ldc           #13                 // String Callback object must not be null
       3: invokestatic  #14                 // Method org/springframework/util/Assert.notNull:(Ljava/lang/Object;Ljava/lang/String;)V
       6: aload_0
       7: invokevirtual #15                 // Method obtainDataSource:()Ljavax/sql/DataSource;
      10: invokestatic  #16                 // Method org/springframework/jdbc/datasource/DataSourceUtils.getConnection:(Ljavax/sql/DataSource;)Ljava/sql/Connection;
      13: astore_2
      14: aconst_null
      15: astore_3
      16: aload_2
      17: invokeinterface #32,  1           // InterfaceMethod java/sql/Connection.createStatement:()Ljava/sql/Statement;
      22: astore_3
      23: aload_0
      24: aload_3
      25: invokevirtual #33                 // Method applyStatementSettings:(Ljava/sql/Statement;)V
      28: aload_1
      29: aload_3
      30: invokeinterface #34,  2           // InterfaceMethod org/springframework/jdbc/core/StatementCallback.doInStatement:(Ljava/sql/Statement;)Ljava/lang/Object;
      35: astore        4
      37: aload_0
      38: aload_3
      39: invokevirtual #35                 // Method handleWarnings:(Ljava/sql/Statement;)V
      42: aload         4
      44: astore        5
      46: aload_3
      47: invokestatic  #36                 // Method org/springframework/jdbc/support/JdbcUtils.closeStatement:(Ljava/sql/Statement;)V
      50: aload_2
      51: aload_0
      52: invokevirtual #19                 // Method getDataSource:()Ljavax/sql/DataSource;
      55: invokestatic  #20                 // Method org/springframework/jdbc/datasource/DataSourceUtils.releaseConnection:(Ljava/sql/Connection;Ljavax/sql/DataSource;)V
      58: aload         5
      60: areturn
      61: astore        4
      63: aload_1
      64: invokestatic  #22                 // Method getSql:(Ljava/lang/Object;)Ljava/lang/String;
      67: astore        5
      69: aload_3
      70: invokestatic  #36                 // Method org/springframework/jdbc/support/JdbcUtils.closeStatement:(Ljava/sql/Statement;)V
      73: aconst_null
      74: astore_3
      75: aload_2
      76: aload_0
      77: invokevirtual #19                 // Method getDataSource:()Ljavax/sql/DataSource;
      80: invokestatic  #20                 // Method org/springframework/jdbc/datasource/DataSourceUtils.releaseConnection:(Ljava/sql/Connection;Ljavax/sql/DataSource;)V
      83: aconst_null
      84: astore_2
      85: aload_0
      86: ldc           #37                 // String StatementCallback
      88: aload         5
      90: aload         4
      92: invokevirtual #24                 // Method translateException:(Ljava/lang/String;Ljava/lang/String;Ljava/sql/SQLException;)Lorg/springframework/dao/DataAccessException;
      95: athrow
      96: astore        6
      98: aload_3
      99: invokestatic  #36                 // Method org/springframework/jdbc/support/JdbcUtils.closeStatement:(Ljava/sql/Statement;)V
     102: aload_2
     103: aload_0
     104: invokevirtual #19                 // Method getDataSource:()Ljavax/sql/DataSource;
     107: invokestatic  #20                 // Method org/springframework/jdbc/datasource/DataSourceUtils.releaseConnection:(Ljava/sql/Connection;Ljavax/sql/DataSource;)V
     110: aload         6
     112: athrow
    Exception table:
       from    to  target type
          16    46    61   Class java/sql/SQLException
          16    46    96   any
          61    98    96   any

  public void execute(java.lang.String) throws org.springframework.dao.DataAccessException;
    Code:
       0: aload_0
       1: getfield      #1                  // Field logger:Lorg/apache/commons/logging/Log;
       4: invokeinterface #38,  1           // InterfaceMethod org/apache/commons/logging/Log.isDebugEnabled:()Z
       9: ifeq          45
      12: aload_0
      13: getfield      #1                  // Field logger:Lorg/apache/commons/logging/Log;
      16: new           #39                 // class java/lang/StringBuilder
      19: dup
      20: invokespecial #40                 // Method java/lang/StringBuilder."<init>":()V
      23: ldc           #41                 // String Executing SQL statement [
      25: invokevirtual #42                 // Method java/lang/StringBuilder.append:(Ljava/lang/String;)Ljava/lang/StringBuilder;
      28: aload_1
      29: invokevirtual #42                 // Method java/lang/StringBuilder.append:(Ljava/lang/String;)Ljava/lang/StringBuilder;
      32: ldc           #43                 // String ]
      34: invokevirtual #42                 // Method java/lang/StringBuilder.append:(Ljava/lang/String;)Ljava/lang/StringBuilder;
      37: invokevirtual #44                 // Method java/lang/StringBuilder.toString:()Ljava/lang/String;
      40: invokeinterface #45,  2           // InterfaceMethod org/apache/commons/logging/Log.debug:(Ljava/lang/Object;)V
      45: aload_0
      46: new           #46                 // class org/springframework/jdbc/core/JdbcTemplate$1ExecuteStatementCallback
      49: dup
      50: aload_0
      51: aload_1
      52: invokespecial #47                 // Method org/springframework/jdbc/core/JdbcTemplate$1ExecuteStatementCallback."<init>":(Lorg/springframework/jdbc/core/JdbcTemplate;Ljava/lang/String;)V
      55: invokevirtual #48                 // Method execute:(Lorg/springframework/jdbc/core/StatementCallback;)Ljava/lang/Object;
      58: pop
      59: return

  public <T> T query(java.lang.String, org.springframework.jdbc.core.ResultSetExtractor<T>) throws org.springframework.dao.DataAccessException;
    Code:
       0: aload_1
       1: ldc           #49                 // String SQL must not be null
       3: invokestatic  #14                 // Method org/springframework/util/Assert.notNull:(Ljava/lang/Object;Ljava/lang/String;)V
       6: aload_2
       7: ldc           #50                 // String ResultSetExtractor must not be null
       9: invokestatic  #14                 // Method org/springframework/util/Assert.notNull:(Ljava/lang/Object;Ljava/lang/String;)V
      12: aload_0
      13: getfield      #1                  // Field logger:Lorg/apache/commons/logging/Log;
      16: invokeinterface #38,  1           // InterfaceMethod org/apache/commons/logging/Log.isDebugEnabled:()Z
      21: ifeq          57
      24: aload_0
      25: getfield      #1                  // Field logger:Lorg/apache/commons/logging/Log;
      28: new           #39                 // class java/lang/StringBuilder
      31: dup
      32: invokespecial #40                 // Method java/lang/StringBuilder."<init>":()V
      35: ldc           #51                 // String Executing SQL query [
      37: invokevirtual #42                 // Method java/lang/StringBuilder.append:(Ljava/lang/String;)Ljava/lang/StringBuilder;
      40: aload_1
      41: invokevirtual #42                 // Method java/lang/StringBuilder.append:(Ljava/lang/String;)Ljava/lang/StringBuilder;
      44: ldc           #43                 // String ]
      46: invokevirtual #42                 // Method java/lang/StringBuilder.append:(Ljava/lang/String;)Ljava/lang/StringBuilder;
      49: invokevirtual #44                 // Method java/lang/StringBuilder.toString:()Ljava/lang/String;
      52: invokeinterface #45,  2           // InterfaceMethod org/apache/commons/logging/Log.debug:(Ljava/lang/Object;)V
      57: aload_0
      58: new           #52                 // class org/springframework/jdbc/core/JdbcTemplate$1QueryStatementCallback
      61: dup
      62: aload_0
      63: aload_1
      64: aload_2
      65: invokespecial #53                 // Method org/springframework/jdbc/core/JdbcTemplate$1QueryStatementCallback."<init>":(Lorg/springframework/jdbc/core/JdbcTemplate;Ljava/lang/String;Lorg/springframework/jdbc/core/ResultSetExtractor;)V
      68: invokevirtual #48                 // Method execute:(Lorg/springframework/jdbc/core/StatementCallback;)Ljava/lang/Object;
      71: areturn

  public void query(java.lang.String, org.springframework.jdbc.core.RowCallbackHandler) throws org.springframework.dao.DataAccessException;
    Code:
       0: aload_0
       1: aload_1
       2: new           #54                 // class org/springframework/jdbc/core/JdbcTemplate$RowCallbackHandlerResultSetExtractor
       5: dup
       6: aload_2
       7: invokespecial #55                 // Method org/springframework/jdbc/core/JdbcTemplate$RowCallbackHandlerResultSetExtractor."<init>":(Lorg/springframework/jdbc/core/RowCallbackHandler;)V
      10: invokevirtual #56                 // Method query:(Ljava/lang/String;Lorg/springframework/jdbc/core/ResultSetExtractor;)Ljava/lang/Object;
      13: pop
      14: return

  public <T> java.util.List<T> query(java.lang.String, org.springframework.jdbc.core.RowMapper<T>) throws org.springframework.dao.DataAccessException;
    Code:
       0: aload_0
       1: aload_1
       2: new           #57                 // class org/springframework/jdbc/core/RowMapperResultSetExtractor
       5: dup
       6: aload_2
       7: invokespecial #58                 // Method org/springframework/jdbc/core/RowMapperResultSetExtractor."<init>":(Lorg/springframework/jdbc/core/RowMapper;)V
      10: invokevirtual #56                 // Method query:(Ljava/lang/String;Lorg/springframework/jdbc/core/ResultSetExtractor;)Ljava/lang/Object;
      13: invokestatic  #59                 // Method result:(Ljava/lang/Object;)Ljava/lang/Object;
      16: checkcast     #60                 // class java/util/List
      19: areturn

  public java.util.Map<java.lang.String, java.lang.Object> queryForMap(java.lang.String) throws org.springframework.dao.DataAccessException;
    Code:
       0: aload_0
       1: aload_1
       2: aload_0
       3: invokevirtual #61                 // Method getColumnMapRowMapper:()Lorg/springframework/jdbc/core/RowMapper;
       6: invokevirtual #62                 // Method queryForObject:(Ljava/lang/String;Lorg/springframework/jdbc/core/RowMapper;)Ljava/lang/Object;
       9: invokestatic  #59                 // Method result:(Ljava/lang/Object;)Ljava/lang/Object;
      12: checkcast     #63                 // class java/util/Map
      15: areturn

  public <T> T queryForObject(java.lang.String, org.springframework.jdbc.core.RowMapper<T>) throws org.springframework.dao.DataAccessException;
    Code:
       0: aload_0
       1: aload_1
       2: aload_2
       3: invokevirtual #64                 // Method query:(Ljava/lang/String;Lorg/springframework/jdbc/core/RowMapper;)Ljava/util/List;
       6: astore_3
       7: aload_3
       8: invokestatic  #65                 // Method org/springframework/dao/support/DataAccessUtils.nullableSingleResult:(Ljava/util/Collection;)Ljava/lang/Object;
      11: areturn

  public <T> T queryForObject(java.lang.String, java.lang.Class<T>) throws org.springframework.dao.DataAccessException;
    Code:
       0: aload_0
       1: aload_1
       2: aload_0
       3: aload_2
       4: invokevirtual #66                 // Method getSingleColumnRowMapper:(Ljava/lang/Class;)Lorg/springframework/jdbc/core/RowMapper;
       7: invokevirtual #62                 // Method queryForObject:(Ljava/lang/String;Lorg/springframework/jdbc/core/RowMapper;)Ljava/lang/Object;
      10: areturn

  public <T> java.util.List<T> queryForList(java.lang.String, java.lang.Class<T>) throws org.springframework.dao.DataAccessException;
    Code:
       0: aload_0
       1: aload_1
       2: aload_0
       3: aload_2
       4: invokevirtual #66                 // Method getSingleColumnRowMapper:(Ljava/lang/Class;)Lorg/springframework/jdbc/core/RowMapper;
       7: invokevirtual #64                 // Method query:(Ljava/lang/String;Lorg/springframework/jdbc/core/RowMapper;)Ljava/util/List;
      10: areturn

  public java.util.List<java.util.Map<java.lang.String, java.lang.Object>> queryForList(java.lang.String) throws org.springframework.dao.DataAccessException;
    Code:
       0: aload_0
       1: aload_1
       2: aload_0
       3: invokevirtual #61                 // Method getColumnMapRowMapper:()Lorg/springframework/jdbc/core/RowMapper;
       6: invokevirtual #64                 // Method query:(Ljava/lang/String;Lorg/springframework/jdbc/core/RowMapper;)Ljava/util/List;
       9: areturn

  public org.springframework.jdbc.support.rowset.SqlRowSet queryForRowSet(java.lang.String) throws org.springframework.dao.DataAccessException;
    Code:
       0: aload_0
       1: aload_1
       2: new           #67                 // class org/springframework/jdbc/core/SqlRowSetResultSetExtractor
       5: dup
       6: invokespecial #68                 // Method org/springframework/jdbc/core/SqlRowSetResultSetExtractor."<init>":()V
       9: invokevirtual #56                 // Method query:(Ljava/lang/String;Lorg/springframework/jdbc/core/ResultSetExtractor;)Ljava/lang/Object;
      12: invokestatic  #59                 // Method result:(Ljava/lang/Object;)Ljava/lang/Object;
      15: checkcast     #69                 // class org/springframework/jdbc/support/rowset/SqlRowSet
      18: areturn

  public int update(java.lang.String) throws org.springframework.dao.DataAccessException;
    Code:
       0: aload_1
       1: ldc           #49                 // String SQL must not be null
       3: invokestatic  #14                 // Method org/springframework/util/Assert.notNull:(Ljava/lang/Object;Ljava/lang/String;)V
       6: aload_0
       7: getfield      #1                  // Field logger:Lorg/apache/commons/logging/Log;
      10: invokeinterface #38,  1           // InterfaceMethod org/apache/commons/logging/Log.isDebugEnabled:()Z
      15: ifeq          51
      18: aload_0
      19: getfield      #1                  // Field logger:Lorg/apache/commons/logging/Log;
      22: new           #39                 // class java/lang/StringBuilder
      25: dup
      26: invokespecial #40                 // Method java/lang/StringBuilder."<init>":()V
      29: ldc           #70                 // String Executing SQL update [
      31: invokevirtual #42                 // Method java/lang/StringBuilder.append:(Ljava/lang/String;)Ljava/lang/StringBuilder;
      34: aload_1
      35: invokevirtual #42                 // Method java/lang/StringBuilder.append:(Ljava/lang/String;)Ljava/lang/StringBuilder;
      38: ldc           #43                 // String ]
      40: invokevirtual #42                 // Method java/lang/StringBuilder.append:(Ljava/lang/String;)Ljava/lang/StringBuilder;
      43: invokevirtual #44                 // Method java/lang/StringBuilder.toString:()Ljava/lang/String;
      46: invokeinterface #45,  2           // InterfaceMethod org/apache/commons/logging/Log.debug:(Ljava/lang/Object;)V
      51: aload_0
      52: new           #71                 // class org/springframework/jdbc/core/JdbcTemplate$1UpdateStatementCallback
      55: dup
      56: aload_0
      57: aload_1
      58: invokespecial #72                 // Method org/springframework/jdbc/core/JdbcTemplate$1UpdateStatementCallback."<init>":(Lorg/springframework/jdbc/core/JdbcTemplate;Ljava/lang/String;)V
      61: invokevirtual #48                 // Method execute:(Lorg/springframework/jdbc/core/StatementCallback;)Ljava/lang/Object;
      64: checkcast     #73                 // class java/lang/Integer
      67: invokestatic  #74                 // Method updateCount:(Ljava/lang/Integer;)I
      70: ireturn

  public int[] batchUpdate(java.lang.String...) throws org.springframework.dao.DataAccessException;
    Code:
       0: aload_1
       1: ldc           #75                 // String SQL array must not be empty
       3: invokestatic  #76                 // Method org/springframework/util/Assert.notEmpty:([Ljava/lang/Object;Ljava/lang/String;)V
       6: aload_0
       7: getfield      #1                  // Field logger:Lorg/apache/commons/logging/Log;
      10: invokeinterface #38,  1           // InterfaceMethod org/apache/commons/logging/Log.isDebugEnabled:()Z
      15: ifeq          52
      18: aload_0
      19: getfield      #1                  // Field logger:Lorg/apache/commons/logging/Log;
      22: new           #39                 // class java/lang/StringBuilder
      25: dup
      26: invokespecial #40                 // Method java/lang/StringBuilder."<init>":()V
      29: ldc           #77                 // String Executing SQL batch update of
      31: invokevirtual #42                 // Method java/lang/StringBuilder.append:(Ljava/lang/String;)Ljava/lang/StringBuilder;
      34: aload_1
      35: arraylength
      36: invokevirtual #78                 // Method java/lang/StringBuilder.append:(I)Ljava/lang/StringBuilder;
      39: ldc           #79                 // String  statements
      41: invokevirtual #42                 // Method java/lang/StringBuilder.append:(Ljava/lang/String;)Ljava/lang/StringBuilder;
      44: invokevirtual #44                 // Method java/lang/StringBuilder.toString:()Ljava/lang/String;
      47: invokeinterface #45,  2           // InterfaceMethod org/apache/commons/logging/Log.debug:(Ljava/lang/Object;)V
      52: aload_0
      53: new           #80                 // class org/springframework/jdbc/core/JdbcTemplate$1BatchUpdateStatementCallback
      56: dup
      57: aload_0
      58: aload_1
      59: invokespecial #81                 // Method org/springframework/jdbc/core/JdbcTemplate$1BatchUpdateStatementCallback."<init>":(Lorg/springframework/jdbc/core/JdbcTemplate;[Ljava/lang/String;)V
      62: invokevirtual #48                 // Method execute:(Lorg/springframework/jdbc/core/StatementCallback;)Ljava/lang/Object;
      65: checkcast     #82                 // class "[I"
      68: astore_2
      69: aload_2
      70: ifnull        77
      73: iconst_1
      74: goto          78
      77: iconst_0
      78: ldc           #83                 // String No update counts
      80: invokestatic  #84                 // Method org/springframework/util/Assert.state:(ZLjava/lang/String;)V
      83: aload_2
      84: areturn

  public <T> T execute(org.springframework.jdbc.core.PreparedStatementCreator, org.springframework.jdbc.core.PreparedStatementCallback<T>) throws org.springframework.dao.DataAccessException;
    Code:
       0: aload_1
       1: ldc           #85                 // String PreparedStatementCreator must not be null
       3: invokestatic  #14                 // Method org/springframework/util/Assert.notNull:(Ljava/lang/Object;Ljava/lang/String;)V
       6: aload_2
       7: ldc           #13                 // String Callback object must not be null
       9: invokestatic  #14                 // Method org/springframework/util/Assert.notNull:(Ljava/lang/Object;Ljava/lang/String;)V
      12: aload_0
      13: getfield      #1                  // Field logger:Lorg/apache/commons/logging/Log;
      16: invokeinterface #38,  1           // InterfaceMethod org/apache/commons/logging/Log.isDebugEnabled:()Z
      21: ifeq          89
      24: aload_1
      25: invokestatic  #22                 // Method getSql:(Ljava/lang/Object;)Ljava/lang/String;
      28: astore_3
      29: aload_0
      30: getfield      #1                  // Field logger:Lorg/apache/commons/logging/Log;
      33: new           #39                 // class java/lang/StringBuilder
      36: dup
      37: invokespecial #40                 // Method java/lang/StringBuilder."<init>":()V
      40: ldc           #86                 // String Executing prepared SQL statement
      42: invokevirtual #42                 // Method java/lang/StringBuilder.append:(Ljava/lang/String;)Ljava/lang/StringBuilder;
      45: aload_3
      46: ifnull        76
      49: new           #39                 // class java/lang/StringBuilder
      52: dup
      53: invokespecial #40                 // Method java/lang/StringBuilder."<init>":()V
      56: ldc           #87                 // String  [
      58: invokevirtual #42                 // Method java/lang/StringBuilder.append:(Ljava/lang/String;)Ljava/lang/StringBuilder;
      61: aload_3
      62: invokevirtual #42                 // Method java/lang/StringBuilder.append:(Ljava/lang/String;)Ljava/lang/StringBuilder;
      65: ldc           #43                 // String ]
      67: invokevirtual #42                 // Method java/lang/StringBuilder.append:(Ljava/lang/String;)Ljava/lang/StringBuilder;
      70: invokevirtual #44                 // Method java/lang/StringBuilder.toString:()Ljava/lang/String;
      73: goto          78
      76: ldc           #88                 // String
      78: invokevirtual #42                 // Method java/lang/StringBuilder.append:(Ljava/lang/String;)Ljava/lang/StringBuilder;
      81: invokevirtual #44                 // Method java/lang/StringBuilder.toString:()Ljava/lang/String;
      84: invokeinterface #45,  2           // InterfaceMethod org/apache/commons/logging/Log.debug:(Ljava/lang/Object;)V
      89: aload_0
      90: invokevirtual #15                 // Method obtainDataSource:()Ljavax/sql/DataSource;
      93: invokestatic  #16                 // Method org/springframework/jdbc/datasource/DataSourceUtils.getConnection:(Ljavax/sql/DataSource;)Ljava/sql/Connection;
      96: astore_3
      97: aconst_null
      98: astore        4
     100: aload_1
     101: aload_3
     102: invokeinterface #89,  2           // InterfaceMethod org/springframework/jdbc/core/PreparedStatementCreator.createPreparedStatement:(Ljava/sql/Connection;)Ljava/sql/PreparedStatement;
     107: astore        4
     109: aload_0
     110: aload         4
     112: invokevirtual #33                 // Method applyStatementSettings:(Ljava/sql/Statement;)V
     115: aload_2
     116: aload         4
     118: invokeinterface #90,  2           // InterfaceMethod org/springframework/jdbc/core/PreparedStatementCallback.doInPreparedStatement:(Ljava/sql/PreparedStatement;)Ljava/lang/Object;
     123: astore        5
     125: aload_0
     126: aload         4
     128: invokevirtual #35                 // Method handleWarnings:(Ljava/sql/Statement;)V
     131: aload         5
     133: astore        6
     135: aload_1
     136: instanceof    #91                 // class org/springframework/jdbc/core/ParameterDisposer
     139: ifeq          151
     142: aload_1
     143: checkcast     #91                 // class org/springframework/jdbc/core/ParameterDisposer
     146: invokeinterface #92,  1           // InterfaceMethod org/springframework/jdbc/core/ParameterDisposer.cleanupParameters:()V
     151: aload         4
     153: invokestatic  #36                 // Method org/springframework/jdbc/support/JdbcUtils.closeStatement:(Ljava/sql/Statement;)V
     156: aload_3
     157: aload_0
     158: invokevirtual #19                 // Method getDataSource:()Ljavax/sql/DataSource;
     161: invokestatic  #20                 // Method org/springframework/jdbc/datasource/DataSourceUtils.releaseConnection:(Ljava/sql/Connection;Ljavax/sql/DataSource;)V
     164: aload         6
     166: areturn
     167: astore        5
     169: aload_1
     170: instanceof    #91                 // class org/springframework/jdbc/core/ParameterDisposer
     173: ifeq          185
     176: aload_1
     177: checkcast     #91                 // class org/springframework/jdbc/core/ParameterDisposer
     180: invokeinterface #92,  1           // InterfaceMethod org/springframework/jdbc/core/ParameterDisposer.cleanupParameters:()V
     185: aload_1
     186: invokestatic  #22                 // Method getSql:(Ljava/lang/Object;)Ljava/lang/String;
     189: astore        6
     191: aconst_null
     192: astore_1
     193: aload         4
     195: invokestatic  #36                 // Method org/springframework/jdbc/support/JdbcUtils.closeStatement:(Ljava/sql/Statement;)V
     198: aconst_null
     199: astore        4
     201: aload_3
     202: aload_0
     203: invokevirtual #19                 // Method getDataSource:()Ljavax/sql/DataSource;
     206: invokestatic  #20                 // Method org/springframework/jdbc/datasource/DataSourceUtils.releaseConnection:(Ljava/sql/Connection;Ljavax/sql/DataSource;)V
     209: aconst_null
     210: astore_3
     211: aload_0
     212: ldc           #93                 // String PreparedStatementCallback
     214: aload         6
     216: aload         5
     218: invokevirtual #24                 // Method translateException:(Ljava/lang/String;Ljava/lang/String;Ljava/sql/SQLException;)Lorg/springframework/dao/DataAccessException;
     221: athrow
     222: astore        7
     224: aload_1
     225: instanceof    #91                 // class org/springframework/jdbc/core/ParameterDisposer
     228: ifeq          240
     231: aload_1
     232: checkcast     #91                 // class org/springframework/jdbc/core/ParameterDisposer
     235: invokeinterface #92,  1           // InterfaceMethod org/springframework/jdbc/core/ParameterDisposer.cleanupParameters:()V
     240: aload         4
     242: invokestatic  #36                 // Method org/springframework/jdbc/support/JdbcUtils.closeStatement:(Ljava/sql/Statement;)V
     245: aload_3
     246: aload_0
     247: invokevirtual #19                 // Method getDataSource:()Ljavax/sql/DataSource;
     250: invokestatic  #20                 // Method org/springframework/jdbc/datasource/DataSourceUtils.releaseConnection:(Ljava/sql/Connection;Ljavax/sql/DataSource;)V
     253: aload         7
     255: athrow
    Exception table:
       from    to  target type
         100   135   167   Class java/sql/SQLException
         100   135   222   any
         167   224   222   any

  public <T> T execute(java.lang.String, org.springframework.jdbc.core.PreparedStatementCallback<T>) throws org.springframework.dao.DataAccessException;
    Code:
       0: aload_0
       1: new           #94                 // class org/springframework/jdbc/core/JdbcTemplate$SimplePreparedStatementCreator
       4: dup
       5: aload_1
       6: invokespecial #95                 // Method org/springframework/jdbc/core/JdbcTemplate$SimplePreparedStatementCreator."<init>":(Ljava/lang/String;)V
       9: aload_2
      10: invokevirtual #96                 // Method execute:(Lorg/springframework/jdbc/core/PreparedStatementCreator;Lorg/springframework/jdbc/core/PreparedStatementCallback;)Ljava/lang/Object;
      13: areturn

  public <T> T query(org.springframework.jdbc.core.PreparedStatementCreator, org.springframework.jdbc.core.PreparedStatementSetter, org.springframework.jdbc.core.ResultSetExtractor<T>) throws org.springframework.dao.DataAccessException;
    Code:
       0: aload_3
       1: ldc           #50                 // String ResultSetExtractor must not be null
       3: invokestatic  #14                 // Method org/springframework/util/Assert.notNull:(Ljava/lang/Object;Ljava/lang/String;)V
       6: aload_0
       7: getfield      #1                  // Field logger:Lorg/apache/commons/logging/Log;
      10: ldc           #97                 // String Executing prepared SQL query
      12: invokeinterface #45,  2           // InterfaceMethod org/apache/commons/logging/Log.debug:(Ljava/lang/Object;)V
      17: aload_0
      18: aload_1
      19: new           #98                 // class org/springframework/jdbc/core/JdbcTemplate$1
      22: dup
      23: aload_0
      24: aload_2
      25: aload_3
      26: invokespecial #99                 // Method org/springframework/jdbc/core/JdbcTemplate$1."<init>":(Lorg/springframework/jdbc/core/JdbcTemplate;Lorg/springframework/jdbc/core/PreparedStatementSetter;Lorg/springframework/jdbc/core/ResultSetExtractor;)V
      29: invokevirtual #96                 // Method execute:(Lorg/springframework/jdbc/core/PreparedStatementCreator;Lorg/springframework/jdbc/core/PreparedStatementCallback;)Ljava/lang/Object;
      32: areturn

  public <T> T query(org.springframework.jdbc.core.PreparedStatementCreator, org.springframework.jdbc.core.ResultSetExtractor<T>) throws org.springframework.dao.DataAccessException;
    Code:
       0: aload_0
       1: aload_1
       2: aconst_null
       3: aload_2
       4: invokevirtual #100                // Method query:(Lorg/springframework/jdbc/core/PreparedStatementCreator;Lorg/springframework/jdbc/core/PreparedStatementSetter;Lorg/springframework/jdbc/core/ResultSetExtractor;)Ljava/lang/Object;
       7: areturn

  public <T> T query(java.lang.String, org.springframework.jdbc.core.PreparedStatementSetter, org.springframework.jdbc.core.ResultSetExtractor<T>) throws org.springframework.dao.DataAccessException;
    Code:
       0: aload_0
       1: new           #94                 // class org/springframework/jdbc/core/JdbcTemplate$SimplePreparedStatementCreator
       4: dup
       5: aload_1
       6: invokespecial #95                 // Method org/springframework/jdbc/core/JdbcTemplate$SimplePreparedStatementCreator."<init>":(Ljava/lang/String;)V
       9: aload_2
      10: aload_3
      11: invokevirtual #100                // Method query:(Lorg/springframework/jdbc/core/PreparedStatementCreator;Lorg/springframework/jdbc/core/PreparedStatementSetter;Lorg/springframework/jdbc/core/ResultSetExtractor;)Ljava/lang/Object;
      14: areturn

  public <T> T query(java.lang.String, java.lang.Object[], int[], org.springframework.jdbc.core.ResultSetExtractor<T>) throws org.springframework.dao.DataAccessException;
    Code:
       0: aload_0
       1: aload_1
       2: aload_0
       3: aload_2
       4: aload_3
       5: invokevirtual #101                // Method newArgTypePreparedStatementSetter:([Ljava/lang/Object;[I)Lorg/springframework/jdbc/core/PreparedStatementSetter;
       8: aload         4
      10: invokevirtual #102                // Method query:(Ljava/lang/String;Lorg/springframework/jdbc/core/PreparedStatementSetter;Lorg/springframework/jdbc/core/ResultSetExtractor;)Ljava/lang/Object;
      13: areturn

  public <T> T query(java.lang.String, java.lang.Object[], org.springframework.jdbc.core.ResultSetExtractor<T>) throws org.springframework.dao.DataAccessException;
    Code:
       0: aload_0
       1: aload_1
       2: aload_0
       3: aload_2
       4: invokevirtual #103                // Method newArgPreparedStatementSetter:([Ljava/lang/Object;)Lorg/springframework/jdbc/core/PreparedStatementSetter;
       7: aload_3
       8: invokevirtual #102                // Method query:(Ljava/lang/String;Lorg/springframework/jdbc/core/PreparedStatementSetter;Lorg/springframework/jdbc/core/ResultSetExtractor;)Ljava/lang/Object;
      11: areturn

  public <T> T query(java.lang.String, org.springframework.jdbc.core.ResultSetExtractor<T>, java.lang.Object...) throws org.springframework.dao.DataAccessException;
    Code:
       0: aload_0
       1: aload_1
       2: aload_0
       3: aload_3
       4: invokevirtual #103                // Method newArgPreparedStatementSetter:([Ljava/lang/Object;)Lorg/springframework/jdbc/core/PreparedStatementSetter;
       7: aload_2
       8: invokevirtual #102                // Method query:(Ljava/lang/String;Lorg/springframework/jdbc/core/PreparedStatementSetter;Lorg/springframework/jdbc/core/ResultSetExtractor;)Ljava/lang/Object;
      11: areturn

  public void query(org.springframework.jdbc.core.PreparedStatementCreator, org.springframework.jdbc.core.RowCallbackHandler) throws org.springframework.dao.DataAccessException;
    Code:
       0: aload_0
       1: aload_1
       2: new           #54                 // class org/springframework/jdbc/core/JdbcTemplate$RowCallbackHandlerResultSetExtractor
       5: dup
       6: aload_2
       7: invokespecial #55                 // Method org/springframework/jdbc/core/JdbcTemplate$RowCallbackHandlerResultSetExtractor."<init>":(Lorg/springframework/jdbc/core/RowCallbackHandler;)V
      10: invokevirtual #104                // Method query:(Lorg/springframework/jdbc/core/PreparedStatementCreator;Lorg/springframework/jdbc/core/ResultSetExtractor;)Ljava/lang/Object;
      13: pop
      14: return

  public void query(java.lang.String, org.springframework.jdbc.core.PreparedStatementSetter, org.springframework.jdbc.core.RowCallbackHandler) throws org.springframework.dao.DataAccessException;
    Code:
       0: aload_0
       1: aload_1
       2: aload_2
       3: new           #54                 // class org/springframework/jdbc/core/JdbcTemplate$RowCallbackHandlerResultSetExtractor
       6: dup
       7: aload_3
       8: invokespecial #55                 // Method org/springframework/jdbc/core/JdbcTemplate$RowCallbackHandlerResultSetExtractor."<init>":(Lorg/springframework/jdbc/core/RowCallbackHandler;)V
      11: invokevirtual #102                // Method query:(Ljava/lang/String;Lorg/springframework/jdbc/core/PreparedStatementSetter;Lorg/springframework/jdbc/core/ResultSetExtractor;)Ljava/lang/Object;
      14: pop
      15: return

  public void query(java.lang.String, java.lang.Object[], int[], org.springframework.jdbc.core.RowCallbackHandler) throws org.springframework.dao.DataAccessException;
    Code:
       0: aload_0
       1: aload_1
       2: aload_0
       3: aload_2
       4: aload_3
       5: invokevirtual #101                // Method newArgTypePreparedStatementSetter:([Ljava/lang/Object;[I)Lorg/springframework/jdbc/core/PreparedStatementSetter;
       8: aload         4
      10: invokevirtual #105                // Method query:(Ljava/lang/String;Lorg/springframework/jdbc/core/PreparedStatementSetter;Lorg/springframework/jdbc/core/RowCallbackHandler;)V
      13: return

  public void query(java.lang.String, java.lang.Object[], org.springframework.jdbc.core.RowCallbackHandler) throws org.springframework.dao.DataAccessException;
    Code:
       0: aload_0
       1: aload_1
       2: aload_0
       3: aload_2
       4: invokevirtual #103                // Method newArgPreparedStatementSetter:([Ljava/lang/Object;)Lorg/springframework/jdbc/core/PreparedStatementSetter;
       7: aload_3
       8: invokevirtual #105                // Method query:(Ljava/lang/String;Lorg/springframework/jdbc/core/PreparedStatementSetter;Lorg/springframework/jdbc/core/RowCallbackHandler;)V
      11: return

  public void query(java.lang.String, org.springframework.jdbc.core.RowCallbackHandler, java.lang.Object...) throws org.springframework.dao.DataAccessException;
    Code:
       0: aload_0
       1: aload_1
       2: aload_0
       3: aload_3
       4: invokevirtual #103                // Method newArgPreparedStatementSetter:([Ljava/lang/Object;)Lorg/springframework/jdbc/core/PreparedStatementSetter;
       7: aload_2
       8: invokevirtual #105                // Method query:(Ljava/lang/String;Lorg/springframework/jdbc/core/PreparedStatementSetter;Lorg/springframework/jdbc/core/RowCallbackHandler;)V
      11: return

  public <T> java.util.List<T> query(org.springframework.jdbc.core.PreparedStatementCreator, org.springframework.jdbc.core.RowMapper<T>) throws org.springframework.dao.DataAccessException;
    Code:
       0: aload_0
       1: aload_1
       2: new           #57                 // class org/springframework/jdbc/core/RowMapperResultSetExtractor
       5: dup
       6: aload_2
       7: invokespecial #58                 // Method org/springframework/jdbc/core/RowMapperResultSetExtractor."<init>":(Lorg/springframework/jdbc/core/RowMapper;)V
      10: invokevirtual #104                // Method query:(Lorg/springframework/jdbc/core/PreparedStatementCreator;Lorg/springframework/jdbc/core/ResultSetExtractor;)Ljava/lang/Object;
      13: invokestatic  #59                 // Method result:(Ljava/lang/Object;)Ljava/lang/Object;
      16: checkcast     #60                 // class java/util/List
      19: areturn

  public <T> java.util.List<T> query(java.lang.String, org.springframework.jdbc.core.PreparedStatementSetter, org.springframework.jdbc.core.RowMapper<T>) throws org.springframework.dao.DataAccessException;
    Code:
       0: aload_0
       1: aload_1
       2: aload_2
       3: new           #57                 // class org/springframework/jdbc/core/RowMapperResultSetExtractor
       6: dup
       7: aload_3
       8: invokespecial #58                 // Method org/springframework/jdbc/core/RowMapperResultSetExtractor."<init>":(Lorg/springframework/jdbc/core/RowMapper;)V
      11: invokevirtual #102                // Method query:(Ljava/lang/String;Lorg/springframework/jdbc/core/PreparedStatementSetter;Lorg/springframework/jdbc/core/ResultSetExtractor;)Ljava/lang/Object;
      14: invokestatic  #59                 // Method result:(Ljava/lang/Object;)Ljava/lang/Object;
      17: checkcast     #60                 // class java/util/List
      20: areturn

  public <T> java.util.List<T> query(java.lang.String, java.lang.Object[], int[], org.springframework.jdbc.core.RowMapper<T>) throws org.springframework.dao.DataAccessException;
    Code:
       0: aload_0
       1: aload_1
       2: aload_2
       3: aload_3
       4: new           #57                 // class org/springframework/jdbc/core/RowMapperResultSetExtractor
       7: dup
       8: aload         4
      10: invokespecial #58                 // Method org/springframework/jdbc/core/RowMapperResultSetExtractor."<init>":(Lorg/springframework/jdbc/core/RowMapper;)V
      13: invokevirtual #106                // Method query:(Ljava/lang/String;[Ljava/lang/Object;[ILorg/springframework/jdbc/core/ResultSetExtractor;)Ljava/lang/Object;
      16: invokestatic  #59                 // Method result:(Ljava/lang/Object;)Ljava/lang/Object;
      19: checkcast     #60                 // class java/util/List
      22: areturn

  public <T> java.util.List<T> query(java.lang.String, java.lang.Object[], org.springframework.jdbc.core.RowMapper<T>) throws org.springframework.dao.DataAccessException;
    Code:
       0: aload_0
       1: aload_1
       2: aload_2
       3: new           #57                 // class org/springframework/jdbc/core/RowMapperResultSetExtractor
       6: dup
       7: aload_3
       8: invokespecial #58                 // Method org/springframework/jdbc/core/RowMapperResultSetExtractor."<init>":(Lorg/springframework/jdbc/core/RowMapper;)V
      11: invokevirtual #107                // Method query:(Ljava/lang/String;[Ljava/lang/Object;Lorg/springframework/jdbc/core/ResultSetExtractor;)Ljava/lang/Object;
      14: invokestatic  #59                 // Method result:(Ljava/lang/Object;)Ljava/lang/Object;
      17: checkcast     #60                 // class java/util/List
      20: areturn

  public <T> java.util.List<T> query(java.lang.String, org.springframework.jdbc.core.RowMapper<T>, java.lang.Object...) throws org.springframework.dao.DataAccessException;
    Code:
       0: aload_0
       1: aload_1
       2: aload_3
       3: new           #57                 // class org/springframework/jdbc/core/RowMapperResultSetExtractor
       6: dup
       7: aload_2
       8: invokespecial #58                 // Method org/springframework/jdbc/core/RowMapperResultSetExtractor."<init>":(Lorg/springframework/jdbc/core/RowMapper;)V
      11: invokevirtual #107                // Method query:(Ljava/lang/String;[Ljava/lang/Object;Lorg/springframework/jdbc/core/ResultSetExtractor;)Ljava/lang/Object;
      14: invokestatic  #59                 // Method result:(Ljava/lang/Object;)Ljava/lang/Object;
      17: checkcast     #60                 // class java/util/List
      20: areturn

  public <T> T queryForObject(java.lang.String, java.lang.Object[], int[], org.springframework.jdbc.core.RowMapper<T>) throws org.springframework.dao.DataAccessException;
    Code:
       0: aload_0
       1: aload_1
       2: aload_2
       3: aload_3
       4: new           #57                 // class org/springframework/jdbc/core/RowMapperResultSetExtractor
       7: dup
       8: aload         4
      10: iconst_1
      11: invokespecial #108                // Method org/springframework/jdbc/core/RowMapperResultSetExtractor."<init>":(Lorg/springframework/jdbc/core/RowMapper;I)V
      14: invokevirtual #106                // Method query:(Ljava/lang/String;[Ljava/lang/Object;[ILorg/springframework/jdbc/core/ResultSetExtractor;)Ljava/lang/Object;
      17: checkcast     #60                 // class java/util/List
      20: astore        5
      22: aload         5
      24: invokestatic  #65                 // Method org/springframework/dao/support/DataAccessUtils.nullableSingleResult:(Ljava/util/Collection;)Ljava/lang/Object;
      27: areturn

  public <T> T queryForObject(java.lang.String, java.lang.Object[], org.springframework.jdbc.core.RowMapper<T>) throws org.springframework.dao.DataAccessException;
    Code:
       0: aload_0
       1: aload_1
       2: aload_2
       3: new           #57                 // class org/springframework/jdbc/core/RowMapperResultSetExtractor
       6: dup
       7: aload_3
       8: iconst_1
       9: invokespecial #108                // Method org/springframework/jdbc/core/RowMapperResultSetExtractor."<init>":(Lorg/springframework/jdbc/core/RowMapper;I)V
      12: invokevirtual #107                // Method query:(Ljava/lang/String;[Ljava/lang/Object;Lorg/springframework/jdbc/core/ResultSetExtractor;)Ljava/lang/Object;
      15: checkcast     #60                 // class java/util/List
      18: astore        4
      20: aload         4
      22: invokestatic  #65                 // Method org/springframework/dao/support/DataAccessUtils.nullableSingleResult:(Ljava/util/Collection;)Ljava/lang/Object;
      25: areturn

  public <T> T queryForObject(java.lang.String, org.springframework.jdbc.core.RowMapper<T>, java.lang.Object...) throws org.springframework.dao.DataAccessException;
    Code:
       0: aload_0
       1: aload_1
       2: aload_3
       3: new           #57                 // class org/springframework/jdbc/core/RowMapperResultSetExtractor
       6: dup
       7: aload_2
       8: iconst_1
       9: invokespecial #108                // Method org/springframework/jdbc/core/RowMapperResultSetExtractor."<init>":(Lorg/springframework/jdbc/core/RowMapper;I)V
      12: invokevirtual #107                // Method query:(Ljava/lang/String;[Ljava/lang/Object;Lorg/springframework/jdbc/core/ResultSetExtractor;)Ljava/lang/Object;
      15: checkcast     #60                 // class java/util/List
      18: astore        4
      20: aload         4
      22: invokestatic  #65                 // Method org/springframework/dao/support/DataAccessUtils.nullableSingleResult:(Ljava/util/Collection;)Ljava/lang/Object;
      25: areturn

  public <T> T queryForObject(java.lang.String, java.lang.Object[], int[], java.lang.Class<T>) throws org.springframework.dao.DataAccessException;
    Code:
       0: aload_0
       1: aload_1
       2: aload_2
       3: aload_3
       4: aload_0
       5: aload         4
       7: invokevirtual #66                 // Method getSingleColumnRowMapper:(Ljava/lang/Class;)Lorg/springframework/jdbc/core/RowMapper;
      10: invokevirtual #109                // Method queryForObject:(Ljava/lang/String;[Ljava/lang/Object;[ILorg/springframework/jdbc/core/RowMapper;)Ljava/lang/Object;
      13: areturn

  public <T> T queryForObject(java.lang.String, java.lang.Object[], java.lang.Class<T>) throws org.springframework.dao.DataAccessException;
    Code:
       0: aload_0
       1: aload_1
       2: aload_2
       3: aload_0
       4: aload_3
       5: invokevirtual #66                 // Method getSingleColumnRowMapper:(Ljava/lang/Class;)Lorg/springframework/jdbc/core/RowMapper;
       8: invokevirtual #110                // Method queryForObject:(Ljava/lang/String;[Ljava/lang/Object;Lorg/springframework/jdbc/core/RowMapper;)Ljava/lang/Object;
      11: areturn

  public <T> T queryForObject(java.lang.String, java.lang.Class<T>, java.lang.Object...) throws org.springframework.dao.DataAccessException;
    Code:
       0: aload_0
       1: aload_1
       2: aload_3
       3: aload_0
       4: aload_2
       5: invokevirtual #66                 // Method getSingleColumnRowMapper:(Ljava/lang/Class;)Lorg/springframework/jdbc/core/RowMapper;
       8: invokevirtual #110                // Method queryForObject:(Ljava/lang/String;[Ljava/lang/Object;Lorg/springframework/jdbc/core/RowMapper;)Ljava/lang/Object;
      11: areturn

  public java.util.Map<java.lang.String, java.lang.Object> queryForMap(java.lang.String, java.lang.Object[], int[]) throws org.springframework.dao.DataAccessException;
    Code:
       0: aload_0
       1: aload_1
       2: aload_2
       3: aload_3
       4: aload_0
       5: invokevirtual #61                 // Method getColumnMapRowMapper:()Lorg/springframework/jdbc/core/RowMapper;
       8: invokevirtual #109                // Method queryForObject:(Ljava/lang/String;[Ljava/lang/Object;[ILorg/springframework/jdbc/core/RowMapper;)Ljava/lang/Object;
      11: invokestatic  #59                 // Method result:(Ljava/lang/Object;)Ljava/lang/Object;
      14: checkcast     #63                 // class java/util/Map
      17: areturn

  public java.util.Map<java.lang.String, java.lang.Object> queryForMap(java.lang.String, java.lang.Object...) throws org.springframework.dao.DataAccessException;
    Code:
       0: aload_0
       1: aload_1
       2: aload_2
       3: aload_0
       4: invokevirtual #61                 // Method getColumnMapRowMapper:()Lorg/springframework/jdbc/core/RowMapper;
       7: invokevirtual #110                // Method queryForObject:(Ljava/lang/String;[Ljava/lang/Object;Lorg/springframework/jdbc/core/RowMapper;)Ljava/lang/Object;
      10: invokestatic  #59                 // Method result:(Ljava/lang/Object;)Ljava/lang/Object;
      13: checkcast     #63                 // class java/util/Map
      16: areturn

  public <T> java.util.List<T> queryForList(java.lang.String, java.lang.Object[], int[], java.lang.Class<T>) throws org.springframework.dao.DataAccessException;
    Code:
       0: aload_0
       1: aload_1
       2: aload_2
       3: aload_3
       4: aload_0
       5: aload         4
       7: invokevirtual #66                 // Method getSingleColumnRowMapper:(Ljava/lang/Class;)Lorg/springframework/jdbc/core/RowMapper;
      10: invokevirtual #111                // Method query:(Ljava/lang/String;[Ljava/lang/Object;[ILorg/springframework/jdbc/core/RowMapper;)Ljava/util/List;
      13: areturn

  public <T> java.util.List<T> queryForList(java.lang.String, java.lang.Object[], java.lang.Class<T>) throws org.springframework.dao.DataAccessException;
    Code:
       0: aload_0
       1: aload_1
       2: aload_2
       3: aload_0
       4: aload_3
       5: invokevirtual #66                 // Method getSingleColumnRowMapper:(Ljava/lang/Class;)Lorg/springframework/jdbc/core/RowMapper;
       8: invokevirtual #112                // Method query:(Ljava/lang/String;[Ljava/lang/Object;Lorg/springframework/jdbc/core/RowMapper;)Ljava/util/List;
      11: areturn

  public <T> java.util.List<T> queryForList(java.lang.String, java.lang.Class<T>, java.lang.Object...) throws org.springframework.dao.DataAccessException;
    Code:
       0: aload_0
       1: aload_1
       2: aload_3
       3: aload_0
       4: aload_2
       5: invokevirtual #66                 // Method getSingleColumnRowMapper:(Ljava/lang/Class;)Lorg/springframework/jdbc/core/RowMapper;
       8: invokevirtual #112                // Method query:(Ljava/lang/String;[Ljava/lang/Object;Lorg/springframework/jdbc/core/RowMapper;)Ljava/util/List;
      11: areturn

  public java.util.List<java.util.Map<java.lang.String, java.lang.Object>> queryForList(java.lang.String, java.lang.Object[], int[]) throws org.springframework.dao.DataAccessException;
    Code:
       0: aload_0
       1: aload_1
       2: aload_2
       3: aload_3
       4: aload_0
       5: invokevirtual #61                 // Method getColumnMapRowMapper:()Lorg/springframework/jdbc/core/RowMapper;
       8: invokevirtual #111                // Method query:(Ljava/lang/String;[Ljava/lang/Object;[ILorg/springframework/jdbc/core/RowMapper;)Ljava/util/List;
      11: areturn

  public java.util.List<java.util.Map<java.lang.String, java.lang.Object>> queryForList(java.lang.String, java.lang.Object...) throws org.springframework.dao.DataAccessException;
    Code:
       0: aload_0
       1: aload_1
       2: aload_2
       3: aload_0
       4: invokevirtual #61                 // Method getColumnMapRowMapper:()Lorg/springframework/jdbc/core/RowMapper;
       7: invokevirtual #112                // Method query:(Ljava/lang/String;[Ljava/lang/Object;Lorg/springframework/jdbc/core/RowMapper;)Ljava/util/List;
      10: areturn

  public org.springframework.jdbc.support.rowset.SqlRowSet queryForRowSet(java.lang.String, java.lang.Object[], int[]) throws org.springframework.dao.DataAccessException;
    Code:
       0: aload_0
       1: aload_1
       2: aload_2
       3: aload_3
       4: new           #67                 // class org/springframework/jdbc/core/SqlRowSetResultSetExtractor
       7: dup
       8: invokespecial #68                 // Method org/springframework/jdbc/core/SqlRowSetResultSetExtractor."<init>":()V
      11: invokevirtual #106                // Method query:(Ljava/lang/String;[Ljava/lang/Object;[ILorg/springframework/jdbc/core/ResultSetExtractor;)Ljava/lang/Object;
      14: invokestatic  #59                 // Method result:(Ljava/lang/Object;)Ljava/lang/Object;
      17: checkcast     #69                 // class org/springframework/jdbc/support/rowset/SqlRowSet
      20: areturn

  public org.springframework.jdbc.support.rowset.SqlRowSet queryForRowSet(java.lang.String, java.lang.Object...) throws org.springframework.dao.DataAccessException;
    Code:
       0: aload_0
       1: aload_1
       2: aload_2
       3: new           #67                 // class org/springframework/jdbc/core/SqlRowSetResultSetExtractor
       6: dup
       7: invokespecial #68                 // Method org/springframework/jdbc/core/SqlRowSetResultSetExtractor."<init>":()V
      10: invokevirtual #107                // Method query:(Ljava/lang/String;[Ljava/lang/Object;Lorg/springframework/jdbc/core/ResultSetExtractor;)Ljava/lang/Object;
      13: invokestatic  #59                 // Method result:(Ljava/lang/Object;)Ljava/lang/Object;
      16: checkcast     #69                 // class org/springframework/jdbc/support/rowset/SqlRowSet
      19: areturn

  protected int update(org.springframework.jdbc.core.PreparedStatementCreator, org.springframework.jdbc.core.PreparedStatementSetter) throws org.springframework.dao.DataAccessException;
    Code:
       0: aload_0
       1: getfield      #1                  // Field logger:Lorg/apache/commons/logging/Log;
       4: ldc           #113                // String Executing prepared SQL update
       6: invokeinterface #45,  2           // InterfaceMethod org/apache/commons/logging/Log.debug:(Ljava/lang/Object;)V
      11: aload_0
      12: aload_1
      13: aload_0
      14: aload_2
      15: invokedynamic #114,  0            // InvokeDynamic #0:doInPreparedStatement:(Lorg/springframework/jdbc/core/JdbcTemplate;Lorg/springframework/jdbc/core/PreparedStatementSetter;)Lorg/springframework/jdbc/core/PreparedStatementCallback;
      20: invokevirtual #96                 // Method execute:(Lorg/springframework/jdbc/core/PreparedStatementCreator;Lorg/springframework/jdbc/core/PreparedStatementCallback;)Ljava/lang/Object;
      23: checkcast     #73                 // class java/lang/Integer
      26: invokestatic  #74                 // Method updateCount:(Ljava/lang/Integer;)I
      29: ireturn

  public int update(org.springframework.jdbc.core.PreparedStatementCreator) throws org.springframework.dao.DataAccessException;
    Code:
       0: aload_0
       1: aload_1
       2: aconst_null
       3: checkcast     #115                // class org/springframework/jdbc/core/PreparedStatementSetter
       6: invokevirtual #116                // Method update:(Lorg/springframework/jdbc/core/PreparedStatementCreator;Lorg/springframework/jdbc/core/PreparedStatementSetter;)I
       9: ireturn

  public int update(org.springframework.jdbc.core.PreparedStatementCreator, org.springframework.jdbc.support.KeyHolder) throws org.springframework.dao.DataAccessException;
    Code:
       0: aload_2
       1: ldc           #117                // String KeyHolder must not be null
       3: invokestatic  #14                 // Method org/springframework/util/Assert.notNull:(Ljava/lang/Object;Ljava/lang/String;)V
       6: aload_0
       7: getfield      #1                  // Field logger:Lorg/apache/commons/logging/Log;
      10: ldc           #118                // String Executing SQL update and returning generated keys
      12: invokeinterface #45,  2           // InterfaceMethod org/apache/commons/logging/Log.debug:(Ljava/lang/Object;)V
      17: aload_0
      18: aload_1
      19: aload_0
      20: aload_2
      21: invokedynamic #119,  0            // InvokeDynamic #1:doInPreparedStatement:(Lorg/springframework/jdbc/core/JdbcTemplate;Lorg/springframework/jdbc/support/KeyHolder;)Lorg/springframework/jdbc/core/PreparedStatementCallback;
      26: invokevirtual #96                 // Method execute:(Lorg/springframework/jdbc/core/PreparedStatementCreator;Lorg/springframework/jdbc/core/PreparedStatementCallback;)Ljava/lang/Object;
      29: checkcast     #73                 // class java/lang/Integer
      32: invokestatic  #74                 // Method updateCount:(Ljava/lang/Integer;)I
      35: ireturn

  public int update(java.lang.String, org.springframework.jdbc.core.PreparedStatementSetter) throws org.springframework.dao.DataAccessException;
    Code:
       0: aload_0
       1: new           #94                 // class org/springframework/jdbc/core/JdbcTemplate$SimplePreparedStatementCreator
       4: dup
       5: aload_1
       6: invokespecial #95                 // Method org/springframework/jdbc/core/JdbcTemplate$SimplePreparedStatementCreator."<init>":(Ljava/lang/String;)V
       9: aload_2
      10: invokevirtual #116                // Method update:(Lorg/springframework/jdbc/core/PreparedStatementCreator;Lorg/springframework/jdbc/core/PreparedStatementSetter;)I
      13: ireturn

  public int update(java.lang.String, java.lang.Object[], int[]) throws org.springframework.dao.DataAccessException;
    Code:
       0: aload_0
       1: aload_1
       2: aload_0
       3: aload_2
       4: aload_3
       5: invokevirtual #101                // Method newArgTypePreparedStatementSetter:([Ljava/lang/Object;[I)Lorg/springframework/jdbc/core/PreparedStatementSetter;
       8: invokevirtual #120                // Method update:(Ljava/lang/String;Lorg/springframework/jdbc/core/PreparedStatementSetter;)I
      11: ireturn

  public int update(java.lang.String, java.lang.Object...) throws org.springframework.dao.DataAccessException;
    Code:
       0: aload_0
       1: aload_1
       2: aload_0
       3: aload_2
       4: invokevirtual #103                // Method newArgPreparedStatementSetter:([Ljava/lang/Object;)Lorg/springframework/jdbc/core/PreparedStatementSetter;
       7: invokevirtual #120                // Method update:(Ljava/lang/String;Lorg/springframework/jdbc/core/PreparedStatementSetter;)I
      10: ireturn

  public int[] batchUpdate(java.lang.String, org.springframework.jdbc.core.BatchPreparedStatementSetter) throws org.springframework.dao.DataAccessException;
    Code:
       0: aload_0
       1: getfield      #1                  // Field logger:Lorg/apache/commons/logging/Log;
       4: invokeinterface #38,  1           // InterfaceMethod org/apache/commons/logging/Log.isDebugEnabled:()Z
       9: ifeq          45
      12: aload_0
      13: getfield      #1                  // Field logger:Lorg/apache/commons/logging/Log;
      16: new           #39                 // class java/lang/StringBuilder
      19: dup
      20: invokespecial #40                 // Method java/lang/StringBuilder."<init>":()V
      23: ldc           #121                // String Executing SQL batch update [
      25: invokevirtual #42                 // Method java/lang/StringBuilder.append:(Ljava/lang/String;)Ljava/lang/StringBuilder;
      28: aload_1
      29: invokevirtual #42                 // Method java/lang/StringBuilder.append:(Ljava/lang/String;)Ljava/lang/StringBuilder;
      32: ldc           #43                 // String ]
      34: invokevirtual #42                 // Method java/lang/StringBuilder.append:(Ljava/lang/String;)Ljava/lang/StringBuilder;
      37: invokevirtual #44                 // Method java/lang/StringBuilder.toString:()Ljava/lang/String;
      40: invokeinterface #45,  2           // InterfaceMethod org/apache/commons/logging/Log.debug:(Ljava/lang/Object;)V
      45: aload_0
      46: aload_1
      47: aload_2
      48: invokedynamic #122,  0            // InvokeDynamic #2:doInPreparedStatement:(Lorg/springframework/jdbc/core/BatchPreparedStatementSetter;)Lorg/springframework/jdbc/core/PreparedStatementCallback;
      53: invokevirtual #123                // Method execute:(Ljava/lang/String;Lorg/springframework/jdbc/core/PreparedStatementCallback;)Ljava/lang/Object;
      56: checkcast     #82                 // class "[I"
      59: astore_3
      60: aload_3
      61: ifnull        68
      64: iconst_1
      65: goto          69
      68: iconst_0
      69: ldc           #124                // String No result array
      71: invokestatic  #84                 // Method org/springframework/util/Assert.state:(ZLjava/lang/String;)V
      74: aload_3
      75: areturn

  public int[] batchUpdate(java.lang.String, java.util.List<java.lang.Object[]>) throws org.springframework.dao.DataAccessException;
    Code:
       0: aload_0
       1: aload_1
       2: aload_2
       3: iconst_0
       4: newarray       int
       6: invokevirtual #125                // Method batchUpdate:(Ljava/lang/String;Ljava/util/List;[I)[I
       9: areturn

  public int[] batchUpdate(java.lang.String, java.util.List<java.lang.Object[]>, int[]) throws org.springframework.dao.DataAccessException;
    Code:
       0: aload_2
       1: invokeinterface #126,  1          // InterfaceMethod java/util/List.isEmpty:()Z
       6: ifeq          13
       9: iconst_0
      10: newarray       int
      12: areturn
      13: aload_0
      14: aload_1
      15: new           #127                // class org/springframework/jdbc/core/JdbcTemplate$2
      18: dup
      19: aload_0
      20: aload_2
      21: aload_3
      22: invokespecial #128                // Method org/springframework/jdbc/core/JdbcTemplate$2."<init>":(Lorg/springframework/jdbc/core/JdbcTemplate;Ljava/util/List;[I)V
      25: invokevirtual #129                // Method batchUpdate:(Ljava/lang/String;Lorg/springframework/jdbc/core/BatchPreparedStatementSetter;)[I
      28: areturn

  public <T> int[][] batchUpdate(java.lang.String, java.util.Collection<T>, int, org.springframework.jdbc.core.ParameterizedPreparedStatementSetter<T>) throws org.springframework.dao.DataAccessException;
    Code:
       0: aload_0
       1: getfield      #1                  // Field logger:Lorg/apache/commons/logging/Log;
       4: invokeinterface #38,  1           // InterfaceMethod org/apache/commons/logging/Log.isDebugEnabled:()Z
       9: ifeq          49
      12: aload_0
      13: getfield      #1                  // Field logger:Lorg/apache/commons/logging/Log;
      16: new           #39                 // class java/lang/StringBuilder
      19: dup
      20: invokespecial #40                 // Method java/lang/StringBuilder."<init>":()V
      23: ldc           #121                // String Executing SQL batch update [
      25: invokevirtual #42                 // Method java/lang/StringBuilder.append:(Ljava/lang/String;)Ljava/lang/StringBuilder;
      28: aload_1
      29: invokevirtual #42                 // Method java/lang/StringBuilder.append:(Ljava/lang/String;)Ljava/lang/StringBuilder;
      32: ldc           #130                // String ] with a batch size of
      34: invokevirtual #42                 // Method java/lang/StringBuilder.append:(Ljava/lang/String;)Ljava/lang/StringBuilder;
      37: iload_3
      38: invokevirtual #78                 // Method java/lang/StringBuilder.append:(I)Ljava/lang/StringBuilder;
      41: invokevirtual #44                 // Method java/lang/StringBuilder.toString:()Ljava/lang/String;
      44: invokeinterface #45,  2           // InterfaceMethod org/apache/commons/logging/Log.debug:(Ljava/lang/Object;)V
      49: aload_0
      50: aload_1
      51: aload_0
      52: aload_2
      53: aload         4
      55: iload_3
      56: invokedynamic #131,  0            // InvokeDynamic #3:doInPreparedStatement:(Lorg/springframework/jdbc/core/JdbcTemplate;Ljava/util/Collection;Lorg/springframework/jdbc/core/ParameterizedPreparedStatementSetter;I)Lorg/springframework/jdbc/core/PreparedStatementCallback;
      61: invokevirtual #123                // Method execute:(Ljava/lang/String;Lorg/springframework/jdbc/core/PreparedStatementCallback;)Ljava/lang/Object;
      64: checkcast     #132                // class "[[I"
      67: astore        5
      69: aload         5
      71: ifnull        78
      74: iconst_1
      75: goto          79
      78: iconst_0
      79: ldc           #124                // String No result array
      81: invokestatic  #84                 // Method org/springframework/util/Assert.state:(ZLjava/lang/String;)V
      84: aload         5
      86: areturn

  public <T> T execute(org.springframework.jdbc.core.CallableStatementCreator, org.springframework.jdbc.core.CallableStatementCallback<T>) throws org.springframework.dao.DataAccessException;
    Code:
       0: aload_1
       1: ldc           #133                // String CallableStatementCreator must not be null
       3: invokestatic  #14                 // Method org/springframework/util/Assert.notNull:(Ljava/lang/Object;Ljava/lang/String;)V
       6: aload_2
       7: ldc           #13                 // String Callback object must not be null
       9: invokestatic  #14                 // Method org/springframework/util/Assert.notNull:(Ljava/lang/Object;Ljava/lang/String;)V
      12: aload_0
      13: getfield      #1                  // Field logger:Lorg/apache/commons/logging/Log;
      16: invokeinterface #38,  1           // InterfaceMethod org/apache/commons/logging/Log.isDebugEnabled:()Z
      21: ifeq          89
      24: aload_1
      25: invokestatic  #22                 // Method getSql:(Ljava/lang/Object;)Ljava/lang/String;
      28: astore_3
      29: aload_0
      30: getfield      #1                  // Field logger:Lorg/apache/commons/logging/Log;
      33: new           #39                 // class java/lang/StringBuilder
      36: dup
      37: invokespecial #40                 // Method java/lang/StringBuilder."<init>":()V
      40: ldc           #134                // String Calling stored procedure
      42: invokevirtual #42                 // Method java/lang/StringBuilder.append:(Ljava/lang/String;)Ljava/lang/StringBuilder;
      45: aload_3
      46: ifnull        76
      49: new           #39                 // class java/lang/StringBuilder
      52: dup
      53: invokespecial #40                 // Method java/lang/StringBuilder."<init>":()V
      56: ldc           #87                 // String  [
      58: invokevirtual #42                 // Method java/lang/StringBuilder.append:(Ljava/lang/String;)Ljava/lang/StringBuilder;
      61: aload_3
      62: invokevirtual #42                 // Method java/lang/StringBuilder.append:(Ljava/lang/String;)Ljava/lang/StringBuilder;
      65: ldc           #43                 // String ]
      67: invokevirtual #42                 // Method java/lang/StringBuilder.append:(Ljava/lang/String;)Ljava/lang/StringBuilder;
      70: invokevirtual #44                 // Method java/lang/StringBuilder.toString:()Ljava/lang/String;
      73: goto          78
      76: ldc           #88                 // String
      78: invokevirtual #42                 // Method java/lang/StringBuilder.append:(Ljava/lang/String;)Ljava/lang/StringBuilder;
      81: invokevirtual #44                 // Method java/lang/StringBuilder.toString:()Ljava/lang/String;
      84: invokeinterface #45,  2           // InterfaceMethod org/apache/commons/logging/Log.debug:(Ljava/lang/Object;)V
      89: aload_0
      90: invokevirtual #15                 // Method obtainDataSource:()Ljavax/sql/DataSource;
      93: invokestatic  #16                 // Method org/springframework/jdbc/datasource/DataSourceUtils.getConnection:(Ljavax/sql/DataSource;)Ljava/sql/Connection;
      96: astore_3
      97: aconst_null
      98: astore        4
     100: aload_1
     101: aload_3
     102: invokeinterface #135,  2          // InterfaceMethod org/springframework/jdbc/core/CallableStatementCreator.createCallableStatement:(Ljava/sql/Connection;)Ljava/sql/CallableStatement;
     107: astore        4
     109: aload_0
     110: aload         4
     112: invokevirtual #33                 // Method applyStatementSettings:(Ljava/sql/Statement;)V
     115: aload_2
     116: aload         4
     118: invokeinterface #136,  2          // InterfaceMethod org/springframework/jdbc/core/CallableStatementCallback.doInCallableStatement:(Ljava/sql/CallableStatement;)Ljava/lang/Object;
     123: astore        5
     125: aload_0
     126: aload         4
     128: invokevirtual #35                 // Method handleWarnings:(Ljava/sql/Statement;)V
     131: aload         5
     133: astore        6
     135: aload_1
     136: instanceof    #91                 // class org/springframework/jdbc/core/ParameterDisposer
     139: ifeq          151
     142: aload_1
     143: checkcast     #91                 // class org/springframework/jdbc/core/ParameterDisposer
     146: invokeinterface #92,  1           // InterfaceMethod org/springframework/jdbc/core/ParameterDisposer.cleanupParameters:()V
     151: aload         4
     153: invokestatic  #36                 // Method org/springframework/jdbc/support/JdbcUtils.closeStatement:(Ljava/sql/Statement;)V
     156: aload_3
     157: aload_0
     158: invokevirtual #19                 // Method getDataSource:()Ljavax/sql/DataSource;
     161: invokestatic  #20                 // Method org/springframework/jdbc/datasource/DataSourceUtils.releaseConnection:(Ljava/sql/Connection;Ljavax/sql/DataSource;)V
     164: aload         6
     166: areturn
     167: astore        5
     169: aload_1
     170: instanceof    #91                 // class org/springframework/jdbc/core/ParameterDisposer
     173: ifeq          185
     176: aload_1
     177: checkcast     #91                 // class org/springframework/jdbc/core/ParameterDisposer
     180: invokeinterface #92,  1           // InterfaceMethod org/springframework/jdbc/core/ParameterDisposer.cleanupParameters:()V
     185: aload_1
     186: invokestatic  #22                 // Method getSql:(Ljava/lang/Object;)Ljava/lang/String;
     189: astore        6
     191: aconst_null
     192: astore_1
     193: aload         4
     195: invokestatic  #36                 // Method org/springframework/jdbc/support/JdbcUtils.closeStatement:(Ljava/sql/Statement;)V
     198: aconst_null
     199: astore        4
     201: aload_3
     202: aload_0
     203: invokevirtual #19                 // Method getDataSource:()Ljavax/sql/DataSource;
     206: invokestatic  #20                 // Method org/springframework/jdbc/datasource/DataSourceUtils.releaseConnection:(Ljava/sql/Connection;Ljavax/sql/DataSource;)V
     209: aconst_null
     210: astore_3
     211: aload_0
     212: ldc           #137                // String CallableStatementCallback
     214: aload         6
     216: aload         5
     218: invokevirtual #24                 // Method translateException:(Ljava/lang/String;Ljava/lang/String;Ljava/sql/SQLException;)Lorg/springframework/dao/DataAccessException;
     221: athrow
     222: astore        7
     224: aload_1
     225: instanceof    #91                 // class org/springframework/jdbc/core/ParameterDisposer
     228: ifeq          240
     231: aload_1
     232: checkcast     #91                 // class org/springframework/jdbc/core/ParameterDisposer
     235: invokeinterface #92,  1           // InterfaceMethod org/springframework/jdbc/core/ParameterDisposer.cleanupParameters:()V
     240: aload         4
     242: invokestatic  #36                 // Method org/springframework/jdbc/support/JdbcUtils.closeStatement:(Ljava/sql/Statement;)V
     245: aload_3
     246: aload_0
     247: invokevirtual #19                 // Method getDataSource:()Ljavax/sql/DataSource;
     250: invokestatic  #20                 // Method org/springframework/jdbc/datasource/DataSourceUtils.releaseConnection:(Ljava/sql/Connection;Ljavax/sql/DataSource;)V
     253: aload         7
     255: athrow
    Exception table:
       from    to  target type
         100   135   167   Class java/sql/SQLException
         100   135   222   any
         167   224   222   any

  public <T> T execute(java.lang.String, org.springframework.jdbc.core.CallableStatementCallback<T>) throws org.springframework.dao.DataAccessException;
    Code:
       0: aload_0
       1: new           #138                // class org/springframework/jdbc/core/JdbcTemplate$SimpleCallableStatementCreator
       4: dup
       5: aload_1
       6: invokespecial #139                // Method org/springframework/jdbc/core/JdbcTemplate$SimpleCallableStatementCreator."<init>":(Ljava/lang/String;)V
       9: aload_2
      10: invokevirtual #140                // Method execute:(Lorg/springframework/jdbc/core/CallableStatementCreator;Lorg/springframework/jdbc/core/CallableStatementCallback;)Ljava/lang/Object;
      13: areturn

  public java.util.Map<java.lang.String, java.lang.Object> call(org.springframework.jdbc.core.CallableStatementCreator, java.util.List<org.springframework.jdbc.core.SqlParameter>) throws org.springframework.dao.DataAccessException;
    Code:
       0: new           #141                // class java/util/ArrayList
       3: dup
       4: invokespecial #142                // Method java/util/ArrayList."<init>":()V
       7: astore_3
       8: new           #141                // class java/util/ArrayList
      11: dup
      12: invokespecial #142                // Method java/util/ArrayList."<init>":()V
      15: astore        4
      17: new           #141                // class java/util/ArrayList
      20: dup
      21: invokespecial #142                // Method java/util/ArrayList."<init>":()V
      24: astore        5
      26: aload_2
      27: invokeinterface #143,  1          // InterfaceMethod java/util/List.iterator:()Ljava/util/Iterator;
      32: astore        6
      34: aload         6
      36: invokeinterface #144,  1          // InterfaceMethod java/util/Iterator.hasNext:()Z
      41: ifeq          110
      44: aload         6
      46: invokeinterface #145,  1          // InterfaceMethod java/util/Iterator.next:()Ljava/lang/Object;
      51: checkcast     #146                // class org/springframework/jdbc/core/SqlParameter
      54: astore        7
      56: aload         7
      58: invokevirtual #147                // Method org/springframework/jdbc/core/SqlParameter.isResultsParameter:()Z
      61: ifeq          97
      64: aload         7
      66: instanceof    #148                // class org/springframework/jdbc/core/SqlReturnResultSet
      69: ifeq          85
      72: aload         4
      74: aload         7
      76: invokeinterface #149,  2          // InterfaceMethod java/util/List.add:(Ljava/lang/Object;)Z
      81: pop
      82: goto          107
      85: aload_3
      86: aload         7
      88: invokeinterface #149,  2          // InterfaceMethod java/util/List.add:(Ljava/lang/Object;)Z
      93: pop
      94: goto          107
      97: aload         5
      99: aload         7
     101: invokeinterface #149,  2          // InterfaceMethod java/util/List.add:(Ljava/lang/Object;)Z
     106: pop
     107: goto          34
     110: aload_0
     111: aload_1
     112: aload_0
     113: aload_3
     114: aload         4
     116: aload         5
     118: invokedynamic #150,  0            // InvokeDynamic #4:doInCallableStatement:(Lorg/springframework/jdbc/core/JdbcTemplate;Ljava/util/List;Ljava/util/List;Ljava/util/List;)Lorg/springframework/jdbc/core/CallableStatementCallback;
     123: invokevirtual #140                // Method execute:(Lorg/springframework/jdbc/core/CallableStatementCreator;Lorg/springframework/jdbc/core/CallableStatementCallback;)Ljava/lang/Object;
     126: checkcast     #63                 // class java/util/Map
     129: astore        6
     131: aload         6
     133: ifnull        140
     136: iconst_1
     137: goto          141
     140: iconst_0
     141: ldc           #151                // String No result map
     143: invokestatic  #84                 // Method org/springframework/util/Assert.state:(ZLjava/lang/String;)V
     146: aload         6
     148: areturn

  protected java.util.Map<java.lang.String, java.lang.Object> extractReturnedResults(java.sql.CallableStatement, java.util.List<org.springframework.jdbc.core.SqlParameter>, java.util.List<org.springframework.jdbc.core.SqlParameter>, int) throws java.sql.SQLException;
    Code:
       0: new           #152                // class java/util/LinkedHashMap
       3: dup
       4: iconst_4
       5: invokespecial #153                // Method java/util/LinkedHashMap."<init>":(I)V
       8: astore        5
      10: iconst_0
      11: istore        6
      13: iconst_0
      14: istore        7
      16: aload_0
      17: getfield      #7                  // Field skipResultsProcessing:Z
      20: ifne          418
      23: iload         4
      25: iconst_m1
      26: if_icmpne     199
      29: aload_3
      30: ifnull        82
      33: aload_3
      34: invokeinterface #154,  1          // InterfaceMethod java/util/List.size:()I
      39: iload         6
      41: if_icmple     82
      44: aload_3
      45: iload         6
      47: invokeinterface #155,  2          // InterfaceMethod java/util/List.get:(I)Ljava/lang/Object;
      52: checkcast     #148                // class org/springframework/jdbc/core/SqlReturnResultSet
      55: astore        9
      57: aload         5
      59: aload_0
      60: aload_1
      61: invokeinterface #156,  1          // InterfaceMethod java/sql/CallableStatement.getResultSet:()Ljava/sql/ResultSet;
      66: aload         9
      68: invokevirtual #157                // Method processResultSet:(Ljava/sql/ResultSet;Lorg/springframework/jdbc/core/ResultSetSupportingSqlParameter;)Ljava/util/Map;
      71: invokeinterface #158,  2          // InterfaceMethod java/util/Map.putAll:(Ljava/util/Map;)V
      76: iinc          6, 1
      79: goto          350
      82: aload_0
      83: getfield      #8                  // Field skipUndeclaredResults:Z
      86: ifne          350
      89: new           #39                 // class java/lang/StringBuilder
      92: dup
      93: invokespecial #40                 // Method java/lang/StringBuilder."<init>":()V
      96: ldc           #160                // String #result-set-
      98: invokevirtual #42                 // Method java/lang/StringBuilder.append:(Ljava/lang/String;)Ljava/lang/StringBuilder;
     101: iload         6
     103: iconst_1
     104: iadd
     105: invokevirtual #78                 // Method java/lang/StringBuilder.append:(I)Ljava/lang/StringBuilder;
     108: invokevirtual #44                 // Method java/lang/StringBuilder.toString:()Ljava/lang/String;
     111: astore        9
     113: new           #148                // class org/springframework/jdbc/core/SqlReturnResultSet
     116: dup
     117: aload         9
     119: aload_0
     120: invokevirtual #61                 // Method getColumnMapRowMapper:()Lorg/springframework/jdbc/core/RowMapper;
     123: invokespecial #161                // Method org/springframework/jdbc/core/SqlReturnResultSet."<init>":(Ljava/lang/String;Lorg/springframework/jdbc/core/RowMapper;)V
     126: astore        10
     128: aload_0
     129: getfield      #1                  // Field logger:Lorg/apache/commons/logging/Log;
     132: invokeinterface #162,  1          // InterfaceMethod org/apache/commons/logging/Log.isTraceEnabled:()Z
     137: ifeq          174
     140: aload_0
     141: getfield      #1                  // Field logger:Lorg/apache/commons/logging/Log;
     144: new           #39                 // class java/lang/StringBuilder
     147: dup
     148: invokespecial #40                 // Method java/lang/StringBuilder."<init>":()V
     151: ldc           #163                // String Added default SqlReturnResultSet parameter named \'
     153: invokevirtual #42                 // Method java/lang/StringBuilder.append:(Ljava/lang/String;)Ljava/lang/StringBuilder;
     156: aload         9
     158: invokevirtual #42                 // Method java/lang/StringBuilder.append:(Ljava/lang/String;)Ljava/lang/StringBuilder;
     161: ldc           #164                // String \'
     163: invokevirtual #42                 // Method java/lang/StringBuilder.append:(Ljava/lang/String;)Ljava/lang/StringBuilder;
     166: invokevirtual #44                 // Method java/lang/StringBuilder.toString:()Ljava/lang/String;
     169: invokeinterface #165,  2          // InterfaceMethod org/apache/commons/logging/Log.trace:(Ljava/lang/Object;)V
     174: aload         5
     176: aload_0
     177: aload_1
     178: invokeinterface #156,  1          // InterfaceMethod java/sql/CallableStatement.getResultSet:()Ljava/sql/ResultSet;
     183: aload         10
     185: invokevirtual #157                // Method processResultSet:(Ljava/sql/ResultSet;Lorg/springframework/jdbc/core/ResultSetSupportingSqlParameter;)Ljava/util/Map;
     188: invokeinterface #158,  2          // InterfaceMethod java/util/Map.putAll:(Ljava/util/Map;)V
     193: iinc          6, 1
     196: goto          350
     199: aload_2
     200: ifnull        255
     203: aload_2
     204: invokeinterface #154,  1          // InterfaceMethod java/util/List.size:()I
     209: iload         7
     211: if_icmple     255
     214: aload_2
     215: iload         7
     217: invokeinterface #155,  2          // InterfaceMethod java/util/List.get:(I)Ljava/lang/Object;
     222: checkcast     #166                // class org/springframework/jdbc/core/SqlReturnUpdateCount
     225: astore        9
     227: aload         9
     229: invokevirtual #167                // Method org/springframework/jdbc/core/SqlReturnUpdateCount.getName:()Ljava/lang/String;
     232: astore        10
     234: aload         5
     236: aload         10
     238: iload         4
     240: invokestatic  #168                // Method java/lang/Integer.valueOf:(I)Ljava/lang/Integer;
     243: invokeinterface #169,  3          // InterfaceMethod java/util/Map.put:(Ljava/lang/Object;Ljava/lang/Object;)Ljava/lang/Object;
     248: pop
     249: iinc          7, 1
     252: goto          350
     255: aload_0
     256: getfield      #8                  // Field skipUndeclaredResults:Z
     259: ifne          350
     262: new           #39                 // class java/lang/StringBuilder
     265: dup
     266: invokespecial #40                 // Method java/lang/StringBuilder."<init>":()V
     269: ldc           #170                // String #update-count-
     271: invokevirtual #42                 // Method java/lang/StringBuilder.append:(Ljava/lang/String;)Ljava/lang/StringBuilder;
     274: iload         7
     276: iconst_1
     277: iadd
     278: invokevirtual #78                 // Method java/lang/StringBuilder.append:(I)Ljava/lang/StringBuilder;
     281: invokevirtual #44                 // Method java/lang/StringBuilder.toString:()Ljava/lang/String;
     284: astore        9
     286: aload_0
     287: getfield      #1                  // Field logger:Lorg/apache/commons/logging/Log;
     290: invokeinterface #162,  1          // InterfaceMethod org/apache/commons/logging/Log.isTraceEnabled:()Z
     295: ifeq          332
     298: aload_0
     299: getfield      #1                  // Field logger:Lorg/apache/commons/logging/Log;
     302: new           #39                 // class java/lang/StringBuilder
     305: dup
     306: invokespecial #40                 // Method java/lang/StringBuilder."<init>":()V
     309: ldc           #171                // String Added default SqlReturnUpdateCount parameter named \'
     311: invokevirtual #42                 // Method java/lang/StringBuilder.append:(Ljava/lang/String;)Ljava/lang/StringBuilder;
     314: aload         9
     316: invokevirtual #42                 // Method java/lang/StringBuilder.append:(Ljava/lang/String;)Ljava/lang/StringBuilder;
     319: ldc           #164                // String \'
     321: invokevirtual #42                 // Method java/lang/StringBuilder.append:(Ljava/lang/String;)Ljava/lang/StringBuilder;
     324: invokevirtual #44                 // Method java/lang/StringBuilder.toString:()Ljava/lang/String;
     327: invokeinterface #165,  2          // InterfaceMethod org/apache/commons/logging/Log.trace:(Ljava/lang/Object;)V
     332: aload         5
     334: aload         9
     336: iload         4
     338: invokestatic  #168                // Method java/lang/Integer.valueOf:(I)Ljava/lang/Integer;
     341: invokeinterface #169,  3          // InterfaceMethod java/util/Map.put:(Ljava/lang/Object;Ljava/lang/Object;)Ljava/lang/Object;
     346: pop
     347: iinc          7, 1
     350: aload_1
     351: invokeinterface #172,  1          // InterfaceMethod java/sql/CallableStatement.getMoreResults:()Z
     356: istore        8
     358: aload_1
     359: invokeinterface #173,  1          // InterfaceMethod java/sql/CallableStatement.getUpdateCount:()I
     364: istore        4
     366: aload_0
     367: getfield      #1                  // Field logger:Lorg/apache/commons/logging/Log;
     370: invokeinterface #162,  1          // InterfaceMethod org/apache/commons/logging/Log.isTraceEnabled:()Z
     375: ifeq          407
     378: aload_0
     379: getfield      #1                  // Field logger:Lorg/apache/commons/logging/Log;
     382: new           #39                 // class java/lang/StringBuilder
     385: dup
     386: invokespecial #40                 // Method java/lang/StringBuilder."<init>":()V
     389: ldc           #174                // String CallableStatement.getUpdateCount() returned
     391: invokevirtual #42                 // Method java/lang/StringBuilder.append:(Ljava/lang/String;)Ljava/lang/StringBuilder;
     394: iload         4
     396: invokevirtual #78                 // Method java/lang/StringBuilder.append:(I)Ljava/lang/StringBuilder;
     399: invokevirtual #44                 // Method java/lang/StringBuilder.toString:()Ljava/lang/String;
     402: invokeinterface #165,  2          // InterfaceMethod org/apache/commons/logging/Log.trace:(Ljava/lang/Object;)V
     407: iload         8
     409: ifne          23
     412: iload         4
     414: iconst_m1
     415: if_icmpne     23
     418: aload         5
     420: areturn

  protected java.util.Map<java.lang.String, java.lang.Object> extractOutputParameters(java.sql.CallableStatement, java.util.List<org.springframework.jdbc.core.SqlParameter>) throws java.sql.SQLException;
    Code:
       0: new           #152                // class java/util/LinkedHashMap
       3: dup
       4: aload_2
       5: invokeinterface #154,  1          // InterfaceMethod java/util/List.size:()I
      10: invokespecial #153                // Method java/util/LinkedHashMap."<init>":(I)V
      13: astore_3
      14: iconst_1
      15: istore        4
      17: aload_2
      18: invokeinterface #143,  1          // InterfaceMethod java/util/List.iterator:()Ljava/util/Iterator;
      23: astore        5
      25: aload         5
      27: invokeinterface #144,  1          // InterfaceMethod java/util/Iterator.hasNext:()Z
      32: ifeq          293
      35: aload         5
      37: invokeinterface #145,  1          // InterfaceMethod java/util/Iterator.next:()Ljava/lang/Object;
      42: checkcast     #146                // class org/springframework/jdbc/core/SqlParameter
      45: astore        6
      47: aload         6
      49: instanceof    #175                // class org/springframework/jdbc/core/SqlOutParameter
      52: ifeq          279
      55: aload         6
      57: checkcast     #175                // class org/springframework/jdbc/core/SqlOutParameter
      60: astore        7
      62: aload         7
      64: invokevirtual #176                // Method org/springframework/jdbc/core/SqlOutParameter.getName:()Ljava/lang/String;
      67: ifnull        74
      70: iconst_1
      71: goto          75
      74: iconst_0
      75: ldc           #177                // String Anonymous parameters not allowed
      77: invokestatic  #84                 // Method org/springframework/util/Assert.state:(ZLjava/lang/String;)V
      80: aload         7
      82: invokevirtual #178                // Method org/springframework/jdbc/core/SqlOutParameter.getSqlReturnType:()Lorg/springframework/jdbc/core/SqlReturnType;
      85: astore        8
      87: aload         8
      89: ifnull        131
      92: aload         8
      94: aload_1
      95: iload         4
      97: aload         7
      99: invokevirtual #179                // Method org/springframework/jdbc/core/SqlOutParameter.getSqlType:()I
     102: aload         7
     104: invokevirtual #180                // Method org/springframework/jdbc/core/SqlOutParameter.getTypeName:()Ljava/lang/String;
     107: invokeinterface #181,  5          // InterfaceMethod org/springframework/jdbc/core/SqlReturnType.getTypeValue:(Ljava/sql/CallableStatement;IILjava/lang/String;)Ljava/lang/Object;
     112: astore        9
     114: aload_3
     115: aload         7
     117: invokevirtual #176                // Method org/springframework/jdbc/core/SqlOutParameter.getName:()Ljava/lang/String;
     120: aload         9
     122: invokeinterface #169,  3          // InterfaceMethod java/util/Map.put:(Ljava/lang/Object;Ljava/lang/Object;)Ljava/lang/Object;
     127: pop
     128: goto          279
     131: aload_1
     132: iload         4
     134: invokeinterface #182,  2          // InterfaceMethod java/sql/CallableStatement.getObject:(I)Ljava/lang/Object;
     139: astore        9
     141: aload         9
     143: instanceof    #183                // class java/sql/ResultSet
     146: ifeq          265
     149: aload         7
     151: invokevirtual #184                // Method org/springframework/jdbc/core/SqlOutParameter.isResultSetSupported:()Z
     154: ifeq          177
     157: aload_3
     158: aload_0
     159: aload         9
     161: checkcast     #183                // class java/sql/ResultSet
     164: aload         7
     166: invokevirtual #157                // Method processResultSet:(Ljava/sql/ResultSet;Lorg/springframework/jdbc/core/ResultSetSupportingSqlParameter;)Ljava/util/Map;
     169: invokeinterface #158,  2          // InterfaceMethod java/util/Map.putAll:(Ljava/util/Map;)V
     174: goto          279
     177: aload         7
     179: invokevirtual #176                // Method org/springframework/jdbc/core/SqlOutParameter.getName:()Ljava/lang/String;
     182: astore        10
     184: new           #148                // class org/springframework/jdbc/core/SqlReturnResultSet
     187: dup
     188: aload         10
     190: aload_0
     191: invokevirtual #61                 // Method getColumnMapRowMapper:()Lorg/springframework/jdbc/core/RowMapper;
     194: invokespecial #161                // Method org/springframework/jdbc/core/SqlReturnResultSet."<init>":(Ljava/lang/String;Lorg/springframework/jdbc/core/RowMapper;)V
     197: astore        11
     199: aload_3
     200: aload_0
     201: aload         9
     203: checkcast     #183                // class java/sql/ResultSet
     206: aload         11
     208: invokevirtual #157                // Method processResultSet:(Ljava/sql/ResultSet;Lorg/springframework/jdbc/core/ResultSetSupportingSqlParameter;)Ljava/util/Map;
     211: invokeinterface #158,  2          // InterfaceMethod java/util/Map.putAll:(Ljava/util/Map;)V
     216: aload_0
     217: getfield      #1                  // Field logger:Lorg/apache/commons/logging/Log;
     220: invokeinterface #162,  1          // InterfaceMethod org/apache/commons/logging/Log.isTraceEnabled:()Z
     225: ifeq          262
     228: aload_0
     229: getfield      #1                  // Field logger:Lorg/apache/commons/logging/Log;
     232: new           #39                 // class java/lang/StringBuilder
     235: dup
     236: invokespecial #40                 // Method java/lang/StringBuilder."<init>":()V
     239: ldc           #163                // String Added default SqlReturnResultSet parameter named \'
     241: invokevirtual #42                 // Method java/lang/StringBuilder.append:(Ljava/lang/String;)Ljava/lang/StringBuilder;
     244: aload         10
     246: invokevirtual #42                 // Method java/lang/StringBuilder.append:(Ljava/lang/String;)Ljava/lang/StringBuilder;
     249: ldc           #164                // String \'
     251: invokevirtual #42                 // Method java/lang/StringBuilder.append:(Ljava/lang/String;)Ljava/lang/StringBuilder;
     254: invokevirtual #44                 // Method java/lang/StringBuilder.toString:()Ljava/lang/String;
     257: invokeinterface #165,  2          // InterfaceMethod org/apache/commons/logging/Log.trace:(Ljava/lang/Object;)V
     262: goto          279
     265: aload_3
     266: aload         7
     268: invokevirtual #176                // Method org/springframework/jdbc/core/SqlOutParameter.getName:()Ljava/lang/String;
     271: aload         9
     273: invokeinterface #169,  3          // InterfaceMethod java/util/Map.put:(Ljava/lang/Object;Ljava/lang/Object;)Ljava/lang/Object;
     278: pop
     279: aload         6
     281: invokevirtual #147                // Method org/springframework/jdbc/core/SqlParameter.isResultsParameter:()Z
     284: ifne          290
     287: iinc          4, 1
     290: goto          25
     293: aload_3
     294: areturn

  protected java.util.Map<java.lang.String, java.lang.Object> processResultSet(java.sql.ResultSet, org.springframework.jdbc.core.ResultSetSupportingSqlParameter) throws java.sql.SQLException;
    Code:
       0: aload_1
       1: ifnull        142
       4: aload_2
       5: invokevirtual #185                // Method org/springframework/jdbc/core/ResultSetSupportingSqlParameter.getRowMapper:()Lorg/springframework/jdbc/core/RowMapper;
       8: ifnull        48
      11: aload_2
      12: invokevirtual #185                // Method org/springframework/jdbc/core/ResultSetSupportingSqlParameter.getRowMapper:()Lorg/springframework/jdbc/core/RowMapper;
      15: astore_3
      16: new           #57                 // class org/springframework/jdbc/core/RowMapperResultSetExtractor
      19: dup
      20: aload_3
      21: invokespecial #58                 // Method org/springframework/jdbc/core/RowMapperResultSetExtractor."<init>":(Lorg/springframework/jdbc/core/RowMapper;)V
      24: aload_1
      25: invokevirtual #186                // Method org/springframework/jdbc/core/RowMapperResultSetExtractor.extractData:(Ljava/sql/ResultSet;)Ljava/util/List;
      28: astore        4
      30: aload_2
      31: invokevirtual #187                // Method org/springframework/jdbc/core/ResultSetSupportingSqlParameter.getName:()Ljava/lang/String;
      34: aload         4
      36: invokestatic  #188                // Method java/util/Collections.singletonMap:(Ljava/lang/Object;Ljava/lang/Object;)Ljava/util/Map;
      39: astore        5
      41: aload_1
      42: invokestatic  #189                // Method org/springframework/jdbc/support/JdbcUtils.closeResultSet:(Ljava/sql/ResultSet;)V
      45: aload         5
      47: areturn
      48: aload_2
      49: invokevirtual #190                // Method org/springframework/jdbc/core/ResultSetSupportingSqlParameter.getRowCallbackHandler:()Lorg/springframework/jdbc/core/RowCallbackHandler;
      52: ifnull        91
      55: aload_2
      56: invokevirtual #190                // Method org/springframework/jdbc/core/ResultSetSupportingSqlParameter.getRowCallbackHandler:()Lorg/springframework/jdbc/core/RowCallbackHandler;
      59: astore_3
      60: new           #54                 // class org/springframework/jdbc/core/JdbcTemplate$RowCallbackHandlerResultSetExtractor
      63: dup
      64: aload_3
      65: invokespecial #55                 // Method org/springframework/jdbc/core/JdbcTemplate$RowCallbackHandlerResultSetExtractor."<init>":(Lorg/springframework/jdbc/core/RowCallbackHandler;)V
      68: aload_1
      69: invokevirtual #191                // Method org/springframework/jdbc/core/JdbcTemplate$RowCallbackHandlerResultSetExtractor.extractData:(Ljava/sql/ResultSet;)Ljava/lang/Object;
      72: pop
      73: aload_2
      74: invokevirtual #187                // Method org/springframework/jdbc/core/ResultSetSupportingSqlParameter.getName:()Ljava/lang/String;
      77: ldc           #192                // String ResultSet returned from stored procedure was processed
      79: invokestatic  #188                // Method java/util/Collections.singletonMap:(Ljava/lang/Object;Ljava/lang/Object;)Ljava/util/Map;
      82: astore        4
      84: aload_1
      85: invokestatic  #189                // Method org/springframework/jdbc/support/JdbcUtils.closeResultSet:(Ljava/sql/ResultSet;)V
      88: aload         4
      90: areturn
      91: aload_2
      92: invokevirtual #193                // Method org/springframework/jdbc/core/ResultSetSupportingSqlParameter.getResultSetExtractor:()Lorg/springframework/jdbc/core/ResultSetExtractor;
      95: ifnull        126
      98: aload_2
      99: invokevirtual #193                // Method org/springframework/jdbc/core/ResultSetSupportingSqlParameter.getResultSetExtractor:()Lorg/springframework/jdbc/core/ResultSetExtractor;
     102: aload_1
     103: invokeinterface #194,  2          // InterfaceMethod org/springframework/jdbc/core/ResultSetExtractor.extractData:(Ljava/sql/ResultSet;)Ljava/lang/Object;
     108: astore_3
     109: aload_2
     110: invokevirtual #187                // Method org/springframework/jdbc/core/ResultSetSupportingSqlParameter.getName:()Ljava/lang/String;
     113: aload_3
     114: invokestatic  #188                // Method java/util/Collections.singletonMap:(Ljava/lang/Object;Ljava/lang/Object;)Ljava/util/Map;
     117: astore        4
     119: aload_1
     120: invokestatic  #189                // Method org/springframework/jdbc/support/JdbcUtils.closeResultSet:(Ljava/sql/ResultSet;)V
     123: aload         4
     125: areturn
     126: aload_1
     127: invokestatic  #189                // Method org/springframework/jdbc/support/JdbcUtils.closeResultSet:(Ljava/sql/ResultSet;)V
     130: goto          142
     133: astore        6
     135: aload_1
     136: invokestatic  #189                // Method org/springframework/jdbc/support/JdbcUtils.closeResultSet:(Ljava/sql/ResultSet;)V
     139: aload         6
     141: athrow
     142: invokestatic  #195                // Method java/util/Collections.emptyMap:()Ljava/util/Map;
     145: areturn
    Exception table:
       from    to  target type
           4    41   133   any
          48    84   133   any
          91   119   133   any
         133   135   133   any

  protected org.springframework.jdbc.core.RowMapper<java.util.Map<java.lang.String, java.lang.Object>> getColumnMapRowMapper();
    Code:
       0: new           #196                // class org/springframework/jdbc/core/ColumnMapRowMapper
       3: dup
       4: invokespecial #197                // Method org/springframework/jdbc/core/ColumnMapRowMapper."<init>":()V
       7: areturn

  protected <T> org.springframework.jdbc.core.RowMapper<T> getSingleColumnRowMapper(java.lang.Class<T>);
    Code:
       0: new           #198                // class org/springframework/jdbc/core/SingleColumnRowMapper
       3: dup
       4: aload_1
       5: invokespecial #199                // Method org/springframework/jdbc/core/SingleColumnRowMapper."<init>":(Ljava/lang/Class;)V
       8: areturn

  protected java.util.Map<java.lang.String, java.lang.Object> createResultsMap();
    Code:
       0: aload_0
       1: invokevirtual #200                // Method isResultsMapCaseInsensitive:()Z
       4: ifeq          15
       7: new           #201                // class org/springframework/util/LinkedCaseInsensitiveMap
      10: dup
      11: invokespecial #202                // Method org/springframework/util/LinkedCaseInsensitiveMap."<init>":()V
      14: areturn
      15: new           #152                // class java/util/LinkedHashMap
      18: dup
      19: invokespecial #203                // Method java/util/LinkedHashMap."<init>":()V
      22: areturn

  protected void applyStatementSettings(java.sql.Statement) throws java.sql.SQLException;
    Code:
       0: aload_0
       1: invokevirtual #204                // Method getFetchSize:()I
       4: istore_2
       5: iload_2
       6: iconst_m1
       7: if_icmpeq     17
      10: aload_1
      11: iload_2
      12: invokeinterface #205,  2          // InterfaceMethod java/sql/Statement.setFetchSize:(I)V
      17: aload_0
      18: invokevirtual #206                // Method getMaxRows:()I
      21: istore_3
      22: iload_3
      23: iconst_m1
      24: if_icmpeq     34
      27: aload_1
      28: iload_3
      29: invokeinterface #207,  2          // InterfaceMethod java/sql/Statement.setMaxRows:(I)V
      34: aload_1
      35: aload_0
      36: invokevirtual #19                 // Method getDataSource:()Ljavax/sql/DataSource;
      39: aload_0
      40: invokevirtual #208                // Method getQueryTimeout:()I
      43: invokestatic  #209                // Method org/springframework/jdbc/datasource/DataSourceUtils.applyTimeout:(Ljava/sql/Statement;Ljavax/sql/DataSource;I)V
      46: return

  protected org.springframework.jdbc.core.PreparedStatementSetter newArgPreparedStatementSetter(java.lang.Object[]);
    Code:
       0: new           #210                // class org/springframework/jdbc/core/ArgumentPreparedStatementSetter
       3: dup
       4: aload_1
       5: invokespecial #211                // Method org/springframework/jdbc/core/ArgumentPreparedStatementSetter."<init>":([Ljava/lang/Object;)V
       8: areturn

  protected org.springframework.jdbc.core.PreparedStatementSetter newArgTypePreparedStatementSetter(java.lang.Object[], int[]);
    Code:
       0: new           #212                // class org/springframework/jdbc/core/ArgumentTypePreparedStatementSetter
       3: dup
       4: aload_1
       5: aload_2
       6: invokespecial #213                // Method org/springframework/jdbc/core/ArgumentTypePreparedStatementSetter."<init>":([Ljava/lang/Object;[I)V
       9: areturn

  protected void handleWarnings(java.sql.Statement) throws java.sql.SQLException;
    Code:
       0: aload_0
       1: invokevirtual #214                // Method isIgnoreWarnings:()Z
       4: ifeq          101
       7: aload_0
       8: getfield      #1                  // Field logger:Lorg/apache/commons/logging/Log;
      11: invokeinterface #38,  1           // InterfaceMethod org/apache/commons/logging/Log.isDebugEnabled:()Z
      16: ifeq          111
      19: aload_1
      20: invokeinterface #215,  1          // InterfaceMethod java/sql/Statement.getWarnings:()Ljava/sql/SQLWarning;
      25: astore_2
      26: aload_2
      27: ifnull        98
      30: aload_0
      31: getfield      #1                  // Field logger:Lorg/apache/commons/logging/Log;
      34: new           #39                 // class java/lang/StringBuilder
      37: dup
      38: invokespecial #40                 // Method java/lang/StringBuilder."<init>":()V
      41: ldc           #216                // String SQLWarning ignored: SQL state \'
      43: invokevirtual #42                 // Method java/lang/StringBuilder.append:(Ljava/lang/String;)Ljava/lang/StringBuilder;
      46: aload_2
      47: invokevirtual #217                // Method java/sql/SQLWarning.getSQLState:()Ljava/lang/String;
      50: invokevirtual #42                 // Method java/lang/StringBuilder.append:(Ljava/lang/String;)Ljava/lang/StringBuilder;
      53: ldc           #218                // String \', error code \'
      55: invokevirtual #42                 // Method java/lang/StringBuilder.append:(Ljava/lang/String;)Ljava/lang/StringBuilder;
      58: aload_2
      59: invokevirtual #219                // Method java/sql/SQLWarning.getErrorCode:()I
      62: invokevirtual #78                 // Method java/lang/StringBuilder.append:(I)Ljava/lang/StringBuilder;
      65: ldc           #220                // String \', message [
      67: invokevirtual #42                 // Method java/lang/StringBuilder.append:(Ljava/lang/String;)Ljava/lang/StringBuilder;
      70: aload_2
      71: invokevirtual #221                // Method java/sql/SQLWarning.getMessage:()Ljava/lang/String;
      74: invokevirtual #42                 // Method java/lang/StringBuilder.append:(Ljava/lang/String;)Ljava/lang/StringBuilder;
      77: ldc           #43                 // String ]
      79: invokevirtual #42                 // Method java/lang/StringBuilder.append:(Ljava/lang/String;)Ljava/lang/StringBuilder;
      82: invokevirtual #44                 // Method java/lang/StringBuilder.toString:()Ljava/lang/String;
      85: invokeinterface #45,  2           // InterfaceMethod org/apache/commons/logging/Log.debug:(Ljava/lang/Object;)V
      90: aload_2
      91: invokevirtual #222                // Method java/sql/SQLWarning.getNextWarning:()Ljava/sql/SQLWarning;
      94: astore_2
      95: goto          26
      98: goto          111
     101: aload_0
     102: aload_1
     103: invokeinterface #215,  1          // InterfaceMethod java/sql/Statement.getWarnings:()Ljava/sql/SQLWarning;
     108: invokevirtual #223                // Method handleWarnings:(Ljava/sql/SQLWarning;)V
     111: return

  protected void handleWarnings(java.sql.SQLWarning) throws org.springframework.jdbc.SQLWarningException;
    Code:
       0: aload_1
       1: ifnull        15
       4: new           #224                // class org/springframework/jdbc/SQLWarningException
       7: dup
       8: ldc           #225                // String Warning not ignored
      10: aload_1
      11: invokespecial #226                // Method org/springframework/jdbc/SQLWarningException."<init>":(Ljava/lang/String;Ljava/sql/SQLWarning;)V
      14: athrow
      15: return

  protected org.springframework.dao.DataAccessException translateException(java.lang.String, java.lang.String, java.sql.SQLException);
    Code:
       0: aload_0
       1: invokevirtual #227                // Method getExceptionTranslator:()Lorg/springframework/jdbc/support/SQLExceptionTranslator;
       4: aload_1
       5: aload_2
       6: aload_3
       7: invokeinterface #228,  4          // InterfaceMethod org/springframework/jdbc/support/SQLExceptionTranslator.translate:(Ljava/lang/String;Ljava/lang/String;Ljava/sql/SQLException;)Lorg/springframework/dao/DataAccessException;
      12: astore        4
      14: aload         4
      16: ifnull        24
      19: aload         4
      21: goto          34
      24: new           #229                // class org/springframework/jdbc/UncategorizedSQLException
      27: dup
      28: aload_1
      29: aload_2
      30: aload_3
      31: invokespecial #230                // Method org/springframework/jdbc/UncategorizedSQLException."<init>":(Ljava/lang/String;Ljava/lang/String;Ljava/sql/SQLException;)V
      34: areturn

  private static java.lang.String getSql(java.lang.Object);
    Code:
       0: aload_0
       1: instanceof    #231                // class org/springframework/jdbc/core/SqlProvider
       4: ifeq          17
       7: aload_0
       8: checkcast     #231                // class org/springframework/jdbc/core/SqlProvider
      11: invokeinterface #232,  1          // InterfaceMethod org/springframework/jdbc/core/SqlProvider.getSql:()Ljava/lang/String;
      16: areturn
      17: aconst_null
      18: areturn

  private static <T> T result(T);
    Code:
       0: aload_0
       1: ifnull        8
       4: iconst_1
       5: goto          9
       8: iconst_0
       9: ldc           #233                // String No result
      11: invokestatic  #84                 // Method org/springframework/util/Assert.state:(ZLjava/lang/String;)V
      14: aload_0
      15: areturn

  private static int updateCount(java.lang.Integer);
    Code:
       0: aload_0
       1: ifnull        8
       4: iconst_1
       5: goto          9
       8: iconst_0
       9: ldc           #234                // String No update count
      11: invokestatic  #84                 // Method org/springframework/util/Assert.state:(ZLjava/lang/String;)V
      14: aload_0
      15: invokevirtual #235                // Method java/lang/Integer.intValue:()I
      18: ireturn

  private java.util.Map lambda$call$4(java.util.List, java.util.List, java.util.List, java.sql.CallableStatement) throws java.sql.SQLException, org.springframework.dao.DataAccessException;
    Code:
       0: aload         4
       2: invokeinterface #236,  1          // InterfaceMethod java/sql/CallableStatement.execute:()Z
       7: istore        5
       9: aload         4
      11: invokeinterface #173,  1          // InterfaceMethod java/sql/CallableStatement.getUpdateCount:()I
      16: istore        6
      18: aload_0
      19: getfield      #1                  // Field logger:Lorg/apache/commons/logging/Log;
      22: invokeinterface #162,  1          // InterfaceMethod org/apache/commons/logging/Log.isTraceEnabled:()Z
      27: ifeq          93
      30: aload_0
      31: getfield      #1                  // Field logger:Lorg/apache/commons/logging/Log;
      34: new           #39                 // class java/lang/StringBuilder
      37: dup
      38: invokespecial #40                 // Method java/lang/StringBuilder."<init>":()V
      41: ldc           #237                // String CallableStatement.execute() returned \'
      43: invokevirtual #42                 // Method java/lang/StringBuilder.append:(Ljava/lang/String;)Ljava/lang/StringBuilder;
      46: iload         5
      48: invokevirtual #238                // Method java/lang/StringBuilder.append:(Z)Ljava/lang/StringBuilder;
      51: ldc           #164                // String \'
      53: invokevirtual #42                 // Method java/lang/StringBuilder.append:(Ljava/lang/String;)Ljava/lang/StringBuilder;
      56: invokevirtual #44                 // Method java/lang/StringBuilder.toString:()Ljava/lang/String;
      59: invokeinterface #165,  2          // InterfaceMethod org/apache/commons/logging/Log.trace:(Ljava/lang/Object;)V
      64: aload_0
      65: getfield      #1                  // Field logger:Lorg/apache/commons/logging/Log;
      68: new           #39                 // class java/lang/StringBuilder
      71: dup
      72: invokespecial #40                 // Method java/lang/StringBuilder."<init>":()V
      75: ldc           #174                // String CallableStatement.getUpdateCount() returned
      77: invokevirtual #42                 // Method java/lang/StringBuilder.append:(Ljava/lang/String;)Ljava/lang/StringBuilder;
      80: iload         6
      82: invokevirtual #78                 // Method java/lang/StringBuilder.append:(I)Ljava/lang/StringBuilder;
      85: invokevirtual #44                 // Method java/lang/StringBuilder.toString:()Ljava/lang/String;
      88: invokeinterface #165,  2          // InterfaceMethod org/apache/commons/logging/Log.trace:(Ljava/lang/Object;)V
      93: aload_0
      94: invokevirtual #239                // Method createResultsMap:()Ljava/util/Map;
      97: astore        7
      99: iload         5
     101: ifne          110
     104: iload         6
     106: iconst_m1
     107: if_icmpeq     127
     110: aload         7
     112: aload_0
     113: aload         4
     115: aload_1
     116: aload_2
     117: iload         6
     119: invokevirtual #240                // Method extractReturnedResults:(Ljava/sql/CallableStatement;Ljava/util/List;Ljava/util/List;I)Ljava/util/Map;
     122: invokeinterface #158,  2          // InterfaceMethod java/util/Map.putAll:(Ljava/util/Map;)V
     127: aload         7
     129: aload_0
     130: aload         4
     132: aload_3
     133: invokevirtual #241                // Method extractOutputParameters:(Ljava/sql/CallableStatement;Ljava/util/List;)Ljava/util/Map;
     136: invokeinterface #158,  2          // InterfaceMethod java/util/Map.putAll:(Ljava/util/Map;)V
     141: aload         7
     143: areturn

  private int[][] lambda$batchUpdate$3(java.util.Collection, org.springframework.jdbc.core.ParameterizedPreparedStatementSetter, int, java.sql.PreparedStatement) throws java.sql.SQLException, org.springframework.dao.DataAccessException;
    Code:
       0: new           #141                // class java/util/ArrayList
       3: dup
       4: invokespecial #142                // Method java/util/ArrayList."<init>":()V
       7: astore        5
       9: aload         4
      11: invokeinterface #242,  1          // InterfaceMethod java/sql/PreparedStatement.getConnection:()Ljava/sql/Connection;
      16: invokestatic  #243                // Method org/springframework/jdbc/support/JdbcUtils.supportsBatchUpdates:(Ljava/sql/Connection;)Z
      19: istore        6
      21: iconst_0
      22: istore        7
      24: aload_1
      25: invokeinterface #244,  1          // InterfaceMethod java/util/Collection.iterator:()Ljava/util/Iterator;
      30: astore        8
      32: aload         8
      34: invokeinterface #144,  1          // InterfaceMethod java/util/Iterator.hasNext:()Z
      39: ifeq          245
      42: aload         8
      44: invokeinterface #145,  1          // InterfaceMethod java/util/Iterator.next:()Ljava/lang/Object;
      49: astore        9
      51: aload_2
      52: aload         4
      54: aload         9
      56: invokeinterface #245,  3          // InterfaceMethod org/springframework/jdbc/core/ParameterizedPreparedStatementSetter.setValues:(Ljava/sql/PreparedStatement;Ljava/lang/Object;)V
      61: iinc          7, 1
      64: iload         6
      66: ifeq          217
      69: aload         4
      71: invokeinterface #246,  1          // InterfaceMethod java/sql/PreparedStatement.addBatch:()V
      76: iload         7
      78: iload_3
      79: irem
      80: ifeq          94
      83: iload         7
      85: aload_1
      86: invokeinterface #247,  1          // InterfaceMethod java/util/Collection.size:()I
      91: if_icmpne     242
      94: aload_0
      95: getfield      #1                  // Field logger:Lorg/apache/commons/logging/Log;
      98: invokeinterface #162,  1          // InterfaceMethod org/apache/commons/logging/Log.isTraceEnabled:()Z
     103: ifeq          199
     106: iload         7
     108: iload_3
     109: irem
     110: ifne          120
     113: iload         7
     115: iload_3
     116: idiv
     117: goto          126
     120: iload         7
     122: iload_3
     123: idiv
     124: iconst_1
     125: iadd
     126: istore        10
     128: iload         7
     130: iload         7
     132: iload_3
     133: irem
     134: ifne          146
     137: iload         7
     139: iload_3
     140: idiv
     141: iconst_1
     142: isub
     143: goto          150
     146: iload         7
     148: iload_3
     149: idiv
     150: iload_3
     151: imul
     152: isub
     153: istore        11
     155: aload_0
     156: getfield      #1                  // Field logger:Lorg/apache/commons/logging/Log;
     159: new           #39                 // class java/lang/StringBuilder
     162: dup
     163: invokespecial #40                 // Method java/lang/StringBuilder."<init>":()V
     166: ldc           #248                // String Sending SQL batch update #
     168: invokevirtual #42                 // Method java/lang/StringBuilder.append:(Ljava/lang/String;)Ljava/lang/StringBuilder;
     171: iload         10
     173: invokevirtual #78                 // Method java/lang/StringBuilder.append:(I)Ljava/lang/StringBuilder;
     176: ldc           #249                // String  with
     178: invokevirtual #42                 // Method java/lang/StringBuilder.append:(Ljava/lang/String;)Ljava/lang/StringBuilder;
     181: iload         11
     183: invokevirtual #78                 // Method java/lang/StringBuilder.append:(I)Ljava/lang/StringBuilder;
     186: ldc           #250                // String  items
     188: invokevirtual #42                 // Method java/lang/StringBuilder.append:(Ljava/lang/String;)Ljava/lang/StringBuilder;
     191: invokevirtual #44                 // Method java/lang/StringBuilder.toString:()Ljava/lang/String;
     194: invokeinterface #165,  2          // InterfaceMethod org/apache/commons/logging/Log.trace:(Ljava/lang/Object;)V
     199: aload         5
     201: aload         4
     203: invokeinterface #251,  1          // InterfaceMethod java/sql/PreparedStatement.executeBatch:()[I
     208: invokeinterface #149,  2          // InterfaceMethod java/util/List.add:(Ljava/lang/Object;)Z
     213: pop
     214: goto          242
     217: aload         4
     219: invokeinterface #252,  1          // InterfaceMethod java/sql/PreparedStatement.executeUpdate:()I
     224: istore        10
     226: aload         5
     228: iconst_1
     229: newarray       int
     231: dup
     232: iconst_0
     233: iload         10
     235: iastore
     236: invokeinterface #149,  2          // InterfaceMethod java/util/List.add:(Ljava/lang/Object;)Z
     241: pop
     242: goto          32
     245: aload         5
     247: invokeinterface #154,  1          // InterfaceMethod java/util/List.size:()I
     252: anewarray     #82                 // class "[I"
     255: astore        8
     257: iconst_0
     258: istore        9
     260: iload         9
     262: aload         8
     264: arraylength
     265: if_icmpge     291
     268: aload         8
     270: iload         9
     272: aload         5
     274: iload         9
     276: invokeinterface #155,  2          // InterfaceMethod java/util/List.get:(I)Ljava/lang/Object;
     281: checkcast     #82                 // class "[I"
     284: aastore
     285: iinc          9, 1
     288: goto          260
     291: aload         8
     293: astore        9
     295: aload_2
     296: instanceof    #91                 // class org/springframework/jdbc/core/ParameterDisposer
     299: ifeq          311
     302: aload_2
     303: checkcast     #91                 // class org/springframework/jdbc/core/ParameterDisposer
     306: invokeinterface #92,  1           // InterfaceMethod org/springframework/jdbc/core/ParameterDisposer.cleanupParameters:()V
     311: aload         9
     313: areturn
     314: astore        12
     316: aload_2
     317: instanceof    #91                 // class org/springframework/jdbc/core/ParameterDisposer
     320: ifeq          332
     323: aload_2
     324: checkcast     #91                 // class org/springframework/jdbc/core/ParameterDisposer
     327: invokeinterface #92,  1           // InterfaceMethod org/springframework/jdbc/core/ParameterDisposer.cleanupParameters:()V
     332: aload         12
     334: athrow
    Exception table:
       from    to  target type
           9   295   314   any
         314   316   314   any

  private static int[] lambda$batchUpdate$2(org.springframework.jdbc.core.BatchPreparedStatementSetter, java.sql.PreparedStatement) throws java.sql.SQLException, org.springframework.dao.DataAccessException;
    Code:
       0: aload_0
       1: invokeinterface #253,  1          // InterfaceMethod org/springframework/jdbc/core/BatchPreparedStatementSetter.getBatchSize:()I
       6: istore_2
       7: aload_0
       8: instanceof    #254                // class org/springframework/jdbc/core/InterruptibleBatchPreparedStatementSetter
      11: ifeq          21
      14: aload_0
      15: checkcast     #254                // class org/springframework/jdbc/core/InterruptibleBatchPreparedStatementSetter
      18: goto          22
      21: aconst_null
      22: astore_3
      23: aload_1
      24: invokeinterface #242,  1          // InterfaceMethod java/sql/PreparedStatement.getConnection:()Ljava/sql/Connection;
      29: invokestatic  #243                // Method org/springframework/jdbc/support/JdbcUtils.supportsBatchUpdates:(Ljava/sql/Connection;)Z
      32: ifeq          110
      35: iconst_0
      36: istore        4
      38: iload         4
      40: iload_2
      41: if_icmpge     83
      44: aload_0
      45: aload_1
      46: iload         4
      48: invokeinterface #255,  3          // InterfaceMethod org/springframework/jdbc/core/BatchPreparedStatementSetter.setValues:(Ljava/sql/PreparedStatement;I)V
      53: aload_3
      54: ifnull        71
      57: aload_3
      58: iload         4
      60: invokeinterface #256,  2          // InterfaceMethod org/springframework/jdbc/core/InterruptibleBatchPreparedStatementSetter.isBatchExhausted:(I)Z
      65: ifeq          71
      68: goto          83
      71: aload_1
      72: invokeinterface #246,  1          // InterfaceMethod java/sql/PreparedStatement.addBatch:()V
      77: iinc          4, 1
      80: goto          38
      83: aload_1
      84: invokeinterface #251,  1          // InterfaceMethod java/sql/PreparedStatement.executeBatch:()[I
      89: astore        4
      91: aload_0
      92: instanceof    #91                 // class org/springframework/jdbc/core/ParameterDisposer
      95: ifeq          107
      98: aload_0
      99: checkcast     #91                 // class org/springframework/jdbc/core/ParameterDisposer
     102: invokeinterface #92,  1           // InterfaceMethod org/springframework/jdbc/core/ParameterDisposer.cleanupParameters:()V
     107: aload         4
     109: areturn
     110: new           #141                // class java/util/ArrayList
     113: dup
     114: invokespecial #142                // Method java/util/ArrayList."<init>":()V
     117: astore        4
     119: iconst_0
     120: istore        5
     122: iload         5
     124: iload_2
     125: if_icmpge     178
     128: aload_0
     129: aload_1
     130: iload         5
     132: invokeinterface #255,  3          // InterfaceMethod org/springframework/jdbc/core/BatchPreparedStatementSetter.setValues:(Ljava/sql/PreparedStatement;I)V
     137: aload_3
     138: ifnull        155
     141: aload_3
     142: iload         5
     144: invokeinterface #256,  2          // InterfaceMethod org/springframework/jdbc/core/InterruptibleBatchPreparedStatementSetter.isBatchExhausted:(I)Z
     149: ifeq          155
     152: goto          178
     155: aload         4
     157: aload_1
     158: invokeinterface #252,  1          // InterfaceMethod java/sql/PreparedStatement.executeUpdate:()I
     163: invokestatic  #168                // Method java/lang/Integer.valueOf:(I)Ljava/lang/Integer;
     166: invokeinterface #149,  2          // InterfaceMethod java/util/List.add:(Ljava/lang/Object;)Z
     171: pop
     172: iinc          5, 1
     175: goto          122
     178: aload         4
     180: invokeinterface #154,  1          // InterfaceMethod java/util/List.size:()I
     185: newarray       int
     187: astore        5
     189: iconst_0
     190: istore        6
     192: iload         6
     194: aload         5
     196: arraylength
     197: if_icmpge     226
     200: aload         5
     202: iload         6
     204: aload         4
     206: iload         6
     208: invokeinterface #155,  2          // InterfaceMethod java/util/List.get:(I)Ljava/lang/Object;
     213: checkcast     #73                 // class java/lang/Integer
     216: invokevirtual #235                // Method java/lang/Integer.intValue:()I
     219: iastore
     220: iinc          6, 1
     223: goto          192
     226: aload         5
     228: astore        6
     230: aload_0
     231: instanceof    #91                 // class org/springframework/jdbc/core/ParameterDisposer
     234: ifeq          246
     237: aload_0
     238: checkcast     #91                 // class org/springframework/jdbc/core/ParameterDisposer
     241: invokeinterface #92,  1           // InterfaceMethod org/springframework/jdbc/core/ParameterDisposer.cleanupParameters:()V
     246: aload         6
     248: areturn
     249: astore        7
     251: aload_0
     252: instanceof    #91                 // class org/springframework/jdbc/core/ParameterDisposer
     255: ifeq          267
     258: aload_0
     259: checkcast     #91                 // class org/springframework/jdbc/core/ParameterDisposer
     262: invokeinterface #92,  1           // InterfaceMethod org/springframework/jdbc/core/ParameterDisposer.cleanupParameters:()V
     267: aload         7
     269: athrow
    Exception table:
       from    to  target type
           0    91   249   any
         110   230   249   any
         249   251   249   any

  private java.lang.Integer lambda$update$1(org.springframework.jdbc.support.KeyHolder, java.sql.PreparedStatement) throws java.sql.SQLException, org.springframework.dao.DataAccessException;
    Code:
       0: aload_2
       1: invokeinterface #252,  1          // InterfaceMethod java/sql/PreparedStatement.executeUpdate:()I
       6: istore_3
       7: aload_1
       8: invokeinterface #257,  1          // InterfaceMethod org/springframework/jdbc/support/KeyHolder.getKeyList:()Ljava/util/List;
      13: astore        4
      15: aload         4
      17: invokeinterface #258,  1          // InterfaceMethod java/util/List.clear:()V
      22: aload_2
      23: invokeinterface #259,  1          // InterfaceMethod java/sql/PreparedStatement.getGeneratedKeys:()Ljava/sql/ResultSet;
      28: astore        5
      30: aload         5
      32: ifnull        88
      35: new           #57                 // class org/springframework/jdbc/core/RowMapperResultSetExtractor
      38: dup
      39: aload_0
      40: invokevirtual #61                 // Method getColumnMapRowMapper:()Lorg/springframework/jdbc/core/RowMapper;
      43: iconst_1
      44: invokespecial #108                // Method org/springframework/jdbc/core/RowMapperResultSetExtractor."<init>":(Lorg/springframework/jdbc/core/RowMapper;I)V
      47: astore        6
      49: aload         4
      51: aload         6
      53: aload         5
      55: invokevirtual #186                // Method org/springframework/jdbc/core/RowMapperResultSetExtractor.extractData:(Ljava/sql/ResultSet;)Ljava/util/List;
      58: invokestatic  #59                 // Method result:(Ljava/lang/Object;)Ljava/lang/Object;
      61: checkcast     #260                // class java/util/Collection
      64: invokeinterface #261,  2          // InterfaceMethod java/util/List.addAll:(Ljava/util/Collection;)Z
      69: pop
      70: aload         5
      72: invokestatic  #189                // Method org/springframework/jdbc/support/JdbcUtils.closeResultSet:(Ljava/sql/ResultSet;)V
      75: goto          88
      78: astore        7
      80: aload         5
      82: invokestatic  #189                // Method org/springframework/jdbc/support/JdbcUtils.closeResultSet:(Ljava/sql/ResultSet;)V
      85: aload         7
      87: athrow
      88: aload_0
      89: getfield      #1                  // Field logger:Lorg/apache/commons/logging/Log;
      92: invokeinterface #162,  1          // InterfaceMethod org/apache/commons/logging/Log.isTraceEnabled:()Z
      97: ifeq          151
     100: aload_0
     101: getfield      #1                  // Field logger:Lorg/apache/commons/logging/Log;
     104: new           #39                 // class java/lang/StringBuilder
     107: dup
     108: invokespecial #40                 // Method java/lang/StringBuilder."<init>":()V
     111: ldc_w         #262                // String SQL update affected
     114: invokevirtual #42                 // Method java/lang/StringBuilder.append:(Ljava/lang/String;)Ljava/lang/StringBuilder;
     117: iload_3
     118: invokevirtual #78                 // Method java/lang/StringBuilder.append:(I)Ljava/lang/StringBuilder;
     121: ldc_w         #263                // String  rows and returned
     124: invokevirtual #42                 // Method java/lang/StringBuilder.append:(Ljava/lang/String;)Ljava/lang/StringBuilder;
     127: aload         4
     129: invokeinterface #154,  1          // InterfaceMethod java/util/List.size:()I
     134: invokevirtual #78                 // Method java/lang/StringBuilder.append:(I)Ljava/lang/StringBuilder;
     137: ldc_w         #264                // String  keys
     140: invokevirtual #42                 // Method java/lang/StringBuilder.append:(Ljava/lang/String;)Ljava/lang/StringBuilder;
     143: invokevirtual #44                 // Method java/lang/StringBuilder.toString:()Ljava/lang/String;
     146: invokeinterface #165,  2          // InterfaceMethod org/apache/commons/logging/Log.trace:(Ljava/lang/Object;)V
     151: iload_3
     152: invokestatic  #168                // Method java/lang/Integer.valueOf:(I)Ljava/lang/Integer;
     155: areturn
    Exception table:
       from    to  target type
          35    70    78   any
          78    80    78   any

  private java.lang.Integer lambda$update$0(org.springframework.jdbc.core.PreparedStatementSetter, java.sql.PreparedStatement) throws java.sql.SQLException, org.springframework.dao.DataAccessException;
    Code:
       0: aload_1
       1: ifnull        11
       4: aload_1
       5: aload_2
       6: invokeinterface #265,  2          // InterfaceMethod org/springframework/jdbc/core/PreparedStatementSetter.setValues:(Ljava/sql/PreparedStatement;)V
      11: aload_2
      12: invokeinterface #252,  1          // InterfaceMethod java/sql/PreparedStatement.executeUpdate:()I
      17: istore_3
      18: aload_0
      19: getfield      #1                  // Field logger:Lorg/apache/commons/logging/Log;
      22: invokeinterface #162,  1          // InterfaceMethod org/apache/commons/logging/Log.isTraceEnabled:()Z
      27: ifeq          65
      30: aload_0
      31: getfield      #1                  // Field logger:Lorg/apache/commons/logging/Log;
      34: new           #39                 // class java/lang/StringBuilder
      37: dup
      38: invokespecial #40                 // Method java/lang/StringBuilder."<init>":()V
      41: ldc_w         #262                // String SQL update affected
      44: invokevirtual #42                 // Method java/lang/StringBuilder.append:(Ljava/lang/String;)Ljava/lang/StringBuilder;
      47: iload_3
      48: invokevirtual #78                 // Method java/lang/StringBuilder.append:(I)Ljava/lang/StringBuilder;
      51: ldc_w         #266                // String  rows
      54: invokevirtual #42                 // Method java/lang/StringBuilder.append:(Ljava/lang/String;)Ljava/lang/StringBuilder;
      57: invokevirtual #44                 // Method java/lang/StringBuilder.toString:()Ljava/lang/String;
      60: invokeinterface #165,  2          // InterfaceMethod org/apache/commons/logging/Log.trace:(Ljava/lang/Object;)V
      65: iload_3
      66: invokestatic  #168                // Method java/lang/Integer.valueOf:(I)Ljava/lang/Integer;
      69: astore        4
      71: aload_1
      72: instanceof    #91                 // class org/springframework/jdbc/core/ParameterDisposer
      75: ifeq          87
      78: aload_1
      79: checkcast     #91                 // class org/springframework/jdbc/core/ParameterDisposer
      82: invokeinterface #92,  1           // InterfaceMethod org/springframework/jdbc/core/ParameterDisposer.cleanupParameters:()V
      87: aload         4
      89: areturn
      90: astore        5
      92: aload_1
      93: instanceof    #91                 // class org/springframework/jdbc/core/ParameterDisposer
      96: ifeq          108
      99: aload_1
     100: checkcast     #91                 // class org/springframework/jdbc/core/ParameterDisposer
     103: invokeinterface #92,  1           // InterfaceMethod org/springframework/jdbc/core/ParameterDisposer.cleanupParameters:()V
     108: aload         5
     110: athrow
    Exception table:
       from    to  target type
           0    71    90   any
          90    92    90   any

  static org.apache.commons.logging.Log access$000(org.springframework.jdbc.core.JdbcTemplate);
    Code:
       0: aload_0
       1: getfield      #1                  // Field logger:Lorg/apache/commons/logging/Log;
       4: areturn

  static org.apache.commons.logging.Log access$100(org.springframework.jdbc.core.JdbcTemplate);
    Code:
       0: aload_0
       1: getfield      #1                  // Field logger:Lorg/apache/commons/logging/Log;
       4: areturn
}
