public class org.bouncycastle.cert.cmp.GeneralPKIMessage {
  private final org.bouncycastle.asn1.cmp.PKIMessage pkiMessage;

  private static org.bouncycastle.asn1.cmp.PKIMessage parseBytes(byte[]) throws java.io.IOException;
    Code:
       0: aload_0
       1: invokestatic  #71                 // Method org/bouncycastle/asn1/ASN1Primitive.fromByteArray:([B)Lorg/bouncycastle/asn1/ASN1Primitive;
       4: invokestatic  #75                 // Method org/bouncycastle/asn1/cmp/PKIMessage.getInstance:(Ljava/lang/Object;)Lorg/bouncycastle/asn1/cmp/PKIMessage;
       7: areturn
       8: astore_1
       9: new           #37                 // class org/bouncycastle/cert/CertIOException
      12: dup
      13: new           #33                 // class java/lang/StringBuilder
      16: dup
      17: invokespecial #68                 // Method java/lang/StringBuilder."<init>":()V
      20: ldc           #1                  // String malformed data:
      22: invokevirtual #70                 // Method java/lang/StringBuilder.append:(Ljava/lang/String;)Ljava/lang/StringBuilder;
      25: aload_1
      26: invokevirtual #65                 // Method java/lang/ClassCastException.getMessage:()Ljava/lang/String;
      29: invokevirtual #70                 // Method java/lang/StringBuilder.append:(Ljava/lang/String;)Ljava/lang/StringBuilder;
      32: invokevirtual #69                 // Method java/lang/StringBuilder.toString:()Ljava/lang/String;
      35: aload_1
      36: invokespecial #76                 // Method org/bouncycastle/cert/CertIOException."<init>":(Ljava/lang/String;Ljava/lang/Throwable;)V
      39: athrow
      40: astore_1
      41: new           #37                 // class org/bouncycastle/cert/CertIOException
      44: dup
      45: new           #33                 // class java/lang/StringBuilder
      48: dup
      49: invokespecial #68                 // Method java/lang/StringBuilder."<init>":()V
      52: ldc           #1                  // String malformed data:
      54: invokevirtual #70                 // Method java/lang/StringBuilder.append:(Ljava/lang/String;)Ljava/lang/StringBuilder;
      57: aload_1
      58: invokevirtual #66                 // Method java/lang/IllegalArgumentException.getMessage:()Ljava/lang/String;
      61: invokevirtual #70                 // Method java/lang/StringBuilder.append:(Ljava/lang/String;)Ljava/lang/StringBuilder;
      64: invokevirtual #69                 // Method java/lang/StringBuilder.toString:()Ljava/lang/String;
      67: aload_1
      68: invokespecial #76                 // Method org/bouncycastle/cert/CertIOException."<init>":(Ljava/lang/String;Ljava/lang/Throwable;)V
      71: athrow
    Exception table:
       from    to  target type
           0     7     8   Class java/lang/ClassCastException
           0     7    40   Class java/lang/IllegalArgumentException

  public org.bouncycastle.cert.cmp.GeneralPKIMessage(byte[]) throws java.io.IOException;
    Code:
       0: aload_0
       1: aload_1
       2: invokestatic  #78                 // Method parseBytes:([B)Lorg/bouncycastle/asn1/cmp/PKIMessage;
       5: invokespecial #77                 // Method "<init>":(Lorg/bouncycastle/asn1/cmp/PKIMessage;)V
       8: return

  public org.bouncycastle.cert.cmp.GeneralPKIMessage(org.bouncycastle.asn1.cmp.PKIMessage);
    Code:
       0: aload_0
       1: invokespecial #67                 // Method java/lang/Object."<init>":()V
       4: aload_0
       5: aload_1
       6: putfield      #64                 // Field pkiMessage:Lorg/bouncycastle/asn1/cmp/PKIMessage;
       9: return

  public org.bouncycastle.asn1.cmp.PKIHeader getHeader();
    Code:
       0: aload_0
       1: getfield      #64                 // Field pkiMessage:Lorg/bouncycastle/asn1/cmp/PKIMessage;
       4: invokevirtual #74                 // Method org/bouncycastle/asn1/cmp/PKIMessage.getHeader:()Lorg/bouncycastle/asn1/cmp/PKIHeader;
       7: areturn

  public org.bouncycastle.asn1.cmp.PKIBody getBody();
    Code:
       0: aload_0
       1: getfield      #64                 // Field pkiMessage:Lorg/bouncycastle/asn1/cmp/PKIMessage;
       4: invokevirtual #73                 // Method org/bouncycastle/asn1/cmp/PKIMessage.getBody:()Lorg/bouncycastle/asn1/cmp/PKIBody;
       7: areturn

  public boolean hasProtection();
    Code:
       0: aload_0
       1: getfield      #64                 // Field pkiMessage:Lorg/bouncycastle/asn1/cmp/PKIMessage;
       4: invokevirtual #74                 // Method org/bouncycastle/asn1/cmp/PKIMessage.getHeader:()Lorg/bouncycastle/asn1/cmp/PKIHeader;
       7: invokevirtual #72                 // Method org/bouncycastle/asn1/cmp/PKIHeader.getProtectionAlg:()Lorg/bouncycastle/asn1/x509/AlgorithmIdentifier;
      10: ifnull        17
      13: iconst_1
      14: goto          18
      17: iconst_0
      18: ireturn

  public org.bouncycastle.asn1.cmp.PKIMessage toASN1Structure();
    Code:
       0: aload_0
       1: getfield      #64                 // Field pkiMessage:Lorg/bouncycastle/asn1/cmp/PKIMessage;
       4: areturn
}
