Compiled from "AttributesResourceHandler.java"
public class org.sonatype.nexus.rest.attributes.AttributesResourceHandler extends org.sonatype.nexus.rest.restore.AbstractRestoreResourceHandler {
  public org.sonatype.nexus.rest.attributes.AttributesResourceHandler(org.restlet.Context, org.restlet.data.Request, org.restlet.data.Response);
    Code:
       0: aload_0
       1: aload_1
       2: aload_2
       3: aload_3
       4: invokespecial #1                  // Method org/sonatype/nexus/rest/restore/AbstractRestoreResourceHandler."<init>":(Lorg/restlet/Context;Lorg/restlet/data/Request;Lorg/restlet/data/Response;)V
       7: return

  public void handleDelete();
    Code:
       0: aload_0
       1: invokevirtual #2                  // Method getNexus:()Lorg/sonatype/nexus/Nexus;
       4: ldc_w         #3                  // class org/sonatype/nexus/tasks/RebuildAttributesTask
       7: invokeinterface #4,  2            // InterfaceMethod org/sonatype/nexus/Nexus.createTaskInstance:(Ljava/lang/Class;)Lorg/sonatype/scheduling/SchedulerTask;
      12: checkcast     #3                  // class org/sonatype/nexus/tasks/RebuildAttributesTask
      15: astore_1
      16: aload_1
      17: aload_0
      18: invokevirtual #5                  // Method getRepositoryId:()Ljava/lang/String;
      21: invokevirtual #6                  // Method org/sonatype/nexus/tasks/RebuildAttributesTask.setRepositoryId:(Ljava/lang/String;)V
      24: aload_1
      25: aload_0
      26: invokevirtual #7                  // Method getRepositoryGroupId:()Ljava/lang/String;
      29: invokevirtual #8                  // Method org/sonatype/nexus/tasks/RebuildAttributesTask.setRepositoryGroupId:(Ljava/lang/String;)V
      32: aload_1
      33: aload_0
      34: invokevirtual #9                  // Method getResourceStorePath:()Ljava/lang/String;
      37: invokevirtual #10                 // Method org/sonatype/nexus/tasks/RebuildAttributesTask.setResourceStorePath:(Ljava/lang/String;)V
      40: aload_0
      41: aload_1
      42: invokespecial #11                 // Method org/sonatype/nexus/rest/restore/AbstractRestoreResourceHandler.handleDelete:(Lorg/sonatype/scheduling/SchedulerTask;)V
      45: return
}
