Compiled from "TMultiplexedProcessor.java"
public class org.apache.thrift.TMultiplexedProcessor implements org.apache.thrift.TProcessor {
  private final java.util.Map<java.lang.String, org.apache.thrift.TProcessor> SERVICE_PROCESSOR_MAP;

  public org.apache.thrift.TMultiplexedProcessor();
    Code:
       0: aload_0
       1: invokespecial #1                  // Method java/lang/Object."<init>":()V
       4: aload_0
       5: new           #2                  // class java/util/HashMap
       8: dup
       9: invokespecial #3                  // Method java/util/HashMap."<init>":()V
      12: putfield      #4                  // Field SERVICE_PROCESSOR_MAP:Ljava/util/Map;
      15: return

  public void registerProcessor(java.lang.String, org.apache.thrift.TProcessor);
    Code:
       0: aload_0
       1: getfield      #4                  // Field SERVICE_PROCESSOR_MAP:Ljava/util/Map;
       4: aload_1
       5: aload_2
       6: invokeinterface #5,  3            // InterfaceMethod java/util/Map.put:(Ljava/lang/Object;Ljava/lang/Object;)Ljava/lang/Object;
      11: pop
      12: return

  public boolean process(org.apache.thrift.protocol.TProtocol, org.apache.thrift.protocol.TProtocol) throws org.apache.thrift.TException;
    Code:
       0: aload_1
       1: invokevirtual #6                  // Method org/apache/thrift/protocol/TProtocol.readMessageBegin:()Lorg/apache/thrift/protocol/TMessage;
       4: astore_3
       5: aload_3
       6: getfield      #7                  // Field org/apache/thrift/protocol/TMessage.type:B
       9: iconst_1
      10: if_icmpeq     31
      13: aload_3
      14: getfield      #7                  // Field org/apache/thrift/protocol/TMessage.type:B
      17: iconst_4
      18: if_icmpeq     31
      21: new           #8                  // class org/apache/thrift/TException
      24: dup
      25: ldc           #9                  // String This should not have happened!?
      27: invokespecial #10                 // Method org/apache/thrift/TException."<init>":(Ljava/lang/String;)V
      30: athrow
      31: aload_3
      32: getfield      #11                 // Field org/apache/thrift/protocol/TMessage.name:Ljava/lang/String;
      35: ldc           #12                 // String :
      37: invokevirtual #13                 // Method java/lang/String.indexOf:(Ljava/lang/String;)I
      40: istore        4
      42: iload         4
      44: ifge          87
      47: new           #8                  // class org/apache/thrift/TException
      50: dup
      51: new           #14                 // class java/lang/StringBuilder
      54: dup
      55: invokespecial #15                 // Method java/lang/StringBuilder."<init>":()V
      58: ldc           #16                 // String Service name not found in message name:
      60: invokevirtual #17                 // Method java/lang/StringBuilder.append:(Ljava/lang/String;)Ljava/lang/StringBuilder;
      63: aload_3
      64: getfield      #11                 // Field org/apache/thrift/protocol/TMessage.name:Ljava/lang/String;
      67: invokevirtual #17                 // Method java/lang/StringBuilder.append:(Ljava/lang/String;)Ljava/lang/StringBuilder;
      70: ldc           #18                 // String .  Did you
      72: invokevirtual #17                 // Method java/lang/StringBuilder.append:(Ljava/lang/String;)Ljava/lang/StringBuilder;
      75: ldc           #19                 // String forget to use a TMultiplexProtocol in your client?
      77: invokevirtual #17                 // Method java/lang/StringBuilder.append:(Ljava/lang/String;)Ljava/lang/StringBuilder;
      80: invokevirtual #20                 // Method java/lang/StringBuilder.toString:()Ljava/lang/String;
      83: invokespecial #10                 // Method org/apache/thrift/TException."<init>":(Ljava/lang/String;)V
      86: athrow
      87: aload_3
      88: getfield      #11                 // Field org/apache/thrift/protocol/TMessage.name:Ljava/lang/String;
      91: iconst_0
      92: iload         4
      94: invokevirtual #21                 // Method java/lang/String.substring:(II)Ljava/lang/String;
      97: astore        5
      99: aload_0
     100: getfield      #4                  // Field SERVICE_PROCESSOR_MAP:Ljava/util/Map;
     103: aload         5
     105: invokeinterface #22,  2           // InterfaceMethod java/util/Map.get:(Ljava/lang/Object;)Ljava/lang/Object;
     110: checkcast     #23                 // class org/apache/thrift/TProcessor
     113: astore        6
     115: aload         6
     117: ifnonnull     158
     120: new           #8                  // class org/apache/thrift/TException
     123: dup
     124: new           #14                 // class java/lang/StringBuilder
     127: dup
     128: invokespecial #15                 // Method java/lang/StringBuilder."<init>":()V
     131: ldc           #24                 // String Service name not found:
     133: invokevirtual #17                 // Method java/lang/StringBuilder.append:(Ljava/lang/String;)Ljava/lang/StringBuilder;
     136: aload         5
     138: invokevirtual #17                 // Method java/lang/StringBuilder.append:(Ljava/lang/String;)Ljava/lang/StringBuilder;
     141: ldc           #25                 // String .  Did you forget
     143: invokevirtual #17                 // Method java/lang/StringBuilder.append:(Ljava/lang/String;)Ljava/lang/StringBuilder;
     146: ldc           #26                 // String to call registerProcessor()?
     148: invokevirtual #17                 // Method java/lang/StringBuilder.append:(Ljava/lang/String;)Ljava/lang/StringBuilder;
     151: invokevirtual #20                 // Method java/lang/StringBuilder.toString:()Ljava/lang/String;
     154: invokespecial #10                 // Method org/apache/thrift/TException."<init>":(Ljava/lang/String;)V
     157: athrow
     158: new           #27                 // class org/apache/thrift/protocol/TMessage
     161: dup
     162: aload_3
     163: getfield      #11                 // Field org/apache/thrift/protocol/TMessage.name:Ljava/lang/String;
     166: aload         5
     168: invokevirtual #28                 // Method java/lang/String.length:()I
     171: ldc           #12                 // String :
     173: invokevirtual #28                 // Method java/lang/String.length:()I
     176: iadd
     177: invokevirtual #29                 // Method java/lang/String.substring:(I)Ljava/lang/String;
     180: aload_3
     181: getfield      #7                  // Field org/apache/thrift/protocol/TMessage.type:B
     184: aload_3
     185: getfield      #30                 // Field org/apache/thrift/protocol/TMessage.seqid:I
     188: invokespecial #31                 // Method org/apache/thrift/protocol/TMessage."<init>":(Ljava/lang/String;BI)V
     191: astore        7
     193: aload         6
     195: new           #32                 // class org/apache/thrift/TMultiplexedProcessor$StoredMessageProtocol
     198: dup
     199: aload_1
     200: aload         7
     202: invokespecial #33                 // Method org/apache/thrift/TMultiplexedProcessor$StoredMessageProtocol."<init>":(Lorg/apache/thrift/protocol/TProtocol;Lorg/apache/thrift/protocol/TMessage;)V
     205: aload_2
     206: invokeinterface #34,  3           // InterfaceMethod org/apache/thrift/TProcessor.process:(Lorg/apache/thrift/protocol/TProtocol;Lorg/apache/thrift/protocol/TProtocol;)Z
     211: ireturn
}
