Compiled from "TUnion.java"
class org.apache.thrift.TUnion$TUnionStandardScheme extends org.apache.thrift.scheme.StandardScheme<org.apache.thrift.TUnion> {
  private org.apache.thrift.TUnion$TUnionStandardScheme();
    Code:
       0: aload_0
       1: invokespecial #2                  // Method org/apache/thrift/scheme/StandardScheme."<init>":()V
       4: return

  public void read(org.apache.thrift.protocol.TProtocol, org.apache.thrift.TUnion) throws org.apache.thrift.TException;
    Code:
       0: aload_2
       1: aconst_null
       2: putfield      #3                  // Field org/apache/thrift/TUnion.setField_:Lorg/apache/thrift/TFieldIdEnum;
       5: aload_2
       6: aconst_null
       7: putfield      #4                  // Field org/apache/thrift/TUnion.value_:Ljava/lang/Object;
      10: aload_1
      11: invokevirtual #5                  // Method org/apache/thrift/protocol/TProtocol.readStructBegin:()Lorg/apache/thrift/protocol/TStruct;
      14: pop
      15: aload_1
      16: invokevirtual #6                  // Method org/apache/thrift/protocol/TProtocol.readFieldBegin:()Lorg/apache/thrift/protocol/TField;
      19: astore_3
      20: aload_2
      21: aload_2
      22: aload_1
      23: aload_3
      24: invokevirtual #7                  // Method org/apache/thrift/TUnion.standardSchemeReadValue:(Lorg/apache/thrift/protocol/TProtocol;Lorg/apache/thrift/protocol/TField;)Ljava/lang/Object;
      27: putfield      #4                  // Field org/apache/thrift/TUnion.value_:Ljava/lang/Object;
      30: aload_2
      31: getfield      #4                  // Field org/apache/thrift/TUnion.value_:Ljava/lang/Object;
      34: ifnull        49
      37: aload_2
      38: aload_2
      39: aload_3
      40: getfield      #8                  // Field org/apache/thrift/protocol/TField.id:S
      43: invokevirtual #9                  // Method org/apache/thrift/TUnion.enumForId:(S)Lorg/apache/thrift/TFieldIdEnum;
      46: putfield      #3                  // Field org/apache/thrift/TUnion.setField_:Lorg/apache/thrift/TFieldIdEnum;
      49: aload_1
      50: invokevirtual #10                 // Method org/apache/thrift/protocol/TProtocol.readFieldEnd:()V
      53: aload_1
      54: invokevirtual #6                  // Method org/apache/thrift/protocol/TProtocol.readFieldBegin:()Lorg/apache/thrift/protocol/TField;
      57: pop
      58: aload_1
      59: invokevirtual #11                 // Method org/apache/thrift/protocol/TProtocol.readStructEnd:()V
      62: return

  public void write(org.apache.thrift.protocol.TProtocol, org.apache.thrift.TUnion) throws org.apache.thrift.TException;
    Code:
       0: aload_2
       1: invokevirtual #12                 // Method org/apache/thrift/TUnion.getSetField:()Lorg/apache/thrift/TFieldIdEnum;
       4: ifnull        14
       7: aload_2
       8: invokevirtual #13                 // Method org/apache/thrift/TUnion.getFieldValue:()Ljava/lang/Object;
      11: ifnonnull     24
      14: new           #14                 // class org/apache/thrift/protocol/TProtocolException
      17: dup
      18: ldc           #15                 // String Cannot write a TUnion with no set value!
      20: invokespecial #16                 // Method org/apache/thrift/protocol/TProtocolException."<init>":(Ljava/lang/String;)V
      23: athrow
      24: aload_1
      25: aload_2
      26: invokevirtual #17                 // Method org/apache/thrift/TUnion.getStructDesc:()Lorg/apache/thrift/protocol/TStruct;
      29: invokevirtual #18                 // Method org/apache/thrift/protocol/TProtocol.writeStructBegin:(Lorg/apache/thrift/protocol/TStruct;)V
      32: aload_1
      33: aload_2
      34: aload_2
      35: getfield      #3                  // Field org/apache/thrift/TUnion.setField_:Lorg/apache/thrift/TFieldIdEnum;
      38: invokevirtual #19                 // Method org/apache/thrift/TUnion.getFieldDesc:(Lorg/apache/thrift/TFieldIdEnum;)Lorg/apache/thrift/protocol/TField;
      41: invokevirtual #20                 // Method org/apache/thrift/protocol/TProtocol.writeFieldBegin:(Lorg/apache/thrift/protocol/TField;)V
      44: aload_2
      45: aload_1
      46: invokevirtual #21                 // Method org/apache/thrift/TUnion.standardSchemeWriteValue:(Lorg/apache/thrift/protocol/TProtocol;)V
      49: aload_1
      50: invokevirtual #22                 // Method org/apache/thrift/protocol/TProtocol.writeFieldEnd:()V
      53: aload_1
      54: invokevirtual #23                 // Method org/apache/thrift/protocol/TProtocol.writeFieldStop:()V
      57: aload_1
      58: invokevirtual #24                 // Method org/apache/thrift/protocol/TProtocol.writeStructEnd:()V
      61: return

  public void write(org.apache.thrift.protocol.TProtocol, org.apache.thrift.TBase) throws org.apache.thrift.TException;
    Code:
       0: aload_0
       1: aload_1
       2: aload_2
       3: checkcast     #25                 // class org/apache/thrift/TUnion
       6: invokevirtual #26                 // Method write:(Lorg/apache/thrift/protocol/TProtocol;Lorg/apache/thrift/TUnion;)V
       9: return

  public void read(org.apache.thrift.protocol.TProtocol, org.apache.thrift.TBase) throws org.apache.thrift.TException;
    Code:
       0: aload_0
       1: aload_1
       2: aload_2
       3: checkcast     #25                 // class org/apache/thrift/TUnion
       6: invokevirtual #27                 // Method read:(Lorg/apache/thrift/protocol/TProtocol;Lorg/apache/thrift/TUnion;)V
       9: return

  org.apache.thrift.TUnion$TUnionStandardScheme(org.apache.thrift.TUnion$1);
    Code:
       0: aload_0
       1: invokespecial #1                  // Method "<init>":()V
       4: return
}
