Compiled from "ClassLoaderLogManager.java"
final class org.apache.juli.ClassLoaderLogManager$Cleaner extends java.lang.Thread {
  final org.apache.juli.ClassLoaderLogManager this$0;

  private org.apache.juli.ClassLoaderLogManager$Cleaner(org.apache.juli.ClassLoaderLogManager);
    Code:
       0: aload_0
       1: aload_1
       2: putfield      #2                  // Field this$0:Lorg/apache/juli/ClassLoaderLogManager;
       5: aload_0
       6: invokespecial #3                  // Method java/lang/Thread."<init>":()V
       9: return

  public void run();
    Code:
       0: aload_0
       1: getfield      #2                  // Field this$0:Lorg/apache/juli/ClassLoaderLogManager;
       4: getfield      #4                  // Field org/apache/juli/ClassLoaderLogManager.useShutdownHook:Z
       7: ifeq          17
      10: aload_0
      11: getfield      #2                  // Field this$0:Lorg/apache/juli/ClassLoaderLogManager;
      14: invokevirtual #5                  // Method org/apache/juli/ClassLoaderLogManager.shutdown:()V
      17: return

  org.apache.juli.ClassLoaderLogManager$Cleaner(org.apache.juli.ClassLoaderLogManager, org.apache.juli.ClassLoaderLogManager$1);
    Code:
       0: aload_0
       1: aload_1
       2: invokespecial #1                  // Method "<init>":(Lorg/apache/juli/ClassLoaderLogManager;)V
       5: return
}
