Compiled from "SchemaObject.java"
public abstract class org.flywaydb.core.internal.dbsupport.SchemaObject {
  protected final org.flywaydb.core.internal.dbsupport.JdbcTemplate jdbcTemplate;

  protected final org.flywaydb.core.internal.dbsupport.DbSupport dbSupport;

  protected final org.flywaydb.core.internal.dbsupport.Schema schema;

  protected final java.lang.String name;

  public org.flywaydb.core.internal.dbsupport.SchemaObject(org.flywaydb.core.internal.dbsupport.JdbcTemplate, org.flywaydb.core.internal.dbsupport.DbSupport, org.flywaydb.core.internal.dbsupport.Schema, java.lang.String);
    Code:
       0: aload_0
       1: invokespecial #1                  // Method java/lang/Object."<init>":()V
       4: aload_0
       5: aload         4
       7: putfield      #2                  // Field name:Ljava/lang/String;
      10: aload_0
      11: aload_1
      12: putfield      #3                  // Field jdbcTemplate:Lorg/flywaydb/core/internal/dbsupport/JdbcTemplate;
      15: aload_0
      16: aload_2
      17: putfield      #4                  // Field dbSupport:Lorg/flywaydb/core/internal/dbsupport/DbSupport;
      20: aload_0
      21: aload_3
      22: putfield      #5                  // Field schema:Lorg/flywaydb/core/internal/dbsupport/Schema;
      25: return

  public final org.flywaydb.core.internal.dbsupport.Schema getSchema();
    Code:
       0: aload_0
       1: getfield      #5                  // Field schema:Lorg/flywaydb/core/internal/dbsupport/Schema;
       4: areturn

  public final java.lang.String getName();
    Code:
       0: aload_0
       1: getfield      #2                  // Field name:Ljava/lang/String;
       4: areturn

  public final void drop();
    Code:
       0: aload_0
       1: invokevirtual #6                  // Method doDrop:()V
       4: goto          36
       7: astore_1
       8: new           #8                  // class org/flywaydb/core/api/FlywayException
      11: dup
      12: new           #9                  // class java/lang/StringBuilder
      15: dup
      16: invokespecial #10                 // Method java/lang/StringBuilder."<init>":()V
      19: ldc           #11                 // String Unable to drop
      21: invokevirtual #12                 // Method java/lang/StringBuilder.append:(Ljava/lang/String;)Ljava/lang/StringBuilder;
      24: aload_0
      25: invokevirtual #13                 // Method java/lang/StringBuilder.append:(Ljava/lang/Object;)Ljava/lang/StringBuilder;
      28: invokevirtual #14                 // Method java/lang/StringBuilder.toString:()Ljava/lang/String;
      31: aload_1
      32: invokespecial #15                 // Method org/flywaydb/core/api/FlywayException."<init>":(Ljava/lang/String;Ljava/lang/Throwable;)V
      35: athrow
      36: return
    Exception table:
       from    to  target type
           0     4     7   Class java/sql/SQLException

  protected abstract void doDrop() throws java.sql.SQLException;

  public java.lang.String toString();
    Code:
       0: aload_0
       1: getfield      #4                  // Field dbSupport:Lorg/flywaydb/core/internal/dbsupport/DbSupport;
       4: iconst_2
       5: anewarray     #16                 // class java/lang/String
       8: dup
       9: iconst_0
      10: aload_0
      11: getfield      #5                  // Field schema:Lorg/flywaydb/core/internal/dbsupport/Schema;
      14: invokevirtual #17                 // Method org/flywaydb/core/internal/dbsupport/Schema.getName:()Ljava/lang/String;
      17: aastore
      18: dup
      19: iconst_1
      20: aload_0
      21: getfield      #2                  // Field name:Ljava/lang/String;
      24: aastore
      25: invokevirtual #18                 // Method org/flywaydb/core/internal/dbsupport/DbSupport.quote:([Ljava/lang/String;)Ljava/lang/String;
      28: areturn
}
