Compiled from "SQLExceptionConverterFactory.java"
final class org.hibernate.exception.spi.SQLExceptionConverterFactory$1 implements org.hibernate.exception.spi.SQLExceptionConverter {
  org.hibernate.exception.spi.SQLExceptionConverterFactory$1();
    Code:
       0: aload_0
       1: invokespecial #1                  // Method java/lang/Object."<init>":()V
       4: return

  public org.hibernate.JDBCException convert(java.sql.SQLException, java.lang.String, java.lang.String);
    Code:
       0: new           #2                  // class org/hibernate/exception/GenericJDBCException
       3: dup
       4: aload_2
       5: aload_1
       6: aload_3
       7: invokespecial #3                  // Method org/hibernate/exception/GenericJDBCException."<init>":(Ljava/lang/String;Ljava/sql/SQLException;Ljava/lang/String;)V
      10: areturn
}
