Compiled from "HttpProxyConfigActions.java"
public class xworker.dataObject.proxy.HttpProxyConfigActions {
  public xworker.dataObject.proxy.HttpProxyConfigActions();
    Code:
       0: aload_0
       1: invokespecial #1                  // Method java/lang/Object."<init>":()V
       4: return

  public static java.lang.String getBaseUrl(org.xmeta.ActionContext);
    Code:
       0: aload_0
       1: ldc           #2                  // String self
       3: invokevirtual #3                  // Method org/xmeta/ActionContext.get:(Ljava/lang/Object;)Ljava/lang/Object;
       6: checkcast     #4                  // class org/xmeta/Thing
       9: astore_1
      10: aload_1
      11: ldc           #5                  // String baseUrl
      13: invokevirtual #6                  // Method org/xmeta/Thing.getString:(Ljava/lang/String;)Ljava/lang/String;
      16: areturn

  public static org.apache.http.client.HttpClient getHttpClient(org.xmeta.ActionContext);
    Code:
       0: aload_0
       1: ldc           #2                  // String self
       3: invokevirtual #3                  // Method org/xmeta/ActionContext.get:(Ljava/lang/Object;)Ljava/lang/Object;
       6: checkcast     #4                  // class org/xmeta/Thing
       9: astore_1
      10: invokestatic  #7                  // Method org/xmeta/World.getInstance:()Lorg/xmeta/World;
      13: aload_1
      14: ldc           #8                  // String httpClient
      16: invokevirtual #6                  // Method org/xmeta/Thing.getString:(Ljava/lang/String;)Ljava/lang/String;
      19: invokevirtual #9                  // Method org/xmeta/World.getThing:(Ljava/lang/String;)Lorg/xmeta/Thing;
      22: astore_2
      23: aload_2
      24: ifnonnull     34
      27: aload_1
      28: ldc           #10                 // String HttpClient@0
      30: invokevirtual #11                 // Method org/xmeta/Thing.getThing:(Ljava/lang/String;)Lorg/xmeta/Thing;
      33: astore_2
      34: aload_2
      35: ifnonnull     65
      38: new           #12                 // class xworker/dataObject/DataObjectException
      41: dup
      42: new           #13                 // class java/lang/StringBuilder
      45: dup
      46: invokespecial #14                 // Method java/lang/StringBuilder."<init>":()V
      49: ldc           #15                 // String Please set up httpClient, thing=
      51: invokevirtual #16                 // Method java/lang/StringBuilder.append:(Ljava/lang/String;)Ljava/lang/StringBuilder;
      54: aload_1
      55: invokevirtual #17                 // Method java/lang/StringBuilder.append:(Ljava/lang/Object;)Ljava/lang/StringBuilder;
      58: invokevirtual #18                 // Method java/lang/StringBuilder.toString:()Ljava/lang/String;
      61: invokespecial #19                 // Method xworker/dataObject/DataObjectException."<init>":(Ljava/lang/String;)V
      64: athrow
      65: aload_2
      66: ldc           #20                 // String getHttpClient
      68: aload_0
      69: invokevirtual #21                 // Method org/xmeta/Thing.doAction:(Ljava/lang/String;Lorg/xmeta/ActionContext;)Ljava/lang/Object;
      72: checkcast     #22                 // class org/apache/http/client/HttpClient
      75: areturn
}
