Compiled from "AbstractHTTPServlet.java"
public abstract class org.apache.cxf.transport.servlet.AbstractHTTPServlet extends javax.servlet.http.HttpServlet implements javax.servlet.Filter {
  private static final long serialVersionUID;

  private static final java.util.logging.Logger LOG;

  private static final java.util.ResourceBundle BUNDLE;

  private static final java.util.List<java.lang.String> KNOWN_HTTP_VERBS;

  private static final java.lang.String STATIC_RESOURCES_PARAMETER;

  private static final java.lang.String STATIC_WELCOME_FILE_PARAMETER;

  private static final java.lang.String STATIC_CACHE_CONTROL;

  private static final java.lang.String STATIC_RESOURCES_MAP_RESOURCE;

  private static final java.lang.String REDIRECTS_PARAMETER;

  private static final java.lang.String REDIRECT_SERVLET_NAME_PARAMETER;

  private static final java.lang.String REDIRECT_SERVLET_PATH_PARAMETER;

  private static final java.lang.String REDIRECT_ATTRIBUTES_PARAMETER;

  private static final java.lang.String REDIRECT_QUERY_CHECK_PARAMETER;

  private static final java.lang.String REDIRECT_WITH_INCLUDE_PARAMETER;

  private static final java.lang.String USE_X_FORWARDED_HEADERS_PARAMETER;

  private static final java.lang.String X_FORWARDED_PROTO_HEADER;

  private static final java.lang.String X_FORWARDED_FOR_HEADER;

  private static final java.util.Map<java.lang.String, java.lang.String> DEFAULT_STATIC_CONTENT_TYPES;

  private java.util.List<java.util.regex.Pattern> staticResourcesList;

  private java.lang.String staticWelcomeFile;

  private java.util.List<java.util.regex.Pattern> redirectList;

  private java.lang.String dispatcherServletPath;

  private java.lang.String dispatcherServletName;

  private java.util.Map<java.lang.String, java.lang.String> redirectAttributes;

  private java.util.Map<java.lang.String, java.lang.String> staticContentTypes;

  private boolean redirectQueryCheck;

  private boolean useXForwardedHeaders;

  public org.apache.cxf.transport.servlet.AbstractHTTPServlet();
    Code:
       0: aload_0
       1: invokespecial #1                  // Method javax/servlet/http/HttpServlet."<init>":()V
       4: aload_0
       5: new           #2                  // class java/util/HashMap
       8: dup
       9: getstatic     #3                  // Field DEFAULT_STATIC_CONTENT_TYPES:Ljava/util/Map;
      12: invokespecial #4                  // Method java/util/HashMap."<init>":(Ljava/util/Map;)V
      15: putfield      #5                  // Field staticContentTypes:Ljava/util/Map;
      18: return

  public void init(javax.servlet.ServletConfig) throws javax.servlet.ServletException;
    Code:
       0: aload_0
       1: aload_1
       2: invokespecial #6                  // Method javax/servlet/http/HttpServlet.init:(Ljavax/servlet/ServletConfig;)V
       5: aload_0
       6: aload_1
       7: ldc           #7                  // String static-resources-list
       9: invokeinterface #8,  2            // InterfaceMethod javax/servlet/ServletConfig.getInitParameter:(Ljava/lang/String;)Ljava/lang/String;
      14: invokestatic  #9                  // Method parseListSequence:(Ljava/lang/String;)Ljava/util/List;
      17: putfield      #10                 // Field staticResourcesList:Ljava/util/List;
      20: aload_0
      21: aload_1
      22: ldc           #11                 // String static-welcome-file
      24: invokeinterface #8,  2            // InterfaceMethod javax/servlet/ServletConfig.getInitParameter:(Ljava/lang/String;)Ljava/lang/String;
      29: putfield      #12                 // Field staticWelcomeFile:Ljava/lang/String;
      32: aload_0
      33: aload_1
      34: ldc           #13                 // String redirects-list
      36: invokeinterface #8,  2            // InterfaceMethod javax/servlet/ServletConfig.getInitParameter:(Ljava/lang/String;)Ljava/lang/String;
      41: invokestatic  #9                  // Method parseListSequence:(Ljava/lang/String;)Ljava/util/List;
      44: putfield      #14                 // Field redirectList:Ljava/util/List;
      47: aload_0
      48: aload_1
      49: ldc           #15                 // String redirect-query-check
      51: invokeinterface #8,  2            // InterfaceMethod javax/servlet/ServletConfig.getInitParameter:(Ljava/lang/String;)Ljava/lang/String;
      56: invokestatic  #16                 // Method java/lang/Boolean.valueOf:(Ljava/lang/String;)Ljava/lang/Boolean;
      59: invokevirtual #17                 // Method java/lang/Boolean.booleanValue:()Z
      62: putfield      #18                 // Field redirectQueryCheck:Z
      65: aload_0
      66: aload_1
      67: ldc           #19                 // String redirect-servlet-name
      69: invokeinterface #8,  2            // InterfaceMethod javax/servlet/ServletConfig.getInitParameter:(Ljava/lang/String;)Ljava/lang/String;
      74: putfield      #20                 // Field dispatcherServletName:Ljava/lang/String;
      77: aload_0
      78: aload_1
      79: ldc           #21                 // String redirect-servlet-path
      81: invokeinterface #8,  2            // InterfaceMethod javax/servlet/ServletConfig.getInitParameter:(Ljava/lang/String;)Ljava/lang/String;
      86: putfield      #22                 // Field dispatcherServletPath:Ljava/lang/String;
      89: aload_0
      90: aload_1
      91: ldc           #23                 // String redirect-attributes
      93: invokeinterface #8,  2            // InterfaceMethod javax/servlet/ServletConfig.getInitParameter:(Ljava/lang/String;)Ljava/lang/String;
      98: invokestatic  #24                 // Method parseMapSequence:(Ljava/lang/String;)Ljava/util/Map;
     101: putfield      #25                 // Field redirectAttributes:Ljava/util/Map;
     104: aload_0
     105: aload_1
     106: ldc           #26                 // String use-x-forwarded-headers
     108: invokeinterface #8,  2            // InterfaceMethod javax/servlet/ServletConfig.getInitParameter:(Ljava/lang/String;)Ljava/lang/String;
     113: invokestatic  #16                 // Method java/lang/Boolean.valueOf:(Ljava/lang/String;)Ljava/lang/Boolean;
     116: invokevirtual #17                 // Method java/lang/Boolean.booleanValue:()Z
     119: putfield      #27                 // Field useXForwardedHeaders:Z
     122: return

  protected void finalizeServletInit(javax.servlet.ServletConfig);
    Code:
       0: aload_0
       1: ldc           #28                 // String /WEB-INF/cxfServletStaticResourcesMap.txt
       3: invokevirtual #29                 // Method getResourceAsStream:(Ljava/lang/String;)Ljava/io/InputStream;
       6: astore_2
       7: aload_2
       8: ifnonnull     18
      11: aload_0
      12: ldc           #30                 // String /cxfServletStaticResourcesMap.txt
      14: invokevirtual #29                 // Method getResourceAsStream:(Ljava/lang/String;)Ljava/io/InputStream;
      17: astore_2
      18: aload_2
      19: ifnull        122
      22: new           #31                 // class java/util/Properties
      25: dup
      26: invokespecial #32                 // Method java/util/Properties."<init>":()V
      29: astore_3
      30: aload_3
      31: aload_2
      32: invokevirtual #33                 // Method java/util/Properties.load:(Ljava/io/InputStream;)V
      35: aload_3
      36: invokevirtual #34                 // Method java/util/Properties.stringPropertyNames:()Ljava/util/Set;
      39: invokeinterface #35,  1           // InterfaceMethod java/util/Set.iterator:()Ljava/util/Iterator;
      44: astore        4
      46: aload         4
      48: invokeinterface #36,  1           // InterfaceMethod java/util/Iterator.hasNext:()Z
      53: ifeq          89
      56: aload         4
      58: invokeinterface #37,  1           // InterfaceMethod java/util/Iterator.next:()Ljava/lang/Object;
      63: checkcast     #38                 // class java/lang/String
      66: astore        5
      68: aload_0
      69: getfield      #5                  // Field staticContentTypes:Ljava/util/Map;
      72: aload         5
      74: aload_3
      75: aload         5
      77: invokevirtual #39                 // Method java/util/Properties.getProperty:(Ljava/lang/String;)Ljava/lang/String;
      80: invokeinterface #40,  3           // InterfaceMethod java/util/Map.put:(Ljava/lang/Object;Ljava/lang/Object;)Ljava/lang/Object;
      85: pop
      86: goto          46
      89: goto          122
      92: astore_3
      93: new           #42                 // class org/apache/cxf/common/i18n/Message
      96: dup
      97: ldc           #43                 // String STATIC_RESOURCES_MAP_LOAD_FAILURE
      99: getstatic     #44                 // Field BUNDLE:Ljava/util/ResourceBundle;
     102: iconst_0
     103: anewarray     #45                 // class java/lang/Object
     106: invokespecial #46                 // Method org/apache/cxf/common/i18n/Message."<init>":(Ljava/lang/String;Ljava/util/ResourceBundle;[Ljava/lang/Object;)V
     109: invokevirtual #47                 // Method org/apache/cxf/common/i18n/Message.toString:()Ljava/lang/String;
     112: astore        4
     114: getstatic     #48                 // Field LOG:Ljava/util/logging/Logger;
     117: aload         4
     119: invokevirtual #49                 // Method java/util/logging/Logger.warning:(Ljava/lang/String;)V
     122: return
    Exception table:
       from    to  target type
          22    89    92   Class java/io/IOException

  protected java.io.InputStream getResourceAsStream(java.lang.String);
    Code:
       0: aload_1
       1: ldc_w         #50                 // class org/apache/cxf/transport/servlet/AbstractHTTPServlet
       4: invokestatic  #51                 // Method org/apache/cxf/common/classloader/ClassLoaderUtils.getResourceAsStream:(Ljava/lang/String;Ljava/lang/Class;)Ljava/io/InputStream;
       7: astore_2
       8: aload_2
       9: ifnonnull     53
      12: aload_0
      13: invokevirtual #52                 // Method getBus:()Lorg/apache/cxf/Bus;
      16: ifnull        53
      19: aload_0
      20: invokevirtual #52                 // Method getBus:()Lorg/apache/cxf/Bus;
      23: ldc_w         #53                 // class org/apache/cxf/resource/ResourceManager
      26: invokeinterface #54,  2           // InterfaceMethod org/apache/cxf/Bus.getExtension:(Ljava/lang/Class;)Ljava/lang/Object;
      31: checkcast     #53                 // class org/apache/cxf/resource/ResourceManager
      34: astore_3
      35: aload_3
      36: ifnull        53
      39: aload_3
      40: aload_1
      41: ldc_w         #55                 // class java/io/InputStream
      44: invokeinterface #56,  3           // InterfaceMethod org/apache/cxf/resource/ResourceManager.resolveResource:(Ljava/lang/String;Ljava/lang/Class;)Ljava/lang/Object;
      49: checkcast     #55                 // class java/io/InputStream
      52: astore_2
      53: aload_2
      54: areturn

  public final void init(javax.servlet.FilterConfig) throws javax.servlet.ServletException;
    Code:
       0: aload_0
       1: new           #57                 // class org/apache/cxf/transport/servlet/AbstractHTTPServlet$1
       4: dup
       5: aload_0
       6: aload_1
       7: invokespecial #58                 // Method org/apache/cxf/transport/servlet/AbstractHTTPServlet$1."<init>":(Lorg/apache/cxf/transport/servlet/AbstractHTTPServlet;Ljavax/servlet/FilterConfig;)V
      10: invokevirtual #59                 // Method init:(Ljavax/servlet/ServletConfig;)V
      13: return

  protected static java.util.List<java.util.regex.Pattern> parseListSequence(java.lang.String);
    Code:
       0: aload_0
       1: ifnull        76
       4: new           #60                 // class java/util/LinkedList
       7: dup
       8: invokespecial #61                 // Method java/util/LinkedList."<init>":()V
      11: astore_1
      12: aload_0
      13: ldc           #62                 // String
      15: invokestatic  #63                 // Method org/apache/cxf/common/util/StringUtils.split:(Ljava/lang/String;Ljava/lang/String;)[Ljava/lang/String;
      18: astore_2
      19: aload_2
      20: astore_3
      21: aload_3
      22: arraylength
      23: istore        4
      25: iconst_0
      26: istore        5
      28: iload         5
      30: iload         4
      32: if_icmpge     74
      35: aload_3
      36: iload         5
      38: aaload
      39: astore        6
      41: aload         6
      43: invokevirtual #64                 // Method java/lang/String.trim:()Ljava/lang/String;
      46: astore        7
      48: aload         7
      50: invokevirtual #65                 // Method java/lang/String.length:()I
      53: ifle          68
      56: aload_1
      57: aload         7
      59: invokestatic  #66                 // Method java/util/regex/Pattern.compile:(Ljava/lang/String;)Ljava/util/regex/Pattern;
      62: invokeinterface #67,  2           // InterfaceMethod java/util/List.add:(Ljava/lang/Object;)Z
      67: pop
      68: iinc          5, 1
      71: goto          28
      74: aload_1
      75: areturn
      76: aconst_null
      77: areturn

  protected static java.util.Map<java.lang.String, java.lang.String> parseMapSequence(java.lang.String);
    Code:
       0: aload_0
       1: ifnull        123
       4: aload_0
       5: invokevirtual #64                 // Method java/lang/String.trim:()Ljava/lang/String;
       8: astore_0
       9: new           #2                  // class java/util/HashMap
      12: dup
      13: invokespecial #68                 // Method java/util/HashMap."<init>":()V
      16: astore_1
      17: aload_0
      18: ldc           #62                 // String
      20: invokestatic  #63                 // Method org/apache/cxf/common/util/StringUtils.split:(Ljava/lang/String;Ljava/lang/String;)[Ljava/lang/String;
      23: astore_2
      24: aload_2
      25: astore_3
      26: aload_3
      27: arraylength
      28: istore        4
      30: iconst_0
      31: istore        5
      33: iload         5
      35: iload         4
      37: if_icmpge     121
      40: aload_3
      41: iload         5
      43: aaload
      44: astore        6
      46: aload         6
      48: invokevirtual #64                 // Method java/lang/String.trim:()Ljava/lang/String;
      51: astore        7
      53: aload         7
      55: invokevirtual #65                 // Method java/lang/String.length:()I
      58: ifne          64
      61: goto          115
      64: aload         7
      66: ldc           #69                 // String =
      68: invokestatic  #63                 // Method org/apache/cxf/common/util/StringUtils.split:(Ljava/lang/String;Ljava/lang/String;)[Ljava/lang/String;
      71: astore        8
      73: aload         8
      75: arraylength
      76: iconst_2
      77: if_icmpne     104
      80: aload_1
      81: aload         8
      83: iconst_0
      84: aaload
      85: invokevirtual #64                 // Method java/lang/String.trim:()Ljava/lang/String;
      88: aload         8
      90: iconst_1
      91: aaload
      92: invokevirtual #64                 // Method java/lang/String.trim:()Ljava/lang/String;
      95: invokeinterface #40,  3           // InterfaceMethod java/util/Map.put:(Ljava/lang/Object;Ljava/lang/Object;)Ljava/lang/Object;
     100: pop
     101: goto          115
     104: aload_1
     105: aload         7
     107: ldc           #70                 // String
     109: invokeinterface #40,  3           // InterfaceMethod java/util/Map.put:(Ljava/lang/Object;Ljava/lang/Object;)Ljava/lang/Object;
     114: pop
     115: iinc          5, 1
     118: goto          33
     121: aload_1
     122: areturn
     123: invokestatic  #71                 // Method java/util/Collections.emptyMap:()Ljava/util/Map;
     126: areturn

  protected void doPost(javax.servlet.http.HttpServletRequest, javax.servlet.http.HttpServletResponse) throws javax.servlet.ServletException;
    Code:
       0: aload_0
       1: aload_1
       2: aload_2
       3: invokevirtual #72                 // Method handleRequest:(Ljavax/servlet/http/HttpServletRequest;Ljavax/servlet/http/HttpServletResponse;)V
       6: return

  protected void doGet(javax.servlet.http.HttpServletRequest, javax.servlet.http.HttpServletResponse) throws javax.servlet.ServletException;
    Code:
       0: aload_0
       1: aload_1
       2: aload_2
       3: invokevirtual #72                 // Method handleRequest:(Ljavax/servlet/http/HttpServletRequest;Ljavax/servlet/http/HttpServletResponse;)V
       6: return

  protected void doDelete(javax.servlet.http.HttpServletRequest, javax.servlet.http.HttpServletResponse) throws javax.servlet.ServletException, java.io.IOException;
    Code:
       0: aload_0
       1: aload_1
       2: aload_2
       3: invokevirtual #72                 // Method handleRequest:(Ljavax/servlet/http/HttpServletRequest;Ljavax/servlet/http/HttpServletResponse;)V
       6: return

  protected void doPut(javax.servlet.http.HttpServletRequest, javax.servlet.http.HttpServletResponse) throws javax.servlet.ServletException, java.io.IOException;
    Code:
       0: aload_0
       1: aload_1
       2: aload_2
       3: invokevirtual #72                 // Method handleRequest:(Ljavax/servlet/http/HttpServletRequest;Ljavax/servlet/http/HttpServletResponse;)V
       6: return

  protected void doHead(javax.servlet.http.HttpServletRequest, javax.servlet.http.HttpServletResponse) throws javax.servlet.ServletException, java.io.IOException;
    Code:
       0: aload_0
       1: aload_1
       2: aload_2
       3: invokevirtual #72                 // Method handleRequest:(Ljavax/servlet/http/HttpServletRequest;Ljavax/servlet/http/HttpServletResponse;)V
       6: return

  protected void doOptions(javax.servlet.http.HttpServletRequest, javax.servlet.http.HttpServletResponse) throws javax.servlet.ServletException, java.io.IOException;
    Code:
       0: aload_0
       1: aload_1
       2: aload_2
       3: invokevirtual #72                 // Method handleRequest:(Ljavax/servlet/http/HttpServletRequest;Ljavax/servlet/http/HttpServletResponse;)V
       6: return

  public void service(javax.servlet.ServletRequest, javax.servlet.ServletResponse) throws javax.servlet.ServletException, java.io.IOException;
    Code:
       0: aload_1
       1: checkcast     #73                 // class javax/servlet/http/HttpServletRequest
       4: astore_3
       5: aload_2
       6: checkcast     #74                 // class javax/servlet/http/HttpServletResponse
       9: astore        4
      11: goto          26
      14: astore        5
      16: new           #76                 // class javax/servlet/ServletException
      19: dup
      20: ldc           #77                 // String Unrecognized HTTP request or response object
      22: invokespecial #78                 // Method javax/servlet/ServletException."<init>":(Ljava/lang/String;)V
      25: athrow
      26: aload_3
      27: invokeinterface #79,  1           // InterfaceMethod javax/servlet/http/HttpServletRequest.getMethod:()Ljava/lang/String;
      32: astore        5
      34: getstatic     #80                 // Field KNOWN_HTTP_VERBS:Ljava/util/List;
      37: aload         5
      39: invokeinterface #81,  2           // InterfaceMethod java/util/List.contains:(Ljava/lang/Object;)Z
      44: ifeq          57
      47: aload_0
      48: aload_3
      49: aload         4
      51: invokespecial #82                 // Method javax/servlet/http/HttpServlet.service:(Ljavax/servlet/http/HttpServletRequest;Ljavax/servlet/http/HttpServletResponse;)V
      54: goto          64
      57: aload_0
      58: aload_3
      59: aload         4
      61: invokevirtual #72                 // Method handleRequest:(Ljavax/servlet/http/HttpServletRequest;Ljavax/servlet/http/HttpServletResponse;)V
      64: return
    Exception table:
       from    to  target type
           0    11    14   Class java/lang/ClassCastException

  protected void handleRequest(javax.servlet.http.HttpServletRequest, javax.servlet.http.HttpServletResponse) throws javax.servlet.ServletException;
    Code:
       0: aload_0
       1: getfield      #22                 // Field dispatcherServletPath:Ljava/lang/String;
       4: ifnonnull     14
       7: aload_0
       8: getfield      #20                 // Field dispatcherServletName:Ljava/lang/String;
      11: ifnull        53
      14: aload_0
      15: getfield      #14                 // Field redirectList:Ljava/util/List;
      18: ifnull        33
      21: aload_0
      22: aload_0
      23: getfield      #14                 // Field redirectList:Ljava/util/List;
      26: aload_1
      27: invokespecial #83                 // Method matchPath:(Ljava/util/List;Ljavax/servlet/http/HttpServletRequest;)Z
      30: ifne          40
      33: aload_0
      34: getfield      #14                 // Field redirectList:Ljava/util/List;
      37: ifnonnull     53
      40: aload_0
      41: aload_1
      42: aload_2
      43: aload_1
      44: invokeinterface #84,  1           // InterfaceMethod javax/servlet/http/HttpServletRequest.getPathInfo:()Ljava/lang/String;
      49: invokevirtual #85                 // Method redirect:(Ljavax/servlet/http/HttpServletRequest;Ljavax/servlet/http/HttpServletResponse;Ljava/lang/String;)V
      52: return
      53: aload_0
      54: getfield      #10                 // Field staticResourcesList:Ljava/util/List;
      57: ifnull        76
      60: aload_0
      61: aload_0
      62: getfield      #10                 // Field staticResourcesList:Ljava/util/List;
      65: aload_1
      66: invokespecial #83                 // Method matchPath:(Ljava/util/List;Ljavax/servlet/http/HttpServletRequest;)Z
      69: ifeq          76
      72: iconst_1
      73: goto          77
      76: iconst_0
      77: istore_3
      78: aload_0
      79: getfield      #12                 // Field staticWelcomeFile:Ljava/lang/String;
      82: ifnull        115
      85: aload_1
      86: invokeinterface #84,  1           // InterfaceMethod javax/servlet/http/HttpServletRequest.getPathInfo:()Ljava/lang/String;
      91: invokestatic  #86                 // Method org/apache/cxf/common/util/StringUtils.isEmpty:(Ljava/lang/String;)Z
      94: ifne          111
      97: aload_1
      98: invokeinterface #84,  1           // InterfaceMethod javax/servlet/http/HttpServletRequest.getPathInfo:()Ljava/lang/String;
     103: ldc           #87                 // String /
     105: invokevirtual #88                 // Method java/lang/String.equals:(Ljava/lang/Object;)Z
     108: ifeq          115
     111: iconst_1
     112: goto          116
     115: iconst_0
     116: istore        4
     118: iload_3
     119: ifne          127
     122: iload         4
     124: ifeq          152
     127: aload_0
     128: aload_1
     129: aload_2
     130: iload         4
     132: ifeq          142
     135: aload_0
     136: getfield      #12                 // Field staticWelcomeFile:Ljava/lang/String;
     139: goto          148
     142: aload_1
     143: invokeinterface #84,  1           // InterfaceMethod javax/servlet/http/HttpServletRequest.getPathInfo:()Ljava/lang/String;
     148: invokevirtual #89                 // Method serveStaticContent:(Ljavax/servlet/http/HttpServletRequest;Ljavax/servlet/http/HttpServletResponse;Ljava/lang/String;)V
     151: return
     152: aload_0
     153: aload_1
     154: invokevirtual #90                 // Method checkXForwardedHeaders:(Ljavax/servlet/http/HttpServletRequest;)Ljavax/servlet/http/HttpServletRequest;
     157: astore_1
     158: aload_0
     159: aload_1
     160: aload_2
     161: invokevirtual #91                 // Method invoke:(Ljavax/servlet/http/HttpServletRequest;Ljavax/servlet/http/HttpServletResponse;)V
     164: return

  protected javax.servlet.http.HttpServletRequest checkXForwardedHeaders(javax.servlet.http.HttpServletRequest);
    Code:
       0: aload_0
       1: getfield      #27                 // Field useXForwardedHeaders:Z
       4: ifeq          44
       7: aload_1
       8: ldc           #92                 // String X-Forwarded-Proto
      10: invokeinterface #93,  2           // InterfaceMethod javax/servlet/http/HttpServletRequest.getHeader:(Ljava/lang/String;)Ljava/lang/String;
      15: astore_2
      16: aload_1
      17: ldc           #94                 // String X-Forwarded-For
      19: invokeinterface #93,  2           // InterfaceMethod javax/servlet/http/HttpServletRequest.getHeader:(Ljava/lang/String;)Ljava/lang/String;
      24: astore_3
      25: aload_2
      26: ifnonnull     33
      29: aload_3
      30: ifnull        44
      33: new           #95                 // class org/apache/cxf/transport/servlet/AbstractHTTPServlet$HttpServletRequestXForwardedFilter
      36: dup
      37: aload_1
      38: aload_2
      39: aload_3
      40: invokespecial #96                 // Method org/apache/cxf/transport/servlet/AbstractHTTPServlet$HttpServletRequestXForwardedFilter."<init>":(Ljavax/servlet/http/HttpServletRequest;Ljava/lang/String;Ljava/lang/String;)V
      43: areturn
      44: aload_1
      45: areturn

  private boolean matchPath(java.util.List<java.util.regex.Pattern>, javax.servlet.http.HttpServletRequest);
    Code:
       0: aload_2
       1: invokeinterface #84,  1           // InterfaceMethod javax/servlet/http/HttpServletRequest.getPathInfo:()Ljava/lang/String;
       6: astore_3
       7: aload_3
       8: ifnonnull     14
      11: ldc           #87                 // String /
      13: astore_3
      14: aload_0
      15: getfield      #18                 // Field redirectQueryCheck:Z
      18: ifeq          67
      21: aload_2
      22: invokeinterface #97,  1           // InterfaceMethod javax/servlet/http/HttpServletRequest.getQueryString:()Ljava/lang/String;
      27: astore        4
      29: aload         4
      31: ifnull        67
      34: aload         4
      36: invokevirtual #65                 // Method java/lang/String.length:()I
      39: ifle          67
      42: new           #98                 // class java/lang/StringBuilder
      45: dup
      46: invokespecial #99                 // Method java/lang/StringBuilder."<init>":()V
      49: aload_3
      50: invokevirtual #100                // Method java/lang/StringBuilder.append:(Ljava/lang/String;)Ljava/lang/StringBuilder;
      53: ldc           #101                // String ?
      55: invokevirtual #100                // Method java/lang/StringBuilder.append:(Ljava/lang/String;)Ljava/lang/StringBuilder;
      58: aload         4
      60: invokevirtual #100                // Method java/lang/StringBuilder.append:(Ljava/lang/String;)Ljava/lang/StringBuilder;
      63: invokevirtual #102                // Method java/lang/StringBuilder.toString:()Ljava/lang/String;
      66: astore_3
      67: aload_1
      68: invokeinterface #103,  1          // InterfaceMethod java/util/List.iterator:()Ljava/util/Iterator;
      73: astore        4
      75: aload         4
      77: invokeinterface #36,  1           // InterfaceMethod java/util/Iterator.hasNext:()Z
      82: ifeq          114
      85: aload         4
      87: invokeinterface #37,  1           // InterfaceMethod java/util/Iterator.next:()Ljava/lang/Object;
      92: checkcast     #104                // class java/util/regex/Pattern
      95: astore        5
      97: aload         5
      99: aload_3
     100: invokevirtual #105                // Method java/util/regex/Pattern.matcher:(Ljava/lang/CharSequence;)Ljava/util/regex/Matcher;
     103: invokevirtual #106                // Method java/util/regex/Matcher.matches:()Z
     106: ifeq          111
     109: iconst_1
     110: ireturn
     111: goto          75
     114: iconst_0
     115: ireturn

  protected abstract org.apache.cxf.Bus getBus();

  protected void serveStaticContent(javax.servlet.http.HttpServletRequest, javax.servlet.http.HttpServletResponse, java.lang.String) throws javax.servlet.ServletException;
    Code:
       0: aload_0
       1: aload_3
       2: invokevirtual #29                 // Method getResourceAsStream:(Ljava/lang/String;)Ljava/io/InputStream;
       5: astore        4
       7: aload         4
       9: ifnonnull     44
      12: new           #76                 // class javax/servlet/ServletException
      15: dup
      16: new           #98                 // class java/lang/StringBuilder
      19: dup
      20: invokespecial #99                 // Method java/lang/StringBuilder."<init>":()V
      23: ldc           #107                // String Static resource
      25: invokevirtual #100                // Method java/lang/StringBuilder.append:(Ljava/lang/String;)Ljava/lang/StringBuilder;
      28: aload_3
      29: invokevirtual #100                // Method java/lang/StringBuilder.append:(Ljava/lang/String;)Ljava/lang/StringBuilder;
      32: ldc           #108                // String  is not available
      34: invokevirtual #100                // Method java/lang/StringBuilder.append:(Ljava/lang/String;)Ljava/lang/StringBuilder;
      37: invokevirtual #102                // Method java/lang/StringBuilder.toString:()Ljava/lang/String;
      40: invokespecial #78                 // Method javax/servlet/ServletException."<init>":(Ljava/lang/String;)V
      43: athrow
      44: aload_3
      45: ldc           #109                // String .
      47: invokevirtual #110                // Method java/lang/String.lastIndexOf:(Ljava/lang/String;)I
      50: istore        5
      52: iload         5
      54: iconst_m1
      55: if_icmpeq     94
      58: iload         5
      60: aload_3
      61: invokevirtual #65                 // Method java/lang/String.length:()I
      64: if_icmpge     94
      67: aload_0
      68: aload_3
      69: iload         5
      71: iconst_1
      72: iadd
      73: invokevirtual #111                // Method java/lang/String.substring:(I)Ljava/lang/String;
      76: invokevirtual #112                // Method getStaticResourceContentType:(Ljava/lang/String;)Ljava/lang/String;
      79: astore        6
      81: aload         6
      83: ifnull        94
      86: aload_2
      87: aload         6
      89: invokeinterface #113,  2          // InterfaceMethod javax/servlet/http/HttpServletResponse.setContentType:(Ljava/lang/String;)V
      94: aload_0
      95: invokevirtual #114                // Method getServletConfig:()Ljavax/servlet/ServletConfig;
      98: ldc           #115                // String static-cache-control
     100: invokeinterface #8,  2            // InterfaceMethod javax/servlet/ServletConfig.getInitParameter:(Ljava/lang/String;)Ljava/lang/String;
     105: astore        6
     107: aload         6
     109: ifnull        125
     112: aload_2
     113: ldc           #116                // String Cache-Control
     115: aload         6
     117: invokevirtual #64                 // Method java/lang/String.trim:()Ljava/lang/String;
     120: invokeinterface #117,  3          // InterfaceMethod javax/servlet/http/HttpServletResponse.setHeader:(Ljava/lang/String;Ljava/lang/String;)V
     125: aload_2
     126: invokeinterface #118,  1          // InterfaceMethod javax/servlet/http/HttpServletResponse.getOutputStream:()Ljavax/servlet/ServletOutputStream;
     131: astore        7
     133: aload         4
     135: aload         7
     137: invokestatic  #119                // Method org/apache/cxf/helpers/IOUtils.copy:(Ljava/io/InputStream;Ljava/io/OutputStream;)I
     140: pop
     141: aload         7
     143: invokevirtual #120                // Method javax/servlet/ServletOutputStream.flush:()V
     146: goto          183
     149: astore        5
     151: new           #76                 // class javax/servlet/ServletException
     154: dup
     155: new           #98                 // class java/lang/StringBuilder
     158: dup
     159: invokespecial #99                 // Method java/lang/StringBuilder."<init>":()V
     162: ldc           #107                // String Static resource
     164: invokevirtual #100                // Method java/lang/StringBuilder.append:(Ljava/lang/String;)Ljava/lang/StringBuilder;
     167: aload_3
     168: invokevirtual #100                // Method java/lang/StringBuilder.append:(Ljava/lang/String;)Ljava/lang/StringBuilder;
     171: ldc           #121                // String  can not be written to the output stream
     173: invokevirtual #100                // Method java/lang/StringBuilder.append:(Ljava/lang/String;)Ljava/lang/StringBuilder;
     176: invokevirtual #102                // Method java/lang/StringBuilder.toString:()Ljava/lang/String;
     179: invokespecial #78                 // Method javax/servlet/ServletException."<init>":(Ljava/lang/String;)V
     182: athrow
     183: return
    Exception table:
       from    to  target type
          44   146   149   Class java/io/IOException

  protected java.lang.String getStaticResourceContentType(java.lang.String);
    Code:
       0: aload_0
       1: getfield      #5                  // Field staticContentTypes:Ljava/util/Map;
       4: aload_1
       5: invokeinterface #122,  2          // InterfaceMethod java/util/Map.get:(Ljava/lang/Object;)Ljava/lang/Object;
      10: checkcast     #38                 // class java/lang/String
      13: areturn

  protected void redirect(javax.servlet.http.HttpServletRequest, javax.servlet.http.HttpServletResponse, java.lang.String) throws javax.servlet.ServletException;
    Code:
       0: aload_0
       1: getfield      #22                 // Field dispatcherServletPath:Ljava/lang/String;
       4: ifnull        11
       7: iconst_1
       8: goto          12
      11: iconst_0
      12: istore        4
      14: iload         4
      16: ifeq          26
      19: aload_0
      20: getfield      #22                 // Field dispatcherServletPath:Ljava/lang/String;
      23: goto          28
      26: ldc           #87                 // String /
      28: astore        5
      30: aload_0
      31: invokespecial #123                // Method javax/servlet/http/HttpServlet.getServletContext:()Ljavax/servlet/ServletContext;
      34: astore        6
      36: aload_0
      37: getfield      #20                 // Field dispatcherServletName:Ljava/lang/String;
      40: ifnull        57
      43: aload         6
      45: aload_0
      46: getfield      #20                 // Field dispatcherServletName:Ljava/lang/String;
      49: invokeinterface #124,  2          // InterfaceMethod javax/servlet/ServletContext.getNamedDispatcher:(Ljava/lang/String;)Ljavax/servlet/RequestDispatcher;
      54: goto          90
      57: aload         6
      59: new           #98                 // class java/lang/StringBuilder
      62: dup
      63: invokespecial #99                 // Method java/lang/StringBuilder."<init>":()V
      66: aload         5
      68: invokevirtual #100                // Method java/lang/StringBuilder.append:(Ljava/lang/String;)Ljava/lang/StringBuilder;
      71: aload_3
      72: invokevirtual #100                // Method java/lang/StringBuilder.append:(Ljava/lang/String;)Ljava/lang/StringBuilder;
      75: invokevirtual #102                // Method java/lang/StringBuilder.toString:()Ljava/lang/String;
      78: ldc           #125                // String //
      80: ldc           #87                 // String /
      82: invokevirtual #126                // Method java/lang/String.replace:(Ljava/lang/CharSequence;Ljava/lang/CharSequence;)Ljava/lang/String;
      85: invokeinterface #127,  2          // InterfaceMethod javax/servlet/ServletContext.getRequestDispatcher:(Ljava/lang/String;)Ljavax/servlet/RequestDispatcher;
      90: astore        7
      92: aload         7
      94: ifnonnull     164
      97: new           #98                 // class java/lang/StringBuilder
     100: dup
     101: invokespecial #99                 // Method java/lang/StringBuilder."<init>":()V
     104: ldc           #128                // String No RequestDispatcher can be created for path
     106: invokevirtual #100                // Method java/lang/StringBuilder.append:(Ljava/lang/String;)Ljava/lang/StringBuilder;
     109: aload_3
     110: invokevirtual #100                // Method java/lang/StringBuilder.append:(Ljava/lang/String;)Ljava/lang/StringBuilder;
     113: invokevirtual #102                // Method java/lang/StringBuilder.toString:()Ljava/lang/String;
     116: astore        8
     118: aload_0
     119: getfield      #20                 // Field dispatcherServletName:Ljava/lang/String;
     122: ifnull        154
     125: new           #98                 // class java/lang/StringBuilder
     128: dup
     129: invokespecial #99                 // Method java/lang/StringBuilder."<init>":()V
     132: aload         8
     134: invokevirtual #100                // Method java/lang/StringBuilder.append:(Ljava/lang/String;)Ljava/lang/StringBuilder;
     137: ldc           #129                // String , dispatcher name:
     139: invokevirtual #100                // Method java/lang/StringBuilder.append:(Ljava/lang/String;)Ljava/lang/StringBuilder;
     142: aload_0
     143: getfield      #20                 // Field dispatcherServletName:Ljava/lang/String;
     146: invokevirtual #100                // Method java/lang/StringBuilder.append:(Ljava/lang/String;)Ljava/lang/StringBuilder;
     149: invokevirtual #102                // Method java/lang/StringBuilder.toString:()Ljava/lang/String;
     152: astore        8
     154: new           #76                 // class javax/servlet/ServletException
     157: dup
     158: aload         8
     160: invokespecial #78                 // Method javax/servlet/ServletException."<init>":(Ljava/lang/String;)V
     163: athrow
     164: aload_0
     165: getfield      #25                 // Field redirectAttributes:Ljava/util/Map;
     168: invokeinterface #130,  1          // InterfaceMethod java/util/Map.entrySet:()Ljava/util/Set;
     173: invokeinterface #35,  1           // InterfaceMethod java/util/Set.iterator:()Ljava/util/Iterator;
     178: astore        8
     180: aload         8
     182: invokeinterface #36,  1           // InterfaceMethod java/util/Iterator.hasNext:()Z
     187: ifeq          228
     190: aload         8
     192: invokeinterface #37,  1           // InterfaceMethod java/util/Iterator.next:()Ljava/lang/Object;
     197: checkcast     #131                // class java/util/Map$Entry
     200: astore        9
     202: aload_1
     203: aload         9
     205: invokeinterface #132,  1          // InterfaceMethod java/util/Map$Entry.getKey:()Ljava/lang/Object;
     210: checkcast     #38                 // class java/lang/String
     213: aload         9
     215: invokeinterface #133,  1          // InterfaceMethod java/util/Map$Entry.getValue:()Ljava/lang/Object;
     220: invokeinterface #134,  3          // InterfaceMethod javax/servlet/http/HttpServletRequest.setAttribute:(Ljava/lang/String;Ljava/lang/Object;)V
     225: goto          180
     228: new           #135                // class org/apache/cxf/transport/servlet/AbstractHTTPServlet$HttpServletRequestRedirectFilter
     231: dup
     232: aload_1
     233: aload_3
     234: aload         5
     236: iload         4
     238: invokespecial #136                // Method org/apache/cxf/transport/servlet/AbstractHTTPServlet$HttpServletRequestRedirectFilter."<init>":(Ljavax/servlet/http/HttpServletRequest;Ljava/lang/String;Ljava/lang/String;Z)V
     241: astore        8
     243: aload_0
     244: invokevirtual #114                // Method getServletConfig:()Ljavax/servlet/ServletConfig;
     247: ldc           #137                // String redirect-with-include
     249: invokeinterface #8,  2            // InterfaceMethod javax/servlet/ServletConfig.getInitParameter:(Ljava/lang/String;)Ljava/lang/String;
     254: invokestatic  #138                // Method org/apache/cxf/common/util/PropertyUtils.isTrue:(Ljava/lang/Object;)Z
     257: ifeq          273
     260: aload         7
     262: aload         8
     264: aload_2
     265: invokeinterface #139,  3          // InterfaceMethod javax/servlet/RequestDispatcher.include:(Ljavax/servlet/ServletRequest;Ljavax/servlet/ServletResponse;)V
     270: goto          283
     273: aload         7
     275: aload         8
     277: aload_2
     278: invokeinterface #140,  3          // InterfaceMethod javax/servlet/RequestDispatcher.forward:(Ljavax/servlet/ServletRequest;Ljavax/servlet/ServletResponse;)V
     283: goto          322
     286: astore        8
     288: new           #76                 // class javax/servlet/ServletException
     291: dup
     292: new           #98                 // class java/lang/StringBuilder
     295: dup
     296: invokespecial #99                 // Method java/lang/StringBuilder."<init>":()V
     299: ldc           #142                // String RequestDispatcher for path
     301: invokevirtual #100                // Method java/lang/StringBuilder.append:(Ljava/lang/String;)Ljava/lang/StringBuilder;
     304: aload_3
     305: invokevirtual #100                // Method java/lang/StringBuilder.append:(Ljava/lang/String;)Ljava/lang/StringBuilder;
     308: ldc           #143                // String  has failed
     310: invokevirtual #100                // Method java/lang/StringBuilder.append:(Ljava/lang/String;)Ljava/lang/StringBuilder;
     313: invokevirtual #102                // Method java/lang/StringBuilder.toString:()Ljava/lang/String;
     316: aload         8
     318: invokespecial #144                // Method javax/servlet/ServletException."<init>":(Ljava/lang/String;Ljava/lang/Throwable;)V
     321: athrow
     322: return
    Exception table:
       from    to  target type
         164   283   286   Class java/lang/Throwable

  protected abstract void invoke(javax.servlet.http.HttpServletRequest, javax.servlet.http.HttpServletResponse) throws javax.servlet.ServletException;

  static {};
    Code:
       0: ldc_w         #50                 // class org/apache/cxf/transport/servlet/AbstractHTTPServlet
       3: invokestatic  #145                // Method org/apache/cxf/common/logging/LogUtils.getL7dLogger:(Ljava/lang/Class;)Ljava/util/logging/Logger;
       6: putstatic     #48                 // Field LOG:Ljava/util/logging/Logger;
       9: ldc_w         #50                 // class org/apache/cxf/transport/servlet/AbstractHTTPServlet
      12: invokestatic  #146                // Method org/apache/cxf/common/i18n/BundleUtils.getBundle:(Ljava/lang/Class;)Ljava/util/ResourceBundle;
      15: putstatic     #44                 // Field BUNDLE:Ljava/util/ResourceBundle;
      18: bipush        7
      20: anewarray     #38                 // class java/lang/String
      23: dup
      24: iconst_0
      25: ldc           #147                // String POST
      27: aastore
      28: dup
      29: iconst_1
      30: ldc           #148                // String GET
      32: aastore
      33: dup
      34: iconst_2
      35: ldc           #149                // String PUT
      37: aastore
      38: dup
      39: iconst_3
      40: ldc           #150                // String DELETE
      42: aastore
      43: dup
      44: iconst_4
      45: ldc           #151                // String HEAD
      47: aastore
      48: dup
      49: iconst_5
      50: ldc           #152                // String OPTIONS
      52: aastore
      53: dup
      54: bipush        6
      56: ldc           #153                // String TRACE
      58: aastore
      59: invokestatic  #154                // Method java/util/Arrays.asList:([Ljava/lang/Object;)Ljava/util/List;
      62: putstatic     #80                 // Field KNOWN_HTTP_VERBS:Ljava/util/List;
      65: new           #2                  // class java/util/HashMap
      68: dup
      69: invokespecial #68                 // Method java/util/HashMap."<init>":()V
      72: putstatic     #3                  // Field DEFAULT_STATIC_CONTENT_TYPES:Ljava/util/Map;
      75: getstatic     #3                  // Field DEFAULT_STATIC_CONTENT_TYPES:Ljava/util/Map;
      78: ldc           #155                // String html
      80: ldc           #156                // String text/html
      82: invokeinterface #40,  3           // InterfaceMethod java/util/Map.put:(Ljava/lang/Object;Ljava/lang/Object;)Ljava/lang/Object;
      87: pop
      88: getstatic     #3                  // Field DEFAULT_STATIC_CONTENT_TYPES:Ljava/util/Map;
      91: ldc           #157                // String txt
      93: ldc           #158                // String text/plain
      95: invokeinterface #40,  3           // InterfaceMethod java/util/Map.put:(Ljava/lang/Object;Ljava/lang/Object;)Ljava/lang/Object;
     100: pop
     101: getstatic     #3                  // Field DEFAULT_STATIC_CONTENT_TYPES:Ljava/util/Map;
     104: ldc           #159                // String css
     106: ldc           #160                // String text/css
     108: invokeinterface #40,  3           // InterfaceMethod java/util/Map.put:(Ljava/lang/Object;Ljava/lang/Object;)Ljava/lang/Object;
     113: pop
     114: getstatic     #3                  // Field DEFAULT_STATIC_CONTENT_TYPES:Ljava/util/Map;
     117: ldc           #161                // String pdf
     119: ldc           #162                // String application/pdf
     121: invokeinterface #40,  3           // InterfaceMethod java/util/Map.put:(Ljava/lang/Object;Ljava/lang/Object;)Ljava/lang/Object;
     126: pop
     127: getstatic     #3                  // Field DEFAULT_STATIC_CONTENT_TYPES:Ljava/util/Map;
     130: ldc           #163                // String xsd
     132: ldc           #164                // String application/xml
     134: invokeinterface #40,  3           // InterfaceMethod java/util/Map.put:(Ljava/lang/Object;Ljava/lang/Object;)Ljava/lang/Object;
     139: pop
     140: getstatic     #3                  // Field DEFAULT_STATIC_CONTENT_TYPES:Ljava/util/Map;
     143: ldc           #165                // String js
     145: ldc           #166                // String application/javascript
     147: invokeinterface #40,  3           // InterfaceMethod java/util/Map.put:(Ljava/lang/Object;Ljava/lang/Object;)Ljava/lang/Object;
     152: pop
     153: return
}
