Compiled from "GraphNode.java"
class org.apache.jena.reasoner.transitiveReasoner.GraphNode$3 implements org.apache.jena.reasoner.transitiveReasoner.TransitiveGraphCache$Visitor<java.util.Set<org.apache.jena.reasoner.transitiveReasoner.GraphNode>, org.apache.jena.reasoner.transitiveReasoner.GraphNode> {
  final org.apache.jena.reasoner.transitiveReasoner.GraphNode this$0;

  org.apache.jena.reasoner.transitiveReasoner.GraphNode$3(org.apache.jena.reasoner.transitiveReasoner.GraphNode);
    Code:
       0: aload_0
       1: aload_1
       2: putfield      #1                  // Field this$0:Lorg/apache/jena/reasoner/transitiveReasoner/GraphNode;
       5: aload_0
       6: invokespecial #2                  // Method java/lang/Object."<init>":()V
       9: return

  public java.util.List<org.apache.jena.reasoner.transitiveReasoner.GraphNode> visit(org.apache.jena.reasoner.transitiveReasoner.GraphNode, org.apache.jena.reasoner.transitiveReasoner.GraphNode, java.util.Set<org.apache.jena.reasoner.transitiveReasoner.GraphNode>, org.apache.jena.reasoner.transitiveReasoner.GraphNode);
    Code:
       0: aload_3
       1: aload_1
       2: invokeinterface #3,  2            // InterfaceMethod java/util/Set.add:(Ljava/lang/Object;)Z
       7: ifeq          90
      10: aload         4
      12: invokestatic  #4                  // Method org/apache/jena/reasoner/transitiveReasoner/GraphNode.access$100:(Lorg/apache/jena/reasoner/transitiveReasoner/GraphNode;)Ljava/util/Set;
      15: astore        5
      17: aload_1
      18: getfield      #5                  // Field org/apache/jena/reasoner/transitiveReasoner/GraphNode.succ:Ljava/util/Set;
      21: invokeinterface #6,  1            // InterfaceMethod java/util/Set.size:()I
      26: istore        6
      28: aload_1
      29: getfield      #5                  // Field org/apache/jena/reasoner/transitiveReasoner/GraphNode.succ:Ljava/util/Set;
      32: aload         5
      34: invokeinterface #7,  2            // InterfaceMethod java/util/Set.removeAll:(Ljava/util/Collection;)Z
      39: pop
      40: aload_1
      41: getfield      #8                  // Field org/apache/jena/reasoner/transitiveReasoner/GraphNode.succClosed:Ljava/util/Set;
      44: aload         5
      46: invokeinterface #7,  2            // InterfaceMethod java/util/Set.removeAll:(Ljava/util/Collection;)Z
      51: pop
      52: aload_1
      53: getfield      #8                  // Field org/apache/jena/reasoner/transitiveReasoner/GraphNode.succClosed:Ljava/util/Set;
      56: aload         4
      58: invokeinterface #3,  2            // InterfaceMethod java/util/Set.add:(Ljava/lang/Object;)Z
      63: pop
      64: aload_1
      65: getfield      #5                  // Field org/apache/jena/reasoner/transitiveReasoner/GraphNode.succ:Ljava/util/Set;
      68: invokeinterface #6,  1            // InterfaceMethod java/util/Set.size:()I
      73: iload         6
      75: if_icmpeq     90
      78: aload_1
      79: getfield      #5                  // Field org/apache/jena/reasoner/transitiveReasoner/GraphNode.succ:Ljava/util/Set;
      82: aload         4
      84: invokeinterface #3,  2            // InterfaceMethod java/util/Set.add:(Ljava/lang/Object;)Z
      89: pop
      90: aconst_null
      91: areturn

  public java.util.List visit(org.apache.jena.reasoner.transitiveReasoner.GraphNode, org.apache.jena.reasoner.transitiveReasoner.GraphNode, java.lang.Object, java.lang.Object);
    Code:
       0: aload_0
       1: aload_1
       2: aload_2
       3: aload_3
       4: checkcast     #9                  // class java/util/Set
       7: aload         4
       9: checkcast     #10                 // class org/apache/jena/reasoner/transitiveReasoner/GraphNode
      12: invokevirtual #11                 // Method visit:(Lorg/apache/jena/reasoner/transitiveReasoner/GraphNode;Lorg/apache/jena/reasoner/transitiveReasoner/GraphNode;Ljava/util/Set;Lorg/apache/jena/reasoner/transitiveReasoner/GraphNode;)Ljava/util/List;
      15: areturn
}
