Compiled from "GraphNode.java"
class org.apache.jena.reasoner.transitiveReasoner.GraphNode$2 implements org.apache.jena.reasoner.transitiveReasoner.TransitiveGraphCache$Visitor<java.util.Set<org.apache.jena.reasoner.transitiveReasoner.GraphNode>, java.lang.Object> {
  final org.apache.jena.reasoner.transitiveReasoner.GraphNode this$0;

  org.apache.jena.reasoner.transitiveReasoner.GraphNode$2(org.apache.jena.reasoner.transitiveReasoner.GraphNode);
    Code:
       0: aload_0
       1: aload_1
       2: putfield      #1                  // Field this$0:Lorg/apache/jena/reasoner/transitiveReasoner/GraphNode;
       5: aload_0
       6: invokespecial #2                  // Method java/lang/Object."<init>":()V
       9: return

  public java.util.List<org.apache.jena.reasoner.transitiveReasoner.GraphNode> visit(org.apache.jena.reasoner.transitiveReasoner.GraphNode, org.apache.jena.reasoner.transitiveReasoner.GraphNode, java.util.Set<org.apache.jena.reasoner.transitiveReasoner.GraphNode>, java.lang.Object);
    Code:
       0: aload_1
       1: getfield      #3                  // Field org/apache/jena/reasoner/transitiveReasoner/GraphNode.succClosed:Ljava/util/Set;
       4: aload_3
       5: invokeinterface #4,  2            // InterfaceMethod java/util/Set.addAll:(Ljava/util/Collection;)Z
      10: pop
      11: aconst_null
      12: astore        5
      14: aload_1
      15: getfield      #5                  // Field org/apache/jena/reasoner/transitiveReasoner/GraphNode.succ:Ljava/util/Set;
      18: invokeinterface #6,  1            // InterfaceMethod java/util/Set.iterator:()Ljava/util/Iterator;
      23: astore        6
      25: aload         6
      27: invokeinterface #7,  1            // InterfaceMethod java/util/Iterator.hasNext:()Z
      32: ifeq          112
      35: aload         6
      37: invokeinterface #8,  1            // InterfaceMethod java/util/Iterator.next:()Ljava/lang/Object;
      42: checkcast     #9                  // class org/apache/jena/reasoner/transitiveReasoner/GraphNode
      45: astore        7
      47: aload_3
      48: aload         7
      50: invokeinterface #10,  2           // InterfaceMethod java/util/Set.contains:(Ljava/lang/Object;)Z
      55: ifeq          109
      58: aload         6
      60: invokeinterface #11,  1           // InterfaceMethod java/util/Iterator.remove:()V
      65: aload         7
      67: aload_2
      68: if_acmpne     97
      71: aload         5
      73: ifnonnull     85
      76: new           #12                 // class java/util/ArrayList
      79: dup
      80: invokespecial #13                 // Method java/util/ArrayList."<init>":()V
      83: astore        5
      85: aload         5
      87: aload_1
      88: invokeinterface #14,  2           // InterfaceMethod java/util/List.add:(Ljava/lang/Object;)Z
      93: pop
      94: goto          109
      97: aload         7
      99: getfield      #15                 // Field org/apache/jena/reasoner/transitiveReasoner/GraphNode.pred:Ljava/util/Set;
     102: aload_1
     103: invokeinterface #16,  2           // InterfaceMethod java/util/Set.remove:(Ljava/lang/Object;)Z
     108: pop
     109: goto          25
     112: aload         5
     114: areturn

  public java.util.List visit(org.apache.jena.reasoner.transitiveReasoner.GraphNode, org.apache.jena.reasoner.transitiveReasoner.GraphNode, java.lang.Object, java.lang.Object);
    Code:
       0: aload_0
       1: aload_1
       2: aload_2
       3: aload_3
       4: checkcast     #17                 // class java/util/Set
       7: aload         4
       9: invokevirtual #18                 // Method visit:(Lorg/apache/jena/reasoner/transitiveReasoner/GraphNode;Lorg/apache/jena/reasoner/transitiveReasoner/GraphNode;Ljava/util/Set;Ljava/lang/Object;)Ljava/util/List;
      12: areturn
}
