Compiled from "AutoValue_IndexRangesResponse.java"
final class org.graylog2.rest.models.system.indexer.responses.AutoValue_IndexRangesResponse extends org.graylog2.rest.models.system.indexer.responses.$AutoValue_IndexRangesResponse {
  org.graylog2.rest.models.system.indexer.responses.AutoValue_IndexRangesResponse(int, java.util.List<org.graylog2.rest.models.system.indexer.responses.IndexRangeSummary>);
    Code:
       0: aload_0
       1: iload_1
       2: aload_2
       3: invokespecial #1                  // Method org/graylog2/rest/models/system/indexer/responses/$AutoValue_IndexRangesResponse."<init>":(ILjava/util/List;)V
       6: return

  public final int getTotal();
    Code:
       0: aload_0
       1: invokevirtual #2                  // Method total:()I
       4: ireturn

  public final java.util.List<org.graylog2.rest.models.system.indexer.responses.IndexRangeSummary> getRanges();
    Code:
       0: aload_0
       1: invokevirtual #3                  // Method ranges:()Ljava/util/List;
       4: areturn
}
