Compiled from "AutoValue_IndexRangeSummary.java"
final class org.graylog2.rest.models.system.indexer.responses.AutoValue_IndexRangeSummary extends org.graylog2.rest.models.system.indexer.responses.$AutoValue_IndexRangeSummary {
  org.graylog2.rest.models.system.indexer.responses.AutoValue_IndexRangeSummary(java.lang.String, org.joda.time.DateTime, org.joda.time.DateTime, org.joda.time.DateTime, int);
    Code:
       0: aload_0
       1: aload_1
       2: aload_2
       3: aload_3
       4: aload         4
       6: iload         5
       8: invokespecial #1                  // Method org/graylog2/rest/models/system/indexer/responses/$AutoValue_IndexRangeSummary."<init>":(Ljava/lang/String;Lorg/joda/time/DateTime;Lorg/joda/time/DateTime;Lorg/joda/time/DateTime;I)V
      11: return

  public final java.lang.String getIndexName();
    Code:
       0: aload_0
       1: invokevirtual #2                  // Method indexName:()Ljava/lang/String;
       4: areturn

  public final org.joda.time.DateTime getBegin();
    Code:
       0: aload_0
       1: invokevirtual #3                  // Method begin:()Lorg/joda/time/DateTime;
       4: areturn

  public final org.joda.time.DateTime getEnd();
    Code:
       0: aload_0
       1: invokevirtual #4                  // Method end:()Lorg/joda/time/DateTime;
       4: areturn

  public final org.joda.time.DateTime getCalculatedAt();
    Code:
       0: aload_0
       1: invokevirtual #5                  // Method calculatedAt:()Lorg/joda/time/DateTime;
       4: areturn

  public final int getCalculationTookMs();
    Code:
       0: aload_0
       1: invokevirtual #6                  // Method calculationTookMs:()I
       4: ireturn
}
