Compiled from "ClosedIndices.java"
public abstract class org.graylog2.rest.models.system.indexer.responses.ClosedIndices {
  public org.graylog2.rest.models.system.indexer.responses.ClosedIndices();
    Code:
       0: aload_0
       1: invokespecial #1                  // Method java/lang/Object."<init>":()V
       4: return

  public abstract java.util.Set<java.lang.String> indices();

  public abstract int total();

  public static org.graylog2.rest.models.system.indexer.responses.ClosedIndices create(java.util.Set<java.lang.String>, int);
    Code:
       0: new           #2                  // class org/graylog2/rest/models/system/indexer/responses/AutoValue_ClosedIndices
       3: dup
       4: aload_0
       5: iload_1
       6: invokespecial #3                  // Method org/graylog2/rest/models/system/indexer/responses/AutoValue_ClosedIndices."<init>":(Ljava/util/Set;I)V
       9: areturn
}
