Compiled from "IndexSizeSummary.java"
public abstract class org.graylog2.rest.models.system.indexer.responses.IndexSizeSummary {
  public org.graylog2.rest.models.system.indexer.responses.IndexSizeSummary();
    Code:
       0: aload_0
       1: invokespecial #1                  // Method java/lang/Object."<init>":()V
       4: return

  public abstract long events();

  public abstract long deleted();

  public abstract long bytes();

  public static org.graylog2.rest.models.system.indexer.responses.IndexSizeSummary create(long, long, long);
    Code:
       0: new           #2                  // class org/graylog2/rest/models/system/indexer/responses/AutoValue_IndexSizeSummary
       3: dup
       4: lload_0
       5: lload_2
       6: lload         4
       8: invokespecial #3                  // Method org/graylog2/rest/models/system/indexer/responses/AutoValue_IndexSizeSummary."<init>":(JJJ)V
      11: areturn
}
