Compiled from "AutoCompleteRenderer.java"
public class de.larmic.butterfaces.component.renderkit.html_basic.text.part.AutoCompleteRenderer extends de.larmic.butterfaces.component.base.renderer.HtmlBasicRenderer {
  public de.larmic.butterfaces.component.renderkit.html_basic.text.part.AutoCompleteRenderer();
    Code:
       0: aload_0
       1: invokespecial #1                  // Method de/larmic/butterfaces/component/base/renderer/HtmlBasicRenderer."<init>":()V
       4: return

  public void encodeBegin(javax.faces.context.FacesContext, javax.faces.component.UIComponent) throws java.io.IOException;
    Code:
       0: aload_2
       1: invokevirtual #2                  // Method javax/faces/component/UIComponent.isRendered:()Z
       4: ifne          8
       7: return
       8: aload_1
       9: invokevirtual #3                  // Method javax/faces/context/FacesContext.getResponseWriter:()Ljavax/faces/context/ResponseWriter;
      12: astore_3
      13: aload_2
      14: checkcast     #4                  // class de/larmic/butterfaces/component/html/text/part/HtmlAutoComplete
      17: astore        4
      19: aload_3
      20: ldc           #6                  // String div
      22: aload         4
      24: invokevirtual #7                  // Method javax/faces/context/ResponseWriter.startElement:(Ljava/lang/String;Ljavax/faces/component/UIComponent;)V
      27: aload_0
      28: aload_1
      29: aload_3
      30: aload         4
      32: invokevirtual #8                  // Method writeIdAttribute:(Ljavax/faces/context/FacesContext;Ljavax/faces/context/ResponseWriter;Ljavax/faces/component/UIComponent;)Ljava/lang/String;
      35: pop
      36: aload_3
      37: ldc           #9                  // String class
      39: ldc           #10                 // String butter-component-autocomplete butter-dropdownlist-container
      41: aconst_null
      42: invokevirtual #11                 // Method javax/faces/context/ResponseWriter.writeAttribute:(Ljava/lang/String;Ljava/lang/Object;Ljava/lang/String;)V
      45: aload         4
      47: invokevirtual #12                 // Method de/larmic/butterfaces/component/html/text/part/HtmlAutoComplete.getCachedAutoCompleteValues:()Ljava/util/List;
      50: invokeinterface #13,  1           // InterfaceMethod java/util/List.isEmpty:()Z
      55: ifne          159
      58: aload_3
      59: ldc           #14                 // String ul
      61: aload         4
      63: invokevirtual #7                  // Method javax/faces/context/ResponseWriter.startElement:(Ljava/lang/String;Ljavax/faces/component/UIComponent;)V
      66: aload_3
      67: ldc           #9                  // String class
      69: ldc           #15                 // String butter-dropdownlist-resultList
      71: aconst_null
      72: invokevirtual #11                 // Method javax/faces/context/ResponseWriter.writeAttribute:(Ljava/lang/String;Ljava/lang/Object;Ljava/lang/String;)V
      75: aload         4
      77: invokevirtual #12                 // Method de/larmic/butterfaces/component/html/text/part/HtmlAutoComplete.getCachedAutoCompleteValues:()Ljava/util/List;
      80: invokeinterface #16,  1           // InterfaceMethod java/util/List.iterator:()Ljava/util/Iterator;
      85: astore        5
      87: aload         5
      89: invokeinterface #17,  1           // InterfaceMethod java/util/Iterator.hasNext:()Z
      94: ifeq          153
      97: aload         5
      99: invokeinterface #18,  1           // InterfaceMethod java/util/Iterator.next:()Ljava/lang/Object;
     104: checkcast     #19                 // class java/lang/String
     107: astore        6
     109: aload_3
     110: ldc           #20                 // String li
     112: aload         4
     114: invokevirtual #7                  // Method javax/faces/context/ResponseWriter.startElement:(Ljava/lang/String;Ljavax/faces/component/UIComponent;)V
     117: aload_3
     118: ldc           #9                  // String class
     120: ldc           #21                 // String butter-dropdownlist-resultItem
     122: aconst_null
     123: invokevirtual #11                 // Method javax/faces/context/ResponseWriter.writeAttribute:(Ljava/lang/String;Ljava/lang/Object;Ljava/lang/String;)V
     126: aload_3
     127: ldc           #22                 // String data-select-value
     129: aload         6
     131: aconst_null
     132: invokevirtual #11                 // Method javax/faces/context/ResponseWriter.writeAttribute:(Ljava/lang/String;Ljava/lang/Object;Ljava/lang/String;)V
     135: aload_3
     136: aload         6
     138: aload         4
     140: aconst_null
     141: invokevirtual #23                 // Method javax/faces/context/ResponseWriter.writeText:(Ljava/lang/Object;Ljavax/faces/component/UIComponent;Ljava/lang/String;)V
     144: aload_3
     145: ldc           #20                 // String li
     147: invokevirtual #24                 // Method javax/faces/context/ResponseWriter.endElement:(Ljava/lang/String;)V
     150: goto          87
     153: aload_3
     154: ldc           #14                 // String ul
     156: invokevirtual #24                 // Method javax/faces/context/ResponseWriter.endElement:(Ljava/lang/String;)V
     159: return

  public void encodeEnd(javax.faces.context.FacesContext, javax.faces.component.UIComponent) throws java.io.IOException;
    Code:
       0: aload_2
       1: invokevirtual #2                  // Method javax/faces/component/UIComponent.isRendered:()Z
       4: ifne          8
       7: return
       8: aload_1
       9: invokevirtual #3                  // Method javax/faces/context/FacesContext.getResponseWriter:()Ljavax/faces/context/ResponseWriter;
      12: astore_3
      13: aload_3
      14: ldc           #6                  // String div
      16: invokevirtual #24                 // Method javax/faces/context/ResponseWriter.endElement:(Ljava/lang/String;)V
      19: return
}
