Compiled from "XATransactionContext.java"
public class net.sf.ehcache.transaction.xa.XATransactionContext {
  private static final org.slf4j.Logger LOG;

  private final java.util.concurrent.ConcurrentMap<java.lang.Object, net.sf.ehcache.Element> commandElements;

  private final java.util.Set<java.lang.Object> removedKeys;

  private final java.util.Set<java.lang.Object> addedKeys;

  private int sizeModifier;

  private final java.util.Map<java.lang.Object, net.sf.ehcache.transaction.xa.commands.Command> commands;

  private final net.sf.ehcache.store.Store underlyingStore;

  public net.sf.ehcache.transaction.xa.XATransactionContext(net.sf.ehcache.store.Store);
    Code:
       0: aload_0
       1: invokespecial #1                  // Method java/lang/Object."<init>":()V
       4: aload_0
       5: new           #2                  // class java/util/concurrent/ConcurrentHashMap
       8: dup
       9: invokespecial #3                  // Method java/util/concurrent/ConcurrentHashMap."<init>":()V
      12: putfield      #4                  // Field commandElements:Ljava/util/concurrent/ConcurrentMap;
      15: aload_0
      16: new           #5                  // class java/util/HashSet
      19: dup
      20: invokespecial #6                  // Method java/util/HashSet."<init>":()V
      23: putfield      #7                  // Field removedKeys:Ljava/util/Set;
      26: aload_0
      27: new           #5                  // class java/util/HashSet
      30: dup
      31: invokespecial #6                  // Method java/util/HashSet."<init>":()V
      34: putfield      #8                  // Field addedKeys:Ljava/util/Set;
      37: aload_0
      38: new           #9                  // class java/util/LinkedHashMap
      41: dup
      42: invokespecial #10                 // Method java/util/LinkedHashMap."<init>":()V
      45: putfield      #11                 // Field commands:Ljava/util/Map;
      48: aload_0
      49: aload_1
      50: putfield      #12                 // Field underlyingStore:Lnet/sf/ehcache/store/Store;
      53: return

  public void addCommand(net.sf.ehcache.transaction.xa.commands.Command, net.sf.ehcache.Element);
    Code:
       0: aload_1
       1: invokeinterface #13,  1           // InterfaceMethod net/sf/ehcache/transaction/xa/commands/Command.getObjectKey:()Ljava/lang/Object;
       6: astore_3
       7: aload_2
       8: ifnull        26
      11: aload_0
      12: getfield      #4                  // Field commandElements:Ljava/util/concurrent/ConcurrentMap;
      15: aload_3
      16: aload_2
      17: invokeinterface #14,  3           // InterfaceMethod java/util/concurrent/ConcurrentMap.put:(Ljava/lang/Object;Ljava/lang/Object;)Ljava/lang/Object;
      22: pop
      23: goto          37
      26: aload_0
      27: getfield      #4                  // Field commandElements:Ljava/util/concurrent/ConcurrentMap;
      30: aload_3
      31: invokeinterface #15,  2           // InterfaceMethod java/util/concurrent/ConcurrentMap.remove:(Ljava/lang/Object;)Ljava/lang/Object;
      36: pop
      37: aload_1
      38: aload_3
      39: invokeinterface #16,  2           // InterfaceMethod net/sf/ehcache/transaction/xa/commands/Command.isPut:(Ljava/lang/Object;)Z
      44: ifeq          107
      47: aload_0
      48: getfield      #7                  // Field removedKeys:Ljava/util/Set;
      51: aload_3
      52: invokeinterface #17,  2           // InterfaceMethod java/util/Set.remove:(Ljava/lang/Object;)Z
      57: istore        4
      59: aload_0
      60: getfield      #8                  // Field addedKeys:Ljava/util/Set;
      63: aload_3
      64: invokeinterface #18,  2           // InterfaceMethod java/util/Set.add:(Ljava/lang/Object;)Z
      69: istore        5
      71: iload         4
      73: ifne          94
      76: iload         5
      78: ifeq          104
      81: aload_0
      82: getfield      #12                 // Field underlyingStore:Lnet/sf/ehcache/store/Store;
      85: aload_3
      86: invokeinterface #19,  2           // InterfaceMethod net/sf/ehcache/store/Store.containsKey:(Ljava/lang/Object;)Z
      91: ifne          104
      94: aload_0
      95: dup
      96: getfield      #20                 // Field sizeModifier:I
      99: iconst_1
     100: iadd
     101: putfield      #20                 // Field sizeModifier:I
     104: goto          164
     107: aload_1
     108: aload_3
     109: invokeinterface #21,  2           // InterfaceMethod net/sf/ehcache/transaction/xa/commands/Command.isRemove:(Ljava/lang/Object;)Z
     114: ifeq          164
     117: aload_0
     118: getfield      #7                  // Field removedKeys:Ljava/util/Set;
     121: aload_3
     122: invokeinterface #18,  2           // InterfaceMethod java/util/Set.add:(Ljava/lang/Object;)Z
     127: pop
     128: aload_0
     129: getfield      #8                  // Field addedKeys:Ljava/util/Set;
     132: aload_3
     133: invokeinterface #17,  2           // InterfaceMethod java/util/Set.remove:(Ljava/lang/Object;)Z
     138: ifne          154
     141: aload_0
     142: getfield      #12                 // Field underlyingStore:Lnet/sf/ehcache/store/Store;
     145: aload_3
     146: invokeinterface #19,  2           // InterfaceMethod net/sf/ehcache/store/Store.containsKey:(Ljava/lang/Object;)Z
     151: ifeq          164
     154: aload_0
     155: dup
     156: getfield      #20                 // Field sizeModifier:I
     159: iconst_1
     160: isub
     161: putfield      #20                 // Field sizeModifier:I
     164: aload_0
     165: getfield      #11                 // Field commands:Ljava/util/Map;
     168: aload_3
     169: aload_1
     170: invokeinterface #22,  3           // InterfaceMethod java/util/Map.put:(Ljava/lang/Object;Ljava/lang/Object;)Ljava/lang/Object;
     175: pop
     176: getstatic     #23                 // Field LOG:Lorg/slf4j/Logger;
     179: ldc           #24                 // String XA context added new command [{}], it now contains {} command(s)
     181: aload_1
     182: aload_0
     183: getfield      #11                 // Field commands:Ljava/util/Map;
     186: invokeinterface #25,  1           // InterfaceMethod java/util/Map.size:()I
     191: invokestatic  #26                 // Method java/lang/Integer.valueOf:(I)Ljava/lang/Integer;
     194: invokeinterface #27,  4           // InterfaceMethod org/slf4j/Logger.debug:(Ljava/lang/String;Ljava/lang/Object;Ljava/lang/Object;)V
     199: return

  public java.util.List<net.sf.ehcache.transaction.xa.commands.Command> getCommands();
    Code:
       0: new           #28                 // class java/util/ArrayList
       3: dup
       4: aload_0
       5: getfield      #11                 // Field commands:Ljava/util/Map;
       8: invokeinterface #29,  1           // InterfaceMethod java/util/Map.values:()Ljava/util/Collection;
      13: invokespecial #30                 // Method java/util/ArrayList."<init>":(Ljava/util/Collection;)V
      16: areturn

  public net.sf.ehcache.Element get(java.lang.Object);
    Code:
       0: aload_0
       1: getfield      #7                  // Field removedKeys:Ljava/util/Set;
       4: aload_1
       5: invokeinterface #31,  2           // InterfaceMethod java/util/Set.contains:(Ljava/lang/Object;)Z
      10: ifeq          17
      13: aconst_null
      14: goto          30
      17: aload_0
      18: getfield      #4                  // Field commandElements:Ljava/util/concurrent/ConcurrentMap;
      21: aload_1
      22: invokeinterface #32,  2           // InterfaceMethod java/util/concurrent/ConcurrentMap.get:(Ljava/lang/Object;)Ljava/lang/Object;
      27: checkcast     #33                 // class net/sf/ehcache/Element
      30: areturn

  public boolean isRemoved(java.lang.Object);
    Code:
       0: aload_0
       1: getfield      #7                  // Field removedKeys:Ljava/util/Set;
       4: aload_1
       5: invokeinterface #31,  2           // InterfaceMethod java/util/Set.contains:(Ljava/lang/Object;)Z
      10: ireturn

  public java.util.Collection getAddedKeys();
    Code:
       0: aload_0
       1: getfield      #8                  // Field addedKeys:Ljava/util/Set;
       4: invokestatic  #34                 // Method java/util/Collections.unmodifiableSet:(Ljava/util/Set;)Ljava/util/Set;
       7: areturn

  public java.util.Collection getRemovedKeys();
    Code:
       0: aload_0
       1: getfield      #7                  // Field removedKeys:Ljava/util/Set;
       4: invokestatic  #34                 // Method java/util/Collections.unmodifiableSet:(Ljava/util/Set;)Ljava/util/Set;
       7: areturn

  public int getSizeModifier();
    Code:
       0: aload_0
       1: getfield      #20                 // Field sizeModifier:I
       4: ireturn

  public java.lang.String toString();
    Code:
       0: new           #35                 // class java/lang/StringBuilder
       3: dup
       4: invokespecial #36                 // Method java/lang/StringBuilder."<init>":()V
       7: ldc           #37                 // String XATransactionContext with
       9: invokevirtual #38                 // Method java/lang/StringBuilder.append:(Ljava/lang/String;)Ljava/lang/StringBuilder;
      12: aload_0
      13: getfield      #11                 // Field commands:Ljava/util/Map;
      16: invokeinterface #25,  1           // InterfaceMethod java/util/Map.size:()I
      21: invokevirtual #39                 // Method java/lang/StringBuilder.append:(I)Ljava/lang/StringBuilder;
      24: ldc           #40                 // String  command(s)
      26: invokevirtual #38                 // Method java/lang/StringBuilder.append:(Ljava/lang/String;)Ljava/lang/StringBuilder;
      29: invokevirtual #41                 // Method java/lang/StringBuilder.toString:()Ljava/lang/String;
      32: areturn

  static {};
    Code:
       0: ldc_w         #42                 // class net/sf/ehcache/transaction/xa/XATransactionContext
       3: invokevirtual #43                 // Method java/lang/Class.getName:()Ljava/lang/String;
       6: invokestatic  #44                 // Method org/slf4j/LoggerFactory.getLogger:(Ljava/lang/String;)Lorg/slf4j/Logger;
       9: putstatic     #23                 // Field LOG:Lorg/slf4j/Logger;
      12: return
}
