Compiled from "Slf4jCurrentTraceContext.java"
public final class org.springframework.cloud.sleuth.log.Slf4jCurrentTraceContext extends brave.propagation.CurrentTraceContext {
  private static final java.lang.String LEGACY_EXPORTABLE_NAME;

  private static final java.lang.String LEGACY_PARENT_ID_NAME;

  private static final java.lang.String LEGACY_TRACE_ID_NAME;

  private static final java.lang.String LEGACY_SPAN_ID_NAME;

  private static final org.slf4j.Logger log;

  final brave.propagation.CurrentTraceContext delegate;

  public static org.springframework.cloud.sleuth.log.Slf4jCurrentTraceContext create();
    Code:
       0: invokestatic  #2                  // Method brave/propagation/CurrentTraceContext$Default.inheritable:()Lbrave/propagation/CurrentTraceContext;
       3: invokestatic  #3                  // Method create:(Lbrave/propagation/CurrentTraceContext;)Lorg/springframework/cloud/sleuth/log/Slf4jCurrentTraceContext;
       6: areturn

  public static org.springframework.cloud.sleuth.log.Slf4jCurrentTraceContext create(brave.propagation.CurrentTraceContext);
    Code:
       0: new           #4                  // class org/springframework/cloud/sleuth/log/Slf4jCurrentTraceContext
       3: dup
       4: aload_0
       5: invokespecial #5                  // Method "<init>":(Lbrave/propagation/CurrentTraceContext;)V
       8: areturn

  org.springframework.cloud.sleuth.log.Slf4jCurrentTraceContext(brave.propagation.CurrentTraceContext);
    Code:
       0: aload_0
       1: invokespecial #6                  // Method brave/propagation/CurrentTraceContext."<init>":()V
       4: aload_1
       5: ifnonnull     18
       8: new           #7                  // class java/lang/NullPointerException
      11: dup
      12: ldc           #8                  // String delegate == null
      14: invokespecial #9                  // Method java/lang/NullPointerException."<init>":(Ljava/lang/String;)V
      17: athrow
      18: aload_0
      19: aload_1
      20: putfield      #10                 // Field delegate:Lbrave/propagation/CurrentTraceContext;
      23: return

  public brave.propagation.TraceContext get();
    Code:
       0: aload_0
       1: getfield      #10                 // Field delegate:Lbrave/propagation/CurrentTraceContext;
       4: invokevirtual #11                 // Method brave/propagation/CurrentTraceContext.get:()Lbrave/propagation/TraceContext;
       7: areturn

  public brave.propagation.CurrentTraceContext$Scope newScope(brave.propagation.TraceContext);
    Code:
       0: ldc           #12                 // String traceId
       2: invokestatic  #13                 // Method org/slf4j/MDC.get:(Ljava/lang/String;)Ljava/lang/String;
       5: astore_2
       6: ldc           #14                 // String parentId
       8: invokestatic  #13                 // Method org/slf4j/MDC.get:(Ljava/lang/String;)Ljava/lang/String;
      11: astore_3
      12: ldc           #15                 // String spanId
      14: invokestatic  #13                 // Method org/slf4j/MDC.get:(Ljava/lang/String;)Ljava/lang/String;
      17: astore        4
      19: ldc           #16                 // String spanExportable
      21: invokestatic  #13                 // Method org/slf4j/MDC.get:(Ljava/lang/String;)Ljava/lang/String;
      24: astore        5
      26: ldc           #17                 // String X-B3-TraceId
      28: invokestatic  #13                 // Method org/slf4j/MDC.get:(Ljava/lang/String;)Ljava/lang/String;
      31: astore        6
      33: ldc           #18                 // String X-B3-ParentSpanId
      35: invokestatic  #13                 // Method org/slf4j/MDC.get:(Ljava/lang/String;)Ljava/lang/String;
      38: astore        7
      40: ldc           #19                 // String X-B3-SpanId
      42: invokestatic  #13                 // Method org/slf4j/MDC.get:(Ljava/lang/String;)Ljava/lang/String;
      45: astore        8
      47: ldc           #20                 // String X-Span-Export
      49: invokestatic  #13                 // Method org/slf4j/MDC.get:(Ljava/lang/String;)Ljava/lang/String;
      52: astore        9
      54: aload_1
      55: ifnull        203
      58: aload_1
      59: invokevirtual #21                 // Method brave/propagation/TraceContext.traceIdString:()Ljava/lang/String;
      62: astore        10
      64: ldc           #12                 // String traceId
      66: aload         10
      68: invokestatic  #22                 // Method org/slf4j/MDC.put:(Ljava/lang/String;Ljava/lang/String;)V
      71: ldc           #17                 // String X-B3-TraceId
      73: aload         10
      75: invokestatic  #22                 // Method org/slf4j/MDC.put:(Ljava/lang/String;Ljava/lang/String;)V
      78: aload_1
      79: invokevirtual #23                 // Method brave/propagation/TraceContext.parentId:()Ljava/lang/Long;
      82: ifnull        98
      85: aload_1
      86: invokevirtual #23                 // Method brave/propagation/TraceContext.parentId:()Ljava/lang/Long;
      89: invokevirtual #24                 // Method java/lang/Long.longValue:()J
      92: invokestatic  #25                 // Method brave/internal/HexCodec.toLowerHex:(J)Ljava/lang/String;
      95: goto          99
      98: aconst_null
      99: astore        11
     101: ldc           #14                 // String parentId
     103: aload         11
     105: invokestatic  #26                 // Method replace:(Ljava/lang/String;Ljava/lang/String;)V
     108: ldc           #18                 // String X-B3-ParentSpanId
     110: aload         11
     112: invokestatic  #26                 // Method replace:(Ljava/lang/String;Ljava/lang/String;)V
     115: aload_1
     116: invokevirtual #27                 // Method brave/propagation/TraceContext.spanId:()J
     119: invokestatic  #25                 // Method brave/internal/HexCodec.toLowerHex:(J)Ljava/lang/String;
     122: astore        12
     124: ldc           #15                 // String spanId
     126: aload         12
     128: invokestatic  #22                 // Method org/slf4j/MDC.put:(Ljava/lang/String;Ljava/lang/String;)V
     131: ldc           #19                 // String X-B3-SpanId
     133: aload         12
     135: invokestatic  #22                 // Method org/slf4j/MDC.put:(Ljava/lang/String;Ljava/lang/String;)V
     138: aload_1
     139: invokevirtual #28                 // Method brave/propagation/TraceContext.sampled:()Ljava/lang/Boolean;
     142: invokestatic  #29                 // Method java/lang/String.valueOf:(Ljava/lang/Object;)Ljava/lang/String;
     145: astore        13
     147: ldc           #16                 // String spanExportable
     149: aload         13
     151: invokestatic  #22                 // Method org/slf4j/MDC.put:(Ljava/lang/String;Ljava/lang/String;)V
     154: ldc           #20                 // String X-Span-Export
     156: aload         13
     158: invokestatic  #22                 // Method org/slf4j/MDC.put:(Ljava/lang/String;Ljava/lang/String;)V
     161: aload_0
     162: ldc           #30                 // String Starting scope for span: {}
     164: aload_1
     165: invokespecial #1                  // Method log:(Ljava/lang/String;Lbrave/propagation/TraceContext;)V
     168: aload_1
     169: invokevirtual #23                 // Method brave/propagation/TraceContext.parentId:()Ljava/lang/Long;
     172: ifnull        200
     175: getstatic     #31                 // Field log:Lorg/slf4j/Logger;
     178: invokeinterface #32,  1           // InterfaceMethod org/slf4j/Logger.isTraceEnabled:()Z
     183: ifeq          200
     186: getstatic     #31                 // Field log:Lorg/slf4j/Logger;
     189: ldc           #33                 // String With parent: {}
     191: aload_1
     192: invokevirtual #23                 // Method brave/propagation/TraceContext.parentId:()Ljava/lang/Long;
     195: invokeinterface #34,  3           // InterfaceMethod org/slf4j/Logger.trace:(Ljava/lang/String;Ljava/lang/Object;)V
     200: goto          243
     203: ldc           #12                 // String traceId
     205: invokestatic  #35                 // Method org/slf4j/MDC.remove:(Ljava/lang/String;)V
     208: ldc           #14                 // String parentId
     210: invokestatic  #35                 // Method org/slf4j/MDC.remove:(Ljava/lang/String;)V
     213: ldc           #15                 // String spanId
     215: invokestatic  #35                 // Method org/slf4j/MDC.remove:(Ljava/lang/String;)V
     218: ldc           #16                 // String spanExportable
     220: invokestatic  #35                 // Method org/slf4j/MDC.remove:(Ljava/lang/String;)V
     223: ldc           #17                 // String X-B3-TraceId
     225: invokestatic  #35                 // Method org/slf4j/MDC.remove:(Ljava/lang/String;)V
     228: ldc           #18                 // String X-B3-ParentSpanId
     230: invokestatic  #35                 // Method org/slf4j/MDC.remove:(Ljava/lang/String;)V
     233: ldc           #19                 // String X-B3-SpanId
     235: invokestatic  #35                 // Method org/slf4j/MDC.remove:(Ljava/lang/String;)V
     238: ldc           #20                 // String X-Span-Export
     240: invokestatic  #35                 // Method org/slf4j/MDC.remove:(Ljava/lang/String;)V
     243: aload_0
     244: getfield      #10                 // Field delegate:Lbrave/propagation/CurrentTraceContext;
     247: aload_1
     248: invokevirtual #36                 // Method brave/propagation/CurrentTraceContext.newScope:(Lbrave/propagation/TraceContext;)Lbrave/propagation/CurrentTraceContext$Scope;
     251: astore        10
     253: new           #37                 // class org/springframework/cloud/sleuth/log/Slf4jCurrentTraceContext$1ThreadContextCurrentTraceContextScope
     256: dup
     257: aload_0
     258: aload_1
     259: aload         10
     261: aload_2
     262: aload_3
     263: aload         4
     265: aload         5
     267: aload         6
     269: aload         7
     271: aload         8
     273: aload         9
     275: invokespecial #38                 // Method org/springframework/cloud/sleuth/log/Slf4jCurrentTraceContext$1ThreadContextCurrentTraceContextScope."<init>":(Lorg/springframework/cloud/sleuth/log/Slf4jCurrentTraceContext;Lbrave/propagation/TraceContext;Lbrave/propagation/CurrentTraceContext$Scope;Ljava/lang/String;Ljava/lang/String;Ljava/lang/String;Ljava/lang/String;Ljava/lang/String;Ljava/lang/String;Ljava/lang/String;Ljava/lang/String;)V
     278: areturn

  private void log(java.lang.String, brave.propagation.TraceContext);
    Code:
       0: aload_2
       1: ifnonnull     5
       4: return
       5: getstatic     #31                 // Field log:Lorg/slf4j/Logger;
       8: invokeinterface #32,  1           // InterfaceMethod org/slf4j/Logger.isTraceEnabled:()Z
      13: ifeq          26
      16: getstatic     #31                 // Field log:Lorg/slf4j/Logger;
      19: aload_1
      20: aload_2
      21: invokeinterface #34,  3           // InterfaceMethod org/slf4j/Logger.trace:(Ljava/lang/String;Ljava/lang/Object;)V
      26: return

  static void replace(java.lang.String, java.lang.String);
    Code:
       0: aload_1
       1: ifnull        12
       4: aload_0
       5: aload_1
       6: invokestatic  #22                 // Method org/slf4j/MDC.put:(Ljava/lang/String;Ljava/lang/String;)V
       9: goto          16
      12: aload_0
      13: invokestatic  #35                 // Method org/slf4j/MDC.remove:(Ljava/lang/String;)V
      16: return

  static void access$000(org.springframework.cloud.sleuth.log.Slf4jCurrentTraceContext, java.lang.String, brave.propagation.TraceContext);
    Code:
       0: aload_0
       1: aload_1
       2: aload_2
       3: invokespecial #1                  // Method log:(Ljava/lang/String;Lbrave/propagation/TraceContext;)V
       6: return

  static {};
    Code:
       0: ldc           #4                  // class org/springframework/cloud/sleuth/log/Slf4jCurrentTraceContext
       2: invokestatic  #39                 // Method org/slf4j/LoggerFactory.getLogger:(Ljava/lang/Class;)Lorg/slf4j/Logger;
       5: putstatic     #31                 // Field log:Lorg/slf4j/Logger;
       8: return
}
