Compiled from "Cut.java"
abstract class com.google.common.collect.Cut<C extends java.lang.Comparable> implements java.lang.Comparable<com.google.common.collect.Cut<C>>, java.io.Serializable {
  final C endpoint;

  private static final long serialVersionUID;

  com.google.common.collect.Cut(C);
    Code:
       0: aload_0
       1: invokespecial #1                  // Method java/lang/Object."<init>":()V
       4: aload_0
       5: aload_1
       6: putfield      #2                  // Field endpoint:Ljava/lang/Comparable;
       9: return

  abstract boolean isLessThan(C);

  abstract com.google.common.collect.BoundType typeAsLowerBound();

  abstract com.google.common.collect.BoundType typeAsUpperBound();

  abstract com.google.common.collect.Cut<C> withLowerBoundType(com.google.common.collect.BoundType, com.google.common.collect.DiscreteDomain<C>);

  abstract com.google.common.collect.Cut<C> withUpperBoundType(com.google.common.collect.BoundType, com.google.common.collect.DiscreteDomain<C>);

  abstract void describeAsLowerBound(java.lang.StringBuilder);

  abstract void describeAsUpperBound(java.lang.StringBuilder);

  abstract C leastValueAbove(com.google.common.collect.DiscreteDomain<C>);

  abstract C greatestValueBelow(com.google.common.collect.DiscreteDomain<C>);

  com.google.common.collect.Cut<C> canonical(com.google.common.collect.DiscreteDomain<C>);
    Code:
       0: aload_0
       1: areturn

  public int compareTo(com.google.common.collect.Cut<C>);
    Code:
       0: aload_1
       1: invokestatic  #3                  // Method belowAll:()Lcom/google/common/collect/Cut;
       4: if_acmpne     9
       7: iconst_1
       8: ireturn
       9: aload_1
      10: invokestatic  #4                  // Method aboveAll:()Lcom/google/common/collect/Cut;
      13: if_acmpne     18
      16: iconst_m1
      17: ireturn
      18: aload_0
      19: getfield      #2                  // Field endpoint:Ljava/lang/Comparable;
      22: aload_1
      23: getfield      #2                  // Field endpoint:Ljava/lang/Comparable;
      26: invokestatic  #5                  // Method com/google/common/collect/Range.compareOrThrow:(Ljava/lang/Comparable;Ljava/lang/Comparable;)I
      29: istore_2
      30: iload_2
      31: ifeq          36
      34: iload_2
      35: ireturn
      36: aload_0
      37: instanceof    #6                  // class com/google/common/collect/Cut$AboveValue
      40: aload_1
      41: instanceof    #6                  // class com/google/common/collect/Cut$AboveValue
      44: invokestatic  #7                  // Method com/google/common/primitives/Booleans.compare:(ZZ)I
      47: ireturn

  C endpoint();
    Code:
       0: aload_0
       1: getfield      #2                  // Field endpoint:Ljava/lang/Comparable;
       4: areturn

  public boolean equals(java.lang.Object);
    Code:
       0: aload_1
       1: instanceof    #8                  // class com/google/common/collect/Cut
       4: ifeq          29
       7: aload_1
       8: checkcast     #8                  // class com/google/common/collect/Cut
      11: astore_2
      12: aload_0
      13: aload_2
      14: invokevirtual #9                  // Method compareTo:(Lcom/google/common/collect/Cut;)I
      17: istore_3
      18: iload_3
      19: ifne          26
      22: iconst_1
      23: goto          27
      26: iconst_0
      27: ireturn
      28: astore_3
      29: iconst_0
      30: ireturn
    Exception table:
       from    to  target type
          12    27    28   Class java/lang/ClassCastException

  public abstract int hashCode();

  static <C extends java.lang.Comparable> com.google.common.collect.Cut<C> belowAll();
    Code:
       0: invokestatic  #11                 // Method com/google/common/collect/Cut$BelowAll.access$000:()Lcom/google/common/collect/Cut$BelowAll;
       3: areturn

  static <C extends java.lang.Comparable> com.google.common.collect.Cut<C> aboveAll();
    Code:
       0: invokestatic  #12                 // Method com/google/common/collect/Cut$AboveAll.access$100:()Lcom/google/common/collect/Cut$AboveAll;
       3: areturn

  static <C extends java.lang.Comparable> com.google.common.collect.Cut<C> belowValue(C);
    Code:
       0: new           #13                 // class com/google/common/collect/Cut$BelowValue
       3: dup
       4: aload_0
       5: invokespecial #14                 // Method com/google/common/collect/Cut$BelowValue."<init>":(Ljava/lang/Comparable;)V
       8: areturn

  static <C extends java.lang.Comparable> com.google.common.collect.Cut<C> aboveValue(C);
    Code:
       0: new           #6                  // class com/google/common/collect/Cut$AboveValue
       3: dup
       4: aload_0
       5: invokespecial #15                 // Method com/google/common/collect/Cut$AboveValue."<init>":(Ljava/lang/Comparable;)V
       8: areturn

  public int compareTo(java.lang.Object);
    Code:
       0: aload_0
       1: aload_1
       2: checkcast     #8                  // class com/google/common/collect/Cut
       5: invokevirtual #9                  // Method compareTo:(Lcom/google/common/collect/Cut;)I
       8: ireturn
}
