Compiled from "ImmutableList.java"
class com.google.common.collect.ImmutableList$ReverseImmutableList<E> extends com.google.common.collect.ImmutableList<E> {
  private final transient com.google.common.collect.ImmutableList<E> forwardList;

  com.google.common.collect.ImmutableList$ReverseImmutableList(com.google.common.collect.ImmutableList<E>);
    Code:
       0: aload_0
       1: invokespecial #1                  // Method com/google/common/collect/ImmutableList."<init>":()V
       4: aload_0
       5: aload_1
       6: putfield      #2                  // Field forwardList:Lcom/google/common/collect/ImmutableList;
       9: return

  private int reverseIndex(int);
    Code:
       0: aload_0
       1: invokevirtual #3                  // Method size:()I
       4: iconst_1
       5: isub
       6: iload_1
       7: isub
       8: ireturn

  private int reversePosition(int);
    Code:
       0: aload_0
       1: invokevirtual #3                  // Method size:()I
       4: iload_1
       5: isub
       6: ireturn

  public com.google.common.collect.ImmutableList<E> reverse();
    Code:
       0: aload_0
       1: getfield      #2                  // Field forwardList:Lcom/google/common/collect/ImmutableList;
       4: areturn

  public boolean contains(java.lang.Object);
    Code:
       0: aload_0
       1: getfield      #2                  // Field forwardList:Lcom/google/common/collect/ImmutableList;
       4: aload_1
       5: invokevirtual #4                  // Method com/google/common/collect/ImmutableList.contains:(Ljava/lang/Object;)Z
       8: ireturn

  public int indexOf(java.lang.Object);
    Code:
       0: aload_0
       1: getfield      #2                  // Field forwardList:Lcom/google/common/collect/ImmutableList;
       4: aload_1
       5: invokevirtual #5                  // Method com/google/common/collect/ImmutableList.lastIndexOf:(Ljava/lang/Object;)I
       8: istore_2
       9: iload_2
      10: iflt          21
      13: aload_0
      14: iload_2
      15: invokespecial #6                  // Method reverseIndex:(I)I
      18: goto          22
      21: iconst_m1
      22: ireturn

  public int lastIndexOf(java.lang.Object);
    Code:
       0: aload_0
       1: getfield      #2                  // Field forwardList:Lcom/google/common/collect/ImmutableList;
       4: aload_1
       5: invokevirtual #7                  // Method com/google/common/collect/ImmutableList.indexOf:(Ljava/lang/Object;)I
       8: istore_2
       9: iload_2
      10: iflt          21
      13: aload_0
      14: iload_2
      15: invokespecial #6                  // Method reverseIndex:(I)I
      18: goto          22
      21: iconst_m1
      22: ireturn

  public com.google.common.collect.ImmutableList<E> subList(int, int);
    Code:
       0: iload_1
       1: iload_2
       2: aload_0
       3: invokevirtual #3                  // Method size:()I
       6: invokestatic  #8                  // Method com/google/common/base/Preconditions.checkPositionIndexes:(III)V
       9: aload_0
      10: getfield      #2                  // Field forwardList:Lcom/google/common/collect/ImmutableList;
      13: aload_0
      14: iload_2
      15: invokespecial #9                  // Method reversePosition:(I)I
      18: aload_0
      19: iload_1
      20: invokespecial #9                  // Method reversePosition:(I)I
      23: invokevirtual #10                 // Method com/google/common/collect/ImmutableList.subList:(II)Lcom/google/common/collect/ImmutableList;
      26: invokevirtual #11                 // Method com/google/common/collect/ImmutableList.reverse:()Lcom/google/common/collect/ImmutableList;
      29: areturn

  public E get(int);
    Code:
       0: iload_1
       1: aload_0
       2: invokevirtual #3                  // Method size:()I
       5: invokestatic  #12                 // Method com/google/common/base/Preconditions.checkElementIndex:(II)I
       8: pop
       9: aload_0
      10: getfield      #2                  // Field forwardList:Lcom/google/common/collect/ImmutableList;
      13: aload_0
      14: iload_1
      15: invokespecial #6                  // Method reverseIndex:(I)I
      18: invokevirtual #13                 // Method com/google/common/collect/ImmutableList.get:(I)Ljava/lang/Object;
      21: areturn

  public int size();
    Code:
       0: aload_0
       1: getfield      #2                  // Field forwardList:Lcom/google/common/collect/ImmutableList;
       4: invokevirtual #14                 // Method com/google/common/collect/ImmutableList.size:()I
       7: ireturn

  boolean isPartialView();
    Code:
       0: aload_0
       1: getfield      #2                  // Field forwardList:Lcom/google/common/collect/ImmutableList;
       4: invokevirtual #15                 // Method com/google/common/collect/ImmutableList.isPartialView:()Z
       7: ireturn

  public java.util.List subList(int, int);
    Code:
       0: aload_0
       1: iload_1
       2: iload_2
       3: invokevirtual #16                 // Method subList:(II)Lcom/google/common/collect/ImmutableList;
       6: areturn

  public java.util.ListIterator listIterator(int);
    Code:
       0: aload_0
       1: iload_1
       2: invokespecial #17                 // Method com/google/common/collect/ImmutableList.listIterator:(I)Lcom/google/common/collect/UnmodifiableListIterator;
       5: areturn

  public java.util.ListIterator listIterator();
    Code:
       0: aload_0
       1: invokespecial #18                 // Method com/google/common/collect/ImmutableList.listIterator:()Lcom/google/common/collect/UnmodifiableListIterator;
       4: areturn

  public java.util.Iterator iterator();
    Code:
       0: aload_0
       1: invokespecial #19                 // Method com/google/common/collect/ImmutableList.iterator:()Lcom/google/common/collect/UnmodifiableIterator;
       4: areturn
}
