Compiled from "Iterables.java"
class com.google.common.collect.Iterables$7 extends com.google.common.collect.FluentIterable<T> {
  final java.lang.Iterable val$iterable;

  final int val$limitSize;

  com.google.common.collect.Iterables$7(java.lang.Iterable, int);
    Code:
       0: aload_0
       1: aload_1
       2: putfield      #1                  // Field val$iterable:Ljava/lang/Iterable;
       5: aload_0
       6: iload_2
       7: putfield      #2                  // Field val$limitSize:I
      10: aload_0
      11: invokespecial #3                  // Method com/google/common/collect/FluentIterable."<init>":()V
      14: return

  public java.util.Iterator<T> iterator();
    Code:
       0: aload_0
       1: getfield      #1                  // Field val$iterable:Ljava/lang/Iterable;
       4: invokeinterface #4,  1            // InterfaceMethod java/lang/Iterable.iterator:()Ljava/util/Iterator;
       9: aload_0
      10: getfield      #2                  // Field val$limitSize:I
      13: invokestatic  #5                  // Method com/google/common/collect/Iterators.limit:(Ljava/util/Iterator;I)Ljava/util/Iterator;
      16: areturn

  public java.util.Spliterator<T> spliterator();
    Code:
       0: aload_0
       1: getfield      #1                  // Field val$iterable:Ljava/lang/Iterable;
       4: invokestatic  #6                  // Method com/google/common/collect/Streams.stream:(Ljava/lang/Iterable;)Ljava/util/stream/Stream;
       7: aload_0
       8: getfield      #2                  // Field val$limitSize:I
      11: i2l
      12: invokeinterface #7,  3            // InterfaceMethod java/util/stream/Stream.limit:(J)Ljava/util/stream/Stream;
      17: invokeinterface #8,  1            // InterfaceMethod java/util/stream/Stream.spliterator:()Ljava/util/Spliterator;
      22: areturn
}
