Compiled from "Synchronized.java"
class com.google.common.collect.Synchronized$SynchronizedBiMap<K, V> extends com.google.common.collect.Synchronized$SynchronizedMap<K, V> implements com.google.common.collect.BiMap<K, V>, java.io.Serializable {
  private transient java.util.Set<V> valueSet;

  private transient com.google.common.collect.BiMap<V, K> inverse;

  private static final long serialVersionUID;

  private com.google.common.collect.Synchronized$SynchronizedBiMap(com.google.common.collect.BiMap<K, V>, java.lang.Object, com.google.common.collect.BiMap<V, K>);
    Code:
       0: aload_0
       1: aload_1
       2: aload_2
       3: invokespecial #2                  // Method com/google/common/collect/Synchronized$SynchronizedMap."<init>":(Ljava/util/Map;Ljava/lang/Object;)V
       6: aload_0
       7: aload_3
       8: putfield      #3                  // Field inverse:Lcom/google/common/collect/BiMap;
      11: return

  com.google.common.collect.BiMap<K, V> delegate();
    Code:
       0: aload_0
       1: invokespecial #4                  // Method com/google/common/collect/Synchronized$SynchronizedMap.delegate:()Ljava/util/Map;
       4: checkcast     #5                  // class com/google/common/collect/BiMap
       7: areturn

  public java.util.Set<V> values();
    Code:
       0: aload_0
       1: getfield      #6                  // Field mutex:Ljava/lang/Object;
       4: dup
       5: astore_1
       6: monitorenter
       7: aload_0
       8: getfield      #7                  // Field valueSet:Ljava/util/Set;
      11: ifnonnull     34
      14: aload_0
      15: aload_0
      16: invokevirtual #8                  // Method delegate:()Lcom/google/common/collect/BiMap;
      19: invokeinterface #9,  1            // InterfaceMethod com/google/common/collect/BiMap.values:()Ljava/util/Set;
      24: aload_0
      25: getfield      #6                  // Field mutex:Ljava/lang/Object;
      28: invokestatic  #10                 // Method com/google/common/collect/Synchronized.set:(Ljava/util/Set;Ljava/lang/Object;)Ljava/util/Set;
      31: putfield      #7                  // Field valueSet:Ljava/util/Set;
      34: aload_0
      35: getfield      #7                  // Field valueSet:Ljava/util/Set;
      38: aload_1
      39: monitorexit
      40: areturn
      41: astore_2
      42: aload_1
      43: monitorexit
      44: aload_2
      45: athrow
    Exception table:
       from    to  target type
           7    40    41   any
          41    44    41   any

  public V forcePut(K, V);
    Code:
       0: aload_0
       1: getfield      #6                  // Field mutex:Ljava/lang/Object;
       4: dup
       5: astore_3
       6: monitorenter
       7: aload_0
       8: invokevirtual #8                  // Method delegate:()Lcom/google/common/collect/BiMap;
      11: aload_1
      12: aload_2
      13: invokeinterface #11,  3           // InterfaceMethod com/google/common/collect/BiMap.forcePut:(Ljava/lang/Object;Ljava/lang/Object;)Ljava/lang/Object;
      18: aload_3
      19: monitorexit
      20: areturn
      21: astore        4
      23: aload_3
      24: monitorexit
      25: aload         4
      27: athrow
    Exception table:
       from    to  target type
           7    20    21   any
          21    25    21   any

  public com.google.common.collect.BiMap<V, K> inverse();
    Code:
       0: aload_0
       1: getfield      #6                  // Field mutex:Ljava/lang/Object;
       4: dup
       5: astore_1
       6: monitorenter
       7: aload_0
       8: getfield      #3                  // Field inverse:Lcom/google/common/collect/BiMap;
      11: ifnonnull     39
      14: aload_0
      15: new           #12                 // class com/google/common/collect/Synchronized$SynchronizedBiMap
      18: dup
      19: aload_0
      20: invokevirtual #8                  // Method delegate:()Lcom/google/common/collect/BiMap;
      23: invokeinterface #13,  1           // InterfaceMethod com/google/common/collect/BiMap.inverse:()Lcom/google/common/collect/BiMap;
      28: aload_0
      29: getfield      #6                  // Field mutex:Ljava/lang/Object;
      32: aload_0
      33: invokespecial #1                  // Method "<init>":(Lcom/google/common/collect/BiMap;Ljava/lang/Object;Lcom/google/common/collect/BiMap;)V
      36: putfield      #3                  // Field inverse:Lcom/google/common/collect/BiMap;
      39: aload_0
      40: getfield      #3                  // Field inverse:Lcom/google/common/collect/BiMap;
      43: aload_1
      44: monitorexit
      45: areturn
      46: astore_2
      47: aload_1
      48: monitorexit
      49: aload_2
      50: athrow
    Exception table:
       from    to  target type
           7    45    46   any
          46    49    46   any

  public java.util.Collection values();
    Code:
       0: aload_0
       1: invokevirtual #14                 // Method values:()Ljava/util/Set;
       4: areturn

  java.util.Map delegate();
    Code:
       0: aload_0
       1: invokevirtual #8                  // Method delegate:()Lcom/google/common/collect/BiMap;
       4: areturn

  java.lang.Object delegate();
    Code:
       0: aload_0
       1: invokevirtual #8                  // Method delegate:()Lcom/google/common/collect/BiMap;
       4: areturn

  com.google.common.collect.Synchronized$SynchronizedBiMap(com.google.common.collect.BiMap, java.lang.Object, com.google.common.collect.BiMap, com.google.common.collect.Synchronized$1);
    Code:
       0: aload_0
       1: aload_1
       2: aload_2
       3: aload_3
       4: invokespecial #1                  // Method "<init>":(Lcom/google/common/collect/BiMap;Ljava/lang/Object;Lcom/google/common/collect/BiMap;)V
       7: return
}
