Compiled from "TreeMultiset.java"
final class com.google.common.collect.TreeMultiset$Reference<T> {
  private T value;

  private com.google.common.collect.TreeMultiset$Reference();
    Code:
       0: aload_0
       1: invokespecial #2                  // Method java/lang/Object."<init>":()V
       4: return

  public T get();
    Code:
       0: aload_0
       1: getfield      #3                  // Field value:Ljava/lang/Object;
       4: areturn

  public void checkAndSet(T, T);
    Code:
       0: aload_0
       1: getfield      #3                  // Field value:Ljava/lang/Object;
       4: aload_1
       5: if_acmpeq     16
       8: new           #4                  // class java/util/ConcurrentModificationException
      11: dup
      12: invokespecial #5                  // Method java/util/ConcurrentModificationException."<init>":()V
      15: athrow
      16: aload_0
      17: aload_2
      18: putfield      #3                  // Field value:Ljava/lang/Object;
      21: return

  void clear();
    Code:
       0: aload_0
       1: aconst_null
       2: putfield      #3                  // Field value:Ljava/lang/Object;
       5: return

  com.google.common.collect.TreeMultiset$Reference(com.google.common.collect.TreeMultiset$1);
    Code:
       0: aload_0
       1: invokespecial #1                  // Method "<init>":()V
       4: return
}
