Compiled from "utils.kt"
public final class kotlin.reflect.jvm.internal.impl.load.java.DeprecationCausedByFunctionN {
  private final kotlin.reflect.jvm.internal.impl.descriptors.DeclarationDescriptor target;

  public kotlin.reflect.jvm.internal.impl.load.java.DeprecationCausedByFunctionN(kotlin.reflect.jvm.internal.impl.descriptors.DeclarationDescriptor);
    Code:
       0: aload_1
       1: ldc           #1                  // String target
       3: invokestatic  #7                  // Method kotlin/jvm/internal/Intrinsics.checkParameterIsNotNull:(Ljava/lang/Object;Ljava/lang/String;)V
       6: aload_0
       7: invokespecial #6                  // Method java/lang/Object."<init>":()V
      10: aload_0
      11: aload_1
      12: putfield      #5                  // Field target:Lkotlin/reflect/jvm/internal/impl/descriptors/DeclarationDescriptor;
      15: return
}
