Compiled from "JavaVisibilities.java"
public class kotlin.reflect.jvm.internal.impl.load.java.JavaVisibilities {
  public static final kotlin.reflect.jvm.internal.impl.descriptors.Visibility PACKAGE_VISIBILITY;

  public static final kotlin.reflect.jvm.internal.impl.descriptors.Visibility PROTECTED_STATIC_VISIBILITY;

  public static final kotlin.reflect.jvm.internal.impl.descriptors.Visibility PROTECTED_AND_PACKAGE;

  private static boolean isVisibleForProtectedAndPackage(kotlin.reflect.jvm.internal.impl.resolve.scopes.receivers.ReceiverValue, kotlin.reflect.jvm.internal.impl.descriptors.DeclarationDescriptorWithVisibility, kotlin.reflect.jvm.internal.impl.descriptors.DeclarationDescriptor);
    Code:
       0: aload_1
       1: invokestatic  #29                 // Method kotlin/reflect/jvm/internal/impl/resolve/DescriptorUtils.unwrapFakeOverrideToAnyDeclaration:(Lkotlin/reflect/jvm/internal/impl/descriptors/DeclarationDescriptorWithVisibility;)Lkotlin/reflect/jvm/internal/impl/descriptors/DeclarationDescriptorWithVisibility;
       4: aload_2
       5: invokestatic  #22                 // Method areInSamePackage:(Lkotlin/reflect/jvm/internal/impl/descriptors/DeclarationDescriptor;Lkotlin/reflect/jvm/internal/impl/descriptors/DeclarationDescriptor;)Z
       8: ifeq          13
      11: iconst_1
      12: ireturn
      13: getstatic     #17                 // Field kotlin/reflect/jvm/internal/impl/descriptors/Visibilities.PROTECTED:Lkotlin/reflect/jvm/internal/impl/descriptors/Visibility;
      16: aload_0
      17: aload_1
      18: aload_2
      19: invokevirtual #21                 // Method kotlin/reflect/jvm/internal/impl/descriptors/Visibility.isVisible:(Lkotlin/reflect/jvm/internal/impl/resolve/scopes/receivers/ReceiverValue;Lkotlin/reflect/jvm/internal/impl/descriptors/DeclarationDescriptorWithVisibility;Lkotlin/reflect/jvm/internal/impl/descriptors/DeclarationDescriptor;)Z
      22: ireturn

  private static boolean areInSamePackage(kotlin.reflect.jvm.internal.impl.descriptors.DeclarationDescriptor, kotlin.reflect.jvm.internal.impl.descriptors.DeclarationDescriptor);
    Code:
       0: aload_0
       1: ldc           #7                  // class kotlin/reflect/jvm/internal/impl/descriptors/PackageFragmentDescriptor
       3: iconst_0
       4: invokestatic  #28                 // Method kotlin/reflect/jvm/internal/impl/resolve/DescriptorUtils.getParentOfType:(Lkotlin/reflect/jvm/internal/impl/descriptors/DeclarationDescriptor;Ljava/lang/Class;Z)Lkotlin/reflect/jvm/internal/impl/descriptors/DeclarationDescriptor;
       7: checkcast     #7                  // class kotlin/reflect/jvm/internal/impl/descriptors/PackageFragmentDescriptor
      10: astore_2
      11: aload_1
      12: ldc           #7                  // class kotlin/reflect/jvm/internal/impl/descriptors/PackageFragmentDescriptor
      14: iconst_0
      15: invokestatic  #28                 // Method kotlin/reflect/jvm/internal/impl/resolve/DescriptorUtils.getParentOfType:(Lkotlin/reflect/jvm/internal/impl/descriptors/DeclarationDescriptor;Ljava/lang/Class;Z)Lkotlin/reflect/jvm/internal/impl/descriptors/DeclarationDescriptor;
      18: checkcast     #7                  // class kotlin/reflect/jvm/internal/impl/descriptors/PackageFragmentDescriptor
      21: astore_3
      22: aload_3
      23: ifnull        52
      26: aload_2
      27: ifnull        52
      30: aload_2
      31: invokeinterface #30,  1           // InterfaceMethod kotlin/reflect/jvm/internal/impl/descriptors/PackageFragmentDescriptor.getFqName:()Lkotlin/reflect/jvm/internal/impl/name/FqName;
      36: aload_3
      37: invokeinterface #30,  1           // InterfaceMethod kotlin/reflect/jvm/internal/impl/descriptors/PackageFragmentDescriptor.getFqName:()Lkotlin/reflect/jvm/internal/impl/name/FqName;
      42: invokevirtual #27                 // Method kotlin/reflect/jvm/internal/impl/name/FqName.equals:(Ljava/lang/Object;)Z
      45: ifeq          52
      48: iconst_1
      49: goto          53
      52: iconst_0
      53: ireturn

  static boolean access$000(kotlin.reflect.jvm.internal.impl.descriptors.DeclarationDescriptor, kotlin.reflect.jvm.internal.impl.descriptors.DeclarationDescriptor);
    Code:
       0: aload_0
       1: aload_1
       2: invokestatic  #22                 // Method areInSamePackage:(Lkotlin/reflect/jvm/internal/impl/descriptors/DeclarationDescriptor;Lkotlin/reflect/jvm/internal/impl/descriptors/DeclarationDescriptor;)Z
       5: ireturn

  static boolean access$100(kotlin.reflect.jvm.internal.impl.resolve.scopes.receivers.ReceiverValue, kotlin.reflect.jvm.internal.impl.descriptors.DeclarationDescriptorWithVisibility, kotlin.reflect.jvm.internal.impl.descriptors.DeclarationDescriptor);
    Code:
       0: aload_0
       1: aload_1
       2: aload_2
       3: invokestatic  #23                 // Method isVisibleForProtectedAndPackage:(Lkotlin/reflect/jvm/internal/impl/resolve/scopes/receivers/ReceiverValue;Lkotlin/reflect/jvm/internal/impl/descriptors/DeclarationDescriptorWithVisibility;Lkotlin/reflect/jvm/internal/impl/descriptors/DeclarationDescriptor;)Z
       6: ireturn

  static {};
    Code:
       0: new           #11                 // class kotlin/reflect/jvm/internal/impl/load/java/JavaVisibilities$1
       3: dup
       4: ldc           #1                  // String package
       6: iconst_0
       7: invokespecial #24                 // Method kotlin/reflect/jvm/internal/impl/load/java/JavaVisibilities$1."<init>":(Ljava/lang/String;Z)V
      10: putstatic     #18                 // Field PACKAGE_VISIBILITY:Lkotlin/reflect/jvm/internal/impl/descriptors/Visibility;
      13: new           #12                 // class kotlin/reflect/jvm/internal/impl/load/java/JavaVisibilities$2
      16: dup
      17: ldc           #3                  // String protected_static
      19: iconst_1
      20: invokespecial #25                 // Method kotlin/reflect/jvm/internal/impl/load/java/JavaVisibilities$2."<init>":(Ljava/lang/String;Z)V
      23: putstatic     #20                 // Field PROTECTED_STATIC_VISIBILITY:Lkotlin/reflect/jvm/internal/impl/descriptors/Visibility;
      26: new           #13                 // class kotlin/reflect/jvm/internal/impl/load/java/JavaVisibilities$3
      29: dup
      30: ldc           #2                  // String protected_and_package
      32: iconst_1
      33: invokespecial #26                 // Method kotlin/reflect/jvm/internal/impl/load/java/JavaVisibilities$3."<init>":(Ljava/lang/String;Z)V
      36: putstatic     #19                 // Field PROTECTED_AND_PACKAGE:Lkotlin/reflect/jvm/internal/impl/descriptors/Visibility;
      39: return
}
