Compiled from "BaseTrustEngineRule.java"
public abstract class org.opensaml.ws.security.provider.BaseTrustEngineRule<TokenType> implements org.opensaml.ws.security.SecurityPolicyRule {
  private final org.slf4j.Logger log;

  private org.opensaml.xml.security.trust.TrustEngine<TokenType> trustEngine;

  public org.opensaml.ws.security.provider.BaseTrustEngineRule(org.opensaml.xml.security.trust.TrustEngine<TokenType>);
    Code:
       0: aload_0
       1: invokespecial #1                  // Method java/lang/Object."<init>":()V
       4: aload_0
       5: ldc_w         #2                  // class org/opensaml/ws/security/provider/BaseTrustEngineRule
       8: invokestatic  #3                  // Method org/slf4j/LoggerFactory.getLogger:(Ljava/lang/Class;)Lorg/slf4j/Logger;
      11: putfield      #4                  // Field log:Lorg/slf4j/Logger;
      14: aload_0
      15: aload_1
      16: putfield      #5                  // Field trustEngine:Lorg/opensaml/xml/security/trust/TrustEngine;
      19: return

  protected org.opensaml.xml.security.trust.TrustEngine<TokenType> getTrustEngine();
    Code:
       0: aload_0
       1: getfield      #5                  // Field trustEngine:Lorg/opensaml/xml/security/trust/TrustEngine;
       4: areturn

  protected abstract org.opensaml.xml.security.CriteriaSet buildCriteriaSet(java.lang.String, org.opensaml.ws.message.MessageContext) throws org.opensaml.ws.security.SecurityPolicyException;

  protected boolean evaluate(TokenType, java.lang.String, org.opensaml.ws.message.MessageContext) throws org.opensaml.ws.security.SecurityPolicyException;
    Code:
       0: aload_0
       1: aload_2
       2: aload_3
       3: invokevirtual #6                  // Method buildCriteriaSet:(Ljava/lang/String;Lorg/opensaml/ws/message/MessageContext;)Lorg/opensaml/xml/security/CriteriaSet;
       6: astore        4
       8: aload         4
      10: ifnonnull     34
      13: aload_0
      14: getfield      #4                  // Field log:Lorg/slf4j/Logger;
      17: ldc           #7                  // String Returned criteria set was null, can not perform trust engine evaluation of token
      19: invokeinterface #8,  2            // InterfaceMethod org/slf4j/Logger.error:(Ljava/lang/String;)V
      24: new           #9                  // class org/opensaml/ws/security/SecurityPolicyException
      27: dup
      28: ldc           #10                 // String Returned criteria set was null
      30: invokespecial #11                 // Method org/opensaml/ws/security/SecurityPolicyException."<init>":(Ljava/lang/String;)V
      33: athrow
      34: aload_0
      35: aload_1
      36: aload         4
      38: invokevirtual #12                 // Method evaluate:(Ljava/lang/Object;Lorg/opensaml/xml/security/CriteriaSet;)Z
      41: ireturn

  protected boolean evaluate(TokenType, org.opensaml.xml.security.CriteriaSet) throws org.opensaml.ws.security.SecurityPolicyException;
    Code:
       0: aload_0
       1: invokevirtual #13                 // Method getTrustEngine:()Lorg/opensaml/xml/security/trust/TrustEngine;
       4: aload_1
       5: aload_2
       6: invokeinterface #14,  3           // InterfaceMethod org/opensaml/xml/security/trust/TrustEngine.validate:(Ljava/lang/Object;Lorg/opensaml/xml/security/CriteriaSet;)Z
      11: ireturn
      12: astore_3
      13: aload_0
      14: getfield      #4                  // Field log:Lorg/slf4j/Logger;
      17: ldc           #16                 // String There was an error evaluating the request\'s token using the trust engine
      19: aload_3
      20: invokeinterface #17,  3           // InterfaceMethod org/slf4j/Logger.error:(Ljava/lang/String;Ljava/lang/Throwable;)V
      25: new           #9                  // class org/opensaml/ws/security/SecurityPolicyException
      28: dup
      29: ldc           #18                 // String Error during trust engine evaluation of the token
      31: aload_3
      32: invokespecial #19                 // Method org/opensaml/ws/security/SecurityPolicyException."<init>":(Ljava/lang/String;Ljava/lang/Exception;)V
      35: athrow
    Exception table:
       from    to  target type
           0    11    12   Class org/opensaml/xml/security/SecurityException
}
