Compiled from "IdentityProviderConfiguration.java"
final class software.amazon.awssdk.services.healthlake.model.IdentityProviderConfiguration$BuilderImpl implements software.amazon.awssdk.services.healthlake.model.IdentityProviderConfiguration$Builder {
  private java.lang.String authorizationStrategy;

  private java.lang.Boolean fineGrainedAuthorizationEnabled;

  private java.lang.String metadata;

  private java.lang.String idpLambdaArn;

  private software.amazon.awssdk.services.healthlake.model.IdentityProviderConfiguration$BuilderImpl();
    Code:
       0: aload_0
       1: invokespecial #7                  // Method java/lang/Object."<init>":()V
       4: return

  private software.amazon.awssdk.services.healthlake.model.IdentityProviderConfiguration$BuilderImpl(software.amazon.awssdk.services.healthlake.model.IdentityProviderConfiguration);
    Code:
       0: aload_0
       1: invokespecial #7                  // Method java/lang/Object."<init>":()V
       4: aload_0
       5: aload_1
       6: invokestatic  #8                  // Method software/amazon/awssdk/services/healthlake/model/IdentityProviderConfiguration.access$600:(Lsoftware/amazon/awssdk/services/healthlake/model/IdentityProviderConfiguration;)Ljava/lang/String;
       9: invokevirtual #9                  // Method authorizationStrategy:(Ljava/lang/String;)Lsoftware/amazon/awssdk/services/healthlake/model/IdentityProviderConfiguration$Builder;
      12: pop
      13: aload_0
      14: aload_1
      15: invokestatic  #10                 // Method software/amazon/awssdk/services/healthlake/model/IdentityProviderConfiguration.access$700:(Lsoftware/amazon/awssdk/services/healthlake/model/IdentityProviderConfiguration;)Ljava/lang/Boolean;
      18: invokevirtual #11                 // Method fineGrainedAuthorizationEnabled:(Ljava/lang/Boolean;)Lsoftware/amazon/awssdk/services/healthlake/model/IdentityProviderConfiguration$Builder;
      21: pop
      22: aload_0
      23: aload_1
      24: invokestatic  #12                 // Method software/amazon/awssdk/services/healthlake/model/IdentityProviderConfiguration.access$800:(Lsoftware/amazon/awssdk/services/healthlake/model/IdentityProviderConfiguration;)Ljava/lang/String;
      27: invokevirtual #13                 // Method metadata:(Ljava/lang/String;)Lsoftware/amazon/awssdk/services/healthlake/model/IdentityProviderConfiguration$Builder;
      30: pop
      31: aload_0
      32: aload_1
      33: invokestatic  #14                 // Method software/amazon/awssdk/services/healthlake/model/IdentityProviderConfiguration.access$900:(Lsoftware/amazon/awssdk/services/healthlake/model/IdentityProviderConfiguration;)Ljava/lang/String;
      36: invokevirtual #15                 // Method idpLambdaArn:(Ljava/lang/String;)Lsoftware/amazon/awssdk/services/healthlake/model/IdentityProviderConfiguration$Builder;
      39: pop
      40: return

  public final java.lang.String getAuthorizationStrategy();
    Code:
       0: aload_0
       1: getfield      #6                  // Field authorizationStrategy:Ljava/lang/String;
       4: areturn

  public final void setAuthorizationStrategy(java.lang.String);
    Code:
       0: aload_0
       1: aload_1
       2: putfield      #6                  // Field authorizationStrategy:Ljava/lang/String;
       5: return

  public final software.amazon.awssdk.services.healthlake.model.IdentityProviderConfiguration$Builder authorizationStrategy(java.lang.String);
    Code:
       0: aload_0
       1: aload_1
       2: putfield      #6                  // Field authorizationStrategy:Ljava/lang/String;
       5: aload_0
       6: areturn

  public final software.amazon.awssdk.services.healthlake.model.IdentityProviderConfiguration$Builder authorizationStrategy(software.amazon.awssdk.services.healthlake.model.AuthorizationStrategy);
    Code:
       0: aload_0
       1: aload_1
       2: ifnonnull     9
       5: aconst_null
       6: goto          13
       9: aload_1
      10: invokevirtual #16                 // Method software/amazon/awssdk/services/healthlake/model/AuthorizationStrategy.toString:()Ljava/lang/String;
      13: invokevirtual #9                  // Method authorizationStrategy:(Ljava/lang/String;)Lsoftware/amazon/awssdk/services/healthlake/model/IdentityProviderConfiguration$Builder;
      16: pop
      17: aload_0
      18: areturn

  public final java.lang.Boolean getFineGrainedAuthorizationEnabled();
    Code:
       0: aload_0
       1: getfield      #5                  // Field fineGrainedAuthorizationEnabled:Ljava/lang/Boolean;
       4: areturn

  public final void setFineGrainedAuthorizationEnabled(java.lang.Boolean);
    Code:
       0: aload_0
       1: aload_1
       2: putfield      #5                  // Field fineGrainedAuthorizationEnabled:Ljava/lang/Boolean;
       5: return

  public final software.amazon.awssdk.services.healthlake.model.IdentityProviderConfiguration$Builder fineGrainedAuthorizationEnabled(java.lang.Boolean);
    Code:
       0: aload_0
       1: aload_1
       2: putfield      #5                  // Field fineGrainedAuthorizationEnabled:Ljava/lang/Boolean;
       5: aload_0
       6: areturn

  public final java.lang.String getMetadata();
    Code:
       0: aload_0
       1: getfield      #4                  // Field metadata:Ljava/lang/String;
       4: areturn

  public final void setMetadata(java.lang.String);
    Code:
       0: aload_0
       1: aload_1
       2: putfield      #4                  // Field metadata:Ljava/lang/String;
       5: return

  public final software.amazon.awssdk.services.healthlake.model.IdentityProviderConfiguration$Builder metadata(java.lang.String);
    Code:
       0: aload_0
       1: aload_1
       2: putfield      #4                  // Field metadata:Ljava/lang/String;
       5: aload_0
       6: areturn

  public final java.lang.String getIdpLambdaArn();
    Code:
       0: aload_0
       1: getfield      #3                  // Field idpLambdaArn:Ljava/lang/String;
       4: areturn

  public final void setIdpLambdaArn(java.lang.String);
    Code:
       0: aload_0
       1: aload_1
       2: putfield      #3                  // Field idpLambdaArn:Ljava/lang/String;
       5: return

  public final software.amazon.awssdk.services.healthlake.model.IdentityProviderConfiguration$Builder idpLambdaArn(java.lang.String);
    Code:
       0: aload_0
       1: aload_1
       2: putfield      #3                  // Field idpLambdaArn:Ljava/lang/String;
       5: aload_0
       6: areturn

  public software.amazon.awssdk.services.healthlake.model.IdentityProviderConfiguration build();
    Code:
       0: new           #17                 // class software/amazon/awssdk/services/healthlake/model/IdentityProviderConfiguration
       3: dup
       4: aload_0
       5: aconst_null
       6: invokespecial #18                 // Method software/amazon/awssdk/services/healthlake/model/IdentityProviderConfiguration."<init>":(Lsoftware/amazon/awssdk/services/healthlake/model/IdentityProviderConfiguration$BuilderImpl;Lsoftware/amazon/awssdk/services/healthlake/model/IdentityProviderConfiguration$1;)V
       9: areturn

  public java.util.List<software.amazon.awssdk.core.SdkField<?>> sdkFields();
    Code:
       0: invokestatic  #19                 // Method software/amazon/awssdk/services/healthlake/model/IdentityProviderConfiguration.access$1100:()Ljava/util/List;
       3: areturn

  public java.lang.Object build();
    Code:
       0: aload_0
       1: invokevirtual #20                 // Method build:()Lsoftware/amazon/awssdk/services/healthlake/model/IdentityProviderConfiguration;
       4: areturn

  static java.lang.String access$000(software.amazon.awssdk.services.healthlake.model.IdentityProviderConfiguration$BuilderImpl);
    Code:
       0: aload_0
       1: getfield      #6                  // Field authorizationStrategy:Ljava/lang/String;
       4: areturn

  static java.lang.Boolean access$100(software.amazon.awssdk.services.healthlake.model.IdentityProviderConfiguration$BuilderImpl);
    Code:
       0: aload_0
       1: getfield      #5                  // Field fineGrainedAuthorizationEnabled:Ljava/lang/Boolean;
       4: areturn

  static java.lang.String access$200(software.amazon.awssdk.services.healthlake.model.IdentityProviderConfiguration$BuilderImpl);
    Code:
       0: aload_0
       1: getfield      #4                  // Field metadata:Ljava/lang/String;
       4: areturn

  static java.lang.String access$300(software.amazon.awssdk.services.healthlake.model.IdentityProviderConfiguration$BuilderImpl);
    Code:
       0: aload_0
       1: getfield      #3                  // Field idpLambdaArn:Ljava/lang/String;
       4: areturn

  software.amazon.awssdk.services.healthlake.model.IdentityProviderConfiguration$BuilderImpl(software.amazon.awssdk.services.healthlake.model.IdentityProviderConfiguration, software.amazon.awssdk.services.healthlake.model.IdentityProviderConfiguration$1);
    Code:
       0: aload_0
       1: aload_1
       2: invokespecial #2                  // Method "<init>":(Lsoftware/amazon/awssdk/services/healthlake/model/IdentityProviderConfiguration;)V
       5: return

  software.amazon.awssdk.services.healthlake.model.IdentityProviderConfiguration$BuilderImpl(software.amazon.awssdk.services.healthlake.model.IdentityProviderConfiguration$1);
    Code:
       0: aload_0
       1: invokespecial #1                  // Method "<init>":()V
       4: return
}
