Compiled from "ResourceDeleteHook.java"
public class io.dekorate.hook.ResourceDeleteHook extends io.dekorate.hook.ProjectHook {
  private final io.dekorate.utils.Exec$ProjectExec exec;

  private final java.lang.String group;

  private final java.lang.String command;

  private final java.lang.String path;

  public io.dekorate.hook.ResourceDeleteHook(io.dekorate.project.Project, java.lang.String, java.lang.String);
    Code:
       0: aload_0
       1: aload_1
       2: invokespecial #1                  // Method io/dekorate/hook/ProjectHook."<init>":(Lio/dekorate/project/Project;)V
       5: aload_0
       6: aload_1
       7: invokestatic  #2                  // Method io/dekorate/utils/Exec.inProject:(Lio/dekorate/project/Project;)Lio/dekorate/utils/Exec$ProjectExec;
      10: putfield      #3                  // Field exec:Lio/dekorate/utils/Exec$ProjectExec;
      13: aload_0
      14: aload_2
      15: putfield      #4                  // Field group:Ljava/lang/String;
      18: aload_0
      19: aload_3
      20: putfield      #5                  // Field command:Ljava/lang/String;
      23: aload_0
      24: aload_1
      25: invokevirtual #6                  // Method io/dekorate/project/Project.getBuildInfo:()Lio/dekorate/project/BuildInfo;
      28: invokevirtual #7                  // Method io/dekorate/project/BuildInfo.getClassOutputDir:()Ljava/nio/file/Path;
      31: aload_1
      32: invokevirtual #8                  // Method io/dekorate/project/Project.getDekorateOutputDir:()Ljava/lang/String;
      35: invokeinterface #9,  2            // InterfaceMethod java/nio/file/Path.resolve:(Ljava/lang/String;)Ljava/nio/file/Path;
      40: new           #10                 // class java/lang/StringBuilder
      43: dup
      44: invokespecial #11                 // Method java/lang/StringBuilder."<init>":()V
      47: aload_2
      48: invokevirtual #12                 // Method java/lang/StringBuilder.append:(Ljava/lang/String;)Ljava/lang/StringBuilder;
      51: ldc           #13                 // String .yml
      53: invokevirtual #12                 // Method java/lang/StringBuilder.append:(Ljava/lang/String;)Ljava/lang/StringBuilder;
      56: invokevirtual #14                 // Method java/lang/StringBuilder.toString:()Ljava/lang/String;
      59: invokeinterface #9,  2            // InterfaceMethod java/nio/file/Path.resolve:(Ljava/lang/String;)Ljava/nio/file/Path;
      64: invokeinterface #15,  1           // InterfaceMethod java/nio/file/Path.toAbsolutePath:()Ljava/nio/file/Path;
      69: invokeinterface #16,  1           // InterfaceMethod java/nio/file/Path.toString:()Ljava/lang/String;
      74: putfield      #17                 // Field path:Ljava/lang/String;
      77: return

  public void run();
    Code:
       0: aload_0
       1: getfield      #3                  // Field exec:Lio/dekorate/utils/Exec$ProjectExec;
       4: iconst_4
       5: anewarray     #18                 // class java/lang/String
       8: dup
       9: iconst_0
      10: aload_0
      11: getfield      #5                  // Field command:Ljava/lang/String;
      14: aastore
      15: dup
      16: iconst_1
      17: ldc           #19                 // String delete
      19: aastore
      20: dup
      21: iconst_2
      22: ldc           #20                 // String -f
      24: aastore
      25: dup
      26: iconst_3
      27: aload_0
      28: getfield      #17                 // Field path:Ljava/lang/String;
      31: aastore
      32: invokevirtual #21                 // Method io/dekorate/utils/Exec$ProjectExec.commands:([Ljava/lang/String;)Z
      35: pop
      36: return

  public void init();
    Code:
       0: return

  public void warmup();
    Code:
       0: return
}
