Compiled from "AuthChallengeProcessor.java"
public final class org.apache.commons.httpclient.auth.AuthChallengeProcessor {
  private static final org.apache.commons.logging.Log LOG;

  private org.apache.commons.httpclient.params.HttpParams params;

  static java.lang.Class class$org$apache$commons$httpclient$auth$AuthChallengeProcessor;

  public org.apache.commons.httpclient.auth.AuthChallengeProcessor(org.apache.commons.httpclient.params.HttpParams);
    Code:
       0: aload_0
       1: invokespecial #6                  // Method java/lang/Object."<init>":()V
       4: aload_0
       5: aconst_null
       6: putfield      #7                  // Field params:Lorg/apache/commons/httpclient/params/HttpParams;
       9: aload_1
      10: ifnonnull     23
      13: new           #8                  // class java/lang/IllegalArgumentException
      16: dup
      17: ldc           #9                  // String Parameter collection may not be null
      19: invokespecial #10                 // Method java/lang/IllegalArgumentException."<init>":(Ljava/lang/String;)V
      22: athrow
      23: aload_0
      24: aload_1
      25: putfield      #7                  // Field params:Lorg/apache/commons/httpclient/params/HttpParams;
      28: return

  public org.apache.commons.httpclient.auth.AuthScheme selectAuthScheme(java.util.Map) throws org.apache.commons.httpclient.auth.AuthChallengeException;
    Code:
       0: aload_1
       1: ifnonnull     14
       4: new           #8                  // class java/lang/IllegalArgumentException
       7: dup
       8: ldc           #11                 // String Challenge map may not be null
      10: invokespecial #10                 // Method java/lang/IllegalArgumentException."<init>":(Ljava/lang/String;)V
      13: athrow
      14: aload_0
      15: getfield      #7                  // Field params:Lorg/apache/commons/httpclient/params/HttpParams;
      18: ldc           #12                 // String http.auth.scheme-priority
      20: invokeinterface #13,  2           // InterfaceMethod org/apache/commons/httpclient/params/HttpParams.getParameter:(Ljava/lang/String;)Ljava/lang/Object;
      25: checkcast     #14                 // class java/util/Collection
      28: astore_2
      29: aload_2
      30: ifnull        42
      33: aload_2
      34: invokeinterface #15,  1           // InterfaceMethod java/util/Collection.isEmpty:()Z
      39: ifeq          46
      42: invokestatic  #16                 // Method org/apache/commons/httpclient/auth/AuthPolicy.getDefaultAuthPrefs:()Ljava/util/List;
      45: astore_2
      46: getstatic     #17                 // Field LOG:Lorg/apache/commons/logging/Log;
      49: invokeinterface #18,  1           // InterfaceMethod org/apache/commons/logging/Log.isDebugEnabled:()Z
      54: ifeq          84
      57: getstatic     #17                 // Field LOG:Lorg/apache/commons/logging/Log;
      60: new           #19                 // class java/lang/StringBuffer
      63: dup
      64: invokespecial #20                 // Method java/lang/StringBuffer."<init>":()V
      67: ldc           #21                 // String Supported authentication schemes in the order of preference:
      69: invokevirtual #22                 // Method java/lang/StringBuffer.append:(Ljava/lang/String;)Ljava/lang/StringBuffer;
      72: aload_2
      73: invokevirtual #23                 // Method java/lang/StringBuffer.append:(Ljava/lang/Object;)Ljava/lang/StringBuffer;
      76: invokevirtual #24                 // Method java/lang/StringBuffer.toString:()Ljava/lang/String;
      79: invokeinterface #25,  2           // InterfaceMethod org/apache/commons/logging/Log.debug:(Ljava/lang/Object;)V
      84: aconst_null
      85: astore_3
      86: aconst_null
      87: astore        4
      89: aload_2
      90: invokeinterface #26,  1           // InterfaceMethod java/util/Collection.iterator:()Ljava/util/Iterator;
      95: astore        5
      97: aload         5
      99: invokeinterface #27,  1           // InterfaceMethod java/util/Iterator.hasNext:()Z
     104: ifeq          250
     107: aload         5
     109: invokeinterface #28,  1           // InterfaceMethod java/util/Iterator.next:()Ljava/lang/Object;
     114: checkcast     #29                 // class java/lang/String
     117: astore        6
     119: aload_1
     120: aload         6
     122: invokevirtual #30                 // Method java/lang/String.toLowerCase:()Ljava/lang/String;
     125: invokeinterface #31,  2           // InterfaceMethod java/util/Map.get:(Ljava/lang/Object;)Ljava/lang/Object;
     130: checkcast     #29                 // class java/lang/String
     133: astore        4
     135: aload         4
     137: ifnull        203
     140: getstatic     #17                 // Field LOG:Lorg/apache/commons/logging/Log;
     143: invokeinterface #32,  1           // InterfaceMethod org/apache/commons/logging/Log.isInfoEnabled:()Z
     148: ifeq          179
     151: getstatic     #17                 // Field LOG:Lorg/apache/commons/logging/Log;
     154: new           #19                 // class java/lang/StringBuffer
     157: dup
     158: invokespecial #20                 // Method java/lang/StringBuffer."<init>":()V
     161: aload         6
     163: invokevirtual #22                 // Method java/lang/StringBuffer.append:(Ljava/lang/String;)Ljava/lang/StringBuffer;
     166: ldc           #33                 // String  authentication scheme selected
     168: invokevirtual #22                 // Method java/lang/StringBuffer.append:(Ljava/lang/String;)Ljava/lang/StringBuffer;
     171: invokevirtual #24                 // Method java/lang/StringBuffer.toString:()Ljava/lang/String;
     174: invokeinterface #34,  2           // InterfaceMethod org/apache/commons/logging/Log.info:(Ljava/lang/Object;)V
     179: aload         6
     181: invokestatic  #35                 // Method org/apache/commons/httpclient/auth/AuthPolicy.getAuthScheme:(Ljava/lang/String;)Lorg/apache/commons/httpclient/auth/AuthScheme;
     184: astore_3
     185: goto          250
     188: astore        7
     190: new           #37                 // class org/apache/commons/httpclient/auth/AuthChallengeException
     193: dup
     194: aload         7
     196: invokevirtual #38                 // Method java/lang/IllegalStateException.getMessage:()Ljava/lang/String;
     199: invokespecial #39                 // Method org/apache/commons/httpclient/auth/AuthChallengeException."<init>":(Ljava/lang/String;)V
     202: athrow
     203: getstatic     #17                 // Field LOG:Lorg/apache/commons/logging/Log;
     206: invokeinterface #18,  1           // InterfaceMethod org/apache/commons/logging/Log.isDebugEnabled:()Z
     211: ifeq          247
     214: getstatic     #17                 // Field LOG:Lorg/apache/commons/logging/Log;
     217: new           #19                 // class java/lang/StringBuffer
     220: dup
     221: invokespecial #20                 // Method java/lang/StringBuffer."<init>":()V
     224: ldc           #40                 // String Challenge for
     226: invokevirtual #22                 // Method java/lang/StringBuffer.append:(Ljava/lang/String;)Ljava/lang/StringBuffer;
     229: aload         6
     231: invokevirtual #22                 // Method java/lang/StringBuffer.append:(Ljava/lang/String;)Ljava/lang/StringBuffer;
     234: ldc           #41                 // String  authentication scheme not available
     236: invokevirtual #22                 // Method java/lang/StringBuffer.append:(Ljava/lang/String;)Ljava/lang/StringBuffer;
     239: invokevirtual #24                 // Method java/lang/StringBuffer.toString:()Ljava/lang/String;
     242: invokeinterface #25,  2           // InterfaceMethod org/apache/commons/logging/Log.debug:(Ljava/lang/Object;)V
     247: goto          97
     250: aload_3
     251: ifnonnull     281
     254: new           #37                 // class org/apache/commons/httpclient/auth/AuthChallengeException
     257: dup
     258: new           #19                 // class java/lang/StringBuffer
     261: dup
     262: invokespecial #20                 // Method java/lang/StringBuffer."<init>":()V
     265: ldc           #42                 // String Unable to respond to any of these challenges:
     267: invokevirtual #22                 // Method java/lang/StringBuffer.append:(Ljava/lang/String;)Ljava/lang/StringBuffer;
     270: aload_1
     271: invokevirtual #23                 // Method java/lang/StringBuffer.append:(Ljava/lang/Object;)Ljava/lang/StringBuffer;
     274: invokevirtual #24                 // Method java/lang/StringBuffer.toString:()Ljava/lang/String;
     277: invokespecial #39                 // Method org/apache/commons/httpclient/auth/AuthChallengeException."<init>":(Ljava/lang/String;)V
     280: athrow
     281: aload_3
     282: areturn
    Exception table:
       from    to  target type
         179   185   188   Class java/lang/IllegalStateException

  public org.apache.commons.httpclient.auth.AuthScheme processChallenge(org.apache.commons.httpclient.auth.AuthState, java.util.Map) throws org.apache.commons.httpclient.auth.MalformedChallengeException, org.apache.commons.httpclient.auth.AuthenticationException;
    Code:
       0: aload_1
       1: ifnonnull     14
       4: new           #8                  // class java/lang/IllegalArgumentException
       7: dup
       8: ldc           #43                 // String Authentication state may not be null
      10: invokespecial #10                 // Method java/lang/IllegalArgumentException."<init>":(Ljava/lang/String;)V
      13: athrow
      14: aload_2
      15: ifnonnull     28
      18: new           #8                  // class java/lang/IllegalArgumentException
      21: dup
      22: ldc           #11                 // String Challenge map may not be null
      24: invokespecial #10                 // Method java/lang/IllegalArgumentException."<init>":(Ljava/lang/String;)V
      27: athrow
      28: aload_1
      29: invokevirtual #44                 // Method org/apache/commons/httpclient/auth/AuthState.isPreemptive:()Z
      32: ifne          42
      35: aload_1
      36: invokevirtual #45                 // Method org/apache/commons/httpclient/auth/AuthState.getAuthScheme:()Lorg/apache/commons/httpclient/auth/AuthScheme;
      39: ifnonnull     51
      42: aload_1
      43: aload_0
      44: aload_2
      45: invokevirtual #46                 // Method selectAuthScheme:(Ljava/util/Map;)Lorg/apache/commons/httpclient/auth/AuthScheme;
      48: invokevirtual #47                 // Method org/apache/commons/httpclient/auth/AuthState.setAuthScheme:(Lorg/apache/commons/httpclient/auth/AuthScheme;)V
      51: aload_1
      52: invokevirtual #45                 // Method org/apache/commons/httpclient/auth/AuthState.getAuthScheme:()Lorg/apache/commons/httpclient/auth/AuthScheme;
      55: astore_3
      56: aload_3
      57: invokeinterface #48,  1           // InterfaceMethod org/apache/commons/httpclient/auth/AuthScheme.getSchemeName:()Ljava/lang/String;
      62: astore        4
      64: getstatic     #17                 // Field LOG:Lorg/apache/commons/logging/Log;
      67: invokeinterface #18,  1           // InterfaceMethod org/apache/commons/logging/Log.isDebugEnabled:()Z
      72: ifeq          103
      75: getstatic     #17                 // Field LOG:Lorg/apache/commons/logging/Log;
      78: new           #19                 // class java/lang/StringBuffer
      81: dup
      82: invokespecial #20                 // Method java/lang/StringBuffer."<init>":()V
      85: ldc           #49                 // String Using authentication scheme:
      87: invokevirtual #22                 // Method java/lang/StringBuffer.append:(Ljava/lang/String;)Ljava/lang/StringBuffer;
      90: aload         4
      92: invokevirtual #22                 // Method java/lang/StringBuffer.append:(Ljava/lang/String;)Ljava/lang/StringBuffer;
      95: invokevirtual #24                 // Method java/lang/StringBuffer.toString:()Ljava/lang/String;
      98: invokeinterface #25,  2           // InterfaceMethod org/apache/commons/logging/Log.debug:(Ljava/lang/Object;)V
     103: aload_2
     104: aload         4
     106: invokevirtual #30                 // Method java/lang/String.toLowerCase:()Ljava/lang/String;
     109: invokeinterface #31,  2           // InterfaceMethod java/util/Map.get:(Ljava/lang/Object;)Ljava/lang/Object;
     114: checkcast     #29                 // class java/lang/String
     117: astore        5
     119: aload         5
     121: ifnonnull     152
     124: new           #50                 // class org/apache/commons/httpclient/auth/AuthenticationException
     127: dup
     128: new           #19                 // class java/lang/StringBuffer
     131: dup
     132: invokespecial #20                 // Method java/lang/StringBuffer."<init>":()V
     135: aload         4
     137: invokevirtual #22                 // Method java/lang/StringBuffer.append:(Ljava/lang/String;)Ljava/lang/StringBuffer;
     140: ldc           #51                 // String  authorization challenge expected, but not found
     142: invokevirtual #22                 // Method java/lang/StringBuffer.append:(Ljava/lang/String;)Ljava/lang/StringBuffer;
     145: invokevirtual #24                 // Method java/lang/StringBuffer.toString:()Ljava/lang/String;
     148: invokespecial #52                 // Method org/apache/commons/httpclient/auth/AuthenticationException."<init>":(Ljava/lang/String;)V
     151: athrow
     152: aload_3
     153: aload         5
     155: invokeinterface #53,  2           // InterfaceMethod org/apache/commons/httpclient/auth/AuthScheme.processChallenge:(Ljava/lang/String;)V
     160: getstatic     #17                 // Field LOG:Lorg/apache/commons/logging/Log;
     163: ldc           #54                 // String Authorization challenge processed
     165: invokeinterface #25,  2           // InterfaceMethod org/apache/commons/logging/Log.debug:(Ljava/lang/Object;)V
     170: aload_3
     171: areturn

  static java.lang.Class class$(java.lang.String);
    Code:
       0: aload_0
       1: invokestatic  #1                  // Method java/lang/Class.forName:(Ljava/lang/String;)Ljava/lang/Class;
       4: areturn
       5: astore_1
       6: new           #3                  // class java/lang/NoClassDefFoundError
       9: dup
      10: aload_1
      11: invokevirtual #4                  // Method java/lang/ClassNotFoundException.getMessage:()Ljava/lang/String;
      14: invokespecial #5                  // Method java/lang/NoClassDefFoundError."<init>":(Ljava/lang/String;)V
      17: athrow
    Exception table:
       from    to  target type
           0     4     5   Class java/lang/ClassNotFoundException

  static {};
    Code:
       0: getstatic     #55                 // Field class$org$apache$commons$httpclient$auth$AuthChallengeProcessor:Ljava/lang/Class;
       3: ifnonnull     18
       6: ldc           #56                 // String org.apache.commons.httpclient.auth.AuthChallengeProcessor
       8: invokestatic  #57                 // Method class$:(Ljava/lang/String;)Ljava/lang/Class;
      11: dup
      12: putstatic     #55                 // Field class$org$apache$commons$httpclient$auth$AuthChallengeProcessor:Ljava/lang/Class;
      15: goto          21
      18: getstatic     #55                 // Field class$org$apache$commons$httpclient$auth$AuthChallengeProcessor:Ljava/lang/Class;
      21: invokestatic  #58                 // Method org/apache/commons/logging/LogFactory.getLog:(Ljava/lang/Class;)Lorg/apache/commons/logging/Log;
      24: putstatic     #17                 // Field LOG:Lorg/apache/commons/logging/Log;
      27: return
}
