Compiled from "InvalidCredentialsException.java"
public class org.apache.commons.httpclient.auth.InvalidCredentialsException extends org.apache.commons.httpclient.auth.AuthenticationException {
  public org.apache.commons.httpclient.auth.InvalidCredentialsException();
    Code:
       0: aload_0
       1: invokespecial #1                  // Method org/apache/commons/httpclient/auth/AuthenticationException."<init>":()V
       4: return

  public org.apache.commons.httpclient.auth.InvalidCredentialsException(java.lang.String);
    Code:
       0: aload_0
       1: aload_1
       2: invokespecial #2                  // Method org/apache/commons/httpclient/auth/AuthenticationException."<init>":(Ljava/lang/String;)V
       5: return

  public org.apache.commons.httpclient.auth.InvalidCredentialsException(java.lang.String, java.lang.Throwable);
    Code:
       0: aload_0
       1: aload_1
       2: aload_2
       3: invokespecial #3                  // Method org/apache/commons/httpclient/auth/AuthenticationException."<init>":(Ljava/lang/String;Ljava/lang/Throwable;)V
       6: return
}
