Compiled from "View.java"
public final class io.opencensus.proto.stats.v1.View$AggregationCase extends java.lang.Enum<io.opencensus.proto.stats.v1.View$AggregationCase> implements com.google.protobuf.Internal$EnumLite {
  public static final io.opencensus.proto.stats.v1.View$AggregationCase COUNT_AGGREGATION;

  public static final io.opencensus.proto.stats.v1.View$AggregationCase SUM_AGGREGATION;

  public static final io.opencensus.proto.stats.v1.View$AggregationCase LAST_VALUE_AGGREGATION;

  public static final io.opencensus.proto.stats.v1.View$AggregationCase DISTRIBUTION_AGGREGATION;

  public static final io.opencensus.proto.stats.v1.View$AggregationCase AGGREGATION_NOT_SET;

  private final int value;

  private static final io.opencensus.proto.stats.v1.View$AggregationCase[] $VALUES;

  public static io.opencensus.proto.stats.v1.View$AggregationCase[] values();
    Code:
       0: getstatic     #1                  // Field $VALUES:[Lio/opencensus/proto/stats/v1/View$AggregationCase;
       3: invokevirtual #2                  // Method "[Lio/opencensus/proto/stats/v1/View$AggregationCase;".clone:()Ljava/lang/Object;
       6: checkcast     #3                  // class "[Lio/opencensus/proto/stats/v1/View$AggregationCase;"
       9: areturn

  public static io.opencensus.proto.stats.v1.View$AggregationCase valueOf(java.lang.String);
    Code:
       0: ldc           #4                  // class io/opencensus/proto/stats/v1/View$AggregationCase
       2: aload_0
       3: invokestatic  #5                  // Method java/lang/Enum.valueOf:(Ljava/lang/Class;Ljava/lang/String;)Ljava/lang/Enum;
       6: checkcast     #4                  // class io/opencensus/proto/stats/v1/View$AggregationCase
       9: areturn

  private io.opencensus.proto.stats.v1.View$AggregationCase(int);
    Code:
       0: aload_0
       1: aload_1
       2: iload_2
       3: invokespecial #6                  // Method java/lang/Enum."<init>":(Ljava/lang/String;I)V
       6: aload_0
       7: iload_3
       8: putfield      #7                  // Field value:I
      11: return

  public static io.opencensus.proto.stats.v1.View$AggregationCase valueOf(int);
    Code:
       0: iload_0
       1: invokestatic  #8                  // Method forNumber:(I)Lio/opencensus/proto/stats/v1/View$AggregationCase;
       4: areturn

  public static io.opencensus.proto.stats.v1.View$AggregationCase forNumber(int);
    Code:
       0: iload_0
       1: tableswitch   { // 0 to 8
                     0: 68
                     1: 72
                     2: 72
                     3: 72
                     4: 72
                     5: 52
                     6: 56
                     7: 60
                     8: 64
               default: 72
          }
      52: getstatic     #9                  // Field COUNT_AGGREGATION:Lio/opencensus/proto/stats/v1/View$AggregationCase;
      55: areturn
      56: getstatic     #10                 // Field SUM_AGGREGATION:Lio/opencensus/proto/stats/v1/View$AggregationCase;
      59: areturn
      60: getstatic     #11                 // Field LAST_VALUE_AGGREGATION:Lio/opencensus/proto/stats/v1/View$AggregationCase;
      63: areturn
      64: getstatic     #12                 // Field DISTRIBUTION_AGGREGATION:Lio/opencensus/proto/stats/v1/View$AggregationCase;
      67: areturn
      68: getstatic     #13                 // Field AGGREGATION_NOT_SET:Lio/opencensus/proto/stats/v1/View$AggregationCase;
      71: areturn
      72: aconst_null
      73: areturn

  public int getNumber();
    Code:
       0: aload_0
       1: getfield      #7                  // Field value:I
       4: ireturn

  static {};
    Code:
       0: new           #4                  // class io/opencensus/proto/stats/v1/View$AggregationCase
       3: dup
       4: ldc           #14                 // String COUNT_AGGREGATION
       6: iconst_0
       7: iconst_5
       8: invokespecial #15                 // Method "<init>":(Ljava/lang/String;II)V
      11: putstatic     #9                  // Field COUNT_AGGREGATION:Lio/opencensus/proto/stats/v1/View$AggregationCase;
      14: new           #4                  // class io/opencensus/proto/stats/v1/View$AggregationCase
      17: dup
      18: ldc           #16                 // String SUM_AGGREGATION
      20: iconst_1
      21: bipush        6
      23: invokespecial #15                 // Method "<init>":(Ljava/lang/String;II)V
      26: putstatic     #10                 // Field SUM_AGGREGATION:Lio/opencensus/proto/stats/v1/View$AggregationCase;
      29: new           #4                  // class io/opencensus/proto/stats/v1/View$AggregationCase
      32: dup
      33: ldc           #17                 // String LAST_VALUE_AGGREGATION
      35: iconst_2
      36: bipush        7
      38: invokespecial #15                 // Method "<init>":(Ljava/lang/String;II)V
      41: putstatic     #11                 // Field LAST_VALUE_AGGREGATION:Lio/opencensus/proto/stats/v1/View$AggregationCase;
      44: new           #4                  // class io/opencensus/proto/stats/v1/View$AggregationCase
      47: dup
      48: ldc           #18                 // String DISTRIBUTION_AGGREGATION
      50: iconst_3
      51: bipush        8
      53: invokespecial #15                 // Method "<init>":(Ljava/lang/String;II)V
      56: putstatic     #12                 // Field DISTRIBUTION_AGGREGATION:Lio/opencensus/proto/stats/v1/View$AggregationCase;
      59: new           #4                  // class io/opencensus/proto/stats/v1/View$AggregationCase
      62: dup
      63: ldc           #19                 // String AGGREGATION_NOT_SET
      65: iconst_4
      66: iconst_0
      67: invokespecial #15                 // Method "<init>":(Ljava/lang/String;II)V
      70: putstatic     #13                 // Field AGGREGATION_NOT_SET:Lio/opencensus/proto/stats/v1/View$AggregationCase;
      73: iconst_5
      74: anewarray     #4                  // class io/opencensus/proto/stats/v1/View$AggregationCase
      77: dup
      78: iconst_0
      79: getstatic     #9                  // Field COUNT_AGGREGATION:Lio/opencensus/proto/stats/v1/View$AggregationCase;
      82: aastore
      83: dup
      84: iconst_1
      85: getstatic     #10                 // Field SUM_AGGREGATION:Lio/opencensus/proto/stats/v1/View$AggregationCase;
      88: aastore
      89: dup
      90: iconst_2
      91: getstatic     #11                 // Field LAST_VALUE_AGGREGATION:Lio/opencensus/proto/stats/v1/View$AggregationCase;
      94: aastore
      95: dup
      96: iconst_3
      97: getstatic     #12                 // Field DISTRIBUTION_AGGREGATION:Lio/opencensus/proto/stats/v1/View$AggregationCase;
     100: aastore
     101: dup
     102: iconst_4
     103: getstatic     #13                 // Field AGGREGATION_NOT_SET:Lio/opencensus/proto/stats/v1/View$AggregationCase;
     106: aastore
     107: putstatic     #1                  // Field $VALUES:[Lio/opencensus/proto/stats/v1/View$AggregationCase;
     110: return
}
