Compiled from "AnonymousProvider.java"
public class org.eclipse.milo.opcua.sdk.client.api.identity.AnonymousProvider implements org.eclipse.milo.opcua.sdk.client.api.identity.IdentityProvider {
  public org.eclipse.milo.opcua.sdk.client.api.identity.AnonymousProvider();
    Code:
       0: aload_0
       1: invokespecial #1                  // Method java/lang/Object."<init>":()V
       4: return

  public org.jooq.lambda.tuple.Tuple2<org.eclipse.milo.opcua.stack.core.types.structured.UserIdentityToken, org.eclipse.milo.opcua.stack.core.types.structured.SignatureData> getIdentityToken(org.eclipse.milo.opcua.stack.core.types.structured.EndpointDescription, org.eclipse.milo.opcua.stack.core.types.builtin.ByteString) throws java.lang.Exception;
    Code:
       0: aload_1
       1: invokevirtual #2                  // Method org/eclipse/milo/opcua/stack/core/types/structured/EndpointDescription.getUserIdentityTokens:()[Lorg/eclipse/milo/opcua/stack/core/types/structured/UserTokenPolicy;
       4: invokestatic  #3                  // Method org/eclipse/milo/opcua/stack/core/util/ConversionUtil.l:([Ljava/lang/Object;)Ljava/util/List;
       7: astore_3
       8: aload_3
       9: invokeinterface #4,  1            // InterfaceMethod java/util/List.stream:()Ljava/util/stream/Stream;
      14: invokedynamic #5,  0              // InvokeDynamic #0:test:()Ljava/util/function/Predicate;
      19: invokeinterface #6,  2            // InterfaceMethod java/util/stream/Stream.filter:(Ljava/util/function/Predicate;)Ljava/util/stream/Stream;
      24: invokeinterface #7,  1            // InterfaceMethod java/util/stream/Stream.findFirst:()Ljava/util/Optional;
      29: invokedynamic #8,  0              // InvokeDynamic #1:apply:()Ljava/util/function/Function;
      34: invokevirtual #9                  // Method java/util/Optional.map:(Ljava/util/function/Function;)Ljava/util/Optional;
      37: invokedynamic #10,  0             // InvokeDynamic #2:get:()Ljava/util/function/Supplier;
      42: invokevirtual #11                 // Method java/util/Optional.orElseThrow:(Ljava/util/function/Supplier;)Ljava/lang/Object;
      45: checkcast     #12                 // class org/jooq/lambda/tuple/Tuple2
      48: areturn

  public java.lang.String toString();
    Code:
       0: ldc           #13                 // String AnonymousProvider{}
       2: areturn

  private static java.lang.Exception lambda$getIdentityToken$2();
    Code:
       0: new           #14                 // class java/lang/Exception
       3: dup
       4: ldc           #15                 // String no anonymous token policy found
       6: invokespecial #16                 // Method java/lang/Exception."<init>":(Ljava/lang/String;)V
       9: areturn

  private static org.jooq.lambda.tuple.Tuple2 lambda$getIdentityToken$1(org.eclipse.milo.opcua.stack.core.types.structured.UserTokenPolicy);
    Code:
       0: new           #17                 // class org/eclipse/milo/opcua/stack/core/types/structured/AnonymousIdentityToken
       3: dup
       4: aload_0
       5: invokevirtual #18                 // Method org/eclipse/milo/opcua/stack/core/types/structured/UserTokenPolicy.getPolicyId:()Ljava/lang/String;
       8: invokespecial #19                 // Method org/eclipse/milo/opcua/stack/core/types/structured/AnonymousIdentityToken."<init>":(Ljava/lang/String;)V
      11: astore_1
      12: new           #12                 // class org/jooq/lambda/tuple/Tuple2
      15: dup
      16: aload_1
      17: new           #20                 // class org/eclipse/milo/opcua/stack/core/types/structured/SignatureData
      20: dup
      21: invokespecial #21                 // Method org/eclipse/milo/opcua/stack/core/types/structured/SignatureData."<init>":()V
      24: invokespecial #22                 // Method org/jooq/lambda/tuple/Tuple2."<init>":(Ljava/lang/Object;Ljava/lang/Object;)V
      27: areturn

  private static boolean lambda$getIdentityToken$0(org.eclipse.milo.opcua.stack.core.types.structured.UserTokenPolicy);
    Code:
       0: aload_0
       1: invokevirtual #23                 // Method org/eclipse/milo/opcua/stack/core/types/structured/UserTokenPolicy.getTokenType:()Lorg/eclipse/milo/opcua/stack/core/types/enumerated/UserTokenType;
       4: getstatic     #24                 // Field org/eclipse/milo/opcua/stack/core/types/enumerated/UserTokenType.Anonymous:Lorg/eclipse/milo/opcua/stack/core/types/enumerated/UserTokenType;
       7: if_acmpne     14
      10: iconst_1
      11: goto          15
      14: iconst_0
      15: ireturn
}
