Compiled from "FlatFormatter.java"
public class org.apache.jena.atlas.logging.java.FlatFormatter extends java.util.logging.Formatter {
  private final boolean ensureNL;

  public org.apache.jena.atlas.logging.java.FlatFormatter();
    Code:
       0: aload_0
       1: iconst_1
       2: invokespecial #1                  // Method "<init>":(Z)V
       5: return

  public org.apache.jena.atlas.logging.java.FlatFormatter(boolean);
    Code:
       0: aload_0
       1: invokespecial #2                  // Method java/util/logging/Formatter."<init>":()V
       4: aload_0
       5: iload_1
       6: putfield      #3                  // Field ensureNL:Z
       9: return

  public java.lang.String format(java.util.logging.LogRecord);
    Code:
       0: aload_1
       1: invokevirtual #4                  // Method java/util/logging/LogRecord.getMessage:()Ljava/lang/String;
       4: astore_2
       5: aload_1
       6: invokevirtual #5                  // Method java/util/logging/LogRecord.getParameters:()[Ljava/lang/Object;
       9: ifnull        21
      12: aload_2
      13: aload_1
      14: invokevirtual #5                  // Method java/util/logging/LogRecord.getParameters:()[Ljava/lang/Object;
      17: invokestatic  #6                  // Method java/text/MessageFormat.format:(Ljava/lang/String;[Ljava/lang/Object;)Ljava/lang/String;
      20: astore_2
      21: aload_0
      22: getfield      #3                  // Field ensureNL:Z
      25: ifeq          57
      28: aload_2
      29: ldc           #7                  // String \n
      31: invokevirtual #8                  // Method java/lang/String.endsWith:(Ljava/lang/String;)Z
      34: ifne          57
      37: new           #9                  // class java/lang/StringBuilder
      40: dup
      41: invokespecial #10                 // Method java/lang/StringBuilder."<init>":()V
      44: aload_2
      45: invokevirtual #11                 // Method java/lang/StringBuilder.append:(Ljava/lang/String;)Ljava/lang/StringBuilder;
      48: ldc           #7                  // String \n
      50: invokevirtual #11                 // Method java/lang/StringBuilder.append:(Ljava/lang/String;)Ljava/lang/StringBuilder;
      53: invokevirtual #12                 // Method java/lang/StringBuilder.toString:()Ljava/lang/String;
      56: astore_2
      57: aload_2
      58: areturn
}
