Compiled from "AbstractDeploymentUploadHandler.java"
public abstract class org.jboss.as.domain.controller.operations.deployment.AbstractDeploymentUploadHandler implements org.jboss.as.controller.OperationStepHandler {
  private static final java.util.Set<org.jboss.as.controller.access.Action$ActionEffect> ACTION_EFFECT_SET;

  private final org.jboss.as.repository.ContentRepository contentRepository;

  protected final org.jboss.as.controller.AttributeDefinition attribute;

  protected org.jboss.as.domain.controller.operations.deployment.AbstractDeploymentUploadHandler(org.jboss.as.repository.ContentRepository, org.jboss.as.controller.AttributeDefinition);
    Code:
       0: aload_0
       1: invokespecial #1                  // Method java/lang/Object."<init>":()V
       4: aload_0
       5: aload_1
       6: putfield      #2                  // Field contentRepository:Lorg/jboss/as/repository/ContentRepository;
       9: aload_0
      10: aload_2
      11: putfield      #3                  // Field attribute:Lorg/jboss/as/controller/AttributeDefinition;
      14: return

  public void execute(org.jboss.as.controller.OperationContext, org.jboss.dmr.ModelNode) throws org.jboss.as.controller.OperationFailedException;
    Code:
       0: aload_0
       1: getfield      #2                  // Field contentRepository:Lorg/jboss/as/repository/ContentRepository;
       4: ifnull        126
       7: aload_1
       8: aload_2
       9: getstatic     #4                  // Field ACTION_EFFECT_SET:Ljava/util/Set;
      12: invokeinterface #5,  3            // InterfaceMethod org/jboss/as/controller/OperationContext.authorize:(Lorg/jboss/dmr/ModelNode;Ljava/util/Set;)Lorg/jboss/as/controller/access/AuthorizationResult;
      17: astore_3
      18: aload_3
      19: invokevirtual #6                  // Method org/jboss/as/controller/access/AuthorizationResult.getDecision:()Lorg/jboss/as/controller/access/AuthorizationResult$Decision;
      22: getstatic     #7                  // Field org/jboss/as/controller/access/AuthorizationResult$Decision.DENY:Lorg/jboss/as/controller/access/AuthorizationResult$Decision;
      25: if_acmpne     59
      28: getstatic     #8                  // Field org/jboss/as/controller/logging/ControllerLogger.ROOT_LOGGER:Lorg/jboss/as/controller/logging/ControllerLogger;
      31: aload_2
      32: ldc           #10                 // String operation
      34: invokevirtual #11                 // Method org/jboss/dmr/ModelNode.get:(Ljava/lang/String;)Lorg/jboss/dmr/ModelNode;
      37: invokevirtual #12                 // Method org/jboss/dmr/ModelNode.asString:()Ljava/lang/String;
      40: aload_2
      41: ldc           #13                 // String address
      43: invokevirtual #11                 // Method org/jboss/dmr/ModelNode.get:(Ljava/lang/String;)Lorg/jboss/dmr/ModelNode;
      46: invokestatic  #14                 // Method org/jboss/as/controller/PathAddress.pathAddress:(Lorg/jboss/dmr/ModelNode;)Lorg/jboss/as/controller/PathAddress;
      49: aload_3
      50: invokevirtual #15                 // Method org/jboss/as/controller/access/AuthorizationResult.getExplanation:()Lorg/jboss/dmr/ModelNode;
      53: invokeinterface #16,  4           // InterfaceMethod org/jboss/as/controller/logging/ControllerLogger.unauthorized:(Ljava/lang/String;Lorg/jboss/as/controller/PathAddress;Lorg/jboss/dmr/ModelNode;)Lorg/jboss/as/controller/UnauthorizedException;
      58: athrow
      59: aload_0
      60: aload_1
      61: aload_2
      62: invokevirtual #17                 // Method getContentInputStream:(Lorg/jboss/as/controller/OperationContext;Lorg/jboss/dmr/ModelNode;)Ljava/io/InputStream;
      65: astore        4
      67: aload_0
      68: getfield      #2                  // Field contentRepository:Lorg/jboss/as/repository/ContentRepository;
      71: aload         4
      73: invokeinterface #18,  2           // InterfaceMethod org/jboss/as/repository/ContentRepository.addContent:(Ljava/io/InputStream;)[B
      78: astore        5
      80: aload_1
      81: invokeinterface #19,  1           // InterfaceMethod org/jboss/as/controller/OperationContext.getResult:()Lorg/jboss/dmr/ModelNode;
      86: aload         5
      88: invokevirtual #20                 // Method org/jboss/dmr/ModelNode.set:([B)Lorg/jboss/dmr/ModelNode;
      91: pop
      92: aload         4
      94: invokestatic  #21                 // Method safeClose:(Ljava/io/InputStream;)V
      97: goto          110
     100: astore        6
     102: aload         4
     104: invokestatic  #21                 // Method safeClose:(Ljava/io/InputStream;)V
     107: aload         6
     109: athrow
     110: goto          126
     113: astore        4
     115: getstatic     #23                 // Field org/jboss/as/domain/controller/logging/DomainControllerLogger.ROOT_LOGGER:Lorg/jboss/as/domain/controller/logging/DomainControllerLogger;
     118: aload         4
     120: invokeinterface #24,  2           // InterfaceMethod org/jboss/as/domain/controller/logging/DomainControllerLogger.caughtIOExceptionUploadingContent:(Ljava/io/IOException;)Lorg/jboss/as/controller/OperationFailedException;
     125: athrow
     126: return
    Exception table:
       from    to  target type
          67    92   100   any
         100   102   100   any
          59   110   113   Class java/io/IOException

  protected abstract java.io.InputStream getContentInputStream(org.jboss.as.controller.OperationContext, org.jboss.dmr.ModelNode) throws org.jboss.as.controller.OperationFailedException;

  private static void safeClose(java.io.InputStream);
    Code:
       0: aload_0
       1: ifnull        21
       4: aload_0
       5: invokevirtual #25                 // Method java/io/InputStream.close:()V
       8: goto          21
      11: astore_1
      12: getstatic     #23                 // Field org/jboss/as/domain/controller/logging/DomainControllerLogger.ROOT_LOGGER:Lorg/jboss/as/domain/controller/logging/DomainControllerLogger;
      15: aload_1
      16: invokeinterface #27,  2           // InterfaceMethod org/jboss/as/domain/controller/logging/DomainControllerLogger.caughtExceptionClosingInputStream:(Ljava/lang/Throwable;)V
      21: return
    Exception table:
       from    to  target type
           4     8    11   Class java/lang/Exception

  static {};
    Code:
       0: getstatic     #28                 // Field org/jboss/as/controller/access/Action$ActionEffect.WRITE_RUNTIME:Lorg/jboss/as/controller/access/Action$ActionEffect;
       3: invokestatic  #29                 // Method java/util/EnumSet.of:(Ljava/lang/Enum;)Ljava/util/EnumSet;
       6: putstatic     #4                  // Field ACTION_EFFECT_SET:Ljava/util/Set;
       9: return
}
