Compiled from "DeploymentRemoveHandler.java"
class org.jboss.as.domain.controller.operations.deployment.DeploymentRemoveHandler$1 implements org.jboss.as.controller.OperationStepHandler {
  final org.jboss.as.controller.PathAddress val$address;

  final java.util.List val$deploymentHashes;

  final org.jboss.as.domain.controller.operations.deployment.DeploymentRemoveHandler this$0;

  org.jboss.as.domain.controller.operations.deployment.DeploymentRemoveHandler$1(org.jboss.as.domain.controller.operations.deployment.DeploymentRemoveHandler, org.jboss.as.controller.PathAddress, java.util.List);
    Code:
       0: aload_0
       1: aload_1
       2: putfield      #1                  // Field this$0:Lorg/jboss/as/domain/controller/operations/deployment/DeploymentRemoveHandler;
       5: aload_0
       6: aload_2
       7: putfield      #2                  // Field val$address:Lorg/jboss/as/controller/PathAddress;
      10: aload_0
      11: aload_3
      12: putfield      #3                  // Field val$deploymentHashes:Ljava/util/List;
      15: aload_0
      16: invokespecial #4                  // Method java/lang/Object."<init>":()V
      19: return

  public void execute(org.jboss.as.controller.OperationContext, org.jboss.dmr.ModelNode) throws org.jboss.as.controller.OperationFailedException;
    Code:
       0: aload_1
       1: new           #5                  // class org/jboss/as/domain/controller/operations/deployment/DeploymentRemoveHandler$1$1
       4: dup
       5: aload_0
       6: invokespecial #6                  // Method org/jboss/as/domain/controller/operations/deployment/DeploymentRemoveHandler$1$1."<init>":(Lorg/jboss/as/domain/controller/operations/deployment/DeploymentRemoveHandler$1;)V
       9: invokeinterface #7,  2            // InterfaceMethod org/jboss/as/controller/OperationContext.completeStep:(Lorg/jboss/as/controller/OperationContext$ResultHandler;)V
      14: return
}
