Compiled from "TicketIssuer.java"
public abstract class org.apache.kerby.kerberos.kerb.server.request.TicketIssuer {
  private static final org.slf4j.Logger LOG;

  private final org.apache.kerby.kerberos.kerb.server.request.KdcRequest kdcRequest;

  public org.apache.kerby.kerberos.kerb.server.request.TicketIssuer(org.apache.kerby.kerberos.kerb.server.request.KdcRequest);
    Code:
       0: aload_0
       1: invokespecial #1                  // Method java/lang/Object."<init>":()V
       4: aload_0
       5: aload_1
       6: putfield      #2                  // Field kdcRequest:Lorg/apache/kerby/kerberos/kerb/server/request/KdcRequest;
       9: return

  protected org.apache.kerby.kerberos.kerb.server.request.KdcRequest getKdcRequest();
    Code:
       0: aload_0
       1: getfield      #2                  // Field kdcRequest:Lorg/apache/kerby/kerberos/kerb/server/request/KdcRequest;
       4: areturn

  public org.apache.kerby.kerberos.kerb.type.ticket.Ticket issueTicket() throws org.apache.kerby.kerberos.kerb.KrbException;
    Code:
       0: aload_0
       1: getfield      #2                  // Field kdcRequest:Lorg/apache/kerby/kerberos/kerb/server/request/KdcRequest;
       4: invokevirtual #3                  // Method org/apache/kerby/kerberos/kerb/server/request/KdcRequest.getKdcReq:()Lorg/apache/kerby/kerberos/kerb/type/kdc/KdcReq;
       7: astore_1
       8: new           #4                  // class org/apache/kerby/kerberos/kerb/type/ticket/Ticket
      11: dup
      12: invokespecial #5                  // Method org/apache/kerby/kerberos/kerb/type/ticket/Ticket."<init>":()V
      15: astore_2
      16: aload_0
      17: invokevirtual #6                  // Method getServerPrincipal:()Lorg/apache/kerby/kerberos/kerb/type/base/PrincipalName;
      20: astore_3
      21: aload_2
      22: aload_3
      23: invokevirtual #7                  // Method org/apache/kerby/kerberos/kerb/type/ticket/Ticket.setSname:(Lorg/apache/kerby/kerberos/kerb/type/base/PrincipalName;)V
      26: aload_1
      27: invokevirtual #8                  // Method org/apache/kerby/kerberos/kerb/type/kdc/KdcReq.getReqBody:()Lorg/apache/kerby/kerberos/kerb/type/kdc/KdcReqBody;
      30: invokevirtual #9                  // Method org/apache/kerby/kerberos/kerb/type/kdc/KdcReqBody.getRealm:()Ljava/lang/String;
      33: astore        4
      35: aload_2
      36: aload         4
      38: invokevirtual #10                 // Method org/apache/kerby/kerberos/kerb/type/ticket/Ticket.setRealm:(Ljava/lang/String;)V
      41: aload_0
      42: invokevirtual #11                 // Method makeEncTicketPart:()Lorg/apache/kerby/kerberos/kerb/type/ticket/EncTicketPart;
      45: astore        5
      47: aload_0
      48: invokevirtual #12                 // Method getTicketEncryptionKey:()Lorg/apache/kerby/kerberos/kerb/type/base/EncryptionKey;
      51: astore        6
      53: aload         5
      55: aload         6
      57: getstatic     #13                 // Field org/apache/kerby/kerberos/kerb/type/base/KeyUsage.KDC_REP_TICKET:Lorg/apache/kerby/kerberos/kerb/type/base/KeyUsage;
      60: invokestatic  #14                 // Method org/apache/kerby/kerberos/kerb/common/EncryptionUtil.seal:(Lorg/apache/kerby/asn1/type/Asn1Encodeable;Lorg/apache/kerby/kerberos/kerb/type/base/EncryptionKey;Lorg/apache/kerby/kerberos/kerb/type/base/KeyUsage;)Lorg/apache/kerby/kerberos/kerb/type/base/EncryptedData;
      63: astore        7
      65: aload_2
      66: aload         7
      68: invokevirtual #15                 // Method org/apache/kerby/kerberos/kerb/type/ticket/Ticket.setEncryptedEncPart:(Lorg/apache/kerby/kerberos/kerb/type/base/EncryptedData;)V
      71: aload_2
      72: aload         5
      74: invokevirtual #16                 // Method org/apache/kerby/kerberos/kerb/type/ticket/Ticket.setEncPart:(Lorg/apache/kerby/kerberos/kerb/type/ticket/EncTicketPart;)V
      77: aload_2
      78: areturn

  public org.apache.kerby.kerberos.kerb.type.ticket.EncTicketPart makeEncTicketPart() throws org.apache.kerby.kerberos.kerb.KrbException;
    Code:
       0: aload_0
       1: getfield      #2                  // Field kdcRequest:Lorg/apache/kerby/kerberos/kerb/server/request/KdcRequest;
       4: invokevirtual #3                  // Method org/apache/kerby/kerberos/kerb/server/request/KdcRequest.getKdcReq:()Lorg/apache/kerby/kerberos/kerb/type/kdc/KdcReq;
       7: astore_1
       8: new           #17                 // class org/apache/kerby/kerberos/kerb/type/ticket/EncTicketPart
      11: dup
      12: invokespecial #18                 // Method org/apache/kerby/kerberos/kerb/type/ticket/EncTicketPart."<init>":()V
      15: astore_2
      16: aload_0
      17: getfield      #2                  // Field kdcRequest:Lorg/apache/kerby/kerberos/kerb/server/request/KdcRequest;
      20: invokevirtual #19                 // Method org/apache/kerby/kerberos/kerb/server/request/KdcRequest.getKdcContext:()Lorg/apache/kerby/kerberos/kerb/server/KdcContext;
      23: invokevirtual #20                 // Method org/apache/kerby/kerberos/kerb/server/KdcContext.getConfig:()Lorg/apache/kerby/kerberos/kerb/server/KdcConfig;
      26: astore_3
      27: new           #21                 // class org/apache/kerby/kerberos/kerb/type/ticket/TicketFlags
      30: dup
      31: invokespecial #22                 // Method org/apache/kerby/kerberos/kerb/type/ticket/TicketFlags."<init>":()V
      34: astore        4
      36: aload_2
      37: aload         4
      39: invokevirtual #23                 // Method org/apache/kerby/kerberos/kerb/type/ticket/EncTicketPart.setFlags:(Lorg/apache/kerby/kerberos/kerb/type/ticket/TicketFlags;)V
      42: aload         4
      44: getstatic     #24                 // Field org/apache/kerby/kerberos/kerb/type/ticket/TicketFlag.INITIAL:Lorg/apache/kerby/kerberos/kerb/type/ticket/TicketFlag;
      47: invokevirtual #25                 // Method org/apache/kerby/kerberos/kerb/type/ticket/TicketFlags.setFlag:(Lorg/apache/kerby/asn1/EnumType;)V
      50: aload_0
      51: getfield      #2                  // Field kdcRequest:Lorg/apache/kerby/kerberos/kerb/server/request/KdcRequest;
      54: invokevirtual #26                 // Method org/apache/kerby/kerberos/kerb/server/request/KdcRequest.isPreAuthenticated:()Z
      57: ifeq          68
      60: aload         4
      62: getstatic     #27                 // Field org/apache/kerby/kerberos/kerb/type/ticket/TicketFlag.PRE_AUTH:Lorg/apache/kerby/kerberos/kerb/type/ticket/TicketFlag;
      65: invokevirtual #25                 // Method org/apache/kerby/kerberos/kerb/type/ticket/TicketFlags.setFlag:(Lorg/apache/kerby/asn1/EnumType;)V
      68: aload_1
      69: invokevirtual #8                  // Method org/apache/kerby/kerberos/kerb/type/kdc/KdcReq.getReqBody:()Lorg/apache/kerby/kerberos/kerb/type/kdc/KdcReqBody;
      72: invokevirtual #28                 // Method org/apache/kerby/kerberos/kerb/type/kdc/KdcReqBody.getKdcOptions:()Lorg/apache/kerby/kerberos/kerb/type/kdc/KdcOptions;
      75: getstatic     #29                 // Field org/apache/kerby/kerberos/kerb/type/kdc/KdcOption.FORWARDABLE:Lorg/apache/kerby/kerberos/kerb/type/kdc/KdcOption;
      78: invokevirtual #30                 // Method org/apache/kerby/kerberos/kerb/type/kdc/KdcOptions.isFlagSet:(Lorg/apache/kerby/asn1/EnumType;)Z
      81: ifeq          120
      84: aload_3
      85: invokevirtual #31                 // Method org/apache/kerby/kerberos/kerb/server/KdcConfig.isForwardableAllowed:()Z
      88: ifne          112
      91: getstatic     #32                 // Field LOG:Lorg/slf4j/Logger;
      94: ldc           #33                 // String Forward is not allowed.
      96: invokeinterface #34,  2           // InterfaceMethod org/slf4j/Logger.warn:(Ljava/lang/String;)V
     101: new           #35                 // class org/apache/kerby/kerberos/kerb/KrbException
     104: dup
     105: getstatic     #36                 // Field org/apache/kerby/kerberos/kerb/KrbErrorCode.KDC_ERR_POLICY:Lorg/apache/kerby/kerberos/kerb/KrbErrorCode;
     108: invokespecial #37                 // Method org/apache/kerby/kerberos/kerb/KrbException."<init>":(Lorg/apache/kerby/kerberos/kerb/KrbErrorCode;)V
     111: athrow
     112: aload         4
     114: getstatic     #38                 // Field org/apache/kerby/kerberos/kerb/type/ticket/TicketFlag.FORWARDABLE:Lorg/apache/kerby/kerberos/kerb/type/ticket/TicketFlag;
     117: invokevirtual #25                 // Method org/apache/kerby/kerberos/kerb/type/ticket/TicketFlags.setFlag:(Lorg/apache/kerby/asn1/EnumType;)V
     120: aload_1
     121: invokevirtual #8                  // Method org/apache/kerby/kerberos/kerb/type/kdc/KdcReq.getReqBody:()Lorg/apache/kerby/kerberos/kerb/type/kdc/KdcReqBody;
     124: invokevirtual #28                 // Method org/apache/kerby/kerberos/kerb/type/kdc/KdcReqBody.getKdcOptions:()Lorg/apache/kerby/kerberos/kerb/type/kdc/KdcOptions;
     127: getstatic     #39                 // Field org/apache/kerby/kerberos/kerb/type/kdc/KdcOption.PROXIABLE:Lorg/apache/kerby/kerberos/kerb/type/kdc/KdcOption;
     130: invokevirtual #30                 // Method org/apache/kerby/kerberos/kerb/type/kdc/KdcOptions.isFlagSet:(Lorg/apache/kerby/asn1/EnumType;)Z
     133: ifeq          172
     136: aload_3
     137: invokevirtual #40                 // Method org/apache/kerby/kerberos/kerb/server/KdcConfig.isProxiableAllowed:()Z
     140: ifne          164
     143: getstatic     #32                 // Field LOG:Lorg/slf4j/Logger;
     146: ldc           #41                 // String Proxy is not allowed.
     148: invokeinterface #34,  2           // InterfaceMethod org/slf4j/Logger.warn:(Ljava/lang/String;)V
     153: new           #35                 // class org/apache/kerby/kerberos/kerb/KrbException
     156: dup
     157: getstatic     #36                 // Field org/apache/kerby/kerberos/kerb/KrbErrorCode.KDC_ERR_POLICY:Lorg/apache/kerby/kerberos/kerb/KrbErrorCode;
     160: invokespecial #37                 // Method org/apache/kerby/kerberos/kerb/KrbException."<init>":(Lorg/apache/kerby/kerberos/kerb/KrbErrorCode;)V
     163: athrow
     164: aload         4
     166: getstatic     #42                 // Field org/apache/kerby/kerberos/kerb/type/ticket/TicketFlag.PROXIABLE:Lorg/apache/kerby/kerberos/kerb/type/ticket/TicketFlag;
     169: invokevirtual #25                 // Method org/apache/kerby/kerberos/kerb/type/ticket/TicketFlags.setFlag:(Lorg/apache/kerby/asn1/EnumType;)V
     172: aload_1
     173: invokevirtual #8                  // Method org/apache/kerby/kerberos/kerb/type/kdc/KdcReq.getReqBody:()Lorg/apache/kerby/kerberos/kerb/type/kdc/KdcReqBody;
     176: invokevirtual #28                 // Method org/apache/kerby/kerberos/kerb/type/kdc/KdcReqBody.getKdcOptions:()Lorg/apache/kerby/kerberos/kerb/type/kdc/KdcOptions;
     179: getstatic     #43                 // Field org/apache/kerby/kerberos/kerb/type/kdc/KdcOption.ALLOW_POSTDATE:Lorg/apache/kerby/kerberos/kerb/type/kdc/KdcOption;
     182: invokevirtual #30                 // Method org/apache/kerby/kerberos/kerb/type/kdc/KdcOptions.isFlagSet:(Lorg/apache/kerby/asn1/EnumType;)Z
     185: ifeq          224
     188: aload_3
     189: invokevirtual #44                 // Method org/apache/kerby/kerberos/kerb/server/KdcConfig.isPostdatedAllowed:()Z
     192: ifne          216
     195: getstatic     #32                 // Field LOG:Lorg/slf4j/Logger;
     198: ldc           #45                 // String Post date is not allowed.
     200: invokeinterface #34,  2           // InterfaceMethod org/slf4j/Logger.warn:(Ljava/lang/String;)V
     205: new           #35                 // class org/apache/kerby/kerberos/kerb/KrbException
     208: dup
     209: getstatic     #36                 // Field org/apache/kerby/kerberos/kerb/KrbErrorCode.KDC_ERR_POLICY:Lorg/apache/kerby/kerberos/kerb/KrbErrorCode;
     212: invokespecial #37                 // Method org/apache/kerby/kerberos/kerb/KrbException."<init>":(Lorg/apache/kerby/kerberos/kerb/KrbErrorCode;)V
     215: athrow
     216: aload         4
     218: getstatic     #46                 // Field org/apache/kerby/kerberos/kerb/type/ticket/TicketFlag.MAY_POSTDATE:Lorg/apache/kerby/kerberos/kerb/type/ticket/TicketFlag;
     221: invokevirtual #25                 // Method org/apache/kerby/kerberos/kerb/type/ticket/TicketFlags.setFlag:(Lorg/apache/kerby/asn1/EnumType;)V
     224: aload_0
     225: getfield      #2                  // Field kdcRequest:Lorg/apache/kerby/kerberos/kerb/server/request/KdcRequest;
     228: invokevirtual #47                 // Method org/apache/kerby/kerberos/kerb/server/request/KdcRequest.getEncryptionType:()Lorg/apache/kerby/kerberos/kerb/type/base/EncryptionType;
     231: invokestatic  #48                 // Method org/apache/kerby/kerberos/kerb/crypto/EncryptionHandler.random2Key:(Lorg/apache/kerby/kerberos/kerb/type/base/EncryptionType;)Lorg/apache/kerby/kerberos/kerb/type/base/EncryptionKey;
     234: astore        5
     236: aload_2
     237: aload         5
     239: invokevirtual #49                 // Method org/apache/kerby/kerberos/kerb/type/ticket/EncTicketPart.setKey:(Lorg/apache/kerby/kerberos/kerb/type/base/EncryptionKey;)V
     242: aload_2
     243: aload_0
     244: invokevirtual #50                 // Method getclientPrincipal:()Lorg/apache/kerby/kerberos/kerb/type/base/PrincipalName;
     247: invokevirtual #51                 // Method org/apache/kerby/kerberos/kerb/type/ticket/EncTicketPart.setCname:(Lorg/apache/kerby/kerberos/kerb/type/base/PrincipalName;)V
     250: aload_2
     251: aload_1
     252: invokevirtual #8                  // Method org/apache/kerby/kerberos/kerb/type/kdc/KdcReq.getReqBody:()Lorg/apache/kerby/kerberos/kerb/type/kdc/KdcReqBody;
     255: invokevirtual #9                  // Method org/apache/kerby/kerberos/kerb/type/kdc/KdcReqBody.getRealm:()Ljava/lang/String;
     258: invokevirtual #52                 // Method org/apache/kerby/kerberos/kerb/type/ticket/EncTicketPart.setCrealm:(Ljava/lang/String;)V
     261: aload_0
     262: invokevirtual #53                 // Method getTransitedEncoding:()Lorg/apache/kerby/kerberos/kerb/type/base/TransitedEncoding;
     265: astore        6
     267: aload_2
     268: aload         6
     270: invokevirtual #54                 // Method org/apache/kerby/kerberos/kerb/type/ticket/EncTicketPart.setTransited:(Lorg/apache/kerby/kerberos/kerb/type/base/TransitedEncoding;)V
     273: aload_1
     274: invokevirtual #8                  // Method org/apache/kerby/kerberos/kerb/type/kdc/KdcReq.getReqBody:()Lorg/apache/kerby/kerberos/kerb/type/kdc/KdcReqBody;
     277: invokevirtual #28                 // Method org/apache/kerby/kerberos/kerb/type/kdc/KdcReqBody.getKdcOptions:()Lorg/apache/kerby/kerberos/kerb/type/kdc/KdcOptions;
     280: astore        7
     282: invokestatic  #55                 // Method org/apache/kerby/kerberos/kerb/type/KerberosTime.now:()Lorg/apache/kerby/kerberos/kerb/type/KerberosTime;
     285: astore        8
     287: aload_2
     288: aload         8
     290: invokevirtual #56                 // Method org/apache/kerby/kerberos/kerb/type/ticket/EncTicketPart.setAuthTime:(Lorg/apache/kerby/kerberos/kerb/type/KerberosTime;)V
     293: aload_1
     294: invokevirtual #8                  // Method org/apache/kerby/kerberos/kerb/type/kdc/KdcReq.getReqBody:()Lorg/apache/kerby/kerberos/kerb/type/kdc/KdcReqBody;
     297: invokevirtual #57                 // Method org/apache/kerby/kerberos/kerb/type/kdc/KdcReqBody.getFrom:()Lorg/apache/kerby/kerberos/kerb/type/KerberosTime;
     300: astore        9
     302: aload         9
     304: ifnull        329
     307: aload         9
     309: aload         8
     311: invokevirtual #58                 // Method org/apache/kerby/kerberos/kerb/type/KerberosTime.lessThan:(Lorg/apache/kerby/kerberos/kerb/type/KerberosTime;)Z
     314: ifne          329
     317: aload         9
     319: aload_3
     320: invokevirtual #59                 // Method org/apache/kerby/kerberos/kerb/server/KdcConfig.getAllowableClockSkew:()J
     323: invokevirtual #60                 // Method org/apache/kerby/kerberos/kerb/type/KerberosTime.isInClockSkew:(J)Z
     326: ifeq          333
     329: aload         8
     331: astore        9
     333: aload         9
     335: aload         8
     337: invokevirtual #61                 // Method org/apache/kerby/kerberos/kerb/type/KerberosTime.greaterThan:(Lorg/apache/kerby/kerberos/kerb/type/KerberosTime;)Z
     340: ifeq          377
     343: aload         9
     345: aload_3
     346: invokevirtual #59                 // Method org/apache/kerby/kerberos/kerb/server/KdcConfig.getAllowableClockSkew:()J
     349: invokevirtual #60                 // Method org/apache/kerby/kerberos/kerb/type/KerberosTime.isInClockSkew:(J)Z
     352: ifne          377
     355: aload         7
     357: getstatic     #62                 // Field org/apache/kerby/kerberos/kerb/type/kdc/KdcOption.POSTDATED:Lorg/apache/kerby/kerberos/kerb/type/kdc/KdcOption;
     360: invokevirtual #30                 // Method org/apache/kerby/kerberos/kerb/type/kdc/KdcOptions.isFlagSet:(Lorg/apache/kerby/asn1/EnumType;)Z
     363: ifne          377
     366: new           #35                 // class org/apache/kerby/kerberos/kerb/KrbException
     369: dup
     370: getstatic     #63                 // Field org/apache/kerby/kerberos/kerb/KrbErrorCode.KDC_ERR_CANNOT_POSTDATE:Lorg/apache/kerby/kerberos/kerb/KrbErrorCode;
     373: invokespecial #37                 // Method org/apache/kerby/kerberos/kerb/KrbException."<init>":(Lorg/apache/kerby/kerberos/kerb/KrbErrorCode;)V
     376: athrow
     377: aload         7
     379: getstatic     #62                 // Field org/apache/kerby/kerberos/kerb/type/kdc/KdcOption.POSTDATED:Lorg/apache/kerby/kerberos/kerb/type/kdc/KdcOption;
     382: invokevirtual #30                 // Method org/apache/kerby/kerberos/kerb/type/kdc/KdcOptions.isFlagSet:(Lorg/apache/kerby/asn1/EnumType;)Z
     385: ifeq          420
     388: aload_3
     389: invokevirtual #44                 // Method org/apache/kerby/kerberos/kerb/server/KdcConfig.isPostdatedAllowed:()Z
     392: ifne          406
     395: new           #35                 // class org/apache/kerby/kerberos/kerb/KrbException
     398: dup
     399: getstatic     #36                 // Field org/apache/kerby/kerberos/kerb/KrbErrorCode.KDC_ERR_POLICY:Lorg/apache/kerby/kerberos/kerb/KrbErrorCode;
     402: invokespecial #37                 // Method org/apache/kerby/kerberos/kerb/KrbException."<init>":(Lorg/apache/kerby/kerberos/kerb/KrbErrorCode;)V
     405: athrow
     406: aload         4
     408: getstatic     #64                 // Field org/apache/kerby/kerberos/kerb/type/ticket/TicketFlag.POSTDATED:Lorg/apache/kerby/kerberos/kerb/type/ticket/TicketFlag;
     411: invokevirtual #25                 // Method org/apache/kerby/kerberos/kerb/type/ticket/TicketFlags.setFlag:(Lorg/apache/kerby/asn1/EnumType;)V
     414: aload_2
     415: aload         9
     417: invokevirtual #65                 // Method org/apache/kerby/kerberos/kerb/type/ticket/EncTicketPart.setStartTime:(Lorg/apache/kerby/kerberos/kerb/type/KerberosTime;)V
     420: aload_1
     421: invokevirtual #8                  // Method org/apache/kerby/kerberos/kerb/type/kdc/KdcReq.getReqBody:()Lorg/apache/kerby/kerberos/kerb/type/kdc/KdcReqBody;
     424: invokevirtual #66                 // Method org/apache/kerby/kerberos/kerb/type/kdc/KdcReqBody.getTill:()Lorg/apache/kerby/kerberos/kerb/type/KerberosTime;
     427: astore        10
     429: aload         10
     431: ifnull        444
     434: aload         10
     436: invokevirtual #67                 // Method org/apache/kerby/kerberos/kerb/type/KerberosTime.getTime:()J
     439: lconst_0
     440: lcmp
     441: ifne          462
     444: aload         9
     446: aload_3
     447: invokevirtual #68                 // Method org/apache/kerby/kerberos/kerb/server/KdcConfig.getMaximumTicketLifetime:()J
     450: ldc2_w        #69                 // long 1000l
     453: lmul
     454: invokevirtual #71                 // Method org/apache/kerby/kerberos/kerb/type/KerberosTime.extend:(J)Lorg/apache/kerby/kerberos/kerb/type/KerberosTime;
     457: astore        10
     459: goto          483
     462: aload         9
     464: aload         10
     466: invokevirtual #61                 // Method org/apache/kerby/kerberos/kerb/type/KerberosTime.greaterThan:(Lorg/apache/kerby/kerberos/kerb/type/KerberosTime;)Z
     469: ifeq          483
     472: new           #35                 // class org/apache/kerby/kerberos/kerb/KrbException
     475: dup
     476: getstatic     #72                 // Field org/apache/kerby/kerberos/kerb/KrbErrorCode.KDC_ERR_NEVER_VALID:Lorg/apache/kerby/kerberos/kerb/KrbErrorCode;
     479: invokespecial #37                 // Method org/apache/kerby/kerberos/kerb/KrbException."<init>":(Lorg/apache/kerby/kerberos/kerb/KrbErrorCode;)V
     482: athrow
     483: aload_2
     484: aload         10
     486: invokevirtual #73                 // Method org/apache/kerby/kerberos/kerb/type/ticket/EncTicketPart.setEndTime:(Lorg/apache/kerby/kerberos/kerb/type/KerberosTime;)V
     489: aload         10
     491: aload         9
     493: invokevirtual #74                 // Method org/apache/kerby/kerberos/kerb/type/KerberosTime.diff:(Lorg/apache/kerby/kerberos/kerb/type/KerberosTime;)J
     496: invokestatic  #75                 // Method java/lang/Math.abs:(J)J
     499: lstore        11
     501: lload         11
     503: aload_3
     504: invokevirtual #76                 // Method org/apache/kerby/kerberos/kerb/server/KdcConfig.getMinimumTicketLifetime:()J
     507: lcmp
     508: ifge          522
     511: new           #35                 // class org/apache/kerby/kerberos/kerb/KrbException
     514: dup
     515: getstatic     #72                 // Field org/apache/kerby/kerberos/kerb/KrbErrorCode.KDC_ERR_NEVER_VALID:Lorg/apache/kerby/kerberos/kerb/KrbErrorCode;
     518: invokespecial #37                 // Method org/apache/kerby/kerberos/kerb/KrbException."<init>":(Lorg/apache/kerby/kerberos/kerb/KrbErrorCode;)V
     521: athrow
     522: aload_1
     523: invokevirtual #8                  // Method org/apache/kerby/kerberos/kerb/type/kdc/KdcReq.getReqBody:()Lorg/apache/kerby/kerberos/kerb/type/kdc/KdcReqBody;
     526: invokevirtual #77                 // Method org/apache/kerby/kerberos/kerb/type/kdc/KdcReqBody.getRtime:()Lorg/apache/kerby/kerberos/kerb/type/KerberosTime;
     529: astore        13
     531: aload         7
     533: getstatic     #78                 // Field org/apache/kerby/kerberos/kerb/type/kdc/KdcOption.RENEWABLE_OK:Lorg/apache/kerby/kerberos/kerb/type/kdc/KdcOption;
     536: invokevirtual #30                 // Method org/apache/kerby/kerberos/kerb/type/kdc/KdcOptions.isFlagSet:(Lorg/apache/kerby/asn1/EnumType;)Z
     539: ifeq          550
     542: aload         7
     544: getstatic     #79                 // Field org/apache/kerby/kerberos/kerb/type/kdc/KdcOption.RENEWABLE:Lorg/apache/kerby/kerberos/kerb/type/kdc/KdcOption;
     547: invokevirtual #80                 // Method org/apache/kerby/kerberos/kerb/type/kdc/KdcOptions.setFlag:(Lorg/apache/kerby/asn1/EnumType;)V
     550: aload         7
     552: getstatic     #79                 // Field org/apache/kerby/kerberos/kerb/type/kdc/KdcOption.RENEWABLE:Lorg/apache/kerby/kerberos/kerb/type/kdc/KdcOption;
     555: invokevirtual #30                 // Method org/apache/kerby/kerberos/kerb/type/kdc/KdcOptions.isFlagSet:(Lorg/apache/kerby/asn1/EnumType;)Z
     558: ifeq          645
     561: aload_3
     562: invokevirtual #81                 // Method org/apache/kerby/kerberos/kerb/server/KdcConfig.isRenewableAllowed:()Z
     565: ifne          579
     568: new           #35                 // class org/apache/kerby/kerberos/kerb/KrbException
     571: dup
     572: getstatic     #36                 // Field org/apache/kerby/kerberos/kerb/KrbErrorCode.KDC_ERR_POLICY:Lorg/apache/kerby/kerberos/kerb/KrbErrorCode;
     575: invokespecial #37                 // Method org/apache/kerby/kerberos/kerb/KrbException."<init>":(Lorg/apache/kerby/kerberos/kerb/KrbErrorCode;)V
     578: athrow
     579: aload         4
     581: getstatic     #82                 // Field org/apache/kerby/kerberos/kerb/type/ticket/TicketFlag.RENEWABLE:Lorg/apache/kerby/kerberos/kerb/type/ticket/TicketFlag;
     584: invokevirtual #25                 // Method org/apache/kerby/kerberos/kerb/type/ticket/TicketFlags.setFlag:(Lorg/apache/kerby/asn1/EnumType;)V
     587: aload         13
     589: ifnull        602
     592: aload         13
     594: invokevirtual #67                 // Method org/apache/kerby/kerberos/kerb/type/KerberosTime.getTime:()J
     597: lconst_0
     598: lcmp
     599: ifne          606
     602: aload         10
     604: astore        13
     606: aload         9
     608: astore        14
     610: aload         14
     612: aload_3
     613: invokevirtual #83                 // Method org/apache/kerby/kerberos/kerb/server/KdcConfig.getMaximumRenewableLifetime:()J
     616: ldc2_w        #69                 // long 1000l
     619: lmul
     620: invokevirtual #71                 // Method org/apache/kerby/kerberos/kerb/type/KerberosTime.extend:(J)Lorg/apache/kerby/kerberos/kerb/type/KerberosTime;
     623: astore        14
     625: aload         13
     627: aload         14
     629: invokevirtual #61                 // Method org/apache/kerby/kerberos/kerb/type/KerberosTime.greaterThan:(Lorg/apache/kerby/kerberos/kerb/type/KerberosTime;)Z
     632: ifeq          639
     635: aload         14
     637: astore        13
     639: aload_2
     640: aload         13
     642: invokevirtual #84                 // Method org/apache/kerby/kerberos/kerb/type/ticket/EncTicketPart.setRenewtill:(Lorg/apache/kerby/kerberos/kerb/type/KerberosTime;)V
     645: aload_1
     646: invokevirtual #8                  // Method org/apache/kerby/kerberos/kerb/type/kdc/KdcReq.getReqBody:()Lorg/apache/kerby/kerberos/kerb/type/kdc/KdcReqBody;
     649: invokevirtual #85                 // Method org/apache/kerby/kerberos/kerb/type/kdc/KdcReqBody.getAddresses:()Lorg/apache/kerby/kerberos/kerb/type/base/HostAddresses;
     652: astore        14
     654: aload         14
     656: ifnull        667
     659: aload         14
     661: invokevirtual #86                 // Method org/apache/kerby/kerberos/kerb/type/base/HostAddresses.isEmpty:()Z
     664: ifeq          685
     667: aload_3
     668: invokevirtual #87                 // Method org/apache/kerby/kerberos/kerb/server/KdcConfig.isEmptyAddressesAllowed:()Z
     671: ifne          691
     674: new           #35                 // class org/apache/kerby/kerberos/kerb/KrbException
     677: dup
     678: getstatic     #36                 // Field org/apache/kerby/kerberos/kerb/KrbErrorCode.KDC_ERR_POLICY:Lorg/apache/kerby/kerberos/kerb/KrbErrorCode;
     681: invokespecial #37                 // Method org/apache/kerby/kerberos/kerb/KrbException."<init>":(Lorg/apache/kerby/kerberos/kerb/KrbErrorCode;)V
     684: athrow
     685: aload_2
     686: aload         14
     688: invokevirtual #88                 // Method org/apache/kerby/kerberos/kerb/type/ticket/EncTicketPart.setClientAddresses:(Lorg/apache/kerby/kerberos/kerb/type/base/HostAddresses;)V
     691: aload_0
     692: aload_0
     693: getfield      #2                  // Field kdcRequest:Lorg/apache/kerby/kerberos/kerb/server/request/KdcRequest;
     696: aload_2
     697: invokevirtual #89                 // Method makeAuthorizationData:(Lorg/apache/kerby/kerberos/kerb/server/request/KdcRequest;Lorg/apache/kerby/kerberos/kerb/type/ticket/EncTicketPart;)Lorg/apache/kerby/kerberos/kerb/type/ad/AuthorizationData;
     700: astore        15
     702: aload         15
     704: ifnull        713
     707: aload_2
     708: aload         15
     710: invokevirtual #90                 // Method org/apache/kerby/kerberos/kerb/type/ticket/EncTicketPart.setAuthorizationData:(Lorg/apache/kerby/kerberos/kerb/type/ad/AuthorizationData;)V
     713: aload_2
     714: areturn

  protected org.apache.kerby.kerberos.kerb.type.ad.AuthorizationData makeAuthorizationData(org.apache.kerby.kerberos.kerb.server.request.KdcRequest, org.apache.kerby.kerberos.kerb.type.ticket.EncTicketPart) throws org.apache.kerby.kerberos.kerb.KrbException;
    Code:
       0: new           #91                 // class org/apache/kerby/kerberos/kerb/type/kdc/KdcClientRequest
       3: dup
       4: invokespecial #92                 // Method org/apache/kerby/kerberos/kerb/type/kdc/KdcClientRequest."<init>":()V
       7: astore_3
       8: aload_3
       9: aload_1
      10: invokevirtual #93                 // Method org/apache/kerby/kerberos/kerb/server/request/KdcRequest.isAnonymous:()Z
      13: invokevirtual #94                 // Method org/apache/kerby/kerberos/kerb/type/kdc/KdcClientRequest.setAnonymous:(Z)V
      16: aload_3
      17: aload_1
      18: invokevirtual #95                 // Method org/apache/kerby/kerberos/kerb/server/request/KdcRequest.getClientAddress:()Ljava/net/InetAddress;
      21: invokevirtual #96                 // Method org/apache/kerby/kerberos/kerb/type/kdc/KdcClientRequest.setClientAddress:(Ljava/net/InetAddress;)V
      24: aload_3
      25: aload_1
      26: invokevirtual #97                 // Method org/apache/kerby/kerberos/kerb/server/request/KdcRequest.getClientKey:()Lorg/apache/kerby/kerberos/kerb/type/base/EncryptionKey;
      29: invokevirtual #98                 // Method org/apache/kerby/kerberos/kerb/type/kdc/KdcClientRequest.setClientKey:(Lorg/apache/kerby/kerberos/kerb/type/base/EncryptionKey;)V
      32: aload_3
      33: aload_1
      34: invokevirtual #99                 // Method org/apache/kerby/kerberos/kerb/server/request/KdcRequest.getClientPrincipal:()Lorg/apache/kerby/kerberos/kerb/type/base/PrincipalName;
      37: invokevirtual #100                // Method org/apache/kerby/kerberos/kerb/type/kdc/KdcClientRequest.setClientPrincipal:(Lorg/apache/kerby/kerberos/kerb/type/base/PrincipalName;)V
      40: aload_3
      41: aload_1
      42: invokevirtual #47                 // Method org/apache/kerby/kerberos/kerb/server/request/KdcRequest.getEncryptionType:()Lorg/apache/kerby/kerberos/kerb/type/base/EncryptionType;
      45: invokevirtual #101                // Method org/apache/kerby/kerberos/kerb/type/kdc/KdcClientRequest.setEncryptionType:(Lorg/apache/kerby/kerberos/kerb/type/base/EncryptionType;)V
      48: aload_3
      49: aload_1
      50: invokevirtual #102                // Method org/apache/kerby/kerberos/kerb/server/request/KdcRequest.isPkinit:()Z
      53: invokevirtual #103                // Method org/apache/kerby/kerberos/kerb/type/kdc/KdcClientRequest.setPkinit:(Z)V
      56: aload_3
      57: aload_1
      58: invokevirtual #26                 // Method org/apache/kerby/kerberos/kerb/server/request/KdcRequest.isPreAuthenticated:()Z
      61: invokevirtual #104                // Method org/apache/kerby/kerberos/kerb/type/kdc/KdcClientRequest.setPreAuthenticated:(Z)V
      64: aload_3
      65: aload_1
      66: invokevirtual #105                // Method org/apache/kerby/kerberos/kerb/server/request/KdcRequest.getToken:()Lorg/apache/kerby/kerberos/kerb/type/base/AuthToken;
      69: invokevirtual #106                // Method org/apache/kerby/kerberos/kerb/type/kdc/KdcClientRequest.setToken:(Lorg/apache/kerby/kerberos/kerb/type/base/AuthToken;)V
      72: aload_3
      73: aload_1
      74: invokevirtual #107                // Method org/apache/kerby/kerberos/kerb/server/request/KdcRequest.isToken:()Z
      77: invokevirtual #108                // Method org/apache/kerby/kerberos/kerb/type/kdc/KdcClientRequest.setToken:(Z)V
      80: aload_0
      81: invokevirtual #109                // Method getKdcContext:()Lorg/apache/kerby/kerberos/kerb/server/KdcContext;
      84: invokevirtual #110                // Method org/apache/kerby/kerberos/kerb/server/KdcContext.getIdentityService:()Lorg/apache/kerby/kerberos/kerb/identity/IdentityService;
      87: aload_3
      88: aload_2
      89: invokeinterface #111,  3          // InterfaceMethod org/apache/kerby/kerberos/kerb/identity/IdentityService.getIdentityAuthorizationData:(Lorg/apache/kerby/kerberos/kerb/type/kdc/KdcClientRequest;Lorg/apache/kerby/kerberos/kerb/type/ticket/EncTicketPart;)Lorg/apache/kerby/kerberos/kerb/type/ad/AuthorizationData;
      94: areturn

  protected org.apache.kerby.kerberos.kerb.server.KdcContext getKdcContext();
    Code:
       0: aload_0
       1: getfield      #2                  // Field kdcRequest:Lorg/apache/kerby/kerberos/kerb/server/request/KdcRequest;
       4: invokevirtual #19                 // Method org/apache/kerby/kerberos/kerb/server/request/KdcRequest.getKdcContext:()Lorg/apache/kerby/kerberos/kerb/server/KdcContext;
       7: areturn

  protected org.apache.kerby.kerberos.kerb.type.kdc.KdcReq getKdcReq();
    Code:
       0: aload_0
       1: getfield      #2                  // Field kdcRequest:Lorg/apache/kerby/kerberos/kerb/server/request/KdcRequest;
       4: invokevirtual #3                  // Method org/apache/kerby/kerberos/kerb/server/request/KdcRequest.getKdcReq:()Lorg/apache/kerby/kerberos/kerb/type/kdc/KdcReq;
       7: areturn

  protected org.apache.kerby.kerberos.kerb.type.base.PrincipalName getclientPrincipal();
    Code:
       0: aload_0
       1: getfield      #2                  // Field kdcRequest:Lorg/apache/kerby/kerberos/kerb/server/request/KdcRequest;
       4: invokevirtual #107                // Method org/apache/kerby/kerberos/kerb/server/request/KdcRequest.isToken:()Z
       7: ifeq          30
      10: new           #112                // class org/apache/kerby/kerberos/kerb/type/base/PrincipalName
      13: dup
      14: aload_0
      15: getfield      #2                  // Field kdcRequest:Lorg/apache/kerby/kerberos/kerb/server/request/KdcRequest;
      18: invokevirtual #105                // Method org/apache/kerby/kerberos/kerb/server/request/KdcRequest.getToken:()Lorg/apache/kerby/kerberos/kerb/type/base/AuthToken;
      21: invokeinterface #113,  1          // InterfaceMethod org/apache/kerby/kerberos/kerb/type/base/AuthToken.getSubject:()Ljava/lang/String;
      26: invokespecial #114                // Method org/apache/kerby/kerberos/kerb/type/base/PrincipalName."<init>":(Ljava/lang/String;)V
      29: areturn
      30: aload_0
      31: invokevirtual #115                // Method getKdcReq:()Lorg/apache/kerby/kerberos/kerb/type/kdc/KdcReq;
      34: invokevirtual #8                  // Method org/apache/kerby/kerberos/kerb/type/kdc/KdcReq.getReqBody:()Lorg/apache/kerby/kerberos/kerb/type/kdc/KdcReqBody;
      37: invokevirtual #116                // Method org/apache/kerby/kerberos/kerb/type/kdc/KdcReqBody.getCname:()Lorg/apache/kerby/kerberos/kerb/type/base/PrincipalName;
      40: astore_1
      41: aload_0
      42: invokevirtual #117                // Method getKdcRequest:()Lorg/apache/kerby/kerberos/kerb/server/request/KdcRequest;
      45: invokevirtual #93                 // Method org/apache/kerby/kerberos/kerb/server/request/KdcRequest.isAnonymous:()Z
      48: ifeq          58
      51: aload_1
      52: getstatic     #118                // Field org/apache/kerby/kerberos/kerb/type/base/NameType.NT_WELLKNOWN:Lorg/apache/kerby/kerberos/kerb/type/base/NameType;
      55: invokevirtual #119                // Method org/apache/kerby/kerberos/kerb/type/base/PrincipalName.setNameType:(Lorg/apache/kerby/kerberos/kerb/type/base/NameType;)V
      58: aload_1
      59: areturn

  protected org.apache.kerby.kerberos.kerb.type.base.PrincipalName getServerPrincipal();
    Code:
       0: aload_0
       1: invokevirtual #115                // Method getKdcReq:()Lorg/apache/kerby/kerberos/kerb/type/kdc/KdcReq;
       4: invokevirtual #8                  // Method org/apache/kerby/kerberos/kerb/type/kdc/KdcReq.getReqBody:()Lorg/apache/kerby/kerberos/kerb/type/kdc/KdcReqBody;
       7: invokevirtual #120                // Method org/apache/kerby/kerberos/kerb/type/kdc/KdcReqBody.getSname:()Lorg/apache/kerby/kerberos/kerb/type/base/PrincipalName;
      10: areturn

  protected org.apache.kerby.kerberos.kerb.type.base.EncryptionType getTicketEncryptionType() throws org.apache.kerby.kerberos.kerb.KrbException;
    Code:
       0: aload_0
       1: getfield      #2                  // Field kdcRequest:Lorg/apache/kerby/kerberos/kerb/server/request/KdcRequest;
       4: invokevirtual #47                 // Method org/apache/kerby/kerberos/kerb/server/request/KdcRequest.getEncryptionType:()Lorg/apache/kerby/kerberos/kerb/type/base/EncryptionType;
       7: astore_1
       8: aload_1
       9: areturn

  protected org.apache.kerby.kerberos.kerb.type.base.EncryptionKey getTicketEncryptionKey() throws org.apache.kerby.kerberos.kerb.KrbException;
    Code:
       0: aload_0
       1: invokevirtual #121                // Method getTicketEncryptionType:()Lorg/apache/kerby/kerberos/kerb/type/base/EncryptionType;
       4: astore_1
       5: aload_0
       6: getfield      #2                  // Field kdcRequest:Lorg/apache/kerby/kerberos/kerb/server/request/KdcRequest;
       9: invokevirtual #122                // Method org/apache/kerby/kerberos/kerb/server/request/KdcRequest.getServerEntry:()Lorg/apache/kerby/kerberos/kerb/identity/KrbIdentity;
      12: invokevirtual #123                // Method org/apache/kerby/kerberos/kerb/identity/KrbIdentity.getKeys:()Ljava/util/Map;
      15: aload_1
      16: invokeinterface #124,  2          // InterfaceMethod java/util/Map.get:(Ljava/lang/Object;)Ljava/lang/Object;
      21: checkcast     #125                // class org/apache/kerby/kerberos/kerb/type/base/EncryptionKey
      24: astore_2
      25: aload_2
      26: areturn

  protected org.apache.kerby.kerberos.kerb.type.base.TransitedEncoding getTransitedEncoding();
    Code:
       0: new           #126                // class org/apache/kerby/kerberos/kerb/type/base/TransitedEncoding
       3: dup
       4: invokespecial #127                // Method org/apache/kerby/kerberos/kerb/type/base/TransitedEncoding."<init>":()V
       7: astore_1
       8: aload_1
       9: getstatic     #128                // Field org/apache/kerby/kerberos/kerb/type/base/TransitedEncodingType.DOMAIN_X500_COMPRESS:Lorg/apache/kerby/kerberos/kerb/type/base/TransitedEncodingType;
      12: invokevirtual #129                // Method org/apache/kerby/kerberos/kerb/type/base/TransitedEncoding.setTrType:(Lorg/apache/kerby/kerberos/kerb/type/base/TransitedEncodingType;)V
      15: iconst_0
      16: newarray       byte
      18: astore_2
      19: aload_1
      20: aload_2
      21: invokevirtual #130                // Method org/apache/kerby/kerberos/kerb/type/base/TransitedEncoding.setContents:([B)V
      24: aload_1
      25: areturn

  static {};
    Code:
       0: ldc_w         #131                // class org/apache/kerby/kerberos/kerb/server/request/TicketIssuer
       3: invokestatic  #132                // Method org/slf4j/LoggerFactory.getLogger:(Ljava/lang/Class;)Lorg/slf4j/Logger;
       6: putstatic     #32                 // Field LOG:Lorg/slf4j/Logger;
       9: return
}
