Compiled from "OperationInputProcessor.java"
public class org.apache.wss4j.stax.impl.processor.input.OperationInputProcessor extends org.apache.xml.security.stax.ext.AbstractInputProcessor {
  public org.apache.wss4j.stax.impl.processor.input.OperationInputProcessor(org.apache.xml.security.stax.ext.XMLSecurityProperties);
    Code:
       0: aload_0
       1: aload_1
       2: invokespecial #1                  // Method org/apache/xml/security/stax/ext/AbstractInputProcessor."<init>":(Lorg/apache/xml/security/stax/ext/XMLSecurityProperties;)V
       5: aload_0
       6: getstatic     #2                  // Field org/apache/xml/security/stax/ext/XMLSecurityConstants$Phase.POSTPROCESSING:Lorg/apache/xml/security/stax/ext/XMLSecurityConstants$Phase;
       9: invokevirtual #3                  // Method setPhase:(Lorg/apache/xml/security/stax/ext/XMLSecurityConstants$Phase;)V
      12: aload_0
      13: ldc_w         #4                  // class org/apache/wss4j/stax/impl/processor/input/SecurityHeaderInputProcessor
      16: invokevirtual #5                  // Method java/lang/Class.getName:()Ljava/lang/String;
      19: invokevirtual #6                  // Method addBeforeProcessor:(Ljava/lang/Object;)V
      22: return

  public org.apache.xml.security.stax.ext.stax.XMLSecEvent processNextHeaderEvent(org.apache.xml.security.stax.ext.InputProcessorChain) throws javax.xml.stream.XMLStreamException, org.apache.xml.security.exceptions.XMLSecurityException;
    Code:
       0: aload_1
       1: invokeinterface #7,  1            // InterfaceMethod org/apache/xml/security/stax/ext/InputProcessorChain.processHeaderEvent:()Lorg/apache/xml/security/stax/ext/stax/XMLSecEvent;
       6: areturn

  public org.apache.xml.security.stax.ext.stax.XMLSecEvent processNextEvent(org.apache.xml.security.stax.ext.InputProcessorChain) throws javax.xml.stream.XMLStreamException, org.apache.xml.security.exceptions.XMLSecurityException;
    Code:
       0: aload_1
       1: invokeinterface #8,  1            // InterfaceMethod org/apache/xml/security/stax/ext/InputProcessorChain.processEvent:()Lorg/apache/xml/security/stax/ext/stax/XMLSecEvent;
       6: astore_2
       7: aload_2
       8: invokeinterface #9,  1            // InterfaceMethod org/apache/xml/security/stax/ext/stax/XMLSecEvent.getEventType:()I
      13: iconst_1
      14: if_icmpne     105
      17: aload_2
      18: invokeinterface #10,  1           // InterfaceMethod org/apache/xml/security/stax/ext/stax/XMLSecEvent.asStartElement:()Lorg/apache/xml/security/stax/ext/stax/XMLSecStartElement;
      23: astore_3
      24: aload_3
      25: invokeinterface #11,  1           // InterfaceMethod org/apache/xml/security/stax/ext/stax/XMLSecStartElement.getElementPath:()Ljava/util/List;
      30: astore        4
      32: aload         4
      34: invokeinterface #12,  1           // InterfaceMethod java/util/List.size:()I
      39: iconst_3
      40: if_icmpne     105
      43: aload         4
      45: invokestatic  #13                 // Method org/apache/wss4j/stax/utils/WSSUtils.isInSOAPBody:(Ljava/util/List;)Z
      48: ifeq          105
      51: new           #14                 // class org/apache/wss4j/stax/securityEvent/OperationSecurityEvent
      54: dup
      55: invokespecial #15                 // Method org/apache/wss4j/stax/securityEvent/OperationSecurityEvent."<init>":()V
      58: astore        5
      60: aload         5
      62: aload_2
      63: invokeinterface #10,  1           // InterfaceMethod org/apache/xml/security/stax/ext/stax/XMLSecEvent.asStartElement:()Lorg/apache/xml/security/stax/ext/stax/XMLSecStartElement;
      68: invokeinterface #16,  1           // InterfaceMethod org/apache/xml/security/stax/ext/stax/XMLSecStartElement.getName:()Ljavax/xml/namespace/QName;
      73: invokevirtual #17                 // Method org/apache/wss4j/stax/securityEvent/OperationSecurityEvent.setOperation:(Ljavax/xml/namespace/QName;)V
      76: aload         5
      78: aconst_null
      79: invokestatic  #18                 // Method org/apache/xml/security/stax/impl/util/IDGenerator.generateID:(Ljava/lang/String;)Ljava/lang/String;
      82: invokevirtual #19                 // Method org/apache/wss4j/stax/securityEvent/OperationSecurityEvent.setCorrelationID:(Ljava/lang/String;)V
      85: aload_1
      86: invokeinterface #20,  1           // InterfaceMethod org/apache/xml/security/stax/ext/InputProcessorChain.getSecurityContext:()Lorg/apache/xml/security/stax/ext/InboundSecurityContext;
      91: aload         5
      93: invokeinterface #21,  2           // InterfaceMethod org/apache/xml/security/stax/ext/InboundSecurityContext.registerSecurityEvent:(Lorg/apache/xml/security/stax/securityEvent/SecurityEvent;)V
      98: aload_1
      99: aload_0
     100: invokeinterface #22,  2           // InterfaceMethod org/apache/xml/security/stax/ext/InputProcessorChain.removeProcessor:(Lorg/apache/xml/security/stax/ext/InputProcessor;)V
     105: aload_2
     106: areturn
}
