Compiled from "ExposedState.java"
public class org.aspectj.weaver.patterns.ExposedState {
  public static final boolean[] NO_ERRONEOUS_VARS;

  public org.aspectj.weaver.ast.Var[] vars;

  private boolean[] erroneousVars;

  private org.aspectj.weaver.ast.Expr aspectInstance;

  private org.aspectj.weaver.UnresolvedType[] expectedVarTypes;

  private org.aspectj.weaver.ResolvedType concreteAspect;

  public org.aspectj.weaver.patterns.ExposedState(int);
    Code:
       0: aload_0
       1: invokespecial #1                  // Method java/lang/Object."<init>":()V
       4: iload_1
       5: ifne          25
       8: aload_0
       9: getstatic     #2                  // Field org/aspectj/weaver/ast/Var.NONE:[Lorg/aspectj/weaver/ast/Var;
      12: putfield      #3                  // Field vars:[Lorg/aspectj/weaver/ast/Var;
      15: aload_0
      16: getstatic     #4                  // Field NO_ERRONEOUS_VARS:[Z
      19: putfield      #5                  // Field erroneousVars:[Z
      22: goto          40
      25: aload_0
      26: iload_1
      27: anewarray     #6                  // class org/aspectj/weaver/ast/Var
      30: putfield      #3                  // Field vars:[Lorg/aspectj/weaver/ast/Var;
      33: aload_0
      34: iload_1
      35: newarray       boolean
      37: putfield      #5                  // Field erroneousVars:[Z
      40: return

  public org.aspectj.weaver.patterns.ExposedState(org.aspectj.weaver.Member);
    Code:
       0: aload_0
       1: aload_1
       2: invokeinterface #7,  1            // InterfaceMethod org/aspectj/weaver/Member.getParameterTypes:()[Lorg/aspectj/weaver/UnresolvedType;
       7: arraylength
       8: invokespecial #8                  // Method "<init>":(I)V
      11: aload_0
      12: aload_1
      13: invokeinterface #7,  1            // InterfaceMethod org/aspectj/weaver/Member.getParameterTypes:()[Lorg/aspectj/weaver/UnresolvedType;
      18: arraylength
      19: anewarray     #9                  // class org/aspectj/weaver/UnresolvedType
      22: putfield      #10                 // Field expectedVarTypes:[Lorg/aspectj/weaver/UnresolvedType;
      25: aload_0
      26: getfield      #10                 // Field expectedVarTypes:[Lorg/aspectj/weaver/UnresolvedType;
      29: arraylength
      30: ifle          66
      33: iconst_0
      34: istore_2
      35: iload_2
      36: aload_1
      37: invokeinterface #7,  1            // InterfaceMethod org/aspectj/weaver/Member.getParameterTypes:()[Lorg/aspectj/weaver/UnresolvedType;
      42: arraylength
      43: if_icmpge     66
      46: aload_0
      47: getfield      #10                 // Field expectedVarTypes:[Lorg/aspectj/weaver/UnresolvedType;
      50: iload_2
      51: aload_1
      52: invokeinterface #7,  1            // InterfaceMethod org/aspectj/weaver/Member.getParameterTypes:()[Lorg/aspectj/weaver/UnresolvedType;
      57: iload_2
      58: aaload
      59: aastore
      60: iinc          2, 1
      63: goto          35
      66: return

  public boolean isFullySetUp();
    Code:
       0: iconst_0
       1: istore_1
       2: iload_1
       3: aload_0
       4: getfield      #3                  // Field vars:[Lorg/aspectj/weaver/ast/Var;
       7: arraylength
       8: if_icmpge     28
      11: aload_0
      12: getfield      #3                  // Field vars:[Lorg/aspectj/weaver/ast/Var;
      15: iload_1
      16: aaload
      17: ifnonnull     22
      20: iconst_0
      21: ireturn
      22: iinc          1, 1
      25: goto          2
      28: iconst_1
      29: ireturn

  public void set(int, org.aspectj.weaver.ast.Var);
    Code:
       0: aload_0
       1: getfield      #10                 // Field expectedVarTypes:[Lorg/aspectj/weaver/UnresolvedType;
       4: ifnull        57
       7: aload_0
       8: getfield      #10                 // Field expectedVarTypes:[Lorg/aspectj/weaver/UnresolvedType;
      11: iload_1
      12: aaload
      13: aload_2
      14: invokevirtual #11                 // Method org/aspectj/weaver/ast/Var.getType:()Lorg/aspectj/weaver/ResolvedType;
      17: invokevirtual #12                 // Method org/aspectj/weaver/ResolvedType.getWorld:()Lorg/aspectj/weaver/World;
      20: invokevirtual #13                 // Method org/aspectj/weaver/UnresolvedType.resolve:(Lorg/aspectj/weaver/World;)Lorg/aspectj/weaver/ResolvedType;
      23: astore_3
      24: aload_3
      25: getstatic     #14                 // Field org/aspectj/weaver/ResolvedType.OBJECT:Lorg/aspectj/weaver/UnresolvedType;
      28: invokevirtual #15                 // Method org/aspectj/weaver/ResolvedType.equals:(Ljava/lang/Object;)Z
      31: ifne          57
      34: aload_3
      35: aload_2
      36: invokevirtual #11                 // Method org/aspectj/weaver/ast/Var.getType:()Lorg/aspectj/weaver/ResolvedType;
      39: invokevirtual #16                 // Method org/aspectj/weaver/ResolvedType.isAssignableFrom:(Lorg/aspectj/weaver/ResolvedType;)Z
      42: ifne          57
      45: aload_2
      46: invokevirtual #11                 // Method org/aspectj/weaver/ast/Var.getType:()Lorg/aspectj/weaver/ResolvedType;
      49: aload_3
      50: invokevirtual #17                 // Method org/aspectj/weaver/ResolvedType.isCoerceableFrom:(Lorg/aspectj/weaver/ResolvedType;)Z
      53: ifne          57
      56: return
      57: aload_0
      58: getfield      #3                  // Field vars:[Lorg/aspectj/weaver/ast/Var;
      61: iload_1
      62: aload_2
      63: aastore
      64: return

  public org.aspectj.weaver.ast.Var get(int);
    Code:
       0: aload_0
       1: getfield      #3                  // Field vars:[Lorg/aspectj/weaver/ast/Var;
       4: iload_1
       5: aaload
       6: areturn

  public int size();
    Code:
       0: aload_0
       1: getfield      #3                  // Field vars:[Lorg/aspectj/weaver/ast/Var;
       4: arraylength
       5: ireturn

  public org.aspectj.weaver.ast.Expr getAspectInstance();
    Code:
       0: aload_0
       1: getfield      #18                 // Field aspectInstance:Lorg/aspectj/weaver/ast/Expr;
       4: areturn

  public void setAspectInstance(org.aspectj.weaver.ast.Expr);
    Code:
       0: aload_0
       1: aload_1
       2: putfield      #18                 // Field aspectInstance:Lorg/aspectj/weaver/ast/Expr;
       5: return

  public java.lang.String toString();
    Code:
       0: new           #19                 // class java/lang/StringBuilder
       3: dup
       4: invokespecial #20                 // Method java/lang/StringBuilder."<init>":()V
       7: ldc           #21                 // String ExposedState(#Vars=
       9: invokevirtual #22                 // Method java/lang/StringBuilder.append:(Ljava/lang/String;)Ljava/lang/StringBuilder;
      12: aload_0
      13: getfield      #3                  // Field vars:[Lorg/aspectj/weaver/ast/Var;
      16: arraylength
      17: invokevirtual #23                 // Method java/lang/StringBuilder.append:(I)Ljava/lang/StringBuilder;
      20: ldc           #24                 // String ,Vars=
      22: invokevirtual #22                 // Method java/lang/StringBuilder.append:(Ljava/lang/String;)Ljava/lang/StringBuilder;
      25: aload_0
      26: getfield      #3                  // Field vars:[Lorg/aspectj/weaver/ast/Var;
      29: invokestatic  #25                 // Method java/util/Arrays.asList:([Ljava/lang/Object;)Ljava/util/List;
      32: invokevirtual #26                 // Method java/lang/StringBuilder.append:(Ljava/lang/Object;)Ljava/lang/StringBuilder;
      35: ldc           #27                 // String ,AspectInstance=
      37: invokevirtual #22                 // Method java/lang/StringBuilder.append:(Ljava/lang/String;)Ljava/lang/StringBuilder;
      40: aload_0
      41: getfield      #18                 // Field aspectInstance:Lorg/aspectj/weaver/ast/Expr;
      44: invokevirtual #26                 // Method java/lang/StringBuilder.append:(Ljava/lang/Object;)Ljava/lang/StringBuilder;
      47: ldc           #28                 // String )
      49: invokevirtual #22                 // Method java/lang/StringBuilder.append:(Ljava/lang/String;)Ljava/lang/StringBuilder;
      52: invokevirtual #29                 // Method java/lang/StringBuilder.toString:()Ljava/lang/String;
      55: areturn

  public void setErroneousVar(int);
    Code:
       0: aload_0
       1: getfield      #5                  // Field erroneousVars:[Z
       4: iload_1
       5: iconst_1
       6: bastore
       7: return

  public boolean isErroneousVar(int);
    Code:
       0: aload_0
       1: getfield      #5                  // Field erroneousVars:[Z
       4: iload_1
       5: baload
       6: ireturn

  public void setConcreteAspect(org.aspectj.weaver.ResolvedType);
    Code:
       0: aload_0
       1: aload_1
       2: putfield      #30                 // Field concreteAspect:Lorg/aspectj/weaver/ResolvedType;
       5: return

  public org.aspectj.weaver.ResolvedType getConcreteAspect();
    Code:
       0: aload_0
       1: getfield      #30                 // Field concreteAspect:Lorg/aspectj/weaver/ResolvedType;
       4: areturn

  static {};
    Code:
       0: iconst_0
       1: newarray       boolean
       3: putstatic     #4                  // Field NO_ERRONEOUS_VARS:[Z
       6: return
}
