Compiled from "RemoteResourceRefresher.java"
public class org.springframework.cloud.client.hypermedia.RemoteResourceRefresher extends org.springframework.scheduling.config.ContextLifecycleScheduledTaskRegistrar {
  private final java.util.List<org.springframework.cloud.client.hypermedia.RemoteResource> discoveredResources;

  private final int fixedDelay;

  private final int initialDelay;

  public org.springframework.cloud.client.hypermedia.RemoteResourceRefresher(java.util.List<org.springframework.cloud.client.hypermedia.RemoteResource>, int, int);
    Code:
       0: aload_0
       1: invokespecial #1                  // Method org/springframework/scheduling/config/ContextLifecycleScheduledTaskRegistrar."<init>":()V
       4: aload_0
       5: aload_1
       6: putfield      #2                  // Field discoveredResources:Ljava/util/List;
       9: aload_0
      10: iload_2
      11: putfield      #3                  // Field fixedDelay:I
      14: aload_0
      15: iload_3
      16: putfield      #4                  // Field initialDelay:I
      19: return

  public void afterPropertiesSet();
    Code:
       0: aload_0
       1: getfield      #2                  // Field discoveredResources:Ljava/util/List;
       4: invokeinterface #5,  1            // InterfaceMethod java/util/List.iterator:()Ljava/util/Iterator;
       9: astore_1
      10: aload_1
      11: invokeinterface #6,  1            // InterfaceMethod java/util/Iterator.hasNext:()Z
      16: ifeq          62
      19: aload_1
      20: invokeinterface #7,  1            // InterfaceMethod java/util/Iterator.next:()Ljava/lang/Object;
      25: checkcast     #8                  // class org/springframework/cloud/client/hypermedia/RemoteResource
      28: astore_2
      29: aload_0
      30: new           #9                  // class org/springframework/scheduling/config/IntervalTask
      33: dup
      34: new           #10                 // class org/springframework/cloud/client/hypermedia/RemoteResourceRefresher$1
      37: dup
      38: aload_0
      39: aload_2
      40: invokespecial #11                 // Method org/springframework/cloud/client/hypermedia/RemoteResourceRefresher$1."<init>":(Lorg/springframework/cloud/client/hypermedia/RemoteResourceRefresher;Lorg/springframework/cloud/client/hypermedia/RemoteResource;)V
      43: aload_0
      44: getfield      #3                  // Field fixedDelay:I
      47: i2l
      48: aload_0
      49: getfield      #4                  // Field initialDelay:I
      52: i2l
      53: invokespecial #12                 // Method org/springframework/scheduling/config/IntervalTask."<init>":(Ljava/lang/Runnable;JJ)V
      56: invokevirtual #13                 // Method addFixedDelayTask:(Lorg/springframework/scheduling/config/IntervalTask;)V
      59: goto          10
      62: aload_0
      63: invokespecial #14                 // Method org/springframework/scheduling/config/ContextLifecycleScheduledTaskRegistrar.afterPropertiesSet:()V
      66: return
}
