Compiled from "SerializerRegistry.java"
final class org.apache.jena.sparql.serializer.SerializerRegistry$2 implements org.apache.jena.sparql.serializer.UpdateSerializerFactory {
  org.apache.jena.sparql.serializer.SerializerRegistry$2();
    Code:
       0: aload_0
       1: invokespecial #1                  // Method java/lang/Object."<init>":()V
       4: return

  public org.apache.jena.sparql.modify.request.UpdateSerializer create(org.apache.jena.query.Syntax, org.apache.jena.sparql.core.Prologue, org.apache.jena.atlas.io.IndentedWriter);
    Code:
       0: aload_2
       1: invokevirtual #2                  // Method org/apache/jena/sparql/core/Prologue.explicitlySetBaseURI:()Z
       4: ifne          23
       7: new           #3                  // class org/apache/jena/sparql/core/Prologue
      10: dup
      11: aload_2
      12: invokevirtual #4                  // Method org/apache/jena/sparql/core/Prologue.getPrefixMapping:()Lorg/apache/jena/shared/PrefixMapping;
      15: aconst_null
      16: checkcast     #5                  // class org/apache/jena/riot/system/IRIResolver
      19: invokespecial #6                  // Method org/apache/jena/sparql/core/Prologue."<init>":(Lorg/apache/jena/shared/PrefixMapping;Lorg/apache/jena/riot/system/IRIResolver;)V
      22: astore_2
      23: new           #7                  // class org/apache/jena/sparql/serializer/SerializationContext
      26: dup
      27: aload_2
      28: invokespecial #8                  // Method org/apache/jena/sparql/serializer/SerializationContext."<init>":(Lorg/apache/jena/sparql/core/Prologue;)V
      31: astore        4
      33: new           #9                  // class org/apache/jena/sparql/modify/request/UpdateWriter
      36: dup
      37: aload_3
      38: aload         4
      40: invokespecial #10                 // Method org/apache/jena/sparql/modify/request/UpdateWriter."<init>":(Lorg/apache/jena/atlas/io/IndentedWriter;Lorg/apache/jena/sparql/serializer/SerializationContext;)V
      43: areturn

  public boolean accept(org.apache.jena.query.Syntax);
    Code:
       0: getstatic     #11                 // Field org/apache/jena/query/Syntax.syntaxARQ:Lorg/apache/jena/query/Syntax;
       3: aload_1
       4: invokevirtual #12                 // Method org/apache/jena/query/Syntax.equals:(Ljava/lang/Object;)Z
       7: ifne          30
      10: getstatic     #13                 // Field org/apache/jena/query/Syntax.syntaxSPARQL_10:Lorg/apache/jena/query/Syntax;
      13: aload_1
      14: invokevirtual #12                 // Method org/apache/jena/query/Syntax.equals:(Ljava/lang/Object;)Z
      17: ifne          30
      20: getstatic     #14                 // Field org/apache/jena/query/Syntax.syntaxSPARQL_11:Lorg/apache/jena/query/Syntax;
      23: aload_1
      24: invokevirtual #12                 // Method org/apache/jena/query/Syntax.equals:(Ljava/lang/Object;)Z
      27: ifeq          34
      30: iconst_1
      31: goto          35
      34: iconst_0
      35: ireturn
}
