Compiled from "AnnotationDescImpl.java"
class org.apache.axis2.jaxws.runtime.description.marshal.impl.AnnotationDescImpl implements org.apache.axis2.jaxws.runtime.description.marshal.AnnotationDesc {
  private boolean _hasXmlRootElement;

  private java.lang.String _XmlRootElementName;

  private java.lang.String _XmlRootElementNamespace;

  private java.lang.Class[] _XmlSeeAlsoClasses;

  private boolean _hasXmlType;

  private java.lang.String _XmlTypeName;

  private java.lang.String _XmlTypeNamespace;

  private org.apache.axis2.jaxws.runtime.description.marshal.impl.AnnotationDescImpl();
    Code:
       0: aload_0
       1: invokespecial #1                  // Method java/lang/Object."<init>":()V
       4: aload_0
       5: iconst_0
       6: putfield      #2                  // Field _hasXmlRootElement:Z
       9: aload_0
      10: aconst_null
      11: putfield      #3                  // Field _XmlRootElementName:Ljava/lang/String;
      14: aload_0
      15: aconst_null
      16: putfield      #4                  // Field _XmlRootElementNamespace:Ljava/lang/String;
      19: aload_0
      20: aconst_null
      21: putfield      #5                  // Field _XmlSeeAlsoClasses:[Ljava/lang/Class;
      24: aload_0
      25: iconst_0
      26: putfield      #6                  // Field _hasXmlType:Z
      29: aload_0
      30: aconst_null
      31: putfield      #7                  // Field _XmlTypeName:Ljava/lang/String;
      34: aload_0
      35: aconst_null
      36: putfield      #8                  // Field _XmlTypeNamespace:Ljava/lang/String;
      39: return

  public boolean hasXmlRootElement();
    Code:
       0: aload_0
       1: getfield      #2                  // Field _hasXmlRootElement:Z
       4: ireturn

  public java.lang.String getXmlRootElementName();
    Code:
       0: aload_0
       1: getfield      #3                  // Field _XmlRootElementName:Ljava/lang/String;
       4: areturn

  public java.lang.String getXmlRootElementNamespace();
    Code:
       0: aload_0
       1: getfield      #4                  // Field _XmlRootElementNamespace:Ljava/lang/String;
       4: areturn

  public boolean hasXmlType();
    Code:
       0: aload_0
       1: getfield      #6                  // Field _hasXmlType:Z
       4: ireturn

  public java.lang.String getXmlTypeName();
    Code:
       0: aload_0
       1: getfield      #7                  // Field _XmlTypeName:Ljava/lang/String;
       4: areturn

  public java.lang.String getXmlTypeNamespace();
    Code:
       0: aload_0
       1: getfield      #8                  // Field _XmlTypeNamespace:Ljava/lang/String;
       4: areturn

  static org.apache.axis2.jaxws.runtime.description.marshal.AnnotationDesc create(java.lang.Class);
    Code:
       0: new           #9                  // class org/apache/axis2/jaxws/runtime/description/marshal/impl/AnnotationDescImpl
       3: dup
       4: invokespecial #10                 // Method "<init>":()V
       7: astore_1
       8: aload_0
       9: ldc           #11                 // class javax/xml/bind/annotation/XmlSeeAlso
      11: invokestatic  #12                 // Method getAnnotation:(Ljava/lang/reflect/AnnotatedElement;Ljava/lang/Class;)Ljava/lang/annotation/Annotation;
      14: checkcast     #11                 // class javax/xml/bind/annotation/XmlSeeAlso
      17: astore_2
      18: aload_2
      19: ifnull        32
      22: aload_1
      23: aload_2
      24: invokeinterface #13,  1           // InterfaceMethod javax/xml/bind/annotation/XmlSeeAlso.value:()[Ljava/lang/Class;
      29: putfield      #5                  // Field _XmlSeeAlsoClasses:[Ljava/lang/Class;
      32: aload_0
      33: invokestatic  #14                 // Method org/apache/axis2/jaxws/utility/XMLRootElementUtil.getXmlRootElementQName:(Ljava/lang/Class;)Ljavax/xml/namespace/QName;
      36: astore_3
      37: aload_3
      38: ifnull        62
      41: aload_1
      42: iconst_1
      43: putfield      #2                  // Field _hasXmlRootElement:Z
      46: aload_1
      47: aload_3
      48: invokevirtual #15                 // Method javax/xml/namespace/QName.getLocalPart:()Ljava/lang/String;
      51: putfield      #3                  // Field _XmlRootElementName:Ljava/lang/String;
      54: aload_1
      55: aload_3
      56: invokevirtual #16                 // Method javax/xml/namespace/QName.getNamespaceURI:()Ljava/lang/String;
      59: putfield      #4                  // Field _XmlRootElementNamespace:Ljava/lang/String;
      62: aload_0
      63: invokestatic  #17                 // Method org/apache/axis2/jaxws/utility/XMLRootElementUtil.getXmlTypeQName:(Ljava/lang/Class;)Ljavax/xml/namespace/QName;
      66: astore_3
      67: aload_3
      68: ifnull        92
      71: aload_1
      72: iconst_1
      73: putfield      #6                  // Field _hasXmlType:Z
      76: aload_1
      77: aload_3
      78: invokevirtual #15                 // Method javax/xml/namespace/QName.getLocalPart:()Ljava/lang/String;
      81: putfield      #7                  // Field _XmlTypeName:Ljava/lang/String;
      84: aload_1
      85: aload_3
      86: invokevirtual #16                 // Method javax/xml/namespace/QName.getNamespaceURI:()Ljava/lang/String;
      89: putfield      #8                  // Field _XmlTypeNamespace:Ljava/lang/String;
      92: aload_1
      93: areturn

  public java.lang.String toString();
    Code:
       0: ldc           #18                 // String \n
       2: astore_1
       3: new           #19                 // class java/lang/StringBuffer
       6: dup
       7: invokespecial #20                 // Method java/lang/StringBuffer."<init>":()V
      10: astore_2
      11: aload_2
      12: ldc           #18                 // String \n
      14: invokevirtual #21                 // Method java/lang/StringBuffer.append:(Ljava/lang/String;)Ljava/lang/StringBuffer;
      17: pop
      18: aload_2
      19: new           #22                 // class java/lang/StringBuilder
      22: dup
      23: invokespecial #23                 // Method java/lang/StringBuilder."<init>":()V
      26: ldc           #24                 // String       @XMLRootElement exists =
      28: invokevirtual #25                 // Method java/lang/StringBuilder.append:(Ljava/lang/String;)Ljava/lang/StringBuilder;
      31: aload_0
      32: invokevirtual #26                 // Method hasXmlRootElement:()Z
      35: invokevirtual #27                 // Method java/lang/StringBuilder.append:(Z)Ljava/lang/StringBuilder;
      38: invokevirtual #28                 // Method java/lang/StringBuilder.toString:()Ljava/lang/String;
      41: invokevirtual #21                 // Method java/lang/StringBuffer.append:(Ljava/lang/String;)Ljava/lang/StringBuffer;
      44: pop
      45: aload_0
      46: invokevirtual #26                 // Method hasXmlRootElement:()Z
      49: ifeq          120
      52: aload_2
      53: ldc           #18                 // String \n
      55: invokevirtual #21                 // Method java/lang/StringBuffer.append:(Ljava/lang/String;)Ljava/lang/StringBuffer;
      58: pop
      59: aload_2
      60: new           #22                 // class java/lang/StringBuilder
      63: dup
      64: invokespecial #23                 // Method java/lang/StringBuilder."<init>":()V
      67: ldc           #29                 // String       @XMLRootElement namespace =
      69: invokevirtual #25                 // Method java/lang/StringBuilder.append:(Ljava/lang/String;)Ljava/lang/StringBuilder;
      72: aload_0
      73: invokevirtual #30                 // Method getXmlRootElementNamespace:()Ljava/lang/String;
      76: invokevirtual #25                 // Method java/lang/StringBuilder.append:(Ljava/lang/String;)Ljava/lang/StringBuilder;
      79: invokevirtual #28                 // Method java/lang/StringBuilder.toString:()Ljava/lang/String;
      82: invokevirtual #21                 // Method java/lang/StringBuffer.append:(Ljava/lang/String;)Ljava/lang/StringBuffer;
      85: pop
      86: aload_2
      87: ldc           #18                 // String \n
      89: invokevirtual #21                 // Method java/lang/StringBuffer.append:(Ljava/lang/String;)Ljava/lang/StringBuffer;
      92: pop
      93: aload_2
      94: new           #22                 // class java/lang/StringBuilder
      97: dup
      98: invokespecial #23                 // Method java/lang/StringBuilder."<init>":()V
     101: ldc           #31                 // String       @XMLRootElement name      =
     103: invokevirtual #25                 // Method java/lang/StringBuilder.append:(Ljava/lang/String;)Ljava/lang/StringBuilder;
     106: aload_0
     107: invokevirtual #32                 // Method getXmlRootElementName:()Ljava/lang/String;
     110: invokevirtual #25                 // Method java/lang/StringBuilder.append:(Ljava/lang/String;)Ljava/lang/StringBuilder;
     113: invokevirtual #28                 // Method java/lang/StringBuilder.toString:()Ljava/lang/String;
     116: invokevirtual #21                 // Method java/lang/StringBuffer.append:(Ljava/lang/String;)Ljava/lang/StringBuffer;
     119: pop
     120: aload_2
     121: ldc           #18                 // String \n
     123: invokevirtual #21                 // Method java/lang/StringBuffer.append:(Ljava/lang/String;)Ljava/lang/StringBuffer;
     126: pop
     127: aload_2
     128: new           #22                 // class java/lang/StringBuilder
     131: dup
     132: invokespecial #23                 // Method java/lang/StringBuilder."<init>":()V
     135: ldc           #33                 // String       @XmlType exists =
     137: invokevirtual #25                 // Method java/lang/StringBuilder.append:(Ljava/lang/String;)Ljava/lang/StringBuilder;
     140: aload_0
     141: invokevirtual #34                 // Method hasXmlType:()Z
     144: invokevirtual #27                 // Method java/lang/StringBuilder.append:(Z)Ljava/lang/StringBuilder;
     147: invokevirtual #28                 // Method java/lang/StringBuilder.toString:()Ljava/lang/String;
     150: invokevirtual #21                 // Method java/lang/StringBuffer.append:(Ljava/lang/String;)Ljava/lang/StringBuffer;
     153: pop
     154: aload_0
     155: invokevirtual #26                 // Method hasXmlRootElement:()Z
     158: ifeq          229
     161: aload_2
     162: ldc           #18                 // String \n
     164: invokevirtual #21                 // Method java/lang/StringBuffer.append:(Ljava/lang/String;)Ljava/lang/StringBuffer;
     167: pop
     168: aload_2
     169: new           #22                 // class java/lang/StringBuilder
     172: dup
     173: invokespecial #23                 // Method java/lang/StringBuilder."<init>":()V
     176: ldc           #35                 // String       @XmlType namespace =
     178: invokevirtual #25                 // Method java/lang/StringBuilder.append:(Ljava/lang/String;)Ljava/lang/StringBuilder;
     181: aload_0
     182: invokevirtual #36                 // Method getXmlTypeNamespace:()Ljava/lang/String;
     185: invokevirtual #25                 // Method java/lang/StringBuilder.append:(Ljava/lang/String;)Ljava/lang/StringBuilder;
     188: invokevirtual #28                 // Method java/lang/StringBuilder.toString:()Ljava/lang/String;
     191: invokevirtual #21                 // Method java/lang/StringBuffer.append:(Ljava/lang/String;)Ljava/lang/StringBuffer;
     194: pop
     195: aload_2
     196: ldc           #18                 // String \n
     198: invokevirtual #21                 // Method java/lang/StringBuffer.append:(Ljava/lang/String;)Ljava/lang/StringBuffer;
     201: pop
     202: aload_2
     203: new           #22                 // class java/lang/StringBuilder
     206: dup
     207: invokespecial #23                 // Method java/lang/StringBuilder."<init>":()V
     210: ldc           #37                 // String       @XmlType name      =
     212: invokevirtual #25                 // Method java/lang/StringBuilder.append:(Ljava/lang/String;)Ljava/lang/StringBuilder;
     215: aload_0
     216: invokevirtual #38                 // Method getXmlTypeName:()Ljava/lang/String;
     219: invokevirtual #25                 // Method java/lang/StringBuilder.append:(Ljava/lang/String;)Ljava/lang/StringBuilder;
     222: invokevirtual #28                 // Method java/lang/StringBuilder.toString:()Ljava/lang/String;
     225: invokevirtual #21                 // Method java/lang/StringBuffer.append:(Ljava/lang/String;)Ljava/lang/StringBuffer;
     228: pop
     229: aload_0
     230: getfield      #5                  // Field _XmlSeeAlsoClasses:[Ljava/lang/Class;
     233: ifnull        292
     236: iconst_0
     237: istore_3
     238: iload_3
     239: aload_0
     240: getfield      #5                  // Field _XmlSeeAlsoClasses:[Ljava/lang/Class;
     243: arraylength
     244: if_icmpge     292
     247: aload_2
     248: ldc           #18                 // String \n
     250: invokevirtual #21                 // Method java/lang/StringBuffer.append:(Ljava/lang/String;)Ljava/lang/StringBuffer;
     253: pop
     254: aload_2
     255: new           #22                 // class java/lang/StringBuilder
     258: dup
     259: invokespecial #23                 // Method java/lang/StringBuilder."<init>":()V
     262: ldc           #39                 // String       @XMLSeeAlso class =
     264: invokevirtual #25                 // Method java/lang/StringBuilder.append:(Ljava/lang/String;)Ljava/lang/StringBuilder;
     267: aload_0
     268: getfield      #5                  // Field _XmlSeeAlsoClasses:[Ljava/lang/Class;
     271: iload_3
     272: aaload
     273: invokevirtual #40                 // Method java/lang/Class.getName:()Ljava/lang/String;
     276: invokevirtual #25                 // Method java/lang/StringBuilder.append:(Ljava/lang/String;)Ljava/lang/StringBuilder;
     279: invokevirtual #28                 // Method java/lang/StringBuilder.toString:()Ljava/lang/String;
     282: invokevirtual #21                 // Method java/lang/StringBuffer.append:(Ljava/lang/String;)Ljava/lang/StringBuffer;
     285: pop
     286: iinc          3, 1
     289: goto          238
     292: aload_2
     293: invokevirtual #41                 // Method java/lang/StringBuffer.toString:()Ljava/lang/String;
     296: areturn

  public java.lang.Class[] getXmlSeeAlsoClasses();
    Code:
       0: aload_0
       1: getfield      #5                  // Field _XmlSeeAlsoClasses:[Ljava/lang/Class;
       4: areturn

  private static java.lang.annotation.Annotation getAnnotation(java.lang.reflect.AnnotatedElement, java.lang.Class);
    Code:
       0: new           #42                 // class org/apache/axis2/jaxws/runtime/description/marshal/impl/AnnotationDescImpl$1
       3: dup
       4: aload_0
       5: aload_1
       6: invokespecial #43                 // Method org/apache/axis2/jaxws/runtime/description/marshal/impl/AnnotationDescImpl$1."<init>":(Ljava/lang/reflect/AnnotatedElement;Ljava/lang/Class;)V
       9: invokestatic  #44                 // Method org/apache/axis2/java/security/AccessController.doPrivileged:(Ljava/security/PrivilegedAction;)Ljava/lang/Object;
      12: checkcast     #45                 // class java/lang/annotation/Annotation
      15: areturn
}
