Compiled from "PackageSetBuilder.java"
public class org.apache.axis2.jaxws.runtime.description.marshal.impl.PackageSetBuilder {
  private static org.apache.commons.logging.Log log;

  private static final java.lang.Class[] noClass;

  private org.apache.axis2.jaxws.runtime.description.marshal.impl.PackageSetBuilder();
    Code:
       0: aload_0
       1: invokespecial #2                  // Method java/lang/Object."<init>":()V
       4: return

  public static java.util.TreeSet<java.lang.String> getPackagesFromSchema(org.apache.axis2.jaxws.description.ServiceDescription);
    Code:
       0: getstatic     #1                  // Field log:Lorg/apache/commons/logging/Log;
       3: invokeinterface #3,  1            // InterfaceMethod org/apache/commons/logging/Log.isDebugEnabled:()Z
       8: ifeq          51
      11: getstatic     #1                  // Field log:Lorg/apache/commons/logging/Log;
      14: ldc           #4                  // String start getPackagesFromSchema
      16: invokeinterface #5,  2            // InterfaceMethod org/apache/commons/logging/Log.debug:(Ljava/lang/Object;)V
      21: getstatic     #1                  // Field log:Lorg/apache/commons/logging/Log;
      24: new           #6                  // class java/lang/StringBuilder
      27: dup
      28: invokespecial #7                  // Method java/lang/StringBuilder."<init>":()V
      31: ldc           #8                  // String ServiceDescription =
      33: invokevirtual #9                  // Method java/lang/StringBuilder.append:(Ljava/lang/String;)Ljava/lang/StringBuilder;
      36: aload_0
      37: invokevirtual #10                 // Method java/lang/Object.toString:()Ljava/lang/String;
      40: invokevirtual #9                  // Method java/lang/StringBuilder.append:(Ljava/lang/String;)Ljava/lang/StringBuilder;
      43: invokevirtual #11                 // Method java/lang/StringBuilder.toString:()Ljava/lang/String;
      46: invokeinterface #5,  2            // InterfaceMethod org/apache/commons/logging/Log.debug:(Ljava/lang/Object;)V
      51: new           #12                 // class java/util/TreeSet
      54: dup
      55: invokespecial #13                 // Method java/util/TreeSet."<init>":()V
      58: astore_1
      59: aload_0
      60: checkcast     #14                 // class org/apache/axis2/jaxws/description/ServiceDescriptionWSDL
      63: astore_2
      64: aload_2
      65: invokeinterface #15,  1           // InterfaceMethod org/apache/axis2/jaxws/description/ServiceDescriptionWSDL.getWSDLDefinition:()Ljavax/wsdl/Definition;
      70: astore_3
      71: aload_0
      72: invokeinterface #16,  1           // InterfaceMethod org/apache/axis2/jaxws/description/ServiceDescription.getEndpointDescriptions_AsCollection:()Ljava/util/Collection;
      77: astore        4
      79: aload         4
      81: ifnull        189
      84: aload         4
      86: invokeinterface #17,  1           // InterfaceMethod java/util/Collection.iterator:()Ljava/util/Iterator;
      91: astore        5
      93: aload         5
      95: invokeinterface #18,  1           // InterfaceMethod java/util/Iterator.hasNext:()Z
     100: ifeq          189
     103: aload         5
     105: invokeinterface #19,  1           // InterfaceMethod java/util/Iterator.next:()Ljava/lang/Object;
     110: checkcast     #20                 // class org/apache/axis2/jaxws/description/EndpointDescription
     113: astore        6
     115: aload_3
     116: ifnonnull     145
     119: aload         6
     121: instanceof    #21                 // class org/apache/axis2/jaxws/description/EndpointDescriptionJava
     124: ifeq          145
     127: aload         6
     129: checkcast     #21                 // class org/apache/axis2/jaxws/description/EndpointDescriptionJava
     132: invokeinterface #22,  1           // InterfaceMethod org/apache/axis2/jaxws/description/EndpointDescriptionJava.getAnnoWebServiceWSDLLocation:()Ljava/lang/String;
     137: astore        7
     139: aload         7
     141: invokestatic  #23                 // Method getWSDLDefinition:(Ljava/lang/String;)Ljavax/wsdl/Definition;
     144: astore_3
     145: aload_3
     146: ifnull        186
     149: new           #24                 // class org/apache/axis2/jaxws/wsdl/impl/SchemaReaderImpl
     152: dup
     153: invokespecial #25                 // Method org/apache/axis2/jaxws/wsdl/impl/SchemaReaderImpl."<init>":()V
     156: astore        7
     158: aload         7
     160: aload_3
     161: invokeinterface #26,  2           // InterfaceMethod org/apache/axis2/jaxws/wsdl/SchemaReader.readPackagesFromSchema:(Ljavax/wsdl/Definition;)Ljava/util/Set;
     166: astore        8
     168: aload_1
     169: aload         8
     171: invokevirtual #27                 // Method java/util/TreeSet.addAll:(Ljava/util/Collection;)Z
     174: pop
     175: goto          186
     178: astore        8
     180: aload         8
     182: invokestatic  #29                 // Method org/apache/axis2/jaxws/ExceptionFactory.makeWebServiceException:(Ljava/lang/Throwable;)Ljavax/xml/ws/WebServiceException;
     185: athrow
     186: goto          93
     189: getstatic     #1                  // Field log:Lorg/apache/commons/logging/Log;
     192: invokeinterface #3,  1            // InterfaceMethod org/apache/commons/logging/Log.isDebugEnabled:()Z
     197: ifeq          210
     200: getstatic     #1                  // Field log:Lorg/apache/commons/logging/Log;
     203: ldc           #30                 // String end getPackagesFromSchema
     205: invokeinterface #5,  2            // InterfaceMethod org/apache/commons/logging/Log.debug:(Ljava/lang/Object;)V
     210: aload_1
     211: areturn
    Exception table:
       from    to  target type
         158   175   178   Class org/apache/axis2/jaxws/wsdl/SchemaReaderException

  public static java.util.TreeSet<java.lang.String> getPackagesFromAnnotations(org.apache.axis2.jaxws.description.ServiceDescription, org.apache.axis2.jaxws.runtime.description.marshal.MarshalServiceRuntimeDescription);
    Code:
       0: getstatic     #1                  // Field log:Lorg/apache/commons/logging/Log;
       3: invokeinterface #3,  1            // InterfaceMethod org/apache/commons/logging/Log.isDebugEnabled:()Z
       8: ifeq          81
      11: getstatic     #1                  // Field log:Lorg/apache/commons/logging/Log;
      14: ldc           #31                 // String start getPackagesFromAnnotations
      16: invokeinterface #5,  2            // InterfaceMethod org/apache/commons/logging/Log.debug:(Ljava/lang/Object;)V
      21: getstatic     #1                  // Field log:Lorg/apache/commons/logging/Log;
      24: new           #6                  // class java/lang/StringBuilder
      27: dup
      28: invokespecial #7                  // Method java/lang/StringBuilder."<init>":()V
      31: ldc           #8                  // String ServiceDescription =
      33: invokevirtual #9                  // Method java/lang/StringBuilder.append:(Ljava/lang/String;)Ljava/lang/StringBuilder;
      36: aload_0
      37: invokevirtual #10                 // Method java/lang/Object.toString:()Ljava/lang/String;
      40: invokevirtual #9                  // Method java/lang/StringBuilder.append:(Ljava/lang/String;)Ljava/lang/StringBuilder;
      43: invokevirtual #11                 // Method java/lang/StringBuilder.toString:()Ljava/lang/String;
      46: invokeinterface #5,  2            // InterfaceMethod org/apache/commons/logging/Log.debug:(Ljava/lang/Object;)V
      51: getstatic     #1                  // Field log:Lorg/apache/commons/logging/Log;
      54: new           #6                  // class java/lang/StringBuilder
      57: dup
      58: invokespecial #7                  // Method java/lang/StringBuilder."<init>":()V
      61: ldc           #32                 // String MarshalServiceRuntimeDescription =
      63: invokevirtual #9                  // Method java/lang/StringBuilder.append:(Ljava/lang/String;)Ljava/lang/StringBuilder;
      66: aload_1
      67: invokevirtual #10                 // Method java/lang/Object.toString:()Ljava/lang/String;
      70: invokevirtual #9                  // Method java/lang/StringBuilder.append:(Ljava/lang/String;)Ljava/lang/StringBuilder;
      73: invokevirtual #11                 // Method java/lang/StringBuilder.toString:()Ljava/lang/String;
      76: invokeinterface #5,  2            // InterfaceMethod org/apache/commons/logging/Log.debug:(Ljava/lang/Object;)V
      81: new           #12                 // class java/util/TreeSet
      84: dup
      85: invokespecial #13                 // Method java/util/TreeSet."<init>":()V
      88: astore_2
      89: aload_0
      90: invokeinterface #16,  1           // InterfaceMethod org/apache/axis2/jaxws/description/ServiceDescription.getEndpointDescriptions_AsCollection:()Ljava/util/Collection;
      95: astore_3
      96: aload_3
      97: ifnull        144
     100: aload_3
     101: invokeinterface #17,  1           // InterfaceMethod java/util/Collection.iterator:()Ljava/util/Iterator;
     106: astore        4
     108: aload         4
     110: invokeinterface #18,  1           // InterfaceMethod java/util/Iterator.hasNext:()Z
     115: ifeq          144
     118: aload         4
     120: invokeinterface #19,  1           // InterfaceMethod java/util/Iterator.next:()Ljava/lang/Object;
     125: checkcast     #20                 // class org/apache/axis2/jaxws/description/EndpointDescription
     128: astore        5
     130: aload_2
     131: aload         5
     133: aload_1
     134: invokestatic  #33                 // Method getPackagesFromAnnotations:(Lorg/apache/axis2/jaxws/description/EndpointDescription;Lorg/apache/axis2/jaxws/runtime/description/marshal/MarshalServiceRuntimeDescription;)Ljava/util/TreeSet;
     137: invokevirtual #27                 // Method java/util/TreeSet.addAll:(Ljava/util/Collection;)Z
     140: pop
     141: goto          108
     144: getstatic     #1                  // Field log:Lorg/apache/commons/logging/Log;
     147: invokeinterface #3,  1            // InterfaceMethod org/apache/commons/logging/Log.isDebugEnabled:()Z
     152: ifeq          165
     155: getstatic     #1                  // Field log:Lorg/apache/commons/logging/Log;
     158: ldc           #34                 // String end getPackagesFromAnnotations
     160: invokeinterface #5,  2            // InterfaceMethod org/apache/commons/logging/Log.debug:(Ljava/lang/Object;)V
     165: aload_2
     166: areturn

  private static java.util.TreeSet<java.lang.String> getPackagesFromAnnotations(org.apache.axis2.jaxws.description.EndpointDescription, org.apache.axis2.jaxws.runtime.description.marshal.MarshalServiceRuntimeDescription);
    Code:
       0: getstatic     #1                  // Field log:Lorg/apache/commons/logging/Log;
       3: invokeinterface #3,  1            // InterfaceMethod org/apache/commons/logging/Log.isDebugEnabled:()Z
       8: ifeq          43
      11: getstatic     #1                  // Field log:Lorg/apache/commons/logging/Log;
      14: new           #6                  // class java/lang/StringBuilder
      17: dup
      18: invokespecial #7                  // Method java/lang/StringBuilder."<init>":()V
      21: ldc           #35                 // String start getPackagesFromAnnotations for EndpointDescription
      23: invokevirtual #9                  // Method java/lang/StringBuilder.append:(Ljava/lang/String;)Ljava/lang/StringBuilder;
      26: aload_0
      27: invokeinterface #36,  1           // InterfaceMethod org/apache/axis2/jaxws/description/EndpointDescription.getName:()Ljava/lang/String;
      32: invokevirtual #9                  // Method java/lang/StringBuilder.append:(Ljava/lang/String;)Ljava/lang/StringBuilder;
      35: invokevirtual #11                 // Method java/lang/StringBuilder.toString:()Ljava/lang/String;
      38: invokeinterface #5,  2            // InterfaceMethod org/apache/commons/logging/Log.debug:(Ljava/lang/Object;)V
      43: new           #12                 // class java/util/TreeSet
      46: dup
      47: invokespecial #13                 // Method java/util/TreeSet."<init>":()V
      50: astore_2
      51: aload_0
      52: invokestatic  #37                 // Method getServiceImplClassName:(Lorg/apache/axis2/jaxws/description/EndpointDescription;)Ljava/lang/String;
      55: astore_3
      56: aload_3
      57: ifnull        136
      60: getstatic     #1                  // Field log:Lorg/apache/commons/logging/Log;
      63: invokeinterface #3,  1            // InterfaceMethod org/apache/commons/logging/Log.isDebugEnabled:()Z
      68: ifeq          98
      71: getstatic     #1                  // Field log:Lorg/apache/commons/logging/Log;
      74: new           #6                  // class java/lang/StringBuilder
      77: dup
      78: invokespecial #7                  // Method java/lang/StringBuilder."<init>":()V
      81: ldc           #38                 // String EndpointDescription implClassName =
      83: invokevirtual #9                  // Method java/lang/StringBuilder.append:(Ljava/lang/String;)Ljava/lang/StringBuilder;
      86: aload_3
      87: invokevirtual #9                  // Method java/lang/StringBuilder.append:(Ljava/lang/String;)Ljava/lang/StringBuilder;
      90: invokevirtual #11                 // Method java/lang/StringBuilder.toString:()Ljava/lang/String;
      93: invokeinterface #5,  2            // InterfaceMethod org/apache/commons/logging/Log.debug:(Ljava/lang/Object;)V
      98: aload_3
      99: invokestatic  #39                 // Method loadClass:(Ljava/lang/String;)Ljava/lang/Class;
     102: astore        4
     104: aload         4
     106: ifnonnull     124
     109: aload_3
     110: aload_0
     111: invokeinterface #40,  1           // InterfaceMethod org/apache/axis2/jaxws/description/EndpointDescription.getAxisService:()Lorg/apache/axis2/description/AxisService;
     116: invokevirtual #41                 // Method org/apache/axis2/description/AxisService.getClassLoader:()Ljava/lang/ClassLoader;
     119: invokestatic  #42                 // Method loadClass:(Ljava/lang/String;Ljava/lang/ClassLoader;)Ljava/lang/Class;
     122: astore        4
     124: aload         4
     126: ifnull        136
     129: aload         4
     131: aload_1
     132: aload_2
     133: invokestatic  #43                 // Method addXmlSeeAlsoPackages:(Ljava/lang/Class;Lorg/apache/axis2/jaxws/runtime/description/marshal/MarshalServiceRuntimeDescription;Ljava/util/TreeSet;)V
     136: aload_0
     137: invokeinterface #44,  1           // InterfaceMethod org/apache/axis2/jaxws/description/EndpointDescription.getEndpointInterfaceDescription:()Lorg/apache/axis2/jaxws/description/EndpointInterfaceDescription;
     142: astore        4
     144: aload         4
     146: ifnull        157
     149: aload_0
     150: aload         4
     152: aload_2
     153: aload_1
     154: invokestatic  #45                 // Method getPackagesFromAnnotations:(Lorg/apache/axis2/jaxws/description/EndpointDescription;Lorg/apache/axis2/jaxws/description/EndpointInterfaceDescription;Ljava/util/TreeSet;Lorg/apache/axis2/jaxws/runtime/description/marshal/MarshalServiceRuntimeDescription;)V
     157: getstatic     #1                  // Field log:Lorg/apache/commons/logging/Log;
     160: invokeinterface #3,  1            // InterfaceMethod org/apache/commons/logging/Log.isDebugEnabled:()Z
     165: ifeq          200
     168: getstatic     #1                  // Field log:Lorg/apache/commons/logging/Log;
     171: new           #6                  // class java/lang/StringBuilder
     174: dup
     175: invokespecial #7                  // Method java/lang/StringBuilder."<init>":()V
     178: ldc           #46                 // String end getPackagesFromAnnotations for EndpointDescription
     180: invokevirtual #9                  // Method java/lang/StringBuilder.append:(Ljava/lang/String;)Ljava/lang/StringBuilder;
     183: aload_0
     184: invokeinterface #36,  1           // InterfaceMethod org/apache/axis2/jaxws/description/EndpointDescription.getName:()Ljava/lang/String;
     189: invokevirtual #9                  // Method java/lang/StringBuilder.append:(Ljava/lang/String;)Ljava/lang/StringBuilder;
     192: invokevirtual #11                 // Method java/lang/StringBuilder.toString:()Ljava/lang/String;
     195: invokeinterface #5,  2            // InterfaceMethod org/apache/commons/logging/Log.debug:(Ljava/lang/Object;)V
     200: aload_2
     201: areturn

  private static void getPackagesFromAnnotations(org.apache.axis2.jaxws.description.EndpointDescription, org.apache.axis2.jaxws.description.EndpointInterfaceDescription, java.util.TreeSet<java.lang.String>, org.apache.axis2.jaxws.runtime.description.marshal.MarshalServiceRuntimeDescription);
    Code:
       0: getstatic     #1                  // Field log:Lorg/apache/commons/logging/Log;
       3: invokeinterface #3,  1            // InterfaceMethod org/apache/commons/logging/Log.isDebugEnabled:()Z
       8: ifeq          43
      11: getstatic     #1                  // Field log:Lorg/apache/commons/logging/Log;
      14: new           #6                  // class java/lang/StringBuilder
      17: dup
      18: invokespecial #7                  // Method java/lang/StringBuilder."<init>":()V
      21: ldc           #47                 // String start getPackagesFromAnnotations for EndpointInterfaceDescription
      23: invokevirtual #9                  // Method java/lang/StringBuilder.append:(Ljava/lang/String;)Ljava/lang/StringBuilder;
      26: aload_1
      27: invokeinterface #48,  1           // InterfaceMethod org/apache/axis2/jaxws/description/EndpointInterfaceDescription.getPortType:()Ljavax/xml/namespace/QName;
      32: invokevirtual #49                 // Method java/lang/StringBuilder.append:(Ljava/lang/Object;)Ljava/lang/StringBuilder;
      35: invokevirtual #11                 // Method java/lang/StringBuilder.toString:()Ljava/lang/String;
      38: invokeinterface #5,  2            // InterfaceMethod org/apache/commons/logging/Log.debug:(Ljava/lang/Object;)V
      43: aload_1
      44: invokeinterface #50,  1           // InterfaceMethod org/apache/axis2/jaxws/description/EndpointInterfaceDescription.getDispatchableOperations:()[Lorg/apache/axis2/jaxws/description/OperationDescription;
      49: astore        4
      51: aload_1
      52: invokeinterface #51,  1           // InterfaceMethod org/apache/axis2/jaxws/description/EndpointInterfaceDescription.getSEIClass:()Ljava/lang/Class;
      57: astore        5
      59: getstatic     #1                  // Field log:Lorg/apache/commons/logging/Log;
      62: invokeinterface #3,  1            // InterfaceMethod org/apache/commons/logging/Log.isDebugEnabled:()Z
      67: ifeq          98
      70: getstatic     #1                  // Field log:Lorg/apache/commons/logging/Log;
      73: new           #6                  // class java/lang/StringBuilder
      76: dup
      77: invokespecial #7                  // Method java/lang/StringBuilder."<init>":()V
      80: ldc           #52                 // String SEI Class is
      82: invokevirtual #9                  // Method java/lang/StringBuilder.append:(Ljava/lang/String;)Ljava/lang/StringBuilder;
      85: aload         5
      87: invokevirtual #49                 // Method java/lang/StringBuilder.append:(Ljava/lang/Object;)Ljava/lang/StringBuilder;
      90: invokevirtual #11                 // Method java/lang/StringBuilder.toString:()Ljava/lang/String;
      93: invokeinterface #5,  2            // InterfaceMethod org/apache/commons/logging/Log.debug:(Ljava/lang/Object;)V
      98: aload         5
     100: ifnonnull     279
     103: aload_0
     104: invokestatic  #37                 // Method getServiceImplClassName:(Lorg/apache/axis2/jaxws/description/EndpointDescription;)Ljava/lang/String;
     107: astore        6
     109: aload         6
     111: ifnull        279
     114: getstatic     #1                  // Field log:Lorg/apache/commons/logging/Log;
     117: invokeinterface #3,  1            // InterfaceMethod org/apache/commons/logging/Log.isDebugEnabled:()Z
     122: ifeq          153
     125: getstatic     #1                  // Field log:Lorg/apache/commons/logging/Log;
     128: new           #6                  // class java/lang/StringBuilder
     131: dup
     132: invokespecial #7                  // Method java/lang/StringBuilder."<init>":()V
     135: ldc           #38                 // String EndpointDescription implClassName =
     137: invokevirtual #9                  // Method java/lang/StringBuilder.append:(Ljava/lang/String;)Ljava/lang/StringBuilder;
     140: aload         6
     142: invokevirtual #9                  // Method java/lang/StringBuilder.append:(Ljava/lang/String;)Ljava/lang/StringBuilder;
     145: invokevirtual #11                 // Method java/lang/StringBuilder.toString:()Ljava/lang/String;
     148: invokeinterface #5,  2            // InterfaceMethod org/apache/commons/logging/Log.debug:(Ljava/lang/Object;)V
     153: aload         6
     155: invokestatic  #39                 // Method loadClass:(Ljava/lang/String;)Ljava/lang/Class;
     158: astore        7
     160: aload         7
     162: ifnonnull     181
     165: aload         6
     167: aload_0
     168: invokeinterface #40,  1           // InterfaceMethod org/apache/axis2/jaxws/description/EndpointDescription.getAxisService:()Lorg/apache/axis2/description/AxisService;
     173: invokevirtual #41                 // Method org/apache/axis2/description/AxisService.getClassLoader:()Ljava/lang/ClassLoader;
     176: invokestatic  #42                 // Method loadClass:(Ljava/lang/String;Ljava/lang/ClassLoader;)Ljava/lang/Class;
     179: astore        7
     181: aload         7
     183: ifnull        279
     186: aload         7
     188: ldc           #53                 // class javax/jws/WebService
     190: invokestatic  #54                 // Method getAnnotation:(Ljava/lang/reflect/AnnotatedElement;Ljava/lang/Class;)Ljava/lang/annotation/Annotation;
     193: checkcast     #53                 // class javax/jws/WebService
     196: astore        8
     198: aload         8
     200: ifnull        279
     203: aload         8
     205: invokeinterface #55,  1           // InterfaceMethod javax/jws/WebService.endpointInterface:()Ljava/lang/String;
     210: astore        9
     212: getstatic     #1                  // Field log:Lorg/apache/commons/logging/Log;
     215: invokeinterface #3,  1            // InterfaceMethod org/apache/commons/logging/Log.isDebugEnabled:()Z
     220: ifeq          251
     223: getstatic     #1                  // Field log:Lorg/apache/commons/logging/Log;
     226: new           #6                  // class java/lang/StringBuilder
     229: dup
     230: invokespecial #7                  // Method java/lang/StringBuilder."<init>":()V
     233: ldc           #56                 // String WebService endpointinterface =
     235: invokevirtual #9                  // Method java/lang/StringBuilder.append:(Ljava/lang/String;)Ljava/lang/StringBuilder;
     238: aload         9
     240: invokevirtual #9                  // Method java/lang/StringBuilder.append:(Ljava/lang/String;)Ljava/lang/StringBuilder;
     243: invokevirtual #11                 // Method java/lang/StringBuilder.toString:()Ljava/lang/String;
     246: invokeinterface #5,  2            // InterfaceMethod org/apache/commons/logging/Log.debug:(Ljava/lang/Object;)V
     251: aload         9
     253: invokestatic  #39                 // Method loadClass:(Ljava/lang/String;)Ljava/lang/Class;
     256: astore        5
     258: aload         5
     260: ifnonnull     279
     263: aload         9
     265: aload_0
     266: invokeinterface #40,  1           // InterfaceMethod org/apache/axis2/jaxws/description/EndpointDescription.getAxisService:()Lorg/apache/axis2/description/AxisService;
     271: invokevirtual #41                 // Method org/apache/axis2/description/AxisService.getClassLoader:()Ljava/lang/ClassLoader;
     274: invokestatic  #42                 // Method loadClass:(Ljava/lang/String;Ljava/lang/ClassLoader;)Ljava/lang/Class;
     277: astore        5
     279: aload         5
     281: aload_3
     282: aload_2
     283: invokestatic  #43                 // Method addXmlSeeAlsoPackages:(Ljava/lang/Class;Lorg/apache/axis2/jaxws/runtime/description/marshal/MarshalServiceRuntimeDescription;Ljava/util/TreeSet;)V
     286: aload         4
     288: ifnull        319
     291: iconst_0
     292: istore        6
     294: iload         6
     296: aload         4
     298: arraylength
     299: if_icmpge     319
     302: aload_0
     303: aload         4
     305: iload         6
     307: aaload
     308: aload_2
     309: aload_3
     310: invokestatic  #57                 // Method getPackagesFromAnnotations:(Lorg/apache/axis2/jaxws/description/EndpointDescription;Lorg/apache/axis2/jaxws/description/OperationDescription;Ljava/util/TreeSet;Lorg/apache/axis2/jaxws/runtime/description/marshal/MarshalServiceRuntimeDescription;)V
     313: iinc          6, 1
     316: goto          294
     319: getstatic     #1                  // Field log:Lorg/apache/commons/logging/Log;
     322: invokeinterface #3,  1            // InterfaceMethod org/apache/commons/logging/Log.isDebugEnabled:()Z
     327: ifeq          362
     330: getstatic     #1                  // Field log:Lorg/apache/commons/logging/Log;
     333: new           #6                  // class java/lang/StringBuilder
     336: dup
     337: invokespecial #7                  // Method java/lang/StringBuilder."<init>":()V
     340: ldc           #58                 // String end getPackagesFromAnnotations for EndpointInterfaceDescription
     342: invokevirtual #9                  // Method java/lang/StringBuilder.append:(Ljava/lang/String;)Ljava/lang/StringBuilder;
     345: aload_1
     346: invokeinterface #48,  1           // InterfaceMethod org/apache/axis2/jaxws/description/EndpointInterfaceDescription.getPortType:()Ljavax/xml/namespace/QName;
     351: invokevirtual #49                 // Method java/lang/StringBuilder.append:(Ljava/lang/Object;)Ljava/lang/StringBuilder;
     354: invokevirtual #11                 // Method java/lang/StringBuilder.toString:()Ljava/lang/String;
     357: invokeinterface #5,  2            // InterfaceMethod org/apache/commons/logging/Log.debug:(Ljava/lang/Object;)V
     362: return

  private static void getPackagesFromAnnotations(org.apache.axis2.jaxws.description.EndpointDescription, org.apache.axis2.jaxws.description.OperationDescription, java.util.TreeSet<java.lang.String>, org.apache.axis2.jaxws.runtime.description.marshal.MarshalServiceRuntimeDescription);
    Code:
       0: aload_1
       1: invokeinterface #59,  1           // InterfaceMethod org/apache/axis2/jaxws/description/OperationDescription.getParameterDescriptions:()[Lorg/apache/axis2/jaxws/description/ParameterDescription;
       6: astore        4
       8: aload         4
      10: ifnull        40
      13: iconst_0
      14: istore        5
      16: iload         5
      18: aload         4
      20: arraylength
      21: if_icmpge     40
      24: aload         4
      26: iload         5
      28: aaload
      29: aload_2
      30: aload_3
      31: invokestatic  #60                 // Method getPackagesFromAnnotations:(Lorg/apache/axis2/jaxws/description/ParameterDescription;Ljava/util/TreeSet;Lorg/apache/axis2/jaxws/runtime/description/marshal/MarshalServiceRuntimeDescription;)V
      34: iinc          5, 1
      37: goto          16
      40: aload_1
      41: invokeinterface #61,  1           // InterfaceMethod org/apache/axis2/jaxws/description/OperationDescription.getFaultDescriptions:()[Lorg/apache/axis2/jaxws/description/FaultDescription;
      46: astore        5
      48: aload         5
      50: ifnull        81
      53: iconst_0
      54: istore        6
      56: iload         6
      58: aload         5
      60: arraylength
      61: if_icmpge     81
      64: aload_0
      65: aload         5
      67: iload         6
      69: aaload
      70: aload_2
      71: aload_3
      72: invokestatic  #62                 // Method getPackagesFromAnnotations:(Lorg/apache/axis2/jaxws/description/EndpointDescription;Lorg/apache/axis2/jaxws/description/FaultDescription;Ljava/util/TreeSet;Lorg/apache/axis2/jaxws/runtime/description/marshal/MarshalServiceRuntimeDescription;)V
      75: iinc          6, 1
      78: goto          56
      81: aload_3
      82: aload_1
      83: invokeinterface #63,  2           // InterfaceMethod org/apache/axis2/jaxws/runtime/description/marshal/MarshalServiceRuntimeDescription.getRequestWrapperClassName:(Lorg/apache/axis2/jaxws/description/OperationDescription;)Ljava/lang/String;
      88: astore        6
      90: aload         6
      92: invokestatic  #64                 // Method getPackageFromClassName:(Ljava/lang/String;)Ljava/lang/String;
      95: astore        7
      97: getstatic     #1                  // Field log:Lorg/apache/commons/logging/Log;
     100: invokeinterface #3,  1            // InterfaceMethod org/apache/commons/logging/Log.isDebugEnabled:()Z
     105: ifeq          136
     108: getstatic     #1                  // Field log:Lorg/apache/commons/logging/Log;
     111: new           #6                  // class java/lang/StringBuilder
     114: dup
     115: invokespecial #7                  // Method java/lang/StringBuilder."<init>":()V
     118: ldc           #65                 // String Package from Request Wrapper annotation =
     120: invokevirtual #9                  // Method java/lang/StringBuilder.append:(Ljava/lang/String;)Ljava/lang/StringBuilder;
     123: aload         7
     125: invokevirtual #9                  // Method java/lang/StringBuilder.append:(Ljava/lang/String;)Ljava/lang/StringBuilder;
     128: invokevirtual #11                 // Method java/lang/StringBuilder.toString:()Ljava/lang/String;
     131: invokeinterface #5,  2            // InterfaceMethod org/apache/commons/logging/Log.debug:(Ljava/lang/Object;)V
     136: aload         7
     138: ifnull        203
     141: aload_2
     142: aload         7
     144: invokevirtual #66                 // Method java/util/TreeSet.add:(Ljava/lang/Object;)Z
     147: pop
     148: aload_2
     149: new           #6                  // class java/lang/StringBuilder
     152: dup
     153: invokespecial #7                  // Method java/lang/StringBuilder."<init>":()V
     156: ldc           #67                 // String @
     158: invokevirtual #9                  // Method java/lang/StringBuilder.append:(Ljava/lang/String;)Ljava/lang/StringBuilder;
     161: aload         7
     163: invokevirtual #9                  // Method java/lang/StringBuilder.append:(Ljava/lang/String;)Ljava/lang/StringBuilder;
     166: invokevirtual #11                 // Method java/lang/StringBuilder.toString:()Ljava/lang/String;
     169: invokevirtual #66                 // Method java/util/TreeSet.add:(Ljava/lang/Object;)Z
     172: pop
     173: aload_2
     174: new           #6                  // class java/lang/StringBuilder
     177: dup
     178: invokespecial #7                  // Method java/lang/StringBuilder."<init>":()V
     181: ldc           #68                 // String [
     183: invokevirtual #9                  // Method java/lang/StringBuilder.append:(Ljava/lang/String;)Ljava/lang/StringBuilder;
     186: aload         6
     188: invokevirtual #9                  // Method java/lang/StringBuilder.append:(Ljava/lang/String;)Ljava/lang/StringBuilder;
     191: ldc           #69                 // String ]
     193: invokevirtual #9                  // Method java/lang/StringBuilder.append:(Ljava/lang/String;)Ljava/lang/StringBuilder;
     196: invokevirtual #11                 // Method java/lang/StringBuilder.toString:()Ljava/lang/String;
     199: invokevirtual #66                 // Method java/util/TreeSet.add:(Ljava/lang/Object;)Z
     202: pop
     203: aload_3
     204: aload_1
     205: invokeinterface #70,  2           // InterfaceMethod org/apache/axis2/jaxws/runtime/description/marshal/MarshalServiceRuntimeDescription.getResponseWrapperClassName:(Lorg/apache/axis2/jaxws/description/OperationDescription;)Ljava/lang/String;
     210: astore        8
     212: aload         8
     214: invokestatic  #64                 // Method getPackageFromClassName:(Ljava/lang/String;)Ljava/lang/String;
     217: astore        9
     219: getstatic     #1                  // Field log:Lorg/apache/commons/logging/Log;
     222: invokeinterface #3,  1            // InterfaceMethod org/apache/commons/logging/Log.isDebugEnabled:()Z
     227: ifeq          258
     230: getstatic     #1                  // Field log:Lorg/apache/commons/logging/Log;
     233: new           #6                  // class java/lang/StringBuilder
     236: dup
     237: invokespecial #7                  // Method java/lang/StringBuilder."<init>":()V
     240: ldc           #71                 // String Package from Response Wrapper annotation =
     242: invokevirtual #9                  // Method java/lang/StringBuilder.append:(Ljava/lang/String;)Ljava/lang/StringBuilder;
     245: aload         9
     247: invokevirtual #9                  // Method java/lang/StringBuilder.append:(Ljava/lang/String;)Ljava/lang/StringBuilder;
     250: invokevirtual #11                 // Method java/lang/StringBuilder.toString:()Ljava/lang/String;
     253: invokeinterface #5,  2            // InterfaceMethod org/apache/commons/logging/Log.debug:(Ljava/lang/Object;)V
     258: aload         9
     260: ifnull        325
     263: aload_2
     264: aload         9
     266: invokevirtual #66                 // Method java/util/TreeSet.add:(Ljava/lang/Object;)Z
     269: pop
     270: aload_2
     271: new           #6                  // class java/lang/StringBuilder
     274: dup
     275: invokespecial #7                  // Method java/lang/StringBuilder."<init>":()V
     278: ldc           #67                 // String @
     280: invokevirtual #9                  // Method java/lang/StringBuilder.append:(Ljava/lang/String;)Ljava/lang/StringBuilder;
     283: aload         9
     285: invokevirtual #9                  // Method java/lang/StringBuilder.append:(Ljava/lang/String;)Ljava/lang/StringBuilder;
     288: invokevirtual #11                 // Method java/lang/StringBuilder.toString:()Ljava/lang/String;
     291: invokevirtual #66                 // Method java/util/TreeSet.add:(Ljava/lang/Object;)Z
     294: pop
     295: aload_2
     296: new           #6                  // class java/lang/StringBuilder
     299: dup
     300: invokespecial #7                  // Method java/lang/StringBuilder."<init>":()V
     303: ldc           #68                 // String [
     305: invokevirtual #9                  // Method java/lang/StringBuilder.append:(Ljava/lang/String;)Ljava/lang/StringBuilder;
     308: aload         8
     310: invokevirtual #9                  // Method java/lang/StringBuilder.append:(Ljava/lang/String;)Ljava/lang/StringBuilder;
     313: ldc           #69                 // String ]
     315: invokevirtual #9                  // Method java/lang/StringBuilder.append:(Ljava/lang/String;)Ljava/lang/StringBuilder;
     318: invokevirtual #11                 // Method java/lang/StringBuilder.toString:()Ljava/lang/String;
     321: invokevirtual #66                 // Method java/util/TreeSet.add:(Ljava/lang/Object;)Z
     324: pop
     325: aload_1
     326: invokeinterface #72,  1           // InterfaceMethod org/apache/axis2/jaxws/description/OperationDescription.getRequestWrapperTargetNamespace:()Ljava/lang/String;
     331: astore        10
     333: aload         10
     335: ifnull        399
     338: aload         10
     340: invokevirtual #73                 // Method java/lang/String.length:()I
     343: ifle          399
     346: getstatic     #1                  // Field log:Lorg/apache/commons/logging/Log;
     349: invokeinterface #3,  1            // InterfaceMethod org/apache/commons/logging/Log.isDebugEnabled:()Z
     354: ifeq          385
     357: getstatic     #1                  // Field log:Lorg/apache/commons/logging/Log;
     360: new           #6                  // class java/lang/StringBuilder
     363: dup
     364: invokespecial #7                  // Method java/lang/StringBuilder."<init>":()V
     367: ldc           #74                 // String TargetNamespace from Request Wrapper annotation =
     369: invokevirtual #9                  // Method java/lang/StringBuilder.append:(Ljava/lang/String;)Ljava/lang/StringBuilder;
     372: aload         10
     374: invokevirtual #9                  // Method java/lang/StringBuilder.append:(Ljava/lang/String;)Ljava/lang/StringBuilder;
     377: invokevirtual #11                 // Method java/lang/StringBuilder.toString:()Ljava/lang/String;
     380: invokeinterface #5,  2            // InterfaceMethod org/apache/commons/logging/Log.debug:(Ljava/lang/Object;)V
     385: aload         10
     387: invokestatic  #75                 // Method makePackages:(Ljava/lang/String;)Ljava/util/List;
     390: astore        11
     392: aload_2
     393: aload         11
     395: invokevirtual #27                 // Method java/util/TreeSet.addAll:(Ljava/util/Collection;)Z
     398: pop
     399: aload_1
     400: invokeinterface #76,  1           // InterfaceMethod org/apache/axis2/jaxws/description/OperationDescription.getResponseWrapperTargetNamespace:()Ljava/lang/String;
     405: astore        10
     407: aload         10
     409: ifnull        473
     412: aload         10
     414: invokevirtual #73                 // Method java/lang/String.length:()I
     417: ifle          473
     420: getstatic     #1                  // Field log:Lorg/apache/commons/logging/Log;
     423: invokeinterface #3,  1            // InterfaceMethod org/apache/commons/logging/Log.isDebugEnabled:()Z
     428: ifeq          459
     431: getstatic     #1                  // Field log:Lorg/apache/commons/logging/Log;
     434: new           #6                  // class java/lang/StringBuilder
     437: dup
     438: invokespecial #7                  // Method java/lang/StringBuilder."<init>":()V
     441: ldc           #77                 // String TargetNamespace from Response Wrapper annotation =
     443: invokevirtual #9                  // Method java/lang/StringBuilder.append:(Ljava/lang/String;)Ljava/lang/StringBuilder;
     446: aload         10
     448: invokevirtual #9                  // Method java/lang/StringBuilder.append:(Ljava/lang/String;)Ljava/lang/StringBuilder;
     451: invokevirtual #11                 // Method java/lang/StringBuilder.toString:()Ljava/lang/String;
     454: invokeinterface #5,  2            // InterfaceMethod org/apache/commons/logging/Log.debug:(Ljava/lang/Object;)V
     459: aload         10
     461: invokestatic  #75                 // Method makePackages:(Ljava/lang/String;)Ljava/util/List;
     464: astore        11
     466: aload_2
     467: aload         11
     469: invokevirtual #27                 // Method java/util/TreeSet.addAll:(Ljava/util/Collection;)Z
     472: pop
     473: aload_1
     474: aload_3
     475: invokestatic  #78                 // Method getMethod:(Lorg/apache/axis2/jaxws/description/OperationDescription;Lorg/apache/axis2/jaxws/runtime/description/marshal/MarshalServiceRuntimeDescription;)Ljava/lang/reflect/Method;
     478: astore        11
     480: getstatic     #1                  // Field log:Lorg/apache/commons/logging/Log;
     483: invokeinterface #3,  1            // InterfaceMethod org/apache/commons/logging/Log.isDebugEnabled:()Z
     488: ifeq          519
     491: getstatic     #1                  // Field log:Lorg/apache/commons/logging/Log;
     494: new           #6                  // class java/lang/StringBuilder
     497: dup
     498: invokespecial #7                  // Method java/lang/StringBuilder."<init>":()V
     501: ldc           #79                 // String Method obtained:
     503: invokevirtual #9                  // Method java/lang/StringBuilder.append:(Ljava/lang/String;)Ljava/lang/StringBuilder;
     506: aload         11
     508: invokevirtual #49                 // Method java/lang/StringBuilder.append:(Ljava/lang/Object;)Ljava/lang/StringBuilder;
     511: invokevirtual #11                 // Method java/lang/StringBuilder.toString:()Ljava/lang/String;
     514: invokeinterface #5,  2            // InterfaceMethod org/apache/commons/logging/Log.debug:(Ljava/lang/Object;)V
     519: getstatic     #1                  // Field log:Lorg/apache/commons/logging/Log;
     522: invokeinterface #3,  1            // InterfaceMethod org/apache/commons/logging/Log.isDebugEnabled:()Z
     527: ifeq          540
     530: getstatic     #1                  // Field log:Lorg/apache/commons/logging/Log;
     533: ldc           #80                 // String Collect the packages of the parameters
     535: invokeinterface #5,  2            // InterfaceMethod org/apache/commons/logging/Log.debug:(Ljava/lang/Object;)V
     540: aload_2
     541: aload_1
     542: invokestatic  #81                 // Method addPackagesFromParameters:(Ljava/util/TreeSet;Lorg/apache/axis2/jaxws/description/OperationDescription;)V
     545: aload         11
     547: ifnull        556
     550: aload_2
     551: aload         11
     553: invokestatic  #82                 // Method addPackagesFromParameters:(Ljava/util/TreeSet;Ljava/lang/reflect/Method;)V
     556: aload_1
     557: invokeinterface #83,  1           // InterfaceMethod org/apache/axis2/jaxws/description/OperationDescription.getResultActualType:()Ljava/lang/Class;
     562: astore        12
     564: aload         12
     566: ifnull        711
     569: aload         12
     571: getstatic     #84                 // Field java/lang/Void.TYPE:Ljava/lang/Class;
     574: if_acmpeq     711
     577: aload         12
     579: ldc           #85                 // class java/lang/Void
     581: if_acmpeq     711
     584: aload         12
     586: invokestatic  #86                 // Method getPackageFromClass:(Ljava/lang/Class;)Ljava/lang/String;
     589: astore        13
     591: getstatic     #1                  // Field log:Lorg/apache/commons/logging/Log;
     594: invokeinterface #3,  1            // InterfaceMethod org/apache/commons/logging/Log.isDebugEnabled:()Z
     599: ifeq          630
     602: getstatic     #1                  // Field log:Lorg/apache/commons/logging/Log;
     605: new           #6                  // class java/lang/StringBuilder
     608: dup
     609: invokespecial #7                  // Method java/lang/StringBuilder."<init>":()V
     612: ldc           #87                 // String Package from Return Type =
     614: invokevirtual #9                  // Method java/lang/StringBuilder.append:(Ljava/lang/String;)Ljava/lang/StringBuilder;
     617: aload         13
     619: invokevirtual #9                  // Method java/lang/StringBuilder.append:(Ljava/lang/String;)Ljava/lang/StringBuilder;
     622: invokevirtual #11                 // Method java/lang/StringBuilder.toString:()Ljava/lang/String;
     625: invokeinterface #5,  2            // InterfaceMethod org/apache/commons/logging/Log.debug:(Ljava/lang/Object;)V
     630: aload         13
     632: ifnull        700
     635: aload_2
     636: aload         13
     638: invokevirtual #66                 // Method java/util/TreeSet.add:(Ljava/lang/Object;)Z
     641: pop
     642: aload_2
     643: new           #6                  // class java/lang/StringBuilder
     646: dup
     647: invokespecial #7                  // Method java/lang/StringBuilder."<init>":()V
     650: ldc           #67                 // String @
     652: invokevirtual #9                  // Method java/lang/StringBuilder.append:(Ljava/lang/String;)Ljava/lang/StringBuilder;
     655: aload         13
     657: invokevirtual #9                  // Method java/lang/StringBuilder.append:(Ljava/lang/String;)Ljava/lang/StringBuilder;
     660: invokevirtual #11                 // Method java/lang/StringBuilder.toString:()Ljava/lang/String;
     663: invokevirtual #66                 // Method java/util/TreeSet.add:(Ljava/lang/Object;)Z
     666: pop
     667: aload_2
     668: new           #6                  // class java/lang/StringBuilder
     671: dup
     672: invokespecial #7                  // Method java/lang/StringBuilder."<init>":()V
     675: ldc           #68                 // String [
     677: invokevirtual #9                  // Method java/lang/StringBuilder.append:(Ljava/lang/String;)Ljava/lang/StringBuilder;
     680: aload         12
     682: invokevirtual #88                 // Method java/lang/Class.getCanonicalName:()Ljava/lang/String;
     685: invokevirtual #9                  // Method java/lang/StringBuilder.append:(Ljava/lang/String;)Ljava/lang/StringBuilder;
     688: ldc           #69                 // String ]
     690: invokevirtual #9                  // Method java/lang/StringBuilder.append:(Ljava/lang/String;)Ljava/lang/StringBuilder;
     693: invokevirtual #11                 // Method java/lang/StringBuilder.toString:()Ljava/lang/String;
     696: invokevirtual #66                 // Method java/util/TreeSet.add:(Ljava/lang/Object;)Z
     699: pop
     700: aload         11
     702: ifnull        711
     705: aload_2
     706: aload         11
     708: invokestatic  #89                 // Method addPackagesFromReturn:(Ljava/util/TreeSet;Ljava/lang/reflect/Method;)V
     711: return

  private static java.lang.reflect.Method getMethod(org.apache.axis2.jaxws.description.OperationDescription, org.apache.axis2.jaxws.runtime.description.marshal.MarshalServiceRuntimeDescription);
    Code:
       0: aconst_null
       1: astore_2
       2: aload_1
       3: aload_0
       4: invokeinterface #90,  2           // InterfaceMethod org/apache/axis2/jaxws/runtime/description/marshal/MarshalServiceRuntimeDescription.getMethod:(Lorg/apache/axis2/jaxws/description/OperationDescription;)Ljava/lang/reflect/Method;
       9: astore_2
      10: goto          52
      13: astore_3
      14: getstatic     #1                  // Field log:Lorg/apache/commons/logging/Log;
      17: invokeinterface #3,  1            // InterfaceMethod org/apache/commons/logging/Log.isDebugEnabled:()Z
      22: ifeq          52
      25: getstatic     #1                  // Field log:Lorg/apache/commons/logging/Log;
      28: new           #6                  // class java/lang/StringBuilder
      31: dup
      32: invokespecial #7                  // Method java/lang/StringBuilder."<init>":()V
      35: ldc           #92                 // String Method could not be obtained due to
      37: invokevirtual #9                  // Method java/lang/StringBuilder.append:(Ljava/lang/String;)Ljava/lang/StringBuilder;
      40: aload_3
      41: invokevirtual #49                 // Method java/lang/StringBuilder.append:(Ljava/lang/Object;)Ljava/lang/StringBuilder;
      44: invokevirtual #11                 // Method java/lang/StringBuilder.toString:()Ljava/lang/String;
      47: invokeinterface #5,  2            // InterfaceMethod org/apache/commons/logging/Log.debug:(Ljava/lang/Object;)V
      52: aload_2
      53: areturn
    Exception table:
       from    to  target type
           2    10    13   Class java/lang/Throwable

  private static void addPackagesFromParameters(java.util.TreeSet<java.lang.String>, java.lang.reflect.Method);
    Code:
       0: getstatic     #1                  // Field log:Lorg/apache/commons/logging/Log;
       3: invokeinterface #3,  1            // InterfaceMethod org/apache/commons/logging/Log.isDebugEnabled:()Z
       8: ifeq          38
      11: getstatic     #1                  // Field log:Lorg/apache/commons/logging/Log;
      14: new           #6                  // class java/lang/StringBuilder
      17: dup
      18: invokespecial #7                  // Method java/lang/StringBuilder."<init>":()V
      21: ldc           #93                 // String enter addPackagesFromParameters for
      23: invokevirtual #9                  // Method java/lang/StringBuilder.append:(Ljava/lang/String;)Ljava/lang/StringBuilder;
      26: aload_1
      27: invokevirtual #49                 // Method java/lang/StringBuilder.append:(Ljava/lang/Object;)Ljava/lang/StringBuilder;
      30: invokevirtual #11                 // Method java/lang/StringBuilder.toString:()Ljava/lang/String;
      33: invokeinterface #5,  2            // InterfaceMethod org/apache/commons/logging/Log.debug:(Ljava/lang/Object;)V
      38: aload_1
      39: ifnull        93
      42: new           #94                 // class java/util/HashSet
      45: dup
      46: invokespecial #95                 // Method java/util/HashSet."<init>":()V
      49: astore_2
      50: aload_1
      51: invokevirtual #96                 // Method java/lang/reflect/Method.getGenericParameterTypes:()[Ljava/lang/reflect/Type;
      54: astore_3
      55: aload_3
      56: arraylength
      57: istore        4
      59: iconst_0
      60: istore        5
      62: iload         5
      64: iload         4
      66: if_icmpge     88
      69: aload_3
      70: iload         5
      72: aaload
      73: astore        6
      75: aload         6
      77: aload_2
      78: invokestatic  #97                 // Method org/apache/axis2/jaxws/utility/ClassUtils.getClasses:(Ljava/lang/reflect/Type;Ljava/util/Set;)Ljava/util/Set;
      81: astore_2
      82: iinc          5, 1
      85: goto          62
      88: aload_2
      89: aload_0
      90: invokestatic  #98                 // Method addClassesToPackageSet:(Ljava/util/Set;Ljava/util/TreeSet;)V
      93: goto          154
      96: astore_2
      97: getstatic     #1                  // Field log:Lorg/apache/commons/logging/Log;
     100: invokeinterface #3,  1            // InterfaceMethod org/apache/commons/logging/Log.isDebugEnabled:()Z
     105: ifeq          154
     108: getstatic     #1                  // Field log:Lorg/apache/commons/logging/Log;
     111: new           #6                  // class java/lang/StringBuilder
     114: dup
     115: invokespecial #7                  // Method java/lang/StringBuilder."<init>":()V
     118: ldc           #99                 // String Could not reflect the information on method
     120: invokevirtual #9                  // Method java/lang/StringBuilder.append:(Ljava/lang/String;)Ljava/lang/StringBuilder;
     123: aload_1
     124: invokevirtual #49                 // Method java/lang/StringBuilder.append:(Ljava/lang/Object;)Ljava/lang/StringBuilder;
     127: ldc           #100                // String  due to
     129: invokevirtual #9                  // Method java/lang/StringBuilder.append:(Ljava/lang/String;)Ljava/lang/StringBuilder;
     132: aload_2
     133: invokevirtual #49                 // Method java/lang/StringBuilder.append:(Ljava/lang/Object;)Ljava/lang/StringBuilder;
     136: invokevirtual #11                 // Method java/lang/StringBuilder.toString:()Ljava/lang/String;
     139: invokeinterface #5,  2            // InterfaceMethod org/apache/commons/logging/Log.debug:(Ljava/lang/Object;)V
     144: getstatic     #1                  // Field log:Lorg/apache/commons/logging/Log;
     147: ldc           #101                // String Processing continues
     149: invokeinterface #5,  2            // InterfaceMethod org/apache/commons/logging/Log.debug:(Ljava/lang/Object;)V
     154: getstatic     #1                  // Field log:Lorg/apache/commons/logging/Log;
     157: invokeinterface #3,  1            // InterfaceMethod org/apache/commons/logging/Log.isDebugEnabled:()Z
     162: ifeq          175
     165: getstatic     #1                  // Field log:Lorg/apache/commons/logging/Log;
     168: ldc           #102                // String exit addPackagesFromParameters
     170: invokeinterface #5,  2            // InterfaceMethod org/apache/commons/logging/Log.debug:(Ljava/lang/Object;)V
     175: return
    Exception table:
       from    to  target type
          38    93    96   Class java/lang/Throwable

  private static void addPackagesFromReturn(java.util.TreeSet<java.lang.String>, java.lang.reflect.Method);
    Code:
       0: getstatic     #1                  // Field log:Lorg/apache/commons/logging/Log;
       3: invokeinterface #3,  1            // InterfaceMethod org/apache/commons/logging/Log.isDebugEnabled:()Z
       8: ifeq          38
      11: getstatic     #1                  // Field log:Lorg/apache/commons/logging/Log;
      14: new           #6                  // class java/lang/StringBuilder
      17: dup
      18: invokespecial #7                  // Method java/lang/StringBuilder."<init>":()V
      21: ldc           #103                // String enter addPackagesFromReturn for
      23: invokevirtual #9                  // Method java/lang/StringBuilder.append:(Ljava/lang/String;)Ljava/lang/StringBuilder;
      26: aload_1
      27: invokevirtual #49                 // Method java/lang/StringBuilder.append:(Ljava/lang/Object;)Ljava/lang/StringBuilder;
      30: invokevirtual #11                 // Method java/lang/StringBuilder.toString:()Ljava/lang/String;
      33: invokeinterface #5,  2            // InterfaceMethod org/apache/commons/logging/Log.debug:(Ljava/lang/Object;)V
      38: aload_1
      39: ifnull        64
      42: new           #94                 // class java/util/HashSet
      45: dup
      46: invokespecial #95                 // Method java/util/HashSet."<init>":()V
      49: astore_2
      50: aload_1
      51: invokevirtual #104                // Method java/lang/reflect/Method.getGenericReturnType:()Ljava/lang/reflect/Type;
      54: aload_2
      55: invokestatic  #97                 // Method org/apache/axis2/jaxws/utility/ClassUtils.getClasses:(Ljava/lang/reflect/Type;Ljava/util/Set;)Ljava/util/Set;
      58: astore_2
      59: aload_2
      60: aload_0
      61: invokestatic  #98                 // Method addClassesToPackageSet:(Ljava/util/Set;Ljava/util/TreeSet;)V
      64: goto          125
      67: astore_2
      68: getstatic     #1                  // Field log:Lorg/apache/commons/logging/Log;
      71: invokeinterface #3,  1            // InterfaceMethod org/apache/commons/logging/Log.isDebugEnabled:()Z
      76: ifeq          125
      79: getstatic     #1                  // Field log:Lorg/apache/commons/logging/Log;
      82: new           #6                  // class java/lang/StringBuilder
      85: dup
      86: invokespecial #7                  // Method java/lang/StringBuilder."<init>":()V
      89: ldc           #99                 // String Could not reflect the information on method
      91: invokevirtual #9                  // Method java/lang/StringBuilder.append:(Ljava/lang/String;)Ljava/lang/StringBuilder;
      94: aload_1
      95: invokevirtual #49                 // Method java/lang/StringBuilder.append:(Ljava/lang/Object;)Ljava/lang/StringBuilder;
      98: ldc           #100                // String  due to
     100: invokevirtual #9                  // Method java/lang/StringBuilder.append:(Ljava/lang/String;)Ljava/lang/StringBuilder;
     103: aload_2
     104: invokevirtual #49                 // Method java/lang/StringBuilder.append:(Ljava/lang/Object;)Ljava/lang/StringBuilder;
     107: invokevirtual #11                 // Method java/lang/StringBuilder.toString:()Ljava/lang/String;
     110: invokeinterface #5,  2            // InterfaceMethod org/apache/commons/logging/Log.debug:(Ljava/lang/Object;)V
     115: getstatic     #1                  // Field log:Lorg/apache/commons/logging/Log;
     118: ldc           #101                // String Processing continues
     120: invokeinterface #5,  2            // InterfaceMethod org/apache/commons/logging/Log.debug:(Ljava/lang/Object;)V
     125: getstatic     #1                  // Field log:Lorg/apache/commons/logging/Log;
     128: invokeinterface #3,  1            // InterfaceMethod org/apache/commons/logging/Log.isDebugEnabled:()Z
     133: ifeq          146
     136: getstatic     #1                  // Field log:Lorg/apache/commons/logging/Log;
     139: ldc           #105                // String exit addPackagesFromReturn
     141: invokeinterface #5,  2            // InterfaceMethod org/apache/commons/logging/Log.debug:(Ljava/lang/Object;)V
     146: return
    Exception table:
       from    to  target type
          38    64    67   Class java/lang/Throwable

  private static void addClassesToPackageSet(java.util.Set<java.lang.Class>, java.util.TreeSet<java.lang.String>);
    Code:
       0: getstatic     #1                  // Field log:Lorg/apache/commons/logging/Log;
       3: invokeinterface #3,  1            // InterfaceMethod org/apache/commons/logging/Log.isDebugEnabled:()Z
       8: ifeq          21
      11: getstatic     #1                  // Field log:Lorg/apache/commons/logging/Log;
      14: ldc           #106                // String enter addClassesToPackageSet
      16: invokeinterface #5,  2            // InterfaceMethod org/apache/commons/logging/Log.debug:(Ljava/lang/Object;)V
      21: aload_0
      22: ifnull        203
      25: aload_0
      26: invokeinterface #107,  1          // InterfaceMethod java/util/Set.iterator:()Ljava/util/Iterator;
      31: astore_2
      32: aload_2
      33: invokeinterface #18,  1           // InterfaceMethod java/util/Iterator.hasNext:()Z
      38: ifeq          203
      41: aload_2
      42: invokeinterface #19,  1           // InterfaceMethod java/util/Iterator.next:()Ljava/lang/Object;
      47: checkcast     #108                // class java/lang/Class
      50: astore_3
      51: aload_3
      52: ifnull        200
      55: aload_3
      56: ldc           #109                // class javax/xml/ws/Holder
      58: if_acmpeq     200
      61: aload_3
      62: ldc           #110                // class java/util/concurrent/Future
      64: if_acmpeq     200
      67: aload_3
      68: ldc           #111                // class javax/xml/ws/Response
      70: if_acmpeq     200
      73: aload_3
      74: invokevirtual #112                // Method java/lang/Class.getPackage:()Ljava/lang/Package;
      77: astore        4
      79: aload         4
      81: ifnull        92
      84: aload         4
      86: invokevirtual #113                // Method java/lang/Package.getName:()Ljava/lang/String;
      89: goto          93
      92: aconst_null
      93: astore        5
      95: aload         4
      97: ifnull        200
     100: aload_3
     101: invokevirtual #88                 // Method java/lang/Class.getCanonicalName:()Ljava/lang/String;
     104: astore        6
     106: getstatic     #1                  // Field log:Lorg/apache/commons/logging/Log;
     109: invokeinterface #3,  1            // InterfaceMethod org/apache/commons/logging/Log.isDebugEnabled:()Z
     114: ifeq          145
     117: getstatic     #1                  // Field log:Lorg/apache/commons/logging/Log;
     120: new           #6                  // class java/lang/StringBuilder
     123: dup
     124: invokespecial #7                  // Method java/lang/StringBuilder."<init>":()V
     127: ldc           #114                // String  adding class
     129: invokevirtual #9                  // Method java/lang/StringBuilder.append:(Ljava/lang/String;)Ljava/lang/StringBuilder;
     132: aload         6
     134: invokevirtual #9                  // Method java/lang/StringBuilder.append:(Ljava/lang/String;)Ljava/lang/StringBuilder;
     137: invokevirtual #11                 // Method java/lang/StringBuilder.toString:()Ljava/lang/String;
     140: invokeinterface #5,  2            // InterfaceMethod org/apache/commons/logging/Log.debug:(Ljava/lang/Object;)V
     145: aload_1
     146: new           #6                  // class java/lang/StringBuilder
     149: dup
     150: invokespecial #7                  // Method java/lang/StringBuilder."<init>":()V
     153: ldc           #67                 // String @
     155: invokevirtual #9                  // Method java/lang/StringBuilder.append:(Ljava/lang/String;)Ljava/lang/StringBuilder;
     158: aload         5
     160: invokevirtual #9                  // Method java/lang/StringBuilder.append:(Ljava/lang/String;)Ljava/lang/StringBuilder;
     163: invokevirtual #11                 // Method java/lang/StringBuilder.toString:()Ljava/lang/String;
     166: invokevirtual #66                 // Method java/util/TreeSet.add:(Ljava/lang/Object;)Z
     169: pop
     170: aload_1
     171: new           #6                  // class java/lang/StringBuilder
     174: dup
     175: invokespecial #7                  // Method java/lang/StringBuilder."<init>":()V
     178: ldc           #68                 // String [
     180: invokevirtual #9                  // Method java/lang/StringBuilder.append:(Ljava/lang/String;)Ljava/lang/StringBuilder;
     183: aload         6
     185: invokevirtual #9                  // Method java/lang/StringBuilder.append:(Ljava/lang/String;)Ljava/lang/StringBuilder;
     188: ldc           #69                 // String ]
     190: invokevirtual #9                  // Method java/lang/StringBuilder.append:(Ljava/lang/String;)Ljava/lang/StringBuilder;
     193: invokevirtual #11                 // Method java/lang/StringBuilder.toString:()Ljava/lang/String;
     196: invokevirtual #66                 // Method java/util/TreeSet.add:(Ljava/lang/Object;)Z
     199: pop
     200: goto          32
     203: getstatic     #1                  // Field log:Lorg/apache/commons/logging/Log;
     206: invokeinterface #3,  1            // InterfaceMethod org/apache/commons/logging/Log.isDebugEnabled:()Z
     211: ifeq          224
     214: getstatic     #1                  // Field log:Lorg/apache/commons/logging/Log;
     217: ldc           #115                // String exit addClassesToPackageSet
     219: invokeinterface #5,  2            // InterfaceMethod org/apache/commons/logging/Log.debug:(Ljava/lang/Object;)V
     224: return

  private static void addPackagesFromParameters(java.util.TreeSet<java.lang.String>, org.apache.axis2.jaxws.description.OperationDescription);
    Code:
       0: aload_1
       1: invokeinterface #59,  1           // InterfaceMethod org/apache/axis2/jaxws/description/OperationDescription.getParameterDescriptions:()[Lorg/apache/axis2/jaxws/description/ParameterDescription;
       6: astore_2
       7: aload_2
       8: ifnull        170
      11: iconst_0
      12: istore_3
      13: iload_3
      14: aload_2
      15: arraylength
      16: if_icmpge     170
      19: aload_2
      20: iload_3
      21: aaload
      22: astore        4
      24: aload         4
      26: ifnull        164
      29: aload         4
      31: invokeinterface #116,  1          // InterfaceMethod org/apache/axis2/jaxws/description/ParameterDescription.getParameterActualType:()Ljava/lang/Class;
      36: astore        5
      38: aload         5
      40: invokestatic  #86                 // Method getPackageFromClass:(Ljava/lang/Class;)Ljava/lang/String;
      43: astore        6
      45: getstatic     #1                  // Field log:Lorg/apache/commons/logging/Log;
      48: invokeinterface #3,  1            // InterfaceMethod org/apache/commons/logging/Log.isDebugEnabled:()Z
      53: ifeq          94
      56: getstatic     #1                  // Field log:Lorg/apache/commons/logging/Log;
      59: new           #6                  // class java/lang/StringBuilder
      62: dup
      63: invokespecial #7                  // Method java/lang/StringBuilder."<init>":()V
      66: ldc           #117                // String Package from Parameter (
      68: invokevirtual #9                  // Method java/lang/StringBuilder.append:(Ljava/lang/String;)Ljava/lang/StringBuilder;
      71: aload         5
      73: invokevirtual #49                 // Method java/lang/StringBuilder.append:(Ljava/lang/Object;)Ljava/lang/StringBuilder;
      76: ldc           #118                // String ) =
      78: invokevirtual #9                  // Method java/lang/StringBuilder.append:(Ljava/lang/String;)Ljava/lang/StringBuilder;
      81: aload         6
      83: invokevirtual #9                  // Method java/lang/StringBuilder.append:(Ljava/lang/String;)Ljava/lang/StringBuilder;
      86: invokevirtual #11                 // Method java/lang/StringBuilder.toString:()Ljava/lang/String;
      89: invokeinterface #5,  2            // InterfaceMethod org/apache/commons/logging/Log.debug:(Ljava/lang/Object;)V
      94: aload         6
      96: ifnull        164
      99: aload_0
     100: aload         6
     102: invokevirtual #66                 // Method java/util/TreeSet.add:(Ljava/lang/Object;)Z
     105: pop
     106: aload_0
     107: new           #6                  // class java/lang/StringBuilder
     110: dup
     111: invokespecial #7                  // Method java/lang/StringBuilder."<init>":()V
     114: ldc           #67                 // String @
     116: invokevirtual #9                  // Method java/lang/StringBuilder.append:(Ljava/lang/String;)Ljava/lang/StringBuilder;
     119: aload         6
     121: invokevirtual #9                  // Method java/lang/StringBuilder.append:(Ljava/lang/String;)Ljava/lang/StringBuilder;
     124: invokevirtual #11                 // Method java/lang/StringBuilder.toString:()Ljava/lang/String;
     127: invokevirtual #66                 // Method java/util/TreeSet.add:(Ljava/lang/Object;)Z
     130: pop
     131: aload_0
     132: new           #6                  // class java/lang/StringBuilder
     135: dup
     136: invokespecial #7                  // Method java/lang/StringBuilder."<init>":()V
     139: ldc           #68                 // String [
     141: invokevirtual #9                  // Method java/lang/StringBuilder.append:(Ljava/lang/String;)Ljava/lang/StringBuilder;
     144: aload         5
     146: invokevirtual #88                 // Method java/lang/Class.getCanonicalName:()Ljava/lang/String;
     149: invokevirtual #9                  // Method java/lang/StringBuilder.append:(Ljava/lang/String;)Ljava/lang/StringBuilder;
     152: ldc           #69                 // String ]
     154: invokevirtual #9                  // Method java/lang/StringBuilder.append:(Ljava/lang/String;)Ljava/lang/StringBuilder;
     157: invokevirtual #11                 // Method java/lang/StringBuilder.toString:()Ljava/lang/String;
     160: invokevirtual #66                 // Method java/util/TreeSet.add:(Ljava/lang/Object;)Z
     163: pop
     164: iinc          3, 1
     167: goto          13
     170: return

  private static void getPackagesFromAnnotations(org.apache.axis2.jaxws.description.ParameterDescription, java.util.TreeSet<java.lang.String>, org.apache.axis2.jaxws.runtime.description.marshal.MarshalServiceRuntimeDescription);
    Code:
       0: aload_0
       1: invokeinterface #116,  1          // InterfaceMethod org/apache/axis2/jaxws/description/ParameterDescription.getParameterActualType:()Ljava/lang/Class;
       6: astore_3
       7: aload_3
       8: ifnull        29
      11: aload_3
      12: aload_0
      13: invokeinterface #119,  1          // InterfaceMethod org/apache/axis2/jaxws/description/ParameterDescription.getTargetNamespace:()Ljava/lang/String;
      18: aload_0
      19: invokeinterface #120,  1          // InterfaceMethod org/apache/axis2/jaxws/description/ParameterDescription.getPartName:()Ljava/lang/String;
      24: aload_1
      25: aload_2
      26: invokestatic  #121                // Method setTypeAndElementPackages:(Ljava/lang/Class;Ljava/lang/String;Ljava/lang/String;Ljava/util/TreeSet;Lorg/apache/axis2/jaxws/runtime/description/marshal/MarshalServiceRuntimeDescription;)V
      29: return

  private static void getPackagesFromAnnotations(org.apache.axis2.jaxws.description.EndpointDescription, org.apache.axis2.jaxws.description.FaultDescription, java.util.TreeSet<java.lang.String>, org.apache.axis2.jaxws.runtime.description.marshal.MarshalServiceRuntimeDescription);
    Code:
       0: aload_3
       1: aload_1
       2: invokeinterface #122,  2          // InterfaceMethod org/apache/axis2/jaxws/runtime/description/marshal/MarshalServiceRuntimeDescription.getFaultBeanDesc:(Lorg/apache/axis2/jaxws/description/FaultDescription;)Lorg/apache/axis2/jaxws/runtime/description/marshal/FaultBeanDesc;
       7: astore        4
       9: aload         4
      11: ifnonnull     36
      14: getstatic     #1                  // Field log:Lorg/apache/commons/logging/Log;
      17: invokeinterface #3,  1            // InterfaceMethod org/apache/commons/logging/Log.isDebugEnabled:()Z
      22: ifeq          35
      25: getstatic     #1                  // Field log:Lorg/apache/commons/logging/Log;
      28: ldc           #123                // String faultBeanDesc from MarshallServiceRuntimeDescription is null
      30: invokeinterface #5,  2            // InterfaceMethod org/apache/commons/logging/Log.debug:(Ljava/lang/Object;)V
      35: return
      36: aload         4
      38: invokeinterface #124,  1          // InterfaceMethod org/apache/axis2/jaxws/runtime/description/marshal/FaultBeanDesc.getFaultBeanClassName:()Ljava/lang/String;
      43: astore        5
      45: aload         5
      47: ifnonnull     72
      50: getstatic     #1                  // Field log:Lorg/apache/commons/logging/Log;
      53: invokeinterface #3,  1            // InterfaceMethod org/apache/commons/logging/Log.isDebugEnabled:()Z
      58: ifeq          71
      61: getstatic     #1                  // Field log:Lorg/apache/commons/logging/Log;
      64: ldc           #125                // String FaultBeanName is null
      66: invokeinterface #5,  2            // InterfaceMethod org/apache/commons/logging/Log.debug:(Ljava/lang/Object;)V
      71: return
      72: aload         5
      74: invokestatic  #39                 // Method loadClass:(Ljava/lang/String;)Ljava/lang/Class;
      77: astore        6
      79: aload         6
      81: ifnonnull     100
      84: aload         5
      86: aload_0
      87: invokeinterface #40,  1           // InterfaceMethod org/apache/axis2/jaxws/description/EndpointDescription.getAxisService:()Lorg/apache/axis2/description/AxisService;
      92: invokevirtual #41                 // Method org/apache/axis2/description/AxisService.getClassLoader:()Ljava/lang/ClassLoader;
      95: invokestatic  #42                 // Method loadClass:(Ljava/lang/String;Ljava/lang/ClassLoader;)Ljava/lang/Class;
      98: astore        6
     100: aload         6
     102: ifnull        126
     105: aload         6
     107: aload         4
     109: invokeinterface #126,  1          // InterfaceMethod org/apache/axis2/jaxws/runtime/description/marshal/FaultBeanDesc.getFaultBeanNamespace:()Ljava/lang/String;
     114: aload         4
     116: invokeinterface #127,  1          // InterfaceMethod org/apache/axis2/jaxws/runtime/description/marshal/FaultBeanDesc.getFaultBeanLocalName:()Ljava/lang/String;
     121: aload_2
     122: aload_3
     123: invokestatic  #121                // Method setTypeAndElementPackages:(Ljava/lang/Class;Ljava/lang/String;Ljava/lang/String;Ljava/util/TreeSet;Lorg/apache/axis2/jaxws/runtime/description/marshal/MarshalServiceRuntimeDescription;)V
     126: return

  private static void setTypeAndElementPackages(java.lang.Class, java.lang.String, java.lang.String, java.util.TreeSet<java.lang.String>, org.apache.axis2.jaxws.runtime.description.marshal.MarshalServiceRuntimeDescription);
    Code:
       0: aload_0
       1: aload         4
       3: invokestatic  #128                // Method getElement:(Ljava/lang/Class;Lorg/apache/axis2/jaxws/runtime/description/marshal/MarshalServiceRuntimeDescription;)Ljava/lang/Class;
       6: astore        5
       8: aload_0
       9: invokestatic  #129                // Method getType:(Ljava/lang/Class;)Ljava/lang/Class;
      12: astore        6
      14: aload         6
      16: ifnull        312
      19: aload         6
      21: invokevirtual #112                // Method java/lang/Class.getPackage:()Ljava/lang/Package;
      24: astore        7
      26: aload         7
      28: ifnull        39
      31: aload         7
      33: invokevirtual #113                // Method java/lang/Package.getName:()Ljava/lang/String;
      36: goto          40
      39: aconst_null
      40: astore        8
      42: aload         8
      44: ifnull        112
      47: aload_3
      48: aload         8
      50: invokevirtual #66                 // Method java/util/TreeSet.add:(Ljava/lang/Object;)Z
      53: pop
      54: aload_3
      55: new           #6                  // class java/lang/StringBuilder
      58: dup
      59: invokespecial #7                  // Method java/lang/StringBuilder."<init>":()V
      62: ldc           #67                 // String @
      64: invokevirtual #9                  // Method java/lang/StringBuilder.append:(Ljava/lang/String;)Ljava/lang/StringBuilder;
      67: aload         8
      69: invokevirtual #9                  // Method java/lang/StringBuilder.append:(Ljava/lang/String;)Ljava/lang/StringBuilder;
      72: invokevirtual #11                 // Method java/lang/StringBuilder.toString:()Ljava/lang/String;
      75: invokevirtual #66                 // Method java/util/TreeSet.add:(Ljava/lang/Object;)Z
      78: pop
      79: aload_3
      80: new           #6                  // class java/lang/StringBuilder
      83: dup
      84: invokespecial #7                  // Method java/lang/StringBuilder."<init>":()V
      87: ldc           #68                 // String [
      89: invokevirtual #9                  // Method java/lang/StringBuilder.append:(Ljava/lang/String;)Ljava/lang/StringBuilder;
      92: aload         6
      94: invokevirtual #88                 // Method java/lang/Class.getCanonicalName:()Ljava/lang/String;
      97: invokevirtual #9                  // Method java/lang/StringBuilder.append:(Ljava/lang/String;)Ljava/lang/StringBuilder;
     100: ldc           #69                 // String ]
     102: invokevirtual #9                  // Method java/lang/StringBuilder.append:(Ljava/lang/String;)Ljava/lang/StringBuilder;
     105: invokevirtual #11                 // Method java/lang/StringBuilder.toString:()Ljava/lang/String;
     108: invokevirtual #66                 // Method java/util/TreeSet.add:(Ljava/lang/Object;)Z
     111: pop
     112: aload         8
     114: ifnull        304
     117: aload         4
     119: aload         6
     121: invokeinterface #130,  2          // InterfaceMethod org/apache/axis2/jaxws/runtime/description/marshal/MarshalServiceRuntimeDescription.getAnnotationDesc:(Ljava/lang/Class;)Lorg/apache/axis2/jaxws/runtime/description/marshal/AnnotationDesc;
     126: astore        9
     128: aload         9
     130: ifnull        304
     133: aload         9
     135: invokeinterface #131,  1          // InterfaceMethod org/apache/axis2/jaxws/runtime/description/marshal/AnnotationDesc.hasXmlType:()Z
     140: ifeq          304
     143: aload         9
     145: invokeinterface #132,  1          // InterfaceMethod org/apache/axis2/jaxws/runtime/description/marshal/AnnotationDesc.getXmlTypeNamespace:()Ljava/lang/String;
     150: astore        10
     152: aload         10
     154: ifnull        304
     157: aload         10
     159: invokevirtual #73                 // Method java/lang/String.length:()I
     162: ifle          304
     165: aload         10
     167: invokestatic  #75                 // Method makePackages:(Ljava/lang/String;)Ljava/util/List;
     170: astore        11
     172: aload         11
     174: ifnull        304
     177: iconst_0
     178: istore        12
     180: iload         12
     182: aload         11
     184: invokeinterface #133,  1          // InterfaceMethod java/util/List.size:()I
     189: if_icmpge     304
     192: aload         11
     194: iload         12
     196: invokeinterface #134,  2          // InterfaceMethod java/util/List.get:(I)Ljava/lang/Object;
     201: checkcast     #135                // class java/lang/String
     204: astore        13
     206: aload         8
     208: aload         13
     210: invokevirtual #136                // Method java/lang/String.equals:(Ljava/lang/Object;)Z
     213: ifne          298
     216: new           #6                  // class java/lang/StringBuilder
     219: dup
     220: invokespecial #7                  // Method java/lang/StringBuilder."<init>":()V
     223: aload         8
     225: invokevirtual #9                  // Method java/lang/StringBuilder.append:(Ljava/lang/String;)Ljava/lang/StringBuilder;
     228: ldc           #137                // String  >
     230: invokevirtual #9                  // Method java/lang/StringBuilder.append:(Ljava/lang/String;)Ljava/lang/StringBuilder;
     233: aload         13
     235: invokevirtual #9                  // Method java/lang/StringBuilder.append:(Ljava/lang/String;)Ljava/lang/StringBuilder;
     238: invokevirtual #11                 // Method java/lang/StringBuilder.toString:()Ljava/lang/String;
     241: astore        14
     243: aload_3
     244: aload         14
     246: invokevirtual #138                // Method java/util/TreeSet.contains:(Ljava/lang/Object;)Z
     249: ifne          298
     252: aload_3
     253: aload         14
     255: invokevirtual #66                 // Method java/util/TreeSet.add:(Ljava/lang/Object;)Z
     258: pop
     259: getstatic     #1                  // Field log:Lorg/apache/commons/logging/Log;
     262: invokeinterface #3,  1            // InterfaceMethod org/apache/commons/logging/Log.isDebugEnabled:()Z
     267: ifeq          298
     270: getstatic     #1                  // Field log:Lorg/apache/commons/logging/Log;
     273: new           #6                  // class java/lang/StringBuilder
     276: dup
     277: invokespecial #7                  // Method java/lang/StringBuilder."<init>":()V
     280: ldc           #139                // String Adding override=
     282: invokevirtual #9                  // Method java/lang/StringBuilder.append:(Ljava/lang/String;)Ljava/lang/StringBuilder;
     285: aload         14
     287: invokevirtual #9                  // Method java/lang/StringBuilder.append:(Ljava/lang/String;)Ljava/lang/StringBuilder;
     290: invokevirtual #11                 // Method java/lang/StringBuilder.toString:()Ljava/lang/String;
     293: invokeinterface #5,  2            // InterfaceMethod org/apache/commons/logging/Log.debug:(Ljava/lang/Object;)V
     298: iinc          12, 1
     301: goto          180
     304: aload         6
     306: aload         4
     308: aload_3
     309: invokestatic  #43                 // Method addXmlSeeAlsoPackages:(Ljava/lang/Class;Lorg/apache/axis2/jaxws/runtime/description/marshal/MarshalServiceRuntimeDescription;Ljava/util/TreeSet;)V
     312: aload         6
     314: aload         5
     316: if_acmpeq     649
     319: aload         5
     321: ifnonnull     356
     324: aload_1
     325: ifnull        649
     328: aload_1
     329: invokevirtual #73                 // Method java/lang/String.length:()I
     332: ifle          649
     335: aload_1
     336: invokestatic  #75                 // Method makePackages:(Ljava/lang/String;)Ljava/util/List;
     339: astore        7
     341: aload         7
     343: ifnull        353
     346: aload_3
     347: aload         7
     349: invokevirtual #27                 // Method java/util/TreeSet.addAll:(Ljava/util/Collection;)Z
     352: pop
     353: goto          649
     356: aload         5
     358: invokevirtual #112                // Method java/lang/Class.getPackage:()Ljava/lang/Package;
     361: astore        7
     363: aload         7
     365: ifnull        376
     368: aload         7
     370: invokevirtual #113                // Method java/lang/Package.getName:()Ljava/lang/String;
     373: goto          377
     376: aconst_null
     377: astore        8
     379: aload         8
     381: ifnull        449
     384: aload_3
     385: aload         8
     387: invokevirtual #66                 // Method java/util/TreeSet.add:(Ljava/lang/Object;)Z
     390: pop
     391: aload_3
     392: new           #6                  // class java/lang/StringBuilder
     395: dup
     396: invokespecial #7                  // Method java/lang/StringBuilder."<init>":()V
     399: ldc           #67                 // String @
     401: invokevirtual #9                  // Method java/lang/StringBuilder.append:(Ljava/lang/String;)Ljava/lang/StringBuilder;
     404: aload         8
     406: invokevirtual #9                  // Method java/lang/StringBuilder.append:(Ljava/lang/String;)Ljava/lang/StringBuilder;
     409: invokevirtual #11                 // Method java/lang/StringBuilder.toString:()Ljava/lang/String;
     412: invokevirtual #66                 // Method java/util/TreeSet.add:(Ljava/lang/Object;)Z
     415: pop
     416: aload_3
     417: new           #6                  // class java/lang/StringBuilder
     420: dup
     421: invokespecial #7                  // Method java/lang/StringBuilder."<init>":()V
     424: ldc           #68                 // String [
     426: invokevirtual #9                  // Method java/lang/StringBuilder.append:(Ljava/lang/String;)Ljava/lang/StringBuilder;
     429: aload         5
     431: invokevirtual #88                 // Method java/lang/Class.getCanonicalName:()Ljava/lang/String;
     434: invokevirtual #9                  // Method java/lang/StringBuilder.append:(Ljava/lang/String;)Ljava/lang/StringBuilder;
     437: ldc           #69                 // String ]
     439: invokevirtual #9                  // Method java/lang/StringBuilder.append:(Ljava/lang/String;)Ljava/lang/StringBuilder;
     442: invokevirtual #11                 // Method java/lang/StringBuilder.toString:()Ljava/lang/String;
     445: invokevirtual #66                 // Method java/util/TreeSet.add:(Ljava/lang/Object;)Z
     448: pop
     449: aload         8
     451: ifnull        641
     454: aload         4
     456: aload         6
     458: invokeinterface #130,  2          // InterfaceMethod org/apache/axis2/jaxws/runtime/description/marshal/MarshalServiceRuntimeDescription.getAnnotationDesc:(Ljava/lang/Class;)Lorg/apache/axis2/jaxws/runtime/description/marshal/AnnotationDesc;
     463: astore        9
     465: aload         9
     467: ifnull        641
     470: aload         9
     472: invokeinterface #140,  1          // InterfaceMethod org/apache/axis2/jaxws/runtime/description/marshal/AnnotationDesc.hasXmlRootElement:()Z
     477: ifeq          641
     480: aload         9
     482: invokeinterface #141,  1          // InterfaceMethod org/apache/axis2/jaxws/runtime/description/marshal/AnnotationDesc.getXmlRootElementNamespace:()Ljava/lang/String;
     487: astore        10
     489: aload         10
     491: ifnull        641
     494: aload         10
     496: invokevirtual #73                 // Method java/lang/String.length:()I
     499: ifle          641
     502: aload         10
     504: invokestatic  #75                 // Method makePackages:(Ljava/lang/String;)Ljava/util/List;
     507: astore        11
     509: aload         11
     511: ifnull        641
     514: iconst_0
     515: istore        12
     517: iload         12
     519: aload         11
     521: invokeinterface #133,  1          // InterfaceMethod java/util/List.size:()I
     526: if_icmpge     641
     529: aload         11
     531: iload         12
     533: invokeinterface #134,  2          // InterfaceMethod java/util/List.get:(I)Ljava/lang/Object;
     538: checkcast     #135                // class java/lang/String
     541: astore        13
     543: aload         8
     545: aload         13
     547: invokevirtual #136                // Method java/lang/String.equals:(Ljava/lang/Object;)Z
     550: ifne          635
     553: new           #6                  // class java/lang/StringBuilder
     556: dup
     557: invokespecial #7                  // Method java/lang/StringBuilder."<init>":()V
     560: aload         8
     562: invokevirtual #9                  // Method java/lang/StringBuilder.append:(Ljava/lang/String;)Ljava/lang/StringBuilder;
     565: ldc           #137                // String  >
     567: invokevirtual #9                  // Method java/lang/StringBuilder.append:(Ljava/lang/String;)Ljava/lang/StringBuilder;
     570: aload         13
     572: invokevirtual #9                  // Method java/lang/StringBuilder.append:(Ljava/lang/String;)Ljava/lang/StringBuilder;
     575: invokevirtual #11                 // Method java/lang/StringBuilder.toString:()Ljava/lang/String;
     578: astore        14
     580: aload_3
     581: aload         14
     583: invokevirtual #138                // Method java/util/TreeSet.contains:(Ljava/lang/Object;)Z
     586: ifne          635
     589: aload_3
     590: aload         14
     592: invokevirtual #66                 // Method java/util/TreeSet.add:(Ljava/lang/Object;)Z
     595: pop
     596: getstatic     #1                  // Field log:Lorg/apache/commons/logging/Log;
     599: invokeinterface #3,  1            // InterfaceMethod org/apache/commons/logging/Log.isDebugEnabled:()Z
     604: ifeq          635
     607: getstatic     #1                  // Field log:Lorg/apache/commons/logging/Log;
     610: new           #6                  // class java/lang/StringBuilder
     613: dup
     614: invokespecial #7                  // Method java/lang/StringBuilder."<init>":()V
     617: ldc           #139                // String Adding override=
     619: invokevirtual #9                  // Method java/lang/StringBuilder.append:(Ljava/lang/String;)Ljava/lang/StringBuilder;
     622: aload         14
     624: invokevirtual #9                  // Method java/lang/StringBuilder.append:(Ljava/lang/String;)Ljava/lang/StringBuilder;
     627: invokevirtual #11                 // Method java/lang/StringBuilder.toString:()Ljava/lang/String;
     630: invokeinterface #5,  2            // InterfaceMethod org/apache/commons/logging/Log.debug:(Ljava/lang/Object;)V
     635: iinc          12, 1
     638: goto          517
     641: aload         6
     643: aload         4
     645: aload_3
     646: invokestatic  #43                 // Method addXmlSeeAlsoPackages:(Ljava/lang/Class;Lorg/apache/axis2/jaxws/runtime/description/marshal/MarshalServiceRuntimeDescription;Ljava/util/TreeSet;)V
     649: return

  private static java.lang.Class getElement(java.lang.Class, org.apache.axis2.jaxws.runtime.description.marshal.MarshalServiceRuntimeDescription);
    Code:
       0: aload_1
       1: aload_0
       2: invokeinterface #130,  2          // InterfaceMethod org/apache/axis2/jaxws/runtime/description/marshal/MarshalServiceRuntimeDescription.getAnnotationDesc:(Ljava/lang/Class;)Lorg/apache/axis2/jaxws/runtime/description/marshal/AnnotationDesc;
       7: astore_2
       8: aload_2
       9: ifnonnull     17
      12: aload_0
      13: invokestatic  #142                // Method org/apache/axis2/jaxws/runtime/description/marshal/impl/AnnotationDescImpl.create:(Ljava/lang/Class;)Lorg/apache/axis2/jaxws/runtime/description/marshal/AnnotationDesc;
      16: astore_2
      17: aload_2
      18: invokeinterface #140,  1          // InterfaceMethod org/apache/axis2/jaxws/runtime/description/marshal/AnnotationDesc.hasXmlRootElement:()Z
      23: ifeq          28
      26: aload_0
      27: areturn
      28: aconst_null
      29: areturn

  private static java.lang.Class getType(java.lang.Class);
    Code:
       0: ldc           #143                // class javax/xml/bind/JAXBElement
       2: aload_0
       3: invokevirtual #144                // Method java/lang/Class.isAssignableFrom:(Ljava/lang/Class;)Z
       6: ifeq          48
       9: aload_0
      10: ldc           #145                // String getValue
      12: getstatic     #146                // Field noClass:[Ljava/lang/Class;
      15: invokevirtual #147                // Method java/lang/Class.getMethod:(Ljava/lang/String;[Ljava/lang/Class;)Ljava/lang/reflect/Method;
      18: astore_1
      19: aload_1
      20: invokevirtual #148                // Method java/lang/reflect/Method.getReturnType:()Ljava/lang/Class;
      23: areturn
      24: astore_1
      25: getstatic     #1                  // Field log:Lorg/apache/commons/logging/Log;
      28: invokeinterface #3,  1            // InterfaceMethod org/apache/commons/logging/Log.isDebugEnabled:()Z
      33: ifeq          46
      36: getstatic     #1                  // Field log:Lorg/apache/commons/logging/Log;
      39: ldc           #150                // String Cannot find JAXBElement.getValue method.
      41: invokeinterface #5,  2            // InterfaceMethod org/apache/commons/logging/Log.debug:(Ljava/lang/Object;)V
      46: aconst_null
      47: areturn
      48: aload_0
      49: areturn
    Exception table:
       from    to  target type
           9    23    24   Class java/lang/Exception

  private static java.util.List makePackages(java.lang.String);
    Code:
       0: aload_0
       1: invokestatic  #151                // Method org/apache/axis2/jaxws/utility/JavaUtils.getPackagesFromNamespace:(Ljava/lang/String;)Ljava/util/List;
       4: astore_1
       5: aload_1
       6: areturn

  public static java.lang.String getPackageFromClassName(java.lang.String);
    Code:
       0: aload_0
       1: invokestatic  #39                 // Method loadClass:(Ljava/lang/String;)Ljava/lang/Class;
       4: astore_1
       5: aload_1
       6: invokestatic  #86                 // Method getPackageFromClass:(Ljava/lang/Class;)Ljava/lang/String;
       9: astore_2
      10: aload_2
      11: areturn

  public static java.lang.String getPackageFromClass(java.lang.Class);
    Code:
       0: aconst_null
       1: astore_1
       2: aload_0
       3: ifnonnull     11
       6: aconst_null
       7: astore_1
       8: goto          61
      11: aload_0
      12: invokevirtual #152                // Method java/lang/Class.isArray:()Z
      15: ifeq          29
      18: aload_0
      19: invokevirtual #153                // Method java/lang/Class.getComponentType:()Ljava/lang/Class;
      22: invokestatic  #86                 // Method getPackageFromClass:(Ljava/lang/Class;)Ljava/lang/String;
      25: astore_1
      26: goto          61
      29: aload_0
      30: invokevirtual #154                // Method java/lang/Class.isPrimitive:()Z
      33: ifeq          41
      36: aconst_null
      37: astore_1
      38: goto          61
      41: aload_0
      42: invokevirtual #112                // Method java/lang/Class.getPackage:()Ljava/lang/Package;
      45: ifnonnull     53
      48: ldc           #155                // String
      50: goto          60
      53: aload_0
      54: invokevirtual #112                // Method java/lang/Class.getPackage:()Ljava/lang/Package;
      57: invokevirtual #113                // Method java/lang/Package.getName:()Ljava/lang/String;
      60: astore_1
      61: aload_1
      62: areturn

  private static void addXmlSeeAlsoPackages(java.lang.Class, org.apache.axis2.jaxws.runtime.description.marshal.MarshalServiceRuntimeDescription, java.util.TreeSet<java.lang.String>);
    Code:
       0: getstatic     #1                  // Field log:Lorg/apache/commons/logging/Log;
       3: invokeinterface #3,  1            // InterfaceMethod org/apache/commons/logging/Log.isDebugEnabled:()Z
       8: ifeq          38
      11: getstatic     #1                  // Field log:Lorg/apache/commons/logging/Log;
      14: new           #6                  // class java/lang/StringBuilder
      17: dup
      18: invokespecial #7                  // Method java/lang/StringBuilder."<init>":()V
      21: ldc           #156                // String start addXmlSeeAlsoPackages for
      23: invokevirtual #9                  // Method java/lang/StringBuilder.append:(Ljava/lang/String;)Ljava/lang/StringBuilder;
      26: aload_0
      27: invokevirtual #49                 // Method java/lang/StringBuilder.append:(Ljava/lang/Object;)Ljava/lang/StringBuilder;
      30: invokevirtual #11                 // Method java/lang/StringBuilder.toString:()Ljava/lang/String;
      33: invokeinterface #5,  2            // InterfaceMethod org/apache/commons/logging/Log.debug:(Ljava/lang/Object;)V
      38: aload_0
      39: ifnull        275
      42: aload_1
      43: aload_0
      44: invokeinterface #130,  2          // InterfaceMethod org/apache/axis2/jaxws/runtime/description/marshal/MarshalServiceRuntimeDescription.getAnnotationDesc:(Ljava/lang/Class;)Lorg/apache/axis2/jaxws/runtime/description/marshal/AnnotationDesc;
      49: astore_3
      50: aload_3
      51: ifnull        237
      54: aload_3
      55: invokeinterface #157,  1          // InterfaceMethod org/apache/axis2/jaxws/runtime/description/marshal/AnnotationDesc.getXmlSeeAlsoClasses:()[Ljava/lang/Class;
      60: astore        4
      62: aload         4
      64: ifnull        237
      67: iconst_0
      68: istore        5
      70: iload         5
      72: aload         4
      74: arraylength
      75: if_icmpge     237
      78: aload         4
      80: iload         5
      82: aaload
      83: ifnonnull     90
      86: aconst_null
      87: goto          117
      90: aload         4
      92: iload         5
      94: aaload
      95: invokevirtual #112                // Method java/lang/Class.getPackage:()Ljava/lang/Package;
      98: ifnonnull     106
     101: ldc           #155                // String
     103: goto          117
     106: aload         4
     108: iload         5
     110: aaload
     111: invokevirtual #112                // Method java/lang/Class.getPackage:()Ljava/lang/Package;
     114: invokevirtual #113                // Method java/lang/Package.getName:()Ljava/lang/String;
     117: astore        6
     119: aload         6
     121: ifnull        231
     124: getstatic     #1                  // Field log:Lorg/apache/commons/logging/Log;
     127: invokeinterface #3,  1            // InterfaceMethod org/apache/commons/logging/Log.isDebugEnabled:()Z
     132: ifeq          163
     135: getstatic     #1                  // Field log:Lorg/apache/commons/logging/Log;
     138: new           #6                  // class java/lang/StringBuilder
     141: dup
     142: invokespecial #7                  // Method java/lang/StringBuilder."<init>":()V
     145: ldc           #158                // String  adding package =
     147: invokevirtual #9                  // Method java/lang/StringBuilder.append:(Ljava/lang/String;)Ljava/lang/StringBuilder;
     150: aload         6
     152: invokevirtual #9                  // Method java/lang/StringBuilder.append:(Ljava/lang/String;)Ljava/lang/StringBuilder;
     155: invokevirtual #11                 // Method java/lang/StringBuilder.toString:()Ljava/lang/String;
     158: invokeinterface #5,  2            // InterfaceMethod org/apache/commons/logging/Log.debug:(Ljava/lang/Object;)V
     163: aload_2
     164: aload         6
     166: invokevirtual #66                 // Method java/util/TreeSet.add:(Ljava/lang/Object;)Z
     169: pop
     170: aload_2
     171: new           #6                  // class java/lang/StringBuilder
     174: dup
     175: invokespecial #7                  // Method java/lang/StringBuilder."<init>":()V
     178: ldc           #67                 // String @
     180: invokevirtual #9                  // Method java/lang/StringBuilder.append:(Ljava/lang/String;)Ljava/lang/StringBuilder;
     183: aload         6
     185: invokevirtual #9                  // Method java/lang/StringBuilder.append:(Ljava/lang/String;)Ljava/lang/StringBuilder;
     188: invokevirtual #11                 // Method java/lang/StringBuilder.toString:()Ljava/lang/String;
     191: invokevirtual #66                 // Method java/util/TreeSet.add:(Ljava/lang/Object;)Z
     194: pop
     195: aload_2
     196: new           #6                  // class java/lang/StringBuilder
     199: dup
     200: invokespecial #7                  // Method java/lang/StringBuilder."<init>":()V
     203: ldc           #68                 // String [
     205: invokevirtual #9                  // Method java/lang/StringBuilder.append:(Ljava/lang/String;)Ljava/lang/StringBuilder;
     208: aload         4
     210: iload         5
     212: aaload
     213: invokevirtual #88                 // Method java/lang/Class.getCanonicalName:()Ljava/lang/String;
     216: invokevirtual #9                  // Method java/lang/StringBuilder.append:(Ljava/lang/String;)Ljava/lang/StringBuilder;
     219: ldc           #69                 // String ]
     221: invokevirtual #9                  // Method java/lang/StringBuilder.append:(Ljava/lang/String;)Ljava/lang/StringBuilder;
     224: invokevirtual #11                 // Method java/lang/StringBuilder.toString:()Ljava/lang/String;
     227: invokevirtual #66                 // Method java/util/TreeSet.add:(Ljava/lang/Object;)Z
     230: pop
     231: iinc          5, 1
     234: goto          70
     237: aload_0
     238: invokevirtual #159                // Method java/lang/Class.getInterfaces:()[Ljava/lang/Class;
     241: astore        4
     243: aload         4
     245: ifnull        275
     248: iconst_0
     249: istore        5
     251: iload         5
     253: aload         4
     255: arraylength
     256: if_icmpge     275
     259: aload         4
     261: iload         5
     263: aaload
     264: aload_1
     265: aload_2
     266: invokestatic  #43                 // Method addXmlSeeAlsoPackages:(Ljava/lang/Class;Lorg/apache/axis2/jaxws/runtime/description/marshal/MarshalServiceRuntimeDescription;Ljava/util/TreeSet;)V
     269: iinc          5, 1
     272: goto          251
     275: getstatic     #1                  // Field log:Lorg/apache/commons/logging/Log;
     278: invokeinterface #3,  1            // InterfaceMethod org/apache/commons/logging/Log.isDebugEnabled:()Z
     283: ifeq          313
     286: getstatic     #1                  // Field log:Lorg/apache/commons/logging/Log;
     289: new           #6                  // class java/lang/StringBuilder
     292: dup
     293: invokespecial #7                  // Method java/lang/StringBuilder."<init>":()V
     296: ldc           #160                // String end addXmlSeeAlsoPackages for
     298: invokevirtual #9                  // Method java/lang/StringBuilder.append:(Ljava/lang/String;)Ljava/lang/StringBuilder;
     301: aload_0
     302: invokevirtual #49                 // Method java/lang/StringBuilder.append:(Ljava/lang/Object;)Ljava/lang/StringBuilder;
     305: invokevirtual #11                 // Method java/lang/StringBuilder.toString:()Ljava/lang/String;
     308: invokeinterface #5,  2            // InterfaceMethod org/apache/commons/logging/Log.debug:(Ljava/lang/Object;)V
     313: return

  private static java.lang.Class loadClass(java.lang.String);
    Code:
       0: aload_0
       1: ifnull        11
       4: aload_0
       5: invokevirtual #73                 // Method java/lang/String.length:()I
       8: ifne          13
      11: aconst_null
      12: areturn
      13: aload_0
      14: invokestatic  #161                // Method org/apache/axis2/jaxws/utility/ClassUtils.getPrimitiveClass:(Ljava/lang/String;)Ljava/lang/Class;
      17: astore_1
      18: aload_1
      19: ifnonnull     31
      22: aload_0
      23: iconst_1
      24: invokestatic  #162                // Method getContextClassLoader:()Ljava/lang/ClassLoader;
      27: invokestatic  #163                // Method java/lang/Class.forName:(Ljava/lang/String;ZLjava/lang/ClassLoader;)Ljava/lang/Class;
      30: astore_1
      31: aload_1
      32: areturn
      33: astore_1
      34: getstatic     #1                  // Field log:Lorg/apache/commons/logging/Log;
      37: invokeinterface #3,  1            // InterfaceMethod org/apache/commons/logging/Log.isDebugEnabled:()Z
      42: ifeq          72
      45: getstatic     #1                  // Field log:Lorg/apache/commons/logging/Log;
      48: new           #6                  // class java/lang/StringBuilder
      51: dup
      52: invokespecial #7                  // Method java/lang/StringBuilder."<init>":()V
      55: ldc           #164                // String PackageSetBuilder cannot load the following class:
      57: invokevirtual #9                  // Method java/lang/StringBuilder.append:(Ljava/lang/String;)Ljava/lang/StringBuilder;
      60: aload_0
      61: invokevirtual #9                  // Method java/lang/StringBuilder.append:(Ljava/lang/String;)Ljava/lang/StringBuilder;
      64: invokevirtual #11                 // Method java/lang/StringBuilder.toString:()Ljava/lang/String;
      67: invokeinterface #5,  2            // InterfaceMethod org/apache/commons/logging/Log.debug:(Ljava/lang/Object;)V
      72: aconst_null
      73: areturn
    Exception table:
       from    to  target type
          13    32    33   Class java/lang/Throwable

  private static java.lang.Class loadClass(java.lang.String, java.lang.ClassLoader);
    Code:
       0: aload_0
       1: ifnull        11
       4: aload_0
       5: invokevirtual #73                 // Method java/lang/String.length:()I
       8: ifne          13
      11: aconst_null
      12: areturn
      13: aload_0
      14: invokestatic  #161                // Method org/apache/axis2/jaxws/utility/ClassUtils.getPrimitiveClass:(Ljava/lang/String;)Ljava/lang/Class;
      17: astore_2
      18: aload_2
      19: ifnonnull     29
      22: aload_0
      23: iconst_1
      24: aload_1
      25: invokestatic  #165                // Method forName:(Ljava/lang/String;ZLjava/lang/ClassLoader;)Ljava/lang/Class;
      28: astore_2
      29: aload_2
      30: areturn
      31: astore_2
      32: getstatic     #1                  // Field log:Lorg/apache/commons/logging/Log;
      35: invokeinterface #3,  1            // InterfaceMethod org/apache/commons/logging/Log.isDebugEnabled:()Z
      40: ifeq          70
      43: getstatic     #1                  // Field log:Lorg/apache/commons/logging/Log;
      46: new           #6                  // class java/lang/StringBuilder
      49: dup
      50: invokespecial #7                  // Method java/lang/StringBuilder."<init>":()V
      53: ldc           #164                // String PackageSetBuilder cannot load the following class:
      55: invokevirtual #9                  // Method java/lang/StringBuilder.append:(Ljava/lang/String;)Ljava/lang/StringBuilder;
      58: aload_0
      59: invokevirtual #9                  // Method java/lang/StringBuilder.append:(Ljava/lang/String;)Ljava/lang/StringBuilder;
      62: invokevirtual #11                 // Method java/lang/StringBuilder.toString:()Ljava/lang/String;
      65: invokeinterface #5,  2            // InterfaceMethod org/apache/commons/logging/Log.debug:(Ljava/lang/Object;)V
      70: aconst_null
      71: areturn
    Exception table:
       from    to  target type
          13    30    31   Class java/lang/Throwable

  private static javax.wsdl.Definition getWSDLDefinition(java.lang.String);
    Code:
       0: aconst_null
       1: astore_1
       2: aload_0
       3: astore_2
       4: aload_2
       5: ifnull        78
       8: aload_2
       9: invokevirtual #166                // Method java/lang/String.trim:()Ljava/lang/String;
      12: invokevirtual #73                 // Method java/lang/String.length:()I
      15: ifle          78
      18: new           #167                // class org/apache/axis2/jaxws/runtime/description/marshal/impl/PackageSetBuilder$1
      21: dup
      22: aload_2
      23: invokespecial #168                // Method org/apache/axis2/jaxws/runtime/description/marshal/impl/PackageSetBuilder$1."<init>":(Ljava/lang/String;)V
      26: invokestatic  #169                // Method org/apache/axis2/java/security/AccessController.doPrivileged:(Ljava/security/PrivilegedExceptionAction;)Ljava/lang/Object;
      29: checkcast     #170                // class javax/wsdl/Definition
      32: astore_1
      33: goto          78
      36: astore_3
      37: getstatic     #1                  // Field log:Lorg/apache/commons/logging/Log;
      40: invokeinterface #3,  1            // InterfaceMethod org/apache/commons/logging/Log.isDebugEnabled:()Z
      45: ifeq          78
      48: getstatic     #1                  // Field log:Lorg/apache/commons/logging/Log;
      51: new           #6                  // class java/lang/StringBuilder
      54: dup
      55: invokespecial #7                  // Method java/lang/StringBuilder."<init>":()V
      58: ldc           #172                // String Exception getting wsdlLocation:
      60: invokevirtual #9                  // Method java/lang/StringBuilder.append:(Ljava/lang/String;)Ljava/lang/StringBuilder;
      63: aload_3
      64: invokevirtual #173                // Method java/security/PrivilegedActionException.getException:()Ljava/lang/Exception;
      67: invokevirtual #49                 // Method java/lang/StringBuilder.append:(Ljava/lang/Object;)Ljava/lang/StringBuilder;
      70: invokevirtual #11                 // Method java/lang/StringBuilder.toString:()Ljava/lang/String;
      73: invokeinterface #5,  2            // InterfaceMethod org/apache/commons/logging/Log.debug:(Ljava/lang/Object;)V
      78: aload_1
      79: areturn
    Exception table:
       from    to  target type
          18    33    36   Class java/security/PrivilegedActionException

  static java.lang.Class forName(java.lang.String, boolean, java.lang.ClassLoader) throws java.lang.ClassNotFoundException;
    Code:
       0: aconst_null
       1: astore_3
       2: new           #174                // class org/apache/axis2/jaxws/runtime/description/marshal/impl/PackageSetBuilder$2
       5: dup
       6: aload_0
       7: iload_1
       8: aload_2
       9: invokespecial #175                // Method org/apache/axis2/jaxws/runtime/description/marshal/impl/PackageSetBuilder$2."<init>":(Ljava/lang/String;ZLjava/lang/ClassLoader;)V
      12: invokestatic  #169                // Method org/apache/axis2/java/security/AccessController.doPrivileged:(Ljava/security/PrivilegedExceptionAction;)Ljava/lang/Object;
      15: checkcast     #108                // class java/lang/Class
      18: astore_3
      19: goto          72
      22: astore        4
      24: getstatic     #1                  // Field log:Lorg/apache/commons/logging/Log;
      27: invokeinterface #3,  1            // InterfaceMethod org/apache/commons/logging/Log.isDebugEnabled:()Z
      32: ifeq          63
      35: getstatic     #1                  // Field log:Lorg/apache/commons/logging/Log;
      38: new           #6                  // class java/lang/StringBuilder
      41: dup
      42: invokespecial #7                  // Method java/lang/StringBuilder."<init>":()V
      45: ldc           #176                // String Exception thrown from AccessController:
      47: invokevirtual #9                  // Method java/lang/StringBuilder.append:(Ljava/lang/String;)Ljava/lang/StringBuilder;
      50: aload         4
      52: invokevirtual #49                 // Method java/lang/StringBuilder.append:(Ljava/lang/Object;)Ljava/lang/StringBuilder;
      55: invokevirtual #11                 // Method java/lang/StringBuilder.toString:()Ljava/lang/String;
      58: invokeinterface #5,  2            // InterfaceMethod org/apache/commons/logging/Log.debug:(Ljava/lang/Object;)V
      63: aload         4
      65: invokevirtual #173                // Method java/security/PrivilegedActionException.getException:()Ljava/lang/Exception;
      68: checkcast     #177                // class java/lang/ClassNotFoundException
      71: athrow
      72: aload_3
      73: areturn
    Exception table:
       from    to  target type
           2    19    22   Class java/security/PrivilegedActionException

  static java.lang.ClassLoader getContextClassLoader();
    Code:
       0: aconst_null
       1: astore_0
       2: new           #178                // class org/apache/axis2/jaxws/runtime/description/marshal/impl/PackageSetBuilder$3
       5: dup
       6: invokespecial #179                // Method org/apache/axis2/jaxws/runtime/description/marshal/impl/PackageSetBuilder$3."<init>":()V
       9: invokestatic  #169                // Method org/apache/axis2/java/security/AccessController.doPrivileged:(Ljava/security/PrivilegedExceptionAction;)Ljava/lang/Object;
      12: checkcast     #180                // class java/lang/ClassLoader
      15: astore_0
      16: goto          66
      19: astore_1
      20: getstatic     #1                  // Field log:Lorg/apache/commons/logging/Log;
      23: invokeinterface #3,  1            // InterfaceMethod org/apache/commons/logging/Log.isDebugEnabled:()Z
      28: ifeq          58
      31: getstatic     #1                  // Field log:Lorg/apache/commons/logging/Log;
      34: new           #6                  // class java/lang/StringBuilder
      37: dup
      38: invokespecial #7                  // Method java/lang/StringBuilder."<init>":()V
      41: ldc           #176                // String Exception thrown from AccessController:
      43: invokevirtual #9                  // Method java/lang/StringBuilder.append:(Ljava/lang/String;)Ljava/lang/StringBuilder;
      46: aload_1
      47: invokevirtual #49                 // Method java/lang/StringBuilder.append:(Ljava/lang/Object;)Ljava/lang/StringBuilder;
      50: invokevirtual #11                 // Method java/lang/StringBuilder.toString:()Ljava/lang/String;
      53: invokeinterface #5,  2            // InterfaceMethod org/apache/commons/logging/Log.debug:(Ljava/lang/Object;)V
      58: aload_1
      59: invokevirtual #173                // Method java/security/PrivilegedActionException.getException:()Ljava/lang/Exception;
      62: checkcast     #181                // class java/lang/RuntimeException
      65: athrow
      66: aload_0
      67: areturn
    Exception table:
       from    to  target type
           2    16    19   Class java/security/PrivilegedActionException

  private static java.lang.String getServiceImplClassName(org.apache.axis2.jaxws.description.EndpointDescription);
    Code:
       0: aconst_null
       1: astore_1
       2: aload_0
       3: ifnull        39
       6: aload_0
       7: invokeinterface #40,  1           // InterfaceMethod org/apache/axis2/jaxws/description/EndpointDescription.getAxisService:()Lorg/apache/axis2/description/AxisService;
      12: astore_2
      13: aload_2
      14: ifnull        39
      17: aload_2
      18: ldc           #183                // String ServiceClass
      20: invokevirtual #184                // Method org/apache/axis2/description/AxisService.getParameter:(Ljava/lang/String;)Lorg/apache/axis2/description/Parameter;
      23: astore_3
      24: aload_3
      25: ifnull        39
      28: aload_3
      29: invokevirtual #185                // Method org/apache/axis2/description/Parameter.getValue:()Ljava/lang/Object;
      32: checkcast     #135                // class java/lang/String
      35: invokevirtual #166                // Method java/lang/String.trim:()Ljava/lang/String;
      38: astore_1
      39: aload_1
      40: areturn

  private static java.lang.annotation.Annotation getAnnotation(java.lang.reflect.AnnotatedElement, java.lang.Class);
    Code:
       0: new           #186                // class org/apache/axis2/jaxws/runtime/description/marshal/impl/PackageSetBuilder$4
       3: dup
       4: aload_0
       5: aload_1
       6: invokespecial #187                // Method org/apache/axis2/jaxws/runtime/description/marshal/impl/PackageSetBuilder$4."<init>":(Ljava/lang/reflect/AnnotatedElement;Ljava/lang/Class;)V
       9: invokestatic  #188                // Method org/apache/axis2/java/security/AccessController.doPrivileged:(Ljava/security/PrivilegedAction;)Ljava/lang/Object;
      12: checkcast     #189                // class java/lang/annotation/Annotation
      15: areturn

  static org.apache.commons.logging.Log access$000();
    Code:
       0: getstatic     #1                  // Field log:Lorg/apache/commons/logging/Log;
       3: areturn

  static {};
    Code:
       0: ldc           #190                // class org/apache/axis2/jaxws/runtime/description/marshal/impl/PackageSetBuilder
       2: invokestatic  #191                // Method org/apache/commons/logging/LogFactory.getLog:(Ljava/lang/Class;)Lorg/apache/commons/logging/Log;
       5: putstatic     #1                  // Field log:Lorg/apache/commons/logging/Log;
       8: iconst_0
       9: anewarray     #108                // class java/lang/Class
      12: putstatic     #146                // Field noClass:[Ljava/lang/Class;
      15: return
}
