Compiled from "ContentHandlerCompressor.java"
public class net.minidev.json.parser.ContentHandlerCompressor implements net.minidev.json.parser.ContentHandler {
  java.lang.Appendable out;

  net.minidev.json.JSONStyle compression;

  int[] stack;

  int pos;

  private void push(int);
    Code:
       0: aload_0
       1: dup
       2: getfield      #1                  // Field pos:I
       5: iconst_2
       6: iadd
       7: putfield      #1                  // Field pos:I
      10: aload_0
      11: getfield      #1                  // Field pos:I
      14: aload_0
      15: getfield      #2                  // Field stack:[I
      18: arraylength
      19: if_icmplt     52
      22: aload_0
      23: getfield      #2                  // Field stack:[I
      26: arraylength
      27: iconst_2
      28: imul
      29: newarray       int
      31: astore_2
      32: aload_0
      33: getfield      #2                  // Field stack:[I
      36: iconst_0
      37: aload_2
      38: iconst_0
      39: aload_0
      40: getfield      #2                  // Field stack:[I
      43: arraylength
      44: invokestatic  #3                  // Method java/lang/System.arraycopy:(Ljava/lang/Object;ILjava/lang/Object;II)V
      47: aload_0
      48: aload_2
      49: putfield      #2                  // Field stack:[I
      52: aload_0
      53: getfield      #2                  // Field stack:[I
      56: aload_0
      57: getfield      #1                  // Field pos:I
      60: iload_1
      61: iastore
      62: aload_0
      63: getfield      #2                  // Field stack:[I
      66: aload_0
      67: getfield      #1                  // Field pos:I
      70: iconst_1
      71: iadd
      72: iconst_0
      73: iastore
      74: return

  private boolean isInObject();
    Code:
       0: aload_0
       1: getfield      #2                  // Field stack:[I
       4: aload_0
       5: getfield      #1                  // Field pos:I
       8: iaload
       9: ifne          16
      12: iconst_1
      13: goto          17
      16: iconst_0
      17: ireturn

  private boolean isInArray();
    Code:
       0: aload_0
       1: getfield      #2                  // Field stack:[I
       4: aload_0
       5: getfield      #1                  // Field pos:I
       8: iaload
       9: iconst_1
      10: if_icmpne     17
      13: iconst_1
      14: goto          18
      17: iconst_0
      18: ireturn

  public net.minidev.json.parser.ContentHandlerCompressor(java.lang.Appendable, net.minidev.json.JSONStyle);
    Code:
       0: aload_0
       1: invokespecial #4                  // Method java/lang/Object."<init>":()V
       4: aload_0
       5: bipush        10
       7: newarray       int
       9: putfield      #2                  // Field stack:[I
      12: aload_0
      13: aload_1
      14: putfield      #5                  // Field out:Ljava/lang/Appendable;
      17: aload_0
      18: aload_2
      19: putfield      #6                  // Field compression:Lnet/minidev/json/JSONStyle;
      22: return

  public void startJSON() throws net.minidev.json.parser.ParseException, java.io.IOException;
    Code:
       0: return

  public void endJSON() throws net.minidev.json.parser.ParseException, java.io.IOException;
    Code:
       0: return

  public boolean startObject() throws net.minidev.json.parser.ParseException, java.io.IOException;
    Code:
       0: aload_0
       1: invokespecial #7                  // Method isInArray:()Z
       4: ifeq          38
       7: aload_0
       8: getfield      #2                  // Field stack:[I
      11: aload_0
      12: getfield      #1                  // Field pos:I
      15: iconst_1
      16: iadd
      17: dup2
      18: iaload
      19: dup_x2
      20: iconst_1
      21: iadd
      22: iastore
      23: ifle          38
      26: aload_0
      27: getfield      #5                  // Field out:Ljava/lang/Appendable;
      30: bipush        44
      32: invokeinterface #8,  2            // InterfaceMethod java/lang/Appendable.append:(C)Ljava/lang/Appendable;
      37: pop
      38: aload_0
      39: getfield      #5                  // Field out:Ljava/lang/Appendable;
      42: bipush        123
      44: invokeinterface #8,  2            // InterfaceMethod java/lang/Appendable.append:(C)Ljava/lang/Appendable;
      49: pop
      50: aload_0
      51: iconst_0
      52: invokespecial #9                  // Method push:(I)V
      55: iconst_0
      56: ireturn

  public boolean endObject() throws net.minidev.json.parser.ParseException, java.io.IOException;
    Code:
       0: aload_0
       1: getfield      #5                  // Field out:Ljava/lang/Appendable;
       4: bipush        125
       6: invokeinterface #8,  2            // InterfaceMethod java/lang/Appendable.append:(C)Ljava/lang/Appendable;
      11: pop
      12: aload_0
      13: dup
      14: getfield      #1                  // Field pos:I
      17: iconst_2
      18: isub
      19: putfield      #1                  // Field pos:I
      22: iconst_0
      23: ireturn

  public boolean startObjectEntry(java.lang.String) throws net.minidev.json.parser.ParseException, java.io.IOException;
    Code:
       0: aload_0
       1: getfield      #2                  // Field stack:[I
       4: aload_0
       5: getfield      #1                  // Field pos:I
       8: iconst_1
       9: iadd
      10: dup2
      11: iaload
      12: dup_x2
      13: iconst_1
      14: iadd
      15: iastore
      16: ifle          31
      19: aload_0
      20: getfield      #5                  // Field out:Ljava/lang/Appendable;
      23: bipush        44
      25: invokeinterface #8,  2            // InterfaceMethod java/lang/Appendable.append:(C)Ljava/lang/Appendable;
      30: pop
      31: aload_1
      32: ifnonnull     50
      35: aload_0
      36: getfield      #5                  // Field out:Ljava/lang/Appendable;
      39: ldc           #10                 // String null
      41: invokeinterface #11,  2           // InterfaceMethod java/lang/Appendable.append:(Ljava/lang/CharSequence;)Ljava/lang/Appendable;
      46: pop
      47: goto          111
      50: aload_0
      51: getfield      #6                  // Field compression:Lnet/minidev/json/JSONStyle;
      54: aload_1
      55: invokevirtual #12                 // Method net/minidev/json/JSONStyle.mustProtectKey:(Ljava/lang/String;)Z
      58: ifne          75
      61: aload_0
      62: getfield      #5                  // Field out:Ljava/lang/Appendable;
      65: aload_1
      66: invokeinterface #11,  2           // InterfaceMethod java/lang/Appendable.append:(Ljava/lang/CharSequence;)Ljava/lang/Appendable;
      71: pop
      72: goto          111
      75: aload_0
      76: getfield      #5                  // Field out:Ljava/lang/Appendable;
      79: bipush        34
      81: invokeinterface #8,  2            // InterfaceMethod java/lang/Appendable.append:(C)Ljava/lang/Appendable;
      86: pop
      87: aload_1
      88: aload_0
      89: getfield      #5                  // Field out:Ljava/lang/Appendable;
      92: aload_0
      93: getfield      #6                  // Field compression:Lnet/minidev/json/JSONStyle;
      96: invokestatic  #13                 // Method net/minidev/json/JSONValue.escape:(Ljava/lang/String;Ljava/lang/Appendable;Lnet/minidev/json/JSONStyle;)V
      99: aload_0
     100: getfield      #5                  // Field out:Ljava/lang/Appendable;
     103: bipush        34
     105: invokeinterface #8,  2            // InterfaceMethod java/lang/Appendable.append:(C)Ljava/lang/Appendable;
     110: pop
     111: aload_0
     112: getfield      #5                  // Field out:Ljava/lang/Appendable;
     115: bipush        58
     117: invokeinterface #8,  2            // InterfaceMethod java/lang/Appendable.append:(C)Ljava/lang/Appendable;
     122: pop
     123: iconst_0
     124: ireturn

  public boolean endObjectEntry() throws net.minidev.json.parser.ParseException, java.io.IOException;
    Code:
       0: iconst_0
       1: ireturn

  public boolean startArray() throws net.minidev.json.parser.ParseException, java.io.IOException;
    Code:
       0: aload_0
       1: invokespecial #7                  // Method isInArray:()Z
       4: ifeq          38
       7: aload_0
       8: getfield      #2                  // Field stack:[I
      11: aload_0
      12: getfield      #1                  // Field pos:I
      15: iconst_1
      16: iadd
      17: dup2
      18: iaload
      19: dup_x2
      20: iconst_1
      21: iadd
      22: iastore
      23: ifle          38
      26: aload_0
      27: getfield      #5                  // Field out:Ljava/lang/Appendable;
      30: bipush        44
      32: invokeinterface #8,  2            // InterfaceMethod java/lang/Appendable.append:(C)Ljava/lang/Appendable;
      37: pop
      38: aload_0
      39: getfield      #5                  // Field out:Ljava/lang/Appendable;
      42: bipush        91
      44: invokeinterface #8,  2            // InterfaceMethod java/lang/Appendable.append:(C)Ljava/lang/Appendable;
      49: pop
      50: aload_0
      51: iconst_1
      52: invokespecial #9                  // Method push:(I)V
      55: iconst_0
      56: ireturn

  public boolean endArray() throws net.minidev.json.parser.ParseException, java.io.IOException;
    Code:
       0: aload_0
       1: getfield      #5                  // Field out:Ljava/lang/Appendable;
       4: bipush        93
       6: invokeinterface #8,  2            // InterfaceMethod java/lang/Appendable.append:(C)Ljava/lang/Appendable;
      11: pop
      12: aload_0
      13: dup
      14: getfield      #1                  // Field pos:I
      17: iconst_2
      18: isub
      19: putfield      #1                  // Field pos:I
      22: iconst_0
      23: ireturn

  public boolean primitive(java.lang.Object) throws net.minidev.json.parser.ParseException, java.io.IOException;
    Code:
       0: aload_0
       1: invokespecial #14                 // Method isInObject:()Z
       4: ifne          38
       7: aload_0
       8: getfield      #2                  // Field stack:[I
      11: aload_0
      12: getfield      #1                  // Field pos:I
      15: iconst_1
      16: iadd
      17: dup2
      18: iaload
      19: dup_x2
      20: iconst_1
      21: iadd
      22: iastore
      23: ifle          38
      26: aload_0
      27: getfield      #5                  // Field out:Ljava/lang/Appendable;
      30: bipush        44
      32: invokeinterface #8,  2            // InterfaceMethod java/lang/Appendable.append:(C)Ljava/lang/Appendable;
      37: pop
      38: aload_1
      39: instanceof    #15                 // class java/lang/String
      42: ifeq          63
      45: aload_0
      46: getfield      #6                  // Field compression:Lnet/minidev/json/JSONStyle;
      49: aload_0
      50: getfield      #5                  // Field out:Ljava/lang/Appendable;
      53: aload_1
      54: checkcast     #15                 // class java/lang/String
      57: invokevirtual #16                 // Method net/minidev/json/JSONStyle.writeString:(Ljava/lang/Appendable;Ljava/lang/String;)V
      60: goto          75
      63: aload_1
      64: aload_0
      65: getfield      #5                  // Field out:Ljava/lang/Appendable;
      68: aload_0
      69: getfield      #6                  // Field compression:Lnet/minidev/json/JSONStyle;
      72: invokestatic  #17                 // Method net/minidev/json/JSONValue.writeJSONString:(Ljava/lang/Object;Ljava/lang/Appendable;Lnet/minidev/json/JSONStyle;)V
      75: iconst_0
      76: ireturn
}
