Compiled from "TieringPicoContainer.java"
class org.picocontainer.containers.TieringPicoContainer$AskingParentForComponent extends java.lang.ThreadLocal {
  private org.picocontainer.containers.TieringPicoContainer$AskingParentForComponent();
    Code:
       0: aload_0
       1: invokespecial #14                 // Method java/lang/ThreadLocal."<init>":()V
       4: return

  protected java.lang.Object initialValue();
    Code:
       0: getstatic     #24                 // Field java/lang/Boolean.FALSE:Ljava/lang/Boolean;
       3: areturn

  org.picocontainer.containers.TieringPicoContainer$AskingParentForComponent(org.picocontainer.containers.TieringPicoContainer$1);
    Code:
       0: aload_0
       1: invokespecial #26                 // Method "<init>":()V
       4: return
}
