Compiled from "HygieneUtilMacros.scala"
public final class monix.execution.misc.HygieneUtilMacros$util$$anonfun$isClean$1 extends scala.runtime.AbstractFunction1<scala.reflect.api.Exprs$Expr<?>, java.lang.Object> implements scala.Serializable {
  public static final long serialVersionUID;

  private final monix.execution.misc.HygieneUtilMacros$util$ $outer;

  public final boolean apply(scala.reflect.api.Exprs$Expr<?>);
    Code:
       0: aload_1
       1: invokeinterface #27,  1           // InterfaceMethod scala/reflect/api/Exprs$Expr.tree:()Lscala/reflect/api/Trees$TreeApi;
       6: astore_2
       7: aload_0
       8: getfield      #29                 // Field $outer:Lmonix/execution/misc/HygieneUtilMacros$util$;
      11: invokevirtual #33                 // Method monix/execution/misc/HygieneUtilMacros$util$.monix$execution$misc$HygieneUtilMacros$util$$$outer:()Lmonix/execution/misc/HygieneUtilMacros;
      14: invokeinterface #39,  1           // InterfaceMethod monix/execution/misc/HygieneUtilMacros.c:()Lscala/reflect/macros/whitebox/Context;
      19: invokeinterface #45,  1           // InterfaceMethod scala/reflect/macros/whitebox/Context.universe:()Lscala/reflect/macros/Universe;
      24: invokevirtual #51                 // Method scala/reflect/macros/Universe.IdentTag:()Lscala/reflect/ClassTag;
      27: aload_2
      28: invokeinterface #57,  2           // InterfaceMethod scala/reflect/ClassTag.unapply:(Ljava/lang/Object;)Lscala/Option;
      33: astore_3
      34: aload_3
      35: invokevirtual #63                 // Method scala/Option.isEmpty:()Z
      38: ifne          165
      41: aload_3
      42: invokevirtual #67                 // Method scala/Option.get:()Ljava/lang/Object;
      45: checkcast     #69                 // class scala/reflect/api/Trees$IdentApi
      48: astore        4
      50: aload_0
      51: getfield      #29                 // Field $outer:Lmonix/execution/misc/HygieneUtilMacros$util$;
      54: invokevirtual #33                 // Method monix/execution/misc/HygieneUtilMacros$util$.monix$execution$misc$HygieneUtilMacros$util$$$outer:()Lmonix/execution/misc/HygieneUtilMacros;
      57: invokeinterface #39,  1           // InterfaceMethod monix/execution/misc/HygieneUtilMacros.c:()Lscala/reflect/macros/whitebox/Context;
      62: invokeinterface #45,  1           // InterfaceMethod scala/reflect/macros/whitebox/Context.universe:()Lscala/reflect/macros/Universe;
      67: invokevirtual #73                 // Method scala/reflect/macros/Universe.Ident:()Lscala/reflect/api/Trees$IdentExtractor;
      70: aload         4
      72: invokevirtual #78                 // Method scala/reflect/api/Trees$IdentExtractor.unapply:(Lscala/reflect/api/Trees$IdentApi;)Lscala/Option;
      75: astore        5
      77: aload         5
      79: invokevirtual #63                 // Method scala/Option.isEmpty:()Z
      82: ifne          165
      85: aload         5
      87: invokevirtual #67                 // Method scala/Option.get:()Ljava/lang/Object;
      90: astore        6
      92: aload_0
      93: getfield      #29                 // Field $outer:Lmonix/execution/misc/HygieneUtilMacros$util$;
      96: invokevirtual #33                 // Method monix/execution/misc/HygieneUtilMacros$util$.monix$execution$misc$HygieneUtilMacros$util$$$outer:()Lmonix/execution/misc/HygieneUtilMacros;
      99: invokeinterface #39,  1           // InterfaceMethod monix/execution/misc/HygieneUtilMacros.c:()Lscala/reflect/macros/whitebox/Context;
     104: invokeinterface #45,  1           // InterfaceMethod scala/reflect/macros/whitebox/Context.universe:()Lscala/reflect/macros/Universe;
     109: invokevirtual #81                 // Method scala/reflect/macros/Universe.TermNameTag:()Lscala/reflect/ClassTag;
     112: aload         6
     114: invokeinterface #57,  2           // InterfaceMethod scala/reflect/ClassTag.unapply:(Ljava/lang/Object;)Lscala/Option;
     119: astore        7
     121: aload         7
     123: invokevirtual #63                 // Method scala/Option.isEmpty:()Z
     126: ifne          165
     129: aload         7
     131: invokevirtual #67                 // Method scala/Option.get:()Ljava/lang/Object;
     134: ifnull        165
     137: aload_2
     138: checkcast     #83                 // class scala/reflect/api/Trees$SymTreeApi
     141: invokeinterface #87,  1           // InterfaceMethod scala/reflect/api/Trees$SymTreeApi.symbol:()Lscala/reflect/api/Symbols$SymbolApi;
     146: invokeinterface #93,  1           // InterfaceMethod scala/reflect/api/Symbols$SymbolApi.asTerm:()Lscala/reflect/api/Symbols$TermSymbolApi;
     151: invokeinterface #98,  1           // InterfaceMethod scala/reflect/api/Symbols$TermSymbolApi.isStable:()Z
     156: ifeq          165
     159: iconst_1
     160: istore        8
     162: goto          255
     165: aload_0
     166: getfield      #29                 // Field $outer:Lmonix/execution/misc/HygieneUtilMacros$util$;
     169: invokevirtual #33                 // Method monix/execution/misc/HygieneUtilMacros$util$.monix$execution$misc$HygieneUtilMacros$util$$$outer:()Lmonix/execution/misc/HygieneUtilMacros;
     172: invokeinterface #39,  1           // InterfaceMethod monix/execution/misc/HygieneUtilMacros.c:()Lscala/reflect/macros/whitebox/Context;
     177: invokeinterface #45,  1           // InterfaceMethod scala/reflect/macros/whitebox/Context.universe:()Lscala/reflect/macros/Universe;
     182: invokevirtual #101                // Method scala/reflect/macros/Universe.FunctionTag:()Lscala/reflect/ClassTag;
     185: aload_2
     186: invokeinterface #57,  2           // InterfaceMethod scala/reflect/ClassTag.unapply:(Ljava/lang/Object;)Lscala/Option;
     191: astore        9
     193: aload         9
     195: invokevirtual #63                 // Method scala/Option.isEmpty:()Z
     198: ifne          246
     201: aload         9
     203: invokevirtual #67                 // Method scala/Option.get:()Ljava/lang/Object;
     206: checkcast     #103                // class scala/reflect/api/Trees$FunctionApi
     209: astore        10
     211: aload_0
     212: getfield      #29                 // Field $outer:Lmonix/execution/misc/HygieneUtilMacros$util$;
     215: invokevirtual #33                 // Method monix/execution/misc/HygieneUtilMacros$util$.monix$execution$misc$HygieneUtilMacros$util$$$outer:()Lmonix/execution/misc/HygieneUtilMacros;
     218: invokeinterface #39,  1           // InterfaceMethod monix/execution/misc/HygieneUtilMacros.c:()Lscala/reflect/macros/whitebox/Context;
     223: invokeinterface #45,  1           // InterfaceMethod scala/reflect/macros/whitebox/Context.universe:()Lscala/reflect/macros/Universe;
     228: invokevirtual #107                // Method scala/reflect/macros/Universe.Function:()Lscala/reflect/api/Trees$FunctionExtractor;
     231: aload         10
     233: invokevirtual #112                // Method scala/reflect/api/Trees$FunctionExtractor.unapply:(Lscala/reflect/api/Trees$FunctionApi;)Lscala/Option;
     236: astore        11
     238: aload         11
     240: invokevirtual #63                 // Method scala/Option.isEmpty:()Z
     243: ifeq          252
     246: iconst_0
     247: istore        8
     249: goto          255
     252: iconst_1
     253: istore        8
     255: iload         8
     257: ireturn

  public final java.lang.Object apply(java.lang.Object);
    Code:
       0: aload_0
       1: aload_1
       2: checkcast     #23                 // class scala/reflect/api/Exprs$Expr
       5: invokevirtual #121                // Method apply:(Lscala/reflect/api/Exprs$Expr;)Z
       8: invokestatic  #127                // Method scala/runtime/BoxesRunTime.boxToBoolean:(Z)Ljava/lang/Boolean;
      11: areturn

  public monix.execution.misc.HygieneUtilMacros$util$$anonfun$isClean$1(monix.execution.misc.HygieneUtilMacros$util$);
    Code:
       0: aload_1
       1: ifnonnull     6
       4: aconst_null
       5: athrow
       6: aload_0
       7: aload_1
       8: putfield      #29                 // Field $outer:Lmonix/execution/misc/HygieneUtilMacros$util$;
      11: aload_0
      12: invokespecial #134                // Method scala/runtime/AbstractFunction1."<init>":()V
      15: return
}
