Compiled from "InlineMacros.scala"
public abstract class monix.execution.misc.InlineMacros$class {
  private static monix.execution.misc.InlineMacros$InlineApply$2$ InlineApply$1$lzycompute(monix.execution.misc.InlineMacros, scala.reflect.api.Names$TermNameApi, scala.runtime.VolatileObjectRef);
    Code:
       0: aload_0
       1: dup
       2: astore_3
       3: monitorenter
       4: aload_2
       5: getfield      #13                 // Field scala/runtime/VolatileObjectRef.elem:Ljava/lang/Object;
       8: ifnonnull     24
      11: aload_2
      12: new           #15                 // class monix/execution/misc/InlineMacros$InlineApply$2$
      15: dup
      16: aload_0
      17: aload_1
      18: invokespecial #19                 // Method monix/execution/misc/InlineMacros$InlineApply$2$."<init>":(Lmonix/execution/misc/InlineMacros;Lscala/reflect/api/Names$TermNameApi;)V
      21: putfield      #13                 // Field scala/runtime/VolatileObjectRef.elem:Ljava/lang/Object;
      24: getstatic     #25                 // Field scala/runtime/BoxedUnit.UNIT:Lscala/runtime/BoxedUnit;
      27: pop
      28: aload_3
      29: monitorexit
      30: aconst_null
      31: pop
      32: aload_2
      33: getfield      #13                 // Field scala/runtime/VolatileObjectRef.elem:Ljava/lang/Object;
      36: checkcast     #15                 // class monix/execution/misc/InlineMacros$InlineApply$2$
      39: areturn
      40: aload_3
      41: monitorexit
      42: athrow
    Exception table:
       from    to  target type
           4    30    40   any

  public static scala.reflect.api.Exprs$Expr inlineAndReset(monix.execution.misc.InlineMacros, scala.reflect.api.Trees$TreeApi);
    Code:
       0: aload_0
       1: invokeinterface #41,  1           // InterfaceMethod monix/execution/misc/InlineMacros.c:()Lscala/reflect/macros/whitebox/Context;
       6: aload_0
       7: aload_1
       8: invokeinterface #45,  2           // InterfaceMethod monix/execution/misc/InlineMacros.inlineAndResetTree:(Lscala/reflect/api/Trees$TreeApi;)Lscala/reflect/api/Trees$TreeApi;
      13: aload_0
      14: invokeinterface #41,  1           // InterfaceMethod monix/execution/misc/InlineMacros.c:()Lscala/reflect/macros/whitebox/Context;
      19: invokeinterface #51,  1           // InterfaceMethod scala/reflect/macros/whitebox/Context.universe:()Lscala/reflect/macros/Universe;
      24: astore_2
      25: aload_0
      26: invokeinterface #41,  1           // InterfaceMethod monix/execution/misc/InlineMacros.c:()Lscala/reflect/macros/whitebox/Context;
      31: invokeinterface #51,  1           // InterfaceMethod scala/reflect/macros/whitebox/Context.universe:()Lscala/reflect/macros/Universe;
      36: invokevirtual #57                 // Method scala/reflect/macros/Universe.rootMirror:()Lscala/reflect/api/Mirror;
      39: astore_3
      40: aload_2
      41: invokevirtual #61                 // Method scala/reflect/macros/Universe.WeakTypeTag:()Lscala/reflect/api/TypeTags$WeakTypeTag$;
      44: aload_3
      45: new           #63                 // class monix/execution/misc/InlineMacros$$typecreator1$1
      48: dup
      49: aload_0
      50: invokespecial #66                 // Method monix/execution/misc/InlineMacros$$typecreator1$1."<init>":(Lmonix/execution/misc/InlineMacros;)V
      53: invokevirtual #72                 // Method scala/reflect/api/TypeTags$WeakTypeTag$.apply:(Lscala/reflect/api/Mirror;Lscala/reflect/api/TypeCreator;)Lscala/reflect/api/TypeTags$WeakTypeTag;
      56: invokeinterface #76,  3           // InterfaceMethod scala/reflect/macros/whitebox/Context.Expr:(Lscala/reflect/api/Trees$TreeApi;Lscala/reflect/api/TypeTags$WeakTypeTag;)Lscala/reflect/api/Exprs$Expr;
      61: areturn

  public static scala.reflect.api.Trees$TreeApi inlineAndResetTree(monix.execution.misc.InlineMacros, scala.reflect.api.Trees$TreeApi);
    Code:
       0: aload_0
       1: aload_1
       2: invokeinterface #87,  2           // InterfaceMethod monix/execution/misc/InlineMacros.inlineApplyRecursive:(Lscala/reflect/api/Trees$TreeApi;)Lscala/reflect/api/Trees$TreeApi;
       7: astore_2
       8: aload_0
       9: invokeinterface #41,  1           // InterfaceMethod monix/execution/misc/InlineMacros.c:()Lscala/reflect/macros/whitebox/Context;
      14: aload_2
      15: invokeinterface #90,  2           // InterfaceMethod scala/reflect/macros/whitebox/Context.untypecheck:(Lscala/reflect/api/Trees$TreeApi;)Lscala/reflect/api/Trees$TreeApi;
      20: astore_3
      21: new           #92                 // class monix/execution/misc/InlineMacros$StripUnApplyNodes$1
      24: dup
      25: aload_0
      26: invokespecial #93                 // Method monix/execution/misc/InlineMacros$StripUnApplyNodes$1."<init>":(Lmonix/execution/misc/InlineMacros;)V
      29: aload_3
      30: invokevirtual #96                 // Method monix/execution/misc/InlineMacros$StripUnApplyNodes$1.transform:(Lscala/reflect/api/Trees$TreeApi;)Lscala/reflect/api/Trees$TreeApi;
      33: areturn

  public static scala.reflect.api.Trees$TreeApi inlineApplyRecursive(monix.execution.misc.InlineMacros, scala.reflect.api.Trees$TreeApi);
    Code:
       0: invokestatic  #102                // Method scala/runtime/VolatileObjectRef.zero:()Lscala/runtime/VolatileObjectRef;
       3: astore_2
       4: aload_0
       5: invokeinterface #41,  1           // InterfaceMethod monix/execution/misc/InlineMacros.c:()Lscala/reflect/macros/whitebox/Context;
      10: invokeinterface #51,  1           // InterfaceMethod scala/reflect/macros/whitebox/Context.universe:()Lscala/reflect/macros/Universe;
      15: invokevirtual #106                // Method scala/reflect/macros/Universe.TermName:()Lscala/reflect/api/Names$TermNameExtractor;
      18: ldc           #107                // String apply
      20: invokevirtual #112                // Method scala/reflect/api/Names$TermNameExtractor.apply:(Ljava/lang/String;)Lscala/reflect/api/Names$TermNameApi;
      23: astore_3
      24: aload_0
      25: aload_3
      26: aload_2
      27: invokestatic  #115                // Method InlineApply$1:(Lmonix/execution/misc/InlineMacros;Lscala/reflect/api/Names$TermNameApi;Lscala/runtime/VolatileObjectRef;)Lmonix/execution/misc/InlineMacros$InlineApply$2$;
      30: aload_1
      31: invokevirtual #116                // Method monix/execution/misc/InlineMacros$InlineApply$2$.transform:(Lscala/reflect/api/Trees$TreeApi;)Lscala/reflect/api/Trees$TreeApi;
      34: areturn

  private static final monix.execution.misc.InlineMacros$InlineApply$2$ InlineApply$1(monix.execution.misc.InlineMacros, scala.reflect.api.Names$TermNameApi, scala.runtime.VolatileObjectRef);
    Code:
       0: aload_2
       1: getfield      #13                 // Field scala/runtime/VolatileObjectRef.elem:Ljava/lang/Object;
       4: ifnonnull     16
       7: aload_0
       8: aload_1
       9: aload_2
      10: invokestatic  #120                // Method InlineApply$1$lzycompute:(Lmonix/execution/misc/InlineMacros;Lscala/reflect/api/Names$TermNameApi;Lscala/runtime/VolatileObjectRef;)Lmonix/execution/misc/InlineMacros$InlineApply$2$;
      13: goto          23
      16: aload_2
      17: getfield      #13                 // Field scala/runtime/VolatileObjectRef.elem:Ljava/lang/Object;
      20: checkcast     #15                 // class monix/execution/misc/InlineMacros$InlineApply$2$
      23: areturn

  public static void $init$(monix.execution.misc.InlineMacros);
    Code:
       0: return
}
