Compiled from "SimpleCache.java"
final class com.ctc.wstx.util.SimpleCache$LimitMap<K, V> extends java.util.LinkedHashMap<K, V> {
  final int mMaxSize;

  public com.ctc.wstx.util.SimpleCache$LimitMap(int);
    Code:
       0: aload_0
       1: iload_1
       2: ldc           #1                  // float 0.8f
       4: iconst_1
       5: invokespecial #2                  // Method java/util/LinkedHashMap."<init>":(IFZ)V
       8: aload_0
       9: iload_1
      10: putfield      #3                  // Field mMaxSize:I
      13: return

  public boolean removeEldestEntry(java.util.Map$Entry<K, V>);
    Code:
       0: aload_0
       1: invokevirtual #4                  // Method size:()I
       4: aload_0
       5: getfield      #3                  // Field mMaxSize:I
       8: if_icmplt     15
      11: iconst_1
      12: goto          16
      15: iconst_0
      16: ireturn
}
