Compiled from "FailFastProblemReporter.java"
public class org.springframework.beans.factory.parsing.FailFastProblemReporter implements org.springframework.beans.factory.parsing.ProblemReporter {
  private org.apache.commons.logging.Log logger;

  public org.springframework.beans.factory.parsing.FailFastProblemReporter();
    Code:
       0: aload_0
       1: invokespecial #1                  // Method java/lang/Object."<init>":()V
       4: aload_0
       5: aload_0
       6: invokevirtual #2                  // Method java/lang/Object.getClass:()Ljava/lang/Class;
       9: invokestatic  #3                  // Method org/apache/commons/logging/LogFactory.getLog:(Ljava/lang/Class;)Lorg/apache/commons/logging/Log;
      12: putfield      #4                  // Field logger:Lorg/apache/commons/logging/Log;
      15: return

  public void setLogger(org.apache.commons.logging.Log);
    Code:
       0: aload_0
       1: aload_1
       2: ifnull        9
       5: aload_1
       6: goto          16
       9: aload_0
      10: invokevirtual #2                  // Method java/lang/Object.getClass:()Ljava/lang/Class;
      13: invokestatic  #3                  // Method org/apache/commons/logging/LogFactory.getLog:(Ljava/lang/Class;)Lorg/apache/commons/logging/Log;
      16: putfield      #4                  // Field logger:Lorg/apache/commons/logging/Log;
      19: return

  public void fatal(org.springframework.beans.factory.parsing.Problem);
    Code:
       0: new           #5                  // class org/springframework/beans/factory/parsing/BeanDefinitionParsingException
       3: dup
       4: aload_1
       5: invokespecial #6                  // Method org/springframework/beans/factory/parsing/BeanDefinitionParsingException."<init>":(Lorg/springframework/beans/factory/parsing/Problem;)V
       8: athrow

  public void error(org.springframework.beans.factory.parsing.Problem);
    Code:
       0: new           #5                  // class org/springframework/beans/factory/parsing/BeanDefinitionParsingException
       3: dup
       4: aload_1
       5: invokespecial #6                  // Method org/springframework/beans/factory/parsing/BeanDefinitionParsingException."<init>":(Lorg/springframework/beans/factory/parsing/Problem;)V
       8: athrow

  public void warning(org.springframework.beans.factory.parsing.Problem);
    Code:
       0: aload_0
       1: getfield      #4                  // Field logger:Lorg/apache/commons/logging/Log;
       4: aload_1
       5: aload_1
       6: invokevirtual #7                  // Method org/springframework/beans/factory/parsing/Problem.getRootCause:()Ljava/lang/Throwable;
       9: invokeinterface #8,  3            // InterfaceMethod org/apache/commons/logging/Log.warn:(Ljava/lang/Object;Ljava/lang/Throwable;)V
      14: return
}
