Compiled from "IpcResponse.java"
public final class io.vertx.tp.ipc.eon.IpcResponse extends com.google.protobuf.GeneratedMessageV3 implements io.vertx.tp.ipc.eon.IpcResponseOrBuilder {
  private static final long serialVersionUID;

  public static final int ENVELOP_FIELD_NUMBER;

  private io.vertx.tp.ipc.eon.IpcEnvelop envelop_;

  public static final int CLIENT_ID_FIELD_NUMBER;

  private volatile java.lang.Object clientId_;

  public static final int OAUTH_SCOPE_FIELD_NUMBER;

  private volatile java.lang.Object oauthScope_;

  private byte memoizedIsInitialized;

  private static final io.vertx.tp.ipc.eon.IpcResponse DEFAULT_INSTANCE;

  private static final com.google.protobuf.Parser<io.vertx.tp.ipc.eon.IpcResponse> PARSER;

  private io.vertx.tp.ipc.eon.IpcResponse(com.google.protobuf.GeneratedMessageV3$Builder<?>);
    Code:
       0: aload_0
       1: aload_1
       2: invokespecial #10                 // Method com/google/protobuf/GeneratedMessageV3."<init>":(Lcom/google/protobuf/GeneratedMessageV3$Builder;)V
       5: aload_0
       6: iconst_m1
       7: putfield      #11                 // Field memoizedIsInitialized:B
      10: return

  private io.vertx.tp.ipc.eon.IpcResponse();
    Code:
       0: aload_0
       1: invokespecial #12                 // Method com/google/protobuf/GeneratedMessageV3."<init>":()V
       4: aload_0
       5: iconst_m1
       6: putfield      #11                 // Field memoizedIsInitialized:B
       9: aload_0
      10: ldc           #13                 // String
      12: putfield      #6                  // Field clientId_:Ljava/lang/Object;
      15: aload_0
      16: ldc           #13                 // String
      18: putfield      #5                  // Field oauthScope_:Ljava/lang/Object;
      21: return

  protected java.lang.Object newInstance(com.google.protobuf.GeneratedMessageV3$UnusedPrivateParameter);
    Code:
       0: new           #14                 // class io/vertx/tp/ipc/eon/IpcResponse
       3: dup
       4: invokespecial #15                 // Method "<init>":()V
       7: areturn

  public final com.google.protobuf.UnknownFieldSet getUnknownFields();
    Code:
       0: aload_0
       1: getfield      #4                  // Field unknownFields:Lcom/google/protobuf/UnknownFieldSet;
       4: areturn

  private io.vertx.tp.ipc.eon.IpcResponse(com.google.protobuf.CodedInputStream, com.google.protobuf.ExtensionRegistryLite) throws com.google.protobuf.InvalidProtocolBufferException;
    Code:
       0: aload_0
       1: invokespecial #15                 // Method "<init>":()V
       4: aload_2
       5: ifnonnull     16
       8: new           #16                 // class java/lang/NullPointerException
      11: dup
      12: invokespecial #17                 // Method java/lang/NullPointerException."<init>":()V
      15: athrow
      16: invokestatic  #18                 // Method com/google/protobuf/UnknownFieldSet.newBuilder:()Lcom/google/protobuf/UnknownFieldSet$Builder;
      19: astore_3
      20: iconst_0
      21: istore        4
      23: iload         4
      25: ifne          195
      28: aload_1
      29: invokevirtual #19                 // Method com/google/protobuf/CodedInputStream.readTag:()I
      32: istore        5
      34: iload         5
      36: lookupswitch  { // 4
                     0: 80
                    10: 86
                    18: 147
                    26: 162
               default: 177
          }
      80: iconst_1
      81: istore        4
      83: goto          192
      86: aconst_null
      87: astore        6
      89: aload_0
      90: getfield      #7                  // Field envelop_:Lio/vertx/tp/ipc/eon/IpcEnvelop;
      93: ifnull        105
      96: aload_0
      97: getfield      #7                  // Field envelop_:Lio/vertx/tp/ipc/eon/IpcEnvelop;
     100: invokevirtual #20                 // Method io/vertx/tp/ipc/eon/IpcEnvelop.toBuilder:()Lio/vertx/tp/ipc/eon/IpcEnvelop$Builder;
     103: astore        6
     105: aload_0
     106: aload_1
     107: invokestatic  #21                 // Method io/vertx/tp/ipc/eon/IpcEnvelop.parser:()Lcom/google/protobuf/Parser;
     110: aload_2
     111: invokevirtual #22                 // Method com/google/protobuf/CodedInputStream.readMessage:(Lcom/google/protobuf/Parser;Lcom/google/protobuf/ExtensionRegistryLite;)Lcom/google/protobuf/MessageLite;
     114: checkcast     #23                 // class io/vertx/tp/ipc/eon/IpcEnvelop
     117: putfield      #7                  // Field envelop_:Lio/vertx/tp/ipc/eon/IpcEnvelop;
     120: aload         6
     122: ifnull        192
     125: aload         6
     127: aload_0
     128: getfield      #7                  // Field envelop_:Lio/vertx/tp/ipc/eon/IpcEnvelop;
     131: invokevirtual #24                 // Method io/vertx/tp/ipc/eon/IpcEnvelop$Builder.mergeFrom:(Lio/vertx/tp/ipc/eon/IpcEnvelop;)Lio/vertx/tp/ipc/eon/IpcEnvelop$Builder;
     134: pop
     135: aload_0
     136: aload         6
     138: invokevirtual #25                 // Method io/vertx/tp/ipc/eon/IpcEnvelop$Builder.buildPartial:()Lio/vertx/tp/ipc/eon/IpcEnvelop;
     141: putfield      #7                  // Field envelop_:Lio/vertx/tp/ipc/eon/IpcEnvelop;
     144: goto          192
     147: aload_1
     148: invokevirtual #26                 // Method com/google/protobuf/CodedInputStream.readStringRequireUtf8:()Ljava/lang/String;
     151: astore        6
     153: aload_0
     154: aload         6
     156: putfield      #6                  // Field clientId_:Ljava/lang/Object;
     159: goto          192
     162: aload_1
     163: invokevirtual #26                 // Method com/google/protobuf/CodedInputStream.readStringRequireUtf8:()Ljava/lang/String;
     166: astore        6
     168: aload_0
     169: aload         6
     171: putfield      #5                  // Field oauthScope_:Ljava/lang/Object;
     174: goto          192
     177: aload_0
     178: aload_1
     179: aload_3
     180: aload_2
     181: iload         5
     183: invokevirtual #27                 // Method parseUnknownField:(Lcom/google/protobuf/CodedInputStream;Lcom/google/protobuf/UnknownFieldSet$Builder;Lcom/google/protobuf/ExtensionRegistryLite;I)Z
     186: ifne          192
     189: iconst_1
     190: istore        4
     192: goto          23
     195: aload_0
     196: aload_3
     197: invokevirtual #28                 // Method com/google/protobuf/UnknownFieldSet$Builder.build:()Lcom/google/protobuf/UnknownFieldSet;
     200: putfield      #4                  // Field unknownFields:Lcom/google/protobuf/UnknownFieldSet;
     203: aload_0
     204: invokevirtual #29                 // Method makeExtensionsImmutable:()V
     207: goto          252
     210: astore        4
     212: aload         4
     214: aload_0
     215: invokevirtual #31                 // Method com/google/protobuf/InvalidProtocolBufferException.setUnfinishedMessage:(Lcom/google/protobuf/MessageLite;)Lcom/google/protobuf/InvalidProtocolBufferException;
     218: athrow
     219: astore        4
     221: new           #30                 // class com/google/protobuf/InvalidProtocolBufferException
     224: dup
     225: aload         4
     227: invokespecial #33                 // Method com/google/protobuf/InvalidProtocolBufferException."<init>":(Ljava/io/IOException;)V
     230: aload_0
     231: invokevirtual #31                 // Method com/google/protobuf/InvalidProtocolBufferException.setUnfinishedMessage:(Lcom/google/protobuf/MessageLite;)Lcom/google/protobuf/InvalidProtocolBufferException;
     234: athrow
     235: astore        7
     237: aload_0
     238: aload_3
     239: invokevirtual #28                 // Method com/google/protobuf/UnknownFieldSet$Builder.build:()Lcom/google/protobuf/UnknownFieldSet;
     242: putfield      #4                  // Field unknownFields:Lcom/google/protobuf/UnknownFieldSet;
     245: aload_0
     246: invokevirtual #29                 // Method makeExtensionsImmutable:()V
     249: aload         7
     251: athrow
     252: return
    Exception table:
       from    to  target type
          20   195   210   Class com/google/protobuf/InvalidProtocolBufferException
          20   195   219   Class java/io/IOException
          20   195   235   any
         210   237   235   any

  public static final com.google.protobuf.Descriptors$Descriptor getDescriptor();
    Code:
       0: getstatic     #34                 // Field io/vertx/tp/ipc/eon/UpEnvelop.internal_static_io_vertx_tp_ipc_eon_IpcResponse_descriptor:Lcom/google/protobuf/Descriptors$Descriptor;
       3: areturn

  protected com.google.protobuf.GeneratedMessageV3$FieldAccessorTable internalGetFieldAccessorTable();
    Code:
       0: getstatic     #35                 // Field io/vertx/tp/ipc/eon/UpEnvelop.internal_static_io_vertx_tp_ipc_eon_IpcResponse_fieldAccessorTable:Lcom/google/protobuf/GeneratedMessageV3$FieldAccessorTable;
       3: ldc           #14                 // class io/vertx/tp/ipc/eon/IpcResponse
       5: ldc           #36                 // class io/vertx/tp/ipc/eon/IpcResponse$Builder
       7: invokevirtual #37                 // Method com/google/protobuf/GeneratedMessageV3$FieldAccessorTable.ensureFieldAccessorsInitialized:(Ljava/lang/Class;Ljava/lang/Class;)Lcom/google/protobuf/GeneratedMessageV3$FieldAccessorTable;
      10: areturn

  public boolean hasEnvelop();
    Code:
       0: aload_0
       1: getfield      #7                  // Field envelop_:Lio/vertx/tp/ipc/eon/IpcEnvelop;
       4: ifnull        11
       7: iconst_1
       8: goto          12
      11: iconst_0
      12: ireturn

  public io.vertx.tp.ipc.eon.IpcEnvelop getEnvelop();
    Code:
       0: aload_0
       1: getfield      #7                  // Field envelop_:Lio/vertx/tp/ipc/eon/IpcEnvelop;
       4: ifnonnull     13
       7: invokestatic  #38                 // Method io/vertx/tp/ipc/eon/IpcEnvelop.getDefaultInstance:()Lio/vertx/tp/ipc/eon/IpcEnvelop;
      10: goto          17
      13: aload_0
      14: getfield      #7                  // Field envelop_:Lio/vertx/tp/ipc/eon/IpcEnvelop;
      17: areturn

  public io.vertx.tp.ipc.eon.IpcEnvelopOrBuilder getEnvelopOrBuilder();
    Code:
       0: aload_0
       1: invokevirtual #39                 // Method getEnvelop:()Lio/vertx/tp/ipc/eon/IpcEnvelop;
       4: areturn

  public java.lang.String getClientId();
    Code:
       0: aload_0
       1: getfield      #6                  // Field clientId_:Ljava/lang/Object;
       4: astore_1
       5: aload_1
       6: instanceof    #40                 // class java/lang/String
       9: ifeq          17
      12: aload_1
      13: checkcast     #40                 // class java/lang/String
      16: areturn
      17: aload_1
      18: checkcast     #41                 // class com/google/protobuf/ByteString
      21: astore_2
      22: aload_2
      23: invokevirtual #42                 // Method com/google/protobuf/ByteString.toStringUtf8:()Ljava/lang/String;
      26: astore_3
      27: aload_0
      28: aload_3
      29: putfield      #6                  // Field clientId_:Ljava/lang/Object;
      32: aload_3
      33: areturn

  public com.google.protobuf.ByteString getClientIdBytes();
    Code:
       0: aload_0
       1: getfield      #6                  // Field clientId_:Ljava/lang/Object;
       4: astore_1
       5: aload_1
       6: instanceof    #40                 // class java/lang/String
       9: ifeq          27
      12: aload_1
      13: checkcast     #40                 // class java/lang/String
      16: invokestatic  #43                 // Method com/google/protobuf/ByteString.copyFromUtf8:(Ljava/lang/String;)Lcom/google/protobuf/ByteString;
      19: astore_2
      20: aload_0
      21: aload_2
      22: putfield      #6                  // Field clientId_:Ljava/lang/Object;
      25: aload_2
      26: areturn
      27: aload_1
      28: checkcast     #41                 // class com/google/protobuf/ByteString
      31: areturn

  public java.lang.String getOauthScope();
    Code:
       0: aload_0
       1: getfield      #5                  // Field oauthScope_:Ljava/lang/Object;
       4: astore_1
       5: aload_1
       6: instanceof    #40                 // class java/lang/String
       9: ifeq          17
      12: aload_1
      13: checkcast     #40                 // class java/lang/String
      16: areturn
      17: aload_1
      18: checkcast     #41                 // class com/google/protobuf/ByteString
      21: astore_2
      22: aload_2
      23: invokevirtual #42                 // Method com/google/protobuf/ByteString.toStringUtf8:()Ljava/lang/String;
      26: astore_3
      27: aload_0
      28: aload_3
      29: putfield      #5                  // Field oauthScope_:Ljava/lang/Object;
      32: aload_3
      33: areturn

  public com.google.protobuf.ByteString getOauthScopeBytes();
    Code:
       0: aload_0
       1: getfield      #5                  // Field oauthScope_:Ljava/lang/Object;
       4: astore_1
       5: aload_1
       6: instanceof    #40                 // class java/lang/String
       9: ifeq          27
      12: aload_1
      13: checkcast     #40                 // class java/lang/String
      16: invokestatic  #43                 // Method com/google/protobuf/ByteString.copyFromUtf8:(Ljava/lang/String;)Lcom/google/protobuf/ByteString;
      19: astore_2
      20: aload_0
      21: aload_2
      22: putfield      #5                  // Field oauthScope_:Ljava/lang/Object;
      25: aload_2
      26: areturn
      27: aload_1
      28: checkcast     #41                 // class com/google/protobuf/ByteString
      31: areturn

  public final boolean isInitialized();
    Code:
       0: aload_0
       1: getfield      #11                 // Field memoizedIsInitialized:B
       4: istore_1
       5: iload_1
       6: iconst_1
       7: if_icmpne     12
      10: iconst_1
      11: ireturn
      12: iload_1
      13: ifne          18
      16: iconst_0
      17: ireturn
      18: aload_0
      19: iconst_1
      20: putfield      #11                 // Field memoizedIsInitialized:B
      23: iconst_1
      24: ireturn

  public void writeTo(com.google.protobuf.CodedOutputStream) throws java.io.IOException;
    Code:
       0: aload_0
       1: getfield      #7                  // Field envelop_:Lio/vertx/tp/ipc/eon/IpcEnvelop;
       4: ifnull        16
       7: aload_1
       8: iconst_1
       9: aload_0
      10: invokevirtual #39                 // Method getEnvelop:()Lio/vertx/tp/ipc/eon/IpcEnvelop;
      13: invokevirtual #44                 // Method com/google/protobuf/CodedOutputStream.writeMessage:(ILcom/google/protobuf/MessageLite;)V
      16: aload_0
      17: invokevirtual #45                 // Method getClientIdBytes:()Lcom/google/protobuf/ByteString;
      20: invokevirtual #46                 // Method com/google/protobuf/ByteString.isEmpty:()Z
      23: ifne          35
      26: aload_1
      27: iconst_2
      28: aload_0
      29: getfield      #6                  // Field clientId_:Ljava/lang/Object;
      32: invokestatic  #47                 // Method com/google/protobuf/GeneratedMessageV3.writeString:(Lcom/google/protobuf/CodedOutputStream;ILjava/lang/Object;)V
      35: aload_0
      36: invokevirtual #48                 // Method getOauthScopeBytes:()Lcom/google/protobuf/ByteString;
      39: invokevirtual #46                 // Method com/google/protobuf/ByteString.isEmpty:()Z
      42: ifne          54
      45: aload_1
      46: iconst_3
      47: aload_0
      48: getfield      #5                  // Field oauthScope_:Ljava/lang/Object;
      51: invokestatic  #47                 // Method com/google/protobuf/GeneratedMessageV3.writeString:(Lcom/google/protobuf/CodedOutputStream;ILjava/lang/Object;)V
      54: aload_0
      55: getfield      #4                  // Field unknownFields:Lcom/google/protobuf/UnknownFieldSet;
      58: aload_1
      59: invokevirtual #49                 // Method com/google/protobuf/UnknownFieldSet.writeTo:(Lcom/google/protobuf/CodedOutputStream;)V
      62: return

  public int getSerializedSize();
    Code:
       0: aload_0
       1: getfield      #50                 // Field memoizedSize:I
       4: istore_1
       5: iload_1
       6: iconst_m1
       7: if_icmpeq     12
      10: iload_1
      11: ireturn
      12: iconst_0
      13: istore_1
      14: aload_0
      15: getfield      #7                  // Field envelop_:Lio/vertx/tp/ipc/eon/IpcEnvelop;
      18: ifnull        32
      21: iload_1
      22: iconst_1
      23: aload_0
      24: invokevirtual #39                 // Method getEnvelop:()Lio/vertx/tp/ipc/eon/IpcEnvelop;
      27: invokestatic  #51                 // Method com/google/protobuf/CodedOutputStream.computeMessageSize:(ILcom/google/protobuf/MessageLite;)I
      30: iadd
      31: istore_1
      32: aload_0
      33: invokevirtual #45                 // Method getClientIdBytes:()Lcom/google/protobuf/ByteString;
      36: invokevirtual #46                 // Method com/google/protobuf/ByteString.isEmpty:()Z
      39: ifne          53
      42: iload_1
      43: iconst_2
      44: aload_0
      45: getfield      #6                  // Field clientId_:Ljava/lang/Object;
      48: invokestatic  #52                 // Method com/google/protobuf/GeneratedMessageV3.computeStringSize:(ILjava/lang/Object;)I
      51: iadd
      52: istore_1
      53: aload_0
      54: invokevirtual #48                 // Method getOauthScopeBytes:()Lcom/google/protobuf/ByteString;
      57: invokevirtual #46                 // Method com/google/protobuf/ByteString.isEmpty:()Z
      60: ifne          74
      63: iload_1
      64: iconst_3
      65: aload_0
      66: getfield      #5                  // Field oauthScope_:Ljava/lang/Object;
      69: invokestatic  #52                 // Method com/google/protobuf/GeneratedMessageV3.computeStringSize:(ILjava/lang/Object;)I
      72: iadd
      73: istore_1
      74: iload_1
      75: aload_0
      76: getfield      #4                  // Field unknownFields:Lcom/google/protobuf/UnknownFieldSet;
      79: invokevirtual #53                 // Method com/google/protobuf/UnknownFieldSet.getSerializedSize:()I
      82: iadd
      83: istore_1
      84: aload_0
      85: iload_1
      86: putfield      #50                 // Field memoizedSize:I
      89: iload_1
      90: ireturn

  public boolean equals(java.lang.Object);
    Code:
       0: aload_1
       1: aload_0
       2: if_acmpne     7
       5: iconst_1
       6: ireturn
       7: aload_1
       8: instanceof    #14                 // class io/vertx/tp/ipc/eon/IpcResponse
      11: ifne          20
      14: aload_0
      15: aload_1
      16: invokespecial #54                 // Method com/google/protobuf/GeneratedMessageV3.equals:(Ljava/lang/Object;)Z
      19: ireturn
      20: aload_1
      21: checkcast     #14                 // class io/vertx/tp/ipc/eon/IpcResponse
      24: astore_2
      25: aload_0
      26: invokevirtual #55                 // Method hasEnvelop:()Z
      29: aload_2
      30: invokevirtual #55                 // Method hasEnvelop:()Z
      33: if_icmpeq     38
      36: iconst_0
      37: ireturn
      38: aload_0
      39: invokevirtual #55                 // Method hasEnvelop:()Z
      42: ifeq          61
      45: aload_0
      46: invokevirtual #39                 // Method getEnvelop:()Lio/vertx/tp/ipc/eon/IpcEnvelop;
      49: aload_2
      50: invokevirtual #39                 // Method getEnvelop:()Lio/vertx/tp/ipc/eon/IpcEnvelop;
      53: invokevirtual #56                 // Method io/vertx/tp/ipc/eon/IpcEnvelop.equals:(Ljava/lang/Object;)Z
      56: ifne          61
      59: iconst_0
      60: ireturn
      61: aload_0
      62: invokevirtual #57                 // Method getClientId:()Ljava/lang/String;
      65: aload_2
      66: invokevirtual #57                 // Method getClientId:()Ljava/lang/String;
      69: invokevirtual #58                 // Method java/lang/String.equals:(Ljava/lang/Object;)Z
      72: ifne          77
      75: iconst_0
      76: ireturn
      77: aload_0
      78: invokevirtual #59                 // Method getOauthScope:()Ljava/lang/String;
      81: aload_2
      82: invokevirtual #59                 // Method getOauthScope:()Ljava/lang/String;
      85: invokevirtual #58                 // Method java/lang/String.equals:(Ljava/lang/Object;)Z
      88: ifne          93
      91: iconst_0
      92: ireturn
      93: aload_0
      94: getfield      #4                  // Field unknownFields:Lcom/google/protobuf/UnknownFieldSet;
      97: aload_2
      98: getfield      #4                  // Field unknownFields:Lcom/google/protobuf/UnknownFieldSet;
     101: invokevirtual #60                 // Method com/google/protobuf/UnknownFieldSet.equals:(Ljava/lang/Object;)Z
     104: ifne          109
     107: iconst_0
     108: ireturn
     109: iconst_1
     110: ireturn

  public int hashCode();
    Code:
       0: aload_0
       1: getfield      #61                 // Field memoizedHashCode:I
       4: ifeq          12
       7: aload_0
       8: getfield      #61                 // Field memoizedHashCode:I
      11: ireturn
      12: bipush        41
      14: istore_1
      15: bipush        19
      17: iload_1
      18: imul
      19: invokestatic  #62                 // Method getDescriptor:()Lcom/google/protobuf/Descriptors$Descriptor;
      22: invokevirtual #63                 // Method java/lang/Object.hashCode:()I
      25: iadd
      26: istore_1
      27: aload_0
      28: invokevirtual #55                 // Method hasEnvelop:()Z
      31: ifeq          54
      34: bipush        37
      36: iload_1
      37: imul
      38: iconst_1
      39: iadd
      40: istore_1
      41: bipush        53
      43: iload_1
      44: imul
      45: aload_0
      46: invokevirtual #39                 // Method getEnvelop:()Lio/vertx/tp/ipc/eon/IpcEnvelop;
      49: invokevirtual #64                 // Method io/vertx/tp/ipc/eon/IpcEnvelop.hashCode:()I
      52: iadd
      53: istore_1
      54: bipush        37
      56: iload_1
      57: imul
      58: iconst_2
      59: iadd
      60: istore_1
      61: bipush        53
      63: iload_1
      64: imul
      65: aload_0
      66: invokevirtual #57                 // Method getClientId:()Ljava/lang/String;
      69: invokevirtual #65                 // Method java/lang/String.hashCode:()I
      72: iadd
      73: istore_1
      74: bipush        37
      76: iload_1
      77: imul
      78: iconst_3
      79: iadd
      80: istore_1
      81: bipush        53
      83: iload_1
      84: imul
      85: aload_0
      86: invokevirtual #59                 // Method getOauthScope:()Ljava/lang/String;
      89: invokevirtual #65                 // Method java/lang/String.hashCode:()I
      92: iadd
      93: istore_1
      94: bipush        29
      96: iload_1
      97: imul
      98: aload_0
      99: getfield      #4                  // Field unknownFields:Lcom/google/protobuf/UnknownFieldSet;
     102: invokevirtual #66                 // Method com/google/protobuf/UnknownFieldSet.hashCode:()I
     105: iadd
     106: istore_1
     107: aload_0
     108: iload_1
     109: putfield      #61                 // Field memoizedHashCode:I
     112: iload_1
     113: ireturn

  public static io.vertx.tp.ipc.eon.IpcResponse parseFrom(java.nio.ByteBuffer) throws com.google.protobuf.InvalidProtocolBufferException;
    Code:
       0: getstatic     #3                  // Field PARSER:Lcom/google/protobuf/Parser;
       3: aload_0
       4: invokeinterface #67,  2           // InterfaceMethod com/google/protobuf/Parser.parseFrom:(Ljava/nio/ByteBuffer;)Ljava/lang/Object;
       9: checkcast     #14                 // class io/vertx/tp/ipc/eon/IpcResponse
      12: areturn

  public static io.vertx.tp.ipc.eon.IpcResponse parseFrom(java.nio.ByteBuffer, com.google.protobuf.ExtensionRegistryLite) throws com.google.protobuf.InvalidProtocolBufferException;
    Code:
       0: getstatic     #3                  // Field PARSER:Lcom/google/protobuf/Parser;
       3: aload_0
       4: aload_1
       5: invokeinterface #68,  3           // InterfaceMethod com/google/protobuf/Parser.parseFrom:(Ljava/nio/ByteBuffer;Lcom/google/protobuf/ExtensionRegistryLite;)Ljava/lang/Object;
      10: checkcast     #14                 // class io/vertx/tp/ipc/eon/IpcResponse
      13: areturn

  public static io.vertx.tp.ipc.eon.IpcResponse parseFrom(com.google.protobuf.ByteString) throws com.google.protobuf.InvalidProtocolBufferException;
    Code:
       0: getstatic     #3                  // Field PARSER:Lcom/google/protobuf/Parser;
       3: aload_0
       4: invokeinterface #69,  2           // InterfaceMethod com/google/protobuf/Parser.parseFrom:(Lcom/google/protobuf/ByteString;)Ljava/lang/Object;
       9: checkcast     #14                 // class io/vertx/tp/ipc/eon/IpcResponse
      12: areturn

  public static io.vertx.tp.ipc.eon.IpcResponse parseFrom(com.google.protobuf.ByteString, com.google.protobuf.ExtensionRegistryLite) throws com.google.protobuf.InvalidProtocolBufferException;
    Code:
       0: getstatic     #3                  // Field PARSER:Lcom/google/protobuf/Parser;
       3: aload_0
       4: aload_1
       5: invokeinterface #70,  3           // InterfaceMethod com/google/protobuf/Parser.parseFrom:(Lcom/google/protobuf/ByteString;Lcom/google/protobuf/ExtensionRegistryLite;)Ljava/lang/Object;
      10: checkcast     #14                 // class io/vertx/tp/ipc/eon/IpcResponse
      13: areturn

  public static io.vertx.tp.ipc.eon.IpcResponse parseFrom(byte[]) throws com.google.protobuf.InvalidProtocolBufferException;
    Code:
       0: getstatic     #3                  // Field PARSER:Lcom/google/protobuf/Parser;
       3: aload_0
       4: invokeinterface #71,  2           // InterfaceMethod com/google/protobuf/Parser.parseFrom:([B)Ljava/lang/Object;
       9: checkcast     #14                 // class io/vertx/tp/ipc/eon/IpcResponse
      12: areturn

  public static io.vertx.tp.ipc.eon.IpcResponse parseFrom(byte[], com.google.protobuf.ExtensionRegistryLite) throws com.google.protobuf.InvalidProtocolBufferException;
    Code:
       0: getstatic     #3                  // Field PARSER:Lcom/google/protobuf/Parser;
       3: aload_0
       4: aload_1
       5: invokeinterface #72,  3           // InterfaceMethod com/google/protobuf/Parser.parseFrom:([BLcom/google/protobuf/ExtensionRegistryLite;)Ljava/lang/Object;
      10: checkcast     #14                 // class io/vertx/tp/ipc/eon/IpcResponse
      13: areturn

  public static io.vertx.tp.ipc.eon.IpcResponse parseFrom(java.io.InputStream) throws java.io.IOException;
    Code:
       0: getstatic     #3                  // Field PARSER:Lcom/google/protobuf/Parser;
       3: aload_0
       4: invokestatic  #73                 // Method com/google/protobuf/GeneratedMessageV3.parseWithIOException:(Lcom/google/protobuf/Parser;Ljava/io/InputStream;)Lcom/google/protobuf/Message;
       7: checkcast     #14                 // class io/vertx/tp/ipc/eon/IpcResponse
      10: areturn

  public static io.vertx.tp.ipc.eon.IpcResponse parseFrom(java.io.InputStream, com.google.protobuf.ExtensionRegistryLite) throws java.io.IOException;
    Code:
       0: getstatic     #3                  // Field PARSER:Lcom/google/protobuf/Parser;
       3: aload_0
       4: aload_1
       5: invokestatic  #74                 // Method com/google/protobuf/GeneratedMessageV3.parseWithIOException:(Lcom/google/protobuf/Parser;Ljava/io/InputStream;Lcom/google/protobuf/ExtensionRegistryLite;)Lcom/google/protobuf/Message;
       8: checkcast     #14                 // class io/vertx/tp/ipc/eon/IpcResponse
      11: areturn

  public static io.vertx.tp.ipc.eon.IpcResponse parseDelimitedFrom(java.io.InputStream) throws java.io.IOException;
    Code:
       0: getstatic     #3                  // Field PARSER:Lcom/google/protobuf/Parser;
       3: aload_0
       4: invokestatic  #75                 // Method com/google/protobuf/GeneratedMessageV3.parseDelimitedWithIOException:(Lcom/google/protobuf/Parser;Ljava/io/InputStream;)Lcom/google/protobuf/Message;
       7: checkcast     #14                 // class io/vertx/tp/ipc/eon/IpcResponse
      10: areturn

  public static io.vertx.tp.ipc.eon.IpcResponse parseDelimitedFrom(java.io.InputStream, com.google.protobuf.ExtensionRegistryLite) throws java.io.IOException;
    Code:
       0: getstatic     #3                  // Field PARSER:Lcom/google/protobuf/Parser;
       3: aload_0
       4: aload_1
       5: invokestatic  #76                 // Method com/google/protobuf/GeneratedMessageV3.parseDelimitedWithIOException:(Lcom/google/protobuf/Parser;Ljava/io/InputStream;Lcom/google/protobuf/ExtensionRegistryLite;)Lcom/google/protobuf/Message;
       8: checkcast     #14                 // class io/vertx/tp/ipc/eon/IpcResponse
      11: areturn

  public static io.vertx.tp.ipc.eon.IpcResponse parseFrom(com.google.protobuf.CodedInputStream) throws java.io.IOException;
    Code:
       0: getstatic     #3                  // Field PARSER:Lcom/google/protobuf/Parser;
       3: aload_0
       4: invokestatic  #77                 // Method com/google/protobuf/GeneratedMessageV3.parseWithIOException:(Lcom/google/protobuf/Parser;Lcom/google/protobuf/CodedInputStream;)Lcom/google/protobuf/Message;
       7: checkcast     #14                 // class io/vertx/tp/ipc/eon/IpcResponse
      10: areturn

  public static io.vertx.tp.ipc.eon.IpcResponse parseFrom(com.google.protobuf.CodedInputStream, com.google.protobuf.ExtensionRegistryLite) throws java.io.IOException;
    Code:
       0: getstatic     #3                  // Field PARSER:Lcom/google/protobuf/Parser;
       3: aload_0
       4: aload_1
       5: invokestatic  #78                 // Method com/google/protobuf/GeneratedMessageV3.parseWithIOException:(Lcom/google/protobuf/Parser;Lcom/google/protobuf/CodedInputStream;Lcom/google/protobuf/ExtensionRegistryLite;)Lcom/google/protobuf/Message;
       8: checkcast     #14                 // class io/vertx/tp/ipc/eon/IpcResponse
      11: areturn

  public io.vertx.tp.ipc.eon.IpcResponse$Builder newBuilderForType();
    Code:
       0: invokestatic  #79                 // Method newBuilder:()Lio/vertx/tp/ipc/eon/IpcResponse$Builder;
       3: areturn

  public static io.vertx.tp.ipc.eon.IpcResponse$Builder newBuilder();
    Code:
       0: getstatic     #80                 // Field DEFAULT_INSTANCE:Lio/vertx/tp/ipc/eon/IpcResponse;
       3: invokevirtual #81                 // Method toBuilder:()Lio/vertx/tp/ipc/eon/IpcResponse$Builder;
       6: areturn

  public static io.vertx.tp.ipc.eon.IpcResponse$Builder newBuilder(io.vertx.tp.ipc.eon.IpcResponse);
    Code:
       0: getstatic     #80                 // Field DEFAULT_INSTANCE:Lio/vertx/tp/ipc/eon/IpcResponse;
       3: invokevirtual #81                 // Method toBuilder:()Lio/vertx/tp/ipc/eon/IpcResponse$Builder;
       6: aload_0
       7: invokevirtual #82                 // Method io/vertx/tp/ipc/eon/IpcResponse$Builder.mergeFrom:(Lio/vertx/tp/ipc/eon/IpcResponse;)Lio/vertx/tp/ipc/eon/IpcResponse$Builder;
      10: areturn

  public io.vertx.tp.ipc.eon.IpcResponse$Builder toBuilder();
    Code:
       0: aload_0
       1: getstatic     #80                 // Field DEFAULT_INSTANCE:Lio/vertx/tp/ipc/eon/IpcResponse;
       4: if_acmpne     18
       7: new           #36                 // class io/vertx/tp/ipc/eon/IpcResponse$Builder
      10: dup
      11: aconst_null
      12: invokespecial #83                 // Method io/vertx/tp/ipc/eon/IpcResponse$Builder."<init>":(Lio/vertx/tp/ipc/eon/IpcResponse$1;)V
      15: goto          30
      18: new           #36                 // class io/vertx/tp/ipc/eon/IpcResponse$Builder
      21: dup
      22: aconst_null
      23: invokespecial #83                 // Method io/vertx/tp/ipc/eon/IpcResponse$Builder."<init>":(Lio/vertx/tp/ipc/eon/IpcResponse$1;)V
      26: aload_0
      27: invokevirtual #82                 // Method io/vertx/tp/ipc/eon/IpcResponse$Builder.mergeFrom:(Lio/vertx/tp/ipc/eon/IpcResponse;)Lio/vertx/tp/ipc/eon/IpcResponse$Builder;
      30: areturn

  protected io.vertx.tp.ipc.eon.IpcResponse$Builder newBuilderForType(com.google.protobuf.GeneratedMessageV3$BuilderParent);
    Code:
       0: new           #36                 // class io/vertx/tp/ipc/eon/IpcResponse$Builder
       3: dup
       4: aload_1
       5: aconst_null
       6: invokespecial #84                 // Method io/vertx/tp/ipc/eon/IpcResponse$Builder."<init>":(Lcom/google/protobuf/GeneratedMessageV3$BuilderParent;Lio/vertx/tp/ipc/eon/IpcResponse$1;)V
       9: astore_2
      10: aload_2
      11: areturn

  public static io.vertx.tp.ipc.eon.IpcResponse getDefaultInstance();
    Code:
       0: getstatic     #80                 // Field DEFAULT_INSTANCE:Lio/vertx/tp/ipc/eon/IpcResponse;
       3: areturn

  public static com.google.protobuf.Parser<io.vertx.tp.ipc.eon.IpcResponse> parser();
    Code:
       0: getstatic     #3                  // Field PARSER:Lcom/google/protobuf/Parser;
       3: areturn

  public com.google.protobuf.Parser<io.vertx.tp.ipc.eon.IpcResponse> getParserForType();
    Code:
       0: getstatic     #3                  // Field PARSER:Lcom/google/protobuf/Parser;
       3: areturn

  public io.vertx.tp.ipc.eon.IpcResponse getDefaultInstanceForType();
    Code:
       0: getstatic     #80                 // Field DEFAULT_INSTANCE:Lio/vertx/tp/ipc/eon/IpcResponse;
       3: areturn

  protected com.google.protobuf.Message$Builder newBuilderForType(com.google.protobuf.GeneratedMessageV3$BuilderParent);
    Code:
       0: aload_0
       1: aload_1
       2: invokevirtual #85                 // Method newBuilderForType:(Lcom/google/protobuf/GeneratedMessageV3$BuilderParent;)Lio/vertx/tp/ipc/eon/IpcResponse$Builder;
       5: areturn

  public com.google.protobuf.Message$Builder toBuilder();
    Code:
       0: aload_0
       1: invokevirtual #81                 // Method toBuilder:()Lio/vertx/tp/ipc/eon/IpcResponse$Builder;
       4: areturn

  public com.google.protobuf.Message$Builder newBuilderForType();
    Code:
       0: aload_0
       1: invokevirtual #86                 // Method newBuilderForType:()Lio/vertx/tp/ipc/eon/IpcResponse$Builder;
       4: areturn

  public com.google.protobuf.MessageLite$Builder toBuilder();
    Code:
       0: aload_0
       1: invokevirtual #81                 // Method toBuilder:()Lio/vertx/tp/ipc/eon/IpcResponse$Builder;
       4: areturn

  public com.google.protobuf.MessageLite$Builder newBuilderForType();
    Code:
       0: aload_0
       1: invokevirtual #86                 // Method newBuilderForType:()Lio/vertx/tp/ipc/eon/IpcResponse$Builder;
       4: areturn

  public com.google.protobuf.MessageLite getDefaultInstanceForType();
    Code:
       0: aload_0
       1: invokevirtual #87                 // Method getDefaultInstanceForType:()Lio/vertx/tp/ipc/eon/IpcResponse;
       4: areturn

  public com.google.protobuf.Message getDefaultInstanceForType();
    Code:
       0: aload_0
       1: invokevirtual #87                 // Method getDefaultInstanceForType:()Lio/vertx/tp/ipc/eon/IpcResponse;
       4: areturn

  static boolean access$200();
    Code:
       0: getstatic     #9                  // Field alwaysUseFieldBuilders:Z
       3: ireturn

  io.vertx.tp.ipc.eon.IpcResponse(com.google.protobuf.GeneratedMessageV3$Builder, io.vertx.tp.ipc.eon.IpcResponse$1);
    Code:
       0: aload_0
       1: aload_1
       2: invokespecial #8                  // Method "<init>":(Lcom/google/protobuf/GeneratedMessageV3$Builder;)V
       5: return

  static io.vertx.tp.ipc.eon.IpcEnvelop access$402(io.vertx.tp.ipc.eon.IpcResponse, io.vertx.tp.ipc.eon.IpcEnvelop);
    Code:
       0: aload_0
       1: aload_1
       2: dup_x1
       3: putfield      #7                  // Field envelop_:Lio/vertx/tp/ipc/eon/IpcEnvelop;
       6: areturn

  static java.lang.Object access$502(io.vertx.tp.ipc.eon.IpcResponse, java.lang.Object);
    Code:
       0: aload_0
       1: aload_1
       2: dup_x1
       3: putfield      #6                  // Field clientId_:Ljava/lang/Object;
       6: areturn

  static java.lang.Object access$602(io.vertx.tp.ipc.eon.IpcResponse, java.lang.Object);
    Code:
       0: aload_0
       1: aload_1
       2: dup_x1
       3: putfield      #5                  // Field oauthScope_:Ljava/lang/Object;
       6: areturn

  static java.lang.Object access$500(io.vertx.tp.ipc.eon.IpcResponse);
    Code:
       0: aload_0
       1: getfield      #6                  // Field clientId_:Ljava/lang/Object;
       4: areturn

  static java.lang.Object access$600(io.vertx.tp.ipc.eon.IpcResponse);
    Code:
       0: aload_0
       1: getfield      #5                  // Field oauthScope_:Ljava/lang/Object;
       4: areturn

  static com.google.protobuf.UnknownFieldSet access$700(io.vertx.tp.ipc.eon.IpcResponse);
    Code:
       0: aload_0
       1: getfield      #4                  // Field unknownFields:Lcom/google/protobuf/UnknownFieldSet;
       4: areturn

  static com.google.protobuf.Parser access$800();
    Code:
       0: getstatic     #3                  // Field PARSER:Lcom/google/protobuf/Parser;
       3: areturn

  static void access$900(com.google.protobuf.ByteString) throws java.lang.IllegalArgumentException;
    Code:
       0: aload_0
       1: invokestatic  #2                  // Method checkByteStringIsUtf8:(Lcom/google/protobuf/ByteString;)V
       4: return

  static void access$1000(com.google.protobuf.ByteString) throws java.lang.IllegalArgumentException;
    Code:
       0: aload_0
       1: invokestatic  #2                  // Method checkByteStringIsUtf8:(Lcom/google/protobuf/ByteString;)V
       4: return

  io.vertx.tp.ipc.eon.IpcResponse(com.google.protobuf.CodedInputStream, com.google.protobuf.ExtensionRegistryLite, io.vertx.tp.ipc.eon.IpcResponse$1) throws com.google.protobuf.InvalidProtocolBufferException;
    Code:
       0: aload_0
       1: aload_1
       2: aload_2
       3: invokespecial #1                  // Method "<init>":(Lcom/google/protobuf/CodedInputStream;Lcom/google/protobuf/ExtensionRegistryLite;)V
       6: return

  static {};
    Code:
       0: new           #14                 // class io/vertx/tp/ipc/eon/IpcResponse
       3: dup
       4: invokespecial #15                 // Method "<init>":()V
       7: putstatic     #80                 // Field DEFAULT_INSTANCE:Lio/vertx/tp/ipc/eon/IpcResponse;
      10: new           #88                 // class io/vertx/tp/ipc/eon/IpcResponse$1
      13: dup
      14: invokespecial #89                 // Method io/vertx/tp/ipc/eon/IpcResponse$1."<init>":()V
      17: putstatic     #3                  // Field PARSER:Lcom/google/protobuf/Parser;
      20: return
}
