Compiled from "EncodedString.java"
public class org.apache.wss4j.binding.wss10.EncodedString extends org.apache.wss4j.binding.wss10.AttributedString {
  private java.lang.String encodingType;

  public org.apache.wss4j.binding.wss10.EncodedString();
    Code:
       0: aload_0
       1: invokespecial #1                  // Method org/apache/wss4j/binding/wss10/AttributedString."<init>":()V
       4: return

  public java.lang.String getEncodingType();
    Code:
       0: aload_0
       1: getfield      #2                  // Field encodingType:Ljava/lang/String;
       4: areturn

  public void setEncodingType(java.lang.String);
    Code:
       0: aload_0
       1: aload_1
       2: putfield      #2                  // Field encodingType:Ljava/lang/String;
       5: return
}
