Compiled from "KeyIdentifierType.java"
public class org.apache.wss4j.binding.wss10.KeyIdentifierType extends org.apache.wss4j.binding.wss10.EncodedString {
  private java.lang.String valueType;

  public org.apache.wss4j.binding.wss10.KeyIdentifierType();
    Code:
       0: aload_0
       1: invokespecial #1                  // Method org/apache/wss4j/binding/wss10/EncodedString."<init>":()V
       4: return

  public java.lang.String getValueType();
    Code:
       0: aload_0
       1: getfield      #2                  // Field valueType:Ljava/lang/String;
       4: areturn

  public void setValueType(java.lang.String);
    Code:
       0: aload_0
       1: aload_1
       2: putfield      #2                  // Field valueType:Ljava/lang/String;
       5: return
}
