Compiled from "MessageConsumer.java"
class io.vlingo.lattice.exchange.rabbitmq.MessageConsumer {
  private final boolean autoAcknowledged;

  private final io.vlingo.lattice.exchange.rabbitmq.BrokerQueue queue;

  private boolean closed;

  private java.lang.String tag;

  static io.vlingo.lattice.exchange.rabbitmq.MessageConsumer autoAcknowledgedInstance(io.vlingo.lattice.exchange.rabbitmq.BrokerQueue);
    Code:
       0: aload_0
       1: iconst_1
       2: invokestatic  #2                  // Method instance:(Lio/vlingo/lattice/exchange/rabbitmq/BrokerQueue;Z)Lio/vlingo/lattice/exchange/rabbitmq/MessageConsumer;
       5: areturn

  static io.vlingo.lattice.exchange.rabbitmq.MessageConsumer instance(io.vlingo.lattice.exchange.rabbitmq.BrokerQueue);
    Code:
       0: new           #3                  // class io/vlingo/lattice/exchange/rabbitmq/MessageConsumer
       3: dup
       4: aload_0
       5: iconst_0
       6: invokespecial #4                  // Method "<init>":(Lio/vlingo/lattice/exchange/rabbitmq/BrokerQueue;Z)V
       9: areturn

  static io.vlingo.lattice.exchange.rabbitmq.MessageConsumer instance(io.vlingo.lattice.exchange.rabbitmq.BrokerQueue, boolean);
    Code:
       0: new           #3                  // class io/vlingo/lattice/exchange/rabbitmq/MessageConsumer
       3: dup
       4: aload_0
       5: iload_1
       6: invokespecial #4                  // Method "<init>":(Lio/vlingo/lattice/exchange/rabbitmq/BrokerQueue;Z)V
       9: areturn

  void close();
    Code:
       0: aload_0
       1: iconst_1
       2: putfield      #5                  // Field closed:Z
       5: aload_0
       6: getfield      #6                  // Field queue:Lio/vlingo/lattice/exchange/rabbitmq/BrokerQueue;
       9: invokevirtual #7                  // Method io/vlingo/lattice/exchange/rabbitmq/BrokerQueue.close:()V
      12: return

  boolean isClosed();
    Code:
       0: aload_0
       1: getfield      #5                  // Field closed:Z
       4: ireturn

  void receiveAll(io.vlingo.lattice.exchange.rabbitmq.MessageListener);
    Code:
       0: aload_0
       1: aload_1
       2: invokespecial #8                  // Method receiveFor:(Lio/vlingo/lattice/exchange/rabbitmq/MessageListener;)V
       5: return

  java.lang.String tag();
    Code:
       0: aload_0
       1: getfield      #9                  // Field tag:Ljava/lang/String;
       4: areturn

  protected io.vlingo.lattice.exchange.rabbitmq.MessageConsumer(io.vlingo.lattice.exchange.rabbitmq.BrokerQueue, boolean);
    Code:
       0: aload_0
       1: invokespecial #10                 // Method java/lang/Object."<init>":()V
       4: aload_0
       5: aload_1
       6: putfield      #6                  // Field queue:Lio/vlingo/lattice/exchange/rabbitmq/BrokerQueue;
       9: aload_0
      10: iload_2
      11: putfield      #1                  // Field autoAcknowledged:Z
      14: aload_0
      15: ldc           #11                 // String
      17: putfield      #9                  // Field tag:Ljava/lang/String;
      20: aload_0
      21: invokespecial #12                 // Method equalizeDistribution:()V
      24: return

  protected io.vlingo.lattice.exchange.rabbitmq.BrokerQueue queue();
    Code:
       0: aload_0
       1: getfield      #6                  // Field queue:Lio/vlingo/lattice/exchange/rabbitmq/BrokerQueue;
       4: areturn

  private void equalizeDistribution();
    Code:
       0: aload_0
       1: getfield      #6                  // Field queue:Lio/vlingo/lattice/exchange/rabbitmq/BrokerQueue;
       4: getfield      #13                 // Field io/vlingo/lattice/exchange/rabbitmq/BrokerQueue.connection:Lio/vlingo/lattice/exchange/rabbitmq/BrokerConnection;
       7: invokevirtual #14                 // Method io/vlingo/lattice/exchange/rabbitmq/BrokerConnection.channel:()Lcom/rabbitmq/client/Channel;
      10: iconst_1
      11: invokeinterface #15,  2           // InterfaceMethod com/rabbitmq/client/Channel.basicQos:(I)V
      16: goto          31
      19: astore_1
      20: new           #17                 // class io/vlingo/lattice/exchange/ExchangeException
      23: dup
      24: ldc           #18                 // String Cannot equalize distribution.
      26: aload_1
      27: invokespecial #19                 // Method io/vlingo/lattice/exchange/ExchangeException."<init>":(Ljava/lang/String;Ljava/lang/Throwable;)V
      30: athrow
      31: return
    Exception table:
       from    to  target type
           0    16    19   Class java/io/IOException

  private void receiveFor(io.vlingo.lattice.exchange.rabbitmq.MessageListener);
    Code:
       0: aload_0
       1: getfield      #6                  // Field queue:Lio/vlingo/lattice/exchange/rabbitmq/BrokerQueue;
       4: getfield      #13                 // Field io/vlingo/lattice/exchange/rabbitmq/BrokerQueue.connection:Lio/vlingo/lattice/exchange/rabbitmq/BrokerConnection;
       7: invokevirtual #14                 // Method io/vlingo/lattice/exchange/rabbitmq/BrokerConnection.channel:()Lcom/rabbitmq/client/Channel;
      10: astore_2
      11: aload_0
      12: aload_2
      13: aload_0
      14: getfield      #6                  // Field queue:Lio/vlingo/lattice/exchange/rabbitmq/BrokerQueue;
      17: invokevirtual #20                 // Method io/vlingo/lattice/exchange/rabbitmq/BrokerQueue.name:()Ljava/lang/String;
      20: aload_0
      21: getfield      #1                  // Field autoAcknowledged:Z
      24: new           #21                 // class io/vlingo/lattice/exchange/rabbitmq/MessageConsumer$DispatchingConsumer
      27: dup
      28: aload_0
      29: aload_2
      30: aload_1
      31: invokespecial #22                 // Method io/vlingo/lattice/exchange/rabbitmq/MessageConsumer$DispatchingConsumer."<init>":(Lio/vlingo/lattice/exchange/rabbitmq/MessageConsumer;Lcom/rabbitmq/client/Channel;Lio/vlingo/lattice/exchange/rabbitmq/MessageListener;)V
      34: invokeinterface #23,  4           // InterfaceMethod com/rabbitmq/client/Channel.basicConsume:(Ljava/lang/String;ZLcom/rabbitmq/client/Consumer;)Ljava/lang/String;
      39: putfield      #9                  // Field tag:Ljava/lang/String;
      42: goto          77
      45: astore_3
      46: new           #17                 // class io/vlingo/lattice/exchange/ExchangeException
      49: dup
      50: new           #24                 // class java/lang/StringBuilder
      53: dup
      54: invokespecial #25                 // Method java/lang/StringBuilder."<init>":()V
      57: ldc           #26                 // String Failed to initiate consume because:
      59: invokevirtual #27                 // Method java/lang/StringBuilder.append:(Ljava/lang/String;)Ljava/lang/StringBuilder;
      62: aload_3
      63: invokevirtual #28                 // Method java/io/IOException.getMessage:()Ljava/lang/String;
      66: invokevirtual #27                 // Method java/lang/StringBuilder.append:(Ljava/lang/String;)Ljava/lang/StringBuilder;
      69: invokevirtual #29                 // Method java/lang/StringBuilder.toString:()Ljava/lang/String;
      72: aload_3
      73: invokespecial #19                 // Method io/vlingo/lattice/exchange/ExchangeException."<init>":(Ljava/lang/String;Ljava/lang/Throwable;)V
      76: athrow
      77: return
    Exception table:
       from    to  target type
          11    42    45   Class java/io/IOException

  static boolean access$000(io.vlingo.lattice.exchange.rabbitmq.MessageConsumer);
    Code:
       0: aload_0
       1: getfield      #1                  // Field autoAcknowledged:Z
       4: ireturn
}
