Compiled from "Cache.java"
class okhttp3.Cache$1 implements okhttp3.internal.cache.InternalCache {
  final okhttp3.Cache this$0;

  okhttp3.Cache$1(okhttp3.Cache);
    Code:
       0: aload_0
       1: aload_1
       2: putfield      #1                  // Field this$0:Lokhttp3/Cache;
       5: aload_0
       6: invokespecial #2                  // Method java/lang/Object."<init>":()V
       9: return

  public okhttp3.Response get(okhttp3.Request) throws java.io.IOException;
    Code:
       0: aload_0
       1: getfield      #1                  // Field this$0:Lokhttp3/Cache;
       4: aload_1
       5: invokevirtual #3                  // Method okhttp3/Cache.get:(Lokhttp3/Request;)Lokhttp3/Response;
       8: areturn

  public okhttp3.internal.cache.CacheRequest put(okhttp3.Response) throws java.io.IOException;
    Code:
       0: aload_0
       1: getfield      #1                  // Field this$0:Lokhttp3/Cache;
       4: aload_1
       5: invokevirtual #4                  // Method okhttp3/Cache.put:(Lokhttp3/Response;)Lokhttp3/internal/cache/CacheRequest;
       8: areturn

  public void remove(okhttp3.Request) throws java.io.IOException;
    Code:
       0: aload_0
       1: getfield      #1                  // Field this$0:Lokhttp3/Cache;
       4: aload_1
       5: invokevirtual #5                  // Method okhttp3/Cache.remove:(Lokhttp3/Request;)V
       8: return

  public void update(okhttp3.Response, okhttp3.Response);
    Code:
       0: aload_0
       1: getfield      #1                  // Field this$0:Lokhttp3/Cache;
       4: aload_1
       5: aload_2
       6: invokevirtual #6                  // Method okhttp3/Cache.update:(Lokhttp3/Response;Lokhttp3/Response;)V
       9: return

  public void trackConditionalCacheHit();
    Code:
       0: aload_0
       1: getfield      #1                  // Field this$0:Lokhttp3/Cache;
       4: invokevirtual #7                  // Method okhttp3/Cache.trackConditionalCacheHit:()V
       7: return

  public void trackResponse(okhttp3.internal.cache.CacheStrategy);
    Code:
       0: aload_0
       1: getfield      #1                  // Field this$0:Lokhttp3/Cache;
       4: aload_1
       5: invokevirtual #8                  // Method okhttp3/Cache.trackResponse:(Lokhttp3/internal/cache/CacheStrategy;)V
       8: return
}
