Compiled from "Headers.java"
public final class okhttp3.Headers {
  private final java.lang.String[] namesAndValues;

  okhttp3.Headers(okhttp3.Headers$Builder);
    Code:
       0: aload_0
       1: invokespecial #1                  // Method java/lang/Object."<init>":()V
       4: aload_0
       5: aload_1
       6: getfield      #2                  // Field okhttp3/Headers$Builder.namesAndValues:Ljava/util/List;
       9: aload_1
      10: getfield      #2                  // Field okhttp3/Headers$Builder.namesAndValues:Ljava/util/List;
      13: invokeinterface #3,  1            // InterfaceMethod java/util/List.size:()I
      18: anewarray     #4                  // class java/lang/String
      21: invokeinterface #5,  2            // InterfaceMethod java/util/List.toArray:([Ljava/lang/Object;)[Ljava/lang/Object;
      26: checkcast     #6                  // class "[Ljava/lang/String;"
      29: putfield      #7                  // Field namesAndValues:[Ljava/lang/String;
      32: return

  private okhttp3.Headers(java.lang.String[]);
    Code:
       0: aload_0
       1: invokespecial #1                  // Method java/lang/Object."<init>":()V
       4: aload_0
       5: aload_1
       6: putfield      #7                  // Field namesAndValues:[Ljava/lang/String;
       9: return

  public java.lang.String get(java.lang.String);
    Code:
       0: aload_0
       1: getfield      #7                  // Field namesAndValues:[Ljava/lang/String;
       4: aload_1
       5: invokestatic  #8                  // Method get:([Ljava/lang/String;Ljava/lang/String;)Ljava/lang/String;
       8: areturn

  public java.util.Date getDate(java.lang.String);
    Code:
       0: aload_0
       1: aload_1
       2: invokevirtual #9                  // Method get:(Ljava/lang/String;)Ljava/lang/String;
       5: astore_2
       6: aload_2
       7: ifnull        17
      10: aload_2
      11: invokestatic  #10                 // Method okhttp3/internal/http/HttpDate.parse:(Ljava/lang/String;)Ljava/util/Date;
      14: goto          18
      17: aconst_null
      18: areturn

  public java.time.Instant getInstant(java.lang.String);
    Code:
       0: aload_0
       1: aload_1
       2: invokevirtual #11                 // Method getDate:(Ljava/lang/String;)Ljava/util/Date;
       5: astore_2
       6: aload_2
       7: ifnull        17
      10: aload_2
      11: invokevirtual #12                 // Method java/util/Date.toInstant:()Ljava/time/Instant;
      14: goto          18
      17: aconst_null
      18: areturn

  public int size();
    Code:
       0: aload_0
       1: getfield      #7                  // Field namesAndValues:[Ljava/lang/String;
       4: arraylength
       5: iconst_2
       6: idiv
       7: ireturn

  public java.lang.String name(int);
    Code:
       0: aload_0
       1: getfield      #7                  // Field namesAndValues:[Ljava/lang/String;
       4: iload_1
       5: iconst_2
       6: imul
       7: aaload
       8: areturn

  public java.lang.String value(int);
    Code:
       0: aload_0
       1: getfield      #7                  // Field namesAndValues:[Ljava/lang/String;
       4: iload_1
       5: iconst_2
       6: imul
       7: iconst_1
       8: iadd
       9: aaload
      10: areturn

  public java.util.Set<java.lang.String> names();
    Code:
       0: new           #13                 // class java/util/TreeSet
       3: dup
       4: getstatic     #14                 // Field java/lang/String.CASE_INSENSITIVE_ORDER:Ljava/util/Comparator;
       7: invokespecial #15                 // Method java/util/TreeSet."<init>":(Ljava/util/Comparator;)V
      10: astore_1
      11: iconst_0
      12: istore_2
      13: aload_0
      14: invokevirtual #16                 // Method size:()I
      17: istore_3
      18: iload_2
      19: iload_3
      20: if_icmpge     39
      23: aload_1
      24: aload_0
      25: iload_2
      26: invokevirtual #17                 // Method name:(I)Ljava/lang/String;
      29: invokevirtual #18                 // Method java/util/TreeSet.add:(Ljava/lang/Object;)Z
      32: pop
      33: iinc          2, 1
      36: goto          18
      39: aload_1
      40: invokestatic  #19                 // Method java/util/Collections.unmodifiableSet:(Ljava/util/Set;)Ljava/util/Set;
      43: areturn

  public java.util.List<java.lang.String> values(java.lang.String);
    Code:
       0: aconst_null
       1: astore_2
       2: iconst_0
       3: istore_3
       4: aload_0
       5: invokevirtual #16                 // Method size:()I
       8: istore        4
      10: iload_3
      11: iload         4
      13: if_icmpge     59
      16: aload_1
      17: aload_0
      18: iload_3
      19: invokevirtual #17                 // Method name:(I)Ljava/lang/String;
      22: invokevirtual #20                 // Method java/lang/String.equalsIgnoreCase:(Ljava/lang/String;)Z
      25: ifeq          53
      28: aload_2
      29: ifnonnull     41
      32: new           #21                 // class java/util/ArrayList
      35: dup
      36: iconst_2
      37: invokespecial #22                 // Method java/util/ArrayList."<init>":(I)V
      40: astore_2
      41: aload_2
      42: aload_0
      43: iload_3
      44: invokevirtual #23                 // Method value:(I)Ljava/lang/String;
      47: invokeinterface #24,  2           // InterfaceMethod java/util/List.add:(Ljava/lang/Object;)Z
      52: pop
      53: iinc          3, 1
      56: goto          10
      59: aload_2
      60: ifnull        70
      63: aload_2
      64: invokestatic  #25                 // Method java/util/Collections.unmodifiableList:(Ljava/util/List;)Ljava/util/List;
      67: goto          73
      70: invokestatic  #26                 // Method java/util/Collections.emptyList:()Ljava/util/List;
      73: areturn

  public long byteCount();
    Code:
       0: aload_0
       1: getfield      #7                  // Field namesAndValues:[Ljava/lang/String;
       4: arraylength
       5: iconst_2
       6: imul
       7: i2l
       8: lstore_1
       9: iconst_0
      10: istore_3
      11: aload_0
      12: getfield      #7                  // Field namesAndValues:[Ljava/lang/String;
      15: arraylength
      16: istore        4
      18: iload_3
      19: iload         4
      21: if_icmpge     43
      24: lload_1
      25: aload_0
      26: getfield      #7                  // Field namesAndValues:[Ljava/lang/String;
      29: iload_3
      30: aaload
      31: invokevirtual #27                 // Method java/lang/String.length:()I
      34: i2l
      35: ladd
      36: lstore_1
      37: iinc          3, 1
      40: goto          18
      43: lload_1
      44: lreturn

  public okhttp3.Headers$Builder newBuilder();
    Code:
       0: new           #28                 // class okhttp3/Headers$Builder
       3: dup
       4: invokespecial #29                 // Method okhttp3/Headers$Builder."<init>":()V
       7: astore_1
       8: aload_1
       9: getfield      #2                  // Field okhttp3/Headers$Builder.namesAndValues:Ljava/util/List;
      12: aload_0
      13: getfield      #7                  // Field namesAndValues:[Ljava/lang/String;
      16: invokestatic  #30                 // Method java/util/Collections.addAll:(Ljava/util/Collection;[Ljava/lang/Object;)Z
      19: pop
      20: aload_1
      21: areturn

  public boolean equals(java.lang.Object);
    Code:
       0: aload_1
       1: instanceof    #31                 // class okhttp3/Headers
       4: ifeq          28
       7: aload_1
       8: checkcast     #31                 // class okhttp3/Headers
      11: getfield      #7                  // Field namesAndValues:[Ljava/lang/String;
      14: aload_0
      15: getfield      #7                  // Field namesAndValues:[Ljava/lang/String;
      18: invokestatic  #32                 // Method java/util/Arrays.equals:([Ljava/lang/Object;[Ljava/lang/Object;)Z
      21: ifeq          28
      24: iconst_1
      25: goto          29
      28: iconst_0
      29: ireturn

  public int hashCode();
    Code:
       0: aload_0
       1: getfield      #7                  // Field namesAndValues:[Ljava/lang/String;
       4: invokestatic  #33                 // Method java/util/Arrays.hashCode:([Ljava/lang/Object;)I
       7: ireturn

  public java.lang.String toString();
    Code:
       0: new           #34                 // class java/lang/StringBuilder
       3: dup
       4: invokespecial #35                 // Method java/lang/StringBuilder."<init>":()V
       7: astore_1
       8: iconst_0
       9: istore_2
      10: aload_0
      11: invokevirtual #16                 // Method size:()I
      14: istore_3
      15: iload_2
      16: iload_3
      17: if_icmpge     54
      20: aload_1
      21: aload_0
      22: iload_2
      23: invokevirtual #17                 // Method name:(I)Ljava/lang/String;
      26: invokevirtual #36                 // Method java/lang/StringBuilder.append:(Ljava/lang/String;)Ljava/lang/StringBuilder;
      29: ldc           #37                 // String :
      31: invokevirtual #36                 // Method java/lang/StringBuilder.append:(Ljava/lang/String;)Ljava/lang/StringBuilder;
      34: aload_0
      35: iload_2
      36: invokevirtual #23                 // Method value:(I)Ljava/lang/String;
      39: invokevirtual #36                 // Method java/lang/StringBuilder.append:(Ljava/lang/String;)Ljava/lang/StringBuilder;
      42: ldc           #38                 // String \n
      44: invokevirtual #36                 // Method java/lang/StringBuilder.append:(Ljava/lang/String;)Ljava/lang/StringBuilder;
      47: pop
      48: iinc          2, 1
      51: goto          15
      54: aload_1
      55: invokevirtual #39                 // Method java/lang/StringBuilder.toString:()Ljava/lang/String;
      58: areturn

  public java.util.Map<java.lang.String, java.util.List<java.lang.String>> toMultimap();
    Code:
       0: new           #40                 // class java/util/TreeMap
       3: dup
       4: getstatic     #14                 // Field java/lang/String.CASE_INSENSITIVE_ORDER:Ljava/util/Comparator;
       7: invokespecial #41                 // Method java/util/TreeMap."<init>":(Ljava/util/Comparator;)V
      10: astore_1
      11: iconst_0
      12: istore_2
      13: aload_0
      14: invokevirtual #16                 // Method size:()I
      17: istore_3
      18: iload_2
      19: iload_3
      20: if_icmpge     94
      23: aload_0
      24: iload_2
      25: invokevirtual #17                 // Method name:(I)Ljava/lang/String;
      28: getstatic     #42                 // Field java/util/Locale.US:Ljava/util/Locale;
      31: invokevirtual #43                 // Method java/lang/String.toLowerCase:(Ljava/util/Locale;)Ljava/lang/String;
      34: astore        4
      36: aload_1
      37: aload         4
      39: invokeinterface #44,  2           // InterfaceMethod java/util/Map.get:(Ljava/lang/Object;)Ljava/lang/Object;
      44: checkcast     #45                 // class java/util/List
      47: astore        5
      49: aload         5
      51: ifnonnull     75
      54: new           #21                 // class java/util/ArrayList
      57: dup
      58: iconst_2
      59: invokespecial #22                 // Method java/util/ArrayList."<init>":(I)V
      62: astore        5
      64: aload_1
      65: aload         4
      67: aload         5
      69: invokeinterface #46,  3           // InterfaceMethod java/util/Map.put:(Ljava/lang/Object;Ljava/lang/Object;)Ljava/lang/Object;
      74: pop
      75: aload         5
      77: aload_0
      78: iload_2
      79: invokevirtual #23                 // Method value:(I)Ljava/lang/String;
      82: invokeinterface #24,  2           // InterfaceMethod java/util/List.add:(Ljava/lang/Object;)Z
      87: pop
      88: iinc          2, 1
      91: goto          18
      94: aload_1
      95: areturn

  private static java.lang.String get(java.lang.String[], java.lang.String);
    Code:
       0: aload_0
       1: arraylength
       2: iconst_2
       3: isub
       4: istore_2
       5: iload_2
       6: iflt          31
       9: aload_1
      10: aload_0
      11: iload_2
      12: aaload
      13: invokevirtual #20                 // Method java/lang/String.equalsIgnoreCase:(Ljava/lang/String;)Z
      16: ifeq          25
      19: aload_0
      20: iload_2
      21: iconst_1
      22: iadd
      23: aaload
      24: areturn
      25: iinc          2, -2
      28: goto          5
      31: aconst_null
      32: areturn

  public static okhttp3.Headers of(java.lang.String...);
    Code:
       0: aload_0
       1: ifnonnull     14
       4: new           #47                 // class java/lang/NullPointerException
       7: dup
       8: ldc           #48                 // String namesAndValues == null
      10: invokespecial #49                 // Method java/lang/NullPointerException."<init>":(Ljava/lang/String;)V
      13: athrow
      14: aload_0
      15: arraylength
      16: iconst_2
      17: irem
      18: ifeq          31
      21: new           #50                 // class java/lang/IllegalArgumentException
      24: dup
      25: ldc           #51                 // String Expected alternating header names and values
      27: invokespecial #52                 // Method java/lang/IllegalArgumentException."<init>":(Ljava/lang/String;)V
      30: athrow
      31: aload_0
      32: invokevirtual #53                 // Method "[Ljava/lang/String;".clone:()Ljava/lang/Object;
      35: checkcast     #6                  // class "[Ljava/lang/String;"
      38: astore_0
      39: iconst_0
      40: istore_1
      41: iload_1
      42: aload_0
      43: arraylength
      44: if_icmpge     78
      47: aload_0
      48: iload_1
      49: aaload
      50: ifnonnull     63
      53: new           #50                 // class java/lang/IllegalArgumentException
      56: dup
      57: ldc           #54                 // String Headers cannot be null
      59: invokespecial #52                 // Method java/lang/IllegalArgumentException."<init>":(Ljava/lang/String;)V
      62: athrow
      63: aload_0
      64: iload_1
      65: aload_0
      66: iload_1
      67: aaload
      68: invokevirtual #55                 // Method java/lang/String.trim:()Ljava/lang/String;
      71: aastore
      72: iinc          1, 1
      75: goto          41
      78: iconst_0
      79: istore_1
      80: iload_1
      81: aload_0
      82: arraylength
      83: if_icmpge     111
      86: aload_0
      87: iload_1
      88: aaload
      89: astore_2
      90: aload_0
      91: iload_1
      92: iconst_1
      93: iadd
      94: aaload
      95: astore_3
      96: aload_2
      97: invokestatic  #56                 // Method checkName:(Ljava/lang/String;)V
     100: aload_3
     101: aload_2
     102: invokestatic  #57                 // Method checkValue:(Ljava/lang/String;Ljava/lang/String;)V
     105: iinc          1, 2
     108: goto          80
     111: new           #31                 // class okhttp3/Headers
     114: dup
     115: aload_0
     116: invokespecial #58                 // Method "<init>":([Ljava/lang/String;)V
     119: areturn

  public static okhttp3.Headers of(java.util.Map<java.lang.String, java.lang.String>);
    Code:
       0: aload_0
       1: ifnonnull     14
       4: new           #47                 // class java/lang/NullPointerException
       7: dup
       8: ldc           #59                 // String headers == null
      10: invokespecial #49                 // Method java/lang/NullPointerException."<init>":(Ljava/lang/String;)V
      13: athrow
      14: aload_0
      15: invokeinterface #60,  1           // InterfaceMethod java/util/Map.size:()I
      20: iconst_2
      21: imul
      22: anewarray     #4                  // class java/lang/String
      25: astore_1
      26: iconst_0
      27: istore_2
      28: aload_0
      29: invokeinterface #61,  1           // InterfaceMethod java/util/Map.entrySet:()Ljava/util/Set;
      34: invokeinterface #62,  1           // InterfaceMethod java/util/Set.iterator:()Ljava/util/Iterator;
      39: astore_3
      40: aload_3
      41: invokeinterface #63,  1           // InterfaceMethod java/util/Iterator.hasNext:()Z
      46: ifeq          150
      49: aload_3
      50: invokeinterface #64,  1           // InterfaceMethod java/util/Iterator.next:()Ljava/lang/Object;
      55: checkcast     #65                 // class java/util/Map$Entry
      58: astore        4
      60: aload         4
      62: invokeinterface #66,  1           // InterfaceMethod java/util/Map$Entry.getKey:()Ljava/lang/Object;
      67: ifnull        80
      70: aload         4
      72: invokeinterface #67,  1           // InterfaceMethod java/util/Map$Entry.getValue:()Ljava/lang/Object;
      77: ifnonnull     90
      80: new           #50                 // class java/lang/IllegalArgumentException
      83: dup
      84: ldc           #54                 // String Headers cannot be null
      86: invokespecial #52                 // Method java/lang/IllegalArgumentException."<init>":(Ljava/lang/String;)V
      89: athrow
      90: aload         4
      92: invokeinterface #66,  1           // InterfaceMethod java/util/Map$Entry.getKey:()Ljava/lang/Object;
      97: checkcast     #4                  // class java/lang/String
     100: invokevirtual #55                 // Method java/lang/String.trim:()Ljava/lang/String;
     103: astore        5
     105: aload         4
     107: invokeinterface #67,  1           // InterfaceMethod java/util/Map$Entry.getValue:()Ljava/lang/Object;
     112: checkcast     #4                  // class java/lang/String
     115: invokevirtual #55                 // Method java/lang/String.trim:()Ljava/lang/String;
     118: astore        6
     120: aload         5
     122: invokestatic  #56                 // Method checkName:(Ljava/lang/String;)V
     125: aload         6
     127: aload         5
     129: invokestatic  #57                 // Method checkValue:(Ljava/lang/String;Ljava/lang/String;)V
     132: aload_1
     133: iload_2
     134: aload         5
     136: aastore
     137: aload_1
     138: iload_2
     139: iconst_1
     140: iadd
     141: aload         6
     143: aastore
     144: iinc          2, 2
     147: goto          40
     150: new           #31                 // class okhttp3/Headers
     153: dup
     154: aload_1
     155: invokespecial #58                 // Method "<init>":([Ljava/lang/String;)V
     158: areturn

  static void checkName(java.lang.String);
    Code:
       0: aload_0
       1: ifnonnull     14
       4: new           #47                 // class java/lang/NullPointerException
       7: dup
       8: ldc           #68                 // String name == null
      10: invokespecial #49                 // Method java/lang/NullPointerException."<init>":(Ljava/lang/String;)V
      13: athrow
      14: aload_0
      15: invokevirtual #69                 // Method java/lang/String.isEmpty:()Z
      18: ifeq          31
      21: new           #50                 // class java/lang/IllegalArgumentException
      24: dup
      25: ldc           #70                 // String name is empty
      27: invokespecial #52                 // Method java/lang/IllegalArgumentException."<init>":(Ljava/lang/String;)V
      30: athrow
      31: iconst_0
      32: istore_1
      33: aload_0
      34: invokevirtual #27                 // Method java/lang/String.length:()I
      37: istore_2
      38: iload_1
      39: iload_2
      40: if_icmpge     102
      43: aload_0
      44: iload_1
      45: invokevirtual #71                 // Method java/lang/String.charAt:(I)C
      48: istore_3
      49: iload_3
      50: bipush        32
      52: if_icmple     61
      55: iload_3
      56: bipush        127
      58: if_icmplt     96
      61: new           #50                 // class java/lang/IllegalArgumentException
      64: dup
      65: ldc           #72                 // String Unexpected char %#04x at %d in header name: %s
      67: iconst_3
      68: anewarray     #73                 // class java/lang/Object
      71: dup
      72: iconst_0
      73: iload_3
      74: invokestatic  #74                 // Method java/lang/Integer.valueOf:(I)Ljava/lang/Integer;
      77: aastore
      78: dup
      79: iconst_1
      80: iload_1
      81: invokestatic  #74                 // Method java/lang/Integer.valueOf:(I)Ljava/lang/Integer;
      84: aastore
      85: dup
      86: iconst_2
      87: aload_0
      88: aastore
      89: invokestatic  #75                 // Method okhttp3/internal/Util.format:(Ljava/lang/String;[Ljava/lang/Object;)Ljava/lang/String;
      92: invokespecial #52                 // Method java/lang/IllegalArgumentException."<init>":(Ljava/lang/String;)V
      95: athrow
      96: iinc          1, 1
      99: goto          38
     102: return

  static void checkValue(java.lang.String, java.lang.String);
    Code:
       0: aload_0
       1: ifnonnull     36
       4: new           #47                 // class java/lang/NullPointerException
       7: dup
       8: new           #34                 // class java/lang/StringBuilder
      11: dup
      12: invokespecial #35                 // Method java/lang/StringBuilder."<init>":()V
      15: ldc           #76                 // String value for name
      17: invokevirtual #36                 // Method java/lang/StringBuilder.append:(Ljava/lang/String;)Ljava/lang/StringBuilder;
      20: aload_1
      21: invokevirtual #36                 // Method java/lang/StringBuilder.append:(Ljava/lang/String;)Ljava/lang/StringBuilder;
      24: ldc           #77                 // String  == null
      26: invokevirtual #36                 // Method java/lang/StringBuilder.append:(Ljava/lang/String;)Ljava/lang/StringBuilder;
      29: invokevirtual #39                 // Method java/lang/StringBuilder.toString:()Ljava/lang/String;
      32: invokespecial #49                 // Method java/lang/NullPointerException."<init>":(Ljava/lang/String;)V
      35: athrow
      36: iconst_0
      37: istore_2
      38: aload_0
      39: invokevirtual #27                 // Method java/lang/String.length:()I
      42: istore_3
      43: iload_2
      44: iload_3
      45: if_icmpge     122
      48: aload_0
      49: iload_2
      50: invokevirtual #71                 // Method java/lang/String.charAt:(I)C
      53: istore        4
      55: iload         4
      57: bipush        31
      59: if_icmpgt     69
      62: iload         4
      64: bipush        9
      66: if_icmpne     76
      69: iload         4
      71: bipush        127
      73: if_icmplt     116
      76: new           #50                 // class java/lang/IllegalArgumentException
      79: dup
      80: ldc           #78                 // String Unexpected char %#04x at %d in %s value: %s
      82: iconst_4
      83: anewarray     #73                 // class java/lang/Object
      86: dup
      87: iconst_0
      88: iload         4
      90: invokestatic  #74                 // Method java/lang/Integer.valueOf:(I)Ljava/lang/Integer;
      93: aastore
      94: dup
      95: iconst_1
      96: iload_2
      97: invokestatic  #74                 // Method java/lang/Integer.valueOf:(I)Ljava/lang/Integer;
     100: aastore
     101: dup
     102: iconst_2
     103: aload_1
     104: aastore
     105: dup
     106: iconst_3
     107: aload_0
     108: aastore
     109: invokestatic  #75                 // Method okhttp3/internal/Util.format:(Ljava/lang/String;[Ljava/lang/Object;)Ljava/lang/String;
     112: invokespecial #52                 // Method java/lang/IllegalArgumentException."<init>":(Ljava/lang/String;)V
     115: athrow
     116: iinc          2, 1
     119: goto          43
     122: return
}
