Compiled from "FixCertpathDebugLogging.scala"
public final class com.typesafe.sslconfig.ssl.debug.FixCertpathDebugLogging$MonkeyPatchSunSecurityUtilDebugAction$$anonfun$run$1 extends scala.runtime.AbstractFunction1<java.lang.Class<?>, scala.runtime.BoxedUnit> implements scala.Serializable {
  public static final long serialVersionUID;

  private final com.typesafe.sslconfig.ssl.debug.FixCertpathDebugLogging$MonkeyPatchSunSecurityUtilDebugAction $outer;

  public final sun.security.util.Debug debugValue$1;

  public final scala.runtime.BooleanRef isPatched$1;

  public final void apply(java.lang.Class<?>);
    Code:
       0: getstatic     #31                 // Field scala/Predef$.MODULE$:Lscala/Predef$;
       3: aload_1
       4: invokevirtual #37                 // Method java/lang/Class.getDeclaredFields:()[Ljava/lang/reflect/Field;
       7: checkcast     #39                 // class "[Ljava/lang/Object;"
      10: invokevirtual #43                 // Method scala/Predef$.refArrayOps:([Ljava/lang/Object;)Lscala/collection/mutable/ArrayOps;
      13: new           #45                 // class com/typesafe/sslconfig/ssl/debug/FixCertpathDebugLogging$MonkeyPatchSunSecurityUtilDebugAction$$anonfun$run$1$$anonfun$apply$1
      16: dup
      17: aload_0
      18: aload_1
      19: invokespecial #49                 // Method com/typesafe/sslconfig/ssl/debug/FixCertpathDebugLogging$MonkeyPatchSunSecurityUtilDebugAction$$anonfun$run$1$$anonfun$apply$1."<init>":(Lcom/typesafe/sslconfig/ssl/debug/FixCertpathDebugLogging$MonkeyPatchSunSecurityUtilDebugAction$$anonfun$run$1;Ljava/lang/Class;)V
      22: invokeinterface #55,  2           // InterfaceMethod scala/collection/mutable/ArrayOps.foreach:(Lscala/Function1;)V
      27: return

  public com.typesafe.sslconfig.ssl.debug.FixCertpathDebugLogging$MonkeyPatchSunSecurityUtilDebugAction com$typesafe$sslconfig$ssl$debug$FixCertpathDebugLogging$MonkeyPatchSunSecurityUtilDebugAction$$anonfun$$$outer();
    Code:
       0: aload_0
       1: getfield      #63                 // Field $outer:Lcom/typesafe/sslconfig/ssl/debug/FixCertpathDebugLogging$MonkeyPatchSunSecurityUtilDebugAction;
       4: areturn

  public final java.lang.Object apply(java.lang.Object);
    Code:
       0: aload_0
       1: aload_1
       2: checkcast     #33                 // class java/lang/Class
       5: invokevirtual #66                 // Method apply:(Ljava/lang/Class;)V
       8: getstatic     #72                 // Field scala/runtime/BoxedUnit.UNIT:Lscala/runtime/BoxedUnit;
      11: areturn

  public com.typesafe.sslconfig.ssl.debug.FixCertpathDebugLogging$MonkeyPatchSunSecurityUtilDebugAction$$anonfun$run$1(com.typesafe.sslconfig.ssl.debug.FixCertpathDebugLogging$MonkeyPatchSunSecurityUtilDebugAction, sun.security.util.Debug, scala.runtime.BooleanRef);
    Code:
       0: aload_1
       1: ifnonnull     6
       4: aconst_null
       5: athrow
       6: aload_0
       7: aload_1
       8: putfield      #63                 // Field $outer:Lcom/typesafe/sslconfig/ssl/debug/FixCertpathDebugLogging$MonkeyPatchSunSecurityUtilDebugAction;
      11: aload_0
      12: aload_2
      13: putfield      #77                 // Field debugValue$1:Lsun/security/util/Debug;
      16: aload_0
      17: aload_3
      18: putfield      #79                 // Field isPatched$1:Lscala/runtime/BooleanRef;
      21: aload_0
      22: invokespecial #81                 // Method scala/runtime/AbstractFunction1."<init>":()V
      25: return
}
