Compiled from "ProgressBar.java"
class org.wicketstuff.progressbar.ProgressBar$5 extends org.apache.wicket.ajax.AjaxSelfUpdatingTimerBehavior {
  private static final long serialVersionUID;

  final org.wicketstuff.progressbar.ProgressBar this$0;

  org.wicketstuff.progressbar.ProgressBar$5(org.wicketstuff.progressbar.ProgressBar, java.time.Duration);
    Code:
       0: aload_0
       1: aload_1
       2: putfield      #1                  // Field this$0:Lorg/wicketstuff/progressbar/ProgressBar;
       5: aload_0
       6: aload_2
       7: invokespecial #2                  // Method org/apache/wicket/ajax/AjaxSelfUpdatingTimerBehavior."<init>":(Ljava/time/Duration;)V
      10: return

  protected void onPostProcessTarget(org.apache.wicket.ajax.AjaxRequestTarget);
    Code:
       0: aload_0
       1: getfield      #1                  // Field this$0:Lorg/wicketstuff/progressbar/ProgressBar;
       4: invokevirtual #3                  // Method org/wicketstuff/progressbar/ProgressBar.getDefaultModel:()Lorg/apache/wicket/model/IModel;
       7: checkcast     #4                  // class org/wicketstuff/progressbar/ProgressionModel
      10: astore_2
      11: aload_2
      12: invokevirtual #5                  // Method org/wicketstuff/progressbar/ProgressionModel.getProgression:()Lorg/wicketstuff/progressbar/Progression;
      15: astore_3
      16: aload_3
      17: invokevirtual #6                  // Method org/wicketstuff/progressbar/Progression.isDone:()Z
      20: ifeq          36
      23: aload_0
      24: aload_1
      25: invokevirtual #7                  // Method stop:(Lorg/apache/wicket/core/request/handler/IPartialPageRequestHandler;)V
      28: aload_0
      29: getfield      #1                  // Field this$0:Lorg/wicketstuff/progressbar/ProgressBar;
      32: aload_1
      33: invokevirtual #8                  // Method org/wicketstuff/progressbar/ProgressBar.onFinished:(Lorg/apache/wicket/ajax/AjaxRequestTarget;)V
      36: return
}
