Compiled from "Parser.java"
public class com.google.javascript.jscomp.parsing.parser.Parser$Config {
  public final boolean atLeast6;

  public final boolean atLeast5;

  public final boolean isStrictMode;

  public final boolean warnTrailingCommas;

  public final boolean warnLineContinuations;

  public final boolean warnES6NumberLiteral;

  public com.google.javascript.jscomp.parsing.parser.Parser$Config(com.google.javascript.jscomp.parsing.parser.Parser$Config$Mode);
    Code:
       0: aload_0
       1: invokespecial #1                  // Method java/lang/Object."<init>":()V
       4: aload_0
       5: aload_1
       6: getstatic     #2                  // Field com/google/javascript/jscomp/parsing/parser/Parser$Config$Mode.ES6:Lcom/google/javascript/jscomp/parsing/parser/Parser$Config$Mode;
       9: if_acmpeq     26
      12: aload_1
      13: getstatic     #3                  // Field com/google/javascript/jscomp/parsing/parser/Parser$Config$Mode.ES6_STRICT:Lcom/google/javascript/jscomp/parsing/parser/Parser$Config$Mode;
      16: if_acmpeq     26
      19: aload_1
      20: getstatic     #4                  // Field com/google/javascript/jscomp/parsing/parser/Parser$Config$Mode.ES6_TYPED:Lcom/google/javascript/jscomp/parsing/parser/Parser$Config$Mode;
      23: if_acmpne     30
      26: iconst_1
      27: goto          31
      30: iconst_0
      31: putfield      #5                  // Field atLeast6:Z
      34: aload_0
      35: aload_0
      36: getfield      #5                  // Field atLeast6:Z
      39: ifne          56
      42: aload_1
      43: getstatic     #6                  // Field com/google/javascript/jscomp/parsing/parser/Parser$Config$Mode.ES5:Lcom/google/javascript/jscomp/parsing/parser/Parser$Config$Mode;
      46: if_acmpeq     56
      49: aload_1
      50: getstatic     #7                  // Field com/google/javascript/jscomp/parsing/parser/Parser$Config$Mode.ES5_STRICT:Lcom/google/javascript/jscomp/parsing/parser/Parser$Config$Mode;
      53: if_acmpne     60
      56: iconst_1
      57: goto          61
      60: iconst_0
      61: putfield      #8                  // Field atLeast5:Z
      64: aload_0
      65: aload_1
      66: getstatic     #7                  // Field com/google/javascript/jscomp/parsing/parser/Parser$Config$Mode.ES5_STRICT:Lcom/google/javascript/jscomp/parsing/parser/Parser$Config$Mode;
      69: if_acmpeq     86
      72: aload_1
      73: getstatic     #3                  // Field com/google/javascript/jscomp/parsing/parser/Parser$Config$Mode.ES6_STRICT:Lcom/google/javascript/jscomp/parsing/parser/Parser$Config$Mode;
      76: if_acmpeq     86
      79: aload_1
      80: getstatic     #4                  // Field com/google/javascript/jscomp/parsing/parser/Parser$Config$Mode.ES6_TYPED:Lcom/google/javascript/jscomp/parsing/parser/Parser$Config$Mode;
      83: if_acmpne     90
      86: iconst_1
      87: goto          91
      90: iconst_0
      91: putfield      #9                  // Field isStrictMode:Z
      94: aload_0
      95: aload_0
      96: getfield      #8                  // Field atLeast5:Z
      99: ifne          106
     102: iconst_1
     103: goto          107
     106: iconst_0
     107: putfield      #10                 // Field warnTrailingCommas:Z
     110: aload_0
     111: aload_0
     112: getfield      #5                  // Field atLeast6:Z
     115: ifne          122
     118: iconst_1
     119: goto          123
     122: iconst_0
     123: putfield      #11                 // Field warnLineContinuations:Z
     126: aload_0
     127: aload_0
     128: getfield      #5                  // Field atLeast6:Z
     131: ifne          138
     134: iconst_1
     135: goto          139
     138: iconst_0
     139: putfield      #12                 // Field warnES6NumberLiteral:Z
     142: return
}
