Compiled from "JBossAppServerJtaPlatform.java"
class org.jboss.as.jpa.hibernate5.JBossAppServerJtaPlatform$1 implements org.hibernate.engine.transaction.jta.platform.internal.SynchronizationRegistryAccess {
  final org.jipijapa.plugin.spi.JtaManager val$jtaManager;

  final org.jboss.as.jpa.hibernate5.JBossAppServerJtaPlatform this$0;

  org.jboss.as.jpa.hibernate5.JBossAppServerJtaPlatform$1(org.jboss.as.jpa.hibernate5.JBossAppServerJtaPlatform, org.jipijapa.plugin.spi.JtaManager);
    Code:
       0: aload_0
       1: aload_1
       2: putfield      #1                  // Field this$0:Lorg/jboss/as/jpa/hibernate5/JBossAppServerJtaPlatform;
       5: aload_0
       6: aload_2
       7: putfield      #2                  // Field val$jtaManager:Lorg/jipijapa/plugin/spi/JtaManager;
      10: aload_0
      11: invokespecial #3                  // Method java/lang/Object."<init>":()V
      14: return

  public javax.transaction.TransactionSynchronizationRegistry getSynchronizationRegistry();
    Code:
       0: aload_0
       1: getfield      #2                  // Field val$jtaManager:Lorg/jipijapa/plugin/spi/JtaManager;
       4: invokeinterface #4,  1            // InterfaceMethod org/jipijapa/plugin/spi/JtaManager.getSynchronizationRegistry:()Ljavax/transaction/TransactionSynchronizationRegistry;
       9: areturn
}
