Compiled from "ReferenceMapUtils.java"
public final class org.graylog2.contentpacks.model.entities.references.ReferenceMapUtils {
  public org.graylog2.contentpacks.model.entities.references.ReferenceMapUtils();
    Code:
       0: aload_0
       1: invokespecial #1                  // Method java/lang/Object."<init>":()V
       4: return

  public static org.graylog2.contentpacks.model.entities.references.ReferenceMap toReferenceMap(java.util.Map<java.lang.String, java.lang.Object>);
    Code:
       0: invokestatic  #2                  // Method com/google/common/collect/ImmutableMap.builder:()Lcom/google/common/collect/ImmutableMap$Builder;
       3: astore_1
       4: aload_0
       5: invokeinterface #3,  1            // InterfaceMethod java/util/Map.entrySet:()Ljava/util/Set;
      10: invokeinterface #4,  1            // InterfaceMethod java/util/Set.iterator:()Ljava/util/Iterator;
      15: astore_2
      16: aload_2
      17: invokeinterface #5,  1            // InterfaceMethod java/util/Iterator.hasNext:()Z
      22: ifeq          145
      25: aload_2
      26: invokeinterface #6,  1            // InterfaceMethod java/util/Iterator.next:()Ljava/lang/Object;
      31: checkcast     #7                  // class java/util/Map$Entry
      34: astore_3
      35: aload_3
      36: invokeinterface #8,  1            // InterfaceMethod java/util/Map$Entry.getValue:()Ljava/lang/Object;
      41: astore        4
      43: aload         4
      45: instanceof    #9                  // class java/util/Collection
      48: ifeq          77
      51: aload         4
      53: checkcast     #10                 // class java/util/List
      56: astore        5
      58: aload_1
      59: aload_3
      60: invokeinterface #11,  1           // InterfaceMethod java/util/Map$Entry.getKey:()Ljava/lang/Object;
      65: checkcast     #12                 // class java/lang/String
      68: aload         5
      70: invokestatic  #13                 // Method toReferenceList:(Ljava/util/Collection;)Lorg/graylog2/contentpacks/model/entities/references/ReferenceList;
      73: invokevirtual #14                 // Method com/google/common/collect/ImmutableMap$Builder.put:(Ljava/lang/Object;Ljava/lang/Object;)Lcom/google/common/collect/ImmutableMap$Builder;
      76: pop
      77: aload         4
      79: instanceof    #15                 // class java/util/Map
      82: ifeq          114
      85: aload         4
      87: checkcast     #15                 // class java/util/Map
      90: astore        5
      92: aload_1
      93: aload_3
      94: invokeinterface #11,  1           // InterfaceMethod java/util/Map$Entry.getKey:()Ljava/lang/Object;
      99: checkcast     #12                 // class java/lang/String
     102: aload         5
     104: invokestatic  #16                 // Method toReferenceMap:(Ljava/util/Map;)Lorg/graylog2/contentpacks/model/entities/references/ReferenceMap;
     107: invokevirtual #14                 // Method com/google/common/collect/ImmutableMap$Builder.put:(Ljava/lang/Object;Ljava/lang/Object;)Lcom/google/common/collect/ImmutableMap$Builder;
     110: pop
     111: goto          142
     114: aload         4
     116: invokestatic  #17                 // Method org/graylog2/contentpacks/model/entities/references/ValueReference.of:(Ljava/lang/Object;)Lorg/graylog2/contentpacks/model/entities/references/ValueReference;
     119: astore        5
     121: aload         5
     123: ifnull        142
     126: aload_1
     127: aload_3
     128: invokeinterface #11,  1           // InterfaceMethod java/util/Map$Entry.getKey:()Ljava/lang/Object;
     133: checkcast     #12                 // class java/lang/String
     136: aload         5
     138: invokevirtual #14                 // Method com/google/common/collect/ImmutableMap$Builder.put:(Ljava/lang/Object;Ljava/lang/Object;)Lcom/google/common/collect/ImmutableMap$Builder;
     141: pop
     142: goto          16
     145: new           #18                 // class org/graylog2/contentpacks/model/entities/references/ReferenceMap
     148: dup
     149: aload_1
     150: invokevirtual #19                 // Method com/google/common/collect/ImmutableMap$Builder.build:()Lcom/google/common/collect/ImmutableMap;
     153: invokespecial #20                 // Method org/graylog2/contentpacks/model/entities/references/ReferenceMap."<init>":(Ljava/util/Map;)V
     156: areturn

  private static org.graylog2.contentpacks.model.entities.references.ReferenceList toReferenceList(java.util.Collection<java.lang.Object>);
    Code:
       0: aload_0
       1: invokeinterface #21,  1           // InterfaceMethod java/util/Collection.stream:()Ljava/util/stream/Stream;
       6: invokedynamic #22,  0             // InvokeDynamic #0:apply:()Ljava/util/function/Function;
      11: invokeinterface #23,  2           // InterfaceMethod java/util/stream/Stream.map:(Ljava/util/function/Function;)Ljava/util/stream/Stream;
      16: invokedynamic #24,  0             // InvokeDynamic #1:test:()Ljava/util/function/Predicate;
      21: invokeinterface #25,  2           // InterfaceMethod java/util/stream/Stream.filter:(Ljava/util/function/Predicate;)Ljava/util/stream/Stream;
      26: invokedynamic #26,  0             // InvokeDynamic #2:get:()Ljava/util/function/Supplier;
      31: invokestatic  #27                 // Method java/util/stream/Collectors.toCollection:(Ljava/util/function/Supplier;)Ljava/util/stream/Collector;
      34: invokeinterface #28,  2           // InterfaceMethod java/util/stream/Stream.collect:(Ljava/util/stream/Collector;)Ljava/lang/Object;
      39: checkcast     #29                 // class org/graylog2/contentpacks/model/entities/references/ReferenceList
      42: areturn

  public static java.util.Map<java.lang.String, java.lang.Object> toValueMap(org.graylog2.contentpacks.model.entities.references.ReferenceMap, java.util.Map<java.lang.String, org.graylog2.contentpacks.model.entities.references.ValueReference>);
    Code:
       0: invokestatic  #2                  // Method com/google/common/collect/ImmutableMap.builder:()Lcom/google/common/collect/ImmutableMap$Builder;
       3: astore_2
       4: aload_0
       5: invokevirtual #30                 // Method org/graylog2/contentpacks/model/entities/references/ReferenceMap.entrySet:()Ljava/util/Set;
       8: invokeinterface #4,  1            // InterfaceMethod java/util/Set.iterator:()Ljava/util/Iterator;
      13: astore_3
      14: aload_3
      15: invokeinterface #5,  1            // InterfaceMethod java/util/Iterator.hasNext:()Z
      20: ifeq          75
      23: aload_3
      24: invokeinterface #6,  1            // InterfaceMethod java/util/Iterator.next:()Ljava/lang/Object;
      29: checkcast     #7                  // class java/util/Map$Entry
      32: astore        4
      34: aload         4
      36: invokeinterface #8,  1            // InterfaceMethod java/util/Map$Entry.getValue:()Ljava/lang/Object;
      41: checkcast     #31                 // class org/graylog2/contentpacks/model/entities/references/Reference
      44: aload_1
      45: invokestatic  #32                 // Method valueOf:(Lorg/graylog2/contentpacks/model/entities/references/Reference;Ljava/util/Map;)Ljava/lang/Object;
      48: astore        5
      50: aload         5
      52: ifnull        72
      55: aload_2
      56: aload         4
      58: invokeinterface #11,  1           // InterfaceMethod java/util/Map$Entry.getKey:()Ljava/lang/Object;
      63: checkcast     #12                 // class java/lang/String
      66: aload         5
      68: invokevirtual #14                 // Method com/google/common/collect/ImmutableMap$Builder.put:(Ljava/lang/Object;Ljava/lang/Object;)Lcom/google/common/collect/ImmutableMap$Builder;
      71: pop
      72: goto          14
      75: aload_2
      76: invokevirtual #19                 // Method com/google/common/collect/ImmutableMap$Builder.build:()Lcom/google/common/collect/ImmutableMap;
      79: areturn

  private static java.lang.Object valueOf(org.graylog2.contentpacks.model.entities.references.Reference, java.util.Map<java.lang.String, org.graylog2.contentpacks.model.entities.references.ValueReference>);
    Code:
       0: aload_0
       1: instanceof    #33                 // class org/graylog2/contentpacks/model/entities/references/ValueReference
       4: ifeq          18
       7: aload_0
       8: checkcast     #33                 // class org/graylog2/contentpacks/model/entities/references/ValueReference
      11: astore_2
      12: aload_2
      13: aload_1
      14: invokestatic  #34                 // Method valueOf:(Lorg/graylog2/contentpacks/model/entities/references/ValueReference;Ljava/util/Map;)Ljava/lang/Object;
      17: areturn
      18: aload_0
      19: instanceof    #29                 // class org/graylog2/contentpacks/model/entities/references/ReferenceList
      22: ifeq          36
      25: aload_0
      26: checkcast     #29                 // class org/graylog2/contentpacks/model/entities/references/ReferenceList
      29: astore_2
      30: aload_2
      31: aload_1
      32: invokestatic  #35                 // Method toValueList:(Lorg/graylog2/contentpacks/model/entities/references/ReferenceList;Ljava/util/Map;)Ljava/util/List;
      35: areturn
      36: aload_0
      37: instanceof    #18                 // class org/graylog2/contentpacks/model/entities/references/ReferenceMap
      40: ifeq          54
      43: aload_0
      44: checkcast     #18                 // class org/graylog2/contentpacks/model/entities/references/ReferenceMap
      47: astore_2
      48: aload_2
      49: aload_1
      50: invokestatic  #36                 // Method toValueMap:(Lorg/graylog2/contentpacks/model/entities/references/ReferenceMap;Ljava/util/Map;)Ljava/util/Map;
      53: areturn
      54: aconst_null
      55: areturn

  private static java.lang.Object valueOf(org.graylog2.contentpacks.model.entities.references.ValueReference, java.util.Map<java.lang.String, org.graylog2.contentpacks.model.entities.references.ValueReference>);
    Code:
       0: getstatic     #37                 // Field org/graylog2/contentpacks/model/entities/references/ReferenceMapUtils$1.$SwitchMap$org$graylog2$contentpacks$model$entities$references$ValueType:[I
       3: aload_0
       4: invokevirtual #38                 // Method org/graylog2/contentpacks/model/entities/references/ValueReference.valueType:()Lorg/graylog2/contentpacks/model/entities/references/ValueType;
       7: invokevirtual #39                 // Method org/graylog2/contentpacks/model/entities/references/ValueType.ordinal:()I
      10: iaload
      11: tableswitch   { // 1 to 7
                     1: 52
                     2: 58
                     3: 64
                     4: 70
                     5: 76
                     6: 82
                     7: 88
               default: 94
          }
      52: aload_0
      53: aload_1
      54: invokevirtual #40                 // Method org/graylog2/contentpacks/model/entities/references/ValueReference.asBoolean:(Ljava/util/Map;)Ljava/lang/Boolean;
      57: areturn
      58: aload_0
      59: aload_1
      60: invokevirtual #41                 // Method org/graylog2/contentpacks/model/entities/references/ValueReference.asDouble:(Ljava/util/Map;)Ljava/lang/Double;
      63: areturn
      64: aload_0
      65: aload_1
      66: invokevirtual #42                 // Method org/graylog2/contentpacks/model/entities/references/ValueReference.asFloat:(Ljava/util/Map;)Ljava/lang/Float;
      69: areturn
      70: aload_0
      71: aload_1
      72: invokevirtual #43                 // Method org/graylog2/contentpacks/model/entities/references/ValueReference.asInteger:(Ljava/util/Map;)Ljava/lang/Integer;
      75: areturn
      76: aload_0
      77: aload_1
      78: invokevirtual #44                 // Method org/graylog2/contentpacks/model/entities/references/ValueReference.asLong:(Ljava/util/Map;)Ljava/lang/Long;
      81: areturn
      82: aload_0
      83: aload_1
      84: invokevirtual #45                 // Method org/graylog2/contentpacks/model/entities/references/ValueReference.asString:(Ljava/util/Map;)Ljava/lang/String;
      87: areturn
      88: aload_0
      89: aload_1
      90: invokestatic  #46                 // Method resolveParameterReference:(Lorg/graylog2/contentpacks/model/entities/references/ValueReference;Ljava/util/Map;)Ljava/lang/Object;
      93: areturn
      94: aconst_null
      95: areturn

  private static java.lang.Object resolveParameterReference(org.graylog2.contentpacks.model.entities.references.ValueReference, java.util.Map<java.lang.String, org.graylog2.contentpacks.model.entities.references.ValueReference>);
    Code:
       0: aload_0
       1: invokevirtual #47                 // Method org/graylog2/contentpacks/model/entities/references/ValueReference.value:()Ljava/lang/Object;
       4: astore_2
       5: aload_2
       6: instanceof    #12                 // class java/lang/String
       9: ifeq          97
      12: aload_1
      13: aload_2
      14: invokeinterface #48,  2           // InterfaceMethod java/util/Map.get:(Ljava/lang/Object;)Ljava/lang/Object;
      19: checkcast     #33                 // class org/graylog2/contentpacks/model/entities/references/ValueReference
      22: astore_3
      23: aload_3
      24: ifnonnull     54
      27: new           #49                 // class java/lang/IllegalArgumentException
      30: dup
      31: new           #50                 // class java/lang/StringBuilder
      34: dup
      35: invokespecial #51                 // Method java/lang/StringBuilder."<init>":()V
      38: ldc           #52                 // String Missing parameter
      40: invokevirtual #53                 // Method java/lang/StringBuilder.append:(Ljava/lang/String;)Ljava/lang/StringBuilder;
      43: aload_2
      44: invokevirtual #54                 // Method java/lang/StringBuilder.append:(Ljava/lang/Object;)Ljava/lang/StringBuilder;
      47: invokevirtual #55                 // Method java/lang/StringBuilder.toString:()Ljava/lang/String;
      50: invokespecial #56                 // Method java/lang/IllegalArgumentException."<init>":(Ljava/lang/String;)V
      53: athrow
      54: aload_3
      55: invokevirtual #38                 // Method org/graylog2/contentpacks/model/entities/references/ValueReference.valueType:()Lorg/graylog2/contentpacks/model/entities/references/ValueType;
      58: getstatic     #57                 // Field org/graylog2/contentpacks/model/entities/references/ValueType.PARAMETER:Lorg/graylog2/contentpacks/model/entities/references/ValueType;
      61: if_acmpne     91
      64: new           #49                 // class java/lang/IllegalArgumentException
      67: dup
      68: new           #50                 // class java/lang/StringBuilder
      71: dup
      72: invokespecial #51                 // Method java/lang/StringBuilder."<init>":()V
      75: ldc           #58                 // String Circular parameter
      77: invokevirtual #53                 // Method java/lang/StringBuilder.append:(Ljava/lang/String;)Ljava/lang/StringBuilder;
      80: aload_2
      81: invokevirtual #54                 // Method java/lang/StringBuilder.append:(Ljava/lang/Object;)Ljava/lang/StringBuilder;
      84: invokevirtual #55                 // Method java/lang/StringBuilder.toString:()Ljava/lang/String;
      87: invokespecial #56                 // Method java/lang/IllegalArgumentException."<init>":(Ljava/lang/String;)V
      90: athrow
      91: aload_3
      92: aload_1
      93: invokestatic  #34                 // Method valueOf:(Lorg/graylog2/contentpacks/model/entities/references/ValueReference;Ljava/util/Map;)Ljava/lang/Object;
      96: areturn
      97: aconst_null
      98: areturn

  private static java.util.List<java.lang.Object> toValueList(org.graylog2.contentpacks.model.entities.references.ReferenceList, java.util.Map<java.lang.String, org.graylog2.contentpacks.model.entities.references.ValueReference>);
    Code:
       0: aload_0
       1: invokevirtual #59                 // Method org/graylog2/contentpacks/model/entities/references/ReferenceList.stream:()Ljava/util/stream/Stream;
       4: aload_1
       5: invokedynamic #60,  0             // InvokeDynamic #3:apply:(Ljava/util/Map;)Ljava/util/function/Function;
      10: invokeinterface #23,  2           // InterfaceMethod java/util/stream/Stream.map:(Ljava/util/function/Function;)Ljava/util/stream/Stream;
      15: invokedynamic #61,  0             // InvokeDynamic #4:test:()Ljava/util/function/Predicate;
      20: invokeinterface #25,  2           // InterfaceMethod java/util/stream/Stream.filter:(Ljava/util/function/Predicate;)Ljava/util/stream/Stream;
      25: invokestatic  #62                 // Method java/util/stream/Collectors.toList:()Ljava/util/stream/Collector;
      28: invokeinterface #28,  2           // InterfaceMethod java/util/stream/Stream.collect:(Ljava/util/stream/Collector;)Ljava/lang/Object;
      33: checkcast     #10                 // class java/util/List
      36: areturn

  private static java.lang.Object lambda$toValueList$0(java.util.Map, org.graylog2.contentpacks.model.entities.references.Reference);
    Code:
       0: aload_1
       1: aload_0
       2: invokestatic  #32                 // Method valueOf:(Lorg/graylog2/contentpacks/model/entities/references/Reference;Ljava/util/Map;)Ljava/lang/Object;
       5: areturn
}
