Compiled from "SpringWebFluxTemplateEngine.java"
public class org.thymeleaf.spring5.SpringWebFluxTemplateEngine extends org.thymeleaf.spring5.SpringTemplateEngine implements org.thymeleaf.spring5.ISpringWebFluxTemplateEngine {
  private static final org.slf4j.Logger logger;

  private static final java.lang.String LOG_CATEGORY_FULL_OUTPUT;

  private static final java.lang.String LOG_CATEGORY_CHUNKED_OUTPUT;

  private static final java.lang.String LOG_CATEGORY_DATADRIVEN_INPUT;

  private static final java.lang.String LOG_CATEGORY_DATADRIVEN_OUTPUT;

  public org.thymeleaf.spring5.SpringWebFluxTemplateEngine();
    Code:
       0: aload_0
       1: invokespecial #1                  // Method org/thymeleaf/spring5/SpringTemplateEngine."<init>":()V
       4: aload_0
       5: new           #2                  // class org/thymeleaf/spring5/context/webflux/SpringWebFluxEngineContextFactory
       8: dup
       9: invokespecial #3                  // Method org/thymeleaf/spring5/context/webflux/SpringWebFluxEngineContextFactory."<init>":()V
      12: invokevirtual #4                  // Method setEngineContextFactory:(Lorg/thymeleaf/context/IEngineContextFactory;)V
      15: aload_0
      16: new           #5                  // class org/thymeleaf/spring5/linkbuilder/webflux/SpringWebFluxLinkBuilder
      19: dup
      20: invokespecial #6                  // Method org/thymeleaf/spring5/linkbuilder/webflux/SpringWebFluxLinkBuilder."<init>":()V
      23: invokevirtual #7                  // Method setLinkBuilder:(Lorg/thymeleaf/linkbuilder/ILinkBuilder;)V
      26: return

  public org.reactivestreams.Publisher<org.springframework.core.io.buffer.DataBuffer> processStream(java.lang.String, java.util.Set<java.lang.String>, org.thymeleaf.context.IContext, org.springframework.core.io.buffer.DataBufferFactory, org.springframework.http.MediaType, java.nio.charset.Charset);
    Code:
       0: aload_0
       1: aload_1
       2: aload_2
       3: aload_3
       4: aload         4
       6: aload         5
       8: aload         6
      10: ldc           #9                  // int 2147483647
      12: invokevirtual #10                 // Method processStream:(Ljava/lang/String;Ljava/util/Set;Lorg/thymeleaf/context/IContext;Lorg/springframework/core/io/buffer/DataBufferFactory;Lorg/springframework/http/MediaType;Ljava/nio/charset/Charset;I)Lorg/reactivestreams/Publisher;
      15: areturn

  public org.reactivestreams.Publisher<org.springframework.core.io.buffer.DataBuffer> processStream(java.lang.String, java.util.Set<java.lang.String>, org.thymeleaf.context.IContext, org.springframework.core.io.buffer.DataBufferFactory, org.springframework.http.MediaType, java.nio.charset.Charset, int);
    Code:
       0: aload_1
       1: ifnonnull     17
       4: new           #11                 // class java/lang/IllegalArgumentException
       7: dup
       8: ldc           #12                 // String Template cannot be null
      10: invokespecial #13                 // Method java/lang/IllegalArgumentException."<init>":(Ljava/lang/String;)V
      13: invokestatic  #14                 // Method reactor/core/publisher/Flux.error:(Ljava/lang/Throwable;)Lreactor/core/publisher/Flux;
      16: areturn
      17: aload_3
      18: ifnonnull     34
      21: new           #11                 // class java/lang/IllegalArgumentException
      24: dup
      25: ldc           #15                 // String Context cannot be null
      27: invokespecial #13                 // Method java/lang/IllegalArgumentException."<init>":(Ljava/lang/String;)V
      30: invokestatic  #14                 // Method reactor/core/publisher/Flux.error:(Ljava/lang/Throwable;)Lreactor/core/publisher/Flux;
      33: areturn
      34: aload         4
      36: ifnonnull     52
      39: new           #11                 // class java/lang/IllegalArgumentException
      42: dup
      43: ldc           #16                 // String Buffer Factory cannot be null
      45: invokespecial #13                 // Method java/lang/IllegalArgumentException."<init>":(Ljava/lang/String;)V
      48: invokestatic  #14                 // Method reactor/core/publisher/Flux.error:(Ljava/lang/Throwable;)Lreactor/core/publisher/Flux;
      51: areturn
      52: aload         5
      54: ifnonnull     70
      57: new           #11                 // class java/lang/IllegalArgumentException
      60: dup
      61: ldc           #17                 // String Media Type cannot be null
      63: invokespecial #13                 // Method java/lang/IllegalArgumentException."<init>":(Ljava/lang/String;)V
      66: invokestatic  #14                 // Method reactor/core/publisher/Flux.error:(Ljava/lang/Throwable;)Lreactor/core/publisher/Flux;
      69: areturn
      70: aload         6
      72: ifnonnull     88
      75: new           #11                 // class java/lang/IllegalArgumentException
      78: dup
      79: ldc           #18                 // String Charset cannot be null
      81: invokespecial #13                 // Method java/lang/IllegalArgumentException."<init>":(Ljava/lang/String;)V
      84: invokestatic  #14                 // Method reactor/core/publisher/Flux.error:(Ljava/lang/Throwable;)Lreactor/core/publisher/Flux;
      87: areturn
      88: iload         7
      90: ifne          106
      93: new           #11                 // class java/lang/IllegalArgumentException
      96: dup
      97: ldc           #19                 // String Max Chunk Size cannot be zero
      99: invokespecial #13                 // Method java/lang/IllegalArgumentException."<init>":(Ljava/lang/String;)V
     102: invokestatic  #14                 // Method reactor/core/publisher/Flux.error:(Ljava/lang/Throwable;)Lreactor/core/publisher/Flux;
     105: areturn
     106: iload         7
     108: ifge          116
     111: ldc           #9                  // int 2147483647
     113: goto          118
     116: iload         7
     118: istore        8
     120: getstatic     #20                 // Field org/springframework/http/MediaType.TEXT_EVENT_STREAM:Lorg/springframework/http/MediaType;
     123: aload         5
     125: invokevirtual #21                 // Method org/springframework/http/MediaType.includes:(Lorg/springframework/http/MediaType;)Z
     128: istore        9
     130: aload_3
     131: invokestatic  #22                 // Method findDataDriverInModel:(Lorg/thymeleaf/context/IContext;)Ljava/lang/String;
     134: astore        10
     136: aload         10
     138: ifnull        159
     141: aload_0
     142: aload_1
     143: aload_2
     144: aload_3
     145: aload         10
     147: aload         4
     149: aload         6
     151: iload         8
     153: iload         9
     155: invokespecial #23                 // Method createDataDrivenStream:(Ljava/lang/String;Ljava/util/Set;Lorg/thymeleaf/context/IContext;Ljava/lang/String;Lorg/springframework/core/io/buffer/DataBufferFactory;Ljava/nio/charset/Charset;IZ)Lreactor/core/publisher/Flux;
     158: areturn
     159: goto          170
     162: astore        10
     164: aload         10
     166: invokestatic  #14                 // Method reactor/core/publisher/Flux.error:(Ljava/lang/Throwable;)Lreactor/core/publisher/Flux;
     169: areturn
     170: iload         9
     172: ifeq          214
     175: new           #25                 // class org/thymeleaf/exceptions/TemplateProcessingException
     178: dup
     179: new           #26                 // class java/lang/StringBuilder
     182: dup
     183: invokespecial #27                 // Method java/lang/StringBuilder."<init>":()V
     186: ldc           #28                 // String SSE mode has been requested (\'Accept: text/event-stream\') but no data-driver variable has been added to the model/context. In order to perform SSE rendering, a variable implementing the
     188: invokevirtual #29                 // Method java/lang/StringBuilder.append:(Ljava/lang/String;)Ljava/lang/StringBuilder;
     191: ldc           #30                 // class org/thymeleaf/spring5/context/webflux/IReactiveDataDriverContextVariable
     193: invokevirtual #31                 // Method java/lang/Class.getName:()Ljava/lang/String;
     196: invokevirtual #29                 // Method java/lang/StringBuilder.append:(Ljava/lang/String;)Ljava/lang/StringBuilder;
     199: ldc           #32                 // String  interface is required.
     201: invokevirtual #29                 // Method java/lang/StringBuilder.append:(Ljava/lang/String;)Ljava/lang/StringBuilder;
     204: invokevirtual #33                 // Method java/lang/StringBuilder.toString:()Ljava/lang/String;
     207: invokespecial #34                 // Method org/thymeleaf/exceptions/TemplateProcessingException."<init>":(Ljava/lang/String;)V
     210: invokestatic  #14                 // Method reactor/core/publisher/Flux.error:(Ljava/lang/Throwable;)Lreactor/core/publisher/Flux;
     213: areturn
     214: iload         8
     216: ldc           #9                  // int 2147483647
     218: if_icmpne     233
     221: aload_0
     222: aload_1
     223: aload_2
     224: aload_3
     225: aload         4
     227: aload         6
     229: invokespecial #35                 // Method createFullStream:(Ljava/lang/String;Ljava/util/Set;Lorg/thymeleaf/context/IContext;Lorg/springframework/core/io/buffer/DataBufferFactory;Ljava/nio/charset/Charset;)Lreactor/core/publisher/Mono;
     232: areturn
     233: aload_0
     234: aload_1
     235: aload_2
     236: aload_3
     237: aload         4
     239: aload         6
     241: iload         7
     243: invokespecial #36                 // Method createChunkedStream:(Ljava/lang/String;Ljava/util/Set;Lorg/thymeleaf/context/IContext;Lorg/springframework/core/io/buffer/DataBufferFactory;Ljava/nio/charset/Charset;I)Lreactor/core/publisher/Flux;
     246: areturn
    Exception table:
       from    to  target type
         130   158   162   Class java/lang/Throwable

  private reactor.core.publisher.Mono<org.springframework.core.io.buffer.DataBuffer> createFullStream(java.lang.String, java.util.Set<java.lang.String>, org.thymeleaf.context.IContext, org.springframework.core.io.buffer.DataBufferFactory, java.nio.charset.Charset);
    Code:
       0: aload_0
       1: aload_1
       2: aload_3
       3: aload         4
       5: aload         5
       7: aload_2
       8: invokedynamic #37,  0             // InvokeDynamic #0:accept:(Lorg/thymeleaf/spring5/SpringWebFluxTemplateEngine;Ljava/lang/String;Lorg/thymeleaf/context/IContext;Lorg/springframework/core/io/buffer/DataBufferFactory;Ljava/nio/charset/Charset;Ljava/util/Set;)Ljava/util/function/Consumer;
      13: invokestatic  #38                 // Method reactor/core/publisher/Mono.create:(Ljava/util/function/Consumer;)Lreactor/core/publisher/Mono;
      16: astore        6
      18: aload         6
      20: getstatic     #39                 // Field LOG_CATEGORY_FULL_OUTPUT:Ljava/lang/String;
      23: getstatic     #40                 // Field java/util/logging/Level.FINEST:Ljava/util/logging/Level;
      26: iconst_0
      27: anewarray     #41                 // class reactor/core/publisher/SignalType
      30: invokevirtual #42                 // Method reactor/core/publisher/Mono.log:(Ljava/lang/String;Ljava/util/logging/Level;[Lreactor/core/publisher/SignalType;)Lreactor/core/publisher/Mono;
      33: areturn

  private reactor.core.publisher.Flux<org.springframework.core.io.buffer.DataBuffer> createChunkedStream(java.lang.String, java.util.Set<java.lang.String>, org.thymeleaf.context.IContext, org.springframework.core.io.buffer.DataBufferFactory, java.nio.charset.Charset, int);
    Code:
       0: aload_0
       1: aload_1
       2: aload_2
       3: aload_3
       4: invokedynamic #43,  0             // InvokeDynamic #1:call:(Lorg/thymeleaf/spring5/SpringWebFluxTemplateEngine;Ljava/lang/String;Ljava/util/Set;Lorg/thymeleaf/context/IContext;)Ljava/util/concurrent/Callable;
       9: aload_1
      10: aload_3
      11: aload         4
      13: iload         6
      15: aload         5
      17: invokedynamic #44,  0             // InvokeDynamic #2:apply:(Ljava/lang/String;Lorg/thymeleaf/context/IContext;Lorg/springframework/core/io/buffer/DataBufferFactory;ILjava/nio/charset/Charset;)Ljava/util/function/BiFunction;
      22: invokestatic  #45                 // Method reactor/core/publisher/Flux.generate:(Ljava/util/concurrent/Callable;Ljava/util/function/BiFunction;)Lreactor/core/publisher/Flux;
      25: astore        7
      27: aload         7
      29: getstatic     #46                 // Field LOG_CATEGORY_CHUNKED_OUTPUT:Ljava/lang/String;
      32: getstatic     #40                 // Field java/util/logging/Level.FINEST:Ljava/util/logging/Level;
      35: iconst_0
      36: anewarray     #41                 // class reactor/core/publisher/SignalType
      39: invokevirtual #47                 // Method reactor/core/publisher/Flux.log:(Ljava/lang/String;Ljava/util/logging/Level;[Lreactor/core/publisher/SignalType;)Lreactor/core/publisher/Flux;
      42: areturn

  private reactor.core.publisher.Flux<org.springframework.core.io.buffer.DataBuffer> createDataDrivenStream(java.lang.String, java.util.Set<java.lang.String>, org.thymeleaf.context.IContext, java.lang.String, org.springframework.core.io.buffer.DataBufferFactory, java.nio.charset.Charset, int, boolean);
    Code:
       0: aload_3
       1: aload         4
       3: invokeinterface #48,  2           // InterfaceMethod org/thymeleaf/context/IContext.getVariable:(Ljava/lang/String;)Ljava/lang/Object;
       8: checkcast     #30                 // class org/thymeleaf/spring5/context/webflux/IReactiveDataDriverContextVariable
      11: astore        9
      13: aload         9
      15: invokeinterface #49,  1           // InterfaceMethod org/thymeleaf/spring5/context/webflux/IReactiveDataDriverContextVariable.getBufferSizeElements:()I
      20: istore        10
      22: aload         9
      24: instanceof    #50                 // class org/thymeleaf/spring5/context/webflux/IReactiveSSEDataDriverContextVariable
      27: ifeq          43
      30: aload         9
      32: checkcast     #50                 // class org/thymeleaf/spring5/context/webflux/IReactiveSSEDataDriverContextVariable
      35: invokeinterface #51,  1           // InterfaceMethod org/thymeleaf/spring5/context/webflux/IReactiveSSEDataDriverContextVariable.getSseEventsPrefix:()Ljava/lang/String;
      40: goto          44
      43: aconst_null
      44: astore        11
      46: aload         9
      48: instanceof    #50                 // class org/thymeleaf/spring5/context/webflux/IReactiveSSEDataDriverContextVariable
      51: ifeq          67
      54: aload         9
      56: checkcast     #50                 // class org/thymeleaf/spring5/context/webflux/IReactiveSSEDataDriverContextVariable
      59: invokeinterface #52,  1           // InterfaceMethod org/thymeleaf/spring5/context/webflux/IReactiveSSEDataDriverContextVariable.getSseEventsFirstID:()J
      64: goto          68
      67: lconst_0
      68: lstore        12
      70: aload_3
      71: instanceof    #53                 // class org/thymeleaf/spring5/context/webflux/SpringWebFluxContext
      74: ifeq          87
      77: aload_3
      78: checkcast     #53                 // class org/thymeleaf/spring5/context/webflux/SpringWebFluxContext
      81: invokevirtual #54                 // Method org/thymeleaf/spring5/context/webflux/SpringWebFluxContext.getReactiveAdapterRegistry:()Lorg/springframework/core/ReactiveAdapterRegistry;
      84: goto          88
      87: aconst_null
      88: astore        14
      90: new           #55                 // class org/thymeleaf/engine/DataDrivenTemplateIterator
      93: dup
      94: invokespecial #56                 // Method org/thymeleaf/engine/DataDrivenTemplateIterator."<init>":()V
      97: astore        15
      99: aload_3
     100: aload         4
     102: aload         15
     104: invokestatic  #57                 // Method applyDataDriverWrapper:(Lorg/thymeleaf/context/IContext;Ljava/lang/String;Lorg/thymeleaf/engine/DataDrivenTemplateIterator;)Lorg/thymeleaf/context/IContext;
     107: astore        16
     109: aload         9
     111: aload         14
     113: invokeinterface #58,  2           // InterfaceMethod org/thymeleaf/spring5/context/webflux/IReactiveDataDriverContextVariable.getDataStream:(Lorg/springframework/core/ReactiveAdapterRegistry;)Lorg/reactivestreams/Publisher;
     118: invokestatic  #59                 // Method reactor/core/publisher/Flux.from:(Lorg/reactivestreams/Publisher;)Lreactor/core/publisher/Flux;
     121: iload         10
     123: invokevirtual #60                 // Method reactor/core/publisher/Flux.buffer:(I)Lreactor/core/publisher/Flux;
     126: getstatic     #61                 // Field LOG_CATEGORY_DATADRIVEN_INPUT:Ljava/lang/String;
     129: getstatic     #40                 // Field java/util/logging/Level.FINEST:Ljava/util/logging/Level;
     132: iconst_0
     133: anewarray     #41                 // class reactor/core/publisher/SignalType
     136: invokevirtual #47                 // Method reactor/core/publisher/Flux.log:(Ljava/lang/String;Ljava/util/logging/Level;[Lreactor/core/publisher/SignalType;)Lreactor/core/publisher/Flux;
     139: astore        17
     141: aload_0
     142: iload         8
     144: aload_1
     145: aload_2
     146: aload         16
     148: aload         15
     150: aload         11
     152: lload         12
     154: invokedynamic #62,  0             // InvokeDynamic #3:call:(Lorg/thymeleaf/spring5/SpringWebFluxTemplateEngine;ZLjava/lang/String;Ljava/util/Set;Lorg/thymeleaf/context/IContext;Lorg/thymeleaf/engine/DataDrivenTemplateIterator;Ljava/lang/String;J)Ljava/util/concurrent/Callable;
     159: aload         17
     161: invokedynamic #63,  0             // InvokeDynamic #4:apply:(Lreactor/core/publisher/Flux;)Ljava/util/function/Function;
     166: invokedynamic #64,  0             // InvokeDynamic #5:accept:()Ljava/util/function/Consumer;
     171: invokestatic  #65                 // Method reactor/core/publisher/Flux.using:(Ljava/util/concurrent/Callable;Ljava/util/function/Function;Ljava/util/function/Consumer;)Lreactor/core/publisher/Flux;
     174: astore        18
     176: aload         18
     178: aload_1
     179: aload_3
     180: iload         7
     182: aload         5
     184: aload         6
     186: invokedynamic #66,  0             // InvokeDynamic #6:apply:(Ljava/lang/String;Lorg/thymeleaf/context/IContext;ILorg/springframework/core/io/buffer/DataBufferFactory;Ljava/nio/charset/Charset;)Ljava/util/function/Function;
     191: invokevirtual #67                 // Method reactor/core/publisher/Flux.concatMap:(Ljava/util/function/Function;)Lreactor/core/publisher/Flux;
     194: astore        19
     196: aload         19
     198: getstatic     #68                 // Field LOG_CATEGORY_DATADRIVEN_OUTPUT:Ljava/lang/String;
     201: getstatic     #40                 // Field java/util/logging/Level.FINEST:Ljava/util/logging/Level;
     204: iconst_0
     205: anewarray     #41                 // class reactor/core/publisher/SignalType
     208: invokevirtual #47                 // Method reactor/core/publisher/Flux.log:(Ljava/lang/String;Ljava/util/logging/Level;[Lreactor/core/publisher/SignalType;)Lreactor/core/publisher/Flux;
     211: areturn

  private static org.thymeleaf.context.IContext applyDataDriverWrapper(org.thymeleaf.context.IContext, java.lang.String, org.thymeleaf.engine.DataDrivenTemplateIterator);
    Code:
       0: aload_0
       1: instanceof    #69                 // class org/thymeleaf/context/IEngineContext
       4: ifeq          20
       7: aload_0
       8: checkcast     #69                 // class org/thymeleaf/context/IEngineContext
      11: aload_1
      12: aload_2
      13: invokeinterface #70,  3           // InterfaceMethod org/thymeleaf/context/IEngineContext.setVariable:(Ljava/lang/String;Ljava/lang/Object;)V
      18: aload_0
      19: areturn
      20: aload_0
      21: instanceof    #71                 // class org/thymeleaf/spring5/context/webflux/ISpringWebFluxContext
      24: ifeq          41
      27: new           #72                 // class org/thymeleaf/spring5/SpringWebFluxTemplateEngine$DataDrivenSpringWebFluxContextWrapper
      30: dup
      31: aload_0
      32: checkcast     #71                 // class org/thymeleaf/spring5/context/webflux/ISpringWebFluxContext
      35: aload_1
      36: aload_2
      37: invokespecial #73                 // Method org/thymeleaf/spring5/SpringWebFluxTemplateEngine$DataDrivenSpringWebFluxContextWrapper."<init>":(Lorg/thymeleaf/spring5/context/webflux/ISpringWebFluxContext;Ljava/lang/String;Lorg/thymeleaf/engine/DataDrivenTemplateIterator;)V
      40: areturn
      41: new           #74                 // class org/thymeleaf/spring5/SpringWebFluxTemplateEngine$DataDrivenContextWrapper
      44: dup
      45: aload_0
      46: aload_1
      47: aload_2
      48: invokespecial #75                 // Method org/thymeleaf/spring5/SpringWebFluxTemplateEngine$DataDrivenContextWrapper."<init>":(Lorg/thymeleaf/context/IContext;Ljava/lang/String;Lorg/thymeleaf/engine/DataDrivenTemplateIterator;)V
      51: areturn

  private static java.lang.String findDataDriverInModel(org.thymeleaf.context.IContext);
    Code:
       0: aconst_null
       1: astore_1
       2: aload_0
       3: invokeinterface #76,  1           // InterfaceMethod org/thymeleaf/context/IContext.getVariableNames:()Ljava/util/Set;
       8: astore_2
       9: aload_2
      10: invokeinterface #77,  1           // InterfaceMethod java/util/Set.iterator:()Ljava/util/Iterator;
      15: astore_3
      16: aload_3
      17: invokeinterface #78,  1           // InterfaceMethod java/util/Iterator.hasNext:()Z
      22: ifeq          106
      25: aload_3
      26: invokeinterface #79,  1           // InterfaceMethod java/util/Iterator.next:()Ljava/lang/Object;
      31: checkcast     #80                 // class java/lang/String
      34: astore        4
      36: aload_0
      37: aload         4
      39: invokeinterface #48,  2           // InterfaceMethod org/thymeleaf/context/IContext.getVariable:(Ljava/lang/String;)Ljava/lang/Object;
      44: astore        5
      46: aload         5
      48: instanceof    #30                 // class org/thymeleaf/spring5/context/webflux/IReactiveDataDriverContextVariable
      51: ifeq          103
      54: aload_1
      55: ifnull        100
      58: new           #25                 // class org/thymeleaf/exceptions/TemplateProcessingException
      61: dup
      62: new           #26                 // class java/lang/StringBuilder
      65: dup
      66: invokespecial #27                 // Method java/lang/StringBuilder."<init>":()V
      69: ldc           #81                 // String Only one data-driver variable is allowed to be specified as a model attribute, but at least two have been identified: \'
      71: invokevirtual #29                 // Method java/lang/StringBuilder.append:(Ljava/lang/String;)Ljava/lang/StringBuilder;
      74: aload_1
      75: invokevirtual #29                 // Method java/lang/StringBuilder.append:(Ljava/lang/String;)Ljava/lang/StringBuilder;
      78: ldc           #82                 // String \' and \'
      80: invokevirtual #29                 // Method java/lang/StringBuilder.append:(Ljava/lang/String;)Ljava/lang/StringBuilder;
      83: aload         4
      85: invokevirtual #29                 // Method java/lang/StringBuilder.append:(Ljava/lang/String;)Ljava/lang/StringBuilder;
      88: ldc           #83                 // String \'
      90: invokevirtual #29                 // Method java/lang/StringBuilder.append:(Ljava/lang/String;)Ljava/lang/StringBuilder;
      93: invokevirtual #33                 // Method java/lang/StringBuilder.toString:()Ljava/lang/String;
      96: invokespecial #34                 // Method org/thymeleaf/exceptions/TemplateProcessingException."<init>":(Ljava/lang/String;)V
      99: athrow
     100: aload         4
     102: astore_1
     103: goto          16
     106: aload_1
     107: areturn

  private static org.reactivestreams.Publisher lambda$createDataDrivenStream$11(java.lang.String, org.thymeleaf.context.IContext, int, org.springframework.core.io.buffer.DataBufferFactory, java.nio.charset.Charset, org.thymeleaf.spring5.SpringWebFluxTemplateEngine$DataDrivenFluxStep);
    Code:
       0: invokedynamic #84,  0             // InvokeDynamic #7:call:()Ljava/util/concurrent/Callable;
       5: aload         5
       7: aload_0
       8: aload_1
       9: iload_2
      10: aload_3
      11: aload         4
      13: invokedynamic #85,  0             // InvokeDynamic #8:apply:(Lorg/thymeleaf/spring5/SpringWebFluxTemplateEngine$DataDrivenFluxStep;Ljava/lang/String;Lorg/thymeleaf/context/IContext;ILorg/springframework/core/io/buffer/DataBufferFactory;Ljava/nio/charset/Charset;)Ljava/util/function/BiFunction;
      18: invokestatic  #45                 // Method reactor/core/publisher/Flux.generate:(Ljava/util/concurrent/Callable;Ljava/util/function/BiFunction;)Lreactor/core/publisher/Flux;
      21: areturn

  private static java.lang.Boolean lambda$createDataDrivenStream$10(org.thymeleaf.spring5.SpringWebFluxTemplateEngine$DataDrivenFluxStep, java.lang.String, org.thymeleaf.context.IContext, int, org.springframework.core.io.buffer.DataBufferFactory, java.nio.charset.Charset, java.lang.Boolean, reactor.core.publisher.SynchronousSink);
    Code:
       0: aload_0
       1: invokevirtual #86                 // Method org/thymeleaf/spring5/SpringWebFluxTemplateEngine$DataDrivenFluxStep.getThrottledProcessor:()Lorg/thymeleaf/spring5/SpringWebFluxTemplateEngine$StreamThrottledTemplateProcessor;
       4: astore        8
       6: aload         8
       8: invokevirtual #87                 // Method org/thymeleaf/spring5/SpringWebFluxTemplateEngine$StreamThrottledTemplateProcessor.getDataDrivenTemplateIterator:()Lorg/thymeleaf/engine/DataDrivenTemplateIterator;
      11: astore        9
      13: aload         8
      15: invokevirtual #88                 // Method org/thymeleaf/spring5/SpringWebFluxTemplateEngine$StreamThrottledTemplateProcessor.isFinished:()Z
      18: ifeq          32
      21: aload         7
      23: invokeinterface #89,  1           // InterfaceMethod reactor/core/publisher/SynchronousSink.complete:()V
      28: getstatic     #90                 // Field java/lang/Boolean.FALSE:Ljava/lang/Boolean;
      31: areturn
      32: aload         6
      34: invokevirtual #91                 // Method java/lang/Boolean.booleanValue:()Z
      37: ifeq          84
      40: aload_0
      41: invokevirtual #92                 // Method org/thymeleaf/spring5/SpringWebFluxTemplateEngine$DataDrivenFluxStep.isHead:()Z
      44: ifeq          55
      47: aload         9
      49: invokevirtual #93                 // Method org/thymeleaf/engine/DataDrivenTemplateIterator.startHead:()V
      52: goto          84
      55: aload_0
      56: invokevirtual #94                 // Method org/thymeleaf/spring5/SpringWebFluxTemplateEngine$DataDrivenFluxStep.isDataBuffer:()Z
      59: ifeq          74
      62: aload         9
      64: aload_0
      65: invokevirtual #95                 // Method org/thymeleaf/spring5/SpringWebFluxTemplateEngine$DataDrivenFluxStep.getValues:()Ljava/util/List;
      68: invokevirtual #96                 // Method org/thymeleaf/engine/DataDrivenTemplateIterator.feedBuffer:(Ljava/util/List;)V
      71: goto          84
      74: aload         9
      76: invokevirtual #97                 // Method org/thymeleaf/engine/DataDrivenTemplateIterator.feedingComplete:()V
      79: aload         9
      81: invokevirtual #98                 // Method org/thymeleaf/engine/DataDrivenTemplateIterator.startTail:()V
      84: aload         8
      86: invokevirtual #99                 // Method org/thymeleaf/spring5/SpringWebFluxTemplateEngine$StreamThrottledTemplateProcessor.startChunk:()V
      89: getstatic     #100                // Field logger:Lorg/slf4j/Logger;
      92: invokeinterface #101,  1          // InterfaceMethod org/slf4j/Logger.isTraceEnabled:()Z
      97: ifeq          164
     100: getstatic     #100                // Field logger:Lorg/slf4j/Logger;
     103: ldc           #102                // String [THYMELEAF][{}][{}] STARTING PARTIAL STREAM PROCESS (DATA-DRIVEN MODE, THROTTLER ID \"{}\", CHUNK {}) FOR TEMPLATE \"{}\" WITH LOCALE {}
     105: bipush        6
     107: anewarray     #103                // class java/lang/Object
     110: dup
     111: iconst_0
     112: invokestatic  #104                // Method org/thymeleaf/TemplateEngine.threadIndex:()Ljava/lang/String;
     115: aastore
     116: dup
     117: iconst_1
     118: aload         8
     120: invokevirtual #105                // Method org/thymeleaf/spring5/SpringWebFluxTemplateEngine$StreamThrottledTemplateProcessor.getProcessorIdentifier:()Ljava/lang/String;
     123: aastore
     124: dup
     125: iconst_2
     126: aload         8
     128: invokevirtual #105                // Method org/thymeleaf/spring5/SpringWebFluxTemplateEngine$StreamThrottledTemplateProcessor.getProcessorIdentifier:()Ljava/lang/String;
     131: aastore
     132: dup
     133: iconst_3
     134: aload         8
     136: invokevirtual #106                // Method org/thymeleaf/spring5/SpringWebFluxTemplateEngine$StreamThrottledTemplateProcessor.getChunkCount:()I
     139: invokestatic  #107                // Method java/lang/Integer.valueOf:(I)Ljava/lang/Integer;
     142: aastore
     143: dup
     144: iconst_4
     145: aload_1
     146: invokestatic  #108                // Method org/thymeleaf/util/LoggingUtils.loggifyTemplateName:(Ljava/lang/String;)Ljava/lang/String;
     149: aastore
     150: dup
     151: iconst_5
     152: aload_2
     153: invokeinterface #109,  1          // InterfaceMethod org/thymeleaf/context/IContext.getLocale:()Ljava/util/Locale;
     158: aastore
     159: invokeinterface #110,  3          // InterfaceMethod org/slf4j/Logger.trace:(Ljava/lang/String;[Ljava/lang/Object;)V
     164: iload_3
     165: ldc           #9                  // int 2147483647
     167: if_icmpeq     181
     170: aload         4
     172: iload_3
     173: invokeinterface #111,  2          // InterfaceMethod org/springframework/core/io/buffer/DataBufferFactory.allocateBuffer:(I)Lorg/springframework/core/io/buffer/DataBuffer;
     178: goto          188
     181: aload         4
     183: invokeinterface #112,  1          // InterfaceMethod org/springframework/core/io/buffer/DataBufferFactory.allocateBuffer:()Lorg/springframework/core/io/buffer/DataBuffer;
     188: astore        10
     190: aload         8
     192: iload_3
     193: aload         10
     195: invokeinterface #113,  1          // InterfaceMethod org/springframework/core/io/buffer/DataBuffer.asOutputStream:()Ljava/io/OutputStream;
     200: aload         5
     202: invokevirtual #114                // Method org/thymeleaf/spring5/SpringWebFluxTemplateEngine$StreamThrottledTemplateProcessor.process:(ILjava/io/OutputStream;Ljava/nio/charset/Charset;)I
     205: istore        11
     207: goto          225
     210: astore        12
     212: aload         7
     214: aload         12
     216: invokeinterface #115,  2          // InterfaceMethod reactor/core/publisher/SynchronousSink.error:(Ljava/lang/Throwable;)V
     221: getstatic     #90                 // Field java/lang/Boolean.FALSE:Ljava/lang/Boolean;
     224: areturn
     225: getstatic     #100                // Field logger:Lorg/slf4j/Logger;
     228: invokeinterface #101,  1          // InterfaceMethod org/slf4j/Logger.isTraceEnabled:()Z
     233: ifeq          309
     236: getstatic     #100                // Field logger:Lorg/slf4j/Logger;
     239: ldc           #116                // String [THYMELEAF][{}][{}] FINISHED PARTIAL STREAM PROCESS (DATA-DRIVEN MODE, THROTTLER ID \"{}\", CHUNK {}) FOR TEMPLATE \"{}\" WITH LOCALE {}. PRODUCED {} BYTES
     241: bipush        7
     243: anewarray     #103                // class java/lang/Object
     246: dup
     247: iconst_0
     248: invokestatic  #104                // Method org/thymeleaf/TemplateEngine.threadIndex:()Ljava/lang/String;
     251: aastore
     252: dup
     253: iconst_1
     254: aload         8
     256: invokevirtual #105                // Method org/thymeleaf/spring5/SpringWebFluxTemplateEngine$StreamThrottledTemplateProcessor.getProcessorIdentifier:()Ljava/lang/String;
     259: aastore
     260: dup
     261: iconst_2
     262: aload         8
     264: invokevirtual #105                // Method org/thymeleaf/spring5/SpringWebFluxTemplateEngine$StreamThrottledTemplateProcessor.getProcessorIdentifier:()Ljava/lang/String;
     267: aastore
     268: dup
     269: iconst_3
     270: aload         8
     272: invokevirtual #106                // Method org/thymeleaf/spring5/SpringWebFluxTemplateEngine$StreamThrottledTemplateProcessor.getChunkCount:()I
     275: invokestatic  #107                // Method java/lang/Integer.valueOf:(I)Ljava/lang/Integer;
     278: aastore
     279: dup
     280: iconst_4
     281: aload_1
     282: invokestatic  #108                // Method org/thymeleaf/util/LoggingUtils.loggifyTemplateName:(Ljava/lang/String;)Ljava/lang/String;
     285: aastore
     286: dup
     287: iconst_5
     288: aload_2
     289: invokeinterface #109,  1          // InterfaceMethod org/thymeleaf/context/IContext.getLocale:()Ljava/util/Locale;
     294: aastore
     295: dup
     296: bipush        6
     298: iload         11
     300: invokestatic  #107                // Method java/lang/Integer.valueOf:(I)Ljava/lang/Integer;
     303: aastore
     304: invokeinterface #110,  3          // InterfaceMethod org/slf4j/Logger.trace:(Ljava/lang/String;[Ljava/lang/Object;)V
     309: iload         11
     311: ifne          319
     314: aload         9
     316: invokevirtual #117                // Method org/thymeleaf/engine/DataDrivenTemplateIterator.takeBackLastEventID:()V
     319: iconst_0
     320: istore        12
     322: aload         8
     324: invokevirtual #88                 // Method org/thymeleaf/spring5/SpringWebFluxTemplateEngine$StreamThrottledTemplateProcessor.isFinished:()Z
     327: ifeq          430
     330: getstatic     #100                // Field logger:Lorg/slf4j/Logger;
     333: invokeinterface #101,  1          // InterfaceMethod org/slf4j/Logger.isTraceEnabled:()Z
     338: ifeq          419
     341: getstatic     #100                // Field logger:Lorg/slf4j/Logger;
     344: ldc           #118                // String [THYMELEAF][{}][{}] FINISHED ALL STREAM PROCESS (DATA-DRIVEN MODE, THROTTLER ID \"{}\") FOR TEMPLATE \"{}\" WITH LOCALE {}. PRODUCED A TOTAL OF {} BYTES IN {} CHUNKS
     346: bipush        7
     348: anewarray     #103                // class java/lang/Object
     351: dup
     352: iconst_0
     353: invokestatic  #104                // Method org/thymeleaf/TemplateEngine.threadIndex:()Ljava/lang/String;
     356: aastore
     357: dup
     358: iconst_1
     359: aload         8
     361: invokevirtual #105                // Method org/thymeleaf/spring5/SpringWebFluxTemplateEngine$StreamThrottledTemplateProcessor.getProcessorIdentifier:()Ljava/lang/String;
     364: aastore
     365: dup
     366: iconst_2
     367: aload         8
     369: invokevirtual #105                // Method org/thymeleaf/spring5/SpringWebFluxTemplateEngine$StreamThrottledTemplateProcessor.getProcessorIdentifier:()Ljava/lang/String;
     372: aastore
     373: dup
     374: iconst_3
     375: aload_1
     376: invokestatic  #108                // Method org/thymeleaf/util/LoggingUtils.loggifyTemplateName:(Ljava/lang/String;)Ljava/lang/String;
     379: aastore
     380: dup
     381: iconst_4
     382: aload_2
     383: invokeinterface #109,  1          // InterfaceMethod org/thymeleaf/context/IContext.getLocale:()Ljava/util/Locale;
     388: aastore
     389: dup
     390: iconst_5
     391: aload         8
     393: invokevirtual #119                // Method org/thymeleaf/spring5/SpringWebFluxTemplateEngine$StreamThrottledTemplateProcessor.getTotalBytesProduced:()J
     396: invokestatic  #120                // Method java/lang/Long.valueOf:(J)Ljava/lang/Long;
     399: aastore
     400: dup
     401: bipush        6
     403: aload         8
     405: invokevirtual #106                // Method org/thymeleaf/spring5/SpringWebFluxTemplateEngine$StreamThrottledTemplateProcessor.getChunkCount:()I
     408: iconst_1
     409: iadd
     410: invokestatic  #107                // Method java/lang/Integer.valueOf:(I)Ljava/lang/Integer;
     413: aastore
     414: invokeinterface #110,  3          // InterfaceMethod org/slf4j/Logger.trace:(Ljava/lang/String;[Ljava/lang/Object;)V
     419: iconst_1
     420: istore        12
     422: aload         9
     424: invokevirtual #121                // Method org/thymeleaf/engine/DataDrivenTemplateIterator.finishStep:()V
     427: goto          474
     430: aload_0
     431: invokevirtual #92                 // Method org/thymeleaf/spring5/SpringWebFluxTemplateEngine$DataDrivenFluxStep.isHead:()Z
     434: ifeq          456
     437: aload         9
     439: invokevirtual #122                // Method org/thymeleaf/engine/DataDrivenTemplateIterator.hasBeenQueried:()Z
     442: ifeq          456
     445: iconst_1
     446: istore        12
     448: aload         9
     450: invokevirtual #121                // Method org/thymeleaf/engine/DataDrivenTemplateIterator.finishStep:()V
     453: goto          474
     456: aload_0
     457: invokevirtual #94                 // Method org/thymeleaf/spring5/SpringWebFluxTemplateEngine$DataDrivenFluxStep.isDataBuffer:()Z
     460: ifeq          474
     463: aload         9
     465: invokevirtual #123                // Method org/thymeleaf/engine/DataDrivenTemplateIterator.continueBufferExecution:()Z
     468: ifne          474
     471: iconst_1
     472: istore        12
     474: aload         9
     476: invokevirtual #124                // Method org/thymeleaf/engine/DataDrivenTemplateIterator.isStepOutputFinished:()Z
     479: istore        13
     481: aload         7
     483: aload         10
     485: invokeinterface #125,  2          // InterfaceMethod reactor/core/publisher/SynchronousSink.next:(Ljava/lang/Object;)V
     490: iload         12
     492: ifeq          507
     495: iload         13
     497: ifeq          507
     500: aload         7
     502: invokeinterface #89,  1           // InterfaceMethod reactor/core/publisher/SynchronousSink.complete:()V
     507: getstatic     #90                 // Field java/lang/Boolean.FALSE:Ljava/lang/Boolean;
     510: areturn
    Exception table:
       from    to  target type
         190   207   210   Class java/lang/Throwable

  private static java.lang.Boolean lambda$createDataDrivenStream$9() throws java.lang.Exception;
    Code:
       0: getstatic     #126                // Field java/lang/Boolean.TRUE:Ljava/lang/Boolean;
       3: areturn

  private static void lambda$createDataDrivenStream$8(org.thymeleaf.spring5.SpringWebFluxTemplateEngine$StreamThrottledTemplateProcessor);
    Code:
       0: return

  private static org.reactivestreams.Publisher lambda$createDataDrivenStream$7(reactor.core.publisher.Flux, org.thymeleaf.spring5.SpringWebFluxTemplateEngine$StreamThrottledTemplateProcessor);
    Code:
       0: invokedynamic #127,  0            // InvokeDynamic #9:call:()Ljava/util/concurrent/Callable;
       5: aload_1
       6: aload_0
       7: invokedynamic #128,  0            // InvokeDynamic #10:apply:(Lorg/thymeleaf/spring5/SpringWebFluxTemplateEngine$StreamThrottledTemplateProcessor;Lreactor/core/publisher/Flux;)Ljava/util/function/BiFunction;
      12: invokestatic  #45                 // Method reactor/core/publisher/Flux.generate:(Ljava/util/concurrent/Callable;Ljava/util/function/BiFunction;)Lreactor/core/publisher/Flux;
      15: invokestatic  #129                // Method reactor/core/publisher/Flux.concat:(Lorg/reactivestreams/Publisher;)Lreactor/core/publisher/Flux;
      18: areturn

  private static org.thymeleaf.spring5.SpringWebFluxTemplateEngine$DataDrivenFluxStep$FluxStepPhase lambda$createDataDrivenStream$6(org.thymeleaf.spring5.SpringWebFluxTemplateEngine$StreamThrottledTemplateProcessor, reactor.core.publisher.Flux, org.thymeleaf.spring5.SpringWebFluxTemplateEngine$DataDrivenFluxStep$FluxStepPhase, reactor.core.publisher.SynchronousSink);
    Code:
       0: aload_0
       1: invokevirtual #88                 // Method org/thymeleaf/spring5/SpringWebFluxTemplateEngine$StreamThrottledTemplateProcessor.isFinished:()Z
       4: ifeq          15
       7: aload_3
       8: invokeinterface #89,  1           // InterfaceMethod reactor/core/publisher/SynchronousSink.complete:()V
      13: aconst_null
      14: areturn
      15: getstatic     #130                // Field org/thymeleaf/spring5/SpringWebFluxTemplateEngine$1.$SwitchMap$org$thymeleaf$spring5$SpringWebFluxTemplateEngine$DataDrivenFluxStep$FluxStepPhase:[I
      18: aload_2
      19: invokevirtual #131                // Method org/thymeleaf/spring5/SpringWebFluxTemplateEngine$DataDrivenFluxStep$FluxStepPhase.ordinal:()I
      22: iaload
      23: tableswitch   { // 1 to 3
                     1: 48
                     2: 65
                     3: 85
               default: 104
          }
      48: aload_3
      49: aload_0
      50: invokestatic  #132                // Method org/thymeleaf/spring5/SpringWebFluxTemplateEngine$DataDrivenFluxStep.forHead:(Lorg/thymeleaf/spring5/SpringWebFluxTemplateEngine$StreamThrottledTemplateProcessor;)Lorg/thymeleaf/spring5/SpringWebFluxTemplateEngine$DataDrivenFluxStep;
      53: invokestatic  #133                // Method reactor/core/publisher/Mono.just:(Ljava/lang/Object;)Lreactor/core/publisher/Mono;
      56: invokeinterface #125,  2          // InterfaceMethod reactor/core/publisher/SynchronousSink.next:(Ljava/lang/Object;)V
      61: getstatic     #134                // Field org/thymeleaf/spring5/SpringWebFluxTemplateEngine$DataDrivenFluxStep$FluxStepPhase.DATA_DRIVEN_PHASE_BUFFER:Lorg/thymeleaf/spring5/SpringWebFluxTemplateEngine$DataDrivenFluxStep$FluxStepPhase;
      64: areturn
      65: aload_3
      66: aload_1
      67: aload_0
      68: invokedynamic #135,  0            // InvokeDynamic #11:apply:(Lorg/thymeleaf/spring5/SpringWebFluxTemplateEngine$StreamThrottledTemplateProcessor;)Ljava/util/function/Function;
      73: invokevirtual #136                // Method reactor/core/publisher/Flux.map:(Ljava/util/function/Function;)Lreactor/core/publisher/Flux;
      76: invokeinterface #125,  2          // InterfaceMethod reactor/core/publisher/SynchronousSink.next:(Ljava/lang/Object;)V
      81: getstatic     #137                // Field org/thymeleaf/spring5/SpringWebFluxTemplateEngine$DataDrivenFluxStep$FluxStepPhase.DATA_DRIVEN_PHASE_TAIL:Lorg/thymeleaf/spring5/SpringWebFluxTemplateEngine$DataDrivenFluxStep$FluxStepPhase;
      84: areturn
      85: aload_3
      86: aload_0
      87: invokestatic  #138                // Method org/thymeleaf/spring5/SpringWebFluxTemplateEngine$DataDrivenFluxStep.forTail:(Lorg/thymeleaf/spring5/SpringWebFluxTemplateEngine$StreamThrottledTemplateProcessor;)Lorg/thymeleaf/spring5/SpringWebFluxTemplateEngine$DataDrivenFluxStep;
      90: invokestatic  #133                // Method reactor/core/publisher/Mono.just:(Ljava/lang/Object;)Lreactor/core/publisher/Mono;
      93: invokeinterface #125,  2          // InterfaceMethod reactor/core/publisher/SynchronousSink.next:(Ljava/lang/Object;)V
      98: aload_3
      99: invokeinterface #89,  1           // InterfaceMethod reactor/core/publisher/SynchronousSink.complete:()V
     104: aconst_null
     105: areturn

  private static org.thymeleaf.spring5.SpringWebFluxTemplateEngine$DataDrivenFluxStep lambda$createDataDrivenStream$5(org.thymeleaf.spring5.SpringWebFluxTemplateEngine$StreamThrottledTemplateProcessor, java.util.List);
    Code:
       0: aload_0
       1: aload_1
       2: invokestatic  #139                // Method org/thymeleaf/spring5/SpringWebFluxTemplateEngine$DataDrivenFluxStep.forBuffer:(Lorg/thymeleaf/spring5/SpringWebFluxTemplateEngine$StreamThrottledTemplateProcessor;Ljava/util/List;)Lorg/thymeleaf/spring5/SpringWebFluxTemplateEngine$DataDrivenFluxStep;
       5: areturn

  private static org.thymeleaf.spring5.SpringWebFluxTemplateEngine$DataDrivenFluxStep$FluxStepPhase lambda$createDataDrivenStream$4() throws java.lang.Exception;
    Code:
       0: getstatic     #140                // Field org/thymeleaf/spring5/SpringWebFluxTemplateEngine$DataDrivenFluxStep$FluxStepPhase.DATA_DRIVEN_PHASE_HEAD:Lorg/thymeleaf/spring5/SpringWebFluxTemplateEngine$DataDrivenFluxStep$FluxStepPhase;
       3: areturn

  private org.thymeleaf.spring5.SpringWebFluxTemplateEngine$StreamThrottledTemplateProcessor lambda$createDataDrivenStream$3(boolean, java.lang.String, java.util.Set, org.thymeleaf.context.IContext, org.thymeleaf.engine.DataDrivenTemplateIterator, java.lang.String, long) throws java.lang.Exception;
    Code:
       0: iload_1
       1: ifeq          9
       4: ldc           #141                // String text/event-stream
       6: goto          10
       9: aconst_null
      10: astore        9
      12: new           #142                // class org/thymeleaf/TemplateSpec
      15: dup
      16: aload_2
      17: aload_3
      18: aload         9
      20: aconst_null
      21: invokespecial #143                // Method org/thymeleaf/TemplateSpec."<init>":(Ljava/lang/String;Ljava/util/Set;Ljava/lang/String;Ljava/util/Map;)V
      24: astore        10
      26: new           #144                // class org/thymeleaf/spring5/SpringWebFluxTemplateEngine$StreamThrottledTemplateProcessor
      29: dup
      30: aload_0
      31: aload         10
      33: aload         4
      35: invokevirtual #145                // Method processThrottled:(Lorg/thymeleaf/TemplateSpec;Lorg/thymeleaf/context/IContext;)Lorg/thymeleaf/IThrottledTemplateProcessor;
      38: aload         5
      40: aload         6
      42: lload         7
      44: iload_1
      45: invokespecial #146                // Method org/thymeleaf/spring5/SpringWebFluxTemplateEngine$StreamThrottledTemplateProcessor."<init>":(Lorg/thymeleaf/IThrottledTemplateProcessor;Lorg/thymeleaf/engine/DataDrivenTemplateIterator;Ljava/lang/String;JZ)V
      48: areturn

  private static org.thymeleaf.spring5.SpringWebFluxTemplateEngine$StreamThrottledTemplateProcessor lambda$createChunkedStream$2(java.lang.String, org.thymeleaf.context.IContext, org.springframework.core.io.buffer.DataBufferFactory, int, java.nio.charset.Charset, org.thymeleaf.spring5.SpringWebFluxTemplateEngine$StreamThrottledTemplateProcessor, reactor.core.publisher.SynchronousSink);
    Code:
       0: aload         5
       2: invokevirtual #99                 // Method org/thymeleaf/spring5/SpringWebFluxTemplateEngine$StreamThrottledTemplateProcessor.startChunk:()V
       5: getstatic     #100                // Field logger:Lorg/slf4j/Logger;
       8: invokeinterface #101,  1          // InterfaceMethod org/slf4j/Logger.isTraceEnabled:()Z
      13: ifeq          80
      16: getstatic     #100                // Field logger:Lorg/slf4j/Logger;
      19: ldc           #147                // String [THYMELEAF][{}][{}] STARTING PARTIAL STREAM PROCESS (CHUNKED MODE, THROTTLER ID \"{}\", CHUNK {}) FOR TEMPLATE \"{}\" WITH LOCALE {}
      21: bipush        6
      23: anewarray     #103                // class java/lang/Object
      26: dup
      27: iconst_0
      28: invokestatic  #104                // Method org/thymeleaf/TemplateEngine.threadIndex:()Ljava/lang/String;
      31: aastore
      32: dup
      33: iconst_1
      34: aload         5
      36: invokevirtual #105                // Method org/thymeleaf/spring5/SpringWebFluxTemplateEngine$StreamThrottledTemplateProcessor.getProcessorIdentifier:()Ljava/lang/String;
      39: aastore
      40: dup
      41: iconst_2
      42: aload         5
      44: invokevirtual #105                // Method org/thymeleaf/spring5/SpringWebFluxTemplateEngine$StreamThrottledTemplateProcessor.getProcessorIdentifier:()Ljava/lang/String;
      47: aastore
      48: dup
      49: iconst_3
      50: aload         5
      52: invokevirtual #106                // Method org/thymeleaf/spring5/SpringWebFluxTemplateEngine$StreamThrottledTemplateProcessor.getChunkCount:()I
      55: invokestatic  #107                // Method java/lang/Integer.valueOf:(I)Ljava/lang/Integer;
      58: aastore
      59: dup
      60: iconst_4
      61: aload_0
      62: invokestatic  #108                // Method org/thymeleaf/util/LoggingUtils.loggifyTemplateName:(Ljava/lang/String;)Ljava/lang/String;
      65: aastore
      66: dup
      67: iconst_5
      68: aload_1
      69: invokeinterface #109,  1          // InterfaceMethod org/thymeleaf/context/IContext.getLocale:()Ljava/util/Locale;
      74: aastore
      75: invokeinterface #110,  3          // InterfaceMethod org/slf4j/Logger.trace:(Ljava/lang/String;[Ljava/lang/Object;)V
      80: aload_2
      81: iload_3
      82: invokeinterface #111,  2          // InterfaceMethod org/springframework/core/io/buffer/DataBufferFactory.allocateBuffer:(I)Lorg/springframework/core/io/buffer/DataBuffer;
      87: astore        7
      89: aload         5
      91: iload_3
      92: aload         7
      94: invokeinterface #113,  1          // InterfaceMethod org/springframework/core/io/buffer/DataBuffer.asOutputStream:()Ljava/io/OutputStream;
      99: aload         4
     101: invokevirtual #114                // Method org/thymeleaf/spring5/SpringWebFluxTemplateEngine$StreamThrottledTemplateProcessor.process:(ILjava/io/OutputStream;Ljava/nio/charset/Charset;)I
     104: istore        8
     106: goto          122
     109: astore        9
     111: aload         6
     113: aload         9
     115: invokeinterface #115,  2          // InterfaceMethod reactor/core/publisher/SynchronousSink.error:(Ljava/lang/Throwable;)V
     120: aconst_null
     121: areturn
     122: getstatic     #100                // Field logger:Lorg/slf4j/Logger;
     125: invokeinterface #101,  1          // InterfaceMethod org/slf4j/Logger.isTraceEnabled:()Z
     130: ifeq          206
     133: getstatic     #100                // Field logger:Lorg/slf4j/Logger;
     136: ldc           #148                // String [THYMELEAF][{}][{}] FINISHED PARTIAL STREAM PROCESS (CHUNKED MODE, THROTTLER ID \"{}\", CHUNK {}) FOR TEMPLATE \"{}\" WITH LOCALE {}. PRODUCED {} BYTES
     138: bipush        7
     140: anewarray     #103                // class java/lang/Object
     143: dup
     144: iconst_0
     145: invokestatic  #104                // Method org/thymeleaf/TemplateEngine.threadIndex:()Ljava/lang/String;
     148: aastore
     149: dup
     150: iconst_1
     151: aload         5
     153: invokevirtual #105                // Method org/thymeleaf/spring5/SpringWebFluxTemplateEngine$StreamThrottledTemplateProcessor.getProcessorIdentifier:()Ljava/lang/String;
     156: aastore
     157: dup
     158: iconst_2
     159: aload         5
     161: invokevirtual #105                // Method org/thymeleaf/spring5/SpringWebFluxTemplateEngine$StreamThrottledTemplateProcessor.getProcessorIdentifier:()Ljava/lang/String;
     164: aastore
     165: dup
     166: iconst_3
     167: aload         5
     169: invokevirtual #106                // Method org/thymeleaf/spring5/SpringWebFluxTemplateEngine$StreamThrottledTemplateProcessor.getChunkCount:()I
     172: invokestatic  #107                // Method java/lang/Integer.valueOf:(I)Ljava/lang/Integer;
     175: aastore
     176: dup
     177: iconst_4
     178: aload_0
     179: invokestatic  #108                // Method org/thymeleaf/util/LoggingUtils.loggifyTemplateName:(Ljava/lang/String;)Ljava/lang/String;
     182: aastore
     183: dup
     184: iconst_5
     185: aload_1
     186: invokeinterface #109,  1          // InterfaceMethod org/thymeleaf/context/IContext.getLocale:()Ljava/util/Locale;
     191: aastore
     192: dup
     193: bipush        6
     195: iload         8
     197: invokestatic  #107                // Method java/lang/Integer.valueOf:(I)Ljava/lang/Integer;
     200: aastore
     201: invokeinterface #110,  3          // InterfaceMethod org/slf4j/Logger.trace:(Ljava/lang/String;[Ljava/lang/Object;)V
     206: aload         6
     208: aload         7
     210: invokeinterface #125,  2          // InterfaceMethod reactor/core/publisher/SynchronousSink.next:(Ljava/lang/Object;)V
     215: aload         5
     217: invokevirtual #88                 // Method org/thymeleaf/spring5/SpringWebFluxTemplateEngine$StreamThrottledTemplateProcessor.isFinished:()Z
     220: ifeq          319
     223: getstatic     #100                // Field logger:Lorg/slf4j/Logger;
     226: invokeinterface #101,  1          // InterfaceMethod org/slf4j/Logger.isTraceEnabled:()Z
     231: ifeq          312
     234: getstatic     #100                // Field logger:Lorg/slf4j/Logger;
     237: ldc           #149                // String [THYMELEAF][{}][{}] FINISHED ALL STREAM PROCESS (CHUNKED MODE, THROTTLER ID \"{}\") FOR TEMPLATE \"{}\" WITH LOCALE {}. PRODUCED A TOTAL OF {} BYTES IN {} CHUNKS
     239: bipush        7
     241: anewarray     #103                // class java/lang/Object
     244: dup
     245: iconst_0
     246: invokestatic  #104                // Method org/thymeleaf/TemplateEngine.threadIndex:()Ljava/lang/String;
     249: aastore
     250: dup
     251: iconst_1
     252: aload         5
     254: invokevirtual #105                // Method org/thymeleaf/spring5/SpringWebFluxTemplateEngine$StreamThrottledTemplateProcessor.getProcessorIdentifier:()Ljava/lang/String;
     257: aastore
     258: dup
     259: iconst_2
     260: aload         5
     262: invokevirtual #105                // Method org/thymeleaf/spring5/SpringWebFluxTemplateEngine$StreamThrottledTemplateProcessor.getProcessorIdentifier:()Ljava/lang/String;
     265: aastore
     266: dup
     267: iconst_3
     268: aload_0
     269: invokestatic  #108                // Method org/thymeleaf/util/LoggingUtils.loggifyTemplateName:(Ljava/lang/String;)Ljava/lang/String;
     272: aastore
     273: dup
     274: iconst_4
     275: aload_1
     276: invokeinterface #109,  1          // InterfaceMethod org/thymeleaf/context/IContext.getLocale:()Ljava/util/Locale;
     281: aastore
     282: dup
     283: iconst_5
     284: aload         5
     286: invokevirtual #119                // Method org/thymeleaf/spring5/SpringWebFluxTemplateEngine$StreamThrottledTemplateProcessor.getTotalBytesProduced:()J
     289: invokestatic  #120                // Method java/lang/Long.valueOf:(J)Ljava/lang/Long;
     292: aastore
     293: dup
     294: bipush        6
     296: aload         5
     298: invokevirtual #106                // Method org/thymeleaf/spring5/SpringWebFluxTemplateEngine$StreamThrottledTemplateProcessor.getChunkCount:()I
     301: iconst_1
     302: iadd
     303: invokestatic  #107                // Method java/lang/Integer.valueOf:(I)Ljava/lang/Integer;
     306: aastore
     307: invokeinterface #110,  3          // InterfaceMethod org/slf4j/Logger.trace:(Ljava/lang/String;[Ljava/lang/Object;)V
     312: aload         6
     314: invokeinterface #89,  1           // InterfaceMethod reactor/core/publisher/SynchronousSink.complete:()V
     319: aload         5
     321: areturn
    Exception table:
       from    to  target type
          89   106   109   Class java/lang/Throwable

  private org.thymeleaf.spring5.SpringWebFluxTemplateEngine$StreamThrottledTemplateProcessor lambda$createChunkedStream$1(java.lang.String, java.util.Set, org.thymeleaf.context.IContext) throws java.lang.Exception;
    Code:
       0: new           #144                // class org/thymeleaf/spring5/SpringWebFluxTemplateEngine$StreamThrottledTemplateProcessor
       3: dup
       4: aload_0
       5: aload_1
       6: aload_2
       7: aload_3
       8: invokevirtual #150                // Method processThrottled:(Ljava/lang/String;Ljava/util/Set;Lorg/thymeleaf/context/IContext;)Lorg/thymeleaf/IThrottledTemplateProcessor;
      11: aconst_null
      12: aconst_null
      13: lconst_0
      14: iconst_0
      15: invokespecial #146                // Method org/thymeleaf/spring5/SpringWebFluxTemplateEngine$StreamThrottledTemplateProcessor."<init>":(Lorg/thymeleaf/IThrottledTemplateProcessor;Lorg/thymeleaf/engine/DataDrivenTemplateIterator;Ljava/lang/String;JZ)V
      18: areturn

  private void lambda$createFullStream$0(java.lang.String, org.thymeleaf.context.IContext, org.springframework.core.io.buffer.DataBufferFactory, java.nio.charset.Charset, java.util.Set, reactor.core.publisher.MonoSink);
    Code:
       0: getstatic     #100                // Field logger:Lorg/slf4j/Logger;
       3: invokeinterface #101,  1          // InterfaceMethod org/slf4j/Logger.isTraceEnabled:()Z
       8: ifeq          47
      11: getstatic     #100                // Field logger:Lorg/slf4j/Logger;
      14: ldc           #151                // String [THYMELEAF][{}] STARTING STREAM PROCESS (FULL MODE) OF TEMPLATE \"{}\" WITH LOCALE {}
      16: iconst_3
      17: anewarray     #103                // class java/lang/Object
      20: dup
      21: iconst_0
      22: invokestatic  #104                // Method org/thymeleaf/TemplateEngine.threadIndex:()Ljava/lang/String;
      25: aastore
      26: dup
      27: iconst_1
      28: aload_1
      29: invokestatic  #108                // Method org/thymeleaf/util/LoggingUtils.loggifyTemplateName:(Ljava/lang/String;)Ljava/lang/String;
      32: aastore
      33: dup
      34: iconst_2
      35: aload_2
      36: invokeinterface #109,  1          // InterfaceMethod org/thymeleaf/context/IContext.getLocale:()Ljava/util/Locale;
      41: aastore
      42: invokeinterface #110,  3          // InterfaceMethod org/slf4j/Logger.trace:(Ljava/lang/String;[Ljava/lang/Object;)V
      47: aload_3
      48: invokeinterface #112,  1          // InterfaceMethod org/springframework/core/io/buffer/DataBufferFactory.allocateBuffer:()Lorg/springframework/core/io/buffer/DataBuffer;
      53: astore        7
      55: new           #152                // class java/io/OutputStreamWriter
      58: dup
      59: aload         7
      61: invokeinterface #113,  1          // InterfaceMethod org/springframework/core/io/buffer/DataBuffer.asOutputStream:()Ljava/io/OutputStream;
      66: aload         4
      68: invokespecial #153                // Method java/io/OutputStreamWriter."<init>":(Ljava/io/OutputStream;Ljava/nio/charset/Charset;)V
      71: astore        8
      73: aload_0
      74: aload_1
      75: aload         5
      77: aload_2
      78: aload         8
      80: invokevirtual #154                // Method process:(Ljava/lang/String;Ljava/util/Set;Lorg/thymeleaf/context/IContext;Ljava/io/Writer;)V
      83: goto          138
      86: astore        9
      88: getstatic     #100                // Field logger:Lorg/slf4j/Logger;
      91: ldc           #155                // String [THYMELEAF][%s] Exception processing template \"%s\": %s
      93: iconst_3
      94: anewarray     #103                // class java/lang/Object
      97: dup
      98: iconst_0
      99: invokestatic  #104                // Method org/thymeleaf/TemplateEngine.threadIndex:()Ljava/lang/String;
     102: aastore
     103: dup
     104: iconst_1
     105: aload_1
     106: invokestatic  #108                // Method org/thymeleaf/util/LoggingUtils.loggifyTemplateName:(Ljava/lang/String;)Ljava/lang/String;
     109: aastore
     110: dup
     111: iconst_2
     112: aload         9
     114: invokevirtual #156                // Method java/lang/Throwable.getMessage:()Ljava/lang/String;
     117: aastore
     118: invokestatic  #157                // Method java/lang/String.format:(Ljava/lang/String;[Ljava/lang/Object;)Ljava/lang/String;
     121: aload         9
     123: invokeinterface #158,  3          // InterfaceMethod org/slf4j/Logger.error:(Ljava/lang/String;Ljava/lang/Throwable;)V
     128: aload         6
     130: aload         9
     132: invokeinterface #159,  2          // InterfaceMethod reactor/core/publisher/MonoSink.error:(Ljava/lang/Throwable;)V
     137: return
     138: aload         7
     140: invokeinterface #160,  1          // InterfaceMethod org/springframework/core/io/buffer/DataBuffer.readableByteCount:()I
     145: istore        9
     147: getstatic     #100                // Field logger:Lorg/slf4j/Logger;
     150: invokeinterface #101,  1          // InterfaceMethod org/slf4j/Logger.isTraceEnabled:()Z
     155: ifeq          202
     158: getstatic     #100                // Field logger:Lorg/slf4j/Logger;
     161: ldc           #161                // String [THYMELEAF][{}] FINISHED STREAM PROCESS (FULL MODE) OF TEMPLATE \"{}\" WITH LOCALE {}. PRODUCED {} BYTES
     163: iconst_4
     164: anewarray     #103                // class java/lang/Object
     167: dup
     168: iconst_0
     169: invokestatic  #104                // Method org/thymeleaf/TemplateEngine.threadIndex:()Ljava/lang/String;
     172: aastore
     173: dup
     174: iconst_1
     175: aload_1
     176: invokestatic  #108                // Method org/thymeleaf/util/LoggingUtils.loggifyTemplateName:(Ljava/lang/String;)Ljava/lang/String;
     179: aastore
     180: dup
     181: iconst_2
     182: aload_2
     183: invokeinterface #109,  1          // InterfaceMethod org/thymeleaf/context/IContext.getLocale:()Ljava/util/Locale;
     188: aastore
     189: dup
     190: iconst_3
     191: iload         9
     193: invokestatic  #107                // Method java/lang/Integer.valueOf:(I)Ljava/lang/Integer;
     196: aastore
     197: invokeinterface #110,  3          // InterfaceMethod org/slf4j/Logger.trace:(Ljava/lang/String;[Ljava/lang/Object;)V
     202: aload         6
     204: aload         7
     206: invokeinterface #162,  2          // InterfaceMethod reactor/core/publisher/MonoSink.success:(Ljava/lang/Object;)V
     211: return
    Exception table:
       from    to  target type
          73    83    86   Class java/lang/Throwable

  static {};
    Code:
       0: ldc           #163                // class org/thymeleaf/spring5/SpringWebFluxTemplateEngine
       2: invokestatic  #164                // Method org/slf4j/LoggerFactory.getLogger:(Ljava/lang/Class;)Lorg/slf4j/Logger;
       5: putstatic     #100                // Field logger:Lorg/slf4j/Logger;
       8: new           #26                 // class java/lang/StringBuilder
      11: dup
      12: invokespecial #27                 // Method java/lang/StringBuilder."<init>":()V
      15: ldc           #163                // class org/thymeleaf/spring5/SpringWebFluxTemplateEngine
      17: invokevirtual #31                 // Method java/lang/Class.getName:()Ljava/lang/String;
      20: invokevirtual #29                 // Method java/lang/StringBuilder.append:(Ljava/lang/String;)Ljava/lang/StringBuilder;
      23: ldc           #165                // String .DOWNSTREAM.FULL
      25: invokevirtual #29                 // Method java/lang/StringBuilder.append:(Ljava/lang/String;)Ljava/lang/StringBuilder;
      28: invokevirtual #33                 // Method java/lang/StringBuilder.toString:()Ljava/lang/String;
      31: putstatic     #39                 // Field LOG_CATEGORY_FULL_OUTPUT:Ljava/lang/String;
      34: new           #26                 // class java/lang/StringBuilder
      37: dup
      38: invokespecial #27                 // Method java/lang/StringBuilder."<init>":()V
      41: ldc           #163                // class org/thymeleaf/spring5/SpringWebFluxTemplateEngine
      43: invokevirtual #31                 // Method java/lang/Class.getName:()Ljava/lang/String;
      46: invokevirtual #29                 // Method java/lang/StringBuilder.append:(Ljava/lang/String;)Ljava/lang/StringBuilder;
      49: ldc           #166                // String .DOWNSTREAM.CHUNKED
      51: invokevirtual #29                 // Method java/lang/StringBuilder.append:(Ljava/lang/String;)Ljava/lang/StringBuilder;
      54: invokevirtual #33                 // Method java/lang/StringBuilder.toString:()Ljava/lang/String;
      57: putstatic     #46                 // Field LOG_CATEGORY_CHUNKED_OUTPUT:Ljava/lang/String;
      60: new           #26                 // class java/lang/StringBuilder
      63: dup
      64: invokespecial #27                 // Method java/lang/StringBuilder."<init>":()V
      67: ldc           #163                // class org/thymeleaf/spring5/SpringWebFluxTemplateEngine
      69: invokevirtual #31                 // Method java/lang/Class.getName:()Ljava/lang/String;
      72: invokevirtual #29                 // Method java/lang/StringBuilder.append:(Ljava/lang/String;)Ljava/lang/StringBuilder;
      75: ldc           #167                // String .UPSTREAM.DATA-DRIVEN
      77: invokevirtual #29                 // Method java/lang/StringBuilder.append:(Ljava/lang/String;)Ljava/lang/StringBuilder;
      80: invokevirtual #33                 // Method java/lang/StringBuilder.toString:()Ljava/lang/String;
      83: putstatic     #61                 // Field LOG_CATEGORY_DATADRIVEN_INPUT:Ljava/lang/String;
      86: new           #26                 // class java/lang/StringBuilder
      89: dup
      90: invokespecial #27                 // Method java/lang/StringBuilder."<init>":()V
      93: ldc           #163                // class org/thymeleaf/spring5/SpringWebFluxTemplateEngine
      95: invokevirtual #31                 // Method java/lang/Class.getName:()Ljava/lang/String;
      98: invokevirtual #29                 // Method java/lang/StringBuilder.append:(Ljava/lang/String;)Ljava/lang/StringBuilder;
     101: ldc           #168                // String .DOWNSTREAM.DATA-DRIVEN
     103: invokevirtual #29                 // Method java/lang/StringBuilder.append:(Ljava/lang/String;)Ljava/lang/StringBuilder;
     106: invokevirtual #33                 // Method java/lang/StringBuilder.toString:()Ljava/lang/String;
     109: putstatic     #68                 // Field LOG_CATEGORY_DATADRIVEN_OUTPUT:Ljava/lang/String;
     112: return
}
