Compiled from "YAMLParser.java"
public class io.dekorate.deps.jackson.dataformat.yaml.YAMLParser extends io.dekorate.deps.jackson.core.base.ParserBase {
  private static final java.util.regex.Pattern PATTERN_FLOAT;

  protected io.dekorate.deps.jackson.core.ObjectCodec _objectCodec;

  protected int _formatFeatures;

  protected final java.io.Reader _reader;

  protected final io.dekorate.deps.snakeyaml.parser.ParserImpl _yamlParser;

  protected final io.dekorate.deps.snakeyaml.resolver.Resolver _yamlResolver;

  protected io.dekorate.deps.snakeyaml.events.Event _lastEvent;

  protected java.lang.String _textValue;

  protected java.lang.String _cleanedTextValue;

  protected java.lang.String _currentFieldName;

  protected boolean _currentIsAlias;

  protected java.lang.String _currentAnchor;

  public io.dekorate.deps.jackson.dataformat.yaml.YAMLParser(io.dekorate.deps.jackson.core.io.IOContext, io.dekorate.deps.jackson.core.util.BufferRecycler, int, int, io.dekorate.deps.jackson.core.ObjectCodec, java.io.Reader);
    Code:
       0: aload_0
       1: aload_1
       2: iload_3
       3: invokespecial #43                 // Method io/dekorate/deps/jackson/core/base/ParserBase."<init>":(Lio/dekorate/deps/jackson/core/io/IOContext;I)V
       6: aload_0
       7: new           #45                 // class io/dekorate/deps/snakeyaml/resolver/Resolver
      10: dup
      11: invokespecial #48                 // Method io/dekorate/deps/snakeyaml/resolver/Resolver."<init>":()V
      14: putfield      #50                 // Field _yamlResolver:Lio/dekorate/deps/snakeyaml/resolver/Resolver;
      17: aload_0
      18: aload         5
      20: putfield      #52                 // Field _objectCodec:Lio/dekorate/deps/jackson/core/ObjectCodec;
      23: aload_0
      24: iload         4
      26: putfield      #54                 // Field _formatFeatures:I
      29: aload_0
      30: aload         6
      32: putfield      #56                 // Field _reader:Ljava/io/Reader;
      35: aload_0
      36: new           #58                 // class io/dekorate/deps/snakeyaml/parser/ParserImpl
      39: dup
      40: new           #60                 // class io/dekorate/deps/snakeyaml/reader/StreamReader
      43: dup
      44: aload         6
      46: invokespecial #63                 // Method io/dekorate/deps/snakeyaml/reader/StreamReader."<init>":(Ljava/io/Reader;)V
      49: invokespecial #66                 // Method io/dekorate/deps/snakeyaml/parser/ParserImpl."<init>":(Lio/dekorate/deps/snakeyaml/reader/StreamReader;)V
      52: putfield      #68                 // Field _yamlParser:Lio/dekorate/deps/snakeyaml/parser/ParserImpl;
      55: return

  public io.dekorate.deps.jackson.core.ObjectCodec getCodec();
    Code:
       0: aload_0
       1: getfield      #52                 // Field _objectCodec:Lio/dekorate/deps/jackson/core/ObjectCodec;
       4: areturn

  public void setCodec(io.dekorate.deps.jackson.core.ObjectCodec);
    Code:
       0: aload_0
       1: aload_1
       2: putfield      #52                 // Field _objectCodec:Lio/dekorate/deps/jackson/core/ObjectCodec;
       5: return

  public boolean isCurrentAlias();
    Code:
       0: aload_0
       1: getfield      #87                 // Field _currentIsAlias:Z
       4: ireturn

  public java.lang.String getCurrentAnchor();
    Code:
       0: aload_0
       1: getfield      #92                 // Field _currentAnchor:Ljava/lang/String;
       4: areturn

  public io.dekorate.deps.jackson.core.Version version();
    Code:
       0: getstatic     #100                // Field io/dekorate/deps/jackson/dataformat/yaml/PackageVersion.VERSION:Lio/dekorate/deps/jackson/core/Version;
       3: areturn

  protected void _closeInput() throws java.io.IOException;
    Code:
       0: aload_0
       1: getfield      #106                // Field _ioContext:Lio/dekorate/deps/jackson/core/io/IOContext;
       4: invokevirtual #111                // Method io/dekorate/deps/jackson/core/io/IOContext.isResourceManaged:()Z
       7: ifne          20
      10: aload_0
      11: getstatic     #115                // Field io/dekorate/deps/jackson/core/JsonParser$Feature.AUTO_CLOSE_SOURCE:Lio/dekorate/deps/jackson/core/JsonParser$Feature;
      14: invokevirtual #119                // Method isEnabled:(Lio/dekorate/deps/jackson/core/JsonParser$Feature;)Z
      17: ifeq          27
      20: aload_0
      21: getfield      #56                 // Field _reader:Ljava/io/Reader;
      24: invokevirtual #124                // Method java/io/Reader.close:()V
      27: return

  public int getFormatFeatures();
    Code:
       0: aload_0
       1: getfield      #54                 // Field _formatFeatures:I
       4: ireturn

  public io.dekorate.deps.jackson.core.JsonParser overrideFormatFeatures(int, int);
    Code:
       0: aload_0
       1: aload_0
       2: getfield      #54                 // Field _formatFeatures:I
       5: iload_2
       6: iconst_m1
       7: ixor
       8: iand
       9: iload_1
      10: iload_2
      11: iand
      12: ior
      13: putfield      #54                 // Field _formatFeatures:I
      16: aload_0
      17: areturn

  public io.dekorate.deps.jackson.core.JsonParser enable(io.dekorate.deps.jackson.dataformat.yaml.YAMLParser$Feature);
    Code:
       0: aload_0
       1: dup
       2: getfield      #54                 // Field _formatFeatures:I
       5: aload_1
       6: invokevirtual #135                // Method io/dekorate/deps/jackson/dataformat/yaml/YAMLParser$Feature.getMask:()I
       9: ior
      10: putfield      #54                 // Field _formatFeatures:I
      13: aload_0
      14: areturn

  public io.dekorate.deps.jackson.core.JsonParser disable(io.dekorate.deps.jackson.dataformat.yaml.YAMLParser$Feature);
    Code:
       0: aload_0
       1: dup
       2: getfield      #54                 // Field _formatFeatures:I
       5: aload_1
       6: invokevirtual #135                // Method io/dekorate/deps/jackson/dataformat/yaml/YAMLParser$Feature.getMask:()I
       9: iconst_m1
      10: ixor
      11: iand
      12: putfield      #54                 // Field _formatFeatures:I
      15: aload_0
      16: areturn

  public io.dekorate.deps.jackson.core.JsonParser configure(io.dekorate.deps.jackson.dataformat.yaml.YAMLParser$Feature, boolean);
    Code:
       0: iload_2
       1: ifeq          13
       4: aload_0
       5: aload_1
       6: invokevirtual #142                // Method enable:(Lio/dekorate/deps/jackson/dataformat/yaml/YAMLParser$Feature;)Lio/dekorate/deps/jackson/core/JsonParser;
       9: pop
      10: goto          19
      13: aload_0
      14: aload_1
      15: invokevirtual #144                // Method disable:(Lio/dekorate/deps/jackson/dataformat/yaml/YAMLParser$Feature;)Lio/dekorate/deps/jackson/core/JsonParser;
      18: pop
      19: aload_0
      20: areturn

  public boolean isEnabled(io.dekorate.deps.jackson.dataformat.yaml.YAMLParser$Feature);
    Code:
       0: aload_0
       1: getfield      #54                 // Field _formatFeatures:I
       4: aload_1
       5: invokevirtual #135                // Method io/dekorate/deps/jackson/dataformat/yaml/YAMLParser$Feature.getMask:()I
       8: iand
       9: ifeq          16
      12: iconst_1
      13: goto          17
      16: iconst_0
      17: ireturn

  public io.dekorate.deps.jackson.core.JsonLocation getTokenLocation();
    Code:
       0: aload_0
       1: getfield      #150                // Field _lastEvent:Lio/dekorate/deps/snakeyaml/events/Event;
       4: ifnonnull     11
       7: getstatic     #156                // Field io/dekorate/deps/jackson/core/JsonLocation.NA:Lio/dekorate/deps/jackson/core/JsonLocation;
      10: areturn
      11: aload_0
      12: aload_0
      13: getfield      #150                // Field _lastEvent:Lio/dekorate/deps/snakeyaml/events/Event;
      16: invokevirtual #160                // Method io/dekorate/deps/snakeyaml/events/Event.getStartMark:()Lio/dekorate/deps/snakeyaml/error/Mark;
      19: invokevirtual #164                // Method _locationFor:(Lio/dekorate/deps/snakeyaml/error/Mark;)Lio/dekorate/deps/jackson/core/JsonLocation;
      22: areturn

  public io.dekorate.deps.jackson.core.JsonLocation getCurrentLocation();
    Code:
       0: aload_0
       1: getfield      #150                // Field _lastEvent:Lio/dekorate/deps/snakeyaml/events/Event;
       4: ifnonnull     11
       7: getstatic     #156                // Field io/dekorate/deps/jackson/core/JsonLocation.NA:Lio/dekorate/deps/jackson/core/JsonLocation;
      10: areturn
      11: aload_0
      12: aload_0
      13: getfield      #150                // Field _lastEvent:Lio/dekorate/deps/snakeyaml/events/Event;
      16: invokevirtual #168                // Method io/dekorate/deps/snakeyaml/events/Event.getEndMark:()Lio/dekorate/deps/snakeyaml/error/Mark;
      19: invokevirtual #164                // Method _locationFor:(Lio/dekorate/deps/snakeyaml/error/Mark;)Lio/dekorate/deps/jackson/core/JsonLocation;
      22: areturn

  protected io.dekorate.deps.jackson.core.JsonLocation _locationFor(io.dekorate.deps.snakeyaml.error.Mark);
    Code:
       0: aload_1
       1: ifnonnull     24
       4: new           #152                // class io/dekorate/deps/jackson/core/JsonLocation
       7: dup
       8: aload_0
       9: getfield      #106                // Field _ioContext:Lio/dekorate/deps/jackson/core/io/IOContext;
      12: invokevirtual #172                // Method io/dekorate/deps/jackson/core/io/IOContext.getSourceReference:()Ljava/lang/Object;
      15: ldc2_w        #173                // long -1l
      18: iconst_m1
      19: iconst_m1
      20: invokespecial #177                // Method io/dekorate/deps/jackson/core/JsonLocation."<init>":(Ljava/lang/Object;JII)V
      23: areturn
      24: new           #152                // class io/dekorate/deps/jackson/core/JsonLocation
      27: dup
      28: aload_0
      29: getfield      #106                // Field _ioContext:Lio/dekorate/deps/jackson/core/io/IOContext;
      32: invokevirtual #172                // Method io/dekorate/deps/jackson/core/io/IOContext.getSourceReference:()Ljava/lang/Object;
      35: ldc2_w        #173                // long -1l
      38: aload_1
      39: invokevirtual #182                // Method io/dekorate/deps/snakeyaml/error/Mark.getLine:()I
      42: iconst_1
      43: iadd
      44: aload_1
      45: invokevirtual #185                // Method io/dekorate/deps/snakeyaml/error/Mark.getColumn:()I
      48: iconst_1
      49: iadd
      50: invokespecial #177                // Method io/dekorate/deps/jackson/core/JsonLocation."<init>":(Ljava/lang/Object;JII)V
      53: areturn

  public io.dekorate.deps.jackson.core.JsonToken nextToken() throws java.io.IOException;
    Code:
       0: aload_0
       1: iconst_0
       2: putfield      #87                 // Field _currentIsAlias:Z
       5: aload_0
       6: aconst_null
       7: putfield      #195                // Field _binaryValue:[B
      10: aload_0
      11: getfield      #198                // Field _closed:Z
      14: ifeq          19
      17: aconst_null
      18: areturn
      19: aload_0
      20: getfield      #68                 // Field _yamlParser:Lio/dekorate/deps/snakeyaml/parser/ParserImpl;
      23: invokevirtual #202                // Method io/dekorate/deps/snakeyaml/parser/ParserImpl.getEvent:()Lio/dekorate/deps/snakeyaml/events/Event;
      26: astore_1
      27: goto          61
      30: astore_2
      31: aload_2
      32: instanceof    #204                // class io/dekorate/deps/snakeyaml/error/MarkedYAMLException
      35: ifeq          47
      38: aload_0
      39: aload_2
      40: checkcast     #204                // class io/dekorate/deps/snakeyaml/error/MarkedYAMLException
      43: invokestatic  #210                // Method io/dekorate/deps/jackson/dataformat/yaml/snakeyaml/error/MarkedYAMLException.from:(Lio/dekorate/deps/jackson/core/JsonParser;Lio/dekorate/deps/snakeyaml/error/MarkedYAMLException;)Lio/dekorate/deps/jackson/dataformat/yaml/snakeyaml/error/MarkedYAMLException;
      46: athrow
      47: new           #212                // class io/dekorate/deps/jackson/dataformat/yaml/JacksonYAMLParseException
      50: dup
      51: aload_0
      52: aload_2
      53: invokevirtual #215                // Method io/dekorate/deps/snakeyaml/error/YAMLException.getMessage:()Ljava/lang/String;
      56: aload_2
      57: invokespecial #218                // Method io/dekorate/deps/jackson/dataformat/yaml/JacksonYAMLParseException."<init>":(Lio/dekorate/deps/jackson/core/JsonParser;Ljava/lang/String;Ljava/lang/Exception;)V
      60: athrow
      61: aload_1
      62: ifnonnull     77
      65: aload_0
      66: aconst_null
      67: putfield      #92                 // Field _currentAnchor:Ljava/lang/String;
      70: aload_0
      71: aconst_null
      72: dup_x1
      73: putfield      #222                // Field _currToken:Lio/dekorate/deps/jackson/core/JsonToken;
      76: areturn
      77: aload_0
      78: aload_1
      79: putfield      #150                // Field _lastEvent:Lio/dekorate/deps/snakeyaml/events/Event;
      82: aload_0
      83: getfield      #226                // Field _parsingContext:Lio/dekorate/deps/jackson/core/json/JsonReadContext;
      86: invokevirtual #231                // Method io/dekorate/deps/jackson/core/json/JsonReadContext.inObject:()Z
      89: ifeq          251
      92: aload_0
      93: getfield      #222                // Field _currToken:Lio/dekorate/deps/jackson/core/JsonToken;
      96: getstatic     #236                // Field io/dekorate/deps/jackson/core/JsonToken.FIELD_NAME:Lio/dekorate/deps/jackson/core/JsonToken;
      99: if_acmpeq     269
     102: aload_1
     103: getstatic     #240                // Field io/dekorate/deps/snakeyaml/events/Event$ID.Scalar:Lio/dekorate/deps/snakeyaml/events/Event$ID;
     106: invokevirtual #244                // Method io/dekorate/deps/snakeyaml/events/Event.is:(Lio/dekorate/deps/snakeyaml/events/Event$ID;)Z
     109: ifne          189
     112: aload_0
     113: aconst_null
     114: putfield      #92                 // Field _currentAnchor:Ljava/lang/String;
     117: aload_1
     118: getstatic     #247                // Field io/dekorate/deps/snakeyaml/events/Event$ID.MappingEnd:Lio/dekorate/deps/snakeyaml/events/Event$ID;
     121: invokevirtual #244                // Method io/dekorate/deps/snakeyaml/events/Event.is:(Lio/dekorate/deps/snakeyaml/events/Event$ID;)Z
     124: ifeq          165
     127: aload_0
     128: getfield      #226                // Field _parsingContext:Lio/dekorate/deps/jackson/core/json/JsonReadContext;
     131: invokevirtual #231                // Method io/dekorate/deps/jackson/core/json/JsonReadContext.inObject:()Z
     134: ifne          145
     137: aload_0
     138: bipush        125
     140: bipush        93
     142: invokevirtual #251                // Method _reportMismatchedEndMarker:(IC)V
     145: aload_0
     146: aload_0
     147: getfield      #226                // Field _parsingContext:Lio/dekorate/deps/jackson/core/json/JsonReadContext;
     150: invokevirtual #255                // Method io/dekorate/deps/jackson/core/json/JsonReadContext.getParent:()Lio/dekorate/deps/jackson/core/json/JsonReadContext;
     153: putfield      #226                // Field _parsingContext:Lio/dekorate/deps/jackson/core/json/JsonReadContext;
     156: aload_0
     157: getstatic     #258                // Field io/dekorate/deps/jackson/core/JsonToken.END_OBJECT:Lio/dekorate/deps/jackson/core/JsonToken;
     160: dup_x1
     161: putfield      #222                // Field _currToken:Lio/dekorate/deps/jackson/core/JsonToken;
     164: areturn
     165: aload_0
     166: new           #260                // class java/lang/StringBuilder
     169: dup
     170: invokespecial #261                // Method java/lang/StringBuilder."<init>":()V
     173: ldc_w         #263                // String Expected a field name (Scalar value in YAML), got this instead:
     176: invokevirtual #267                // Method java/lang/StringBuilder.append:(Ljava/lang/String;)Ljava/lang/StringBuilder;
     179: aload_1
     180: invokevirtual #270                // Method java/lang/StringBuilder.append:(Ljava/lang/Object;)Ljava/lang/StringBuilder;
     183: invokevirtual #273                // Method java/lang/StringBuilder.toString:()Ljava/lang/String;
     186: invokevirtual #277                // Method _reportError:(Ljava/lang/String;)V
     189: aload_1
     190: checkcast     #279                // class io/dekorate/deps/snakeyaml/events/ScalarEvent
     193: astore_2
     194: aload_2
     195: invokevirtual #282                // Method io/dekorate/deps/snakeyaml/events/ScalarEvent.getAnchor:()Ljava/lang/String;
     198: astore_3
     199: aload_3
     200: ifnonnull     213
     203: aload_0
     204: getfield      #222                // Field _currToken:Lio/dekorate/deps/jackson/core/JsonToken;
     207: getstatic     #285                // Field io/dekorate/deps/jackson/core/JsonToken.START_OBJECT:Lio/dekorate/deps/jackson/core/JsonToken;
     210: if_acmpeq     221
     213: aload_0
     214: aload_2
     215: invokevirtual #282                // Method io/dekorate/deps/snakeyaml/events/ScalarEvent.getAnchor:()Ljava/lang/String;
     218: putfield      #92                 // Field _currentAnchor:Ljava/lang/String;
     221: aload_2
     222: invokevirtual #290                // Method io/dekorate/deps/snakeyaml/events/ScalarEvent.getValue:()Ljava/lang/String;
     225: astore        4
     227: aload_0
     228: aload         4
     230: putfield      #292                // Field _currentFieldName:Ljava/lang/String;
     233: aload_0
     234: getfield      #226                // Field _parsingContext:Lio/dekorate/deps/jackson/core/json/JsonReadContext;
     237: aload         4
     239: invokevirtual #295                // Method io/dekorate/deps/jackson/core/json/JsonReadContext.setCurrentName:(Ljava/lang/String;)V
     242: aload_0
     243: getstatic     #236                // Field io/dekorate/deps/jackson/core/JsonToken.FIELD_NAME:Lio/dekorate/deps/jackson/core/JsonToken;
     246: dup_x1
     247: putfield      #222                // Field _currToken:Lio/dekorate/deps/jackson/core/JsonToken;
     250: areturn
     251: aload_0
     252: getfield      #226                // Field _parsingContext:Lio/dekorate/deps/jackson/core/json/JsonReadContext;
     255: invokevirtual #298                // Method io/dekorate/deps/jackson/core/json/JsonReadContext.inArray:()Z
     258: ifeq          269
     261: aload_0
     262: getfield      #226                // Field _parsingContext:Lio/dekorate/deps/jackson/core/json/JsonReadContext;
     265: invokevirtual #301                // Method io/dekorate/deps/jackson/core/json/JsonReadContext.expectComma:()Z
     268: pop
     269: aload_0
     270: aconst_null
     271: putfield      #92                 // Field _currentAnchor:Ljava/lang/String;
     274: aload_1
     275: getstatic     #240                // Field io/dekorate/deps/snakeyaml/events/Event$ID.Scalar:Lio/dekorate/deps/snakeyaml/events/Event$ID;
     278: invokevirtual #244                // Method io/dekorate/deps/snakeyaml/events/Event.is:(Lio/dekorate/deps/snakeyaml/events/Event$ID;)Z
     281: ifeq          300
     284: aload_0
     285: aload_1
     286: checkcast     #279                // class io/dekorate/deps/snakeyaml/events/ScalarEvent
     289: invokevirtual #305                // Method _decodeScalar:(Lio/dekorate/deps/snakeyaml/events/ScalarEvent;)Lio/dekorate/deps/jackson/core/JsonToken;
     292: astore_2
     293: aload_0
     294: aload_2
     295: putfield      #222                // Field _currToken:Lio/dekorate/deps/jackson/core/JsonToken;
     298: aload_2
     299: areturn
     300: aload_1
     301: getstatic     #308                // Field io/dekorate/deps/snakeyaml/events/Event$ID.MappingStart:Lio/dekorate/deps/snakeyaml/events/Event$ID;
     304: invokevirtual #244                // Method io/dekorate/deps/snakeyaml/events/Event.is:(Lio/dekorate/deps/snakeyaml/events/Event$ID;)Z
     307: ifeq          356
     310: aload_1
     311: invokevirtual #160                // Method io/dekorate/deps/snakeyaml/events/Event.getStartMark:()Lio/dekorate/deps/snakeyaml/error/Mark;
     314: astore_2
     315: aload_1
     316: checkcast     #310                // class io/dekorate/deps/snakeyaml/events/MappingStartEvent
     319: astore_3
     320: aload_0
     321: aload_3
     322: invokevirtual #311                // Method io/dekorate/deps/snakeyaml/events/MappingStartEvent.getAnchor:()Ljava/lang/String;
     325: putfield      #92                 // Field _currentAnchor:Ljava/lang/String;
     328: aload_0
     329: aload_0
     330: getfield      #226                // Field _parsingContext:Lio/dekorate/deps/jackson/core/json/JsonReadContext;
     333: aload_2
     334: invokevirtual #182                // Method io/dekorate/deps/snakeyaml/error/Mark.getLine:()I
     337: aload_2
     338: invokevirtual #185                // Method io/dekorate/deps/snakeyaml/error/Mark.getColumn:()I
     341: invokevirtual #315                // Method io/dekorate/deps/jackson/core/json/JsonReadContext.createChildObjectContext:(II)Lio/dekorate/deps/jackson/core/json/JsonReadContext;
     344: putfield      #226                // Field _parsingContext:Lio/dekorate/deps/jackson/core/json/JsonReadContext;
     347: aload_0
     348: getstatic     #285                // Field io/dekorate/deps/jackson/core/JsonToken.START_OBJECT:Lio/dekorate/deps/jackson/core/JsonToken;
     351: dup_x1
     352: putfield      #222                // Field _currToken:Lio/dekorate/deps/jackson/core/JsonToken;
     355: areturn
     356: aload_1
     357: getstatic     #247                // Field io/dekorate/deps/snakeyaml/events/Event$ID.MappingEnd:Lio/dekorate/deps/snakeyaml/events/Event$ID;
     360: invokevirtual #244                // Method io/dekorate/deps/snakeyaml/events/Event.is:(Lio/dekorate/deps/snakeyaml/events/Event$ID;)Z
     363: ifeq          373
     366: aload_0
     367: ldc_w         #317                // String Not expecting END_OBJECT but a value
     370: invokevirtual #277                // Method _reportError:(Ljava/lang/String;)V
     373: aload_1
     374: getstatic     #320                // Field io/dekorate/deps/snakeyaml/events/Event$ID.SequenceStart:Lio/dekorate/deps/snakeyaml/events/Event$ID;
     377: invokevirtual #244                // Method io/dekorate/deps/snakeyaml/events/Event.is:(Lio/dekorate/deps/snakeyaml/events/Event$ID;)Z
     380: ifeq          427
     383: aload_1
     384: invokevirtual #160                // Method io/dekorate/deps/snakeyaml/events/Event.getStartMark:()Lio/dekorate/deps/snakeyaml/error/Mark;
     387: astore_2
     388: aload_0
     389: aload_1
     390: checkcast     #322                // class io/dekorate/deps/snakeyaml/events/NodeEvent
     393: invokevirtual #323                // Method io/dekorate/deps/snakeyaml/events/NodeEvent.getAnchor:()Ljava/lang/String;
     396: putfield      #92                 // Field _currentAnchor:Ljava/lang/String;
     399: aload_0
     400: aload_0
     401: getfield      #226                // Field _parsingContext:Lio/dekorate/deps/jackson/core/json/JsonReadContext;
     404: aload_2
     405: invokevirtual #182                // Method io/dekorate/deps/snakeyaml/error/Mark.getLine:()I
     408: aload_2
     409: invokevirtual #185                // Method io/dekorate/deps/snakeyaml/error/Mark.getColumn:()I
     412: invokevirtual #326                // Method io/dekorate/deps/jackson/core/json/JsonReadContext.createChildArrayContext:(II)Lio/dekorate/deps/jackson/core/json/JsonReadContext;
     415: putfield      #226                // Field _parsingContext:Lio/dekorate/deps/jackson/core/json/JsonReadContext;
     418: aload_0
     419: getstatic     #329                // Field io/dekorate/deps/jackson/core/JsonToken.START_ARRAY:Lio/dekorate/deps/jackson/core/JsonToken;
     422: dup_x1
     423: putfield      #222                // Field _currToken:Lio/dekorate/deps/jackson/core/JsonToken;
     426: areturn
     427: aload_1
     428: getstatic     #332                // Field io/dekorate/deps/snakeyaml/events/Event$ID.SequenceEnd:Lio/dekorate/deps/snakeyaml/events/Event$ID;
     431: invokevirtual #244                // Method io/dekorate/deps/snakeyaml/events/Event.is:(Lio/dekorate/deps/snakeyaml/events/Event$ID;)Z
     434: ifeq          475
     437: aload_0
     438: getfield      #226                // Field _parsingContext:Lio/dekorate/deps/jackson/core/json/JsonReadContext;
     441: invokevirtual #298                // Method io/dekorate/deps/jackson/core/json/JsonReadContext.inArray:()Z
     444: ifne          455
     447: aload_0
     448: bipush        93
     450: bipush        125
     452: invokevirtual #251                // Method _reportMismatchedEndMarker:(IC)V
     455: aload_0
     456: aload_0
     457: getfield      #226                // Field _parsingContext:Lio/dekorate/deps/jackson/core/json/JsonReadContext;
     460: invokevirtual #255                // Method io/dekorate/deps/jackson/core/json/JsonReadContext.getParent:()Lio/dekorate/deps/jackson/core/json/JsonReadContext;
     463: putfield      #226                // Field _parsingContext:Lio/dekorate/deps/jackson/core/json/JsonReadContext;
     466: aload_0
     467: getstatic     #335                // Field io/dekorate/deps/jackson/core/JsonToken.END_ARRAY:Lio/dekorate/deps/jackson/core/JsonToken;
     470: dup_x1
     471: putfield      #222                // Field _currToken:Lio/dekorate/deps/jackson/core/JsonToken;
     474: areturn
     475: aload_1
     476: getstatic     #338                // Field io/dekorate/deps/snakeyaml/events/Event$ID.DocumentEnd:Lio/dekorate/deps/snakeyaml/events/Event$ID;
     479: invokevirtual #244                // Method io/dekorate/deps/snakeyaml/events/Event.is:(Lio/dekorate/deps/snakeyaml/events/Event$ID;)Z
     482: ifeq          488
     485: goto          19
     488: aload_1
     489: getstatic     #341                // Field io/dekorate/deps/snakeyaml/events/Event$ID.DocumentStart:Lio/dekorate/deps/snakeyaml/events/Event$ID;
     492: invokevirtual #244                // Method io/dekorate/deps/snakeyaml/events/Event.is:(Lio/dekorate/deps/snakeyaml/events/Event$ID;)Z
     495: ifeq          501
     498: goto          19
     501: aload_1
     502: getstatic     #344                // Field io/dekorate/deps/snakeyaml/events/Event$ID.Alias:Lio/dekorate/deps/snakeyaml/events/Event$ID;
     505: invokevirtual #244                // Method io/dekorate/deps/snakeyaml/events/Event.is:(Lio/dekorate/deps/snakeyaml/events/Event$ID;)Z
     508: ifeq          543
     511: aload_1
     512: checkcast     #346                // class io/dekorate/deps/snakeyaml/events/AliasEvent
     515: astore_2
     516: aload_0
     517: iconst_1
     518: putfield      #87                 // Field _currentIsAlias:Z
     521: aload_0
     522: aload_2
     523: invokevirtual #347                // Method io/dekorate/deps/snakeyaml/events/AliasEvent.getAnchor:()Ljava/lang/String;
     526: putfield      #349                // Field _textValue:Ljava/lang/String;
     529: aload_0
     530: aconst_null
     531: putfield      #351                // Field _cleanedTextValue:Ljava/lang/String;
     534: aload_0
     535: getstatic     #354                // Field io/dekorate/deps/jackson/core/JsonToken.VALUE_STRING:Lio/dekorate/deps/jackson/core/JsonToken;
     538: dup_x1
     539: putfield      #222                // Field _currToken:Lio/dekorate/deps/jackson/core/JsonToken;
     542: areturn
     543: aload_1
     544: getstatic     #357                // Field io/dekorate/deps/snakeyaml/events/Event$ID.StreamEnd:Lio/dekorate/deps/snakeyaml/events/Event$ID;
     547: invokevirtual #244                // Method io/dekorate/deps/snakeyaml/events/Event.is:(Lio/dekorate/deps/snakeyaml/events/Event$ID;)Z
     550: ifeq          564
     553: aload_0
     554: invokevirtual #358                // Method close:()V
     557: aload_0
     558: aconst_null
     559: dup_x1
     560: putfield      #222                // Field _currToken:Lio/dekorate/deps/jackson/core/JsonToken;
     563: areturn
     564: aload_1
     565: getstatic     #361                // Field io/dekorate/deps/snakeyaml/events/Event$ID.StreamStart:Lio/dekorate/deps/snakeyaml/events/Event$ID;
     568: invokevirtual #244                // Method io/dekorate/deps/snakeyaml/events/Event.is:(Lio/dekorate/deps/snakeyaml/events/Event$ID;)Z
     571: ifeq          577
     574: goto          19
     577: goto          19
    Exception table:
       from    to  target type
          19    27    30   Class io/dekorate/deps/snakeyaml/error/YAMLException

  protected io.dekorate.deps.jackson.core.JsonToken _decodeScalar(io.dekorate.deps.snakeyaml.events.ScalarEvent) throws java.io.IOException;
    Code:
       0: aload_1
       1: invokevirtual #290                // Method io/dekorate/deps/snakeyaml/events/ScalarEvent.getValue:()Ljava/lang/String;
       4: astore_2
       5: aload_0
       6: aload_2
       7: putfield      #349                // Field _textValue:Ljava/lang/String;
      10: aload_0
      11: aconst_null
      12: putfield      #351                // Field _cleanedTextValue:Ljava/lang/String;
      15: aload_1
      16: invokevirtual #378                // Method io/dekorate/deps/snakeyaml/events/ScalarEvent.getTag:()Ljava/lang/String;
      19: astore_3
      20: aload_2
      21: invokevirtual #381                // Method java/lang/String.length:()I
      24: istore        4
      26: aload_3
      27: ifnull        40
      30: aload_3
      31: ldc_w         #383                // String !
      34: invokevirtual #387                // Method java/lang/String.equals:(Ljava/lang/Object;)Z
      37: ifeq          169
      40: aload_0
      41: getfield      #50                 // Field _yamlResolver:Lio/dekorate/deps/snakeyaml/resolver/Resolver;
      44: getstatic     #392                // Field io/dekorate/deps/snakeyaml/nodes/NodeId.scalar:Lio/dekorate/deps/snakeyaml/nodes/NodeId;
      47: aload_2
      48: aload_1
      49: invokevirtual #396                // Method io/dekorate/deps/snakeyaml/events/ScalarEvent.getImplicit:()Lio/dekorate/deps/snakeyaml/events/ImplicitTuple;
      52: invokevirtual #401                // Method io/dekorate/deps/snakeyaml/events/ImplicitTuple.canOmitTagInPlainScalar:()Z
      55: invokevirtual #405                // Method io/dekorate/deps/snakeyaml/resolver/Resolver.resolve:(Lio/dekorate/deps/snakeyaml/nodes/NodeId;Ljava/lang/String;Z)Lio/dekorate/deps/snakeyaml/nodes/Tag;
      58: astore        5
      60: aload         5
      62: getstatic     #411                // Field io/dekorate/deps/snakeyaml/nodes/Tag.STR:Lio/dekorate/deps/snakeyaml/nodes/Tag;
      65: if_acmpne     72
      68: getstatic     #354                // Field io/dekorate/deps/jackson/core/JsonToken.VALUE_STRING:Lio/dekorate/deps/jackson/core/JsonToken;
      71: areturn
      72: aload         5
      74: getstatic     #414                // Field io/dekorate/deps/snakeyaml/nodes/Tag.INT:Lio/dekorate/deps/snakeyaml/nodes/Tag;
      77: if_acmpne     88
      80: aload_0
      81: aload_2
      82: iload         4
      84: invokevirtual #418                // Method _decodeNumberScalar:(Ljava/lang/String;I)Lio/dekorate/deps/jackson/core/JsonToken;
      87: areturn
      88: aload         5
      90: getstatic     #421                // Field io/dekorate/deps/snakeyaml/nodes/Tag.FLOAT:Lio/dekorate/deps/snakeyaml/nodes/Tag;
      93: if_acmpne     107
      96: aload_0
      97: iconst_0
      98: putfield      #424                // Field _numTypesValid:I
     101: aload_0
     102: aload_2
     103: invokespecial #428                // Method _cleanYamlFloat:(Ljava/lang/String;)Lio/dekorate/deps/jackson/core/JsonToken;
     106: areturn
     107: aload         5
     109: getstatic     #431                // Field io/dekorate/deps/snakeyaml/nodes/Tag.BOOL:Lio/dekorate/deps/snakeyaml/nodes/Tag;
     112: if_acmpne     150
     115: aload_0
     116: aload_2
     117: iload         4
     119: invokevirtual #435                // Method _matchYAMLBoolean:(Ljava/lang/String;I)Ljava/lang/Boolean;
     122: astore        6
     124: aload         6
     126: ifnull        147
     129: aload         6
     131: invokevirtual #440                // Method java/lang/Boolean.booleanValue:()Z
     134: ifeq          143
     137: getstatic     #443                // Field io/dekorate/deps/jackson/core/JsonToken.VALUE_TRUE:Lio/dekorate/deps/jackson/core/JsonToken;
     140: goto          146
     143: getstatic     #446                // Field io/dekorate/deps/jackson/core/JsonToken.VALUE_FALSE:Lio/dekorate/deps/jackson/core/JsonToken;
     146: areturn
     147: goto          166
     150: aload         5
     152: getstatic     #449                // Field io/dekorate/deps/snakeyaml/nodes/Tag.NULL:Lio/dekorate/deps/snakeyaml/nodes/Tag;
     155: if_acmpne     162
     158: getstatic     #452                // Field io/dekorate/deps/jackson/core/JsonToken.VALUE_NULL:Lio/dekorate/deps/jackson/core/JsonToken;
     161: areturn
     162: getstatic     #354                // Field io/dekorate/deps/jackson/core/JsonToken.VALUE_STRING:Lio/dekorate/deps/jackson/core/JsonToken;
     165: areturn
     166: goto          352
     169: aload_3
     170: ldc_w         #454                // String tag:yaml.org,2002:
     173: invokevirtual #458                // Method java/lang/String.startsWith:(Ljava/lang/String;)Z
     176: ifeq          210
     179: aload_3
     180: ldc_w         #454                // String tag:yaml.org,2002:
     183: invokevirtual #381                // Method java/lang/String.length:()I
     186: invokevirtual #462                // Method java/lang/String.substring:(I)Ljava/lang/String;
     189: astore_3
     190: aload_3
     191: ldc_w         #464                // String ,
     194: invokevirtual #468                // Method java/lang/String.contains:(Ljava/lang/CharSequence;)Z
     197: ifeq          210
     200: aload_3
     201: ldc_w         #464                // String ,
     204: invokevirtual #472                // Method java/lang/String.split:(Ljava/lang/String;)[Ljava/lang/String;
     207: iconst_0
     208: aaload
     209: astore_3
     210: ldc_w         #474                // String binary
     213: aload_3
     214: invokevirtual #387                // Method java/lang/String.equals:(Ljava/lang/Object;)Z
     217: ifeq          254
     220: aload_2
     221: invokevirtual #477                // Method java/lang/String.trim:()Ljava/lang/String;
     224: astore_2
     225: aload_0
     226: getstatic     #483                // Field io/dekorate/deps/jackson/core/Base64Variants.MIME:Lio/dekorate/deps/jackson/core/Base64Variant;
     229: aload_2
     230: invokevirtual #489                // Method io/dekorate/deps/jackson/core/Base64Variant.decode:(Ljava/lang/String;)[B
     233: putfield      #195                // Field _binaryValue:[B
     236: goto          250
     239: astore        5
     241: aload_0
     242: aload         5
     244: invokevirtual #490                // Method java/lang/IllegalArgumentException.getMessage:()Ljava/lang/String;
     247: invokevirtual #277                // Method _reportError:(Ljava/lang/String;)V
     250: getstatic     #493                // Field io/dekorate/deps/jackson/core/JsonToken.VALUE_EMBEDDED_OBJECT:Lio/dekorate/deps/jackson/core/JsonToken;
     253: areturn
     254: ldc_w         #495                // String bool
     257: aload_3
     258: invokevirtual #387                // Method java/lang/String.equals:(Ljava/lang/Object;)Z
     261: ifeq          299
     264: aload_0
     265: aload_2
     266: iload         4
     268: invokevirtual #435                // Method _matchYAMLBoolean:(Ljava/lang/String;I)Ljava/lang/Boolean;
     271: astore        5
     273: aload         5
     275: ifnull        296
     278: aload         5
     280: invokevirtual #440                // Method java/lang/Boolean.booleanValue:()Z
     283: ifeq          292
     286: getstatic     #443                // Field io/dekorate/deps/jackson/core/JsonToken.VALUE_TRUE:Lio/dekorate/deps/jackson/core/JsonToken;
     289: goto          295
     292: getstatic     #446                // Field io/dekorate/deps/jackson/core/JsonToken.VALUE_FALSE:Lio/dekorate/deps/jackson/core/JsonToken;
     295: areturn
     296: goto          352
     299: ldc_w         #497                // String int
     302: aload_3
     303: invokevirtual #387                // Method java/lang/String.equals:(Ljava/lang/Object;)Z
     306: ifeq          317
     309: aload_0
     310: aload_2
     311: iload         4
     313: invokevirtual #418                // Method _decodeNumberScalar:(Ljava/lang/String;I)Lio/dekorate/deps/jackson/core/JsonToken;
     316: areturn
     317: ldc_w         #499                // String float
     320: aload_3
     321: invokevirtual #387                // Method java/lang/String.equals:(Ljava/lang/Object;)Z
     324: ifeq          338
     327: aload_0
     328: iconst_0
     329: putfield      #424                // Field _numTypesValid:I
     332: aload_0
     333: aload_2
     334: invokespecial #428                // Method _cleanYamlFloat:(Ljava/lang/String;)Lio/dekorate/deps/jackson/core/JsonToken;
     337: areturn
     338: ldc_w         #501                // String null
     341: aload_3
     342: invokevirtual #387                // Method java/lang/String.equals:(Ljava/lang/Object;)Z
     345: ifeq          352
     348: getstatic     #452                // Field io/dekorate/deps/jackson/core/JsonToken.VALUE_NULL:Lio/dekorate/deps/jackson/core/JsonToken;
     351: areturn
     352: getstatic     #354                // Field io/dekorate/deps/jackson/core/JsonToken.VALUE_STRING:Lio/dekorate/deps/jackson/core/JsonToken;
     355: areturn
    Exception table:
       from    to  target type
         225   236   239   Class java/lang/IllegalArgumentException

  protected java.lang.Boolean _matchYAMLBoolean(java.lang.String, int);
    Code:
       0: iload_2
       1: tableswitch   { // 1 to 5
                     1: 36
                     2: 95
                     3: 123
                     4: 151
                     5: 165
               default: 179
          }
      36: aload_1
      37: iconst_0
      38: invokevirtual #512                // Method java/lang/String.charAt:(I)C
      41: lookupswitch  { // 4
                    78: 88
                    89: 84
                   110: 88
                   121: 84
               default: 92
          }
      84: getstatic     #515                // Field java/lang/Boolean.TRUE:Ljava/lang/Boolean;
      87: areturn
      88: getstatic     #518                // Field java/lang/Boolean.FALSE:Ljava/lang/Boolean;
      91: areturn
      92: goto          179
      95: ldc_w         #520                // String no
      98: aload_1
      99: invokevirtual #523                // Method java/lang/String.equalsIgnoreCase:(Ljava/lang/String;)Z
     102: ifeq          109
     105: getstatic     #518                // Field java/lang/Boolean.FALSE:Ljava/lang/Boolean;
     108: areturn
     109: ldc_w         #525                // String on
     112: aload_1
     113: invokevirtual #523                // Method java/lang/String.equalsIgnoreCase:(Ljava/lang/String;)Z
     116: ifeq          179
     119: getstatic     #515                // Field java/lang/Boolean.TRUE:Ljava/lang/Boolean;
     122: areturn
     123: ldc_w         #527                // String yes
     126: aload_1
     127: invokevirtual #523                // Method java/lang/String.equalsIgnoreCase:(Ljava/lang/String;)Z
     130: ifeq          137
     133: getstatic     #515                // Field java/lang/Boolean.TRUE:Ljava/lang/Boolean;
     136: areturn
     137: ldc_w         #529                // String off
     140: aload_1
     141: invokevirtual #523                // Method java/lang/String.equalsIgnoreCase:(Ljava/lang/String;)Z
     144: ifeq          179
     147: getstatic     #518                // Field java/lang/Boolean.FALSE:Ljava/lang/Boolean;
     150: areturn
     151: ldc_w         #531                // String true
     154: aload_1
     155: invokevirtual #523                // Method java/lang/String.equalsIgnoreCase:(Ljava/lang/String;)Z
     158: ifeq          179
     161: getstatic     #515                // Field java/lang/Boolean.TRUE:Ljava/lang/Boolean;
     164: areturn
     165: ldc_w         #533                // String false
     168: aload_1
     169: invokevirtual #523                // Method java/lang/String.equalsIgnoreCase:(Ljava/lang/String;)Z
     172: ifeq          179
     175: getstatic     #518                // Field java/lang/Boolean.FALSE:Ljava/lang/Boolean;
     178: areturn
     179: aconst_null
     180: areturn

  protected io.dekorate.deps.jackson.core.JsonToken _decodeNumberScalar(java.lang.String, int);
    Code:
       0: ldc_w         #535                // String 0
       3: aload_1
       4: invokevirtual #387                // Method java/lang/String.equals:(Ljava/lang/Object;)Z
       7: ifeq          29
      10: aload_0
      11: iconst_0
      12: putfield      #538                // Field _numberNegative:Z
      15: aload_0
      16: iconst_0
      17: putfield      #541                // Field _numberInt:I
      20: aload_0
      21: iconst_1
      22: putfield      #424                // Field _numTypesValid:I
      25: getstatic     #544                // Field io/dekorate/deps/jackson/core/JsonToken.VALUE_NUMBER_INT:Lio/dekorate/deps/jackson/core/JsonToken;
      28: areturn
      29: aload_1
      30: iconst_0
      31: invokevirtual #512                // Method java/lang/String.charAt:(I)C
      34: istore        4
      36: iload         4
      38: bipush        45
      40: if_icmpne     60
      43: aload_0
      44: iconst_1
      45: putfield      #538                // Field _numberNegative:Z
      48: iload_2
      49: iconst_1
      50: if_icmpne     55
      53: aconst_null
      54: areturn
      55: iconst_1
      56: istore_3
      57: goto          91
      60: iload         4
      62: bipush        43
      64: if_icmpne     84
      67: aload_0
      68: iconst_0
      69: putfield      #538                // Field _numberNegative:Z
      72: iload_2
      73: iconst_1
      74: if_icmpne     79
      77: aconst_null
      78: areturn
      79: iconst_1
      80: istore_3
      81: goto          91
      84: aload_0
      85: iconst_0
      86: putfield      #538                // Field _numberNegative:Z
      89: iconst_0
      90: istore_3
      91: iconst_0
      92: istore        5
      94: aload_1
      95: iload_3
      96: invokevirtual #512                // Method java/lang/String.charAt:(I)C
      99: istore        6
     101: iload         6
     103: bipush        57
     105: if_icmpgt     115
     108: iload         6
     110: bipush        48
     112: if_icmpge     128
     115: iload         6
     117: bipush        95
     119: if_icmpeq     125
     122: goto          170
     125: iinc          5, 1
     128: iinc          3, 1
     131: iload_3
     132: iload_2
     133: if_icmpne     167
     136: aload_0
     137: iconst_0
     138: putfield      #424                // Field _numTypesValid:I
     141: iload         5
     143: ifle          155
     146: aload_0
     147: aload_0
     148: getfield      #349                // Field _textValue:Ljava/lang/String;
     151: invokespecial #547                // Method _cleanYamlInt:(Ljava/lang/String;)Lio/dekorate/deps/jackson/core/JsonToken;
     154: areturn
     155: aload_0
     156: aload_0
     157: getfield      #349                // Field _textValue:Ljava/lang/String;
     160: putfield      #351                // Field _cleanedTextValue:Ljava/lang/String;
     163: getstatic     #544                // Field io/dekorate/deps/jackson/core/JsonToken.VALUE_NUMBER_INT:Lio/dekorate/deps/jackson/core/JsonToken;
     166: areturn
     167: goto          94
     170: getstatic     #549                // Field PATTERN_FLOAT:Ljava/util/regex/Pattern;
     173: aload_1
     174: invokevirtual #555                // Method java/util/regex/Pattern.matcher:(Ljava/lang/CharSequence;)Ljava/util/regex/Matcher;
     177: invokevirtual #560                // Method java/util/regex/Matcher.matches:()Z
     180: ifeq          197
     183: aload_0
     184: iconst_0
     185: putfield      #424                // Field _numTypesValid:I
     188: aload_0
     189: aload_0
     190: getfield      #349                // Field _textValue:Ljava/lang/String;
     193: invokespecial #428                // Method _cleanYamlFloat:(Ljava/lang/String;)Lio/dekorate/deps/jackson/core/JsonToken;
     196: areturn
     197: getstatic     #354                // Field io/dekorate/deps/jackson/core/JsonToken.VALUE_STRING:Lio/dekorate/deps/jackson/core/JsonToken;
     200: areturn

  protected io.dekorate.deps.jackson.core.JsonToken _decodeIntWithUnderscores(java.lang.String, int);
    Code:
       0: getstatic     #544                // Field io/dekorate/deps/jackson/core/JsonToken.VALUE_NUMBER_INT:Lio/dekorate/deps/jackson/core/JsonToken;
       3: areturn

  public boolean hasTextCharacters();
    Code:
       0: iconst_0
       1: ireturn

  public java.lang.String getText() throws java.io.IOException;
    Code:
       0: aload_0
       1: getfield      #222                // Field _currToken:Lio/dekorate/deps/jackson/core/JsonToken;
       4: getstatic     #354                // Field io/dekorate/deps/jackson/core/JsonToken.VALUE_STRING:Lio/dekorate/deps/jackson/core/JsonToken;
       7: if_acmpne     15
      10: aload_0
      11: getfield      #349                // Field _textValue:Ljava/lang/String;
      14: areturn
      15: aload_0
      16: getfield      #222                // Field _currToken:Lio/dekorate/deps/jackson/core/JsonToken;
      19: getstatic     #236                // Field io/dekorate/deps/jackson/core/JsonToken.FIELD_NAME:Lio/dekorate/deps/jackson/core/JsonToken;
      22: if_acmpne     30
      25: aload_0
      26: getfield      #292                // Field _currentFieldName:Ljava/lang/String;
      29: areturn
      30: aload_0
      31: getfield      #222                // Field _currToken:Lio/dekorate/deps/jackson/core/JsonToken;
      34: ifnull        60
      37: aload_0
      38: getfield      #222                // Field _currToken:Lio/dekorate/deps/jackson/core/JsonToken;
      41: invokevirtual #570                // Method io/dekorate/deps/jackson/core/JsonToken.isScalarValue:()Z
      44: ifeq          52
      47: aload_0
      48: getfield      #349                // Field _textValue:Ljava/lang/String;
      51: areturn
      52: aload_0
      53: getfield      #222                // Field _currToken:Lio/dekorate/deps/jackson/core/JsonToken;
      56: invokevirtual #573                // Method io/dekorate/deps/jackson/core/JsonToken.asString:()Ljava/lang/String;
      59: areturn
      60: aconst_null
      61: areturn

  public java.lang.String getCurrentName() throws java.io.IOException;
    Code:
       0: aload_0
       1: getfield      #222                // Field _currToken:Lio/dekorate/deps/jackson/core/JsonToken;
       4: getstatic     #236                // Field io/dekorate/deps/jackson/core/JsonToken.FIELD_NAME:Lio/dekorate/deps/jackson/core/JsonToken;
       7: if_acmpne     15
      10: aload_0
      11: getfield      #292                // Field _currentFieldName:Ljava/lang/String;
      14: areturn
      15: aload_0
      16: invokespecial #576                // Method io/dekorate/deps/jackson/core/base/ParserBase.getCurrentName:()Ljava/lang/String;
      19: areturn

  public char[] getTextCharacters() throws java.io.IOException;
    Code:
       0: aload_0
       1: invokevirtual #580                // Method getText:()Ljava/lang/String;
       4: astore_1
       5: aload_1
       6: ifnonnull     13
       9: aconst_null
      10: goto          17
      13: aload_1
      14: invokevirtual #583                // Method java/lang/String.toCharArray:()[C
      17: areturn

  public int getTextLength() throws java.io.IOException;
    Code:
       0: aload_0
       1: invokevirtual #580                // Method getText:()Ljava/lang/String;
       4: astore_1
       5: aload_1
       6: ifnonnull     13
       9: iconst_0
      10: goto          17
      13: aload_1
      14: invokevirtual #381                // Method java/lang/String.length:()I
      17: ireturn

  public int getTextOffset() throws java.io.IOException;
    Code:
       0: iconst_0
       1: ireturn

  public int getText(java.io.Writer) throws java.io.IOException;
    Code:
       0: aload_0
       1: invokevirtual #580                // Method getText:()Ljava/lang/String;
       4: astore_2
       5: aload_2
       6: ifnonnull     11
       9: iconst_0
      10: ireturn
      11: aload_1
      12: aload_2
      13: invokevirtual #594                // Method java/io/Writer.write:(Ljava/lang/String;)V
      16: aload_2
      17: invokevirtual #381                // Method java/lang/String.length:()I
      20: ireturn

  public java.lang.Object getEmbeddedObject() throws java.io.IOException;
    Code:
       0: aload_0
       1: getfield      #222                // Field _currToken:Lio/dekorate/deps/jackson/core/JsonToken;
       4: getstatic     #493                // Field io/dekorate/deps/jackson/core/JsonToken.VALUE_EMBEDDED_OBJECT:Lio/dekorate/deps/jackson/core/JsonToken;
       7: if_acmpne     15
      10: aload_0
      11: getfield      #195                // Field _binaryValue:[B
      14: areturn
      15: aconst_null
      16: areturn

  public int readBinaryValue(io.dekorate.deps.jackson.core.Base64Variant, java.io.OutputStream) throws java.io.IOException;
    Code:
       0: aload_0
       1: aload_1
       2: invokevirtual #604                // Method getBinaryValue:(Lio/dekorate/deps/jackson/core/Base64Variant;)[B
       5: astore_3
       6: aload_2
       7: aload_3
       8: invokevirtual #609                // Method java/io/OutputStream.write:([B)V
      11: aload_3
      12: arraylength
      13: ireturn

  protected void _parseNumericValue(int) throws java.io.IOException;
    Code:
       0: aload_0
       1: getfield      #222                // Field _currToken:Lio/dekorate/deps/jackson/core/JsonToken;
       4: getstatic     #544                // Field io/dekorate/deps/jackson/core/JsonToken.VALUE_NUMBER_INT:Lio/dekorate/deps/jackson/core/JsonToken;
       7: if_acmpne     216
      10: aload_0
      11: getfield      #349                // Field _textValue:Ljava/lang/String;
      14: invokevirtual #381                // Method java/lang/String.length:()I
      17: istore_2
      18: aload_0
      19: getfield      #538                // Field _numberNegative:Z
      22: ifeq          28
      25: iinc          2, -1
      28: iload_2
      29: bipush        9
      31: if_icmpgt     51
      34: aload_0
      35: aload_0
      36: getfield      #349                // Field _textValue:Ljava/lang/String;
      39: invokestatic  #623                // Method java/lang/Integer.parseInt:(Ljava/lang/String;)I
      42: putfield      #541                // Field _numberInt:I
      45: aload_0
      46: iconst_1
      47: putfield      #424                // Field _numTypesValid:I
      50: return
      51: iload_2
      52: bipush        18
      54: if_icmpgt     129
      57: aload_0
      58: getfield      #351                // Field _cleanedTextValue:Ljava/lang/String;
      61: invokestatic  #629                // Method java/lang/Long.parseLong:(Ljava/lang/String;)J
      64: lstore_3
      65: iload_2
      66: bipush        10
      68: if_icmpne     118
      71: aload_0
      72: getfield      #538                // Field _numberNegative:Z
      75: ifeq          98
      78: lload_3
      79: ldc2_w        #630                // long -2147483648l
      82: lcmp
      83: iflt          118
      86: aload_0
      87: lload_3
      88: l2i
      89: putfield      #541                // Field _numberInt:I
      92: aload_0
      93: iconst_1
      94: putfield      #424                // Field _numTypesValid:I
      97: return
      98: lload_3
      99: ldc2_w        #632                // long 2147483647l
     102: lcmp
     103: ifgt          118
     106: aload_0
     107: lload_3
     108: l2i
     109: putfield      #541                // Field _numberInt:I
     112: aload_0
     113: iconst_1
     114: putfield      #424                // Field _numTypesValid:I
     117: return
     118: aload_0
     119: lload_3
     120: putfield      #637                // Field _numberLong:J
     123: aload_0
     124: iconst_2
     125: putfield      #424                // Field _numTypesValid:I
     128: return
     129: new           #639                // class java/math/BigInteger
     132: dup
     133: aload_0
     134: getfield      #351                // Field _cleanedTextValue:Ljava/lang/String;
     137: invokespecial #641                // Method java/math/BigInteger."<init>":(Ljava/lang/String;)V
     140: astore_3
     141: iload_2
     142: bipush        19
     144: if_icmpne     170
     147: aload_3
     148: invokevirtual #644                // Method java/math/BigInteger.bitLength:()I
     151: bipush        63
     153: if_icmpgt     170
     156: aload_0
     157: aload_3
     158: invokevirtual #648                // Method java/math/BigInteger.longValue:()J
     161: putfield      #637                // Field _numberLong:J
     164: aload_0
     165: iconst_2
     166: putfield      #424                // Field _numTypesValid:I
     169: return
     170: aload_0
     171: aload_3
     172: putfield      #652                // Field _numberBigInt:Ljava/math/BigInteger;
     175: aload_0
     176: iconst_4
     177: putfield      #424                // Field _numTypesValid:I
     180: return
     181: astore_3
     182: aload_0
     183: new           #260                // class java/lang/StringBuilder
     186: dup
     187: invokespecial #261                // Method java/lang/StringBuilder."<init>":()V
     190: ldc_w         #654                // String Malformed numeric value \'
     193: invokevirtual #267                // Method java/lang/StringBuilder.append:(Ljava/lang/String;)Ljava/lang/StringBuilder;
     196: aload_0
     197: getfield      #349                // Field _textValue:Ljava/lang/String;
     200: invokevirtual #267                // Method java/lang/StringBuilder.append:(Ljava/lang/String;)Ljava/lang/StringBuilder;
     203: ldc_w         #656                // String \'
     206: invokevirtual #267                // Method java/lang/StringBuilder.append:(Ljava/lang/String;)Ljava/lang/StringBuilder;
     209: invokevirtual #273                // Method java/lang/StringBuilder.toString:()Ljava/lang/String;
     212: aload_3
     213: invokevirtual #660                // Method _wrapError:(Ljava/lang/String;Ljava/lang/Throwable;)V
     216: aload_0
     217: getfield      #222                // Field _currToken:Lio/dekorate/deps/jackson/core/JsonToken;
     220: getstatic     #663                // Field io/dekorate/deps/jackson/core/JsonToken.VALUE_NUMBER_FLOAT:Lio/dekorate/deps/jackson/core/JsonToken;
     223: if_acmpne     311
     226: aload_0
     227: getfield      #351                // Field _cleanedTextValue:Ljava/lang/String;
     230: astore_2
     231: iload_1
     232: bipush        16
     234: if_icmpne     258
     237: aload_0
     238: new           #665                // class java/math/BigDecimal
     241: dup
     242: aload_2
     243: invokespecial #666                // Method java/math/BigDecimal."<init>":(Ljava/lang/String;)V
     246: putfield      #670                // Field _numberBigDecimal:Ljava/math/BigDecimal;
     249: aload_0
     250: bipush        16
     252: putfield      #424                // Field _numTypesValid:I
     255: goto          272
     258: aload_0
     259: aload_2
     260: invokestatic  #676                // Method java/lang/Double.parseDouble:(Ljava/lang/String;)D
     263: putfield      #680                // Field _numberDouble:D
     266: aload_0
     267: bipush        8
     269: putfield      #424                // Field _numTypesValid:I
     272: goto          310
     275: astore_3
     276: aload_0
     277: new           #260                // class java/lang/StringBuilder
     280: dup
     281: invokespecial #261                // Method java/lang/StringBuilder."<init>":()V
     284: ldc_w         #654                // String Malformed numeric value \'
     287: invokevirtual #267                // Method java/lang/StringBuilder.append:(Ljava/lang/String;)Ljava/lang/StringBuilder;
     290: aload_0
     291: getfield      #349                // Field _textValue:Ljava/lang/String;
     294: invokevirtual #267                // Method java/lang/StringBuilder.append:(Ljava/lang/String;)Ljava/lang/StringBuilder;
     297: ldc_w         #656                // String \'
     300: invokevirtual #267                // Method java/lang/StringBuilder.append:(Ljava/lang/String;)Ljava/lang/StringBuilder;
     303: invokevirtual #273                // Method java/lang/StringBuilder.toString:()Ljava/lang/String;
     306: aload_3
     307: invokevirtual #660                // Method _wrapError:(Ljava/lang/String;Ljava/lang/Throwable;)V
     310: return
     311: aload_0
     312: new           #260                // class java/lang/StringBuilder
     315: dup
     316: invokespecial #261                // Method java/lang/StringBuilder."<init>":()V
     319: ldc_w         #682                // String Current token (
     322: invokevirtual #267                // Method java/lang/StringBuilder.append:(Ljava/lang/String;)Ljava/lang/StringBuilder;
     325: aload_0
     326: getfield      #222                // Field _currToken:Lio/dekorate/deps/jackson/core/JsonToken;
     329: invokevirtual #270                // Method java/lang/StringBuilder.append:(Ljava/lang/Object;)Ljava/lang/StringBuilder;
     332: ldc_w         #684                // String ) not numeric, can not use numeric value accessors
     335: invokevirtual #267                // Method java/lang/StringBuilder.append:(Ljava/lang/String;)Ljava/lang/StringBuilder;
     338: invokevirtual #273                // Method java/lang/StringBuilder.toString:()Ljava/lang/String;
     341: invokevirtual #277                // Method _reportError:(Ljava/lang/String;)V
     344: return
    Exception table:
       from    to  target type
         129   169   181   Class java/lang/NumberFormatException
         170   180   181   Class java/lang/NumberFormatException
         231   272   275   Class java/lang/NumberFormatException

  protected int _parseIntValue() throws java.io.IOException;
    Code:
       0: aload_0
       1: getfield      #222                // Field _currToken:Lio/dekorate/deps/jackson/core/JsonToken;
       4: getstatic     #544                // Field io/dekorate/deps/jackson/core/JsonToken.VALUE_NUMBER_INT:Lio/dekorate/deps/jackson/core/JsonToken;
       7: if_acmpne     52
      10: aload_0
      11: getfield      #351                // Field _cleanedTextValue:Ljava/lang/String;
      14: invokevirtual #381                // Method java/lang/String.length:()I
      17: istore_1
      18: aload_0
      19: getfield      #538                // Field _numberNegative:Z
      22: ifeq          28
      25: iinc          1, -1
      28: iload_1
      29: bipush        9
      31: if_icmpgt     52
      34: aload_0
      35: iconst_1
      36: putfield      #424                // Field _numTypesValid:I
      39: aload_0
      40: aload_0
      41: getfield      #351                // Field _cleanedTextValue:Ljava/lang/String;
      44: invokestatic  #623                // Method java/lang/Integer.parseInt:(Ljava/lang/String;)I
      47: dup_x1
      48: putfield      #541                // Field _numberInt:I
      51: ireturn
      52: aload_0
      53: iconst_1
      54: invokevirtual #692                // Method _parseNumericValue:(I)V
      57: aload_0
      58: getfield      #424                // Field _numTypesValid:I
      61: iconst_1
      62: iand
      63: ifne          70
      66: aload_0
      67: invokevirtual #695                // Method convertNumberToInt:()V
      70: aload_0
      71: getfield      #541                // Field _numberInt:I
      74: ireturn

  public boolean canReadObjectId();
    Code:
       0: iconst_1
       1: ireturn

  public boolean canReadTypeId();
    Code:
       0: iconst_1
       1: ireturn

  public java.lang.String getObjectId() throws java.io.IOException;
    Code:
       0: aload_0
       1: getfield      #92                 // Field _currentAnchor:Ljava/lang/String;
       4: areturn

  public java.lang.String getTypeId() throws java.io.IOException;
    Code:
       0: aload_0
       1: getfield      #150                // Field _lastEvent:Lio/dekorate/deps/snakeyaml/events/Event;
       4: instanceof    #701                // class io/dekorate/deps/snakeyaml/events/CollectionStartEvent
       7: ifeq          24
      10: aload_0
      11: getfield      #150                // Field _lastEvent:Lio/dekorate/deps/snakeyaml/events/Event;
      14: checkcast     #701                // class io/dekorate/deps/snakeyaml/events/CollectionStartEvent
      17: invokevirtual #702                // Method io/dekorate/deps/snakeyaml/events/CollectionStartEvent.getTag:()Ljava/lang/String;
      20: astore_1
      21: goto          50
      24: aload_0
      25: getfield      #150                // Field _lastEvent:Lio/dekorate/deps/snakeyaml/events/Event;
      28: instanceof    #279                // class io/dekorate/deps/snakeyaml/events/ScalarEvent
      31: ifeq          48
      34: aload_0
      35: getfield      #150                // Field _lastEvent:Lio/dekorate/deps/snakeyaml/events/Event;
      38: checkcast     #279                // class io/dekorate/deps/snakeyaml/events/ScalarEvent
      41: invokevirtual #378                // Method io/dekorate/deps/snakeyaml/events/ScalarEvent.getTag:()Ljava/lang/String;
      44: astore_1
      45: goto          50
      48: aconst_null
      49: areturn
      50: aload_1
      51: ifnull        75
      54: aload_1
      55: ldc_w         #383                // String !
      58: invokevirtual #458                // Method java/lang/String.startsWith:(Ljava/lang/String;)Z
      61: ifeq          73
      64: aload_1
      65: iconst_1
      66: invokevirtual #462                // Method java/lang/String.substring:(I)Ljava/lang/String;
      69: astore_1
      70: goto          54
      73: aload_1
      74: areturn
      75: aconst_null
      76: areturn

  private io.dekorate.deps.jackson.core.JsonToken _cleanYamlInt(java.lang.String);
    Code:
       0: aload_1
       1: invokevirtual #381                // Method java/lang/String.length:()I
       4: istore_2
       5: new           #260                // class java/lang/StringBuilder
       8: dup
       9: iload_2
      10: invokespecial #705                // Method java/lang/StringBuilder."<init>":(I)V
      13: astore_3
      14: aload_1
      15: iconst_0
      16: invokevirtual #512                // Method java/lang/String.charAt:(I)C
      19: bipush        43
      21: if_icmpne     28
      24: iconst_1
      25: goto          29
      28: iconst_0
      29: istore        4
      31: iload         4
      33: iload_2
      34: if_icmpge     65
      37: aload_1
      38: iload         4
      40: invokevirtual #512                // Method java/lang/String.charAt:(I)C
      43: istore        5
      45: iload         5
      47: bipush        95
      49: if_icmpeq     59
      52: aload_3
      53: iload         5
      55: invokevirtual #708                // Method java/lang/StringBuilder.append:(C)Ljava/lang/StringBuilder;
      58: pop
      59: iinc          4, 1
      62: goto          31
      65: aload_0
      66: aload_3
      67: invokevirtual #273                // Method java/lang/StringBuilder.toString:()Ljava/lang/String;
      70: putfield      #351                // Field _cleanedTextValue:Ljava/lang/String;
      73: getstatic     #544                // Field io/dekorate/deps/jackson/core/JsonToken.VALUE_NUMBER_INT:Lio/dekorate/deps/jackson/core/JsonToken;
      76: areturn

  private io.dekorate.deps.jackson.core.JsonToken _cleanYamlFloat(java.lang.String);
    Code:
       0: aload_1
       1: invokevirtual #381                // Method java/lang/String.length:()I
       4: istore_2
       5: aload_1
       6: bipush        95
       8: invokevirtual #714                // Method java/lang/String.indexOf:(I)I
      11: istore_3
      12: iload_3
      13: iflt          20
      16: iload_2
      17: ifne          29
      20: aload_0
      21: aload_1
      22: putfield      #351                // Field _cleanedTextValue:Ljava/lang/String;
      25: getstatic     #663                // Field io/dekorate/deps/jackson/core/JsonToken.VALUE_NUMBER_FLOAT:Lio/dekorate/deps/jackson/core/JsonToken;
      28: areturn
      29: new           #260                // class java/lang/StringBuilder
      32: dup
      33: iload_2
      34: invokespecial #705                // Method java/lang/StringBuilder."<init>":(I)V
      37: astore        4
      39: aload_1
      40: iconst_0
      41: invokevirtual #512                // Method java/lang/String.charAt:(I)C
      44: bipush        43
      46: if_icmpne     53
      49: iconst_1
      50: goto          54
      53: iconst_0
      54: istore        5
      56: iload         5
      58: iload_2
      59: if_icmpge     91
      62: aload_1
      63: iload         5
      65: invokevirtual #512                // Method java/lang/String.charAt:(I)C
      68: istore        6
      70: iload         6
      72: bipush        95
      74: if_icmpeq     85
      77: aload         4
      79: iload         6
      81: invokevirtual #708                // Method java/lang/StringBuilder.append:(C)Ljava/lang/StringBuilder;
      84: pop
      85: iinc          5, 1
      88: goto          56
      91: aload_0
      92: aload         4
      94: invokevirtual #273                // Method java/lang/StringBuilder.toString:()Ljava/lang/String;
      97: putfield      #351                // Field _cleanedTextValue:Ljava/lang/String;
     100: getstatic     #663                // Field io/dekorate/deps/jackson/core/JsonToken.VALUE_NUMBER_FLOAT:Lio/dekorate/deps/jackson/core/JsonToken;
     103: areturn

  public java.lang.Object getTypeId() throws java.io.IOException;
    Code:
       0: aload_0
       1: invokevirtual #717                // Method getTypeId:()Ljava/lang/String;
       4: areturn

  public java.lang.Object getObjectId() throws java.io.IOException;
    Code:
       0: aload_0
       1: invokevirtual #719                // Method getObjectId:()Ljava/lang/String;
       4: areturn

  static {};
    Code:
       0: ldc_w         #722                // String [-+]?([0-9][0-9_]*)?\\.[0-9]*([eE][-+][0-9]+)?
       3: invokestatic  #726                // Method java/util/regex/Pattern.compile:(Ljava/lang/String;)Ljava/util/regex/Pattern;
       6: putstatic     #549                // Field PATTERN_FLOAT:Ljava/util/regex/Pattern;
       9: return
}
