Compiled from "SleeTransactionSynchronization.java"
public class org.mobicents.slee.runtime.transaction.SleeTransactionSynchronization implements javax.transaction.Synchronization {
  private static final org.apache.log4j.Logger logger;

  private final javax.transaction.Transaction tx;

  private final org.mobicents.slee.runtime.transaction.TransactionContextImpl txContext;

  public org.mobicents.slee.runtime.transaction.SleeTransactionSynchronization(javax.transaction.Transaction, org.mobicents.slee.runtime.transaction.TransactionContextImpl);
    Code:
       0: aload_0
       1: invokespecial #1                  // Method java/lang/Object."<init>":()V
       4: aload_0
       5: aload_1
       6: putfield      #2                  // Field tx:Ljavax/transaction/Transaction;
       9: aload_0
      10: aload_2
      11: putfield      #3                  // Field txContext:Lorg/mobicents/slee/runtime/transaction/TransactionContextImpl;
      14: return

  public void afterCompletion(int);
    Code:
       0: aconst_null
       1: invokestatic  #4                  // Method org/mobicents/slee/runtime/transaction/TransactionContextThreadLocal.setTransactionContext:(Lorg/mobicents/slee/container/transaction/TransactionContext;)V
       4: iload_1
       5: lookupswitch  { // 2
                     3: 32
                     4: 86
               default: 133
          }
      32: getstatic     #5                  // Field logger:Lorg/apache/log4j/Logger;
      35: invokevirtual #6                  // Method org/apache/log4j/Logger.isDebugEnabled:()Z
      38: ifeq          69
      41: getstatic     #5                  // Field logger:Lorg/apache/log4j/Logger;
      44: new           #7                  // class java/lang/StringBuilder
      47: dup
      48: invokespecial #8                  // Method java/lang/StringBuilder."<init>":()V
      51: ldc           #9                  // String Completed commit of tx
      53: invokevirtual #10                 // Method java/lang/StringBuilder.append:(Ljava/lang/String;)Ljava/lang/StringBuilder;
      56: aload_0
      57: getfield      #2                  // Field tx:Ljavax/transaction/Transaction;
      60: invokevirtual #11                 // Method java/lang/StringBuilder.append:(Ljava/lang/Object;)Ljava/lang/StringBuilder;
      63: invokevirtual #12                 // Method java/lang/StringBuilder.toString:()Ljava/lang/String;
      66: invokevirtual #13                 // Method org/apache/log4j/Logger.debug:(Ljava/lang/Object;)V
      69: aload_0
      70: getfield      #3                  // Field txContext:Lorg/mobicents/slee/runtime/transaction/TransactionContextImpl;
      73: invokevirtual #14                 // Method org/mobicents/slee/runtime/transaction/TransactionContextImpl.executeAfterCommitPriorityActions:()V
      76: aload_0
      77: getfield      #3                  // Field txContext:Lorg/mobicents/slee/runtime/transaction/TransactionContextImpl;
      80: invokevirtual #15                 // Method org/mobicents/slee/runtime/transaction/TransactionContextImpl.executeAfterCommitActions:()V
      83: goto          160
      86: getstatic     #5                  // Field logger:Lorg/apache/log4j/Logger;
      89: invokevirtual #6                  // Method org/apache/log4j/Logger.isDebugEnabled:()Z
      92: ifeq          123
      95: getstatic     #5                  // Field logger:Lorg/apache/log4j/Logger;
      98: new           #7                  // class java/lang/StringBuilder
     101: dup
     102: invokespecial #8                  // Method java/lang/StringBuilder."<init>":()V
     105: ldc           #16                 // String Completed rollback of tx
     107: invokevirtual #10                 // Method java/lang/StringBuilder.append:(Ljava/lang/String;)Ljava/lang/StringBuilder;
     110: aload_0
     111: getfield      #2                  // Field tx:Ljavax/transaction/Transaction;
     114: invokevirtual #11                 // Method java/lang/StringBuilder.append:(Ljava/lang/Object;)Ljava/lang/StringBuilder;
     117: invokevirtual #12                 // Method java/lang/StringBuilder.toString:()Ljava/lang/String;
     120: invokevirtual #13                 // Method org/apache/log4j/Logger.debug:(Ljava/lang/Object;)V
     123: aload_0
     124: getfield      #3                  // Field txContext:Lorg/mobicents/slee/runtime/transaction/TransactionContextImpl;
     127: invokevirtual #17                 // Method org/mobicents/slee/runtime/transaction/TransactionContextImpl.executeAfterRollbackActions:()V
     130: goto          160
     133: new           #18                 // class java/lang/IllegalStateException
     136: dup
     137: new           #7                  // class java/lang/StringBuilder
     140: dup
     141: invokespecial #8                  // Method java/lang/StringBuilder."<init>":()V
     144: ldc           #19                 // String Unexpected transaction state
     146: invokevirtual #10                 // Method java/lang/StringBuilder.append:(Ljava/lang/String;)Ljava/lang/StringBuilder;
     149: iload_1
     150: invokevirtual #20                 // Method java/lang/StringBuilder.append:(I)Ljava/lang/StringBuilder;
     153: invokevirtual #12                 // Method java/lang/StringBuilder.toString:()Ljava/lang/String;
     156: invokespecial #21                 // Method java/lang/IllegalStateException."<init>":(Ljava/lang/String;)V
     159: athrow
     160: aload_0
     161: getfield      #3                  // Field txContext:Lorg/mobicents/slee/runtime/transaction/TransactionContextImpl;
     164: invokevirtual #22                 // Method org/mobicents/slee/runtime/transaction/TransactionContextImpl.cleanup:()V
     167: return

  public void beforeCompletion();
    Code:
       0: aload_0
       1: getfield      #3                  // Field txContext:Lorg/mobicents/slee/runtime/transaction/TransactionContextImpl;
       4: invokevirtual #23                 // Method org/mobicents/slee/runtime/transaction/TransactionContextImpl.executeBeforeCommitPriorityActions:()V
       7: aload_0
       8: getfield      #3                  // Field txContext:Lorg/mobicents/slee/runtime/transaction/TransactionContextImpl;
      11: invokevirtual #24                 // Method org/mobicents/slee/runtime/transaction/TransactionContextImpl.executeBeforeCommitActions:()V
      14: return

  static {};
    Code:
       0: ldc_w         #25                 // class org/mobicents/slee/runtime/transaction/SleeTransactionManagerImpl
       3: invokestatic  #26                 // Method org/apache/log4j/Logger.getLogger:(Ljava/lang/Class;)Lorg/apache/log4j/Logger;
       6: putstatic     #5                  // Field logger:Lorg/apache/log4j/Logger;
       9: return
}
