Compiled from "BroadcastTransmitter.java"
public class org.agrona.concurrent.broadcast.BroadcastTransmitter {
  private final org.agrona.concurrent.AtomicBuffer buffer;

  private final int capacity;

  private final int maxMsgLength;

  private final int tailIntentCountIndex;

  private final int tailCounterIndex;

  private final int latestCounterIndex;

  public org.agrona.concurrent.broadcast.BroadcastTransmitter(org.agrona.concurrent.AtomicBuffer);
    Code:
       0: aload_0
       1: invokespecial #2                  // Method java/lang/Object."<init>":()V
       4: aload_0
       5: aload_1
       6: putfield      #3                  // Field buffer:Lorg/agrona/concurrent/AtomicBuffer;
       9: aload_0
      10: aload_1
      11: invokeinterface #4,  1            // InterfaceMethod org/agrona/concurrent/AtomicBuffer.capacity:()I
      16: getstatic     #5                  // Field org/agrona/concurrent/broadcast/BroadcastBufferDescriptor.TRAILER_LENGTH:I
      19: isub
      20: putfield      #6                  // Field capacity:I
      23: aload_0
      24: getfield      #6                  // Field capacity:I
      27: invokestatic  #7                  // Method org/agrona/concurrent/broadcast/BroadcastBufferDescriptor.checkCapacity:(I)V
      30: aload_1
      31: invokeinterface #8,  1            // InterfaceMethod org/agrona/concurrent/AtomicBuffer.verifyAlignment:()V
      36: aload_0
      37: aload_0
      38: getfield      #6                  // Field capacity:I
      41: invokestatic  #9                  // Method org/agrona/concurrent/broadcast/RecordDescriptor.calculateMaxMessageLength:(I)I
      44: putfield      #10                 // Field maxMsgLength:I
      47: aload_0
      48: aload_0
      49: getfield      #6                  // Field capacity:I
      52: getstatic     #11                 // Field org/agrona/concurrent/broadcast/BroadcastBufferDescriptor.TAIL_INTENT_COUNTER_OFFSET:I
      55: iadd
      56: putfield      #12                 // Field tailIntentCountIndex:I
      59: aload_0
      60: aload_0
      61: getfield      #6                  // Field capacity:I
      64: getstatic     #13                 // Field org/agrona/concurrent/broadcast/BroadcastBufferDescriptor.TAIL_COUNTER_OFFSET:I
      67: iadd
      68: putfield      #14                 // Field tailCounterIndex:I
      71: aload_0
      72: aload_0
      73: getfield      #6                  // Field capacity:I
      76: getstatic     #15                 // Field org/agrona/concurrent/broadcast/BroadcastBufferDescriptor.LATEST_COUNTER_OFFSET:I
      79: iadd
      80: putfield      #16                 // Field latestCounterIndex:I
      83: return

  public int capacity();
    Code:
       0: aload_0
       1: getfield      #6                  // Field capacity:I
       4: ireturn

  public int maxMsgLength();
    Code:
       0: aload_0
       1: getfield      #10                 // Field maxMsgLength:I
       4: ireturn

  public void transmit(int, org.agrona.DirectBuffer, int, int);
    Code:
       0: iload_1
       1: invokestatic  #17                 // Method org/agrona/concurrent/broadcast/RecordDescriptor.checkTypeId:(I)V
       4: aload_0
       5: iload         4
       7: invokespecial #18                 // Method checkMessageLength:(I)V
      10: aload_0
      11: getfield      #3                  // Field buffer:Lorg/agrona/concurrent/AtomicBuffer;
      14: astore        5
      16: aload         5
      18: aload_0
      19: getfield      #14                 // Field tailCounterIndex:I
      22: invokeinterface #19,  2           // InterfaceMethod org/agrona/concurrent/AtomicBuffer.getLong:(I)J
      27: lstore        6
      29: lload         6
      31: l2i
      32: aload_0
      33: getfield      #6                  // Field capacity:I
      36: iconst_1
      37: isub
      38: iand
      39: istore        8
      41: bipush        8
      43: iload         4
      45: iadd
      46: istore        9
      48: iload         9
      50: bipush        8
      52: invokestatic  #20                 // Method org/agrona/BitUtil.align:(II)I
      55: istore        10
      57: lload         6
      59: iload         10
      61: i2l
      62: ladd
      63: lstore        11
      65: aload_0
      66: getfield      #6                  // Field capacity:I
      69: iload         8
      71: isub
      72: istore        13
      74: iload         13
      76: iload         10
      78: if_icmpge     116
      81: aload_0
      82: aload         5
      84: lload         11
      86: iload         13
      88: i2l
      89: ladd
      90: invokespecial #21                 // Method signalTailIntent:(Lorg/agrona/concurrent/AtomicBuffer;J)V
      93: aload         5
      95: iload         8
      97: iload         13
      99: invokestatic  #22                 // Method insertPaddingRecord:(Lorg/agrona/concurrent/AtomicBuffer;II)V
     102: lload         6
     104: iload         13
     106: i2l
     107: ladd
     108: lstore        6
     110: iconst_0
     111: istore        8
     113: goto          124
     116: aload_0
     117: aload         5
     119: lload         11
     121: invokespecial #21                 // Method signalTailIntent:(Lorg/agrona/concurrent/AtomicBuffer;J)V
     124: aload         5
     126: iload         8
     128: invokestatic  #23                 // Method org/agrona/concurrent/broadcast/RecordDescriptor.lengthOffset:(I)I
     131: iload         9
     133: invokeinterface #24,  3           // InterfaceMethod org/agrona/concurrent/AtomicBuffer.putInt:(II)V
     138: aload         5
     140: iload         8
     142: invokestatic  #25                 // Method org/agrona/concurrent/broadcast/RecordDescriptor.typeOffset:(I)I
     145: iload_1
     146: invokeinterface #24,  3           // InterfaceMethod org/agrona/concurrent/AtomicBuffer.putInt:(II)V
     151: aload         5
     153: iload         8
     155: invokestatic  #26                 // Method org/agrona/concurrent/broadcast/RecordDescriptor.msgOffset:(I)I
     158: aload_2
     159: iload_3
     160: iload         4
     162: invokeinterface #27,  5           // InterfaceMethod org/agrona/concurrent/AtomicBuffer.putBytes:(ILorg/agrona/DirectBuffer;II)V
     167: aload         5
     169: aload_0
     170: getfield      #16                 // Field latestCounterIndex:I
     173: lload         6
     175: invokeinterface #28,  4           // InterfaceMethod org/agrona/concurrent/AtomicBuffer.putLong:(IJ)V
     180: aload         5
     182: aload_0
     183: getfield      #14                 // Field tailCounterIndex:I
     186: lload         6
     188: iload         10
     190: i2l
     191: ladd
     192: invokeinterface #29,  4           // InterfaceMethod org/agrona/concurrent/AtomicBuffer.putLongOrdered:(IJ)V
     197: return

  private void signalTailIntent(org.agrona.concurrent.AtomicBuffer, long);
    Code:
       0: aload_1
       1: aload_0
       2: getfield      #12                 // Field tailIntentCountIndex:I
       5: lload_2
       6: invokeinterface #28,  4           // InterfaceMethod org/agrona/concurrent/AtomicBuffer.putLong:(IJ)V
      11: getstatic     #30                 // Field org/agrona/UnsafeAccess.UNSAFE:Lsun/misc/Unsafe;
      14: invokevirtual #31                 // Method sun/misc/Unsafe.storeFence:()V
      17: return

  private static void insertPaddingRecord(org.agrona.concurrent.AtomicBuffer, int, int);
    Code:
       0: aload_0
       1: iload_1
       2: invokestatic  #23                 // Method org/agrona/concurrent/broadcast/RecordDescriptor.lengthOffset:(I)I
       5: iload_2
       6: invokeinterface #24,  3           // InterfaceMethod org/agrona/concurrent/AtomicBuffer.putInt:(II)V
      11: aload_0
      12: iload_1
      13: invokestatic  #25                 // Method org/agrona/concurrent/broadcast/RecordDescriptor.typeOffset:(I)I
      16: iconst_m1
      17: invokeinterface #24,  3           // InterfaceMethod org/agrona/concurrent/AtomicBuffer.putInt:(II)V
      22: return

  private void checkMessageLength(int);
    Code:
       0: iload_1
       1: aload_0
       2: getfield      #10                 // Field maxMsgLength:I
       5: if_icmple     44
       8: ldc           #32                 // String encoded message exceeds maxMsgLength of %d, length=%d
      10: iconst_2
      11: anewarray     #33                 // class java/lang/Object
      14: dup
      15: iconst_0
      16: aload_0
      17: getfield      #10                 // Field maxMsgLength:I
      20: invokestatic  #34                 // Method java/lang/Integer.valueOf:(I)Ljava/lang/Integer;
      23: aastore
      24: dup
      25: iconst_1
      26: iload_1
      27: invokestatic  #34                 // Method java/lang/Integer.valueOf:(I)Ljava/lang/Integer;
      30: aastore
      31: invokestatic  #35                 // Method java/lang/String.format:(Ljava/lang/String;[Ljava/lang/Object;)Ljava/lang/String;
      34: astore_2
      35: new           #36                 // class java/lang/IllegalArgumentException
      38: dup
      39: aload_2
      40: invokespecial #37                 // Method java/lang/IllegalArgumentException."<init>":(Ljava/lang/String;)V
      43: athrow
      44: return
}
