Compiled from "RecordDescriptor.java"
public class org.agrona.concurrent.broadcast.RecordDescriptor {
  public static final int PADDING_MSG_TYPE_ID;

  public static final int LENGTH_OFFSET;

  public static final int TYPE_OFFSET;

  public static final int HEADER_LENGTH;

  public static final int RECORD_ALIGNMENT;

  public org.agrona.concurrent.broadcast.RecordDescriptor();
    Code:
       0: aload_0
       1: invokespecial #3                  // Method java/lang/Object."<init>":()V
       4: return

  public static int calculateMaxMessageLength(int);
    Code:
       0: iload_0
       1: bipush        8
       3: idiv
       4: ireturn

  public static int lengthOffset(int);
    Code:
       0: iload_0
       1: iconst_0
       2: iadd
       3: ireturn

  public static int typeOffset(int);
    Code:
       0: iload_0
       1: iconst_4
       2: iadd
       3: ireturn

  public static int msgOffset(int);
    Code:
       0: iload_0
       1: bipush        8
       3: iadd
       4: ireturn

  public static void checkTypeId(int);
    Code:
       0: iload_0
       1: iconst_1
       2: if_icmpge     31
       5: ldc           #4                  // String Type id must be greater than zero, msgTypeId=%d
       7: iconst_1
       8: anewarray     #5                  // class java/lang/Object
      11: dup
      12: iconst_0
      13: iload_0
      14: invokestatic  #6                  // Method java/lang/Integer.valueOf:(I)Ljava/lang/Integer;
      17: aastore
      18: invokestatic  #7                  // Method java/lang/String.format:(Ljava/lang/String;[Ljava/lang/Object;)Ljava/lang/String;
      21: astore_1
      22: new           #8                  // class java/lang/IllegalArgumentException
      25: dup
      26: aload_1
      27: invokespecial #9                  // Method java/lang/IllegalArgumentException."<init>":(Ljava/lang/String;)V
      30: athrow
      31: return
}
