Compiled from "OrderImpl.java"
public class org.hibernate.query.criteria.internal.OrderImpl implements javax.persistence.criteria.Order,java.io.Serializable {
  private final javax.persistence.criteria.Expression<?> expression;

  private boolean ascending;

  public org.hibernate.query.criteria.internal.OrderImpl(javax.persistence.criteria.Expression<?>);
    Code:
       0: aload_0
       1: aload_1
       2: iconst_1
       3: invokespecial #1                  // Method "<init>":(Ljavax/persistence/criteria/Expression;Z)V
       6: return

  public org.hibernate.query.criteria.internal.OrderImpl(javax.persistence.criteria.Expression<?>, boolean);
    Code:
       0: aload_0
       1: invokespecial #2                  // Method java/lang/Object."<init>":()V
       4: aload_0
       5: aload_1
       6: putfield      #3                  // Field expression:Ljavax/persistence/criteria/Expression;
       9: aload_0
      10: iload_2
      11: putfield      #4                  // Field ascending:Z
      14: return

  public javax.persistence.criteria.Order reverse();
    Code:
       0: aload_0
       1: aload_0
       2: getfield      #4                  // Field ascending:Z
       5: ifne          12
       8: iconst_1
       9: goto          13
      12: iconst_0
      13: putfield      #4                  // Field ascending:Z
      16: aload_0
      17: areturn

  public boolean isAscending();
    Code:
       0: aload_0
       1: getfield      #4                  // Field ascending:Z
       4: ireturn

  public javax.persistence.criteria.Expression<?> getExpression();
    Code:
       0: aload_0
       1: getfield      #3                  // Field expression:Ljavax/persistence/criteria/Expression;
       4: areturn
}
