Compiled from "_AvalonLoggerFactory.java"
public class freemarker.log._AvalonLoggerFactory implements freemarker.log.LoggerFactory {
  public freemarker.log._AvalonLoggerFactory();
    Code:
       0: aload_0
       1: invokespecial #1                  // Method java/lang/Object."<init>":()V
       4: return

  public freemarker.log.Logger getLogger(java.lang.String);
    Code:
       0: new           #2                  // class freemarker/log/_AvalonLoggerFactory$AvalonLogger
       3: dup
       4: invokestatic  #3                  // Method org/apache/log/Hierarchy.getDefaultHierarchy:()Lorg/apache/log/Hierarchy;
       7: aload_1
       8: invokevirtual #4                  // Method org/apache/log/Hierarchy.getLoggerFor:(Ljava/lang/String;)Lorg/apache/log/Logger;
      11: invokespecial #5                  // Method freemarker/log/_AvalonLoggerFactory$AvalonLogger."<init>":(Lorg/apache/log/Logger;)V
      14: areturn
}
