Compiled from "Release.java"
public class org.sonar.updatecenter.common.Release implements java.lang.Comparable<org.sonar.updatecenter.common.Release> {
  private org.sonar.updatecenter.common.Artifact artifact;

  private org.sonar.updatecenter.common.Version version;

  private java.lang.String description;

  private java.net.URL downloadUrl;

  private java.net.URL changelogUrl;

  private boolean isPublic;

  private boolean isArchived;

  private java.lang.String groupId;

  private java.lang.String artifactId;

  private java.util.Set<org.sonar.updatecenter.common.Release> outgoingDependencies;

  private java.util.Set<org.sonar.updatecenter.common.Release> incomingDependencies;

  private java.util.SortedSet<org.sonar.updatecenter.common.Version> compatibleSqVersions;

  private java.util.Date date;

  public org.sonar.updatecenter.common.Release(org.sonar.updatecenter.common.Artifact, org.sonar.updatecenter.common.Version);
    Code:
       0: aload_0
       1: invokespecial #1                  // Method java/lang/Object."<init>":()V
       4: aload_0
       5: aload_1
       6: putfield      #2                  // Field artifact:Lorg/sonar/updatecenter/common/Artifact;
       9: aload_0
      10: aload_2
      11: putfield      #3                  // Field version:Lorg/sonar/updatecenter/common/Version;
      14: aload_0
      15: iconst_1
      16: putfield      #4                  // Field isPublic:Z
      19: aload_0
      20: iconst_0
      21: putfield      #5                  // Field isArchived:Z
      24: aload_0
      25: invokestatic  #6                  // Method com/google/common/collect/Sets.newTreeSet:()Ljava/util/TreeSet;
      28: putfield      #7                  // Field compatibleSqVersions:Ljava/util/SortedSet;
      31: aload_0
      32: invokestatic  #8                  // Method com/google/common/collect/Sets.newHashSet:()Ljava/util/HashSet;
      35: putfield      #9                  // Field outgoingDependencies:Ljava/util/Set;
      38: aload_0
      39: invokestatic  #8                  // Method com/google/common/collect/Sets.newHashSet:()Ljava/util/HashSet;
      42: putfield      #10                 // Field incomingDependencies:Ljava/util/Set;
      45: return

  public org.sonar.updatecenter.common.Release(org.sonar.updatecenter.common.Artifact, java.lang.String);
    Code:
       0: aload_0
       1: aload_1
       2: aload_2
       3: invokestatic  #11                 // Method org/sonar/updatecenter/common/Version.create:(Ljava/lang/String;)Lorg/sonar/updatecenter/common/Version;
       6: invokespecial #12                 // Method "<init>":(Lorg/sonar/updatecenter/common/Artifact;Lorg/sonar/updatecenter/common/Version;)V
       9: return

  public org.sonar.updatecenter.common.Artifact getArtifact();
    Code:
       0: aload_0
       1: getfield      #2                  // Field artifact:Lorg/sonar/updatecenter/common/Artifact;
       4: areturn

  public org.sonar.updatecenter.common.Version getVersion();
    Code:
       0: aload_0
       1: getfield      #3                  // Field version:Lorg/sonar/updatecenter/common/Version;
       4: areturn

  public org.sonar.updatecenter.common.Release setVersion(org.sonar.updatecenter.common.Version);
    Code:
       0: aload_0
       1: aload_1
       2: putfield      #3                  // Field version:Lorg/sonar/updatecenter/common/Version;
       5: aload_0
       6: areturn

  public java.lang.String getDownloadUrl();
    Code:
       0: aload_0
       1: getfield      #13                 // Field downloadUrl:Ljava/net/URL;
       4: ifnonnull     11
       7: aconst_null
       8: goto          18
      11: aload_0
      12: getfield      #13                 // Field downloadUrl:Ljava/net/URL;
      15: invokevirtual #14                 // Method java/net/URL.toString:()Ljava/lang/String;
      18: areturn

  public org.sonar.updatecenter.common.Release setDownloadUrl(java.lang.String);
    Code:
       0: aload_1
       1: ifnonnull     12
       4: aload_0
       5: aconst_null
       6: putfield      #13                 // Field downloadUrl:Ljava/net/URL;
       9: goto          42
      12: aload_0
      13: new           #15                 // class java/net/URI
      16: dup
      17: aload_1
      18: invokespecial #16                 // Method java/net/URI."<init>":(Ljava/lang/String;)V
      21: invokevirtual #17                 // Method java/net/URI.toURL:()Ljava/net/URL;
      24: putfield      #13                 // Field downloadUrl:Ljava/net/URL;
      27: goto          42
      30: astore_2
      31: new           #20                 // class java/lang/IllegalArgumentException
      34: dup
      35: ldc           #21                 // String downloadUrl invalid
      37: aload_2
      38: invokespecial #22                 // Method java/lang/IllegalArgumentException."<init>":(Ljava/lang/String;Ljava/lang/Throwable;)V
      41: athrow
      42: aload_0
      43: areturn
    Exception table:
       from    to  target type
          12    27    30   Class java/net/URISyntaxException
          12    27    30   Class java/net/MalformedURLException

  public java.lang.String getFilename();
    Code:
       0: aload_0
       1: getfield      #13                 // Field downloadUrl:Ljava/net/URL;
       4: ifnonnull     11
       7: aconst_null
       8: goto          23
      11: aload_0
      12: getfield      #13                 // Field downloadUrl:Ljava/net/URL;
      15: invokevirtual #23                 // Method java/net/URL.getPath:()Ljava/lang/String;
      18: ldc           #24                 // String /
      20: invokestatic  #25                 // Method org/apache/commons/lang/StringUtils.substringAfterLast:(Ljava/lang/String;Ljava/lang/String;)Ljava/lang/String;
      23: areturn

  public java.util.SortedSet<org.sonar.updatecenter.common.Version> getRequiredSonarVersions();
    Code:
       0: aload_0
       1: getfield      #7                  // Field compatibleSqVersions:Ljava/util/SortedSet;
       4: areturn

  public boolean supportSonarVersion(org.sonar.updatecenter.common.Version);
    Code:
       0: aload_0
       1: getfield      #7                  // Field compatibleSqVersions:Ljava/util/SortedSet;
       4: invokeinterface #26,  1           // InterfaceMethod java/util/SortedSet.iterator:()Ljava/util/Iterator;
       9: astore_2
      10: aload_2
      11: invokeinterface #27,  1           // InterfaceMethod java/util/Iterator.hasNext:()Z
      16: ifeq          42
      19: aload_2
      20: invokeinterface #28,  1           // InterfaceMethod java/util/Iterator.next:()Ljava/lang/Object;
      25: checkcast     #29                 // class org/sonar/updatecenter/common/Version
      28: astore_3
      29: aload_3
      30: aload_1
      31: invokevirtual #30                 // Method org/sonar/updatecenter/common/Version.isCompatibleWith:(Lorg/sonar/updatecenter/common/Version;)Z
      34: ifeq          39
      37: iconst_1
      38: ireturn
      39: goto          10
      42: iconst_0
      43: ireturn

  public org.sonar.updatecenter.common.Release addRequiredSonarVersions(org.sonar.updatecenter.common.Version...);
    Code:
       0: aload_1
       1: ifnull        18
       4: aload_0
       5: getfield      #7                  // Field compatibleSqVersions:Ljava/util/SortedSet;
       8: aload_1
       9: invokestatic  #31                 // Method java/util/Arrays.asList:([Ljava/lang/Object;)Ljava/util/List;
      12: invokeinterface #32,  2           // InterfaceMethod java/util/SortedSet.addAll:(Ljava/util/Collection;)Z
      17: pop
      18: aload_0
      19: areturn

  public org.sonar.updatecenter.common.Release addRequiredSonarVersions(java.lang.String...);
    Code:
       0: aload_1
       1: ifnull        45
       4: aload_1
       5: astore_2
       6: aload_2
       7: arraylength
       8: istore_3
       9: iconst_0
      10: istore        4
      12: iload         4
      14: iload_3
      15: if_icmpge     45
      18: aload_2
      19: iload         4
      21: aaload
      22: astore        5
      24: aload_0
      25: getfield      #7                  // Field compatibleSqVersions:Ljava/util/SortedSet;
      28: aload         5
      30: invokestatic  #11                 // Method org/sonar/updatecenter/common/Version.create:(Ljava/lang/String;)Lorg/sonar/updatecenter/common/Version;
      33: invokeinterface #33,  2           // InterfaceMethod java/util/SortedSet.add:(Ljava/lang/Object;)Z
      38: pop
      39: iinc          4, 1
      42: goto          12
      45: aload_0
      46: areturn

  public org.sonar.updatecenter.common.Version getLastRequiredSonarVersion();
    Code:
       0: aload_0
       1: getfield      #7                  // Field compatibleSqVersions:Ljava/util/SortedSet;
       4: invokeinterface #34,  1           // InterfaceMethod java/util/SortedSet.isEmpty:()Z
       9: ifne          25
      12: aload_0
      13: getfield      #7                  // Field compatibleSqVersions:Ljava/util/SortedSet;
      16: invokeinterface #35,  1           // InterfaceMethod java/util/SortedSet.last:()Ljava/lang/Object;
      21: checkcast     #29                 // class org/sonar/updatecenter/common/Version
      24: areturn
      25: aconst_null
      26: areturn

  public org.sonar.updatecenter.common.Version getMinimumRequiredSonarVersion();
    Code:
       0: aload_0
       1: getfield      #7                  // Field compatibleSqVersions:Ljava/util/SortedSet;
       4: invokeinterface #34,  1           // InterfaceMethod java/util/SortedSet.isEmpty:()Z
       9: ifne          25
      12: aload_0
      13: getfield      #7                  // Field compatibleSqVersions:Ljava/util/SortedSet;
      16: invokeinterface #36,  1           // InterfaceMethod java/util/SortedSet.first:()Ljava/lang/Object;
      21: checkcast     #29                 // class org/sonar/updatecenter/common/Version
      24: areturn
      25: aconst_null
      26: areturn

  public org.sonar.updatecenter.common.Version[] getSonarVersionFromString(java.lang.String);
    Code:
       0: aload_0
       1: getfield      #7                  // Field compatibleSqVersions:Ljava/util/SortedSet;
       4: new           #37                 // class org/sonar/updatecenter/common/Release$1
       7: dup
       8: aload_0
       9: aload_1
      10: invokespecial #38                 // Method org/sonar/updatecenter/common/Release$1."<init>":(Lorg/sonar/updatecenter/common/Release;Ljava/lang/String;)V
      13: invokestatic  #39                 // Method com/google/common/collect/Collections2.filter:(Ljava/util/Collection;Lcom/google/common/base/Predicate;)Ljava/util/Collection;
      16: astore_2
      17: aload_2
      18: aload_2
      19: invokeinterface #40,  1           // InterfaceMethod java/util/Collection.size:()I
      24: anewarray     #29                 // class org/sonar/updatecenter/common/Version
      27: invokeinterface #41,  2           // InterfaceMethod java/util/Collection.toArray:([Ljava/lang/Object;)[Ljava/lang/Object;
      32: checkcast     #42                 // class "[Lorg/sonar/updatecenter/common/Version;"
      35: areturn

  public java.util.Date getDate();
    Code:
       0: aload_0
       1: getfield      #43                 // Field date:Ljava/util/Date;
       4: ifnull        24
       7: new           #44                 // class java/util/Date
      10: dup
      11: aload_0
      12: getfield      #43                 // Field date:Ljava/util/Date;
      15: invokevirtual #45                 // Method java/util/Date.getTime:()J
      18: invokespecial #46                 // Method java/util/Date."<init>":(J)V
      21: goto          25
      24: aconst_null
      25: areturn

  public org.sonar.updatecenter.common.Release setDate(java.util.Date);
    Code:
       0: aload_0
       1: aload_1
       2: ifnull        19
       5: new           #44                 // class java/util/Date
       8: dup
       9: aload_1
      10: invokevirtual #45                 // Method java/util/Date.getTime:()J
      13: invokespecial #46                 // Method java/util/Date."<init>":(J)V
      16: goto          20
      19: aconst_null
      20: putfield      #43                 // Field date:Ljava/util/Date;
      23: aload_0
      24: areturn

  public java.lang.String getDescription();
    Code:
       0: aload_0
       1: getfield      #47                 // Field description:Ljava/lang/String;
       4: areturn

  public org.sonar.updatecenter.common.Release setDescription(java.lang.String);
    Code:
       0: aload_0
       1: aload_1
       2: putfield      #47                 // Field description:Ljava/lang/String;
       5: aload_0
       6: areturn

  public java.lang.String getChangelogUrl();
    Code:
       0: aload_0
       1: getfield      #48                 // Field changelogUrl:Ljava/net/URL;
       4: ifnonnull     11
       7: aconst_null
       8: goto          18
      11: aload_0
      12: getfield      #48                 // Field changelogUrl:Ljava/net/URL;
      15: invokevirtual #14                 // Method java/net/URL.toString:()Ljava/lang/String;
      18: areturn

  public org.sonar.updatecenter.common.Release setChangelogUrl(java.lang.String);
    Code:
       0: aload_1
       1: ifnonnull     12
       4: aload_0
       5: aconst_null
       6: putfield      #48                 // Field changelogUrl:Ljava/net/URL;
       9: goto          42
      12: aload_0
      13: new           #15                 // class java/net/URI
      16: dup
      17: aload_1
      18: invokespecial #16                 // Method java/net/URI."<init>":(Ljava/lang/String;)V
      21: invokevirtual #17                 // Method java/net/URI.toURL:()Ljava/net/URL;
      24: putfield      #48                 // Field changelogUrl:Ljava/net/URL;
      27: goto          42
      30: astore_2
      31: new           #20                 // class java/lang/IllegalArgumentException
      34: dup
      35: ldc           #49                 // String changelogUrl invalid
      37: aload_2
      38: invokespecial #22                 // Method java/lang/IllegalArgumentException."<init>":(Ljava/lang/String;Ljava/lang/Throwable;)V
      41: athrow
      42: aload_0
      43: areturn
    Exception table:
       from    to  target type
          12    27    30   Class java/net/URISyntaxException
          12    27    30   Class java/net/MalformedURLException

  public java.util.Set<org.sonar.updatecenter.common.Release> getOutgoingDependencies();
    Code:
       0: aload_0
       1: getfield      #9                  // Field outgoingDependencies:Ljava/util/Set;
       4: invokestatic  #50                 // Method com/google/common/collect/ImmutableSortedSet.copyOf:(Ljava/util/Collection;)Lcom/google/common/collect/ImmutableSortedSet;
       7: areturn

  public org.sonar.updatecenter.common.Release addOutgoingDependency(org.sonar.updatecenter.common.Release);
    Code:
       0: aload_0
       1: getfield      #9                  // Field outgoingDependencies:Ljava/util/Set;
       4: aload_1
       5: invokeinterface #51,  2           // InterfaceMethod java/util/Set.add:(Ljava/lang/Object;)Z
      10: pop
      11: aload_0
      12: areturn

  public java.util.Set<org.sonar.updatecenter.common.Release> getIncomingDependencies();
    Code:
       0: aload_0
       1: getfield      #10                 // Field incomingDependencies:Ljava/util/Set;
       4: invokestatic  #50                 // Method com/google/common/collect/ImmutableSortedSet.copyOf:(Ljava/util/Collection;)Lcom/google/common/collect/ImmutableSortedSet;
       7: areturn

  public org.sonar.updatecenter.common.Release addIncomingDependency(org.sonar.updatecenter.common.Release);
    Code:
       0: aload_0
       1: getfield      #10                 // Field incomingDependencies:Ljava/util/Set;
       4: aload_1
       5: invokeinterface #51,  2           // InterfaceMethod java/util/Set.add:(Ljava/lang/Object;)Z
      10: pop
      11: aload_0
      12: areturn

  public java.lang.String getKey();
    Code:
       0: aload_0
       1: invokevirtual #52                 // Method getArtifact:()Lorg/sonar/updatecenter/common/Artifact;
       4: invokevirtual #53                 // Method org/sonar/updatecenter/common/Artifact.getKey:()Ljava/lang/String;
       7: areturn

  public org.sonar.updatecenter.common.Version getAdjustedVersion();
    Code:
       0: aload_0
       1: getfield      #3                  // Field version:Lorg/sonar/updatecenter/common/Version;
       4: invokevirtual #54                 // Method org/sonar/updatecenter/common/Version.removeQualifier:()Lorg/sonar/updatecenter/common/Version;
       7: areturn

  public boolean isPublic();
    Code:
       0: aload_0
       1: getfield      #4                  // Field isPublic:Z
       4: ireturn

  public void setPublic(boolean);
    Code:
       0: aload_0
       1: iload_1
       2: putfield      #4                  // Field isPublic:Z
       5: return

  public boolean isArchived();
    Code:
       0: aload_0
       1: getfield      #5                  // Field isArchived:Z
       4: ireturn

  public void setArchived(boolean);
    Code:
       0: aload_0
       1: iload_1
       2: putfield      #5                  // Field isArchived:Z
       5: return

  public java.lang.String groupId();
    Code:
       0: aload_0
       1: getfield      #55                 // Field groupId:Ljava/lang/String;
       4: areturn

  public void setGroupId(java.lang.String);
    Code:
       0: aload_0
       1: aload_1
       2: putfield      #55                 // Field groupId:Ljava/lang/String;
       5: return

  public java.lang.String artifactId();
    Code:
       0: aload_0
       1: getfield      #56                 // Field artifactId:Ljava/lang/String;
       4: areturn

  public void setArtifactId(java.lang.String);
    Code:
       0: aload_0
       1: aload_1
       2: putfield      #56                 // Field artifactId:Ljava/lang/String;
       5: return

  public boolean equals(java.lang.Object);
    Code:
       0: aload_0
       1: aload_1
       2: if_acmpne     7
       5: iconst_1
       6: ireturn
       7: aload_1
       8: ifnull        22
      11: aload_0
      12: invokevirtual #57                 // Method java/lang/Object.getClass:()Ljava/lang/Class;
      15: aload_1
      16: invokevirtual #57                 // Method java/lang/Object.getClass:()Ljava/lang/Class;
      19: if_acmpeq     24
      22: iconst_0
      23: ireturn
      24: aload_1
      25: checkcast     #58                 // class org/sonar/updatecenter/common/Release
      28: astore_2
      29: aload_0
      30: getfield      #2                  // Field artifact:Lorg/sonar/updatecenter/common/Artifact;
      33: aload_2
      34: getfield      #2                  // Field artifact:Lorg/sonar/updatecenter/common/Artifact;
      37: invokevirtual #59                 // Method org/sonar/updatecenter/common/Artifact.equals:(Ljava/lang/Object;)Z
      40: ifne          45
      43: iconst_0
      44: ireturn
      45: aload_0
      46: getfield      #3                  // Field version:Lorg/sonar/updatecenter/common/Version;
      49: aload_2
      50: getfield      #3                  // Field version:Lorg/sonar/updatecenter/common/Version;
      53: invokevirtual #60                 // Method org/sonar/updatecenter/common/Version.equals:(Ljava/lang/Object;)Z
      56: ifne          61
      59: iconst_0
      60: ireturn
      61: iconst_1
      62: ireturn

  public int hashCode();
    Code:
       0: aload_0
       1: getfield      #2                  // Field artifact:Lorg/sonar/updatecenter/common/Artifact;
       4: invokevirtual #61                 // Method org/sonar/updatecenter/common/Artifact.hashCode:()I
       7: istore_1
       8: bipush        31
      10: iload_1
      11: imul
      12: aload_0
      13: getfield      #3                  // Field version:Lorg/sonar/updatecenter/common/Version;
      16: invokevirtual #62                 // Method org/sonar/updatecenter/common/Version.hashCode:()I
      19: iadd
      20: istore_1
      21: iload_1
      22: ireturn

  public java.lang.String toString();
    Code:
       0: new           #63                 // class org/apache/commons/lang/builder/ToStringBuilder
       3: dup
       4: aload_0
       5: invokespecial #64                 // Method org/apache/commons/lang/builder/ToStringBuilder."<init>":(Ljava/lang/Object;)V
       8: ldc           #65                 // String version
      10: aload_0
      11: getfield      #3                  // Field version:Lorg/sonar/updatecenter/common/Version;
      14: invokevirtual #66                 // Method org/apache/commons/lang/builder/ToStringBuilder.append:(Ljava/lang/String;Ljava/lang/Object;)Lorg/apache/commons/lang/builder/ToStringBuilder;
      17: ldc           #67                 // String downloadUrl
      19: aload_0
      20: getfield      #13                 // Field downloadUrl:Ljava/net/URL;
      23: invokevirtual #66                 // Method org/apache/commons/lang/builder/ToStringBuilder.append:(Ljava/lang/String;Ljava/lang/Object;)Lorg/apache/commons/lang/builder/ToStringBuilder;
      26: ldc           #68                 // String changelogUrl
      28: aload_0
      29: getfield      #48                 // Field changelogUrl:Ljava/net/URL;
      32: invokevirtual #66                 // Method org/apache/commons/lang/builder/ToStringBuilder.append:(Ljava/lang/String;Ljava/lang/Object;)Lorg/apache/commons/lang/builder/ToStringBuilder;
      35: ldc           #69                 // String description
      37: aload_0
      38: getfield      #47                 // Field description:Ljava/lang/String;
      41: invokevirtual #66                 // Method org/apache/commons/lang/builder/ToStringBuilder.append:(Ljava/lang/String;Ljava/lang/Object;)Lorg/apache/commons/lang/builder/ToStringBuilder;
      44: invokevirtual #70                 // Method org/apache/commons/lang/builder/ToStringBuilder.toString:()Ljava/lang/String;
      47: areturn

  public int compareTo(org.sonar.updatecenter.common.Release);
    Code:
       0: aload_0
       1: invokevirtual #71                 // Method getVersion:()Lorg/sonar/updatecenter/common/Version;
       4: aload_1
       5: invokevirtual #71                 // Method getVersion:()Lorg/sonar/updatecenter/common/Version;
       8: invokevirtual #72                 // Method org/sonar/updatecenter/common/Version.compareTo:(Lorg/sonar/updatecenter/common/Version;)I
      11: ireturn

  public int compareTo(java.lang.Object);
    Code:
       0: aload_0
       1: aload_1
       2: checkcast     #58                 // class org/sonar/updatecenter/common/Release
       5: invokevirtual #73                 // Method compareTo:(Lorg/sonar/updatecenter/common/Release;)I
       8: ireturn
}
