Compiled from "ActorGraphInterpreter.scala"
public final class akka.stream.impl.fusing.ActorGraphInterpreter$$anonfun$props$1 extends scala.runtime.AbstractFunction0<akka.stream.impl.fusing.ActorGraphInterpreter> implements scala.Serializable {
  public static final long serialVersionUID;

  private final akka.stream.impl.fusing.GraphInterpreterShell shell$1;

  public final akka.stream.impl.fusing.ActorGraphInterpreter apply();
    Code:
       0: new           #23                 // class akka/stream/impl/fusing/ActorGraphInterpreter
       3: dup
       4: aload_0
       5: getfield      #25                 // Field shell$1:Lakka/stream/impl/fusing/GraphInterpreterShell;
       8: invokespecial #29                 // Method akka/stream/impl/fusing/ActorGraphInterpreter."<init>":(Lakka/stream/impl/fusing/GraphInterpreterShell;)V
      11: areturn

  public final java.lang.Object apply();
    Code:
       0: aload_0
       1: invokevirtual #34                 // Method apply:()Lakka/stream/impl/fusing/ActorGraphInterpreter;
       4: areturn

  public akka.stream.impl.fusing.ActorGraphInterpreter$$anonfun$props$1(akka.stream.impl.fusing.GraphInterpreterShell);
    Code:
       0: aload_0
       1: aload_1
       2: putfield      #25                 // Field shell$1:Lakka/stream/impl/fusing/GraphInterpreterShell;
       5: aload_0
       6: invokespecial #37                 // Method scala/runtime/AbstractFunction0."<init>":()V
       9: return
}
