Compiled from "Ops.scala"
public final class akka.stream.impl.fusing.Collect$$anonfun$9 extends scala.runtime.AbstractFunction1<java.lang.Object, scala.Function1<java.lang.Object, java.lang.Object>> implements scala.Serializable {
  public static final long serialVersionUID;

  public final scala.Function1<java.lang.Object, java.lang.Object> apply(java.lang.Object);
    Code:
       0: getstatic     #20                 // Field akka/stream/impl/fusing/Collect$.MODULE$:Lakka/stream/impl/fusing/Collect$;
       3: invokevirtual #24                 // Method akka/stream/impl/fusing/Collect$.NotApplied:()Lscala/Function1;
       6: areturn

  public final java.lang.Object apply(java.lang.Object);
    Code:
       0: aload_0
       1: aload_1
       2: invokevirtual #31                 // Method apply:(Ljava/lang/Object;)Lscala/Function1;
       5: areturn

  public akka.stream.impl.fusing.Collect$$anonfun$9();
    Code:
       0: aload_0
       1: invokespecial #36                 // Method scala/runtime/AbstractFunction1."<init>":()V
       4: return
}
