Compiled from "Fusing.scala"
public final class akka.stream.impl.fusing.Fusing$$anonfun$akka$stream$impl$fusing$Fusing$$fuseGroup$2 extends scala.runtime.AbstractFunction1<scala.Tuple2<akka.stream.Outlet<?>, akka.stream.Outlet<?>>, java.lang.Object> implements scala.Serializable {
  public static final long serialVersionUID;

  private final java.util.ArrayList outsB3$1;

  private final java.util.ArrayList outOwnersB3$1;

  private final java.util.ArrayList outlets$1;

  private final java.util.Map outConns$1;

  private final scala.runtime.IntRef pos$1;

  private final akka.stream.Outlet[] outsB2$1;

  private final int[] outOwnersB2$1;

  public final java.lang.Object apply(scala.Tuple2<akka.stream.Outlet<?>, akka.stream.Outlet<?>>);
    Code:
       0: aload_1
       1: astore_2
       2: aload_2
       3: ifnull        124
       6: aload_2
       7: invokevirtual #37                 // Method scala/Tuple2._1:()Ljava/lang/Object;
      10: checkcast     #39                 // class akka/stream/Outlet
      13: astore_3
      14: aload_2
      15: invokevirtual #42                 // Method scala/Tuple2._2:()Ljava/lang/Object;
      18: checkcast     #39                 // class akka/stream/Outlet
      21: astore        4
      23: aload_0
      24: getfield      #44                 // Field outConns$1:Ljava/util/Map;
      27: aload_3
      28: invokeinterface #50,  2           // InterfaceMethod java/util/Map.containsKey:(Ljava/lang/Object;)Z
      33: ifeq          80
      36: aload_0
      37: getfield      #44                 // Field outConns$1:Ljava/util/Map;
      40: aload_3
      41: invokeinterface #54,  2           // InterfaceMethod java/util/Map.remove:(Ljava/lang/Object;)Ljava/lang/Object;
      46: invokestatic  #60                 // Method scala/runtime/BoxesRunTime.unboxToInt:(Ljava/lang/Object;)I
      49: istore        6
      51: aload_0
      52: getfield      #62                 // Field outsB2$1:[Lakka/stream/Outlet;
      55: iload         6
      57: aload         4
      59: aastore
      60: aload_0
      61: getfield      #64                 // Field outOwnersB2$1:[I
      64: iload         6
      66: aload_0
      67: getfield      #66                 // Field pos$1:Lscala/runtime/IntRef;
      70: getfield      #72                 // Field scala/runtime/IntRef.elem:I
      73: iastore
      74: getstatic     #78                 // Field scala/runtime/BoxedUnit.UNIT:Lscala/runtime/BoxedUnit;
      77: goto          119
      80: aload_0
      81: getfield      #80                 // Field outsB3$1:Ljava/util/ArrayList;
      84: aload         4
      86: invokevirtual #85                 // Method java/util/ArrayList.add:(Ljava/lang/Object;)Z
      89: pop
      90: aload_0
      91: getfield      #87                 // Field outOwnersB3$1:Ljava/util/ArrayList;
      94: aload_0
      95: getfield      #66                 // Field pos$1:Lscala/runtime/IntRef;
      98: getfield      #72                 // Field scala/runtime/IntRef.elem:I
     101: invokestatic  #91                 // Method scala/runtime/BoxesRunTime.boxToInteger:(I)Ljava/lang/Integer;
     104: invokevirtual #85                 // Method java/util/ArrayList.add:(Ljava/lang/Object;)Z
     107: pop
     108: aload_0
     109: getfield      #93                 // Field outlets$1:Ljava/util/ArrayList;
     112: aload_3
     113: invokevirtual #85                 // Method java/util/ArrayList.add:(Ljava/lang/Object;)Z
     116: invokestatic  #97                 // Method scala/runtime/BoxesRunTime.boxToBoolean:(Z)Ljava/lang/Boolean;
     119: astore        5
     121: aload         5
     123: areturn
     124: new           #99                 // class scala/MatchError
     127: dup
     128: aload_2
     129: invokespecial #103                // Method scala/MatchError."<init>":(Ljava/lang/Object;)V
     132: athrow

  public final java.lang.Object apply(java.lang.Object);
    Code:
       0: aload_0
       1: aload_1
       2: checkcast     #33                 // class scala/Tuple2
       5: invokevirtual #115                // Method apply:(Lscala/Tuple2;)Ljava/lang/Object;
       8: areturn

  public akka.stream.impl.fusing.Fusing$$anonfun$akka$stream$impl$fusing$Fusing$$fuseGroup$2(java.util.ArrayList, java.util.ArrayList, java.util.ArrayList, java.util.Map, scala.runtime.IntRef, akka.stream.Outlet[], int[]);
    Code:
       0: aload_0
       1: aload_1
       2: putfield      #80                 // Field outsB3$1:Ljava/util/ArrayList;
       5: aload_0
       6: aload_2
       7: putfield      #87                 // Field outOwnersB3$1:Ljava/util/ArrayList;
      10: aload_0
      11: aload_3
      12: putfield      #93                 // Field outlets$1:Ljava/util/ArrayList;
      15: aload_0
      16: aload         4
      18: putfield      #44                 // Field outConns$1:Ljava/util/Map;
      21: aload_0
      22: aload         5
      24: putfield      #66                 // Field pos$1:Lscala/runtime/IntRef;
      27: aload_0
      28: aload         6
      30: putfield      #62                 // Field outsB2$1:[Lakka/stream/Outlet;
      33: aload_0
      34: aload         7
      36: putfield      #64                 // Field outOwnersB2$1:[I
      39: aload_0
      40: invokespecial #121                // Method scala/runtime/AbstractFunction1."<init>":()V
      43: return
}
