Compiled from "GraphStages.scala"
public final class akka.stream.impl.fusing.GraphStages$MaterializedValueSource<T> extends akka.stream.stage.GraphStage<akka.stream.SourceShape<T>> {
  private final akka.stream.impl.StreamLayout$MaterializedValueNode computation;

  private final akka.stream.Outlet<T> out;

  private final akka.stream.SourceShape<T> shape;

  private final scala.concurrent.Promise<T> akka$stream$impl$fusing$GraphStages$MaterializedValueSource$$promise;

  public akka.stream.impl.StreamLayout$MaterializedValueNode computation();
    Code:
       0: aload_0
       1: getfield      #20                 // Field computation:Lakka/stream/impl/StreamLayout$MaterializedValueNode;
       4: areturn

  public akka.stream.Outlet<T> out();
    Code:
       0: aload_0
       1: getfield      #25                 // Field out:Lakka/stream/Outlet;
       4: areturn

  public akka.stream.Attributes initialAttributes();
    Code:
       0: getstatic     #33                 // Field akka/stream/impl/Stages$DefaultAttributes$.MODULE$:Lakka/stream/impl/Stages$DefaultAttributes$;
       3: invokevirtual #36                 // Method akka/stream/impl/Stages$DefaultAttributes$.materializedValueSource:()Lakka/stream/Attributes;
       6: areturn

  public akka.stream.SourceShape<T> shape();
    Code:
       0: aload_0
       1: getfield      #39                 // Field shape:Lakka/stream/SourceShape;
       4: areturn

  public scala.concurrent.Promise<T> akka$stream$impl$fusing$GraphStages$MaterializedValueSource$$promise();
    Code:
       0: aload_0
       1: getfield      #42                 // Field akka$stream$impl$fusing$GraphStages$MaterializedValueSource$$promise:Lscala/concurrent/Promise;
       4: areturn

  public void setValue(T);
    Code:
       0: aload_0
       1: invokevirtual #46                 // Method akka$stream$impl$fusing$GraphStages$MaterializedValueSource$$promise:()Lscala/concurrent/Promise;
       4: aload_1
       5: invokeinterface #52,  2           // InterfaceMethod scala/concurrent/Promise.success:(Ljava/lang/Object;)Lscala/concurrent/Promise;
      10: pop
      11: return

  public akka.stream.impl.fusing.GraphStages$MaterializedValueSource<T> copySrc();
    Code:
       0: new           #2                  // class akka/stream/impl/fusing/GraphStages$MaterializedValueSource
       3: dup
       4: aload_0
       5: invokevirtual #58                 // Method computation:()Lakka/stream/impl/StreamLayout$MaterializedValueNode;
       8: aload_0
       9: invokevirtual #60                 // Method out:()Lakka/stream/Outlet;
      12: invokespecial #64                 // Method "<init>":(Lakka/stream/impl/StreamLayout$MaterializedValueNode;Lakka/stream/Outlet;)V
      15: areturn

  public akka.stream.stage.GraphStageLogic createLogic(akka.stream.Attributes);
    Code:
       0: new           #68                 // class akka/stream/impl/fusing/GraphStages$MaterializedValueSource$$anon$8
       3: dup
       4: aload_0
       5: invokespecial #71                 // Method akka/stream/impl/fusing/GraphStages$MaterializedValueSource$$anon$8."<init>":(Lakka/stream/impl/fusing/GraphStages$MaterializedValueSource;)V
       8: areturn

  public java.lang.String toString();
    Code:
       0: new           #77                 // class scala/StringContext
       3: dup
       4: getstatic     #82                 // Field scala/Predef$.MODULE$:Lscala/Predef$;
       7: iconst_2
       8: anewarray     #84                 // class java/lang/String
      11: dup
      12: iconst_0
      13: ldc           #86                 // String MaterializedValueSource(
      15: aastore
      16: dup
      17: iconst_1
      18: ldc           #88                 // String )
      20: aastore
      21: checkcast     #90                 // class "[Ljava/lang/Object;"
      24: invokevirtual #94                 // Method scala/Predef$.wrapRefArray:([Ljava/lang/Object;)Lscala/collection/mutable/WrappedArray;
      27: invokespecial #97                 // Method scala/StringContext."<init>":(Lscala/collection/Seq;)V
      30: getstatic     #82                 // Field scala/Predef$.MODULE$:Lscala/Predef$;
      33: iconst_1
      34: anewarray     #99                 // class java/lang/Object
      37: dup
      38: iconst_0
      39: aload_0
      40: invokevirtual #58                 // Method computation:()Lakka/stream/impl/StreamLayout$MaterializedValueNode;
      43: aastore
      44: invokevirtual #103                // Method scala/Predef$.genericWrapArray:(Ljava/lang/Object;)Lscala/collection/mutable/WrappedArray;
      47: invokevirtual #107                // Method scala/StringContext.s:(Lscala/collection/Seq;)Ljava/lang/String;
      50: areturn

  public akka.stream.Shape shape();
    Code:
       0: aload_0
       1: invokevirtual #110                // Method shape:()Lakka/stream/SourceShape;
       4: areturn

  public akka.stream.impl.fusing.GraphStages$MaterializedValueSource(akka.stream.impl.StreamLayout$MaterializedValueNode, akka.stream.Outlet<T>);
    Code:
       0: aload_0
       1: aload_1
       2: putfield      #20                 // Field computation:Lakka/stream/impl/StreamLayout$MaterializedValueNode;
       5: aload_0
       6: aload_2
       7: putfield      #25                 // Field out:Lakka/stream/Outlet;
      10: aload_0
      11: invokespecial #113                // Method akka/stream/stage/GraphStage."<init>":()V
      14: aload_0
      15: new           #115                // class akka/stream/SourceShape
      18: dup
      19: aload_2
      20: invokespecial #118                // Method akka/stream/SourceShape."<init>":(Lakka/stream/Outlet;)V
      23: putfield      #39                 // Field shape:Lakka/stream/SourceShape;
      26: aload_0
      27: getstatic     #123                // Field scala/concurrent/Promise$.MODULE$:Lscala/concurrent/Promise$;
      30: invokevirtual #126                // Method scala/concurrent/Promise$.apply:()Lscala/concurrent/Promise;
      33: putfield      #42                 // Field akka$stream$impl$fusing$GraphStages$MaterializedValueSource$$promise:Lscala/concurrent/Promise;
      36: return

  public akka.stream.impl.fusing.GraphStages$MaterializedValueSource(akka.stream.impl.StreamLayout$MaterializedValueNode);
    Code:
       0: aload_0
       1: aload_1
       2: getstatic     #132                // Field akka/stream/Outlet$.MODULE$:Lakka/stream/Outlet$;
       5: ldc           #134                // String matValue
       7: invokevirtual #137                // Method akka/stream/Outlet$.apply:(Ljava/lang/String;)Lakka/stream/Outlet;
      10: invokespecial #64                 // Method "<init>":(Lakka/stream/impl/StreamLayout$MaterializedValueNode;Lakka/stream/Outlet;)V
      13: return
}
