Compiled from "GraphStages.scala"
public final class akka.stream.impl.fusing.GraphStages$TickSource$$anon$5 extends akka.stream.stage.TimerGraphStageLogic implements akka.actor.Cancellable {
  private final java.util.concurrent.atomic.AtomicBoolean cancelled;

  private final java.util.concurrent.atomic.AtomicReference<scala.Option<akka.stream.stage.AsyncCallback<scala.runtime.BoxedUnit>>> cancelCallback;

  private final akka.stream.impl.fusing.GraphStages$TickSource $outer;

  public java.util.concurrent.atomic.AtomicBoolean cancelled();
    Code:
       0: aload_0
       1: getfield      #22                 // Field cancelled:Ljava/util/concurrent/atomic/AtomicBoolean;
       4: areturn

  public java.util.concurrent.atomic.AtomicReference<scala.Option<akka.stream.stage.AsyncCallback<scala.runtime.BoxedUnit>>> cancelCallback();
    Code:
       0: aload_0
       1: getfield      #27                 // Field cancelCallback:Ljava/util/concurrent/atomic/AtomicReference;
       4: areturn

  public void preStart();
    Code:
       0: aload_0
       1: invokevirtual #31                 // Method cancelCallback:()Ljava/util/concurrent/atomic/AtomicReference;
       4: new           #33                 // class scala/Some
       7: dup
       8: aload_0
       9: new           #35                 // class akka/stream/impl/fusing/GraphStages$TickSource$$anon$5$$anonfun$preStart$1
      12: dup
      13: aload_0
      14: invokespecial #39                 // Method akka/stream/impl/fusing/GraphStages$TickSource$$anon$5$$anonfun$preStart$1."<init>":(Lakka/stream/impl/fusing/GraphStages$TickSource$$anon$5;)V
      17: invokevirtual #43                 // Method getAsyncCallback:(Lscala/Function1;)Lakka/stream/stage/AsyncCallback;
      20: invokespecial #46                 // Method scala/Some."<init>":(Ljava/lang/Object;)V
      23: invokevirtual #51                 // Method java/util/concurrent/atomic/AtomicReference.set:(Ljava/lang/Object;)V
      26: aload_0
      27: invokevirtual #53                 // Method cancelled:()Ljava/util/concurrent/atomic/AtomicBoolean;
      30: invokevirtual #59                 // Method java/util/concurrent/atomic/AtomicBoolean.get:()Z
      33: ifeq          43
      36: aload_0
      37: invokevirtual #62                 // Method completeStage:()V
      40: goto          63
      43: aload_0
      44: ldc           #64                 // String TickTimer
      46: aload_0
      47: getfield      #66                 // Field $outer:Lakka/stream/impl/fusing/GraphStages$TickSource;
      50: invokevirtual #70                 // Method akka/stream/impl/fusing/GraphStages$TickSource.initialDelay:()Lscala/concurrent/duration/FiniteDuration;
      53: aload_0
      54: getfield      #66                 // Field $outer:Lakka/stream/impl/fusing/GraphStages$TickSource;
      57: invokevirtual #73                 // Method akka/stream/impl/fusing/GraphStages$TickSource.interval:()Lscala/concurrent/duration/FiniteDuration;
      60: invokevirtual #77                 // Method schedulePeriodicallyWithInitialDelay:(Ljava/lang/Object;Lscala/concurrent/duration/FiniteDuration;Lscala/concurrent/duration/FiniteDuration;)V
      63: return

  public void onTimer(java.lang.Object);
    Code:
       0: aload_0
       1: aload_0
       2: getfield      #66                 // Field $outer:Lakka/stream/impl/fusing/GraphStages$TickSource;
       5: invokevirtual #82                 // Method akka/stream/impl/fusing/GraphStages$TickSource.out:()Lakka/stream/Outlet;
       8: invokevirtual #86                 // Method isAvailable:(Lakka/stream/Outlet;)Z
      11: ifeq          39
      14: aload_0
      15: invokevirtual #89                 // Method isCancelled:()Z
      18: ifne          39
      21: aload_0
      22: aload_0
      23: getfield      #66                 // Field $outer:Lakka/stream/impl/fusing/GraphStages$TickSource;
      26: invokevirtual #82                 // Method akka/stream/impl/fusing/GraphStages$TickSource.out:()Lakka/stream/Outlet;
      29: aload_0
      30: getfield      #66                 // Field $outer:Lakka/stream/impl/fusing/GraphStages$TickSource;
      33: invokevirtual #93                 // Method akka/stream/impl/fusing/GraphStages$TickSource.tick:()Ljava/lang/Object;
      36: invokevirtual #97                 // Method push:(Lakka/stream/Outlet;Ljava/lang/Object;)V
      39: return

  public boolean cancel();
    Code:
       0: aload_0
       1: invokevirtual #53                 // Method cancelled:()Ljava/util/concurrent/atomic/AtomicBoolean;
       4: iconst_1
       5: invokevirtual #104                // Method java/util/concurrent/atomic/AtomicBoolean.getAndSet:(Z)Z
       8: ifeq          15
      11: iconst_0
      12: goto          16
      15: iconst_1
      16: istore_1
      17: iload_1
      18: ifeq          42
      21: aload_0
      22: invokevirtual #31                 // Method cancelCallback:()Ljava/util/concurrent/atomic/AtomicReference;
      25: invokevirtual #106                // Method java/util/concurrent/atomic/AtomicReference.get:()Ljava/lang/Object;
      28: checkcast     #108                // class scala/Option
      31: new           #110                // class akka/stream/impl/fusing/GraphStages$TickSource$$anon$5$$anonfun$cancel$1
      34: dup
      35: aload_0
      36: invokespecial #111                // Method akka/stream/impl/fusing/GraphStages$TickSource$$anon$5$$anonfun$cancel$1."<init>":(Lakka/stream/impl/fusing/GraphStages$TickSource$$anon$5;)V
      39: invokevirtual #115                // Method scala/Option.foreach:(Lscala/Function1;)V
      42: iload_1
      43: ireturn

  public boolean isCancelled();
    Code:
       0: aload_0
       1: invokevirtual #53                 // Method cancelled:()Ljava/util/concurrent/atomic/AtomicBoolean;
       4: invokevirtual #59                 // Method java/util/concurrent/atomic/AtomicBoolean.get:()Z
       7: ireturn

  public java.lang.String toString();
    Code:
       0: ldc           #121                // String TickSourceLogic
       2: areturn

  public akka.stream.impl.fusing.GraphStages$TickSource$$anon$5(akka.stream.impl.fusing.GraphStages$TickSource<T>);
    Code:
       0: aload_1
       1: ifnonnull     6
       4: aconst_null
       5: athrow
       6: aload_0
       7: aload_1
       8: putfield      #66                 // Field $outer:Lakka/stream/impl/fusing/GraphStages$TickSource;
      11: aload_0
      12: aload_1
      13: invokevirtual #126                // Method akka/stream/impl/fusing/GraphStages$TickSource.shape:()Lakka/stream/SourceShape;
      16: invokespecial #129                // Method akka/stream/stage/TimerGraphStageLogic."<init>":(Lakka/stream/Shape;)V
      19: aload_0
      20: new           #55                 // class java/util/concurrent/atomic/AtomicBoolean
      23: dup
      24: iconst_0
      25: invokespecial #132                // Method java/util/concurrent/atomic/AtomicBoolean."<init>":(Z)V
      28: putfield      #22                 // Field cancelled:Ljava/util/concurrent/atomic/AtomicBoolean;
      31: aload_0
      32: new           #48                 // class java/util/concurrent/atomic/AtomicReference
      35: dup
      36: getstatic     #138                // Field scala/None$.MODULE$:Lscala/None$;
      39: invokespecial #139                // Method java/util/concurrent/atomic/AtomicReference."<init>":(Ljava/lang/Object;)V
      42: putfield      #27                 // Field cancelCallback:Ljava/util/concurrent/atomic/AtomicReference;
      45: aload_0
      46: aload_1
      47: invokevirtual #82                 // Method akka/stream/impl/fusing/GraphStages$TickSource.out:()Lakka/stream/Outlet;
      50: aload_0
      51: invokevirtual #143                // Method eagerTerminateOutput:()Lakka/stream/stage/OutHandler;
      54: invokevirtual #147                // Method setHandler:(Lakka/stream/Outlet;Lakka/stream/stage/OutHandler;)V
      57: return
}
