Compiled from "StreamOfStreams.scala"
public class akka.stream.impl.fusing.GroupBy$$anon$1$SubstreamSource extends akka.stream.stage.GraphStageLogic$SubSourceOutlet<T> implements akka.stream.stage.OutHandler {
  private final K key;

  private T firstElement;

  public K key();
    Code:
       0: aload_0
       1: getfield      #16                 // Field key:Ljava/lang/Object;
       4: areturn

  public T firstElement();
    Code:
       0: aload_0
       1: getfield      #20                 // Field firstElement:Ljava/lang/Object;
       4: areturn

  public void firstElement_$eq(T);
    Code:
       0: aload_0
       1: aload_1
       2: putfield      #20                 // Field firstElement:Ljava/lang/Object;
       5: return

  public boolean firstPush();
    Code:
       0: aload_0
       1: invokevirtual #27                 // Method firstElement:()Ljava/lang/Object;
       4: ifnonnull     11
       7: iconst_0
       8: goto          12
      11: iconst_1
      12: ireturn

  public boolean hasNextForSubSource();
    Code:
       0: aload_0
       1: invokevirtual #32                 // Method akka$stream$impl$fusing$GroupBy$$anon$SubstreamSource$$$outer:()Lakka/stream/impl/fusing/GroupBy$$anon$1;
       4: invokevirtual #37                 // Method akka/stream/impl/fusing/GroupBy$$anon$1.akka$stream$impl$fusing$GroupBy$$anon$$hasNextElement:()Z
       7: ifeq          31
      10: aload_0
      11: invokevirtual #32                 // Method akka$stream$impl$fusing$GroupBy$$anon$SubstreamSource$$$outer:()Lakka/stream/impl/fusing/GroupBy$$anon$1;
      14: invokevirtual #40                 // Method akka/stream/impl/fusing/GroupBy$$anon$1.akka$stream$impl$fusing$GroupBy$$anon$$nextElementKey:()Ljava/lang/Object;
      17: aload_0
      18: invokevirtual #42                 // Method key:()Ljava/lang/Object;
      21: invokestatic  #48                 // Method scala/runtime/BoxesRunTime.equals:(Ljava/lang/Object;Ljava/lang/Object;)Z
      24: ifeq          31
      27: iconst_1
      28: goto          32
      31: iconst_0
      32: ireturn

  private void completeSubStream();
    Code:
       0: aload_0
       1: invokevirtual #53                 // Method complete:()V
       4: aload_0
       5: invokevirtual #32                 // Method akka$stream$impl$fusing$GroupBy$$anon$SubstreamSource$$$outer:()Lakka/stream/impl/fusing/GroupBy$$anon$1;
       8: invokevirtual #57                 // Method akka/stream/impl/fusing/GroupBy$$anon$1.akka$stream$impl$fusing$GroupBy$$anon$$activeSubstreamsMap:()Ljava/util/HashMap;
      11: aload_0
      12: invokevirtual #42                 // Method key:()Ljava/lang/Object;
      15: invokevirtual #63                 // Method java/util/HashMap.remove:(Ljava/lang/Object;)Ljava/lang/Object;
      18: pop
      19: aload_0
      20: invokevirtual #32                 // Method akka$stream$impl$fusing$GroupBy$$anon$SubstreamSource$$$outer:()Lakka/stream/impl/fusing/GroupBy$$anon$1;
      23: invokevirtual #67                 // Method akka/stream/impl/fusing/GroupBy$$anon$1.akka$stream$impl$fusing$GroupBy$$anon$$closedSubstreams:()Ljava/util/HashSet;
      26: aload_0
      27: invokevirtual #42                 // Method key:()Ljava/lang/Object;
      30: invokevirtual #73                 // Method java/util/HashSet.add:(Ljava/lang/Object;)Z
      33: pop
      34: return

  private void tryCompleteHandler();
    Code:
       0: aload_0
       1: invokevirtual #32                 // Method akka$stream$impl$fusing$GroupBy$$anon$SubstreamSource$$$outer:()Lakka/stream/impl/fusing/GroupBy$$anon$1;
       4: aload_0
       5: invokevirtual #32                 // Method akka$stream$impl$fusing$GroupBy$$anon$SubstreamSource$$$outer:()Lakka/stream/impl/fusing/GroupBy$$anon$1;
       8: invokevirtual #78                 // Method akka/stream/impl/fusing/GroupBy$$anon$1.akka$stream$impl$fusing$GroupBy$$anon$$$outer:()Lakka/stream/impl/fusing/GroupBy;
      11: invokevirtual #84                 // Method akka/stream/impl/fusing/GroupBy.in:()Lakka/stream/Inlet;
      14: invokevirtual #88                 // Method akka/stream/impl/fusing/GroupBy$$anon$1.isClosed:(Lakka/stream/Inlet;)Z
      17: ifeq          39
      20: aload_0
      21: invokevirtual #90                 // Method hasNextForSubSource:()Z
      24: ifne          39
      27: aload_0
      28: invokespecial #92                 // Method completeSubStream:()V
      31: aload_0
      32: invokevirtual #32                 // Method akka$stream$impl$fusing$GroupBy$$anon$SubstreamSource$$$outer:()Lakka/stream/impl/fusing/GroupBy$$anon$1;
      35: invokevirtual #95                 // Method akka/stream/impl/fusing/GroupBy$$anon$1.akka$stream$impl$fusing$GroupBy$$anon$$tryCompleteAll:()Z
      38: pop
      39: return

  public void onPull();
    Code:
       0: aload_0
       1: invokevirtual #32                 // Method akka$stream$impl$fusing$GroupBy$$anon$SubstreamSource$$$outer:()Lakka/stream/impl/fusing/GroupBy$$anon$1;
       4: aload_0
       5: invokevirtual #42                 // Method key:()Ljava/lang/Object;
       8: invokevirtual #99                 // Method akka/stream/impl/fusing/GroupBy$$anon$1.cancelTimer:(Ljava/lang/Object;)V
      11: aload_0
      12: invokevirtual #101                // Method firstPush:()Z
      15: ifeq          83
      18: aload_0
      19: invokevirtual #32                 // Method akka$stream$impl$fusing$GroupBy$$anon$SubstreamSource$$$outer:()Lakka/stream/impl/fusing/GroupBy$$anon$1;
      22: aload_0
      23: invokevirtual #32                 // Method akka$stream$impl$fusing$GroupBy$$anon$SubstreamSource$$$outer:()Lakka/stream/impl/fusing/GroupBy$$anon$1;
      26: invokevirtual #105                // Method akka/stream/impl/fusing/GroupBy$$anon$1.akka$stream$impl$fusing$GroupBy$$anon$$firstPushCounter:()I
      29: iconst_1
      30: isub
      31: invokevirtual #109                // Method akka/stream/impl/fusing/GroupBy$$anon$1.akka$stream$impl$fusing$GroupBy$$anon$$firstPushCounter_$eq:(I)V
      34: aload_0
      35: aload_0
      36: invokevirtual #27                 // Method firstElement:()Ljava/lang/Object;
      39: invokevirtual #112                // Method push:(Ljava/lang/Object;)V
      42: aload_0
      43: aconst_null
      44: invokevirtual #114                // Method firstElement_$eq:(Ljava/lang/Object;)V
      47: aload_0
      48: invokevirtual #32                 // Method akka$stream$impl$fusing$GroupBy$$anon$SubstreamSource$$$outer:()Lakka/stream/impl/fusing/GroupBy$$anon$1;
      51: invokevirtual #117                // Method akka/stream/impl/fusing/GroupBy$$anon$1.akka$stream$impl$fusing$GroupBy$$anon$$substreamsJustStared:()Ljava/util/HashSet;
      54: aload_0
      55: invokevirtual #119                // Method java/util/HashSet.remove:(Ljava/lang/Object;)Z
      58: pop
      59: aload_0
      60: invokevirtual #32                 // Method akka$stream$impl$fusing$GroupBy$$anon$SubstreamSource$$$outer:()Lakka/stream/impl/fusing/GroupBy$$anon$1;
      63: invokevirtual #117                // Method akka/stream/impl/fusing/GroupBy$$anon$1.akka$stream$impl$fusing$GroupBy$$anon$$substreamsJustStared:()Ljava/util/HashSet;
      66: invokevirtual #122                // Method java/util/HashSet.isEmpty:()Z
      69: ifeq          138
      72: aload_0
      73: invokevirtual #32                 // Method akka$stream$impl$fusing$GroupBy$$anon$SubstreamSource$$$outer:()Lakka/stream/impl/fusing/GroupBy$$anon$1;
      76: iconst_0
      77: invokevirtual #126                // Method akka/stream/impl/fusing/GroupBy$$anon$1.setKeepGoing:(Z)V
      80: goto          138
      83: aload_0
      84: invokevirtual #90                 // Method hasNextForSubSource:()Z
      87: ifeq          111
      90: aload_0
      91: aload_0
      92: invokevirtual #32                 // Method akka$stream$impl$fusing$GroupBy$$anon$SubstreamSource$$$outer:()Lakka/stream/impl/fusing/GroupBy$$anon$1;
      95: invokevirtual #129                // Method akka/stream/impl/fusing/GroupBy$$anon$1.akka$stream$impl$fusing$GroupBy$$anon$$nextElementValue:()Ljava/lang/Object;
      98: invokevirtual #112                // Method push:(Ljava/lang/Object;)V
     101: aload_0
     102: invokevirtual #32                 // Method akka$stream$impl$fusing$GroupBy$$anon$SubstreamSource$$$outer:()Lakka/stream/impl/fusing/GroupBy$$anon$1;
     105: invokevirtual #132                // Method akka/stream/impl/fusing/GroupBy$$anon$1.akka$stream$impl$fusing$GroupBy$$anon$$clearNextElement:()V
     108: goto          138
     111: aload_0
     112: invokevirtual #32                 // Method akka$stream$impl$fusing$GroupBy$$anon$SubstreamSource$$$outer:()Lakka/stream/impl/fusing/GroupBy$$anon$1;
     115: invokevirtual #135                // Method akka/stream/impl/fusing/GroupBy$$anon$1.akka$stream$impl$fusing$GroupBy$$anon$$needToPull:()Z
     118: ifeq          138
     121: aload_0
     122: invokevirtual #32                 // Method akka$stream$impl$fusing$GroupBy$$anon$SubstreamSource$$$outer:()Lakka/stream/impl/fusing/GroupBy$$anon$1;
     125: aload_0
     126: invokevirtual #32                 // Method akka$stream$impl$fusing$GroupBy$$anon$SubstreamSource$$$outer:()Lakka/stream/impl/fusing/GroupBy$$anon$1;
     129: invokevirtual #78                 // Method akka/stream/impl/fusing/GroupBy$$anon$1.akka$stream$impl$fusing$GroupBy$$anon$$$outer:()Lakka/stream/impl/fusing/GroupBy;
     132: invokevirtual #84                 // Method akka/stream/impl/fusing/GroupBy.in:()Lakka/stream/Inlet;
     135: invokevirtual #139                // Method akka/stream/impl/fusing/GroupBy$$anon$1.pull:(Lakka/stream/Inlet;)V
     138: aload_0
     139: invokespecial #141                // Method tryCompleteHandler:()V
     142: return

  public void onDownstreamFinish();
    Code:
       0: aload_0
       1: invokevirtual #32                 // Method akka$stream$impl$fusing$GroupBy$$anon$SubstreamSource$$$outer:()Lakka/stream/impl/fusing/GroupBy$$anon$1;
       4: invokevirtual #37                 // Method akka/stream/impl/fusing/GroupBy$$anon$1.akka$stream$impl$fusing$GroupBy$$anon$$hasNextElement:()Z
       7: ifeq          34
      10: aload_0
      11: invokevirtual #32                 // Method akka$stream$impl$fusing$GroupBy$$anon$SubstreamSource$$$outer:()Lakka/stream/impl/fusing/GroupBy$$anon$1;
      14: invokevirtual #40                 // Method akka/stream/impl/fusing/GroupBy$$anon$1.akka$stream$impl$fusing$GroupBy$$anon$$nextElementKey:()Ljava/lang/Object;
      17: aload_0
      18: invokevirtual #42                 // Method key:()Ljava/lang/Object;
      21: invokestatic  #48                 // Method scala/runtime/BoxesRunTime.equals:(Ljava/lang/Object;Ljava/lang/Object;)Z
      24: ifeq          34
      27: aload_0
      28: invokevirtual #32                 // Method akka$stream$impl$fusing$GroupBy$$anon$SubstreamSource$$$outer:()Lakka/stream/impl/fusing/GroupBy$$anon$1;
      31: invokevirtual #132                // Method akka/stream/impl/fusing/GroupBy$$anon$1.akka$stream$impl$fusing$GroupBy$$anon$$clearNextElement:()V
      34: aload_0
      35: invokevirtual #101                // Method firstPush:()Z
      38: ifeq          57
      41: aload_0
      42: invokevirtual #32                 // Method akka$stream$impl$fusing$GroupBy$$anon$SubstreamSource$$$outer:()Lakka/stream/impl/fusing/GroupBy$$anon$1;
      45: aload_0
      46: invokevirtual #32                 // Method akka$stream$impl$fusing$GroupBy$$anon$SubstreamSource$$$outer:()Lakka/stream/impl/fusing/GroupBy$$anon$1;
      49: invokevirtual #105                // Method akka/stream/impl/fusing/GroupBy$$anon$1.akka$stream$impl$fusing$GroupBy$$anon$$firstPushCounter:()I
      52: iconst_1
      53: isub
      54: invokevirtual #109                // Method akka/stream/impl/fusing/GroupBy$$anon$1.akka$stream$impl$fusing$GroupBy$$anon$$firstPushCounter_$eq:(I)V
      57: aload_0
      58: invokespecial #92                 // Method completeSubStream:()V
      61: aload_0
      62: invokevirtual #32                 // Method akka$stream$impl$fusing$GroupBy$$anon$SubstreamSource$$$outer:()Lakka/stream/impl/fusing/GroupBy$$anon$1;
      65: aload_0
      66: invokevirtual #32                 // Method akka$stream$impl$fusing$GroupBy$$anon$SubstreamSource$$$outer:()Lakka/stream/impl/fusing/GroupBy$$anon$1;
      69: invokevirtual #78                 // Method akka/stream/impl/fusing/GroupBy$$anon$1.akka$stream$impl$fusing$GroupBy$$anon$$$outer:()Lakka/stream/impl/fusing/GroupBy;
      72: invokevirtual #84                 // Method akka/stream/impl/fusing/GroupBy.in:()Lakka/stream/Inlet;
      75: invokevirtual #88                 // Method akka/stream/impl/fusing/GroupBy$$anon$1.isClosed:(Lakka/stream/Inlet;)Z
      78: ifeq          92
      81: aload_0
      82: invokevirtual #32                 // Method akka$stream$impl$fusing$GroupBy$$anon$SubstreamSource$$$outer:()Lakka/stream/impl/fusing/GroupBy$$anon$1;
      85: invokevirtual #95                 // Method akka/stream/impl/fusing/GroupBy$$anon$1.akka$stream$impl$fusing$GroupBy$$anon$$tryCompleteAll:()Z
      88: pop
      89: goto          119
      92: aload_0
      93: invokevirtual #32                 // Method akka$stream$impl$fusing$GroupBy$$anon$SubstreamSource$$$outer:()Lakka/stream/impl/fusing/GroupBy$$anon$1;
      96: invokevirtual #135                // Method akka/stream/impl/fusing/GroupBy$$anon$1.akka$stream$impl$fusing$GroupBy$$anon$$needToPull:()Z
      99: ifeq          119
     102: aload_0
     103: invokevirtual #32                 // Method akka$stream$impl$fusing$GroupBy$$anon$SubstreamSource$$$outer:()Lakka/stream/impl/fusing/GroupBy$$anon$1;
     106: aload_0
     107: invokevirtual #32                 // Method akka$stream$impl$fusing$GroupBy$$anon$SubstreamSource$$$outer:()Lakka/stream/impl/fusing/GroupBy$$anon$1;
     110: invokevirtual #78                 // Method akka/stream/impl/fusing/GroupBy$$anon$1.akka$stream$impl$fusing$GroupBy$$anon$$$outer:()Lakka/stream/impl/fusing/GroupBy;
     113: invokevirtual #84                 // Method akka/stream/impl/fusing/GroupBy.in:()Lakka/stream/Inlet;
     116: invokevirtual #139                // Method akka/stream/impl/fusing/GroupBy$$anon$1.pull:(Lakka/stream/Inlet;)V
     119: return

  public akka.stream.impl.fusing.GroupBy$$anon$1 akka$stream$impl$fusing$GroupBy$$anon$SubstreamSource$$$outer();
    Code:
       0: aload_0
       1: getfield      #146                // Field $outer:Lakka/stream/stage/GraphStageLogic;
       4: checkcast     #34                 // class akka/stream/impl/fusing/GroupBy$$anon$1
       7: areturn

  public akka.stream.impl.fusing.GroupBy$$anon$1$SubstreamSource(akka.stream.impl.fusing.GroupBy$$anon$1, java.lang.String, K, T);
    Code:
       0: aload_0
       1: aload_3
       2: putfield      #16                 // Field key:Ljava/lang/Object;
       5: aload_0
       6: aload         4
       8: putfield      #20                 // Field firstElement:Ljava/lang/Object;
      11: aload_0
      12: aload_1
      13: aload_2
      14: invokespecial #151                // Method akka/stream/stage/GraphStageLogic$SubSourceOutlet."<init>":(Lakka/stream/stage/GraphStageLogic;Ljava/lang/String;)V
      17: aload_0
      18: invokestatic  #157                // Method akka/stream/stage/OutHandler$class.$init$:(Lakka/stream/stage/OutHandler;)V
      21: aload_0
      22: aload_0
      23: invokevirtual #160                // Method setHandler:(Lakka/stream/stage/OutHandler;)V
      26: return
}
