Compiled from "Ops.scala"
public final class akka.stream.impl.fusing.Sliding$$anon$18 extends akka.stream.stage.GraphStageLogic implements akka.stream.stage.InHandler,akka.stream.stage.OutHandler {
  private scala.collection.immutable.Vector<T> buf;

  private final akka.stream.impl.fusing.Sliding $outer;

  public void onDownstreamFinish() throws java.lang.Exception;
    Code:
       0: aload_0
       1: invokestatic  #28                 // Method akka/stream/stage/OutHandler$class.onDownstreamFinish:(Lakka/stream/stage/OutHandler;)V
       4: return

  public void onUpstreamFailure(java.lang.Throwable) throws java.lang.Exception;
    Code:
       0: aload_0
       1: aload_1
       2: invokestatic  #37                 // Method akka/stream/stage/InHandler$class.onUpstreamFailure:(Lakka/stream/stage/InHandler;Ljava/lang/Throwable;)V
       5: return

  private scala.collection.immutable.Vector<T> buf();
    Code:
       0: aload_0
       1: getfield      #42                 // Field buf:Lscala/collection/immutable/Vector;
       4: areturn

  private void buf_$eq(scala.collection.immutable.Vector<T>);
    Code:
       0: aload_0
       1: aload_1
       2: putfield      #42                 // Field buf:Lscala/collection/immutable/Vector;
       5: return

  public void onPush();
    Code:
       0: aload_0
       1: aload_0
       2: invokespecial #48                 // Method buf:()Lscala/collection/immutable/Vector;
       5: aload_0
       6: aload_0
       7: getfield      #50                 // Field $outer:Lakka/stream/impl/fusing/Sliding;
      10: invokevirtual #54                 // Method akka/stream/impl/fusing/Sliding.in:()Lakka/stream/Inlet;
      13: invokevirtual #58                 // Method grab:(Lakka/stream/Inlet;)Ljava/lang/Object;
      16: getstatic     #64                 // Field scala/collection/immutable/Vector$.MODULE$:Lscala/collection/immutable/Vector$;
      19: invokevirtual #68                 // Method scala/collection/immutable/Vector$.canBuildFrom:()Lscala/collection/generic/CanBuildFrom;
      22: invokevirtual #74                 // Method scala/collection/immutable/Vector.$colon$plus:(Ljava/lang/Object;Lscala/collection/generic/CanBuildFrom;)Ljava/lang/Object;
      25: checkcast     #70                 // class scala/collection/immutable/Vector
      28: invokespecial #76                 // Method buf_$eq:(Lscala/collection/immutable/Vector;)V
      31: aload_0
      32: invokespecial #48                 // Method buf:()Lscala/collection/immutable/Vector;
      35: invokevirtual #80                 // Method scala/collection/immutable/Vector.size:()I
      38: aload_0
      39: getfield      #50                 // Field $outer:Lakka/stream/impl/fusing/Sliding;
      42: invokevirtual #83                 // Method akka/stream/impl/fusing/Sliding.n:()I
      45: if_icmpge     62
      48: aload_0
      49: aload_0
      50: getfield      #50                 // Field $outer:Lakka/stream/impl/fusing/Sliding;
      53: invokevirtual #54                 // Method akka/stream/impl/fusing/Sliding.in:()Lakka/stream/Inlet;
      56: invokevirtual #87                 // Method pull:(Lakka/stream/Inlet;)V
      59: goto          244
      62: aload_0
      63: invokespecial #48                 // Method buf:()Lscala/collection/immutable/Vector;
      66: invokevirtual #80                 // Method scala/collection/immutable/Vector.size:()I
      69: aload_0
      70: getfield      #50                 // Field $outer:Lakka/stream/impl/fusing/Sliding;
      73: invokevirtual #83                 // Method akka/stream/impl/fusing/Sliding.n:()I
      76: if_icmpne     97
      79: aload_0
      80: aload_0
      81: getfield      #50                 // Field $outer:Lakka/stream/impl/fusing/Sliding;
      84: invokevirtual #91                 // Method akka/stream/impl/fusing/Sliding.out:()Lakka/stream/Outlet;
      87: aload_0
      88: invokespecial #48                 // Method buf:()Lscala/collection/immutable/Vector;
      91: invokevirtual #95                 // Method push:(Lakka/stream/Outlet;Ljava/lang/Object;)V
      94: goto          244
      97: aload_0
      98: getfield      #50                 // Field $outer:Lakka/stream/impl/fusing/Sliding;
     101: invokevirtual #98                 // Method akka/stream/impl/fusing/Sliding.step:()I
     104: aload_0
     105: getfield      #50                 // Field $outer:Lakka/stream/impl/fusing/Sliding;
     108: invokevirtual #83                 // Method akka/stream/impl/fusing/Sliding.n:()I
     111: if_icmpgt     181
     114: aload_0
     115: aload_0
     116: invokespecial #48                 // Method buf:()Lscala/collection/immutable/Vector;
     119: aload_0
     120: getfield      #50                 // Field $outer:Lakka/stream/impl/fusing/Sliding;
     123: invokevirtual #98                 // Method akka/stream/impl/fusing/Sliding.step:()I
     126: invokevirtual #102                // Method scala/collection/immutable/Vector.drop:(I)Lscala/collection/immutable/Vector;
     129: invokespecial #76                 // Method buf_$eq:(Lscala/collection/immutable/Vector;)V
     132: aload_0
     133: invokespecial #48                 // Method buf:()Lscala/collection/immutable/Vector;
     136: invokevirtual #80                 // Method scala/collection/immutable/Vector.size:()I
     139: aload_0
     140: getfield      #50                 // Field $outer:Lakka/stream/impl/fusing/Sliding;
     143: invokevirtual #83                 // Method akka/stream/impl/fusing/Sliding.n:()I
     146: if_icmpne     167
     149: aload_0
     150: aload_0
     151: getfield      #50                 // Field $outer:Lakka/stream/impl/fusing/Sliding;
     154: invokevirtual #91                 // Method akka/stream/impl/fusing/Sliding.out:()Lakka/stream/Outlet;
     157: aload_0
     158: invokespecial #48                 // Method buf:()Lscala/collection/immutable/Vector;
     161: invokevirtual #95                 // Method push:(Lakka/stream/Outlet;Ljava/lang/Object;)V
     164: goto          244
     167: aload_0
     168: aload_0
     169: getfield      #50                 // Field $outer:Lakka/stream/impl/fusing/Sliding;
     172: invokevirtual #54                 // Method akka/stream/impl/fusing/Sliding.in:()Lakka/stream/Inlet;
     175: invokevirtual #87                 // Method pull:(Lakka/stream/Inlet;)V
     178: goto          244
     181: aload_0
     182: getfield      #50                 // Field $outer:Lakka/stream/impl/fusing/Sliding;
     185: invokevirtual #98                 // Method akka/stream/impl/fusing/Sliding.step:()I
     188: aload_0
     189: getfield      #50                 // Field $outer:Lakka/stream/impl/fusing/Sliding;
     192: invokevirtual #83                 // Method akka/stream/impl/fusing/Sliding.n:()I
     195: if_icmple     244
     198: aload_0
     199: invokespecial #48                 // Method buf:()Lscala/collection/immutable/Vector;
     202: invokevirtual #80                 // Method scala/collection/immutable/Vector.size:()I
     205: aload_0
     206: getfield      #50                 // Field $outer:Lakka/stream/impl/fusing/Sliding;
     209: invokevirtual #98                 // Method akka/stream/impl/fusing/Sliding.step:()I
     212: if_icmpne     233
     215: aload_0
     216: aload_0
     217: invokespecial #48                 // Method buf:()Lscala/collection/immutable/Vector;
     220: aload_0
     221: getfield      #50                 // Field $outer:Lakka/stream/impl/fusing/Sliding;
     224: invokevirtual #98                 // Method akka/stream/impl/fusing/Sliding.step:()I
     227: invokevirtual #102                // Method scala/collection/immutable/Vector.drop:(I)Lscala/collection/immutable/Vector;
     230: invokespecial #76                 // Method buf_$eq:(Lscala/collection/immutable/Vector;)V
     233: aload_0
     234: aload_0
     235: getfield      #50                 // Field $outer:Lakka/stream/impl/fusing/Sliding;
     238: invokevirtual #54                 // Method akka/stream/impl/fusing/Sliding.in:()Lakka/stream/Inlet;
     241: invokevirtual #87                 // Method pull:(Lakka/stream/Inlet;)V
     244: return

  public void onPull();
    Code:
       0: aload_0
       1: aload_0
       2: getfield      #50                 // Field $outer:Lakka/stream/impl/fusing/Sliding;
       5: invokevirtual #54                 // Method akka/stream/impl/fusing/Sliding.in:()Lakka/stream/Inlet;
       8: invokevirtual #87                 // Method pull:(Lakka/stream/Inlet;)V
      11: return

  public void onUpstreamFinish();
    Code:
       0: aload_0
       1: invokespecial #48                 // Method buf:()Lscala/collection/immutable/Vector;
       4: invokevirtual #80                 // Method scala/collection/immutable/Vector.size:()I
       7: aload_0
       8: getfield      #50                 // Field $outer:Lakka/stream/impl/fusing/Sliding;
      11: invokevirtual #83                 // Method akka/stream/impl/fusing/Sliding.n:()I
      14: if_icmpge     43
      17: aload_0
      18: invokespecial #48                 // Method buf:()Lscala/collection/immutable/Vector;
      21: invokevirtual #80                 // Method scala/collection/immutable/Vector.size:()I
      24: iconst_0
      25: if_icmple     43
      28: aload_0
      29: aload_0
      30: getfield      #50                 // Field $outer:Lakka/stream/impl/fusing/Sliding;
      33: invokevirtual #91                 // Method akka/stream/impl/fusing/Sliding.out:()Lakka/stream/Outlet;
      36: aload_0
      37: invokespecial #48                 // Method buf:()Lscala/collection/immutable/Vector;
      40: invokevirtual #95                 // Method push:(Lakka/stream/Outlet;Ljava/lang/Object;)V
      43: aload_0
      44: invokevirtual #107                // Method completeStage:()V
      47: return

  public akka.stream.impl.fusing.Sliding$$anon$18(akka.stream.impl.fusing.Sliding<T>);
    Code:
       0: aload_1
       1: ifnonnull     6
       4: aconst_null
       5: athrow
       6: aload_0
       7: aload_1
       8: putfield      #50                 // Field $outer:Lakka/stream/impl/fusing/Sliding;
      11: aload_0
      12: aload_1
      13: invokevirtual #113                // Method akka/stream/impl/fusing/Sliding.shape:()Lakka/stream/FlowShape;
      16: invokespecial #116                // Method akka/stream/stage/GraphStageLogic."<init>":(Lakka/stream/Shape;)V
      19: aload_0
      20: invokestatic  #120                // Method akka/stream/stage/InHandler$class.$init$:(Lakka/stream/stage/InHandler;)V
      23: aload_0
      24: invokestatic  #122                // Method akka/stream/stage/OutHandler$class.$init$:(Lakka/stream/stage/OutHandler;)V
      27: aload_0
      28: getstatic     #127                // Field scala/package$.MODULE$:Lscala/package$;
      31: invokevirtual #131                // Method scala/package$.Vector:()Lscala/collection/immutable/Vector$;
      34: invokevirtual #134                // Method scala/collection/immutable/Vector$.empty:()Lscala/collection/immutable/Vector;
      37: putfield      #42                 // Field buf:Lscala/collection/immutable/Vector;
      40: aload_0
      41: aload_1
      42: invokevirtual #54                 // Method akka/stream/impl/fusing/Sliding.in:()Lakka/stream/Inlet;
      45: aload_1
      46: invokevirtual #91                 // Method akka/stream/impl/fusing/Sliding.out:()Lakka/stream/Outlet;
      49: aload_0
      50: invokevirtual #138                // Method setHandlers:(Lakka/stream/Inlet;Lakka/stream/Outlet;Lakka/stream/stage/InHandler;)V
      53: return
}
