Compiled from "WebFluxAutoConfiguration.java"
public class org.springframework.boot.autoconfigure.web.reactive.WebFluxAutoConfiguration$WelcomePageConfiguration {
  public org.springframework.boot.autoconfigure.web.reactive.WebFluxAutoConfiguration$WelcomePageConfiguration();
    Code:
       0: aload_0
       1: invokespecial #1                  // Method java/lang/Object."<init>":()V
       4: return

  public org.springframework.web.reactive.function.server.support.RouterFunctionMapping welcomePageRouterFunctionMapping(org.springframework.context.ApplicationContext, org.springframework.boot.autoconfigure.web.reactive.WebFluxProperties, org.springframework.boot.autoconfigure.web.ResourceProperties);
    Code:
       0: new           #2                  // class org/springframework/boot/autoconfigure/web/reactive/WelcomePageRouterFunctionFactory
       3: dup
       4: new           #3                  // class org/springframework/boot/autoconfigure/template/TemplateAvailabilityProviders
       7: dup
       8: aload_1
       9: invokespecial #4                  // Method org/springframework/boot/autoconfigure/template/TemplateAvailabilityProviders."<init>":(Lorg/springframework/context/ApplicationContext;)V
      12: aload_1
      13: aload_3
      14: invokevirtual #5                  // Method org/springframework/boot/autoconfigure/web/ResourceProperties.getStaticLocations:()[Ljava/lang/String;
      17: aload_2
      18: invokevirtual #6                  // Method org/springframework/boot/autoconfigure/web/reactive/WebFluxProperties.getStaticPathPattern:()Ljava/lang/String;
      21: invokespecial #7                  // Method org/springframework/boot/autoconfigure/web/reactive/WelcomePageRouterFunctionFactory."<init>":(Lorg/springframework/boot/autoconfigure/template/TemplateAvailabilityProviders;Lorg/springframework/context/ApplicationContext;[Ljava/lang/String;Ljava/lang/String;)V
      24: astore        4
      26: aload         4
      28: invokevirtual #8                  // Method org/springframework/boot/autoconfigure/web/reactive/WelcomePageRouterFunctionFactory.createRouterFunction:()Lorg/springframework/web/reactive/function/server/RouterFunction;
      31: astore        5
      33: aload         5
      35: ifnull        58
      38: new           #9                  // class org/springframework/web/reactive/function/server/support/RouterFunctionMapping
      41: dup
      42: aload         5
      44: invokespecial #10                 // Method org/springframework/web/reactive/function/server/support/RouterFunctionMapping."<init>":(Lorg/springframework/web/reactive/function/server/RouterFunction;)V
      47: astore        6
      49: aload         6
      51: iconst_1
      52: invokevirtual #11                 // Method org/springframework/web/reactive/function/server/support/RouterFunctionMapping.setOrder:(I)V
      55: aload         6
      57: areturn
      58: aconst_null
      59: areturn
}
