Compiled from "AnimationItem.java"
class org.eclipse.ui.internal.progress.AnimationItem$2 implements org.eclipse.swt.events.MouseListener {
  final org.eclipse.ui.internal.progress.AnimationItem this$0;

  org.eclipse.ui.internal.progress.AnimationItem$2(org.eclipse.ui.internal.progress.AnimationItem);
    Code:
       0: aload_0
       1: aload_1
       2: putfield      #37                 // Field this$0:Lorg/eclipse/ui/internal/progress/AnimationItem;
       5: aload_0
       6: invokespecial #38                 // Method java/lang/Object."<init>":()V
       9: return

  public void mouseDoubleClick(org.eclipse.swt.events.MouseEvent);
    Code:
       0: aload_0
       1: getfield      #37                 // Field this$0:Lorg/eclipse/ui/internal/progress/AnimationItem;
       4: getfield      #36                 // Field org/eclipse/ui/internal/progress/AnimationItem.window:Lorg/eclipse/ui/IWorkbenchWindow;
       7: invokestatic  #39                 // Method org/eclipse/ui/internal/progress/ProgressManagerUtil.openProgressView:(Lorg/eclipse/ui/IWorkbenchWindow;)V
      10: return

  public void mouseDown(org.eclipse.swt.events.MouseEvent);
    Code:
       0: return

  public void mouseUp(org.eclipse.swt.events.MouseEvent);
    Code:
       0: return
}
