Compiled from "BlockedJobsDialog.java"
class org.eclipse.ui.internal.progress.BlockedJobsDialog$BlockedUIElement extends org.eclipse.ui.internal.progress.JobTreeElement {
  final org.eclipse.ui.internal.progress.BlockedJobsDialog this$0;

  private org.eclipse.ui.internal.progress.BlockedJobsDialog$BlockedUIElement(org.eclipse.ui.internal.progress.BlockedJobsDialog);
    Code:
       0: aload_0
       1: aload_1
       2: putfield      #62                 // Field this$0:Lorg/eclipse/ui/internal/progress/BlockedJobsDialog;
       5: aload_0
       6: invokespecial #67                 // Method org/eclipse/ui/internal/progress/JobTreeElement."<init>":()V
       9: return

  java.lang.Object[] getChildren();
    Code:
       0: getstatic     #63                 // Field org/eclipse/ui/internal/progress/ProgressManagerUtil.EMPTY_OBJECT_ARRAY:[Ljava/lang/Object;
       3: areturn

  java.lang.String getDisplayString();
    Code:
       0: aload_0
       1: getfield      #62                 // Field this$0:Lorg/eclipse/ui/internal/progress/BlockedJobsDialog;
       4: getfield      #60                 // Field org/eclipse/ui/internal/progress/BlockedJobsDialog.blockedTaskName:Ljava/lang/String;
       7: ifnull        23
      10: aload_0
      11: getfield      #62                 // Field this$0:Lorg/eclipse/ui/internal/progress/BlockedJobsDialog;
      14: getfield      #60                 // Field org/eclipse/ui/internal/progress/BlockedJobsDialog.blockedTaskName:Ljava/lang/String;
      17: invokevirtual #65                 // Method java/lang/String.isEmpty:()Z
      20: ifeq          27
      23: getstatic     #64                 // Field org/eclipse/ui/internal/progress/ProgressMessages.BlockedJobsDialog_UserInterfaceTreeElement:Ljava/lang/String;
      26: areturn
      27: aload_0
      28: getfield      #62                 // Field this$0:Lorg/eclipse/ui/internal/progress/BlockedJobsDialog;
      31: getfield      #60                 // Field org/eclipse/ui/internal/progress/BlockedJobsDialog.blockedTaskName:Ljava/lang/String;
      34: areturn

  public org.eclipse.swt.graphics.Image getDisplayImage();
    Code:
       0: ldc           #1                  // String WAITING_JOB
       2: invokestatic  #66                 // Method org/eclipse/jface/resource/JFaceResources.getImage:(Ljava/lang/String;)Lorg/eclipse/swt/graphics/Image;
       5: areturn

  boolean hasChildren();
    Code:
       0: iconst_0
       1: ireturn

  boolean isActive();
    Code:
       0: iconst_1
       1: ireturn

  boolean isJobInfo();
    Code:
       0: iconst_0
       1: ireturn

  public void cancel();
    Code:
       0: aload_0
       1: getfield      #62                 // Field this$0:Lorg/eclipse/ui/internal/progress/BlockedJobsDialog;
       4: getfield      #61                 // Field org/eclipse/ui/internal/progress/BlockedJobsDialog.blockingMonitor:Lorg/eclipse/core/runtime/IProgressMonitor;
       7: iconst_1
       8: invokeinterface #68,  2           // InterfaceMethod org/eclipse/core/runtime/IProgressMonitor.setCanceled:(Z)V
      13: return

  public boolean isCancellable();
    Code:
       0: iconst_1
       1: ireturn
}
