Compiled from "DetailedProgressViewer.java"
public class org.eclipse.ui.internal.progress.DetailedProgressViewer extends org.eclipse.ui.internal.progress.AbstractProgressViewer {
  private int maxDisplayed;

  org.eclipse.swt.widgets.Composite control;

  private org.eclipse.swt.custom.ScrolledComposite scrolled;

  private org.eclipse.swt.widgets.Composite noEntryArea;

  private final java.util.Map<org.eclipse.ui.internal.progress.JobTreeElement, org.eclipse.ui.internal.progress.ProgressInfoItem> jobItemControls;

  static final boolean $assertionsDisabled;

  static {};
    Code:
       0: ldc           #3                  // class org/eclipse/ui/internal/progress/DetailedProgressViewer
       2: invokevirtual #485                // Method java/lang/Class.desiredAssertionStatus:()Z
       5: ifne          12
       8: iconst_1
       9: goto          13
      12: iconst_0
      13: putstatic     #478                // Field $assertionsDisabled:Z
      16: return

  public org.eclipse.ui.internal.progress.DetailedProgressViewer(org.eclipse.swt.widgets.Composite, int);
    Code:
       0: aload_0
       1: invokespecial #536                // Method org/eclipse/ui/internal/progress/AbstractProgressViewer."<init>":()V
       4: aload_0
       5: new           #235                // class java/util/HashMap
       8: dup
       9: invokespecial #493                // Method java/util/HashMap."<init>":()V
      12: putfield      #479                // Field jobItemControls:Ljava/util/Map;
      15: aload_0
      16: new           #244                // class org/eclipse/swt/custom/ScrolledComposite
      19: dup
      20: aload_1
      21: sipush        512
      24: iload_2
      25: ior
      26: invokespecial #504                // Method org/eclipse/swt/custom/ScrolledComposite."<init>":(Lorg/eclipse/swt/widgets/Composite;I)V
      29: putfield      #480                // Field scrolled:Lorg/eclipse/swt/custom/ScrolledComposite;
      32: invokestatic  #495                // Method org/eclipse/jface/resource/JFaceResources.getDefaultFont:()Lorg/eclipse/swt/graphics/Font;
      35: invokevirtual #508                // Method org/eclipse/swt/graphics/Font.getFontData:()[Lorg/eclipse/swt/graphics/FontData;
      38: iconst_0
      39: aaload
      40: invokevirtual #509                // Method org/eclipse/swt/graphics/FontData.getHeight:()I
      43: istore_3
      44: aload_0
      45: getfield      #480                // Field scrolled:Lorg/eclipse/swt/custom/ScrolledComposite;
      48: invokevirtual #507                // Method org/eclipse/swt/custom/ScrolledComposite.getVerticalBar:()Lorg/eclipse/swt/widgets/ScrollBar;
      51: iload_3
      52: iconst_2
      53: imul
      54: invokevirtual #531                // Method org/eclipse/swt/widgets/ScrollBar.setIncrement:(I)V
      57: aload_0
      58: getfield      #480                // Field scrolled:Lorg/eclipse/swt/custom/ScrolledComposite;
      61: iconst_1
      62: invokevirtual #498                // Method org/eclipse/swt/custom/ScrolledComposite.setExpandHorizontal:(Z)V
      65: aload_0
      66: getfield      #480                // Field scrolled:Lorg/eclipse/swt/custom/ScrolledComposite;
      69: iconst_1
      70: invokevirtual #499                // Method org/eclipse/swt/custom/ScrolledComposite.setExpandVertical:(Z)V
      73: aload_0
      74: new           #251                // class org/eclipse/swt/widgets/Composite
      77: dup
      78: aload_0
      79: getfield      #480                // Field scrolled:Lorg/eclipse/swt/custom/ScrolledComposite;
      82: iconst_0
      83: invokespecial #519                // Method org/eclipse/swt/widgets/Composite."<init>":(Lorg/eclipse/swt/widgets/Composite;I)V
      86: putfield      #481                // Field control:Lorg/eclipse/swt/widgets/Composite;
      89: new           #250                // class org/eclipse/swt/layout/GridLayout
      92: dup
      93: invokespecial #511                // Method org/eclipse/swt/layout/GridLayout."<init>":()V
      96: astore        4
      98: aload         4
     100: iconst_0
     101: putfield      #475                // Field org/eclipse/swt/layout/GridLayout.marginHeight:I
     104: aload         4
     106: iconst_0
     107: putfield      #476                // Field org/eclipse/swt/layout/GridLayout.marginWidth:I
     110: aload_0
     111: getfield      #481                // Field control:Lorg/eclipse/swt/widgets/Composite;
     114: aload         4
     116: invokevirtual #522                // Method org/eclipse/swt/widgets/Composite.setLayout:(Lorg/eclipse/swt/widgets/Layout;)V
     119: aload_0
     120: getfield      #481                // Field control:Lorg/eclipse/swt/widgets/Composite;
     123: aload_1
     124: invokevirtual #521                // Method org/eclipse/swt/widgets/Composite.getDisplay:()Lorg/eclipse/swt/widgets/Display;
     127: bipush        25
     129: invokevirtual #526                // Method org/eclipse/swt/widgets/Display.getSystemColor:(I)Lorg/eclipse/swt/graphics/Color;
     132: invokevirtual #516                // Method org/eclipse/swt/widgets/Composite.setBackground:(Lorg/eclipse/swt/graphics/Color;)V
     135: aload_0
     136: getfield      #481                // Field control:Lorg/eclipse/swt/widgets/Composite;
     139: new           #262                // class org/eclipse/ui/internal/progress/DetailedProgressViewer$1
     142: dup
     143: aload_0
     144: invokespecial #559                // Method org/eclipse/ui/internal/progress/DetailedProgressViewer$1."<init>":(Lorg/eclipse/ui/internal/progress/DetailedProgressViewer;)V
     147: invokevirtual #515                // Method org/eclipse/swt/widgets/Composite.addFocusListener:(Lorg/eclipse/swt/events/FocusListener;)V
     150: aload_0
     151: getfield      #481                // Field control:Lorg/eclipse/swt/widgets/Composite;
     154: new           #263                // class org/eclipse/ui/internal/progress/DetailedProgressViewer$2
     157: dup
     158: aload_0
     159: invokespecial #560                // Method org/eclipse/ui/internal/progress/DetailedProgressViewer$2."<init>":(Lorg/eclipse/ui/internal/progress/DetailedProgressViewer;)V
     162: invokevirtual #514                // Method org/eclipse/swt/widgets/Composite.addControlListener:(Lorg/eclipse/swt/events/ControlListener;)V
     165: invokestatic  #533                // Method org/eclipse/ui/PlatformUI.getWorkbench:()Lorg/eclipse/ui/IWorkbench;
     168: invokeinterface #591,  1          // InterfaceMethod org/eclipse/ui/IWorkbench.getHelpSystem:()Lorg/eclipse/ui/help/IWorkbenchHelpSystem;
     173: aload_0
     174: getfield      #481                // Field control:Lorg/eclipse/swt/widgets/Composite;
     177: ldc           #2                  // String org.eclipse.ui.responsive_ui_context
     179: invokeinterface #592,  3          // InterfaceMethod org/eclipse/ui/help/IWorkbenchHelpSystem.setHelp:(Lorg/eclipse/swt/widgets/Control;Ljava/lang/String;)V
     184: aload_0
     185: getfield      #480                // Field scrolled:Lorg/eclipse/swt/custom/ScrolledComposite;
     188: aload_0
     189: getfield      #481                // Field control:Lorg/eclipse/swt/widgets/Composite;
     192: invokevirtual #506                // Method org/eclipse/swt/custom/ScrolledComposite.setContent:(Lorg/eclipse/swt/widgets/Control;)V
     195: aload_0
     196: aload_0
     197: getfield      #481                // Field control:Lorg/eclipse/swt/widgets/Composite;
     200: invokevirtual #550                // Method hookControl:(Lorg/eclipse/swt/widgets/Control;)V
     203: aload_0
     204: new           #251                // class org/eclipse/swt/widgets/Composite
     207: dup
     208: aload_0
     209: getfield      #480                // Field scrolled:Lorg/eclipse/swt/custom/ScrolledComposite;
     212: iconst_0
     213: invokespecial #519                // Method org/eclipse/swt/widgets/Composite."<init>":(Lorg/eclipse/swt/widgets/Composite;I)V
     216: putfield      #482                // Field noEntryArea:Lorg/eclipse/swt/widgets/Composite;
     219: aload_0
     220: getfield      #482                // Field noEntryArea:Lorg/eclipse/swt/widgets/Composite;
     223: new           #250                // class org/eclipse/swt/layout/GridLayout
     226: dup
     227: invokespecial #511                // Method org/eclipse/swt/layout/GridLayout."<init>":()V
     230: invokevirtual #522                // Method org/eclipse/swt/widgets/Composite.setLayout:(Lorg/eclipse/swt/widgets/Layout;)V
     233: aload_0
     234: getfield      #482                // Field noEntryArea:Lorg/eclipse/swt/widgets/Composite;
     237: aload_0
     238: getfield      #482                // Field noEntryArea:Lorg/eclipse/swt/widgets/Composite;
     241: invokevirtual #521                // Method org/eclipse/swt/widgets/Composite.getDisplay:()Lorg/eclipse/swt/widgets/Display;
     244: bipush        25
     246: invokevirtual #526                // Method org/eclipse/swt/widgets/Display.getSystemColor:(I)Lorg/eclipse/swt/graphics/Color;
     249: invokevirtual #516                // Method org/eclipse/swt/widgets/Composite.setBackground:(Lorg/eclipse/swt/graphics/Color;)V
     252: new           #254                // class org/eclipse/swt/widgets/Label
     255: dup
     256: aload_0
     257: getfield      #482                // Field noEntryArea:Lorg/eclipse/swt/widgets/Composite;
     260: iconst_0
     261: invokespecial #530                // Method org/eclipse/swt/widgets/Label."<init>":(Lorg/eclipse/swt/widgets/Composite;I)V
     264: astore        5
     266: aload         5
     268: getstatic     #483                // Field org/eclipse/ui/internal/progress/ProgressMessages.ProgressView_NoOperations:Ljava/lang/String;
     271: invokevirtual #528                // Method org/eclipse/swt/widgets/Label.setText:(Ljava/lang/String;)V
     274: aload         5
     276: aload_0
     277: getfield      #482                // Field noEntryArea:Lorg/eclipse/swt/widgets/Composite;
     280: invokevirtual #521                // Method org/eclipse/swt/widgets/Composite.getDisplay:()Lorg/eclipse/swt/widgets/Display;
     283: bipush        25
     285: invokevirtual #526                // Method org/eclipse/swt/widgets/Display.getSystemColor:(I)Lorg/eclipse/swt/graphics/Color;
     288: invokevirtual #529                // Method org/eclipse/swt/widgets/Label.setBackground:(Lorg/eclipse/swt/graphics/Color;)V
     291: new           #249                // class org/eclipse/swt/layout/GridData
     294: dup
     295: iconst_2
     296: invokespecial #510                // Method org/eclipse/swt/layout/GridData."<init>":(I)V
     299: astore        6
     301: aload         5
     303: aload         6
     305: invokevirtual #527                // Method org/eclipse/swt/widgets/Label.setLayoutData:(Ljava/lang/Object;)V
     308: invokestatic  #533                // Method org/eclipse/ui/PlatformUI.getWorkbench:()Lorg/eclipse/ui/IWorkbench;
     311: invokeinterface #591,  1          // InterfaceMethod org/eclipse/ui/IWorkbench.getHelpSystem:()Lorg/eclipse/ui/help/IWorkbenchHelpSystem;
     316: aload         5
     318: ldc           #2                  // String org.eclipse.ui.responsive_ui_context
     320: invokeinterface #592,  3          // InterfaceMethod org/eclipse/ui/help/IWorkbenchHelpSystem.setHelp:(Lorg/eclipse/swt/widgets/Control;Ljava/lang/String;)V
     325: invokestatic  #535                // Method org/eclipse/ui/internal/WorkbenchPlugin.getDefault:()Lorg/eclipse/ui/internal/WorkbenchPlugin;
     328: invokevirtual #534                // Method org/eclipse/ui/internal/WorkbenchPlugin.getPreferenceStore:()Lorg/eclipse/jface/preference/IPreferenceStore;
     331: astore        7
     333: aload_0
     334: aload         7
     336: invokevirtual #547                // Method updateMaxDisplayedValue:(Lorg/eclipse/jface/preference/IPreferenceStore;)V
     339: aload_0
     340: invokedynamic #598,  0            // InvokeDynamic #0:propertyChange:(Lorg/eclipse/ui/internal/progress/DetailedProgressViewer;)Lorg/eclipse/jface/util/IPropertyChangeListener;
     345: astore        8
     347: aload         7
     349: aload         8
     351: invokeinterface #589,  2          // InterfaceMethod org/eclipse/jface/preference/IPreferenceStore.addPropertyChangeListener:(Lorg/eclipse/jface/util/IPropertyChangeListener;)V
     356: aload_0
     357: getfield      #480                // Field scrolled:Lorg/eclipse/swt/custom/ScrolledComposite;
     360: aload         7
     362: aload         8
     364: invokedynamic #599,  0            // InvokeDynamic #1:widgetDisposed:(Lorg/eclipse/jface/preference/IPreferenceStore;Lorg/eclipse/jface/util/IPropertyChangeListener;)Lorg/eclipse/swt/events/DisposeListener;
     369: invokevirtual #500                // Method org/eclipse/swt/custom/ScrolledComposite.addDisposeListener:(Lorg/eclipse/swt/events/DisposeListener;)V
     372: return

  public void propertyChange(org.eclipse.jface.util.PropertyChangeEvent);
    Code:
       0: ldc           #1                  // String MAX_PROGRESS_ENTRIES
       2: aload_1
       3: invokevirtual #496                // Method org/eclipse/jface/util/PropertyChangeEvent.getProperty:()Ljava/lang/String;
       6: invokevirtual #489                // Method java/lang/String.equals:(Ljava/lang/Object;)Z
       9: ifne          13
      12: return
      13: aload_0
      14: invokestatic  #535                // Method org/eclipse/ui/internal/WorkbenchPlugin.getDefault:()Lorg/eclipse/ui/internal/WorkbenchPlugin;
      17: invokevirtual #534                // Method org/eclipse/ui/internal/WorkbenchPlugin.getPreferenceStore:()Lorg/eclipse/jface/preference/IPreferenceStore;
      20: invokevirtual #547                // Method updateMaxDisplayedValue:(Lorg/eclipse/jface/preference/IPreferenceStore;)V
      23: return

  private void updateMaxDisplayedValue(org.eclipse.jface.preference.IPreferenceStore);
    Code:
       0: iconst_1
       1: aload_1
       2: ldc           #1                  // String MAX_PROGRESS_ENTRIES
       4: invokeinterface #588,  2          // InterfaceMethod org/eclipse/jface/preference/IPreferenceStore.getInt:(Ljava/lang/String;)I
       9: invokestatic  #486                // Method java/lang/Math.max:(II)I
      12: istore_2
      13: aload_0
      14: iload_2
      15: invokevirtual #543                // Method setMaxDisplayed:(I)V
      18: return

  public void add(org.eclipse.ui.internal.progress.JobTreeElement...);
    Code:
       0: aload_0
       1: invokevirtual #549                // Method getComparator:()Lorg/eclipse/jface/viewers/ViewerComparator;
       4: astore_2
       5: new           #237                // class java/util/LinkedHashSet
       8: dup
       9: aload_0
      10: getfield      #479                // Field jobItemControls:Ljava/util/Map;
      13: invokeinterface #582,  1          // InterfaceMethod java/util/Map.keySet:()Ljava/util/Set;
      18: invokespecial #494                // Method java/util/LinkedHashSet."<init>":(Ljava/util/Collection;)V
      21: astore_3
      22: aload_1
      23: dup
      24: astore        7
      26: arraylength
      27: istore        6
      29: iconst_0
      30: istore        5
      32: goto          59
      35: aload         7
      37: iload         5
      39: aaload
      40: astore        4
      42: aload         4
      44: ifnull        56
      47: aload_3
      48: aload         4
      50: invokeinterface #586,  2          // InterfaceMethod java/util/Set.add:(Ljava/lang/Object;)Z
      55: pop
      56: iinc          5, 1
      59: iload         5
      61: iload         6
      63: if_icmplt     35
      66: aload_3
      67: iconst_0
      68: anewarray     #267                // class org/eclipse/ui/internal/progress/JobTreeElement
      71: invokeinterface #587,  2          // InterfaceMethod java/util/Set.toArray:([Ljava/lang/Object;)[Ljava/lang/Object;
      76: checkcast     #223                // class "[Lorg/eclipse/ui/internal/progress/JobTreeElement;"
      79: astore        4
      81: aload_2
      82: ifnull        92
      85: aload_2
      86: aload_0
      87: aload         4
      89: invokevirtual #497                // Method org/eclipse/jface/viewers/ViewerComparator.sort:(Lorg/eclipse/jface/viewers/Viewer;[Ljava/lang/Object;)V
      92: aload_0
      93: aload         4
      95: invokevirtual #546                // Method reorderControls:([Ljava/lang/Object;)V
      98: aload_0
      99: invokevirtual #540                // Method updateForShowingProgress:()V
     102: return

  private void updateForShowingProgress();
    Code:
       0: aload_0
       1: getfield      #479                // Field jobItemControls:Ljava/util/Map;
       4: invokeinterface #579,  1          // InterfaceMethod java/util/Map.size:()I
       9: ifle          24
      12: aload_0
      13: invokevirtual #541                // Method updateSize:()V
      16: aload_0
      17: getfield      #481                // Field control:Lorg/eclipse/swt/widgets/Composite;
      20: astore_1
      21: goto          37
      24: aload_0
      25: getfield      #480                // Field scrolled:Lorg/eclipse/swt/custom/ScrolledComposite;
      28: aconst_null
      29: invokevirtual #502                // Method org/eclipse/swt/custom/ScrolledComposite.setMinSize:(Lorg/eclipse/swt/graphics/Point;)V
      32: aload_0
      33: getfield      #482                // Field noEntryArea:Lorg/eclipse/swt/widgets/Composite;
      36: astore_1
      37: aload_0
      38: getfield      #480                // Field scrolled:Lorg/eclipse/swt/custom/ScrolledComposite;
      41: invokevirtual #505                // Method org/eclipse/swt/custom/ScrolledComposite.getContent:()Lorg/eclipse/swt/widgets/Control;
      44: aload_1
      45: if_acmpeq     56
      48: aload_0
      49: getfield      #480                // Field scrolled:Lorg/eclipse/swt/custom/ScrolledComposite;
      52: aload_1
      53: invokevirtual #506                // Method org/eclipse/swt/custom/ScrolledComposite.setContent:(Lorg/eclipse/swt/widgets/Control;)V
      56: aload_0
      57: getfield      #481                // Field control:Lorg/eclipse/swt/widgets/Composite;
      60: invokevirtual #512                // Method org/eclipse/swt/widgets/Composite.requestLayout:()V
      63: return

  private org.eclipse.ui.internal.progress.ProgressInfoItem createNewItem(org.eclipse.ui.internal.progress.JobTreeElement);
    Code:
       0: new           #268                // class org/eclipse/ui/internal/progress/ProgressInfoItem
       3: dup
       4: aload_0
       5: getfield      #481                // Field control:Lorg/eclipse/swt/widgets/Composite;
       8: iconst_0
       9: aload_1
      10: invokespecial #575                // Method org/eclipse/ui/internal/progress/ProgressInfoItem."<init>":(Lorg/eclipse/swt/widgets/Composite;ILorg/eclipse/ui/internal/progress/JobTreeElement;)V
      13: astore_2
      14: aload_2
      15: new           #264                // class org/eclipse/ui/internal/progress/DetailedProgressViewer$3
      18: dup
      19: aload_0
      20: aload_2
      21: invokespecial #561                // Method org/eclipse/ui/internal/progress/DetailedProgressViewer$3."<init>":(Lorg/eclipse/ui/internal/progress/DetailedProgressViewer;Lorg/eclipse/ui/internal/progress/ProgressInfoItem;)V
      24: invokevirtual #571                // Method org/eclipse/ui/internal/progress/ProgressInfoItem.addControlListener:(Lorg/eclipse/swt/events/ControlListener;)V
      27: aload_2
      28: new           #265                // class org/eclipse/ui/internal/progress/DetailedProgressViewer$4
      31: dup
      32: aload_0
      33: aload_2
      34: invokespecial #562                // Method org/eclipse/ui/internal/progress/DetailedProgressViewer$4."<init>":(Lorg/eclipse/ui/internal/progress/DetailedProgressViewer;Lorg/eclipse/ui/internal/progress/ProgressInfoItem;)V
      37: invokevirtual #574                // Method org/eclipse/ui/internal/progress/ProgressInfoItem.setIndexListener:(Lorg/eclipse/ui/internal/progress/ProgressInfoItem$IndexListener;)V
      40: aload_2
      41: areturn

  protected void selectPrevious(org.eclipse.ui.internal.progress.ProgressInfoItem);
    Code:
       0: aload_0
       1: getfield      #481                // Field control:Lorg/eclipse/swt/widgets/Composite;
       4: invokevirtual #520                // Method org/eclipse/swt/widgets/Composite.getChildren:()[Lorg/eclipse/swt/widgets/Control;
       7: astore_2
       8: iconst_0
       9: istore_3
      10: goto          73
      13: aload_2
      14: iload_3
      15: aaload
      16: checkcast     #268                // class org/eclipse/ui/internal/progress/ProgressInfoItem
      19: astore        4
      21: aload_1
      22: aload         4
      24: invokevirtual #488                // Method java/lang/Object.equals:(Ljava/lang/Object;)Z
      27: ifeq          70
      30: iload_3
      31: ifne          48
      34: aload_2
      35: aload_2
      36: arraylength
      37: iconst_1
      38: isub
      39: aaload
      40: checkcast     #268                // class org/eclipse/ui/internal/progress/ProgressInfoItem
      43: astore        5
      45: goto          58
      48: aload_2
      49: iload_3
      50: iconst_1
      51: isub
      52: aaload
      53: checkcast     #268                // class org/eclipse/ui/internal/progress/ProgressInfoItem
      56: astore        5
      58: aload_1
      59: iconst_0
      60: invokevirtual #570                // Method org/eclipse/ui/internal/progress/ProgressInfoItem.selectWidgets:(Z)V
      63: aload         5
      65: iconst_1
      66: invokevirtual #570                // Method org/eclipse/ui/internal/progress/ProgressInfoItem.selectWidgets:(Z)V
      69: return
      70: iinc          3, 1
      73: iload_3
      74: aload_2
      75: arraylength
      76: if_icmplt     13
      79: return

  protected void selectNext(org.eclipse.ui.internal.progress.ProgressInfoItem);
    Code:
       0: aload_0
       1: getfield      #481                // Field control:Lorg/eclipse/swt/widgets/Composite;
       4: invokevirtual #520                // Method org/eclipse/swt/widgets/Composite.getChildren:()[Lorg/eclipse/swt/widgets/Control;
       7: astore_2
       8: iconst_0
       9: istore_3
      10: goto          74
      13: aload_2
      14: iload_3
      15: aaload
      16: checkcast     #268                // class org/eclipse/ui/internal/progress/ProgressInfoItem
      19: astore        4
      21: aload_1
      22: aload         4
      24: invokevirtual #488                // Method java/lang/Object.equals:(Ljava/lang/Object;)Z
      27: ifeq          71
      30: iload_3
      31: aload_2
      32: arraylength
      33: iconst_1
      34: isub
      35: if_icmpne     49
      38: aload_2
      39: iconst_0
      40: aaload
      41: checkcast     #268                // class org/eclipse/ui/internal/progress/ProgressInfoItem
      44: astore        5
      46: goto          59
      49: aload_2
      50: iload_3
      51: iconst_1
      52: iadd
      53: aaload
      54: checkcast     #268                // class org/eclipse/ui/internal/progress/ProgressInfoItem
      57: astore        5
      59: aload_1
      60: iconst_0
      61: invokevirtual #570                // Method org/eclipse/ui/internal/progress/ProgressInfoItem.selectWidgets:(Z)V
      64: aload         5
      66: iconst_1
      67: invokevirtual #570                // Method org/eclipse/ui/internal/progress/ProgressInfoItem.selectWidgets:(Z)V
      70: return
      71: iinc          3, 1
      74: iload_3
      75: aload_2
      76: arraylength
      77: if_icmplt     13
      80: return

  protected org.eclipse.swt.widgets.Widget doFindInputItem(java.lang.Object);
    Code:
       0: aconst_null
       1: areturn

  protected org.eclipse.swt.widgets.Widget doFindItem(java.lang.Object);
    Code:
       0: aload_1
       1: instanceof    #267                // class org/eclipse/ui/internal/progress/JobTreeElement
       4: ifeq          21
       7: aload_0
       8: getfield      #479                // Field jobItemControls:Ljava/util/Map;
      11: aload_1
      12: invokeinterface #583,  2          // InterfaceMethod java/util/Map.get:(Ljava/lang/Object;)Ljava/lang/Object;
      17: checkcast     #256                // class org/eclipse/swt/widgets/Widget
      20: areturn
      21: aload_0
      22: getfield      #481                // Field control:Lorg/eclipse/swt/widgets/Composite;
      25: invokevirtual #520                // Method org/eclipse/swt/widgets/Composite.getChildren:()[Lorg/eclipse/swt/widgets/Control;
      28: dup
      29: astore        5
      31: arraylength
      32: istore        4
      34: iconst_0
      35: istore_3
      36: goto          77
      39: aload         5
      41: iload_3
      42: aaload
      43: astore_2
      44: aload_2
      45: invokevirtual #524                // Method org/eclipse/swt/widgets/Control.isDisposed:()Z
      48: ifne          74
      51: aload_2
      52: invokevirtual #525                // Method org/eclipse/swt/widgets/Control.getData:()Ljava/lang/Object;
      55: ifnonnull     61
      58: goto          74
      61: aload_2
      62: invokevirtual #525                // Method org/eclipse/swt/widgets/Control.getData:()Ljava/lang/Object;
      65: aload_1
      66: invokevirtual #488                // Method java/lang/Object.equals:(Ljava/lang/Object;)Z
      69: ifeq          74
      72: aload_2
      73: areturn
      74: iinc          3, 1
      77: iload_3
      78: iload         4
      80: if_icmplt     39
      83: aconst_null
      84: areturn

  protected void doUpdateItem(org.eclipse.swt.widgets.Widget, java.lang.Object, boolean);
    Code:
       0: aload_0
       1: invokevirtual #542                // Method usingElementMap:()Z
       4: ifeq          12
       7: aload_0
       8: aload_1
       9: invokevirtual #545                // Method unmapElement:(Ljava/lang/Object;)V
      12: aload_1
      13: invokevirtual #532                // Method org/eclipse/swt/widgets/Widget.dispose:()V
      16: aload_0
      17: iconst_1
      18: anewarray     #267                // class org/eclipse/ui/internal/progress/JobTreeElement
      21: dup
      22: iconst_0
      23: aload_2
      24: checkcast     #267                // class org/eclipse/ui/internal/progress/JobTreeElement
      27: aastore
      28: invokevirtual #552                // Method add:([Lorg/eclipse/ui/internal/progress/JobTreeElement;)V
      31: return

  public org.eclipse.swt.widgets.Control getControl();
    Code:
       0: aload_0
       1: getfield      #480                // Field scrolled:Lorg/eclipse/swt/custom/ScrolledComposite;
       4: areturn

  protected java.util.List getSelectionFromWidget();
    Code:
       0: new           #233                // class java/util/ArrayList
       3: dup
       4: iconst_0
       5: invokespecial #492                // Method java/util/ArrayList."<init>":(I)V
       8: areturn

  protected void inputChanged(java.lang.Object, java.lang.Object);
    Code:
       0: aload_0
       1: aload_1
       2: aload_2
       3: invokespecial #537                // Method org/eclipse/ui/internal/progress/AbstractProgressViewer.inputChanged:(Ljava/lang/Object;Ljava/lang/Object;)V
       6: aload_0
       7: invokevirtual #539                // Method refreshAll:()V
      10: return

  protected void internalRefresh(java.lang.Object);
    Code:
       0: aload_1
       1: ifnonnull     5
       4: return
       5: aload_1
       6: aload_0
       7: invokevirtual #544                // Method getRoot:()Ljava/lang/Object;
      10: invokevirtual #488                // Method java/lang/Object.equals:(Ljava/lang/Object;)Z
      13: ifeq          21
      16: aload_0
      17: invokevirtual #539                // Method refreshAll:()V
      20: return
      21: aload_0
      22: aload_1
      23: invokevirtual #556                // Method findItem:(Ljava/lang/Object;)Lorg/eclipse/swt/widgets/Widget;
      26: astore_2
      27: aload_2
      28: ifnonnull     47
      31: aload_0
      32: iconst_1
      33: anewarray     #267                // class org/eclipse/ui/internal/progress/JobTreeElement
      36: dup
      37: iconst_0
      38: aload_1
      39: checkcast     #267                // class org/eclipse/ui/internal/progress/JobTreeElement
      42: aastore
      43: invokevirtual #552                // Method add:([Lorg/eclipse/ui/internal/progress/JobTreeElement;)V
      46: return
      47: aload_2
      48: checkcast     #268                // class org/eclipse/ui/internal/progress/ProgressInfoItem
      51: invokevirtual #566                // Method org/eclipse/ui/internal/progress/ProgressInfoItem.refresh:()V
      54: aload_0
      55: invokevirtual #541                // Method updateSize:()V
      58: return

  public void remove(org.eclipse.ui.internal.progress.JobTreeElement...);
    Code:
       0: aload_1
       1: dup
       2: astore        5
       4: arraylength
       5: istore        4
       7: iconst_0
       8: istore_3
       9: goto          130
      12: aload         5
      14: iload_3
      15: aaload
      16: astore_2
      17: aload_2
      18: checkcast     #267                // class org/eclipse/ui/internal/progress/JobTreeElement
      21: astore        6
      23: invokestatic  #563                // Method org/eclipse/ui/internal/progress/FinishedJobs.getInstance:()Lorg/eclipse/ui/internal/progress/FinishedJobs;
      26: aload         6
      28: invokevirtual #564                // Method org/eclipse/ui/internal/progress/FinishedJobs.isKept:(Lorg/eclipse/ui/internal/progress/JobTreeElement;)Z
      31: ifeq          57
      34: aload_0
      35: aload_2
      36: invokevirtual #555                // Method doFindItem:(Ljava/lang/Object;)Lorg/eclipse/swt/widgets/Widget;
      39: astore        7
      41: aload         7
      43: ifnull        127
      46: aload         7
      48: checkcast     #268                // class org/eclipse/ui/internal/progress/ProgressInfoItem
      51: invokevirtual #566                // Method org/eclipse/ui/internal/progress/ProgressInfoItem.refresh:()V
      54: goto          127
      57: aload_0
      58: aload         6
      60: invokevirtual #555                // Method doFindItem:(Ljava/lang/Object;)Lorg/eclipse/swt/widgets/Widget;
      63: astore        7
      65: aload         7
      67: ifnonnull     101
      70: aload         6
      72: invokevirtual #565                // Method org/eclipse/ui/internal/progress/JobTreeElement.getParent:()Lorg/eclipse/ui/internal/progress/JobTreeElement;
      75: astore        8
      77: aload         8
      79: ifnull        101
      82: aload         8
      84: aload_2
      85: if_acmpeq     101
      88: aload_0
      89: iconst_1
      90: anewarray     #267                // class org/eclipse/ui/internal/progress/JobTreeElement
      93: dup
      94: iconst_0
      95: aload         8
      97: aastore
      98: invokevirtual #553                // Method remove:([Lorg/eclipse/ui/internal/progress/JobTreeElement;)V
     101: aload         7
     103: ifnull        127
     106: aload_0
     107: getfield      #479                // Field jobItemControls:Ljava/util/Map;
     110: aload_2
     111: invokeinterface #584,  2          // InterfaceMethod java/util/Map.remove:(Ljava/lang/Object;)Ljava/lang/Object;
     116: pop
     117: aload_0
     118: aload_2
     119: invokevirtual #545                // Method unmapElement:(Ljava/lang/Object;)V
     122: aload         7
     124: invokevirtual #532                // Method org/eclipse/swt/widgets/Widget.dispose:()V
     127: iinc          3, 1
     130: iload_3
     131: iload         4
     133: if_icmplt     12
     136: aload_0
     137: getfield      #481                // Field control:Lorg/eclipse/swt/widgets/Composite;
     140: invokevirtual #520                // Method org/eclipse/swt/widgets/Composite.getChildren:()[Lorg/eclipse/swt/widgets/Control;
     143: astore_2
     144: iconst_0
     145: istore_3
     146: goto          166
     149: aload_2
     150: iload_3
     151: aaload
     152: checkcast     #268                // class org/eclipse/ui/internal/progress/ProgressInfoItem
     155: astore        4
     157: aload         4
     159: iload_3
     160: invokevirtual #568                // Method org/eclipse/ui/internal/progress/ProgressInfoItem.setColor:(I)V
     163: iinc          3, 1
     166: iload_3
     167: aload_2
     168: arraylength
     169: if_icmplt     149
     172: aload_0
     173: invokevirtual #540                // Method updateForShowingProgress:()V
     176: return

  public void reveal(java.lang.Object);
    Code:
       0: return

  protected void setSelectionToWidget(java.util.List, boolean);
    Code:
       0: return

  public void cancelSelection();
    Code:
       0: return

  public void setFocus();
    Code:
       0: aload_0
       1: getfield      #481                // Field control:Lorg/eclipse/swt/widgets/Composite;
       4: invokevirtual #520                // Method org/eclipse/swt/widgets/Composite.getChildren:()[Lorg/eclipse/swt/widgets/Control;
       7: astore_1
       8: aload_1
       9: arraylength
      10: ifle          25
      13: aload_1
      14: iconst_0
      15: aaload
      16: checkcast     #268                // class org/eclipse/ui/internal/progress/ProgressInfoItem
      19: invokevirtual #567                // Method org/eclipse/ui/internal/progress/ProgressInfoItem.setButtonFocus:()V
      22: goto          33
      25: aload_0
      26: getfield      #482                // Field noEntryArea:Lorg/eclipse/swt/widgets/Composite;
      29: invokevirtual #513                // Method org/eclipse/swt/widgets/Composite.setFocus:()Z
      32: pop
      33: return

  private void refreshAll();
    Code:
       0: aload_0
       1: aload_0
       2: invokevirtual #544                // Method getRoot:()Ljava/lang/Object;
       5: invokevirtual #554                // Method getSortedChildren:(Ljava/lang/Object;)[Ljava/lang/Object;
       8: astore_1
       9: aload_0
      10: aload_1
      11: invokevirtual #546                // Method reorderControls:([Ljava/lang/Object;)V
      14: aload_0
      15: invokevirtual #540                // Method updateForShowingProgress:()V
      18: return

  private void reorderControls(java.lang.Object[]);
    Code:
       0: aload_1
       1: arraylength
       2: aload_0
       3: invokevirtual #538                // Method getMaxDisplayed:()I
       6: invokestatic  #487                // Method java/lang/Math.min:(II)I
       9: istore_2
      10: iload_2
      11: ifne          68
      14: aload_0
      15: getfield      #479                // Field jobItemControls:Ljava/util/Map;
      18: invokeinterface #581,  1          // InterfaceMethod java/util/Map.values:()Ljava/util/Collection;
      23: invokeinterface #576,  1          // InterfaceMethod java/util/Collection.iterator:()Ljava/util/Iterator;
      28: astore        4
      30: goto          48
      33: aload         4
      35: invokeinterface #578,  1          // InterfaceMethod java/util/Iterator.next:()Ljava/lang/Object;
      40: checkcast     #252                // class org/eclipse/swt/widgets/Control
      43: astore_3
      44: aload_3
      45: invokevirtual #523                // Method org/eclipse/swt/widgets/Control.dispose:()V
      48: aload         4
      50: invokeinterface #577,  1          // InterfaceMethod java/util/Iterator.hasNext:()Z
      55: ifne          33
      58: aload_0
      59: getfield      #479                // Field jobItemControls:Ljava/util/Map;
      62: invokeinterface #580,  1          // InterfaceMethod java/util/Map.clear:()V
      67: return
      68: aload_0
      69: getfield      #481                // Field control:Lorg/eclipse/swt/widgets/Composite;
      72: invokevirtual #520                // Method org/eclipse/swt/widgets/Composite.getChildren:()[Lorg/eclipse/swt/widgets/Control;
      75: astore_3
      76: aconst_null
      77: astore        4
      79: iconst_0
      80: istore        5
      82: iconst_0
      83: istore        6
      85: goto          294
      88: aload_1
      89: iload         6
      91: aaload
      92: checkcast     #267                // class org/eclipse/ui/internal/progress/JobTreeElement
      95: astore        7
      97: aload_0
      98: getfield      #479                // Field jobItemControls:Ljava/util/Map;
     101: aload         7
     103: invokeinterface #583,  2          // InterfaceMethod java/util/Map.get:(Ljava/lang/Object;)Ljava/lang/Object;
     108: checkcast     #268                // class org/eclipse/ui/internal/progress/ProgressInfoItem
     111: astore        8
     113: aload         8
     115: ifnonnull     194
     118: aload_0
     119: aload         7
     121: invokevirtual #557                // Method createNewItem:(Lorg/eclipse/ui/internal/progress/JobTreeElement;)Lorg/eclipse/ui/internal/progress/ProgressInfoItem;
     124: astore        8
     126: aload_0
     127: getfield      #479                // Field jobItemControls:Ljava/util/Map;
     130: aload         7
     132: aload         8
     134: invokeinterface #585,  3          // InterfaceMethod java/util/Map.put:(Ljava/lang/Object;Ljava/lang/Object;)Ljava/lang/Object;
     139: pop
     140: iload         5
     142: aload_3
     143: arraylength
     144: if_icmpge     280
     147: aload         4
     149: ifnonnull     161
     152: aload         8
     154: aconst_null
     155: invokevirtual #572                // Method org/eclipse/ui/internal/progress/ProgressInfoItem.moveAbove:(Lorg/eclipse/swt/widgets/Control;)V
     158: goto          280
     161: aload         8
     163: aload         4
     165: invokevirtual #573                // Method org/eclipse/ui/internal/progress/ProgressInfoItem.moveBelow:(Lorg/eclipse/swt/widgets/Control;)V
     168: goto          280
     171: aload_3
     172: iload         5
     174: aaload
     175: ifnull        191
     178: aload_3
     179: iload         5
     181: aaload
     182: invokevirtual #524                // Method org/eclipse/swt/widgets/Control.isDisposed:()Z
     185: ifne          191
     188: goto          201
     191: iinc          5, 1
     194: iload         5
     196: aload_3
     197: arraylength
     198: if_icmplt     171
     201: iload         5
     203: aload_3
     204: arraylength
     205: if_icmpge     277
     208: aload_3
     209: iload         5
     211: aaload
     212: aload         8
     214: if_acmpeq     277
     217: aload         4
     219: ifnonnull     231
     222: aload         8
     224: aconst_null
     225: invokevirtual #572                // Method org/eclipse/ui/internal/progress/ProgressInfoItem.moveAbove:(Lorg/eclipse/swt/widgets/Control;)V
     228: goto          238
     231: aload         8
     233: aload         4
     235: invokevirtual #573                // Method org/eclipse/ui/internal/progress/ProgressInfoItem.moveBelow:(Lorg/eclipse/swt/widgets/Control;)V
     238: iload         5
     240: iconst_1
     241: iadd
     242: istore        9
     244: goto          267
     247: aload_3
     248: iload         9
     250: aaload
     251: aload         8
     253: if_acmpne     264
     256: aload_3
     257: iload         9
     259: aconst_null
     260: aastore
     261: goto          280
     264: iinc          9, 1
     267: iload         9
     269: aload_3
     270: arraylength
     271: if_icmplt     247
     274: goto          280
     277: iinc          5, 1
     280: aload         8
     282: iload         6
     284: invokevirtual #568                // Method org/eclipse/ui/internal/progress/ProgressInfoItem.setColor:(I)V
     287: aload         8
     289: astore        4
     291: iinc          6, 1
     294: iload         6
     296: iload_2
     297: if_icmplt     88
     300: iload         5
     302: istore        6
     304: goto          341
     307: aload_3
     308: iload         6
     310: aaload
     311: ifnull        338
     314: aload_0
     315: getfield      #479                // Field jobItemControls:Ljava/util/Map;
     318: aload_3
     319: iload         6
     321: aaload
     322: invokevirtual #525                // Method org/eclipse/swt/widgets/Control.getData:()Ljava/lang/Object;
     325: invokeinterface #584,  2          // InterfaceMethod java/util/Map.remove:(Ljava/lang/Object;)Ljava/lang/Object;
     330: pop
     331: aload_3
     332: iload         6
     334: aaload
     335: invokevirtual #523                // Method org/eclipse/swt/widgets/Control.dispose:()V
     338: iinc          6, 1
     341: iload         6
     343: aload_3
     344: arraylength
     345: if_icmplt     307
     348: return

  private void updateVisibleItems();
    Code:
       0: aload_0
       1: aload_0
       2: getfield      #481                // Field control:Lorg/eclipse/swt/widgets/Composite;
       5: invokevirtual #520                // Method org/eclipse/swt/widgets/Composite.getChildren:()[Lorg/eclipse/swt/widgets/Control;
       8: invokevirtual #551                // Method updateVisibleProgressItems:([Lorg/eclipse/swt/widgets/Control;)V
      11: return

  private void updateVisibleProgressItems(org.eclipse.swt.widgets.Control...);
    Code:
       0: aload_0
       1: getfield      #480                // Field scrolled:Lorg/eclipse/swt/custom/ScrolledComposite;
       4: invokevirtual #501                // Method org/eclipse/swt/custom/ScrolledComposite.getOrigin:()Lorg/eclipse/swt/graphics/Point;
       7: getfield      #473                // Field org/eclipse/swt/graphics/Point.y:I
      10: istore_2
      11: iload_2
      12: aload_0
      13: getfield      #480                // Field scrolled:Lorg/eclipse/swt/custom/ScrolledComposite;
      16: invokevirtual #503                // Method org/eclipse/swt/custom/ScrolledComposite.getParent:()Lorg/eclipse/swt/widgets/Composite;
      19: invokevirtual #518                // Method org/eclipse/swt/widgets/Composite.getBounds:()Lorg/eclipse/swt/graphics/Rectangle;
      22: getfield      #474                // Field org/eclipse/swt/graphics/Rectangle.height:I
      25: iadd
      26: istore_3
      27: aload_1
      28: dup
      29: astore        7
      31: arraylength
      32: istore        6
      34: iconst_0
      35: istore        5
      37: goto          64
      40: aload         7
      42: iload         5
      44: aaload
      45: astore        4
      47: aload         4
      49: checkcast     #268                // class org/eclipse/ui/internal/progress/ProgressInfoItem
      52: astore        8
      54: aload         8
      56: iload_2
      57: iload_3
      58: invokevirtual #569                // Method org/eclipse/ui/internal/progress/ProgressInfoItem.setDisplayed:(II)V
      61: iinc          5, 1
      64: iload         5
      66: iload         6
      68: if_icmplt     40
      71: return

  private void updateSize();
    Code:
       0: aload_0
       1: getfield      #481                // Field control:Lorg/eclipse/swt/widgets/Composite;
       4: iconst_m1
       5: iconst_m1
       6: invokevirtual #517                // Method org/eclipse/swt/widgets/Composite.computeSize:(II)Lorg/eclipse/swt/graphics/Point;
       9: astore_1
      10: aload_1
      11: iconst_0
      12: putfield      #472                // Field org/eclipse/swt/graphics/Point.x:I
      15: aload_1
      16: dup
      17: getfield      #473                // Field org/eclipse/swt/graphics/Point.y:I
      20: iconst_4
      21: iadd
      22: putfield      #473                // Field org/eclipse/swt/graphics/Point.y:I
      25: aload_0
      26: getfield      #480                // Field scrolled:Lorg/eclipse/swt/custom/ScrolledComposite;
      29: aload_1
      30: invokevirtual #502                // Method org/eclipse/swt/custom/ScrolledComposite.setMinSize:(Lorg/eclipse/swt/graphics/Point;)V
      33: return

  public org.eclipse.ui.internal.progress.ProgressInfoItem[] getProgressInfoItems();
    Code:
       0: aload_0
       1: getfield      #481                // Field control:Lorg/eclipse/swt/widgets/Composite;
       4: invokevirtual #520                // Method org/eclipse/swt/widgets/Composite.getChildren:()[Lorg/eclipse/swt/widgets/Control;
       7: astore_1
       8: aload_1
       9: arraylength
      10: anewarray     #268                // class org/eclipse/ui/internal/progress/ProgressInfoItem
      13: astore_2
      14: aload_1
      15: iconst_0
      16: aload_2
      17: iconst_0
      18: aload_1
      19: arraylength
      20: invokestatic  #490                // Method java/lang/System.arraycopy:(Ljava/lang/Object;ILjava/lang/Object;II)V
      23: getstatic     #478                // Field $assertionsDisabled:Z
      26: ifne          51
      29: aload_1
      30: arraylength
      31: aload_0
      32: getfield      #479                // Field jobItemControls:Ljava/util/Map;
      35: invokeinterface #579,  1          // InterfaceMethod java/util/Map.size:()I
      40: if_icmpeq     51
      43: new           #225                // class java/lang/AssertionError
      46: dup
      47: invokespecial #484                // Method java/lang/AssertionError."<init>":()V
      50: athrow
      51: aload_2
      52: areturn

  public int getMaxDisplayed();
    Code:
       0: aload_0
       1: getfield      #477                // Field maxDisplayed:I
       4: ireturn

  public void setMaxDisplayed(int);
    Code:
       0: aload_0
       1: iload_1
       2: putfield      #477                // Field maxDisplayed:I
       5: return

  private static void lambda$1(org.eclipse.jface.preference.IPreferenceStore, org.eclipse.jface.util.IPropertyChangeListener, org.eclipse.swt.events.DisposeEvent);
    Code:
       0: aload_0
       1: aload_1
       2: invokeinterface #590,  2          // InterfaceMethod org/eclipse/jface/preference/IPreferenceStore.removePropertyChangeListener:(Lorg/eclipse/jface/util/IPropertyChangeListener;)V
       7: return
}
