Compiled from "ProgressManagerUtil.java"
class org.eclipse.ui.internal.progress.ProgressManagerUtil$ProgressViewerComparator extends org.eclipse.jface.viewers.ViewerComparator {
  org.eclipse.ui.internal.progress.ProgressManagerUtil$ProgressViewerComparator();
    Code:
       0: aload_0
       1: invokespecial #56                 // Method org/eclipse/jface/viewers/ViewerComparator."<init>":()V
       4: return

  public int compare(org.eclipse.jface.viewers.Viewer, java.lang.Object, java.lang.Object);
    Code:
       0: aload_2
       1: checkcast     #28                 // class java/lang/Comparable
       4: aload_3
       5: invokeinterface #60,  2           // InterfaceMethod java/lang/Comparable.compareTo:(Ljava/lang/Object;)I
      10: ireturn

  public void sort(org.eclipse.jface.viewers.Viewer, java.lang.Object[]);
    Code:
       0: iconst_3
       1: istore_3
       2: goto          21
       5: aload_2
       6: aload_0
       7: aload_1
       8: invokedynamic #64,  0             // InvokeDynamic #0:compare:(Lorg/eclipse/ui/internal/progress/ProgressManagerUtil$ProgressViewerComparator;Lorg/eclipse/jface/viewers/Viewer;)Ljava/util/Comparator;
      13: invokestatic  #55                 // Method java/util/Arrays.sort:([Ljava/lang/Object;Ljava/util/Comparator;)V
      16: return
      17: pop
      18: iinc          3, -1
      21: iload_3
      22: ifgt          5
      25: aload_0
      26: aload_1
      27: aload_2
      28: invokespecial #57                 // Method org/eclipse/jface/viewers/ViewerComparator.sort:(Lorg/eclipse/jface/viewers/Viewer;[Ljava/lang/Object;)V
      31: return
    Exception table:
       from    to  target type
           5    16    17   Class java/lang/IllegalArgumentException

  private int lambda$0(org.eclipse.jface.viewers.Viewer, java.lang.Object, java.lang.Object);
    Code:
       0: aload_0
       1: aload_1
       2: aload_2
       3: aload_3
       4: invokevirtual #58                 // Method compare:(Lorg/eclipse/jface/viewers/Viewer;Ljava/lang/Object;Ljava/lang/Object;)I
       7: ireturn
}
