Compiled from "ProgressMonitorFocusJobDialog.java"
class org.eclipse.ui.internal.progress.ProgressMonitorFocusJobDialog$1 extends org.eclipse.core.runtime.jobs.JobChangeAdapter {
  final org.eclipse.ui.internal.progress.ProgressMonitorFocusJobDialog this$0;

  org.eclipse.ui.internal.progress.ProgressMonitorFocusJobDialog$1(org.eclipse.ui.internal.progress.ProgressMonitorFocusJobDialog);
    Code:
       0: aload_0
       1: aload_1
       2: putfield      #75                 // Field this$0:Lorg/eclipse/ui/internal/progress/ProgressMonitorFocusJobDialog;
       5: aload_0
       6: invokespecial #78                 // Method org/eclipse/core/runtime/jobs/JobChangeAdapter."<init>":()V
       9: return

  public void done(org.eclipse.core.runtime.jobs.IJobChangeEvent);
    Code:
       0: aload_1
       1: invokeinterface #86,  1           // InterfaceMethod org/eclipse/core/runtime/jobs/IJobChangeEvent.getJob:()Lorg/eclipse/core/runtime/jobs/Job;
       6: aload_0
       7: invokevirtual #77                 // Method org/eclipse/core/runtime/jobs/Job.removeJobChangeListener:(Lorg/eclipse/core/runtime/jobs/IJobChangeListener;)V
      10: invokestatic  #81                 // Method org/eclipse/ui/PlatformUI.isWorkbenchRunning:()Z
      13: ifne          17
      16: return
      17: aload_0
      18: getfield      #75                 // Field this$0:Lorg/eclipse/ui/internal/progress/ProgressMonitorFocusJobDialog;
      21: invokevirtual #83                 // Method org/eclipse/ui/internal/progress/ProgressMonitorFocusJobDialog.getShell:()Lorg/eclipse/swt/widgets/Shell;
      24: ifnonnull     28
      27: return
      28: invokestatic  #82                 // Method org/eclipse/ui/PlatformUI.getWorkbench:()Lorg/eclipse/ui/IWorkbench;
      31: invokeinterface #87,  1           // InterfaceMethod org/eclipse/ui/IWorkbench.getDisplay:()Lorg/eclipse/swt/widgets/Display;
      36: aload_0
      37: invokedynamic #91,  0             // InvokeDynamic #0:run:(Lorg/eclipse/ui/internal/progress/ProgressMonitorFocusJobDialog$1;)Ljava/lang/Runnable;
      42: invokevirtual #79                 // Method org/eclipse/swt/widgets/Display.asyncExec:(Ljava/lang/Runnable;)V
      45: return

  private void lambda$0();
    Code:
       0: aload_0
       1: getfield      #75                 // Field this$0:Lorg/eclipse/ui/internal/progress/ProgressMonitorFocusJobDialog;
       4: invokevirtual #83                 // Method org/eclipse/ui/internal/progress/ProgressMonitorFocusJobDialog.getShell:()Lorg/eclipse/swt/widgets/Shell;
       7: astore_1
       8: aload_1
       9: ifnull        19
      12: aload_1
      13: invokevirtual #80                 // Method org/eclipse/swt/widgets/Shell.isDisposed:()Z
      16: ifeq          20
      19: return
      20: aload_0
      21: getfield      #75                 // Field this$0:Lorg/eclipse/ui/internal/progress/ProgressMonitorFocusJobDialog;
      24: invokestatic  #84                 // Method org/eclipse/ui/internal/progress/ProgressMonitorFocusJobDialog.access$0:(Lorg/eclipse/ui/internal/progress/ProgressMonitorFocusJobDialog;)V
      27: return
}
