Compiled from "ProgressManager.java"
class org.eclipse.ui.internal.progress.ProgressManager$RunnableWithStatus$1 extends org.eclipse.ui.internal.dialogs.EventLoopProgressMonitor {
  final org.eclipse.ui.internal.progress.ProgressManager$RunnableWithStatus this$1;

  org.eclipse.ui.internal.progress.ProgressManager$RunnableWithStatus$1(org.eclipse.ui.internal.progress.ProgressManager$RunnableWithStatus, org.eclipse.core.runtime.IProgressMonitor);
    Code:
       0: aload_0
       1: aload_1
       2: putfield      #46                 // Field this$1:Lorg/eclipse/ui/internal/progress/ProgressManager$RunnableWithStatus;
       5: aload_0
       6: aload_2
       7: invokespecial #48                 // Method org/eclipse/ui/internal/dialogs/EventLoopProgressMonitor."<init>":(Lorg/eclipse/core/runtime/IProgressMonitor;)V
      10: return

  public void setBlocked(org.eclipse.core.runtime.IStatus);
    Code:
       0: invokestatic  #47                 // Method org/eclipse/jface/dialogs/Dialog.getBlockedHandler:()Lorg/eclipse/jface/dialogs/IDialogBlockedHandler;
       3: invokestatic  #50                 // Method org/eclipse/ui/internal/progress/ProgressManagerUtil.getDefaultParent:()Lorg/eclipse/swt/widgets/Shell;
       6: aload_0
       7: aload_1
       8: aload_0
       9: invokevirtual #49                 // Method getTaskName:()Ljava/lang/String;
      12: invokeinterface #51,  5           // InterfaceMethod org/eclipse/jface/dialogs/IDialogBlockedHandler.showBlocked:(Lorg/eclipse/swt/widgets/Shell;Lorg/eclipse/core/runtime/IProgressMonitor;Lorg/eclipse/core/runtime/IStatus;Ljava/lang/String;)V
      17: return
}
