Compiled from "Wrappers.scala"
public class scala.collection.convert.Wrappers$JEnumerationWrapper<A> extends scala.collection.AbstractIterator<A> implements scala.Product, scala.Serializable {
  private final java.util.Enumeration<A> underlying;

  public final scala.collection.convert.Wrappers $outer;

  public java.util.Enumeration<A> underlying();
    Code:
       0: aload_0
       1: getfield      #18                 // Field underlying:Ljava/util/Enumeration;
       4: areturn

  public boolean hasNext();
    Code:
       0: aload_0
       1: invokevirtual #24                 // Method underlying:()Ljava/util/Enumeration;
       4: invokeinterface #29,  1           // InterfaceMethod java/util/Enumeration.hasMoreElements:()Z
       9: ireturn

  public A next();
    Code:
       0: aload_0
       1: invokevirtual #24                 // Method underlying:()Ljava/util/Enumeration;
       4: invokeinterface #34,  1           // InterfaceMethod java/util/Enumeration.nextElement:()Ljava/lang/Object;
       9: areturn

  public <A> scala.collection.convert.Wrappers$JEnumerationWrapper<A> copy(java.util.Enumeration<A>);
    Code:
       0: new           #2                  // class scala/collection/convert/Wrappers$JEnumerationWrapper
       3: dup
       4: aload_0
       5: invokevirtual #40                 // Method scala$collection$convert$Wrappers$JEnumerationWrapper$$$outer:()Lscala/collection/convert/Wrappers;
       8: aload_1
       9: invokespecial #44                 // Method "<init>":(Lscala/collection/convert/Wrappers;Ljava/util/Enumeration;)V
      12: areturn

  public <A> java.util.Enumeration<A> copy$default$1();
    Code:
       0: aload_0
       1: invokevirtual #24                 // Method underlying:()Ljava/util/Enumeration;
       4: areturn

  public java.lang.String productPrefix();
    Code:
       0: ldc           #49                 // String JEnumerationWrapper
       2: areturn

  public int productArity();
    Code:
       0: iconst_1
       1: ireturn

  public java.lang.Object productElement(int);
    Code:
       0: iload_1
       1: tableswitch   { // 0 to 0
                     0: 35
               default: 20
          }
      20: new           #55                 // class java/lang/IndexOutOfBoundsException
      23: dup
      24: iload_1
      25: invokestatic  #61                 // Method scala/runtime/BoxesRunTime.boxToInteger:(I)Ljava/lang/Integer;
      28: invokevirtual #66                 // Method java/lang/Object.toString:()Ljava/lang/String;
      31: invokespecial #69                 // Method java/lang/IndexOutOfBoundsException."<init>":(Ljava/lang/String;)V
      34: athrow
      35: aload_0
      36: invokevirtual #24                 // Method underlying:()Ljava/util/Enumeration;
      39: areturn

  public scala.collection.Iterator<java.lang.Object> productIterator();
    Code:
       0: getstatic     #79                 // Field scala/runtime/ScalaRunTime$.MODULE$:Lscala/runtime/ScalaRunTime$;
       3: aload_0
       4: invokevirtual #83                 // Method scala/runtime/ScalaRunTime$.typedProductIterator:(Lscala/Product;)Lscala/collection/Iterator;
       7: areturn

  public boolean canEqual(java.lang.Object);
    Code:
       0: aload_1
       1: instanceof    #2                  // class scala/collection/convert/Wrappers$JEnumerationWrapper
       4: ireturn

  public int hashCode();
    Code:
       0: getstatic     #79                 // Field scala/runtime/ScalaRunTime$.MODULE$:Lscala/runtime/ScalaRunTime$;
       3: aload_0
       4: invokevirtual #91                 // Method scala/runtime/ScalaRunTime$._hashCode:(Lscala/Product;)I
       7: ireturn

  public boolean equals(java.lang.Object);
    Code:
       0: aload_0
       1: aload_1
       2: if_acmpeq     89
       5: aload_1
       6: instanceof    #2                  // class scala/collection/convert/Wrappers$JEnumerationWrapper
       9: ifeq          31
      12: aload_1
      13: checkcast     #2                  // class scala/collection/convert/Wrappers$JEnumerationWrapper
      16: invokevirtual #40                 // Method scala$collection$convert$Wrappers$JEnumerationWrapper$$$outer:()Lscala/collection/convert/Wrappers;
      19: aload_0
      20: invokevirtual #40                 // Method scala$collection$convert$Wrappers$JEnumerationWrapper$$$outer:()Lscala/collection/convert/Wrappers;
      23: if_acmpne     31
      26: iconst_1
      27: istore_2
      28: goto          33
      31: iconst_0
      32: istore_2
      33: iload_2
      34: ifeq          93
      37: aload_1
      38: checkcast     #2                  // class scala/collection/convert/Wrappers$JEnumerationWrapper
      41: astore        4
      43: aload_0
      44: invokevirtual #24                 // Method underlying:()Ljava/util/Enumeration;
      47: aload         4
      49: invokevirtual #24                 // Method underlying:()Ljava/util/Enumeration;
      52: astore_3
      53: dup
      54: ifnonnull     65
      57: pop
      58: aload_3
      59: ifnull        72
      62: goto          85
      65: aload_3
      66: invokevirtual #94                 // Method java/lang/Object.equals:(Ljava/lang/Object;)Z
      69: ifeq          85
      72: aload         4
      74: aload_0
      75: invokevirtual #96                 // Method canEqual:(Ljava/lang/Object;)Z
      78: ifeq          85
      81: iconst_1
      82: goto          86
      85: iconst_0
      86: ifeq          93
      89: iconst_1
      90: goto          94
      93: iconst_0
      94: ireturn

  public scala.collection.convert.Wrappers scala$collection$convert$Wrappers$JEnumerationWrapper$$$outer();
    Code:
       0: aload_0
       1: getfield      #98                 // Field $outer:Lscala/collection/convert/Wrappers;
       4: areturn

  public scala.collection.convert.Wrappers$JEnumerationWrapper(scala.collection.convert.Wrappers, java.util.Enumeration<A>);
    Code:
       0: aload_0
       1: aload_2
       2: putfield      #18                 // Field underlying:Ljava/util/Enumeration;
       5: aload_1
       6: ifnonnull     11
       9: aconst_null
      10: athrow
      11: aload_0
      12: aload_1
      13: putfield      #98                 // Field $outer:Lscala/collection/convert/Wrappers;
      16: aload_0
      17: invokespecial #101                // Method scala/collection/AbstractIterator."<init>":()V
      20: aload_0
      21: invokestatic  #107                // Method scala/Product$class.$init$:(Lscala/Product;)V
      24: return
}
