Compiled from "Wrappers.scala"
public abstract class scala.collection.convert.Wrappers$IterableWrapperTrait$class {
  public static int size(scala.collection.convert.Wrappers$IterableWrapperTrait);
    Code:
       0: aload_0
       1: invokeinterface #13,  1           // InterfaceMethod scala/collection/convert/Wrappers$IterableWrapperTrait.underlying:()Lscala/collection/Iterable;
       6: invokeinterface #18,  1           // InterfaceMethod scala/collection/Iterable.size:()I
      11: ireturn

  public static scala.collection.convert.Wrappers$IteratorWrapper iterator(scala.collection.convert.Wrappers$IterableWrapperTrait);
    Code:
       0: new           #24                 // class scala/collection/convert/Wrappers$IteratorWrapper
       3: dup
       4: aload_0
       5: invokeinterface #28,  1           // InterfaceMethod scala/collection/convert/Wrappers$IterableWrapperTrait.scala$collection$convert$Wrappers$IterableWrapperTrait$$$outer:()Lscala/collection/convert/Wrappers;
      10: aload_0
      11: invokeinterface #13,  1           // InterfaceMethod scala/collection/convert/Wrappers$IterableWrapperTrait.underlying:()Lscala/collection/Iterable;
      16: invokeinterface #31,  1           // InterfaceMethod scala/collection/Iterable.iterator:()Lscala/collection/Iterator;
      21: invokespecial #35                 // Method scala/collection/convert/Wrappers$IteratorWrapper."<init>":(Lscala/collection/convert/Wrappers;Lscala/collection/Iterator;)V
      24: areturn

  public static boolean isEmpty(scala.collection.convert.Wrappers$IterableWrapperTrait);
    Code:
       0: aload_0
       1: invokeinterface #13,  1           // InterfaceMethod scala/collection/convert/Wrappers$IterableWrapperTrait.underlying:()Lscala/collection/Iterable;
       6: invokeinterface #40,  1           // InterfaceMethod scala/collection/Iterable.isEmpty:()Z
      11: ireturn

  public static void $init$(scala.collection.convert.Wrappers$IterableWrapperTrait);
    Code:
       0: return
}
