Compiled from "Wrappers.scala"
public class scala.collection.convert.Wrappers$JPropertiesWrapper extends scala.collection.mutable.AbstractMap<java.lang.String, java.lang.String> implements scala.Product, scala.Serializable {
  private final java.util.Properties underlying;

  public final scala.collection.convert.Wrappers $outer;

  public java.util.Properties underlying();
    Code:
       0: aload_0
       1: getfield      #17                 // Field underlying:Ljava/util/Properties;
       4: areturn

  public int size();
    Code:
       0: aload_0
       1: invokevirtual #23                 // Method underlying:()Ljava/util/Properties;
       4: invokevirtual #27                 // Method java/util/Properties.size:()I
       7: ireturn

  public scala.Option<java.lang.String> get(java.lang.String);
    Code:
       0: aload_0
       1: invokevirtual #23                 // Method underlying:()Ljava/util/Properties;
       4: aload_1
       5: invokevirtual #32                 // Method java/util/Properties.get:(Ljava/lang/Object;)Ljava/lang/Object;
       8: astore_2
       9: aload_2
      10: ifnonnull     19
      13: getstatic     #38                 // Field scala/None$.MODULE$:Lscala/None$;
      16: goto          30
      19: new           #40                 // class scala/Some
      22: dup
      23: aload_2
      24: checkcast     #42                 // class java/lang/String
      27: invokespecial #46                 // Method scala/Some."<init>":(Ljava/lang/Object;)V
      30: areturn

  public scala.collection.convert.Wrappers$JPropertiesWrapper $plus$eq(scala.Tuple2<java.lang.String, java.lang.String>);
    Code:
       0: aload_0
       1: invokevirtual #23                 // Method underlying:()Ljava/util/Properties;
       4: aload_1
       5: invokevirtual #62                 // Method scala/Tuple2._1:()Ljava/lang/Object;
       8: aload_1
       9: invokevirtual #65                 // Method scala/Tuple2._2:()Ljava/lang/Object;
      12: invokevirtual #69                 // Method java/util/Properties.put:(Ljava/lang/Object;Ljava/lang/Object;)Ljava/lang/Object;
      15: pop
      16: aload_0
      17: areturn

  public scala.collection.convert.Wrappers$JPropertiesWrapper $minus$eq(java.lang.String);
    Code:
       0: aload_0
       1: invokevirtual #23                 // Method underlying:()Ljava/util/Properties;
       4: aload_1
       5: invokevirtual #76                 // Method java/util/Properties.remove:(Ljava/lang/Object;)Ljava/lang/Object;
       8: pop
       9: aload_0
      10: areturn

  public scala.Option<java.lang.String> put(java.lang.String, java.lang.String);
    Code:
       0: aload_0
       1: invokevirtual #23                 // Method underlying:()Ljava/util/Properties;
       4: aload_1
       5: aload_2
       6: invokevirtual #69                 // Method java/util/Properties.put:(Ljava/lang/Object;Ljava/lang/Object;)Ljava/lang/Object;
       9: astore_3
      10: aload_3
      11: ifnonnull     20
      14: getstatic     #38                 // Field scala/None$.MODULE$:Lscala/None$;
      17: goto          31
      20: new           #40                 // class scala/Some
      23: dup
      24: aload_3
      25: checkcast     #42                 // class java/lang/String
      28: invokespecial #46                 // Method scala/Some."<init>":(Ljava/lang/Object;)V
      31: areturn

  public void update(java.lang.String, java.lang.String);
    Code:
       0: aload_0
       1: invokevirtual #23                 // Method underlying:()Ljava/util/Properties;
       4: aload_1
       5: aload_2
       6: invokevirtual #69                 // Method java/util/Properties.put:(Ljava/lang/Object;Ljava/lang/Object;)Ljava/lang/Object;
       9: pop
      10: return

  public scala.Option<java.lang.String> remove(java.lang.String);
    Code:
       0: aload_0
       1: invokevirtual #23                 // Method underlying:()Ljava/util/Properties;
       4: aload_1
       5: invokevirtual #76                 // Method java/util/Properties.remove:(Ljava/lang/Object;)Ljava/lang/Object;
       8: astore_2
       9: aload_2
      10: ifnonnull     19
      13: getstatic     #38                 // Field scala/None$.MODULE$:Lscala/None$;
      16: goto          30
      19: new           #40                 // class scala/Some
      22: dup
      23: aload_2
      24: checkcast     #42                 // class java/lang/String
      27: invokespecial #46                 // Method scala/Some."<init>":(Ljava/lang/Object;)V
      30: areturn

  public scala.collection.Iterator<scala.Tuple2<java.lang.String, java.lang.String>> iterator();
    Code:
       0: new           #85                 // class scala/collection/convert/Wrappers$JPropertiesWrapper$$anon$3
       3: dup
       4: aload_0
       5: invokespecial #88                 // Method scala/collection/convert/Wrappers$JPropertiesWrapper$$anon$3."<init>":(Lscala/collection/convert/Wrappers$JPropertiesWrapper;)V
       8: areturn

  public void clear();
    Code:
       0: aload_0
       1: invokevirtual #23                 // Method underlying:()Ljava/util/Properties;
       4: invokevirtual #92                 // Method java/util/Properties.clear:()V
       7: return

  public scala.collection.convert.Wrappers$JPropertiesWrapper empty();
    Code:
       0: new           #2                  // class scala/collection/convert/Wrappers$JPropertiesWrapper
       3: dup
       4: aload_0
       5: invokevirtual #98                 // Method scala$collection$convert$Wrappers$JPropertiesWrapper$$$outer:()Lscala/collection/convert/Wrappers;
       8: new           #25                 // class java/util/Properties
      11: dup
      12: invokespecial #100                // Method java/util/Properties."<init>":()V
      15: invokespecial #103                // Method "<init>":(Lscala/collection/convert/Wrappers;Ljava/util/Properties;)V
      18: areturn

  public java.lang.String getProperty(java.lang.String);
    Code:
       0: aload_0
       1: invokevirtual #23                 // Method underlying:()Ljava/util/Properties;
       4: aload_1
       5: invokevirtual #107                // Method java/util/Properties.getProperty:(Ljava/lang/String;)Ljava/lang/String;
       8: areturn

  public java.lang.String getProperty(java.lang.String, java.lang.String);
    Code:
       0: aload_0
       1: invokevirtual #23                 // Method underlying:()Ljava/util/Properties;
       4: aload_1
       5: aload_2
       6: invokevirtual #110                // Method java/util/Properties.getProperty:(Ljava/lang/String;Ljava/lang/String;)Ljava/lang/String;
       9: areturn

  public java.lang.Object setProperty(java.lang.String, java.lang.String);
    Code:
       0: aload_0
       1: invokevirtual #23                 // Method underlying:()Ljava/util/Properties;
       4: aload_1
       5: aload_2
       6: invokevirtual #115                // Method java/util/Properties.setProperty:(Ljava/lang/String;Ljava/lang/String;)Ljava/lang/Object;
       9: areturn

  public scala.collection.convert.Wrappers$JPropertiesWrapper copy(java.util.Properties);
    Code:
       0: new           #2                  // class scala/collection/convert/Wrappers$JPropertiesWrapper
       3: dup
       4: aload_0
       5: invokevirtual #98                 // Method scala$collection$convert$Wrappers$JPropertiesWrapper$$$outer:()Lscala/collection/convert/Wrappers;
       8: aload_1
       9: invokespecial #103                // Method "<init>":(Lscala/collection/convert/Wrappers;Ljava/util/Properties;)V
      12: areturn

  public java.util.Properties copy$default$1();
    Code:
       0: aload_0
       1: invokevirtual #23                 // Method underlying:()Ljava/util/Properties;
       4: areturn

  public java.lang.String productPrefix();
    Code:
       0: ldc           #123                // String JPropertiesWrapper
       2: areturn

  public int productArity();
    Code:
       0: iconst_1
       1: ireturn

  public java.lang.Object productElement(int);
    Code:
       0: iload_1
       1: tableswitch   { // 0 to 0
                     0: 35
               default: 20
          }
      20: new           #128                // class java/lang/IndexOutOfBoundsException
      23: dup
      24: iload_1
      25: invokestatic  #134                // Method scala/runtime/BoxesRunTime.boxToInteger:(I)Ljava/lang/Integer;
      28: invokevirtual #137                // Method java/lang/Object.toString:()Ljava/lang/String;
      31: invokespecial #140                // Method java/lang/IndexOutOfBoundsException."<init>":(Ljava/lang/String;)V
      34: athrow
      35: aload_0
      36: invokevirtual #23                 // Method underlying:()Ljava/util/Properties;
      39: areturn

  public scala.collection.Iterator<java.lang.Object> productIterator();
    Code:
       0: getstatic     #148                // Field scala/runtime/ScalaRunTime$.MODULE$:Lscala/runtime/ScalaRunTime$;
       3: aload_0
       4: invokevirtual #152                // Method scala/runtime/ScalaRunTime$.typedProductIterator:(Lscala/Product;)Lscala/collection/Iterator;
       7: areturn

  public scala.collection.convert.Wrappers scala$collection$convert$Wrappers$JPropertiesWrapper$$$outer();
    Code:
       0: aload_0
       1: getfield      #154                // Field $outer:Lscala/collection/convert/Wrappers;
       4: areturn

  public scala.collection.GenTraversable toTraversable();
    Code:
       0: aload_0
       1: invokevirtual #159                // Method toTraversable:()Lscala/collection/Traversable;
       4: areturn

  public scala.collection.GenMap groupBy(scala.Function1);
    Code:
       0: aload_0
       1: aload_1
       2: invokevirtual #164                // Method groupBy:(Lscala/Function1;)Lscala/collection/immutable/Map;
       5: areturn

  public scala.collection.generic.Subtractable repr();
    Code:
       0: aload_0
       1: invokevirtual #170                // Method repr:()Ljava/lang/Object;
       4: checkcast     #172                // class scala/collection/generic/Subtractable
       7: areturn

  public scala.collection.TraversableView view(int, int);
    Code:
       0: aload_0
       1: iload_1
       2: iload_2
       3: invokevirtual #177                // Method view:(II)Lscala/collection/IterableView;
       6: areturn

  public scala.collection.TraversableView view();
    Code:
       0: aload_0
       1: invokevirtual #183                // Method view:()Lscala/collection/IterableView;
       4: areturn

  public scala.collection.GenIterable toIterable();
    Code:
       0: aload_0
       1: invokevirtual #188                // Method toIterable:()Lscala/collection/Iterable;
       4: areturn

  public scala.collection.Traversable toCollection(java.lang.Object);
    Code:
       0: aload_0
       1: aload_1
       2: invokevirtual #193                // Method toCollection:(Ljava/lang/Object;)Lscala/collection/Iterable;
       5: areturn

  public scala.collection.Traversable thisCollection();
    Code:
       0: aload_0
       1: invokevirtual #196                // Method thisCollection:()Lscala/collection/Iterable;
       4: areturn

  public scala.collection.GenSeq toSeq();
    Code:
       0: aload_0
       1: invokevirtual #201                // Method toSeq:()Lscala/collection/Seq;
       4: areturn

  public java.lang.Object filterNot(scala.Function1);
    Code:
       0: aload_0
       1: aload_1
       2: invokevirtual #206                // Method filterNot:(Lscala/Function1;)Lscala/collection/Map;
       5: areturn

  public scala.collection.GenMap mapValues(scala.Function1);
    Code:
       0: aload_0
       1: aload_1
       2: invokevirtual #210                // Method mapValues:(Lscala/Function1;)Lscala/collection/Map;
       5: areturn

  public scala.collection.GenMap filterKeys(scala.Function1);
    Code:
       0: aload_0
       1: aload_1
       2: invokevirtual #213                // Method filterKeys:(Lscala/Function1;)Lscala/collection/Map;
       5: areturn

  public scala.collection.GenIterable values();
    Code:
       0: aload_0
       1: invokevirtual #216                // Method values:()Lscala/collection/Iterable;
       4: areturn

  public scala.collection.GenIterable keys();
    Code:
       0: aload_0
       1: invokevirtual #219                // Method keys:()Lscala/collection/Iterable;
       4: areturn

  public scala.collection.GenSet keySet();
    Code:
       0: aload_0
       1: invokevirtual #224                // Method keySet:()Lscala/collection/Set;
       4: areturn

  public scala.collection.generic.Subtractable $minus$minus(scala.collection.GenTraversableOnce);
    Code:
       0: aload_0
       1: aload_1
       2: invokevirtual #229                // Method $minus$minus:(Lscala/collection/GenTraversableOnce;)Lscala/collection/mutable/Map;
       5: areturn

  public scala.collection.generic.Subtractable $minus(java.lang.Object, java.lang.Object, scala.collection.Seq);
    Code:
       0: aload_0
       1: aload_1
       2: aload_2
       3: aload_3
       4: invokevirtual #236                // Method $minus:(Ljava/lang/Object;Ljava/lang/Object;Lscala/collection/Seq;)Lscala/collection/mutable/Map;
       7: areturn

  public java.lang.Object result();
    Code:
       0: aload_0
       1: invokevirtual #244                // Method result:()Lscala/collection/mutable/Map;
       4: areturn

  public java.lang.Object clone();
    Code:
       0: aload_0
       1: invokevirtual #247                // Method clone:()Lscala/collection/mutable/Map;
       4: areturn

  public java.lang.Object $minus(java.lang.Object);
    Code:
       0: aload_0
       1: aload_1
       2: invokevirtual #250                // Method $minus:(Ljava/lang/Object;)Lscala/collection/mutable/Map;
       5: areturn

  public scala.collection.generic.Subtractable $minus(java.lang.Object);
    Code:
       0: aload_0
       1: aload_1
       2: invokevirtual #250                // Method $minus:(Ljava/lang/Object;)Lscala/collection/mutable/Map;
       5: areturn

  public scala.collection.Map $minus(java.lang.Object);
    Code:
       0: aload_0
       1: aload_1
       2: invokevirtual #250                // Method $minus:(Ljava/lang/Object;)Lscala/collection/mutable/Map;
       5: areturn

  public scala.collection.Map $plus$plus(scala.collection.GenTraversableOnce);
    Code:
       0: aload_0
       1: aload_1
       2: invokevirtual #257                // Method $plus$plus:(Lscala/collection/GenTraversableOnce;)Lscala/collection/mutable/Map;
       5: areturn

  public scala.collection.Map $plus(scala.Tuple2, scala.Tuple2, scala.collection.Seq);
    Code:
       0: aload_0
       1: aload_1
       2: aload_2
       3: aload_3
       4: invokevirtual #262                // Method $plus:(Lscala/Tuple2;Lscala/Tuple2;Lscala/collection/Seq;)Lscala/collection/mutable/Map;
       7: areturn

  public scala.collection.GenMap $plus(scala.Tuple2);
    Code:
       0: aload_0
       1: aload_1
       2: invokevirtual #269                // Method $plus:(Lscala/Tuple2;)Lscala/collection/mutable/Map;
       5: areturn

  public scala.collection.Map $plus(scala.Tuple2);
    Code:
       0: aload_0
       1: aload_1
       2: invokevirtual #269                // Method $plus:(Lscala/Tuple2;)Lscala/collection/mutable/Map;
       5: areturn

  public scala.collection.GenMap updated(java.lang.Object, java.lang.Object);
    Code:
       0: aload_0
       1: aload_1
       2: aload_2
       3: invokevirtual #275                // Method updated:(Ljava/lang/Object;Ljava/lang/Object;)Lscala/collection/mutable/Map;
       6: areturn

  public scala.collection.Map updated(java.lang.Object, java.lang.Object);
    Code:
       0: aload_0
       1: aload_1
       2: aload_2
       3: invokevirtual #275                // Method updated:(Ljava/lang/Object;Ljava/lang/Object;)Lscala/collection/mutable/Map;
       6: areturn

  public scala.collection.Map seq();
    Code:
       0: aload_0
       1: invokevirtual #280                // Method seq:()Lscala/collection/mutable/Map;
       4: areturn

  public scala.collection.Map empty();
    Code:
       0: aload_0
       1: invokevirtual #282                // Method empty:()Lscala/collection/convert/Wrappers$JPropertiesWrapper;
       4: areturn

  public scala.collection.mutable.Map empty();
    Code:
       0: aload_0
       1: invokevirtual #282                // Method empty:()Lscala/collection/convert/Wrappers$JPropertiesWrapper;
       4: areturn

  public scala.Option remove(java.lang.Object);
    Code:
       0: aload_0
       1: aload_1
       2: checkcast     #42                 // class java/lang/String
       5: invokevirtual #285                // Method remove:(Ljava/lang/String;)Lscala/Option;
       8: areturn

  public void update(java.lang.Object, java.lang.Object);
    Code:
       0: aload_0
       1: aload_1
       2: checkcast     #42                 // class java/lang/String
       5: aload_2
       6: checkcast     #42                 // class java/lang/String
       9: invokevirtual #288                // Method update:(Ljava/lang/String;Ljava/lang/String;)V
      12: return

  public scala.Option put(java.lang.Object, java.lang.Object);
    Code:
       0: aload_0
       1: aload_1
       2: checkcast     #42                 // class java/lang/String
       5: aload_2
       6: checkcast     #42                 // class java/lang/String
       9: invokevirtual #291                // Method put:(Ljava/lang/String;Ljava/lang/String;)Lscala/Option;
      12: areturn

  public scala.collection.generic.Shrinkable $minus$eq(java.lang.Object);
    Code:
       0: aload_0
       1: aload_1
       2: checkcast     #42                 // class java/lang/String
       5: invokevirtual #294                // Method $minus$eq:(Ljava/lang/String;)Lscala/collection/convert/Wrappers$JPropertiesWrapper;
       8: areturn

  public scala.collection.mutable.MapLike $minus$eq(java.lang.Object);
    Code:
       0: aload_0
       1: aload_1
       2: checkcast     #42                 // class java/lang/String
       5: invokevirtual #294                // Method $minus$eq:(Ljava/lang/String;)Lscala/collection/convert/Wrappers$JPropertiesWrapper;
       8: areturn

  public scala.collection.generic.Growable $plus$eq(java.lang.Object);
    Code:
       0: aload_0
       1: aload_1
       2: checkcast     #58                 // class scala/Tuple2
       5: invokevirtual #298                // Method $plus$eq:(Lscala/Tuple2;)Lscala/collection/convert/Wrappers$JPropertiesWrapper;
       8: areturn

  public scala.collection.mutable.Builder $plus$eq(java.lang.Object);
    Code:
       0: aload_0
       1: aload_1
       2: checkcast     #58                 // class scala/Tuple2
       5: invokevirtual #298                // Method $plus$eq:(Lscala/Tuple2;)Lscala/collection/convert/Wrappers$JPropertiesWrapper;
       8: areturn

  public scala.collection.mutable.MapLike $plus$eq(scala.Tuple2);
    Code:
       0: aload_0
       1: aload_1
       2: invokevirtual #298                // Method $plus$eq:(Lscala/Tuple2;)Lscala/collection/convert/Wrappers$JPropertiesWrapper;
       5: areturn

  public scala.Option get(java.lang.Object);
    Code:
       0: aload_0
       1: aload_1
       2: checkcast     #42                 // class java/lang/String
       5: invokevirtual #302                // Method get:(Ljava/lang/String;)Lscala/Option;
       8: areturn

  public scala.collection.convert.Wrappers$JPropertiesWrapper(scala.collection.convert.Wrappers, java.util.Properties);
    Code:
       0: aload_0
       1: aload_2
       2: putfield      #17                 // Field underlying:Ljava/util/Properties;
       5: aload_1
       6: ifnonnull     11
       9: aconst_null
      10: athrow
      11: aload_0
      12: aload_1
      13: putfield      #154                // Field $outer:Lscala/collection/convert/Wrappers;
      16: aload_0
      17: invokespecial #303                // Method scala/collection/mutable/AbstractMap."<init>":()V
      20: aload_0
      21: invokestatic  #309                // Method scala/Product$class.$init$:(Lscala/Product;)V
      24: return
}
