Compiled from "Wrappers.scala"
public class scala.collection.convert.Wrappers$MutableBufferWrapper<A> extends java.util.AbstractList<A> implements scala.collection.convert.Wrappers$IterableWrapperTrait<A>, scala.Product, scala.Serializable {
  private final scala.collection.mutable.Buffer<A> underlying;

  public final scala.collection.convert.Wrappers $outer;

  public int size();
    Code:
       0: aload_0
       1: invokestatic  #24                 // Method scala/collection/convert/Wrappers$IterableWrapperTrait$class.size:(Lscala/collection/convert/Wrappers$IterableWrapperTrait;)I
       4: ireturn

  public scala.collection.convert.Wrappers$IteratorWrapper<A> iterator();
    Code:
       0: aload_0
       1: invokestatic  #31                 // Method scala/collection/convert/Wrappers$IterableWrapperTrait$class.iterator:(Lscala/collection/convert/Wrappers$IterableWrapperTrait;)Lscala/collection/convert/Wrappers$IteratorWrapper;
       4: areturn

  public boolean isEmpty();
    Code:
       0: aload_0
       1: invokestatic  #36                 // Method scala/collection/convert/Wrappers$IterableWrapperTrait$class.isEmpty:(Lscala/collection/convert/Wrappers$IterableWrapperTrait;)Z
       4: ireturn

  public scala.collection.mutable.Buffer<A> underlying();
    Code:
       0: aload_0
       1: getfield      #39                 // Field underlying:Lscala/collection/mutable/Buffer;
       4: areturn

  public A get(int);
    Code:
       0: aload_0
       1: invokevirtual #43                 // Method underlying:()Lscala/collection/mutable/Buffer;
       4: iload_1
       5: invokeinterface #48,  2           // InterfaceMethod scala/collection/mutable/Buffer.apply:(I)Ljava/lang/Object;
      10: areturn

  public A set(int, A);
    Code:
       0: aload_0
       1: invokevirtual #43                 // Method underlying:()Lscala/collection/mutable/Buffer;
       4: iload_1
       5: invokeinterface #48,  2           // InterfaceMethod scala/collection/mutable/Buffer.apply:(I)Ljava/lang/Object;
      10: astore_3
      11: aload_0
      12: invokevirtual #43                 // Method underlying:()Lscala/collection/mutable/Buffer;
      15: iload_1
      16: aload_2
      17: invokeinterface #56,  3           // InterfaceMethod scala/collection/mutable/Buffer.update:(ILjava/lang/Object;)V
      22: aload_3
      23: areturn

  public boolean add(A);
    Code:
       0: aload_0
       1: invokevirtual #43                 // Method underlying:()Lscala/collection/mutable/Buffer;
       4: getstatic     #67                 // Field scala/Predef$.MODULE$:Lscala/Predef$;
       7: iconst_1
       8: anewarray     #69                 // class java/lang/Object
      11: dup
      12: iconst_0
      13: aload_1
      14: aastore
      15: invokevirtual #73                 // Method scala/Predef$.genericWrapArray:(Ljava/lang/Object;)Lscala/collection/mutable/WrappedArray;
      18: invokeinterface #77,  2           // InterfaceMethod scala/collection/mutable/Buffer.append:(Lscala/collection/Seq;)V
      23: iconst_1
      24: ireturn

  public A remove(int);
    Code:
       0: aload_0
       1: invokevirtual #43                 // Method underlying:()Lscala/collection/mutable/Buffer;
       4: iload_1
       5: invokeinterface #80,  2           // InterfaceMethod scala/collection/mutable/Buffer.remove:(I)Ljava/lang/Object;
      10: areturn

  public <A> scala.collection.convert.Wrappers$MutableBufferWrapper<A> copy(scala.collection.mutable.Buffer<A>);
    Code:
       0: new           #2                  // class scala/collection/convert/Wrappers$MutableBufferWrapper
       3: dup
       4: aload_0
       5: invokevirtual #86                 // Method scala$collection$convert$Wrappers$MutableBufferWrapper$$$outer:()Lscala/collection/convert/Wrappers;
       8: aload_1
       9: invokespecial #90                 // Method "<init>":(Lscala/collection/convert/Wrappers;Lscala/collection/mutable/Buffer;)V
      12: areturn

  public <A> scala.collection.mutable.Buffer<A> copy$default$1();
    Code:
       0: aload_0
       1: invokevirtual #43                 // Method underlying:()Lscala/collection/mutable/Buffer;
       4: areturn

  public java.lang.String productPrefix();
    Code:
       0: ldc           #95                 // String MutableBufferWrapper
       2: areturn

  public int productArity();
    Code:
       0: iconst_1
       1: ireturn

  public java.lang.Object productElement(int);
    Code:
       0: iload_1
       1: tableswitch   { // 0 to 0
                     0: 35
               default: 20
          }
      20: new           #99                 // class java/lang/IndexOutOfBoundsException
      23: dup
      24: iload_1
      25: invokestatic  #105                // Method scala/runtime/BoxesRunTime.boxToInteger:(I)Ljava/lang/Integer;
      28: invokevirtual #108                // Method java/lang/Object.toString:()Ljava/lang/String;
      31: invokespecial #111                // Method java/lang/IndexOutOfBoundsException."<init>":(Ljava/lang/String;)V
      34: athrow
      35: aload_0
      36: invokevirtual #43                 // Method underlying:()Lscala/collection/mutable/Buffer;
      39: areturn

  public scala.collection.Iterator<java.lang.Object> productIterator();
    Code:
       0: getstatic     #119                // Field scala/runtime/ScalaRunTime$.MODULE$:Lscala/runtime/ScalaRunTime$;
       3: aload_0
       4: invokevirtual #123                // Method scala/runtime/ScalaRunTime$.typedProductIterator:(Lscala/Product;)Lscala/collection/Iterator;
       7: areturn

  public boolean canEqual(java.lang.Object);
    Code:
       0: aload_1
       1: instanceof    #2                  // class scala/collection/convert/Wrappers$MutableBufferWrapper
       4: ireturn

  public scala.collection.convert.Wrappers scala$collection$convert$Wrappers$MutableBufferWrapper$$$outer();
    Code:
       0: aload_0
       1: getfield      #126                // Field $outer:Lscala/collection/convert/Wrappers;
       4: areturn

  public scala.collection.convert.Wrappers scala$collection$convert$Wrappers$IterableWrapperTrait$$$outer();
    Code:
       0: aload_0
       1: invokevirtual #86                 // Method scala$collection$convert$Wrappers$MutableBufferWrapper$$$outer:()Lscala/collection/convert/Wrappers;
       4: areturn

  public java.util.Iterator iterator();
    Code:
       0: aload_0
       1: invokevirtual #130                // Method iterator:()Lscala/collection/convert/Wrappers$IteratorWrapper;
       4: areturn

  public scala.collection.Iterable underlying();
    Code:
       0: aload_0
       1: invokevirtual #43                 // Method underlying:()Lscala/collection/mutable/Buffer;
       4: areturn

  public scala.collection.convert.Wrappers$MutableBufferWrapper(scala.collection.convert.Wrappers, scala.collection.mutable.Buffer<A>);
    Code:
       0: aload_0
       1: aload_2
       2: putfield      #39                 // Field underlying:Lscala/collection/mutable/Buffer;
       5: aload_1
       6: ifnonnull     11
       9: aconst_null
      10: athrow
      11: aload_0
      12: aload_1
      13: putfield      #126                // Field $outer:Lscala/collection/convert/Wrappers;
      16: aload_0
      17: invokespecial #134                // Method java/util/AbstractList."<init>":()V
      20: aload_0
      21: invokestatic  #138                // Method scala/collection/convert/Wrappers$IterableWrapperTrait$class.$init$:(Lscala/collection/convert/Wrappers$IterableWrapperTrait;)V
      24: aload_0
      25: invokestatic  #143                // Method scala/Product$class.$init$:(Lscala/Product;)V
      28: return
}
