Compiled from "JpaComplianceImpl.java"
public class org.hibernate.jpa.internal.JpaComplianceImpl$JpaComplianceBuilder {
  private boolean queryCompliance;

  private boolean transactionCompliance;

  private boolean listCompliance;

  private boolean closedCompliance;

  private boolean proxyCompliance;

  private boolean cachingCompliance;

  private boolean globalGeneratorNameScopeCompliance;

  public org.hibernate.jpa.internal.JpaComplianceImpl$JpaComplianceBuilder();
    Code:
       0: aload_0
       1: invokespecial #1                  // Method java/lang/Object."<init>":()V
       4: return

  public org.hibernate.jpa.internal.JpaComplianceImpl$JpaComplianceBuilder setQueryCompliance(boolean);
    Code:
       0: aload_0
       1: iload_1
       2: putfield      #2                  // Field queryCompliance:Z
       5: aload_0
       6: areturn

  public org.hibernate.jpa.internal.JpaComplianceImpl$JpaComplianceBuilder setTransactionCompliance(boolean);
    Code:
       0: aload_0
       1: iload_1
       2: putfield      #3                  // Field transactionCompliance:Z
       5: aload_0
       6: areturn

  public org.hibernate.jpa.internal.JpaComplianceImpl$JpaComplianceBuilder setListCompliance(boolean);
    Code:
       0: aload_0
       1: iload_1
       2: putfield      #4                  // Field listCompliance:Z
       5: aload_0
       6: areturn

  public org.hibernate.jpa.internal.JpaComplianceImpl$JpaComplianceBuilder setClosedCompliance(boolean);
    Code:
       0: aload_0
       1: iload_1
       2: putfield      #5                  // Field closedCompliance:Z
       5: aload_0
       6: areturn

  public org.hibernate.jpa.internal.JpaComplianceImpl$JpaComplianceBuilder setProxyCompliance(boolean);
    Code:
       0: aload_0
       1: iload_1
       2: putfield      #6                  // Field proxyCompliance:Z
       5: aload_0
       6: areturn

  public org.hibernate.jpa.internal.JpaComplianceImpl$JpaComplianceBuilder setCachingCompliance(boolean);
    Code:
       0: aload_0
       1: iload_1
       2: putfield      #7                  // Field cachingCompliance:Z
       5: aload_0
       6: areturn

  public org.hibernate.jpa.internal.JpaComplianceImpl$JpaComplianceBuilder setGlobalGeneratorNameCompliance(boolean);
    Code:
       0: aload_0
       1: iload_1
       2: putfield      #8                  // Field globalGeneratorNameScopeCompliance:Z
       5: aload_0
       6: areturn

  org.hibernate.jpa.spi.JpaCompliance createJpaCompliance();
    Code:
       0: new           #9                  // class org/hibernate/jpa/internal/JpaComplianceImpl
       3: dup
       4: aload_0
       5: getfield      #2                  // Field queryCompliance:Z
       8: aload_0
       9: getfield      #3                  // Field transactionCompliance:Z
      12: aload_0
      13: getfield      #4                  // Field listCompliance:Z
      16: aload_0
      17: getfield      #5                  // Field closedCompliance:Z
      20: aload_0
      21: getfield      #6                  // Field proxyCompliance:Z
      24: aload_0
      25: getfield      #7                  // Field cachingCompliance:Z
      28: aload_0
      29: getfield      #8                  // Field globalGeneratorNameScopeCompliance:Z
      32: aconst_null
      33: invokespecial #10                 // Method org/hibernate/jpa/internal/JpaComplianceImpl."<init>":(ZZZZZZZLorg/hibernate/jpa/internal/JpaComplianceImpl$1;)V
      36: areturn
}
