Compiled from "BaseException.java"
public class com.amazonaws.services.cloudsearchv2.model.BaseException extends com.amazonaws.AmazonServiceException {
  private static final long serialVersionUID;

  private java.lang.String code;

  public com.amazonaws.services.cloudsearchv2.model.BaseException(java.lang.String);
    Code:
       0: aload_0
       1: aload_1
       2: invokespecial #1                  // Method com/amazonaws/AmazonServiceException."<init>":(Ljava/lang/String;)V
       5: return

  public void setCode(java.lang.String);
    Code:
       0: aload_0
       1: aload_1
       2: putfield      #2                  // Field code:Ljava/lang/String;
       5: return

  public java.lang.String getCode();
    Code:
       0: aload_0
       1: getfield      #2                  // Field code:Ljava/lang/String;
       4: areturn

  public com.amazonaws.services.cloudsearchv2.model.BaseException withCode(java.lang.String);
    Code:
       0: aload_0
       1: aload_1
       2: invokevirtual #3                  // Method setCode:(Ljava/lang/String;)V
       5: aload_0
       6: areturn
}
