Compiled from "ClassloadingUtil.java"
public final class org.hornetq.utils.ClassloadingUtil {
  private static final java.lang.String INSTANTIATION_EXCEPTION_MESSAGE;

  public org.hornetq.utils.ClassloadingUtil();
    Code:
       0: aload_0
       1: invokespecial #1                  // Method java/lang/Object."<init>":()V
       4: return

  public static java.lang.Object newInstanceFromClassLoader(java.lang.String);
    Code:
       0: ldc           #2                  // class org/hornetq/utils/ClassloadingUtil
       2: invokevirtual #3                  // Method java/lang/Class.getClassLoader:()Ljava/lang/ClassLoader;
       5: astore_1
       6: aload_1
       7: aload_0
       8: invokevirtual #4                  // Method java/lang/ClassLoader.loadClass:(Ljava/lang/String;)Ljava/lang/Class;
      11: astore_2
      12: aload_2
      13: invokevirtual #5                  // Method java/lang/Class.newInstance:()Ljava/lang/Object;
      16: areturn
      17: astore_2
      18: aload_2
      19: instanceof    #7                  // class java/lang/InstantiationException
      22: ifeq          33
      25: getstatic     #8                  // Field java/lang/System.out:Ljava/io/PrintStream;
      28: ldc           #9                  // String Your class must have a constructor without arguments. If it is an inner class, it must be static!
      30: invokevirtual #10                 // Method java/io/PrintStream.println:(Ljava/lang/String;)V
      33: invokestatic  #11                 // Method java/lang/Thread.currentThread:()Ljava/lang/Thread;
      36: invokevirtual #12                 // Method java/lang/Thread.getContextClassLoader:()Ljava/lang/ClassLoader;
      39: astore_1
      40: aload_1
      41: ifnonnull     55
      44: new           #13                 // class java/lang/RuntimeException
      47: dup
      48: ldc           #14                 // String No local context classloader
      50: aload_2
      51: invokespecial #15                 // Method java/lang/RuntimeException."<init>":(Ljava/lang/String;Ljava/lang/Throwable;)V
      54: athrow
      55: aload_1
      56: aload_0
      57: invokevirtual #4                  // Method java/lang/ClassLoader.loadClass:(Ljava/lang/String;)Ljava/lang/Class;
      60: invokevirtual #5                  // Method java/lang/Class.newInstance:()Ljava/lang/Object;
      63: areturn
      64: astore_3
      65: new           #13                 // class java/lang/RuntimeException
      68: dup
      69: new           #16                 // class java/lang/StringBuilder
      72: dup
      73: invokespecial #17                 // Method java/lang/StringBuilder."<init>":()V
      76: ldc           #18                 // String Your class must have a constructor without arguments. If it is an inner class, it must be static!
      78: invokevirtual #19                 // Method java/lang/StringBuilder.append:(Ljava/lang/String;)Ljava/lang/StringBuilder;
      81: aload_0
      82: invokevirtual #19                 // Method java/lang/StringBuilder.append:(Ljava/lang/String;)Ljava/lang/StringBuilder;
      85: invokevirtual #20                 // Method java/lang/StringBuilder.toString:()Ljava/lang/String;
      88: aload_3
      89: invokespecial #15                 // Method java/lang/RuntimeException."<init>":(Ljava/lang/String;Ljava/lang/Throwable;)V
      92: athrow
      93: astore_3
      94: new           #22                 // class java/lang/IllegalStateException
      97: dup
      98: aload_3
      99: invokespecial #23                 // Method java/lang/IllegalStateException."<init>":(Ljava/lang/Throwable;)V
     102: athrow
     103: astore_3
     104: new           #13                 // class java/lang/RuntimeException
     107: dup
     108: aload_3
     109: invokespecial #25                 // Method java/lang/RuntimeException."<init>":(Ljava/lang/Throwable;)V
     112: athrow
    Exception table:
       from    to  target type
           6    16    17   Class java/lang/Throwable
          55    63    64   Class java/lang/InstantiationException
          55    63    93   Class java/lang/ClassNotFoundException
          55    63   103   Class java/lang/IllegalAccessException

  public static java.lang.Object newInstanceFromClassLoader(java.lang.String, java.lang.Object...);
    Code:
       0: ldc           #2                  // class org/hornetq/utils/ClassloadingUtil
       2: invokevirtual #3                  // Method java/lang/Class.getClassLoader:()Ljava/lang/ClassLoader;
       5: astore_2
       6: aload_1
       7: arraylength
       8: anewarray     #26                 // class java/lang/Class
      11: astore_3
      12: iconst_0
      13: istore        4
      15: iload         4
      17: aload_1
      18: arraylength
      19: if_icmpge     39
      22: aload_3
      23: iload         4
      25: aload_1
      26: iload         4
      28: aaload
      29: invokevirtual #27                 // Method java/lang/Object.getClass:()Ljava/lang/Class;
      32: aastore
      33: iinc          4, 1
      36: goto          15
      39: aload_2
      40: aload_0
      41: invokevirtual #4                  // Method java/lang/ClassLoader.loadClass:(Ljava/lang/String;)Ljava/lang/Class;
      44: astore        4
      46: aload         4
      48: aload_3
      49: invokevirtual #28                 // Method java/lang/Class.getConstructor:([Ljava/lang/Class;)Ljava/lang/reflect/Constructor;
      52: aload_1
      53: invokevirtual #29                 // Method java/lang/reflect/Constructor.newInstance:([Ljava/lang/Object;)Ljava/lang/Object;
      56: areturn
      57: astore_3
      58: aload_3
      59: instanceof    #7                  // class java/lang/InstantiationException
      62: ifeq          73
      65: getstatic     #8                  // Field java/lang/System.out:Ljava/io/PrintStream;
      68: ldc           #9                  // String Your class must have a constructor without arguments. If it is an inner class, it must be static!
      70: invokevirtual #10                 // Method java/io/PrintStream.println:(Ljava/lang/String;)V
      73: invokestatic  #11                 // Method java/lang/Thread.currentThread:()Ljava/lang/Thread;
      76: invokevirtual #12                 // Method java/lang/Thread.getContextClassLoader:()Ljava/lang/ClassLoader;
      79: astore_2
      80: aload_2
      81: ifnonnull     95
      84: new           #13                 // class java/lang/RuntimeException
      87: dup
      88: ldc           #14                 // String No local context classloader
      90: aload_3
      91: invokespecial #15                 // Method java/lang/RuntimeException."<init>":(Ljava/lang/String;Ljava/lang/Throwable;)V
      94: athrow
      95: aload_2
      96: aload_0
      97: invokevirtual #4                  // Method java/lang/ClassLoader.loadClass:(Ljava/lang/String;)Ljava/lang/Class;
     100: invokevirtual #5                  // Method java/lang/Class.newInstance:()Ljava/lang/Object;
     103: areturn
     104: astore        4
     106: new           #13                 // class java/lang/RuntimeException
     109: dup
     110: new           #16                 // class java/lang/StringBuilder
     113: dup
     114: invokespecial #17                 // Method java/lang/StringBuilder."<init>":()V
     117: ldc           #18                 // String Your class must have a constructor without arguments. If it is an inner class, it must be static!
     119: invokevirtual #19                 // Method java/lang/StringBuilder.append:(Ljava/lang/String;)Ljava/lang/StringBuilder;
     122: aload_0
     123: invokevirtual #19                 // Method java/lang/StringBuilder.append:(Ljava/lang/String;)Ljava/lang/StringBuilder;
     126: invokevirtual #20                 // Method java/lang/StringBuilder.toString:()Ljava/lang/String;
     129: aload         4
     131: invokespecial #15                 // Method java/lang/RuntimeException."<init>":(Ljava/lang/String;Ljava/lang/Throwable;)V
     134: athrow
     135: astore        4
     137: new           #22                 // class java/lang/IllegalStateException
     140: dup
     141: aload         4
     143: invokespecial #23                 // Method java/lang/IllegalStateException."<init>":(Ljava/lang/Throwable;)V
     146: athrow
     147: astore        4
     149: new           #13                 // class java/lang/RuntimeException
     152: dup
     153: aload         4
     155: invokespecial #25                 // Method java/lang/RuntimeException."<init>":(Ljava/lang/Throwable;)V
     158: athrow
    Exception table:
       from    to  target type
           6    56    57   Class java/lang/Throwable
          95   103   104   Class java/lang/InstantiationException
          95   103   135   Class java/lang/ClassNotFoundException
          95   103   147   Class java/lang/IllegalAccessException

  public static java.net.URL findResource(java.lang.String);
    Code:
       0: ldc           #2                  // class org/hornetq/utils/ClassloadingUtil
       2: invokevirtual #3                  // Method java/lang/Class.getClassLoader:()Ljava/lang/ClassLoader;
       5: astore_1
       6: aload_1
       7: aload_0
       8: invokevirtual #30                 // Method java/lang/ClassLoader.getResource:(Ljava/lang/String;)Ljava/net/URL;
      11: astore_2
      12: aload_2
      13: ifnull        18
      16: aload_2
      17: areturn
      18: goto          22
      21: astore_2
      22: invokestatic  #11                 // Method java/lang/Thread.currentThread:()Ljava/lang/Thread;
      25: invokevirtual #12                 // Method java/lang/Thread.getContextClassLoader:()Ljava/lang/ClassLoader;
      28: astore_1
      29: aload_1
      30: ifnonnull     35
      33: aconst_null
      34: areturn
      35: aload_1
      36: aload_0
      37: invokevirtual #30                 // Method java/lang/ClassLoader.getResource:(Ljava/lang/String;)Ljava/net/URL;
      40: areturn
    Exception table:
       from    to  target type
           6    17    21   Class java/lang/Throwable
}
