Compiled from "CheckImeiRequestImpl.java"
public class org.mobicents.protocols.ss7.map.service.mobility.imei.CheckImeiRequestImpl extends org.mobicents.protocols.ss7.map.service.mobility.MobilityMessageImpl implements org.mobicents.protocols.ss7.map.api.service.mobility.imei.CheckImeiRequest {
  public static final java.lang.String _PrimitiveName;

  private org.mobicents.protocols.ss7.map.api.primitives.IMEI imei;

  private org.mobicents.protocols.ss7.map.api.service.mobility.imei.RequestedEquipmentInfo requestedEquipmentInfo;

  private org.mobicents.protocols.ss7.map.api.primitives.MAPExtensionContainer extensionContainer;

  private org.mobicents.protocols.ss7.map.api.primitives.IMSI imsi;

  private long mapProtocolVersion;

  private int encodedLength;

  public org.mobicents.protocols.ss7.map.service.mobility.imei.CheckImeiRequestImpl(long);
    Code:
       0: aload_0
       1: invokespecial #1                  // Method org/mobicents/protocols/ss7/map/service/mobility/MobilityMessageImpl."<init>":()V
       4: aload_0
       5: aconst_null
       6: putfield      #2                  // Field imei:Lorg/mobicents/protocols/ss7/map/api/primitives/IMEI;
       9: aload_0
      10: aconst_null
      11: putfield      #3                  // Field requestedEquipmentInfo:Lorg/mobicents/protocols/ss7/map/api/service/mobility/imei/RequestedEquipmentInfo;
      14: aload_0
      15: aconst_null
      16: putfield      #4                  // Field extensionContainer:Lorg/mobicents/protocols/ss7/map/api/primitives/MAPExtensionContainer;
      19: aload_0
      20: aconst_null
      21: putfield      #5                  // Field imsi:Lorg/mobicents/protocols/ss7/map/api/primitives/IMSI;
      24: aload_0
      25: lload_1
      26: putfield      #6                  // Field mapProtocolVersion:J
      29: return

  public org.mobicents.protocols.ss7.map.service.mobility.imei.CheckImeiRequestImpl(long, org.mobicents.protocols.ss7.map.api.primitives.IMEI, org.mobicents.protocols.ss7.map.api.service.mobility.imei.RequestedEquipmentInfo, org.mobicents.protocols.ss7.map.api.primitives.MAPExtensionContainer);
    Code:
       0: aload_0
       1: invokespecial #1                  // Method org/mobicents/protocols/ss7/map/service/mobility/MobilityMessageImpl."<init>":()V
       4: aload_0
       5: aconst_null
       6: putfield      #2                  // Field imei:Lorg/mobicents/protocols/ss7/map/api/primitives/IMEI;
       9: aload_0
      10: aconst_null
      11: putfield      #3                  // Field requestedEquipmentInfo:Lorg/mobicents/protocols/ss7/map/api/service/mobility/imei/RequestedEquipmentInfo;
      14: aload_0
      15: aconst_null
      16: putfield      #4                  // Field extensionContainer:Lorg/mobicents/protocols/ss7/map/api/primitives/MAPExtensionContainer;
      19: aload_0
      20: aconst_null
      21: putfield      #5                  // Field imsi:Lorg/mobicents/protocols/ss7/map/api/primitives/IMSI;
      24: aload_0
      25: lload_1
      26: putfield      #6                  // Field mapProtocolVersion:J
      29: aload_0
      30: aload_3
      31: putfield      #2                  // Field imei:Lorg/mobicents/protocols/ss7/map/api/primitives/IMEI;
      34: aload_0
      35: aload         4
      37: putfield      #3                  // Field requestedEquipmentInfo:Lorg/mobicents/protocols/ss7/map/api/service/mobility/imei/RequestedEquipmentInfo;
      40: aload_0
      41: aload         5
      43: putfield      #4                  // Field extensionContainer:Lorg/mobicents/protocols/ss7/map/api/primitives/MAPExtensionContainer;
      46: return

  public long getMapProtocolVersion();
    Code:
       0: aload_0
       1: getfield      #6                  // Field mapProtocolVersion:J
       4: lreturn

  public int getTag() throws org.mobicents.protocols.ss7.map.api.MAPException;
    Code:
       0: aload_0
       1: getfield      #6                  // Field mapProtocolVersion:J
       4: ldc2_w        #7                  // long 3l
       7: lcmp
       8: iflt          14
      11: bipush        16
      13: ireturn
      14: iconst_4
      15: ireturn

  public int getTagClass();
    Code:
       0: iconst_0
       1: ireturn

  public boolean getIsPrimitive();
    Code:
       0: aload_0
       1: getfield      #6                  // Field mapProtocolVersion:J
       4: ldc2_w        #7                  // long 3l
       7: lcmp
       8: iflt          13
      11: iconst_0
      12: ireturn
      13: iconst_1
      14: ireturn

  public int getEncodedLength();
    Code:
       0: aload_0
       1: getfield      #9                  // Field encodedLength:I
       4: ireturn

  public org.mobicents.protocols.ss7.map.api.primitives.IMSI getIMSI();
    Code:
       0: aload_0
       1: getfield      #5                  // Field imsi:Lorg/mobicents/protocols/ss7/map/api/primitives/IMSI;
       4: areturn

  public void setIMSI(org.mobicents.protocols.ss7.map.api.primitives.IMSI);
    Code:
       0: aload_0
       1: aload_1
       2: putfield      #5                  // Field imsi:Lorg/mobicents/protocols/ss7/map/api/primitives/IMSI;
       5: return

  public void decodeAll(org.mobicents.protocols.asn.AsnInputStream) throws org.mobicents.protocols.ss7.map.api.MAPParsingComponentException;
    Code:
       0: aload_1
       1: invokevirtual #10                 // Method org/mobicents/protocols/asn/AsnInputStream.readLength:()I
       4: istore_2
       5: aload_0
       6: aload_1
       7: iload_2
       8: invokespecial #11                 // Method _decode:(Lorg/mobicents/protocols/asn/AsnInputStream;I)V
      11: goto          84
      14: astore_2
      15: new           #13                 // class org/mobicents/protocols/ss7/map/api/MAPParsingComponentException
      18: dup
      19: new           #14                 // class java/lang/StringBuilder
      22: dup
      23: invokespecial #15                 // Method java/lang/StringBuilder."<init>":()V
      26: ldc           #16                 // String IOException when decoding CheckImeiRequest:
      28: invokevirtual #17                 // Method java/lang/StringBuilder.append:(Ljava/lang/String;)Ljava/lang/StringBuilder;
      31: aload_2
      32: invokevirtual #18                 // Method java/io/IOException.getMessage:()Ljava/lang/String;
      35: invokevirtual #17                 // Method java/lang/StringBuilder.append:(Ljava/lang/String;)Ljava/lang/StringBuilder;
      38: invokevirtual #19                 // Method java/lang/StringBuilder.toString:()Ljava/lang/String;
      41: aload_2
      42: getstatic     #20                 // Field org/mobicents/protocols/ss7/map/api/MAPParsingComponentExceptionReason.MistypedParameter:Lorg/mobicents/protocols/ss7/map/api/MAPParsingComponentExceptionReason;
      45: invokespecial #21                 // Method org/mobicents/protocols/ss7/map/api/MAPParsingComponentException."<init>":(Ljava/lang/String;Ljava/lang/Throwable;Lorg/mobicents/protocols/ss7/map/api/MAPParsingComponentExceptionReason;)V
      48: athrow
      49: astore_2
      50: new           #13                 // class org/mobicents/protocols/ss7/map/api/MAPParsingComponentException
      53: dup
      54: new           #14                 // class java/lang/StringBuilder
      57: dup
      58: invokespecial #15                 // Method java/lang/StringBuilder."<init>":()V
      61: ldc           #23                 // String AsnException when decoding CheckImeiRequest:
      63: invokevirtual #17                 // Method java/lang/StringBuilder.append:(Ljava/lang/String;)Ljava/lang/StringBuilder;
      66: aload_2
      67: invokevirtual #24                 // Method org/mobicents/protocols/asn/AsnException.getMessage:()Ljava/lang/String;
      70: invokevirtual #17                 // Method java/lang/StringBuilder.append:(Ljava/lang/String;)Ljava/lang/StringBuilder;
      73: invokevirtual #19                 // Method java/lang/StringBuilder.toString:()Ljava/lang/String;
      76: aload_2
      77: getstatic     #20                 // Field org/mobicents/protocols/ss7/map/api/MAPParsingComponentExceptionReason.MistypedParameter:Lorg/mobicents/protocols/ss7/map/api/MAPParsingComponentExceptionReason;
      80: invokespecial #21                 // Method org/mobicents/protocols/ss7/map/api/MAPParsingComponentException."<init>":(Ljava/lang/String;Ljava/lang/Throwable;Lorg/mobicents/protocols/ss7/map/api/MAPParsingComponentExceptionReason;)V
      83: athrow
      84: return
    Exception table:
       from    to  target type
           0    11    14   Class java/io/IOException
           0    11    49   Class org/mobicents/protocols/asn/AsnException

  public void decodeData(org.mobicents.protocols.asn.AsnInputStream, int) throws org.mobicents.protocols.ss7.map.api.MAPParsingComponentException;
    Code:
       0: aload_0
       1: aload_1
       2: iload_2
       3: invokespecial #11                 // Method _decode:(Lorg/mobicents/protocols/asn/AsnInputStream;I)V
       6: goto          79
       9: astore_3
      10: new           #13                 // class org/mobicents/protocols/ss7/map/api/MAPParsingComponentException
      13: dup
      14: new           #14                 // class java/lang/StringBuilder
      17: dup
      18: invokespecial #15                 // Method java/lang/StringBuilder."<init>":()V
      21: ldc           #16                 // String IOException when decoding CheckImeiRequest:
      23: invokevirtual #17                 // Method java/lang/StringBuilder.append:(Ljava/lang/String;)Ljava/lang/StringBuilder;
      26: aload_3
      27: invokevirtual #18                 // Method java/io/IOException.getMessage:()Ljava/lang/String;
      30: invokevirtual #17                 // Method java/lang/StringBuilder.append:(Ljava/lang/String;)Ljava/lang/StringBuilder;
      33: invokevirtual #19                 // Method java/lang/StringBuilder.toString:()Ljava/lang/String;
      36: aload_3
      37: getstatic     #20                 // Field org/mobicents/protocols/ss7/map/api/MAPParsingComponentExceptionReason.MistypedParameter:Lorg/mobicents/protocols/ss7/map/api/MAPParsingComponentExceptionReason;
      40: invokespecial #21                 // Method org/mobicents/protocols/ss7/map/api/MAPParsingComponentException."<init>":(Ljava/lang/String;Ljava/lang/Throwable;Lorg/mobicents/protocols/ss7/map/api/MAPParsingComponentExceptionReason;)V
      43: athrow
      44: astore_3
      45: new           #13                 // class org/mobicents/protocols/ss7/map/api/MAPParsingComponentException
      48: dup
      49: new           #14                 // class java/lang/StringBuilder
      52: dup
      53: invokespecial #15                 // Method java/lang/StringBuilder."<init>":()V
      56: ldc           #23                 // String AsnException when decoding CheckImeiRequest:
      58: invokevirtual #17                 // Method java/lang/StringBuilder.append:(Ljava/lang/String;)Ljava/lang/StringBuilder;
      61: aload_3
      62: invokevirtual #24                 // Method org/mobicents/protocols/asn/AsnException.getMessage:()Ljava/lang/String;
      65: invokevirtual #17                 // Method java/lang/StringBuilder.append:(Ljava/lang/String;)Ljava/lang/StringBuilder;
      68: invokevirtual #19                 // Method java/lang/StringBuilder.toString:()Ljava/lang/String;
      71: aload_3
      72: getstatic     #20                 // Field org/mobicents/protocols/ss7/map/api/MAPParsingComponentExceptionReason.MistypedParameter:Lorg/mobicents/protocols/ss7/map/api/MAPParsingComponentExceptionReason;
      75: invokespecial #21                 // Method org/mobicents/protocols/ss7/map/api/MAPParsingComponentException."<init>":(Ljava/lang/String;Ljava/lang/Throwable;Lorg/mobicents/protocols/ss7/map/api/MAPParsingComponentExceptionReason;)V
      78: athrow
      79: return
    Exception table:
       from    to  target type
           0     6     9   Class java/io/IOException
           0     6    44   Class org/mobicents/protocols/asn/AsnException

  private void _decode(org.mobicents.protocols.asn.AsnInputStream, int) throws org.mobicents.protocols.ss7.map.api.MAPParsingComponentException, java.io.IOException, org.mobicents.protocols.asn.AsnException;
    Code:
       0: aload_0
       1: aconst_null
       2: putfield      #2                  // Field imei:Lorg/mobicents/protocols/ss7/map/api/primitives/IMEI;
       5: aload_0
       6: aconst_null
       7: putfield      #3                  // Field requestedEquipmentInfo:Lorg/mobicents/protocols/ss7/map/api/service/mobility/imei/RequestedEquipmentInfo;
      10: aload_0
      11: aconst_null
      12: putfield      #4                  // Field extensionContainer:Lorg/mobicents/protocols/ss7/map/api/primitives/MAPExtensionContainer;
      15: aload_0
      16: aconst_null
      17: putfield      #5                  // Field imsi:Lorg/mobicents/protocols/ss7/map/api/primitives/IMSI;
      20: aload_0
      21: getfield      #6                  // Field mapProtocolVersion:J
      24: ldc2_w        #7                  // long 3l
      27: lcmp
      28: iflt          369
      31: aload_1
      32: iload_2
      33: invokevirtual #25                 // Method org/mobicents/protocols/asn/AsnInputStream.readSequenceStreamData:(I)Lorg/mobicents/protocols/asn/AsnInputStream;
      36: astore_3
      37: iconst_0
      38: istore        4
      40: aload_3
      41: invokevirtual #26                 // Method org/mobicents/protocols/asn/AsnInputStream.available:()I
      44: ifne          50
      47: goto          329
      50: aload_3
      51: invokevirtual #27                 // Method org/mobicents/protocols/asn/AsnInputStream.readTag:()I
      54: istore        5
      56: iload         4
      58: lookupswitch  { // 2
                     0: 84
                     1: 172
               default: 260
          }
      84: iload         5
      86: iconst_4
      87: if_icmpne     104
      90: aload_3
      91: invokevirtual #28                 // Method org/mobicents/protocols/asn/AsnInputStream.getTagClass:()I
      94: ifne          104
      97: aload_3
      98: invokevirtual #29                 // Method org/mobicents/protocols/asn/AsnInputStream.isTagPrimitive:()Z
     101: ifne          147
     104: new           #13                 // class org/mobicents/protocols/ss7/map/api/MAPParsingComponentException
     107: dup
     108: new           #14                 // class java/lang/StringBuilder
     111: dup
     112: invokespecial #15                 // Method java/lang/StringBuilder."<init>":()V
     115: ldc           #30                 // String Error while decoding CheckImeiRequest.imei: bad tag or tag class or is not primitive: TagClass=
     117: invokevirtual #17                 // Method java/lang/StringBuilder.append:(Ljava/lang/String;)Ljava/lang/StringBuilder;
     120: aload_3
     121: invokevirtual #28                 // Method org/mobicents/protocols/asn/AsnInputStream.getTagClass:()I
     124: invokevirtual #31                 // Method java/lang/StringBuilder.append:(I)Ljava/lang/StringBuilder;
     127: ldc           #32                 // String , tag=
     129: invokevirtual #17                 // Method java/lang/StringBuilder.append:(Ljava/lang/String;)Ljava/lang/StringBuilder;
     132: iload         5
     134: invokevirtual #31                 // Method java/lang/StringBuilder.append:(I)Ljava/lang/StringBuilder;
     137: invokevirtual #19                 // Method java/lang/StringBuilder.toString:()Ljava/lang/String;
     140: getstatic     #20                 // Field org/mobicents/protocols/ss7/map/api/MAPParsingComponentExceptionReason.MistypedParameter:Lorg/mobicents/protocols/ss7/map/api/MAPParsingComponentExceptionReason;
     143: invokespecial #33                 // Method org/mobicents/protocols/ss7/map/api/MAPParsingComponentException."<init>":(Ljava/lang/String;Lorg/mobicents/protocols/ss7/map/api/MAPParsingComponentExceptionReason;)V
     146: athrow
     147: aload_0
     148: new           #34                 // class org/mobicents/protocols/ss7/map/primitives/IMEIImpl
     151: dup
     152: invokespecial #35                 // Method org/mobicents/protocols/ss7/map/primitives/IMEIImpl."<init>":()V
     155: putfield      #2                  // Field imei:Lorg/mobicents/protocols/ss7/map/api/primitives/IMEI;
     158: aload_0
     159: getfield      #2                  // Field imei:Lorg/mobicents/protocols/ss7/map/api/primitives/IMEI;
     162: checkcast     #34                 // class org/mobicents/protocols/ss7/map/primitives/IMEIImpl
     165: aload_3
     166: invokevirtual #36                 // Method org/mobicents/protocols/ss7/map/primitives/IMEIImpl.decodeAll:(Lorg/mobicents/protocols/asn/AsnInputStream;)V
     169: goto          323
     172: iload         5
     174: iconst_3
     175: if_icmpne     192
     178: aload_3
     179: invokevirtual #28                 // Method org/mobicents/protocols/asn/AsnInputStream.getTagClass:()I
     182: ifne          192
     185: aload_3
     186: invokevirtual #29                 // Method org/mobicents/protocols/asn/AsnInputStream.isTagPrimitive:()Z
     189: ifne          235
     192: new           #13                 // class org/mobicents/protocols/ss7/map/api/MAPParsingComponentException
     195: dup
     196: new           #14                 // class java/lang/StringBuilder
     199: dup
     200: invokespecial #15                 // Method java/lang/StringBuilder."<init>":()V
     203: ldc           #37                 // String Error while decoding CheckImeiRequest.requestedEquipmentInfo: bad tag or tag class or is not primitive: TagClass=
     205: invokevirtual #17                 // Method java/lang/StringBuilder.append:(Ljava/lang/String;)Ljava/lang/StringBuilder;
     208: aload_3
     209: invokevirtual #28                 // Method org/mobicents/protocols/asn/AsnInputStream.getTagClass:()I
     212: invokevirtual #31                 // Method java/lang/StringBuilder.append:(I)Ljava/lang/StringBuilder;
     215: ldc           #32                 // String , tag=
     217: invokevirtual #17                 // Method java/lang/StringBuilder.append:(Ljava/lang/String;)Ljava/lang/StringBuilder;
     220: iload         5
     222: invokevirtual #31                 // Method java/lang/StringBuilder.append:(I)Ljava/lang/StringBuilder;
     225: invokevirtual #19                 // Method java/lang/StringBuilder.toString:()Ljava/lang/String;
     228: getstatic     #20                 // Field org/mobicents/protocols/ss7/map/api/MAPParsingComponentExceptionReason.MistypedParameter:Lorg/mobicents/protocols/ss7/map/api/MAPParsingComponentExceptionReason;
     231: invokespecial #33                 // Method org/mobicents/protocols/ss7/map/api/MAPParsingComponentException."<init>":(Ljava/lang/String;Lorg/mobicents/protocols/ss7/map/api/MAPParsingComponentExceptionReason;)V
     234: athrow
     235: aload_0
     236: new           #38                 // class org/mobicents/protocols/ss7/map/service/mobility/imei/RequestedEquipmentInfoImpl
     239: dup
     240: invokespecial #39                 // Method org/mobicents/protocols/ss7/map/service/mobility/imei/RequestedEquipmentInfoImpl."<init>":()V
     243: putfield      #3                  // Field requestedEquipmentInfo:Lorg/mobicents/protocols/ss7/map/api/service/mobility/imei/RequestedEquipmentInfo;
     246: aload_0
     247: getfield      #3                  // Field requestedEquipmentInfo:Lorg/mobicents/protocols/ss7/map/api/service/mobility/imei/RequestedEquipmentInfo;
     250: checkcast     #38                 // class org/mobicents/protocols/ss7/map/service/mobility/imei/RequestedEquipmentInfoImpl
     253: aload_3
     254: invokevirtual #40                 // Method org/mobicents/protocols/ss7/map/service/mobility/imei/RequestedEquipmentInfoImpl.decodeAll:(Lorg/mobicents/protocols/asn/AsnInputStream;)V
     257: goto          323
     260: iload         5
     262: bipush        16
     264: if_icmpne     319
     267: aload_3
     268: invokevirtual #28                 // Method org/mobicents/protocols/asn/AsnInputStream.getTagClass:()I
     271: ifne          319
     274: aload_3
     275: invokevirtual #29                 // Method org/mobicents/protocols/asn/AsnInputStream.isTagPrimitive:()Z
     278: ifeq          294
     281: new           #13                 // class org/mobicents/protocols/ss7/map/api/MAPParsingComponentException
     284: dup
     285: ldc           #41                 // String Error while decoding CheckImeiRequest: Parameter extensionContainer is primitive
     287: getstatic     #20                 // Field org/mobicents/protocols/ss7/map/api/MAPParsingComponentExceptionReason.MistypedParameter:Lorg/mobicents/protocols/ss7/map/api/MAPParsingComponentExceptionReason;
     290: invokespecial #33                 // Method org/mobicents/protocols/ss7/map/api/MAPParsingComponentException."<init>":(Ljava/lang/String;Lorg/mobicents/protocols/ss7/map/api/MAPParsingComponentExceptionReason;)V
     293: athrow
     294: aload_0
     295: new           #42                 // class org/mobicents/protocols/ss7/map/primitives/MAPExtensionContainerImpl
     298: dup
     299: invokespecial #43                 // Method org/mobicents/protocols/ss7/map/primitives/MAPExtensionContainerImpl."<init>":()V
     302: putfield      #4                  // Field extensionContainer:Lorg/mobicents/protocols/ss7/map/api/primitives/MAPExtensionContainer;
     305: aload_0
     306: getfield      #4                  // Field extensionContainer:Lorg/mobicents/protocols/ss7/map/api/primitives/MAPExtensionContainer;
     309: checkcast     #42                 // class org/mobicents/protocols/ss7/map/primitives/MAPExtensionContainerImpl
     312: aload_3
     313: invokevirtual #44                 // Method org/mobicents/protocols/ss7/map/primitives/MAPExtensionContainerImpl.decodeAll:(Lorg/mobicents/protocols/asn/AsnInputStream;)V
     316: goto          323
     319: aload_3
     320: invokevirtual #45                 // Method org/mobicents/protocols/asn/AsnInputStream.advanceElement:()V
     323: iinc          4, 1
     326: goto          40
     329: iload         4
     331: iconst_2
     332: if_icmpge     366
     335: new           #13                 // class org/mobicents/protocols/ss7/map/api/MAPParsingComponentException
     338: dup
     339: new           #14                 // class java/lang/StringBuilder
     342: dup
     343: invokespecial #15                 // Method java/lang/StringBuilder."<init>":()V
     346: ldc           #46                 // String Error while decoding CheckImeiRequest: Needs at least 2 mandatory parameters, found
     348: invokevirtual #17                 // Method java/lang/StringBuilder.append:(Ljava/lang/String;)Ljava/lang/StringBuilder;
     351: iload         4
     353: invokevirtual #31                 // Method java/lang/StringBuilder.append:(I)Ljava/lang/StringBuilder;
     356: invokevirtual #19                 // Method java/lang/StringBuilder.toString:()Ljava/lang/String;
     359: getstatic     #20                 // Field org/mobicents/protocols/ss7/map/api/MAPParsingComponentExceptionReason.MistypedParameter:Lorg/mobicents/protocols/ss7/map/api/MAPParsingComponentExceptionReason;
     362: invokespecial #33                 // Method org/mobicents/protocols/ss7/map/api/MAPParsingComponentException."<init>":(Ljava/lang/String;Lorg/mobicents/protocols/ss7/map/api/MAPParsingComponentExceptionReason;)V
     365: athrow
     366: goto          492
     369: aload_0
     370: new           #34                 // class org/mobicents/protocols/ss7/map/primitives/IMEIImpl
     373: dup
     374: invokespecial #35                 // Method org/mobicents/protocols/ss7/map/primitives/IMEIImpl."<init>":()V
     377: putfield      #2                  // Field imei:Lorg/mobicents/protocols/ss7/map/api/primitives/IMEI;
     380: aload_0
     381: getfield      #2                  // Field imei:Lorg/mobicents/protocols/ss7/map/api/primitives/IMEI;
     384: checkcast     #34                 // class org/mobicents/protocols/ss7/map/primitives/IMEIImpl
     387: aload_1
     388: iload_2
     389: invokevirtual #47                 // Method org/mobicents/protocols/ss7/map/primitives/IMEIImpl.decodeData:(Lorg/mobicents/protocols/asn/AsnInputStream;I)V
     392: aload_1
     393: invokevirtual #26                 // Method org/mobicents/protocols/asn/AsnInputStream.available:()I
     396: ifeq          492
     399: aload_1
     400: invokevirtual #27                 // Method org/mobicents/protocols/asn/AsnInputStream.readTag:()I
     403: istore_3
     404: aload_1
     405: invokevirtual #10                 // Method org/mobicents/protocols/asn/AsnInputStream.readLength:()I
     408: istore_2
     409: iload_3
     410: ifeq          469
     413: aload_1
     414: invokevirtual #28                 // Method org/mobicents/protocols/asn/AsnInputStream.getTagClass:()I
     417: ifeq          469
     420: aload_1
     421: invokevirtual #29                 // Method org/mobicents/protocols/asn/AsnInputStream.isTagPrimitive:()Z
     424: ifne          469
     427: new           #13                 // class org/mobicents/protocols/ss7/map/api/MAPParsingComponentException
     430: dup
     431: new           #14                 // class java/lang/StringBuilder
     434: dup
     435: invokespecial #15                 // Method java/lang/StringBuilder."<init>":()V
     438: ldc           #48                 // String Error while decoding CheckImeiRequest.imsi: bad tag or tag class or is not primitive: TagClass=
     440: invokevirtual #17                 // Method java/lang/StringBuilder.append:(Ljava/lang/String;)Ljava/lang/StringBuilder;
     443: aload_1
     444: invokevirtual #28                 // Method org/mobicents/protocols/asn/AsnInputStream.getTagClass:()I
     447: invokevirtual #31                 // Method java/lang/StringBuilder.append:(I)Ljava/lang/StringBuilder;
     450: ldc           #32                 // String , tag=
     452: invokevirtual #17                 // Method java/lang/StringBuilder.append:(Ljava/lang/String;)Ljava/lang/StringBuilder;
     455: iload_3
     456: invokevirtual #31                 // Method java/lang/StringBuilder.append:(I)Ljava/lang/StringBuilder;
     459: invokevirtual #19                 // Method java/lang/StringBuilder.toString:()Ljava/lang/String;
     462: getstatic     #20                 // Field org/mobicents/protocols/ss7/map/api/MAPParsingComponentExceptionReason.MistypedParameter:Lorg/mobicents/protocols/ss7/map/api/MAPParsingComponentExceptionReason;
     465: invokespecial #33                 // Method org/mobicents/protocols/ss7/map/api/MAPParsingComponentException."<init>":(Ljava/lang/String;Lorg/mobicents/protocols/ss7/map/api/MAPParsingComponentExceptionReason;)V
     468: athrow
     469: aload_0
     470: new           #49                 // class org/mobicents/protocols/ss7/map/primitives/IMSIImpl
     473: dup
     474: invokespecial #50                 // Method org/mobicents/protocols/ss7/map/primitives/IMSIImpl."<init>":()V
     477: putfield      #5                  // Field imsi:Lorg/mobicents/protocols/ss7/map/api/primitives/IMSI;
     480: aload_0
     481: getfield      #5                  // Field imsi:Lorg/mobicents/protocols/ss7/map/api/primitives/IMSI;
     484: checkcast     #49                 // class org/mobicents/protocols/ss7/map/primitives/IMSIImpl
     487: aload_1
     488: iload_2
     489: invokevirtual #51                 // Method org/mobicents/protocols/ss7/map/primitives/IMSIImpl.decodeData:(Lorg/mobicents/protocols/asn/AsnInputStream;I)V
     492: return

  public void encodeAll(org.mobicents.protocols.asn.AsnOutputStream) throws org.mobicents.protocols.ss7.map.api.MAPException;
    Code:
       0: aload_0
       1: aload_1
       2: aload_0
       3: invokevirtual #52                 // Method getTagClass:()I
       6: aload_0
       7: invokevirtual #53                 // Method getTag:()I
      10: invokevirtual #54                 // Method encodeAll:(Lorg/mobicents/protocols/asn/AsnOutputStream;II)V
      13: return

  public void encodeAll(org.mobicents.protocols.asn.AsnOutputStream, int, int) throws org.mobicents.protocols.ss7.map.api.MAPException;
    Code:
       0: aload_1
       1: iload_2
       2: aload_0
       3: invokevirtual #55                 // Method getIsPrimitive:()Z
       6: iload_3
       7: invokevirtual #56                 // Method org/mobicents/protocols/asn/AsnOutputStream.writeTag:(IZI)V
      10: aload_0
      11: getfield      #5                  // Field imsi:Lorg/mobicents/protocols/ss7/map/api/primitives/IMSI;
      14: ifnonnull     37
      17: aload_1
      18: invokevirtual #57                 // Method org/mobicents/protocols/asn/AsnOutputStream.StartContentDefiniteLength:()I
      21: istore        4
      23: aload_0
      24: aload_1
      25: invokevirtual #58                 // Method encodeData:(Lorg/mobicents/protocols/asn/AsnOutputStream;)V
      28: aload_1
      29: iload         4
      31: invokevirtual #59                 // Method org/mobicents/protocols/asn/AsnOutputStream.FinalizeContent:(I)V
      34: goto          65
      37: new           #60                 // class org/mobicents/protocols/asn/AsnOutputStream
      40: dup
      41: invokespecial #61                 // Method org/mobicents/protocols/asn/AsnOutputStream."<init>":()V
      44: astore        4
      46: aload_0
      47: aload         4
      49: invokevirtual #58                 // Method encodeData:(Lorg/mobicents/protocols/asn/AsnOutputStream;)V
      52: aload_1
      53: aload_0
      54: invokevirtual #62                 // Method getEncodedLength:()I
      57: invokevirtual #63                 // Method org/mobicents/protocols/asn/AsnOutputStream.writeLength:(I)V
      60: aload_0
      61: aload_1
      62: invokevirtual #58                 // Method encodeData:(Lorg/mobicents/protocols/asn/AsnOutputStream;)V
      65: goto          138
      68: astore        4
      70: new           #64                 // class org/mobicents/protocols/ss7/map/api/MAPException
      73: dup
      74: new           #14                 // class java/lang/StringBuilder
      77: dup
      78: invokespecial #15                 // Method java/lang/StringBuilder."<init>":()V
      81: ldc           #65                 // String AsnException when encoding CheckImeiRequest:
      83: invokevirtual #17                 // Method java/lang/StringBuilder.append:(Ljava/lang/String;)Ljava/lang/StringBuilder;
      86: aload         4
      88: invokevirtual #24                 // Method org/mobicents/protocols/asn/AsnException.getMessage:()Ljava/lang/String;
      91: invokevirtual #17                 // Method java/lang/StringBuilder.append:(Ljava/lang/String;)Ljava/lang/StringBuilder;
      94: invokevirtual #19                 // Method java/lang/StringBuilder.toString:()Ljava/lang/String;
      97: aload         4
      99: invokespecial #66                 // Method org/mobicents/protocols/ss7/map/api/MAPException."<init>":(Ljava/lang/String;Ljava/lang/Throwable;)V
     102: athrow
     103: astore        4
     105: new           #64                 // class org/mobicents/protocols/ss7/map/api/MAPException
     108: dup
     109: new           #14                 // class java/lang/StringBuilder
     112: dup
     113: invokespecial #15                 // Method java/lang/StringBuilder."<init>":()V
     116: ldc           #67                 // String IOException when encoding CheckImeiRequest:
     118: invokevirtual #17                 // Method java/lang/StringBuilder.append:(Ljava/lang/String;)Ljava/lang/StringBuilder;
     121: aload         4
     123: invokevirtual #18                 // Method java/io/IOException.getMessage:()Ljava/lang/String;
     126: invokevirtual #17                 // Method java/lang/StringBuilder.append:(Ljava/lang/String;)Ljava/lang/StringBuilder;
     129: invokevirtual #19                 // Method java/lang/StringBuilder.toString:()Ljava/lang/String;
     132: aload         4
     134: invokespecial #66                 // Method org/mobicents/protocols/ss7/map/api/MAPException."<init>":(Ljava/lang/String;Ljava/lang/Throwable;)V
     137: athrow
     138: return
    Exception table:
       from    to  target type
           0    65    68   Class org/mobicents/protocols/asn/AsnException
           0    65   103   Class java/io/IOException

  public void encodeData(org.mobicents.protocols.asn.AsnOutputStream) throws org.mobicents.protocols.ss7.map.api.MAPException;
    Code:
       0: aload_0
       1: getfield      #2                  // Field imei:Lorg/mobicents/protocols/ss7/map/api/primitives/IMEI;
       4: ifnonnull     17
       7: new           #64                 // class org/mobicents/protocols/ss7/map/api/MAPException
      10: dup
      11: ldc           #68                 // String imei parameter must not be null
      13: invokespecial #69                 // Method org/mobicents/protocols/ss7/map/api/MAPException."<init>":(Ljava/lang/String;)V
      16: athrow
      17: aload_0
      18: getfield      #6                  // Field mapProtocolVersion:J
      21: ldc2_w        #7                  // long 3l
      24: lcmp
      25: iflt          88
      28: aload_0
      29: getfield      #3                  // Field requestedEquipmentInfo:Lorg/mobicents/protocols/ss7/map/api/service/mobility/imei/RequestedEquipmentInfo;
      32: ifnonnull     45
      35: new           #64                 // class org/mobicents/protocols/ss7/map/api/MAPException
      38: dup
      39: ldc           #70                 // String requestedEquipmentInfo parameter must not be null
      41: invokespecial #69                 // Method org/mobicents/protocols/ss7/map/api/MAPException."<init>":(Ljava/lang/String;)V
      44: athrow
      45: aload_0
      46: getfield      #2                  // Field imei:Lorg/mobicents/protocols/ss7/map/api/primitives/IMEI;
      49: checkcast     #34                 // class org/mobicents/protocols/ss7/map/primitives/IMEIImpl
      52: aload_1
      53: invokevirtual #71                 // Method org/mobicents/protocols/ss7/map/primitives/IMEIImpl.encodeAll:(Lorg/mobicents/protocols/asn/AsnOutputStream;)V
      56: aload_0
      57: getfield      #3                  // Field requestedEquipmentInfo:Lorg/mobicents/protocols/ss7/map/api/service/mobility/imei/RequestedEquipmentInfo;
      60: checkcast     #38                 // class org/mobicents/protocols/ss7/map/service/mobility/imei/RequestedEquipmentInfoImpl
      63: aload_1
      64: invokevirtual #72                 // Method org/mobicents/protocols/ss7/map/service/mobility/imei/RequestedEquipmentInfoImpl.encodeAll:(Lorg/mobicents/protocols/asn/AsnOutputStream;)V
      67: aload_0
      68: getfield      #4                  // Field extensionContainer:Lorg/mobicents/protocols/ss7/map/api/primitives/MAPExtensionContainer;
      71: ifnull        127
      74: aload_0
      75: getfield      #4                  // Field extensionContainer:Lorg/mobicents/protocols/ss7/map/api/primitives/MAPExtensionContainer;
      78: checkcast     #42                 // class org/mobicents/protocols/ss7/map/primitives/MAPExtensionContainerImpl
      81: aload_1
      82: invokevirtual #73                 // Method org/mobicents/protocols/ss7/map/primitives/MAPExtensionContainerImpl.encodeAll:(Lorg/mobicents/protocols/asn/AsnOutputStream;)V
      85: goto          127
      88: aload_0
      89: getfield      #2                  // Field imei:Lorg/mobicents/protocols/ss7/map/api/primitives/IMEI;
      92: checkcast     #34                 // class org/mobicents/protocols/ss7/map/primitives/IMEIImpl
      95: aload_1
      96: invokevirtual #74                 // Method org/mobicents/protocols/ss7/map/primitives/IMEIImpl.encodeData:(Lorg/mobicents/protocols/asn/AsnOutputStream;)V
      99: aload_0
     100: aload_1
     101: invokevirtual #75                 // Method org/mobicents/protocols/asn/AsnOutputStream.size:()I
     104: putfield      #9                  // Field encodedLength:I
     107: aload_0
     108: getfield      #5                  // Field imsi:Lorg/mobicents/protocols/ss7/map/api/primitives/IMSI;
     111: ifnull        127
     114: aload_0
     115: getfield      #5                  // Field imsi:Lorg/mobicents/protocols/ss7/map/api/primitives/IMSI;
     118: checkcast     #49                 // class org/mobicents/protocols/ss7/map/primitives/IMSIImpl
     121: aload_1
     122: iconst_0
     123: iconst_0
     124: invokevirtual #76                 // Method org/mobicents/protocols/ss7/map/primitives/IMSIImpl.encodeAll:(Lorg/mobicents/protocols/asn/AsnOutputStream;II)V
     127: return

  public org.mobicents.protocols.ss7.map.api.MAPMessageType getMessageType();
    Code:
       0: getstatic     #77                 // Field org/mobicents/protocols/ss7/map/api/MAPMessageType.checkIMEI_Request:Lorg/mobicents/protocols/ss7/map/api/MAPMessageType;
       3: areturn

  public int getOperationCode();
    Code:
       0: bipush        43
       2: ireturn

  public org.mobicents.protocols.ss7.map.api.primitives.IMEI getIMEI();
    Code:
       0: aload_0
       1: getfield      #2                  // Field imei:Lorg/mobicents/protocols/ss7/map/api/primitives/IMEI;
       4: areturn

  public org.mobicents.protocols.ss7.map.api.service.mobility.imei.RequestedEquipmentInfo getRequestedEquipmentInfo();
    Code:
       0: aload_0
       1: getfield      #3                  // Field requestedEquipmentInfo:Lorg/mobicents/protocols/ss7/map/api/service/mobility/imei/RequestedEquipmentInfo;
       4: areturn

  public org.mobicents.protocols.ss7.map.api.primitives.MAPExtensionContainer getExtensionContainer();
    Code:
       0: aload_0
       1: getfield      #4                  // Field extensionContainer:Lorg/mobicents/protocols/ss7/map/api/primitives/MAPExtensionContainer;
       4: areturn

  public java.lang.String toString();
    Code:
       0: new           #14                 // class java/lang/StringBuilder
       3: dup
       4: invokespecial #15                 // Method java/lang/StringBuilder."<init>":()V
       7: astore_1
       8: aload_1
       9: ldc           #78                 // String CheckImeiRequest
      11: invokevirtual #17                 // Method java/lang/StringBuilder.append:(Ljava/lang/String;)Ljava/lang/StringBuilder;
      14: pop
      15: aload_1
      16: ldc           #79                 // String  [
      18: invokevirtual #17                 // Method java/lang/StringBuilder.append:(Ljava/lang/String;)Ljava/lang/StringBuilder;
      21: pop
      22: aload_0
      23: getfield      #2                  // Field imei:Lorg/mobicents/protocols/ss7/map/api/primitives/IMEI;
      26: ifnull        55
      29: aload_1
      30: ldc           #80                 // String imei=
      32: invokevirtual #17                 // Method java/lang/StringBuilder.append:(Ljava/lang/String;)Ljava/lang/StringBuilder;
      35: pop
      36: aload_1
      37: aload_0
      38: getfield      #2                  // Field imei:Lorg/mobicents/protocols/ss7/map/api/primitives/IMEI;
      41: invokevirtual #81                 // Method java/lang/Object.toString:()Ljava/lang/String;
      44: invokevirtual #17                 // Method java/lang/StringBuilder.append:(Ljava/lang/String;)Ljava/lang/StringBuilder;
      47: pop
      48: aload_1
      49: ldc           #82                 // String ,
      51: invokevirtual #17                 // Method java/lang/StringBuilder.append:(Ljava/lang/String;)Ljava/lang/StringBuilder;
      54: pop
      55: aload_0
      56: getfield      #3                  // Field requestedEquipmentInfo:Lorg/mobicents/protocols/ss7/map/api/service/mobility/imei/RequestedEquipmentInfo;
      59: ifnull        88
      62: aload_1
      63: ldc           #83                 // String requestedEquipmentInfo=
      65: invokevirtual #17                 // Method java/lang/StringBuilder.append:(Ljava/lang/String;)Ljava/lang/StringBuilder;
      68: pop
      69: aload_1
      70: aload_0
      71: getfield      #3                  // Field requestedEquipmentInfo:Lorg/mobicents/protocols/ss7/map/api/service/mobility/imei/RequestedEquipmentInfo;
      74: invokevirtual #81                 // Method java/lang/Object.toString:()Ljava/lang/String;
      77: invokevirtual #17                 // Method java/lang/StringBuilder.append:(Ljava/lang/String;)Ljava/lang/StringBuilder;
      80: pop
      81: aload_1
      82: ldc           #82                 // String ,
      84: invokevirtual #17                 // Method java/lang/StringBuilder.append:(Ljava/lang/String;)Ljava/lang/StringBuilder;
      87: pop
      88: aload_0
      89: getfield      #4                  // Field extensionContainer:Lorg/mobicents/protocols/ss7/map/api/primitives/MAPExtensionContainer;
      92: ifnull        121
      95: aload_1
      96: ldc           #84                 // String extensionContainer=
      98: invokevirtual #17                 // Method java/lang/StringBuilder.append:(Ljava/lang/String;)Ljava/lang/StringBuilder;
     101: pop
     102: aload_1
     103: aload_0
     104: getfield      #4                  // Field extensionContainer:Lorg/mobicents/protocols/ss7/map/api/primitives/MAPExtensionContainer;
     107: invokevirtual #81                 // Method java/lang/Object.toString:()Ljava/lang/String;
     110: invokevirtual #17                 // Method java/lang/StringBuilder.append:(Ljava/lang/String;)Ljava/lang/StringBuilder;
     113: pop
     114: aload_1
     115: ldc           #82                 // String ,
     117: invokevirtual #17                 // Method java/lang/StringBuilder.append:(Ljava/lang/String;)Ljava/lang/StringBuilder;
     120: pop
     121: aload_0
     122: getfield      #5                  // Field imsi:Lorg/mobicents/protocols/ss7/map/api/primitives/IMSI;
     125: ifnull        154
     128: aload_1
     129: ldc           #85                 // String imsi=
     131: invokevirtual #17                 // Method java/lang/StringBuilder.append:(Ljava/lang/String;)Ljava/lang/StringBuilder;
     134: pop
     135: aload_1
     136: aload_0
     137: getfield      #5                  // Field imsi:Lorg/mobicents/protocols/ss7/map/api/primitives/IMSI;
     140: invokevirtual #81                 // Method java/lang/Object.toString:()Ljava/lang/String;
     143: invokevirtual #17                 // Method java/lang/StringBuilder.append:(Ljava/lang/String;)Ljava/lang/StringBuilder;
     146: pop
     147: aload_1
     148: ldc           #82                 // String ,
     150: invokevirtual #17                 // Method java/lang/StringBuilder.append:(Ljava/lang/String;)Ljava/lang/StringBuilder;
     153: pop
     154: aload_1
     155: ldc           #86                 // String mapProtocolVersion=
     157: invokevirtual #17                 // Method java/lang/StringBuilder.append:(Ljava/lang/String;)Ljava/lang/StringBuilder;
     160: pop
     161: aload_1
     162: aload_0
     163: getfield      #6                  // Field mapProtocolVersion:J
     166: invokevirtual #87                 // Method java/lang/StringBuilder.append:(J)Ljava/lang/StringBuilder;
     169: pop
     170: aload_1
     171: ldc           #88                 // String ]
     173: invokevirtual #17                 // Method java/lang/StringBuilder.append:(Ljava/lang/String;)Ljava/lang/StringBuilder;
     176: pop
     177: aload_1
     178: invokevirtual #19                 // Method java/lang/StringBuilder.toString:()Ljava/lang/String;
     181: areturn
}
