Compiled from "RequestedEquipmentInfoImpl.java"
public class org.mobicents.protocols.ss7.map.service.mobility.imei.RequestedEquipmentInfoImpl extends org.mobicents.protocols.ss7.map.primitives.BitStringBase implements org.mobicents.protocols.ss7.map.api.service.mobility.imei.RequestedEquipmentInfo {
  public static final java.lang.String _PrimitiveName;

  private static final int _INDEX_EQUIPMENT_STATUS;

  private static final int _INDEX_BMUEF;

  public org.mobicents.protocols.ss7.map.service.mobility.imei.RequestedEquipmentInfoImpl();
    Code:
       0: aload_0
       1: iconst_2
       2: bipush        8
       4: iconst_2
       5: ldc           #1                  // String RequestedEquipmentInfo
       7: invokespecial #2                  // Method org/mobicents/protocols/ss7/map/primitives/BitStringBase."<init>":(IIILjava/lang/String;)V
      10: return

  public org.mobicents.protocols.ss7.map.service.mobility.imei.RequestedEquipmentInfoImpl(boolean, boolean);
    Code:
       0: aload_0
       1: iconst_2
       2: bipush        8
       4: iconst_2
       5: ldc           #1                  // String RequestedEquipmentInfo
       7: invokespecial #2                  // Method org/mobicents/protocols/ss7/map/primitives/BitStringBase."<init>":(IIILjava/lang/String;)V
      10: iload_1
      11: ifeq          22
      14: aload_0
      15: getfield      #3                  // Field bitString:Lorg/mobicents/protocols/asn/BitSetStrictLength;
      18: iconst_0
      19: invokevirtual #4                  // Method org/mobicents/protocols/asn/BitSetStrictLength.set:(I)V
      22: iload_2
      23: ifeq          34
      26: aload_0
      27: getfield      #3                  // Field bitString:Lorg/mobicents/protocols/asn/BitSetStrictLength;
      30: iconst_1
      31: invokevirtual #4                  // Method org/mobicents/protocols/asn/BitSetStrictLength.set:(I)V
      34: return

  public boolean getEquipmentStatus();
    Code:
       0: aload_0
       1: getfield      #3                  // Field bitString:Lorg/mobicents/protocols/asn/BitSetStrictLength;
       4: iconst_0
       5: invokevirtual #5                  // Method org/mobicents/protocols/asn/BitSetStrictLength.get:(I)Z
       8: ireturn

  public boolean getBmuef();
    Code:
       0: aload_0
       1: getfield      #3                  // Field bitString:Lorg/mobicents/protocols/asn/BitSetStrictLength;
       4: iconst_1
       5: invokevirtual #5                  // Method org/mobicents/protocols/asn/BitSetStrictLength.get:(I)Z
       8: ireturn

  public java.lang.String toString();
    Code:
       0: new           #6                  // class java/lang/StringBuilder
       3: dup
       4: invokespecial #7                  // Method java/lang/StringBuilder."<init>":()V
       7: astore_1
       8: aload_1
       9: ldc           #1                  // String RequestedEquipmentInfo
      11: invokevirtual #8                  // Method java/lang/StringBuilder.append:(Ljava/lang/String;)Ljava/lang/StringBuilder;
      14: pop
      15: aload_1
      16: ldc           #9                  // String  [
      18: invokevirtual #8                  // Method java/lang/StringBuilder.append:(Ljava/lang/String;)Ljava/lang/StringBuilder;
      21: pop
      22: aload_0
      23: invokevirtual #10                 // Method getEquipmentStatus:()Z
      26: ifeq          36
      29: aload_1
      30: ldc           #11                 // String EquipmentStatus,
      32: invokevirtual #8                  // Method java/lang/StringBuilder.append:(Ljava/lang/String;)Ljava/lang/StringBuilder;
      35: pop
      36: aload_0
      37: invokevirtual #12                 // Method getBmuef:()Z
      40: ifeq          50
      43: aload_1
      44: ldc           #13                 // String bmuef,
      46: invokevirtual #8                  // Method java/lang/StringBuilder.append:(Ljava/lang/String;)Ljava/lang/StringBuilder;
      49: pop
      50: aload_1
      51: ldc           #14                 // String ]
      53: invokevirtual #8                  // Method java/lang/StringBuilder.append:(Ljava/lang/String;)Ljava/lang/StringBuilder;
      56: pop
      57: aload_1
      58: invokevirtual #15                 // Method java/lang/StringBuilder.toString:()Ljava/lang/String;
      61: areturn
}
