Compiled from "Main.java"
final class org.codehaus.groovy.antlr.Main$1 extends java.awt.event.WindowAdapter {
  final groovyjarjarantlr.debug.misc.ASTFrame val$frame;

  org.codehaus.groovy.antlr.Main$1(groovyjarjarantlr.debug.misc.ASTFrame);
    Code:
       0: aload_0
       1: aload_1
       2: putfield      #16                 // Field val$frame:Lgroovyjarjarantlr/debug/misc/ASTFrame;
       5: aload_0
       6: invokespecial #19                 // Method java/awt/event/WindowAdapter."<init>":()V
       9: return

  public void windowClosing(java.awt.event.WindowEvent);
    Code:
       0: aload_0
       1: getfield      #16                 // Field val$frame:Lgroovyjarjarantlr/debug/misc/ASTFrame;
       4: iconst_0
       5: invokevirtual #29                 // Method groovyjarjarantlr/debug/misc/ASTFrame.setVisible:(Z)V
       8: aload_0
       9: getfield      #16                 // Field val$frame:Lgroovyjarjarantlr/debug/misc/ASTFrame;
      12: invokevirtual #32                 // Method groovyjarjarantlr/debug/misc/ASTFrame.dispose:()V
      15: iconst_0
      16: invokestatic  #38                 // Method java/lang/System.exit:(I)V
      19: return
}
