Compiled from "SegmentConstantPoolArrayCache.java"
public class org.apache.commons.compress.harmony.unpack200.SegmentConstantPoolArrayCache$CachedArray {
  java.lang.String[] primaryArray;

  int lastKnownSize;

  java.util.HashMap primaryTable;

  final org.apache.commons.compress.harmony.unpack200.SegmentConstantPoolArrayCache this$0;

  public org.apache.commons.compress.harmony.unpack200.SegmentConstantPoolArrayCache$CachedArray(org.apache.commons.compress.harmony.unpack200.SegmentConstantPoolArrayCache, java.lang.String[]);
    Code:
       0: aload_0
       1: aload_1
       2: putfield      #1                  // Field this$0:Lorg/apache/commons/compress/harmony/unpack200/SegmentConstantPoolArrayCache;
       5: aload_0
       6: invokespecial #2                  // Method java/lang/Object."<init>":()V
       9: aload_0
      10: aload_2
      11: putfield      #3                  // Field primaryArray:[Ljava/lang/String;
      14: aload_0
      15: aload_2
      16: arraylength
      17: putfield      #4                  // Field lastKnownSize:I
      20: aload_0
      21: new           #5                  // class java/util/HashMap
      24: dup
      25: aload_0
      26: getfield      #4                  // Field lastKnownSize:I
      29: invokespecial #6                  // Method java/util/HashMap."<init>":(I)V
      32: putfield      #7                  // Field primaryTable:Ljava/util/HashMap;
      35: aload_0
      36: invokevirtual #8                  // Method cacheIndexes:()V
      39: return

  public int lastKnownSize();
    Code:
       0: aload_0
       1: getfield      #4                  // Field lastKnownSize:I
       4: ireturn

  public java.util.List indexesForKey(java.lang.String);
    Code:
       0: aload_0
       1: getfield      #7                  // Field primaryTable:Ljava/util/HashMap;
       4: aload_1
       5: invokevirtual #9                  // Method java/util/HashMap.containsKey:(Ljava/lang/Object;)Z
       8: ifne          15
      11: getstatic     #10                 // Field java/util/Collections.EMPTY_LIST:Ljava/util/List;
      14: areturn
      15: aload_0
      16: getfield      #7                  // Field primaryTable:Ljava/util/HashMap;
      19: aload_1
      20: invokevirtual #11                 // Method java/util/HashMap.get:(Ljava/lang/Object;)Ljava/lang/Object;
      23: checkcast     #12                 // class java/util/List
      26: areturn

  protected void cacheIndexes();
    Code:
       0: iconst_0
       1: istore_1
       2: iload_1
       3: aload_0
       4: getfield      #3                  // Field primaryArray:[Ljava/lang/String;
       7: arraylength
       8: if_icmpge     70
      11: aload_0
      12: getfield      #3                  // Field primaryArray:[Ljava/lang/String;
      15: iload_1
      16: aaload
      17: astore_2
      18: aload_0
      19: getfield      #7                  // Field primaryTable:Ljava/util/HashMap;
      22: aload_2
      23: invokevirtual #9                  // Method java/util/HashMap.containsKey:(Ljava/lang/Object;)Z
      26: ifne          45
      29: aload_0
      30: getfield      #7                  // Field primaryTable:Ljava/util/HashMap;
      33: aload_2
      34: new           #13                 // class java/util/ArrayList
      37: dup
      38: invokespecial #14                 // Method java/util/ArrayList."<init>":()V
      41: invokevirtual #15                 // Method java/util/HashMap.put:(Ljava/lang/Object;Ljava/lang/Object;)Ljava/lang/Object;
      44: pop
      45: aload_0
      46: getfield      #7                  // Field primaryTable:Ljava/util/HashMap;
      49: aload_2
      50: invokevirtual #11                 // Method java/util/HashMap.get:(Ljava/lang/Object;)Ljava/lang/Object;
      53: checkcast     #13                 // class java/util/ArrayList
      56: iload_1
      57: invokestatic  #16                 // Method java/lang/Integer.valueOf:(I)Ljava/lang/Integer;
      60: invokevirtual #17                 // Method java/util/ArrayList.add:(Ljava/lang/Object;)Z
      63: pop
      64: iinc          1, 1
      67: goto          2
      70: return
}
