Compiled from "AttributesHelper.java"
public class org.hibernate.boot.model.source.internal.hbm.AttributesHelper {
  public org.hibernate.boot.model.source.internal.hbm.AttributesHelper();
    Code:
       0: aload_0
       1: invokespecial #1                  // Method java/lang/Object."<init>":()V
       4: return

  public static void processAttributes(org.hibernate.boot.model.source.internal.hbm.MappingDocument, org.hibernate.boot.model.source.internal.hbm.AttributesHelper$Callback, java.util.List, java.lang.String, org.hibernate.boot.model.source.spi.NaturalIdMutability);
    Code:
       0: aload_2
       1: invokeinterface #2,  1            // InterfaceMethod java/util/List.iterator:()Ljava/util/Iterator;
       6: astore        5
       8: aload         5
      10: invokeinterface #3,  1            // InterfaceMethod java/util/Iterator.hasNext:()Z
      15: ifeq          40
      18: aload         5
      20: invokeinterface #4,  1            // InterfaceMethod java/util/Iterator.next:()Ljava/lang/Object;
      25: astore        6
      27: aload_0
      28: aload_1
      29: aload         6
      31: aload_3
      32: aload         4
      34: invokestatic  #5                  // Method processAttribute:(Lorg/hibernate/boot/model/source/internal/hbm/MappingDocument;Lorg/hibernate/boot/model/source/internal/hbm/AttributesHelper$Callback;Ljava/lang/Object;Ljava/lang/String;Lorg/hibernate/boot/model/source/spi/NaturalIdMutability;)V
      37: goto          8
      40: return

  private static void processAttribute(org.hibernate.boot.model.source.internal.hbm.MappingDocument, org.hibernate.boot.model.source.internal.hbm.AttributesHelper$Callback, java.lang.Object, java.lang.String, org.hibernate.boot.model.source.spi.NaturalIdMutability);
    Code:
       0: ldc           #6                  // class javax/xml/bind/JAXBElement
       2: aload_2
       3: invokevirtual #7                  // Method java/lang/Class.isInstance:(Ljava/lang/Object;)Z
       6: ifeq          27
       9: aload_0
      10: aload_1
      11: aload_2
      12: checkcast     #6                  // class javax/xml/bind/JAXBElement
      15: invokevirtual #8                  // Method javax/xml/bind/JAXBElement.getValue:()Ljava/lang/Object;
      18: aload_3
      19: aload         4
      21: invokestatic  #5                  // Method processAttribute:(Lorg/hibernate/boot/model/source/internal/hbm/MappingDocument;Lorg/hibernate/boot/model/source/internal/hbm/AttributesHelper$Callback;Ljava/lang/Object;Ljava/lang/String;Lorg/hibernate/boot/model/source/spi/NaturalIdMutability;)V
      24: goto          475
      27: ldc           #9                  // class org/hibernate/boot/jaxb/hbm/spi/JaxbHbmCompositeKeyBasicAttributeType
      29: aload_2
      30: invokevirtual #7                  // Method java/lang/Class.isInstance:(Ljava/lang/Object;)Z
      33: ifeq          63
      36: aload_1
      37: new           #10                 // class org/hibernate/boot/model/source/internal/hbm/CompositeIdentifierSingularAttributeSourceBasicImpl
      40: dup
      41: aload_0
      42: aload_1
      43: invokeinterface #11,  1           // InterfaceMethod org/hibernate/boot/model/source/internal/hbm/AttributesHelper$Callback.getAttributeSourceContainer:()Lorg/hibernate/boot/model/source/spi/AttributeSourceContainer;
      48: aload_2
      49: checkcast     #9                  // class org/hibernate/boot/jaxb/hbm/spi/JaxbHbmCompositeKeyBasicAttributeType
      52: invokespecial #12                 // Method org/hibernate/boot/model/source/internal/hbm/CompositeIdentifierSingularAttributeSourceBasicImpl."<init>":(Lorg/hibernate/boot/model/source/internal/hbm/MappingDocument;Lorg/hibernate/boot/model/source/spi/AttributeSourceContainer;Lorg/hibernate/boot/jaxb/hbm/spi/JaxbHbmCompositeKeyBasicAttributeType;)V
      55: invokeinterface #13,  2           // InterfaceMethod org/hibernate/boot/model/source/internal/hbm/AttributesHelper$Callback.addAttributeSource:(Lorg/hibernate/boot/model/source/spi/AttributeSource;)V
      60: goto          475
      63: ldc           #14                 // class org/hibernate/boot/jaxb/hbm/spi/JaxbHbmCompositeKeyManyToOneType
      65: aload_2
      66: invokevirtual #7                  // Method java/lang/Class.isInstance:(Ljava/lang/Object;)Z
      69: ifeq          99
      72: aload_1
      73: new           #15                 // class org/hibernate/boot/model/source/internal/hbm/CompositeIdentifierSingularAttributeSourceManyToOneImpl
      76: dup
      77: aload_0
      78: aload_1
      79: invokeinterface #11,  1           // InterfaceMethod org/hibernate/boot/model/source/internal/hbm/AttributesHelper$Callback.getAttributeSourceContainer:()Lorg/hibernate/boot/model/source/spi/AttributeSourceContainer;
      84: aload_2
      85: checkcast     #14                 // class org/hibernate/boot/jaxb/hbm/spi/JaxbHbmCompositeKeyManyToOneType
      88: invokespecial #16                 // Method org/hibernate/boot/model/source/internal/hbm/CompositeIdentifierSingularAttributeSourceManyToOneImpl."<init>":(Lorg/hibernate/boot/model/source/internal/hbm/MappingDocument;Lorg/hibernate/boot/model/source/spi/AttributeSourceContainer;Lorg/hibernate/boot/jaxb/hbm/spi/JaxbHbmCompositeKeyManyToOneType;)V
      91: invokeinterface #13,  2           // InterfaceMethod org/hibernate/boot/model/source/internal/hbm/AttributesHelper$Callback.addAttributeSource:(Lorg/hibernate/boot/model/source/spi/AttributeSource;)V
      96: goto          475
      99: ldc           #17                 // class org/hibernate/boot/jaxb/hbm/spi/JaxbHbmPropertiesType
     101: aload_2
     102: invokevirtual #7                  // Method java/lang/Class.isInstance:(Ljava/lang/Object;)Z
     105: ifeq          123
     108: aload_0
     109: aload_1
     110: aload_2
     111: checkcast     #17                 // class org/hibernate/boot/jaxb/hbm/spi/JaxbHbmPropertiesType
     114: aload_3
     115: aload         4
     117: invokestatic  #18                 // Method processPropertiesGroup:(Lorg/hibernate/boot/model/source/internal/hbm/MappingDocument;Lorg/hibernate/boot/model/source/internal/hbm/AttributesHelper$Callback;Lorg/hibernate/boot/jaxb/hbm/spi/JaxbHbmPropertiesType;Ljava/lang/String;Lorg/hibernate/boot/model/source/spi/NaturalIdMutability;)V
     120: goto          475
     123: ldc           #19                 // class org/hibernate/boot/jaxb/hbm/spi/JaxbHbmBasicAttributeType
     125: aload_2
     126: invokevirtual #7                  // Method java/lang/Class.isInstance:(Ljava/lang/Object;)Z
     129: ifeq          147
     132: aload_0
     133: aload_1
     134: aload_2
     135: checkcast     #19                 // class org/hibernate/boot/jaxb/hbm/spi/JaxbHbmBasicAttributeType
     138: aload_3
     139: aload         4
     141: invokestatic  #20                 // Method processBasicAttribute:(Lorg/hibernate/boot/model/source/internal/hbm/MappingDocument;Lorg/hibernate/boot/model/source/internal/hbm/AttributesHelper$Callback;Lorg/hibernate/boot/jaxb/hbm/spi/JaxbHbmBasicAttributeType;Ljava/lang/String;Lorg/hibernate/boot/model/source/spi/NaturalIdMutability;)V
     144: goto          475
     147: ldc           #21                 // class org/hibernate/boot/jaxb/hbm/spi/JaxbHbmCompositeAttributeType
     149: aload_2
     150: invokevirtual #7                  // Method java/lang/Class.isInstance:(Ljava/lang/Object;)Z
     153: ifeq          171
     156: aload_0
     157: aload_1
     158: aload_2
     159: checkcast     #21                 // class org/hibernate/boot/jaxb/hbm/spi/JaxbHbmCompositeAttributeType
     162: aload_3
     163: aload         4
     165: invokestatic  #22                 // Method processEmbeddedAttribute:(Lorg/hibernate/boot/model/source/internal/hbm/MappingDocument;Lorg/hibernate/boot/model/source/internal/hbm/AttributesHelper$Callback;Lorg/hibernate/boot/jaxb/hbm/spi/JaxbHbmCompositeAttributeType;Ljava/lang/String;Lorg/hibernate/boot/model/source/spi/NaturalIdMutability;)V
     168: goto          475
     171: ldc           #23                 // class org/hibernate/boot/jaxb/hbm/spi/JaxbHbmDynamicComponentType
     173: aload_2
     174: invokevirtual #7                  // Method java/lang/Class.isInstance:(Ljava/lang/Object;)Z
     177: ifeq          195
     180: aload_0
     181: aload_1
     182: aload_2
     183: checkcast     #23                 // class org/hibernate/boot/jaxb/hbm/spi/JaxbHbmDynamicComponentType
     186: aload_3
     187: aload         4
     189: invokestatic  #24                 // Method processDynamicComponentAttribute:(Lorg/hibernate/boot/model/source/internal/hbm/MappingDocument;Lorg/hibernate/boot/model/source/internal/hbm/AttributesHelper$Callback;Lorg/hibernate/boot/jaxb/hbm/spi/JaxbHbmDynamicComponentType;Ljava/lang/String;Lorg/hibernate/boot/model/source/spi/NaturalIdMutability;)V
     192: goto          475
     195: ldc           #25                 // class org/hibernate/boot/jaxb/hbm/spi/JaxbHbmManyToOneType
     197: aload_2
     198: invokevirtual #7                  // Method java/lang/Class.isInstance:(Ljava/lang/Object;)Z
     201: ifeq          219
     204: aload_0
     205: aload_1
     206: aload_2
     207: checkcast     #25                 // class org/hibernate/boot/jaxb/hbm/spi/JaxbHbmManyToOneType
     210: aload_3
     211: aload         4
     213: invokestatic  #26                 // Method processManyToOneAttribute:(Lorg/hibernate/boot/model/source/internal/hbm/MappingDocument;Lorg/hibernate/boot/model/source/internal/hbm/AttributesHelper$Callback;Lorg/hibernate/boot/jaxb/hbm/spi/JaxbHbmManyToOneType;Ljava/lang/String;Lorg/hibernate/boot/model/source/spi/NaturalIdMutability;)V
     216: goto          475
     219: ldc           #27                 // class org/hibernate/boot/jaxb/hbm/spi/JaxbHbmOneToOneType
     221: aload_2
     222: invokevirtual #7                  // Method java/lang/Class.isInstance:(Ljava/lang/Object;)Z
     225: ifeq          243
     228: aload_0
     229: aload_1
     230: aload_2
     231: checkcast     #27                 // class org/hibernate/boot/jaxb/hbm/spi/JaxbHbmOneToOneType
     234: aload_3
     235: aload         4
     237: invokestatic  #28                 // Method processOneToOneAttribute:(Lorg/hibernate/boot/model/source/internal/hbm/MappingDocument;Lorg/hibernate/boot/model/source/internal/hbm/AttributesHelper$Callback;Lorg/hibernate/boot/jaxb/hbm/spi/JaxbHbmOneToOneType;Ljava/lang/String;Lorg/hibernate/boot/model/source/spi/NaturalIdMutability;)V
     240: goto          475
     243: ldc           #29                 // class org/hibernate/boot/jaxb/hbm/spi/JaxbHbmAnyAssociationType
     245: aload_2
     246: invokevirtual #7                  // Method java/lang/Class.isInstance:(Ljava/lang/Object;)Z
     249: ifeq          267
     252: aload_0
     253: aload_1
     254: aload_2
     255: checkcast     #29                 // class org/hibernate/boot/jaxb/hbm/spi/JaxbHbmAnyAssociationType
     258: aload_3
     259: aload         4
     261: invokestatic  #30                 // Method processAnyAttribute:(Lorg/hibernate/boot/model/source/internal/hbm/MappingDocument;Lorg/hibernate/boot/model/source/internal/hbm/AttributesHelper$Callback;Lorg/hibernate/boot/jaxb/hbm/spi/JaxbHbmAnyAssociationType;Ljava/lang/String;Lorg/hibernate/boot/model/source/spi/NaturalIdMutability;)V
     264: goto          475
     267: ldc           #31                 // class org/hibernate/boot/jaxb/hbm/spi/JaxbHbmMapType
     269: aload_2
     270: invokevirtual #7                  // Method java/lang/Class.isInstance:(Ljava/lang/Object;)Z
     273: ifeq          288
     276: aload_0
     277: aload_1
     278: aload_2
     279: checkcast     #31                 // class org/hibernate/boot/jaxb/hbm/spi/JaxbHbmMapType
     282: invokestatic  #32                 // Method processMapAttribute:(Lorg/hibernate/boot/model/source/internal/hbm/MappingDocument;Lorg/hibernate/boot/model/source/internal/hbm/AttributesHelper$Callback;Lorg/hibernate/boot/jaxb/hbm/spi/JaxbHbmMapType;)V
     285: goto          475
     288: ldc           #33                 // class org/hibernate/boot/jaxb/hbm/spi/JaxbHbmListType
     290: aload_2
     291: invokevirtual #7                  // Method java/lang/Class.isInstance:(Ljava/lang/Object;)Z
     294: ifeq          309
     297: aload_0
     298: aload_1
     299: aload_2
     300: checkcast     #33                 // class org/hibernate/boot/jaxb/hbm/spi/JaxbHbmListType
     303: invokestatic  #34                 // Method processListAttribute:(Lorg/hibernate/boot/model/source/internal/hbm/MappingDocument;Lorg/hibernate/boot/model/source/internal/hbm/AttributesHelper$Callback;Lorg/hibernate/boot/jaxb/hbm/spi/JaxbHbmListType;)V
     306: goto          475
     309: ldc           #35                 // class org/hibernate/boot/jaxb/hbm/spi/JaxbHbmArrayType
     311: aload_2
     312: invokevirtual #7                  // Method java/lang/Class.isInstance:(Ljava/lang/Object;)Z
     315: ifeq          330
     318: aload_0
     319: aload_1
     320: aload_2
     321: checkcast     #35                 // class org/hibernate/boot/jaxb/hbm/spi/JaxbHbmArrayType
     324: invokestatic  #36                 // Method processArrayAttribute:(Lorg/hibernate/boot/model/source/internal/hbm/MappingDocument;Lorg/hibernate/boot/model/source/internal/hbm/AttributesHelper$Callback;Lorg/hibernate/boot/jaxb/hbm/spi/JaxbHbmArrayType;)V
     327: goto          475
     330: ldc           #37                 // class org/hibernate/boot/jaxb/hbm/spi/JaxbHbmPrimitiveArrayType
     332: aload_2
     333: invokevirtual #7                  // Method java/lang/Class.isInstance:(Ljava/lang/Object;)Z
     336: ifeq          351
     339: aload_0
     340: aload_1
     341: aload_2
     342: checkcast     #37                 // class org/hibernate/boot/jaxb/hbm/spi/JaxbHbmPrimitiveArrayType
     345: invokestatic  #38                 // Method processPrimitiveArrayAttribute:(Lorg/hibernate/boot/model/source/internal/hbm/MappingDocument;Lorg/hibernate/boot/model/source/internal/hbm/AttributesHelper$Callback;Lorg/hibernate/boot/jaxb/hbm/spi/JaxbHbmPrimitiveArrayType;)V
     348: goto          475
     351: ldc           #39                 // class org/hibernate/boot/jaxb/hbm/spi/JaxbHbmSetType
     353: aload_2
     354: invokevirtual #7                  // Method java/lang/Class.isInstance:(Ljava/lang/Object;)Z
     357: ifeq          372
     360: aload_0
     361: aload_1
     362: aload_2
     363: checkcast     #39                 // class org/hibernate/boot/jaxb/hbm/spi/JaxbHbmSetType
     366: invokestatic  #40                 // Method processSetAttribute:(Lorg/hibernate/boot/model/source/internal/hbm/MappingDocument;Lorg/hibernate/boot/model/source/internal/hbm/AttributesHelper$Callback;Lorg/hibernate/boot/jaxb/hbm/spi/JaxbHbmSetType;)V
     369: goto          475
     372: ldc           #41                 // class org/hibernate/boot/jaxb/hbm/spi/JaxbHbmBagCollectionType
     374: aload_2
     375: invokevirtual #7                  // Method java/lang/Class.isInstance:(Ljava/lang/Object;)Z
     378: ifeq          393
     381: aload_0
     382: aload_1
     383: aload_2
     384: checkcast     #41                 // class org/hibernate/boot/jaxb/hbm/spi/JaxbHbmBagCollectionType
     387: invokestatic  #42                 // Method processBagAttribute:(Lorg/hibernate/boot/model/source/internal/hbm/MappingDocument;Lorg/hibernate/boot/model/source/internal/hbm/AttributesHelper$Callback;Lorg/hibernate/boot/jaxb/hbm/spi/JaxbHbmBagCollectionType;)V
     390: goto          475
     393: ldc           #43                 // class org/hibernate/boot/jaxb/hbm/spi/JaxbHbmIdBagCollectionType
     395: aload_2
     396: invokevirtual #7                  // Method java/lang/Class.isInstance:(Ljava/lang/Object;)Z
     399: ifeq          414
     402: aload_0
     403: aload_1
     404: aload_2
     405: checkcast     #43                 // class org/hibernate/boot/jaxb/hbm/spi/JaxbHbmIdBagCollectionType
     408: invokestatic  #44                 // Method processIdBagAttribute:(Lorg/hibernate/boot/model/source/internal/hbm/MappingDocument;Lorg/hibernate/boot/model/source/internal/hbm/AttributesHelper$Callback;Lorg/hibernate/boot/jaxb/hbm/spi/JaxbHbmIdBagCollectionType;)V
     411: goto          475
     414: ldc           #45                 // class org/hibernate/boot/jaxb/hbm/spi/JaxbHbmNestedCompositeElementType
     416: aload_2
     417: invokevirtual #7                  // Method java/lang/Class.isInstance:(Ljava/lang/Object;)Z
     420: ifeq          438
     423: aload_0
     424: aload_1
     425: aload_2
     426: checkcast     #45                 // class org/hibernate/boot/jaxb/hbm/spi/JaxbHbmNestedCompositeElementType
     429: aload_3
     430: aload         4
     432: invokestatic  #46                 // Method processNestedEmbeddedElement:(Lorg/hibernate/boot/model/source/internal/hbm/MappingDocument;Lorg/hibernate/boot/model/source/internal/hbm/AttributesHelper$Callback;Lorg/hibernate/boot/jaxb/hbm/spi/JaxbHbmNestedCompositeElementType;Ljava/lang/String;Lorg/hibernate/boot/model/source/spi/NaturalIdMutability;)V
     435: goto          475
     438: new           #47                 // class org/hibernate/boot/MappingException
     441: dup
     442: new           #48                 // class java/lang/StringBuilder
     445: dup
     446: invokespecial #49                 // Method java/lang/StringBuilder."<init>":()V
     449: ldc           #50                 // String Encountered unexpected JAXB mapping type for attribute :
     451: invokevirtual #51                 // Method java/lang/StringBuilder.append:(Ljava/lang/String;)Ljava/lang/StringBuilder;
     454: aload_2
     455: invokevirtual #52                 // Method java/lang/Object.getClass:()Ljava/lang/Class;
     458: invokevirtual #53                 // Method java/lang/Class.getName:()Ljava/lang/String;
     461: invokevirtual #51                 // Method java/lang/StringBuilder.append:(Ljava/lang/String;)Ljava/lang/StringBuilder;
     464: invokevirtual #54                 // Method java/lang/StringBuilder.toString:()Ljava/lang/String;
     467: aload_0
     468: invokevirtual #55                 // Method org/hibernate/boot/model/source/internal/hbm/MappingDocument.getOrigin:()Lorg/hibernate/boot/jaxb/Origin;
     471: invokespecial #56                 // Method org/hibernate/boot/MappingException."<init>":(Ljava/lang/String;Lorg/hibernate/boot/jaxb/Origin;)V
     474: athrow
     475: return

  public static void processCompositeKeySubAttributes(org.hibernate.boot.model.source.internal.hbm.MappingDocument, org.hibernate.boot.model.source.internal.hbm.AttributesHelper$Callback, java.util.List<?>);
    Code:
       0: aload_2
       1: invokeinterface #2,  1            // InterfaceMethod java/util/List.iterator:()Ljava/util/Iterator;
       6: astore_3
       7: aload_3
       8: invokeinterface #3,  1            // InterfaceMethod java/util/Iterator.hasNext:()Z
      13: ifeq          141
      16: aload_3
      17: invokeinterface #4,  1            // InterfaceMethod java/util/Iterator.next:()Ljava/lang/Object;
      22: astore        4
      24: ldc           #9                  // class org/hibernate/boot/jaxb/hbm/spi/JaxbHbmCompositeKeyBasicAttributeType
      26: aload         4
      28: invokevirtual #7                  // Method java/lang/Class.isInstance:(Ljava/lang/Object;)Z
      31: ifeq          62
      34: aload_1
      35: new           #10                 // class org/hibernate/boot/model/source/internal/hbm/CompositeIdentifierSingularAttributeSourceBasicImpl
      38: dup
      39: aload_0
      40: aload_1
      41: invokeinterface #11,  1           // InterfaceMethod org/hibernate/boot/model/source/internal/hbm/AttributesHelper$Callback.getAttributeSourceContainer:()Lorg/hibernate/boot/model/source/spi/AttributeSourceContainer;
      46: aload         4
      48: checkcast     #9                  // class org/hibernate/boot/jaxb/hbm/spi/JaxbHbmCompositeKeyBasicAttributeType
      51: invokespecial #12                 // Method org/hibernate/boot/model/source/internal/hbm/CompositeIdentifierSingularAttributeSourceBasicImpl."<init>":(Lorg/hibernate/boot/model/source/internal/hbm/MappingDocument;Lorg/hibernate/boot/model/source/spi/AttributeSourceContainer;Lorg/hibernate/boot/jaxb/hbm/spi/JaxbHbmCompositeKeyBasicAttributeType;)V
      54: invokeinterface #13,  2           // InterfaceMethod org/hibernate/boot/model/source/internal/hbm/AttributesHelper$Callback.addAttributeSource:(Lorg/hibernate/boot/model/source/spi/AttributeSource;)V
      59: goto          138
      62: ldc           #14                 // class org/hibernate/boot/jaxb/hbm/spi/JaxbHbmCompositeKeyManyToOneType
      64: aload         4
      66: invokevirtual #7                  // Method java/lang/Class.isInstance:(Ljava/lang/Object;)Z
      69: ifeq          100
      72: aload_1
      73: new           #15                 // class org/hibernate/boot/model/source/internal/hbm/CompositeIdentifierSingularAttributeSourceManyToOneImpl
      76: dup
      77: aload_0
      78: aload_1
      79: invokeinterface #11,  1           // InterfaceMethod org/hibernate/boot/model/source/internal/hbm/AttributesHelper$Callback.getAttributeSourceContainer:()Lorg/hibernate/boot/model/source/spi/AttributeSourceContainer;
      84: aload         4
      86: checkcast     #14                 // class org/hibernate/boot/jaxb/hbm/spi/JaxbHbmCompositeKeyManyToOneType
      89: invokespecial #16                 // Method org/hibernate/boot/model/source/internal/hbm/CompositeIdentifierSingularAttributeSourceManyToOneImpl."<init>":(Lorg/hibernate/boot/model/source/internal/hbm/MappingDocument;Lorg/hibernate/boot/model/source/spi/AttributeSourceContainer;Lorg/hibernate/boot/jaxb/hbm/spi/JaxbHbmCompositeKeyManyToOneType;)V
      92: invokeinterface #13,  2           // InterfaceMethod org/hibernate/boot/model/source/internal/hbm/AttributesHelper$Callback.addAttributeSource:(Lorg/hibernate/boot/model/source/spi/AttributeSource;)V
      97: goto          138
     100: new           #47                 // class org/hibernate/boot/MappingException
     103: dup
     104: new           #48                 // class java/lang/StringBuilder
     107: dup
     108: invokespecial #49                 // Method java/lang/StringBuilder."<init>":()V
     111: ldc           #57                 // String Unexpected composite-key sub-attribute type :
     113: invokevirtual #51                 // Method java/lang/StringBuilder.append:(Ljava/lang/String;)Ljava/lang/StringBuilder;
     116: aload         4
     118: invokevirtual #52                 // Method java/lang/Object.getClass:()Ljava/lang/Class;
     121: invokevirtual #53                 // Method java/lang/Class.getName:()Ljava/lang/String;
     124: invokevirtual #51                 // Method java/lang/StringBuilder.append:(Ljava/lang/String;)Ljava/lang/StringBuilder;
     127: invokevirtual #54                 // Method java/lang/StringBuilder.toString:()Ljava/lang/String;
     130: aload_0
     131: invokevirtual #55                 // Method org/hibernate/boot/model/source/internal/hbm/MappingDocument.getOrigin:()Lorg/hibernate/boot/jaxb/Origin;
     134: invokespecial #56                 // Method org/hibernate/boot/MappingException."<init>":(Ljava/lang/String;Lorg/hibernate/boot/jaxb/Origin;)V
     137: athrow
     138: goto          7
     141: return

  private static void processPropertiesGroup(org.hibernate.boot.model.source.internal.hbm.MappingDocument, org.hibernate.boot.model.source.internal.hbm.AttributesHelper$Callback, org.hibernate.boot.jaxb.hbm.spi.JaxbHbmPropertiesType, java.lang.String, org.hibernate.boot.model.source.spi.NaturalIdMutability);
    Code:
       0: aload_2
       1: invokevirtual #58                 // Method org/hibernate/boot/jaxb/hbm/spi/JaxbHbmPropertiesType.getName:()Ljava/lang/String;
       4: astore        5
       6: aload_1
       7: invokeinterface #11,  1           // InterfaceMethod org/hibernate/boot/model/source/internal/hbm/AttributesHelper$Callback.getAttributeSourceContainer:()Lorg/hibernate/boot/model/source/spi/AttributeSourceContainer;
      12: invokeinterface #59,  1           // InterfaceMethod org/hibernate/boot/model/source/spi/AttributeSourceContainer.getAttributeRoleBase:()Lorg/hibernate/boot/model/source/spi/AttributeRole;
      17: aload         5
      19: invokevirtual #60                 // Method org/hibernate/boot/model/source/spi/AttributeRole.append:(Ljava/lang/String;)Lorg/hibernate/boot/model/source/spi/AttributeRole;
      22: astore        6
      24: aload_1
      25: invokeinterface #11,  1           // InterfaceMethod org/hibernate/boot/model/source/internal/hbm/AttributesHelper$Callback.getAttributeSourceContainer:()Lorg/hibernate/boot/model/source/spi/AttributeSourceContainer;
      30: invokeinterface #61,  1           // InterfaceMethod org/hibernate/boot/model/source/spi/AttributeSourceContainer.getAttributePathBase:()Lorg/hibernate/boot/model/source/spi/AttributePath;
      35: aload         5
      37: invokevirtual #62                 // Method org/hibernate/boot/model/source/spi/AttributePath.append:(Ljava/lang/String;)Lorg/hibernate/boot/model/source/spi/AttributePath;
      40: astore        7
      42: new           #63                 // class org/hibernate/boot/model/source/internal/hbm/EmbeddableSourceVirtualImpl
      45: dup
      46: aload_0
      47: aload_1
      48: new           #64                 // class org/hibernate/boot/model/source/internal/hbm/AttributesHelper$1
      51: dup
      52: aload         6
      54: aload         7
      56: aload_1
      57: invokespecial #65                 // Method org/hibernate/boot/model/source/internal/hbm/AttributesHelper$1."<init>":(Lorg/hibernate/boot/model/source/spi/AttributeRole;Lorg/hibernate/boot/model/source/spi/AttributePath;Lorg/hibernate/boot/model/source/internal/hbm/AttributesHelper$Callback;)V
      60: aload_2
      61: invokevirtual #66                 // Method org/hibernate/boot/jaxb/hbm/spi/JaxbHbmPropertiesType.getAttributes:()Ljava/util/List;
      64: aload_3
      65: aload         4
      67: aload_2
      68: invokespecial #67                 // Method org/hibernate/boot/model/source/internal/hbm/EmbeddableSourceVirtualImpl."<init>":(Lorg/hibernate/boot/model/source/internal/hbm/MappingDocument;Lorg/hibernate/boot/model/source/internal/hbm/AttributesHelper$Callback;Lorg/hibernate/boot/model/source/internal/hbm/EmbeddableSourceContainer;Ljava/util/List;Ljava/lang/String;Lorg/hibernate/boot/model/source/spi/NaturalIdMutability;Lorg/hibernate/boot/jaxb/hbm/spi/JaxbHbmPropertiesType;)V
      71: astore        8
      73: new           #68                 // class org/hibernate/boot/model/source/internal/hbm/AttributesHelper$2
      76: dup
      77: invokespecial #69                 // Method org/hibernate/boot/model/source/internal/hbm/AttributesHelper$2."<init>":()V
      80: astore        9
      82: new           #70                 // class org/hibernate/boot/model/source/internal/hbm/AttributesHelper$3
      85: dup
      86: aload_2
      87: aload         9
      89: invokespecial #71                 // Method org/hibernate/boot/model/source/internal/hbm/AttributesHelper$3."<init>":(Lorg/hibernate/boot/jaxb/hbm/spi/JaxbHbmPropertiesType;Lorg/hibernate/boot/model/source/spi/EmbeddableMapping;)V
      92: astore        10
      94: new           #72                 // class org/hibernate/boot/model/source/internal/hbm/AttributesHelper$4
      97: dup
      98: aload_0
      99: aload         10
     101: aload         8
     103: aload         4
     105: aload_2
     106: aload         7
     108: aload         6
     110: aload_0
     111: invokespecial #73                 // Method org/hibernate/boot/model/source/internal/hbm/AttributesHelper$4."<init>":(Lorg/hibernate/boot/model/source/internal/hbm/MappingDocument;Lorg/hibernate/boot/model/source/spi/EmbeddedAttributeMapping;Lorg/hibernate/boot/model/source/spi/EmbeddableSource;Lorg/hibernate/boot/model/source/spi/NaturalIdMutability;Lorg/hibernate/boot/jaxb/hbm/spi/JaxbHbmPropertiesType;Lorg/hibernate/boot/model/source/spi/AttributePath;Lorg/hibernate/boot/model/source/spi/AttributeRole;Lorg/hibernate/boot/model/source/internal/hbm/MappingDocument;)V
     114: astore        11
     116: aload_1
     117: aload         11
     119: invokeinterface #13,  2           // InterfaceMethod org/hibernate/boot/model/source/internal/hbm/AttributesHelper$Callback.addAttributeSource:(Lorg/hibernate/boot/model/source/spi/AttributeSource;)V
     124: return

  public static void processBasicAttribute(org.hibernate.boot.model.source.internal.hbm.MappingDocument, org.hibernate.boot.model.source.internal.hbm.AttributesHelper$Callback, org.hibernate.boot.jaxb.hbm.spi.JaxbHbmBasicAttributeType, java.lang.String, org.hibernate.boot.model.source.spi.NaturalIdMutability);
    Code:
       0: aload_1
       1: new           #74                 // class org/hibernate/boot/model/source/internal/hbm/SingularAttributeSourceBasicImpl
       4: dup
       5: aload_0
       6: aload_1
       7: invokeinterface #11,  1           // InterfaceMethod org/hibernate/boot/model/source/internal/hbm/AttributesHelper$Callback.getAttributeSourceContainer:()Lorg/hibernate/boot/model/source/spi/AttributeSourceContainer;
      12: aload_2
      13: aload_3
      14: aload         4
      16: invokespecial #75                 // Method org/hibernate/boot/model/source/internal/hbm/SingularAttributeSourceBasicImpl."<init>":(Lorg/hibernate/boot/model/source/internal/hbm/MappingDocument;Lorg/hibernate/boot/model/source/spi/AttributeSourceContainer;Lorg/hibernate/boot/jaxb/hbm/spi/JaxbHbmBasicAttributeType;Ljava/lang/String;Lorg/hibernate/boot/model/source/spi/NaturalIdMutability;)V
      19: invokeinterface #13,  2           // InterfaceMethod org/hibernate/boot/model/source/internal/hbm/AttributesHelper$Callback.addAttributeSource:(Lorg/hibernate/boot/model/source/spi/AttributeSource;)V
      24: return

  public static void processEmbeddedAttribute(org.hibernate.boot.model.source.internal.hbm.MappingDocument, org.hibernate.boot.model.source.internal.hbm.AttributesHelper$Callback, org.hibernate.boot.jaxb.hbm.spi.JaxbHbmCompositeAttributeType, java.lang.String, org.hibernate.boot.model.source.spi.NaturalIdMutability);
    Code:
       0: aload_1
       1: new           #76                 // class org/hibernate/boot/model/source/internal/hbm/SingularAttributeSourceEmbeddedImpl
       4: dup
       5: aload_0
       6: aload_1
       7: invokeinterface #11,  1           // InterfaceMethod org/hibernate/boot/model/source/internal/hbm/AttributesHelper$Callback.getAttributeSourceContainer:()Lorg/hibernate/boot/model/source/spi/AttributeSourceContainer;
      12: aload_2
      13: aload         4
      15: aload_3
      16: invokespecial #77                 // Method org/hibernate/boot/model/source/internal/hbm/SingularAttributeSourceEmbeddedImpl."<init>":(Lorg/hibernate/boot/model/source/internal/hbm/MappingDocument;Lorg/hibernate/boot/model/source/spi/AttributeSourceContainer;Lorg/hibernate/boot/jaxb/hbm/spi/JaxbHbmCompositeAttributeType;Lorg/hibernate/boot/model/source/spi/NaturalIdMutability;Ljava/lang/String;)V
      19: invokeinterface #13,  2           // InterfaceMethod org/hibernate/boot/model/source/internal/hbm/AttributesHelper$Callback.addAttributeSource:(Lorg/hibernate/boot/model/source/spi/AttributeSource;)V
      24: return

  private static void processNestedEmbeddedElement(org.hibernate.boot.model.source.internal.hbm.MappingDocument, org.hibernate.boot.model.source.internal.hbm.AttributesHelper$Callback, org.hibernate.boot.jaxb.hbm.spi.JaxbHbmNestedCompositeElementType, java.lang.String, org.hibernate.boot.model.source.spi.NaturalIdMutability);
    Code:
       0: aload_1
       1: new           #76                 // class org/hibernate/boot/model/source/internal/hbm/SingularAttributeSourceEmbeddedImpl
       4: dup
       5: aload_0
       6: aload_1
       7: invokeinterface #11,  1           // InterfaceMethod org/hibernate/boot/model/source/internal/hbm/AttributesHelper$Callback.getAttributeSourceContainer:()Lorg/hibernate/boot/model/source/spi/AttributeSourceContainer;
      12: aload_2
      13: aload         4
      15: aload_3
      16: invokespecial #78                 // Method org/hibernate/boot/model/source/internal/hbm/SingularAttributeSourceEmbeddedImpl."<init>":(Lorg/hibernate/boot/model/source/internal/hbm/MappingDocument;Lorg/hibernate/boot/model/source/spi/AttributeSourceContainer;Lorg/hibernate/boot/jaxb/hbm/spi/JaxbHbmNestedCompositeElementType;Lorg/hibernate/boot/model/source/spi/NaturalIdMutability;Ljava/lang/String;)V
      19: invokeinterface #13,  2           // InterfaceMethod org/hibernate/boot/model/source/internal/hbm/AttributesHelper$Callback.addAttributeSource:(Lorg/hibernate/boot/model/source/spi/AttributeSource;)V
      24: return

  public static void processDynamicComponentAttribute(org.hibernate.boot.model.source.internal.hbm.MappingDocument, org.hibernate.boot.model.source.internal.hbm.AttributesHelper$Callback, org.hibernate.boot.jaxb.hbm.spi.JaxbHbmDynamicComponentType, java.lang.String, org.hibernate.boot.model.source.spi.NaturalIdMutability);
    Code:
       0: aload_1
       1: new           #76                 // class org/hibernate/boot/model/source/internal/hbm/SingularAttributeSourceEmbeddedImpl
       4: dup
       5: aload_0
       6: aload_1
       7: invokeinterface #11,  1           // InterfaceMethod org/hibernate/boot/model/source/internal/hbm/AttributesHelper$Callback.getAttributeSourceContainer:()Lorg/hibernate/boot/model/source/spi/AttributeSourceContainer;
      12: aload_2
      13: aload         4
      15: aload_3
      16: invokespecial #79                 // Method org/hibernate/boot/model/source/internal/hbm/SingularAttributeSourceEmbeddedImpl."<init>":(Lorg/hibernate/boot/model/source/internal/hbm/MappingDocument;Lorg/hibernate/boot/model/source/spi/AttributeSourceContainer;Lorg/hibernate/boot/jaxb/hbm/spi/JaxbHbmDynamicComponentType;Lorg/hibernate/boot/model/source/spi/NaturalIdMutability;Ljava/lang/String;)V
      19: invokeinterface #13,  2           // InterfaceMethod org/hibernate/boot/model/source/internal/hbm/AttributesHelper$Callback.addAttributeSource:(Lorg/hibernate/boot/model/source/spi/AttributeSource;)V
      24: return

  public static void processManyToOneAttribute(org.hibernate.boot.model.source.internal.hbm.MappingDocument, org.hibernate.boot.model.source.internal.hbm.AttributesHelper$Callback, org.hibernate.boot.jaxb.hbm.spi.JaxbHbmManyToOneType, java.lang.String, org.hibernate.boot.model.source.spi.NaturalIdMutability);
    Code:
       0: aload_1
       1: new           #80                 // class org/hibernate/boot/model/source/internal/hbm/SingularAttributeSourceManyToOneImpl
       4: dup
       5: aload_0
       6: aload_1
       7: invokeinterface #11,  1           // InterfaceMethod org/hibernate/boot/model/source/internal/hbm/AttributesHelper$Callback.getAttributeSourceContainer:()Lorg/hibernate/boot/model/source/spi/AttributeSourceContainer;
      12: aload_2
      13: aload_3
      14: aload         4
      16: invokespecial #81                 // Method org/hibernate/boot/model/source/internal/hbm/SingularAttributeSourceManyToOneImpl."<init>":(Lorg/hibernate/boot/model/source/internal/hbm/MappingDocument;Lorg/hibernate/boot/model/source/spi/AttributeSourceContainer;Lorg/hibernate/boot/jaxb/hbm/spi/JaxbHbmManyToOneType;Ljava/lang/String;Lorg/hibernate/boot/model/source/spi/NaturalIdMutability;)V
      19: invokeinterface #13,  2           // InterfaceMethod org/hibernate/boot/model/source/internal/hbm/AttributesHelper$Callback.addAttributeSource:(Lorg/hibernate/boot/model/source/spi/AttributeSource;)V
      24: return

  public static void processOneToOneAttribute(org.hibernate.boot.model.source.internal.hbm.MappingDocument, org.hibernate.boot.model.source.internal.hbm.AttributesHelper$Callback, org.hibernate.boot.jaxb.hbm.spi.JaxbHbmOneToOneType, java.lang.String, org.hibernate.boot.model.source.spi.NaturalIdMutability);
    Code:
       0: aload_1
       1: new           #82                 // class org/hibernate/boot/model/source/internal/hbm/SingularAttributeSourceOneToOneImpl
       4: dup
       5: aload_0
       6: aload_1
       7: invokeinterface #11,  1           // InterfaceMethod org/hibernate/boot/model/source/internal/hbm/AttributesHelper$Callback.getAttributeSourceContainer:()Lorg/hibernate/boot/model/source/spi/AttributeSourceContainer;
      12: aload_2
      13: aload_3
      14: aload         4
      16: invokespecial #83                 // Method org/hibernate/boot/model/source/internal/hbm/SingularAttributeSourceOneToOneImpl."<init>":(Lorg/hibernate/boot/model/source/internal/hbm/MappingDocument;Lorg/hibernate/boot/model/source/spi/AttributeSourceContainer;Lorg/hibernate/boot/jaxb/hbm/spi/JaxbHbmOneToOneType;Ljava/lang/String;Lorg/hibernate/boot/model/source/spi/NaturalIdMutability;)V
      19: invokeinterface #13,  2           // InterfaceMethod org/hibernate/boot/model/source/internal/hbm/AttributesHelper$Callback.addAttributeSource:(Lorg/hibernate/boot/model/source/spi/AttributeSource;)V
      24: return

  public static void processAnyAttribute(org.hibernate.boot.model.source.internal.hbm.MappingDocument, org.hibernate.boot.model.source.internal.hbm.AttributesHelper$Callback, org.hibernate.boot.jaxb.hbm.spi.JaxbHbmAnyAssociationType, java.lang.String, org.hibernate.boot.model.source.spi.NaturalIdMutability);
    Code:
       0: aload_1
       1: new           #84                 // class org/hibernate/boot/model/source/internal/hbm/SingularAttributeSourceAnyImpl
       4: dup
       5: aload_0
       6: aload_1
       7: invokeinterface #11,  1           // InterfaceMethod org/hibernate/boot/model/source/internal/hbm/AttributesHelper$Callback.getAttributeSourceContainer:()Lorg/hibernate/boot/model/source/spi/AttributeSourceContainer;
      12: aload_2
      13: aload_3
      14: aload         4
      16: invokespecial #85                 // Method org/hibernate/boot/model/source/internal/hbm/SingularAttributeSourceAnyImpl."<init>":(Lorg/hibernate/boot/model/source/internal/hbm/MappingDocument;Lorg/hibernate/boot/model/source/spi/AttributeSourceContainer;Lorg/hibernate/boot/jaxb/hbm/spi/JaxbHbmAnyAssociationType;Ljava/lang/String;Lorg/hibernate/boot/model/source/spi/NaturalIdMutability;)V
      19: invokeinterface #13,  2           // InterfaceMethod org/hibernate/boot/model/source/internal/hbm/AttributesHelper$Callback.addAttributeSource:(Lorg/hibernate/boot/model/source/spi/AttributeSource;)V
      24: return

  public static void processMapAttribute(org.hibernate.boot.model.source.internal.hbm.MappingDocument, org.hibernate.boot.model.source.internal.hbm.AttributesHelper$Callback, org.hibernate.boot.jaxb.hbm.spi.JaxbHbmMapType);
    Code:
       0: aload_1
       1: new           #86                 // class org/hibernate/boot/model/source/internal/hbm/PluralAttributeSourceMapImpl
       4: dup
       5: aload_0
       6: aload_2
       7: aload_1
       8: invokeinterface #11,  1           // InterfaceMethod org/hibernate/boot/model/source/internal/hbm/AttributesHelper$Callback.getAttributeSourceContainer:()Lorg/hibernate/boot/model/source/spi/AttributeSourceContainer;
      13: invokespecial #87                 // Method org/hibernate/boot/model/source/internal/hbm/PluralAttributeSourceMapImpl."<init>":(Lorg/hibernate/boot/model/source/internal/hbm/MappingDocument;Lorg/hibernate/boot/jaxb/hbm/spi/JaxbHbmMapType;Lorg/hibernate/boot/model/source/spi/AttributeSourceContainer;)V
      16: invokeinterface #13,  2           // InterfaceMethod org/hibernate/boot/model/source/internal/hbm/AttributesHelper$Callback.addAttributeSource:(Lorg/hibernate/boot/model/source/spi/AttributeSource;)V
      21: return

  public static void processListAttribute(org.hibernate.boot.model.source.internal.hbm.MappingDocument, org.hibernate.boot.model.source.internal.hbm.AttributesHelper$Callback, org.hibernate.boot.jaxb.hbm.spi.JaxbHbmListType);
    Code:
       0: aload_1
       1: new           #88                 // class org/hibernate/boot/model/source/internal/hbm/PluralAttributeSourceListImpl
       4: dup
       5: aload_0
       6: aload_2
       7: aload_1
       8: invokeinterface #11,  1           // InterfaceMethod org/hibernate/boot/model/source/internal/hbm/AttributesHelper$Callback.getAttributeSourceContainer:()Lorg/hibernate/boot/model/source/spi/AttributeSourceContainer;
      13: invokespecial #89                 // Method org/hibernate/boot/model/source/internal/hbm/PluralAttributeSourceListImpl."<init>":(Lorg/hibernate/boot/model/source/internal/hbm/MappingDocument;Lorg/hibernate/boot/jaxb/hbm/spi/JaxbHbmListType;Lorg/hibernate/boot/model/source/spi/AttributeSourceContainer;)V
      16: invokeinterface #13,  2           // InterfaceMethod org/hibernate/boot/model/source/internal/hbm/AttributesHelper$Callback.addAttributeSource:(Lorg/hibernate/boot/model/source/spi/AttributeSource;)V
      21: return

  public static void processArrayAttribute(org.hibernate.boot.model.source.internal.hbm.MappingDocument, org.hibernate.boot.model.source.internal.hbm.AttributesHelper$Callback, org.hibernate.boot.jaxb.hbm.spi.JaxbHbmArrayType);
    Code:
       0: aload_1
       1: new           #90                 // class org/hibernate/boot/model/source/internal/hbm/PluralAttributeSourceArrayImpl
       4: dup
       5: aload_0
       6: aload_2
       7: aload_1
       8: invokeinterface #11,  1           // InterfaceMethod org/hibernate/boot/model/source/internal/hbm/AttributesHelper$Callback.getAttributeSourceContainer:()Lorg/hibernate/boot/model/source/spi/AttributeSourceContainer;
      13: invokespecial #91                 // Method org/hibernate/boot/model/source/internal/hbm/PluralAttributeSourceArrayImpl."<init>":(Lorg/hibernate/boot/model/source/internal/hbm/MappingDocument;Lorg/hibernate/boot/jaxb/hbm/spi/JaxbHbmArrayType;Lorg/hibernate/boot/model/source/spi/AttributeSourceContainer;)V
      16: invokeinterface #13,  2           // InterfaceMethod org/hibernate/boot/model/source/internal/hbm/AttributesHelper$Callback.addAttributeSource:(Lorg/hibernate/boot/model/source/spi/AttributeSource;)V
      21: return

  public static void processPrimitiveArrayAttribute(org.hibernate.boot.model.source.internal.hbm.MappingDocument, org.hibernate.boot.model.source.internal.hbm.AttributesHelper$Callback, org.hibernate.boot.jaxb.hbm.spi.JaxbHbmPrimitiveArrayType);
    Code:
       0: aload_1
       1: new           #92                 // class org/hibernate/boot/model/source/internal/hbm/PluralAttributeSourcePrimitiveArrayImpl
       4: dup
       5: aload_0
       6: aload_2
       7: aload_1
       8: invokeinterface #11,  1           // InterfaceMethod org/hibernate/boot/model/source/internal/hbm/AttributesHelper$Callback.getAttributeSourceContainer:()Lorg/hibernate/boot/model/source/spi/AttributeSourceContainer;
      13: invokespecial #93                 // Method org/hibernate/boot/model/source/internal/hbm/PluralAttributeSourcePrimitiveArrayImpl."<init>":(Lorg/hibernate/boot/model/source/internal/hbm/MappingDocument;Lorg/hibernate/boot/jaxb/hbm/spi/JaxbHbmPrimitiveArrayType;Lorg/hibernate/boot/model/source/spi/AttributeSourceContainer;)V
      16: invokeinterface #13,  2           // InterfaceMethod org/hibernate/boot/model/source/internal/hbm/AttributesHelper$Callback.addAttributeSource:(Lorg/hibernate/boot/model/source/spi/AttributeSource;)V
      21: return

  public static void processSetAttribute(org.hibernate.boot.model.source.internal.hbm.MappingDocument, org.hibernate.boot.model.source.internal.hbm.AttributesHelper$Callback, org.hibernate.boot.jaxb.hbm.spi.JaxbHbmSetType);
    Code:
       0: aload_1
       1: new           #94                 // class org/hibernate/boot/model/source/internal/hbm/PluralAttributeSourceSetImpl
       4: dup
       5: aload_0
       6: aload_2
       7: aload_1
       8: invokeinterface #11,  1           // InterfaceMethod org/hibernate/boot/model/source/internal/hbm/AttributesHelper$Callback.getAttributeSourceContainer:()Lorg/hibernate/boot/model/source/spi/AttributeSourceContainer;
      13: invokespecial #95                 // Method org/hibernate/boot/model/source/internal/hbm/PluralAttributeSourceSetImpl."<init>":(Lorg/hibernate/boot/model/source/internal/hbm/MappingDocument;Lorg/hibernate/boot/jaxb/hbm/spi/JaxbHbmSetType;Lorg/hibernate/boot/model/source/spi/AttributeSourceContainer;)V
      16: invokeinterface #13,  2           // InterfaceMethod org/hibernate/boot/model/source/internal/hbm/AttributesHelper$Callback.addAttributeSource:(Lorg/hibernate/boot/model/source/spi/AttributeSource;)V
      21: return

  public static void processBagAttribute(org.hibernate.boot.model.source.internal.hbm.MappingDocument, org.hibernate.boot.model.source.internal.hbm.AttributesHelper$Callback, org.hibernate.boot.jaxb.hbm.spi.JaxbHbmBagCollectionType);
    Code:
       0: aload_1
       1: new           #96                 // class org/hibernate/boot/model/source/internal/hbm/PluralAttributeSourceBagImpl
       4: dup
       5: aload_0
       6: aload_2
       7: aload_1
       8: invokeinterface #11,  1           // InterfaceMethod org/hibernate/boot/model/source/internal/hbm/AttributesHelper$Callback.getAttributeSourceContainer:()Lorg/hibernate/boot/model/source/spi/AttributeSourceContainer;
      13: invokespecial #97                 // Method org/hibernate/boot/model/source/internal/hbm/PluralAttributeSourceBagImpl."<init>":(Lorg/hibernate/boot/model/source/internal/hbm/MappingDocument;Lorg/hibernate/boot/jaxb/hbm/spi/JaxbHbmBagCollectionType;Lorg/hibernate/boot/model/source/spi/AttributeSourceContainer;)V
      16: invokeinterface #13,  2           // InterfaceMethod org/hibernate/boot/model/source/internal/hbm/AttributesHelper$Callback.addAttributeSource:(Lorg/hibernate/boot/model/source/spi/AttributeSource;)V
      21: return

  public static void processIdBagAttribute(org.hibernate.boot.model.source.internal.hbm.MappingDocument, org.hibernate.boot.model.source.internal.hbm.AttributesHelper$Callback, org.hibernate.boot.jaxb.hbm.spi.JaxbHbmIdBagCollectionType);
    Code:
       0: aload_1
       1: new           #98                 // class org/hibernate/boot/model/source/internal/hbm/PluralAttributeSourceIdBagImpl
       4: dup
       5: aload_0
       6: aload_2
       7: aload_1
       8: invokeinterface #11,  1           // InterfaceMethod org/hibernate/boot/model/source/internal/hbm/AttributesHelper$Callback.getAttributeSourceContainer:()Lorg/hibernate/boot/model/source/spi/AttributeSourceContainer;
      13: invokespecial #99                 // Method org/hibernate/boot/model/source/internal/hbm/PluralAttributeSourceIdBagImpl."<init>":(Lorg/hibernate/boot/model/source/internal/hbm/MappingDocument;Lorg/hibernate/boot/jaxb/hbm/spi/JaxbHbmIdBagCollectionType;Lorg/hibernate/boot/model/source/spi/AttributeSourceContainer;)V
      16: invokeinterface #13,  2           // InterfaceMethod org/hibernate/boot/model/source/internal/hbm/AttributesHelper$Callback.addAttributeSource:(Lorg/hibernate/boot/model/source/spi/AttributeSource;)V
      21: return
}
