Compiled from "ActiveMQConnectionFactory.java"
class org.apache.activemq.artemis.jms.client.ActiveMQConnectionFactory$1 implements java.security.PrivilegedAction<java.lang.Object> {
  final java.lang.String val$protocolManagerFactoryStr;

  final org.apache.activemq.artemis.jms.client.ActiveMQConnectionFactory this$0;

  org.apache.activemq.artemis.jms.client.ActiveMQConnectionFactory$1(org.apache.activemq.artemis.jms.client.ActiveMQConnectionFactory, java.lang.String);
    Code:
       0: aload_0
       1: aload_1
       2: putfield      #1                  // Field this$0:Lorg/apache/activemq/artemis/jms/client/ActiveMQConnectionFactory;
       5: aload_0
       6: aload_2
       7: putfield      #2                  // Field val$protocolManagerFactoryStr:Ljava/lang/String;
      10: aload_0
      11: invokespecial #3                  // Method java/lang/Object."<init>":()V
      14: return

  public java.lang.Object run();
    Code:
       0: aload_0
       1: getfield      #2                  // Field val$protocolManagerFactoryStr:Ljava/lang/String;
       4: invokestatic  #4                  // Method org/apache/activemq/artemis/utils/ClassloadingUtil.newInstanceFromClassLoader:(Ljava/lang/String;)Ljava/lang/Object;
       7: checkcast     #5                  // class org/apache/activemq/artemis/spi/core/remoting/ClientProtocolManagerFactory
      10: astore_1
      11: aload_0
      12: getfield      #1                  // Field this$0:Lorg/apache/activemq/artemis/jms/client/ActiveMQConnectionFactory;
      15: invokestatic  #6                  // Method org/apache/activemq/artemis/jms/client/ActiveMQConnectionFactory.access$000:(Lorg/apache/activemq/artemis/jms/client/ActiveMQConnectionFactory;)Lorg/apache/activemq/artemis/api/core/client/ServerLocator;
      18: aload_1
      19: invokeinterface #7,  2            // InterfaceMethod org/apache/activemq/artemis/api/core/client/ServerLocator.setProtocolManagerFactory:(Lorg/apache/activemq/artemis/spi/core/remoting/ClientProtocolManagerFactory;)Lorg/apache/activemq/artemis/api/core/client/ServerLocator;
      24: pop
      25: aconst_null
      26: areturn
}
