Compiled from "ActiveMQConnection.java"
class org.apache.activemq.artemis.jms.client.ActiveMQConnection$JMSFailureListener implements org.apache.activemq.artemis.api.core.client.SessionFailureListener {
  private final java.lang.ref.WeakReference<org.apache.activemq.artemis.jms.client.ActiveMQConnection> connectionRef;

  org.apache.activemq.artemis.jms.client.ActiveMQConnection$JMSFailureListener(org.apache.activemq.artemis.jms.client.ActiveMQConnection);
    Code:
       0: aload_0
       1: invokespecial #2                  // Method java/lang/Object."<init>":()V
       4: aload_0
       5: new           #3                  // class java/lang/ref/WeakReference
       8: dup
       9: aload_1
      10: invokespecial #4                  // Method java/lang/ref/WeakReference."<init>":(Ljava/lang/Object;)V
      13: putfield      #5                  // Field connectionRef:Ljava/lang/ref/WeakReference;
      16: return

  public synchronized void connectionFailed(org.apache.activemq.artemis.api.core.ActiveMQException, boolean);
    Code:
       0: aload_1
       1: ifnonnull     5
       4: return
       5: aload_0
       6: getfield      #5                  // Field connectionRef:Ljava/lang/ref/WeakReference;
       9: invokevirtual #6                  // Method java/lang/ref/WeakReference.get:()Ljava/lang/Object;
      12: checkcast     #1                  // class org/apache/activemq/artemis/jms/client/ActiveMQConnection
      15: astore_3
      16: aload_3
      17: ifnull        106
      20: aload_3
      21: invokevirtual #7                  // Method org/apache/activemq/artemis/jms/client/ActiveMQConnection.getExceptionListener:()Ljavax/jms/ExceptionListener;
      24: astore        4
      26: aload         4
      28: ifnull        84
      31: new           #8                  // class javax/jms/JMSException
      34: dup
      35: aload_1
      36: invokevirtual #9                  // Method org/apache/activemq/artemis/api/core/ActiveMQException.toString:()Ljava/lang/String;
      39: iload_2
      40: ifeq          48
      43: ldc           #10                 // String FAILOVER
      45: goto          50
      48: ldc           #11                 // String DISCONNECT
      50: invokespecial #12                 // Method javax/jms/JMSException."<init>":(Ljava/lang/String;Ljava/lang/String;)V
      53: astore        5
      55: aload         5
      57: aload_1
      58: invokevirtual #13                 // Method javax/jms/JMSException.initCause:(Ljava/lang/Throwable;)Ljava/lang/Throwable;
      61: pop
      62: new           #14                 // class java/lang/Thread
      65: dup
      66: new           #15                 // class org/apache/activemq/artemis/jms/client/ActiveMQConnection$JMSFailureListener$1
      69: dup
      70: aload_0
      71: aload         4
      73: aload         5
      75: invokespecial #16                 // Method org/apache/activemq/artemis/jms/client/ActiveMQConnection$JMSFailureListener$1."<init>":(Lorg/apache/activemq/artemis/jms/client/ActiveMQConnection$JMSFailureListener;Ljavax/jms/ExceptionListener;Ljavax/jms/JMSException;)V
      78: invokespecial #17                 // Method java/lang/Thread."<init>":(Ljava/lang/Runnable;)V
      81: invokevirtual #18                 // Method java/lang/Thread.start:()V
      84: goto          106
      87: astore        4
      89: aload_3
      90: invokestatic  #19                 // Method org/apache/activemq/artemis/jms/client/ActiveMQConnection.access$000:(Lorg/apache/activemq/artemis/jms/client/ActiveMQConnection;)Z
      93: ifne          106
      96: getstatic     #20                 // Field org/apache/activemq/artemis/jms/client/ActiveMQJMSClientLogger.LOGGER:Lorg/apache/activemq/artemis/jms/client/ActiveMQJMSClientLogger;
      99: aload         4
     101: invokeinterface #21,  2           // InterfaceMethod org/apache/activemq/artemis/jms/client/ActiveMQJMSClientLogger.errorCallingExcListener:(Ljava/lang/Exception;)V
     106: return
    Exception table:
       from    to  target type
          20    84    87   Class javax/jms/JMSException

  public void connectionFailed(org.apache.activemq.artemis.api.core.ActiveMQException, boolean, java.lang.String);
    Code:
       0: aload_0
       1: aload_1
       2: iload_2
       3: invokevirtual #22                 // Method connectionFailed:(Lorg/apache/activemq/artemis/api/core/ActiveMQException;Z)V
       6: return

  public void beforeReconnect(org.apache.activemq.artemis.api.core.ActiveMQException);
    Code:
       0: return
}
