Compiled from "InfocmpHandler.java"
class org.jboss.aesh.terminal.InfocmpHandler$InfocmpHolder {
  static final org.jboss.aesh.terminal.InfocmpHandler INSTANCE;

  private org.jboss.aesh.terminal.InfocmpHandler$InfocmpHolder();
    Code:
       0: aload_0
       1: invokespecial #1                  // Method java/lang/Object."<init>":()V
       4: return

  static {};
    Code:
       0: new           #2                  // class org/jboss/aesh/terminal/InfocmpHandler
       3: dup
       4: aconst_null
       5: invokespecial #3                  // Method org/jboss/aesh/terminal/InfocmpHandler."<init>":(Lorg/jboss/aesh/terminal/InfocmpHandler$1;)V
       8: putstatic     #4                  // Field INSTANCE:Lorg/jboss/aesh/terminal/InfocmpHandler;
      11: return
}
