Compiled from "Constraint.java"
public interface io.fluxcapacitor.common.api.search.Constraint {
  public abstract boolean matches(io.fluxcapacitor.common.search.Document);

  public abstract boolean hasPathConstraint();

  public default io.fluxcapacitor.common.api.search.Constraint decompose();
    Code:
       0: aload_0
       1: areturn

  public default io.fluxcapacitor.common.api.search.Constraint and(io.fluxcapacitor.common.api.search.Constraint);
    Code:
       0: new           #1                  // class java/util/ArrayList
       3: dup
       4: invokespecial #3                  // Method java/util/ArrayList."<init>":()V
       7: astore_2
       8: aload_0
       9: instanceof    #7                  // class io/fluxcapacitor/common/api/search/constraints/AllConstraint
      12: ifeq          32
      15: aload_2
      16: aload_0
      17: checkcast     #7                  // class io/fluxcapacitor/common/api/search/constraints/AllConstraint
      20: invokevirtual #9                  // Method io/fluxcapacitor/common/api/search/constraints/AllConstraint.getAll:()Ljava/util/List;
      23: invokeinterface #13,  2           // InterfaceMethod java/util/List.addAll:(Ljava/util/Collection;)Z
      28: pop
      29: goto          40
      32: aload_2
      33: aload_0
      34: invokeinterface #19,  2           // InterfaceMethod java/util/List.add:(Ljava/lang/Object;)Z
      39: pop
      40: aload_1
      41: instanceof    #7                  // class io/fluxcapacitor/common/api/search/constraints/AllConstraint
      44: ifeq          64
      47: aload_2
      48: aload_1
      49: checkcast     #7                  // class io/fluxcapacitor/common/api/search/constraints/AllConstraint
      52: invokevirtual #9                  // Method io/fluxcapacitor/common/api/search/constraints/AllConstraint.getAll:()Ljava/util/List;
      55: invokeinterface #13,  2           // InterfaceMethod java/util/List.addAll:(Ljava/util/Collection;)Z
      60: pop
      61: goto          72
      64: aload_2
      65: aload_1
      66: invokeinterface #19,  2           // InterfaceMethod java/util/List.add:(Ljava/lang/Object;)Z
      71: pop
      72: aload_2
      73: invokestatic  #23                 // Method io/fluxcapacitor/common/api/search/constraints/AllConstraint.all:(Ljava/util/Collection;)Lio/fluxcapacitor/common/api/search/Constraint;
      76: areturn

  public default io.fluxcapacitor.common.api.search.Constraint or(io.fluxcapacitor.common.api.search.Constraint);
    Code:
       0: new           #1                  // class java/util/ArrayList
       3: dup
       4: invokespecial #3                  // Method java/util/ArrayList."<init>":()V
       7: astore_2
       8: aload_0
       9: instanceof    #27                 // class io/fluxcapacitor/common/api/search/constraints/AnyConstraint
      12: ifeq          32
      15: aload_2
      16: aload_0
      17: checkcast     #27                 // class io/fluxcapacitor/common/api/search/constraints/AnyConstraint
      20: invokevirtual #29                 // Method io/fluxcapacitor/common/api/search/constraints/AnyConstraint.getAny:()Ljava/util/List;
      23: invokeinterface #13,  2           // InterfaceMethod java/util/List.addAll:(Ljava/util/Collection;)Z
      28: pop
      29: goto          40
      32: aload_2
      33: aload_0
      34: invokeinterface #19,  2           // InterfaceMethod java/util/List.add:(Ljava/lang/Object;)Z
      39: pop
      40: aload_1
      41: instanceof    #27                 // class io/fluxcapacitor/common/api/search/constraints/AnyConstraint
      44: ifeq          64
      47: aload_2
      48: aload_1
      49: checkcast     #27                 // class io/fluxcapacitor/common/api/search/constraints/AnyConstraint
      52: invokevirtual #29                 // Method io/fluxcapacitor/common/api/search/constraints/AnyConstraint.getAny:()Ljava/util/List;
      55: invokeinterface #13,  2           // InterfaceMethod java/util/List.addAll:(Ljava/util/Collection;)Z
      60: pop
      61: goto          72
      64: aload_2
      65: aload_1
      66: invokeinterface #19,  2           // InterfaceMethod java/util/List.add:(Ljava/lang/Object;)Z
      71: pop
      72: aload_2
      73: invokestatic  #32                 // Method io/fluxcapacitor/common/api/search/constraints/AnyConstraint.any:(Ljava/util/Collection;)Lio/fluxcapacitor/common/api/search/Constraint;
      76: areturn
}
