Compiled from "FileUpdateTask.java"
final class org.jboss.as.patching.runner.FileUpdateTask extends org.jboss.as.patching.runner.AbstractFileTask {
  org.jboss.as.patching.runner.FileUpdateTask(org.jboss.as.patching.runner.PatchingTaskDescription, java.io.File, java.io.File);
    Code:
       0: aload_0
       1: aload_1
       2: aload_2
       3: aload_3
       4: invokespecial #1                  // Method org/jboss/as/patching/runner/AbstractFileTask."<init>":(Lorg/jboss/as/patching/runner/PatchingTaskDescription;Ljava/io/File;Ljava/io/File;)V
       7: return

  org.jboss.as.patching.metadata.ContentModification createRollbackEntry(org.jboss.as.patching.metadata.ContentModification, org.jboss.as.patching.metadata.MiscContentItem, byte[]);
    Code:
       0: getstatic     #2                  // Field org/jboss/as/patching/IoUtils.NO_CONTENT:[B
       3: aload_2
       4: invokevirtual #3                  // Method org/jboss/as/patching/metadata/MiscContentItem.getContentHash:()[B
       7: invokestatic  #4                  // Method java/util/Arrays.equals:([B[B)Z
      10: ifeq          31
      13: aload_0
      14: getfield      #5                  // Field backup:Ljava/io/File;
      17: invokevirtual #6                  // Method java/io/File.exists:()Z
      20: ifne          31
      23: getstatic     #7                  // Field org/jboss/as/patching/metadata/ModificationType.REMOVE:Lorg/jboss/as/patching/metadata/ModificationType;
      26: astore        4
      28: goto          36
      31: getstatic     #8                  // Field org/jboss/as/patching/metadata/ModificationType.MODIFY:Lorg/jboss/as/patching/metadata/ModificationType;
      34: astore        4
      36: new           #9                  // class org/jboss/as/patching/metadata/ContentModification
      39: dup
      40: aload_2
      41: aload_3
      42: aload         4
      44: aload_1
      45: invokevirtual #10                 // Method org/jboss/as/patching/metadata/ContentModification.getCondition:()Lorg/jboss/as/patching/metadata/ModificationCondition;
      48: invokespecial #11                 // Method org/jboss/as/patching/metadata/ContentModification."<init>":(Lorg/jboss/as/patching/metadata/ContentItem;[BLorg/jboss/as/patching/metadata/ModificationType;Lorg/jboss/as/patching/metadata/ModificationCondition;)V
      51: areturn

  protected org.jboss.as.patching.metadata.ContentModification getOriginalModification(byte[], byte[]);
    Code:
       0: aload_0
       1: aload_1
       2: aload_2
       3: invokespecial #12                 // Method org/jboss/as/patching/runner/AbstractFileTask.getOriginalModification:([B[B)Lorg/jboss/as/patching/metadata/ContentModification;
       6: astore_3
       7: getstatic     #2                  // Field org/jboss/as/patching/IoUtils.NO_CONTENT:[B
      10: aload_2
      11: invokestatic  #4                  // Method java/util/Arrays.equals:([B[B)Z
      14: ifeq          35
      17: aload_0
      18: getfield      #5                  // Field backup:Ljava/io/File;
      21: invokevirtual #6                  // Method java/io/File.exists:()Z
      24: ifne          35
      27: getstatic     #13                 // Field org/jboss/as/patching/metadata/ModificationType.ADD:Lorg/jboss/as/patching/metadata/ModificationType;
      30: astore        4
      32: goto          40
      35: getstatic     #8                  // Field org/jboss/as/patching/metadata/ModificationType.MODIFY:Lorg/jboss/as/patching/metadata/ModificationType;
      38: astore        4
      40: new           #9                  // class org/jboss/as/patching/metadata/ContentModification
      43: dup
      44: aload_3
      45: invokevirtual #14                 // Method org/jboss/as/patching/metadata/ContentModification.getItem:()Lorg/jboss/as/patching/metadata/ContentItem;
      48: aload_3
      49: invokevirtual #15                 // Method org/jboss/as/patching/metadata/ContentModification.getTargetHash:()[B
      52: aload         4
      54: aload_3
      55: invokevirtual #10                 // Method org/jboss/as/patching/metadata/ContentModification.getCondition:()Lorg/jboss/as/patching/metadata/ModificationCondition;
      58: invokespecial #11                 // Method org/jboss/as/patching/metadata/ContentModification."<init>":(Lorg/jboss/as/patching/metadata/ContentItem;[BLorg/jboss/as/patching/metadata/ModificationType;Lorg/jboss/as/patching/metadata/ModificationCondition;)V
      61: areturn
}
