Compiled from "PatchContentLoader.java"
class org.jboss.as.patching.runner.PatchContentLoader$BasicContentLoader extends org.jboss.as.patching.runner.PatchContentLoader {
  private final java.io.File miscRoot;

  private final java.io.File bundlesRoot;

  private final java.io.File modulesRoot;

  org.jboss.as.patching.runner.PatchContentLoader$BasicContentLoader(java.io.File, java.io.File, java.io.File);
    Code:
       0: aload_0
       1: invokespecial #1                  // Method org/jboss/as/patching/runner/PatchContentLoader."<init>":()V
       4: aload_0
       5: aload_1
       6: putfield      #2                  // Field miscRoot:Ljava/io/File;
       9: aload_0
      10: aload_2
      11: putfield      #3                  // Field bundlesRoot:Ljava/io/File;
      14: aload_0
      15: aload_3
      16: putfield      #4                  // Field modulesRoot:Ljava/io/File;
      19: return

  public java.io.File getFile(org.jboss.as.patching.metadata.ContentItem);
    Code:
       0: aload_1
       1: invokevirtual #5                  // Method org/jboss/as/patching/metadata/ContentItem.getContentType:()Lorg/jboss/as/patching/metadata/ContentType;
       4: astore_2
       5: getstatic     #6                  // Field org/jboss/as/patching/runner/PatchContentLoader$1.$SwitchMap$org$jboss$as$patching$metadata$ContentType:[I
       8: aload_2
       9: invokevirtual #7                  // Method org/jboss/as/patching/metadata/ContentType.ordinal:()I
      12: iaload
      13: tableswitch   { // 1 to 3
                     1: 40
                     2: 49
                     3: 58
               default: 67
          }
      40: aload_0
      41: aload_1
      42: checkcast     #8                  // class org/jboss/as/patching/metadata/ModuleItem
      45: invokevirtual #9                  // Method getModulePath:(Lorg/jboss/as/patching/metadata/ModuleItem;)Ljava/io/File;
      48: areturn
      49: aload_0
      50: aload_1
      51: checkcast     #10                 // class org/jboss/as/patching/metadata/MiscContentItem
      54: invokevirtual #11                 // Method getMiscPath:(Lorg/jboss/as/patching/metadata/MiscContentItem;)Ljava/io/File;
      57: areturn
      58: aload_0
      59: aload_1
      60: checkcast     #12                 // class org/jboss/as/patching/metadata/BundleItem
      63: invokevirtual #13                 // Method getBundlePath:(Lorg/jboss/as/patching/metadata/BundleItem;)Ljava/io/File;
      66: areturn
      67: new           #14                 // class java/lang/IllegalStateException
      70: dup
      71: invokespecial #15                 // Method java/lang/IllegalStateException."<init>":()V
      74: athrow

  java.io.File getMiscPath(org.jboss.as.patching.metadata.MiscContentItem);
    Code:
       0: aload_0
       1: getfield      #2                  // Field miscRoot:Ljava/io/File;
       4: aload_1
       5: invokestatic  #16                 // Method getMiscPath:(Ljava/io/File;Lorg/jboss/as/patching/metadata/MiscContentItem;)Ljava/io/File;
       8: areturn

  java.io.File getModulePath(org.jboss.as.patching.metadata.ModuleItem);
    Code:
       0: aload_0
       1: getfield      #4                  // Field modulesRoot:Ljava/io/File;
       4: aload_1
       5: invokestatic  #17                 // Method getModulePath:(Ljava/io/File;Lorg/jboss/as/patching/metadata/ModuleItem;)Ljava/io/File;
       8: areturn

  java.io.File getBundlePath(org.jboss.as.patching.metadata.BundleItem);
    Code:
       0: aload_0
       1: getfield      #3                  // Field bundlesRoot:Ljava/io/File;
       4: aload_1
       5: invokevirtual #18                 // Method org/jboss/as/patching/metadata/BundleItem.getName:()Ljava/lang/String;
       8: aload_1
       9: invokevirtual #19                 // Method org/jboss/as/patching/metadata/BundleItem.getSlot:()Ljava/lang/String;
      12: invokestatic  #20                 // Method getModulePath:(Ljava/io/File;Ljava/lang/String;Ljava/lang/String;)Ljava/io/File;
      15: areturn
}
