Compiled from "PatchingTaskDescription.java"
class org.jboss.as.patching.runner.PatchingTaskDescription {
  private final java.lang.String patchId;

  private final org.jboss.as.patching.metadata.ContentModification modification;

  private final org.jboss.as.patching.runner.PatchContentLoader loader;

  private final boolean conflicts;

  private final boolean skipIfTheSame;

  private final boolean rollback;

  org.jboss.as.patching.runner.PatchingTaskDescription(java.lang.String, org.jboss.as.patching.metadata.ContentModification, org.jboss.as.patching.runner.PatchContentLoader, boolean, boolean, boolean);
    Code:
       0: aload_0
       1: invokespecial #1                  // Method java/lang/Object."<init>":()V
       4: aload_0
       5: aload_1
       6: putfield      #2                  // Field patchId:Ljava/lang/String;
       9: aload_0
      10: aload_2
      11: putfield      #3                  // Field modification:Lorg/jboss/as/patching/metadata/ContentModification;
      14: aload_0
      15: aload_3
      16: putfield      #4                  // Field loader:Lorg/jboss/as/patching/runner/PatchContentLoader;
      19: aload_0
      20: iload         4
      22: putfield      #5                  // Field conflicts:Z
      25: aload_0
      26: iload         5
      28: putfield      #6                  // Field skipIfTheSame:Z
      31: aload_0
      32: iload         6
      34: putfield      #7                  // Field rollback:Z
      37: return

  public java.lang.String getPatchId();
    Code:
       0: aload_0
       1: getfield      #2                  // Field patchId:Ljava/lang/String;
       4: areturn

  public boolean isRolledback();
    Code:
       0: aload_0
       1: getfield      #7                  // Field rollback:Z
       4: ireturn

  public org.jboss.as.patching.metadata.ContentModification getModification();
    Code:
       0: aload_0
       1: getfield      #3                  // Field modification:Lorg/jboss/as/patching/metadata/ContentModification;
       4: areturn

  public org.jboss.as.patching.metadata.ModificationType getModificationType();
    Code:
       0: aload_0
       1: getfield      #3                  // Field modification:Lorg/jboss/as/patching/metadata/ContentModification;
       4: invokevirtual #8                  // Method org/jboss/as/patching/metadata/ContentModification.getType:()Lorg/jboss/as/patching/metadata/ModificationType;
       7: areturn

  public org.jboss.as.patching.metadata.ContentItem getContentItem();
    Code:
       0: aload_0
       1: getfield      #3                  // Field modification:Lorg/jboss/as/patching/metadata/ContentModification;
       4: invokevirtual #9                  // Method org/jboss/as/patching/metadata/ContentModification.getItem:()Lorg/jboss/as/patching/metadata/ContentItem;
       7: areturn

  public <T extends org.jboss.as.patching.metadata.ContentItem> T getContentItem(java.lang.Class<T>);
    Code:
       0: aload_0
       1: getfield      #3                  // Field modification:Lorg/jboss/as/patching/metadata/ContentModification;
       4: aload_1
       5: invokevirtual #10                 // Method org/jboss/as/patching/metadata/ContentModification.getItem:(Ljava/lang/Class;)Lorg/jboss/as/patching/metadata/ContentItem;
       8: areturn

  public org.jboss.as.patching.metadata.ContentType getContentType();
    Code:
       0: aload_0
       1: getfield      #3                  // Field modification:Lorg/jboss/as/patching/metadata/ContentModification;
       4: invokevirtual #9                  // Method org/jboss/as/patching/metadata/ContentModification.getItem:()Lorg/jboss/as/patching/metadata/ContentItem;
       7: invokevirtual #11                 // Method org/jboss/as/patching/metadata/ContentItem.getContentType:()Lorg/jboss/as/patching/metadata/ContentType;
      10: areturn

  public org.jboss.as.patching.runner.PatchContentLoader getLoader();
    Code:
       0: aload_0
       1: getfield      #4                  // Field loader:Lorg/jboss/as/patching/runner/PatchContentLoader;
       4: areturn

  public boolean hasConflicts();
    Code:
       0: aload_0
       1: getfield      #5                  // Field conflicts:Z
       4: ireturn

  public boolean skipIfTheSame();
    Code:
       0: aload_0
       1: getfield      #6                  // Field skipIfTheSame:Z
       4: ireturn

  static org.jboss.as.patching.runner.PatchingTaskDescription create(org.jboss.as.patching.runner.PatchingTasks$ContentTaskDefinition, org.jboss.as.patching.runner.PatchContentLoader);
    Code:
       0: aload_0
       1: invokestatic  #12                 // Method resolveDefinition:(Lorg/jboss/as/patching/runner/PatchingTasks$ContentTaskDefinition;)Lorg/jboss/as/patching/metadata/ContentModification;
       4: astore_2
       5: aload_0
       6: invokevirtual #13                 // Method org/jboss/as/patching/runner/PatchingTasks$ContentTaskDefinition.getTarget:()Lorg/jboss/as/patching/runner/PatchingTasks$ContentEntry;
       9: invokevirtual #14                 // Method org/jboss/as/patching/runner/PatchingTasks$ContentEntry.getItem:()Lorg/jboss/as/patching/metadata/ContentItem;
      12: astore_3
      13: aload_0
      14: invokevirtual #15                 // Method org/jboss/as/patching/runner/PatchingTasks$ContentTaskDefinition.getLatest:()Lorg/jboss/as/patching/runner/PatchingTasks$ContentEntry;
      17: invokevirtual #16                 // Method org/jboss/as/patching/runner/PatchingTasks$ContentEntry.getTargetHash:()[B
      20: astore        4
      22: aload_3
      23: invokevirtual #17                 // Method org/jboss/as/patching/metadata/ContentItem.getContentHash:()[B
      26: astore        5
      28: aload         4
      30: aload         5
      32: invokestatic  #18                 // Method java/util/Arrays.equals:([B[B)Z
      35: istore        6
      37: new           #19                 // class org/jboss/as/patching/runner/PatchingTaskDescription
      40: dup
      41: aload_0
      42: invokevirtual #13                 // Method org/jboss/as/patching/runner/PatchingTasks$ContentTaskDefinition.getTarget:()Lorg/jboss/as/patching/runner/PatchingTasks$ContentEntry;
      45: invokevirtual #20                 // Method org/jboss/as/patching/runner/PatchingTasks$ContentEntry.getPatchId:()Ljava/lang/String;
      48: aload_2
      49: aload_1
      50: aload_0
      51: invokevirtual #21                 // Method org/jboss/as/patching/runner/PatchingTasks$ContentTaskDefinition.hasConflicts:()Z
      54: iload         6
      56: aload_0
      57: invokevirtual #22                 // Method org/jboss/as/patching/runner/PatchingTasks$ContentTaskDefinition.isRollback:()Z
      60: invokespecial #23                 // Method "<init>":(Ljava/lang/String;Lorg/jboss/as/patching/metadata/ContentModification;Lorg/jboss/as/patching/runner/PatchContentLoader;ZZZ)V
      63: areturn

  static org.jboss.as.patching.metadata.ContentModification resolveDefinition(org.jboss.as.patching.runner.PatchingTasks$ContentTaskDefinition);
    Code:
       0: aload_0
       1: invokevirtual #15                 // Method org/jboss/as/patching/runner/PatchingTasks$ContentTaskDefinition.getLatest:()Lorg/jboss/as/patching/runner/PatchingTasks$ContentEntry;
       4: aload_0
       5: invokevirtual #13                 // Method org/jboss/as/patching/runner/PatchingTasks$ContentTaskDefinition.getTarget:()Lorg/jboss/as/patching/runner/PatchingTasks$ContentEntry;
       8: if_acmpne     19
      11: aload_0
      12: invokevirtual #13                 // Method org/jboss/as/patching/runner/PatchingTasks$ContentTaskDefinition.getTarget:()Lorg/jboss/as/patching/runner/PatchingTasks$ContentEntry;
      15: invokevirtual #24                 // Method org/jboss/as/patching/runner/PatchingTasks$ContentEntry.getModification:()Lorg/jboss/as/patching/metadata/ContentModification;
      18: areturn
      19: aload_0
      20: invokevirtual #13                 // Method org/jboss/as/patching/runner/PatchingTasks$ContentTaskDefinition.getTarget:()Lorg/jboss/as/patching/runner/PatchingTasks$ContentEntry;
      23: invokevirtual #14                 // Method org/jboss/as/patching/runner/PatchingTasks$ContentEntry.getItem:()Lorg/jboss/as/patching/metadata/ContentItem;
      26: astore_1
      27: aload_0
      28: invokevirtual #13                 // Method org/jboss/as/patching/runner/PatchingTasks$ContentTaskDefinition.getTarget:()Lorg/jboss/as/patching/runner/PatchingTasks$ContentEntry;
      31: invokevirtual #24                 // Method org/jboss/as/patching/runner/PatchingTasks$ContentEntry.getModification:()Lorg/jboss/as/patching/metadata/ContentModification;
      34: astore_2
      35: aload_0
      36: invokevirtual #15                 // Method org/jboss/as/patching/runner/PatchingTasks$ContentTaskDefinition.getLatest:()Lorg/jboss/as/patching/runner/PatchingTasks$ContentEntry;
      39: invokevirtual #16                 // Method org/jboss/as/patching/runner/PatchingTasks$ContentEntry.getTargetHash:()[B
      42: astore_3
      43: new           #25                 // class org/jboss/as/patching/metadata/ContentModification
      46: dup
      47: aload_1
      48: aload_3
      49: aload_2
      50: invokevirtual #8                  // Method org/jboss/as/patching/metadata/ContentModification.getType:()Lorg/jboss/as/patching/metadata/ModificationType;
      53: aload_2
      54: invokevirtual #26                 // Method org/jboss/as/patching/metadata/ContentModification.getCondition:()Lorg/jboss/as/patching/metadata/ModificationCondition;
      57: invokespecial #27                 // Method org/jboss/as/patching/metadata/ContentModification."<init>":(Lorg/jboss/as/patching/metadata/ContentItem;[BLorg/jboss/as/patching/metadata/ModificationType;Lorg/jboss/as/patching/metadata/ModificationCondition;)V
      60: areturn
}
