Compiled from "DataSourceProperties.java"
class org.springframework.boot.autoconfigure.jdbc.DataSourceProperties$DataSourceBeanCreationException extends org.springframework.beans.factory.BeanCreationException {
  org.springframework.boot.autoconfigure.jdbc.DataSourceProperties$DataSourceBeanCreationException(org.springframework.boot.autoconfigure.jdbc.EmbeddedDatabaseConnection, org.springframework.core.env.Environment, java.lang.String);
    Code:
       0: aload_0
       1: aload_1
       2: aload_2
       3: aload_3
       4: invokestatic  #1                  // Method getMessage:(Lorg/springframework/boot/autoconfigure/jdbc/EmbeddedDatabaseConnection;Lorg/springframework/core/env/Environment;Ljava/lang/String;)Ljava/lang/String;
       7: invokespecial #2                  // Method org/springframework/beans/factory/BeanCreationException."<init>":(Ljava/lang/String;)V
      10: return

  private static java.lang.String getMessage(org.springframework.boot.autoconfigure.jdbc.EmbeddedDatabaseConnection, org.springframework.core.env.Environment, java.lang.String);
    Code:
       0: new           #3                  // class java/lang/StringBuilder
       3: dup
       4: invokespecial #4                  // Method java/lang/StringBuilder."<init>":()V
       7: astore_3
       8: aload_3
       9: new           #3                  // class java/lang/StringBuilder
      12: dup
      13: invokespecial #4                  // Method java/lang/StringBuilder."<init>":()V
      16: ldc           #5                  // String Cannot determine embedded database
      18: invokevirtual #6                  // Method java/lang/StringBuilder.append:(Ljava/lang/String;)Ljava/lang/StringBuilder;
      21: aload_2
      22: invokevirtual #6                  // Method java/lang/StringBuilder.append:(Ljava/lang/String;)Ljava/lang/StringBuilder;
      25: ldc           #7                  // String  for database type
      27: invokevirtual #6                  // Method java/lang/StringBuilder.append:(Ljava/lang/String;)Ljava/lang/StringBuilder;
      30: aload_0
      31: invokevirtual #8                  // Method java/lang/StringBuilder.append:(Ljava/lang/Object;)Ljava/lang/StringBuilder;
      34: ldc           #9                  // String .
      36: invokevirtual #6                  // Method java/lang/StringBuilder.append:(Ljava/lang/String;)Ljava/lang/StringBuilder;
      39: invokevirtual #10                 // Method java/lang/StringBuilder.toString:()Ljava/lang/String;
      42: invokevirtual #6                  // Method java/lang/StringBuilder.append:(Ljava/lang/String;)Ljava/lang/StringBuilder;
      45: pop
      46: aload_3
      47: ldc           #11                 // String If you want an embedded database please put a supported one on the classpath.
      49: invokevirtual #6                  // Method java/lang/StringBuilder.append:(Ljava/lang/String;)Ljava/lang/StringBuilder;
      52: pop
      53: aload_3
      54: ldc           #12                 // String If you have database settings to be loaded from a particular profile you may need to active it
      56: invokevirtual #6                  // Method java/lang/StringBuilder.append:(Ljava/lang/String;)Ljava/lang/StringBuilder;
      59: pop
      60: aload_1
      61: ifnull        127
      64: aload_1
      65: invokeinterface #13,  1           // InterfaceMethod org/springframework/core/env/Environment.getActiveProfiles:()[Ljava/lang/String;
      70: astore        4
      72: aload         4
      74: invokestatic  #14                 // Method org/springframework/util/ObjectUtils.isEmpty:([Ljava/lang/Object;)Z
      77: ifeq          90
      80: aload_3
      81: ldc           #15                 // String  (no profiles are currently active)
      83: invokevirtual #6                  // Method java/lang/StringBuilder.append:(Ljava/lang/String;)Ljava/lang/StringBuilder;
      86: pop
      87: goto          127
      90: aload_3
      91: new           #3                  // class java/lang/StringBuilder
      94: dup
      95: invokespecial #4                  // Method java/lang/StringBuilder."<init>":()V
      98: ldc           #16                 // String  (the profiles \"
     100: invokevirtual #6                  // Method java/lang/StringBuilder.append:(Ljava/lang/String;)Ljava/lang/StringBuilder;
     103: aload_1
     104: invokeinterface #13,  1           // InterfaceMethod org/springframework/core/env/Environment.getActiveProfiles:()[Ljava/lang/String;
     109: invokestatic  #17                 // Method org/springframework/util/StringUtils.arrayToCommaDelimitedString:([Ljava/lang/Object;)Ljava/lang/String;
     112: invokevirtual #6                  // Method java/lang/StringBuilder.append:(Ljava/lang/String;)Ljava/lang/StringBuilder;
     115: ldc           #18                 // String \" are currently active)
     117: invokevirtual #6                  // Method java/lang/StringBuilder.append:(Ljava/lang/String;)Ljava/lang/StringBuilder;
     120: invokevirtual #10                 // Method java/lang/StringBuilder.toString:()Ljava/lang/String;
     123: invokevirtual #6                  // Method java/lang/StringBuilder.append:(Ljava/lang/String;)Ljava/lang/StringBuilder;
     126: pop
     127: aload_3
     128: ldc           #19                 // String .
     130: invokevirtual #6                  // Method java/lang/StringBuilder.append:(Ljava/lang/String;)Ljava/lang/StringBuilder;
     133: pop
     134: aload_3
     135: invokevirtual #10                 // Method java/lang/StringBuilder.toString:()Ljava/lang/String;
     138: areturn
}
