Compiled from "UpdateTimestampsCache.java"
public class org.hibernate.cache.spi.UpdateTimestampsCache {
  private static final org.hibernate.internal.CoreMessageLogger LOG;

  private static final boolean DEBUG_ENABLED;

  public static final java.lang.String REGION_NAME;

  private final org.hibernate.engine.spi.SessionFactoryImplementor factory;

  private final org.hibernate.cache.spi.TimestampsRegion region;

  public org.hibernate.cache.spi.UpdateTimestampsCache(org.hibernate.engine.spi.SessionFactoryImplementor, org.hibernate.cache.spi.TimestampsRegion);
    Code:
       0: aload_0
       1: invokespecial #1                  // Method java/lang/Object."<init>":()V
       4: getstatic     #2                  // Field LOG:Lorg/hibernate/internal/CoreMessageLogger;
       7: aload_2
       8: invokeinterface #3,  1            // InterfaceMethod org/hibernate/cache/spi/TimestampsRegion.getName:()Ljava/lang/String;
      13: invokeinterface #4,  2            // InterfaceMethod org/hibernate/internal/CoreMessageLogger.startingUpdateTimestampsCache:(Ljava/lang/String;)V
      18: aload_0
      19: aload_1
      20: putfield      #5                  // Field factory:Lorg/hibernate/engine/spi/SessionFactoryImplementor;
      23: aload_0
      24: aload_2
      25: putfield      #6                  // Field region:Lorg/hibernate/cache/spi/TimestampsRegion;
      28: return

  public void preInvalidate(java.io.Serializable[], org.hibernate.engine.spi.SharedSessionContractImplementor) throws org.hibernate.cache.CacheException;
    Code:
       0: aload_0
       1: getfield      #5                  // Field factory:Lorg/hibernate/engine/spi/SessionFactoryImplementor;
       4: ifnull        28
       7: aload_0
       8: getfield      #5                  // Field factory:Lorg/hibernate/engine/spi/SessionFactoryImplementor;
      11: invokeinterface #7,  1            // InterfaceMethod org/hibernate/engine/spi/SessionFactoryImplementor.getStatistics:()Lorg/hibernate/stat/spi/StatisticsImplementor;
      16: invokeinterface #8,  1            // InterfaceMethod org/hibernate/stat/spi/StatisticsImplementor.isStatisticsEnabled:()Z
      21: ifeq          28
      24: iconst_1
      25: goto          29
      28: iconst_0
      29: istore_3
      30: aload_0
      31: getfield      #6                  // Field region:Lorg/hibernate/cache/spi/TimestampsRegion;
      34: invokeinterface #9,  1            // InterfaceMethod org/hibernate/cache/spi/TimestampsRegion.nextTimestamp:()J
      39: aload_0
      40: getfield      #6                  // Field region:Lorg/hibernate/cache/spi/TimestampsRegion;
      43: invokeinterface #10,  1           // InterfaceMethod org/hibernate/cache/spi/TimestampsRegion.getTimeout:()I
      48: i2l
      49: ladd
      50: invokestatic  #11                 // Method java/lang/Long.valueOf:(J)Ljava/lang/Long;
      53: astore        4
      55: aload_1
      56: astore        5
      58: aload         5
      60: arraylength
      61: istore        6
      63: iconst_0
      64: istore        7
      66: iload         7
      68: iload         6
      70: if_icmpge     179
      73: aload         5
      75: iload         7
      77: aaload
      78: astore        8
      80: getstatic     #12                 // Field DEBUG_ENABLED:Z
      83: ifeq          100
      86: getstatic     #2                  // Field LOG:Lorg/hibernate/internal/CoreMessageLogger;
      89: ldc           #13                 // String Pre-invalidating space [%s], timestamp: %s
      91: aload         8
      93: aload         4
      95: invokeinterface #14,  4           // InterfaceMethod org/hibernate/internal/CoreMessageLogger.debugf:(Ljava/lang/String;Ljava/lang/Object;Ljava/lang/Object;)V
     100: aload_2
     101: invokeinterface #15,  1           // InterfaceMethod org/hibernate/engine/spi/SharedSessionContractImplementor.getEventListenerManager:()Lorg/hibernate/engine/spi/SessionEventListenerManager;
     106: invokeinterface #16,  1           // InterfaceMethod org/hibernate/engine/spi/SessionEventListenerManager.cachePutStart:()V
     111: aload_0
     112: getfield      #6                  // Field region:Lorg/hibernate/cache/spi/TimestampsRegion;
     115: aload_2
     116: aload         8
     118: aload         4
     120: invokeinterface #17,  4           // InterfaceMethod org/hibernate/cache/spi/TimestampsRegion.put:(Lorg/hibernate/engine/spi/SharedSessionContractImplementor;Ljava/lang/Object;Ljava/lang/Object;)V
     125: aload_2
     126: invokeinterface #15,  1           // InterfaceMethod org/hibernate/engine/spi/SharedSessionContractImplementor.getEventListenerManager:()Lorg/hibernate/engine/spi/SessionEventListenerManager;
     131: invokeinterface #18,  1           // InterfaceMethod org/hibernate/engine/spi/SessionEventListenerManager.cachePutEnd:()V
     136: goto          155
     139: astore        9
     141: aload_2
     142: invokeinterface #15,  1           // InterfaceMethod org/hibernate/engine/spi/SharedSessionContractImplementor.getEventListenerManager:()Lorg/hibernate/engine/spi/SessionEventListenerManager;
     147: invokeinterface #18,  1           // InterfaceMethod org/hibernate/engine/spi/SessionEventListenerManager.cachePutEnd:()V
     152: aload         9
     154: athrow
     155: iload_3
     156: ifeq          173
     159: aload_0
     160: getfield      #5                  // Field factory:Lorg/hibernate/engine/spi/SessionFactoryImplementor;
     163: invokeinterface #7,  1            // InterfaceMethod org/hibernate/engine/spi/SessionFactoryImplementor.getStatistics:()Lorg/hibernate/stat/spi/StatisticsImplementor;
     168: invokeinterface #19,  1           // InterfaceMethod org/hibernate/stat/spi/StatisticsImplementor.updateTimestampsCachePut:()V
     173: iinc          7, 1
     176: goto          66
     179: return
    Exception table:
       from    to  target type
         100   125   139   any
         139   141   139   any

  public void invalidate(java.io.Serializable[], org.hibernate.engine.spi.SharedSessionContractImplementor) throws org.hibernate.cache.CacheException;
    Code:
       0: aload_0
       1: getfield      #5                  // Field factory:Lorg/hibernate/engine/spi/SessionFactoryImplementor;
       4: ifnull        28
       7: aload_0
       8: getfield      #5                  // Field factory:Lorg/hibernate/engine/spi/SessionFactoryImplementor;
      11: invokeinterface #7,  1            // InterfaceMethod org/hibernate/engine/spi/SessionFactoryImplementor.getStatistics:()Lorg/hibernate/stat/spi/StatisticsImplementor;
      16: invokeinterface #8,  1            // InterfaceMethod org/hibernate/stat/spi/StatisticsImplementor.isStatisticsEnabled:()Z
      21: ifeq          28
      24: iconst_1
      25: goto          29
      28: iconst_0
      29: istore_3
      30: aload_0
      31: getfield      #6                  // Field region:Lorg/hibernate/cache/spi/TimestampsRegion;
      34: invokeinterface #9,  1            // InterfaceMethod org/hibernate/cache/spi/TimestampsRegion.nextTimestamp:()J
      39: invokestatic  #11                 // Method java/lang/Long.valueOf:(J)Ljava/lang/Long;
      42: astore        4
      44: aload_1
      45: astore        5
      47: aload         5
      49: arraylength
      50: istore        6
      52: iconst_0
      53: istore        7
      55: iload         7
      57: iload         6
      59: if_icmpge     168
      62: aload         5
      64: iload         7
      66: aaload
      67: astore        8
      69: getstatic     #12                 // Field DEBUG_ENABLED:Z
      72: ifeq          89
      75: getstatic     #2                  // Field LOG:Lorg/hibernate/internal/CoreMessageLogger;
      78: ldc           #20                 // String Invalidating space [%s], timestamp: %s
      80: aload         8
      82: aload         4
      84: invokeinterface #14,  4           // InterfaceMethod org/hibernate/internal/CoreMessageLogger.debugf:(Ljava/lang/String;Ljava/lang/Object;Ljava/lang/Object;)V
      89: aload_2
      90: invokeinterface #15,  1           // InterfaceMethod org/hibernate/engine/spi/SharedSessionContractImplementor.getEventListenerManager:()Lorg/hibernate/engine/spi/SessionEventListenerManager;
      95: invokeinterface #16,  1           // InterfaceMethod org/hibernate/engine/spi/SessionEventListenerManager.cachePutStart:()V
     100: aload_0
     101: getfield      #6                  // Field region:Lorg/hibernate/cache/spi/TimestampsRegion;
     104: aload_2
     105: aload         8
     107: aload         4
     109: invokeinterface #17,  4           // InterfaceMethod org/hibernate/cache/spi/TimestampsRegion.put:(Lorg/hibernate/engine/spi/SharedSessionContractImplementor;Ljava/lang/Object;Ljava/lang/Object;)V
     114: aload_2
     115: invokeinterface #15,  1           // InterfaceMethod org/hibernate/engine/spi/SharedSessionContractImplementor.getEventListenerManager:()Lorg/hibernate/engine/spi/SessionEventListenerManager;
     120: invokeinterface #18,  1           // InterfaceMethod org/hibernate/engine/spi/SessionEventListenerManager.cachePutEnd:()V
     125: goto          144
     128: astore        9
     130: aload_2
     131: invokeinterface #15,  1           // InterfaceMethod org/hibernate/engine/spi/SharedSessionContractImplementor.getEventListenerManager:()Lorg/hibernate/engine/spi/SessionEventListenerManager;
     136: invokeinterface #18,  1           // InterfaceMethod org/hibernate/engine/spi/SessionEventListenerManager.cachePutEnd:()V
     141: aload         9
     143: athrow
     144: iload_3
     145: ifeq          162
     148: aload_0
     149: getfield      #5                  // Field factory:Lorg/hibernate/engine/spi/SessionFactoryImplementor;
     152: invokeinterface #7,  1            // InterfaceMethod org/hibernate/engine/spi/SessionFactoryImplementor.getStatistics:()Lorg/hibernate/stat/spi/StatisticsImplementor;
     157: invokeinterface #19,  1           // InterfaceMethod org/hibernate/stat/spi/StatisticsImplementor.updateTimestampsCachePut:()V
     162: iinc          7, 1
     165: goto          55
     168: return
    Exception table:
       from    to  target type
          89   114   128   any
         128   130   128   any

  public boolean isUpToDate(java.util.Set<java.io.Serializable>, java.lang.Long, org.hibernate.engine.spi.SharedSessionContractImplementor) throws org.hibernate.cache.CacheException;
    Code:
       0: aload_0
       1: getfield      #5                  // Field factory:Lorg/hibernate/engine/spi/SessionFactoryImplementor;
       4: ifnull        28
       7: aload_0
       8: getfield      #5                  // Field factory:Lorg/hibernate/engine/spi/SessionFactoryImplementor;
      11: invokeinterface #7,  1            // InterfaceMethod org/hibernate/engine/spi/SessionFactoryImplementor.getStatistics:()Lorg/hibernate/stat/spi/StatisticsImplementor;
      16: invokeinterface #8,  1            // InterfaceMethod org/hibernate/stat/spi/StatisticsImplementor.isStatisticsEnabled:()Z
      21: ifeq          28
      24: iconst_1
      25: goto          29
      28: iconst_0
      29: istore        4
      31: aload_1
      32: invokeinterface #21,  1           // InterfaceMethod java/util/Set.iterator:()Ljava/util/Iterator;
      37: astore        5
      39: aload         5
      41: invokeinterface #22,  1           // InterfaceMethod java/util/Iterator.hasNext:()Z
      46: ifeq          176
      49: aload         5
      51: invokeinterface #23,  1           // InterfaceMethod java/util/Iterator.next:()Ljava/lang/Object;
      56: checkcast     #24                 // class java/io/Serializable
      59: astore        6
      61: aload_0
      62: aload         6
      64: aload_3
      65: invokespecial #25                 // Method getLastUpdateTimestampForSpace:(Ljava/io/Serializable;Lorg/hibernate/engine/spi/SharedSessionContractImplementor;)Ljava/lang/Long;
      68: astore        7
      70: aload         7
      72: ifnonnull     97
      75: iload         4
      77: ifeq          173
      80: aload_0
      81: getfield      #5                  // Field factory:Lorg/hibernate/engine/spi/SessionFactoryImplementor;
      84: invokeinterface #7,  1            // InterfaceMethod org/hibernate/engine/spi/SessionFactoryImplementor.getStatistics:()Lorg/hibernate/stat/spi/StatisticsImplementor;
      89: invokeinterface #26,  1           // InterfaceMethod org/hibernate/stat/spi/StatisticsImplementor.updateTimestampsCacheMiss:()V
      94: goto          173
      97: getstatic     #12                 // Field DEBUG_ENABLED:Z
     100: ifeq          139
     103: getstatic     #2                  // Field LOG:Lorg/hibernate/internal/CoreMessageLogger;
     106: ldc           #27                 // String [%s] last update timestamp: %s
     108: aload         6
     110: new           #28                 // class java/lang/StringBuilder
     113: dup
     114: invokespecial #29                 // Method java/lang/StringBuilder."<init>":()V
     117: aload         7
     119: invokevirtual #30                 // Method java/lang/StringBuilder.append:(Ljava/lang/Object;)Ljava/lang/StringBuilder;
     122: ldc           #31                 // String , result set timestamp:
     124: invokevirtual #32                 // Method java/lang/StringBuilder.append:(Ljava/lang/String;)Ljava/lang/StringBuilder;
     127: aload_2
     128: invokevirtual #30                 // Method java/lang/StringBuilder.append:(Ljava/lang/Object;)Ljava/lang/StringBuilder;
     131: invokevirtual #33                 // Method java/lang/StringBuilder.toString:()Ljava/lang/String;
     134: invokeinterface #14,  4           // InterfaceMethod org/hibernate/internal/CoreMessageLogger.debugf:(Ljava/lang/String;Ljava/lang/Object;Ljava/lang/Object;)V
     139: iload         4
     141: ifeq          158
     144: aload_0
     145: getfield      #5                  // Field factory:Lorg/hibernate/engine/spi/SessionFactoryImplementor;
     148: invokeinterface #7,  1            // InterfaceMethod org/hibernate/engine/spi/SessionFactoryImplementor.getStatistics:()Lorg/hibernate/stat/spi/StatisticsImplementor;
     153: invokeinterface #34,  1           // InterfaceMethod org/hibernate/stat/spi/StatisticsImplementor.updateTimestampsCacheHit:()V
     158: aload         7
     160: invokevirtual #35                 // Method java/lang/Long.longValue:()J
     163: aload_2
     164: invokevirtual #35                 // Method java/lang/Long.longValue:()J
     167: lcmp
     168: iflt          173
     171: iconst_0
     172: ireturn
     173: goto          39
     176: iconst_1
     177: ireturn

  private java.lang.Long getLastUpdateTimestampForSpace(java.io.Serializable, org.hibernate.engine.spi.SharedSessionContractImplementor);
    Code:
       0: aconst_null
       1: astore_3
       2: aload_2
       3: invokeinterface #15,  1           // InterfaceMethod org/hibernate/engine/spi/SharedSessionContractImplementor.getEventListenerManager:()Lorg/hibernate/engine/spi/SessionEventListenerManager;
       8: invokeinterface #36,  1           // InterfaceMethod org/hibernate/engine/spi/SessionEventListenerManager.cacheGetStart:()V
      13: aload_0
      14: getfield      #6                  // Field region:Lorg/hibernate/cache/spi/TimestampsRegion;
      17: aload_2
      18: aload_1
      19: invokeinterface #37,  3           // InterfaceMethod org/hibernate/cache/spi/TimestampsRegion.get:(Lorg/hibernate/engine/spi/SharedSessionContractImplementor;Ljava/lang/Object;)Ljava/lang/Object;
      24: checkcast     #38                 // class java/lang/Long
      27: astore_3
      28: aload_2
      29: invokeinterface #15,  1           // InterfaceMethod org/hibernate/engine/spi/SharedSessionContractImplementor.getEventListenerManager:()Lorg/hibernate/engine/spi/SessionEventListenerManager;
      34: aload_3
      35: ifnull        42
      38: iconst_1
      39: goto          43
      42: iconst_0
      43: invokeinterface #39,  2           // InterfaceMethod org/hibernate/engine/spi/SessionEventListenerManager.cacheGetEnd:(Z)V
      48: goto          76
      51: astore        4
      53: aload_2
      54: invokeinterface #15,  1           // InterfaceMethod org/hibernate/engine/spi/SharedSessionContractImplementor.getEventListenerManager:()Lorg/hibernate/engine/spi/SessionEventListenerManager;
      59: aload_3
      60: ifnull        67
      63: iconst_1
      64: goto          68
      67: iconst_0
      68: invokeinterface #39,  2           // InterfaceMethod org/hibernate/engine/spi/SessionEventListenerManager.cacheGetEnd:(Z)V
      73: aload         4
      75: athrow
      76: aload_3
      77: areturn
    Exception table:
       from    to  target type
           2    28    51   any
          51    53    51   any

  public void clear() throws org.hibernate.cache.CacheException;
    Code:
       0: aload_0
       1: getfield      #6                  // Field region:Lorg/hibernate/cache/spi/TimestampsRegion;
       4: invokeinterface #40,  1           // InterfaceMethod org/hibernate/cache/spi/TimestampsRegion.evictAll:()V
       9: return

  public void destroy();
    Code:
       0: aload_0
       1: getfield      #6                  // Field region:Lorg/hibernate/cache/spi/TimestampsRegion;
       4: invokeinterface #41,  1           // InterfaceMethod org/hibernate/cache/spi/TimestampsRegion.destroy:()V
       9: goto          34
      12: astore_1
      13: getstatic     #2                  // Field LOG:Lorg/hibernate/internal/CoreMessageLogger;
      16: aload_0
      17: getfield      #6                  // Field region:Lorg/hibernate/cache/spi/TimestampsRegion;
      20: invokeinterface #3,  1            // InterfaceMethod org/hibernate/cache/spi/TimestampsRegion.getName:()Ljava/lang/String;
      25: aload_1
      26: invokevirtual #43                 // Method java/lang/Exception.getMessage:()Ljava/lang/String;
      29: invokeinterface #44,  3           // InterfaceMethod org/hibernate/internal/CoreMessageLogger.unableToDestroyUpdateTimestampsCache:(Ljava/lang/String;Ljava/lang/String;)V
      34: return
    Exception table:
       from    to  target type
           0     9    12   Class java/lang/Exception

  public org.hibernate.cache.spi.TimestampsRegion getRegion();
    Code:
       0: aload_0
       1: getfield      #6                  // Field region:Lorg/hibernate/cache/spi/TimestampsRegion;
       4: areturn

  public java.lang.String toString();
    Code:
       0: ldc           #45                 // String UpdateTimestampsCache
       2: areturn

  static {};
    Code:
       0: ldc           #46                 // class org/hibernate/internal/CoreMessageLogger
       2: ldc           #47                 // class org/hibernate/cache/spi/UpdateTimestampsCache
       4: invokevirtual #48                 // Method java/lang/Class.getName:()Ljava/lang/String;
       7: invokestatic  #49                 // Method org/jboss/logging/Logger.getMessageLogger:(Ljava/lang/Class;Ljava/lang/String;)Ljava/lang/Object;
      10: checkcast     #46                 // class org/hibernate/internal/CoreMessageLogger
      13: putstatic     #2                  // Field LOG:Lorg/hibernate/internal/CoreMessageLogger;
      16: getstatic     #2                  // Field LOG:Lorg/hibernate/internal/CoreMessageLogger;
      19: invokeinterface #50,  1           // InterfaceMethod org/hibernate/internal/CoreMessageLogger.isDebugEnabled:()Z
      24: putstatic     #12                 // Field DEBUG_ENABLED:Z
      27: ldc           #47                 // class org/hibernate/cache/spi/UpdateTimestampsCache
      29: invokevirtual #48                 // Method java/lang/Class.getName:()Ljava/lang/String;
      32: putstatic     #51                 // Field REGION_NAME:Ljava/lang/String;
      35: return
}
