Compiled from "MutableThreadContextStackDeserializer.java"
final class org.apache.logging.log4j.core.jackson.MutableThreadContextStackDeserializer extends com.fasterxml.jackson.databind.deser.std.StdDeserializer<org.apache.logging.log4j.spi.MutableThreadContextStack> {
  private static final long serialVersionUID;

  org.apache.logging.log4j.core.jackson.MutableThreadContextStackDeserializer();
    Code:
       0: aload_0
       1: ldc           #1                  // class org/apache/logging/log4j/spi/MutableThreadContextStack
       3: invokespecial #2                  // Method com/fasterxml/jackson/databind/deser/std/StdDeserializer."<init>":(Ljava/lang/Class;)V
       6: return

  public org.apache.logging.log4j.spi.MutableThreadContextStack deserialize(com.fasterxml.jackson.core.JsonParser, com.fasterxml.jackson.databind.DeserializationContext) throws java.io.IOException, com.fasterxml.jackson.core.JsonProcessingException;
    Code:
       0: aload_1
       1: new           #3                  // class org/apache/logging/log4j/core/jackson/MutableThreadContextStackDeserializer$1
       4: dup
       5: aload_0
       6: invokespecial #4                  // Method org/apache/logging/log4j/core/jackson/MutableThreadContextStackDeserializer$1."<init>":(Lorg/apache/logging/log4j/core/jackson/MutableThreadContextStackDeserializer;)V
       9: invokevirtual #5                  // Method com/fasterxml/jackson/core/JsonParser.readValueAs:(Lcom/fasterxml/jackson/core/type/TypeReference;)Ljava/lang/Object;
      12: checkcast     #6                  // class java/util/List
      15: astore_3
      16: new           #1                  // class org/apache/logging/log4j/spi/MutableThreadContextStack
      19: dup
      20: aload_3
      21: invokespecial #7                  // Method org/apache/logging/log4j/spi/MutableThreadContextStack."<init>":(Ljava/util/List;)V
      24: areturn

  public java.lang.Object deserialize(com.fasterxml.jackson.core.JsonParser, com.fasterxml.jackson.databind.DeserializationContext) throws java.io.IOException, com.fasterxml.jackson.core.JacksonException;
    Code:
       0: aload_0
       1: aload_1
       2: aload_2
       3: invokevirtual #8                  // Method deserialize:(Lcom/fasterxml/jackson/core/JsonParser;Lcom/fasterxml/jackson/databind/DeserializationContext;)Lorg/apache/logging/log4j/spi/MutableThreadContextStack;
       6: areturn
}
