Compiled from "SchemaResponse.java"
public class org.apache.solr.client.solrj.response.schema.SchemaResponse$DynamicFieldsResponse extends org.apache.solr.client.solrj.response.SolrResponseBase {
  java.util.List<java.util.Map<java.lang.String, java.lang.Object>> dynamicFields;

  public org.apache.solr.client.solrj.response.schema.SchemaResponse$DynamicFieldsResponse();
    Code:
       0: aload_0
       1: invokespecial #1                  // Method org/apache/solr/client/solrj/response/SolrResponseBase."<init>":()V
       4: return

  public void setResponse(org.apache.solr.common.util.NamedList<java.lang.Object>);
    Code:
       0: aload_0
       1: aload_1
       2: invokespecial #2                  // Method org/apache/solr/client/solrj/response/SolrResponseBase.setResponse:(Lorg/apache/solr/common/util/NamedList;)V
       5: aload_0
       6: aload_1
       7: iconst_3
       8: invokevirtual #3                  // Method org/apache/solr/common/util/NamedList.asMap:(I)Ljava/util/Map;
      11: invokestatic  #4                  // Method org/apache/solr/client/solrj/response/schema/SchemaResponse.access$400:(Ljava/util/Map;)Ljava/util/List;
      14: putfield      #5                  // Field dynamicFields:Ljava/util/List;
      17: return

  public java.util.List<java.util.Map<java.lang.String, java.lang.Object>> getDynamicFields();
    Code:
       0: aload_0
       1: getfield      #5                  // Field dynamicFields:Ljava/util/List;
       4: areturn
}
