Compiled from "MapIteratorCache.java"
class com.google.common.graph.MapIteratorCache<K, V> {
  private final java.util.Map<K, V> backingMap;

  private transient java.util.Map$Entry<K, V> entrySetCache;

  com.google.common.graph.MapIteratorCache(java.util.Map<K, V>);
    Code:
       0: aload_0
       1: invokespecial #3                  // Method java/lang/Object."<init>":()V
       4: aload_0
       5: aload_1
       6: invokestatic  #4                  // Method com/google/common/base/Preconditions.checkNotNull:(Ljava/lang/Object;)Ljava/lang/Object;
       9: checkcast     #5                  // class java/util/Map
      12: putfield      #2                  // Field backingMap:Ljava/util/Map;
      15: return

  public V put(K, V);
    Code:
       0: aload_0
       1: invokevirtual #6                  // Method clearCache:()V
       4: aload_0
       5: getfield      #2                  // Field backingMap:Ljava/util/Map;
       8: aload_1
       9: aload_2
      10: invokeinterface #7,  3            // InterfaceMethod java/util/Map.put:(Ljava/lang/Object;Ljava/lang/Object;)Ljava/lang/Object;
      15: areturn

  public V remove(java.lang.Object);
    Code:
       0: aload_0
       1: invokevirtual #6                  // Method clearCache:()V
       4: aload_0
       5: getfield      #2                  // Field backingMap:Ljava/util/Map;
       8: aload_1
       9: invokeinterface #8,  2            // InterfaceMethod java/util/Map.remove:(Ljava/lang/Object;)Ljava/lang/Object;
      14: areturn

  public void clear();
    Code:
       0: aload_0
       1: invokevirtual #6                  // Method clearCache:()V
       4: aload_0
       5: getfield      #2                  // Field backingMap:Ljava/util/Map;
       8: invokeinterface #9,  1            // InterfaceMethod java/util/Map.clear:()V
      13: return

  public V get(java.lang.Object);
    Code:
       0: aload_0
       1: aload_1
       2: invokevirtual #10                 // Method getIfCached:(Ljava/lang/Object;)Ljava/lang/Object;
       5: astore_2
       6: aload_2
       7: ifnull        14
      10: aload_2
      11: goto          19
      14: aload_0
      15: aload_1
      16: invokevirtual #11                 // Method getWithoutCaching:(Ljava/lang/Object;)Ljava/lang/Object;
      19: areturn

  public final V getWithoutCaching(java.lang.Object);
    Code:
       0: aload_0
       1: getfield      #2                  // Field backingMap:Ljava/util/Map;
       4: aload_1
       5: invokeinterface #12,  2           // InterfaceMethod java/util/Map.get:(Ljava/lang/Object;)Ljava/lang/Object;
      10: areturn

  public final boolean containsKey(java.lang.Object);
    Code:
       0: aload_0
       1: aload_1
       2: invokevirtual #10                 // Method getIfCached:(Ljava/lang/Object;)Ljava/lang/Object;
       5: ifnonnull     21
       8: aload_0
       9: getfield      #2                  // Field backingMap:Ljava/util/Map;
      12: aload_1
      13: invokeinterface #13,  2           // InterfaceMethod java/util/Map.containsKey:(Ljava/lang/Object;)Z
      18: ifeq          25
      21: iconst_1
      22: goto          26
      25: iconst_0
      26: ireturn

  public final java.util.Set<K> unmodifiableKeySet();
    Code:
       0: new           #14                 // class com/google/common/graph/MapIteratorCache$1
       3: dup
       4: aload_0
       5: invokespecial #15                 // Method com/google/common/graph/MapIteratorCache$1."<init>":(Lcom/google/common/graph/MapIteratorCache;)V
       8: areturn

  protected V getIfCached(java.lang.Object);
    Code:
       0: aload_0
       1: getfield      #1                  // Field entrySetCache:Ljava/util/Map$Entry;
       4: astore_2
       5: aload_2
       6: ifnull        26
       9: aload_2
      10: invokeinterface #16,  1           // InterfaceMethod java/util/Map$Entry.getKey:()Ljava/lang/Object;
      15: aload_1
      16: if_acmpne     26
      19: aload_2
      20: invokeinterface #17,  1           // InterfaceMethod java/util/Map$Entry.getValue:()Ljava/lang/Object;
      25: areturn
      26: aconst_null
      27: areturn

  protected void clearCache();
    Code:
       0: aload_0
       1: aconst_null
       2: putfield      #1                  // Field entrySetCache:Ljava/util/Map$Entry;
       5: return

  static java.util.Map access$000(com.google.common.graph.MapIteratorCache);
    Code:
       0: aload_0
       1: getfield      #2                  // Field backingMap:Ljava/util/Map;
       4: areturn

  static java.util.Map$Entry access$102(com.google.common.graph.MapIteratorCache, java.util.Map$Entry);
    Code:
       0: aload_0
       1: aload_1
       2: dup_x1
       3: putfield      #1                  // Field entrySetCache:Ljava/util/Map$Entry;
       6: areturn
}
