Compiled from "DefaultEntityHelper.java"
public final class io.fluxcapacitor.javaclient.modeling.DefaultEntityHelper$MessageWithEntity implements io.fluxcapacitor.javaclient.common.HasMessage,io.fluxcapacitor.javaclient.modeling.HasEntity {
  private final io.fluxcapacitor.javaclient.modeling.Entity<?> entity;

  private final java.lang.Object payload;

  public io.fluxcapacitor.javaclient.modeling.DefaultEntityHelper$MessageWithEntity(java.lang.Object, io.fluxcapacitor.javaclient.modeling.Entity<?>);
    Code:
       0: aload_0
       1: invokespecial #1                  // Method java/lang/Object."<init>":()V
       4: aload_0
       5: aload_1
       6: putfield      #7                  // Field payload:Ljava/lang/Object;
       9: aload_0
      10: aload_2
      11: putfield      #13                 // Field entity:Lio/fluxcapacitor/javaclient/modeling/Entity;
      14: return

  public io.fluxcapacitor.javaclient.modeling.DefaultEntityHelper$MessageWithEntity withEntity(io.fluxcapacitor.javaclient.modeling.Entity<?>);
    Code:
       0: new           #8                  // class io/fluxcapacitor/javaclient/modeling/DefaultEntityHelper$MessageWithEntity
       3: dup
       4: aload_0
       5: getfield      #7                  // Field payload:Ljava/lang/Object;
       8: aload_1
       9: invokespecial #17                 // Method "<init>":(Ljava/lang/Object;Lio/fluxcapacitor/javaclient/modeling/Entity;)V
      12: areturn

  public io.fluxcapacitor.common.api.Metadata getMetadata();
    Code:
       0: aload_0
       1: getfield      #7                  // Field payload:Ljava/lang/Object;
       4: instanceof    #20                 // class io/fluxcapacitor/common/api/HasMetadata
       7: ifeq          25
      10: aload_0
      11: getfield      #7                  // Field payload:Ljava/lang/Object;
      14: checkcast     #20                 // class io/fluxcapacitor/common/api/HasMetadata
      17: invokeinterface #22,  1           // InterfaceMethod io/fluxcapacitor/common/api/HasMetadata.getMetadata:()Lio/fluxcapacitor/common/api/Metadata;
      22: goto          28
      25: invokestatic  #26                 // Method io/fluxcapacitor/common/api/Metadata.empty:()Lio/fluxcapacitor/common/api/Metadata;
      28: areturn

  public io.fluxcapacitor.javaclient.common.Message toMessage();
    Code:
       0: aload_0
       1: getfield      #7                  // Field payload:Ljava/lang/Object;
       4: invokestatic  #31                 // Method io/fluxcapacitor/javaclient/common/Message.asMessage:(Ljava/lang/Object;)Lio/fluxcapacitor/javaclient/common/Message;
       7: areturn

  public <R> R getPayload();
    Code:
       0: aload_0
       1: getfield      #7                  // Field payload:Ljava/lang/Object;
       4: instanceof    #37                 // class io/fluxcapacitor/javaclient/common/HasMessage
       7: ifeq          25
      10: aload_0
      11: getfield      #7                  // Field payload:Ljava/lang/Object;
      14: checkcast     #37                 // class io/fluxcapacitor/javaclient/common/HasMessage
      17: invokeinterface #39,  1           // InterfaceMethod io/fluxcapacitor/javaclient/common/HasMessage.getPayload:()Ljava/lang/Object;
      22: goto          29
      25: aload_0
      26: getfield      #7                  // Field payload:Ljava/lang/Object;
      29: areturn

  public io.fluxcapacitor.javaclient.modeling.Entity<?> getEntity();
    Code:
       0: aload_0
       1: getfield      #13                 // Field entity:Lio/fluxcapacitor/javaclient/modeling/Entity;
       4: areturn

  public boolean equals(java.lang.Object);
    Code:
       0: aload_1
       1: aload_0
       2: if_acmpne     7
       5: iconst_1
       6: ireturn
       7: aload_1
       8: instanceof    #8                  // class io/fluxcapacitor/javaclient/modeling/DefaultEntityHelper$MessageWithEntity
      11: ifne          16
      14: iconst_0
      15: ireturn
      16: aload_1
      17: checkcast     #8                  // class io/fluxcapacitor/javaclient/modeling/DefaultEntityHelper$MessageWithEntity
      20: astore_2
      21: aload_0
      22: invokevirtual #43                 // Method getEntity:()Lio/fluxcapacitor/javaclient/modeling/Entity;
      25: astore_3
      26: aload_2
      27: invokevirtual #43                 // Method getEntity:()Lio/fluxcapacitor/javaclient/modeling/Entity;
      30: astore        4
      32: aload_3
      33: ifnonnull     44
      36: aload         4
      38: ifnull        55
      41: goto          53
      44: aload_3
      45: aload         4
      47: invokevirtual #47                 // Method java/lang/Object.equals:(Ljava/lang/Object;)Z
      50: ifne          55
      53: iconst_0
      54: ireturn
      55: aload_0
      56: invokevirtual #51                 // Method getPayload:()Ljava/lang/Object;
      59: astore        5
      61: aload_2
      62: invokevirtual #51                 // Method getPayload:()Ljava/lang/Object;
      65: astore        6
      67: aload         5
      69: ifnonnull     80
      72: aload         6
      74: ifnull        92
      77: goto          90
      80: aload         5
      82: aload         6
      84: invokevirtual #47                 // Method java/lang/Object.equals:(Ljava/lang/Object;)Z
      87: ifne          92
      90: iconst_0
      91: ireturn
      92: iconst_1
      93: ireturn

  public int hashCode();
    Code:
       0: bipush        59
       2: istore_1
       3: iconst_1
       4: istore_2
       5: aload_0
       6: invokevirtual #43                 // Method getEntity:()Lio/fluxcapacitor/javaclient/modeling/Entity;
       9: astore_3
      10: iload_2
      11: bipush        59
      13: imul
      14: aload_3
      15: ifnonnull     23
      18: bipush        43
      20: goto          27
      23: aload_3
      24: invokevirtual #52                 // Method java/lang/Object.hashCode:()I
      27: iadd
      28: istore_2
      29: aload_0
      30: invokevirtual #51                 // Method getPayload:()Ljava/lang/Object;
      33: astore        4
      35: iload_2
      36: bipush        59
      38: imul
      39: aload         4
      41: ifnonnull     49
      44: bipush        43
      46: goto          54
      49: aload         4
      51: invokevirtual #52                 // Method java/lang/Object.hashCode:()I
      54: iadd
      55: istore_2
      56: iload_2
      57: ireturn

  public java.lang.String toString();
    Code:
       0: aload_0
       1: invokevirtual #43                 // Method getEntity:()Lio/fluxcapacitor/javaclient/modeling/Entity;
       4: aload_0
       5: invokevirtual #51                 // Method getPayload:()Ljava/lang/Object;
       8: invokedynamic #56,  0             // InvokeDynamic #0:makeConcatWithConstants:(Lio/fluxcapacitor/javaclient/modeling/Entity;Ljava/lang/Object;)Ljava/lang/String;
      13: areturn
}
