Compiled from "BundleConfig.scala"
public class blended.updater.config.BundleConfig implements scala.Product,java.io.Serializable {
  private final blended.updater.config.Artifact artifact;

  private final boolean start;

  private final scala.Option<java.lang.Object> startLevel;

  public static scala.Option<scala.Tuple3<blended.updater.config.Artifact, java.lang.Object, scala.Option<java.lang.Object>>> unapply(blended.updater.config.BundleConfig);
    Code:
       0: getstatic     #29                 // Field blended/updater/config/BundleConfig$.MODULE$:Lblended/updater/config/BundleConfig$;
       3: aload_0
       4: invokevirtual #31                 // Method blended/updater/config/BundleConfig$.unapply:(Lblended/updater/config/BundleConfig;)Lscala/Option;
       7: areturn

  public static blended.updater.config.BundleConfig apply(blended.updater.config.Artifact, boolean, scala.Option<java.lang.Object>);
    Code:
       0: getstatic     #29                 // Field blended/updater/config/BundleConfig$.MODULE$:Lblended/updater/config/BundleConfig$;
       3: aload_0
       4: iload_1
       5: aload_2
       6: invokevirtual #36                 // Method blended/updater/config/BundleConfig$.apply:(Lblended/updater/config/Artifact;ZLscala/Option;)Lblended/updater/config/BundleConfig;
       9: areturn

  public static java.lang.Integer apply$default$5();
    Code:
       0: getstatic     #29                 // Field blended/updater/config/BundleConfig$.MODULE$:Lblended/updater/config/BundleConfig$;
       3: invokevirtual #40                 // Method blended/updater/config/BundleConfig$.apply$default$5:()Ljava/lang/Integer;
       6: areturn

  public static boolean apply$default$4();
    Code:
       0: getstatic     #29                 // Field blended/updater/config/BundleConfig$.MODULE$:Lblended/updater/config/BundleConfig$;
       3: invokevirtual #44                 // Method blended/updater/config/BundleConfig$.apply$default$4:()Z
       6: ireturn

  public static java.lang.String apply$default$3();
    Code:
       0: getstatic     #29                 // Field blended/updater/config/BundleConfig$.MODULE$:Lblended/updater/config/BundleConfig$;
       3: invokevirtual #48                 // Method blended/updater/config/BundleConfig$.apply$default$3:()Ljava/lang/String;
       6: areturn

  public static java.lang.String apply$default$2();
    Code:
       0: getstatic     #29                 // Field blended/updater/config/BundleConfig$.MODULE$:Lblended/updater/config/BundleConfig$;
       3: invokevirtual #51                 // Method blended/updater/config/BundleConfig$.apply$default$2:()Ljava/lang/String;
       6: areturn

  public static blended.updater.config.BundleConfig apply(java.lang.String, java.lang.String, java.lang.String, boolean, java.lang.Integer);
    Code:
       0: getstatic     #29                 // Field blended/updater/config/BundleConfig$.MODULE$:Lblended/updater/config/BundleConfig$;
       3: aload_0
       4: aload_1
       5: aload_2
       6: iload_3
       7: aload         4
       9: invokevirtual #57                 // Method blended/updater/config/BundleConfig$.apply:(Ljava/lang/String;Ljava/lang/String;Ljava/lang/String;ZLjava/lang/Integer;)Lblended/updater/config/BundleConfig;
      12: areturn

  public static scala.Function1<scala.Tuple3<blended.updater.config.Artifact, java.lang.Object, scala.Option<java.lang.Object>>, blended.updater.config.BundleConfig> tupled();
    Code:
       0: getstatic     #29                 // Field blended/updater/config/BundleConfig$.MODULE$:Lblended/updater/config/BundleConfig$;
       3: invokevirtual #62                 // Method blended/updater/config/BundleConfig$.tupled:()Lscala/Function1;
       6: areturn

  public static scala.Function1<blended.updater.config.Artifact, scala.Function1<java.lang.Object, scala.Function1<scala.Option<java.lang.Object>, blended.updater.config.BundleConfig>>> curried();
    Code:
       0: getstatic     #29                 // Field blended/updater/config/BundleConfig$.MODULE$:Lblended/updater/config/BundleConfig$;
       3: invokevirtual #66                 // Method blended/updater/config/BundleConfig$.curried:()Lscala/Function1;
       6: areturn

  public scala.collection.Iterator<java.lang.String> productElementNames();
    Code:
       0: aload_0
       1: invokestatic  #73                 // InterfaceMethod scala/Product.productElementNames$:(Lscala/Product;)Lscala/collection/Iterator;
       4: areturn

  public blended.updater.config.Artifact artifact();
    Code:
       0: aload_0
       1: getfield      #78                 // Field artifact:Lblended/updater/config/Artifact;
       4: areturn

  public boolean start();
    Code:
       0: aload_0
       1: getfield      #80                 // Field start:Z
       4: ireturn

  public scala.Option<java.lang.Object> startLevel();
    Code:
       0: aload_0
       1: getfield      #84                 // Field startLevel:Lscala/Option;
       4: areturn

  public java.lang.String url();
    Code:
       0: aload_0
       1: invokevirtual #86                 // Method artifact:()Lblended/updater/config/Artifact;
       4: invokevirtual #90                 // Method blended/updater/config/Artifact.url:()Ljava/lang/String;
       7: areturn

  public scala.Option<java.lang.String> jarName();
    Code:
       0: aload_0
       1: invokevirtual #86                 // Method artifact:()Lblended/updater/config/Artifact;
       4: invokevirtual #94                 // Method blended/updater/config/Artifact.fileName:()Lscala/Option;
       7: areturn

  public scala.Option<java.lang.String> sha1Sum();
    Code:
       0: aload_0
       1: invokevirtual #86                 // Method artifact:()Lblended/updater/config/Artifact;
       4: invokevirtual #96                 // Method blended/updater/config/Artifact.sha1Sum:()Lscala/Option;
       7: areturn

  public java.lang.String toString();
    Code:
       0: new           #99                 // class java/lang/StringBuilder
       3: dup
       4: ldc           #100                // int 35
       6: invokespecial #104                // Method java/lang/StringBuilder."<init>":(I)V
       9: aload_0
      10: invokevirtual #108                // Method getClass:()Ljava/lang/Class;
      13: invokevirtual #113                // Method java/lang/Class.getSimpleName:()Ljava/lang/String;
      16: invokevirtual #117                // Method java/lang/StringBuilder.append:(Ljava/lang/String;)Ljava/lang/StringBuilder;
      19: ldc           #119                // String (artifact=
      21: invokevirtual #117                // Method java/lang/StringBuilder.append:(Ljava/lang/String;)Ljava/lang/StringBuilder;
      24: aload_0
      25: invokevirtual #86                 // Method artifact:()Lblended/updater/config/Artifact;
      28: invokevirtual #122                // Method java/lang/StringBuilder.append:(Ljava/lang/Object;)Ljava/lang/StringBuilder;
      31: ldc           #124                // String ,start=
      33: invokevirtual #117                // Method java/lang/StringBuilder.append:(Ljava/lang/String;)Ljava/lang/StringBuilder;
      36: aload_0
      37: invokevirtual #126                // Method start:()Z
      40: invokevirtual #129                // Method java/lang/StringBuilder.append:(Z)Ljava/lang/StringBuilder;
      43: ldc           #131                // String ,url=
      45: invokevirtual #117                // Method java/lang/StringBuilder.append:(Ljava/lang/String;)Ljava/lang/StringBuilder;
      48: aload_0
      49: invokevirtual #132                // Method url:()Ljava/lang/String;
      52: invokevirtual #117                // Method java/lang/StringBuilder.append:(Ljava/lang/String;)Ljava/lang/StringBuilder;
      55: ldc           #134                // String ,startLevel=
      57: invokevirtual #117                // Method java/lang/StringBuilder.append:(Ljava/lang/String;)Ljava/lang/StringBuilder;
      60: aload_0
      61: invokevirtual #136                // Method startLevel:()Lscala/Option;
      64: invokevirtual #122                // Method java/lang/StringBuilder.append:(Ljava/lang/Object;)Ljava/lang/StringBuilder;
      67: ldc           #138                // String )
      69: invokevirtual #117                // Method java/lang/StringBuilder.append:(Ljava/lang/String;)Ljava/lang/StringBuilder;
      72: invokevirtual #140                // Method java/lang/StringBuilder.toString:()Ljava/lang/String;
      75: areturn

  public blended.updater.config.BundleConfig copy(blended.updater.config.Artifact, boolean, scala.Option<java.lang.Object>);
    Code:
       0: new           #2                  // class blended/updater/config/BundleConfig
       3: dup
       4: aload_1
       5: iload_2
       6: aload_3
       7: invokespecial #144                // Method "<init>":(Lblended/updater/config/Artifact;ZLscala/Option;)V
      10: areturn

  public blended.updater.config.Artifact copy$default$1();
    Code:
       0: aload_0
       1: invokevirtual #86                 // Method artifact:()Lblended/updater/config/Artifact;
       4: areturn

  public boolean copy$default$2();
    Code:
       0: aload_0
       1: invokevirtual #126                // Method start:()Z
       4: ireturn

  public scala.Option<java.lang.Object> copy$default$3();
    Code:
       0: aload_0
       1: invokevirtual #136                // Method startLevel:()Lscala/Option;
       4: areturn

  public java.lang.String productPrefix();
    Code:
       0: ldc           #150                // String BundleConfig
       2: areturn

  public int productArity();
    Code:
       0: iconst_3
       1: ireturn

  public java.lang.Object productElement(int);
    Code:
       0: iload_1
       1: istore_2
       2: iload_2
       3: tableswitch   { // 0 to 2
                     0: 28
                     1: 35
                     2: 45
               default: 52
          }
      28: aload_0
      29: invokevirtual #86                 // Method artifact:()Lblended/updater/config/Artifact;
      32: goto          59
      35: aload_0
      36: invokevirtual #126                // Method start:()Z
      39: invokestatic  #161                // Method scala/runtime/BoxesRunTime.boxToBoolean:(Z)Ljava/lang/Boolean;
      42: goto          59
      45: aload_0
      46: invokevirtual #136                // Method startLevel:()Lscala/Option;
      49: goto          59
      52: iload_1
      53: invokestatic  #166                // Method scala/runtime/Statics.ioobe:(I)Ljava/lang/Object;
      56: goto          59
      59: areturn

  public scala.collection.Iterator<java.lang.Object> productIterator();
    Code:
       0: getstatic     #174                // Field scala/runtime/ScalaRunTime$.MODULE$:Lscala/runtime/ScalaRunTime$;
       3: aload_0
       4: invokevirtual #177                // Method scala/runtime/ScalaRunTime$.typedProductIterator:(Lscala/Product;)Lscala/collection/Iterator;
       7: areturn

  public boolean canEqual(java.lang.Object);
    Code:
       0: aload_1
       1: instanceof    #2                  // class blended/updater/config/BundleConfig
       4: ireturn

  public java.lang.String productElementName(int);
    Code:
       0: iload_1
       1: istore_2
       2: iload_2
       3: tableswitch   { // 0 to 2
                     0: 28
                     1: 33
                     2: 38
               default: 43
          }
      28: ldc           #183                // String artifact
      30: goto          53
      33: ldc           #184                // String start
      35: goto          53
      38: ldc           #185                // String startLevel
      40: goto          53
      43: iload_1
      44: invokestatic  #166                // Method scala/runtime/Statics.ioobe:(I)Ljava/lang/Object;
      47: checkcast     #187                // class java/lang/String
      50: goto          53
      53: areturn

  public int hashCode();
    Code:
       0: ldc           #189                // int -889275714
       2: istore_1
       3: iload_1
       4: aload_0
       5: invokevirtual #191                // Method productPrefix:()Ljava/lang/String;
       8: invokevirtual #193                // Method java/lang/String.hashCode:()I
      11: invokestatic  #197                // Method scala/runtime/Statics.mix:(II)I
      14: istore_1
      15: iload_1
      16: aload_0
      17: invokevirtual #86                 // Method artifact:()Lblended/updater/config/Artifact;
      20: invokestatic  #201                // Method scala/runtime/Statics.anyHash:(Ljava/lang/Object;)I
      23: invokestatic  #197                // Method scala/runtime/Statics.mix:(II)I
      26: istore_1
      27: iload_1
      28: aload_0
      29: invokevirtual #126                // Method start:()Z
      32: ifeq          41
      35: sipush        1231
      38: goto          44
      41: sipush        1237
      44: invokestatic  #197                // Method scala/runtime/Statics.mix:(II)I
      47: istore_1
      48: iload_1
      49: aload_0
      50: invokevirtual #136                // Method startLevel:()Lscala/Option;
      53: invokestatic  #201                // Method scala/runtime/Statics.anyHash:(Ljava/lang/Object;)I
      56: invokestatic  #197                // Method scala/runtime/Statics.mix:(II)I
      59: istore_1
      60: iload_1
      61: iconst_3
      62: invokestatic  #204                // Method scala/runtime/Statics.finalizeHash:(II)I
      65: ireturn

  public boolean equals(java.lang.Object);
    Code:
       0: aload_0
       1: aload_1
       2: if_acmpeq     130
       5: aload_1
       6: astore_3
       7: aload_3
       8: instanceof    #2                  // class blended/updater/config/BundleConfig
      11: ifeq          19
      14: iconst_1
      15: istore_2
      16: goto          27
      19: goto          22
      22: iconst_0
      23: istore_2
      24: goto          27
      27: iload_2
      28: ifeq          134
      31: aload_1
      32: checkcast     #2                  // class blended/updater/config/BundleConfig
      35: astore        4
      37: aload_0
      38: invokevirtual #126                // Method start:()Z
      41: aload         4
      43: invokevirtual #126                // Method start:()Z
      46: if_icmpne     126
      49: aload_0
      50: invokevirtual #86                 // Method artifact:()Lblended/updater/config/Artifact;
      53: aload         4
      55: invokevirtual #86                 // Method artifact:()Lblended/updater/config/Artifact;
      58: astore        5
      60: dup
      61: ifnonnull     73
      64: pop
      65: aload         5
      67: ifnull        81
      70: goto          126
      73: aload         5
      75: invokevirtual #207                // Method java/lang/Object.equals:(Ljava/lang/Object;)Z
      78: ifeq          126
      81: aload_0
      82: invokevirtual #136                // Method startLevel:()Lscala/Option;
      85: aload         4
      87: invokevirtual #136                // Method startLevel:()Lscala/Option;
      90: astore        6
      92: dup
      93: ifnonnull     105
      96: pop
      97: aload         6
      99: ifnull        113
     102: goto          126
     105: aload         6
     107: invokevirtual #207                // Method java/lang/Object.equals:(Ljava/lang/Object;)Z
     110: ifeq          126
     113: aload         4
     115: aload_0
     116: invokevirtual #209                // Method canEqual:(Ljava/lang/Object;)Z
     119: ifeq          126
     122: iconst_1
     123: goto          127
     126: iconst_0
     127: ifeq          134
     130: iconst_1
     131: goto          135
     134: iconst_0
     135: ireturn

  public blended.updater.config.BundleConfig(blended.updater.config.Artifact, boolean, scala.Option<java.lang.Object>);
    Code:
       0: aload_0
       1: aload_1
       2: putfield      #78                 // Field artifact:Lblended/updater/config/Artifact;
       5: aload_0
       6: iload_2
       7: putfield      #80                 // Field start:Z
      10: aload_0
      11: aload_3
      12: putfield      #84                 // Field startLevel:Lscala/Option;
      15: aload_0
      16: invokespecial #215                // Method java/lang/Object."<init>":()V
      19: aload_0
      20: invokestatic  #219                // InterfaceMethod scala/Product.$init$:(Lscala/Product;)V
      23: return
}
