Compiled from "GetLicenseRequest.java"
public class org.elasticsearch.client.license.GetLicenseRequest implements org.elasticsearch.client.Validatable {
  protected boolean local;

  public org.elasticsearch.client.license.GetLicenseRequest();
    Code:
       0: aload_0
       1: invokespecial #1                  // Method java/lang/Object."<init>":()V
       4: aload_0
       5: iconst_0
       6: putfield      #2                  // Field local:Z
       9: return

  public boolean isLocal();
    Code:
       0: aload_0
       1: getfield      #2                  // Field local:Z
       4: ireturn

  public void setLocal(boolean);
    Code:
       0: aload_0
       1: iload_1
       2: putfield      #2                  // Field local:Z
       5: return
}
