Compiled from "BeanMap.java"
class org.apache.commons.beanutils.BeanMap$11 implements java.util.Iterator<java.lang.Object> {
  final java.util.Iterator val$iter;

  final org.apache.commons.beanutils.BeanMap this$0;

  org.apache.commons.beanutils.BeanMap$11(org.apache.commons.beanutils.BeanMap, java.util.Iterator);
    Code:
       0: aload_0
       1: aload_1
       2: putfield      #1                  // Field this$0:Lorg/apache/commons/beanutils/BeanMap;
       5: aload_0
       6: aload_2
       7: putfield      #2                  // Field val$iter:Ljava/util/Iterator;
      10: aload_0
      11: invokespecial #3                  // Method java/lang/Object."<init>":()V
      14: return

  public boolean hasNext();
    Code:
       0: aload_0
       1: getfield      #2                  // Field val$iter:Ljava/util/Iterator;
       4: invokeinterface #4,  1            // InterfaceMethod java/util/Iterator.hasNext:()Z
       9: ireturn

  public java.lang.Object next();
    Code:
       0: aload_0
       1: getfield      #2                  // Field val$iter:Ljava/util/Iterator;
       4: invokeinterface #5,  1            // InterfaceMethod java/util/Iterator.next:()Ljava/lang/Object;
       9: astore_1
      10: aload_0
      11: getfield      #1                  // Field this$0:Lorg/apache/commons/beanutils/BeanMap;
      14: aload_1
      15: invokevirtual #6                  // Method org/apache/commons/beanutils/BeanMap.get:(Ljava/lang/Object;)Ljava/lang/Object;
      18: areturn

  public void remove();
    Code:
       0: new           #7                  // class java/lang/UnsupportedOperationException
       3: dup
       4: ldc           #8                  // String remove() not supported for BeanMap
       6: invokespecial #9                  // Method java/lang/UnsupportedOperationException."<init>":(Ljava/lang/String;)V
       9: athrow
}
