Compiled from "PartialFunction.scala"
public final class scalaz.std.PartialFunctionInstances$$anon$1$$anonfun$1 extends scala.runtime.AbstractPartialFunction<java.lang.Object, java.lang.Object> implements java.io.Serializable {
  private static final long serialVersionUID;

  private final scalaz.std.PartialFunctionInstances$$anon$1 $outer;

  public final <A1, B1> B1 applyOrElse(A1, scala.Function1<A1, B1>);
    Code:
       0: aload_0
       1: getfield      #23                 // Field $outer:Lscalaz/std/PartialFunctionInstances$$anon$1;
       4: getfield      #27                 // Field scalaz/std/PartialFunctionInstances$$anon$1.scalaz$std$PartialFunctionInstances$$anon$$fallback_pf:Lscala/PartialFunction;
       7: areturn

  public final boolean isDefinedAt(java.lang.Object);
    Code:
       0: iconst_1
       1: ireturn

  public scalaz.std.PartialFunctionInstances$$anon$1$$anonfun$1(scalaz.std.PartialFunctionInstances$$anon$1);
    Code:
       0: aload_1
       1: ifnonnull     6
       4: aconst_null
       5: athrow
       6: aload_0
       7: aload_1
       8: putfield      #23                 // Field $outer:Lscalaz/std/PartialFunctionInstances$$anon$1;
      11: aload_0
      12: invokespecial #38                 // Method scala/runtime/AbstractPartialFunction."<init>":()V
      15: return
}
