Compiled from "Stream.scala"
public final class scalaz.std.StreamInstances$$anon$2 implements scalaz.Applicative<?> {
  private scalaz.syntax.ApplicativeSyntax<?> applicativeSyntax;

  private scalaz.syntax.InvariantApplicativeSyntax<?> invariantApplicativeSyntax;

  private scalaz.syntax.ApplySyntax<?> applySyntax;

  private scalaz.syntax.FunctorSyntax<?> functorSyntax;

  private scalaz.syntax.InvariantFunctorSyntax<?> invariantFunctorSyntax;

  public final <A> java.lang.Object pure(scala.Function0<A>);
    Code:
       0: aload_0
       1: aload_1
       2: invokestatic  #71                 // InterfaceMethod scalaz/Applicative.pure$:(Lscalaz/Applicative;Lscala/Function0;)Ljava/lang/Object;
       5: areturn

  public <A, B> java.lang.Object map(java.lang.Object, scala.Function1<A, B>);
    Code:
       0: aload_0
       1: aload_1
       2: aload_2
       3: invokestatic  #83                 // InterfaceMethod scalaz/Applicative.map$:(Lscalaz/Applicative;Ljava/lang/Object;Lscala/Function1;)Ljava/lang/Object;
       6: areturn

  public <A, B, C> java.lang.Object apply2(scala.Function0<java.lang.Object>, scala.Function0<java.lang.Object>, scala.Function2<A, B, C>);
    Code:
       0: aload_0
       1: aload_1
       2: aload_2
       3: aload_3
       4: invokestatic  #93                 // InterfaceMethod scalaz/Applicative.apply2$:(Lscalaz/Applicative;Lscala/Function0;Lscala/Function0;Lscala/Function2;)Ljava/lang/Object;
       7: areturn

  public <A, G$, B> java.lang.Object traverse(G$, scala.Function1<A, java.lang.Object>, scalaz.Traverse<G$>);
    Code:
       0: aload_0
       1: aload_1
       2: aload_2
       3: aload_3
       4: invokestatic  #103                // InterfaceMethod scalaz/Applicative.traverse$:(Lscalaz/Applicative;Ljava/lang/Object;Lscala/Function1;Lscalaz/Traverse;)Ljava/lang/Object;
       7: areturn

  public <A, G$> java.lang.Object sequence(G$, scalaz.Traverse<G$>);
    Code:
       0: aload_0
       1: aload_1
       2: aload_2
       3: invokestatic  #113                // InterfaceMethod scalaz/Applicative.sequence$:(Lscalaz/Applicative;Ljava/lang/Object;Lscalaz/Traverse;)Ljava/lang/Object;
       6: areturn

  public scalaz.Applicative<?> par();
    Code:
       0: aload_0
       1: invokestatic  #120                // InterfaceMethod scalaz/Applicative.par$:(Lscalaz/Applicative;)Lscalaz/Applicative;
       4: areturn

  public <Z> java.lang.Object xproduct0(scala.Function0<Z>);
    Code:
       0: aload_0
       1: aload_1
       2: invokestatic  #126                // InterfaceMethod scalaz/Applicative.xproduct0$:(Lscalaz/Applicative;Lscala/Function0;)Ljava/lang/Object;
       5: areturn

  public <Z, A1> java.lang.Object xproduct1(scala.Function0<java.lang.Object>, scala.Function1<A1, Z>, scala.Function1<Z, A1>);
    Code:
       0: aload_0
       1: aload_1
       2: aload_2
       3: aload_3
       4: invokestatic  #135                // InterfaceMethod scalaz/Applicative.xproduct1$:(Lscalaz/Applicative;Lscala/Function0;Lscala/Function1;Lscala/Function1;)Ljava/lang/Object;
       7: areturn

  public <Z, A1, A2> java.lang.Object xproduct2(scala.Function0<java.lang.Object>, scala.Function0<java.lang.Object>, scala.Function2<A1, A2, Z>, scala.Function1<Z, scala.Tuple2<A1, A2>>);
    Code:
       0: aload_0
       1: aload_1
       2: aload_2
       3: aload_3
       4: aload         4
       6: invokestatic  #143                // InterfaceMethod scalaz/Applicative.xproduct2$:(Lscalaz/Applicative;Lscala/Function0;Lscala/Function0;Lscala/Function2;Lscala/Function1;)Ljava/lang/Object;
       9: areturn

  public <Z, A1, A2, A3> java.lang.Object xproduct3(scala.Function0<java.lang.Object>, scala.Function0<java.lang.Object>, scala.Function0<java.lang.Object>, scala.Function3<A1, A2, A3, Z>, scala.Function1<Z, scala.Tuple3<A1, A2, A3>>);
    Code:
       0: aload_0
       1: aload_1
       2: aload_2
       3: aload_3
       4: aload         4
       6: aload         5
       8: invokestatic  #151                // InterfaceMethod scalaz/Applicative.xproduct3$:(Lscalaz/Applicative;Lscala/Function0;Lscala/Function0;Lscala/Function0;Lscala/Function3;Lscala/Function1;)Ljava/lang/Object;
      11: areturn

  public <Z, A1, A2, A3, A4> java.lang.Object xproduct4(scala.Function0<java.lang.Object>, scala.Function0<java.lang.Object>, scala.Function0<java.lang.Object>, scala.Function0<java.lang.Object>, scala.Function4<A1, A2, A3, A4, Z>, scala.Function1<Z, scala.Tuple4<A1, A2, A3, A4>>);
    Code:
       0: aload_0
       1: aload_1
       2: aload_2
       3: aload_3
       4: aload         4
       6: aload         5
       8: aload         6
      10: invokestatic  #160                // InterfaceMethod scalaz/Applicative.xproduct4$:(Lscalaz/Applicative;Lscala/Function0;Lscala/Function0;Lscala/Function0;Lscala/Function0;Lscala/Function4;Lscala/Function1;)Ljava/lang/Object;
      13: areturn

  public <A> java.lang.Object replicateM(int, java.lang.Object);
    Code:
       0: aload_0
       1: iload_1
       2: aload_2
       3: invokestatic  #169                // InterfaceMethod scalaz/Applicative.replicateM$:(Lscalaz/Applicative;ILjava/lang/Object;)Ljava/lang/Object;
       6: areturn

  public <A> java.lang.Object replicateM_(int, java.lang.Object);
    Code:
       0: aload_0
       1: iload_1
       2: aload_2
       3: invokestatic  #174                // InterfaceMethod scalaz/Applicative.replicateM_$:(Lscalaz/Applicative;ILjava/lang/Object;)Ljava/lang/Object;
       6: areturn

  public <A, B> java.lang.Object filterM(scalaz.$eq$eq$greater$greater<A, B>, scala.Function1<B, java.lang.Object>, scalaz.Order<A>);
    Code:
       0: aload_0
       1: aload_1
       2: aload_2
       3: aload_3
       4: invokestatic  #182                // InterfaceMethod scalaz/Applicative.filterM$:(Lscalaz/Applicative;Lscalaz/$eq$eq$greater$greater;Lscala/Function1;Lscalaz/Order;)Ljava/lang/Object;
       7: areturn

  public <A> java.lang.Object filterM(scala.collection.immutable.List<A>, scala.Function1<A, java.lang.Object>);
    Code:
       0: aload_0
       1: aload_1
       2: aload_2
       3: invokestatic  #190                // InterfaceMethod scalaz/Applicative.filterM$:(Lscalaz/Applicative;Lscala/collection/immutable/List;Lscala/Function1;)Ljava/lang/Object;
       6: areturn

  public <A> java.lang.Object filterM(scalaz.IList<A>, scala.Function1<A, java.lang.Object>);
    Code:
       0: aload_0
       1: aload_1
       2: aload_2
       3: invokestatic  #196                // InterfaceMethod scalaz/Applicative.filterM$:(Lscalaz/Applicative;Lscalaz/IList;Lscala/Function1;)Ljava/lang/Object;
       6: areturn

  public <A> java.lang.Object unlessM(boolean, scala.Function0<java.lang.Object>);
    Code:
       0: aload_0
       1: iload_1
       2: aload_2
       3: invokestatic  #205                // InterfaceMethod scalaz/Applicative.unlessM$:(Lscalaz/Applicative;ZLscala/Function0;)Ljava/lang/Object;
       6: areturn

  public <A> java.lang.Object whenM(boolean, scala.Function0<java.lang.Object>);
    Code:
       0: aload_0
       1: iload_1
       2: aload_2
       3: invokestatic  #210                // InterfaceMethod scalaz/Applicative.whenM$:(Lscalaz/Applicative;ZLscala/Function0;)Ljava/lang/Object;
       6: areturn

  public <G$> scalaz.Applicative<?> compose(scalaz.Applicative<G$>);
    Code:
       0: aload_0
       1: aload_1
       2: invokestatic  #217                // InterfaceMethod scalaz/Applicative.compose$:(Lscalaz/Applicative;Lscalaz/Applicative;)Lscalaz/Applicative;
       5: areturn

  public <G$> scalaz.Applicative<?> product(scalaz.Applicative<G$>);
    Code:
       0: aload_0
       1: aload_1
       2: invokestatic  #222                // InterfaceMethod scalaz/Applicative.product$:(Lscalaz/Applicative;Lscalaz/Applicative;)Lscalaz/Applicative;
       5: areturn

  public scalaz.Applicative<?> flip();
    Code:
       0: aload_0
       1: invokestatic  #226                // InterfaceMethod scalaz/Applicative.flip$:(Lscalaz/Applicative;)Lscalaz/Applicative;
       4: areturn

  public <A> java.lang.Object plusA(scala.Function0<java.lang.Object>, scala.Function0<java.lang.Object>, scalaz.Semigroup<A>);
    Code:
       0: aload_0
       1: aload_1
       2: aload_2
       3: aload_3
       4: invokestatic  #236                // InterfaceMethod scalaz/Applicative.plusA$:(Lscalaz/Applicative;Lscala/Function0;Lscala/Function0;Lscalaz/Semigroup;)Ljava/lang/Object;
       7: areturn

  public scalaz.Applicative<?>.ApplicativeLaw applicativeLaw();
    Code:
       0: aload_0
       1: invokestatic  #244                // InterfaceMethod scalaz/Applicative.applicativeLaw$:(Lscalaz/Applicative;)Lscalaz/Applicative$ApplicativeLaw;
       4: areturn

  public final <Z> java.lang.Object xderiving0(scala.Function0<Z>);
    Code:
       0: aload_0
       1: aload_1
       2: invokestatic  #251                // InterfaceMethod scalaz/InvariantApplicative.xderiving0$:(Lscalaz/InvariantApplicative;Lscala/Function0;)Ljava/lang/Object;
       5: areturn

  public final <Z, A1> java.lang.Object xderiving1(scala.Function1<A1, Z>, scala.Function1<Z, A1>, java.lang.Object);
    Code:
       0: aload_0
       1: aload_1
       2: aload_2
       3: aload_3
       4: invokestatic  #258                // InterfaceMethod scalaz/InvariantApplicative.xderiving1$:(Lscalaz/InvariantApplicative;Lscala/Function1;Lscala/Function1;Ljava/lang/Object;)Ljava/lang/Object;
       7: areturn

  public final <Z, A1, A2> java.lang.Object xderiving2(scala.Function2<A1, A2, Z>, scala.Function1<Z, scala.Tuple2<A1, A2>>, java.lang.Object, java.lang.Object);
    Code:
       0: aload_0
       1: aload_1
       2: aload_2
       3: aload_3
       4: aload         4
       6: invokestatic  #265                // InterfaceMethod scalaz/InvariantApplicative.xderiving2$:(Lscalaz/InvariantApplicative;Lscala/Function2;Lscala/Function1;Ljava/lang/Object;Ljava/lang/Object;)Ljava/lang/Object;
       9: areturn

  public final <Z, A1, A2, A3> java.lang.Object xderiving3(scala.Function3<A1, A2, A3, Z>, scala.Function1<Z, scala.Tuple3<A1, A2, A3>>, java.lang.Object, java.lang.Object, java.lang.Object);
    Code:
       0: aload_0
       1: aload_1
       2: aload_2
       3: aload_3
       4: aload         4
       6: aload         5
       8: invokestatic  #272                // InterfaceMethod scalaz/InvariantApplicative.xderiving3$:(Lscalaz/InvariantApplicative;Lscala/Function3;Lscala/Function1;Ljava/lang/Object;Ljava/lang/Object;Ljava/lang/Object;)Ljava/lang/Object;
      11: areturn

  public final <Z, A1, A2, A3, A4> java.lang.Object xderiving4(scala.Function4<A1, A2, A3, A4, Z>, scala.Function1<Z, scala.Tuple4<A1, A2, A3, A4>>, java.lang.Object, java.lang.Object, java.lang.Object, java.lang.Object);
    Code:
       0: aload_0
       1: aload_1
       2: aload_2
       3: aload_3
       4: aload         4
       6: aload         5
       8: aload         6
      10: invokestatic  #279                // InterfaceMethod scalaz/InvariantApplicative.xderiving4$:(Lscalaz/InvariantApplicative;Lscala/Function4;Lscala/Function1;Ljava/lang/Object;Ljava/lang/Object;Ljava/lang/Object;Ljava/lang/Object;)Ljava/lang/Object;
      13: areturn

  public <A, G$, B> java.lang.Object traverse1(G$, scala.Function1<A, java.lang.Object>, scalaz.Traverse1<G$>);
    Code:
       0: aload_0
       1: aload_1
       2: aload_2
       3: aload_3
       4: invokestatic  #286                // InterfaceMethod scalaz/Apply.traverse1$:(Lscalaz/Apply;Ljava/lang/Object;Lscala/Function1;Lscalaz/Traverse1;)Ljava/lang/Object;
       7: areturn

  public <A, G$> java.lang.Object sequence1(G$, scalaz.Traverse1<G$>);
    Code:
       0: aload_0
       1: aload_1
       2: aload_2
       3: invokestatic  #294                // InterfaceMethod scalaz/Apply.sequence1$:(Lscalaz/Apply;Ljava/lang/Object;Lscalaz/Traverse1;)Ljava/lang/Object;
       6: areturn

  public <A, B> java.lang.Object forever(java.lang.Object);
    Code:
       0: aload_0
       1: aload_1
       2: invokestatic  #301                // InterfaceMethod scalaz/Apply.forever$:(Lscalaz/Apply;Ljava/lang/Object;)Ljava/lang/Object;
       5: areturn

  public <S$, A, B> scalaz.Maybe<java.lang.Object> unfoldrOpt(S$, scala.Function1<S$, scalaz.Maybe<scala.Tuple2<java.lang.Object, S$>>>, scalaz.Reducer<A, B>);
    Code:
       0: aload_0
       1: aload_1
       2: aload_2
       3: aload_3
       4: invokestatic  #310                // InterfaceMethod scalaz/Apply.unfoldrOpt$:(Lscalaz/Apply;Ljava/lang/Object;Lscala/Function1;Lscalaz/Reducer;)Lscalaz/Maybe;
       7: areturn

  public <G$> scalaz.Apply<?> compose(scalaz.Apply<G$>);
    Code:
       0: aload_0
       1: aload_1
       2: invokestatic  #316                // InterfaceMethod scalaz/Apply.compose$:(Lscalaz/Apply;Lscalaz/Apply;)Lscalaz/Apply;
       5: areturn

  public <G$> scalaz.Apply<?> product(scalaz.Apply<G$>);
    Code:
       0: aload_0
       1: aload_1
       2: invokestatic  #319                // InterfaceMethod scalaz/Apply.product$:(Lscalaz/Apply;Lscalaz/Apply;)Lscalaz/Apply;
       5: areturn

  public <A, B> scala.Function1<java.lang.Object, java.lang.Object> apF(scala.Function0<java.lang.Object>);
    Code:
       0: aload_0
       1: aload_1
       2: invokestatic  #326                // InterfaceMethod scalaz/Apply.apF$:(Lscalaz/Apply;Lscala/Function0;)Lscala/Function1;
       5: areturn

  public <A, B, C> java.lang.Object ap2(scala.Function0<java.lang.Object>, scala.Function0<java.lang.Object>, java.lang.Object);
    Code:
       0: aload_0
       1: aload_1
       2: aload_2
       3: aload_3
       4: invokestatic  #333                // InterfaceMethod scalaz/Apply.ap2$:(Lscalaz/Apply;Lscala/Function0;Lscala/Function0;Ljava/lang/Object;)Ljava/lang/Object;
       7: areturn

  public <A, B, C, D> java.lang.Object ap3(scala.Function0<java.lang.Object>, scala.Function0<java.lang.Object>, scala.Function0<java.lang.Object>, java.lang.Object);
    Code:
       0: aload_0
       1: aload_1
       2: aload_2
       3: aload_3
       4: aload         4
       6: invokestatic  #341                // InterfaceMethod scalaz/Apply.ap3$:(Lscalaz/Apply;Lscala/Function0;Lscala/Function0;Lscala/Function0;Ljava/lang/Object;)Ljava/lang/Object;
       9: areturn

  public <A, B, C, D, E> java.lang.Object ap4(scala.Function0<java.lang.Object>, scala.Function0<java.lang.Object>, scala.Function0<java.lang.Object>, scala.Function0<java.lang.Object>, java.lang.Object);
    Code:
       0: aload_0
       1: aload_1
       2: aload_2
       3: aload_3
       4: aload         4
       6: aload         5
       8: invokestatic  #349                // InterfaceMethod scalaz/Apply.ap4$:(Lscalaz/Apply;Lscala/Function0;Lscala/Function0;Lscala/Function0;Lscala/Function0;Ljava/lang/Object;)Ljava/lang/Object;
      11: areturn

  public <A, B, C, D, E, R> java.lang.Object ap5(scala.Function0<java.lang.Object>, scala.Function0<java.lang.Object>, scala.Function0<java.lang.Object>, scala.Function0<java.lang.Object>, scala.Function0<java.lang.Object>, java.lang.Object);
    Code:
       0: aload_0
       1: aload_1
       2: aload_2
       3: aload_3
       4: aload         4
       6: aload         5
       8: aload         6
      10: invokestatic  #357                // InterfaceMethod scalaz/Apply.ap5$:(Lscalaz/Apply;Lscala/Function0;Lscala/Function0;Lscala/Function0;Lscala/Function0;Lscala/Function0;Ljava/lang/Object;)Ljava/lang/Object;
      13: areturn

  public <A, B, C, D, E, FF, R> java.lang.Object ap6(scala.Function0<java.lang.Object>, scala.Function0<java.lang.Object>, scala.Function0<java.lang.Object>, scala.Function0<java.lang.Object>, scala.Function0<java.lang.Object>, scala.Function0<java.lang.Object>, java.lang.Object);
    Code:
       0: aload_0
       1: aload_1
       2: aload_2
       3: aload_3
       4: aload         4
       6: aload         5
       8: aload         6
      10: aload         7
      12: invokestatic  #365                // InterfaceMethod scalaz/Apply.ap6$:(Lscalaz/Apply;Lscala/Function0;Lscala/Function0;Lscala/Function0;Lscala/Function0;Lscala/Function0;Lscala/Function0;Ljava/lang/Object;)Ljava/lang/Object;
      15: areturn

  public <A, B, C, D, E, FF, G$, R> java.lang.Object ap7(scala.Function0<java.lang.Object>, scala.Function0<java.lang.Object>, scala.Function0<java.lang.Object>, scala.Function0<java.lang.Object>, scala.Function0<java.lang.Object>, scala.Function0<java.lang.Object>, scala.Function0<java.lang.Object>, java.lang.Object);
    Code:
       0: aload_0
       1: aload_1
       2: aload_2
       3: aload_3
       4: aload         4
       6: aload         5
       8: aload         6
      10: aload         7
      12: aload         8
      14: invokestatic  #373                // InterfaceMethod scalaz/Apply.ap7$:(Lscalaz/Apply;Lscala/Function0;Lscala/Function0;Lscala/Function0;Lscala/Function0;Lscala/Function0;Lscala/Function0;Lscala/Function0;Ljava/lang/Object;)Ljava/lang/Object;
      17: areturn

  public <A, B, C, D, E, FF, G$, H, R> java.lang.Object ap8(scala.Function0<java.lang.Object>, scala.Function0<java.lang.Object>, scala.Function0<java.lang.Object>, scala.Function0<java.lang.Object>, scala.Function0<java.lang.Object>, scala.Function0<java.lang.Object>, scala.Function0<java.lang.Object>, scala.Function0<java.lang.Object>, java.lang.Object);
    Code:
       0: aload_0
       1: aload_1
       2: aload_2
       3: aload_3
       4: aload         4
       6: aload         5
       8: aload         6
      10: aload         7
      12: aload         8
      14: aload         9
      16: invokestatic  #381                // InterfaceMethod scalaz/Apply.ap8$:(Lscalaz/Apply;Lscala/Function0;Lscala/Function0;Lscala/Function0;Lscala/Function0;Lscala/Function0;Lscala/Function0;Lscala/Function0;Lscala/Function0;Ljava/lang/Object;)Ljava/lang/Object;
      19: areturn

  public <A, B, C, D> java.lang.Object apply3(scala.Function0<java.lang.Object>, scala.Function0<java.lang.Object>, scala.Function0<java.lang.Object>, scala.Function3<A, B, C, D>);
    Code:
       0: aload_0
       1: aload_1
       2: aload_2
       3: aload_3
       4: aload         4
       6: invokestatic  #388                // InterfaceMethod scalaz/Apply.apply3$:(Lscalaz/Apply;Lscala/Function0;Lscala/Function0;Lscala/Function0;Lscala/Function3;)Ljava/lang/Object;
       9: areturn

  public <A, B, C, D, E> java.lang.Object apply4(scala.Function0<java.lang.Object>, scala.Function0<java.lang.Object>, scala.Function0<java.lang.Object>, scala.Function0<java.lang.Object>, scala.Function4<A, B, C, D, E>);
    Code:
       0: aload_0
       1: aload_1
       2: aload_2
       3: aload_3
       4: aload         4
       6: aload         5
       8: invokestatic  #395                // InterfaceMethod scalaz/Apply.apply4$:(Lscalaz/Apply;Lscala/Function0;Lscala/Function0;Lscala/Function0;Lscala/Function0;Lscala/Function4;)Ljava/lang/Object;
      11: areturn

  public <A, B, C, D, E, R> java.lang.Object apply5(scala.Function0<java.lang.Object>, scala.Function0<java.lang.Object>, scala.Function0<java.lang.Object>, scala.Function0<java.lang.Object>, scala.Function0<java.lang.Object>, scala.Function5<A, B, C, D, E, R>);
    Code:
       0: aload_0
       1: aload_1
       2: aload_2
       3: aload_3
       4: aload         4
       6: aload         5
       8: aload         6
      10: invokestatic  #402                // InterfaceMethod scalaz/Apply.apply5$:(Lscalaz/Apply;Lscala/Function0;Lscala/Function0;Lscala/Function0;Lscala/Function0;Lscala/Function0;Lscala/Function5;)Ljava/lang/Object;
      13: areturn

  public <A, B, C, D, E, FF, R> java.lang.Object apply6(scala.Function0<java.lang.Object>, scala.Function0<java.lang.Object>, scala.Function0<java.lang.Object>, scala.Function0<java.lang.Object>, scala.Function0<java.lang.Object>, scala.Function0<java.lang.Object>, scala.Function6<A, B, C, D, E, FF, R>);
    Code:
       0: aload_0
       1: aload_1
       2: aload_2
       3: aload_3
       4: aload         4
       6: aload         5
       8: aload         6
      10: aload         7
      12: invokestatic  #410                // InterfaceMethod scalaz/Apply.apply6$:(Lscalaz/Apply;Lscala/Function0;Lscala/Function0;Lscala/Function0;Lscala/Function0;Lscala/Function0;Lscala/Function0;Lscala/Function6;)Ljava/lang/Object;
      15: areturn

  public <A, B, C, D, E, FF, G$, R> java.lang.Object apply7(scala.Function0<java.lang.Object>, scala.Function0<java.lang.Object>, scala.Function0<java.lang.Object>, scala.Function0<java.lang.Object>, scala.Function0<java.lang.Object>, scala.Function0<java.lang.Object>, scala.Function0<java.lang.Object>, scala.Function7<A, B, C, D, E, FF, G$, R>);
    Code:
       0: aload_0
       1: aload_1
       2: aload_2
       3: aload_3
       4: aload         4
       6: aload         5
       8: aload         6
      10: aload         7
      12: aload         8
      14: invokestatic  #418                // InterfaceMethod scalaz/Apply.apply7$:(Lscalaz/Apply;Lscala/Function0;Lscala/Function0;Lscala/Function0;Lscala/Function0;Lscala/Function0;Lscala/Function0;Lscala/Function0;Lscala/Function7;)Ljava/lang/Object;
      17: areturn

  public <A, B, C, D, E, FF, G$, H, R> java.lang.Object apply8(scala.Function0<java.lang.Object>, scala.Function0<java.lang.Object>, scala.Function0<java.lang.Object>, scala.Function0<java.lang.Object>, scala.Function0<java.lang.Object>, scala.Function0<java.lang.Object>, scala.Function0<java.lang.Object>, scala.Function0<java.lang.Object>, scala.Function8<A, B, C, D, E, FF, G$, H, R>);
    Code:
       0: aload_0
       1: aload_1
       2: aload_2
       3: aload_3
       4: aload         4
       6: aload         5
       8: aload         6
      10: aload         7
      12: aload         8
      14: aload         9
      16: invokestatic  #426                // InterfaceMethod scalaz/Apply.apply8$:(Lscalaz/Apply;Lscala/Function0;Lscala/Function0;Lscala/Function0;Lscala/Function0;Lscala/Function0;Lscala/Function0;Lscala/Function0;Lscala/Function0;Lscala/Function8;)Ljava/lang/Object;
      19: areturn

  public <A, B, C, D, E, FF, G$, H, I, R> java.lang.Object apply9(scala.Function0<java.lang.Object>, scala.Function0<java.lang.Object>, scala.Function0<java.lang.Object>, scala.Function0<java.lang.Object>, scala.Function0<java.lang.Object>, scala.Function0<java.lang.Object>, scala.Function0<java.lang.Object>, scala.Function0<java.lang.Object>, scala.Function0<java.lang.Object>, scala.Function9<A, B, C, D, E, FF, G$, H, I, R>);
    Code:
       0: aload_0
       1: aload_1
       2: aload_2
       3: aload_3
       4: aload         4
       6: aload         5
       8: aload         6
      10: aload         7
      12: aload         8
      14: aload         9
      16: aload         10
      18: invokestatic  #435                // InterfaceMethod scalaz/Apply.apply9$:(Lscalaz/Apply;Lscala/Function0;Lscala/Function0;Lscala/Function0;Lscala/Function0;Lscala/Function0;Lscala/Function0;Lscala/Function0;Lscala/Function0;Lscala/Function0;Lscala/Function9;)Ljava/lang/Object;
      21: areturn

  public <A, B, C, D, E, FF, G$, H, I, J, R> java.lang.Object apply10(scala.Function0<java.lang.Object>, scala.Function0<java.lang.Object>, scala.Function0<java.lang.Object>, scala.Function0<java.lang.Object>, scala.Function0<java.lang.Object>, scala.Function0<java.lang.Object>, scala.Function0<java.lang.Object>, scala.Function0<java.lang.Object>, scala.Function0<java.lang.Object>, scala.Function0<java.lang.Object>, scala.Function10<A, B, C, D, E, FF, G$, H, I, J, R>);
    Code:
       0: aload_0
       1: aload_1
       2: aload_2
       3: aload_3
       4: aload         4
       6: aload         5
       8: aload         6
      10: aload         7
      12: aload         8
      14: aload         9
      16: aload         10
      18: aload         11
      20: invokestatic  #444                // InterfaceMethod scalaz/Apply.apply10$:(Lscalaz/Apply;Lscala/Function0;Lscala/Function0;Lscala/Function0;Lscala/Function0;Lscala/Function0;Lscala/Function0;Lscala/Function0;Lscala/Function0;Lscala/Function0;Lscala/Function0;Lscala/Function10;)Ljava/lang/Object;
      23: areturn

  public <A, B, C, D, E, FF, G$, H, I, J, K, R> java.lang.Object apply11(scala.Function0<java.lang.Object>, scala.Function0<java.lang.Object>, scala.Function0<java.lang.Object>, scala.Function0<java.lang.Object>, scala.Function0<java.lang.Object>, scala.Function0<java.lang.Object>, scala.Function0<java.lang.Object>, scala.Function0<java.lang.Object>, scala.Function0<java.lang.Object>, scala.Function0<java.lang.Object>, scala.Function0<java.lang.Object>, scala.Function11<A, B, C, D, E, FF, G$, H, I, J, K, R>);
    Code:
       0: aload_0
       1: aload_1
       2: aload_2
       3: aload_3
       4: aload         4
       6: aload         5
       8: aload         6
      10: aload         7
      12: aload         8
      14: aload         9
      16: aload         10
      18: aload         11
      20: aload         12
      22: invokestatic  #453                // InterfaceMethod scalaz/Apply.apply11$:(Lscalaz/Apply;Lscala/Function0;Lscala/Function0;Lscala/Function0;Lscala/Function0;Lscala/Function0;Lscala/Function0;Lscala/Function0;Lscala/Function0;Lscala/Function0;Lscala/Function0;Lscala/Function0;Lscala/Function11;)Ljava/lang/Object;
      25: areturn

  public <A, B, C, D, E, FF, G$, H, I, J, K, L, R> java.lang.Object apply12(scala.Function0<java.lang.Object>, scala.Function0<java.lang.Object>, scala.Function0<java.lang.Object>, scala.Function0<java.lang.Object>, scala.Function0<java.lang.Object>, scala.Function0<java.lang.Object>, scala.Function0<java.lang.Object>, scala.Function0<java.lang.Object>, scala.Function0<java.lang.Object>, scala.Function0<java.lang.Object>, scala.Function0<java.lang.Object>, scala.Function0<java.lang.Object>, scala.Function12<A, B, C, D, E, FF, G$, H, I, J, K, L, R>);
    Code:
       0: aload_0
       1: aload_1
       2: aload_2
       3: aload_3
       4: aload         4
       6: aload         5
       8: aload         6
      10: aload         7
      12: aload         8
      14: aload         9
      16: aload         10
      18: aload         11
      20: aload         12
      22: aload         13
      24: invokestatic  #462                // InterfaceMethod scalaz/Apply.apply12$:(Lscalaz/Apply;Lscala/Function0;Lscala/Function0;Lscala/Function0;Lscala/Function0;Lscala/Function0;Lscala/Function0;Lscala/Function0;Lscala/Function0;Lscala/Function0;Lscala/Function0;Lscala/Function0;Lscala/Function0;Lscala/Function12;)Ljava/lang/Object;
      27: areturn

  public final <Z, A1> java.lang.Object applying1(scala.Function1<A1, Z>, java.lang.Object);
    Code:
       0: aload_0
       1: aload_1
       2: aload_2
       3: invokestatic  #470                // InterfaceMethod scalaz/Apply.applying1$:(Lscalaz/Apply;Lscala/Function1;Ljava/lang/Object;)Ljava/lang/Object;
       6: areturn

  public final <Z, A1, A2> java.lang.Object applying2(scala.Function2<A1, A2, Z>, java.lang.Object, java.lang.Object);
    Code:
       0: aload_0
       1: aload_1
       2: aload_2
       3: aload_3
       4: invokestatic  #477                // InterfaceMethod scalaz/Apply.applying2$:(Lscalaz/Apply;Lscala/Function2;Ljava/lang/Object;Ljava/lang/Object;)Ljava/lang/Object;
       7: areturn

  public final <Z, A1, A2, A3> java.lang.Object applying3(scala.Function3<A1, A2, A3, Z>, java.lang.Object, java.lang.Object, java.lang.Object);
    Code:
       0: aload_0
       1: aload_1
       2: aload_2
       3: aload_3
       4: aload         4
       6: invokestatic  #484                // InterfaceMethod scalaz/Apply.applying3$:(Lscalaz/Apply;Lscala/Function3;Ljava/lang/Object;Ljava/lang/Object;Ljava/lang/Object;)Ljava/lang/Object;
       9: areturn

  public final <Z, A1, A2, A3, A4> java.lang.Object applying4(scala.Function4<A1, A2, A3, A4, Z>, java.lang.Object, java.lang.Object, java.lang.Object, java.lang.Object);
    Code:
       0: aload_0
       1: aload_1
       2: aload_2
       3: aload_3
       4: aload         4
       6: aload         5
       8: invokestatic  #491                // InterfaceMethod scalaz/Apply.applying4$:(Lscalaz/Apply;Lscala/Function4;Ljava/lang/Object;Ljava/lang/Object;Ljava/lang/Object;Ljava/lang/Object;)Ljava/lang/Object;
      11: areturn

  public <A, B> java.lang.Object tuple2(scala.Function0<java.lang.Object>, scala.Function0<java.lang.Object>);
    Code:
       0: aload_0
       1: aload_1
       2: aload_2
       3: invokestatic  #498                // InterfaceMethod scalaz/Apply.tuple2$:(Lscalaz/Apply;Lscala/Function0;Lscala/Function0;)Ljava/lang/Object;
       6: areturn

  public <A, B, C> java.lang.Object tuple3(scala.Function0<java.lang.Object>, scala.Function0<java.lang.Object>, scala.Function0<java.lang.Object>);
    Code:
       0: aload_0
       1: aload_1
       2: aload_2
       3: aload_3
       4: invokestatic  #505                // InterfaceMethod scalaz/Apply.tuple3$:(Lscalaz/Apply;Lscala/Function0;Lscala/Function0;Lscala/Function0;)Ljava/lang/Object;
       7: areturn

  public <A, B, C, D> java.lang.Object tuple4(scala.Function0<java.lang.Object>, scala.Function0<java.lang.Object>, scala.Function0<java.lang.Object>, scala.Function0<java.lang.Object>);
    Code:
       0: aload_0
       1: aload_1
       2: aload_2
       3: aload_3
       4: aload         4
       6: invokestatic  #512                // InterfaceMethod scalaz/Apply.tuple4$:(Lscalaz/Apply;Lscala/Function0;Lscala/Function0;Lscala/Function0;Lscala/Function0;)Ljava/lang/Object;
       9: areturn

  public <A, B, C, D, E> java.lang.Object tuple5(scala.Function0<java.lang.Object>, scala.Function0<java.lang.Object>, scala.Function0<java.lang.Object>, scala.Function0<java.lang.Object>, scala.Function0<java.lang.Object>);
    Code:
       0: aload_0
       1: aload_1
       2: aload_2
       3: aload_3
       4: aload         4
       6: aload         5
       8: invokestatic  #519                // InterfaceMethod scalaz/Apply.tuple5$:(Lscalaz/Apply;Lscala/Function0;Lscala/Function0;Lscala/Function0;Lscala/Function0;Lscala/Function0;)Ljava/lang/Object;
      11: areturn

  public <A, B, C> scala.Function2<java.lang.Object, java.lang.Object, java.lang.Object> lift2(scala.Function2<A, B, C>);
    Code:
       0: aload_0
       1: aload_1
       2: invokestatic  #526                // InterfaceMethod scalaz/Apply.lift2$:(Lscalaz/Apply;Lscala/Function2;)Lscala/Function2;
       5: areturn

  public <A, B, C, D> scala.Function3<java.lang.Object, java.lang.Object, java.lang.Object, java.lang.Object> lift3(scala.Function3<A, B, C, D>);
    Code:
       0: aload_0
       1: aload_1
       2: invokestatic  #533                // InterfaceMethod scalaz/Apply.lift3$:(Lscalaz/Apply;Lscala/Function3;)Lscala/Function3;
       5: areturn

  public <A, B, C, D, E> scala.Function4<java.lang.Object, java.lang.Object, java.lang.Object, java.lang.Object, java.lang.Object> lift4(scala.Function4<A, B, C, D, E>);
    Code:
       0: aload_0
       1: aload_1
       2: invokestatic  #540                // InterfaceMethod scalaz/Apply.lift4$:(Lscalaz/Apply;Lscala/Function4;)Lscala/Function4;
       5: areturn

  public <A, B, C, D, E, R$> scala.Function5<java.lang.Object, java.lang.Object, java.lang.Object, java.lang.Object, java.lang.Object, java.lang.Object> lift5(scala.Function5<A, B, C, D, E, R$>);
    Code:
       0: aload_0
       1: aload_1
       2: invokestatic  #547                // InterfaceMethod scalaz/Apply.lift5$:(Lscalaz/Apply;Lscala/Function5;)Lscala/Function5;
       5: areturn

  public <A, B, C, D, E, FF, R$> scala.Function6<java.lang.Object, java.lang.Object, java.lang.Object, java.lang.Object, java.lang.Object, java.lang.Object, java.lang.Object> lift6(scala.Function6<A, B, C, D, E, FF, R$>);
    Code:
       0: aload_0
       1: aload_1
       2: invokestatic  #554                // InterfaceMethod scalaz/Apply.lift6$:(Lscalaz/Apply;Lscala/Function6;)Lscala/Function6;
       5: areturn

  public <A, B, C, D, E, FF, G$, R$> scala.Function7<java.lang.Object, java.lang.Object, java.lang.Object, java.lang.Object, java.lang.Object, java.lang.Object, java.lang.Object, java.lang.Object> lift7(scala.Function7<A, B, C, D, E, FF, G$, R$>);
    Code:
       0: aload_0
       1: aload_1
       2: invokestatic  #561                // InterfaceMethod scalaz/Apply.lift7$:(Lscalaz/Apply;Lscala/Function7;)Lscala/Function7;
       5: areturn

  public <A, B, C, D, E, FF, G$, H, R$> scala.Function8<java.lang.Object, java.lang.Object, java.lang.Object, java.lang.Object, java.lang.Object, java.lang.Object, java.lang.Object, java.lang.Object, java.lang.Object> lift8(scala.Function8<A, B, C, D, E, FF, G$, H, R$>);
    Code:
       0: aload_0
       1: aload_1
       2: invokestatic  #568                // InterfaceMethod scalaz/Apply.lift8$:(Lscalaz/Apply;Lscala/Function8;)Lscala/Function8;
       5: areturn

  public <A, B, C, D, E, FF, G$, H, I, R$> scala.Function9<java.lang.Object, java.lang.Object, java.lang.Object, java.lang.Object, java.lang.Object, java.lang.Object, java.lang.Object, java.lang.Object, java.lang.Object, java.lang.Object> lift9(scala.Function9<A, B, C, D, E, FF, G$, H, I, R$>);
    Code:
       0: aload_0
       1: aload_1
       2: invokestatic  #575                // InterfaceMethod scalaz/Apply.lift9$:(Lscalaz/Apply;Lscala/Function9;)Lscala/Function9;
       5: areturn

  public <A, B, C, D, E, FF, G$, H, I, J, R$> scala.Function10<java.lang.Object, java.lang.Object, java.lang.Object, java.lang.Object, java.lang.Object, java.lang.Object, java.lang.Object, java.lang.Object, java.lang.Object, java.lang.Object, java.lang.Object> lift10(scala.Function10<A, B, C, D, E, FF, G$, H, I, J, R$>);
    Code:
       0: aload_0
       1: aload_1
       2: invokestatic  #582                // InterfaceMethod scalaz/Apply.lift10$:(Lscalaz/Apply;Lscala/Function10;)Lscala/Function10;
       5: areturn

  public <A, B, C, D, E, FF, G$, H, I, J, K, R$> scala.Function11<java.lang.Object, java.lang.Object, java.lang.Object, java.lang.Object, java.lang.Object, java.lang.Object, java.lang.Object, java.lang.Object, java.lang.Object, java.lang.Object, java.lang.Object, java.lang.Object> lift11(scala.Function11<A, B, C, D, E, FF, G$, H, I, J, K, R$>);
    Code:
       0: aload_0
       1: aload_1
       2: invokestatic  #589                // InterfaceMethod scalaz/Apply.lift11$:(Lscalaz/Apply;Lscala/Function11;)Lscala/Function11;
       5: areturn

  public <A, B, C, D, E, FF, G$, H, I, J, K, L, R$> scala.Function12<java.lang.Object, java.lang.Object, java.lang.Object, java.lang.Object, java.lang.Object, java.lang.Object, java.lang.Object, java.lang.Object, java.lang.Object, java.lang.Object, java.lang.Object, java.lang.Object, java.lang.Object> lift12(scala.Function12<A, B, C, D, E, FF, G$, H, I, J, K, L, R$>);
    Code:
       0: aload_0
       1: aload_1
       2: invokestatic  #596                // InterfaceMethod scalaz/Apply.lift12$:(Lscalaz/Apply;Lscala/Function12;)Lscala/Function12;
       5: areturn

  public <A, B> java.lang.Object discardLeft(scala.Function0<java.lang.Object>, scala.Function0<java.lang.Object>);
    Code:
       0: aload_0
       1: aload_1
       2: aload_2
       3: invokestatic  #600                // InterfaceMethod scalaz/Apply.discardLeft$:(Lscalaz/Apply;Lscala/Function0;Lscala/Function0;)Ljava/lang/Object;
       6: areturn

  public <A, B> java.lang.Object discardRight(scala.Function0<java.lang.Object>, scala.Function0<java.lang.Object>);
    Code:
       0: aload_0
       1: aload_1
       2: aload_2
       3: invokestatic  #604                // InterfaceMethod scalaz/Apply.discardRight$:(Lscalaz/Apply;Lscala/Function0;Lscala/Function0;)Ljava/lang/Object;
       6: areturn

  public scalaz.Applicative<?> applyApplicative();
    Code:
       0: aload_0
       1: invokestatic  #609                // InterfaceMethod scalaz/Apply.applyApplicative$:(Lscalaz/Apply;)Lscalaz/Applicative;
       4: areturn

  public <A, B> scalaz.Reducer<java.lang.Object, java.lang.Object> liftReducer(scalaz.Reducer<A, B>);
    Code:
       0: aload_0
       1: aload_1
       2: invokestatic  #617                // InterfaceMethod scalaz/Apply.liftReducer$:(Lscalaz/Apply;Lscalaz/Reducer;)Lscalaz/Reducer;
       5: areturn

  public scalaz.Apply<?>.ApplyLaw applyLaw();
    Code:
       0: aload_0
       1: invokestatic  #624                // InterfaceMethod scalaz/Apply.applyLaw$:(Lscalaz/Apply;)Lscalaz/Apply$ApplyLaw;
       4: areturn

  public <A, B> java.lang.Object xmap(java.lang.Object, scala.Function1<A, B>, scala.Function1<B, A>);
    Code:
       0: aload_0
       1: aload_1
       2: aload_2
       3: aload_3
       4: invokestatic  #631                // InterfaceMethod scalaz/Functor.xmap$:(Lscalaz/Functor;Ljava/lang/Object;Lscala/Function1;Lscala/Function1;)Ljava/lang/Object;
       7: areturn

  public <A, B> java.lang.Object apply(java.lang.Object, scala.Function1<A, B>);
    Code:
       0: aload_0
       1: aload_1
       2: aload_2
       3: invokestatic  #636                // InterfaceMethod scalaz/Functor.apply$:(Lscalaz/Functor;Ljava/lang/Object;Lscala/Function1;)Ljava/lang/Object;
       6: areturn

  public <A, B> scala.Function1<java.lang.Object, java.lang.Object> lift(scala.Function1<A, B>);
    Code:
       0: aload_0
       1: aload_1
       2: invokestatic  #643                // InterfaceMethod scalaz/Functor.lift$:(Lscalaz/Functor;Lscala/Function1;)Lscala/Function1;
       5: areturn

  public <A, B> java.lang.Object strengthL(A, java.lang.Object);
    Code:
       0: aload_0
       1: aload_1
       2: aload_2
       3: invokestatic  #650                // InterfaceMethod scalaz/Functor.strengthL$:(Lscalaz/Functor;Ljava/lang/Object;Ljava/lang/Object;)Ljava/lang/Object;
       6: areturn

  public <A, B> java.lang.Object strengthR(java.lang.Object, B);
    Code:
       0: aload_0
       1: aload_1
       2: aload_2
       3: invokestatic  #656                // InterfaceMethod scalaz/Functor.strengthR$:(Lscalaz/Functor;Ljava/lang/Object;Ljava/lang/Object;)Ljava/lang/Object;
       6: areturn

  public <A, B> java.lang.Object mapply(A, java.lang.Object);
    Code:
       0: aload_0
       1: aload_1
       2: aload_2
       3: invokestatic  #660                // InterfaceMethod scalaz/Functor.mapply$:(Lscalaz/Functor;Ljava/lang/Object;Ljava/lang/Object;)Ljava/lang/Object;
       6: areturn

  public <A> java.lang.Object fpair(java.lang.Object);
    Code:
       0: aload_0
       1: aload_1
       2: invokestatic  #666                // InterfaceMethod scalaz/Functor.fpair$:(Lscalaz/Functor;Ljava/lang/Object;)Ljava/lang/Object;
       5: areturn

  public <A, B> java.lang.Object fproduct(java.lang.Object, scala.Function1<A, B>);
    Code:
       0: aload_0
       1: aload_1
       2: aload_2
       3: invokestatic  #670                // InterfaceMethod scalaz/Functor.fproduct$:(Lscalaz/Functor;Ljava/lang/Object;Lscala/Function1;)Ljava/lang/Object;
       6: areturn

  public <A> java.lang.Object void(java.lang.Object);
    Code:
       0: aload_0
       1: aload_1
       2: invokestatic  #674                // InterfaceMethod scalaz/Functor.void$:(Lscalaz/Functor;Ljava/lang/Object;)Ljava/lang/Object;
       5: areturn

  public <A, B> java.lang.Object counzip(scalaz.$bslash$div<java.lang.Object, java.lang.Object>);
    Code:
       0: aload_0
       1: aload_1
       2: invokestatic  #681                // InterfaceMethod scalaz/Functor.counzip$:(Lscalaz/Functor;Lscalaz/$bslash$div;)Ljava/lang/Object;
       5: areturn

  public <G$> scalaz.Functor<?> compose(scalaz.Functor<G$>);
    Code:
       0: aload_0
       1: aload_1
       2: invokestatic  #687                // InterfaceMethod scalaz/Functor.compose$:(Lscalaz/Functor;Lscalaz/Functor;)Lscalaz/Functor;
       5: areturn

  public <G$> scalaz.Contravariant<?> icompose(scalaz.Contravariant<G$>);
    Code:
       0: aload_0
       1: aload_1
       2: invokestatic  #695                // InterfaceMethod scalaz/Functor.icompose$:(Lscalaz/Functor;Lscalaz/Contravariant;)Lscalaz/Contravariant;
       5: areturn

  public <G$> scalaz.Bifunctor<?> bicompose(scalaz.Bifunctor<G$>);
    Code:
       0: aload_0
       1: aload_1
       2: invokestatic  #703                // InterfaceMethod scalaz/Functor.bicompose$:(Lscalaz/Functor;Lscalaz/Bifunctor;)Lscalaz/Bifunctor;
       5: areturn

  public <G$> scalaz.Functor<?> product(scalaz.Functor<G$>);
    Code:
       0: aload_0
       1: aload_1
       2: invokestatic  #706                // InterfaceMethod scalaz/Functor.product$:(Lscalaz/Functor;Lscalaz/Functor;)Lscalaz/Functor;
       5: areturn

  public <A, B> java.lang.Object widen(java.lang.Object, scalaz.Liskov<A, B>);
    Code:
       0: aload_0
       1: aload_1
       2: aload_2
       3: invokestatic  #714                // InterfaceMethod scalaz/Functor.widen$:(Lscalaz/Functor;Ljava/lang/Object;Lscalaz/Liskov;)Ljava/lang/Object;
       6: areturn

  public scalaz.Functor<?>.FunctorLaw functorLaw();
    Code:
       0: aload_0
       1: invokestatic  #722                // InterfaceMethod scalaz/Functor.functorLaw$:(Lscalaz/Functor;)Lscalaz/Functor$FunctorLaw;
       4: areturn

  public <A, B> java.lang.Object xmapb(java.lang.Object, scalaz.BijectionT<?, ?, A, B>);
    Code:
       0: aload_0
       1: aload_1
       2: aload_2
       3: invokestatic  #730                // InterfaceMethod scalaz/InvariantFunctor.xmapb$:(Lscalaz/InvariantFunctor;Ljava/lang/Object;Lscalaz/BijectionT;)Ljava/lang/Object;
       6: areturn

  public <A, B> java.lang.Object xmapi(java.lang.Object, scalaz.Isomorphisms$Iso<scala.Function1, A, B>);
    Code:
       0: aload_0
       1: aload_1
       2: aload_2
       3: invokestatic  #739                // InterfaceMethod scalaz/InvariantFunctor.xmapi$:(Lscalaz/InvariantFunctor;Ljava/lang/Object;Lscalaz/Isomorphisms$Iso;)Ljava/lang/Object;
       6: areturn

  public scalaz.InvariantFunctor<?>.InvariantFunctorLaw invariantFunctorLaw();
    Code:
       0: aload_0
       1: invokestatic  #747                // InterfaceMethod scalaz/InvariantFunctor.invariantFunctorLaw$:(Lscalaz/InvariantFunctor;)Lscalaz/InvariantFunctor$InvariantFunctorLaw;
       4: areturn

  public scalaz.syntax.ApplicativeSyntax<?> applicativeSyntax();
    Code:
       0: aload_0
       1: getfield      #751                // Field applicativeSyntax:Lscalaz/syntax/ApplicativeSyntax;
       4: areturn

  public void scalaz$Applicative$_setter_$applicativeSyntax_$eq(scalaz.syntax.ApplicativeSyntax<?>);
    Code:
       0: aload_0
       1: aload_1
       2: putfield      #751                // Field applicativeSyntax:Lscalaz/syntax/ApplicativeSyntax;
       5: return

  public scalaz.syntax.InvariantApplicativeSyntax<?> invariantApplicativeSyntax();
    Code:
       0: aload_0
       1: getfield      #759                // Field invariantApplicativeSyntax:Lscalaz/syntax/InvariantApplicativeSyntax;
       4: areturn

  public void scalaz$InvariantApplicative$_setter_$invariantApplicativeSyntax_$eq(scalaz.syntax.InvariantApplicativeSyntax<?>);
    Code:
       0: aload_0
       1: aload_1
       2: putfield      #759                // Field invariantApplicativeSyntax:Lscalaz/syntax/InvariantApplicativeSyntax;
       5: return

  public scalaz.syntax.ApplySyntax<?> applySyntax();
    Code:
       0: aload_0
       1: getfield      #766                // Field applySyntax:Lscalaz/syntax/ApplySyntax;
       4: areturn

  public void scalaz$Apply$_setter_$applySyntax_$eq(scalaz.syntax.ApplySyntax<?>);
    Code:
       0: aload_0
       1: aload_1
       2: putfield      #766                // Field applySyntax:Lscalaz/syntax/ApplySyntax;
       5: return

  public scalaz.syntax.FunctorSyntax<?> functorSyntax();
    Code:
       0: aload_0
       1: getfield      #773                // Field functorSyntax:Lscalaz/syntax/FunctorSyntax;
       4: areturn

  public void scalaz$Functor$_setter_$functorSyntax_$eq(scalaz.syntax.FunctorSyntax<?>);
    Code:
       0: aload_0
       1: aload_1
       2: putfield      #773                // Field functorSyntax:Lscalaz/syntax/FunctorSyntax;
       5: return

  public scalaz.syntax.InvariantFunctorSyntax<?> invariantFunctorSyntax();
    Code:
       0: aload_0
       1: getfield      #780                // Field invariantFunctorSyntax:Lscalaz/syntax/InvariantFunctorSyntax;
       4: areturn

  public void scalaz$InvariantFunctor$_setter_$invariantFunctorSyntax_$eq(scalaz.syntax.InvariantFunctorSyntax<?>);
    Code:
       0: aload_0
       1: aload_1
       2: putfield      #780                // Field invariantFunctorSyntax:Lscalaz/syntax/InvariantFunctorSyntax;
       5: return

  public <A> java.lang.Object point(scala.Function0<A>);
    Code:
       0: getstatic     #790                // Field scalaz/Tags$.MODULE$:Lscalaz/Tags$;
       3: invokevirtual #794                // Method scalaz/Tags$.Zip:()Lscalaz/Tag$TagOf;
       6: getstatic     #799                // Field scala/package$.MODULE$:Lscala/package$;
       9: invokevirtual #803                // Method scala/package$.Stream:()Lscala/collection/immutable/Stream$;
      12: aload_1
      13: invokevirtual #809                // Method scala/collection/immutable/Stream$.continually:(Lscala/Function0;)Lscala/collection/immutable/Stream;
      16: astore_2
      17: ifnonnull     22
      20: aconst_null
      21: athrow
      22: getstatic     #814                // Field scalaz/Tag$.MODULE$:Lscalaz/Tag$;
      25: invokevirtual #818                // Method scalaz/Tag$.k:()Lscalaz/TagKind;
      28: aload_2
      29: invokevirtual #822                // Method scalaz/TagKind.apply:(Ljava/lang/Object;)Ljava/lang/Object;
      32: areturn

  public <A, B> java.lang.Object ap(scala.Function0<java.lang.Object>, scala.Function0<java.lang.Object>);
    Code:
       0: getstatic     #790                // Field scalaz/Tags$.MODULE$:Lscalaz/Tags$;
       3: invokevirtual #794                // Method scalaz/Tags$.Zip:()Lscalaz/Tag$TagOf;
       6: getstatic     #814                // Field scalaz/Tag$.MODULE$:Lscalaz/Tag$;
       9: aload_2
      10: invokeinterface #829,  1          // InterfaceMethod scala/Function0.apply:()Ljava/lang/Object;
      15: astore_3
      16: invokevirtual #818                // Method scalaz/Tag$.k:()Lscalaz/TagKind;
      19: aload_3
      20: invokevirtual #832                // Method scalaz/TagKind.unwrap:(Ljava/lang/Object;)Ljava/lang/Object;
      23: aconst_null
      24: astore_3
      25: checkcast     #834                // class scala/collection/SeqOps
      28: invokeinterface #838,  1          // InterfaceMethod scala/collection/SeqOps.isEmpty:()Z
      33: ifne          69
      36: getstatic     #814                // Field scalaz/Tag$.MODULE$:Lscalaz/Tag$;
      39: aload_1
      40: invokeinterface #829,  1          // InterfaceMethod scala/Function0.apply:()Ljava/lang/Object;
      45: astore        4
      47: invokevirtual #818                // Method scalaz/Tag$.k:()Lscalaz/TagKind;
      50: aload         4
      52: invokevirtual #832                // Method scalaz/TagKind.unwrap:(Ljava/lang/Object;)Ljava/lang/Object;
      55: aconst_null
      56: astore        4
      58: checkcast     #834                // class scala/collection/SeqOps
      61: invokeinterface #838,  1          // InterfaceMethod scala/collection/SeqOps.isEmpty:()Z
      66: ifeq          81
      69: getstatic     #799                // Field scala/package$.MODULE$:Lscala/package$;
      72: invokevirtual #803                // Method scala/package$.Stream:()Lscala/collection/immutable/Stream$;
      75: invokevirtual #842                // Method scala/collection/immutable/Stream$.empty:()Lscala/collection/immutable/Stream;
      78: goto          163
      81: getstatic     #845                // Field scala/collection/immutable/Stream$cons$.MODULE$:Lscala/collection/immutable/Stream$cons$;
      84: getstatic     #814                // Field scalaz/Tag$.MODULE$:Lscalaz/Tag$;
      87: aload_2
      88: invokeinterface #829,  1          // InterfaceMethod scala/Function0.apply:()Ljava/lang/Object;
      93: astore        5
      95: invokevirtual #818                // Method scalaz/Tag$.k:()Lscalaz/TagKind;
      98: aload         5
     100: invokevirtual #832                // Method scalaz/TagKind.unwrap:(Ljava/lang/Object;)Ljava/lang/Object;
     103: aconst_null
     104: astore        5
     106: checkcast     #847                // class scala/collection/IterableOps
     109: invokeinterface #850,  1          // InterfaceMethod scala/collection/IterableOps.head:()Ljava/lang/Object;
     114: checkcast     #852                // class scala/Function1
     117: getstatic     #814                // Field scalaz/Tag$.MODULE$:Lscalaz/Tag$;
     120: aload_1
     121: invokeinterface #829,  1          // InterfaceMethod scala/Function0.apply:()Ljava/lang/Object;
     126: astore        6
     128: invokevirtual #818                // Method scalaz/Tag$.k:()Lscalaz/TagKind;
     131: aload         6
     133: invokevirtual #832                // Method scalaz/TagKind.unwrap:(Ljava/lang/Object;)Ljava/lang/Object;
     136: aconst_null
     137: astore        6
     139: checkcast     #847                // class scala/collection/IterableOps
     142: invokeinterface #850,  1          // InterfaceMethod scala/collection/IterableOps.head:()Ljava/lang/Object;
     147: invokeinterface #853,  2          // InterfaceMethod scala/Function1.apply:(Ljava/lang/Object;)Ljava/lang/Object;
     152: aload_0
     153: aload_1
     154: aload_2
     155: invokedynamic #872,  0            // InvokeDynamic #0:apply:(Lscalaz/std/StreamInstances$$anon$2;Lscala/Function0;Lscala/Function0;)Lscala/Function0;
     160: invokevirtual #875                // Method scala/collection/immutable/Stream$cons$.apply:(Ljava/lang/Object;Lscala/Function0;)Lscala/collection/immutable/Stream;
     163: astore        7
     165: ifnonnull     170
     168: aconst_null
     169: athrow
     170: getstatic     #814                // Field scalaz/Tag$.MODULE$:Lscalaz/Tag$;
     173: invokevirtual #818                // Method scalaz/Tag$.k:()Lscalaz/TagKind;
     176: aload         7
     178: invokevirtual #822                // Method scalaz/TagKind.apply:(Ljava/lang/Object;)Ljava/lang/Object;
     181: areturn

  public scalaz.Apply flip();
    Code:
       0: aload_0
       1: invokevirtual #879                // Method flip:()Lscalaz/Applicative;
       4: areturn

  public static final java.lang.Object $anonfun$ap$2(scala.Function0);
    Code:
       0: getstatic     #790                // Field scalaz/Tags$.MODULE$:Lscalaz/Tags$;
       3: invokevirtual #794                // Method scalaz/Tags$.Zip:()Lscalaz/Tag$TagOf;
       6: getstatic     #814                // Field scalaz/Tag$.MODULE$:Lscalaz/Tag$;
       9: aload_0
      10: invokeinterface #829,  1          // InterfaceMethod scala/Function0.apply:()Ljava/lang/Object;
      15: astore_1
      16: invokevirtual #818                // Method scalaz/Tag$.k:()Lscalaz/TagKind;
      19: aload_1
      20: invokevirtual #832                // Method scalaz/TagKind.unwrap:(Ljava/lang/Object;)Ljava/lang/Object;
      23: aconst_null
      24: astore_1
      25: checkcast     #847                // class scala/collection/IterableOps
      28: invokeinterface #884,  1          // InterfaceMethod scala/collection/IterableOps.tail:()Ljava/lang/Object;
      33: astore_2
      34: ifnonnull     39
      37: aconst_null
      38: athrow
      39: getstatic     #814                // Field scalaz/Tag$.MODULE$:Lscalaz/Tag$;
      42: invokevirtual #818                // Method scalaz/Tag$.k:()Lscalaz/TagKind;
      45: aload_2
      46: invokevirtual #822                // Method scalaz/TagKind.apply:(Ljava/lang/Object;)Ljava/lang/Object;
      49: areturn

  public static final java.lang.Object $anonfun$ap$3(scala.Function0);
    Code:
       0: getstatic     #790                // Field scalaz/Tags$.MODULE$:Lscalaz/Tags$;
       3: invokevirtual #794                // Method scalaz/Tags$.Zip:()Lscalaz/Tag$TagOf;
       6: getstatic     #814                // Field scalaz/Tag$.MODULE$:Lscalaz/Tag$;
       9: aload_0
      10: invokeinterface #829,  1          // InterfaceMethod scala/Function0.apply:()Ljava/lang/Object;
      15: astore_1
      16: invokevirtual #818                // Method scalaz/Tag$.k:()Lscalaz/TagKind;
      19: aload_1
      20: invokevirtual #832                // Method scalaz/TagKind.unwrap:(Ljava/lang/Object;)Ljava/lang/Object;
      23: aconst_null
      24: astore_1
      25: checkcast     #847                // class scala/collection/IterableOps
      28: invokeinterface #884,  1          // InterfaceMethod scala/collection/IterableOps.tail:()Ljava/lang/Object;
      33: astore_2
      34: ifnonnull     39
      37: aconst_null
      38: athrow
      39: getstatic     #814                // Field scalaz/Tag$.MODULE$:Lscalaz/Tag$;
      42: invokevirtual #818                // Method scalaz/Tag$.k:()Lscalaz/TagKind;
      45: aload_2
      46: invokevirtual #822                // Method scalaz/TagKind.apply:(Ljava/lang/Object;)Ljava/lang/Object;
      49: areturn

  public static final scala.collection.immutable.Stream $anonfun$ap$1(scalaz.std.StreamInstances$$anon$2, scala.Function0, scala.Function0);
    Code:
       0: getstatic     #814                // Field scalaz/Tag$.MODULE$:Lscalaz/Tag$;
       3: aload_1
       4: invokedynamic #893,  0            // InvokeDynamic #1:apply:(Lscala/Function0;)Lscala/Function0;
       9: aload_2
      10: invokedynamic #897,  0            // InvokeDynamic #2:apply:(Lscala/Function0;)Lscala/Function0;
      15: astore        5
      17: astore        4
      19: getstatic     #790                // Field scalaz/Tags$.MODULE$:Lscalaz/Tags$;
      22: invokevirtual #794                // Method scalaz/Tags$.Zip:()Lscalaz/Tag$TagOf;
      25: getstatic     #814                // Field scalaz/Tag$.MODULE$:Lscalaz/Tag$;
      28: getstatic     #790                // Field scalaz/Tags$.MODULE$:Lscalaz/Tags$;
      31: invokevirtual #794                // Method scalaz/Tags$.Zip:()Lscalaz/Tag$TagOf;
      34: getstatic     #814                // Field scalaz/Tag$.MODULE$:Lscalaz/Tag$;
      37: aload_2
      38: invokeinterface #829,  1          // InterfaceMethod scala/Function0.apply:()Ljava/lang/Object;
      43: astore        14
      45: invokevirtual #818                // Method scalaz/Tag$.k:()Lscalaz/TagKind;
      48: aload         14
      50: invokevirtual #832                // Method scalaz/TagKind.unwrap:(Ljava/lang/Object;)Ljava/lang/Object;
      53: aconst_null
      54: astore        14
      56: checkcast     #847                // class scala/collection/IterableOps
      59: invokeinterface #884,  1          // InterfaceMethod scala/collection/IterableOps.tail:()Ljava/lang/Object;
      64: astore        15
      66: ifnonnull     71
      69: aconst_null
      70: athrow
      71: getstatic     #814                // Field scalaz/Tag$.MODULE$:Lscalaz/Tag$;
      74: invokevirtual #818                // Method scalaz/Tag$.k:()Lscalaz/TagKind;
      77: aload         15
      79: invokevirtual #822                // Method scalaz/TagKind.apply:(Ljava/lang/Object;)Ljava/lang/Object;
      82: aconst_null
      83: astore        15
      85: astore        6
      87: invokevirtual #818                // Method scalaz/Tag$.k:()Lscalaz/TagKind;
      90: aload         6
      92: invokevirtual #832                // Method scalaz/TagKind.unwrap:(Ljava/lang/Object;)Ljava/lang/Object;
      95: aconst_null
      96: astore        6
      98: checkcast     #834                // class scala/collection/SeqOps
     101: invokeinterface #838,  1          // InterfaceMethod scala/collection/SeqOps.isEmpty:()Z
     106: ifne          200
     109: getstatic     #814                // Field scalaz/Tag$.MODULE$:Lscalaz/Tag$;
     112: getstatic     #790                // Field scalaz/Tags$.MODULE$:Lscalaz/Tags$;
     115: invokevirtual #794                // Method scalaz/Tags$.Zip:()Lscalaz/Tag$TagOf;
     118: getstatic     #814                // Field scalaz/Tag$.MODULE$:Lscalaz/Tag$;
     121: aload_1
     122: invokeinterface #829,  1          // InterfaceMethod scala/Function0.apply:()Ljava/lang/Object;
     127: astore        16
     129: invokevirtual #818                // Method scalaz/Tag$.k:()Lscalaz/TagKind;
     132: aload         16
     134: invokevirtual #832                // Method scalaz/TagKind.unwrap:(Ljava/lang/Object;)Ljava/lang/Object;
     137: aconst_null
     138: astore        16
     140: checkcast     #847                // class scala/collection/IterableOps
     143: invokeinterface #884,  1          // InterfaceMethod scala/collection/IterableOps.tail:()Ljava/lang/Object;
     148: astore        17
     150: ifnonnull     155
     153: aconst_null
     154: athrow
     155: getstatic     #814                // Field scalaz/Tag$.MODULE$:Lscalaz/Tag$;
     158: invokevirtual #818                // Method scalaz/Tag$.k:()Lscalaz/TagKind;
     161: aload         17
     163: invokevirtual #822                // Method scalaz/TagKind.apply:(Ljava/lang/Object;)Ljava/lang/Object;
     166: aconst_null
     167: astore        17
     169: astore        8
     171: astore        7
     173: aload         7
     175: invokevirtual #818                // Method scalaz/Tag$.k:()Lscalaz/TagKind;
     178: aload         8
     180: invokevirtual #832                // Method scalaz/TagKind.unwrap:(Ljava/lang/Object;)Ljava/lang/Object;
     183: aconst_null
     184: astore        7
     186: aconst_null
     187: astore        8
     189: checkcast     #834                // class scala/collection/SeqOps
     192: invokeinterface #838,  1          // InterfaceMethod scala/collection/SeqOps.isEmpty:()Z
     197: ifeq          212
     200: getstatic     #799                // Field scala/package$.MODULE$:Lscala/package$;
     203: invokevirtual #803                // Method scala/package$.Stream:()Lscala/collection/immutable/Stream$;
     206: invokevirtual #842                // Method scala/collection/immutable/Stream$.empty:()Lscala/collection/immutable/Stream;
     209: goto          412
     212: getstatic     #845                // Field scala/collection/immutable/Stream$cons$.MODULE$:Lscala/collection/immutable/Stream$cons$;
     215: getstatic     #814                // Field scalaz/Tag$.MODULE$:Lscalaz/Tag$;
     218: getstatic     #790                // Field scalaz/Tags$.MODULE$:Lscalaz/Tags$;
     221: invokevirtual #794                // Method scalaz/Tags$.Zip:()Lscalaz/Tag$TagOf;
     224: getstatic     #814                // Field scalaz/Tag$.MODULE$:Lscalaz/Tag$;
     227: aload_2
     228: invokeinterface #829,  1          // InterfaceMethod scala/Function0.apply:()Ljava/lang/Object;
     233: astore        18
     235: invokevirtual #818                // Method scalaz/Tag$.k:()Lscalaz/TagKind;
     238: aload         18
     240: invokevirtual #832                // Method scalaz/TagKind.unwrap:(Ljava/lang/Object;)Ljava/lang/Object;
     243: aconst_null
     244: astore        18
     246: checkcast     #847                // class scala/collection/IterableOps
     249: invokeinterface #884,  1          // InterfaceMethod scala/collection/IterableOps.tail:()Ljava/lang/Object;
     254: astore        19
     256: ifnonnull     261
     259: aconst_null
     260: athrow
     261: getstatic     #814                // Field scalaz/Tag$.MODULE$:Lscalaz/Tag$;
     264: invokevirtual #818                // Method scalaz/Tag$.k:()Lscalaz/TagKind;
     267: aload         19
     269: invokevirtual #822                // Method scalaz/TagKind.apply:(Ljava/lang/Object;)Ljava/lang/Object;
     272: aconst_null
     273: astore        19
     275: astore        10
     277: astore        9
     279: aload         9
     281: invokevirtual #818                // Method scalaz/Tag$.k:()Lscalaz/TagKind;
     284: aload         10
     286: invokevirtual #832                // Method scalaz/TagKind.unwrap:(Ljava/lang/Object;)Ljava/lang/Object;
     289: aconst_null
     290: astore        9
     292: aconst_null
     293: astore        10
     295: checkcast     #847                // class scala/collection/IterableOps
     298: invokeinterface #850,  1          // InterfaceMethod scala/collection/IterableOps.head:()Ljava/lang/Object;
     303: checkcast     #852                // class scala/Function1
     306: getstatic     #814                // Field scalaz/Tag$.MODULE$:Lscalaz/Tag$;
     309: getstatic     #790                // Field scalaz/Tags$.MODULE$:Lscalaz/Tags$;
     312: invokevirtual #794                // Method scalaz/Tags$.Zip:()Lscalaz/Tag$TagOf;
     315: getstatic     #814                // Field scalaz/Tag$.MODULE$:Lscalaz/Tag$;
     318: aload_1
     319: invokeinterface #829,  1          // InterfaceMethod scala/Function0.apply:()Ljava/lang/Object;
     324: astore        20
     326: invokevirtual #818                // Method scalaz/Tag$.k:()Lscalaz/TagKind;
     329: aload         20
     331: invokevirtual #832                // Method scalaz/TagKind.unwrap:(Ljava/lang/Object;)Ljava/lang/Object;
     334: aconst_null
     335: astore        20
     337: checkcast     #847                // class scala/collection/IterableOps
     340: invokeinterface #884,  1          // InterfaceMethod scala/collection/IterableOps.tail:()Ljava/lang/Object;
     345: astore        21
     347: ifnonnull     352
     350: aconst_null
     351: athrow
     352: getstatic     #814                // Field scalaz/Tag$.MODULE$:Lscalaz/Tag$;
     355: invokevirtual #818                // Method scalaz/Tag$.k:()Lscalaz/TagKind;
     358: aload         21
     360: invokevirtual #822                // Method scalaz/TagKind.apply:(Ljava/lang/Object;)Ljava/lang/Object;
     363: aconst_null
     364: astore        21
     366: astore        12
     368: astore        11
     370: aload         11
     372: invokevirtual #818                // Method scalaz/Tag$.k:()Lscalaz/TagKind;
     375: aload         12
     377: invokevirtual #832                // Method scalaz/TagKind.unwrap:(Ljava/lang/Object;)Ljava/lang/Object;
     380: aconst_null
     381: astore        11
     383: aconst_null
     384: astore        12
     386: checkcast     #847                // class scala/collection/IterableOps
     389: invokeinterface #850,  1          // InterfaceMethod scala/collection/IterableOps.head:()Ljava/lang/Object;
     394: invokeinterface #853,  2          // InterfaceMethod scala/Function1.apply:(Ljava/lang/Object;)Ljava/lang/Object;
     399: aload_0
     400: aload         4
     402: aload         5
     404: invokedynamic #872,  0            // InvokeDynamic #0:apply:(Lscalaz/std/StreamInstances$$anon$2;Lscala/Function0;Lscala/Function0;)Lscala/Function0;
     409: invokevirtual #875                // Method scala/collection/immutable/Stream$cons$.apply:(Ljava/lang/Object;Lscala/Function0;)Lscala/collection/immutable/Stream;
     412: astore        13
     414: ifnonnull     419
     417: aconst_null
     418: athrow
     419: getstatic     #814                // Field scalaz/Tag$.MODULE$:Lscalaz/Tag$;
     422: invokevirtual #818                // Method scalaz/Tag$.k:()Lscalaz/TagKind;
     425: aload         13
     427: invokevirtual #822                // Method scalaz/TagKind.apply:(Ljava/lang/Object;)Ljava/lang/Object;
     430: aconst_null
     431: astore        13
     433: aconst_null
     434: astore        4
     436: aconst_null
     437: astore        5
     439: aconst_null
     440: astore        7
     442: aconst_null
     443: astore        8
     445: aconst_null
     446: astore        9
     448: aconst_null
     449: astore        10
     451: aconst_null
     452: astore        11
     454: aconst_null
     455: astore        12
     457: astore_3
     458: invokevirtual #818                // Method scalaz/Tag$.k:()Lscalaz/TagKind;
     461: aload_3
     462: invokevirtual #832                // Method scalaz/TagKind.unwrap:(Ljava/lang/Object;)Ljava/lang/Object;
     465: checkcast     #19                 // class scala/collection/immutable/Stream
     468: areturn

  public scalaz.std.StreamInstances$$anon$2(scalaz.std.StreamInstances);
    Code:
       0: aload_0
       1: invokespecial #912                // Method java/lang/Object."<init>":()V
       4: aload_0
       5: invokestatic  #916                // InterfaceMethod scalaz/InvariantFunctor.$init$:(Lscalaz/InvariantFunctor;)V
       8: aload_0
       9: invokestatic  #919                // InterfaceMethod scalaz/Functor.$init$:(Lscalaz/Functor;)V
      12: aload_0
      13: invokestatic  #922                // InterfaceMethod scalaz/Apply.$init$:(Lscalaz/Apply;)V
      16: aload_0
      17: invokestatic  #925                // InterfaceMethod scalaz/InvariantApplicative.$init$:(Lscalaz/InvariantApplicative;)V
      20: aload_0
      21: invokestatic  #928                // InterfaceMethod scalaz/Applicative.$init$:(Lscalaz/Applicative;)V
      24: invokestatic  #933                // Method scala/runtime/Statics.releaseFence:()V
      27: return

  private static java.lang.Object $deserializeLambda$(java.lang.invoke.SerializedLambda);
    Code:
       0: aload_0
       1: invokedynamic #946,  0            // InvokeDynamic #3:lambdaDeserialize:(Ljava/lang/invoke/SerializedLambda;)Ljava/lang/Object;
       6: areturn
}
