Compiled from "Try.scala"
public final class scalaz.std.TryInstances$$anon$2 implements scalaz.Isomorphisms$IsoFunctorTemplate<scala.util.Try, ?> {
  private scalaz.NaturalTransformation<scala.util.Try, ?> to;

  private scalaz.NaturalTransformation<?, scala.util.Try> from;

  public scalaz.Isomorphisms$Iso2<scalaz.NaturalTransformation, ?, scala.util.Try> flip();
    Code:
       0: aload_0
       1: invokestatic  #31                 // InterfaceMethod scalaz/Isomorphisms$Iso2.flip$:(Lscalaz/Isomorphisms$Iso2;)Lscalaz/Isomorphisms$Iso2;
       4: areturn

  public <A$> scalaz.Isomorphisms$Iso<scala.Function1, scala.util.Try<A$>, scalaz.Validation<java.lang.Throwable, A$>> unlift(scalaz.Liskov<scalaz.NaturalTransformation<scala.util.Try, ?>, scalaz.NaturalTransformation<scala.util.Try, ?>>, scalaz.Liskov<scalaz.NaturalTransformation<?, scala.util.Try>, scalaz.NaturalTransformation<?, scala.util.Try>>);
    Code:
       0: aload_0
       1: aload_1
       2: aload_2
       3: invokestatic  #42                 // InterfaceMethod scalaz/Isomorphisms$Iso2.unlift$:(Lscalaz/Isomorphisms$Iso2;Lscalaz/Liskov;Lscalaz/Liskov;)Lscalaz/Isomorphisms$Iso;
       6: areturn

  public scalaz.NaturalTransformation<scala.util.Try, scala.util.Try> $percent$tilde(scalaz.NaturalTransformation<?, ?>, scalaz.Liskov<scalaz.NaturalTransformation<scala.util.Try, ?>, scalaz.NaturalTransformation<scala.util.Try, ?>>, scalaz.Liskov<scalaz.NaturalTransformation<?, scala.util.Try>, scalaz.NaturalTransformation<?, scala.util.Try>>);
    Code:
       0: aload_0
       1: aload_1
       2: aload_2
       3: aload_3
       4: invokestatic  #51                 // InterfaceMethod scalaz/Isomorphisms$Iso2.$percent$tilde$:(Lscalaz/Isomorphisms$Iso2;Lscalaz/NaturalTransformation;Lscalaz/Liskov;Lscalaz/Liskov;)Lscalaz/NaturalTransformation;
       7: areturn

  public final scalaz.NaturalTransformation<scala.util.Try, ?> to();
    Code:
       0: aload_0
       1: getfield      #55                 // Field to:Lscalaz/NaturalTransformation;
       4: areturn

  public final scalaz.NaturalTransformation<?, scala.util.Try> from();
    Code:
       0: aload_0
       1: getfield      #58                 // Field from:Lscalaz/NaturalTransformation;
       4: areturn

  public final void scalaz$Isomorphisms$IsoFunctorTemplate$_setter_$to_$eq(scalaz.NaturalTransformation<scala.util.Try, ?>);
    Code:
       0: aload_0
       1: aload_1
       2: putfield      #55                 // Field to:Lscalaz/NaturalTransformation;
       5: return

  public final void scalaz$Isomorphisms$IsoFunctorTemplate$_setter_$from_$eq(scalaz.NaturalTransformation<?, scala.util.Try>);
    Code:
       0: aload_0
       1: aload_1
       2: putfield      #58                 // Field from:Lscalaz/NaturalTransformation;
       5: return

  public <A> scalaz.Validation<java.lang.Throwable, A> to_(scala.util.Try<A>);
    Code:
       0: getstatic     #74                 // Field scalaz/std/try$.MODULE$:Lscalaz/std/try$;
       3: aload_1
       4: invokestatic  #80                 // InterfaceMethod scalaz/std/TryFunctions.toValidation$:(Lscalaz/std/TryFunctions;Lscala/util/Try;)Lscalaz/Validation;
       7: areturn

  public <A> scala.util.Try<A> from_(scalaz.Validation<java.lang.Throwable, A>);
    Code:
       0: getstatic     #74                 // Field scalaz/std/try$.MODULE$:Lscalaz/std/try$;
       3: aload_1
       4: invokestatic  #89                 // InterfaceMethod scalaz/std/TryFunctions.fromValidation$:(Lscalaz/std/TryFunctions;Lscalaz/Validation;)Lscala/util/Try;
       7: areturn

  public scalaz.Isomorphisms scalaz$Isomorphisms$IsoFunctorTemplate$$$outer();
    Code:
       0: getstatic     #97                 // Field scalaz/Isomorphism$.MODULE$:Lscalaz/Isomorphism$;
       3: areturn

  public scalaz.Isomorphisms scalaz$Isomorphisms$Iso2$$$outer();
    Code:
       0: getstatic     #97                 // Field scalaz/Isomorphism$.MODULE$:Lscalaz/Isomorphism$;
       3: areturn

  public java.lang.Object from();
    Code:
       0: aload_0
       1: invokevirtual #101                // Method from:()Lscalaz/NaturalTransformation;
       4: areturn

  public java.lang.Object to();
    Code:
       0: aload_0
       1: invokevirtual #103                // Method to:()Lscalaz/NaturalTransformation;
       4: areturn

  public java.lang.Object from_(java.lang.Object);
    Code:
       0: aload_0
       1: aload_1
       2: checkcast     #107                // class scalaz/Validation
       5: invokevirtual #109                // Method from_:(Lscalaz/Validation;)Lscala/util/Try;
       8: areturn

  public java.lang.Object to_(java.lang.Object);
    Code:
       0: aload_0
       1: aload_1
       2: checkcast     #112                // class scala/util/Try
       5: invokevirtual #114                // Method to_:(Lscala/util/Try;)Lscalaz/Validation;
       8: areturn

  public scalaz.std.TryInstances$$anon$2(scalaz.std.TryInstances);
    Code:
       0: aload_0
       1: invokespecial #120                // Method java/lang/Object."<init>":()V
       4: aload_0
       5: invokestatic  #124                // InterfaceMethod scalaz/Isomorphisms$IsoFunctorTemplate.$init$:(Lscalaz/Isomorphisms$IsoFunctorTemplate;)V
       8: invokestatic  #129                // Method scala/runtime/Statics.releaseFence:()V
      11: return
}
