Compiled from "DataFrameIterable.kt"
public final class org.jetbrains.kotlinx.dataframe.api.CreateDataFrameDsl$InferType<T, R> {
  private final kotlin.jvm.functions.Function1<T, R> expression;

  public org.jetbrains.kotlinx.dataframe.api.CreateDataFrameDsl$InferType(kotlin.jvm.functions.Function1<? super T, ? extends R>);
    Code:
       0: aload_1
       1: ldc           #11                 // String expression
       3: invokestatic  #17                 // Method kotlin/jvm/internal/Intrinsics.checkNotNullParameter:(Ljava/lang/Object;Ljava/lang/String;)V
       6: aload_0
       7: invokespecial #20                 // Method java/lang/Object."<init>":()V
      10: aload_0
      11: aload_1
      12: putfield      #23                 // Field expression:Lkotlin/jvm/functions/Function1;
      15: return

  public final kotlin.jvm.functions.Function1<T, R> getExpression();
    Code:
       0: aload_0
       1: getfield      #23                 // Field expression:Lkotlin/jvm/functions/Function1;
       4: areturn

  public final kotlin.jvm.functions.Function1<T, R> component1();
    Code:
       0: aload_0
       1: getfield      #23                 // Field expression:Lkotlin/jvm/functions/Function1;
       4: areturn

  public final org.jetbrains.kotlinx.dataframe.api.CreateDataFrameDsl$InferType<T, R> copy(kotlin.jvm.functions.Function1<? super T, ? extends R>);
    Code:
       0: aload_1
       1: ldc           #11                 // String expression
       3: invokestatic  #17                 // Method kotlin/jvm/internal/Intrinsics.checkNotNullParameter:(Ljava/lang/Object;Ljava/lang/String;)V
       6: new           #2                  // class org/jetbrains/kotlinx/dataframe/api/CreateDataFrameDsl$InferType
       9: dup
      10: aload_1
      11: invokespecial #34                 // Method "<init>":(Lkotlin/jvm/functions/Function1;)V
      14: areturn

  public static org.jetbrains.kotlinx.dataframe.api.CreateDataFrameDsl$InferType copy$default(org.jetbrains.kotlinx.dataframe.api.CreateDataFrameDsl$InferType, kotlin.jvm.functions.Function1, int, java.lang.Object);
    Code:
       0: iload_2
       1: iconst_1
       2: iand
       3: ifeq          11
       6: aload_0
       7: getfield      #23                 // Field expression:Lkotlin/jvm/functions/Function1;
      10: astore_1
      11: aload_0
      12: aload_1
      13: invokevirtual #38                 // Method copy:(Lkotlin/jvm/functions/Function1;)Lorg/jetbrains/kotlinx/dataframe/api/CreateDataFrameDsl$InferType;
      16: areturn

  public java.lang.String toString();
    Code:
       0: new           #42                 // class java/lang/StringBuilder
       3: dup
       4: invokespecial #43                 // Method java/lang/StringBuilder."<init>":()V
       7: ldc           #45                 // String InferType(expression=
       9: invokevirtual #49                 // Method java/lang/StringBuilder.append:(Ljava/lang/String;)Ljava/lang/StringBuilder;
      12: aload_0
      13: getfield      #23                 // Field expression:Lkotlin/jvm/functions/Function1;
      16: invokevirtual #52                 // Method java/lang/StringBuilder.append:(Ljava/lang/Object;)Ljava/lang/StringBuilder;
      19: bipush        41
      21: invokevirtual #55                 // Method java/lang/StringBuilder.append:(C)Ljava/lang/StringBuilder;
      24: invokevirtual #57                 // Method java/lang/StringBuilder.toString:()Ljava/lang/String;
      27: areturn

  public int hashCode();
    Code:
       0: aload_0
       1: getfield      #23                 // Field expression:Lkotlin/jvm/functions/Function1;
       4: invokevirtual #61                 // Method java/lang/Object.hashCode:()I
       7: ireturn

  public boolean equals(java.lang.Object);
    Code:
       0: aload_0
       1: aload_1
       2: if_acmpne     7
       5: iconst_1
       6: ireturn
       7: aload_1
       8: instanceof    #2                  // class org/jetbrains/kotlinx/dataframe/api/CreateDataFrameDsl$InferType
      11: ifne          16
      14: iconst_0
      15: ireturn
      16: aload_1
      17: checkcast     #2                  // class org/jetbrains/kotlinx/dataframe/api/CreateDataFrameDsl$InferType
      20: astore_2
      21: aload_0
      22: getfield      #23                 // Field expression:Lkotlin/jvm/functions/Function1;
      25: aload_2
      26: getfield      #23                 // Field expression:Lkotlin/jvm/functions/Function1;
      29: invokestatic  #68                 // Method kotlin/jvm/internal/Intrinsics.areEqual:(Ljava/lang/Object;Ljava/lang/Object;)Z
      32: ifne          37
      35: iconst_0
      36: ireturn
      37: iconst_1
      38: ireturn
}
