Compiled from "move.kt"
public final class org.jetbrains.kotlinx.dataframe.api.MoveClause<T, C> {
  private final org.jetbrains.kotlinx.dataframe.DataFrame<T> df;

  private final kotlin.jvm.functions.Function2<org.jetbrains.kotlinx.dataframe.api.ColumnsSelectionDsl<? extends T>, org.jetbrains.kotlinx.dataframe.api.ColumnsSelectionDsl<? extends T>, org.jetbrains.kotlinx.dataframe.columns.ColumnSet<C>> columns;

  public org.jetbrains.kotlinx.dataframe.api.MoveClause(org.jetbrains.kotlinx.dataframe.DataFrame<? extends T>, kotlin.jvm.functions.Function2<? super org.jetbrains.kotlinx.dataframe.api.ColumnsSelectionDsl<? extends T>, ? super org.jetbrains.kotlinx.dataframe.api.ColumnsSelectionDsl<? extends T>, ? extends org.jetbrains.kotlinx.dataframe.columns.ColumnSet<? extends C>>);
    Code:
       0: aload_1
       1: ldc           #11                 // String df
       3: invokestatic  #17                 // Method kotlin/jvm/internal/Intrinsics.checkNotNullParameter:(Ljava/lang/Object;Ljava/lang/String;)V
       6: aload_2
       7: ldc           #19                 // String columns
       9: invokestatic  #17                 // Method kotlin/jvm/internal/Intrinsics.checkNotNullParameter:(Ljava/lang/Object;Ljava/lang/String;)V
      12: aload_0
      13: invokespecial #22                 // Method java/lang/Object."<init>":()V
      16: aload_0
      17: aload_1
      18: putfield      #25                 // Field df:Lorg/jetbrains/kotlinx/dataframe/DataFrame;
      21: aload_0
      22: aload_2
      23: putfield      #28                 // Field columns:Lkotlin/jvm/functions/Function2;
      26: return

  public final org.jetbrains.kotlinx.dataframe.DataFrame<T> getDf$dataframe();
    Code:
       0: aload_0
       1: getfield      #25                 // Field df:Lorg/jetbrains/kotlinx/dataframe/DataFrame;
       4: areturn

  public final kotlin.jvm.functions.Function2<org.jetbrains.kotlinx.dataframe.api.ColumnsSelectionDsl<? extends T>, org.jetbrains.kotlinx.dataframe.api.ColumnsSelectionDsl<? extends T>, org.jetbrains.kotlinx.dataframe.columns.ColumnSet<C>> getColumns$dataframe();
    Code:
       0: aload_0
       1: getfield      #28                 // Field columns:Lkotlin/jvm/functions/Function2;
       4: areturn
}
