Compiled from "rename.kt"
final class org.jetbrains.kotlinx.dataframe.api.RenameKt$rename$1 extends kotlin.jvm.internal.Lambda implements kotlin.jvm.functions.Function2<org.jetbrains.kotlinx.dataframe.api.ColumnsSelectionDsl<? extends T>, org.jetbrains.kotlinx.dataframe.api.ColumnsSelectionDsl<? extends T>, org.jetbrains.kotlinx.dataframe.columns.ColumnSet<? extends java.lang.Object>> {
  final kotlin.Pair<java.lang.String, java.lang.String>[] $mappings;

  org.jetbrains.kotlinx.dataframe.api.RenameKt$rename$1(kotlin.Pair<java.lang.String, java.lang.String>[]);
    Code:
       0: aload_0
       1: aload_1
       2: putfield      #14                 // Field $mappings:[Lkotlin/Pair;
       5: aload_0
       6: iconst_2
       7: invokespecial #17                 // Method kotlin/jvm/internal/Lambda."<init>":(I)V
      10: return

  public final org.jetbrains.kotlinx.dataframe.columns.ColumnSet<java.lang.Object> invoke(org.jetbrains.kotlinx.dataframe.api.ColumnsSelectionDsl<? extends T>, org.jetbrains.kotlinx.dataframe.api.ColumnsSelectionDsl<? extends T>);
    Code:
       0: aload_1
       1: ldc           #25                 // String $this$rename
       3: invokestatic  #31                 // Method kotlin/jvm/internal/Intrinsics.checkNotNullParameter:(Ljava/lang/Object;Ljava/lang/String;)V
       6: aload_2
       7: ldc           #33                 // String it
       9: invokestatic  #31                 // Method kotlin/jvm/internal/Intrinsics.checkNotNullParameter:(Ljava/lang/Object;Ljava/lang/String;)V
      12: aload_0
      13: getfield      #14                 // Field $mappings:[Lkotlin/Pair;
      16: astore_3
      17: iconst_0
      18: istore        4
      20: aload_3
      21: astore        5
      23: new           #35                 // class java/util/ArrayList
      26: dup
      27: aload_3
      28: arraylength
      29: invokespecial #36                 // Method java/util/ArrayList."<init>":(I)V
      32: checkcast     #38                 // class java/util/Collection
      35: astore        6
      37: iconst_0
      38: istore        7
      40: aload         5
      42: astore        8
      44: iconst_0
      45: istore        9
      47: aload         8
      49: arraylength
      50: istore        10
      52: iload         9
      54: iload         10
      56: if_icmpge     103
      59: aload         8
      61: iload         9
      63: aaload
      64: astore        11
      66: iinc          9, 1
      69: aload         6
      71: aload         11
      73: astore        12
      75: astore        14
      77: iconst_0
      78: istore        13
      80: aload         12
      82: invokevirtual #44                 // Method kotlin/Pair.getFirst:()Ljava/lang/Object;
      85: checkcast     #46                 // class java/lang/String
      88: invokestatic  #52                 // Method org/jetbrains/kotlinx/dataframe/api/TypeConversionsKt.toColumnAccessor:(Ljava/lang/String;)Lorg/jetbrains/kotlinx/dataframe/columns/ColumnAccessor;
      91: aload         14
      93: swap
      94: invokeinterface #56,  2           // InterfaceMethod java/util/Collection.add:(Ljava/lang/Object;)Z
      99: pop
     100: goto          52
     103: aload         6
     105: checkcast     #58                 // class java/util/List
     108: nop
     109: checkcast     #60                 // class java/lang/Iterable
     112: invokestatic  #66                 // Method org/jetbrains/kotlinx/dataframe/impl/columns/ConstructorsKt.toColumnSetC:(Ljava/lang/Iterable;)Lorg/jetbrains/kotlinx/dataframe/columns/ColumnSet;
     115: areturn

  public java.lang.Object invoke(java.lang.Object, java.lang.Object);
    Code:
       0: aload_0
       1: aload_1
       2: checkcast     #81                 // class org/jetbrains/kotlinx/dataframe/api/ColumnsSelectionDsl
       5: aload_2
       6: checkcast     #81                 // class org/jetbrains/kotlinx/dataframe/api/ColumnsSelectionDsl
       9: invokevirtual #85                 // Method invoke:(Lorg/jetbrains/kotlinx/dataframe/api/ColumnsSelectionDsl;Lorg/jetbrains/kotlinx/dataframe/api/ColumnsSelectionDsl;)Lorg/jetbrains/kotlinx/dataframe/columns/ColumnSet;
      12: areturn
}
