Compiled from "TreeSetConverter.java"
class com.thoughtworks.xstream.converters.collections.TreeSetConverter$1$1 extends java.util.AbstractList {
  final java.util.Map val$target;

  final com.thoughtworks.xstream.converters.collections.TreeSetConverter$1 this$1;

  com.thoughtworks.xstream.converters.collections.TreeSetConverter$1$1(com.thoughtworks.xstream.converters.collections.TreeSetConverter$1, java.util.Map);
    Code:
       0: aload_0
       1: aload_1
       2: putfield      #1                  // Field this$1:Lcom/thoughtworks/xstream/converters/collections/TreeSetConverter$1;
       5: aload_0
       6: aload_2
       7: putfield      #2                  // Field val$target:Ljava/util/Map;
      10: aload_0
      11: invokespecial #3                  // Method java/util/AbstractList."<init>":()V
      14: return

  public boolean add(java.lang.Object);
    Code:
       0: aload_0
       1: getfield      #2                  // Field val$target:Ljava/util/Map;
       4: aload_1
       5: aload_1
       6: invokeinterface #4,  3            // InterfaceMethod java/util/Map.put:(Ljava/lang/Object;Ljava/lang/Object;)Ljava/lang/Object;
      11: ifnull        18
      14: iconst_1
      15: goto          19
      18: iconst_0
      19: ireturn

  public java.lang.Object get(int);
    Code:
       0: aconst_null
       1: areturn

  public int size();
    Code:
       0: aload_0
       1: getfield      #2                  // Field val$target:Ljava/util/Map;
       4: invokeinterface #5,  1            // InterfaceMethod java/util/Map.size:()I
       9: ireturn
}
