Compiled from "RestConsumerContextPathMatcher.java"
public final class org.apache.camel.support.RestConsumerContextPathMatcher {
  private org.apache.camel.support.RestConsumerContextPathMatcher();
    Code:
       0: aload_0
       1: invokespecial #12                 // Method java/lang/Object."<init>":()V
       4: return

  public static boolean matchPath(java.lang.String, java.lang.String, boolean);
    Code:
       0: aload_0
       1: ifnonnull     10
       4: aload_1
       5: ifnonnull     10
       8: iconst_1
       9: ireturn
      10: aload_0
      11: ifnull        18
      14: aload_1
      15: ifnonnull     20
      18: iconst_0
      19: ireturn
      20: aload_0
      21: getstatic     #22                 // Field java/util/Locale.ENGLISH:Ljava/util/Locale;
      24: invokevirtual #28                 // Method java/lang/String.toLowerCase:(Ljava/util/Locale;)Ljava/lang/String;
      27: astore_3
      28: aload_1
      29: getstatic     #22                 // Field java/util/Locale.ENGLISH:Ljava/util/Locale;
      32: invokevirtual #28                 // Method java/lang/String.toLowerCase:(Ljava/util/Locale;)Ljava/lang/String;
      35: astore        4
      37: aload_3
      38: aload         4
      40: invokevirtual #32                 // Method java/lang/String.equals:(Ljava/lang/Object;)Z
      43: ifeq          48
      46: iconst_1
      47: ireturn
      48: iload_2
      49: ifeq          63
      52: aload_3
      53: aload         4
      55: invokevirtual #36                 // Method java/lang/String.startsWith:(Ljava/lang/String;)Z
      58: ifeq          63
      61: iconst_1
      62: ireturn
      63: iconst_0
      64: ireturn

  public static org.apache.camel.support.RestConsumerContextPathMatcher$ConsumerPath matchBestPath(java.lang.String, java.lang.String, java.util.List<org.apache.camel.support.RestConsumerContextPathMatcher$ConsumerPath>);
    Code:
       0: aconst_null
       1: astore_3
       2: new           #47                 // class java/util/ArrayList
       5: dup
       6: invokespecial #48                 // Method java/util/ArrayList."<init>":()V
       9: astore        4
      11: aload_2
      12: invokeinterface #54,  1           // InterfaceMethod java/util/List.iterator:()Ljava/util/Iterator;
      17: astore        5
      19: aload         5
      21: invokeinterface #60,  1           // InterfaceMethod java/util/Iterator.hasNext:()Z
      26: ifeq          68
      29: aload         5
      31: invokeinterface #64,  1           // InterfaceMethod java/util/Iterator.next:()Ljava/lang/Object;
      36: checkcast     #7                  // class org/apache/camel/support/RestConsumerContextPathMatcher$ConsumerPath
      39: astore        6
      41: aload_0
      42: aload         6
      44: invokeinterface #68,  1           // InterfaceMethod org/apache/camel/support/RestConsumerContextPathMatcher$ConsumerPath.getRestrictMethod:()Ljava/lang/String;
      49: invokestatic  #72                 // Method matchRestMethod:(Ljava/lang/String;Ljava/lang/String;)Z
      52: ifeq          65
      55: aload         4
      57: aload         6
      59: invokeinterface #75,  2           // InterfaceMethod java/util/List.add:(Ljava/lang/Object;)Z
      64: pop
      65: goto          19
      68: aload         4
      70: invokeinterface #54,  1           // InterfaceMethod java/util/List.iterator:()Ljava/util/Iterator;
      75: astore        5
      77: aload         5
      79: invokeinterface #60,  1           // InterfaceMethod java/util/Iterator.hasNext:()Z
      84: ifeq          123
      87: aload         5
      89: invokeinterface #64,  1           // InterfaceMethod java/util/Iterator.next:()Ljava/lang/Object;
      94: checkcast     #7                  // class org/apache/camel/support/RestConsumerContextPathMatcher$ConsumerPath
      97: astore        6
      99: aload_1
     100: aload         6
     102: invokeinterface #78,  1           // InterfaceMethod org/apache/camel/support/RestConsumerContextPathMatcher$ConsumerPath.getConsumerPath:()Ljava/lang/String;
     107: iconst_0
     108: invokestatic  #81                 // Method matchRestPath:(Ljava/lang/String;Ljava/lang/String;Z)Z
     111: ifeq          120
     114: aload         6
     116: astore_3
     117: goto          123
     120: goto          77
     123: aload_3
     124: ifnonnull     307
     127: aload         4
     129: invokeinterface #54,  1           // InterfaceMethod java/util/List.iterator:()Ljava/util/Iterator;
     134: astore        5
     136: aload         5
     138: invokeinterface #60,  1           // InterfaceMethod java/util/Iterator.hasNext:()Z
     143: ifeq          183
     146: aload         5
     148: invokeinterface #64,  1           // InterfaceMethod java/util/Iterator.next:()Ljava/lang/Object;
     153: checkcast     #7                  // class org/apache/camel/support/RestConsumerContextPathMatcher$ConsumerPath
     156: astore        6
     158: aload_1
     159: aload         6
     161: invokeinterface #78,  1           // InterfaceMethod org/apache/camel/support/RestConsumerContextPathMatcher$ConsumerPath.getConsumerPath:()Ljava/lang/String;
     166: iconst_1
     167: invokestatic  #81                 // Method matchRestPath:(Ljava/lang/String;Ljava/lang/String;Z)Z
     170: ifne          180
     173: aload         5
     175: invokeinterface #84,  1           // InterfaceMethod java/util/Iterator.remove:()V
     180: goto          136
     183: ldc           #85                 // int 2147483647
     185: istore        6
     187: aconst_null
     188: astore        7
     190: aload         4
     192: invokeinterface #89,  1           // InterfaceMethod java/util/List.size:()I
     197: iconst_1
     198: if_icmple     280
     201: aload         4
     203: invokeinterface #54,  1           // InterfaceMethod java/util/List.iterator:()Ljava/util/Iterator;
     208: astore        5
     210: aload         5
     212: invokeinterface #60,  1           // InterfaceMethod java/util/Iterator.hasNext:()Z
     217: ifeq          272
     220: aload         5
     222: invokeinterface #64,  1           // InterfaceMethod java/util/Iterator.next:()Ljava/lang/Object;
     227: checkcast     #7                  // class org/apache/camel/support/RestConsumerContextPathMatcher$ConsumerPath
     230: astore        8
     232: aload         8
     234: invokeinterface #78,  1           // InterfaceMethod org/apache/camel/support/RestConsumerContextPathMatcher$ConsumerPath.getConsumerPath:()Ljava/lang/String;
     239: invokestatic  #93                 // Method countWildcards:(Ljava/lang/String;)I
     242: istore        9
     244: iload         9
     246: ifle          269
     249: aload         7
     251: ifnull        261
     254: iload         9
     256: iload         6
     258: if_icmpge     269
     261: aload         8
     263: astore        7
     265: iload         9
     267: istore        6
     269: goto          210
     272: aload         7
     274: ifnull        280
     277: aload         7
     279: astore_3
     280: aload_3
     281: ifnonnull     307
     284: aload         4
     286: invokeinterface #89,  1           // InterfaceMethod java/util/List.size:()I
     291: iconst_1
     292: if_icmpne     307
     295: aload         4
     297: iconst_0
     298: invokeinterface #97,  2           // InterfaceMethod java/util/List.get:(I)Ljava/lang/Object;
     303: checkcast     #7                  // class org/apache/camel/support/RestConsumerContextPathMatcher$ConsumerPath
     306: astore_3
     307: aload_3
     308: areturn

  private static boolean matchRestMethod(java.lang.String, java.lang.String);
    Code:
       0: aload_1
       1: ifnonnull     6
       4: iconst_1
       5: ireturn
       6: aload_1
       7: getstatic     #22                 // Field java/util/Locale.ENGLISH:Ljava/util/Locale;
      10: invokevirtual #28                 // Method java/lang/String.toLowerCase:(Ljava/util/Locale;)Ljava/lang/String;
      13: aload_0
      14: getstatic     #22                 // Field java/util/Locale.ENGLISH:Ljava/util/Locale;
      17: invokevirtual #28                 // Method java/lang/String.toLowerCase:(Ljava/util/Locale;)Ljava/lang/String;
      20: invokevirtual #117                // Method java/lang/String.contains:(Ljava/lang/CharSequence;)Z
      23: ireturn

  private static boolean matchRestPath(java.lang.String, java.lang.String, boolean);
    Code:
       0: aload_0
       1: ldc           #121                // String /
       3: invokevirtual #36                 // Method java/lang/String.startsWith:(Ljava/lang/String;)Z
       6: ifeq          15
       9: aload_0
      10: iconst_1
      11: invokevirtual #125                // Method java/lang/String.substring:(I)Ljava/lang/String;
      14: astore_0
      15: aload_0
      16: ldc           #121                // String /
      18: invokevirtual #128                // Method java/lang/String.endsWith:(Ljava/lang/String;)Z
      21: ifeq          36
      24: aload_0
      25: iconst_0
      26: aload_0
      27: invokevirtual #131                // Method java/lang/String.length:()I
      30: iconst_1
      31: isub
      32: invokevirtual #134                // Method java/lang/String.substring:(II)Ljava/lang/String;
      35: astore_0
      36: aload_1
      37: ldc           #121                // String /
      39: invokevirtual #36                 // Method java/lang/String.startsWith:(Ljava/lang/String;)Z
      42: ifeq          51
      45: aload_1
      46: iconst_1
      47: invokevirtual #125                // Method java/lang/String.substring:(I)Ljava/lang/String;
      50: astore_1
      51: aload_1
      52: ldc           #121                // String /
      54: invokevirtual #128                // Method java/lang/String.endsWith:(Ljava/lang/String;)Z
      57: ifeq          72
      60: aload_1
      61: iconst_0
      62: aload_1
      63: invokevirtual #131                // Method java/lang/String.length:()I
      66: iconst_1
      67: isub
      68: invokevirtual #134                // Method java/lang/String.substring:(II)Ljava/lang/String;
      71: astore_1
      72: aload_0
      73: ldc           #121                // String /
      75: invokevirtual #138                // Method java/lang/String.split:(Ljava/lang/String;)[Ljava/lang/String;
      78: astore_3
      79: aload_1
      80: ldc           #121                // String /
      82: invokevirtual #138                // Method java/lang/String.split:(Ljava/lang/String;)[Ljava/lang/String;
      85: astore        4
      87: aload_3
      88: arraylength
      89: aload         4
      91: arraylength
      92: if_icmpeq     97
      95: iconst_0
      96: ireturn
      97: iconst_0
      98: istore        5
     100: iload         5
     102: aload_3
     103: arraylength
     104: if_icmpge     166
     107: aload_3
     108: iload         5
     110: aaload
     111: astore        6
     113: aload         4
     115: iload         5
     117: aaload
     118: astore        7
     120: iload_2
     121: ifeq          147
     124: aload         7
     126: ldc           #142                // String {
     128: invokevirtual #36                 // Method java/lang/String.startsWith:(Ljava/lang/String;)Z
     131: ifeq          147
     134: aload         7
     136: ldc           #144                // String }
     138: invokevirtual #128                // Method java/lang/String.endsWith:(Ljava/lang/String;)Z
     141: ifeq          147
     144: goto          160
     147: aload         6
     149: aload         7
     151: iconst_0
     152: invokestatic  #146                // Method matchPath:(Ljava/lang/String;Ljava/lang/String;Z)Z
     155: ifne          160
     158: iconst_0
     159: ireturn
     160: iinc          5, 1
     163: goto          100
     166: iconst_1
     167: ireturn

  private static int countWildcards(java.lang.String);
    Code:
       0: iconst_0
       1: istore_1
       2: aload_0
       3: ldc           #121                // String /
       5: invokevirtual #36                 // Method java/lang/String.startsWith:(Ljava/lang/String;)Z
       8: ifeq          17
      11: aload_0
      12: iconst_1
      13: invokevirtual #125                // Method java/lang/String.substring:(I)Ljava/lang/String;
      16: astore_0
      17: aload_0
      18: ldc           #121                // String /
      20: invokevirtual #128                // Method java/lang/String.endsWith:(Ljava/lang/String;)Z
      23: ifeq          38
      26: aload_0
      27: iconst_0
      28: aload_0
      29: invokevirtual #131                // Method java/lang/String.length:()I
      32: iconst_1
      33: isub
      34: invokevirtual #134                // Method java/lang/String.substring:(II)Ljava/lang/String;
      37: astore_0
      38: aload_0
      39: ldc           #121                // String /
      41: invokevirtual #138                // Method java/lang/String.split:(Ljava/lang/String;)[Ljava/lang/String;
      44: astore_2
      45: aload_2
      46: astore_3
      47: aload_3
      48: arraylength
      49: istore        4
      51: iconst_0
      52: istore        5
      54: iload         5
      56: iload         4
      58: if_icmpge     96
      61: aload_3
      62: iload         5
      64: aaload
      65: astore        6
      67: aload         6
      69: ldc           #142                // String {
      71: invokevirtual #36                 // Method java/lang/String.startsWith:(Ljava/lang/String;)Z
      74: ifeq          90
      77: aload         6
      79: ldc           #144                // String }
      81: invokevirtual #128                // Method java/lang/String.endsWith:(Ljava/lang/String;)Z
      84: ifeq          90
      87: iinc          1, 1
      90: iinc          5, 1
      93: goto          54
      96: iload_1
      97: ireturn
}
