Compiled from "OnCommittedResponseWrapper.java"
class org.springframework.security.web.util.OnCommittedResponseWrapper$SaveContextServletOutputStream extends javax.servlet.ServletOutputStream {
  private final javax.servlet.ServletOutputStream delegate;

  final org.springframework.security.web.util.OnCommittedResponseWrapper this$0;

  public org.springframework.security.web.util.OnCommittedResponseWrapper$SaveContextServletOutputStream(org.springframework.security.web.util.OnCommittedResponseWrapper, javax.servlet.ServletOutputStream);
    Code:
       0: aload_0
       1: aload_1
       2: putfield      #1                  // Field this$0:Lorg/springframework/security/web/util/OnCommittedResponseWrapper;
       5: aload_0
       6: invokespecial #2                  // Method javax/servlet/ServletOutputStream."<init>":()V
       9: aload_0
      10: aload_2
      11: putfield      #3                  // Field delegate:Ljavax/servlet/ServletOutputStream;
      14: return

  public void write(int) throws java.io.IOException;
    Code:
       0: aload_0
       1: getfield      #1                  // Field this$0:Lorg/springframework/security/web/util/OnCommittedResponseWrapper;
       4: iload_1
       5: invokestatic  #4                  // Method org/springframework/security/web/util/OnCommittedResponseWrapper.access$100:(Lorg/springframework/security/web/util/OnCommittedResponseWrapper;I)V
       8: aload_0
       9: getfield      #3                  // Field delegate:Ljavax/servlet/ServletOutputStream;
      12: iload_1
      13: invokevirtual #5                  // Method javax/servlet/ServletOutputStream.write:(I)V
      16: return

  public void flush() throws java.io.IOException;
    Code:
       0: aload_0
       1: getfield      #1                  // Field this$0:Lorg/springframework/security/web/util/OnCommittedResponseWrapper;
       4: invokestatic  #6                  // Method org/springframework/security/web/util/OnCommittedResponseWrapper.access$000:(Lorg/springframework/security/web/util/OnCommittedResponseWrapper;)V
       7: aload_0
       8: getfield      #3                  // Field delegate:Ljavax/servlet/ServletOutputStream;
      11: invokevirtual #7                  // Method javax/servlet/ServletOutputStream.flush:()V
      14: return

  public void close() throws java.io.IOException;
    Code:
       0: aload_0
       1: getfield      #1                  // Field this$0:Lorg/springframework/security/web/util/OnCommittedResponseWrapper;
       4: invokestatic  #6                  // Method org/springframework/security/web/util/OnCommittedResponseWrapper.access$000:(Lorg/springframework/security/web/util/OnCommittedResponseWrapper;)V
       7: aload_0
       8: getfield      #3                  // Field delegate:Ljavax/servlet/ServletOutputStream;
      11: invokevirtual #8                  // Method javax/servlet/ServletOutputStream.close:()V
      14: return

  public int hashCode();
    Code:
       0: aload_0
       1: getfield      #3                  // Field delegate:Ljavax/servlet/ServletOutputStream;
       4: invokevirtual #9                  // Method java/lang/Object.hashCode:()I
       7: ireturn

  public boolean equals(java.lang.Object);
    Code:
       0: aload_0
       1: getfield      #3                  // Field delegate:Ljavax/servlet/ServletOutputStream;
       4: aload_1
       5: invokevirtual #10                 // Method java/lang/Object.equals:(Ljava/lang/Object;)Z
       8: ireturn

  public void print(boolean) throws java.io.IOException;
    Code:
       0: aload_0
       1: getfield      #1                  // Field this$0:Lorg/springframework/security/web/util/OnCommittedResponseWrapper;
       4: iload_1
       5: invokestatic  #11                 // Method org/springframework/security/web/util/OnCommittedResponseWrapper.access$500:(Lorg/springframework/security/web/util/OnCommittedResponseWrapper;Z)V
       8: aload_0
       9: getfield      #3                  // Field delegate:Ljavax/servlet/ServletOutputStream;
      12: iload_1
      13: invokevirtual #12                 // Method javax/servlet/ServletOutputStream.print:(Z)V
      16: return

  public void print(char) throws java.io.IOException;
    Code:
       0: aload_0
       1: getfield      #1                  // Field this$0:Lorg/springframework/security/web/util/OnCommittedResponseWrapper;
       4: iload_1
       5: invokestatic  #13                 // Method org/springframework/security/web/util/OnCommittedResponseWrapper.access$600:(Lorg/springframework/security/web/util/OnCommittedResponseWrapper;C)V
       8: aload_0
       9: getfield      #3                  // Field delegate:Ljavax/servlet/ServletOutputStream;
      12: iload_1
      13: invokevirtual #14                 // Method javax/servlet/ServletOutputStream.print:(C)V
      16: return

  public void print(double) throws java.io.IOException;
    Code:
       0: aload_0
       1: getfield      #1                  // Field this$0:Lorg/springframework/security/web/util/OnCommittedResponseWrapper;
       4: dload_1
       5: invokestatic  #15                 // Method org/springframework/security/web/util/OnCommittedResponseWrapper.access$800:(Lorg/springframework/security/web/util/OnCommittedResponseWrapper;D)V
       8: aload_0
       9: getfield      #3                  // Field delegate:Ljavax/servlet/ServletOutputStream;
      12: dload_1
      13: invokevirtual #16                 // Method javax/servlet/ServletOutputStream.print:(D)V
      16: return

  public void print(float) throws java.io.IOException;
    Code:
       0: aload_0
       1: getfield      #1                  // Field this$0:Lorg/springframework/security/web/util/OnCommittedResponseWrapper;
       4: fload_1
       5: invokestatic  #17                 // Method org/springframework/security/web/util/OnCommittedResponseWrapper.access$700:(Lorg/springframework/security/web/util/OnCommittedResponseWrapper;F)V
       8: aload_0
       9: getfield      #3                  // Field delegate:Ljavax/servlet/ServletOutputStream;
      12: fload_1
      13: invokevirtual #18                 // Method javax/servlet/ServletOutputStream.print:(F)V
      16: return

  public void print(int) throws java.io.IOException;
    Code:
       0: aload_0
       1: getfield      #1                  // Field this$0:Lorg/springframework/security/web/util/OnCommittedResponseWrapper;
       4: iload_1
       5: invokestatic  #4                  // Method org/springframework/security/web/util/OnCommittedResponseWrapper.access$100:(Lorg/springframework/security/web/util/OnCommittedResponseWrapper;I)V
       8: aload_0
       9: getfield      #3                  // Field delegate:Ljavax/servlet/ServletOutputStream;
      12: iload_1
      13: invokevirtual #19                 // Method javax/servlet/ServletOutputStream.print:(I)V
      16: return

  public void print(long) throws java.io.IOException;
    Code:
       0: aload_0
       1: getfield      #1                  // Field this$0:Lorg/springframework/security/web/util/OnCommittedResponseWrapper;
       4: lload_1
       5: l2f
       6: invokestatic  #17                 // Method org/springframework/security/web/util/OnCommittedResponseWrapper.access$700:(Lorg/springframework/security/web/util/OnCommittedResponseWrapper;F)V
       9: aload_0
      10: getfield      #3                  // Field delegate:Ljavax/servlet/ServletOutputStream;
      13: lload_1
      14: invokevirtual #20                 // Method javax/servlet/ServletOutputStream.print:(J)V
      17: return

  public void print(java.lang.String) throws java.io.IOException;
    Code:
       0: aload_0
       1: getfield      #1                  // Field this$0:Lorg/springframework/security/web/util/OnCommittedResponseWrapper;
       4: aload_1
       5: invokestatic  #21                 // Method org/springframework/security/web/util/OnCommittedResponseWrapper.access$400:(Lorg/springframework/security/web/util/OnCommittedResponseWrapper;Ljava/lang/String;)V
       8: aload_0
       9: getfield      #3                  // Field delegate:Ljavax/servlet/ServletOutputStream;
      12: aload_1
      13: invokevirtual #22                 // Method javax/servlet/ServletOutputStream.print:(Ljava/lang/String;)V
      16: return

  public void println() throws java.io.IOException;
    Code:
       0: aload_0
       1: getfield      #1                  // Field this$0:Lorg/springframework/security/web/util/OnCommittedResponseWrapper;
       4: invokestatic  #23                 // Method org/springframework/security/web/util/OnCommittedResponseWrapper.access$1000:(Lorg/springframework/security/web/util/OnCommittedResponseWrapper;)V
       7: aload_0
       8: getfield      #3                  // Field delegate:Ljavax/servlet/ServletOutputStream;
      11: invokevirtual #24                 // Method javax/servlet/ServletOutputStream.println:()V
      14: return

  public void println(boolean) throws java.io.IOException;
    Code:
       0: aload_0
       1: getfield      #1                  // Field this$0:Lorg/springframework/security/web/util/OnCommittedResponseWrapper;
       4: iload_1
       5: invokestatic  #11                 // Method org/springframework/security/web/util/OnCommittedResponseWrapper.access$500:(Lorg/springframework/security/web/util/OnCommittedResponseWrapper;Z)V
       8: aload_0
       9: getfield      #1                  // Field this$0:Lorg/springframework/security/web/util/OnCommittedResponseWrapper;
      12: invokestatic  #23                 // Method org/springframework/security/web/util/OnCommittedResponseWrapper.access$1000:(Lorg/springframework/security/web/util/OnCommittedResponseWrapper;)V
      15: aload_0
      16: getfield      #3                  // Field delegate:Ljavax/servlet/ServletOutputStream;
      19: iload_1
      20: invokevirtual #25                 // Method javax/servlet/ServletOutputStream.println:(Z)V
      23: return

  public void println(char) throws java.io.IOException;
    Code:
       0: aload_0
       1: getfield      #1                  // Field this$0:Lorg/springframework/security/web/util/OnCommittedResponseWrapper;
       4: iload_1
       5: invokestatic  #13                 // Method org/springframework/security/web/util/OnCommittedResponseWrapper.access$600:(Lorg/springframework/security/web/util/OnCommittedResponseWrapper;C)V
       8: aload_0
       9: getfield      #1                  // Field this$0:Lorg/springframework/security/web/util/OnCommittedResponseWrapper;
      12: invokestatic  #23                 // Method org/springframework/security/web/util/OnCommittedResponseWrapper.access$1000:(Lorg/springframework/security/web/util/OnCommittedResponseWrapper;)V
      15: aload_0
      16: getfield      #3                  // Field delegate:Ljavax/servlet/ServletOutputStream;
      19: iload_1
      20: invokevirtual #26                 // Method javax/servlet/ServletOutputStream.println:(C)V
      23: return

  public void println(double) throws java.io.IOException;
    Code:
       0: aload_0
       1: getfield      #1                  // Field this$0:Lorg/springframework/security/web/util/OnCommittedResponseWrapper;
       4: dload_1
       5: invokestatic  #15                 // Method org/springframework/security/web/util/OnCommittedResponseWrapper.access$800:(Lorg/springframework/security/web/util/OnCommittedResponseWrapper;D)V
       8: aload_0
       9: getfield      #1                  // Field this$0:Lorg/springframework/security/web/util/OnCommittedResponseWrapper;
      12: invokestatic  #23                 // Method org/springframework/security/web/util/OnCommittedResponseWrapper.access$1000:(Lorg/springframework/security/web/util/OnCommittedResponseWrapper;)V
      15: aload_0
      16: getfield      #3                  // Field delegate:Ljavax/servlet/ServletOutputStream;
      19: dload_1
      20: invokevirtual #27                 // Method javax/servlet/ServletOutputStream.println:(D)V
      23: return

  public void println(float) throws java.io.IOException;
    Code:
       0: aload_0
       1: getfield      #1                  // Field this$0:Lorg/springframework/security/web/util/OnCommittedResponseWrapper;
       4: fload_1
       5: invokestatic  #17                 // Method org/springframework/security/web/util/OnCommittedResponseWrapper.access$700:(Lorg/springframework/security/web/util/OnCommittedResponseWrapper;F)V
       8: aload_0
       9: getfield      #1                  // Field this$0:Lorg/springframework/security/web/util/OnCommittedResponseWrapper;
      12: invokestatic  #23                 // Method org/springframework/security/web/util/OnCommittedResponseWrapper.access$1000:(Lorg/springframework/security/web/util/OnCommittedResponseWrapper;)V
      15: aload_0
      16: getfield      #3                  // Field delegate:Ljavax/servlet/ServletOutputStream;
      19: fload_1
      20: invokevirtual #28                 // Method javax/servlet/ServletOutputStream.println:(F)V
      23: return

  public void println(int) throws java.io.IOException;
    Code:
       0: aload_0
       1: getfield      #1                  // Field this$0:Lorg/springframework/security/web/util/OnCommittedResponseWrapper;
       4: iload_1
       5: invokestatic  #4                  // Method org/springframework/security/web/util/OnCommittedResponseWrapper.access$100:(Lorg/springframework/security/web/util/OnCommittedResponseWrapper;I)V
       8: aload_0
       9: getfield      #1                  // Field this$0:Lorg/springframework/security/web/util/OnCommittedResponseWrapper;
      12: invokestatic  #23                 // Method org/springframework/security/web/util/OnCommittedResponseWrapper.access$1000:(Lorg/springframework/security/web/util/OnCommittedResponseWrapper;)V
      15: aload_0
      16: getfield      #3                  // Field delegate:Ljavax/servlet/ServletOutputStream;
      19: iload_1
      20: invokevirtual #29                 // Method javax/servlet/ServletOutputStream.println:(I)V
      23: return

  public void println(long) throws java.io.IOException;
    Code:
       0: aload_0
       1: getfield      #1                  // Field this$0:Lorg/springframework/security/web/util/OnCommittedResponseWrapper;
       4: lload_1
       5: l2f
       6: invokestatic  #17                 // Method org/springframework/security/web/util/OnCommittedResponseWrapper.access$700:(Lorg/springframework/security/web/util/OnCommittedResponseWrapper;F)V
       9: aload_0
      10: getfield      #1                  // Field this$0:Lorg/springframework/security/web/util/OnCommittedResponseWrapper;
      13: invokestatic  #23                 // Method org/springframework/security/web/util/OnCommittedResponseWrapper.access$1000:(Lorg/springframework/security/web/util/OnCommittedResponseWrapper;)V
      16: aload_0
      17: getfield      #3                  // Field delegate:Ljavax/servlet/ServletOutputStream;
      20: lload_1
      21: invokevirtual #30                 // Method javax/servlet/ServletOutputStream.println:(J)V
      24: return

  public void println(java.lang.String) throws java.io.IOException;
    Code:
       0: aload_0
       1: getfield      #1                  // Field this$0:Lorg/springframework/security/web/util/OnCommittedResponseWrapper;
       4: aload_1
       5: invokestatic  #21                 // Method org/springframework/security/web/util/OnCommittedResponseWrapper.access$400:(Lorg/springframework/security/web/util/OnCommittedResponseWrapper;Ljava/lang/String;)V
       8: aload_0
       9: getfield      #1                  // Field this$0:Lorg/springframework/security/web/util/OnCommittedResponseWrapper;
      12: invokestatic  #23                 // Method org/springframework/security/web/util/OnCommittedResponseWrapper.access$1000:(Lorg/springframework/security/web/util/OnCommittedResponseWrapper;)V
      15: aload_0
      16: getfield      #3                  // Field delegate:Ljavax/servlet/ServletOutputStream;
      19: aload_1
      20: invokevirtual #31                 // Method javax/servlet/ServletOutputStream.println:(Ljava/lang/String;)V
      23: return

  public void write(byte[]) throws java.io.IOException;
    Code:
       0: aload_0
       1: getfield      #1                  // Field this$0:Lorg/springframework/security/web/util/OnCommittedResponseWrapper;
       4: aload_1
       5: invokestatic  #32                 // Method org/springframework/security/web/util/OnCommittedResponseWrapper.access$1100:(Lorg/springframework/security/web/util/OnCommittedResponseWrapper;[B)V
       8: aload_0
       9: getfield      #3                  // Field delegate:Ljavax/servlet/ServletOutputStream;
      12: aload_1
      13: invokevirtual #33                 // Method javax/servlet/ServletOutputStream.write:([B)V
      16: return

  public void write(byte[], int, int) throws java.io.IOException;
    Code:
       0: aload_0
       1: getfield      #1                  // Field this$0:Lorg/springframework/security/web/util/OnCommittedResponseWrapper;
       4: iload_3
       5: i2l
       6: invokestatic  #34                 // Method org/springframework/security/web/util/OnCommittedResponseWrapper.access$200:(Lorg/springframework/security/web/util/OnCommittedResponseWrapper;J)V
       9: aload_0
      10: getfield      #3                  // Field delegate:Ljavax/servlet/ServletOutputStream;
      13: aload_1
      14: iload_2
      15: iload_3
      16: invokevirtual #35                 // Method javax/servlet/ServletOutputStream.write:([BII)V
      19: return

  public boolean isReady();
    Code:
       0: aload_0
       1: getfield      #3                  // Field delegate:Ljavax/servlet/ServletOutputStream;
       4: invokevirtual #36                 // Method javax/servlet/ServletOutputStream.isReady:()Z
       7: ireturn

  public void setWriteListener(javax.servlet.WriteListener);
    Code:
       0: aload_0
       1: getfield      #3                  // Field delegate:Ljavax/servlet/ServletOutputStream;
       4: aload_1
       5: invokevirtual #37                 // Method javax/servlet/ServletOutputStream.setWriteListener:(Ljavax/servlet/WriteListener;)V
       8: return

  public java.lang.String toString();
    Code:
       0: new           #38                 // class java/lang/StringBuilder
       3: dup
       4: invokespecial #39                 // Method java/lang/StringBuilder."<init>":()V
       7: aload_0
       8: invokevirtual #40                 // Method java/lang/Object.getClass:()Ljava/lang/Class;
      11: invokevirtual #41                 // Method java/lang/Class.getName:()Ljava/lang/String;
      14: invokevirtual #42                 // Method java/lang/StringBuilder.append:(Ljava/lang/String;)Ljava/lang/StringBuilder;
      17: ldc           #43                 // String [delegate=
      19: invokevirtual #42                 // Method java/lang/StringBuilder.append:(Ljava/lang/String;)Ljava/lang/StringBuilder;
      22: aload_0
      23: getfield      #3                  // Field delegate:Ljavax/servlet/ServletOutputStream;
      26: invokevirtual #44                 // Method java/lang/Object.toString:()Ljava/lang/String;
      29: invokevirtual #42                 // Method java/lang/StringBuilder.append:(Ljava/lang/String;)Ljava/lang/StringBuilder;
      32: ldc           #45                 // String ]
      34: invokevirtual #42                 // Method java/lang/StringBuilder.append:(Ljava/lang/String;)Ljava/lang/StringBuilder;
      37: invokevirtual #46                 // Method java/lang/StringBuilder.toString:()Ljava/lang/String;
      40: areturn
}
