Compiled from "ThrowableAnalyzer.java"
public class org.springframework.security.web.util.ThrowableAnalyzer {
  public static final org.springframework.security.web.util.ThrowableCauseExtractor DEFAULT_EXTRACTOR;

  public static final org.springframework.security.web.util.ThrowableCauseExtractor INVOCATIONTARGET_EXTRACTOR;

  private static final java.util.Comparator<java.lang.Class<? extends java.lang.Throwable>> CLASS_HIERARCHY_COMPARATOR;

  private final java.util.Map<java.lang.Class<? extends java.lang.Throwable>, org.springframework.security.web.util.ThrowableCauseExtractor> extractorMap;

  public org.springframework.security.web.util.ThrowableAnalyzer();
    Code:
       0: aload_0
       1: invokespecial #1                  // Method java/lang/Object."<init>":()V
       4: aload_0
       5: new           #2                  // class java/util/TreeMap
       8: dup
       9: getstatic     #3                  // Field CLASS_HIERARCHY_COMPARATOR:Ljava/util/Comparator;
      12: invokespecial #4                  // Method java/util/TreeMap."<init>":(Ljava/util/Comparator;)V
      15: putfield      #5                  // Field extractorMap:Ljava/util/Map;
      18: aload_0
      19: invokevirtual #6                  // Method initExtractorMap:()V
      22: return

  protected final void registerExtractor(java.lang.Class<? extends java.lang.Throwable>, org.springframework.security.web.util.ThrowableCauseExtractor);
    Code:
       0: aload_2
       1: ldc           #7                  // String Invalid extractor: null
       3: invokestatic  #8                  // Method org/springframework/util/Assert.notNull:(Ljava/lang/Object;Ljava/lang/String;)V
       6: aload_0
       7: getfield      #5                  // Field extractorMap:Ljava/util/Map;
      10: aload_1
      11: aload_2
      12: invokeinterface #9,  3            // InterfaceMethod java/util/Map.put:(Ljava/lang/Object;Ljava/lang/Object;)Ljava/lang/Object;
      17: pop
      18: return

  protected void initExtractorMap();
    Code:
       0: aload_0
       1: ldc           #10                 // class java/lang/reflect/InvocationTargetException
       3: getstatic     #11                 // Field INVOCATIONTARGET_EXTRACTOR:Lorg/springframework/security/web/util/ThrowableCauseExtractor;
       6: invokevirtual #12                 // Method registerExtractor:(Ljava/lang/Class;Lorg/springframework/security/web/util/ThrowableCauseExtractor;)V
       9: aload_0
      10: ldc           #13                 // class java/lang/Throwable
      12: getstatic     #14                 // Field DEFAULT_EXTRACTOR:Lorg/springframework/security/web/util/ThrowableCauseExtractor;
      15: invokevirtual #12                 // Method registerExtractor:(Ljava/lang/Class;Lorg/springframework/security/web/util/ThrowableCauseExtractor;)V
      18: return

  final java.lang.Class<? extends java.lang.Throwable>[] getRegisteredTypes();
    Code:
       0: aload_0
       1: getfield      #5                  // Field extractorMap:Ljava/util/Map;
       4: invokeinterface #15,  1           // InterfaceMethod java/util/Map.keySet:()Ljava/util/Set;
       9: astore_1
      10: aload_1
      11: aload_1
      12: invokeinterface #16,  1           // InterfaceMethod java/util/Set.size:()I
      17: anewarray     #17                 // class java/lang/Class
      20: invokeinterface #18,  2           // InterfaceMethod java/util/Set.toArray:([Ljava/lang/Object;)[Ljava/lang/Object;
      25: checkcast     #19                 // class "[Ljava/lang/Class;"
      28: areturn

  public final java.lang.Throwable[] determineCauseChain(java.lang.Throwable);
    Code:
       0: aload_1
       1: ifnonnull     14
       4: new           #20                 // class java/lang/IllegalArgumentException
       7: dup
       8: ldc           #21                 // String Invalid throwable: null
      10: invokespecial #22                 // Method java/lang/IllegalArgumentException."<init>":(Ljava/lang/String;)V
      13: athrow
      14: new           #23                 // class java/util/ArrayList
      17: dup
      18: invokespecial #24                 // Method java/util/ArrayList."<init>":()V
      21: astore_2
      22: aload_1
      23: astore_3
      24: aload_3
      25: ifnull        45
      28: aload_2
      29: aload_3
      30: invokeinterface #25,  2           // InterfaceMethod java/util/List.add:(Ljava/lang/Object;)Z
      35: pop
      36: aload_0
      37: aload_3
      38: invokespecial #26                 // Method extractCause:(Ljava/lang/Throwable;)Ljava/lang/Throwable;
      41: astore_3
      42: goto          24
      45: aload_2
      46: aload_2
      47: invokeinterface #27,  1           // InterfaceMethod java/util/List.size:()I
      52: anewarray     #13                 // class java/lang/Throwable
      55: invokeinterface #28,  2           // InterfaceMethod java/util/List.toArray:([Ljava/lang/Object;)[Ljava/lang/Object;
      60: checkcast     #29                 // class "[Ljava/lang/Throwable;"
      63: areturn

  private java.lang.Throwable extractCause(java.lang.Throwable);
    Code:
       0: aload_0
       1: getfield      #5                  // Field extractorMap:Ljava/util/Map;
       4: invokeinterface #30,  1           // InterfaceMethod java/util/Map.entrySet:()Ljava/util/Set;
       9: invokeinterface #31,  1           // InterfaceMethod java/util/Set.iterator:()Ljava/util/Iterator;
      14: astore_2
      15: aload_2
      16: invokeinterface #32,  1           // InterfaceMethod java/util/Iterator.hasNext:()Z
      21: ifeq          77
      24: aload_2
      25: invokeinterface #33,  1           // InterfaceMethod java/util/Iterator.next:()Ljava/lang/Object;
      30: checkcast     #34                 // class java/util/Map$Entry
      33: astore_3
      34: aload_3
      35: invokeinterface #35,  1           // InterfaceMethod java/util/Map$Entry.getKey:()Ljava/lang/Object;
      40: checkcast     #17                 // class java/lang/Class
      43: astore        4
      45: aload         4
      47: aload_1
      48: invokevirtual #36                 // Method java/lang/Class.isInstance:(Ljava/lang/Object;)Z
      51: ifeq          74
      54: aload_3
      55: invokeinterface #37,  1           // InterfaceMethod java/util/Map$Entry.getValue:()Ljava/lang/Object;
      60: checkcast     #38                 // class org/springframework/security/web/util/ThrowableCauseExtractor
      63: astore        5
      65: aload         5
      67: aload_1
      68: invokeinterface #39,  2           // InterfaceMethod org/springframework/security/web/util/ThrowableCauseExtractor.extractCause:(Ljava/lang/Throwable;)Ljava/lang/Throwable;
      73: areturn
      74: goto          15
      77: aconst_null
      78: areturn

  public final java.lang.Throwable getFirstThrowableOfType(java.lang.Class<? extends java.lang.Throwable>, java.lang.Throwable[]);
    Code:
       0: aload_2
       1: ifnull        49
       4: aload_2
       5: astore_3
       6: aload_3
       7: arraylength
       8: istore        4
      10: iconst_0
      11: istore        5
      13: iload         5
      15: iload         4
      17: if_icmpge     49
      20: aload_3
      21: iload         5
      23: aaload
      24: astore        6
      26: aload         6
      28: ifnull        43
      31: aload_1
      32: aload         6
      34: invokevirtual #36                 // Method java/lang/Class.isInstance:(Ljava/lang/Object;)Z
      37: ifeq          43
      40: aload         6
      42: areturn
      43: iinc          5, 1
      46: goto          13
      49: aconst_null
      50: areturn

  public static void verifyThrowableHierarchy(java.lang.Throwable, java.lang.Class<? extends java.lang.Throwable>);
    Code:
       0: aload_1
       1: ifnonnull     5
       4: return
       5: aload_0
       6: ifnonnull     19
       9: new           #20                 // class java/lang/IllegalArgumentException
      12: dup
      13: ldc           #21                 // String Invalid throwable: null
      15: invokespecial #22                 // Method java/lang/IllegalArgumentException."<init>":(Ljava/lang/String;)V
      18: athrow
      19: aload_0
      20: invokevirtual #40                 // Method java/lang/Object.getClass:()Ljava/lang/Class;
      23: astore_2
      24: aload_1
      25: aload_2
      26: invokevirtual #41                 // Method java/lang/Class.isAssignableFrom:(Ljava/lang/Class;)Z
      29: ifne          79
      32: new           #20                 // class java/lang/IllegalArgumentException
      35: dup
      36: new           #42                 // class java/lang/StringBuilder
      39: dup
      40: invokespecial #43                 // Method java/lang/StringBuilder."<init>":()V
      43: ldc           #44                 // String Invalid type: \'
      45: invokevirtual #45                 // Method java/lang/StringBuilder.append:(Ljava/lang/String;)Ljava/lang/StringBuilder;
      48: aload_2
      49: invokevirtual #46                 // Method java/lang/Class.getName:()Ljava/lang/String;
      52: invokevirtual #45                 // Method java/lang/StringBuilder.append:(Ljava/lang/String;)Ljava/lang/StringBuilder;
      55: ldc           #47                 // String \'. Has to be a subclass of \'
      57: invokevirtual #45                 // Method java/lang/StringBuilder.append:(Ljava/lang/String;)Ljava/lang/StringBuilder;
      60: aload_1
      61: invokevirtual #46                 // Method java/lang/Class.getName:()Ljava/lang/String;
      64: invokevirtual #45                 // Method java/lang/StringBuilder.append:(Ljava/lang/String;)Ljava/lang/StringBuilder;
      67: ldc           #48                 // String \'
      69: invokevirtual #45                 // Method java/lang/StringBuilder.append:(Ljava/lang/String;)Ljava/lang/StringBuilder;
      72: invokevirtual #49                 // Method java/lang/StringBuilder.toString:()Ljava/lang/String;
      75: invokespecial #22                 // Method java/lang/IllegalArgumentException."<init>":(Ljava/lang/String;)V
      78: athrow
      79: return

  static {};
    Code:
       0: new           #50                 // class org/springframework/security/web/util/ThrowableAnalyzer$1
       3: dup
       4: invokespecial #51                 // Method org/springframework/security/web/util/ThrowableAnalyzer$1."<init>":()V
       7: putstatic     #14                 // Field DEFAULT_EXTRACTOR:Lorg/springframework/security/web/util/ThrowableCauseExtractor;
      10: new           #52                 // class org/springframework/security/web/util/ThrowableAnalyzer$2
      13: dup
      14: invokespecial #53                 // Method org/springframework/security/web/util/ThrowableAnalyzer$2."<init>":()V
      17: putstatic     #11                 // Field INVOCATIONTARGET_EXTRACTOR:Lorg/springframework/security/web/util/ThrowableCauseExtractor;
      20: new           #54                 // class org/springframework/security/web/util/ThrowableAnalyzer$3
      23: dup
      24: invokespecial #55                 // Method org/springframework/security/web/util/ThrowableAnalyzer$3."<init>":()V
      27: putstatic     #3                  // Field CLASS_HIERARCHY_COMPARATOR:Ljava/util/Comparator;
      30: return
}
