Compiled from "EntityArrays.java"
public class net.logstash.logback.encoder.org.apache.commons.lang3.text.translate.EntityArrays {
  private static final java.lang.String[][] ISO8859_1_ESCAPE;

  private static final java.lang.String[][] ISO8859_1_UNESCAPE;

  private static final java.lang.String[][] HTML40_EXTENDED_ESCAPE;

  private static final java.lang.String[][] HTML40_EXTENDED_UNESCAPE;

  private static final java.lang.String[][] BASIC_ESCAPE;

  private static final java.lang.String[][] BASIC_UNESCAPE;

  private static final java.lang.String[][] APOS_ESCAPE;

  private static final java.lang.String[][] APOS_UNESCAPE;

  private static final java.lang.String[][] JAVA_CTRL_CHARS_ESCAPE;

  private static final java.lang.String[][] JAVA_CTRL_CHARS_UNESCAPE;

  public net.logstash.logback.encoder.org.apache.commons.lang3.text.translate.EntityArrays();
    Code:
       0: aload_0
       1: invokespecial #21                 // Method java/lang/Object."<init>":()V
       4: return

  public static java.lang.String[][] ISO8859_1_ESCAPE();
    Code:
       0: getstatic     #26                 // Field ISO8859_1_ESCAPE:[[Ljava/lang/String;
       3: invokevirtual #31                 // Method "[[Ljava/lang/String;".clone:()Ljava/lang/Object;
       6: checkcast     #27                 // class "[[Ljava/lang/String;"
       9: areturn

  public static java.lang.String[][] ISO8859_1_UNESCAPE();
    Code:
       0: getstatic     #33                 // Field ISO8859_1_UNESCAPE:[[Ljava/lang/String;
       3: invokevirtual #31                 // Method "[[Ljava/lang/String;".clone:()Ljava/lang/Object;
       6: checkcast     #27                 // class "[[Ljava/lang/String;"
       9: areturn

  public static java.lang.String[][] HTML40_EXTENDED_ESCAPE();
    Code:
       0: getstatic     #35                 // Field HTML40_EXTENDED_ESCAPE:[[Ljava/lang/String;
       3: invokevirtual #31                 // Method "[[Ljava/lang/String;".clone:()Ljava/lang/Object;
       6: checkcast     #27                 // class "[[Ljava/lang/String;"
       9: areturn

  public static java.lang.String[][] HTML40_EXTENDED_UNESCAPE();
    Code:
       0: getstatic     #37                 // Field HTML40_EXTENDED_UNESCAPE:[[Ljava/lang/String;
       3: invokevirtual #31                 // Method "[[Ljava/lang/String;".clone:()Ljava/lang/Object;
       6: checkcast     #27                 // class "[[Ljava/lang/String;"
       9: areturn

  public static java.lang.String[][] BASIC_ESCAPE();
    Code:
       0: getstatic     #39                 // Field BASIC_ESCAPE:[[Ljava/lang/String;
       3: invokevirtual #31                 // Method "[[Ljava/lang/String;".clone:()Ljava/lang/Object;
       6: checkcast     #27                 // class "[[Ljava/lang/String;"
       9: areturn

  public static java.lang.String[][] BASIC_UNESCAPE();
    Code:
       0: getstatic     #41                 // Field BASIC_UNESCAPE:[[Ljava/lang/String;
       3: invokevirtual #31                 // Method "[[Ljava/lang/String;".clone:()Ljava/lang/Object;
       6: checkcast     #27                 // class "[[Ljava/lang/String;"
       9: areturn

  public static java.lang.String[][] APOS_ESCAPE();
    Code:
       0: getstatic     #43                 // Field APOS_ESCAPE:[[Ljava/lang/String;
       3: invokevirtual #31                 // Method "[[Ljava/lang/String;".clone:()Ljava/lang/Object;
       6: checkcast     #27                 // class "[[Ljava/lang/String;"
       9: areturn

  public static java.lang.String[][] APOS_UNESCAPE();
    Code:
       0: getstatic     #45                 // Field APOS_UNESCAPE:[[Ljava/lang/String;
       3: invokevirtual #31                 // Method "[[Ljava/lang/String;".clone:()Ljava/lang/Object;
       6: checkcast     #27                 // class "[[Ljava/lang/String;"
       9: areturn

  public static java.lang.String[][] JAVA_CTRL_CHARS_ESCAPE();
    Code:
       0: getstatic     #47                 // Field JAVA_CTRL_CHARS_ESCAPE:[[Ljava/lang/String;
       3: invokevirtual #31                 // Method "[[Ljava/lang/String;".clone:()Ljava/lang/Object;
       6: checkcast     #27                 // class "[[Ljava/lang/String;"
       9: areturn

  public static java.lang.String[][] JAVA_CTRL_CHARS_UNESCAPE();
    Code:
       0: getstatic     #49                 // Field JAVA_CTRL_CHARS_UNESCAPE:[[Ljava/lang/String;
       3: invokevirtual #31                 // Method "[[Ljava/lang/String;".clone:()Ljava/lang/Object;
       6: checkcast     #27                 // class "[[Ljava/lang/String;"
       9: areturn

  public static java.lang.String[][] invert(java.lang.String[][]);
    Code:
       0: aload_0
       1: arraylength
       2: iconst_2
       3: multianewarray #27,  2            // class "[[Ljava/lang/String;"
       7: astore_1
       8: iconst_0
       9: istore_2
      10: iload_2
      11: aload_0
      12: arraylength
      13: if_icmpge     42
      16: aload_1
      17: iload_2
      18: aaload
      19: iconst_0
      20: aload_0
      21: iload_2
      22: aaload
      23: iconst_1
      24: aaload
      25: aastore
      26: aload_1
      27: iload_2
      28: aaload
      29: iconst_1
      30: aload_0
      31: iload_2
      32: aaload
      33: iconst_0
      34: aaload
      35: aastore
      36: iinc          2, 1
      39: goto          10
      42: aload_1
      43: areturn

  static {};
    Code:
       0: bipush        96
       2: anewarray     #58                 // class "[Ljava/lang/String;"
       5: dup
       6: iconst_0
       7: iconst_2
       8: anewarray     #60                 // class java/lang/String
      11: dup
      12: iconst_0
      13: ldc           #62                 // String  
      15: aastore
      16: dup
      17: iconst_1
      18: ldc           #64                 // String &nbsp;
      20: aastore
      21: aastore
      22: dup
      23: iconst_1
      24: iconst_2
      25: anewarray     #60                 // class java/lang/String
      28: dup
      29: iconst_0
      30: ldc           #66                 // String ¡
      32: aastore
      33: dup
      34: iconst_1
      35: ldc           #68                 // String &iexcl;
      37: aastore
      38: aastore
      39: dup
      40: iconst_2
      41: iconst_2
      42: anewarray     #60                 // class java/lang/String
      45: dup
      46: iconst_0
      47: ldc           #70                 // String ¢
      49: aastore
      50: dup
      51: iconst_1
      52: ldc           #72                 // String &cent;
      54: aastore
      55: aastore
      56: dup
      57: iconst_3
      58: iconst_2
      59: anewarray     #60                 // class java/lang/String
      62: dup
      63: iconst_0
      64: ldc           #74                 // String £
      66: aastore
      67: dup
      68: iconst_1
      69: ldc           #76                 // String &pound;
      71: aastore
      72: aastore
      73: dup
      74: iconst_4
      75: iconst_2
      76: anewarray     #60                 // class java/lang/String
      79: dup
      80: iconst_0
      81: ldc           #78                 // String ¤
      83: aastore
      84: dup
      85: iconst_1
      86: ldc           #80                 // String &curren;
      88: aastore
      89: aastore
      90: dup
      91: iconst_5
      92: iconst_2
      93: anewarray     #60                 // class java/lang/String
      96: dup
      97: iconst_0
      98: ldc           #82                 // String ¥
     100: aastore
     101: dup
     102: iconst_1
     103: ldc           #84                 // String &yen;
     105: aastore
     106: aastore
     107: dup
     108: bipush        6
     110: iconst_2
     111: anewarray     #60                 // class java/lang/String
     114: dup
     115: iconst_0
     116: ldc           #86                 // String ¦
     118: aastore
     119: dup
     120: iconst_1
     121: ldc           #88                 // String &brvbar;
     123: aastore
     124: aastore
     125: dup
     126: bipush        7
     128: iconst_2
     129: anewarray     #60                 // class java/lang/String
     132: dup
     133: iconst_0
     134: ldc           #90                 // String §
     136: aastore
     137: dup
     138: iconst_1
     139: ldc           #92                 // String &sect;
     141: aastore
     142: aastore
     143: dup
     144: bipush        8
     146: iconst_2
     147: anewarray     #60                 // class java/lang/String
     150: dup
     151: iconst_0
     152: ldc           #94                 // String ¨
     154: aastore
     155: dup
     156: iconst_1
     157: ldc           #96                 // String &uml;
     159: aastore
     160: aastore
     161: dup
     162: bipush        9
     164: iconst_2
     165: anewarray     #60                 // class java/lang/String
     168: dup
     169: iconst_0
     170: ldc           #98                 // String ©
     172: aastore
     173: dup
     174: iconst_1
     175: ldc           #100                // String &copy;
     177: aastore
     178: aastore
     179: dup
     180: bipush        10
     182: iconst_2
     183: anewarray     #60                 // class java/lang/String
     186: dup
     187: iconst_0
     188: ldc           #102                // String ª
     190: aastore
     191: dup
     192: iconst_1
     193: ldc           #104                // String &ordf;
     195: aastore
     196: aastore
     197: dup
     198: bipush        11
     200: iconst_2
     201: anewarray     #60                 // class java/lang/String
     204: dup
     205: iconst_0
     206: ldc           #106                // String «
     208: aastore
     209: dup
     210: iconst_1
     211: ldc           #108                // String &laquo;
     213: aastore
     214: aastore
     215: dup
     216: bipush        12
     218: iconst_2
     219: anewarray     #60                 // class java/lang/String
     222: dup
     223: iconst_0
     224: ldc           #110                // String ¬
     226: aastore
     227: dup
     228: iconst_1
     229: ldc           #112                // String &not;
     231: aastore
     232: aastore
     233: dup
     234: bipush        13
     236: iconst_2
     237: anewarray     #60                 // class java/lang/String
     240: dup
     241: iconst_0
     242: ldc           #114                // String ­
     244: aastore
     245: dup
     246: iconst_1
     247: ldc           #116                // String &shy;
     249: aastore
     250: aastore
     251: dup
     252: bipush        14
     254: iconst_2
     255: anewarray     #60                 // class java/lang/String
     258: dup
     259: iconst_0
     260: ldc           #118                // String ®
     262: aastore
     263: dup
     264: iconst_1
     265: ldc           #120                // String &reg;
     267: aastore
     268: aastore
     269: dup
     270: bipush        15
     272: iconst_2
     273: anewarray     #60                 // class java/lang/String
     276: dup
     277: iconst_0
     278: ldc           #122                // String ¯
     280: aastore
     281: dup
     282: iconst_1
     283: ldc           #124                // String &macr;
     285: aastore
     286: aastore
     287: dup
     288: bipush        16
     290: iconst_2
     291: anewarray     #60                 // class java/lang/String
     294: dup
     295: iconst_0
     296: ldc           #126                // String °
     298: aastore
     299: dup
     300: iconst_1
     301: ldc           #128                // String &deg;
     303: aastore
     304: aastore
     305: dup
     306: bipush        17
     308: iconst_2
     309: anewarray     #60                 // class java/lang/String
     312: dup
     313: iconst_0
     314: ldc           #130                // String ±
     316: aastore
     317: dup
     318: iconst_1
     319: ldc           #132                // String &plusmn;
     321: aastore
     322: aastore
     323: dup
     324: bipush        18
     326: iconst_2
     327: anewarray     #60                 // class java/lang/String
     330: dup
     331: iconst_0
     332: ldc           #134                // String ²
     334: aastore
     335: dup
     336: iconst_1
     337: ldc           #136                // String &sup2;
     339: aastore
     340: aastore
     341: dup
     342: bipush        19
     344: iconst_2
     345: anewarray     #60                 // class java/lang/String
     348: dup
     349: iconst_0
     350: ldc           #138                // String ³
     352: aastore
     353: dup
     354: iconst_1
     355: ldc           #140                // String &sup3;
     357: aastore
     358: aastore
     359: dup
     360: bipush        20
     362: iconst_2
     363: anewarray     #60                 // class java/lang/String
     366: dup
     367: iconst_0
     368: ldc           #142                // String ´
     370: aastore
     371: dup
     372: iconst_1
     373: ldc           #144                // String &acute;
     375: aastore
     376: aastore
     377: dup
     378: bipush        21
     380: iconst_2
     381: anewarray     #60                 // class java/lang/String
     384: dup
     385: iconst_0
     386: ldc           #146                // String µ
     388: aastore
     389: dup
     390: iconst_1
     391: ldc           #148                // String &micro;
     393: aastore
     394: aastore
     395: dup
     396: bipush        22
     398: iconst_2
     399: anewarray     #60                 // class java/lang/String
     402: dup
     403: iconst_0
     404: ldc           #150                // String ¶
     406: aastore
     407: dup
     408: iconst_1
     409: ldc           #152                // String &para;
     411: aastore
     412: aastore
     413: dup
     414: bipush        23
     416: iconst_2
     417: anewarray     #60                 // class java/lang/String
     420: dup
     421: iconst_0
     422: ldc           #154                // String ·
     424: aastore
     425: dup
     426: iconst_1
     427: ldc           #156                // String &middot;
     429: aastore
     430: aastore
     431: dup
     432: bipush        24
     434: iconst_2
     435: anewarray     #60                 // class java/lang/String
     438: dup
     439: iconst_0
     440: ldc           #158                // String ¸
     442: aastore
     443: dup
     444: iconst_1
     445: ldc           #160                // String &cedil;
     447: aastore
     448: aastore
     449: dup
     450: bipush        25
     452: iconst_2
     453: anewarray     #60                 // class java/lang/String
     456: dup
     457: iconst_0
     458: ldc           #162                // String ¹
     460: aastore
     461: dup
     462: iconst_1
     463: ldc           #164                // String &sup1;
     465: aastore
     466: aastore
     467: dup
     468: bipush        26
     470: iconst_2
     471: anewarray     #60                 // class java/lang/String
     474: dup
     475: iconst_0
     476: ldc           #166                // String º
     478: aastore
     479: dup
     480: iconst_1
     481: ldc           #168                // String &ordm;
     483: aastore
     484: aastore
     485: dup
     486: bipush        27
     488: iconst_2
     489: anewarray     #60                 // class java/lang/String
     492: dup
     493: iconst_0
     494: ldc           #170                // String »
     496: aastore
     497: dup
     498: iconst_1
     499: ldc           #172                // String &raquo;
     501: aastore
     502: aastore
     503: dup
     504: bipush        28
     506: iconst_2
     507: anewarray     #60                 // class java/lang/String
     510: dup
     511: iconst_0
     512: ldc           #174                // String ¼
     514: aastore
     515: dup
     516: iconst_1
     517: ldc           #176                // String &frac14;
     519: aastore
     520: aastore
     521: dup
     522: bipush        29
     524: iconst_2
     525: anewarray     #60                 // class java/lang/String
     528: dup
     529: iconst_0
     530: ldc           #178                // String ½
     532: aastore
     533: dup
     534: iconst_1
     535: ldc           #180                // String &frac12;
     537: aastore
     538: aastore
     539: dup
     540: bipush        30
     542: iconst_2
     543: anewarray     #60                 // class java/lang/String
     546: dup
     547: iconst_0
     548: ldc           #182                // String ¾
     550: aastore
     551: dup
     552: iconst_1
     553: ldc           #184                // String &frac34;
     555: aastore
     556: aastore
     557: dup
     558: bipush        31
     560: iconst_2
     561: anewarray     #60                 // class java/lang/String
     564: dup
     565: iconst_0
     566: ldc           #186                // String ¿
     568: aastore
     569: dup
     570: iconst_1
     571: ldc           #188                // String &iquest;
     573: aastore
     574: aastore
     575: dup
     576: bipush        32
     578: iconst_2
     579: anewarray     #60                 // class java/lang/String
     582: dup
     583: iconst_0
     584: ldc           #190                // String À
     586: aastore
     587: dup
     588: iconst_1
     589: ldc           #192                // String &Agrave;
     591: aastore
     592: aastore
     593: dup
     594: bipush        33
     596: iconst_2
     597: anewarray     #60                 // class java/lang/String
     600: dup
     601: iconst_0
     602: ldc           #194                // String Á
     604: aastore
     605: dup
     606: iconst_1
     607: ldc           #196                // String &Aacute;
     609: aastore
     610: aastore
     611: dup
     612: bipush        34
     614: iconst_2
     615: anewarray     #60                 // class java/lang/String
     618: dup
     619: iconst_0
     620: ldc           #198                // String Â
     622: aastore
     623: dup
     624: iconst_1
     625: ldc           #200                // String &Acirc;
     627: aastore
     628: aastore
     629: dup
     630: bipush        35
     632: iconst_2
     633: anewarray     #60                 // class java/lang/String
     636: dup
     637: iconst_0
     638: ldc           #202                // String Ã
     640: aastore
     641: dup
     642: iconst_1
     643: ldc           #204                // String &Atilde;
     645: aastore
     646: aastore
     647: dup
     648: bipush        36
     650: iconst_2
     651: anewarray     #60                 // class java/lang/String
     654: dup
     655: iconst_0
     656: ldc           #206                // String Ä
     658: aastore
     659: dup
     660: iconst_1
     661: ldc           #208                // String &Auml;
     663: aastore
     664: aastore
     665: dup
     666: bipush        37
     668: iconst_2
     669: anewarray     #60                 // class java/lang/String
     672: dup
     673: iconst_0
     674: ldc           #210                // String Å
     676: aastore
     677: dup
     678: iconst_1
     679: ldc           #212                // String &Aring;
     681: aastore
     682: aastore
     683: dup
     684: bipush        38
     686: iconst_2
     687: anewarray     #60                 // class java/lang/String
     690: dup
     691: iconst_0
     692: ldc           #214                // String Æ
     694: aastore
     695: dup
     696: iconst_1
     697: ldc           #216                // String &AElig;
     699: aastore
     700: aastore
     701: dup
     702: bipush        39
     704: iconst_2
     705: anewarray     #60                 // class java/lang/String
     708: dup
     709: iconst_0
     710: ldc           #218                // String Ç
     712: aastore
     713: dup
     714: iconst_1
     715: ldc           #220                // String &Ccedil;
     717: aastore
     718: aastore
     719: dup
     720: bipush        40
     722: iconst_2
     723: anewarray     #60                 // class java/lang/String
     726: dup
     727: iconst_0
     728: ldc           #222                // String È
     730: aastore
     731: dup
     732: iconst_1
     733: ldc           #224                // String &Egrave;
     735: aastore
     736: aastore
     737: dup
     738: bipush        41
     740: iconst_2
     741: anewarray     #60                 // class java/lang/String
     744: dup
     745: iconst_0
     746: ldc           #226                // String É
     748: aastore
     749: dup
     750: iconst_1
     751: ldc           #228                // String &Eacute;
     753: aastore
     754: aastore
     755: dup
     756: bipush        42
     758: iconst_2
     759: anewarray     #60                 // class java/lang/String
     762: dup
     763: iconst_0
     764: ldc           #230                // String Ê
     766: aastore
     767: dup
     768: iconst_1
     769: ldc           #232                // String &Ecirc;
     771: aastore
     772: aastore
     773: dup
     774: bipush        43
     776: iconst_2
     777: anewarray     #60                 // class java/lang/String
     780: dup
     781: iconst_0
     782: ldc           #234                // String Ë
     784: aastore
     785: dup
     786: iconst_1
     787: ldc           #236                // String &Euml;
     789: aastore
     790: aastore
     791: dup
     792: bipush        44
     794: iconst_2
     795: anewarray     #60                 // class java/lang/String
     798: dup
     799: iconst_0
     800: ldc           #238                // String Ì
     802: aastore
     803: dup
     804: iconst_1
     805: ldc           #240                // String &Igrave;
     807: aastore
     808: aastore
     809: dup
     810: bipush        45
     812: iconst_2
     813: anewarray     #60                 // class java/lang/String
     816: dup
     817: iconst_0
     818: ldc           #242                // String Í
     820: aastore
     821: dup
     822: iconst_1
     823: ldc           #244                // String &Iacute;
     825: aastore
     826: aastore
     827: dup
     828: bipush        46
     830: iconst_2
     831: anewarray     #60                 // class java/lang/String
     834: dup
     835: iconst_0
     836: ldc           #246                // String Î
     838: aastore
     839: dup
     840: iconst_1
     841: ldc           #248                // String &Icirc;
     843: aastore
     844: aastore
     845: dup
     846: bipush        47
     848: iconst_2
     849: anewarray     #60                 // class java/lang/String
     852: dup
     853: iconst_0
     854: ldc           #250                // String Ï
     856: aastore
     857: dup
     858: iconst_1
     859: ldc           #252                // String &Iuml;
     861: aastore
     862: aastore
     863: dup
     864: bipush        48
     866: iconst_2
     867: anewarray     #60                 // class java/lang/String
     870: dup
     871: iconst_0
     872: ldc           #254                // String Ð
     874: aastore
     875: dup
     876: iconst_1
     877: ldc_w         #256                // String &ETH;
     880: aastore
     881: aastore
     882: dup
     883: bipush        49
     885: iconst_2
     886: anewarray     #60                 // class java/lang/String
     889: dup
     890: iconst_0
     891: ldc_w         #258                // String Ñ
     894: aastore
     895: dup
     896: iconst_1
     897: ldc_w         #260                // String &Ntilde;
     900: aastore
     901: aastore
     902: dup
     903: bipush        50
     905: iconst_2
     906: anewarray     #60                 // class java/lang/String
     909: dup
     910: iconst_0
     911: ldc_w         #262                // String Ò
     914: aastore
     915: dup
     916: iconst_1
     917: ldc_w         #264                // String &Ograve;
     920: aastore
     921: aastore
     922: dup
     923: bipush        51
     925: iconst_2
     926: anewarray     #60                 // class java/lang/String
     929: dup
     930: iconst_0
     931: ldc_w         #266                // String Ó
     934: aastore
     935: dup
     936: iconst_1
     937: ldc_w         #268                // String &Oacute;
     940: aastore
     941: aastore
     942: dup
     943: bipush        52
     945: iconst_2
     946: anewarray     #60                 // class java/lang/String
     949: dup
     950: iconst_0
     951: ldc_w         #270                // String Ô
     954: aastore
     955: dup
     956: iconst_1
     957: ldc_w         #272                // String &Ocirc;
     960: aastore
     961: aastore
     962: dup
     963: bipush        53
     965: iconst_2
     966: anewarray     #60                 // class java/lang/String
     969: dup
     970: iconst_0
     971: ldc_w         #274                // String Õ
     974: aastore
     975: dup
     976: iconst_1
     977: ldc_w         #276                // String &Otilde;
     980: aastore
     981: aastore
     982: dup
     983: bipush        54
     985: iconst_2
     986: anewarray     #60                 // class java/lang/String
     989: dup
     990: iconst_0
     991: ldc_w         #278                // String Ö
     994: aastore
     995: dup
     996: iconst_1
     997: ldc_w         #280                // String &Ouml;
    1000: aastore
    1001: aastore
    1002: dup
    1003: bipush        55
    1005: iconst_2
    1006: anewarray     #60                 // class java/lang/String
    1009: dup
    1010: iconst_0
    1011: ldc_w         #282                // String ×
    1014: aastore
    1015: dup
    1016: iconst_1
    1017: ldc_w         #284                // String &times;
    1020: aastore
    1021: aastore
    1022: dup
    1023: bipush        56
    1025: iconst_2
    1026: anewarray     #60                 // class java/lang/String
    1029: dup
    1030: iconst_0
    1031: ldc_w         #286                // String Ø
    1034: aastore
    1035: dup
    1036: iconst_1
    1037: ldc_w         #288                // String &Oslash;
    1040: aastore
    1041: aastore
    1042: dup
    1043: bipush        57
    1045: iconst_2
    1046: anewarray     #60                 // class java/lang/String
    1049: dup
    1050: iconst_0
    1051: ldc_w         #290                // String Ù
    1054: aastore
    1055: dup
    1056: iconst_1
    1057: ldc_w         #292                // String &Ugrave;
    1060: aastore
    1061: aastore
    1062: dup
    1063: bipush        58
    1065: iconst_2
    1066: anewarray     #60                 // class java/lang/String
    1069: dup
    1070: iconst_0
    1071: ldc_w         #294                // String Ú
    1074: aastore
    1075: dup
    1076: iconst_1
    1077: ldc_w         #296                // String &Uacute;
    1080: aastore
    1081: aastore
    1082: dup
    1083: bipush        59
    1085: iconst_2
    1086: anewarray     #60                 // class java/lang/String
    1089: dup
    1090: iconst_0
    1091: ldc_w         #298                // String Û
    1094: aastore
    1095: dup
    1096: iconst_1
    1097: ldc_w         #300                // String &Ucirc;
    1100: aastore
    1101: aastore
    1102: dup
    1103: bipush        60
    1105: iconst_2
    1106: anewarray     #60                 // class java/lang/String
    1109: dup
    1110: iconst_0
    1111: ldc_w         #302                // String Ü
    1114: aastore
    1115: dup
    1116: iconst_1
    1117: ldc_w         #304                // String &Uuml;
    1120: aastore
    1121: aastore
    1122: dup
    1123: bipush        61
    1125: iconst_2
    1126: anewarray     #60                 // class java/lang/String
    1129: dup
    1130: iconst_0
    1131: ldc_w         #306                // String Ý
    1134: aastore
    1135: dup
    1136: iconst_1
    1137: ldc_w         #308                // String &Yacute;
    1140: aastore
    1141: aastore
    1142: dup
    1143: bipush        62
    1145: iconst_2
    1146: anewarray     #60                 // class java/lang/String
    1149: dup
    1150: iconst_0
    1151: ldc_w         #310                // String Þ
    1154: aastore
    1155: dup
    1156: iconst_1
    1157: ldc_w         #312                // String &THORN;
    1160: aastore
    1161: aastore
    1162: dup
    1163: bipush        63
    1165: iconst_2
    1166: anewarray     #60                 // class java/lang/String
    1169: dup
    1170: iconst_0
    1171: ldc_w         #314                // String ß
    1174: aastore
    1175: dup
    1176: iconst_1
    1177: ldc_w         #316                // String &szlig;
    1180: aastore
    1181: aastore
    1182: dup
    1183: bipush        64
    1185: iconst_2
    1186: anewarray     #60                 // class java/lang/String
    1189: dup
    1190: iconst_0
    1191: ldc_w         #318                // String à
    1194: aastore
    1195: dup
    1196: iconst_1
    1197: ldc_w         #320                // String &agrave;
    1200: aastore
    1201: aastore
    1202: dup
    1203: bipush        65
    1205: iconst_2
    1206: anewarray     #60                 // class java/lang/String
    1209: dup
    1210: iconst_0
    1211: ldc_w         #322                // String á
    1214: aastore
    1215: dup
    1216: iconst_1
    1217: ldc_w         #324                // String &aacute;
    1220: aastore
    1221: aastore
    1222: dup
    1223: bipush        66
    1225: iconst_2
    1226: anewarray     #60                 // class java/lang/String
    1229: dup
    1230: iconst_0
    1231: ldc_w         #326                // String â
    1234: aastore
    1235: dup
    1236: iconst_1
    1237: ldc_w         #328                // String &acirc;
    1240: aastore
    1241: aastore
    1242: dup
    1243: bipush        67
    1245: iconst_2
    1246: anewarray     #60                 // class java/lang/String
    1249: dup
    1250: iconst_0
    1251: ldc_w         #330                // String ã
    1254: aastore
    1255: dup
    1256: iconst_1
    1257: ldc_w         #332                // String &atilde;
    1260: aastore
    1261: aastore
    1262: dup
    1263: bipush        68
    1265: iconst_2
    1266: anewarray     #60                 // class java/lang/String
    1269: dup
    1270: iconst_0
    1271: ldc_w         #334                // String ä
    1274: aastore
    1275: dup
    1276: iconst_1
    1277: ldc_w         #336                // String &auml;
    1280: aastore
    1281: aastore
    1282: dup
    1283: bipush        69
    1285: iconst_2
    1286: anewarray     #60                 // class java/lang/String
    1289: dup
    1290: iconst_0
    1291: ldc_w         #338                // String å
    1294: aastore
    1295: dup
    1296: iconst_1
    1297: ldc_w         #340                // String &aring;
    1300: aastore
    1301: aastore
    1302: dup
    1303: bipush        70
    1305: iconst_2
    1306: anewarray     #60                 // class java/lang/String
    1309: dup
    1310: iconst_0
    1311: ldc_w         #342                // String æ
    1314: aastore
    1315: dup
    1316: iconst_1
    1317: ldc_w         #344                // String &aelig;
    1320: aastore
    1321: aastore
    1322: dup
    1323: bipush        71
    1325: iconst_2
    1326: anewarray     #60                 // class java/lang/String
    1329: dup
    1330: iconst_0
    1331: ldc_w         #346                // String ç
    1334: aastore
    1335: dup
    1336: iconst_1
    1337: ldc_w         #348                // String &ccedil;
    1340: aastore
    1341: aastore
    1342: dup
    1343: bipush        72
    1345: iconst_2
    1346: anewarray     #60                 // class java/lang/String
    1349: dup
    1350: iconst_0
    1351: ldc_w         #350                // String è
    1354: aastore
    1355: dup
    1356: iconst_1
    1357: ldc_w         #352                // String &egrave;
    1360: aastore
    1361: aastore
    1362: dup
    1363: bipush        73
    1365: iconst_2
    1366: anewarray     #60                 // class java/lang/String
    1369: dup
    1370: iconst_0
    1371: ldc_w         #354                // String é
    1374: aastore
    1375: dup
    1376: iconst_1
    1377: ldc_w         #356                // String &eacute;
    1380: aastore
    1381: aastore
    1382: dup
    1383: bipush        74
    1385: iconst_2
    1386: anewarray     #60                 // class java/lang/String
    1389: dup
    1390: iconst_0
    1391: ldc_w         #358                // String ê
    1394: aastore
    1395: dup
    1396: iconst_1
    1397: ldc_w         #360                // String &ecirc;
    1400: aastore
    1401: aastore
    1402: dup
    1403: bipush        75
    1405: iconst_2
    1406: anewarray     #60                 // class java/lang/String
    1409: dup
    1410: iconst_0
    1411: ldc_w         #362                // String ë
    1414: aastore
    1415: dup
    1416: iconst_1
    1417: ldc_w         #364                // String &euml;
    1420: aastore
    1421: aastore
    1422: dup
    1423: bipush        76
    1425: iconst_2
    1426: anewarray     #60                 // class java/lang/String
    1429: dup
    1430: iconst_0
    1431: ldc_w         #366                // String ì
    1434: aastore
    1435: dup
    1436: iconst_1
    1437: ldc_w         #368                // String &igrave;
    1440: aastore
    1441: aastore
    1442: dup
    1443: bipush        77
    1445: iconst_2
    1446: anewarray     #60                 // class java/lang/String
    1449: dup
    1450: iconst_0
    1451: ldc_w         #370                // String í
    1454: aastore
    1455: dup
    1456: iconst_1
    1457: ldc_w         #372                // String &iacute;
    1460: aastore
    1461: aastore
    1462: dup
    1463: bipush        78
    1465: iconst_2
    1466: anewarray     #60                 // class java/lang/String
    1469: dup
    1470: iconst_0
    1471: ldc_w         #374                // String î
    1474: aastore
    1475: dup
    1476: iconst_1
    1477: ldc_w         #376                // String &icirc;
    1480: aastore
    1481: aastore
    1482: dup
    1483: bipush        79
    1485: iconst_2
    1486: anewarray     #60                 // class java/lang/String
    1489: dup
    1490: iconst_0
    1491: ldc_w         #378                // String ï
    1494: aastore
    1495: dup
    1496: iconst_1
    1497: ldc_w         #380                // String &iuml;
    1500: aastore
    1501: aastore
    1502: dup
    1503: bipush        80
    1505: iconst_2
    1506: anewarray     #60                 // class java/lang/String
    1509: dup
    1510: iconst_0
    1511: ldc_w         #382                // String ð
    1514: aastore
    1515: dup
    1516: iconst_1
    1517: ldc_w         #384                // String &eth;
    1520: aastore
    1521: aastore
    1522: dup
    1523: bipush        81
    1525: iconst_2
    1526: anewarray     #60                 // class java/lang/String
    1529: dup
    1530: iconst_0
    1531: ldc_w         #386                // String ñ
    1534: aastore
    1535: dup
    1536: iconst_1
    1537: ldc_w         #388                // String &ntilde;
    1540: aastore
    1541: aastore
    1542: dup
    1543: bipush        82
    1545: iconst_2
    1546: anewarray     #60                 // class java/lang/String
    1549: dup
    1550: iconst_0
    1551: ldc_w         #390                // String ò
    1554: aastore
    1555: dup
    1556: iconst_1
    1557: ldc_w         #392                // String &ograve;
    1560: aastore
    1561: aastore
    1562: dup
    1563: bipush        83
    1565: iconst_2
    1566: anewarray     #60                 // class java/lang/String
    1569: dup
    1570: iconst_0
    1571: ldc_w         #394                // String ó
    1574: aastore
    1575: dup
    1576: iconst_1
    1577: ldc_w         #396                // String &oacute;
    1580: aastore
    1581: aastore
    1582: dup
    1583: bipush        84
    1585: iconst_2
    1586: anewarray     #60                 // class java/lang/String
    1589: dup
    1590: iconst_0
    1591: ldc_w         #398                // String ô
    1594: aastore
    1595: dup
    1596: iconst_1
    1597: ldc_w         #400                // String &ocirc;
    1600: aastore
    1601: aastore
    1602: dup
    1603: bipush        85
    1605: iconst_2
    1606: anewarray     #60                 // class java/lang/String
    1609: dup
    1610: iconst_0
    1611: ldc_w         #402                // String õ
    1614: aastore
    1615: dup
    1616: iconst_1
    1617: ldc_w         #404                // String &otilde;
    1620: aastore
    1621: aastore
    1622: dup
    1623: bipush        86
    1625: iconst_2
    1626: anewarray     #60                 // class java/lang/String
    1629: dup
    1630: iconst_0
    1631: ldc_w         #406                // String ö
    1634: aastore
    1635: dup
    1636: iconst_1
    1637: ldc_w         #408                // String &ouml;
    1640: aastore
    1641: aastore
    1642: dup
    1643: bipush        87
    1645: iconst_2
    1646: anewarray     #60                 // class java/lang/String
    1649: dup
    1650: iconst_0
    1651: ldc_w         #410                // String ÷
    1654: aastore
    1655: dup
    1656: iconst_1
    1657: ldc_w         #412                // String &divide;
    1660: aastore
    1661: aastore
    1662: dup
    1663: bipush        88
    1665: iconst_2
    1666: anewarray     #60                 // class java/lang/String
    1669: dup
    1670: iconst_0
    1671: ldc_w         #414                // String ø
    1674: aastore
    1675: dup
    1676: iconst_1
    1677: ldc_w         #416                // String &oslash;
    1680: aastore
    1681: aastore
    1682: dup
    1683: bipush        89
    1685: iconst_2
    1686: anewarray     #60                 // class java/lang/String
    1689: dup
    1690: iconst_0
    1691: ldc_w         #418                // String ù
    1694: aastore
    1695: dup
    1696: iconst_1
    1697: ldc_w         #420                // String &ugrave;
    1700: aastore
    1701: aastore
    1702: dup
    1703: bipush        90
    1705: iconst_2
    1706: anewarray     #60                 // class java/lang/String
    1709: dup
    1710: iconst_0
    1711: ldc_w         #422                // String ú
    1714: aastore
    1715: dup
    1716: iconst_1
    1717: ldc_w         #424                // String &uacute;
    1720: aastore
    1721: aastore
    1722: dup
    1723: bipush        91
    1725: iconst_2
    1726: anewarray     #60                 // class java/lang/String
    1729: dup
    1730: iconst_0
    1731: ldc_w         #426                // String û
    1734: aastore
    1735: dup
    1736: iconst_1
    1737: ldc_w         #428                // String &ucirc;
    1740: aastore
    1741: aastore
    1742: dup
    1743: bipush        92
    1745: iconst_2
    1746: anewarray     #60                 // class java/lang/String
    1749: dup
    1750: iconst_0
    1751: ldc_w         #430                // String ü
    1754: aastore
    1755: dup
    1756: iconst_1
    1757: ldc_w         #432                // String &uuml;
    1760: aastore
    1761: aastore
    1762: dup
    1763: bipush        93
    1765: iconst_2
    1766: anewarray     #60                 // class java/lang/String
    1769: dup
    1770: iconst_0
    1771: ldc_w         #434                // String ý
    1774: aastore
    1775: dup
    1776: iconst_1
    1777: ldc_w         #436                // String &yacute;
    1780: aastore
    1781: aastore
    1782: dup
    1783: bipush        94
    1785: iconst_2
    1786: anewarray     #60                 // class java/lang/String
    1789: dup
    1790: iconst_0
    1791: ldc_w         #438                // String þ
    1794: aastore
    1795: dup
    1796: iconst_1
    1797: ldc_w         #440                // String &thorn;
    1800: aastore
    1801: aastore
    1802: dup
    1803: bipush        95
    1805: iconst_2
    1806: anewarray     #60                 // class java/lang/String
    1809: dup
    1810: iconst_0
    1811: ldc_w         #442                // String ÿ
    1814: aastore
    1815: dup
    1816: iconst_1
    1817: ldc_w         #444                // String &yuml;
    1820: aastore
    1821: aastore
    1822: putstatic     #26                 // Field ISO8859_1_ESCAPE:[[Ljava/lang/String;
    1825: getstatic     #26                 // Field ISO8859_1_ESCAPE:[[Ljava/lang/String;
    1828: invokestatic  #446                // Method invert:([[Ljava/lang/String;)[[Ljava/lang/String;
    1831: putstatic     #33                 // Field ISO8859_1_UNESCAPE:[[Ljava/lang/String;
    1834: sipush        152
    1837: anewarray     #58                 // class "[Ljava/lang/String;"
    1840: dup
    1841: iconst_0
    1842: iconst_2
    1843: anewarray     #60                 // class java/lang/String
    1846: dup
    1847: iconst_0
    1848: ldc_w         #448                // String ƒ
    1851: aastore
    1852: dup
    1853: iconst_1
    1854: ldc_w         #450                // String &fnof;
    1857: aastore
    1858: aastore
    1859: dup
    1860: iconst_1
    1861: iconst_2
    1862: anewarray     #60                 // class java/lang/String
    1865: dup
    1866: iconst_0
    1867: ldc_w         #452                // String Α
    1870: aastore
    1871: dup
    1872: iconst_1
    1873: ldc_w         #454                // String &Alpha;
    1876: aastore
    1877: aastore
    1878: dup
    1879: iconst_2
    1880: iconst_2
    1881: anewarray     #60                 // class java/lang/String
    1884: dup
    1885: iconst_0
    1886: ldc_w         #456                // String Β
    1889: aastore
    1890: dup
    1891: iconst_1
    1892: ldc_w         #458                // String &Beta;
    1895: aastore
    1896: aastore
    1897: dup
    1898: iconst_3
    1899: iconst_2
    1900: anewarray     #60                 // class java/lang/String
    1903: dup
    1904: iconst_0
    1905: ldc_w         #460                // String Γ
    1908: aastore
    1909: dup
    1910: iconst_1
    1911: ldc_w         #462                // String &Gamma;
    1914: aastore
    1915: aastore
    1916: dup
    1917: iconst_4
    1918: iconst_2
    1919: anewarray     #60                 // class java/lang/String
    1922: dup
    1923: iconst_0
    1924: ldc_w         #464                // String Δ
    1927: aastore
    1928: dup
    1929: iconst_1
    1930: ldc_w         #466                // String &Delta;
    1933: aastore
    1934: aastore
    1935: dup
    1936: iconst_5
    1937: iconst_2
    1938: anewarray     #60                 // class java/lang/String
    1941: dup
    1942: iconst_0
    1943: ldc_w         #468                // String Ε
    1946: aastore
    1947: dup
    1948: iconst_1
    1949: ldc_w         #470                // String &Epsilon;
    1952: aastore
    1953: aastore
    1954: dup
    1955: bipush        6
    1957: iconst_2
    1958: anewarray     #60                 // class java/lang/String
    1961: dup
    1962: iconst_0
    1963: ldc_w         #472                // String Ζ
    1966: aastore
    1967: dup
    1968: iconst_1
    1969: ldc_w         #474                // String &Zeta;
    1972: aastore
    1973: aastore
    1974: dup
    1975: bipush        7
    1977: iconst_2
    1978: anewarray     #60                 // class java/lang/String
    1981: dup
    1982: iconst_0
    1983: ldc_w         #476                // String Η
    1986: aastore
    1987: dup
    1988: iconst_1
    1989: ldc_w         #478                // String &Eta;
    1992: aastore
    1993: aastore
    1994: dup
    1995: bipush        8
    1997: iconst_2
    1998: anewarray     #60                 // class java/lang/String
    2001: dup
    2002: iconst_0
    2003: ldc_w         #480                // String Θ
    2006: aastore
    2007: dup
    2008: iconst_1
    2009: ldc_w         #482                // String &Theta;
    2012: aastore
    2013: aastore
    2014: dup
    2015: bipush        9
    2017: iconst_2
    2018: anewarray     #60                 // class java/lang/String
    2021: dup
    2022: iconst_0
    2023: ldc_w         #484                // String Ι
    2026: aastore
    2027: dup
    2028: iconst_1
    2029: ldc_w         #486                // String &Iota;
    2032: aastore
    2033: aastore
    2034: dup
    2035: bipush        10
    2037: iconst_2
    2038: anewarray     #60                 // class java/lang/String
    2041: dup
    2042: iconst_0
    2043: ldc_w         #488                // String Κ
    2046: aastore
    2047: dup
    2048: iconst_1
    2049: ldc_w         #490                // String &Kappa;
    2052: aastore
    2053: aastore
    2054: dup
    2055: bipush        11
    2057: iconst_2
    2058: anewarray     #60                 // class java/lang/String
    2061: dup
    2062: iconst_0
    2063: ldc_w         #492                // String Λ
    2066: aastore
    2067: dup
    2068: iconst_1
    2069: ldc_w         #494                // String &Lambda;
    2072: aastore
    2073: aastore
    2074: dup
    2075: bipush        12
    2077: iconst_2
    2078: anewarray     #60                 // class java/lang/String
    2081: dup
    2082: iconst_0
    2083: ldc_w         #496                // String Μ
    2086: aastore
    2087: dup
    2088: iconst_1
    2089: ldc_w         #498                // String &Mu;
    2092: aastore
    2093: aastore
    2094: dup
    2095: bipush        13
    2097: iconst_2
    2098: anewarray     #60                 // class java/lang/String
    2101: dup
    2102: iconst_0
    2103: ldc_w         #500                // String Ν
    2106: aastore
    2107: dup
    2108: iconst_1
    2109: ldc_w         #502                // String &Nu;
    2112: aastore
    2113: aastore
    2114: dup
    2115: bipush        14
    2117: iconst_2
    2118: anewarray     #60                 // class java/lang/String
    2121: dup
    2122: iconst_0
    2123: ldc_w         #504                // String Ξ
    2126: aastore
    2127: dup
    2128: iconst_1
    2129: ldc_w         #506                // String &Xi;
    2132: aastore
    2133: aastore
    2134: dup
    2135: bipush        15
    2137: iconst_2
    2138: anewarray     #60                 // class java/lang/String
    2141: dup
    2142: iconst_0
    2143: ldc_w         #508                // String Ο
    2146: aastore
    2147: dup
    2148: iconst_1
    2149: ldc_w         #510                // String &Omicron;
    2152: aastore
    2153: aastore
    2154: dup
    2155: bipush        16
    2157: iconst_2
    2158: anewarray     #60                 // class java/lang/String
    2161: dup
    2162: iconst_0
    2163: ldc_w         #512                // String Π
    2166: aastore
    2167: dup
    2168: iconst_1
    2169: ldc_w         #514                // String &Pi;
    2172: aastore
    2173: aastore
    2174: dup
    2175: bipush        17
    2177: iconst_2
    2178: anewarray     #60                 // class java/lang/String
    2181: dup
    2182: iconst_0
    2183: ldc_w         #516                // String Ρ
    2186: aastore
    2187: dup
    2188: iconst_1
    2189: ldc_w         #518                // String &Rho;
    2192: aastore
    2193: aastore
    2194: dup
    2195: bipush        18
    2197: iconst_2
    2198: anewarray     #60                 // class java/lang/String
    2201: dup
    2202: iconst_0
    2203: ldc_w         #520                // String Σ
    2206: aastore
    2207: dup
    2208: iconst_1
    2209: ldc_w         #522                // String &Sigma;
    2212: aastore
    2213: aastore
    2214: dup
    2215: bipush        19
    2217: iconst_2
    2218: anewarray     #60                 // class java/lang/String
    2221: dup
    2222: iconst_0
    2223: ldc_w         #524                // String Τ
    2226: aastore
    2227: dup
    2228: iconst_1
    2229: ldc_w         #526                // String &Tau;
    2232: aastore
    2233: aastore
    2234: dup
    2235: bipush        20
    2237: iconst_2
    2238: anewarray     #60                 // class java/lang/String
    2241: dup
    2242: iconst_0
    2243: ldc_w         #528                // String Υ
    2246: aastore
    2247: dup
    2248: iconst_1
    2249: ldc_w         #530                // String &Upsilon;
    2252: aastore
    2253: aastore
    2254: dup
    2255: bipush        21
    2257: iconst_2
    2258: anewarray     #60                 // class java/lang/String
    2261: dup
    2262: iconst_0
    2263: ldc_w         #532                // String Φ
    2266: aastore
    2267: dup
    2268: iconst_1
    2269: ldc_w         #534                // String &Phi;
    2272: aastore
    2273: aastore
    2274: dup
    2275: bipush        22
    2277: iconst_2
    2278: anewarray     #60                 // class java/lang/String
    2281: dup
    2282: iconst_0
    2283: ldc_w         #536                // String Χ
    2286: aastore
    2287: dup
    2288: iconst_1
    2289: ldc_w         #538                // String &Chi;
    2292: aastore
    2293: aastore
    2294: dup
    2295: bipush        23
    2297: iconst_2
    2298: anewarray     #60                 // class java/lang/String
    2301: dup
    2302: iconst_0
    2303: ldc_w         #540                // String Ψ
    2306: aastore
    2307: dup
    2308: iconst_1
    2309: ldc_w         #542                // String &Psi;
    2312: aastore
    2313: aastore
    2314: dup
    2315: bipush        24
    2317: iconst_2
    2318: anewarray     #60                 // class java/lang/String
    2321: dup
    2322: iconst_0
    2323: ldc_w         #544                // String Ω
    2326: aastore
    2327: dup
    2328: iconst_1
    2329: ldc_w         #546                // String &Omega;
    2332: aastore
    2333: aastore
    2334: dup
    2335: bipush        25
    2337: iconst_2
    2338: anewarray     #60                 // class java/lang/String
    2341: dup
    2342: iconst_0
    2343: ldc_w         #548                // String α
    2346: aastore
    2347: dup
    2348: iconst_1
    2349: ldc_w         #550                // String &alpha;
    2352: aastore
    2353: aastore
    2354: dup
    2355: bipush        26
    2357: iconst_2
    2358: anewarray     #60                 // class java/lang/String
    2361: dup
    2362: iconst_0
    2363: ldc_w         #552                // String β
    2366: aastore
    2367: dup
    2368: iconst_1
    2369: ldc_w         #554                // String &beta;
    2372: aastore
    2373: aastore
    2374: dup
    2375: bipush        27
    2377: iconst_2
    2378: anewarray     #60                 // class java/lang/String
    2381: dup
    2382: iconst_0
    2383: ldc_w         #556                // String γ
    2386: aastore
    2387: dup
    2388: iconst_1
    2389: ldc_w         #558                // String &gamma;
    2392: aastore
    2393: aastore
    2394: dup
    2395: bipush        28
    2397: iconst_2
    2398: anewarray     #60                 // class java/lang/String
    2401: dup
    2402: iconst_0
    2403: ldc_w         #560                // String δ
    2406: aastore
    2407: dup
    2408: iconst_1
    2409: ldc_w         #562                // String &delta;
    2412: aastore
    2413: aastore
    2414: dup
    2415: bipush        29
    2417: iconst_2
    2418: anewarray     #60                 // class java/lang/String
    2421: dup
    2422: iconst_0
    2423: ldc_w         #564                // String ε
    2426: aastore
    2427: dup
    2428: iconst_1
    2429: ldc_w         #566                // String &epsilon;
    2432: aastore
    2433: aastore
    2434: dup
    2435: bipush        30
    2437: iconst_2
    2438: anewarray     #60                 // class java/lang/String
    2441: dup
    2442: iconst_0
    2443: ldc_w         #568                // String ζ
    2446: aastore
    2447: dup
    2448: iconst_1
    2449: ldc_w         #570                // String &zeta;
    2452: aastore
    2453: aastore
    2454: dup
    2455: bipush        31
    2457: iconst_2
    2458: anewarray     #60                 // class java/lang/String
    2461: dup
    2462: iconst_0
    2463: ldc_w         #572                // String η
    2466: aastore
    2467: dup
    2468: iconst_1
    2469: ldc_w         #574                // String &eta;
    2472: aastore
    2473: aastore
    2474: dup
    2475: bipush        32
    2477: iconst_2
    2478: anewarray     #60                 // class java/lang/String
    2481: dup
    2482: iconst_0
    2483: ldc_w         #576                // String θ
    2486: aastore
    2487: dup
    2488: iconst_1
    2489: ldc_w         #578                // String &theta;
    2492: aastore
    2493: aastore
    2494: dup
    2495: bipush        33
    2497: iconst_2
    2498: anewarray     #60                 // class java/lang/String
    2501: dup
    2502: iconst_0
    2503: ldc_w         #580                // String ι
    2506: aastore
    2507: dup
    2508: iconst_1
    2509: ldc_w         #582                // String &iota;
    2512: aastore
    2513: aastore
    2514: dup
    2515: bipush        34
    2517: iconst_2
    2518: anewarray     #60                 // class java/lang/String
    2521: dup
    2522: iconst_0
    2523: ldc_w         #584                // String κ
    2526: aastore
    2527: dup
    2528: iconst_1
    2529: ldc_w         #586                // String &kappa;
    2532: aastore
    2533: aastore
    2534: dup
    2535: bipush        35
    2537: iconst_2
    2538: anewarray     #60                 // class java/lang/String
    2541: dup
    2542: iconst_0
    2543: ldc_w         #588                // String λ
    2546: aastore
    2547: dup
    2548: iconst_1
    2549: ldc_w         #590                // String &lambda;
    2552: aastore
    2553: aastore
    2554: dup
    2555: bipush        36
    2557: iconst_2
    2558: anewarray     #60                 // class java/lang/String
    2561: dup
    2562: iconst_0
    2563: ldc_w         #592                // String μ
    2566: aastore
    2567: dup
    2568: iconst_1
    2569: ldc_w         #594                // String &mu;
    2572: aastore
    2573: aastore
    2574: dup
    2575: bipush        37
    2577: iconst_2
    2578: anewarray     #60                 // class java/lang/String
    2581: dup
    2582: iconst_0
    2583: ldc_w         #596                // String ν
    2586: aastore
    2587: dup
    2588: iconst_1
    2589: ldc_w         #598                // String &nu;
    2592: aastore
    2593: aastore
    2594: dup
    2595: bipush        38
    2597: iconst_2
    2598: anewarray     #60                 // class java/lang/String
    2601: dup
    2602: iconst_0
    2603: ldc_w         #600                // String ξ
    2606: aastore
    2607: dup
    2608: iconst_1
    2609: ldc_w         #602                // String &xi;
    2612: aastore
    2613: aastore
    2614: dup
    2615: bipush        39
    2617: iconst_2
    2618: anewarray     #60                 // class java/lang/String
    2621: dup
    2622: iconst_0
    2623: ldc_w         #604                // String ο
    2626: aastore
    2627: dup
    2628: iconst_1
    2629: ldc_w         #606                // String &omicron;
    2632: aastore
    2633: aastore
    2634: dup
    2635: bipush        40
    2637: iconst_2
    2638: anewarray     #60                 // class java/lang/String
    2641: dup
    2642: iconst_0
    2643: ldc_w         #608                // String π
    2646: aastore
    2647: dup
    2648: iconst_1
    2649: ldc_w         #610                // String &pi;
    2652: aastore
    2653: aastore
    2654: dup
    2655: bipush        41
    2657: iconst_2
    2658: anewarray     #60                 // class java/lang/String
    2661: dup
    2662: iconst_0
    2663: ldc_w         #612                // String ρ
    2666: aastore
    2667: dup
    2668: iconst_1
    2669: ldc_w         #614                // String &rho;
    2672: aastore
    2673: aastore
    2674: dup
    2675: bipush        42
    2677: iconst_2
    2678: anewarray     #60                 // class java/lang/String
    2681: dup
    2682: iconst_0
    2683: ldc_w         #616                // String ς
    2686: aastore
    2687: dup
    2688: iconst_1
    2689: ldc_w         #618                // String &sigmaf;
    2692: aastore
    2693: aastore
    2694: dup
    2695: bipush        43
    2697: iconst_2
    2698: anewarray     #60                 // class java/lang/String
    2701: dup
    2702: iconst_0
    2703: ldc_w         #620                // String σ
    2706: aastore
    2707: dup
    2708: iconst_1
    2709: ldc_w         #622                // String &sigma;
    2712: aastore
    2713: aastore
    2714: dup
    2715: bipush        44
    2717: iconst_2
    2718: anewarray     #60                 // class java/lang/String
    2721: dup
    2722: iconst_0
    2723: ldc_w         #624                // String τ
    2726: aastore
    2727: dup
    2728: iconst_1
    2729: ldc_w         #626                // String &tau;
    2732: aastore
    2733: aastore
    2734: dup
    2735: bipush        45
    2737: iconst_2
    2738: anewarray     #60                 // class java/lang/String
    2741: dup
    2742: iconst_0
    2743: ldc_w         #628                // String υ
    2746: aastore
    2747: dup
    2748: iconst_1
    2749: ldc_w         #630                // String &upsilon;
    2752: aastore
    2753: aastore
    2754: dup
    2755: bipush        46
    2757: iconst_2
    2758: anewarray     #60                 // class java/lang/String
    2761: dup
    2762: iconst_0
    2763: ldc_w         #632                // String φ
    2766: aastore
    2767: dup
    2768: iconst_1
    2769: ldc_w         #634                // String &phi;
    2772: aastore
    2773: aastore
    2774: dup
    2775: bipush        47
    2777: iconst_2
    2778: anewarray     #60                 // class java/lang/String
    2781: dup
    2782: iconst_0
    2783: ldc_w         #636                // String χ
    2786: aastore
    2787: dup
    2788: iconst_1
    2789: ldc_w         #638                // String &chi;
    2792: aastore
    2793: aastore
    2794: dup
    2795: bipush        48
    2797: iconst_2
    2798: anewarray     #60                 // class java/lang/String
    2801: dup
    2802: iconst_0
    2803: ldc_w         #640                // String ψ
    2806: aastore
    2807: dup
    2808: iconst_1
    2809: ldc_w         #642                // String &psi;
    2812: aastore
    2813: aastore
    2814: dup
    2815: bipush        49
    2817: iconst_2
    2818: anewarray     #60                 // class java/lang/String
    2821: dup
    2822: iconst_0
    2823: ldc_w         #644                // String ω
    2826: aastore
    2827: dup
    2828: iconst_1
    2829: ldc_w         #646                // String &omega;
    2832: aastore
    2833: aastore
    2834: dup
    2835: bipush        50
    2837: iconst_2
    2838: anewarray     #60                 // class java/lang/String
    2841: dup
    2842: iconst_0
    2843: ldc_w         #648                // String ϑ
    2846: aastore
    2847: dup
    2848: iconst_1
    2849: ldc_w         #650                // String &thetasym;
    2852: aastore
    2853: aastore
    2854: dup
    2855: bipush        51
    2857: iconst_2
    2858: anewarray     #60                 // class java/lang/String
    2861: dup
    2862: iconst_0
    2863: ldc_w         #652                // String ϒ
    2866: aastore
    2867: dup
    2868: iconst_1
    2869: ldc_w         #654                // String &upsih;
    2872: aastore
    2873: aastore
    2874: dup
    2875: bipush        52
    2877: iconst_2
    2878: anewarray     #60                 // class java/lang/String
    2881: dup
    2882: iconst_0
    2883: ldc_w         #656                // String ϖ
    2886: aastore
    2887: dup
    2888: iconst_1
    2889: ldc_w         #658                // String &piv;
    2892: aastore
    2893: aastore
    2894: dup
    2895: bipush        53
    2897: iconst_2
    2898: anewarray     #60                 // class java/lang/String
    2901: dup
    2902: iconst_0
    2903: ldc_w         #660                // String •
    2906: aastore
    2907: dup
    2908: iconst_1
    2909: ldc_w         #662                // String &bull;
    2912: aastore
    2913: aastore
    2914: dup
    2915: bipush        54
    2917: iconst_2
    2918: anewarray     #60                 // class java/lang/String
    2921: dup
    2922: iconst_0
    2923: ldc_w         #664                // String …
    2926: aastore
    2927: dup
    2928: iconst_1
    2929: ldc_w         #666                // String &hellip;
    2932: aastore
    2933: aastore
    2934: dup
    2935: bipush        55
    2937: iconst_2
    2938: anewarray     #60                 // class java/lang/String
    2941: dup
    2942: iconst_0
    2943: ldc_w         #668                // String ′
    2946: aastore
    2947: dup
    2948: iconst_1
    2949: ldc_w         #670                // String &prime;
    2952: aastore
    2953: aastore
    2954: dup
    2955: bipush        56
    2957: iconst_2
    2958: anewarray     #60                 // class java/lang/String
    2961: dup
    2962: iconst_0
    2963: ldc_w         #672                // String ″
    2966: aastore
    2967: dup
    2968: iconst_1
    2969: ldc_w         #674                // String &Prime;
    2972: aastore
    2973: aastore
    2974: dup
    2975: bipush        57
    2977: iconst_2
    2978: anewarray     #60                 // class java/lang/String
    2981: dup
    2982: iconst_0
    2983: ldc_w         #676                // String ‾
    2986: aastore
    2987: dup
    2988: iconst_1
    2989: ldc_w         #678                // String &oline;
    2992: aastore
    2993: aastore
    2994: dup
    2995: bipush        58
    2997: iconst_2
    2998: anewarray     #60                 // class java/lang/String
    3001: dup
    3002: iconst_0
    3003: ldc_w         #680                // String ⁄
    3006: aastore
    3007: dup
    3008: iconst_1
    3009: ldc_w         #682                // String &frasl;
    3012: aastore
    3013: aastore
    3014: dup
    3015: bipush        59
    3017: iconst_2
    3018: anewarray     #60                 // class java/lang/String
    3021: dup
    3022: iconst_0
    3023: ldc_w         #684                // String ℘
    3026: aastore
    3027: dup
    3028: iconst_1
    3029: ldc_w         #686                // String &weierp;
    3032: aastore
    3033: aastore
    3034: dup
    3035: bipush        60
    3037: iconst_2
    3038: anewarray     #60                 // class java/lang/String
    3041: dup
    3042: iconst_0
    3043: ldc_w         #688                // String ℑ
    3046: aastore
    3047: dup
    3048: iconst_1
    3049: ldc_w         #690                // String &image;
    3052: aastore
    3053: aastore
    3054: dup
    3055: bipush        61
    3057: iconst_2
    3058: anewarray     #60                 // class java/lang/String
    3061: dup
    3062: iconst_0
    3063: ldc_w         #692                // String ℜ
    3066: aastore
    3067: dup
    3068: iconst_1
    3069: ldc_w         #694                // String &real;
    3072: aastore
    3073: aastore
    3074: dup
    3075: bipush        62
    3077: iconst_2
    3078: anewarray     #60                 // class java/lang/String
    3081: dup
    3082: iconst_0
    3083: ldc_w         #696                // String ™
    3086: aastore
    3087: dup
    3088: iconst_1
    3089: ldc_w         #698                // String &trade;
    3092: aastore
    3093: aastore
    3094: dup
    3095: bipush        63
    3097: iconst_2
    3098: anewarray     #60                 // class java/lang/String
    3101: dup
    3102: iconst_0
    3103: ldc_w         #700                // String ℵ
    3106: aastore
    3107: dup
    3108: iconst_1
    3109: ldc_w         #702                // String &alefsym;
    3112: aastore
    3113: aastore
    3114: dup
    3115: bipush        64
    3117: iconst_2
    3118: anewarray     #60                 // class java/lang/String
    3121: dup
    3122: iconst_0
    3123: ldc_w         #704                // String ←
    3126: aastore
    3127: dup
    3128: iconst_1
    3129: ldc_w         #706                // String &larr;
    3132: aastore
    3133: aastore
    3134: dup
    3135: bipush        65
    3137: iconst_2
    3138: anewarray     #60                 // class java/lang/String
    3141: dup
    3142: iconst_0
    3143: ldc_w         #708                // String ↑
    3146: aastore
    3147: dup
    3148: iconst_1
    3149: ldc_w         #710                // String &uarr;
    3152: aastore
    3153: aastore
    3154: dup
    3155: bipush        66
    3157: iconst_2
    3158: anewarray     #60                 // class java/lang/String
    3161: dup
    3162: iconst_0
    3163: ldc_w         #712                // String →
    3166: aastore
    3167: dup
    3168: iconst_1
    3169: ldc_w         #714                // String &rarr;
    3172: aastore
    3173: aastore
    3174: dup
    3175: bipush        67
    3177: iconst_2
    3178: anewarray     #60                 // class java/lang/String
    3181: dup
    3182: iconst_0
    3183: ldc_w         #716                // String ↓
    3186: aastore
    3187: dup
    3188: iconst_1
    3189: ldc_w         #718                // String &darr;
    3192: aastore
    3193: aastore
    3194: dup
    3195: bipush        68
    3197: iconst_2
    3198: anewarray     #60                 // class java/lang/String
    3201: dup
    3202: iconst_0
    3203: ldc_w         #720                // String ↔
    3206: aastore
    3207: dup
    3208: iconst_1
    3209: ldc_w         #722                // String &harr;
    3212: aastore
    3213: aastore
    3214: dup
    3215: bipush        69
    3217: iconst_2
    3218: anewarray     #60                 // class java/lang/String
    3221: dup
    3222: iconst_0
    3223: ldc_w         #724                // String ↵
    3226: aastore
    3227: dup
    3228: iconst_1
    3229: ldc_w         #726                // String &crarr;
    3232: aastore
    3233: aastore
    3234: dup
    3235: bipush        70
    3237: iconst_2
    3238: anewarray     #60                 // class java/lang/String
    3241: dup
    3242: iconst_0
    3243: ldc_w         #728                // String ⇐
    3246: aastore
    3247: dup
    3248: iconst_1
    3249: ldc_w         #730                // String &lArr;
    3252: aastore
    3253: aastore
    3254: dup
    3255: bipush        71
    3257: iconst_2
    3258: anewarray     #60                 // class java/lang/String
    3261: dup
    3262: iconst_0
    3263: ldc_w         #732                // String ⇑
    3266: aastore
    3267: dup
    3268: iconst_1
    3269: ldc_w         #734                // String &uArr;
    3272: aastore
    3273: aastore
    3274: dup
    3275: bipush        72
    3277: iconst_2
    3278: anewarray     #60                 // class java/lang/String
    3281: dup
    3282: iconst_0
    3283: ldc_w         #736                // String ⇒
    3286: aastore
    3287: dup
    3288: iconst_1
    3289: ldc_w         #738                // String &rArr;
    3292: aastore
    3293: aastore
    3294: dup
    3295: bipush        73
    3297: iconst_2
    3298: anewarray     #60                 // class java/lang/String
    3301: dup
    3302: iconst_0
    3303: ldc_w         #740                // String ⇓
    3306: aastore
    3307: dup
    3308: iconst_1
    3309: ldc_w         #742                // String &dArr;
    3312: aastore
    3313: aastore
    3314: dup
    3315: bipush        74
    3317: iconst_2
    3318: anewarray     #60                 // class java/lang/String
    3321: dup
    3322: iconst_0
    3323: ldc_w         #744                // String ⇔
    3326: aastore
    3327: dup
    3328: iconst_1
    3329: ldc_w         #746                // String &hArr;
    3332: aastore
    3333: aastore
    3334: dup
    3335: bipush        75
    3337: iconst_2
    3338: anewarray     #60                 // class java/lang/String
    3341: dup
    3342: iconst_0
    3343: ldc_w         #748                // String ∀
    3346: aastore
    3347: dup
    3348: iconst_1
    3349: ldc_w         #750                // String &forall;
    3352: aastore
    3353: aastore
    3354: dup
    3355: bipush        76
    3357: iconst_2
    3358: anewarray     #60                 // class java/lang/String
    3361: dup
    3362: iconst_0
    3363: ldc_w         #752                // String ∂
    3366: aastore
    3367: dup
    3368: iconst_1
    3369: ldc_w         #754                // String &part;
    3372: aastore
    3373: aastore
    3374: dup
    3375: bipush        77
    3377: iconst_2
    3378: anewarray     #60                 // class java/lang/String
    3381: dup
    3382: iconst_0
    3383: ldc_w         #756                // String ∃
    3386: aastore
    3387: dup
    3388: iconst_1
    3389: ldc_w         #758                // String &exist;
    3392: aastore
    3393: aastore
    3394: dup
    3395: bipush        78
    3397: iconst_2
    3398: anewarray     #60                 // class java/lang/String
    3401: dup
    3402: iconst_0
    3403: ldc_w         #760                // String ∅
    3406: aastore
    3407: dup
    3408: iconst_1
    3409: ldc_w         #762                // String &empty;
    3412: aastore
    3413: aastore
    3414: dup
    3415: bipush        79
    3417: iconst_2
    3418: anewarray     #60                 // class java/lang/String
    3421: dup
    3422: iconst_0
    3423: ldc_w         #764                // String ∇
    3426: aastore
    3427: dup
    3428: iconst_1
    3429: ldc_w         #766                // String &nabla;
    3432: aastore
    3433: aastore
    3434: dup
    3435: bipush        80
    3437: iconst_2
    3438: anewarray     #60                 // class java/lang/String
    3441: dup
    3442: iconst_0
    3443: ldc_w         #768                // String ∈
    3446: aastore
    3447: dup
    3448: iconst_1
    3449: ldc_w         #770                // String &isin;
    3452: aastore
    3453: aastore
    3454: dup
    3455: bipush        81
    3457: iconst_2
    3458: anewarray     #60                 // class java/lang/String
    3461: dup
    3462: iconst_0
    3463: ldc_w         #772                // String ∉
    3466: aastore
    3467: dup
    3468: iconst_1
    3469: ldc_w         #774                // String &notin;
    3472: aastore
    3473: aastore
    3474: dup
    3475: bipush        82
    3477: iconst_2
    3478: anewarray     #60                 // class java/lang/String
    3481: dup
    3482: iconst_0
    3483: ldc_w         #776                // String ∋
    3486: aastore
    3487: dup
    3488: iconst_1
    3489: ldc_w         #778                // String &ni;
    3492: aastore
    3493: aastore
    3494: dup
    3495: bipush        83
    3497: iconst_2
    3498: anewarray     #60                 // class java/lang/String
    3501: dup
    3502: iconst_0
    3503: ldc_w         #780                // String ∏
    3506: aastore
    3507: dup
    3508: iconst_1
    3509: ldc_w         #782                // String &prod;
    3512: aastore
    3513: aastore
    3514: dup
    3515: bipush        84
    3517: iconst_2
    3518: anewarray     #60                 // class java/lang/String
    3521: dup
    3522: iconst_0
    3523: ldc_w         #784                // String ∑
    3526: aastore
    3527: dup
    3528: iconst_1
    3529: ldc_w         #786                // String &sum;
    3532: aastore
    3533: aastore
    3534: dup
    3535: bipush        85
    3537: iconst_2
    3538: anewarray     #60                 // class java/lang/String
    3541: dup
    3542: iconst_0
    3543: ldc_w         #788                // String −
    3546: aastore
    3547: dup
    3548: iconst_1
    3549: ldc_w         #790                // String &minus;
    3552: aastore
    3553: aastore
    3554: dup
    3555: bipush        86
    3557: iconst_2
    3558: anewarray     #60                 // class java/lang/String
    3561: dup
    3562: iconst_0
    3563: ldc_w         #792                // String ∗
    3566: aastore
    3567: dup
    3568: iconst_1
    3569: ldc_w         #794                // String &lowast;
    3572: aastore
    3573: aastore
    3574: dup
    3575: bipush        87
    3577: iconst_2
    3578: anewarray     #60                 // class java/lang/String
    3581: dup
    3582: iconst_0
    3583: ldc_w         #796                // String √
    3586: aastore
    3587: dup
    3588: iconst_1
    3589: ldc_w         #798                // String &radic;
    3592: aastore
    3593: aastore
    3594: dup
    3595: bipush        88
    3597: iconst_2
    3598: anewarray     #60                 // class java/lang/String
    3601: dup
    3602: iconst_0
    3603: ldc_w         #800                // String ∝
    3606: aastore
    3607: dup
    3608: iconst_1
    3609: ldc_w         #802                // String &prop;
    3612: aastore
    3613: aastore
    3614: dup
    3615: bipush        89
    3617: iconst_2
    3618: anewarray     #60                 // class java/lang/String
    3621: dup
    3622: iconst_0
    3623: ldc_w         #804                // String ∞
    3626: aastore
    3627: dup
    3628: iconst_1
    3629: ldc_w         #806                // String &infin;
    3632: aastore
    3633: aastore
    3634: dup
    3635: bipush        90
    3637: iconst_2
    3638: anewarray     #60                 // class java/lang/String
    3641: dup
    3642: iconst_0
    3643: ldc_w         #808                // String ∠
    3646: aastore
    3647: dup
    3648: iconst_1
    3649: ldc_w         #810                // String &ang;
    3652: aastore
    3653: aastore
    3654: dup
    3655: bipush        91
    3657: iconst_2
    3658: anewarray     #60                 // class java/lang/String
    3661: dup
    3662: iconst_0
    3663: ldc_w         #812                // String ∧
    3666: aastore
    3667: dup
    3668: iconst_1
    3669: ldc_w         #814                // String &and;
    3672: aastore
    3673: aastore
    3674: dup
    3675: bipush        92
    3677: iconst_2
    3678: anewarray     #60                 // class java/lang/String
    3681: dup
    3682: iconst_0
    3683: ldc_w         #816                // String ∨
    3686: aastore
    3687: dup
    3688: iconst_1
    3689: ldc_w         #818                // String &or;
    3692: aastore
    3693: aastore
    3694: dup
    3695: bipush        93
    3697: iconst_2
    3698: anewarray     #60                 // class java/lang/String
    3701: dup
    3702: iconst_0
    3703: ldc_w         #820                // String ∩
    3706: aastore
    3707: dup
    3708: iconst_1
    3709: ldc_w         #822                // String &cap;
    3712: aastore
    3713: aastore
    3714: dup
    3715: bipush        94
    3717: iconst_2
    3718: anewarray     #60                 // class java/lang/String
    3721: dup
    3722: iconst_0
    3723: ldc_w         #824                // String ∪
    3726: aastore
    3727: dup
    3728: iconst_1
    3729: ldc_w         #826                // String &cup;
    3732: aastore
    3733: aastore
    3734: dup
    3735: bipush        95
    3737: iconst_2
    3738: anewarray     #60                 // class java/lang/String
    3741: dup
    3742: iconst_0
    3743: ldc_w         #828                // String ∫
    3746: aastore
    3747: dup
    3748: iconst_1
    3749: ldc_w         #830                // String &int;
    3752: aastore
    3753: aastore
    3754: dup
    3755: bipush        96
    3757: iconst_2
    3758: anewarray     #60                 // class java/lang/String
    3761: dup
    3762: iconst_0
    3763: ldc_w         #832                // String ∴
    3766: aastore
    3767: dup
    3768: iconst_1
    3769: ldc_w         #834                // String &there4;
    3772: aastore
    3773: aastore
    3774: dup
    3775: bipush        97
    3777: iconst_2
    3778: anewarray     #60                 // class java/lang/String
    3781: dup
    3782: iconst_0
    3783: ldc_w         #836                // String ∼
    3786: aastore
    3787: dup
    3788: iconst_1
    3789: ldc_w         #838                // String &sim;
    3792: aastore
    3793: aastore
    3794: dup
    3795: bipush        98
    3797: iconst_2
    3798: anewarray     #60                 // class java/lang/String
    3801: dup
    3802: iconst_0
    3803: ldc_w         #840                // String ≅
    3806: aastore
    3807: dup
    3808: iconst_1
    3809: ldc_w         #842                // String &cong;
    3812: aastore
    3813: aastore
    3814: dup
    3815: bipush        99
    3817: iconst_2
    3818: anewarray     #60                 // class java/lang/String
    3821: dup
    3822: iconst_0
    3823: ldc_w         #844                // String ≈
    3826: aastore
    3827: dup
    3828: iconst_1
    3829: ldc_w         #846                // String &asymp;
    3832: aastore
    3833: aastore
    3834: dup
    3835: bipush        100
    3837: iconst_2
    3838: anewarray     #60                 // class java/lang/String
    3841: dup
    3842: iconst_0
    3843: ldc_w         #848                // String ≠
    3846: aastore
    3847: dup
    3848: iconst_1
    3849: ldc_w         #850                // String &ne;
    3852: aastore
    3853: aastore
    3854: dup
    3855: bipush        101
    3857: iconst_2
    3858: anewarray     #60                 // class java/lang/String
    3861: dup
    3862: iconst_0
    3863: ldc_w         #852                // String ≡
    3866: aastore
    3867: dup
    3868: iconst_1
    3869: ldc_w         #854                // String &equiv;
    3872: aastore
    3873: aastore
    3874: dup
    3875: bipush        102
    3877: iconst_2
    3878: anewarray     #60                 // class java/lang/String
    3881: dup
    3882: iconst_0
    3883: ldc_w         #856                // String ≤
    3886: aastore
    3887: dup
    3888: iconst_1
    3889: ldc_w         #858                // String &le;
    3892: aastore
    3893: aastore
    3894: dup
    3895: bipush        103
    3897: iconst_2
    3898: anewarray     #60                 // class java/lang/String
    3901: dup
    3902: iconst_0
    3903: ldc_w         #860                // String ≥
    3906: aastore
    3907: dup
    3908: iconst_1
    3909: ldc_w         #862                // String &ge;
    3912: aastore
    3913: aastore
    3914: dup
    3915: bipush        104
    3917: iconst_2
    3918: anewarray     #60                 // class java/lang/String
    3921: dup
    3922: iconst_0
    3923: ldc_w         #864                // String ⊂
    3926: aastore
    3927: dup
    3928: iconst_1
    3929: ldc_w         #866                // String &sub;
    3932: aastore
    3933: aastore
    3934: dup
    3935: bipush        105
    3937: iconst_2
    3938: anewarray     #60                 // class java/lang/String
    3941: dup
    3942: iconst_0
    3943: ldc_w         #868                // String ⊃
    3946: aastore
    3947: dup
    3948: iconst_1
    3949: ldc_w         #870                // String &sup;
    3952: aastore
    3953: aastore
    3954: dup
    3955: bipush        106
    3957: iconst_2
    3958: anewarray     #60                 // class java/lang/String
    3961: dup
    3962: iconst_0
    3963: ldc_w         #872                // String ⊄
    3966: aastore
    3967: dup
    3968: iconst_1
    3969: ldc_w         #874                // String &nsub;
    3972: aastore
    3973: aastore
    3974: dup
    3975: bipush        107
    3977: iconst_2
    3978: anewarray     #60                 // class java/lang/String
    3981: dup
    3982: iconst_0
    3983: ldc_w         #876                // String ⊆
    3986: aastore
    3987: dup
    3988: iconst_1
    3989: ldc_w         #878                // String &sube;
    3992: aastore
    3993: aastore
    3994: dup
    3995: bipush        108
    3997: iconst_2
    3998: anewarray     #60                 // class java/lang/String
    4001: dup
    4002: iconst_0
    4003: ldc_w         #880                // String ⊇
    4006: aastore
    4007: dup
    4008: iconst_1
    4009: ldc_w         #882                // String &supe;
    4012: aastore
    4013: aastore
    4014: dup
    4015: bipush        109
    4017: iconst_2
    4018: anewarray     #60                 // class java/lang/String
    4021: dup
    4022: iconst_0
    4023: ldc_w         #884                // String ⊕
    4026: aastore
    4027: dup
    4028: iconst_1
    4029: ldc_w         #886                // String &oplus;
    4032: aastore
    4033: aastore
    4034: dup
    4035: bipush        110
    4037: iconst_2
    4038: anewarray     #60                 // class java/lang/String
    4041: dup
    4042: iconst_0
    4043: ldc_w         #888                // String ⊗
    4046: aastore
    4047: dup
    4048: iconst_1
    4049: ldc_w         #890                // String &otimes;
    4052: aastore
    4053: aastore
    4054: dup
    4055: bipush        111
    4057: iconst_2
    4058: anewarray     #60                 // class java/lang/String
    4061: dup
    4062: iconst_0
    4063: ldc_w         #892                // String ⊥
    4066: aastore
    4067: dup
    4068: iconst_1
    4069: ldc_w         #894                // String &perp;
    4072: aastore
    4073: aastore
    4074: dup
    4075: bipush        112
    4077: iconst_2
    4078: anewarray     #60                 // class java/lang/String
    4081: dup
    4082: iconst_0
    4083: ldc_w         #896                // String ⋅
    4086: aastore
    4087: dup
    4088: iconst_1
    4089: ldc_w         #898                // String &sdot;
    4092: aastore
    4093: aastore
    4094: dup
    4095: bipush        113
    4097: iconst_2
    4098: anewarray     #60                 // class java/lang/String
    4101: dup
    4102: iconst_0
    4103: ldc_w         #900                // String ⌈
    4106: aastore
    4107: dup
    4108: iconst_1
    4109: ldc_w         #902                // String &lceil;
    4112: aastore
    4113: aastore
    4114: dup
    4115: bipush        114
    4117: iconst_2
    4118: anewarray     #60                 // class java/lang/String
    4121: dup
    4122: iconst_0
    4123: ldc_w         #904                // String ⌉
    4126: aastore
    4127: dup
    4128: iconst_1
    4129: ldc_w         #906                // String &rceil;
    4132: aastore
    4133: aastore
    4134: dup
    4135: bipush        115
    4137: iconst_2
    4138: anewarray     #60                 // class java/lang/String
    4141: dup
    4142: iconst_0
    4143: ldc_w         #908                // String ⌊
    4146: aastore
    4147: dup
    4148: iconst_1
    4149: ldc_w         #910                // String &lfloor;
    4152: aastore
    4153: aastore
    4154: dup
    4155: bipush        116
    4157: iconst_2
    4158: anewarray     #60                 // class java/lang/String
    4161: dup
    4162: iconst_0
    4163: ldc_w         #912                // String ⌋
    4166: aastore
    4167: dup
    4168: iconst_1
    4169: ldc_w         #914                // String &rfloor;
    4172: aastore
    4173: aastore
    4174: dup
    4175: bipush        117
    4177: iconst_2
    4178: anewarray     #60                 // class java/lang/String
    4181: dup
    4182: iconst_0
    4183: ldc_w         #916                // String 〈
    4186: aastore
    4187: dup
    4188: iconst_1
    4189: ldc_w         #918                // String &lang;
    4192: aastore
    4193: aastore
    4194: dup
    4195: bipush        118
    4197: iconst_2
    4198: anewarray     #60                 // class java/lang/String
    4201: dup
    4202: iconst_0
    4203: ldc_w         #920                // String 〉
    4206: aastore
    4207: dup
    4208: iconst_1
    4209: ldc_w         #922                // String &rang;
    4212: aastore
    4213: aastore
    4214: dup
    4215: bipush        119
    4217: iconst_2
    4218: anewarray     #60                 // class java/lang/String
    4221: dup
    4222: iconst_0
    4223: ldc_w         #924                // String ◊
    4226: aastore
    4227: dup
    4228: iconst_1
    4229: ldc_w         #926                // String &loz;
    4232: aastore
    4233: aastore
    4234: dup
    4235: bipush        120
    4237: iconst_2
    4238: anewarray     #60                 // class java/lang/String
    4241: dup
    4242: iconst_0
    4243: ldc_w         #928                // String ♠
    4246: aastore
    4247: dup
    4248: iconst_1
    4249: ldc_w         #930                // String &spades;
    4252: aastore
    4253: aastore
    4254: dup
    4255: bipush        121
    4257: iconst_2
    4258: anewarray     #60                 // class java/lang/String
    4261: dup
    4262: iconst_0
    4263: ldc_w         #932                // String ♣
    4266: aastore
    4267: dup
    4268: iconst_1
    4269: ldc_w         #934                // String &clubs;
    4272: aastore
    4273: aastore
    4274: dup
    4275: bipush        122
    4277: iconst_2
    4278: anewarray     #60                 // class java/lang/String
    4281: dup
    4282: iconst_0
    4283: ldc_w         #936                // String ♥
    4286: aastore
    4287: dup
    4288: iconst_1
    4289: ldc_w         #938                // String &hearts;
    4292: aastore
    4293: aastore
    4294: dup
    4295: bipush        123
    4297: iconst_2
    4298: anewarray     #60                 // class java/lang/String
    4301: dup
    4302: iconst_0
    4303: ldc_w         #940                // String ♦
    4306: aastore
    4307: dup
    4308: iconst_1
    4309: ldc_w         #942                // String &diams;
    4312: aastore
    4313: aastore
    4314: dup
    4315: bipush        124
    4317: iconst_2
    4318: anewarray     #60                 // class java/lang/String
    4321: dup
    4322: iconst_0
    4323: ldc_w         #944                // String Œ
    4326: aastore
    4327: dup
    4328: iconst_1
    4329: ldc_w         #946                // String &OElig;
    4332: aastore
    4333: aastore
    4334: dup
    4335: bipush        125
    4337: iconst_2
    4338: anewarray     #60                 // class java/lang/String
    4341: dup
    4342: iconst_0
    4343: ldc_w         #948                // String œ
    4346: aastore
    4347: dup
    4348: iconst_1
    4349: ldc_w         #950                // String &oelig;
    4352: aastore
    4353: aastore
    4354: dup
    4355: bipush        126
    4357: iconst_2
    4358: anewarray     #60                 // class java/lang/String
    4361: dup
    4362: iconst_0
    4363: ldc_w         #952                // String Š
    4366: aastore
    4367: dup
    4368: iconst_1
    4369: ldc_w         #954                // String &Scaron;
    4372: aastore
    4373: aastore
    4374: dup
    4375: bipush        127
    4377: iconst_2
    4378: anewarray     #60                 // class java/lang/String
    4381: dup
    4382: iconst_0
    4383: ldc_w         #956                // String š
    4386: aastore
    4387: dup
    4388: iconst_1
    4389: ldc_w         #958                // String &scaron;
    4392: aastore
    4393: aastore
    4394: dup
    4395: sipush        128
    4398: iconst_2
    4399: anewarray     #60                 // class java/lang/String
    4402: dup
    4403: iconst_0
    4404: ldc_w         #960                // String Ÿ
    4407: aastore
    4408: dup
    4409: iconst_1
    4410: ldc_w         #962                // String &Yuml;
    4413: aastore
    4414: aastore
    4415: dup
    4416: sipush        129
    4419: iconst_2
    4420: anewarray     #60                 // class java/lang/String
    4423: dup
    4424: iconst_0
    4425: ldc_w         #964                // String ˆ
    4428: aastore
    4429: dup
    4430: iconst_1
    4431: ldc_w         #966                // String &circ;
    4434: aastore
    4435: aastore
    4436: dup
    4437: sipush        130
    4440: iconst_2
    4441: anewarray     #60                 // class java/lang/String
    4444: dup
    4445: iconst_0
    4446: ldc_w         #968                // String ˜
    4449: aastore
    4450: dup
    4451: iconst_1
    4452: ldc_w         #970                // String &tilde;
    4455: aastore
    4456: aastore
    4457: dup
    4458: sipush        131
    4461: iconst_2
    4462: anewarray     #60                 // class java/lang/String
    4465: dup
    4466: iconst_0
    4467: ldc_w         #972                // String  
    4470: aastore
    4471: dup
    4472: iconst_1
    4473: ldc_w         #974                // String &ensp;
    4476: aastore
    4477: aastore
    4478: dup
    4479: sipush        132
    4482: iconst_2
    4483: anewarray     #60                 // class java/lang/String
    4486: dup
    4487: iconst_0
    4488: ldc_w         #976                // String  
    4491: aastore
    4492: dup
    4493: iconst_1
    4494: ldc_w         #978                // String &emsp;
    4497: aastore
    4498: aastore
    4499: dup
    4500: sipush        133
    4503: iconst_2
    4504: anewarray     #60                 // class java/lang/String
    4507: dup
    4508: iconst_0
    4509: ldc_w         #980                // String  
    4512: aastore
    4513: dup
    4514: iconst_1
    4515: ldc_w         #982                // String &thinsp;
    4518: aastore
    4519: aastore
    4520: dup
    4521: sipush        134
    4524: iconst_2
    4525: anewarray     #60                 // class java/lang/String
    4528: dup
    4529: iconst_0
    4530: ldc_w         #984                // String ‌
    4533: aastore
    4534: dup
    4535: iconst_1
    4536: ldc_w         #986                // String &zwnj;
    4539: aastore
    4540: aastore
    4541: dup
    4542: sipush        135
    4545: iconst_2
    4546: anewarray     #60                 // class java/lang/String
    4549: dup
    4550: iconst_0
    4551: ldc_w         #988                // String ‍
    4554: aastore
    4555: dup
    4556: iconst_1
    4557: ldc_w         #990                // String &zwj;
    4560: aastore
    4561: aastore
    4562: dup
    4563: sipush        136
    4566: iconst_2
    4567: anewarray     #60                 // class java/lang/String
    4570: dup
    4571: iconst_0
    4572: ldc_w         #992                // String ‎
    4575: aastore
    4576: dup
    4577: iconst_1
    4578: ldc_w         #994                // String &lrm;
    4581: aastore
    4582: aastore
    4583: dup
    4584: sipush        137
    4587: iconst_2
    4588: anewarray     #60                 // class java/lang/String
    4591: dup
    4592: iconst_0
    4593: ldc_w         #996                // String ‏
    4596: aastore
    4597: dup
    4598: iconst_1
    4599: ldc_w         #998                // String &rlm;
    4602: aastore
    4603: aastore
    4604: dup
    4605: sipush        138
    4608: iconst_2
    4609: anewarray     #60                 // class java/lang/String
    4612: dup
    4613: iconst_0
    4614: ldc_w         #1000               // String –
    4617: aastore
    4618: dup
    4619: iconst_1
    4620: ldc_w         #1002               // String &ndash;
    4623: aastore
    4624: aastore
    4625: dup
    4626: sipush        139
    4629: iconst_2
    4630: anewarray     #60                 // class java/lang/String
    4633: dup
    4634: iconst_0
    4635: ldc_w         #1004               // String —
    4638: aastore
    4639: dup
    4640: iconst_1
    4641: ldc_w         #1006               // String &mdash;
    4644: aastore
    4645: aastore
    4646: dup
    4647: sipush        140
    4650: iconst_2
    4651: anewarray     #60                 // class java/lang/String
    4654: dup
    4655: iconst_0
    4656: ldc_w         #1008               // String ‘
    4659: aastore
    4660: dup
    4661: iconst_1
    4662: ldc_w         #1010               // String &lsquo;
    4665: aastore
    4666: aastore
    4667: dup
    4668: sipush        141
    4671: iconst_2
    4672: anewarray     #60                 // class java/lang/String
    4675: dup
    4676: iconst_0
    4677: ldc_w         #1012               // String ’
    4680: aastore
    4681: dup
    4682: iconst_1
    4683: ldc_w         #1014               // String &rsquo;
    4686: aastore
    4687: aastore
    4688: dup
    4689: sipush        142
    4692: iconst_2
    4693: anewarray     #60                 // class java/lang/String
    4696: dup
    4697: iconst_0
    4698: ldc_w         #1016               // String ‚
    4701: aastore
    4702: dup
    4703: iconst_1
    4704: ldc_w         #1018               // String &sbquo;
    4707: aastore
    4708: aastore
    4709: dup
    4710: sipush        143
    4713: iconst_2
    4714: anewarray     #60                 // class java/lang/String
    4717: dup
    4718: iconst_0
    4719: ldc_w         #1020               // String “
    4722: aastore
    4723: dup
    4724: iconst_1
    4725: ldc_w         #1022               // String &ldquo;
    4728: aastore
    4729: aastore
    4730: dup
    4731: sipush        144
    4734: iconst_2
    4735: anewarray     #60                 // class java/lang/String
    4738: dup
    4739: iconst_0
    4740: ldc_w         #1024               // String ”
    4743: aastore
    4744: dup
    4745: iconst_1
    4746: ldc_w         #1026               // String &rdquo;
    4749: aastore
    4750: aastore
    4751: dup
    4752: sipush        145
    4755: iconst_2
    4756: anewarray     #60                 // class java/lang/String
    4759: dup
    4760: iconst_0
    4761: ldc_w         #1028               // String „
    4764: aastore
    4765: dup
    4766: iconst_1
    4767: ldc_w         #1030               // String &bdquo;
    4770: aastore
    4771: aastore
    4772: dup
    4773: sipush        146
    4776: iconst_2
    4777: anewarray     #60                 // class java/lang/String
    4780: dup
    4781: iconst_0
    4782: ldc_w         #1032               // String †
    4785: aastore
    4786: dup
    4787: iconst_1
    4788: ldc_w         #1034               // String &dagger;
    4791: aastore
    4792: aastore
    4793: dup
    4794: sipush        147
    4797: iconst_2
    4798: anewarray     #60                 // class java/lang/String
    4801: dup
    4802: iconst_0
    4803: ldc_w         #1036               // String ‡
    4806: aastore
    4807: dup
    4808: iconst_1
    4809: ldc_w         #1038               // String &Dagger;
    4812: aastore
    4813: aastore
    4814: dup
    4815: sipush        148
    4818: iconst_2
    4819: anewarray     #60                 // class java/lang/String
    4822: dup
    4823: iconst_0
    4824: ldc_w         #1040               // String ‰
    4827: aastore
    4828: dup
    4829: iconst_1
    4830: ldc_w         #1042               // String &permil;
    4833: aastore
    4834: aastore
    4835: dup
    4836: sipush        149
    4839: iconst_2
    4840: anewarray     #60                 // class java/lang/String
    4843: dup
    4844: iconst_0
    4845: ldc_w         #1044               // String ‹
    4848: aastore
    4849: dup
    4850: iconst_1
    4851: ldc_w         #1046               // String &lsaquo;
    4854: aastore
    4855: aastore
    4856: dup
    4857: sipush        150
    4860: iconst_2
    4861: anewarray     #60                 // class java/lang/String
    4864: dup
    4865: iconst_0
    4866: ldc_w         #1048               // String ›
    4869: aastore
    4870: dup
    4871: iconst_1
    4872: ldc_w         #1050               // String &rsaquo;
    4875: aastore
    4876: aastore
    4877: dup
    4878: sipush        151
    4881: iconst_2
    4882: anewarray     #60                 // class java/lang/String
    4885: dup
    4886: iconst_0
    4887: ldc_w         #1052               // String €
    4890: aastore
    4891: dup
    4892: iconst_1
    4893: ldc_w         #1054               // String &euro;
    4896: aastore
    4897: aastore
    4898: putstatic     #35                 // Field HTML40_EXTENDED_ESCAPE:[[Ljava/lang/String;
    4901: getstatic     #35                 // Field HTML40_EXTENDED_ESCAPE:[[Ljava/lang/String;
    4904: invokestatic  #446                // Method invert:([[Ljava/lang/String;)[[Ljava/lang/String;
    4907: putstatic     #37                 // Field HTML40_EXTENDED_UNESCAPE:[[Ljava/lang/String;
    4910: iconst_4
    4911: anewarray     #58                 // class "[Ljava/lang/String;"
    4914: dup
    4915: iconst_0
    4916: iconst_2
    4917: anewarray     #60                 // class java/lang/String
    4920: dup
    4921: iconst_0
    4922: ldc_w         #1056               // String \"
    4925: aastore
    4926: dup
    4927: iconst_1
    4928: ldc_w         #1058               // String &quot;
    4931: aastore
    4932: aastore
    4933: dup
    4934: iconst_1
    4935: iconst_2
    4936: anewarray     #60                 // class java/lang/String
    4939: dup
    4940: iconst_0
    4941: ldc_w         #1060               // String &
    4944: aastore
    4945: dup
    4946: iconst_1
    4947: ldc_w         #1062               // String &amp;
    4950: aastore
    4951: aastore
    4952: dup
    4953: iconst_2
    4954: iconst_2
    4955: anewarray     #60                 // class java/lang/String
    4958: dup
    4959: iconst_0
    4960: ldc_w         #1064               // String <
    4963: aastore
    4964: dup
    4965: iconst_1
    4966: ldc_w         #1066               // String &lt;
    4969: aastore
    4970: aastore
    4971: dup
    4972: iconst_3
    4973: iconst_2
    4974: anewarray     #60                 // class java/lang/String
    4977: dup
    4978: iconst_0
    4979: ldc_w         #1068               // String >
    4982: aastore
    4983: dup
    4984: iconst_1
    4985: ldc_w         #1070               // String &gt;
    4988: aastore
    4989: aastore
    4990: putstatic     #39                 // Field BASIC_ESCAPE:[[Ljava/lang/String;
    4993: getstatic     #39                 // Field BASIC_ESCAPE:[[Ljava/lang/String;
    4996: invokestatic  #446                // Method invert:([[Ljava/lang/String;)[[Ljava/lang/String;
    4999: putstatic     #41                 // Field BASIC_UNESCAPE:[[Ljava/lang/String;
    5002: iconst_1
    5003: anewarray     #58                 // class "[Ljava/lang/String;"
    5006: dup
    5007: iconst_0
    5008: iconst_2
    5009: anewarray     #60                 // class java/lang/String
    5012: dup
    5013: iconst_0
    5014: ldc_w         #1072               // String \'
    5017: aastore
    5018: dup
    5019: iconst_1
    5020: ldc_w         #1074               // String &apos;
    5023: aastore
    5024: aastore
    5025: putstatic     #43                 // Field APOS_ESCAPE:[[Ljava/lang/String;
    5028: getstatic     #43                 // Field APOS_ESCAPE:[[Ljava/lang/String;
    5031: invokestatic  #446                // Method invert:([[Ljava/lang/String;)[[Ljava/lang/String;
    5034: putstatic     #45                 // Field APOS_UNESCAPE:[[Ljava/lang/String;
    5037: iconst_5
    5038: anewarray     #58                 // class "[Ljava/lang/String;"
    5041: dup
    5042: iconst_0
    5043: iconst_2
    5044: anewarray     #60                 // class java/lang/String
    5047: dup
    5048: iconst_0
    5049: ldc_w         #1076               // String \b
    5052: aastore
    5053: dup
    5054: iconst_1
    5055: ldc_w         #1078               // String \\b
    5058: aastore
    5059: aastore
    5060: dup
    5061: iconst_1
    5062: iconst_2
    5063: anewarray     #60                 // class java/lang/String
    5066: dup
    5067: iconst_0
    5068: ldc_w         #1080               // String \n
    5071: aastore
    5072: dup
    5073: iconst_1
    5074: ldc_w         #1082               // String \\n
    5077: aastore
    5078: aastore
    5079: dup
    5080: iconst_2
    5081: iconst_2
    5082: anewarray     #60                 // class java/lang/String
    5085: dup
    5086: iconst_0
    5087: ldc_w         #1084               // String \t
    5090: aastore
    5091: dup
    5092: iconst_1
    5093: ldc_w         #1086               // String \\t
    5096: aastore
    5097: aastore
    5098: dup
    5099: iconst_3
    5100: iconst_2
    5101: anewarray     #60                 // class java/lang/String
    5104: dup
    5105: iconst_0
    5106: ldc_w         #1088               // String \f
    5109: aastore
    5110: dup
    5111: iconst_1
    5112: ldc_w         #1090               // String \\f
    5115: aastore
    5116: aastore
    5117: dup
    5118: iconst_4
    5119: iconst_2
    5120: anewarray     #60                 // class java/lang/String
    5123: dup
    5124: iconst_0
    5125: ldc_w         #1092               // String \r
    5128: aastore
    5129: dup
    5130: iconst_1
    5131: ldc_w         #1094               // String \\r
    5134: aastore
    5135: aastore
    5136: putstatic     #47                 // Field JAVA_CTRL_CHARS_ESCAPE:[[Ljava/lang/String;
    5139: getstatic     #47                 // Field JAVA_CTRL_CHARS_ESCAPE:[[Ljava/lang/String;
    5142: invokestatic  #446                // Method invert:([[Ljava/lang/String;)[[Ljava/lang/String;
    5145: putstatic     #49                 // Field JAVA_CTRL_CHARS_UNESCAPE:[[Ljava/lang/String;
    5148: return
}
