Compiled from "NumericEntityEscaper.java"
public class net.logstash.logback.encoder.org.apache.commons.lang3.text.translate.NumericEntityEscaper extends net.logstash.logback.encoder.org.apache.commons.lang3.text.translate.CodePointTranslator {
  private final int below;

  private final int above;

  private final boolean between;

  private net.logstash.logback.encoder.org.apache.commons.lang3.text.translate.NumericEntityEscaper(int, int, boolean);
    Code:
       0: aload_0
       1: invokespecial #16                 // Method net/logstash/logback/encoder/org/apache/commons/lang3/text/translate/CodePointTranslator."<init>":()V
       4: aload_0
       5: iload_1
       6: putfield      #18                 // Field below:I
       9: aload_0
      10: iload_2
      11: putfield      #20                 // Field above:I
      14: aload_0
      15: iload_3
      16: putfield      #22                 // Field between:Z
      19: return

  public net.logstash.logback.encoder.org.apache.commons.lang3.text.translate.NumericEntityEscaper();
    Code:
       0: aload_0
       1: iconst_0
       2: ldc           #25                 // int 2147483647
       4: iconst_1
       5: invokespecial #27                 // Method "<init>":(IIZ)V
       8: return

  public static net.logstash.logback.encoder.org.apache.commons.lang3.text.translate.NumericEntityEscaper below(int);
    Code:
       0: iload_0
       1: ldc           #25                 // int 2147483647
       3: invokestatic  #32                 // Method outsideOf:(II)Lnet/logstash/logback/encoder/org/apache/commons/lang3/text/translate/NumericEntityEscaper;
       6: areturn

  public static net.logstash.logback.encoder.org.apache.commons.lang3.text.translate.NumericEntityEscaper above(int);
    Code:
       0: iconst_0
       1: iload_0
       2: invokestatic  #32                 // Method outsideOf:(II)Lnet/logstash/logback/encoder/org/apache/commons/lang3/text/translate/NumericEntityEscaper;
       5: areturn

  public static net.logstash.logback.encoder.org.apache.commons.lang3.text.translate.NumericEntityEscaper between(int, int);
    Code:
       0: new           #2                  // class net/logstash/logback/encoder/org/apache/commons/lang3/text/translate/NumericEntityEscaper
       3: dup
       4: iload_0
       5: iload_1
       6: iconst_1
       7: invokespecial #27                 // Method "<init>":(IIZ)V
      10: areturn

  public static net.logstash.logback.encoder.org.apache.commons.lang3.text.translate.NumericEntityEscaper outsideOf(int, int);
    Code:
       0: new           #2                  // class net/logstash/logback/encoder/org/apache/commons/lang3/text/translate/NumericEntityEscaper
       3: dup
       4: iload_0
       5: iload_1
       6: iconst_0
       7: invokespecial #27                 // Method "<init>":(IIZ)V
      10: areturn

  public boolean translate(int, java.io.Writer) throws java.io.IOException;
    Code:
       0: aload_0
       1: getfield      #22                 // Field between:Z
       4: ifeq          25
       7: iload_1
       8: aload_0
       9: getfield      #18                 // Field below:I
      12: if_icmplt     23
      15: iload_1
      16: aload_0
      17: getfield      #20                 // Field above:I
      20: if_icmple     43
      23: iconst_0
      24: ireturn
      25: iload_1
      26: aload_0
      27: getfield      #18                 // Field below:I
      30: if_icmplt     43
      33: iload_1
      34: aload_0
      35: getfield      #20                 // Field above:I
      38: if_icmpgt     43
      41: iconst_0
      42: ireturn
      43: aload_2
      44: ldc           #41                 // String &#
      46: invokevirtual #47                 // Method java/io/Writer.write:(Ljava/lang/String;)V
      49: aload_2
      50: iload_1
      51: bipush        10
      53: invokestatic  #53                 // Method java/lang/Integer.toString:(II)Ljava/lang/String;
      56: invokevirtual #47                 // Method java/io/Writer.write:(Ljava/lang/String;)V
      59: aload_2
      60: bipush        59
      62: invokevirtual #56                 // Method java/io/Writer.write:(I)V
      65: iconst_1
      66: ireturn
}
