Compiled from "SslHandler.java"
class org.jboss.netty.handler.ssl.SslHandler$1 implements org.jboss.netty.util.TimerTask {
  final org.jboss.netty.channel.Channel val$channel;

  final org.jboss.netty.handler.ssl.SslHandler this$0;

  org.jboss.netty.handler.ssl.SslHandler$1(org.jboss.netty.handler.ssl.SslHandler, org.jboss.netty.channel.Channel);
    Code:
       0: aload_0
       1: aload_1
       2: putfield      #1                  // Field this$0:Lorg/jboss/netty/handler/ssl/SslHandler;
       5: aload_0
       6: aload_2
       7: putfield      #2                  // Field val$channel:Lorg/jboss/netty/channel/Channel;
      10: aload_0
      11: invokespecial #3                  // Method java/lang/Object."<init>":()V
      14: return

  public void run(org.jboss.netty.util.Timeout) throws java.lang.Exception;
    Code:
       0: aload_0
       1: getfield      #1                  // Field this$0:Lorg/jboss/netty/handler/ssl/SslHandler;
       4: invokestatic  #4                  // Method org/jboss/netty/handler/ssl/SslHandler.access$000:(Lorg/jboss/netty/handler/ssl/SslHandler;)Lorg/jboss/netty/channel/ChannelFuture;
       7: astore_2
       8: aload_2
       9: ifnull        22
      12: aload_2
      13: invokeinterface #5,  1            // InterfaceMethod org/jboss/netty/channel/ChannelFuture.isDone:()Z
      18: ifeq          22
      21: return
      22: aload_0
      23: getfield      #1                  // Field this$0:Lorg/jboss/netty/handler/ssl/SslHandler;
      26: aload_0
      27: getfield      #2                  // Field val$channel:Lorg/jboss/netty/channel/Channel;
      30: new           #6                  // class javax/net/ssl/SSLException
      33: dup
      34: new           #7                  // class java/lang/StringBuilder
      37: dup
      38: invokespecial #8                  // Method java/lang/StringBuilder."<init>":()V
      41: ldc           #9                  // String Handshake did not complete within
      43: invokevirtual #10                 // Method java/lang/StringBuilder.append:(Ljava/lang/String;)Ljava/lang/StringBuilder;
      46: aload_0
      47: getfield      #1                  // Field this$0:Lorg/jboss/netty/handler/ssl/SslHandler;
      50: invokestatic  #11                 // Method org/jboss/netty/handler/ssl/SslHandler.access$100:(Lorg/jboss/netty/handler/ssl/SslHandler;)J
      53: invokevirtual #12                 // Method java/lang/StringBuilder.append:(J)Ljava/lang/StringBuilder;
      56: ldc           #13                 // String ms
      58: invokevirtual #10                 // Method java/lang/StringBuilder.append:(Ljava/lang/String;)Ljava/lang/StringBuilder;
      61: invokevirtual #14                 // Method java/lang/StringBuilder.toString:()Ljava/lang/String;
      64: invokespecial #15                 // Method javax/net/ssl/SSLException."<init>":(Ljava/lang/String;)V
      67: invokestatic  #16                 // Method org/jboss/netty/handler/ssl/SslHandler.access$200:(Lorg/jboss/netty/handler/ssl/SslHandler;Lorg/jboss/netty/channel/Channel;Ljavax/net/ssl/SSLException;)V
      70: return
}
