Compiled from "CompressorInputStream.java"
public abstract class io.dekorate.deps.commons.compress.compressors.CompressorInputStream extends java.io.InputStream {
  private long bytesRead;

  public io.dekorate.deps.commons.compress.compressors.CompressorInputStream();
    Code:
       0: aload_0
       1: invokespecial #11                 // Method java/io/InputStream."<init>":()V
       4: aload_0
       5: lconst_0
       6: putfield      #13                 // Field bytesRead:J
       9: return

  protected void count(int);
    Code:
       0: aload_0
       1: iload_1
       2: i2l
       3: invokevirtual #20                 // Method count:(J)V
       6: return

  protected void count(long);
    Code:
       0: lload_1
       1: ldc2_w        #23                 // long -1l
       4: lcmp
       5: ifeq          18
       8: aload_0
       9: aload_0
      10: getfield      #13                 // Field bytesRead:J
      13: lload_1
      14: ladd
      15: putfield      #13                 // Field bytesRead:J
      18: return

  protected void pushedBackBytes(long);
    Code:
       0: aload_0
       1: dup
       2: getfield      #13                 // Field bytesRead:J
       5: lload_1
       6: lsub
       7: putfield      #13                 // Field bytesRead:J
      10: return

  public int getCount();
    Code:
       0: aload_0
       1: getfield      #13                 // Field bytesRead:J
       4: l2i
       5: ireturn

  public long getBytesRead();
    Code:
       0: aload_0
       1: getfield      #13                 // Field bytesRead:J
       4: lreturn

  public long getUncompressedCount();
    Code:
       0: aload_0
       1: invokevirtual #34                 // Method getBytesRead:()J
       4: lreturn
}
