Compiled from "ModelMatcher.java"
class org.jboss.as.controller.transform.ModelMatcher {
  org.jboss.as.controller.transform.ModelMatcher();
    Code:
       0: aload_0
       1: invokespecial #1                  // Method java/lang/Object."<init>":()V
       4: return

  public static java.util.List<org.jboss.as.controller.transform.TransformRule> getRules(org.jboss.as.controller.registry.ImmutableManagementResourceRegistration, org.jboss.as.controller.registry.ImmutableManagementResourceRegistration);
    Code:
       0: aload_0
       1: getstatic     #2                  // Field org/jboss/as/controller/PathAddress.EMPTY_ADDRESS:Lorg/jboss/as/controller/PathAddress;
       4: invokestatic  #3                  // Method readModel:(Lorg/jboss/as/controller/registry/ImmutableManagementResourceRegistration;Lorg/jboss/as/controller/PathAddress;)Lorg/jboss/as/controller/transform/ModelMatcher$Model;
       7: astore_2
       8: aload_1
       9: getstatic     #2                  // Field org/jboss/as/controller/PathAddress.EMPTY_ADDRESS:Lorg/jboss/as/controller/PathAddress;
      12: invokestatic  #3                  // Method readModel:(Lorg/jboss/as/controller/registry/ImmutableManagementResourceRegistration;Lorg/jboss/as/controller/PathAddress;)Lorg/jboss/as/controller/transform/ModelMatcher$Model;
      15: astore_3
      16: aload_3
      17: aload_2
      18: invokevirtual #4                  // Method org/jboss/as/controller/transform/ModelMatcher$Model.isSame:(Lorg/jboss/as/controller/transform/ModelMatcher$Model;)Z
      21: ifeq          29
      24: aload_3
      25: invokevirtual #5                  // Method org/jboss/as/controller/transform/ModelMatcher$Model.toRules:()Ljava/util/List;
      28: areturn
      29: aload_3
      30: aload_2
      31: invokevirtual #6                  // Method org/jboss/as/controller/transform/ModelMatcher$Model.getMatchedRules:(Lorg/jboss/as/controller/transform/ModelMatcher$Model;)Ljava/util/List;
      34: areturn

  public static org.jboss.as.controller.transform.ModelMatcher$Model readModel(org.jboss.as.controller.registry.ImmutableManagementResourceRegistration, org.jboss.as.controller.PathAddress);
    Code:
       0: new           #7                  // class org/jboss/as/controller/transform/ModelMatcher$Model
       3: dup
       4: aload_1
       5: invokespecial #8                  // Method org/jboss/as/controller/transform/ModelMatcher$Model."<init>":(Lorg/jboss/as/controller/PathAddress;)V
       8: astore_2
       9: aload_0
      10: getstatic     #2                  // Field org/jboss/as/controller/PathAddress.EMPTY_ADDRESS:Lorg/jboss/as/controller/PathAddress;
      13: invokeinterface #9,  2            // InterfaceMethod org/jboss/as/controller/registry/ImmutableManagementResourceRegistration.getAttributeNames:(Lorg/jboss/as/controller/PathAddress;)Ljava/util/Set;
      18: astore_3
      19: aload_3
      20: invokeinterface #10,  1           // InterfaceMethod java/util/Set.iterator:()Ljava/util/Iterator;
      25: astore        4
      27: aload         4
      29: invokeinterface #11,  1           // InterfaceMethod java/util/Iterator.hasNext:()Z
      34: ifeq          58
      37: aload         4
      39: invokeinterface #12,  1           // InterfaceMethod java/util/Iterator.next:()Ljava/lang/Object;
      44: checkcast     #13                 // class java/lang/String
      47: astore        5
      49: aload_2
      50: aload         5
      52: invokevirtual #14                 // Method org/jboss/as/controller/transform/ModelMatcher$Model.addAttribute:(Ljava/lang/String;)V
      55: goto          27
      58: aload_0
      59: getstatic     #2                  // Field org/jboss/as/controller/PathAddress.EMPTY_ADDRESS:Lorg/jboss/as/controller/PathAddress;
      62: invokeinterface #15,  2           // InterfaceMethod org/jboss/as/controller/registry/ImmutableManagementResourceRegistration.getChildAddresses:(Lorg/jboss/as/controller/PathAddress;)Ljava/util/Set;
      67: invokeinterface #10,  1           // InterfaceMethod java/util/Set.iterator:()Ljava/util/Iterator;
      72: astore        4
      74: aload         4
      76: invokeinterface #11,  1           // InterfaceMethod java/util/Iterator.hasNext:()Z
      81: ifeq          146
      84: aload         4
      86: invokeinterface #12,  1           // InterfaceMethod java/util/Iterator.next:()Ljava/lang/Object;
      91: checkcast     #16                 // class org/jboss/as/controller/PathElement
      94: astore        5
      96: aload_0
      97: iconst_1
      98: anewarray     #16                 // class org/jboss/as/controller/PathElement
     101: dup
     102: iconst_0
     103: aload         5
     105: aastore
     106: invokestatic  #17                 // Method org/jboss/as/controller/PathAddress.pathAddress:([Lorg/jboss/as/controller/PathElement;)Lorg/jboss/as/controller/PathAddress;
     109: invokeinterface #18,  2           // InterfaceMethod org/jboss/as/controller/registry/ImmutableManagementResourceRegistration.getSubModel:(Lorg/jboss/as/controller/PathAddress;)Lorg/jboss/as/controller/registry/ImmutableManagementResourceRegistration;
     114: astore        6
     116: aload         6
     118: ifnull        143
     121: aload_2
     122: aload         6
     124: aload_1
     125: iconst_1
     126: anewarray     #16                 // class org/jboss/as/controller/PathElement
     129: dup
     130: iconst_0
     131: aload         5
     133: aastore
     134: invokevirtual #19                 // Method org/jboss/as/controller/PathAddress.append:([Lorg/jboss/as/controller/PathElement;)Lorg/jboss/as/controller/PathAddress;
     137: invokestatic  #3                  // Method readModel:(Lorg/jboss/as/controller/registry/ImmutableManagementResourceRegistration;Lorg/jboss/as/controller/PathAddress;)Lorg/jboss/as/controller/transform/ModelMatcher$Model;
     140: invokevirtual #20                 // Method org/jboss/as/controller/transform/ModelMatcher$Model.addChild:(Lorg/jboss/as/controller/transform/ModelMatcher$Model;)V
     143: goto          74
     146: aload_2
     147: areturn
}
