Compiled from "ResourceTransformationContextImpl.java"
class org.jboss.as.controller.transform.ResourceTransformationContextImpl$1 implements org.jboss.as.controller.transform.PathAddressTransformer$Builder {
  final org.jboss.as.controller.PathAddress val$childAddress;

  final org.jboss.as.controller.PathElement val$element;

  final org.jboss.as.controller.transform.ResourceTransformationContextImpl this$0;

  org.jboss.as.controller.transform.ResourceTransformationContextImpl$1(org.jboss.as.controller.transform.ResourceTransformationContextImpl, org.jboss.as.controller.PathAddress, org.jboss.as.controller.PathElement);
    Code:
       0: aload_0
       1: aload_1
       2: putfield      #1                  // Field this$0:Lorg/jboss/as/controller/transform/ResourceTransformationContextImpl;
       5: aload_0
       6: aload_2
       7: putfield      #2                  // Field val$childAddress:Lorg/jboss/as/controller/PathAddress;
      10: aload_0
      11: aload_3
      12: putfield      #3                  // Field val$element:Lorg/jboss/as/controller/PathElement;
      15: aload_0
      16: invokespecial #4                  // Method java/lang/Object."<init>":()V
      19: return

  public org.jboss.as.controller.PathAddress getOriginal();
    Code:
       0: aload_0
       1: getfield      #2                  // Field val$childAddress:Lorg/jboss/as/controller/PathAddress;
       4: areturn

  public org.jboss.as.controller.PathAddress getCurrent();
    Code:
       0: aload_0
       1: getfield      #1                  // Field this$0:Lorg/jboss/as/controller/transform/ResourceTransformationContextImpl;
       4: invokestatic  #5                  // Method org/jboss/as/controller/transform/ResourceTransformationContextImpl.access$500:(Lorg/jboss/as/controller/transform/ResourceTransformationContextImpl;)Lorg/jboss/as/controller/PathAddress;
       7: areturn

  public org.jboss.as.controller.PathAddress getRemaining();
    Code:
       0: getstatic     #6                  // Field org/jboss/as/controller/PathAddress.EMPTY_ADDRESS:Lorg/jboss/as/controller/PathAddress;
       3: iconst_1
       4: anewarray     #7                  // class org/jboss/as/controller/PathElement
       7: dup
       8: iconst_0
       9: aload_0
      10: getfield      #3                  // Field val$element:Lorg/jboss/as/controller/PathElement;
      13: aastore
      14: invokevirtual #8                  // Method org/jboss/as/controller/PathAddress.append:([Lorg/jboss/as/controller/PathElement;)Lorg/jboss/as/controller/PathAddress;
      17: areturn

  public org.jboss.as.controller.PathAddress next(org.jboss.as.controller.PathElement...);
    Code:
       0: aload_0
       1: getfield      #1                  // Field this$0:Lorg/jboss/as/controller/transform/ResourceTransformationContextImpl;
       4: invokestatic  #5                  // Method org/jboss/as/controller/transform/ResourceTransformationContextImpl.access$500:(Lorg/jboss/as/controller/transform/ResourceTransformationContextImpl;)Lorg/jboss/as/controller/PathAddress;
       7: aload_1
       8: invokevirtual #8                  // Method org/jboss/as/controller/PathAddress.append:([Lorg/jboss/as/controller/PathElement;)Lorg/jboss/as/controller/PathAddress;
      11: areturn
}
