Compiled from "TransformerRegistry.java"
public class org.jboss.as.controller.transform.TransformerRegistry$TransformersSubRegistrationImpl implements org.jboss.as.controller.transform.TransformersSubRegistration {
  private final org.jboss.as.controller.PathAddress current;

  private final org.jboss.as.controller.ModelVersionRange range;

  private final org.jboss.as.controller.registry.GlobalTransformerRegistry registry;

  public org.jboss.as.controller.transform.TransformerRegistry$TransformersSubRegistrationImpl(org.jboss.as.controller.ModelVersionRange, org.jboss.as.controller.registry.GlobalTransformerRegistry, org.jboss.as.controller.PathAddress);
    Code:
       0: aload_0
       1: invokespecial #1                  // Method java/lang/Object."<init>":()V
       4: aload_0
       5: aload_1
       6: putfield      #2                  // Field range:Lorg/jboss/as/controller/ModelVersionRange;
       9: aload_0
      10: aload_2
      11: putfield      #3                  // Field registry:Lorg/jboss/as/controller/registry/GlobalTransformerRegistry;
      14: aload_0
      15: aload_3
      16: putfield      #4                  // Field current:Lorg/jboss/as/controller/PathAddress;
      19: return

  public org.jboss.as.controller.transform.TransformersSubRegistration registerSubResource(org.jboss.as.controller.PathElement);
    Code:
       0: aload_0
       1: aload_1
       2: getstatic     #5                  // Field org/jboss/as/controller/transform/ResourceTransformer.DEFAULT:Lorg/jboss/as/controller/transform/ResourceTransformer;
       5: getstatic     #6                  // Field org/jboss/as/controller/transform/OperationTransformer.DEFAULT:Lorg/jboss/as/controller/transform/OperationTransformer;
       8: invokevirtual #7                  // Method registerSubResource:(Lorg/jboss/as/controller/PathElement;Lorg/jboss/as/controller/transform/ResourceTransformer;Lorg/jboss/as/controller/transform/OperationTransformer;)Lorg/jboss/as/controller/transform/TransformersSubRegistration;
      11: areturn

  public org.jboss.as.controller.transform.TransformersSubRegistration registerSubResource(org.jboss.as.controller.PathElement, boolean);
    Code:
       0: iload_2
       1: ifeq          86
       4: aload_0
       5: getfield      #4                  // Field current:Lorg/jboss/as/controller/PathAddress;
       8: iconst_1
       9: anewarray     #8                  // class org/jboss/as/controller/PathElement
      12: dup
      13: iconst_0
      14: aload_1
      15: aastore
      16: invokevirtual #9                  // Method org/jboss/as/controller/PathAddress.append:([Lorg/jboss/as/controller/PathElement;)Lorg/jboss/as/controller/PathAddress;
      19: astore_3
      20: aload_0
      21: getfield      #2                  // Field range:Lorg/jboss/as/controller/ModelVersionRange;
      24: invokeinterface #10,  1           // InterfaceMethod org/jboss/as/controller/ModelVersionRange.getVersions:()[Lorg/jboss/as/controller/ModelVersion;
      29: astore        4
      31: aload         4
      33: arraylength
      34: istore        5
      36: iconst_0
      37: istore        6
      39: iload         6
      41: iload         5
      43: if_icmpge     69
      46: aload         4
      48: iload         6
      50: aaload
      51: astore        7
      53: aload_0
      54: getfield      #3                  // Field registry:Lorg/jboss/as/controller/registry/GlobalTransformerRegistry;
      57: aload_3
      58: aload         7
      60: invokevirtual #11                 // Method org/jboss/as/controller/registry/GlobalTransformerRegistry.createDiscardingChildRegistry:(Lorg/jboss/as/controller/PathAddress;Lorg/jboss/as/controller/ModelVersion;)V
      63: iinc          6, 1
      66: goto          39
      69: new           #12                 // class org/jboss/as/controller/transform/TransformerRegistry$TransformersSubRegistrationImpl
      72: dup
      73: aload_0
      74: getfield      #2                  // Field range:Lorg/jboss/as/controller/ModelVersionRange;
      77: aload_0
      78: getfield      #3                  // Field registry:Lorg/jboss/as/controller/registry/GlobalTransformerRegistry;
      81: aload_3
      82: invokespecial #13                 // Method "<init>":(Lorg/jboss/as/controller/ModelVersionRange;Lorg/jboss/as/controller/registry/GlobalTransformerRegistry;Lorg/jboss/as/controller/PathAddress;)V
      85: areturn
      86: aload_0
      87: aload_1
      88: getstatic     #5                  // Field org/jboss/as/controller/transform/ResourceTransformer.DEFAULT:Lorg/jboss/as/controller/transform/ResourceTransformer;
      91: getstatic     #6                  // Field org/jboss/as/controller/transform/OperationTransformer.DEFAULT:Lorg/jboss/as/controller/transform/OperationTransformer;
      94: invokevirtual #7                  // Method registerSubResource:(Lorg/jboss/as/controller/PathElement;Lorg/jboss/as/controller/transform/ResourceTransformer;Lorg/jboss/as/controller/transform/OperationTransformer;)Lorg/jboss/as/controller/transform/TransformersSubRegistration;
      97: areturn

  public org.jboss.as.controller.transform.TransformersSubRegistration registerSubResource(org.jboss.as.controller.PathElement, org.jboss.as.controller.transform.OperationTransformer);
    Code:
       0: aload_0
       1: aload_1
       2: getstatic     #5                  // Field org/jboss/as/controller/transform/ResourceTransformer.DEFAULT:Lorg/jboss/as/controller/transform/ResourceTransformer;
       5: aload_2
       6: invokevirtual #7                  // Method registerSubResource:(Lorg/jboss/as/controller/PathElement;Lorg/jboss/as/controller/transform/ResourceTransformer;Lorg/jboss/as/controller/transform/OperationTransformer;)Lorg/jboss/as/controller/transform/TransformersSubRegistration;
       9: areturn

  public org.jboss.as.controller.transform.TransformersSubRegistration registerSubResource(org.jboss.as.controller.PathElement, org.jboss.as.controller.transform.ResourceTransformer);
    Code:
       0: aload_0
       1: aload_1
       2: aload_2
       3: getstatic     #6                  // Field org/jboss/as/controller/transform/OperationTransformer.DEFAULT:Lorg/jboss/as/controller/transform/OperationTransformer;
       6: invokevirtual #7                  // Method registerSubResource:(Lorg/jboss/as/controller/PathElement;Lorg/jboss/as/controller/transform/ResourceTransformer;Lorg/jboss/as/controller/transform/OperationTransformer;)Lorg/jboss/as/controller/transform/TransformersSubRegistration;
       9: areturn

  public org.jboss.as.controller.transform.TransformersSubRegistration registerSubResource(org.jboss.as.controller.PathElement, org.jboss.as.controller.transform.CombinedTransformer);
    Code:
       0: aload_0
       1: aload_1
       2: aload_2
       3: aload_2
       4: invokevirtual #7                  // Method registerSubResource:(Lorg/jboss/as/controller/PathElement;Lorg/jboss/as/controller/transform/ResourceTransformer;Lorg/jboss/as/controller/transform/OperationTransformer;)Lorg/jboss/as/controller/transform/TransformersSubRegistration;
       7: areturn

  public org.jboss.as.controller.transform.TransformersSubRegistration registerSubResource(org.jboss.as.controller.PathElement, org.jboss.as.controller.transform.ResourceTransformer, org.jboss.as.controller.transform.OperationTransformer);
    Code:
       0: aload_0
       1: aload_1
       2: getstatic     #14                 // Field org/jboss/as/controller/transform/PathAddressTransformer.DEFAULT:Lorg/jboss/as/controller/transform/PathAddressTransformer;
       5: aload_2
       6: aload_3
       7: invokevirtual #15                 // Method registerSubResource:(Lorg/jboss/as/controller/PathElement;Lorg/jboss/as/controller/transform/PathAddressTransformer;Lorg/jboss/as/controller/transform/ResourceTransformer;Lorg/jboss/as/controller/transform/OperationTransformer;)Lorg/jboss/as/controller/transform/TransformersSubRegistration;
      10: areturn

  public org.jboss.as.controller.transform.TransformersSubRegistration registerSubResource(org.jboss.as.controller.PathElement, org.jboss.as.controller.transform.PathAddressTransformer, org.jboss.as.controller.transform.ResourceTransformer, org.jboss.as.controller.transform.OperationTransformer);
    Code:
       0: aload_0
       1: aload_1
       2: aload_2
       3: aload_3
       4: aload         4
       6: iconst_0
       7: iconst_0
       8: invokevirtual #16                 // Method registerSubResource:(Lorg/jboss/as/controller/PathElement;Lorg/jboss/as/controller/transform/PathAddressTransformer;Lorg/jboss/as/controller/transform/ResourceTransformer;Lorg/jboss/as/controller/transform/OperationTransformer;ZZ)Lorg/jboss/as/controller/transform/TransformersSubRegistration;
      11: areturn

  public org.jboss.as.controller.transform.TransformersSubRegistration registerSubResource(org.jboss.as.controller.PathElement, org.jboss.as.controller.transform.PathAddressTransformer, org.jboss.as.controller.transform.ResourceTransformer, org.jboss.as.controller.transform.OperationTransformer, boolean, boolean);
    Code:
       0: aload_0
       1: getfield      #4                  // Field current:Lorg/jboss/as/controller/PathAddress;
       4: iconst_1
       5: anewarray     #8                  // class org/jboss/as/controller/PathElement
       8: dup
       9: iconst_0
      10: aload_1
      11: aastore
      12: invokevirtual #9                  // Method org/jboss/as/controller/PathAddress.append:([Lorg/jboss/as/controller/PathElement;)Lorg/jboss/as/controller/PathAddress;
      15: astore        7
      17: aload_0
      18: getfield      #2                  // Field range:Lorg/jboss/as/controller/ModelVersionRange;
      21: invokeinterface #10,  1           // InterfaceMethod org/jboss/as/controller/ModelVersionRange.getVersions:()[Lorg/jboss/as/controller/ModelVersion;
      26: astore        8
      28: aload         8
      30: arraylength
      31: istore        9
      33: iconst_0
      34: istore        10
      36: iload         10
      38: iload         9
      40: if_icmpge     75
      43: aload         8
      45: iload         10
      47: aaload
      48: astore        11
      50: aload_0
      51: getfield      #3                  // Field registry:Lorg/jboss/as/controller/registry/GlobalTransformerRegistry;
      54: aload         7
      56: aload         11
      58: aload_2
      59: aload_3
      60: aload         4
      62: iload         5
      64: iload         6
      66: invokevirtual #17                 // Method org/jboss/as/controller/registry/GlobalTransformerRegistry.createChildRegistry:(Lorg/jboss/as/controller/PathAddress;Lorg/jboss/as/controller/ModelVersion;Lorg/jboss/as/controller/transform/PathAddressTransformer;Lorg/jboss/as/controller/transform/ResourceTransformer;Lorg/jboss/as/controller/transform/OperationTransformer;ZZ)V
      69: iinc          10, 1
      72: goto          36
      75: new           #12                 // class org/jboss/as/controller/transform/TransformerRegistry$TransformersSubRegistrationImpl
      78: dup
      79: aload_0
      80: getfield      #2                  // Field range:Lorg/jboss/as/controller/ModelVersionRange;
      83: aload_0
      84: getfield      #3                  // Field registry:Lorg/jboss/as/controller/registry/GlobalTransformerRegistry;
      87: aload         7
      89: invokespecial #13                 // Method "<init>":(Lorg/jboss/as/controller/ModelVersionRange;Lorg/jboss/as/controller/registry/GlobalTransformerRegistry;Lorg/jboss/as/controller/PathAddress;)V
      92: areturn

  public void discardOperations(java.lang.String...);
    Code:
       0: aload_0
       1: getfield      #2                  // Field range:Lorg/jboss/as/controller/ModelVersionRange;
       4: invokeinterface #10,  1           // InterfaceMethod org/jboss/as/controller/ModelVersionRange.getVersions:()[Lorg/jboss/as/controller/ModelVersion;
       9: astore_2
      10: aload_2
      11: arraylength
      12: istore_3
      13: iconst_0
      14: istore        4
      16: iload         4
      18: iload_3
      19: if_icmpge     80
      22: aload_2
      23: iload         4
      25: aaload
      26: astore        5
      28: aload_1
      29: astore        6
      31: aload         6
      33: arraylength
      34: istore        7
      36: iconst_0
      37: istore        8
      39: iload         8
      41: iload         7
      43: if_icmpge     74
      46: aload         6
      48: iload         8
      50: aaload
      51: astore        9
      53: aload_0
      54: getfield      #3                  // Field registry:Lorg/jboss/as/controller/registry/GlobalTransformerRegistry;
      57: aload_0
      58: getfield      #4                  // Field current:Lorg/jboss/as/controller/PathAddress;
      61: aload         5
      63: aload         9
      65: invokevirtual #18                 // Method org/jboss/as/controller/registry/GlobalTransformerRegistry.discardOperation:(Lorg/jboss/as/controller/PathAddress;Lorg/jboss/as/controller/ModelVersion;Ljava/lang/String;)V
      68: iinc          8, 1
      71: goto          39
      74: iinc          4, 1
      77: goto          16
      80: return

  public void registerOperationTransformer(java.lang.String, org.jboss.as.controller.transform.OperationTransformer);
    Code:
       0: aload_0
       1: getfield      #2                  // Field range:Lorg/jboss/as/controller/ModelVersionRange;
       4: invokeinterface #10,  1           // InterfaceMethod org/jboss/as/controller/ModelVersionRange.getVersions:()[Lorg/jboss/as/controller/ModelVersion;
       9: astore_3
      10: aload_3
      11: arraylength
      12: istore        4
      14: iconst_0
      15: istore        5
      17: iload         5
      19: iload         4
      21: if_icmpge     51
      24: aload_3
      25: iload         5
      27: aaload
      28: astore        6
      30: aload_0
      31: getfield      #3                  // Field registry:Lorg/jboss/as/controller/registry/GlobalTransformerRegistry;
      34: aload_0
      35: getfield      #4                  // Field current:Lorg/jboss/as/controller/PathAddress;
      38: aload         6
      40: aload_1
      41: aload_2
      42: invokevirtual #19                 // Method org/jboss/as/controller/registry/GlobalTransformerRegistry.registerTransformer:(Lorg/jboss/as/controller/PathAddress;Lorg/jboss/as/controller/ModelVersion;Ljava/lang/String;Lorg/jboss/as/controller/transform/OperationTransformer;)V
      45: iinc          5, 1
      48: goto          17
      51: return
}
