Compiled from "GatewayList.java"
public final class org.restcomm.connect.dao.entities.GatewayList {
  private final java.util.List<org.restcomm.connect.dao.entities.Gateway> gateways;

  public org.restcomm.connect.dao.entities.GatewayList(java.util.List<org.restcomm.connect.dao.entities.Gateway>);
    Code:
       0: aload_0
       1: invokespecial #1                  // Method java/lang/Object."<init>":()V
       4: aload_0
       5: aload_1
       6: putfield      #2                  // Field gateways:Ljava/util/List;
       9: return

  public java.util.List<org.restcomm.connect.dao.entities.Gateway> getGateways();
    Code:
       0: aload_0
       1: getfield      #2                  // Field gateways:Ljava/util/List;
       4: areturn
}
