Compiled from "IncomingPhoneNumber.java"
public final class org.restcomm.connect.dao.entities.IncomingPhoneNumber$Builder {
  private org.restcomm.connect.commons.dao.Sid sid;

  private java.lang.String friendlyName;

  private org.restcomm.connect.commons.dao.Sid accountSid;

  private java.lang.String phoneNumber;

  private java.lang.String cost;

  private java.lang.String apiVersion;

  private java.lang.Boolean hasVoiceCallerIdLookup;

  private java.net.URI voiceUrl;

  private java.lang.String voiceMethod;

  private java.net.URI voiceFallbackUrl;

  private java.lang.String voiceFallbackMethod;

  private java.net.URI statusCallback;

  private java.lang.String statusCallbackMethod;

  private org.restcomm.connect.commons.dao.Sid voiceApplicationSid;

  private java.net.URI smsUrl;

  private java.lang.String smsMethod;

  private java.net.URI smsFallbackUrl;

  private java.lang.String smsFallbackMethod;

  private org.restcomm.connect.commons.dao.Sid smsApplicationSid;

  private java.net.URI uri;

  private java.net.URI ussdUrl;

  private java.lang.String ussdMethod;

  private java.net.URI ussdFallbackUrl;

  private java.lang.String ussdFallbackMethod;

  private org.restcomm.connect.commons.dao.Sid ussdApplicationSid;

  private java.lang.Boolean voiceCapable;

  private java.lang.Boolean smsCapable;

  private java.lang.Boolean mmsCapable;

  private java.lang.Boolean faxCapable;

  private java.lang.Boolean pureSip;

  private org.restcomm.connect.dao.entities.IncomingPhoneNumber$Builder();
    Code:
       0: aload_0
       1: invokespecial #2                  // Method java/lang/Object."<init>":()V
       4: return

  public org.restcomm.connect.dao.entities.IncomingPhoneNumber build();
    Code:
       0: invokestatic  #3                  // Method org/joda/time/DateTime.now:()Lorg/joda/time/DateTime;
       3: astore_1
       4: new           #4                  // class org/restcomm/connect/dao/entities/IncomingPhoneNumber
       7: dup
       8: aload_0
       9: getfield      #5                  // Field sid:Lorg/restcomm/connect/commons/dao/Sid;
      12: aload_1
      13: aload_1
      14: aload_0
      15: getfield      #6                  // Field friendlyName:Ljava/lang/String;
      18: aload_0
      19: getfield      #7                  // Field accountSid:Lorg/restcomm/connect/commons/dao/Sid;
      22: aload_0
      23: getfield      #8                  // Field phoneNumber:Ljava/lang/String;
      26: aload_0
      27: getfield      #9                  // Field cost:Ljava/lang/String;
      30: aload_0
      31: getfield      #10                 // Field apiVersion:Ljava/lang/String;
      34: aload_0
      35: getfield      #11                 // Field hasVoiceCallerIdLookup:Ljava/lang/Boolean;
      38: aload_0
      39: getfield      #12                 // Field voiceUrl:Ljava/net/URI;
      42: aload_0
      43: getfield      #13                 // Field voiceMethod:Ljava/lang/String;
      46: aload_0
      47: getfield      #14                 // Field voiceFallbackUrl:Ljava/net/URI;
      50: aload_0
      51: getfield      #15                 // Field voiceFallbackMethod:Ljava/lang/String;
      54: aload_0
      55: getfield      #16                 // Field statusCallback:Ljava/net/URI;
      58: aload_0
      59: getfield      #17                 // Field statusCallbackMethod:Ljava/lang/String;
      62: aload_0
      63: getfield      #18                 // Field voiceApplicationSid:Lorg/restcomm/connect/commons/dao/Sid;
      66: aload_0
      67: getfield      #19                 // Field smsUrl:Ljava/net/URI;
      70: aload_0
      71: getfield      #20                 // Field smsMethod:Ljava/lang/String;
      74: aload_0
      75: getfield      #21                 // Field smsFallbackUrl:Ljava/net/URI;
      78: aload_0
      79: getfield      #22                 // Field smsFallbackMethod:Ljava/lang/String;
      82: aload_0
      83: getfield      #23                 // Field smsApplicationSid:Lorg/restcomm/connect/commons/dao/Sid;
      86: aload_0
      87: getfield      #24                 // Field uri:Ljava/net/URI;
      90: aload_0
      91: getfield      #25                 // Field ussdUrl:Ljava/net/URI;
      94: aload_0
      95: getfield      #26                 // Field ussdMethod:Ljava/lang/String;
      98: aload_0
      99: getfield      #27                 // Field ussdFallbackUrl:Ljava/net/URI;
     102: aload_0
     103: getfield      #28                 // Field ussdFallbackMethod:Ljava/lang/String;
     106: aload_0
     107: getfield      #29                 // Field ussdApplicationSid:Lorg/restcomm/connect/commons/dao/Sid;
     110: aload_0
     111: getfield      #30                 // Field voiceCapable:Ljava/lang/Boolean;
     114: aload_0
     115: getfield      #31                 // Field smsCapable:Ljava/lang/Boolean;
     118: aload_0
     119: getfield      #32                 // Field mmsCapable:Ljava/lang/Boolean;
     122: aload_0
     123: getfield      #33                 // Field faxCapable:Ljava/lang/Boolean;
     126: aload_0
     127: getfield      #34                 // Field pureSip:Ljava/lang/Boolean;
     130: invokespecial #35                 // Method org/restcomm/connect/dao/entities/IncomingPhoneNumber."<init>":(Lorg/restcomm/connect/commons/dao/Sid;Lorg/joda/time/DateTime;Lorg/joda/time/DateTime;Ljava/lang/String;Lorg/restcomm/connect/commons/dao/Sid;Ljava/lang/String;Ljava/lang/String;Ljava/lang/String;Ljava/lang/Boolean;Ljava/net/URI;Ljava/lang/String;Ljava/net/URI;Ljava/lang/String;Ljava/net/URI;Ljava/lang/String;Lorg/restcomm/connect/commons/dao/Sid;Ljava/net/URI;Ljava/lang/String;Ljava/net/URI;Ljava/lang/String;Lorg/restcomm/connect/commons/dao/Sid;Ljava/net/URI;Ljava/net/URI;Ljava/lang/String;Ljava/net/URI;Ljava/lang/String;Lorg/restcomm/connect/commons/dao/Sid;Ljava/lang/Boolean;Ljava/lang/Boolean;Ljava/lang/Boolean;Ljava/lang/Boolean;Ljava/lang/Boolean;)V
     133: areturn

  public void setSid(org.restcomm.connect.commons.dao.Sid);
    Code:
       0: aload_0
       1: aload_1
       2: putfield      #5                  // Field sid:Lorg/restcomm/connect/commons/dao/Sid;
       5: return

  public void setFriendlyName(java.lang.String);
    Code:
       0: aload_0
       1: aload_1
       2: putfield      #6                  // Field friendlyName:Ljava/lang/String;
       5: return

  public void setAccountSid(org.restcomm.connect.commons.dao.Sid);
    Code:
       0: aload_0
       1: aload_1
       2: putfield      #7                  // Field accountSid:Lorg/restcomm/connect/commons/dao/Sid;
       5: return

  public void setPhoneNumber(java.lang.String);
    Code:
       0: aload_0
       1: aload_1
       2: putfield      #8                  // Field phoneNumber:Ljava/lang/String;
       5: return

  public void setCost(java.lang.String);
    Code:
       0: aload_0
       1: aload_1
       2: putfield      #9                  // Field cost:Ljava/lang/String;
       5: return

  public void setApiVersion(java.lang.String);
    Code:
       0: aload_0
       1: aload_1
       2: putfield      #10                 // Field apiVersion:Ljava/lang/String;
       5: return

  public void setHasVoiceCallerIdLookup(boolean);
    Code:
       0: aload_0
       1: iload_1
       2: invokestatic  #36                 // Method java/lang/Boolean.valueOf:(Z)Ljava/lang/Boolean;
       5: putfield      #11                 // Field hasVoiceCallerIdLookup:Ljava/lang/Boolean;
       8: return

  public void setVoiceUrl(java.net.URI);
    Code:
       0: aload_0
       1: aload_1
       2: putfield      #12                 // Field voiceUrl:Ljava/net/URI;
       5: return

  public void setVoiceMethod(java.lang.String);
    Code:
       0: aload_0
       1: aload_1
       2: putfield      #13                 // Field voiceMethod:Ljava/lang/String;
       5: return

  public void setVoiceFallbackUrl(java.net.URI);
    Code:
       0: aload_0
       1: aload_1
       2: putfield      #14                 // Field voiceFallbackUrl:Ljava/net/URI;
       5: return

  public void setVoiceFallbackMethod(java.lang.String);
    Code:
       0: aload_0
       1: aload_1
       2: putfield      #15                 // Field voiceFallbackMethod:Ljava/lang/String;
       5: return

  public void setStatusCallback(java.net.URI);
    Code:
       0: aload_0
       1: aload_1
       2: putfield      #16                 // Field statusCallback:Ljava/net/URI;
       5: return

  public void setStatusCallbackMethod(java.lang.String);
    Code:
       0: aload_0
       1: aload_1
       2: putfield      #17                 // Field statusCallbackMethod:Ljava/lang/String;
       5: return

  public void setVoiceApplicationSid(org.restcomm.connect.commons.dao.Sid);
    Code:
       0: aload_0
       1: aload_1
       2: putfield      #18                 // Field voiceApplicationSid:Lorg/restcomm/connect/commons/dao/Sid;
       5: return

  public void setSmsUrl(java.net.URI);
    Code:
       0: aload_0
       1: aload_1
       2: putfield      #19                 // Field smsUrl:Ljava/net/URI;
       5: return

  public void setSmsMethod(java.lang.String);
    Code:
       0: aload_0
       1: aload_1
       2: putfield      #20                 // Field smsMethod:Ljava/lang/String;
       5: return

  public void setSmsFallbackUrl(java.net.URI);
    Code:
       0: aload_0
       1: aload_1
       2: putfield      #21                 // Field smsFallbackUrl:Ljava/net/URI;
       5: return

  public void setSmsFallbackMethod(java.lang.String);
    Code:
       0: aload_0
       1: aload_1
       2: putfield      #22                 // Field smsFallbackMethod:Ljava/lang/String;
       5: return

  public void setSmsApplicationSid(org.restcomm.connect.commons.dao.Sid);
    Code:
       0: aload_0
       1: aload_1
       2: putfield      #23                 // Field smsApplicationSid:Lorg/restcomm/connect/commons/dao/Sid;
       5: return

  public void setUri(java.net.URI);
    Code:
       0: aload_0
       1: aload_1
       2: putfield      #24                 // Field uri:Ljava/net/URI;
       5: return

  public void setUssdUrl(java.net.URI);
    Code:
       0: aload_0
       1: aload_1
       2: putfield      #25                 // Field ussdUrl:Ljava/net/URI;
       5: return

  public void setUssdMethod(java.lang.String);
    Code:
       0: aload_0
       1: aload_1
       2: putfield      #26                 // Field ussdMethod:Ljava/lang/String;
       5: return

  public void setUssdFallbackUrl(java.net.URI);
    Code:
       0: aload_0
       1: aload_1
       2: putfield      #27                 // Field ussdFallbackUrl:Ljava/net/URI;
       5: return

  public void setUssdFallbackMethod(java.lang.String);
    Code:
       0: aload_0
       1: aload_1
       2: putfield      #28                 // Field ussdFallbackMethod:Ljava/lang/String;
       5: return

  public void setUssdApplicationSid(org.restcomm.connect.commons.dao.Sid);
    Code:
       0: aload_0
       1: aload_1
       2: putfield      #29                 // Field ussdApplicationSid:Lorg/restcomm/connect/commons/dao/Sid;
       5: return

  public void setVoiceCapable(java.lang.Boolean);
    Code:
       0: aload_0
       1: aload_1
       2: putfield      #30                 // Field voiceCapable:Ljava/lang/Boolean;
       5: return

  public void setSmsCapable(java.lang.Boolean);
    Code:
       0: aload_0
       1: aload_1
       2: putfield      #31                 // Field smsCapable:Ljava/lang/Boolean;
       5: return

  public void setMmsCapable(java.lang.Boolean);
    Code:
       0: aload_0
       1: aload_1
       2: putfield      #32                 // Field mmsCapable:Ljava/lang/Boolean;
       5: return

  public void setFaxCapable(java.lang.Boolean);
    Code:
       0: aload_0
       1: aload_1
       2: putfield      #33                 // Field faxCapable:Ljava/lang/Boolean;
       5: return

  public void setPureSip(java.lang.Boolean);
    Code:
       0: aload_0
       1: aload_1
       2: putfield      #34                 // Field pureSip:Ljava/lang/Boolean;
       5: return

  public static org.restcomm.connect.dao.entities.IncomingPhoneNumber$Builder builder();
    Code:
       0: new           #37                 // class org/restcomm/connect/dao/entities/IncomingPhoneNumber$Builder
       3: dup
       4: invokespecial #1                  // Method "<init>":()V
       7: areturn

  org.restcomm.connect.dao.entities.IncomingPhoneNumber$Builder(org.restcomm.connect.dao.entities.IncomingPhoneNumber$1);
    Code:
       0: aload_0
       1: invokespecial #1                  // Method "<init>":()V
       4: return
}
