Compiled from "Panorama.scala"
public interface zio.aws.panorama.Panorama extends zio.aws.core.aspects.package$AspectSupport<zio.aws.panorama.Panorama> {
  public static zio.ZIO<zio.aws.core.config.AwsConfig, java.lang.Throwable, zio.aws.panorama.Panorama> scoped(scala.Function1<software.amazon.awssdk.services.panorama.PanoramaAsyncClientBuilder, software.amazon.awssdk.services.panorama.PanoramaAsyncClientBuilder>);
    Code:
       0: getstatic     #196                // Field zio/aws/panorama/Panorama$.MODULE$:Lzio/aws/panorama/Panorama$;
       3: aload_0
       4: invokevirtual #198                // Method zio/aws/panorama/Panorama$.scoped:(Lscala/Function1;)Lzio/ZIO;
       7: areturn

  public static zio.ZLayer<zio.aws.core.config.AwsConfig, java.lang.Throwable, zio.aws.panorama.Panorama> customized(scala.Function1<software.amazon.awssdk.services.panorama.PanoramaAsyncClientBuilder, software.amazon.awssdk.services.panorama.PanoramaAsyncClientBuilder>);
    Code:
       0: getstatic     #196                // Field zio/aws/panorama/Panorama$.MODULE$:Lzio/aws/panorama/Panorama$;
       3: aload_0
       4: invokevirtual #203                // Method zio/aws/panorama/Panorama$.customized:(Lscala/Function1;)Lzio/ZLayer;
       7: areturn

  public static zio.ZLayer<zio.aws.core.config.AwsConfig, java.lang.Throwable, zio.aws.panorama.Panorama> live();
    Code:
       0: getstatic     #196                // Field zio/aws/panorama/Panorama$.MODULE$:Lzio/aws/panorama/Panorama$;
       3: invokevirtual #208                // Method zio/aws/panorama/Panorama$.live:()Lzio/ZLayer;
       6: areturn

  public abstract software.amazon.awssdk.services.panorama.PanoramaAsyncClient api();

  public abstract zio.ZIO<java.lang.Object, zio.aws.core.AwsError, zio.aws.panorama.model.ProvisionDeviceResponse$ReadOnly> provisionDevice(zio.aws.panorama.model.ProvisionDeviceRequest);

  public abstract zio.ZIO<java.lang.Object, zio.aws.core.AwsError, zio.aws.panorama.model.CreatePackageResponse$ReadOnly> createPackage(zio.aws.panorama.model.CreatePackageRequest);

  public abstract zio.ZIO<java.lang.Object, zio.aws.core.AwsError, zio.aws.panorama.model.DescribeDeviceResponse$ReadOnly> describeDevice(zio.aws.panorama.model.DescribeDeviceRequest);

  public abstract zio.ZIO<java.lang.Object, zio.aws.core.AwsError, zio.aws.panorama.model.DeleteDeviceResponse$ReadOnly> deleteDevice(zio.aws.panorama.model.DeleteDeviceRequest);

  public abstract zio.ZIO<java.lang.Object, zio.aws.core.AwsError, zio.aws.panorama.model.DescribePackageImportJobResponse$ReadOnly> describePackageImportJob(zio.aws.panorama.model.DescribePackageImportJobRequest);

  public abstract zio.stream.ZStream<java.lang.Object, zio.aws.core.AwsError, zio.aws.panorama.model.PackageImportJob$ReadOnly> listPackageImportJobs(zio.aws.panorama.model.ListPackageImportJobsRequest);

  public abstract zio.ZIO<java.lang.Object, zio.aws.core.AwsError, zio.aws.panorama.model.ListPackageImportJobsResponse$ReadOnly> listPackageImportJobsPaginated(zio.aws.panorama.model.ListPackageImportJobsRequest);

  public abstract zio.stream.ZStream<java.lang.Object, zio.aws.core.AwsError, zio.aws.panorama.model.NodeInstance$ReadOnly> listApplicationInstanceNodeInstances(zio.aws.panorama.model.ListApplicationInstanceNodeInstancesRequest);

  public abstract zio.ZIO<java.lang.Object, zio.aws.core.AwsError, zio.aws.panorama.model.ListApplicationInstanceNodeInstancesResponse$ReadOnly> listApplicationInstanceNodeInstancesPaginated(zio.aws.panorama.model.ListApplicationInstanceNodeInstancesRequest);

  public abstract zio.stream.ZStream<java.lang.Object, zio.aws.core.AwsError, zio.aws.panorama.model.DeviceJob$ReadOnly> listDevicesJobs(zio.aws.panorama.model.ListDevicesJobsRequest);

  public abstract zio.ZIO<java.lang.Object, zio.aws.core.AwsError, zio.aws.panorama.model.ListDevicesJobsResponse$ReadOnly> listDevicesJobsPaginated(zio.aws.panorama.model.ListDevicesJobsRequest);

  public abstract zio.stream.ZStream<java.lang.Object, zio.aws.core.AwsError, zio.aws.panorama.model.Device$ReadOnly> listDevices(zio.aws.panorama.model.ListDevicesRequest);

  public abstract zio.ZIO<java.lang.Object, zio.aws.core.AwsError, zio.aws.panorama.model.ListDevicesResponse$ReadOnly> listDevicesPaginated(zio.aws.panorama.model.ListDevicesRequest);

  public abstract zio.ZIO<java.lang.Object, zio.aws.core.AwsError, zio.aws.panorama.model.CreateNodeFromTemplateJobResponse$ReadOnly> createNodeFromTemplateJob(zio.aws.panorama.model.CreateNodeFromTemplateJobRequest);

  public abstract zio.ZIO<java.lang.Object, zio.aws.core.AwsError, zio.aws.panorama.model.RemoveApplicationInstanceResponse$ReadOnly> removeApplicationInstance(zio.aws.panorama.model.RemoveApplicationInstanceRequest);

  public abstract zio.ZIO<java.lang.Object, zio.aws.core.AwsError, zio.aws.panorama.model.CreateJobForDevicesResponse$ReadOnly> createJobForDevices(zio.aws.panorama.model.CreateJobForDevicesRequest);

  public abstract zio.ZIO<java.lang.Object, zio.aws.core.AwsError, zio.aws.panorama.model.CreatePackageImportJobResponse$ReadOnly> createPackageImportJob(zio.aws.panorama.model.CreatePackageImportJobRequest);

  public abstract zio.ZIO<java.lang.Object, zio.aws.core.AwsError, zio.aws.panorama.model.DescribeNodeResponse$ReadOnly> describeNode(zio.aws.panorama.model.DescribeNodeRequest);

  public abstract zio.ZIO<java.lang.Object, zio.aws.core.AwsError, zio.aws.panorama.model.DescribePackageResponse$ReadOnly> describePackage(zio.aws.panorama.model.DescribePackageRequest);

  public abstract zio.ZIO<java.lang.Object, zio.aws.core.AwsError, zio.aws.panorama.model.UntagResourceResponse$ReadOnly> untagResource(zio.aws.panorama.model.UntagResourceRequest);

  public abstract zio.ZIO<java.lang.Object, zio.aws.core.AwsError, zio.aws.panorama.model.DeregisterPackageVersionResponse$ReadOnly> deregisterPackageVersion(zio.aws.panorama.model.DeregisterPackageVersionRequest);

  public abstract zio.stream.ZStream<java.lang.Object, zio.aws.core.AwsError, zio.aws.panorama.model.ApplicationInstance$ReadOnly> listApplicationInstances(zio.aws.panorama.model.ListApplicationInstancesRequest);

  public abstract zio.ZIO<java.lang.Object, zio.aws.core.AwsError, zio.aws.panorama.model.ListApplicationInstancesResponse$ReadOnly> listApplicationInstancesPaginated(zio.aws.panorama.model.ListApplicationInstancesRequest);

  public abstract zio.ZIO<java.lang.Object, zio.aws.core.AwsError, zio.aws.panorama.model.DescribeDeviceJobResponse$ReadOnly> describeDeviceJob(zio.aws.panorama.model.DescribeDeviceJobRequest);

  public abstract zio.ZIO<java.lang.Object, zio.aws.core.AwsError, zio.aws.panorama.model.DescribePackageVersionResponse$ReadOnly> describePackageVersion(zio.aws.panorama.model.DescribePackageVersionRequest);

  public abstract zio.ZIO<java.lang.Object, zio.aws.core.AwsError, zio.aws.panorama.model.ListTagsForResourceResponse$ReadOnly> listTagsForResource(zio.aws.panorama.model.ListTagsForResourceRequest);

  public abstract zio.ZIO<java.lang.Object, zio.aws.core.AwsError, zio.aws.panorama.model.TagResourceResponse$ReadOnly> tagResource(zio.aws.panorama.model.TagResourceRequest);

  public abstract zio.ZIO<java.lang.Object, zio.aws.core.AwsError, zio.aws.panorama.model.DeletePackageResponse$ReadOnly> deletePackage(zio.aws.panorama.model.DeletePackageRequest);

  public abstract zio.stream.ZStream<java.lang.Object, zio.aws.core.AwsError, zio.aws.panorama.model.NodeFromTemplateJob$ReadOnly> listNodeFromTemplateJobs(zio.aws.panorama.model.ListNodeFromTemplateJobsRequest);

  public abstract zio.ZIO<java.lang.Object, zio.aws.core.AwsError, zio.aws.panorama.model.ListNodeFromTemplateJobsResponse$ReadOnly> listNodeFromTemplateJobsPaginated(zio.aws.panorama.model.ListNodeFromTemplateJobsRequest);

  public abstract zio.ZIO<java.lang.Object, zio.aws.core.AwsError, zio.aws.panorama.model.CreateApplicationInstanceResponse$ReadOnly> createApplicationInstance(zio.aws.panorama.model.CreateApplicationInstanceRequest);

  public abstract zio.stream.ZStream<java.lang.Object, zio.aws.core.AwsError, zio.aws.panorama.model.PackageObject$ReadOnly> listApplicationInstanceDependencies(zio.aws.panorama.model.ListApplicationInstanceDependenciesRequest);

  public abstract zio.ZIO<java.lang.Object, zio.aws.core.AwsError, zio.aws.panorama.model.ListApplicationInstanceDependenciesResponse$ReadOnly> listApplicationInstanceDependenciesPaginated(zio.aws.panorama.model.ListApplicationInstanceDependenciesRequest);

  public abstract zio.ZIO<java.lang.Object, zio.aws.core.AwsError, zio.aws.panorama.model.DescribeApplicationInstanceDetailsResponse$ReadOnly> describeApplicationInstanceDetails(zio.aws.panorama.model.DescribeApplicationInstanceDetailsRequest);

  public abstract zio.ZIO<java.lang.Object, zio.aws.core.AwsError, zio.aws.panorama.model.RegisterPackageVersionResponse$ReadOnly> registerPackageVersion(zio.aws.panorama.model.RegisterPackageVersionRequest);

  public abstract zio.ZIO<java.lang.Object, zio.aws.core.AwsError, zio.aws.panorama.model.DescribeApplicationInstanceResponse$ReadOnly> describeApplicationInstance(zio.aws.panorama.model.DescribeApplicationInstanceRequest);

  public abstract zio.ZIO<java.lang.Object, zio.aws.core.AwsError, zio.aws.panorama.model.UpdateDeviceMetadataResponse$ReadOnly> updateDeviceMetadata(zio.aws.panorama.model.UpdateDeviceMetadataRequest);

  public abstract zio.stream.ZStream<java.lang.Object, zio.aws.core.AwsError, zio.aws.panorama.model.Node$ReadOnly> listNodes(zio.aws.panorama.model.ListNodesRequest);

  public abstract zio.ZIO<java.lang.Object, zio.aws.core.AwsError, zio.aws.panorama.model.ListNodesResponse$ReadOnly> listNodesPaginated(zio.aws.panorama.model.ListNodesRequest);

  public abstract zio.stream.ZStream<java.lang.Object, zio.aws.core.AwsError, zio.aws.panorama.model.PackageListItem$ReadOnly> listPackages(zio.aws.panorama.model.ListPackagesRequest);

  public abstract zio.ZIO<java.lang.Object, zio.aws.core.AwsError, zio.aws.panorama.model.ListPackagesResponse$ReadOnly> listPackagesPaginated(zio.aws.panorama.model.ListPackagesRequest);

  public abstract zio.ZIO<java.lang.Object, zio.aws.core.AwsError, zio.aws.panorama.model.DescribeNodeFromTemplateJobResponse$ReadOnly> describeNodeFromTemplateJob(zio.aws.panorama.model.DescribeNodeFromTemplateJobRequest);
}
