Compiled from "TLSClientHelloExtractor.java"
public final class org.apache.tomcat.util.net.TLSClientHelloExtractor$ExtractorResult extends java.lang.Enum<org.apache.tomcat.util.net.TLSClientHelloExtractor$ExtractorResult> {
  public static final org.apache.tomcat.util.net.TLSClientHelloExtractor$ExtractorResult COMPLETE;

  public static final org.apache.tomcat.util.net.TLSClientHelloExtractor$ExtractorResult NOT_PRESENT;

  public static final org.apache.tomcat.util.net.TLSClientHelloExtractor$ExtractorResult UNDERFLOW;

  public static final org.apache.tomcat.util.net.TLSClientHelloExtractor$ExtractorResult NEED_READ;

  public static final org.apache.tomcat.util.net.TLSClientHelloExtractor$ExtractorResult NON_SECURE;

  private static final org.apache.tomcat.util.net.TLSClientHelloExtractor$ExtractorResult[] $VALUES;

  public static org.apache.tomcat.util.net.TLSClientHelloExtractor$ExtractorResult[] values();
    Code:
       0: getstatic     #1                  // Field $VALUES:[Lorg/apache/tomcat/util/net/TLSClientHelloExtractor$ExtractorResult;
       3: invokevirtual #2                  // Method "[Lorg/apache/tomcat/util/net/TLSClientHelloExtractor$ExtractorResult;".clone:()Ljava/lang/Object;
       6: checkcast     #3                  // class "[Lorg/apache/tomcat/util/net/TLSClientHelloExtractor$ExtractorResult;"
       9: areturn

  public static org.apache.tomcat.util.net.TLSClientHelloExtractor$ExtractorResult valueOf(java.lang.String);
    Code:
       0: ldc           #4                  // class org/apache/tomcat/util/net/TLSClientHelloExtractor$ExtractorResult
       2: aload_0
       3: invokestatic  #5                  // Method java/lang/Enum.valueOf:(Ljava/lang/Class;Ljava/lang/String;)Ljava/lang/Enum;
       6: checkcast     #4                  // class org/apache/tomcat/util/net/TLSClientHelloExtractor$ExtractorResult
       9: areturn

  private org.apache.tomcat.util.net.TLSClientHelloExtractor$ExtractorResult();
    Code:
       0: aload_0
       1: aload_1
       2: iload_2
       3: invokespecial #6                  // Method java/lang/Enum."<init>":(Ljava/lang/String;I)V
       6: return

  static {};
    Code:
       0: new           #4                  // class org/apache/tomcat/util/net/TLSClientHelloExtractor$ExtractorResult
       3: dup
       4: ldc           #7                  // String COMPLETE
       6: iconst_0
       7: invokespecial #8                  // Method "<init>":(Ljava/lang/String;I)V
      10: putstatic     #9                  // Field COMPLETE:Lorg/apache/tomcat/util/net/TLSClientHelloExtractor$ExtractorResult;
      13: new           #4                  // class org/apache/tomcat/util/net/TLSClientHelloExtractor$ExtractorResult
      16: dup
      17: ldc           #10                 // String NOT_PRESENT
      19: iconst_1
      20: invokespecial #8                  // Method "<init>":(Ljava/lang/String;I)V
      23: putstatic     #11                 // Field NOT_PRESENT:Lorg/apache/tomcat/util/net/TLSClientHelloExtractor$ExtractorResult;
      26: new           #4                  // class org/apache/tomcat/util/net/TLSClientHelloExtractor$ExtractorResult
      29: dup
      30: ldc           #12                 // String UNDERFLOW
      32: iconst_2
      33: invokespecial #8                  // Method "<init>":(Ljava/lang/String;I)V
      36: putstatic     #13                 // Field UNDERFLOW:Lorg/apache/tomcat/util/net/TLSClientHelloExtractor$ExtractorResult;
      39: new           #4                  // class org/apache/tomcat/util/net/TLSClientHelloExtractor$ExtractorResult
      42: dup
      43: ldc           #14                 // String NEED_READ
      45: iconst_3
      46: invokespecial #8                  // Method "<init>":(Ljava/lang/String;I)V
      49: putstatic     #15                 // Field NEED_READ:Lorg/apache/tomcat/util/net/TLSClientHelloExtractor$ExtractorResult;
      52: new           #4                  // class org/apache/tomcat/util/net/TLSClientHelloExtractor$ExtractorResult
      55: dup
      56: ldc           #16                 // String NON_SECURE
      58: iconst_4
      59: invokespecial #8                  // Method "<init>":(Ljava/lang/String;I)V
      62: putstatic     #17                 // Field NON_SECURE:Lorg/apache/tomcat/util/net/TLSClientHelloExtractor$ExtractorResult;
      65: iconst_5
      66: anewarray     #4                  // class org/apache/tomcat/util/net/TLSClientHelloExtractor$ExtractorResult
      69: dup
      70: iconst_0
      71: getstatic     #9                  // Field COMPLETE:Lorg/apache/tomcat/util/net/TLSClientHelloExtractor$ExtractorResult;
      74: aastore
      75: dup
      76: iconst_1
      77: getstatic     #11                 // Field NOT_PRESENT:Lorg/apache/tomcat/util/net/TLSClientHelloExtractor$ExtractorResult;
      80: aastore
      81: dup
      82: iconst_2
      83: getstatic     #13                 // Field UNDERFLOW:Lorg/apache/tomcat/util/net/TLSClientHelloExtractor$ExtractorResult;
      86: aastore
      87: dup
      88: iconst_3
      89: getstatic     #15                 // Field NEED_READ:Lorg/apache/tomcat/util/net/TLSClientHelloExtractor$ExtractorResult;
      92: aastore
      93: dup
      94: iconst_4
      95: getstatic     #17                 // Field NON_SECURE:Lorg/apache/tomcat/util/net/TLSClientHelloExtractor$ExtractorResult;
      98: aastore
      99: putstatic     #1                  // Field $VALUES:[Lorg/apache/tomcat/util/net/TLSClientHelloExtractor$ExtractorResult;
     102: return
}
