Compiled from "DiagnoseParser.java"
class org.eclipse.jdt.internal.compiler.parser.diagnose.DiagnoseParser$RepairCandidate {
  public int symbol;

  public int location;

  public org.eclipse.jdt.internal.compiler.parser.diagnose.DiagnoseParser$RepairCandidate();
    Code:
       0: aload_0
       1: invokespecial #11                 // Method java/lang/Object."<init>":()V
       4: aload_0
       5: iconst_0
       6: putfield      #13                 // Field symbol:I
       9: aload_0
      10: iconst_0
      11: putfield      #15                 // Field location:I
      14: return
}
