Compiled from "NamedFeature.java"
public class org.springframework.cloud.client.actuator.NamedFeature {
  private final java.lang.String name;

  private final java.lang.Class<?> type;

  public org.springframework.cloud.client.actuator.NamedFeature(java.lang.String, java.lang.Class<?>);
    Code:
       0: aload_0
       1: invokespecial #1                  // Method java/lang/Object."<init>":()V
       4: aload_0
       5: aload_1
       6: putfield      #2                  // Field name:Ljava/lang/String;
       9: aload_0
      10: aload_2
      11: putfield      #3                  // Field type:Ljava/lang/Class;
      14: return

  public java.lang.String getName();
    Code:
       0: aload_0
       1: getfield      #2                  // Field name:Ljava/lang/String;
       4: areturn

  public java.lang.Class<?> getType();
    Code:
       0: aload_0
       1: getfield      #3                  // Field type:Ljava/lang/Class;
       4: areturn
}
