Compiled from "DelegationTokenResponse.java"
public class org.apache.solr.client.solrj.response.DelegationTokenResponse$JsonMapResponseParser extends org.apache.solr.client.solrj.ResponseParser {
  public org.apache.solr.client.solrj.response.DelegationTokenResponse$JsonMapResponseParser();
    Code:
       0: aload_0
       1: invokespecial #1                  // Method org/apache/solr/client/solrj/ResponseParser."<init>":()V
       4: return

  public java.lang.String getWriterType();
    Code:
       0: ldc           #2                  // String json
       2: areturn

  public org.apache.solr.common.util.NamedList<java.lang.Object> processResponse(java.io.InputStream, java.lang.String);
    Code:
       0: aconst_null
       1: astore_3
       2: new           #3                  // class org/noggit/ObjectBuilder
       5: dup
       6: new           #4                  // class org/noggit/JSONParser
       9: dup
      10: new           #5                  // class java/io/InputStreamReader
      13: dup
      14: aload_1
      15: aload_2
      16: ifnonnull     24
      19: ldc           #6                  // String UTF-8
      21: goto          25
      24: aload_2
      25: invokespecial #7                  // Method java/io/InputStreamReader."<init>":(Ljava/io/InputStream;Ljava/lang/String;)V
      28: invokespecial #8                  // Method org/noggit/JSONParser."<init>":(Ljava/io/Reader;)V
      31: invokespecial #9                  // Method org/noggit/ObjectBuilder."<init>":(Lorg/noggit/JSONParser;)V
      34: astore        4
      36: aload         4
      38: invokevirtual #10                 // Method org/noggit/ObjectBuilder.getObject:()Ljava/lang/Object;
      41: checkcast     #11                 // class java/util/Map
      44: astore_3
      45: goto          65
      48: astore        4
      50: new           #14                 // class org/apache/solr/common/SolrException
      53: dup
      54: getstatic     #15                 // Field org/apache/solr/common/SolrException$ErrorCode.SERVER_ERROR:Lorg/apache/solr/common/SolrException$ErrorCode;
      57: ldc           #16                 // String parsing error
      59: aload         4
      61: invokespecial #17                 // Method org/apache/solr/common/SolrException."<init>":(Lorg/apache/solr/common/SolrException$ErrorCode;Ljava/lang/String;Ljava/lang/Throwable;)V
      64: athrow
      65: new           #18                 // class org/apache/solr/common/util/NamedList
      68: dup
      69: invokespecial #19                 // Method org/apache/solr/common/util/NamedList."<init>":()V
      72: astore        4
      74: aload         4
      76: aload_3
      77: invokevirtual #20                 // Method org/apache/solr/common/util/NamedList.addAll:(Ljava/util/Map;)Z
      80: pop
      81: aload         4
      83: areturn
    Exception table:
       from    to  target type
           2    45    48   Class java/io/IOException
           2    45    48   Class org/noggit/JSONParser$ParseException

  public org.apache.solr.common.util.NamedList<java.lang.Object> processResponse(java.io.Reader);
    Code:
       0: new           #21                 // class java/lang/RuntimeException
       3: dup
       4: ldc           #22                 // String Cannot handle character stream
       6: invokespecial #23                 // Method java/lang/RuntimeException."<init>":(Ljava/lang/String;)V
       9: athrow

  public java.lang.String getContentType();
    Code:
       0: ldc           #24                 // String application/json
       2: areturn

  public java.lang.String getVersion();
    Code:
       0: ldc           #25                 // String 1
       2: areturn
}
