Compiled from "SpellCheckResponse.java"
public class org.apache.solr.client.solrj.response.SpellCheckResponse$Correction {
  private java.lang.String original;

  private java.lang.String correction;

  final org.apache.solr.client.solrj.response.SpellCheckResponse this$0;

  public org.apache.solr.client.solrj.response.SpellCheckResponse$Correction(org.apache.solr.client.solrj.response.SpellCheckResponse, java.lang.String, java.lang.String);
    Code:
       0: aload_0
       1: aload_1
       2: putfield      #1                  // Field this$0:Lorg/apache/solr/client/solrj/response/SpellCheckResponse;
       5: aload_0
       6: invokespecial #2                  // Method java/lang/Object."<init>":()V
       9: aload_0
      10: aload_2
      11: putfield      #3                  // Field original:Ljava/lang/String;
      14: aload_0
      15: aload_3
      16: putfield      #4                  // Field correction:Ljava/lang/String;
      19: return

  public java.lang.String getOriginal();
    Code:
       0: aload_0
       1: getfield      #3                  // Field original:Ljava/lang/String;
       4: areturn

  public void setOriginal(java.lang.String);
    Code:
       0: aload_0
       1: aload_1
       2: putfield      #3                  // Field original:Ljava/lang/String;
       5: return

  public java.lang.String getCorrection();
    Code:
       0: aload_0
       1: getfield      #4                  // Field correction:Ljava/lang/String;
       4: areturn

  public void setCorrection(java.lang.String);
    Code:
       0: aload_0
       1: aload_1
       2: putfield      #4                  // Field correction:Ljava/lang/String;
       5: return
}
