Compiled from "TermsResponse.java"
public class org.apache.solr.client.solrj.response.TermsResponse {
  private java.util.Map<java.lang.String, java.util.List<org.apache.solr.client.solrj.response.TermsResponse$Term>> termMap;

  public org.apache.solr.client.solrj.response.TermsResponse(org.apache.solr.common.util.NamedList<org.apache.solr.common.util.NamedList<java.lang.Number>>);
    Code:
       0: aload_0
       1: invokespecial #1                  // Method java/lang/Object."<init>":()V
       4: aload_0
       5: new           #2                  // class java/util/HashMap
       8: dup
       9: invokespecial #3                  // Method java/util/HashMap."<init>":()V
      12: putfield      #4                  // Field termMap:Ljava/util/Map;
      15: iconst_0
      16: istore_2
      17: iload_2
      18: aload_1
      19: invokevirtual #5                  // Method org/apache/solr/common/util/NamedList.size:()I
      22: if_icmpge     127
      25: aload_1
      26: iload_2
      27: invokevirtual #6                  // Method org/apache/solr/common/util/NamedList.getName:(I)Ljava/lang/String;
      30: astore_3
      31: new           #7                  // class java/util/ArrayList
      34: dup
      35: invokespecial #8                  // Method java/util/ArrayList."<init>":()V
      38: astore        4
      40: aload_1
      41: iload_2
      42: invokevirtual #9                  // Method org/apache/solr/common/util/NamedList.getVal:(I)Ljava/lang/Object;
      45: checkcast     #10                 // class org/apache/solr/common/util/NamedList
      48: astore        5
      50: iconst_0
      51: istore        6
      53: iload         6
      55: aload         5
      57: invokevirtual #5                  // Method org/apache/solr/common/util/NamedList.size:()I
      60: if_icmpge     108
      63: new           #11                 // class org/apache/solr/client/solrj/response/TermsResponse$Term
      66: dup
      67: aload         5
      69: iload         6
      71: invokevirtual #6                  // Method org/apache/solr/common/util/NamedList.getName:(I)Ljava/lang/String;
      74: aload         5
      76: iload         6
      78: invokevirtual #9                  // Method org/apache/solr/common/util/NamedList.getVal:(I)Ljava/lang/Object;
      81: checkcast     #12                 // class java/lang/Number
      84: invokevirtual #13                 // Method java/lang/Number.longValue:()J
      87: invokespecial #14                 // Method org/apache/solr/client/solrj/response/TermsResponse$Term."<init>":(Ljava/lang/String;J)V
      90: astore        7
      92: aload         4
      94: aload         7
      96: invokeinterface #15,  2           // InterfaceMethod java/util/List.add:(Ljava/lang/Object;)Z
     101: pop
     102: iinc          6, 1
     105: goto          53
     108: aload_0
     109: getfield      #4                  // Field termMap:Ljava/util/Map;
     112: aload_3
     113: aload         4
     115: invokeinterface #16,  3           // InterfaceMethod java/util/Map.put:(Ljava/lang/Object;Ljava/lang/Object;)Ljava/lang/Object;
     120: pop
     121: iinc          2, 1
     124: goto          17
     127: return

  public java.util.List<org.apache.solr.client.solrj.response.TermsResponse$Term> getTerms(java.lang.String);
    Code:
       0: aload_0
       1: getfield      #4                  // Field termMap:Ljava/util/Map;
       4: aload_1
       5: invokeinterface #17,  2           // InterfaceMethod java/util/Map.get:(Ljava/lang/Object;)Ljava/lang/Object;
      10: checkcast     #18                 // class java/util/List
      13: areturn

  public java.util.Map<java.lang.String, java.util.List<org.apache.solr.client.solrj.response.TermsResponse$Term>> getTermMap();
    Code:
       0: aload_0
       1: getfield      #4                  // Field termMap:Ljava/util/Map;
       4: areturn
}
