Compiled from "ArgumentMatchersSugar.scala"
public final class org.mockito.ArgumentMatchersSugar$ implements org.mockito.ArgumentMatchersSugar {
  public static final org.mockito.ArgumentMatchersSugar$ MODULE$;

  private final org.mockito.matchers.N n;

  public static {};
    Code:
       0: new           #2                  // class org/mockito/ArgumentMatchersSugar$
       3: invokespecial #14                 // Method "<init>":()V
       6: return

  public <T> T anyVal(org.mockito.matchers.DefaultValueProvider<T>);
    Code:
       0: aload_0
       1: aload_1
       2: invokestatic  #23                 // Method org/mockito/matchers/MacroBasedMatchers$class.anyVal:(Lorg/mockito/matchers/MacroBasedMatchers;Lorg/mockito/matchers/DefaultValueProvider;)Ljava/lang/Object;
       5: areturn

  public <T> T any(org.mockito.matchers.DefaultValueProvider<T>);
    Code:
       0: aload_0
       1: aload_1
       2: invokestatic  #29                 // Method org/mockito/matchers/MacroBasedMatchers$class.any:(Lorg/mockito/matchers/MacroBasedMatchers;Lorg/mockito/matchers/DefaultValueProvider;)Ljava/lang/Object;
       5: areturn

  public <T> T $times(org.mockito.matchers.DefaultValueProvider<T>);
    Code:
       0: aload_0
       1: aload_1
       2: invokestatic  #32                 // Method org/mockito/matchers/MacroBasedMatchers$class.$times:(Lorg/mockito/matchers/MacroBasedMatchers;Lorg/mockito/matchers/DefaultValueProvider;)Ljava/lang/Object;
       5: areturn

  public org.mockito.matchers.N n();
    Code:
       0: aload_0
       1: getfield      #35                 // Field n:Lorg/mockito/matchers/N;
       4: areturn

  public void org$mockito$matchers$NumericMatchers$_setter_$n_$eq(org.mockito.matchers.N);
    Code:
       0: aload_0
       1: aload_1
       2: putfield      #35                 // Field n:Lorg/mockito/matchers/N;
       5: return

  public <T> org.scalactic.Tolerance$PlusOrMinusWrapper<T> convertNumericToPlusOrMinusWrapper(T, scala.math.Numeric<T>);
    Code:
       0: aload_0
       1: aload_1
       2: aload_2
       3: invokestatic  #45                 // Method org/scalactic/Tolerance$class.convertNumericToPlusOrMinusWrapper:(Lorg/scalactic/Tolerance;Ljava/lang/Object;Lscala/math/Numeric;)Lorg/scalactic/Tolerance$PlusOrMinusWrapper;
       6: areturn

  public <T> scala.Function0<T> function0(T);
    Code:
       0: aload_0
       1: aload_1
       2: invokestatic  #56                 // Method org/mockito/matchers/FunctionMatchers$class.function0:(Lorg/mockito/matchers/FunctionMatchers;Ljava/lang/Object;)Lscala/Function0;
       5: areturn

  public <T> T isNull();
    Code:
       0: aload_0
       1: invokestatic  #64                 // Method org/mockito/matchers/NullMatchers$class.isNull:(Lorg/mockito/matchers/NullMatchers;)Ljava/lang/Object;
       4: areturn

  public <T> T isNotNull();
    Code:
       0: aload_0
       1: invokestatic  #67                 // Method org/mockito/matchers/NullMatchers$class.isNotNull:(Lorg/mockito/matchers/NullMatchers;)Ljava/lang/Object;
       4: areturn

  public java.lang.String matches(java.lang.String);
    Code:
       0: aload_0
       1: aload_1
       2: invokestatic  #74                 // Method org/mockito/matchers/StringThatMatchers$class.matches:(Lorg/mockito/matchers/StringThatMatchers;Ljava/lang/String;)Ljava/lang/String;
       5: areturn

  public java.lang.String startsWith(java.lang.String);
    Code:
       0: aload_0
       1: aload_1
       2: invokestatic  #79                 // Method org/mockito/matchers/StringThatMatchers$class.startsWith:(Lorg/mockito/matchers/StringThatMatchers;Ljava/lang/String;)Ljava/lang/String;
       5: areturn

  public java.lang.String contains(java.lang.String);
    Code:
       0: aload_0
       1: aload_1
       2: invokestatic  #83                 // Method org/mockito/matchers/StringThatMatchers$class.contains:(Lorg/mockito/matchers/StringThatMatchers;Ljava/lang/String;)Ljava/lang/String;
       5: areturn

  public java.lang.String endsWith(java.lang.String);
    Code:
       0: aload_0
       1: aload_1
       2: invokestatic  #87                 // Method org/mockito/matchers/StringThatMatchers$class.endsWith:(Lorg/mockito/matchers/StringThatMatchers;Ljava/lang/String;)Ljava/lang/String;
       5: areturn

  public <T> T argThat(org.mockito.ArgumentMatcher<T>);
    Code:
       0: aload_0
       1: aload_1
       2: invokestatic  #95                 // Method org/mockito/matchers/ThatMatchers$class.argThat:(Lorg/mockito/matchers/ThatMatchers;Lorg/mockito/ArgumentMatcher;)Ljava/lang/Object;
       5: areturn

  public <T> T argThat(scala.Function1<T, java.lang.Object>, scala.Function0<java.lang.String>);
    Code:
       0: aload_0
       1: aload_1
       2: aload_2
       3: invokestatic  #101                // Method org/mockito/matchers/ThatMatchers$class.argThat:(Lorg/mockito/matchers/ThatMatchers;Lscala/Function1;Lscala/Function0;)Ljava/lang/Object;
       6: areturn

  public byte byteThat(org.mockito.ArgumentMatcher<java.lang.Object>);
    Code:
       0: aload_0
       1: aload_1
       2: invokestatic  #110                // Method org/mockito/matchers/ThatMatchers$class.byteThat:(Lorg/mockito/matchers/ThatMatchers;Lorg/mockito/ArgumentMatcher;)B
       5: ireturn

  public boolean booleanThat(org.mockito.ArgumentMatcher<java.lang.Object>);
    Code:
       0: aload_0
       1: aload_1
       2: invokestatic  #115                // Method org/mockito/matchers/ThatMatchers$class.booleanThat:(Lorg/mockito/matchers/ThatMatchers;Lorg/mockito/ArgumentMatcher;)Z
       5: ireturn

  public char charThat(org.mockito.ArgumentMatcher<java.lang.Object>);
    Code:
       0: aload_0
       1: aload_1
       2: invokestatic  #120                // Method org/mockito/matchers/ThatMatchers$class.charThat:(Lorg/mockito/matchers/ThatMatchers;Lorg/mockito/ArgumentMatcher;)C
       5: ireturn

  public double doubleThat(org.mockito.ArgumentMatcher<java.lang.Object>);
    Code:
       0: aload_0
       1: aload_1
       2: invokestatic  #125                // Method org/mockito/matchers/ThatMatchers$class.doubleThat:(Lorg/mockito/matchers/ThatMatchers;Lorg/mockito/ArgumentMatcher;)D
       5: dreturn

  public int intThat(org.mockito.ArgumentMatcher<java.lang.Object>);
    Code:
       0: aload_0
       1: aload_1
       2: invokestatic  #130                // Method org/mockito/matchers/ThatMatchers$class.intThat:(Lorg/mockito/matchers/ThatMatchers;Lorg/mockito/ArgumentMatcher;)I
       5: ireturn

  public float floatThat(org.mockito.ArgumentMatcher<java.lang.Object>);
    Code:
       0: aload_0
       1: aload_1
       2: invokestatic  #135                // Method org/mockito/matchers/ThatMatchers$class.floatThat:(Lorg/mockito/matchers/ThatMatchers;Lorg/mockito/ArgumentMatcher;)F
       5: freturn

  public short shortThat(org.mockito.ArgumentMatcher<java.lang.Object>);
    Code:
       0: aload_0
       1: aload_1
       2: invokestatic  #140                // Method org/mockito/matchers/ThatMatchers$class.shortThat:(Lorg/mockito/matchers/ThatMatchers;Lorg/mockito/ArgumentMatcher;)S
       5: ireturn

  public long longThat(org.mockito.ArgumentMatcher<java.lang.Object>);
    Code:
       0: aload_0
       1: aload_1
       2: invokestatic  #145                // Method org/mockito/matchers/ThatMatchers$class.longThat:(Lorg/mockito/matchers/ThatMatchers;Lorg/mockito/ArgumentMatcher;)J
       5: lreturn

  public <T> T argMatching(scala.PartialFunction<java.lang.Object, scala.runtime.BoxedUnit>);
    Code:
       0: aload_0
       1: aload_1
       2: invokestatic  #150                // Method org/mockito/matchers/ThatMatchers$class.argMatching:(Lorg/mockito/matchers/ThatMatchers;Lscala/PartialFunction;)Ljava/lang/Object;
       5: areturn

  public <T> java.lang.String argThat$default$2();
    Code:
       0: aload_0
       1: invokestatic  #157                // Method org/mockito/matchers/ThatMatchers$class.argThat$default$2:(Lorg/mockito/matchers/ThatMatchers;)Ljava/lang/String;
       4: areturn

  public <T> T same(T);
    Code:
       0: aload_0
       1: aload_1
       2: invokestatic  #164                // Method org/mockito/matchers/EqMatchers$class.same:(Lorg/mockito/matchers/EqMatchers;Ljava/lang/Object;)Ljava/lang/Object;
       5: areturn

  public <T> T isA(scala.reflect.ClassTag<T>);
    Code:
       0: aload_0
       1: aload_1
       2: invokestatic  #169                // Method org/mockito/matchers/EqMatchers$class.isA:(Lorg/mockito/matchers/EqMatchers;Lscala/reflect/ClassTag;)Ljava/lang/Object;
       5: areturn

  public <T> T refEq(T, scala.collection.Seq<java.lang.String>);
    Code:
       0: aload_0
       1: aload_1
       2: aload_2
       3: invokestatic  #176                // Method org/mockito/matchers/EqMatchers$class.refEq:(Lorg/mockito/matchers/EqMatchers;Ljava/lang/Object;Lscala/collection/Seq;)Ljava/lang/Object;
       6: areturn

  public <T> scala.collection.immutable.List<T> anyList();
    Code:
       0: aload_0
       1: invokestatic  #185                // Method org/mockito/matchers/AnyMatchers$class.anyList:(Lorg/mockito/matchers/AnyMatchers;)Lscala/collection/immutable/List;
       4: areturn

  public <T> scala.collection.Seq<T> anySeq();
    Code:
       0: aload_0
       1: invokestatic  #190                // Method org/mockito/matchers/AnyMatchers$class.anySeq:(Lorg/mockito/matchers/AnyMatchers;)Lscala/collection/Seq;
       4: areturn

  public <T> scala.collection.Iterable<T> anyIterable();
    Code:
       0: aload_0
       1: invokestatic  #195                // Method org/mockito/matchers/AnyMatchers$class.anyIterable:(Lorg/mockito/matchers/AnyMatchers;)Lscala/collection/Iterable;
       4: areturn

  public <T> scala.collection.immutable.Set<T> anySet();
    Code:
       0: aload_0
       1: invokestatic  #200                // Method org/mockito/matchers/AnyMatchers$class.anySet:(Lorg/mockito/matchers/AnyMatchers;)Lscala/collection/immutable/Set;
       4: areturn

  public <K, V> scala.collection.immutable.Map<K, V> anyMap();
    Code:
       0: aload_0
       1: invokestatic  #205                // Method org/mockito/matchers/AnyMatchers$class.anyMap:(Lorg/mockito/matchers/AnyMatchers;)Lscala/collection/immutable/Map;
       4: areturn

  public byte anyByte();
    Code:
       0: aload_0
       1: invokestatic  #210                // Method org/mockito/matchers/AnyMatchers$class.anyByte:(Lorg/mockito/matchers/AnyMatchers;)B
       4: ireturn

  public boolean anyBoolean();
    Code:
       0: aload_0
       1: invokestatic  #215                // Method org/mockito/matchers/AnyMatchers$class.anyBoolean:(Lorg/mockito/matchers/AnyMatchers;)Z
       4: ireturn

  public char anyChar();
    Code:
       0: aload_0
       1: invokestatic  #220                // Method org/mockito/matchers/AnyMatchers$class.anyChar:(Lorg/mockito/matchers/AnyMatchers;)C
       4: ireturn

  public double anyDouble();
    Code:
       0: aload_0
       1: invokestatic  #225                // Method org/mockito/matchers/AnyMatchers$class.anyDouble:(Lorg/mockito/matchers/AnyMatchers;)D
       4: dreturn

  public int anyInt();
    Code:
       0: aload_0
       1: invokestatic  #230                // Method org/mockito/matchers/AnyMatchers$class.anyInt:(Lorg/mockito/matchers/AnyMatchers;)I
       4: ireturn

  public float anyFloat();
    Code:
       0: aload_0
       1: invokestatic  #235                // Method org/mockito/matchers/AnyMatchers$class.anyFloat:(Lorg/mockito/matchers/AnyMatchers;)F
       4: freturn

  public short anyShort();
    Code:
       0: aload_0
       1: invokestatic  #240                // Method org/mockito/matchers/AnyMatchers$class.anyShort:(Lorg/mockito/matchers/AnyMatchers;)S
       4: ireturn

  public long anyLong();
    Code:
       0: aload_0
       1: invokestatic  #245                // Method org/mockito/matchers/AnyMatchers$class.anyLong:(Lorg/mockito/matchers/AnyMatchers;)J
       4: lreturn

  private org.mockito.ArgumentMatchersSugar$();
    Code:
       0: aload_0
       1: invokespecial #246                // Method java/lang/Object."<init>":()V
       4: aload_0
       5: putstatic     #248                // Field MODULE$:Lorg/mockito/ArgumentMatchersSugar$;
       8: aload_0
       9: invokestatic  #252                // Method org/mockito/matchers/AnyMatchers$class.$init$:(Lorg/mockito/matchers/AnyMatchers;)V
      12: aload_0
      13: invokestatic  #255                // Method org/mockito/matchers/EqMatchers$class.$init$:(Lorg/mockito/matchers/EqMatchers;)V
      16: aload_0
      17: invokestatic  #260                // Method org/mockito/matchers/EqMatchers_VersionSpecific$class.$init$:(Lorg/mockito/matchers/EqMatchers_VersionSpecific;)V
      20: aload_0
      21: invokestatic  #263                // Method org/mockito/matchers/ThatMatchers$class.$init$:(Lorg/mockito/matchers/ThatMatchers;)V
      24: aload_0
      25: invokestatic  #266                // Method org/mockito/matchers/StringThatMatchers$class.$init$:(Lorg/mockito/matchers/StringThatMatchers;)V
      28: aload_0
      29: invokestatic  #269                // Method org/mockito/matchers/NullMatchers$class.$init$:(Lorg/mockito/matchers/NullMatchers;)V
      32: aload_0
      33: invokestatic  #272                // Method org/mockito/matchers/FunctionMatchers$class.$init$:(Lorg/mockito/matchers/FunctionMatchers;)V
      36: aload_0
      37: invokestatic  #275                // Method org/scalactic/Tolerance$class.$init$:(Lorg/scalactic/Tolerance;)V
      40: aload_0
      41: invokestatic  #280                // Method org/mockito/matchers/NumericMatchers$class.$init$:(Lorg/mockito/matchers/NumericMatchers;)V
      44: aload_0
      45: invokestatic  #283                // Method org/mockito/matchers/MacroBasedMatchers$class.$init$:(Lorg/mockito/matchers/MacroBasedMatchers;)V
      48: return
}
