Compiled from "MockitoScalaSession.scala"
public final class org.mockito.MockitoScalaSession$MockitoScalaSessionListener$$anonfun$cleanLenientStubs$2$$anonfun$apply$5 extends scala.runtime.AbstractFunction1<org.mockito.internal.stubbing.StubbedInvocationMatcher, scala.Tuple2<org.mockito.internal.stubbing.StubbedInvocationMatcher, org.mockito.internal.stubbing.StubbedInvocationMatcher>> implements scala.Serializable {
  public static final long serialVersionUID;

  private final org.mockito.internal.stubbing.StubbedInvocationMatcher s$1;

  public final scala.Tuple2<org.mockito.internal.stubbing.StubbedInvocationMatcher, org.mockito.internal.stubbing.StubbedInvocationMatcher> apply(org.mockito.internal.stubbing.StubbedInvocationMatcher);
    Code:
       0: getstatic     #24                 // Field scala/Predef$ArrowAssoc$.MODULE$:Lscala/Predef$ArrowAssoc$;
       3: getstatic     #29                 // Field scala/Predef$.MODULE$:Lscala/Predef$;
       6: aload_0
       7: getfield      #31                 // Field s$1:Lorg/mockito/internal/stubbing/StubbedInvocationMatcher;
      10: invokevirtual #35                 // Method scala/Predef$.ArrowAssoc:(Ljava/lang/Object;)Ljava/lang/Object;
      13: aload_1
      14: invokevirtual #39                 // Method scala/Predef$ArrowAssoc$.$minus$greater$extension:(Ljava/lang/Object;Ljava/lang/Object;)Lscala/Tuple2;
      17: areturn

  public final java.lang.Object apply(java.lang.Object);
    Code:
       0: aload_0
       1: aload_1
       2: checkcast     #44                 // class org/mockito/internal/stubbing/StubbedInvocationMatcher
       5: invokevirtual #46                 // Method apply:(Lorg/mockito/internal/stubbing/StubbedInvocationMatcher;)Lscala/Tuple2;
       8: areturn

  public org.mockito.MockitoScalaSession$MockitoScalaSessionListener$$anonfun$cleanLenientStubs$2$$anonfun$apply$5(org.mockito.MockitoScalaSession$MockitoScalaSessionListener$$anonfun$cleanLenientStubs$2, org.mockito.internal.stubbing.StubbedInvocationMatcher);
    Code:
       0: aload_0
       1: aload_2
       2: putfield      #31                 // Field s$1:Lorg/mockito/internal/stubbing/StubbedInvocationMatcher;
       5: aload_0
       6: invokespecial #53                 // Method scala/runtime/AbstractFunction1."<init>":()V
       9: return
}
