Compiled from "MockitoScalaSession.scala"
public final class org.mockito.MockitoScalaSession$MockitoScalaSessionListener$$anonfun$cleanLenientStubs$3$$anon$2 implements org.mockito.invocation.DescribedInvocation {
  private final org.mockito.internal.stubbing.StubbedInvocationMatcher lenient$1;

  public org.mockito.invocation.Location getLocation();
    Code:
       0: aload_0
       1: getfield      #15                 // Field lenient$1:Lorg/mockito/internal/stubbing/StubbedInvocationMatcher;
       4: invokevirtual #19                 // Method org/mockito/internal/stubbing/StubbedInvocationMatcher.getLocation:()Lorg/mockito/invocation/Location;
       7: areturn

  public org.mockito.MockitoScalaSession$MockitoScalaSessionListener$$anonfun$cleanLenientStubs$3$$anon$2(org.mockito.MockitoScalaSession$MockitoScalaSessionListener$$anonfun$cleanLenientStubs$3, org.mockito.internal.stubbing.StubbedInvocationMatcher);
    Code:
       0: aload_0
       1: aload_2
       2: putfield      #15                 // Field lenient$1:Lorg/mockito/internal/stubbing/StubbedInvocationMatcher;
       5: aload_0
       6: invokespecial #26                 // Method java/lang/Object."<init>":()V
       9: return
}
