Compiled from "mockito.scala"
public final class org.mockito.package {
  public static <T> org.scalactic.Equality<T> serialisableEquality();
    Code:
       0: getstatic     #16                 // Field org/mockito/package$.MODULE$:Lorg/mockito/package$;
       3: invokevirtual #18                 // Method org/mockito/package$.serialisableEquality:()Lorg/scalactic/Equality;
       6: areturn

  public static org.scalactic.Equality<java.lang.reflect.Method> JavaMethodEquality();
    Code:
       0: getstatic     #16                 // Field org/mockito/package$.MODULE$:Lorg/mockito/package$;
       3: invokevirtual #21                 // Method org/mockito/package$.JavaMethodEquality:()Lorg/scalactic/Equality;
       6: areturn

  public static <T, P0, P1, P2, P3, P4, P5, P6, P7, P8, P9, P10, P11, P12, P13, P14, P15, P16, P17, P18, P19, P20, P21> org.mockito.stubbing.ScalaAnswer<T> functionToAnswer(scala.Function22<P0, P1, P2, P3, P4, P5, P6, P7, P8, P9, P10, P11, P12, P13, P14, P15, P16, P17, P18, P19, P20, P21, T>, org.mockito.internal.ValueClassExtractor<T>, org.mockito.internal.ValueClassWrapper<P0>, org.mockito.internal.ValueClassWrapper<P1>, org.mockito.internal.ValueClassWrapper<P2>, org.mockito.internal.ValueClassWrapper<P3>, org.mockito.internal.ValueClassWrapper<P4>, org.mockito.internal.ValueClassWrapper<P5>, org.mockito.internal.ValueClassWrapper<P6>, org.mockito.internal.ValueClassWrapper<P7>, org.mockito.internal.ValueClassWrapper<P8>, org.mockito.internal.ValueClassWrapper<P9>, org.mockito.internal.ValueClassWrapper<P10>, org.mockito.internal.ValueClassWrapper<P11>, org.mockito.internal.ValueClassWrapper<P12>, org.mockito.internal.ValueClassWrapper<P13>, org.mockito.internal.ValueClassWrapper<P14>, org.mockito.internal.ValueClassWrapper<P15>, org.mockito.internal.ValueClassWrapper<P16>, org.mockito.internal.ValueClassWrapper<P17>, org.mockito.internal.ValueClassWrapper<P18>, org.mockito.internal.ValueClassWrapper<P19>, org.mockito.internal.ValueClassWrapper<P20>, org.mockito.internal.ValueClassWrapper<P21>);
    Code:
       0: getstatic     #16                 // Field org/mockito/package$.MODULE$:Lorg/mockito/package$;
       3: aload_0
       4: aload_1
       5: aload_2
       6: aload_3
       7: aload         4
       9: aload         5
      11: aload         6
      13: aload         7
      15: aload         8
      17: aload         9
      19: aload         10
      21: aload         11
      23: aload         12
      25: aload         13
      27: aload         14
      29: aload         15
      31: aload         16
      33: aload         17
      35: aload         18
      37: aload         19
      39: aload         20
      41: aload         21
      43: aload         22
      45: aload         23
      47: invokevirtual #25                 // Method org/mockito/package$.functionToAnswer:(Lscala/Function22;Lorg/mockito/internal/ValueClassExtractor;Lorg/mockito/internal/ValueClassWrapper;Lorg/mockito/internal/ValueClassWrapper;Lorg/mockito/internal/ValueClassWrapper;Lorg/mockito/internal/ValueClassWrapper;Lorg/mockito/internal/ValueClassWrapper;Lorg/mockito/internal/ValueClassWrapper;Lorg/mockito/internal/ValueClassWrapper;Lorg/mockito/internal/ValueClassWrapper;Lorg/mockito/internal/ValueClassWrapper;Lorg/mockito/internal/ValueClassWrapper;Lorg/mockito/internal/ValueClassWrapper;Lorg/mockito/internal/ValueClassWrapper;Lorg/mockito/internal/ValueClassWrapper;Lorg/mockito/internal/ValueClassWrapper;Lorg/mockito/internal/ValueClassWrapper;Lorg/mockito/internal/ValueClassWrapper;Lorg/mockito/internal/ValueClassWrapper;Lorg/mockito/internal/ValueClassWrapper;Lorg/mockito/internal/ValueClassWrapper;Lorg/mockito/internal/ValueClassWrapper;Lorg/mockito/internal/ValueClassWrapper;Lorg/mockito/internal/ValueClassWrapper;)Lorg/mockito/stubbing/ScalaAnswer;
      50: areturn

  public static <T, P0, P1, P2, P3, P4, P5, P6, P7, P8, P9, P10, P11, P12, P13, P14, P15, P16, P17, P18, P19, P20> org.mockito.stubbing.ScalaAnswer<T> functionToAnswer(scala.Function21<P0, P1, P2, P3, P4, P5, P6, P7, P8, P9, P10, P11, P12, P13, P14, P15, P16, P17, P18, P19, P20, T>, org.mockito.internal.ValueClassExtractor<T>, org.mockito.internal.ValueClassWrapper<P0>, org.mockito.internal.ValueClassWrapper<P1>, org.mockito.internal.ValueClassWrapper<P2>, org.mockito.internal.ValueClassWrapper<P3>, org.mockito.internal.ValueClassWrapper<P4>, org.mockito.internal.ValueClassWrapper<P5>, org.mockito.internal.ValueClassWrapper<P6>, org.mockito.internal.ValueClassWrapper<P7>, org.mockito.internal.ValueClassWrapper<P8>, org.mockito.internal.ValueClassWrapper<P9>, org.mockito.internal.ValueClassWrapper<P10>, org.mockito.internal.ValueClassWrapper<P11>, org.mockito.internal.ValueClassWrapper<P12>, org.mockito.internal.ValueClassWrapper<P13>, org.mockito.internal.ValueClassWrapper<P14>, org.mockito.internal.ValueClassWrapper<P15>, org.mockito.internal.ValueClassWrapper<P16>, org.mockito.internal.ValueClassWrapper<P17>, org.mockito.internal.ValueClassWrapper<P18>, org.mockito.internal.ValueClassWrapper<P19>, org.mockito.internal.ValueClassWrapper<P20>);
    Code:
       0: getstatic     #16                 // Field org/mockito/package$.MODULE$:Lorg/mockito/package$;
       3: aload_0
       4: aload_1
       5: aload_2
       6: aload_3
       7: aload         4
       9: aload         5
      11: aload         6
      13: aload         7
      15: aload         8
      17: aload         9
      19: aload         10
      21: aload         11
      23: aload         12
      25: aload         13
      27: aload         14
      29: aload         15
      31: aload         16
      33: aload         17
      35: aload         18
      37: aload         19
      39: aload         20
      41: aload         21
      43: aload         22
      45: invokevirtual #28                 // Method org/mockito/package$.functionToAnswer:(Lscala/Function21;Lorg/mockito/internal/ValueClassExtractor;Lorg/mockito/internal/ValueClassWrapper;Lorg/mockito/internal/ValueClassWrapper;Lorg/mockito/internal/ValueClassWrapper;Lorg/mockito/internal/ValueClassWrapper;Lorg/mockito/internal/ValueClassWrapper;Lorg/mockito/internal/ValueClassWrapper;Lorg/mockito/internal/ValueClassWrapper;Lorg/mockito/internal/ValueClassWrapper;Lorg/mockito/internal/ValueClassWrapper;Lorg/mockito/internal/ValueClassWrapper;Lorg/mockito/internal/ValueClassWrapper;Lorg/mockito/internal/ValueClassWrapper;Lorg/mockito/internal/ValueClassWrapper;Lorg/mockito/internal/ValueClassWrapper;Lorg/mockito/internal/ValueClassWrapper;Lorg/mockito/internal/ValueClassWrapper;Lorg/mockito/internal/ValueClassWrapper;Lorg/mockito/internal/ValueClassWrapper;Lorg/mockito/internal/ValueClassWrapper;Lorg/mockito/internal/ValueClassWrapper;Lorg/mockito/internal/ValueClassWrapper;)Lorg/mockito/stubbing/ScalaAnswer;
      48: areturn

  public static <T, P0, P1, P2, P3, P4, P5, P6, P7, P8, P9, P10, P11, P12, P13, P14, P15, P16, P17, P18, P19> org.mockito.stubbing.ScalaAnswer<T> functionToAnswer(scala.Function20<P0, P1, P2, P3, P4, P5, P6, P7, P8, P9, P10, P11, P12, P13, P14, P15, P16, P17, P18, P19, T>, org.mockito.internal.ValueClassExtractor<T>, org.mockito.internal.ValueClassWrapper<P0>, org.mockito.internal.ValueClassWrapper<P1>, org.mockito.internal.ValueClassWrapper<P2>, org.mockito.internal.ValueClassWrapper<P3>, org.mockito.internal.ValueClassWrapper<P4>, org.mockito.internal.ValueClassWrapper<P5>, org.mockito.internal.ValueClassWrapper<P6>, org.mockito.internal.ValueClassWrapper<P7>, org.mockito.internal.ValueClassWrapper<P8>, org.mockito.internal.ValueClassWrapper<P9>, org.mockito.internal.ValueClassWrapper<P10>, org.mockito.internal.ValueClassWrapper<P11>, org.mockito.internal.ValueClassWrapper<P12>, org.mockito.internal.ValueClassWrapper<P13>, org.mockito.internal.ValueClassWrapper<P14>, org.mockito.internal.ValueClassWrapper<P15>, org.mockito.internal.ValueClassWrapper<P16>, org.mockito.internal.ValueClassWrapper<P17>, org.mockito.internal.ValueClassWrapper<P18>, org.mockito.internal.ValueClassWrapper<P19>);
    Code:
       0: getstatic     #16                 // Field org/mockito/package$.MODULE$:Lorg/mockito/package$;
       3: aload_0
       4: aload_1
       5: aload_2
       6: aload_3
       7: aload         4
       9: aload         5
      11: aload         6
      13: aload         7
      15: aload         8
      17: aload         9
      19: aload         10
      21: aload         11
      23: aload         12
      25: aload         13
      27: aload         14
      29: aload         15
      31: aload         16
      33: aload         17
      35: aload         18
      37: aload         19
      39: aload         20
      41: aload         21
      43: invokevirtual #31                 // Method org/mockito/package$.functionToAnswer:(Lscala/Function20;Lorg/mockito/internal/ValueClassExtractor;Lorg/mockito/internal/ValueClassWrapper;Lorg/mockito/internal/ValueClassWrapper;Lorg/mockito/internal/ValueClassWrapper;Lorg/mockito/internal/ValueClassWrapper;Lorg/mockito/internal/ValueClassWrapper;Lorg/mockito/internal/ValueClassWrapper;Lorg/mockito/internal/ValueClassWrapper;Lorg/mockito/internal/ValueClassWrapper;Lorg/mockito/internal/ValueClassWrapper;Lorg/mockito/internal/ValueClassWrapper;Lorg/mockito/internal/ValueClassWrapper;Lorg/mockito/internal/ValueClassWrapper;Lorg/mockito/internal/ValueClassWrapper;Lorg/mockito/internal/ValueClassWrapper;Lorg/mockito/internal/ValueClassWrapper;Lorg/mockito/internal/ValueClassWrapper;Lorg/mockito/internal/ValueClassWrapper;Lorg/mockito/internal/ValueClassWrapper;Lorg/mockito/internal/ValueClassWrapper;Lorg/mockito/internal/ValueClassWrapper;)Lorg/mockito/stubbing/ScalaAnswer;
      46: areturn

  public static <T, P0, P1, P2, P3, P4, P5, P6, P7, P8, P9, P10, P11, P12, P13, P14, P15, P16, P17, P18> org.mockito.stubbing.ScalaAnswer<T> functionToAnswer(scala.Function19<P0, P1, P2, P3, P4, P5, P6, P7, P8, P9, P10, P11, P12, P13, P14, P15, P16, P17, P18, T>, org.mockito.internal.ValueClassExtractor<T>, org.mockito.internal.ValueClassWrapper<P0>, org.mockito.internal.ValueClassWrapper<P1>, org.mockito.internal.ValueClassWrapper<P2>, org.mockito.internal.ValueClassWrapper<P3>, org.mockito.internal.ValueClassWrapper<P4>, org.mockito.internal.ValueClassWrapper<P5>, org.mockito.internal.ValueClassWrapper<P6>, org.mockito.internal.ValueClassWrapper<P7>, org.mockito.internal.ValueClassWrapper<P8>, org.mockito.internal.ValueClassWrapper<P9>, org.mockito.internal.ValueClassWrapper<P10>, org.mockito.internal.ValueClassWrapper<P11>, org.mockito.internal.ValueClassWrapper<P12>, org.mockito.internal.ValueClassWrapper<P13>, org.mockito.internal.ValueClassWrapper<P14>, org.mockito.internal.ValueClassWrapper<P15>, org.mockito.internal.ValueClassWrapper<P16>, org.mockito.internal.ValueClassWrapper<P17>, org.mockito.internal.ValueClassWrapper<P18>);
    Code:
       0: getstatic     #16                 // Field org/mockito/package$.MODULE$:Lorg/mockito/package$;
       3: aload_0
       4: aload_1
       5: aload_2
       6: aload_3
       7: aload         4
       9: aload         5
      11: aload         6
      13: aload         7
      15: aload         8
      17: aload         9
      19: aload         10
      21: aload         11
      23: aload         12
      25: aload         13
      27: aload         14
      29: aload         15
      31: aload         16
      33: aload         17
      35: aload         18
      37: aload         19
      39: aload         20
      41: invokevirtual #34                 // Method org/mockito/package$.functionToAnswer:(Lscala/Function19;Lorg/mockito/internal/ValueClassExtractor;Lorg/mockito/internal/ValueClassWrapper;Lorg/mockito/internal/ValueClassWrapper;Lorg/mockito/internal/ValueClassWrapper;Lorg/mockito/internal/ValueClassWrapper;Lorg/mockito/internal/ValueClassWrapper;Lorg/mockito/internal/ValueClassWrapper;Lorg/mockito/internal/ValueClassWrapper;Lorg/mockito/internal/ValueClassWrapper;Lorg/mockito/internal/ValueClassWrapper;Lorg/mockito/internal/ValueClassWrapper;Lorg/mockito/internal/ValueClassWrapper;Lorg/mockito/internal/ValueClassWrapper;Lorg/mockito/internal/ValueClassWrapper;Lorg/mockito/internal/ValueClassWrapper;Lorg/mockito/internal/ValueClassWrapper;Lorg/mockito/internal/ValueClassWrapper;Lorg/mockito/internal/ValueClassWrapper;Lorg/mockito/internal/ValueClassWrapper;Lorg/mockito/internal/ValueClassWrapper;)Lorg/mockito/stubbing/ScalaAnswer;
      44: areturn

  public static <T, P0, P1, P2, P3, P4, P5, P6, P7, P8, P9, P10, P11, P12, P13, P14, P15, P16, P17> org.mockito.stubbing.ScalaAnswer<T> functionToAnswer(scala.Function18<P0, P1, P2, P3, P4, P5, P6, P7, P8, P9, P10, P11, P12, P13, P14, P15, P16, P17, T>, org.mockito.internal.ValueClassExtractor<T>, org.mockito.internal.ValueClassWrapper<P0>, org.mockito.internal.ValueClassWrapper<P1>, org.mockito.internal.ValueClassWrapper<P2>, org.mockito.internal.ValueClassWrapper<P3>, org.mockito.internal.ValueClassWrapper<P4>, org.mockito.internal.ValueClassWrapper<P5>, org.mockito.internal.ValueClassWrapper<P6>, org.mockito.internal.ValueClassWrapper<P7>, org.mockito.internal.ValueClassWrapper<P8>, org.mockito.internal.ValueClassWrapper<P9>, org.mockito.internal.ValueClassWrapper<P10>, org.mockito.internal.ValueClassWrapper<P11>, org.mockito.internal.ValueClassWrapper<P12>, org.mockito.internal.ValueClassWrapper<P13>, org.mockito.internal.ValueClassWrapper<P14>, org.mockito.internal.ValueClassWrapper<P15>, org.mockito.internal.ValueClassWrapper<P16>, org.mockito.internal.ValueClassWrapper<P17>);
    Code:
       0: getstatic     #16                 // Field org/mockito/package$.MODULE$:Lorg/mockito/package$;
       3: aload_0
       4: aload_1
       5: aload_2
       6: aload_3
       7: aload         4
       9: aload         5
      11: aload         6
      13: aload         7
      15: aload         8
      17: aload         9
      19: aload         10
      21: aload         11
      23: aload         12
      25: aload         13
      27: aload         14
      29: aload         15
      31: aload         16
      33: aload         17
      35: aload         18
      37: aload         19
      39: invokevirtual #37                 // Method org/mockito/package$.functionToAnswer:(Lscala/Function18;Lorg/mockito/internal/ValueClassExtractor;Lorg/mockito/internal/ValueClassWrapper;Lorg/mockito/internal/ValueClassWrapper;Lorg/mockito/internal/ValueClassWrapper;Lorg/mockito/internal/ValueClassWrapper;Lorg/mockito/internal/ValueClassWrapper;Lorg/mockito/internal/ValueClassWrapper;Lorg/mockito/internal/ValueClassWrapper;Lorg/mockito/internal/ValueClassWrapper;Lorg/mockito/internal/ValueClassWrapper;Lorg/mockito/internal/ValueClassWrapper;Lorg/mockito/internal/ValueClassWrapper;Lorg/mockito/internal/ValueClassWrapper;Lorg/mockito/internal/ValueClassWrapper;Lorg/mockito/internal/ValueClassWrapper;Lorg/mockito/internal/ValueClassWrapper;Lorg/mockito/internal/ValueClassWrapper;Lorg/mockito/internal/ValueClassWrapper;Lorg/mockito/internal/ValueClassWrapper;)Lorg/mockito/stubbing/ScalaAnswer;
      42: areturn

  public static <T, P0, P1, P2, P3, P4, P5, P6, P7, P8, P9, P10, P11, P12, P13, P14, P15, P16> org.mockito.stubbing.ScalaAnswer<T> functionToAnswer(scala.Function17<P0, P1, P2, P3, P4, P5, P6, P7, P8, P9, P10, P11, P12, P13, P14, P15, P16, T>, org.mockito.internal.ValueClassExtractor<T>, org.mockito.internal.ValueClassWrapper<P0>, org.mockito.internal.ValueClassWrapper<P1>, org.mockito.internal.ValueClassWrapper<P2>, org.mockito.internal.ValueClassWrapper<P3>, org.mockito.internal.ValueClassWrapper<P4>, org.mockito.internal.ValueClassWrapper<P5>, org.mockito.internal.ValueClassWrapper<P6>, org.mockito.internal.ValueClassWrapper<P7>, org.mockito.internal.ValueClassWrapper<P8>, org.mockito.internal.ValueClassWrapper<P9>, org.mockito.internal.ValueClassWrapper<P10>, org.mockito.internal.ValueClassWrapper<P11>, org.mockito.internal.ValueClassWrapper<P12>, org.mockito.internal.ValueClassWrapper<P13>, org.mockito.internal.ValueClassWrapper<P14>, org.mockito.internal.ValueClassWrapper<P15>, org.mockito.internal.ValueClassWrapper<P16>);
    Code:
       0: getstatic     #16                 // Field org/mockito/package$.MODULE$:Lorg/mockito/package$;
       3: aload_0
       4: aload_1
       5: aload_2
       6: aload_3
       7: aload         4
       9: aload         5
      11: aload         6
      13: aload         7
      15: aload         8
      17: aload         9
      19: aload         10
      21: aload         11
      23: aload         12
      25: aload         13
      27: aload         14
      29: aload         15
      31: aload         16
      33: aload         17
      35: aload         18
      37: invokevirtual #40                 // Method org/mockito/package$.functionToAnswer:(Lscala/Function17;Lorg/mockito/internal/ValueClassExtractor;Lorg/mockito/internal/ValueClassWrapper;Lorg/mockito/internal/ValueClassWrapper;Lorg/mockito/internal/ValueClassWrapper;Lorg/mockito/internal/ValueClassWrapper;Lorg/mockito/internal/ValueClassWrapper;Lorg/mockito/internal/ValueClassWrapper;Lorg/mockito/internal/ValueClassWrapper;Lorg/mockito/internal/ValueClassWrapper;Lorg/mockito/internal/ValueClassWrapper;Lorg/mockito/internal/ValueClassWrapper;Lorg/mockito/internal/ValueClassWrapper;Lorg/mockito/internal/ValueClassWrapper;Lorg/mockito/internal/ValueClassWrapper;Lorg/mockito/internal/ValueClassWrapper;Lorg/mockito/internal/ValueClassWrapper;Lorg/mockito/internal/ValueClassWrapper;Lorg/mockito/internal/ValueClassWrapper;)Lorg/mockito/stubbing/ScalaAnswer;
      40: areturn

  public static <T, P0, P1, P2, P3, P4, P5, P6, P7, P8, P9, P10, P11, P12, P13, P14, P15> org.mockito.stubbing.ScalaAnswer<T> functionToAnswer(scala.Function16<P0, P1, P2, P3, P4, P5, P6, P7, P8, P9, P10, P11, P12, P13, P14, P15, T>, org.mockito.internal.ValueClassExtractor<T>, org.mockito.internal.ValueClassWrapper<P0>, org.mockito.internal.ValueClassWrapper<P1>, org.mockito.internal.ValueClassWrapper<P2>, org.mockito.internal.ValueClassWrapper<P3>, org.mockito.internal.ValueClassWrapper<P4>, org.mockito.internal.ValueClassWrapper<P5>, org.mockito.internal.ValueClassWrapper<P6>, org.mockito.internal.ValueClassWrapper<P7>, org.mockito.internal.ValueClassWrapper<P8>, org.mockito.internal.ValueClassWrapper<P9>, org.mockito.internal.ValueClassWrapper<P10>, org.mockito.internal.ValueClassWrapper<P11>, org.mockito.internal.ValueClassWrapper<P12>, org.mockito.internal.ValueClassWrapper<P13>, org.mockito.internal.ValueClassWrapper<P14>, org.mockito.internal.ValueClassWrapper<P15>);
    Code:
       0: getstatic     #16                 // Field org/mockito/package$.MODULE$:Lorg/mockito/package$;
       3: aload_0
       4: aload_1
       5: aload_2
       6: aload_3
       7: aload         4
       9: aload         5
      11: aload         6
      13: aload         7
      15: aload         8
      17: aload         9
      19: aload         10
      21: aload         11
      23: aload         12
      25: aload         13
      27: aload         14
      29: aload         15
      31: aload         16
      33: aload         17
      35: invokevirtual #43                 // Method org/mockito/package$.functionToAnswer:(Lscala/Function16;Lorg/mockito/internal/ValueClassExtractor;Lorg/mockito/internal/ValueClassWrapper;Lorg/mockito/internal/ValueClassWrapper;Lorg/mockito/internal/ValueClassWrapper;Lorg/mockito/internal/ValueClassWrapper;Lorg/mockito/internal/ValueClassWrapper;Lorg/mockito/internal/ValueClassWrapper;Lorg/mockito/internal/ValueClassWrapper;Lorg/mockito/internal/ValueClassWrapper;Lorg/mockito/internal/ValueClassWrapper;Lorg/mockito/internal/ValueClassWrapper;Lorg/mockito/internal/ValueClassWrapper;Lorg/mockito/internal/ValueClassWrapper;Lorg/mockito/internal/ValueClassWrapper;Lorg/mockito/internal/ValueClassWrapper;Lorg/mockito/internal/ValueClassWrapper;Lorg/mockito/internal/ValueClassWrapper;)Lorg/mockito/stubbing/ScalaAnswer;
      38: areturn

  public static <T, P0, P1, P2, P3, P4, P5, P6, P7, P8, P9, P10, P11, P12, P13, P14> org.mockito.stubbing.ScalaAnswer<T> functionToAnswer(scala.Function15<P0, P1, P2, P3, P4, P5, P6, P7, P8, P9, P10, P11, P12, P13, P14, T>, org.mockito.internal.ValueClassExtractor<T>, org.mockito.internal.ValueClassWrapper<P0>, org.mockito.internal.ValueClassWrapper<P1>, org.mockito.internal.ValueClassWrapper<P2>, org.mockito.internal.ValueClassWrapper<P3>, org.mockito.internal.ValueClassWrapper<P4>, org.mockito.internal.ValueClassWrapper<P5>, org.mockito.internal.ValueClassWrapper<P6>, org.mockito.internal.ValueClassWrapper<P7>, org.mockito.internal.ValueClassWrapper<P8>, org.mockito.internal.ValueClassWrapper<P9>, org.mockito.internal.ValueClassWrapper<P10>, org.mockito.internal.ValueClassWrapper<P11>, org.mockito.internal.ValueClassWrapper<P12>, org.mockito.internal.ValueClassWrapper<P13>, org.mockito.internal.ValueClassWrapper<P14>);
    Code:
       0: getstatic     #16                 // Field org/mockito/package$.MODULE$:Lorg/mockito/package$;
       3: aload_0
       4: aload_1
       5: aload_2
       6: aload_3
       7: aload         4
       9: aload         5
      11: aload         6
      13: aload         7
      15: aload         8
      17: aload         9
      19: aload         10
      21: aload         11
      23: aload         12
      25: aload         13
      27: aload         14
      29: aload         15
      31: aload         16
      33: invokevirtual #46                 // Method org/mockito/package$.functionToAnswer:(Lscala/Function15;Lorg/mockito/internal/ValueClassExtractor;Lorg/mockito/internal/ValueClassWrapper;Lorg/mockito/internal/ValueClassWrapper;Lorg/mockito/internal/ValueClassWrapper;Lorg/mockito/internal/ValueClassWrapper;Lorg/mockito/internal/ValueClassWrapper;Lorg/mockito/internal/ValueClassWrapper;Lorg/mockito/internal/ValueClassWrapper;Lorg/mockito/internal/ValueClassWrapper;Lorg/mockito/internal/ValueClassWrapper;Lorg/mockito/internal/ValueClassWrapper;Lorg/mockito/internal/ValueClassWrapper;Lorg/mockito/internal/ValueClassWrapper;Lorg/mockito/internal/ValueClassWrapper;Lorg/mockito/internal/ValueClassWrapper;Lorg/mockito/internal/ValueClassWrapper;)Lorg/mockito/stubbing/ScalaAnswer;
      36: areturn

  public static <T, P0, P1, P2, P3, P4, P5, P6, P7, P8, P9, P10, P11, P12, P13> org.mockito.stubbing.ScalaAnswer<T> functionToAnswer(scala.Function14<P0, P1, P2, P3, P4, P5, P6, P7, P8, P9, P10, P11, P12, P13, T>, org.mockito.internal.ValueClassExtractor<T>, org.mockito.internal.ValueClassWrapper<P0>, org.mockito.internal.ValueClassWrapper<P1>, org.mockito.internal.ValueClassWrapper<P2>, org.mockito.internal.ValueClassWrapper<P3>, org.mockito.internal.ValueClassWrapper<P4>, org.mockito.internal.ValueClassWrapper<P5>, org.mockito.internal.ValueClassWrapper<P6>, org.mockito.internal.ValueClassWrapper<P7>, org.mockito.internal.ValueClassWrapper<P8>, org.mockito.internal.ValueClassWrapper<P9>, org.mockito.internal.ValueClassWrapper<P10>, org.mockito.internal.ValueClassWrapper<P11>, org.mockito.internal.ValueClassWrapper<P12>, org.mockito.internal.ValueClassWrapper<P13>);
    Code:
       0: getstatic     #16                 // Field org/mockito/package$.MODULE$:Lorg/mockito/package$;
       3: aload_0
       4: aload_1
       5: aload_2
       6: aload_3
       7: aload         4
       9: aload         5
      11: aload         6
      13: aload         7
      15: aload         8
      17: aload         9
      19: aload         10
      21: aload         11
      23: aload         12
      25: aload         13
      27: aload         14
      29: aload         15
      31: invokevirtual #49                 // Method org/mockito/package$.functionToAnswer:(Lscala/Function14;Lorg/mockito/internal/ValueClassExtractor;Lorg/mockito/internal/ValueClassWrapper;Lorg/mockito/internal/ValueClassWrapper;Lorg/mockito/internal/ValueClassWrapper;Lorg/mockito/internal/ValueClassWrapper;Lorg/mockito/internal/ValueClassWrapper;Lorg/mockito/internal/ValueClassWrapper;Lorg/mockito/internal/ValueClassWrapper;Lorg/mockito/internal/ValueClassWrapper;Lorg/mockito/internal/ValueClassWrapper;Lorg/mockito/internal/ValueClassWrapper;Lorg/mockito/internal/ValueClassWrapper;Lorg/mockito/internal/ValueClassWrapper;Lorg/mockito/internal/ValueClassWrapper;Lorg/mockito/internal/ValueClassWrapper;)Lorg/mockito/stubbing/ScalaAnswer;
      34: areturn

  public static <T, P0, P1, P2, P3, P4, P5, P6, P7, P8, P9, P10, P11, P12> org.mockito.stubbing.ScalaAnswer<T> functionToAnswer(scala.Function13<P0, P1, P2, P3, P4, P5, P6, P7, P8, P9, P10, P11, P12, T>, org.mockito.internal.ValueClassExtractor<T>, org.mockito.internal.ValueClassWrapper<P0>, org.mockito.internal.ValueClassWrapper<P1>, org.mockito.internal.ValueClassWrapper<P2>, org.mockito.internal.ValueClassWrapper<P3>, org.mockito.internal.ValueClassWrapper<P4>, org.mockito.internal.ValueClassWrapper<P5>, org.mockito.internal.ValueClassWrapper<P6>, org.mockito.internal.ValueClassWrapper<P7>, org.mockito.internal.ValueClassWrapper<P8>, org.mockito.internal.ValueClassWrapper<P9>, org.mockito.internal.ValueClassWrapper<P10>, org.mockito.internal.ValueClassWrapper<P11>, org.mockito.internal.ValueClassWrapper<P12>);
    Code:
       0: getstatic     #16                 // Field org/mockito/package$.MODULE$:Lorg/mockito/package$;
       3: aload_0
       4: aload_1
       5: aload_2
       6: aload_3
       7: aload         4
       9: aload         5
      11: aload         6
      13: aload         7
      15: aload         8
      17: aload         9
      19: aload         10
      21: aload         11
      23: aload         12
      25: aload         13
      27: aload         14
      29: invokevirtual #52                 // Method org/mockito/package$.functionToAnswer:(Lscala/Function13;Lorg/mockito/internal/ValueClassExtractor;Lorg/mockito/internal/ValueClassWrapper;Lorg/mockito/internal/ValueClassWrapper;Lorg/mockito/internal/ValueClassWrapper;Lorg/mockito/internal/ValueClassWrapper;Lorg/mockito/internal/ValueClassWrapper;Lorg/mockito/internal/ValueClassWrapper;Lorg/mockito/internal/ValueClassWrapper;Lorg/mockito/internal/ValueClassWrapper;Lorg/mockito/internal/ValueClassWrapper;Lorg/mockito/internal/ValueClassWrapper;Lorg/mockito/internal/ValueClassWrapper;Lorg/mockito/internal/ValueClassWrapper;Lorg/mockito/internal/ValueClassWrapper;)Lorg/mockito/stubbing/ScalaAnswer;
      32: areturn

  public static <T, P0, P1, P2, P3, P4, P5, P6, P7, P8, P9, P10, P11> org.mockito.stubbing.ScalaAnswer<T> functionToAnswer(scala.Function12<P0, P1, P2, P3, P4, P5, P6, P7, P8, P9, P10, P11, T>, org.mockito.internal.ValueClassExtractor<T>, org.mockito.internal.ValueClassWrapper<P0>, org.mockito.internal.ValueClassWrapper<P1>, org.mockito.internal.ValueClassWrapper<P2>, org.mockito.internal.ValueClassWrapper<P3>, org.mockito.internal.ValueClassWrapper<P4>, org.mockito.internal.ValueClassWrapper<P5>, org.mockito.internal.ValueClassWrapper<P6>, org.mockito.internal.ValueClassWrapper<P7>, org.mockito.internal.ValueClassWrapper<P8>, org.mockito.internal.ValueClassWrapper<P9>, org.mockito.internal.ValueClassWrapper<P10>, org.mockito.internal.ValueClassWrapper<P11>);
    Code:
       0: getstatic     #16                 // Field org/mockito/package$.MODULE$:Lorg/mockito/package$;
       3: aload_0
       4: aload_1
       5: aload_2
       6: aload_3
       7: aload         4
       9: aload         5
      11: aload         6
      13: aload         7
      15: aload         8
      17: aload         9
      19: aload         10
      21: aload         11
      23: aload         12
      25: aload         13
      27: invokevirtual #55                 // Method org/mockito/package$.functionToAnswer:(Lscala/Function12;Lorg/mockito/internal/ValueClassExtractor;Lorg/mockito/internal/ValueClassWrapper;Lorg/mockito/internal/ValueClassWrapper;Lorg/mockito/internal/ValueClassWrapper;Lorg/mockito/internal/ValueClassWrapper;Lorg/mockito/internal/ValueClassWrapper;Lorg/mockito/internal/ValueClassWrapper;Lorg/mockito/internal/ValueClassWrapper;Lorg/mockito/internal/ValueClassWrapper;Lorg/mockito/internal/ValueClassWrapper;Lorg/mockito/internal/ValueClassWrapper;Lorg/mockito/internal/ValueClassWrapper;Lorg/mockito/internal/ValueClassWrapper;)Lorg/mockito/stubbing/ScalaAnswer;
      30: areturn

  public static <T, P0, P1, P2, P3, P4, P5, P6, P7, P8, P9, P10> org.mockito.stubbing.ScalaAnswer<T> functionToAnswer(scala.Function11<P0, P1, P2, P3, P4, P5, P6, P7, P8, P9, P10, T>, org.mockito.internal.ValueClassExtractor<T>, org.mockito.internal.ValueClassWrapper<P0>, org.mockito.internal.ValueClassWrapper<P1>, org.mockito.internal.ValueClassWrapper<P2>, org.mockito.internal.ValueClassWrapper<P3>, org.mockito.internal.ValueClassWrapper<P4>, org.mockito.internal.ValueClassWrapper<P5>, org.mockito.internal.ValueClassWrapper<P6>, org.mockito.internal.ValueClassWrapper<P7>, org.mockito.internal.ValueClassWrapper<P8>, org.mockito.internal.ValueClassWrapper<P9>, org.mockito.internal.ValueClassWrapper<P10>);
    Code:
       0: getstatic     #16                 // Field org/mockito/package$.MODULE$:Lorg/mockito/package$;
       3: aload_0
       4: aload_1
       5: aload_2
       6: aload_3
       7: aload         4
       9: aload         5
      11: aload         6
      13: aload         7
      15: aload         8
      17: aload         9
      19: aload         10
      21: aload         11
      23: aload         12
      25: invokevirtual #58                 // Method org/mockito/package$.functionToAnswer:(Lscala/Function11;Lorg/mockito/internal/ValueClassExtractor;Lorg/mockito/internal/ValueClassWrapper;Lorg/mockito/internal/ValueClassWrapper;Lorg/mockito/internal/ValueClassWrapper;Lorg/mockito/internal/ValueClassWrapper;Lorg/mockito/internal/ValueClassWrapper;Lorg/mockito/internal/ValueClassWrapper;Lorg/mockito/internal/ValueClassWrapper;Lorg/mockito/internal/ValueClassWrapper;Lorg/mockito/internal/ValueClassWrapper;Lorg/mockito/internal/ValueClassWrapper;Lorg/mockito/internal/ValueClassWrapper;)Lorg/mockito/stubbing/ScalaAnswer;
      28: areturn

  public static <T, P0, P1, P2, P3, P4, P5, P6, P7, P8, P9> org.mockito.stubbing.ScalaAnswer<T> functionToAnswer(scala.Function10<P0, P1, P2, P3, P4, P5, P6, P7, P8, P9, T>, org.mockito.internal.ValueClassExtractor<T>, org.mockito.internal.ValueClassWrapper<P0>, org.mockito.internal.ValueClassWrapper<P1>, org.mockito.internal.ValueClassWrapper<P2>, org.mockito.internal.ValueClassWrapper<P3>, org.mockito.internal.ValueClassWrapper<P4>, org.mockito.internal.ValueClassWrapper<P5>, org.mockito.internal.ValueClassWrapper<P6>, org.mockito.internal.ValueClassWrapper<P7>, org.mockito.internal.ValueClassWrapper<P8>, org.mockito.internal.ValueClassWrapper<P9>);
    Code:
       0: getstatic     #16                 // Field org/mockito/package$.MODULE$:Lorg/mockito/package$;
       3: aload_0
       4: aload_1
       5: aload_2
       6: aload_3
       7: aload         4
       9: aload         5
      11: aload         6
      13: aload         7
      15: aload         8
      17: aload         9
      19: aload         10
      21: aload         11
      23: invokevirtual #61                 // Method org/mockito/package$.functionToAnswer:(Lscala/Function10;Lorg/mockito/internal/ValueClassExtractor;Lorg/mockito/internal/ValueClassWrapper;Lorg/mockito/internal/ValueClassWrapper;Lorg/mockito/internal/ValueClassWrapper;Lorg/mockito/internal/ValueClassWrapper;Lorg/mockito/internal/ValueClassWrapper;Lorg/mockito/internal/ValueClassWrapper;Lorg/mockito/internal/ValueClassWrapper;Lorg/mockito/internal/ValueClassWrapper;Lorg/mockito/internal/ValueClassWrapper;Lorg/mockito/internal/ValueClassWrapper;)Lorg/mockito/stubbing/ScalaAnswer;
      26: areturn

  public static <T, P0, P1, P2, P3, P4, P5, P6, P7, P8> org.mockito.stubbing.ScalaAnswer<T> functionToAnswer(scala.Function9<P0, P1, P2, P3, P4, P5, P6, P7, P8, T>, org.mockito.internal.ValueClassExtractor<T>, org.mockito.internal.ValueClassWrapper<P0>, org.mockito.internal.ValueClassWrapper<P1>, org.mockito.internal.ValueClassWrapper<P2>, org.mockito.internal.ValueClassWrapper<P3>, org.mockito.internal.ValueClassWrapper<P4>, org.mockito.internal.ValueClassWrapper<P5>, org.mockito.internal.ValueClassWrapper<P6>, org.mockito.internal.ValueClassWrapper<P7>, org.mockito.internal.ValueClassWrapper<P8>);
    Code:
       0: getstatic     #16                 // Field org/mockito/package$.MODULE$:Lorg/mockito/package$;
       3: aload_0
       4: aload_1
       5: aload_2
       6: aload_3
       7: aload         4
       9: aload         5
      11: aload         6
      13: aload         7
      15: aload         8
      17: aload         9
      19: aload         10
      21: invokevirtual #64                 // Method org/mockito/package$.functionToAnswer:(Lscala/Function9;Lorg/mockito/internal/ValueClassExtractor;Lorg/mockito/internal/ValueClassWrapper;Lorg/mockito/internal/ValueClassWrapper;Lorg/mockito/internal/ValueClassWrapper;Lorg/mockito/internal/ValueClassWrapper;Lorg/mockito/internal/ValueClassWrapper;Lorg/mockito/internal/ValueClassWrapper;Lorg/mockito/internal/ValueClassWrapper;Lorg/mockito/internal/ValueClassWrapper;Lorg/mockito/internal/ValueClassWrapper;)Lorg/mockito/stubbing/ScalaAnswer;
      24: areturn

  public static <T, P0, P1, P2, P3, P4, P5, P6, P7> org.mockito.stubbing.ScalaAnswer<T> functionToAnswer(scala.Function8<P0, P1, P2, P3, P4, P5, P6, P7, T>, org.mockito.internal.ValueClassExtractor<T>, org.mockito.internal.ValueClassWrapper<P0>, org.mockito.internal.ValueClassWrapper<P1>, org.mockito.internal.ValueClassWrapper<P2>, org.mockito.internal.ValueClassWrapper<P3>, org.mockito.internal.ValueClassWrapper<P4>, org.mockito.internal.ValueClassWrapper<P5>, org.mockito.internal.ValueClassWrapper<P6>, org.mockito.internal.ValueClassWrapper<P7>);
    Code:
       0: getstatic     #16                 // Field org/mockito/package$.MODULE$:Lorg/mockito/package$;
       3: aload_0
       4: aload_1
       5: aload_2
       6: aload_3
       7: aload         4
       9: aload         5
      11: aload         6
      13: aload         7
      15: aload         8
      17: aload         9
      19: invokevirtual #67                 // Method org/mockito/package$.functionToAnswer:(Lscala/Function8;Lorg/mockito/internal/ValueClassExtractor;Lorg/mockito/internal/ValueClassWrapper;Lorg/mockito/internal/ValueClassWrapper;Lorg/mockito/internal/ValueClassWrapper;Lorg/mockito/internal/ValueClassWrapper;Lorg/mockito/internal/ValueClassWrapper;Lorg/mockito/internal/ValueClassWrapper;Lorg/mockito/internal/ValueClassWrapper;Lorg/mockito/internal/ValueClassWrapper;)Lorg/mockito/stubbing/ScalaAnswer;
      22: areturn

  public static <T, P0, P1, P2, P3, P4, P5, P6> org.mockito.stubbing.ScalaAnswer<T> functionToAnswer(scala.Function7<P0, P1, P2, P3, P4, P5, P6, T>, org.mockito.internal.ValueClassExtractor<T>, org.mockito.internal.ValueClassWrapper<P0>, org.mockito.internal.ValueClassWrapper<P1>, org.mockito.internal.ValueClassWrapper<P2>, org.mockito.internal.ValueClassWrapper<P3>, org.mockito.internal.ValueClassWrapper<P4>, org.mockito.internal.ValueClassWrapper<P5>, org.mockito.internal.ValueClassWrapper<P6>);
    Code:
       0: getstatic     #16                 // Field org/mockito/package$.MODULE$:Lorg/mockito/package$;
       3: aload_0
       4: aload_1
       5: aload_2
       6: aload_3
       7: aload         4
       9: aload         5
      11: aload         6
      13: aload         7
      15: aload         8
      17: invokevirtual #70                 // Method org/mockito/package$.functionToAnswer:(Lscala/Function7;Lorg/mockito/internal/ValueClassExtractor;Lorg/mockito/internal/ValueClassWrapper;Lorg/mockito/internal/ValueClassWrapper;Lorg/mockito/internal/ValueClassWrapper;Lorg/mockito/internal/ValueClassWrapper;Lorg/mockito/internal/ValueClassWrapper;Lorg/mockito/internal/ValueClassWrapper;Lorg/mockito/internal/ValueClassWrapper;)Lorg/mockito/stubbing/ScalaAnswer;
      20: areturn

  public static <T, P0, P1, P2, P3, P4, P5> org.mockito.stubbing.ScalaAnswer<T> functionToAnswer(scala.Function6<P0, P1, P2, P3, P4, P5, T>, org.mockito.internal.ValueClassExtractor<T>, org.mockito.internal.ValueClassWrapper<P0>, org.mockito.internal.ValueClassWrapper<P1>, org.mockito.internal.ValueClassWrapper<P2>, org.mockito.internal.ValueClassWrapper<P3>, org.mockito.internal.ValueClassWrapper<P4>, org.mockito.internal.ValueClassWrapper<P5>);
    Code:
       0: getstatic     #16                 // Field org/mockito/package$.MODULE$:Lorg/mockito/package$;
       3: aload_0
       4: aload_1
       5: aload_2
       6: aload_3
       7: aload         4
       9: aload         5
      11: aload         6
      13: aload         7
      15: invokevirtual #73                 // Method org/mockito/package$.functionToAnswer:(Lscala/Function6;Lorg/mockito/internal/ValueClassExtractor;Lorg/mockito/internal/ValueClassWrapper;Lorg/mockito/internal/ValueClassWrapper;Lorg/mockito/internal/ValueClassWrapper;Lorg/mockito/internal/ValueClassWrapper;Lorg/mockito/internal/ValueClassWrapper;Lorg/mockito/internal/ValueClassWrapper;)Lorg/mockito/stubbing/ScalaAnswer;
      18: areturn

  public static <T, P0, P1, P2, P3, P4> org.mockito.stubbing.ScalaAnswer<T> functionToAnswer(scala.Function5<P0, P1, P2, P3, P4, T>, org.mockito.internal.ValueClassExtractor<T>, org.mockito.internal.ValueClassWrapper<P0>, org.mockito.internal.ValueClassWrapper<P1>, org.mockito.internal.ValueClassWrapper<P2>, org.mockito.internal.ValueClassWrapper<P3>, org.mockito.internal.ValueClassWrapper<P4>);
    Code:
       0: getstatic     #16                 // Field org/mockito/package$.MODULE$:Lorg/mockito/package$;
       3: aload_0
       4: aload_1
       5: aload_2
       6: aload_3
       7: aload         4
       9: aload         5
      11: aload         6
      13: invokevirtual #76                 // Method org/mockito/package$.functionToAnswer:(Lscala/Function5;Lorg/mockito/internal/ValueClassExtractor;Lorg/mockito/internal/ValueClassWrapper;Lorg/mockito/internal/ValueClassWrapper;Lorg/mockito/internal/ValueClassWrapper;Lorg/mockito/internal/ValueClassWrapper;Lorg/mockito/internal/ValueClassWrapper;)Lorg/mockito/stubbing/ScalaAnswer;
      16: areturn

  public static <T, P0, P1, P2, P3> org.mockito.stubbing.ScalaAnswer<T> functionToAnswer(scala.Function4<P0, P1, P2, P3, T>, org.mockito.internal.ValueClassExtractor<T>, org.mockito.internal.ValueClassWrapper<P0>, org.mockito.internal.ValueClassWrapper<P1>, org.mockito.internal.ValueClassWrapper<P2>, org.mockito.internal.ValueClassWrapper<P3>);
    Code:
       0: getstatic     #16                 // Field org/mockito/package$.MODULE$:Lorg/mockito/package$;
       3: aload_0
       4: aload_1
       5: aload_2
       6: aload_3
       7: aload         4
       9: aload         5
      11: invokevirtual #79                 // Method org/mockito/package$.functionToAnswer:(Lscala/Function4;Lorg/mockito/internal/ValueClassExtractor;Lorg/mockito/internal/ValueClassWrapper;Lorg/mockito/internal/ValueClassWrapper;Lorg/mockito/internal/ValueClassWrapper;Lorg/mockito/internal/ValueClassWrapper;)Lorg/mockito/stubbing/ScalaAnswer;
      14: areturn

  public static <T, P0, P1, P2> org.mockito.stubbing.ScalaAnswer<T> functionToAnswer(scala.Function3<P0, P1, P2, T>, org.mockito.internal.ValueClassExtractor<T>, org.mockito.internal.ValueClassWrapper<P0>, org.mockito.internal.ValueClassWrapper<P1>, org.mockito.internal.ValueClassWrapper<P2>);
    Code:
       0: getstatic     #16                 // Field org/mockito/package$.MODULE$:Lorg/mockito/package$;
       3: aload_0
       4: aload_1
       5: aload_2
       6: aload_3
       7: aload         4
       9: invokevirtual #82                 // Method org/mockito/package$.functionToAnswer:(Lscala/Function3;Lorg/mockito/internal/ValueClassExtractor;Lorg/mockito/internal/ValueClassWrapper;Lorg/mockito/internal/ValueClassWrapper;Lorg/mockito/internal/ValueClassWrapper;)Lorg/mockito/stubbing/ScalaAnswer;
      12: areturn

  public static <T, P0, P1> org.mockito.stubbing.ScalaAnswer<T> functionToAnswer(scala.Function2<P0, P1, T>, org.mockito.internal.ValueClassExtractor<T>, org.mockito.internal.ValueClassWrapper<P0>, org.mockito.internal.ValueClassWrapper<P1>);
    Code:
       0: getstatic     #16                 // Field org/mockito/package$.MODULE$:Lorg/mockito/package$;
       3: aload_0
       4: aload_1
       5: aload_2
       6: aload_3
       7: invokevirtual #85                 // Method org/mockito/package$.functionToAnswer:(Lscala/Function2;Lorg/mockito/internal/ValueClassExtractor;Lorg/mockito/internal/ValueClassWrapper;Lorg/mockito/internal/ValueClassWrapper;)Lorg/mockito/stubbing/ScalaAnswer;
      10: areturn

  public static <T, P0> org.mockito.stubbing.ScalaAnswer<T> functionToAnswer(scala.Function1<P0, T>, org.mockito.internal.ValueClassExtractor<T>, org.mockito.internal.ValueClassWrapper<P0>);
    Code:
       0: getstatic     #16                 // Field org/mockito/package$.MODULE$:Lorg/mockito/package$;
       3: aload_0
       4: aload_1
       5: aload_2
       6: invokevirtual #88                 // Method org/mockito/package$.functionToAnswer:(Lscala/Function1;Lorg/mockito/internal/ValueClassExtractor;Lorg/mockito/internal/ValueClassWrapper;)Lorg/mockito/stubbing/ScalaAnswer;
       9: areturn

  public static <T> org.mockito.stubbing.ScalaAnswer<T> invocationToAnswer(scala.Function1<org.mockito.invocation.InvocationOnMock, T>, org.mockito.internal.ValueClassExtractor<T>);
    Code:
       0: getstatic     #16                 // Field org/mockito/package$.MODULE$:Lorg/mockito/package$;
       3: aload_0
       4: aload_1
       5: invokevirtual #92                 // Method org/mockito/package$.invocationToAnswer:(Lscala/Function1;Lorg/mockito/internal/ValueClassExtractor;)Lorg/mockito/stubbing/ScalaAnswer;
       8: areturn

  public static scala.Function1<org.mockito.invocation.InvocationOnMock, org.mockito.invocation.InvocationOnMock> InvocationOps();
    Code:
       0: getstatic     #16                 // Field org/mockito/package$.MODULE$:Lorg/mockito/package$;
       3: invokevirtual #96                 // Method org/mockito/package$.InvocationOps:()Lscala/Function1;
       6: areturn

  public static <T> java.lang.Class<T> clazz(scala.reflect.ClassTag<T>);
    Code:
       0: getstatic     #16                 // Field org/mockito/package$.MODULE$:Lorg/mockito/package$;
       3: aload_0
       4: invokevirtual #100                // Method org/mockito/package$.clazz:(Lscala/reflect/ClassTag;)Ljava/lang/Class;
       7: areturn
}
