Compiled from "ReflectionUtils.scala"
public final class org.mockito.ReflectionUtils$InvocationOnMockOps$$anonfun$org$mockito$ReflectionUtils$InvocationOnMockOps$$resolveWithScalaGenerics$extension$1$$anonfun$apply$5 extends scala.runtime.AbstractFunction1<scala.reflect.api.Symbols$SymbolApi, java.lang.Object> implements scala.Serializable {
  public static final long serialVersionUID;

  public final boolean apply(scala.reflect.api.Symbols$SymbolApi);
    Code:
       0: getstatic     #22                 // Field org/mockito/ReflectionUtils$.MODULE$:Lorg/mockito/ReflectionUtils$;
       3: aload_1
       4: invokevirtual #26                 // Method org/mockito/ReflectionUtils$.symbolToMethodSymbol:(Lscala/reflect/api/Symbols$SymbolApi;)Lscala/reflect/internal/Symbols$MethodSymbol;
       7: invokevirtual #32                 // Method scala/reflect/internal/Symbols$MethodSymbol.returnType:()Lscala/reflect/internal/Types$Type;
      10: invokevirtual #38                 // Method scala/reflect/internal/Types$Type.typeSymbol:()Lscala/reflect/internal/Symbols$Symbol;
      13: invokevirtual #44                 // Method scala/reflect/internal/Symbols$Symbol.isClass:()Z
      16: ireturn

  public final java.lang.Object apply(java.lang.Object);
    Code:
       0: aload_0
       1: aload_1
       2: checkcast     #51                 // class scala/reflect/api/Symbols$SymbolApi
       5: invokevirtual #53                 // Method apply:(Lscala/reflect/api/Symbols$SymbolApi;)Z
       8: invokestatic  #59                 // Method scala/runtime/BoxesRunTime.boxToBoolean:(Z)Ljava/lang/Boolean;
      11: areturn

  public org.mockito.ReflectionUtils$InvocationOnMockOps$$anonfun$org$mockito$ReflectionUtils$InvocationOnMockOps$$resolveWithScalaGenerics$extension$1$$anonfun$apply$5(org.mockito.ReflectionUtils$InvocationOnMockOps$$anonfun$org$mockito$ReflectionUtils$InvocationOnMockOps$$resolveWithScalaGenerics$extension$1);
    Code:
       0: aload_0
       1: invokespecial #66                 // Method scala/runtime/AbstractFunction1."<init>":()V
       4: return
}
