Compiled from "ReflectionUtils.scala"
public final class org.mockito.ReflectionUtils$$anonfun$extraInterfaces$1$$anonfun$apply$8 extends scala.runtime.AbstractFunction1<scala.reflect.api.Types$TypeApi, java.lang.Class<?>> implements scala.Serializable {
  public static final long serialVersionUID;

  private final org.mockito.ReflectionUtils$$anonfun$extraInterfaces$1 $outer;

  public final java.lang.Class<?> apply(scala.reflect.api.Types$TypeApi);
    Code:
       0: aload_0
       1: getfield      #20                 // Field $outer:Lorg/mockito/ReflectionUtils$$anonfun$extraInterfaces$1;
       4: getfield      #24                 // Field org/mockito/ReflectionUtils$$anonfun$extraInterfaces$1.$wtt$1:Lscala/reflect/api/TypeTags$WeakTypeTag;
       7: invokeinterface #30,  1           // InterfaceMethod scala/reflect/api/TypeTags$WeakTypeTag.mirror:()Lscala/reflect/api/Mirror;
      12: checkcast     #32                 // class scala/reflect/api/Mirrors$RuntimeMirror
      15: aload_1
      16: invokeinterface #36,  2           // InterfaceMethod scala/reflect/api/Mirrors$RuntimeMirror.runtimeClass:(Lscala/reflect/api/Types$TypeApi;)Ljava/lang/Object;
      21: checkcast     #38                 // class java/lang/Class
      24: areturn

  public final java.lang.Object apply(java.lang.Object);
    Code:
       0: aload_0
       1: aload_1
       2: checkcast     #45                 // class scala/reflect/api/Types$TypeApi
       5: invokevirtual #47                 // Method apply:(Lscala/reflect/api/Types$TypeApi;)Ljava/lang/Class;
       8: areturn

  public org.mockito.ReflectionUtils$$anonfun$extraInterfaces$1$$anonfun$apply$8(org.mockito.ReflectionUtils$$anonfun$extraInterfaces$1);
    Code:
       0: aload_1
       1: ifnonnull     6
       4: aconst_null
       5: athrow
       6: aload_0
       7: aload_1
       8: putfield      #20                 // Field $outer:Lorg/mockito/ReflectionUtils$$anonfun$extraInterfaces$1;
      11: aload_0
      12: invokespecial #54                 // Method scala/runtime/AbstractFunction1."<init>":()V
      15: return
}
