Compiled from "LibraryOption.java"
public final class jnr.ffi.LibraryOption extends java.lang.Enum<jnr.ffi.LibraryOption> {
  public static final jnr.ffi.LibraryOption SaveError;

  public static final jnr.ffi.LibraryOption IgnoreError;

  public static final jnr.ffi.LibraryOption TypeMapper;

  public static final jnr.ffi.LibraryOption FunctionMapper;

  public static final jnr.ffi.LibraryOption CallingConvention;

  public static final jnr.ffi.LibraryOption LoadNow;

  private static final jnr.ffi.LibraryOption[] $VALUES;

  public static jnr.ffi.LibraryOption[] values();
    Code:
       0: getstatic     #1                  // Field $VALUES:[Ljnr/ffi/LibraryOption;
       3: invokevirtual #2                  // Method "[Ljnr/ffi/LibraryOption;".clone:()Ljava/lang/Object;
       6: checkcast     #3                  // class "[Ljnr/ffi/LibraryOption;"
       9: areturn

  public static jnr.ffi.LibraryOption valueOf(java.lang.String);
    Code:
       0: ldc           #4                  // class jnr/ffi/LibraryOption
       2: aload_0
       3: invokestatic  #5                  // Method java/lang/Enum.valueOf:(Ljava/lang/Class;Ljava/lang/String;)Ljava/lang/Enum;
       6: checkcast     #4                  // class jnr/ffi/LibraryOption
       9: areturn

  private jnr.ffi.LibraryOption();
    Code:
       0: aload_0
       1: aload_1
       2: iload_2
       3: invokespecial #6                  // Method java/lang/Enum."<init>":(Ljava/lang/String;I)V
       6: return

  static {};
    Code:
       0: new           #4                  // class jnr/ffi/LibraryOption
       3: dup
       4: ldc           #7                  // String SaveError
       6: iconst_0
       7: invokespecial #8                  // Method "<init>":(Ljava/lang/String;I)V
      10: putstatic     #9                  // Field SaveError:Ljnr/ffi/LibraryOption;
      13: new           #4                  // class jnr/ffi/LibraryOption
      16: dup
      17: ldc           #10                 // String IgnoreError
      19: iconst_1
      20: invokespecial #8                  // Method "<init>":(Ljava/lang/String;I)V
      23: putstatic     #11                 // Field IgnoreError:Ljnr/ffi/LibraryOption;
      26: new           #4                  // class jnr/ffi/LibraryOption
      29: dup
      30: ldc           #12                 // String TypeMapper
      32: iconst_2
      33: invokespecial #8                  // Method "<init>":(Ljava/lang/String;I)V
      36: putstatic     #13                 // Field TypeMapper:Ljnr/ffi/LibraryOption;
      39: new           #4                  // class jnr/ffi/LibraryOption
      42: dup
      43: ldc           #14                 // String FunctionMapper
      45: iconst_3
      46: invokespecial #8                  // Method "<init>":(Ljava/lang/String;I)V
      49: putstatic     #15                 // Field FunctionMapper:Ljnr/ffi/LibraryOption;
      52: new           #4                  // class jnr/ffi/LibraryOption
      55: dup
      56: ldc           #16                 // String CallingConvention
      58: iconst_4
      59: invokespecial #8                  // Method "<init>":(Ljava/lang/String;I)V
      62: putstatic     #17                 // Field CallingConvention:Ljnr/ffi/LibraryOption;
      65: new           #4                  // class jnr/ffi/LibraryOption
      68: dup
      69: ldc           #18                 // String LoadNow
      71: iconst_5
      72: invokespecial #8                  // Method "<init>":(Ljava/lang/String;I)V
      75: putstatic     #19                 // Field LoadNow:Ljnr/ffi/LibraryOption;
      78: bipush        6
      80: anewarray     #4                  // class jnr/ffi/LibraryOption
      83: dup
      84: iconst_0
      85: getstatic     #9                  // Field SaveError:Ljnr/ffi/LibraryOption;
      88: aastore
      89: dup
      90: iconst_1
      91: getstatic     #11                 // Field IgnoreError:Ljnr/ffi/LibraryOption;
      94: aastore
      95: dup
      96: iconst_2
      97: getstatic     #13                 // Field TypeMapper:Ljnr/ffi/LibraryOption;
     100: aastore
     101: dup
     102: iconst_3
     103: getstatic     #15                 // Field FunctionMapper:Ljnr/ffi/LibraryOption;
     106: aastore
     107: dup
     108: iconst_4
     109: getstatic     #17                 // Field CallingConvention:Ljnr/ffi/LibraryOption;
     112: aastore
     113: dup
     114: iconst_5
     115: getstatic     #19                 // Field LoadNow:Ljnr/ffi/LibraryOption;
     118: aastore
     119: putstatic     #1                  // Field $VALUES:[Ljnr/ffi/LibraryOption;
     122: return
}
