Compiled from "StructLayout.java"
public abstract class jnr.ffi.StructLayout$String extends jnr.ffi.StructLayout$AbstractField {
  protected final java.nio.charset.Charset charset;

  protected final int length;

  final jnr.ffi.StructLayout this$0;

  protected jnr.ffi.StructLayout$String(jnr.ffi.StructLayout, int, int, int, java.nio.charset.Charset);
    Code:
       0: aload_0
       1: aload_1
       2: putfield      #1                  // Field this$0:Ljnr/ffi/StructLayout;
       5: aload_0
       6: aload_1
       7: iload_2
       8: iload_3
       9: invokespecial #2                  // Method jnr/ffi/StructLayout$AbstractField."<init>":(Ljnr/ffi/StructLayout;II)V
      12: aload_0
      13: iload         4
      15: putfield      #3                  // Field length:I
      18: aload_0
      19: aload         5
      21: putfield      #4                  // Field charset:Ljava/nio/charset/Charset;
      24: return

  protected jnr.ffi.StructLayout$String(jnr.ffi.StructLayout, int, int, jnr.ffi.StructLayout$Offset, int, java.nio.charset.Charset);
    Code:
       0: aload_0
       1: aload_1
       2: putfield      #1                  // Field this$0:Ljnr/ffi/StructLayout;
       5: aload_0
       6: aload_1
       7: iload_2
       8: iload_3
       9: aload         4
      11: invokespecial #5                  // Method jnr/ffi/StructLayout$AbstractField."<init>":(Ljnr/ffi/StructLayout;IILjnr/ffi/StructLayout$Offset;)V
      14: aload_0
      15: iload         5
      17: putfield      #3                  // Field length:I
      20: aload_0
      21: aload         6
      23: putfield      #4                  // Field charset:Ljava/nio/charset/Charset;
      26: return

  public final int length();
    Code:
       0: aload_0
       1: getfield      #3                  // Field length:I
       4: ireturn

  protected abstract jnr.ffi.Pointer getStringMemory(jnr.ffi.Pointer);

  public abstract java.lang.String get(jnr.ffi.Pointer);

  public abstract void set(jnr.ffi.Pointer, java.lang.String);

  public final java.lang.String toString(jnr.ffi.Pointer);
    Code:
       0: aload_0
       1: aload_1
       2: invokevirtual #6                  // Method get:(Ljnr/ffi/Pointer;)Ljava/lang/String;
       5: areturn
}
