Compiled from "CompatBase.scala"
public interface wvlet.airframe.codec.CompatBase {
  public static wvlet.airframe.surface.Surface surfaceOfClass$(wvlet.airframe.codec.CompatBase, java.lang.Class);
    Code:
       0: aload_0
       1: aload_1
       2: invokespecial #13                 // InterfaceMethod surfaceOfClass:(Ljava/lang/Class;)Lwvlet/airframe/surface/Surface;
       5: areturn

  public default wvlet.airframe.surface.Surface surfaceOfClass(java.lang.Class<?>);
    Code:
       0: getstatic     #22                 // Field wvlet/airframe/surface/reflect/ReflectSurfaceFactory$.MODULE$:Lwvlet/airframe/surface/reflect/ReflectSurfaceFactory$;
       3: aload_1
       4: invokevirtual #25                 // Method wvlet/airframe/surface/reflect/ReflectSurfaceFactory$.ofClass:(Ljava/lang/Class;)Lwvlet/airframe/surface/Surface;
       7: areturn
}
