Compiled from "DataType.scala"
public interface wvlet.airframe.codec.DataType {
  public static scala.collection.immutable.Seq<wvlet.airframe.codec.DataType$PrimitiveType> primitiveTypes();
    Code:
       0: getstatic     #80                 // Field wvlet/airframe/codec/DataType$.MODULE$:Lwvlet/airframe/codec/DataType$;
       3: invokevirtual #82                 // Method wvlet/airframe/codec/DataType$.primitiveTypes:()Lscala/collection/immutable/Seq;
       6: areturn

  public abstract java.lang.String signature();

  public abstract java.lang.String typeName();

  public abstract scala.collection.immutable.Seq<wvlet.airframe.codec.DataType> typeArgs();

  public static java.lang.String toString$(wvlet.airframe.codec.DataType);
    Code:
       0: aload_0
       1: invokespecial #93                 // InterfaceMethod toString:()Ljava/lang/String;
       4: areturn

  public default java.lang.String toString();
    Code:
       0: aload_0
       1: invokeinterface #96,  1           // InterfaceMethod signature:()Ljava/lang/String;
       6: areturn
}
