Compiled from "StandardCodec.scala"
public final class wvlet.airframe.codec.StandardCodec$ implements java.io.Serializable {
  private static final scala.collection.immutable.Map javaClassCodec;

  private static final scala.collection.immutable.Map standardCodec;

  public static final wvlet.airframe.codec.StandardCodec$ MODULE$;

  private wvlet.airframe.codec.StandardCodec$();
    Code:
       0: aload_0
       1: invokespecial #28                 // Method java/lang/Object."<init>":()V
       4: return

  public static {};
    Code:
       0: new           #2                  // class wvlet/airframe/codec/StandardCodec$
       3: dup
       4: invokespecial #31                 // Method "<init>":()V
       7: putstatic     #33                 // Field MODULE$:Lwvlet/airframe/codec/StandardCodec$;
      10: getstatic     #38                 // Field scala/Predef$.MODULE$:Lscala/Predef$;
      13: invokevirtual #42                 // Method scala/Predef$.Map:()Lscala/collection/immutable/Map$;
      16: getstatic     #47                 // Field scala/runtime/ScalaRunTime$.MODULE$:Lscala/runtime/ScalaRunTime$;
      19: iconst_5
      20: anewarray     #49                 // class scala/Tuple2
      23: dup
      24: iconst_0
      25: getstatic     #38                 // Field scala/Predef$.MODULE$:Lscala/Predef$;
      28: ldc           #51                 // String scala.Throwable
      30: astore_1
      31: getstatic     #56                 // Field wvlet/airframe/surface/package$.MODULE$:Lwvlet/airframe/surface/package$;
      34: invokevirtual #60                 // Method wvlet/airframe/surface/package$.surfaceCache:()Lscala/collection/concurrent/Map;
      37: aload_1
      38: invokeinterface #66,  2           // InterfaceMethod scala/collection/concurrent/Map.contains:(Ljava/lang/Object;)Z
      43: ifne          103
      46: getstatic     #56                 // Field wvlet/airframe/surface/package$.MODULE$:Lwvlet/airframe/surface/package$;
      49: invokevirtual #60                 // Method wvlet/airframe/surface/package$.surfaceCache:()Lscala/collection/concurrent/Map;
      52: getstatic     #38                 // Field scala/Predef$.MODULE$:Lscala/Predef$;
      55: aload_1
      56: invokevirtual #70                 // Method scala/Predef$.ArrowAssoc:(Ljava/lang/Object;)Ljava/lang/Object;
      59: checkcast     #72                 // class java/lang/String
      62: astore_2
      63: getstatic     #75                 // Field scala/Predef$ArrowAssoc$.MODULE$:Lscala/Predef$ArrowAssoc$;
      66: aload_2
      67: new           #77                 // class wvlet/airframe/surface/GenericSurface
      70: dup
      71: ldc           #79                 // class java/lang/Throwable
      73: getstatic     #84                 // Field wvlet/airframe/surface/GenericSurface$.MODULE$:Lwvlet/airframe/surface/GenericSurface$;
      76: invokevirtual #88                 // Method wvlet/airframe/surface/GenericSurface$.$lessinit$greater$default$2:()Lscala/collection/immutable/Seq;
      79: getstatic     #84                 // Field wvlet/airframe/surface/GenericSurface$.MODULE$:Lwvlet/airframe/surface/GenericSurface$;
      82: invokevirtual #91                 // Method wvlet/airframe/surface/GenericSurface$.$lessinit$greater$default$3:()Lscala/collection/immutable/Seq;
      85: getstatic     #84                 // Field wvlet/airframe/surface/GenericSurface$.MODULE$:Lwvlet/airframe/surface/GenericSurface$;
      88: invokevirtual #95                 // Method wvlet/airframe/surface/GenericSurface$.$lessinit$greater$default$4:()Lscala/Option;
      91: invokespecial #98                 // Method wvlet/airframe/surface/GenericSurface."<init>":(Ljava/lang/Class;Lscala/collection/immutable/Seq;Lscala/collection/immutable/Seq;Lscala/Option;)V
      94: invokevirtual #102                // Method scala/Predef$ArrowAssoc$.$minus$greater$extension:(Ljava/lang/Object;Ljava/lang/Object;)Lscala/Tuple2;
      97: invokeinterface #106,  2          // InterfaceMethod scala/collection/concurrent/Map.$plus$eq:(Ljava/lang/Object;)Lscala/collection/mutable/Growable;
     102: pop
     103: getstatic     #56                 // Field wvlet/airframe/surface/package$.MODULE$:Lwvlet/airframe/surface/package$;
     106: invokevirtual #60                 // Method wvlet/airframe/surface/package$.surfaceCache:()Lscala/collection/concurrent/Map;
     109: aload_1
     110: invokeinterface #109,  2          // InterfaceMethod scala/collection/concurrent/Map.apply:(Ljava/lang/Object;)Ljava/lang/Object;
     115: checkcast     #111                // class wvlet/airframe/surface/Surface
     118: invokevirtual #70                 // Method scala/Predef$.ArrowAssoc:(Ljava/lang/Object;)Ljava/lang/Object;
     121: checkcast     #111                // class wvlet/airframe/surface/Surface
     124: astore_0
     125: getstatic     #75                 // Field scala/Predef$ArrowAssoc$.MODULE$:Lscala/Predef$ArrowAssoc$;
     128: aload_0
     129: getstatic     #116                // Field wvlet/airframe/codec/ThrowableCodec$.MODULE$:Lwvlet/airframe/codec/ThrowableCodec$;
     132: invokevirtual #102                // Method scala/Predef$ArrowAssoc$.$minus$greater$extension:(Ljava/lang/Object;Ljava/lang/Object;)Lscala/Tuple2;
     135: aastore
     136: dup
     137: iconst_1
     138: getstatic     #38                 // Field scala/Predef$.MODULE$:Lscala/Predef$;
     141: ldc           #118                // String scala.Exception
     143: astore        4
     145: getstatic     #56                 // Field wvlet/airframe/surface/package$.MODULE$:Lwvlet/airframe/surface/package$;
     148: invokevirtual #60                 // Method wvlet/airframe/surface/package$.surfaceCache:()Lscala/collection/concurrent/Map;
     151: aload         4
     153: invokeinterface #66,  2           // InterfaceMethod scala/collection/concurrent/Map.contains:(Ljava/lang/Object;)Z
     158: ifne          221
     161: getstatic     #56                 // Field wvlet/airframe/surface/package$.MODULE$:Lwvlet/airframe/surface/package$;
     164: invokevirtual #60                 // Method wvlet/airframe/surface/package$.surfaceCache:()Lscala/collection/concurrent/Map;
     167: getstatic     #38                 // Field scala/Predef$.MODULE$:Lscala/Predef$;
     170: aload         4
     172: invokevirtual #70                 // Method scala/Predef$.ArrowAssoc:(Ljava/lang/Object;)Ljava/lang/Object;
     175: checkcast     #72                 // class java/lang/String
     178: astore        5
     180: getstatic     #75                 // Field scala/Predef$ArrowAssoc$.MODULE$:Lscala/Predef$ArrowAssoc$;
     183: aload         5
     185: new           #77                 // class wvlet/airframe/surface/GenericSurface
     188: dup
     189: ldc           #120                // class java/lang/Exception
     191: getstatic     #84                 // Field wvlet/airframe/surface/GenericSurface$.MODULE$:Lwvlet/airframe/surface/GenericSurface$;
     194: invokevirtual #88                 // Method wvlet/airframe/surface/GenericSurface$.$lessinit$greater$default$2:()Lscala/collection/immutable/Seq;
     197: getstatic     #84                 // Field wvlet/airframe/surface/GenericSurface$.MODULE$:Lwvlet/airframe/surface/GenericSurface$;
     200: invokevirtual #91                 // Method wvlet/airframe/surface/GenericSurface$.$lessinit$greater$default$3:()Lscala/collection/immutable/Seq;
     203: getstatic     #84                 // Field wvlet/airframe/surface/GenericSurface$.MODULE$:Lwvlet/airframe/surface/GenericSurface$;
     206: invokevirtual #95                 // Method wvlet/airframe/surface/GenericSurface$.$lessinit$greater$default$4:()Lscala/Option;
     209: invokespecial #98                 // Method wvlet/airframe/surface/GenericSurface."<init>":(Ljava/lang/Class;Lscala/collection/immutable/Seq;Lscala/collection/immutable/Seq;Lscala/Option;)V
     212: invokevirtual #102                // Method scala/Predef$ArrowAssoc$.$minus$greater$extension:(Ljava/lang/Object;Ljava/lang/Object;)Lscala/Tuple2;
     215: invokeinterface #106,  2          // InterfaceMethod scala/collection/concurrent/Map.$plus$eq:(Ljava/lang/Object;)Lscala/collection/mutable/Growable;
     220: pop
     221: getstatic     #56                 // Field wvlet/airframe/surface/package$.MODULE$:Lwvlet/airframe/surface/package$;
     224: invokevirtual #60                 // Method wvlet/airframe/surface/package$.surfaceCache:()Lscala/collection/concurrent/Map;
     227: aload         4
     229: invokeinterface #109,  2          // InterfaceMethod scala/collection/concurrent/Map.apply:(Ljava/lang/Object;)Ljava/lang/Object;
     234: checkcast     #111                // class wvlet/airframe/surface/Surface
     237: invokevirtual #70                 // Method scala/Predef$.ArrowAssoc:(Ljava/lang/Object;)Ljava/lang/Object;
     240: checkcast     #111                // class wvlet/airframe/surface/Surface
     243: astore_3
     244: getstatic     #75                 // Field scala/Predef$ArrowAssoc$.MODULE$:Lscala/Predef$ArrowAssoc$;
     247: aload_3
     248: getstatic     #116                // Field wvlet/airframe/codec/ThrowableCodec$.MODULE$:Lwvlet/airframe/codec/ThrowableCodec$;
     251: invokevirtual #102                // Method scala/Predef$ArrowAssoc$.$minus$greater$extension:(Ljava/lang/Object;Ljava/lang/Object;)Lscala/Tuple2;
     254: aastore
     255: dup
     256: iconst_2
     257: getstatic     #38                 // Field scala/Predef$.MODULE$:Lscala/Predef$;
     260: ldc           #122                // String java.time.Instant
     262: astore        7
     264: getstatic     #56                 // Field wvlet/airframe/surface/package$.MODULE$:Lwvlet/airframe/surface/package$;
     267: invokevirtual #60                 // Method wvlet/airframe/surface/package$.surfaceCache:()Lscala/collection/concurrent/Map;
     270: aload         7
     272: invokeinterface #66,  2           // InterfaceMethod scala/collection/concurrent/Map.contains:(Ljava/lang/Object;)Z
     277: ifne          340
     280: getstatic     #56                 // Field wvlet/airframe/surface/package$.MODULE$:Lwvlet/airframe/surface/package$;
     283: invokevirtual #60                 // Method wvlet/airframe/surface/package$.surfaceCache:()Lscala/collection/concurrent/Map;
     286: getstatic     #38                 // Field scala/Predef$.MODULE$:Lscala/Predef$;
     289: aload         7
     291: invokevirtual #70                 // Method scala/Predef$.ArrowAssoc:(Ljava/lang/Object;)Ljava/lang/Object;
     294: checkcast     #72                 // class java/lang/String
     297: astore        8
     299: getstatic     #75                 // Field scala/Predef$ArrowAssoc$.MODULE$:Lscala/Predef$ArrowAssoc$;
     302: aload         8
     304: new           #77                 // class wvlet/airframe/surface/GenericSurface
     307: dup
     308: ldc           #124                // class java/time/Instant
     310: getstatic     #84                 // Field wvlet/airframe/surface/GenericSurface$.MODULE$:Lwvlet/airframe/surface/GenericSurface$;
     313: invokevirtual #88                 // Method wvlet/airframe/surface/GenericSurface$.$lessinit$greater$default$2:()Lscala/collection/immutable/Seq;
     316: getstatic     #84                 // Field wvlet/airframe/surface/GenericSurface$.MODULE$:Lwvlet/airframe/surface/GenericSurface$;
     319: invokevirtual #91                 // Method wvlet/airframe/surface/GenericSurface$.$lessinit$greater$default$3:()Lscala/collection/immutable/Seq;
     322: getstatic     #84                 // Field wvlet/airframe/surface/GenericSurface$.MODULE$:Lwvlet/airframe/surface/GenericSurface$;
     325: invokevirtual #95                 // Method wvlet/airframe/surface/GenericSurface$.$lessinit$greater$default$4:()Lscala/Option;
     328: invokespecial #98                 // Method wvlet/airframe/surface/GenericSurface."<init>":(Ljava/lang/Class;Lscala/collection/immutable/Seq;Lscala/collection/immutable/Seq;Lscala/Option;)V
     331: invokevirtual #102                // Method scala/Predef$ArrowAssoc$.$minus$greater$extension:(Ljava/lang/Object;Ljava/lang/Object;)Lscala/Tuple2;
     334: invokeinterface #106,  2          // InterfaceMethod scala/collection/concurrent/Map.$plus$eq:(Ljava/lang/Object;)Lscala/collection/mutable/Growable;
     339: pop
     340: getstatic     #56                 // Field wvlet/airframe/surface/package$.MODULE$:Lwvlet/airframe/surface/package$;
     343: invokevirtual #60                 // Method wvlet/airframe/surface/package$.surfaceCache:()Lscala/collection/concurrent/Map;
     346: aload         7
     348: invokeinterface #109,  2          // InterfaceMethod scala/collection/concurrent/Map.apply:(Ljava/lang/Object;)Ljava/lang/Object;
     353: checkcast     #111                // class wvlet/airframe/surface/Surface
     356: invokevirtual #70                 // Method scala/Predef$.ArrowAssoc:(Ljava/lang/Object;)Ljava/lang/Object;
     359: checkcast     #111                // class wvlet/airframe/surface/Surface
     362: astore        6
     364: getstatic     #75                 // Field scala/Predef$ArrowAssoc$.MODULE$:Lscala/Predef$ArrowAssoc$;
     367: aload         6
     369: getstatic     #129                // Field wvlet/airframe/codec/JavaInstantTimeCodec$.MODULE$:Lwvlet/airframe/codec/JavaInstantTimeCodec$;
     372: invokevirtual #102                // Method scala/Predef$ArrowAssoc$.$minus$greater$extension:(Ljava/lang/Object;Ljava/lang/Object;)Lscala/Tuple2;
     375: aastore
     376: dup
     377: iconst_3
     378: getstatic     #38                 // Field scala/Predef$.MODULE$:Lscala/Predef$;
     381: ldc           #131                // String java.util.UUID
     383: astore        10
     385: getstatic     #56                 // Field wvlet/airframe/surface/package$.MODULE$:Lwvlet/airframe/surface/package$;
     388: invokevirtual #60                 // Method wvlet/airframe/surface/package$.surfaceCache:()Lscala/collection/concurrent/Map;
     391: aload         10
     393: invokeinterface #66,  2           // InterfaceMethod scala/collection/concurrent/Map.contains:(Ljava/lang/Object;)Z
     398: ifne          461
     401: getstatic     #56                 // Field wvlet/airframe/surface/package$.MODULE$:Lwvlet/airframe/surface/package$;
     404: invokevirtual #60                 // Method wvlet/airframe/surface/package$.surfaceCache:()Lscala/collection/concurrent/Map;
     407: getstatic     #38                 // Field scala/Predef$.MODULE$:Lscala/Predef$;
     410: aload         10
     412: invokevirtual #70                 // Method scala/Predef$.ArrowAssoc:(Ljava/lang/Object;)Ljava/lang/Object;
     415: checkcast     #72                 // class java/lang/String
     418: astore        11
     420: getstatic     #75                 // Field scala/Predef$ArrowAssoc$.MODULE$:Lscala/Predef$ArrowAssoc$;
     423: aload         11
     425: new           #77                 // class wvlet/airframe/surface/GenericSurface
     428: dup
     429: ldc           #133                // class java/util/UUID
     431: getstatic     #84                 // Field wvlet/airframe/surface/GenericSurface$.MODULE$:Lwvlet/airframe/surface/GenericSurface$;
     434: invokevirtual #88                 // Method wvlet/airframe/surface/GenericSurface$.$lessinit$greater$default$2:()Lscala/collection/immutable/Seq;
     437: getstatic     #84                 // Field wvlet/airframe/surface/GenericSurface$.MODULE$:Lwvlet/airframe/surface/GenericSurface$;
     440: invokevirtual #91                 // Method wvlet/airframe/surface/GenericSurface$.$lessinit$greater$default$3:()Lscala/collection/immutable/Seq;
     443: getstatic     #84                 // Field wvlet/airframe/surface/GenericSurface$.MODULE$:Lwvlet/airframe/surface/GenericSurface$;
     446: invokevirtual #95                 // Method wvlet/airframe/surface/GenericSurface$.$lessinit$greater$default$4:()Lscala/Option;
     449: invokespecial #98                 // Method wvlet/airframe/surface/GenericSurface."<init>":(Ljava/lang/Class;Lscala/collection/immutable/Seq;Lscala/collection/immutable/Seq;Lscala/Option;)V
     452: invokevirtual #102                // Method scala/Predef$ArrowAssoc$.$minus$greater$extension:(Ljava/lang/Object;Ljava/lang/Object;)Lscala/Tuple2;
     455: invokeinterface #106,  2          // InterfaceMethod scala/collection/concurrent/Map.$plus$eq:(Ljava/lang/Object;)Lscala/collection/mutable/Growable;
     460: pop
     461: getstatic     #56                 // Field wvlet/airframe/surface/package$.MODULE$:Lwvlet/airframe/surface/package$;
     464: invokevirtual #60                 // Method wvlet/airframe/surface/package$.surfaceCache:()Lscala/collection/concurrent/Map;
     467: aload         10
     469: invokeinterface #109,  2          // InterfaceMethod scala/collection/concurrent/Map.apply:(Ljava/lang/Object;)Ljava/lang/Object;
     474: checkcast     #111                // class wvlet/airframe/surface/Surface
     477: invokevirtual #70                 // Method scala/Predef$.ArrowAssoc:(Ljava/lang/Object;)Ljava/lang/Object;
     480: checkcast     #111                // class wvlet/airframe/surface/Surface
     483: astore        9
     485: getstatic     #75                 // Field scala/Predef$ArrowAssoc$.MODULE$:Lscala/Predef$ArrowAssoc$;
     488: aload         9
     490: getstatic     #138                // Field wvlet/airframe/codec/UUIDCodec$.MODULE$:Lwvlet/airframe/codec/UUIDCodec$;
     493: invokevirtual #102                // Method scala/Predef$ArrowAssoc$.$minus$greater$extension:(Ljava/lang/Object;Ljava/lang/Object;)Lscala/Tuple2;
     496: aastore
     497: dup
     498: iconst_4
     499: getstatic     #38                 // Field scala/Predef$.MODULE$:Lscala/Predef$;
     502: ldc           #140                // String wvlet.airframe.ulid.ULID
     504: astore        13
     506: getstatic     #56                 // Field wvlet/airframe/surface/package$.MODULE$:Lwvlet/airframe/surface/package$;
     509: invokevirtual #60                 // Method wvlet/airframe/surface/package$.surfaceCache:()Lscala/collection/concurrent/Map;
     512: aload         13
     514: invokeinterface #66,  2           // InterfaceMethod scala/collection/concurrent/Map.contains:(Ljava/lang/Object;)Z
     519: ifne          721
     522: getstatic     #56                 // Field wvlet/airframe/surface/package$.MODULE$:Lwvlet/airframe/surface/package$;
     525: invokevirtual #60                 // Method wvlet/airframe/surface/package$.surfaceCache:()Lscala/collection/concurrent/Map;
     528: getstatic     #38                 // Field scala/Predef$.MODULE$:Lscala/Predef$;
     531: aload         13
     533: invokevirtual #70                 // Method scala/Predef$.ArrowAssoc:(Ljava/lang/Object;)Ljava/lang/Object;
     536: checkcast     #72                 // class java/lang/String
     539: astore        14
     541: getstatic     #75                 // Field scala/Predef$ArrowAssoc$.MODULE$:Lscala/Predef$ArrowAssoc$;
     544: aload         14
     546: new           #77                 // class wvlet/airframe/surface/GenericSurface
     549: dup
     550: ldc           #142                // class wvlet/airframe/ulid/ULID
     552: getstatic     #47                 // Field scala/runtime/ScalaRunTime$.MODULE$:Lscala/runtime/ScalaRunTime$;
     555: iconst_0
     556: anewarray     #111                // class wvlet/airframe/surface/Surface
     559: invokevirtual #146                // Method scala/runtime/ScalaRunTime$.wrapRefArray:([Ljava/lang/Object;)Lscala/collection/immutable/ArraySeq;
     562: invokevirtual #152                // Method scala/collection/immutable/ArraySeq.toIndexedSeq:()Lscala/collection/immutable/IndexedSeq;
     565: getstatic     #47                 // Field scala/runtime/ScalaRunTime$.MODULE$:Lscala/runtime/ScalaRunTime$;
     568: iconst_1
     569: anewarray     #154                // class wvlet/airframe/surface/StaticMethodParameter
     572: dup
     573: iconst_0
     574: getstatic     #159                // Field wvlet/airframe/surface/StaticMethodParameter$.MODULE$:Lwvlet/airframe/surface/StaticMethodParameter$;
     577: getstatic     #164                // Field wvlet/airframe/surface/MethodRef$.MODULE$:Lwvlet/airframe/surface/MethodRef$;
     580: ldc           #142                // class wvlet/airframe/ulid/ULID
     582: ldc           #165                // String <init>
     584: getstatic     #47                 // Field scala/runtime/ScalaRunTime$.MODULE$:Lscala/runtime/ScalaRunTime$;
     587: iconst_1
     588: anewarray     #167                // class java/lang/Class
     591: dup
     592: iconst_0
     593: ldc           #72                 // class java/lang/String
     595: aastore
     596: invokevirtual #146                // Method scala/runtime/ScalaRunTime$.wrapRefArray:([Ljava/lang/Object;)Lscala/collection/immutable/ArraySeq;
     599: iconst_1
     600: invokevirtual #170                // Method wvlet/airframe/surface/MethodRef$.apply:(Ljava/lang/Class;Ljava/lang/String;Lscala/collection/immutable/Seq;Z)Lwvlet/airframe/surface/MethodRef;
     603: iconst_0
     604: ldc           #172                // String ulid
     606: iconst_0
     607: iconst_0
     608: ldc           #174                // String String
     610: astore        15
     612: getstatic     #56                 // Field wvlet/airframe/surface/package$.MODULE$:Lwvlet/airframe/surface/package$;
     615: invokevirtual #60                 // Method wvlet/airframe/surface/package$.surfaceCache:()Lscala/collection/concurrent/Map;
     618: aload         15
     620: invokeinterface #66,  2           // InterfaceMethod scala/collection/concurrent/Map.contains:(Ljava/lang/Object;)Z
     625: ifne          664
     628: getstatic     #56                 // Field wvlet/airframe/surface/package$.MODULE$:Lwvlet/airframe/surface/package$;
     631: invokevirtual #60                 // Method wvlet/airframe/surface/package$.surfaceCache:()Lscala/collection/concurrent/Map;
     634: getstatic     #38                 // Field scala/Predef$.MODULE$:Lscala/Predef$;
     637: aload         15
     639: invokevirtual #70                 // Method scala/Predef$.ArrowAssoc:(Ljava/lang/Object;)Ljava/lang/Object;
     642: checkcast     #72                 // class java/lang/String
     645: astore        16
     647: getstatic     #75                 // Field scala/Predef$ArrowAssoc$.MODULE$:Lscala/Predef$ArrowAssoc$;
     650: aload         16
     652: getstatic     #177                // Field wvlet/airframe/surface/Primitive$String$.MODULE$:Lwvlet/airframe/surface/Primitive$String$;
     655: invokevirtual #102                // Method scala/Predef$ArrowAssoc$.$minus$greater$extension:(Ljava/lang/Object;Ljava/lang/Object;)Lscala/Tuple2;
     658: invokeinterface #106,  2          // InterfaceMethod scala/collection/concurrent/Map.$plus$eq:(Ljava/lang/Object;)Lscala/collection/mutable/Growable;
     663: pop
     664: getstatic     #56                 // Field wvlet/airframe/surface/package$.MODULE$:Lwvlet/airframe/surface/package$;
     667: invokevirtual #60                 // Method wvlet/airframe/surface/package$.surfaceCache:()Lscala/collection/concurrent/Map;
     670: aload         15
     672: invokeinterface #109,  2          // InterfaceMethod scala/collection/concurrent/Map.apply:(Ljava/lang/Object;)Ljava/lang/Object;
     677: checkcast     #111                // class wvlet/airframe/surface/Surface
     680: getstatic     #182                // Field scala/None$.MODULE$:Lscala/None$;
     683: getstatic     #182                // Field scala/None$.MODULE$:Lscala/None$;
     686: getstatic     #182                // Field scala/None$.MODULE$:Lscala/None$;
     689: invokevirtual #185                // Method wvlet/airframe/surface/StaticMethodParameter$.apply:(Lwvlet/airframe/surface/MethodRef;ILjava/lang/String;ZZLwvlet/airframe/surface/Surface;Lscala/Option;Lscala/Option;Lscala/Option;)Lwvlet/airframe/surface/StaticMethodParameter;
     692: aastore
     693: invokevirtual #146                // Method scala/runtime/ScalaRunTime$.wrapRefArray:([Ljava/lang/Object;)Lscala/collection/immutable/ArraySeq;
     696: getstatic     #190                // Field scala/Some$.MODULE$:Lscala/Some$;
     699: new           #14                 // class wvlet/airframe/codec/StandardCodec$$anon$1
     702: dup
     703: invokespecial #191                // Method wvlet/airframe/codec/StandardCodec$$anon$1."<init>":()V
     706: invokevirtual #194                // Method scala/Some$.apply:(Ljava/lang/Object;)Lscala/Some;
     709: invokespecial #98                 // Method wvlet/airframe/surface/GenericSurface."<init>":(Ljava/lang/Class;Lscala/collection/immutable/Seq;Lscala/collection/immutable/Seq;Lscala/Option;)V
     712: invokevirtual #102                // Method scala/Predef$ArrowAssoc$.$minus$greater$extension:(Ljava/lang/Object;Ljava/lang/Object;)Lscala/Tuple2;
     715: invokeinterface #106,  2          // InterfaceMethod scala/collection/concurrent/Map.$plus$eq:(Ljava/lang/Object;)Lscala/collection/mutable/Growable;
     720: pop
     721: getstatic     #56                 // Field wvlet/airframe/surface/package$.MODULE$:Lwvlet/airframe/surface/package$;
     724: invokevirtual #60                 // Method wvlet/airframe/surface/package$.surfaceCache:()Lscala/collection/concurrent/Map;
     727: aload         13
     729: invokeinterface #109,  2          // InterfaceMethod scala/collection/concurrent/Map.apply:(Ljava/lang/Object;)Ljava/lang/Object;
     734: checkcast     #111                // class wvlet/airframe/surface/Surface
     737: invokevirtual #70                 // Method scala/Predef$.ArrowAssoc:(Ljava/lang/Object;)Ljava/lang/Object;
     740: checkcast     #111                // class wvlet/airframe/surface/Surface
     743: astore        12
     745: getstatic     #75                 // Field scala/Predef$ArrowAssoc$.MODULE$:Lscala/Predef$ArrowAssoc$;
     748: aload         12
     750: getstatic     #199                // Field wvlet/airframe/codec/ULIDCodec$.MODULE$:Lwvlet/airframe/codec/ULIDCodec$;
     753: invokevirtual #102                // Method scala/Predef$ArrowAssoc$.$minus$greater$extension:(Ljava/lang/Object;Ljava/lang/Object;)Lscala/Tuple2;
     756: aastore
     757: invokevirtual #146                // Method scala/runtime/ScalaRunTime$.wrapRefArray:([Ljava/lang/Object;)Lscala/collection/immutable/ArraySeq;
     760: invokevirtual #204                // Method scala/collection/immutable/Map$.apply:(Lscala/collection/immutable/Seq;)Ljava/lang/Object;
     763: checkcast     #206                // class scala/collection/immutable/Map
     766: putstatic     #208                // Field javaClassCodec:Lscala/collection/immutable/Map;
     769: getstatic     #213                // Field wvlet/airframe/codec/PrimitiveCodec$.MODULE$:Lwvlet/airframe/codec/PrimitiveCodec$;
     772: invokevirtual #217                // Method wvlet/airframe/codec/PrimitiveCodec$.primitiveCodec:()Lscala/collection/immutable/Map;
     775: getstatic     #213                // Field wvlet/airframe/codec/PrimitiveCodec$.MODULE$:Lwvlet/airframe/codec/PrimitiveCodec$;
     778: invokevirtual #220                // Method wvlet/airframe/codec/PrimitiveCodec$.primitiveArrayCodec:()Lscala/collection/immutable/Map;
     781: invokeinterface #224,  2          // InterfaceMethod scala/collection/immutable/Map.$plus$plus:(Lscala/collection/IterableOnce;)Lscala/collection/IterableOps;
     786: checkcast     #226                // class scala/collection/MapOps
     789: getstatic     #33                 // Field MODULE$:Lwvlet/airframe/codec/StandardCodec$;
     792: invokevirtual #228                // Method javaClassCodec:()Lscala/collection/immutable/Map;
     795: invokeinterface #229,  2          // InterfaceMethod scala/collection/MapOps.$plus$plus:(Lscala/collection/IterableOnce;)Lscala/collection/IterableOps;
     800: checkcast     #206                // class scala/collection/immutable/Map
     803: putstatic     #231                // Field standardCodec:Lscala/collection/immutable/Map;
     806: return

  private java.lang.Object writeReplace();
    Code:
       0: new           #245                // class scala/runtime/ModuleSerializationProxy
       3: dup
       4: ldc           #2                  // class wvlet/airframe/codec/StandardCodec$
       6: invokespecial #248                // Method scala/runtime/ModuleSerializationProxy."<init>":(Ljava/lang/Class;)V
       9: areturn

  public scala.collection.immutable.Map<wvlet.airframe.surface.Surface, wvlet.airframe.codec.MessageCodec<? extends java.lang.Object>> javaClassCodec();
    Code:
       0: getstatic     #208                // Field javaClassCodec:Lscala/collection/immutable/Map;
       3: areturn

  public scala.collection.immutable.Map<wvlet.airframe.surface.Surface, wvlet.airframe.codec.MessageCodec<?>> standardCodec();
    Code:
       0: getstatic     #231                // Field standardCodec:Lscala/collection/immutable/Map;
       3: areturn
}
