Compiled from "UnionCodec.scala"
public class wvlet.airframe.codec.UnionCodec implements wvlet.airframe.codec.MessageCodec<wvlet.airframe.surface.Union>, scala.Product {
  public static final long OFFSET$0;

  private volatile java.lang.Object logger$lzy1;

  private final scala.collection.immutable.Map codecs;

  public static wvlet.airframe.codec.UnionCodec apply(scala.collection.immutable.Map<wvlet.airframe.surface.Surface, wvlet.airframe.codec.MessageCodec<?>>);
    Code:
       0: getstatic     #58                 // Field wvlet/airframe/codec/UnionCodec$.MODULE$:Lwvlet/airframe/codec/UnionCodec$;
       3: aload_0
       4: invokevirtual #60                 // Method wvlet/airframe/codec/UnionCodec$.apply:(Lscala/collection/immutable/Map;)Lwvlet/airframe/codec/UnionCodec;
       7: areturn

  public static wvlet.airframe.codec.UnionCodec fromProduct(scala.Product);
    Code:
       0: getstatic     #58                 // Field wvlet/airframe/codec/UnionCodec$.MODULE$:Lwvlet/airframe/codec/UnionCodec$;
       3: aload_0
       4: invokevirtual #64                 // Method wvlet/airframe/codec/UnionCodec$.fromProduct:(Lscala/Product;)Lwvlet/airframe/codec/UnionCodec;
       7: areturn

  public static wvlet.airframe.codec.UnionCodec unapply(wvlet.airframe.codec.UnionCodec);
    Code:
       0: getstatic     #58                 // Field wvlet/airframe/codec/UnionCodec$.MODULE$:Lwvlet/airframe/codec/UnionCodec$;
       3: aload_0
       4: invokevirtual #68                 // Method wvlet/airframe/codec/UnionCodec$.unapply:(Lwvlet/airframe/codec/UnionCodec;)Lwvlet/airframe/codec/UnionCodec;
       7: areturn

  public wvlet.airframe.codec.UnionCodec(scala.collection.immutable.Map<wvlet.airframe.surface.Surface, wvlet.airframe.codec.MessageCodec<?>>);
    Code:
       0: aload_0
       1: aload_1
       2: putfield      #73                 // Field codecs:Lscala/collection/immutable/Map;
       5: aload_0
       6: invokespecial #76                 // Method java/lang/Object."<init>":()V
       9: return

  private static {};
    Code:
       0: getstatic     #84                 // Field scala/runtime/LazyVals$.MODULE$:Lscala/runtime/LazyVals$;
       3: ldc           #2                  // class wvlet/airframe/codec/UnionCodec
       5: ldc           #85                 // String logger$lzy1
       7: invokevirtual #91                 // Method java/lang/Class.getDeclaredField:(Ljava/lang/String;)Ljava/lang/reflect/Field;
      10: invokevirtual #95                 // Method scala/runtime/LazyVals$.getOffsetStatic:(Ljava/lang/reflect/Field;)J
      13: putstatic     #97                 // Field OFFSET$0:J
      16: return

  public wvlet.log.Logger wvlet$log$LoggingMethods$$inline$logger();
    Code:
       0: aload_0
       1: invokestatic  #103                // InterfaceMethod wvlet/log/LoggingMethods.wvlet$log$LoggingMethods$$inline$logger$:(Lwvlet/log/LoggingMethods;)Lwvlet/log/Logger;
       4: areturn

  public wvlet.log.Logger logger();
    Code:
       0: aload_0
       1: getfield      #106                // Field logger$lzy1:Ljava/lang/Object;
       4: astore_1
       5: aload_1
       6: instanceof    #108                // class wvlet/log/Logger
       9: ifeq          17
      12: aload_1
      13: checkcast     #108                // class wvlet/log/Logger
      16: areturn
      17: aload_1
      18: getstatic     #111                // Field scala/runtime/LazyVals$NullValue$.MODULE$:Lscala/runtime/LazyVals$NullValue$;
      21: if_acmpne     26
      24: aconst_null
      25: areturn
      26: aload_0
      27: invokespecial #115                // Method logger$lzyINIT1:()Ljava/lang/Object;
      30: checkcast     #108                // class wvlet/log/Logger
      33: areturn

  private java.lang.Object logger$lzyINIT1();
    Code:
       0: aload_0
       1: getfield      #106                // Field logger$lzy1:Ljava/lang/Object;
       4: astore_1
       5: aload_1
       6: ifnonnull     151
       9: getstatic     #84                 // Field scala/runtime/LazyVals$.MODULE$:Lscala/runtime/LazyVals$;
      12: aload_0
      13: getstatic     #97                 // Field OFFSET$0:J
      16: aconst_null
      17: getstatic     #118                // Field scala/runtime/LazyVals$Evaluating$.MODULE$:Lscala/runtime/LazyVals$Evaluating$;
      20: invokevirtual #122                // Method scala/runtime/LazyVals$.objCAS:(Ljava/lang/Object;JLjava/lang/Object;Ljava/lang/Object;)Z
      23: ifeq          148
      26: aconst_null
      27: astore_2
      28: aconst_null
      29: astore_3
      30: aload_0
      31: invokestatic  #126                // InterfaceMethod wvlet/log/LazyLogger.logger$:(Lwvlet/log/LazyLogger;)Lwvlet/log/Logger;
      34: astore_3
      35: aload_3
      36: ifnonnull     46
      39: getstatic     #111                // Field scala/runtime/LazyVals$NullValue$.MODULE$:Lscala/runtime/LazyVals$NullValue$;
      42: astore_2
      43: goto          48
      46: aload_3
      47: astore_2
      48: goto          101
      51: astore        4
      53: getstatic     #84                 // Field scala/runtime/LazyVals$.MODULE$:Lscala/runtime/LazyVals$;
      56: aload_0
      57: getstatic     #97                 // Field OFFSET$0:J
      60: getstatic     #118                // Field scala/runtime/LazyVals$Evaluating$.MODULE$:Lscala/runtime/LazyVals$Evaluating$;
      63: aload_2
      64: invokevirtual #122                // Method scala/runtime/LazyVals$.objCAS:(Ljava/lang/Object;JLjava/lang/Object;Ljava/lang/Object;)Z
      67: ifne          98
      70: aload_0
      71: getfield      #106                // Field logger$lzy1:Ljava/lang/Object;
      74: checkcast     #32                 // class scala/runtime/LazyVals$Waiting
      77: astore        5
      79: getstatic     #84                 // Field scala/runtime/LazyVals$.MODULE$:Lscala/runtime/LazyVals$;
      82: aload_0
      83: getstatic     #97                 // Field OFFSET$0:J
      86: aload         5
      88: aload_2
      89: invokevirtual #122                // Method scala/runtime/LazyVals$.objCAS:(Ljava/lang/Object;JLjava/lang/Object;Ljava/lang/Object;)Z
      92: pop
      93: aload         5
      95: invokevirtual #129                // Method scala/runtime/LazyVals$Waiting.countDown:()V
      98: aload         4
     100: athrow
     101: getstatic     #84                 // Field scala/runtime/LazyVals$.MODULE$:Lscala/runtime/LazyVals$;
     104: aload_0
     105: getstatic     #97                 // Field OFFSET$0:J
     108: getstatic     #118                // Field scala/runtime/LazyVals$Evaluating$.MODULE$:Lscala/runtime/LazyVals$Evaluating$;
     111: aload_2
     112: invokevirtual #122                // Method scala/runtime/LazyVals$.objCAS:(Ljava/lang/Object;JLjava/lang/Object;Ljava/lang/Object;)Z
     115: ifne          146
     118: aload_0
     119: getfield      #106                // Field logger$lzy1:Ljava/lang/Object;
     122: checkcast     #32                 // class scala/runtime/LazyVals$Waiting
     125: astore        5
     127: getstatic     #84                 // Field scala/runtime/LazyVals$.MODULE$:Lscala/runtime/LazyVals$;
     130: aload_0
     131: getstatic     #97                 // Field OFFSET$0:J
     134: aload         5
     136: aload_2
     137: invokevirtual #122                // Method scala/runtime/LazyVals$.objCAS:(Ljava/lang/Object;JLjava/lang/Object;Ljava/lang/Object;)Z
     140: pop
     141: aload         5
     143: invokevirtual #129                // Method scala/runtime/LazyVals$Waiting.countDown:()V
     146: aload_3
     147: areturn
     148: goto          0
     151: aload_1
     152: instanceof    #26                 // class scala/runtime/LazyVals$LazyValControlState
     155: ifeq          206
     158: aload_1
     159: getstatic     #118                // Field scala/runtime/LazyVals$Evaluating$.MODULE$:Lscala/runtime/LazyVals$Evaluating$;
     162: if_acmpne     187
     165: getstatic     #84                 // Field scala/runtime/LazyVals$.MODULE$:Lscala/runtime/LazyVals$;
     168: aload_0
     169: getstatic     #97                 // Field OFFSET$0:J
     172: aload_1
     173: new           #32                 // class scala/runtime/LazyVals$Waiting
     176: dup
     177: invokespecial #130                // Method scala/runtime/LazyVals$Waiting."<init>":()V
     180: invokevirtual #122                // Method scala/runtime/LazyVals$.objCAS:(Ljava/lang/Object;JLjava/lang/Object;Ljava/lang/Object;)Z
     183: pop
     184: goto          0
     187: aload_1
     188: instanceof    #32                 // class scala/runtime/LazyVals$Waiting
     191: ifeq          204
     194: aload_1
     195: checkcast     #32                 // class scala/runtime/LazyVals$Waiting
     198: invokevirtual #133                // Method scala/runtime/LazyVals$Waiting.await:()V
     201: goto          0
     204: aconst_null
     205: areturn
     206: aload_1
     207: areturn
    Exception table:
       from    to  target type
          30    51    51   any

  public byte[] pack(java.lang.Object);
    Code:
       0: aload_0
       1: aload_1
       2: invokestatic  #142                // InterfaceMethod wvlet/airframe/codec/MessageCodec.pack$:(Lwvlet/airframe/codec/MessageCodec;Ljava/lang/Object;)[B
       5: areturn

  public java.lang.Object unpack(byte[]);
    Code:
       0: aload_0
       1: aload_1
       2: invokestatic  #149                // InterfaceMethod wvlet/airframe/codec/MessageCodec.unpack$:(Lwvlet/airframe/codec/MessageCodec;[B)Ljava/lang/Object;
       5: areturn

  public byte[] toMsgPack(java.lang.Object);
    Code:
       0: aload_0
       1: aload_1
       2: invokestatic  #154                // InterfaceMethod wvlet/airframe/codec/MessageCodec.toMsgPack$:(Lwvlet/airframe/codec/MessageCodec;Ljava/lang/Object;)[B
       5: areturn

  public java.lang.String toJson(java.lang.Object);
    Code:
       0: aload_0
       1: aload_1
       2: invokestatic  #160                // InterfaceMethod wvlet/airframe/codec/MessageCodec.toJson$:(Lwvlet/airframe/codec/MessageCodec;Ljava/lang/Object;)Ljava/lang/String;
       5: areturn

  public wvlet.airframe.json.JSON$JSONObject toJSONObject(java.lang.Object);
    Code:
       0: aload_0
       1: aload_1
       2: invokestatic  #166                // InterfaceMethod wvlet/airframe/codec/MessageCodec.toJSONObject$:(Lwvlet/airframe/codec/MessageCodec;Ljava/lang/Object;)Lwvlet/airframe/json/JSON$JSONObject;
       5: areturn

  public scala.Option unpackBytes(byte[]);
    Code:
       0: aload_0
       1: aload_1
       2: invokestatic  #172                // InterfaceMethod wvlet/airframe/codec/MessageCodec.unpackBytes$:(Lwvlet/airframe/codec/MessageCodec;[B)Lscala/Option;
       5: areturn

  public scala.Option unpackBytes(byte[], int, int);
    Code:
       0: aload_0
       1: aload_1
       2: iload_2
       3: iload_3
       4: invokestatic  #178                // InterfaceMethod wvlet/airframe/codec/MessageCodec.unpackBytes$:(Lwvlet/airframe/codec/MessageCodec;[BII)Lscala/Option;
       7: areturn

  public java.lang.Object fromMsgPack(byte[]);
    Code:
       0: aload_0
       1: aload_1
       2: invokestatic  #183                // InterfaceMethod wvlet/airframe/codec/MessageCodec.fromMsgPack$:(Lwvlet/airframe/codec/MessageCodec;[B)Ljava/lang/Object;
       5: areturn

  public scala.Option unpackMsgPack(byte[]);
    Code:
       0: aload_0
       1: aload_1
       2: invokestatic  #187                // InterfaceMethod wvlet/airframe/codec/MessageCodec.unpackMsgPack$:(Lwvlet/airframe/codec/MessageCodec;[B)Lscala/Option;
       5: areturn

  public scala.Option unpackMsgPack(byte[], int, int);
    Code:
       0: aload_0
       1: aload_1
       2: iload_2
       3: iload_3
       4: invokestatic  #189                // InterfaceMethod wvlet/airframe/codec/MessageCodec.unpackMsgPack$:(Lwvlet/airframe/codec/MessageCodec;[BII)Lscala/Option;
       7: areturn

  public scala.Option unpackJson(java.lang.String);
    Code:
       0: aload_0
       1: aload_1
       2: invokestatic  #196                // InterfaceMethod wvlet/airframe/codec/MessageCodec.unpackJson$:(Lwvlet/airframe/codec/MessageCodec;Ljava/lang/String;)Lscala/Option;
       5: areturn

  public java.lang.Object fromJson(java.lang.String);
    Code:
       0: aload_0
       1: aload_1
       2: invokestatic  #203                // InterfaceMethod wvlet/airframe/codec/MessageCodec.fromJson$:(Lwvlet/airframe/codec/MessageCodec;Ljava/lang/String;)Ljava/lang/Object;
       5: areturn

  public java.lang.Object fromJson(byte[]);
    Code:
       0: aload_0
       1: aload_1
       2: invokestatic  #205                // InterfaceMethod wvlet/airframe/codec/MessageCodec.fromJson$:(Lwvlet/airframe/codec/MessageCodec;[B)Ljava/lang/Object;
       5: areturn

  public java.lang.Object fromMap(scala.collection.immutable.Map);
    Code:
       0: aload_0
       1: aload_1
       2: invokestatic  #212                // InterfaceMethod wvlet/airframe/codec/MessageCodec.fromMap$:(Lwvlet/airframe/codec/MessageCodec;Lscala/collection/immutable/Map;)Ljava/lang/Object;
       5: areturn

  public java.lang.Object fromString(java.lang.String);
    Code:
       0: aload_0
       1: aload_1
       2: invokestatic  #217                // InterfaceMethod wvlet/airframe/codec/MessageCodec.fromString$:(Lwvlet/airframe/codec/MessageCodec;Ljava/lang/String;)Ljava/lang/Object;
       5: areturn

  public scala.collection.Iterator productIterator();
    Code:
       0: aload_0
       1: invokestatic  #223                // InterfaceMethod scala/Product.productIterator$:(Lscala/Product;)Lscala/collection/Iterator;
       4: areturn

  public scala.collection.Iterator productElementNames();
    Code:
       0: aload_0
       1: invokestatic  #227                // InterfaceMethod scala/Product.productElementNames$:(Lscala/Product;)Lscala/collection/Iterator;
       4: areturn

  public int hashCode();
    Code:
       0: getstatic     #234                // Field scala/runtime/ScalaRunTime$.MODULE$:Lscala/runtime/ScalaRunTime$;
       3: aload_0
       4: invokevirtual #238                // Method scala/runtime/ScalaRunTime$._hashCode:(Lscala/Product;)I
       7: ireturn

  public boolean equals(java.lang.Object);
    Code:
       0: aload_0
       1: aload_1
       2: if_acmpeq     73
       5: aload_1
       6: astore_2
       7: aload_2
       8: instanceof    #2                  // class wvlet/airframe/codec/UnionCodec
      11: ifeq          66
      14: aload_2
      15: checkcast     #2                  // class wvlet/airframe/codec/UnionCodec
      18: astore_3
      19: aload_0
      20: invokevirtual #244                // Method codecs:()Lscala/collection/immutable/Map;
      23: aload_3
      24: invokevirtual #244                // Method codecs:()Lscala/collection/immutable/Map;
      27: astore        4
      29: dup
      30: ifnonnull     42
      33: pop
      34: aload         4
      36: ifnull        50
      39: goto          62
      42: aload         4
      44: invokevirtual #246                // Method java/lang/Object.equals:(Ljava/lang/Object;)Z
      47: ifeq          62
      50: aload_3
      51: aload_0
      52: invokevirtual #249                // Method canEqual:(Ljava/lang/Object;)Z
      55: ifeq          62
      58: iconst_1
      59: goto          63
      62: iconst_0
      63: goto          70
      66: iconst_0
      67: goto          70
      70: ifeq          77
      73: iconst_1
      74: goto          78
      77: iconst_0
      78: ireturn

  public java.lang.String toString();
    Code:
       0: getstatic     #234                // Field scala/runtime/ScalaRunTime$.MODULE$:Lscala/runtime/ScalaRunTime$;
       3: aload_0
       4: invokevirtual #257                // Method scala/runtime/ScalaRunTime$._toString:(Lscala/Product;)Ljava/lang/String;
       7: areturn

  public boolean canEqual(java.lang.Object);
    Code:
       0: aload_1
       1: instanceof    #2                  // class wvlet/airframe/codec/UnionCodec
       4: ireturn

  public int productArity();
    Code:
       0: iconst_1
       1: ireturn

  public java.lang.String productPrefix();
    Code:
       0: ldc_w         #262                // String UnionCodec
       3: areturn

  public java.lang.Object productElement(int);
    Code:
       0: iload_1
       1: istore_2
       2: iconst_0
       3: iload_2
       4: if_icmpne     12
       7: aload_0
       8: invokevirtual #268                // Method _1:()Lscala/collection/immutable/Map;
      11: areturn
      12: new           #270                // class java/lang/IndexOutOfBoundsException
      15: dup
      16: iload_1
      17: invokestatic  #276                // Method scala/runtime/BoxesRunTime.boxToInteger:(I)Ljava/lang/Integer;
      20: invokevirtual #280                // Method java/lang/Integer.toString:()Ljava/lang/String;
      23: invokespecial #283                // Method java/lang/IndexOutOfBoundsException."<init>":(Ljava/lang/String;)V
      26: athrow

  public java.lang.String productElementName(int);
    Code:
       0: iload_1
       1: istore_2
       2: iconst_0
       3: iload_2
       4: if_icmpne     11
       7: ldc_w         #286                // String codecs
      10: areturn
      11: new           #270                // class java/lang/IndexOutOfBoundsException
      14: dup
      15: iload_1
      16: invokestatic  #276                // Method scala/runtime/BoxesRunTime.boxToInteger:(I)Ljava/lang/Integer;
      19: invokevirtual #280                // Method java/lang/Integer.toString:()Ljava/lang/String;
      22: invokespecial #283                // Method java/lang/IndexOutOfBoundsException."<init>":(Ljava/lang/String;)V
      25: athrow

  public scala.collection.immutable.Map<wvlet.airframe.surface.Surface, wvlet.airframe.codec.MessageCodec<?>> codecs();
    Code:
       0: aload_0
       1: getfield      #73                 // Field codecs:Lscala/collection/immutable/Map;
       4: areturn

  public void pack(wvlet.airframe.msgpack.spi.Packer, wvlet.airframe.surface.Union);
    Code:
       0: aload_2
       1: invokeinterface #295,  1          // InterfaceMethod wvlet/airframe/surface/Union.getElementClass:()Ljava/lang/Class;
       6: astore_3
       7: aload_0
       8: invokevirtual #244                // Method codecs:()Lscala/collection/immutable/Map;
      11: aload_3
      12: invokedynamic #316,  0            // InvokeDynamic #0:apply:(Ljava/lang/Class;)Lscala/Function1;
      17: invokeinterface #320,  2          // InterfaceMethod scala/collection/immutable/Map.find:(Lscala/Function1;)Lscala/Option;
      22: invokedynamic #329,  0            // InvokeDynamic #1:apply:()Lscala/Function1;
      27: invokevirtual #334                // Method scala/Option.map:(Lscala/Function1;)Lscala/Option;
      30: astore        4
      32: aload         4
      34: instanceof    #336                // class scala/Some
      37: ifeq          63
      40: aload         4
      42: checkcast     #336                // class scala/Some
      45: invokevirtual #339                // Method scala/Some.value:()Ljava/lang/Object;
      48: checkcast     #11                 // class wvlet/airframe/codec/MessageCodec
      51: astore        5
      53: aload         5
      55: aload_1
      56: aload_2
      57: invokeinterface #342,  3          // InterfaceMethod wvlet/airframe/codec/MessageCodec.pack:(Lwvlet/airframe/msgpack/spi/Packer;Ljava/lang/Object;)V
      62: return
      63: getstatic     #347                // Field scala/None$.MODULE$:Lscala/None$;
      66: aload         4
      68: invokevirtual #246                // Method java/lang/Object.equals:(Ljava/lang/Object;)Z
      71: ifeq          88
      74: getstatic     #350                // Field wvlet/airframe/codec/PrimitiveCodec$StringCodec$.MODULE$:Lwvlet/airframe/codec/PrimitiveCodec$StringCodec$;
      77: aload_1
      78: aload_2
      79: invokeinterface #351,  1          // InterfaceMethod wvlet/airframe/surface/Union.toString:()Ljava/lang/String;
      84: invokevirtual #354                // Method wvlet/airframe/codec/PrimitiveCodec$StringCodec$.pack:(Lwvlet/airframe/msgpack/spi/Packer;Ljava/lang/String;)V
      87: return
      88: new           #356                // class scala/MatchError
      91: dup
      92: aload         4
      94: invokespecial #359                // Method scala/MatchError."<init>":(Ljava/lang/Object;)V
      97: athrow

  public void unpack(wvlet.airframe.msgpack.spi.Unpacker, wvlet.airframe.codec.MessageContext);
    Code:
       0: aload_1
       1: invokeinterface #373,  1          // InterfaceMethod wvlet/airframe/msgpack/spi/Unpacker.unpackValue:()Lwvlet/airframe/msgpack/spi/Value;
       6: invokeinterface #379,  1          // InterfaceMethod wvlet/airframe/msgpack/spi/Value.toMsgpack:()[B
      11: astore_3
      12: aload_0
      13: invokevirtual #244                // Method codecs:()Lscala/collection/immutable/Map;
      16: invokedynamic #384,  0            // InvokeDynamic #2:apply:()Lscala/Function1;
      21: invokeinterface #387,  2          // InterfaceMethod scala/collection/immutable/Map.map:(Lscala/Function1;)Ljava/lang/Object;
      26: checkcast     #389                // class scala/collection/IterableOnceOps
      29: aload_2
      30: aload_3
      31: invokedynamic #399,  0            // InvokeDynamic #3:apply:(Lwvlet/airframe/codec/MessageContext;[B)Lscala/Function1;
      36: invokeinterface #400,  2          // InterfaceMethod scala/collection/IterableOnceOps.find:(Lscala/Function1;)Lscala/Option;
      41: invokevirtual #404                // Method scala/Option.isDefined:()Z
      44: istore        4
      46: iload         4
      48: ifne          96
      51: aload_2
      52: new           #406                // class wvlet/airframe/codec/MessageCodecException
      55: dup
      56: getstatic     #411                // Field wvlet/airframe/codec/INVALID_DATA$.MODULE$:Lwvlet/airframe/codec/INVALID_DATA$;
      59: aload_0
      60: new           #413                // class java/lang/StringBuilder
      63: dup
      64: ldc_w         #414                // int 41
      67: invokespecial #417                // Method java/lang/StringBuilder."<init>":(I)V
      70: ldc_w         #419                // String No corresponding type is found for data:
      73: invokevirtual #423                // Method java/lang/StringBuilder.append:(Ljava/lang/String;)Ljava/lang/StringBuilder;
      76: getstatic     #428                // Field wvlet/airframe/codec/JSONCodec$.MODULE$:Lwvlet/airframe/codec/JSONCodec$;
      79: aload_3
      80: invokevirtual #430                // Method wvlet/airframe/codec/JSONCodec$.fromMsgPack:([B)Ljava/lang/Object;
      83: invokevirtual #433                // Method java/lang/StringBuilder.append:(Ljava/lang/Object;)Ljava/lang/StringBuilder;
      86: invokevirtual #434                // Method java/lang/StringBuilder.toString:()Ljava/lang/String;
      89: invokespecial #437                // Method wvlet/airframe/codec/MessageCodecException."<init>":(Lwvlet/airframe/codec/CodecErrorCode;Lwvlet/airframe/codec/MessageCodec;Ljava/lang/String;)V
      92: invokevirtual #443                // Method wvlet/airframe/codec/MessageContext.setError:(Ljava/lang/Throwable;)V
      95: return
      96: return

  public wvlet.airframe.codec.UnionCodec copy(scala.collection.immutable.Map<wvlet.airframe.surface.Surface, wvlet.airframe.codec.MessageCodec<?>>);
    Code:
       0: new           #2                  // class wvlet/airframe/codec/UnionCodec
       3: dup
       4: aload_1
       5: invokespecial #452                // Method "<init>":(Lscala/collection/immutable/Map;)V
       8: areturn

  public scala.collection.immutable.Map<wvlet.airframe.surface.Surface, wvlet.airframe.codec.MessageCodec<?>> copy$default$1();
    Code:
       0: aload_0
       1: invokevirtual #244                // Method codecs:()Lscala/collection/immutable/Map;
       4: areturn

  public scala.collection.immutable.Map<wvlet.airframe.surface.Surface, wvlet.airframe.codec.MessageCodec<?>> _1();
    Code:
       0: aload_0
       1: invokevirtual #244                // Method codecs:()Lscala/collection/immutable/Map;
       4: areturn

  public void pack(wvlet.airframe.msgpack.spi.Packer, java.lang.Object);
    Code:
       0: aload_0
       1: aload_1
       2: aload_2
       3: checkcast     #291                // class wvlet/airframe/surface/Union
       6: invokevirtual #455                // Method pack:(Lwvlet/airframe/msgpack/spi/Packer;Lwvlet/airframe/surface/Union;)V
       9: return

  private static final boolean pack$$anonfun$1(java.lang.Class, scala.Tuple2);
    Code:
       0: aload_1
       1: invokevirtual #461                // Method scala/Tuple2._1:()Ljava/lang/Object;
       4: checkcast     #463                // class wvlet/airframe/surface/Surface
       7: invokeinterface #466,  1          // InterfaceMethod wvlet/airframe/surface/Surface.rawType:()Ljava/lang/Class;
      12: aload_0
      13: invokevirtual #470                // Method java/lang/Class.isAssignableFrom:(Ljava/lang/Class;)Z
      16: ireturn

  private static final wvlet.airframe.codec.MessageCodec pack$$anonfun$2(scala.Tuple2);
    Code:
       0: aload_0
       1: invokevirtual #475                // Method scala/Tuple2._2:()Ljava/lang/Object;
       4: checkcast     #11                 // class wvlet/airframe/codec/MessageCodec
       7: areturn

  private static final wvlet.airframe.codec.MessageCodec $anonfun$1(scala.Tuple2);
    Code:
       0: aload_0
       1: invokevirtual #475                // Method scala/Tuple2._2:()Ljava/lang/Object;
       4: checkcast     #11                 // class wvlet/airframe/codec/MessageCodec
       7: areturn

  private static final void $anonfun$2$$anonfun$1(wvlet.airframe.codec.MessageContext, java.lang.Object);
    Code:
       0: aload_0
       1: aload_1
       2: invokevirtual #483                // Method wvlet/airframe/codec/MessageContext.setObject:(Ljava/lang/Object;)V
       5: return

  private static final boolean $anonfun$2(wvlet.airframe.codec.MessageContext, byte[], wvlet.airframe.codec.MessageCodec);
    Code:
       0: aload_2
       1: aload_1
       2: invokeinterface #488,  2          // InterfaceMethod wvlet/airframe/codec/MessageCodec.unpackMsgPack:([B)Lscala/Option;
       7: aload_0
       8: invokedynamic #496,  0            // InvokeDynamic #4:applyVoid:(Lwvlet/airframe/codec/MessageContext;)Lscala/runtime/function/JProcedure1;
      13: invokevirtual #334                // Method scala/Option.map:(Lscala/Function1;)Lscala/Option;
      16: invokevirtual #404                // Method scala/Option.isDefined:()Z
      19: ireturn

  private static java.lang.Object $deserializeLambda$(java.lang.invoke.SerializedLambda);
    Code:
       0: aload_0
       1: invokedynamic #508,  0            // InvokeDynamic #5:lambdaDeserialize:(Ljava/lang/invoke/SerializedLambda;)Ljava/lang/Object;
       6: areturn
}
