Compiled from "SimpleFrontEndProcessor.java"
public class org.apache.cxf.tools.java2wsdl.processor.internal.simple.SimpleFrontEndProcessor implements org.apache.cxf.tools.common.Processor {
  private org.apache.cxf.tools.common.ToolContext context;

  private java.util.List<org.apache.cxf.tools.wsdlto.core.AbstractGenerator> generators;

  public org.apache.cxf.tools.java2wsdl.processor.internal.simple.SimpleFrontEndProcessor();
    Code:
       0: aload_0
       1: invokespecial #1                  // Method java/lang/Object."<init>":()V
       4: aload_0
       5: new           #2                  // class java/util/ArrayList
       8: dup
       9: invokespecial #3                  // Method java/util/ArrayList."<init>":()V
      12: putfield      #4                  // Field generators:Ljava/util/List;
      15: return

  public void process() throws org.apache.cxf.tools.common.ToolException;
    Code:
       0: aload_0
       1: getfield      #5                  // Field context:Lorg/apache/cxf/tools/common/ToolContext;
       4: ldc           #6                  // String serviceList
       6: invokevirtual #7                  // Method org/apache/cxf/tools/common/ToolContext.get:(Ljava/lang/String;)Ljava/lang/Object;
       9: checkcast     #8                  // class java/util/List
      12: astore_1
      13: aload_1
      14: iconst_0
      15: invokeinterface #9,  2            // InterfaceMethod java/util/List.get:(I)Ljava/lang/Object;
      20: checkcast     #10                 // class org/apache/cxf/service/model/ServiceInfo
      23: astore_2
      24: aload_2
      25: invokestatic  #11                 // Method org/apache/cxf/tools/java2ws/util/JavaFirstUtil.serviceInfo2JavaInf:(Lorg/apache/cxf/service/model/ServiceInfo;)Lorg/apache/cxf/tools/common/model/JavaInterface;
      28: astore_3
      29: new           #12                 // class org/apache/cxf/tools/common/model/JavaModel
      32: dup
      33: invokespecial #13                 // Method org/apache/cxf/tools/common/model/JavaModel."<init>":()V
      36: astore        4
      38: aload         4
      40: ldc           #14                 // String inf
      42: aload_3
      43: invokevirtual #15                 // Method org/apache/cxf/tools/common/model/JavaModel.addInterface:(Ljava/lang/String;Lorg/apache/cxf/tools/common/model/JavaInterface;)V
      46: aload_3
      47: aload         4
      49: invokevirtual #16                 // Method org/apache/cxf/tools/common/model/JavaInterface.setJavaModel:(Lorg/apache/cxf/tools/common/model/JavaModel;)V
      52: aload_0
      53: getfield      #5                  // Field context:Lorg/apache/cxf/tools/common/ToolContext;
      56: ldc_w         #12                 // class org/apache/cxf/tools/common/model/JavaModel
      59: aload         4
      61: invokevirtual #17                 // Method org/apache/cxf/tools/common/ToolContext.put:(Ljava/lang/Class;Ljava/lang/Object;)V
      64: aload_0
      65: getfield      #4                  // Field generators:Ljava/util/List;
      68: new           #18                 // class org/apache/cxf/tools/java2wsdl/processor/internal/simple/generator/SimpleSEIGenerator
      71: dup
      72: invokespecial #19                 // Method org/apache/cxf/tools/java2wsdl/processor/internal/simple/generator/SimpleSEIGenerator."<init>":()V
      75: invokeinterface #20,  2           // InterfaceMethod java/util/List.add:(Ljava/lang/Object;)Z
      80: pop
      81: aload_0
      82: getfield      #4                  // Field generators:Ljava/util/List;
      85: new           #21                 // class org/apache/cxf/tools/java2wsdl/processor/internal/simple/generator/SimpleImplGenerator
      88: dup
      89: invokespecial #22                 // Method org/apache/cxf/tools/java2wsdl/processor/internal/simple/generator/SimpleImplGenerator."<init>":()V
      92: invokeinterface #20,  2           // InterfaceMethod java/util/List.add:(Ljava/lang/Object;)Z
      97: pop
      98: aload_0
      99: getfield      #4                  // Field generators:Ljava/util/List;
     102: new           #23                 // class org/apache/cxf/tools/java2wsdl/processor/internal/simple/generator/SimpleServerGenerator
     105: dup
     106: invokespecial #24                 // Method org/apache/cxf/tools/java2wsdl/processor/internal/simple/generator/SimpleServerGenerator."<init>":()V
     109: invokeinterface #20,  2           // InterfaceMethod java/util/List.add:(Ljava/lang/Object;)Z
     114: pop
     115: aload_0
     116: getfield      #4                  // Field generators:Ljava/util/List;
     119: new           #25                 // class org/apache/cxf/tools/java2wsdl/processor/internal/simple/generator/SimpleClientGenerator
     122: dup
     123: invokespecial #26                 // Method org/apache/cxf/tools/java2wsdl/processor/internal/simple/generator/SimpleClientGenerator."<init>":()V
     126: invokeinterface #20,  2           // InterfaceMethod java/util/List.add:(Ljava/lang/Object;)Z
     131: pop
     132: aload_0
     133: getfield      #4                  // Field generators:Ljava/util/List;
     136: new           #27                 // class org/apache/cxf/tools/java2wsdl/processor/internal/AntGenerator
     139: dup
     140: invokespecial #28                 // Method org/apache/cxf/tools/java2wsdl/processor/internal/AntGenerator."<init>":()V
     143: invokeinterface #20,  2           // InterfaceMethod java/util/List.add:(Ljava/lang/Object;)Z
     148: pop
     149: aload_0
     150: getfield      #4                  // Field generators:Ljava/util/List;
     153: invokeinterface #29,  1           // InterfaceMethod java/util/List.iterator:()Ljava/util/Iterator;
     158: astore        5
     160: aload         5
     162: invokeinterface #30,  1           // InterfaceMethod java/util/Iterator.hasNext:()Z
     167: ifeq          194
     170: aload         5
     172: invokeinterface #31,  1           // InterfaceMethod java/util/Iterator.next:()Ljava/lang/Object;
     177: checkcast     #32                 // class org/apache/cxf/tools/wsdlto/core/AbstractGenerator
     180: astore        6
     182: aload         6
     184: aload_0
     185: getfield      #5                  // Field context:Lorg/apache/cxf/tools/common/ToolContext;
     188: invokevirtual #33                 // Method org/apache/cxf/tools/wsdlto/core/AbstractGenerator.generate:(Lorg/apache/cxf/tools/common/ToolContext;)V
     191: goto          160
     194: return

  public void setEnvironment(org.apache.cxf.tools.common.ToolContext);
    Code:
       0: aload_0
       1: aload_1
       2: putfield      #5                  // Field context:Lorg/apache/cxf/tools/common/ToolContext;
       5: return
}
