Compiled from "AddCertificateRequest.java"
public class cn.com.antcloud.api.provider.bot.v1_0_0.request.AddCertificateRequest extends cn.com.antcloud.api.product.provider.AntCloudProdProviderRequest<cn.com.antcloud.api.provider.bot.v1_0_0.response.AddCertificateResponse> {
  private java.lang.Long organizationId;

  private java.lang.String certificate;

  private java.lang.String deviceId;

  private java.lang.String hostDeviceId;

  private java.lang.String projectId;

  public cn.com.antcloud.api.provider.bot.v1_0_0.request.AddCertificateRequest();
    Code:
       0: aload_0
       1: invokespecial #1                  // Method cn/com/antcloud/api/product/provider/AntCloudProdProviderRequest."<init>":()V
       4: return

  public java.lang.Long getOrganizationId();
    Code:
       0: aload_0
       1: getfield      #2                  // Field organizationId:Ljava/lang/Long;
       4: areturn

  public void setOrganizationId(java.lang.Long);
    Code:
       0: aload_0
       1: aload_1
       2: putfield      #2                  // Field organizationId:Ljava/lang/Long;
       5: return

  public java.lang.String getCertificate();
    Code:
       0: aload_0
       1: getfield      #3                  // Field certificate:Ljava/lang/String;
       4: areturn

  public void setCertificate(java.lang.String);
    Code:
       0: aload_0
       1: aload_1
       2: putfield      #3                  // Field certificate:Ljava/lang/String;
       5: return

  public java.lang.String getDeviceId();
    Code:
       0: aload_0
       1: getfield      #4                  // Field deviceId:Ljava/lang/String;
       4: areturn

  public void setDeviceId(java.lang.String);
    Code:
       0: aload_0
       1: aload_1
       2: putfield      #4                  // Field deviceId:Ljava/lang/String;
       5: return

  public java.lang.String getHostDeviceId();
    Code:
       0: aload_0
       1: getfield      #5                  // Field hostDeviceId:Ljava/lang/String;
       4: areturn

  public void setHostDeviceId(java.lang.String);
    Code:
       0: aload_0
       1: aload_1
       2: putfield      #5                  // Field hostDeviceId:Ljava/lang/String;
       5: return

  public java.lang.String getProjectId();
    Code:
       0: aload_0
       1: getfield      #6                  // Field projectId:Ljava/lang/String;
       4: areturn

  public void setProjectId(java.lang.String);
    Code:
       0: aload_0
       1: aload_1
       2: putfield      #6                  // Field projectId:Ljava/lang/String;
       5: return
}
