Compiled from "UpdateThingsdidDidRequest.java"
public class cn.com.antcloud.api.provider.bot.v1_0_0.request.UpdateThingsdidDidRequest extends cn.com.antcloud.api.product.provider.AntCloudProdProviderRequest<cn.com.antcloud.api.provider.bot.v1_0_0.response.UpdateThingsdidDidResponse> {
  private cn.com.antcloud.api.provider.bot.v1_0_0.model.ThingsDidUpdateReq didUpdateReq;

  private java.lang.String nonce;

  public cn.com.antcloud.api.provider.bot.v1_0_0.request.UpdateThingsdidDidRequest();
    Code:
       0: aload_0
       1: invokespecial #1                  // Method cn/com/antcloud/api/product/provider/AntCloudProdProviderRequest."<init>":()V
       4: return

  public cn.com.antcloud.api.provider.bot.v1_0_0.model.ThingsDidUpdateReq getDidUpdateReq();
    Code:
       0: aload_0
       1: getfield      #2                  // Field didUpdateReq:Lcn/com/antcloud/api/provider/bot/v1_0_0/model/ThingsDidUpdateReq;
       4: areturn

  public void setDidUpdateReq(cn.com.antcloud.api.provider.bot.v1_0_0.model.ThingsDidUpdateReq);
    Code:
       0: aload_0
       1: aload_1
       2: putfield      #2                  // Field didUpdateReq:Lcn/com/antcloud/api/provider/bot/v1_0_0/model/ThingsDidUpdateReq;
       5: return

  public java.lang.String getNonce();
    Code:
       0: aload_0
       1: getfield      #3                  // Field nonce:Ljava/lang/String;
       4: areturn

  public void setNonce(java.lang.String);
    Code:
       0: aload_0
       1: aload_1
       2: putfield      #3                  // Field nonce:Ljava/lang/String;
       5: return
}
