Compiled from "PagedListHolder.java"
public class org.springframework.beans.support.PagedListHolder<E> implements java.io.Serializable {
  public static final int DEFAULT_PAGE_SIZE;

  public static final int DEFAULT_MAX_LINKED_PAGES;

  private java.util.List<E> source;

  private java.util.Date refreshDate;

  private org.springframework.beans.support.SortDefinition sort;

  private org.springframework.beans.support.SortDefinition sortUsed;

  private int pageSize;

  private int page;

  private boolean newPageSet;

  private int maxLinkedPages;

  public org.springframework.beans.support.PagedListHolder();
    Code:
       0: aload_0
       1: new           #1                  // class java/util/ArrayList
       4: dup
       5: iconst_0
       6: invokespecial #2                  // Method java/util/ArrayList."<init>":(I)V
       9: invokespecial #3                  // Method "<init>":(Ljava/util/List;)V
      12: return

  public org.springframework.beans.support.PagedListHolder(java.util.List<E>);
    Code:
       0: aload_0
       1: aload_1
       2: new           #4                  // class org/springframework/beans/support/MutableSortDefinition
       5: dup
       6: iconst_1
       7: invokespecial #5                  // Method org/springframework/beans/support/MutableSortDefinition."<init>":(Z)V
      10: invokespecial #6                  // Method "<init>":(Ljava/util/List;Lorg/springframework/beans/support/SortDefinition;)V
      13: return

  public org.springframework.beans.support.PagedListHolder(java.util.List<E>, org.springframework.beans.support.SortDefinition);
    Code:
       0: aload_0
       1: invokespecial #7                  // Method java/lang/Object."<init>":()V
       4: aload_0
       5: invokestatic  #8                  // Method java/util/Collections.emptyList:()Ljava/util/List;
       8: putfield      #9                  // Field source:Ljava/util/List;
      11: aload_0
      12: bipush        10
      14: putfield      #11                 // Field pageSize:I
      17: aload_0
      18: iconst_0
      19: putfield      #12                 // Field page:I
      22: aload_0
      23: bipush        10
      25: putfield      #13                 // Field maxLinkedPages:I
      28: aload_0
      29: aload_1
      30: invokevirtual #14                 // Method setSource:(Ljava/util/List;)V
      33: aload_0
      34: aload_2
      35: invokevirtual #15                 // Method setSort:(Lorg/springframework/beans/support/SortDefinition;)V
      38: return

  public void setSource(java.util.List<E>);
    Code:
       0: aload_1
       1: ldc           #16                 // String Source List must not be null
       3: invokestatic  #17                 // Method org/springframework/util/Assert.notNull:(Ljava/lang/Object;Ljava/lang/String;)V
       6: aload_0
       7: aload_1
       8: putfield      #9                  // Field source:Ljava/util/List;
      11: aload_0
      12: new           #18                 // class java/util/Date
      15: dup
      16: invokespecial #19                 // Method java/util/Date."<init>":()V
      19: putfield      #20                 // Field refreshDate:Ljava/util/Date;
      22: aload_0
      23: aconst_null
      24: putfield      #21                 // Field sortUsed:Lorg/springframework/beans/support/SortDefinition;
      27: return

  public java.util.List<E> getSource();
    Code:
       0: aload_0
       1: getfield      #9                  // Field source:Ljava/util/List;
       4: areturn

  public java.util.Date getRefreshDate();
    Code:
       0: aload_0
       1: getfield      #20                 // Field refreshDate:Ljava/util/Date;
       4: areturn

  public void setSort(org.springframework.beans.support.SortDefinition);
    Code:
       0: aload_0
       1: aload_1
       2: putfield      #22                 // Field sort:Lorg/springframework/beans/support/SortDefinition;
       5: return

  public org.springframework.beans.support.SortDefinition getSort();
    Code:
       0: aload_0
       1: getfield      #22                 // Field sort:Lorg/springframework/beans/support/SortDefinition;
       4: areturn

  public void setPageSize(int);
    Code:
       0: iload_1
       1: aload_0
       2: getfield      #11                 // Field pageSize:I
       5: if_icmpeq     25
       8: aload_0
       9: iload_1
      10: putfield      #11                 // Field pageSize:I
      13: aload_0
      14: getfield      #23                 // Field newPageSet:Z
      17: ifne          25
      20: aload_0
      21: iconst_0
      22: putfield      #12                 // Field page:I
      25: return

  public int getPageSize();
    Code:
       0: aload_0
       1: getfield      #11                 // Field pageSize:I
       4: ireturn

  public void setPage(int);
    Code:
       0: aload_0
       1: iload_1
       2: putfield      #12                 // Field page:I
       5: aload_0
       6: iconst_1
       7: putfield      #23                 // Field newPageSet:Z
      10: return

  public int getPage();
    Code:
       0: aload_0
       1: iconst_0
       2: putfield      #23                 // Field newPageSet:Z
       5: aload_0
       6: getfield      #12                 // Field page:I
       9: aload_0
      10: invokevirtual #24                 // Method getPageCount:()I
      13: if_icmplt     26
      16: aload_0
      17: aload_0
      18: invokevirtual #24                 // Method getPageCount:()I
      21: iconst_1
      22: isub
      23: putfield      #12                 // Field page:I
      26: aload_0
      27: getfield      #12                 // Field page:I
      30: ireturn

  public void setMaxLinkedPages(int);
    Code:
       0: aload_0
       1: iload_1
       2: putfield      #13                 // Field maxLinkedPages:I
       5: return

  public int getMaxLinkedPages();
    Code:
       0: aload_0
       1: getfield      #13                 // Field maxLinkedPages:I
       4: ireturn

  public int getPageCount();
    Code:
       0: aload_0
       1: invokevirtual #25                 // Method getNrOfElements:()I
       4: i2f
       5: aload_0
       6: invokevirtual #26                 // Method getPageSize:()I
       9: i2f
      10: fdiv
      11: fstore_1
      12: fload_1
      13: fload_1
      14: f2i
      15: i2f
      16: fcmpl
      17: ifgt          27
      20: fload_1
      21: f2d
      22: dconst_0
      23: dcmpl
      24: ifne          33
      27: fload_1
      28: fconst_1
      29: fadd
      30: goto          34
      33: fload_1
      34: f2i
      35: ireturn

  public boolean isFirstPage();
    Code:
       0: aload_0
       1: invokevirtual #27                 // Method getPage:()I
       4: ifne          11
       7: iconst_1
       8: goto          12
      11: iconst_0
      12: ireturn

  public boolean isLastPage();
    Code:
       0: aload_0
       1: invokevirtual #27                 // Method getPage:()I
       4: aload_0
       5: invokevirtual #24                 // Method getPageCount:()I
       8: iconst_1
       9: isub
      10: if_icmpne     17
      13: iconst_1
      14: goto          18
      17: iconst_0
      18: ireturn

  public void previousPage();
    Code:
       0: aload_0
       1: invokevirtual #28                 // Method isFirstPage:()Z
       4: ifne          17
       7: aload_0
       8: dup
       9: getfield      #12                 // Field page:I
      12: iconst_1
      13: isub
      14: putfield      #12                 // Field page:I
      17: return

  public void nextPage();
    Code:
       0: aload_0
       1: invokevirtual #29                 // Method isLastPage:()Z
       4: ifne          17
       7: aload_0
       8: dup
       9: getfield      #12                 // Field page:I
      12: iconst_1
      13: iadd
      14: putfield      #12                 // Field page:I
      17: return

  public int getNrOfElements();
    Code:
       0: aload_0
       1: invokevirtual #30                 // Method getSource:()Ljava/util/List;
       4: invokeinterface #31,  1           // InterfaceMethod java/util/List.size:()I
       9: ireturn

  public int getFirstElementOnPage();
    Code:
       0: aload_0
       1: invokevirtual #26                 // Method getPageSize:()I
       4: aload_0
       5: invokevirtual #27                 // Method getPage:()I
       8: imul
       9: ireturn

  public int getLastElementOnPage();
    Code:
       0: aload_0
       1: invokevirtual #26                 // Method getPageSize:()I
       4: aload_0
       5: invokevirtual #27                 // Method getPage:()I
       8: iconst_1
       9: iadd
      10: imul
      11: istore_1
      12: aload_0
      13: invokevirtual #25                 // Method getNrOfElements:()I
      16: istore_2
      17: iload_1
      18: iload_2
      19: if_icmple     26
      22: iload_2
      23: goto          27
      26: iload_1
      27: iconst_1
      28: isub
      29: ireturn

  public java.util.List<E> getPageList();
    Code:
       0: aload_0
       1: invokevirtual #30                 // Method getSource:()Ljava/util/List;
       4: aload_0
       5: invokevirtual #32                 // Method getFirstElementOnPage:()I
       8: aload_0
       9: invokevirtual #33                 // Method getLastElementOnPage:()I
      12: iconst_1
      13: iadd
      14: invokeinterface #34,  3           // InterfaceMethod java/util/List.subList:(II)Ljava/util/List;
      19: areturn

  public int getFirstLinkedPage();
    Code:
       0: iconst_0
       1: aload_0
       2: invokevirtual #27                 // Method getPage:()I
       5: aload_0
       6: invokevirtual #35                 // Method getMaxLinkedPages:()I
       9: iconst_2
      10: idiv
      11: isub
      12: invokestatic  #36                 // Method java/lang/Math.max:(II)I
      15: ireturn

  public int getLastLinkedPage();
    Code:
       0: aload_0
       1: invokevirtual #37                 // Method getFirstLinkedPage:()I
       4: aload_0
       5: invokevirtual #35                 // Method getMaxLinkedPages:()I
       8: iadd
       9: iconst_1
      10: isub
      11: aload_0
      12: invokevirtual #24                 // Method getPageCount:()I
      15: iconst_1
      16: isub
      17: invokestatic  #38                 // Method java/lang/Math.min:(II)I
      20: ireturn

  public void resort();
    Code:
       0: aload_0
       1: invokevirtual #39                 // Method getSort:()Lorg/springframework/beans/support/SortDefinition;
       4: astore_1
       5: aload_1
       6: ifnull        43
       9: aload_1
      10: aload_0
      11: getfield      #21                 // Field sortUsed:Lorg/springframework/beans/support/SortDefinition;
      14: invokevirtual #40                 // Method java/lang/Object.equals:(Ljava/lang/Object;)Z
      17: ifne          43
      20: aload_0
      21: aload_0
      22: aload_1
      23: invokevirtual #41                 // Method copySortDefinition:(Lorg/springframework/beans/support/SortDefinition;)Lorg/springframework/beans/support/SortDefinition;
      26: putfield      #21                 // Field sortUsed:Lorg/springframework/beans/support/SortDefinition;
      29: aload_0
      30: aload_0
      31: invokevirtual #30                 // Method getSource:()Ljava/util/List;
      34: aload_1
      35: invokevirtual #42                 // Method doSort:(Ljava/util/List;Lorg/springframework/beans/support/SortDefinition;)V
      38: aload_0
      39: iconst_0
      40: invokevirtual #43                 // Method setPage:(I)V
      43: return

  protected org.springframework.beans.support.SortDefinition copySortDefinition(org.springframework.beans.support.SortDefinition);
    Code:
       0: new           #4                  // class org/springframework/beans/support/MutableSortDefinition
       3: dup
       4: aload_1
       5: invokespecial #44                 // Method org/springframework/beans/support/MutableSortDefinition."<init>":(Lorg/springframework/beans/support/SortDefinition;)V
       8: areturn

  protected void doSort(java.util.List<E>, org.springframework.beans.support.SortDefinition);
    Code:
       0: aload_1
       1: aload_2
       2: invokestatic  #45                 // Method org/springframework/beans/support/PropertyComparator.sort:(Ljava/util/List;Lorg/springframework/beans/support/SortDefinition;)V
       5: return
}
