Compiled from "ReflectionUtils.scala"
public final class org.elasticsearch.spark.serialization.ReflectionUtils$$anonfun$2 extends scala.runtime.AbstractFunction1<java.lang.String, scala.Tuple2<java.lang.String, java.lang.Object>> implements scala.Serializable {
  public static final long serialVersionUID;

  private final scala.collection.Iterator product$1;

  public final scala.Tuple2<java.lang.String, java.lang.Object> apply(java.lang.String);
    Code:
       0: new           #23                 // class scala/Tuple2
       3: dup
       4: aload_1
       5: aload_0
       6: getfield      #25                 // Field product$1:Lscala/collection/Iterator;
       9: invokeinterface #31,  1           // InterfaceMethod scala/collection/Iterator.next:()Ljava/lang/Object;
      14: invokespecial #35                 // Method scala/Tuple2."<init>":(Ljava/lang/Object;Ljava/lang/Object;)V
      17: areturn

  public final java.lang.Object apply(java.lang.Object);
    Code:
       0: aload_0
       1: aload_1
       2: checkcast     #42                 // class java/lang/String
       5: invokevirtual #44                 // Method apply:(Ljava/lang/String;)Lscala/Tuple2;
       8: areturn

  public org.elasticsearch.spark.serialization.ReflectionUtils$$anonfun$2(scala.collection.Iterator);
    Code:
       0: aload_0
       1: aload_1
       2: putfield      #25                 // Field product$1:Lscala/collection/Iterator;
       5: aload_0
       6: invokespecial #50                 // Method scala/runtime/AbstractFunction1."<init>":()V
       9: return
}
