Compiled from "ScalaMetadataExtractor.scala"
public final class org.elasticsearch.spark.serialization.ScalaMetadataExtractor$$anonfun$getValue$1 extends scala.runtime.AbstractFunction0<scala.runtime.Null$> implements scala.Serializable {
  public static final long serialVersionUID;

  public final scala.runtime.Null$ apply();
    Code:
       0: aconst_null
       1: areturn

  public final java.lang.Object apply();
    Code:
       0: aload_0
       1: invokevirtual #24                 // Method apply:()Lscala/runtime/Null$;
       4: pop
       5: aconst_null
       6: areturn

  public org.elasticsearch.spark.serialization.ScalaMetadataExtractor$$anonfun$getValue$1(org.elasticsearch.spark.serialization.ScalaMetadataExtractor);
    Code:
       0: aload_0
       1: invokespecial #29                 // Method scala/runtime/AbstractFunction0."<init>":()V
       4: return
}
