Compiled from "ScalaValueWriter.scala"
public final class org.elasticsearch.spark.serialization.ScalaValueWriter$ {
  public static final org.elasticsearch.spark.serialization.ScalaValueWriter$ MODULE$;

  public static {};
    Code:
       0: new           #2                  // class org/elasticsearch/spark/serialization/ScalaValueWriter$
       3: invokespecial #12                 // Method "<init>":()V
       6: return

  public boolean $lessinit$greater$default$1();
    Code:
       0: iconst_0
       1: ireturn

  private org.elasticsearch.spark.serialization.ScalaValueWriter$();
    Code:
       0: aload_0
       1: invokespecial #16                 // Method java/lang/Object."<init>":()V
       4: aload_0
       5: putstatic     #18                 // Field MODULE$:Lorg/elasticsearch/spark/serialization/ScalaValueWriter$;
       8: return
}
