Compiled from "SearchableConfigurationElement.java"
public class net.sf.ehcache.config.generator.model.elements.SearchableConfigurationElement extends net.sf.ehcache.config.generator.model.SimpleNodeElement {
  private final net.sf.ehcache.config.Searchable searchable;

  public net.sf.ehcache.config.generator.model.elements.SearchableConfigurationElement(net.sf.ehcache.config.generator.model.NodeElement, net.sf.ehcache.config.Searchable);
    Code:
       0: aload_0
       1: aload_1
       2: ldc           #1                  // String searchable
       4: invokespecial #2                  // Method net/sf/ehcache/config/generator/model/SimpleNodeElement."<init>":(Lnet/sf/ehcache/config/generator/model/NodeElement;Ljava/lang/String;)V
       7: aload_2
       8: ifnonnull     19
      11: new           #3                  // class java/lang/NullPointerException
      14: dup
      15: invokespecial #4                  // Method java/lang/NullPointerException."<init>":()V
      18: athrow
      19: aload_0
      20: aload_2
      21: putfield      #5                  // Field searchable:Lnet/sf/ehcache/config/Searchable;
      24: aload_0
      25: invokespecial #6                  // Method init:()V
      28: return

  private void init();
    Code:
       0: aload_0
       1: getfield      #5                  // Field searchable:Lnet/sf/ehcache/config/Searchable;
       4: invokevirtual #7                  // Method net/sf/ehcache/config/Searchable.getUserDefinedSearchAttributes:()Ljava/util/Map;
       7: invokeinterface #8,  1            // InterfaceMethod java/util/Map.values:()Ljava/util/Collection;
      12: invokeinterface #9,  1            // InterfaceMethod java/util/Collection.iterator:()Ljava/util/Iterator;
      17: astore_1
      18: aload_1
      19: invokeinterface #10,  1           // InterfaceMethod java/util/Iterator.hasNext:()Z
      24: ifeq          49
      27: aload_1
      28: invokeinterface #11,  1           // InterfaceMethod java/util/Iterator.next:()Ljava/lang/Object;
      33: checkcast     #12                 // class net/sf/ehcache/config/SearchAttribute
      36: astore_2
      37: aload_0
      38: aload_2
      39: aload_0
      40: invokevirtual #13                 // Method net/sf/ehcache/config/SearchAttribute.asConfigElement:(Lnet/sf/ehcache/config/generator/model/NodeElement;)Lnet/sf/ehcache/config/generator/model/NodeElement;
      43: invokevirtual #14                 // Method addChildElement:(Lnet/sf/ehcache/config/generator/model/NodeElement;)V
      46: goto          18
      49: aload_0
      50: new           #15                 // class net/sf/ehcache/config/generator/model/SimpleNodeAttribute
      53: dup
      54: ldc           #16                 // String keys
      56: aload_0
      57: getfield      #5                  // Field searchable:Lnet/sf/ehcache/config/Searchable;
      60: invokevirtual #17                 // Method net/sf/ehcache/config/Searchable.keys:()Z
      63: invokespecial #18                 // Method net/sf/ehcache/config/generator/model/SimpleNodeAttribute."<init>":(Ljava/lang/String;Z)V
      66: iconst_1
      67: invokevirtual #19                 // Method net/sf/ehcache/config/generator/model/SimpleNodeAttribute.optional:(Z)Lnet/sf/ehcache/config/generator/model/SimpleNodeAttribute;
      70: iconst_1
      71: invokevirtual #20                 // Method net/sf/ehcache/config/generator/model/SimpleNodeAttribute.defaultValue:(Z)Lnet/sf/ehcache/config/generator/model/SimpleNodeAttribute;
      74: invokevirtual #21                 // Method addAttribute:(Lnet/sf/ehcache/config/generator/model/NodeAttribute;)V
      77: aload_0
      78: new           #15                 // class net/sf/ehcache/config/generator/model/SimpleNodeAttribute
      81: dup
      82: ldc           #22                 // String values
      84: aload_0
      85: getfield      #5                  // Field searchable:Lnet/sf/ehcache/config/Searchable;
      88: invokevirtual #23                 // Method net/sf/ehcache/config/Searchable.values:()Z
      91: invokespecial #18                 // Method net/sf/ehcache/config/generator/model/SimpleNodeAttribute."<init>":(Ljava/lang/String;Z)V
      94: iconst_1
      95: invokevirtual #19                 // Method net/sf/ehcache/config/generator/model/SimpleNodeAttribute.optional:(Z)Lnet/sf/ehcache/config/generator/model/SimpleNodeAttribute;
      98: iconst_1
      99: invokevirtual #20                 // Method net/sf/ehcache/config/generator/model/SimpleNodeAttribute.defaultValue:(Z)Lnet/sf/ehcache/config/generator/model/SimpleNodeAttribute;
     102: invokevirtual #21                 // Method addAttribute:(Lnet/sf/ehcache/config/generator/model/NodeAttribute;)V
     105: aload_0
     106: new           #15                 // class net/sf/ehcache/config/generator/model/SimpleNodeAttribute
     109: dup
     110: ldc           #24                 // String allowDynamicIndexing
     112: aload_0
     113: getfield      #5                  // Field searchable:Lnet/sf/ehcache/config/Searchable;
     116: invokevirtual #25                 // Method net/sf/ehcache/config/Searchable.isDynamicIndexingAllowed:()Z
     119: invokespecial #18                 // Method net/sf/ehcache/config/generator/model/SimpleNodeAttribute."<init>":(Ljava/lang/String;Z)V
     122: iconst_1
     123: invokevirtual #19                 // Method net/sf/ehcache/config/generator/model/SimpleNodeAttribute.optional:(Z)Lnet/sf/ehcache/config/generator/model/SimpleNodeAttribute;
     126: iconst_0
     127: invokevirtual #20                 // Method net/sf/ehcache/config/generator/model/SimpleNodeAttribute.defaultValue:(Z)Lnet/sf/ehcache/config/generator/model/SimpleNodeAttribute;
     130: invokevirtual #21                 // Method addAttribute:(Lnet/sf/ehcache/config/generator/model/NodeAttribute;)V
     133: return
}
