Compiled from "PatternFormatterResourceDefinition.java"
public class org.jboss.as.logging.PatternFormatterResourceDefinition extends org.jboss.as.logging.TransformerResourceDefinition {
  static final java.lang.String COLOR_MAP_VALIDATION_PATTERN;

  public static final org.jboss.as.logging.PropertyAttributeDefinition COLOR_MAP;

  public static final org.jboss.as.logging.PropertyAttributeDefinition PATTERN;

  public static final org.jboss.as.controller.ObjectTypeAttributeDefinition PATTERN_FORMATTER;

  static final org.jboss.as.controller.PathElement PATTERN_FORMATTER_PATH;

  static final org.jboss.as.logging.PropertyAttributeDefinition[] ATTRIBUTES;

  static final org.jboss.as.controller.OperationStepHandler ADD;

  static final org.jboss.as.controller.OperationStepHandler WRITE;

  static final org.jboss.as.controller.OperationStepHandler REMOVE;

  static final org.jboss.as.logging.PatternFormatterResourceDefinition INSTANCE;

  public org.jboss.as.logging.PatternFormatterResourceDefinition();
    Code:
       0: aload_0
       1: getstatic     #1                  // Field PATTERN_FORMATTER_PATH:Lorg/jboss/as/controller/PathElement;
       4: iconst_1
       5: anewarray     #2                  // class java/lang/String
       8: dup
       9: iconst_0
      10: getstatic     #3                  // Field PATTERN_FORMATTER:Lorg/jboss/as/controller/ObjectTypeAttributeDefinition;
      13: invokevirtual #4                  // Method org/jboss/as/controller/ObjectTypeAttributeDefinition.getName:()Ljava/lang/String;
      16: aastore
      17: invokestatic  #5                  // Method org/jboss/as/logging/LoggingExtension.getResourceDescriptionResolver:([Ljava/lang/String;)Lorg/jboss/as/controller/descriptions/ResourceDescriptionResolver;
      20: getstatic     #6                  // Field ADD:Lorg/jboss/as/controller/OperationStepHandler;
      23: getstatic     #7                  // Field REMOVE:Lorg/jboss/as/controller/OperationStepHandler;
      26: invokespecial #8                  // Method org/jboss/as/logging/TransformerResourceDefinition."<init>":(Lorg/jboss/as/controller/PathElement;Lorg/jboss/as/controller/descriptions/ResourceDescriptionResolver;Lorg/jboss/as/controller/OperationStepHandler;Lorg/jboss/as/controller/OperationStepHandler;)V
      29: return

  public void registerAttributes(org.jboss.as.controller.registry.ManagementResourceRegistration);
    Code:
       0: getstatic     #9                  // Field ATTRIBUTES:[Lorg/jboss/as/logging/PropertyAttributeDefinition;
       3: astore_2
       4: aload_2
       5: arraylength
       6: istore_3
       7: iconst_0
       8: istore        4
      10: iload         4
      12: iload_3
      13: if_icmpge     40
      16: aload_2
      17: iload         4
      19: aaload
      20: astore        5
      22: aload_1
      23: aload         5
      25: aconst_null
      26: getstatic     #10                 // Field WRITE:Lorg/jboss/as/controller/OperationStepHandler;
      29: invokeinterface #11,  4           // InterfaceMethod org/jboss/as/controller/registry/ManagementResourceRegistration.registerReadWriteAttribute:(Lorg/jboss/as/controller/AttributeDefinition;Lorg/jboss/as/controller/OperationStepHandler;Lorg/jboss/as/controller/OperationStepHandler;)V
      34: iinc          4, 1
      37: goto          10
      40: return

  public void registerTransformers(org.jboss.as.logging.KnownModelVersion, org.jboss.as.controller.transform.description.ResourceTransformationDescriptionBuilder, org.jboss.as.controller.transform.description.ResourceTransformationDescriptionBuilder);
    Code:
       0: getstatic     #12                 // Field org/jboss/as/logging/PatternFormatterResourceDefinition$5.$SwitchMap$org$jboss$as$logging$KnownModelVersion:[I
       3: aload_1
       4: invokevirtual #13                 // Method org/jboss/as/logging/KnownModelVersion.ordinal:()I
       7: iaload
       8: lookupswitch  { // 1
                     1: 28
               default: 48
          }
      28: aload_2
      29: getstatic     #1                  // Field PATTERN_FORMATTER_PATH:Lorg/jboss/as/controller/PathElement;
      32: invokeinterface #14,  2           // InterfaceMethod org/jboss/as/controller/transform/description/ResourceTransformationDescriptionBuilder.rejectChildResource:(Lorg/jboss/as/controller/PathElement;)Lorg/jboss/as/controller/transform/description/RejectTransformationDescriptionBuilder;
      37: pop
      38: aload_3
      39: getstatic     #1                  // Field PATTERN_FORMATTER_PATH:Lorg/jboss/as/controller/PathElement;
      42: invokeinterface #14,  2           // InterfaceMethod org/jboss/as/controller/transform/description/ResourceTransformationDescriptionBuilder.rejectChildResource:(Lorg/jboss/as/controller/PathElement;)Lorg/jboss/as/controller/transform/description/RejectTransformationDescriptionBuilder;
      47: pop
      48: return

  static {};
    Code:
       0: ldc           #15                 // String color-map
       2: getstatic     #16                 // Field org/jboss/dmr/ModelType.STRING:Lorg/jboss/dmr/ModelType;
       5: invokestatic  #17                 // Method org/jboss/as/logging/PropertyAttributeDefinition$Builder.of:(Ljava/lang/String;Lorg/jboss/dmr/ModelType;)Lorg/jboss/as/logging/PropertyAttributeDefinition$Builder;
       8: iconst_1
       9: invokevirtual #18                 // Method org/jboss/as/logging/PropertyAttributeDefinition$Builder.setAllowExpression:(Z)Lorg/jboss/as/controller/AbstractAttributeDefinitionBuilder;
      12: checkcast     #19                 // class org/jboss/as/logging/PropertyAttributeDefinition$Builder
      15: iconst_1
      16: invokevirtual #20                 // Method org/jboss/as/logging/PropertyAttributeDefinition$Builder.setAllowNull:(Z)Lorg/jboss/as/controller/AbstractAttributeDefinitionBuilder;
      19: checkcast     #19                 // class org/jboss/as/logging/PropertyAttributeDefinition$Builder
      22: ldc           #21                 // String colors
      24: invokevirtual #22                 // Method org/jboss/as/logging/PropertyAttributeDefinition$Builder.setPropertyName:(Ljava/lang/String;)Lorg/jboss/as/logging/PropertyAttributeDefinition$Builder;
      27: new           #23                 // class org/jboss/as/logging/validators/RegexValidator
      30: dup
      31: getstatic     #16                 // Field org/jboss/dmr/ModelType.STRING:Lorg/jboss/dmr/ModelType;
      34: iconst_1
      35: iconst_1
      36: ldc           #25                 // String ^((severe|fatal|error|warn|warning|info|debug|trace|config|fine|finer|finest|):(clear|black|green|red|yellow|blue|magenta|cyan|white|brightblack|brightred|brightgreen|brightblue|brightyellow|brightmagenta|brightcyan|brightwhite|)(,(?!$)|$))*$
      38: invokespecial #26                 // Method org/jboss/as/logging/validators/RegexValidator."<init>":(Lorg/jboss/dmr/ModelType;ZZLjava/lang/String;)V
      41: invokevirtual #27                 // Method org/jboss/as/logging/PropertyAttributeDefinition$Builder.setValidator:(Lorg/jboss/as/controller/operations/validation/ParameterValidator;)Lorg/jboss/as/controller/AbstractAttributeDefinitionBuilder;
      44: checkcast     #19                 // class org/jboss/as/logging/PropertyAttributeDefinition$Builder
      47: invokevirtual #28                 // Method org/jboss/as/logging/PropertyAttributeDefinition$Builder.build:()Lorg/jboss/as/logging/PropertyAttributeDefinition;
      50: putstatic     #29                 // Field COLOR_MAP:Lorg/jboss/as/logging/PropertyAttributeDefinition;
      53: ldc           #30                 // String pattern
      55: getstatic     #16                 // Field org/jboss/dmr/ModelType.STRING:Lorg/jboss/dmr/ModelType;
      58: iconst_1
      59: invokestatic  #31                 // Method org/jboss/as/logging/PropertyAttributeDefinition$Builder.of:(Ljava/lang/String;Lorg/jboss/dmr/ModelType;Z)Lorg/jboss/as/logging/PropertyAttributeDefinition$Builder;
      62: iconst_1
      63: invokevirtual #18                 // Method org/jboss/as/logging/PropertyAttributeDefinition$Builder.setAllowExpression:(Z)Lorg/jboss/as/controller/AbstractAttributeDefinitionBuilder;
      66: checkcast     #19                 // class org/jboss/as/logging/PropertyAttributeDefinition$Builder
      69: new           #32                 // class org/jboss/dmr/ModelNode
      72: dup
      73: ldc           #33                 // String %d{HH:mm:ss,SSS} %-5p [%c] (%t) %s%e%n
      75: invokespecial #34                 // Method org/jboss/dmr/ModelNode."<init>":(Ljava/lang/String;)V
      78: invokevirtual #35                 // Method org/jboss/as/logging/PropertyAttributeDefinition$Builder.setDefaultValue:(Lorg/jboss/dmr/ModelNode;)Lorg/jboss/as/controller/AbstractAttributeDefinitionBuilder;
      81: checkcast     #19                 // class org/jboss/as/logging/PropertyAttributeDefinition$Builder
      84: invokevirtual #28                 // Method org/jboss/as/logging/PropertyAttributeDefinition$Builder.build:()Lorg/jboss/as/logging/PropertyAttributeDefinition;
      87: putstatic     #36                 // Field PATTERN:Lorg/jboss/as/logging/PropertyAttributeDefinition;
      90: ldc           #37                 // String pattern-formatter
      92: iconst_2
      93: anewarray     #38                 // class org/jboss/as/controller/AttributeDefinition
      96: dup
      97: iconst_0
      98: getstatic     #36                 // Field PATTERN:Lorg/jboss/as/logging/PropertyAttributeDefinition;
     101: aastore
     102: dup
     103: iconst_1
     104: getstatic     #29                 // Field COLOR_MAP:Lorg/jboss/as/logging/PropertyAttributeDefinition;
     107: aastore
     108: invokestatic  #39                 // Method org/jboss/as/controller/ObjectTypeAttributeDefinition$Builder.of:(Ljava/lang/String;[Lorg/jboss/as/controller/AttributeDefinition;)Lorg/jboss/as/controller/ObjectTypeAttributeDefinition$Builder;
     111: iconst_0
     112: invokevirtual #40                 // Method org/jboss/as/controller/ObjectTypeAttributeDefinition$Builder.setAllowExpression:(Z)Lorg/jboss/as/controller/AbstractAttributeDefinitionBuilder;
     115: checkcast     #41                 // class org/jboss/as/controller/ObjectTypeAttributeDefinition$Builder
     118: iconst_1
     119: invokevirtual #42                 // Method org/jboss/as/controller/ObjectTypeAttributeDefinition$Builder.setAllowNull:(Z)Lorg/jboss/as/controller/ObjectTypeAttributeDefinition$Builder;
     122: new           #43                 // class org/jboss/as/logging/PatternFormatterResourceDefinition$1
     125: dup
     126: invokespecial #44                 // Method org/jboss/as/logging/PatternFormatterResourceDefinition$1."<init>":()V
     129: invokevirtual #45                 // Method org/jboss/as/controller/ObjectTypeAttributeDefinition$Builder.setAttributeMarshaller:(Lorg/jboss/as/controller/AttributeMarshaller;)Lorg/jboss/as/controller/AbstractAttributeDefinitionBuilder;
     132: checkcast     #41                 // class org/jboss/as/controller/ObjectTypeAttributeDefinition$Builder
     135: invokevirtual #46                 // Method org/jboss/as/controller/ObjectTypeAttributeDefinition$Builder.build:()Lorg/jboss/as/controller/ObjectTypeAttributeDefinition;
     138: putstatic     #3                  // Field PATTERN_FORMATTER:Lorg/jboss/as/controller/ObjectTypeAttributeDefinition;
     141: getstatic     #3                  // Field PATTERN_FORMATTER:Lorg/jboss/as/controller/ObjectTypeAttributeDefinition;
     144: invokevirtual #4                  // Method org/jboss/as/controller/ObjectTypeAttributeDefinition.getName:()Ljava/lang/String;
     147: invokestatic  #47                 // Method org/jboss/as/controller/PathElement.pathElement:(Ljava/lang/String;)Lorg/jboss/as/controller/PathElement;
     150: putstatic     #1                  // Field PATTERN_FORMATTER_PATH:Lorg/jboss/as/controller/PathElement;
     153: iconst_2
     154: anewarray     #48                 // class org/jboss/as/logging/PropertyAttributeDefinition
     157: dup
     158: iconst_0
     159: getstatic     #29                 // Field COLOR_MAP:Lorg/jboss/as/logging/PropertyAttributeDefinition;
     162: aastore
     163: dup
     164: iconst_1
     165: getstatic     #36                 // Field PATTERN:Lorg/jboss/as/logging/PropertyAttributeDefinition;
     168: aastore
     169: putstatic     #9                  // Field ATTRIBUTES:[Lorg/jboss/as/logging/PropertyAttributeDefinition;
     172: new           #49                 // class org/jboss/as/logging/PatternFormatterResourceDefinition$2
     175: dup
     176: invokespecial #50                 // Method org/jboss/as/logging/PatternFormatterResourceDefinition$2."<init>":()V
     179: putstatic     #6                  // Field ADD:Lorg/jboss/as/controller/OperationStepHandler;
     182: new           #51                 // class org/jboss/as/logging/PatternFormatterResourceDefinition$3
     185: dup
     186: getstatic     #9                  // Field ATTRIBUTES:[Lorg/jboss/as/logging/PropertyAttributeDefinition;
     189: invokespecial #52                 // Method org/jboss/as/logging/PatternFormatterResourceDefinition$3."<init>":([Lorg/jboss/as/controller/AttributeDefinition;)V
     192: putstatic     #10                 // Field WRITE:Lorg/jboss/as/controller/OperationStepHandler;
     195: new           #53                 // class org/jboss/as/logging/PatternFormatterResourceDefinition$4
     198: dup
     199: invokespecial #54                 // Method org/jboss/as/logging/PatternFormatterResourceDefinition$4."<init>":()V
     202: putstatic     #7                  // Field REMOVE:Lorg/jboss/as/controller/OperationStepHandler;
     205: new           #24                 // class org/jboss/as/logging/PatternFormatterResourceDefinition
     208: dup
     209: invokespecial #55                 // Method "<init>":()V
     212: putstatic     #56                 // Field INSTANCE:Lorg/jboss/as/logging/PatternFormatterResourceDefinition;
     215: return
}
