Compiled from "SyslogHandlerResourceDefinition.java"
final class org.jboss.as.logging.SyslogHandlerResourceDefinition$FacilityAttribute extends java.lang.Enum<org.jboss.as.logging.SyslogHandlerResourceDefinition$FacilityAttribute> {
  public static final org.jboss.as.logging.SyslogHandlerResourceDefinition$FacilityAttribute KERNEL;

  public static final org.jboss.as.logging.SyslogHandlerResourceDefinition$FacilityAttribute USER_LEVEL;

  public static final org.jboss.as.logging.SyslogHandlerResourceDefinition$FacilityAttribute MAIL_SYSTEM;

  public static final org.jboss.as.logging.SyslogHandlerResourceDefinition$FacilityAttribute SYSTEM_DAEMONS;

  public static final org.jboss.as.logging.SyslogHandlerResourceDefinition$FacilityAttribute SECURITY;

  public static final org.jboss.as.logging.SyslogHandlerResourceDefinition$FacilityAttribute SYSLOGD;

  public static final org.jboss.as.logging.SyslogHandlerResourceDefinition$FacilityAttribute LINE_PRINTER;

  public static final org.jboss.as.logging.SyslogHandlerResourceDefinition$FacilityAttribute NETWORK_NEWS;

  public static final org.jboss.as.logging.SyslogHandlerResourceDefinition$FacilityAttribute UUCP;

  public static final org.jboss.as.logging.SyslogHandlerResourceDefinition$FacilityAttribute CLOCK_DAEMON;

  public static final org.jboss.as.logging.SyslogHandlerResourceDefinition$FacilityAttribute SECURITY2;

  public static final org.jboss.as.logging.SyslogHandlerResourceDefinition$FacilityAttribute FTP_DAEMON;

  public static final org.jboss.as.logging.SyslogHandlerResourceDefinition$FacilityAttribute NTP;

  public static final org.jboss.as.logging.SyslogHandlerResourceDefinition$FacilityAttribute LOG_AUDIT;

  public static final org.jboss.as.logging.SyslogHandlerResourceDefinition$FacilityAttribute LOG_ALERT;

  public static final org.jboss.as.logging.SyslogHandlerResourceDefinition$FacilityAttribute CLOCK_DAEMON2;

  public static final org.jboss.as.logging.SyslogHandlerResourceDefinition$FacilityAttribute LOCAL_USE_0;

  public static final org.jboss.as.logging.SyslogHandlerResourceDefinition$FacilityAttribute LOCAL_USE_1;

  public static final org.jboss.as.logging.SyslogHandlerResourceDefinition$FacilityAttribute LOCAL_USE_2;

  public static final org.jboss.as.logging.SyslogHandlerResourceDefinition$FacilityAttribute LOCAL_USE_3;

  public static final org.jboss.as.logging.SyslogHandlerResourceDefinition$FacilityAttribute LOCAL_USE_4;

  public static final org.jboss.as.logging.SyslogHandlerResourceDefinition$FacilityAttribute LOCAL_USE_5;

  public static final org.jboss.as.logging.SyslogHandlerResourceDefinition$FacilityAttribute LOCAL_USE_6;

  public static final org.jboss.as.logging.SyslogHandlerResourceDefinition$FacilityAttribute LOCAL_USE_7;

  private static final java.util.Map<java.lang.String, org.jboss.as.logging.SyslogHandlerResourceDefinition$FacilityAttribute> MAP;

  private final org.jboss.logmanager.handlers.SyslogHandler$Facility facility;

  private final java.lang.String value;

  private static final org.jboss.as.logging.SyslogHandlerResourceDefinition$FacilityAttribute[] $VALUES;

  public static org.jboss.as.logging.SyslogHandlerResourceDefinition$FacilityAttribute[] values();
    Code:
       0: getstatic     #1                  // Field $VALUES:[Lorg/jboss/as/logging/SyslogHandlerResourceDefinition$FacilityAttribute;
       3: invokevirtual #2                  // Method "[Lorg/jboss/as/logging/SyslogHandlerResourceDefinition$FacilityAttribute;".clone:()Ljava/lang/Object;
       6: checkcast     #3                  // class "[Lorg/jboss/as/logging/SyslogHandlerResourceDefinition$FacilityAttribute;"
       9: areturn

  public static org.jboss.as.logging.SyslogHandlerResourceDefinition$FacilityAttribute valueOf(java.lang.String);
    Code:
       0: ldc           #4                  // class org/jboss/as/logging/SyslogHandlerResourceDefinition$FacilityAttribute
       2: aload_0
       3: invokestatic  #5                  // Method java/lang/Enum.valueOf:(Ljava/lang/Class;Ljava/lang/String;)Ljava/lang/Enum;
       6: checkcast     #4                  // class org/jboss/as/logging/SyslogHandlerResourceDefinition$FacilityAttribute
       9: areturn

  private org.jboss.as.logging.SyslogHandlerResourceDefinition$FacilityAttribute(java.lang.String);
    Code:
       0: aload_0
       1: aload_1
       2: iload_2
       3: invokespecial #6                  // Method java/lang/Enum."<init>":(Ljava/lang/String;I)V
       6: aload_0
       7: aload_3
       8: putfield      #7                  // Field value:Ljava/lang/String;
      11: aload_0
      12: aload_3
      13: ldc           #8                  // String -
      15: ldc           #9                  // String _
      17: invokevirtual #10                 // Method java/lang/String.replace:(Ljava/lang/CharSequence;Ljava/lang/CharSequence;)Ljava/lang/String;
      20: getstatic     #11                 // Field java/util/Locale.ENGLISH:Ljava/util/Locale;
      23: invokevirtual #12                 // Method java/lang/String.toUpperCase:(Ljava/util/Locale;)Ljava/lang/String;
      26: invokestatic  #13                 // Method org/jboss/logmanager/handlers/SyslogHandler$Facility.valueOf:(Ljava/lang/String;)Lorg/jboss/logmanager/handlers/SyslogHandler$Facility;
      29: putfield      #14                 // Field facility:Lorg/jboss/logmanager/handlers/SyslogHandler$Facility;
      32: return

  public org.jboss.logmanager.handlers.SyslogHandler$Facility getFacility();
    Code:
       0: aload_0
       1: getfield      #14                 // Field facility:Lorg/jboss/logmanager/handlers/SyslogHandler$Facility;
       4: areturn

  public java.lang.String getValue();
    Code:
       0: aload_0
       1: getfield      #7                  // Field value:Ljava/lang/String;
       4: areturn

  public java.lang.String toString();
    Code:
       0: aload_0
       1: getfield      #7                  // Field value:Ljava/lang/String;
       4: areturn

  static org.jboss.as.logging.SyslogHandlerResourceDefinition$FacilityAttribute fromString(java.lang.String);
    Code:
       0: getstatic     #15                 // Field MAP:Ljava/util/Map;
       3: aload_0
       4: invokeinterface #16,  2           // InterfaceMethod java/util/Map.get:(Ljava/lang/Object;)Ljava/lang/Object;
       9: checkcast     #4                  // class org/jboss/as/logging/SyslogHandlerResourceDefinition$FacilityAttribute
      12: areturn

  static {};
    Code:
       0: new           #4                  // class org/jboss/as/logging/SyslogHandlerResourceDefinition$FacilityAttribute
       3: dup
       4: ldc           #17                 // String KERNEL
       6: iconst_0
       7: ldc           #18                 // String kernel
       9: invokespecial #19                 // Method "<init>":(Ljava/lang/String;ILjava/lang/String;)V
      12: putstatic     #20                 // Field KERNEL:Lorg/jboss/as/logging/SyslogHandlerResourceDefinition$FacilityAttribute;
      15: new           #4                  // class org/jboss/as/logging/SyslogHandlerResourceDefinition$FacilityAttribute
      18: dup
      19: ldc           #21                 // String USER_LEVEL
      21: iconst_1
      22: ldc           #22                 // String user-level
      24: invokespecial #19                 // Method "<init>":(Ljava/lang/String;ILjava/lang/String;)V
      27: putstatic     #23                 // Field USER_LEVEL:Lorg/jboss/as/logging/SyslogHandlerResourceDefinition$FacilityAttribute;
      30: new           #4                  // class org/jboss/as/logging/SyslogHandlerResourceDefinition$FacilityAttribute
      33: dup
      34: ldc           #24                 // String MAIL_SYSTEM
      36: iconst_2
      37: ldc           #25                 // String mail-system
      39: invokespecial #19                 // Method "<init>":(Ljava/lang/String;ILjava/lang/String;)V
      42: putstatic     #26                 // Field MAIL_SYSTEM:Lorg/jboss/as/logging/SyslogHandlerResourceDefinition$FacilityAttribute;
      45: new           #4                  // class org/jboss/as/logging/SyslogHandlerResourceDefinition$FacilityAttribute
      48: dup
      49: ldc           #27                 // String SYSTEM_DAEMONS
      51: iconst_3
      52: ldc           #28                 // String system-daemons
      54: invokespecial #19                 // Method "<init>":(Ljava/lang/String;ILjava/lang/String;)V
      57: putstatic     #29                 // Field SYSTEM_DAEMONS:Lorg/jboss/as/logging/SyslogHandlerResourceDefinition$FacilityAttribute;
      60: new           #4                  // class org/jboss/as/logging/SyslogHandlerResourceDefinition$FacilityAttribute
      63: dup
      64: ldc           #30                 // String SECURITY
      66: iconst_4
      67: ldc           #31                 // String security
      69: invokespecial #19                 // Method "<init>":(Ljava/lang/String;ILjava/lang/String;)V
      72: putstatic     #32                 // Field SECURITY:Lorg/jboss/as/logging/SyslogHandlerResourceDefinition$FacilityAttribute;
      75: new           #4                  // class org/jboss/as/logging/SyslogHandlerResourceDefinition$FacilityAttribute
      78: dup
      79: ldc           #33                 // String SYSLOGD
      81: iconst_5
      82: ldc           #34                 // String syslogd
      84: invokespecial #19                 // Method "<init>":(Ljava/lang/String;ILjava/lang/String;)V
      87: putstatic     #35                 // Field SYSLOGD:Lorg/jboss/as/logging/SyslogHandlerResourceDefinition$FacilityAttribute;
      90: new           #4                  // class org/jboss/as/logging/SyslogHandlerResourceDefinition$FacilityAttribute
      93: dup
      94: ldc           #36                 // String LINE_PRINTER
      96: bipush        6
      98: ldc           #37                 // String line-printer
     100: invokespecial #19                 // Method "<init>":(Ljava/lang/String;ILjava/lang/String;)V
     103: putstatic     #38                 // Field LINE_PRINTER:Lorg/jboss/as/logging/SyslogHandlerResourceDefinition$FacilityAttribute;
     106: new           #4                  // class org/jboss/as/logging/SyslogHandlerResourceDefinition$FacilityAttribute
     109: dup
     110: ldc           #39                 // String NETWORK_NEWS
     112: bipush        7
     114: ldc           #40                 // String network-news
     116: invokespecial #19                 // Method "<init>":(Ljava/lang/String;ILjava/lang/String;)V
     119: putstatic     #41                 // Field NETWORK_NEWS:Lorg/jboss/as/logging/SyslogHandlerResourceDefinition$FacilityAttribute;
     122: new           #4                  // class org/jboss/as/logging/SyslogHandlerResourceDefinition$FacilityAttribute
     125: dup
     126: ldc           #42                 // String UUCP
     128: bipush        8
     130: ldc           #43                 // String uucp
     132: invokespecial #19                 // Method "<init>":(Ljava/lang/String;ILjava/lang/String;)V
     135: putstatic     #44                 // Field UUCP:Lorg/jboss/as/logging/SyslogHandlerResourceDefinition$FacilityAttribute;
     138: new           #4                  // class org/jboss/as/logging/SyslogHandlerResourceDefinition$FacilityAttribute
     141: dup
     142: ldc           #45                 // String CLOCK_DAEMON
     144: bipush        9
     146: ldc           #46                 // String clock-daemon
     148: invokespecial #19                 // Method "<init>":(Ljava/lang/String;ILjava/lang/String;)V
     151: putstatic     #47                 // Field CLOCK_DAEMON:Lorg/jboss/as/logging/SyslogHandlerResourceDefinition$FacilityAttribute;
     154: new           #4                  // class org/jboss/as/logging/SyslogHandlerResourceDefinition$FacilityAttribute
     157: dup
     158: ldc           #48                 // String SECURITY2
     160: bipush        10
     162: ldc           #49                 // String security2
     164: invokespecial #19                 // Method "<init>":(Ljava/lang/String;ILjava/lang/String;)V
     167: putstatic     #50                 // Field SECURITY2:Lorg/jboss/as/logging/SyslogHandlerResourceDefinition$FacilityAttribute;
     170: new           #4                  // class org/jboss/as/logging/SyslogHandlerResourceDefinition$FacilityAttribute
     173: dup
     174: ldc           #51                 // String FTP_DAEMON
     176: bipush        11
     178: ldc           #52                 // String ftp-daemon
     180: invokespecial #19                 // Method "<init>":(Ljava/lang/String;ILjava/lang/String;)V
     183: putstatic     #53                 // Field FTP_DAEMON:Lorg/jboss/as/logging/SyslogHandlerResourceDefinition$FacilityAttribute;
     186: new           #4                  // class org/jboss/as/logging/SyslogHandlerResourceDefinition$FacilityAttribute
     189: dup
     190: ldc           #54                 // String NTP
     192: bipush        12
     194: ldc           #55                 // String ntp
     196: invokespecial #19                 // Method "<init>":(Ljava/lang/String;ILjava/lang/String;)V
     199: putstatic     #56                 // Field NTP:Lorg/jboss/as/logging/SyslogHandlerResourceDefinition$FacilityAttribute;
     202: new           #4                  // class org/jboss/as/logging/SyslogHandlerResourceDefinition$FacilityAttribute
     205: dup
     206: ldc           #57                 // String LOG_AUDIT
     208: bipush        13
     210: ldc           #58                 // String log-audit
     212: invokespecial #19                 // Method "<init>":(Ljava/lang/String;ILjava/lang/String;)V
     215: putstatic     #59                 // Field LOG_AUDIT:Lorg/jboss/as/logging/SyslogHandlerResourceDefinition$FacilityAttribute;
     218: new           #4                  // class org/jboss/as/logging/SyslogHandlerResourceDefinition$FacilityAttribute
     221: dup
     222: ldc           #60                 // String LOG_ALERT
     224: bipush        14
     226: ldc           #61                 // String log-alert
     228: invokespecial #19                 // Method "<init>":(Ljava/lang/String;ILjava/lang/String;)V
     231: putstatic     #62                 // Field LOG_ALERT:Lorg/jboss/as/logging/SyslogHandlerResourceDefinition$FacilityAttribute;
     234: new           #4                  // class org/jboss/as/logging/SyslogHandlerResourceDefinition$FacilityAttribute
     237: dup
     238: ldc           #63                 // String CLOCK_DAEMON2
     240: bipush        15
     242: ldc           #64                 // String clock-daemon2
     244: invokespecial #19                 // Method "<init>":(Ljava/lang/String;ILjava/lang/String;)V
     247: putstatic     #65                 // Field CLOCK_DAEMON2:Lorg/jboss/as/logging/SyslogHandlerResourceDefinition$FacilityAttribute;
     250: new           #4                  // class org/jboss/as/logging/SyslogHandlerResourceDefinition$FacilityAttribute
     253: dup
     254: ldc           #66                 // String LOCAL_USE_0
     256: bipush        16
     258: ldc           #67                 // String local-use-0
     260: invokespecial #19                 // Method "<init>":(Ljava/lang/String;ILjava/lang/String;)V
     263: putstatic     #68                 // Field LOCAL_USE_0:Lorg/jboss/as/logging/SyslogHandlerResourceDefinition$FacilityAttribute;
     266: new           #4                  // class org/jboss/as/logging/SyslogHandlerResourceDefinition$FacilityAttribute
     269: dup
     270: ldc           #69                 // String LOCAL_USE_1
     272: bipush        17
     274: ldc           #70                 // String local-use-1
     276: invokespecial #19                 // Method "<init>":(Ljava/lang/String;ILjava/lang/String;)V
     279: putstatic     #71                 // Field LOCAL_USE_1:Lorg/jboss/as/logging/SyslogHandlerResourceDefinition$FacilityAttribute;
     282: new           #4                  // class org/jboss/as/logging/SyslogHandlerResourceDefinition$FacilityAttribute
     285: dup
     286: ldc           #72                 // String LOCAL_USE_2
     288: bipush        18
     290: ldc           #73                 // String local-use-2
     292: invokespecial #19                 // Method "<init>":(Ljava/lang/String;ILjava/lang/String;)V
     295: putstatic     #74                 // Field LOCAL_USE_2:Lorg/jboss/as/logging/SyslogHandlerResourceDefinition$FacilityAttribute;
     298: new           #4                  // class org/jboss/as/logging/SyslogHandlerResourceDefinition$FacilityAttribute
     301: dup
     302: ldc           #75                 // String LOCAL_USE_3
     304: bipush        19
     306: ldc           #76                 // String local-use-3
     308: invokespecial #19                 // Method "<init>":(Ljava/lang/String;ILjava/lang/String;)V
     311: putstatic     #77                 // Field LOCAL_USE_3:Lorg/jboss/as/logging/SyslogHandlerResourceDefinition$FacilityAttribute;
     314: new           #4                  // class org/jboss/as/logging/SyslogHandlerResourceDefinition$FacilityAttribute
     317: dup
     318: ldc           #78                 // String LOCAL_USE_4
     320: bipush        20
     322: ldc           #79                 // String local-use-4
     324: invokespecial #19                 // Method "<init>":(Ljava/lang/String;ILjava/lang/String;)V
     327: putstatic     #80                 // Field LOCAL_USE_4:Lorg/jboss/as/logging/SyslogHandlerResourceDefinition$FacilityAttribute;
     330: new           #4                  // class org/jboss/as/logging/SyslogHandlerResourceDefinition$FacilityAttribute
     333: dup
     334: ldc           #81                 // String LOCAL_USE_5
     336: bipush        21
     338: ldc           #82                 // String local-use-5
     340: invokespecial #19                 // Method "<init>":(Ljava/lang/String;ILjava/lang/String;)V
     343: putstatic     #83                 // Field LOCAL_USE_5:Lorg/jboss/as/logging/SyslogHandlerResourceDefinition$FacilityAttribute;
     346: new           #4                  // class org/jboss/as/logging/SyslogHandlerResourceDefinition$FacilityAttribute
     349: dup
     350: ldc           #84                 // String LOCAL_USE_6
     352: bipush        22
     354: ldc           #85                 // String local-use-6
     356: invokespecial #19                 // Method "<init>":(Ljava/lang/String;ILjava/lang/String;)V
     359: putstatic     #86                 // Field LOCAL_USE_6:Lorg/jboss/as/logging/SyslogHandlerResourceDefinition$FacilityAttribute;
     362: new           #4                  // class org/jboss/as/logging/SyslogHandlerResourceDefinition$FacilityAttribute
     365: dup
     366: ldc           #87                 // String LOCAL_USE_7
     368: bipush        23
     370: ldc           #88                 // String local-use-7
     372: invokespecial #19                 // Method "<init>":(Ljava/lang/String;ILjava/lang/String;)V
     375: putstatic     #89                 // Field LOCAL_USE_7:Lorg/jboss/as/logging/SyslogHandlerResourceDefinition$FacilityAttribute;
     378: bipush        24
     380: anewarray     #4                  // class org/jboss/as/logging/SyslogHandlerResourceDefinition$FacilityAttribute
     383: dup
     384: iconst_0
     385: getstatic     #20                 // Field KERNEL:Lorg/jboss/as/logging/SyslogHandlerResourceDefinition$FacilityAttribute;
     388: aastore
     389: dup
     390: iconst_1
     391: getstatic     #23                 // Field USER_LEVEL:Lorg/jboss/as/logging/SyslogHandlerResourceDefinition$FacilityAttribute;
     394: aastore
     395: dup
     396: iconst_2
     397: getstatic     #26                 // Field MAIL_SYSTEM:Lorg/jboss/as/logging/SyslogHandlerResourceDefinition$FacilityAttribute;
     400: aastore
     401: dup
     402: iconst_3
     403: getstatic     #29                 // Field SYSTEM_DAEMONS:Lorg/jboss/as/logging/SyslogHandlerResourceDefinition$FacilityAttribute;
     406: aastore
     407: dup
     408: iconst_4
     409: getstatic     #32                 // Field SECURITY:Lorg/jboss/as/logging/SyslogHandlerResourceDefinition$FacilityAttribute;
     412: aastore
     413: dup
     414: iconst_5
     415: getstatic     #35                 // Field SYSLOGD:Lorg/jboss/as/logging/SyslogHandlerResourceDefinition$FacilityAttribute;
     418: aastore
     419: dup
     420: bipush        6
     422: getstatic     #38                 // Field LINE_PRINTER:Lorg/jboss/as/logging/SyslogHandlerResourceDefinition$FacilityAttribute;
     425: aastore
     426: dup
     427: bipush        7
     429: getstatic     #41                 // Field NETWORK_NEWS:Lorg/jboss/as/logging/SyslogHandlerResourceDefinition$FacilityAttribute;
     432: aastore
     433: dup
     434: bipush        8
     436: getstatic     #44                 // Field UUCP:Lorg/jboss/as/logging/SyslogHandlerResourceDefinition$FacilityAttribute;
     439: aastore
     440: dup
     441: bipush        9
     443: getstatic     #47                 // Field CLOCK_DAEMON:Lorg/jboss/as/logging/SyslogHandlerResourceDefinition$FacilityAttribute;
     446: aastore
     447: dup
     448: bipush        10
     450: getstatic     #50                 // Field SECURITY2:Lorg/jboss/as/logging/SyslogHandlerResourceDefinition$FacilityAttribute;
     453: aastore
     454: dup
     455: bipush        11
     457: getstatic     #53                 // Field FTP_DAEMON:Lorg/jboss/as/logging/SyslogHandlerResourceDefinition$FacilityAttribute;
     460: aastore
     461: dup
     462: bipush        12
     464: getstatic     #56                 // Field NTP:Lorg/jboss/as/logging/SyslogHandlerResourceDefinition$FacilityAttribute;
     467: aastore
     468: dup
     469: bipush        13
     471: getstatic     #59                 // Field LOG_AUDIT:Lorg/jboss/as/logging/SyslogHandlerResourceDefinition$FacilityAttribute;
     474: aastore
     475: dup
     476: bipush        14
     478: getstatic     #62                 // Field LOG_ALERT:Lorg/jboss/as/logging/SyslogHandlerResourceDefinition$FacilityAttribute;
     481: aastore
     482: dup
     483: bipush        15
     485: getstatic     #65                 // Field CLOCK_DAEMON2:Lorg/jboss/as/logging/SyslogHandlerResourceDefinition$FacilityAttribute;
     488: aastore
     489: dup
     490: bipush        16
     492: getstatic     #68                 // Field LOCAL_USE_0:Lorg/jboss/as/logging/SyslogHandlerResourceDefinition$FacilityAttribute;
     495: aastore
     496: dup
     497: bipush        17
     499: getstatic     #71                 // Field LOCAL_USE_1:Lorg/jboss/as/logging/SyslogHandlerResourceDefinition$FacilityAttribute;
     502: aastore
     503: dup
     504: bipush        18
     506: getstatic     #74                 // Field LOCAL_USE_2:Lorg/jboss/as/logging/SyslogHandlerResourceDefinition$FacilityAttribute;
     509: aastore
     510: dup
     511: bipush        19
     513: getstatic     #77                 // Field LOCAL_USE_3:Lorg/jboss/as/logging/SyslogHandlerResourceDefinition$FacilityAttribute;
     516: aastore
     517: dup
     518: bipush        20
     520: getstatic     #80                 // Field LOCAL_USE_4:Lorg/jboss/as/logging/SyslogHandlerResourceDefinition$FacilityAttribute;
     523: aastore
     524: dup
     525: bipush        21
     527: getstatic     #83                 // Field LOCAL_USE_5:Lorg/jboss/as/logging/SyslogHandlerResourceDefinition$FacilityAttribute;
     530: aastore
     531: dup
     532: bipush        22
     534: getstatic     #86                 // Field LOCAL_USE_6:Lorg/jboss/as/logging/SyslogHandlerResourceDefinition$FacilityAttribute;
     537: aastore
     538: dup
     539: bipush        23
     541: getstatic     #89                 // Field LOCAL_USE_7:Lorg/jboss/as/logging/SyslogHandlerResourceDefinition$FacilityAttribute;
     544: aastore
     545: putstatic     #1                  // Field $VALUES:[Lorg/jboss/as/logging/SyslogHandlerResourceDefinition$FacilityAttribute;
     548: new           #90                 // class java/util/HashMap
     551: dup
     552: invokespecial #91                 // Method java/util/HashMap."<init>":()V
     555: putstatic     #15                 // Field MAP:Ljava/util/Map;
     558: invokestatic  #92                 // Method values:()[Lorg/jboss/as/logging/SyslogHandlerResourceDefinition$FacilityAttribute;
     561: astore_0
     562: aload_0
     563: arraylength
     564: istore_1
     565: iconst_0
     566: istore_2
     567: iload_2
     568: iload_1
     569: if_icmpge     596
     572: aload_0
     573: iload_2
     574: aaload
     575: astore_3
     576: getstatic     #15                 // Field MAP:Ljava/util/Map;
     579: aload_3
     580: invokevirtual #93                 // Method toString:()Ljava/lang/String;
     583: aload_3
     584: invokeinterface #94,  3           // InterfaceMethod java/util/Map.put:(Ljava/lang/Object;Ljava/lang/Object;)Ljava/lang/Object;
     589: pop
     590: iinc          2, 1
     593: goto          567
     596: return
}
