Compiled from "AssertionRuleUpdate.scala"
public final class zio.aws.route53recoverycontrolconfig.model.AssertionRuleUpdate$Wrapper implements zio.aws.route53recoverycontrolconfig.model.AssertionRuleUpdate$ReadOnly {
  private final java.lang.String name;

  private final java.lang.String safetyRuleArn;

  private final int waitPeriodMs;

  public zio.aws.route53recoverycontrolconfig.model.AssertionRuleUpdate asEditable();
    Code:
       0: aload_0
       1: invokestatic  #22                 // InterfaceMethod zio/aws/route53recoverycontrolconfig/model/AssertionRuleUpdate$ReadOnly.asEditable$:(Lzio/aws/route53recoverycontrolconfig/model/AssertionRuleUpdate$ReadOnly;)Lzio/aws/route53recoverycontrolconfig/model/AssertionRuleUpdate;
       4: areturn

  public zio.ZIO<java.lang.Object, scala.runtime.Nothing$, java.lang.String> getName();
    Code:
       0: aload_0
       1: invokestatic  #31                 // InterfaceMethod zio/aws/route53recoverycontrolconfig/model/AssertionRuleUpdate$ReadOnly.getName$:(Lzio/aws/route53recoverycontrolconfig/model/AssertionRuleUpdate$ReadOnly;)Lzio/ZIO;
       4: areturn

  public zio.ZIO<java.lang.Object, scala.runtime.Nothing$, java.lang.String> getSafetyRuleArn();
    Code:
       0: aload_0
       1: invokestatic  #35                 // InterfaceMethod zio/aws/route53recoverycontrolconfig/model/AssertionRuleUpdate$ReadOnly.getSafetyRuleArn$:(Lzio/aws/route53recoverycontrolconfig/model/AssertionRuleUpdate$ReadOnly;)Lzio/ZIO;
       4: areturn

  public zio.ZIO<java.lang.Object, scala.runtime.Nothing$, java.lang.Object> getWaitPeriodMs();
    Code:
       0: aload_0
       1: invokestatic  #40                 // InterfaceMethod zio/aws/route53recoverycontrolconfig/model/AssertionRuleUpdate$ReadOnly.getWaitPeriodMs$:(Lzio/aws/route53recoverycontrolconfig/model/AssertionRuleUpdate$ReadOnly;)Lzio/ZIO;
       4: areturn

  public java.lang.String name();
    Code:
       0: aload_0
       1: getfield      #43                 // Field name:Ljava/lang/String;
       4: areturn

  public java.lang.String safetyRuleArn();
    Code:
       0: aload_0
       1: getfield      #45                 // Field safetyRuleArn:Ljava/lang/String;
       4: areturn

  public int waitPeriodMs();
    Code:
       0: aload_0
       1: getfield      #48                 // Field waitPeriodMs:I
       4: ireturn

  public zio.aws.route53recoverycontrolconfig.model.AssertionRuleUpdate$Wrapper(software.amazon.awssdk.services.route53recoverycontrolconfig.model.AssertionRuleUpdate);
    Code:
       0: aload_0
       1: invokespecial #54                 // Method java/lang/Object."<init>":()V
       4: aload_0
       5: invokestatic  #58                 // InterfaceMethod zio/aws/route53recoverycontrolconfig/model/AssertionRuleUpdate$ReadOnly.$init$:(Lzio/aws/route53recoverycontrolconfig/model/AssertionRuleUpdate$ReadOnly;)V
       8: aload_0
       9: aload_1
      10: invokevirtual #62                 // Method software/amazon/awssdk/services/route53recoverycontrolconfig/model/AssertionRuleUpdate.name:()Ljava/lang/String;
      13: putfield      #43                 // Field name:Ljava/lang/String;
      16: aload_0
      17: aload_1
      18: invokevirtual #64                 // Method software/amazon/awssdk/services/route53recoverycontrolconfig/model/AssertionRuleUpdate.safetyRuleArn:()Ljava/lang/String;
      21: putfield      #45                 // Field safetyRuleArn:Ljava/lang/String;
      24: aload_0
      25: getstatic     #70                 // Field scala/Predef$.MODULE$:Lscala/Predef$;
      28: aload_1
      29: invokevirtual #73                 // Method software/amazon/awssdk/services/route53recoverycontrolconfig/model/AssertionRuleUpdate.waitPeriodMs:()Ljava/lang/Integer;
      32: invokevirtual #77                 // Method scala/Predef$.Integer2int:(Ljava/lang/Integer;)I
      35: putfield      #48                 // Field waitPeriodMs:I
      38: return
}
