Compiled from "DeleteSafetyRuleRequest.scala"
public final class zio.aws.route53recoverycontrolconfig.model.DeleteSafetyRuleRequest$Wrapper implements zio.aws.route53recoverycontrolconfig.model.DeleteSafetyRuleRequest$ReadOnly {
  private final java.lang.String safetyRuleArn;

  public zio.aws.route53recoverycontrolconfig.model.DeleteSafetyRuleRequest asEditable();
    Code:
       0: aload_0
       1: invokestatic  #19                 // InterfaceMethod zio/aws/route53recoverycontrolconfig/model/DeleteSafetyRuleRequest$ReadOnly.asEditable$:(Lzio/aws/route53recoverycontrolconfig/model/DeleteSafetyRuleRequest$ReadOnly;)Lzio/aws/route53recoverycontrolconfig/model/DeleteSafetyRuleRequest;
       4: areturn

  public zio.ZIO<java.lang.Object, scala.runtime.Nothing$, java.lang.String> getSafetyRuleArn();
    Code:
       0: aload_0
       1: invokestatic  #28                 // InterfaceMethod zio/aws/route53recoverycontrolconfig/model/DeleteSafetyRuleRequest$ReadOnly.getSafetyRuleArn$:(Lzio/aws/route53recoverycontrolconfig/model/DeleteSafetyRuleRequest$ReadOnly;)Lzio/ZIO;
       4: areturn

  public java.lang.String safetyRuleArn();
    Code:
       0: aload_0
       1: getfield      #31                 // Field safetyRuleArn:Ljava/lang/String;
       4: areturn

  public zio.aws.route53recoverycontrolconfig.model.DeleteSafetyRuleRequest$Wrapper(software.amazon.awssdk.services.route53recoverycontrolconfig.model.DeleteSafetyRuleRequest);
    Code:
       0: aload_0
       1: invokespecial #37                 // Method java/lang/Object."<init>":()V
       4: aload_0
       5: invokestatic  #41                 // InterfaceMethod zio/aws/route53recoverycontrolconfig/model/DeleteSafetyRuleRequest$ReadOnly.$init$:(Lzio/aws/route53recoverycontrolconfig/model/DeleteSafetyRuleRequest$ReadOnly;)V
       8: aload_0
       9: aload_1
      10: invokevirtual #45                 // Method software/amazon/awssdk/services/route53recoverycontrolconfig/model/DeleteSafetyRuleRequest.safetyRuleArn:()Ljava/lang/String;
      13: putfield      #31                 // Field safetyRuleArn:Ljava/lang/String;
      16: return
}
