Compiled from "YarnServiceProtos.java"
public final class org.apache.hadoop.yarn.proto.YarnServiceProtos$UpdateContainerRequestProto$Builder extends com.google.protobuf.GeneratedMessage$Builder<org.apache.hadoop.yarn.proto.YarnServiceProtos$UpdateContainerRequestProto$Builder> implements org.apache.hadoop.yarn.proto.YarnServiceProtos$UpdateContainerRequestProtoOrBuilder {
  private int bitField0_;

  private int containerVersion_;

  private org.apache.hadoop.yarn.proto.YarnProtos$ContainerIdProto containerId_;

  private com.google.protobuf.SingleFieldBuilder<org.apache.hadoop.yarn.proto.YarnProtos$ContainerIdProto, org.apache.hadoop.yarn.proto.YarnProtos$ContainerIdProto$Builder, org.apache.hadoop.yarn.proto.YarnProtos$ContainerIdProtoOrBuilder> containerIdBuilder_;

  private org.apache.hadoop.yarn.proto.YarnServiceProtos$ContainerUpdateTypeProto updateType_;

  private org.apache.hadoop.yarn.proto.YarnProtos$ResourceProto capability_;

  private com.google.protobuf.SingleFieldBuilder<org.apache.hadoop.yarn.proto.YarnProtos$ResourceProto, org.apache.hadoop.yarn.proto.YarnProtos$ResourceProto$Builder, org.apache.hadoop.yarn.proto.YarnProtos$ResourceProtoOrBuilder> capabilityBuilder_;

  private org.apache.hadoop.yarn.proto.YarnProtos$ExecutionTypeProto executionType_;

  public static final com.google.protobuf.Descriptors$Descriptor getDescriptor();
    Code:
       0: invokestatic  #3                  // Method org/apache/hadoop/yarn/proto/YarnServiceProtos.access$5400:()Lcom/google/protobuf/Descriptors$Descriptor;
       3: areturn

  protected com.google.protobuf.GeneratedMessage$FieldAccessorTable internalGetFieldAccessorTable();
    Code:
       0: invokestatic  #4                  // Method org/apache/hadoop/yarn/proto/YarnServiceProtos.access$5500:()Lcom/google/protobuf/GeneratedMessage$FieldAccessorTable;
       3: ldc           #5                  // class org/apache/hadoop/yarn/proto/YarnServiceProtos$UpdateContainerRequestProto
       5: ldc           #6                  // class org/apache/hadoop/yarn/proto/YarnServiceProtos$UpdateContainerRequestProto$Builder
       7: invokevirtual #7                  // Method com/google/protobuf/GeneratedMessage$FieldAccessorTable.ensureFieldAccessorsInitialized:(Ljava/lang/Class;Ljava/lang/Class;)Lcom/google/protobuf/GeneratedMessage$FieldAccessorTable;
      10: areturn

  private org.apache.hadoop.yarn.proto.YarnServiceProtos$UpdateContainerRequestProto$Builder();
    Code:
       0: aload_0
       1: invokespecial #8                  // Method com/google/protobuf/GeneratedMessage$Builder."<init>":()V
       4: aload_0
       5: invokestatic  #9                  // Method org/apache/hadoop/yarn/proto/YarnProtos$ContainerIdProto.getDefaultInstance:()Lorg/apache/hadoop/yarn/proto/YarnProtos$ContainerIdProto;
       8: putfield      #10                 // Field containerId_:Lorg/apache/hadoop/yarn/proto/YarnProtos$ContainerIdProto;
      11: aload_0
      12: getstatic     #11                 // Field org/apache/hadoop/yarn/proto/YarnServiceProtos$ContainerUpdateTypeProto.INCREASE_RESOURCE:Lorg/apache/hadoop/yarn/proto/YarnServiceProtos$ContainerUpdateTypeProto;
      15: putfield      #12                 // Field updateType_:Lorg/apache/hadoop/yarn/proto/YarnServiceProtos$ContainerUpdateTypeProto;
      18: aload_0
      19: invokestatic  #13                 // Method org/apache/hadoop/yarn/proto/YarnProtos$ResourceProto.getDefaultInstance:()Lorg/apache/hadoop/yarn/proto/YarnProtos$ResourceProto;
      22: putfield      #14                 // Field capability_:Lorg/apache/hadoop/yarn/proto/YarnProtos$ResourceProto;
      25: aload_0
      26: getstatic     #15                 // Field org/apache/hadoop/yarn/proto/YarnProtos$ExecutionTypeProto.GUARANTEED:Lorg/apache/hadoop/yarn/proto/YarnProtos$ExecutionTypeProto;
      29: putfield      #16                 // Field executionType_:Lorg/apache/hadoop/yarn/proto/YarnProtos$ExecutionTypeProto;
      32: aload_0
      33: invokespecial #17                 // Method maybeForceBuilderInitialization:()V
      36: return

  private org.apache.hadoop.yarn.proto.YarnServiceProtos$UpdateContainerRequestProto$Builder(com.google.protobuf.GeneratedMessage$BuilderParent);
    Code:
       0: aload_0
       1: aload_1
       2: invokespecial #18                 // Method com/google/protobuf/GeneratedMessage$Builder."<init>":(Lcom/google/protobuf/GeneratedMessage$BuilderParent;)V
       5: aload_0
       6: invokestatic  #9                  // Method org/apache/hadoop/yarn/proto/YarnProtos$ContainerIdProto.getDefaultInstance:()Lorg/apache/hadoop/yarn/proto/YarnProtos$ContainerIdProto;
       9: putfield      #10                 // Field containerId_:Lorg/apache/hadoop/yarn/proto/YarnProtos$ContainerIdProto;
      12: aload_0
      13: getstatic     #11                 // Field org/apache/hadoop/yarn/proto/YarnServiceProtos$ContainerUpdateTypeProto.INCREASE_RESOURCE:Lorg/apache/hadoop/yarn/proto/YarnServiceProtos$ContainerUpdateTypeProto;
      16: putfield      #12                 // Field updateType_:Lorg/apache/hadoop/yarn/proto/YarnServiceProtos$ContainerUpdateTypeProto;
      19: aload_0
      20: invokestatic  #13                 // Method org/apache/hadoop/yarn/proto/YarnProtos$ResourceProto.getDefaultInstance:()Lorg/apache/hadoop/yarn/proto/YarnProtos$ResourceProto;
      23: putfield      #14                 // Field capability_:Lorg/apache/hadoop/yarn/proto/YarnProtos$ResourceProto;
      26: aload_0
      27: getstatic     #15                 // Field org/apache/hadoop/yarn/proto/YarnProtos$ExecutionTypeProto.GUARANTEED:Lorg/apache/hadoop/yarn/proto/YarnProtos$ExecutionTypeProto;
      30: putfield      #16                 // Field executionType_:Lorg/apache/hadoop/yarn/proto/YarnProtos$ExecutionTypeProto;
      33: aload_0
      34: invokespecial #17                 // Method maybeForceBuilderInitialization:()V
      37: return

  private void maybeForceBuilderInitialization();
    Code:
       0: invokestatic  #19                 // Method org/apache/hadoop/yarn/proto/YarnServiceProtos$UpdateContainerRequestProto.access$5900:()Z
       3: ifeq          16
       6: aload_0
       7: invokespecial #20                 // Method getContainerIdFieldBuilder:()Lcom/google/protobuf/SingleFieldBuilder;
      10: pop
      11: aload_0
      12: invokespecial #21                 // Method getCapabilityFieldBuilder:()Lcom/google/protobuf/SingleFieldBuilder;
      15: pop
      16: return

  private static org.apache.hadoop.yarn.proto.YarnServiceProtos$UpdateContainerRequestProto$Builder create();
    Code:
       0: new           #6                  // class org/apache/hadoop/yarn/proto/YarnServiceProtos$UpdateContainerRequestProto$Builder
       3: dup
       4: invokespecial #22                 // Method "<init>":()V
       7: areturn

  public org.apache.hadoop.yarn.proto.YarnServiceProtos$UpdateContainerRequestProto$Builder clear();
    Code:
       0: aload_0
       1: invokespecial #23                 // Method com/google/protobuf/GeneratedMessage$Builder.clear:()Lcom/google/protobuf/GeneratedMessage$Builder;
       4: pop
       5: aload_0
       6: iconst_0
       7: putfield      #24                 // Field containerVersion_:I
      10: aload_0
      11: aload_0
      12: getfield      #25                 // Field bitField0_:I
      15: bipush        -2
      17: iand
      18: putfield      #25                 // Field bitField0_:I
      21: aload_0
      22: getfield      #26                 // Field containerIdBuilder_:Lcom/google/protobuf/SingleFieldBuilder;
      25: ifnonnull     38
      28: aload_0
      29: invokestatic  #9                  // Method org/apache/hadoop/yarn/proto/YarnProtos$ContainerIdProto.getDefaultInstance:()Lorg/apache/hadoop/yarn/proto/YarnProtos$ContainerIdProto;
      32: putfield      #10                 // Field containerId_:Lorg/apache/hadoop/yarn/proto/YarnProtos$ContainerIdProto;
      35: goto          46
      38: aload_0
      39: getfield      #26                 // Field containerIdBuilder_:Lcom/google/protobuf/SingleFieldBuilder;
      42: invokevirtual #27                 // Method com/google/protobuf/SingleFieldBuilder.clear:()Lcom/google/protobuf/SingleFieldBuilder;
      45: pop
      46: aload_0
      47: aload_0
      48: getfield      #25                 // Field bitField0_:I
      51: bipush        -3
      53: iand
      54: putfield      #25                 // Field bitField0_:I
      57: aload_0
      58: getstatic     #11                 // Field org/apache/hadoop/yarn/proto/YarnServiceProtos$ContainerUpdateTypeProto.INCREASE_RESOURCE:Lorg/apache/hadoop/yarn/proto/YarnServiceProtos$ContainerUpdateTypeProto;
      61: putfield      #12                 // Field updateType_:Lorg/apache/hadoop/yarn/proto/YarnServiceProtos$ContainerUpdateTypeProto;
      64: aload_0
      65: aload_0
      66: getfield      #25                 // Field bitField0_:I
      69: bipush        -5
      71: iand
      72: putfield      #25                 // Field bitField0_:I
      75: aload_0
      76: getfield      #28                 // Field capabilityBuilder_:Lcom/google/protobuf/SingleFieldBuilder;
      79: ifnonnull     92
      82: aload_0
      83: invokestatic  #13                 // Method org/apache/hadoop/yarn/proto/YarnProtos$ResourceProto.getDefaultInstance:()Lorg/apache/hadoop/yarn/proto/YarnProtos$ResourceProto;
      86: putfield      #14                 // Field capability_:Lorg/apache/hadoop/yarn/proto/YarnProtos$ResourceProto;
      89: goto          100
      92: aload_0
      93: getfield      #28                 // Field capabilityBuilder_:Lcom/google/protobuf/SingleFieldBuilder;
      96: invokevirtual #27                 // Method com/google/protobuf/SingleFieldBuilder.clear:()Lcom/google/protobuf/SingleFieldBuilder;
      99: pop
     100: aload_0
     101: aload_0
     102: getfield      #25                 // Field bitField0_:I
     105: bipush        -9
     107: iand
     108: putfield      #25                 // Field bitField0_:I
     111: aload_0
     112: getstatic     #15                 // Field org/apache/hadoop/yarn/proto/YarnProtos$ExecutionTypeProto.GUARANTEED:Lorg/apache/hadoop/yarn/proto/YarnProtos$ExecutionTypeProto;
     115: putfield      #16                 // Field executionType_:Lorg/apache/hadoop/yarn/proto/YarnProtos$ExecutionTypeProto;
     118: aload_0
     119: aload_0
     120: getfield      #25                 // Field bitField0_:I
     123: bipush        -17
     125: iand
     126: putfield      #25                 // Field bitField0_:I
     129: aload_0
     130: areturn

  public org.apache.hadoop.yarn.proto.YarnServiceProtos$UpdateContainerRequestProto$Builder clone();
    Code:
       0: invokestatic  #2                  // Method create:()Lorg/apache/hadoop/yarn/proto/YarnServiceProtos$UpdateContainerRequestProto$Builder;
       3: aload_0
       4: invokevirtual #29                 // Method buildPartial:()Lorg/apache/hadoop/yarn/proto/YarnServiceProtos$UpdateContainerRequestProto;
       7: invokevirtual #30                 // Method mergeFrom:(Lorg/apache/hadoop/yarn/proto/YarnServiceProtos$UpdateContainerRequestProto;)Lorg/apache/hadoop/yarn/proto/YarnServiceProtos$UpdateContainerRequestProto$Builder;
      10: areturn

  public com.google.protobuf.Descriptors$Descriptor getDescriptorForType();
    Code:
       0: invokestatic  #3                  // Method org/apache/hadoop/yarn/proto/YarnServiceProtos.access$5400:()Lcom/google/protobuf/Descriptors$Descriptor;
       3: areturn

  public org.apache.hadoop.yarn.proto.YarnServiceProtos$UpdateContainerRequestProto getDefaultInstanceForType();
    Code:
       0: invokestatic  #31                 // Method org/apache/hadoop/yarn/proto/YarnServiceProtos$UpdateContainerRequestProto.getDefaultInstance:()Lorg/apache/hadoop/yarn/proto/YarnServiceProtos$UpdateContainerRequestProto;
       3: areturn

  public org.apache.hadoop.yarn.proto.YarnServiceProtos$UpdateContainerRequestProto build();
    Code:
       0: aload_0
       1: invokevirtual #29                 // Method buildPartial:()Lorg/apache/hadoop/yarn/proto/YarnServiceProtos$UpdateContainerRequestProto;
       4: astore_1
       5: aload_1
       6: invokevirtual #32                 // Method org/apache/hadoop/yarn/proto/YarnServiceProtos$UpdateContainerRequestProto.isInitialized:()Z
       9: ifne          17
      12: aload_1
      13: invokestatic  #33                 // Method newUninitializedMessageException:(Lcom/google/protobuf/Message;)Lcom/google/protobuf/UninitializedMessageException;
      16: athrow
      17: aload_1
      18: areturn

  public org.apache.hadoop.yarn.proto.YarnServiceProtos$UpdateContainerRequestProto buildPartial();
    Code:
       0: new           #5                  // class org/apache/hadoop/yarn/proto/YarnServiceProtos$UpdateContainerRequestProto
       3: dup
       4: aload_0
       5: aconst_null
       6: invokespecial #34                 // Method org/apache/hadoop/yarn/proto/YarnServiceProtos$UpdateContainerRequestProto."<init>":(Lcom/google/protobuf/GeneratedMessage$Builder;Lorg/apache/hadoop/yarn/proto/YarnServiceProtos$1;)V
       9: astore_1
      10: aload_0
      11: getfield      #25                 // Field bitField0_:I
      14: istore_2
      15: iconst_0
      16: istore_3
      17: iload_2
      18: iconst_1
      19: iand
      20: iconst_1
      21: if_icmpne     28
      24: iload_3
      25: iconst_1
      26: ior
      27: istore_3
      28: aload_1
      29: aload_0
      30: getfield      #24                 // Field containerVersion_:I
      33: invokestatic  #35                 // Method org/apache/hadoop/yarn/proto/YarnServiceProtos$UpdateContainerRequestProto.access$6102:(Lorg/apache/hadoop/yarn/proto/YarnServiceProtos$UpdateContainerRequestProto;I)I
      36: pop
      37: iload_2
      38: iconst_2
      39: iand
      40: iconst_2
      41: if_icmpne     48
      44: iload_3
      45: iconst_2
      46: ior
      47: istore_3
      48: aload_0
      49: getfield      #26                 // Field containerIdBuilder_:Lcom/google/protobuf/SingleFieldBuilder;
      52: ifnonnull     67
      55: aload_1
      56: aload_0
      57: getfield      #10                 // Field containerId_:Lorg/apache/hadoop/yarn/proto/YarnProtos$ContainerIdProto;
      60: invokestatic  #36                 // Method org/apache/hadoop/yarn/proto/YarnServiceProtos$UpdateContainerRequestProto.access$6202:(Lorg/apache/hadoop/yarn/proto/YarnServiceProtos$UpdateContainerRequestProto;Lorg/apache/hadoop/yarn/proto/YarnProtos$ContainerIdProto;)Lorg/apache/hadoop/yarn/proto/YarnProtos$ContainerIdProto;
      63: pop
      64: goto          82
      67: aload_1
      68: aload_0
      69: getfield      #26                 // Field containerIdBuilder_:Lcom/google/protobuf/SingleFieldBuilder;
      72: invokevirtual #37                 // Method com/google/protobuf/SingleFieldBuilder.build:()Lcom/google/protobuf/GeneratedMessage;
      75: checkcast     #38                 // class org/apache/hadoop/yarn/proto/YarnProtos$ContainerIdProto
      78: invokestatic  #36                 // Method org/apache/hadoop/yarn/proto/YarnServiceProtos$UpdateContainerRequestProto.access$6202:(Lorg/apache/hadoop/yarn/proto/YarnServiceProtos$UpdateContainerRequestProto;Lorg/apache/hadoop/yarn/proto/YarnProtos$ContainerIdProto;)Lorg/apache/hadoop/yarn/proto/YarnProtos$ContainerIdProto;
      81: pop
      82: iload_2
      83: iconst_4
      84: iand
      85: iconst_4
      86: if_icmpne     93
      89: iload_3
      90: iconst_4
      91: ior
      92: istore_3
      93: aload_1
      94: aload_0
      95: getfield      #12                 // Field updateType_:Lorg/apache/hadoop/yarn/proto/YarnServiceProtos$ContainerUpdateTypeProto;
      98: invokestatic  #39                 // Method org/apache/hadoop/yarn/proto/YarnServiceProtos$UpdateContainerRequestProto.access$6302:(Lorg/apache/hadoop/yarn/proto/YarnServiceProtos$UpdateContainerRequestProto;Lorg/apache/hadoop/yarn/proto/YarnServiceProtos$ContainerUpdateTypeProto;)Lorg/apache/hadoop/yarn/proto/YarnServiceProtos$ContainerUpdateTypeProto;
     101: pop
     102: iload_2
     103: bipush        8
     105: iand
     106: bipush        8
     108: if_icmpne     116
     111: iload_3
     112: bipush        8
     114: ior
     115: istore_3
     116: aload_0
     117: getfield      #28                 // Field capabilityBuilder_:Lcom/google/protobuf/SingleFieldBuilder;
     120: ifnonnull     135
     123: aload_1
     124: aload_0
     125: getfield      #14                 // Field capability_:Lorg/apache/hadoop/yarn/proto/YarnProtos$ResourceProto;
     128: invokestatic  #40                 // Method org/apache/hadoop/yarn/proto/YarnServiceProtos$UpdateContainerRequestProto.access$6402:(Lorg/apache/hadoop/yarn/proto/YarnServiceProtos$UpdateContainerRequestProto;Lorg/apache/hadoop/yarn/proto/YarnProtos$ResourceProto;)Lorg/apache/hadoop/yarn/proto/YarnProtos$ResourceProto;
     131: pop
     132: goto          150
     135: aload_1
     136: aload_0
     137: getfield      #28                 // Field capabilityBuilder_:Lcom/google/protobuf/SingleFieldBuilder;
     140: invokevirtual #37                 // Method com/google/protobuf/SingleFieldBuilder.build:()Lcom/google/protobuf/GeneratedMessage;
     143: checkcast     #41                 // class org/apache/hadoop/yarn/proto/YarnProtos$ResourceProto
     146: invokestatic  #40                 // Method org/apache/hadoop/yarn/proto/YarnServiceProtos$UpdateContainerRequestProto.access$6402:(Lorg/apache/hadoop/yarn/proto/YarnServiceProtos$UpdateContainerRequestProto;Lorg/apache/hadoop/yarn/proto/YarnProtos$ResourceProto;)Lorg/apache/hadoop/yarn/proto/YarnProtos$ResourceProto;
     149: pop
     150: iload_2
     151: bipush        16
     153: iand
     154: bipush        16
     156: if_icmpne     164
     159: iload_3
     160: bipush        16
     162: ior
     163: istore_3
     164: aload_1
     165: aload_0
     166: getfield      #16                 // Field executionType_:Lorg/apache/hadoop/yarn/proto/YarnProtos$ExecutionTypeProto;
     169: invokestatic  #42                 // Method org/apache/hadoop/yarn/proto/YarnServiceProtos$UpdateContainerRequestProto.access$6502:(Lorg/apache/hadoop/yarn/proto/YarnServiceProtos$UpdateContainerRequestProto;Lorg/apache/hadoop/yarn/proto/YarnProtos$ExecutionTypeProto;)Lorg/apache/hadoop/yarn/proto/YarnProtos$ExecutionTypeProto;
     172: pop
     173: aload_1
     174: iload_3
     175: invokestatic  #43                 // Method org/apache/hadoop/yarn/proto/YarnServiceProtos$UpdateContainerRequestProto.access$6602:(Lorg/apache/hadoop/yarn/proto/YarnServiceProtos$UpdateContainerRequestProto;I)I
     178: pop
     179: aload_0
     180: invokevirtual #44                 // Method onBuilt:()V
     183: aload_1
     184: areturn

  public org.apache.hadoop.yarn.proto.YarnServiceProtos$UpdateContainerRequestProto$Builder mergeFrom(com.google.protobuf.Message);
    Code:
       0: aload_1
       1: instanceof    #5                  // class org/apache/hadoop/yarn/proto/YarnServiceProtos$UpdateContainerRequestProto
       4: ifeq          16
       7: aload_0
       8: aload_1
       9: checkcast     #5                  // class org/apache/hadoop/yarn/proto/YarnServiceProtos$UpdateContainerRequestProto
      12: invokevirtual #30                 // Method mergeFrom:(Lorg/apache/hadoop/yarn/proto/YarnServiceProtos$UpdateContainerRequestProto;)Lorg/apache/hadoop/yarn/proto/YarnServiceProtos$UpdateContainerRequestProto$Builder;
      15: areturn
      16: aload_0
      17: aload_1
      18: invokespecial #45                 // Method com/google/protobuf/GeneratedMessage$Builder.mergeFrom:(Lcom/google/protobuf/Message;)Lcom/google/protobuf/AbstractMessage$Builder;
      21: pop
      22: aload_0
      23: areturn

  public org.apache.hadoop.yarn.proto.YarnServiceProtos$UpdateContainerRequestProto$Builder mergeFrom(org.apache.hadoop.yarn.proto.YarnServiceProtos$UpdateContainerRequestProto);
    Code:
       0: aload_1
       1: invokestatic  #31                 // Method org/apache/hadoop/yarn/proto/YarnServiceProtos$UpdateContainerRequestProto.getDefaultInstance:()Lorg/apache/hadoop/yarn/proto/YarnServiceProtos$UpdateContainerRequestProto;
       4: if_acmpne     9
       7: aload_0
       8: areturn
       9: aload_1
      10: invokevirtual #46                 // Method org/apache/hadoop/yarn/proto/YarnServiceProtos$UpdateContainerRequestProto.hasContainerVersion:()Z
      13: ifeq          25
      16: aload_0
      17: aload_1
      18: invokevirtual #47                 // Method org/apache/hadoop/yarn/proto/YarnServiceProtos$UpdateContainerRequestProto.getContainerVersion:()I
      21: invokevirtual #48                 // Method setContainerVersion:(I)Lorg/apache/hadoop/yarn/proto/YarnServiceProtos$UpdateContainerRequestProto$Builder;
      24: pop
      25: aload_1
      26: invokevirtual #49                 // Method org/apache/hadoop/yarn/proto/YarnServiceProtos$UpdateContainerRequestProto.hasContainerId:()Z
      29: ifeq          41
      32: aload_0
      33: aload_1
      34: invokevirtual #50                 // Method org/apache/hadoop/yarn/proto/YarnServiceProtos$UpdateContainerRequestProto.getContainerId:()Lorg/apache/hadoop/yarn/proto/YarnProtos$ContainerIdProto;
      37: invokevirtual #51                 // Method mergeContainerId:(Lorg/apache/hadoop/yarn/proto/YarnProtos$ContainerIdProto;)Lorg/apache/hadoop/yarn/proto/YarnServiceProtos$UpdateContainerRequestProto$Builder;
      40: pop
      41: aload_1
      42: invokevirtual #52                 // Method org/apache/hadoop/yarn/proto/YarnServiceProtos$UpdateContainerRequestProto.hasUpdateType:()Z
      45: ifeq          57
      48: aload_0
      49: aload_1
      50: invokevirtual #53                 // Method org/apache/hadoop/yarn/proto/YarnServiceProtos$UpdateContainerRequestProto.getUpdateType:()Lorg/apache/hadoop/yarn/proto/YarnServiceProtos$ContainerUpdateTypeProto;
      53: invokevirtual #54                 // Method setUpdateType:(Lorg/apache/hadoop/yarn/proto/YarnServiceProtos$ContainerUpdateTypeProto;)Lorg/apache/hadoop/yarn/proto/YarnServiceProtos$UpdateContainerRequestProto$Builder;
      56: pop
      57: aload_1
      58: invokevirtual #55                 // Method org/apache/hadoop/yarn/proto/YarnServiceProtos$UpdateContainerRequestProto.hasCapability:()Z
      61: ifeq          73
      64: aload_0
      65: aload_1
      66: invokevirtual #56                 // Method org/apache/hadoop/yarn/proto/YarnServiceProtos$UpdateContainerRequestProto.getCapability:()Lorg/apache/hadoop/yarn/proto/YarnProtos$ResourceProto;
      69: invokevirtual #57                 // Method mergeCapability:(Lorg/apache/hadoop/yarn/proto/YarnProtos$ResourceProto;)Lorg/apache/hadoop/yarn/proto/YarnServiceProtos$UpdateContainerRequestProto$Builder;
      72: pop
      73: aload_1
      74: invokevirtual #58                 // Method org/apache/hadoop/yarn/proto/YarnServiceProtos$UpdateContainerRequestProto.hasExecutionType:()Z
      77: ifeq          89
      80: aload_0
      81: aload_1
      82: invokevirtual #59                 // Method org/apache/hadoop/yarn/proto/YarnServiceProtos$UpdateContainerRequestProto.getExecutionType:()Lorg/apache/hadoop/yarn/proto/YarnProtos$ExecutionTypeProto;
      85: invokevirtual #60                 // Method setExecutionType:(Lorg/apache/hadoop/yarn/proto/YarnProtos$ExecutionTypeProto;)Lorg/apache/hadoop/yarn/proto/YarnServiceProtos$UpdateContainerRequestProto$Builder;
      88: pop
      89: aload_0
      90: aload_1
      91: invokevirtual #61                 // Method org/apache/hadoop/yarn/proto/YarnServiceProtos$UpdateContainerRequestProto.getUnknownFields:()Lcom/google/protobuf/UnknownFieldSet;
      94: invokevirtual #62                 // Method mergeUnknownFields:(Lcom/google/protobuf/UnknownFieldSet;)Lcom/google/protobuf/GeneratedMessage$Builder;
      97: pop
      98: aload_0
      99: areturn

  public final boolean isInitialized();
    Code:
       0: aload_0
       1: invokevirtual #63                 // Method hasContainerVersion:()Z
       4: ifne          9
       7: iconst_0
       8: ireturn
       9: aload_0
      10: invokevirtual #64                 // Method hasContainerId:()Z
      13: ifne          18
      16: iconst_0
      17: ireturn
      18: aload_0
      19: invokevirtual #65                 // Method hasUpdateType:()Z
      22: ifne          27
      25: iconst_0
      26: ireturn
      27: aload_0
      28: invokevirtual #66                 // Method hasCapability:()Z
      31: ifeq          46
      34: aload_0
      35: invokevirtual #67                 // Method getCapability:()Lorg/apache/hadoop/yarn/proto/YarnProtos$ResourceProto;
      38: invokevirtual #68                 // Method org/apache/hadoop/yarn/proto/YarnProtos$ResourceProto.isInitialized:()Z
      41: ifne          46
      44: iconst_0
      45: ireturn
      46: iconst_1
      47: ireturn

  public org.apache.hadoop.yarn.proto.YarnServiceProtos$UpdateContainerRequestProto$Builder mergeFrom(com.google.protobuf.CodedInputStream, com.google.protobuf.ExtensionRegistryLite) throws java.io.IOException;
    Code:
       0: aconst_null
       1: astore_3
       2: getstatic     #69                 // Field org/apache/hadoop/yarn/proto/YarnServiceProtos$UpdateContainerRequestProto.PARSER:Lcom/google/protobuf/Parser;
       5: aload_1
       6: aload_2
       7: invokeinterface #70,  3           // InterfaceMethod com/google/protobuf/Parser.parsePartialFrom:(Lcom/google/protobuf/CodedInputStream;Lcom/google/protobuf/ExtensionRegistryLite;)Ljava/lang/Object;
      12: checkcast     #5                  // class org/apache/hadoop/yarn/proto/YarnServiceProtos$UpdateContainerRequestProto
      15: astore_3
      16: aload_3
      17: ifnull        58
      20: aload_0
      21: aload_3
      22: invokevirtual #30                 // Method mergeFrom:(Lorg/apache/hadoop/yarn/proto/YarnServiceProtos$UpdateContainerRequestProto;)Lorg/apache/hadoop/yarn/proto/YarnServiceProtos$UpdateContainerRequestProto$Builder;
      25: pop
      26: goto          58
      29: astore        4
      31: aload         4
      33: invokevirtual #72                 // Method com/google/protobuf/InvalidProtocolBufferException.getUnfinishedMessage:()Lcom/google/protobuf/MessageLite;
      36: checkcast     #5                  // class org/apache/hadoop/yarn/proto/YarnServiceProtos$UpdateContainerRequestProto
      39: astore_3
      40: aload         4
      42: athrow
      43: astore        5
      45: aload_3
      46: ifnull        55
      49: aload_0
      50: aload_3
      51: invokevirtual #30                 // Method mergeFrom:(Lorg/apache/hadoop/yarn/proto/YarnServiceProtos$UpdateContainerRequestProto;)Lorg/apache/hadoop/yarn/proto/YarnServiceProtos$UpdateContainerRequestProto$Builder;
      54: pop
      55: aload         5
      57: athrow
      58: aload_0
      59: areturn
    Exception table:
       from    to  target type
           2    16    29   Class com/google/protobuf/InvalidProtocolBufferException
           2    16    43   any
          29    45    43   any

  public boolean hasContainerVersion();
    Code:
       0: aload_0
       1: getfield      #25                 // Field bitField0_:I
       4: iconst_1
       5: iand
       6: iconst_1
       7: if_icmpne     14
      10: iconst_1
      11: goto          15
      14: iconst_0
      15: ireturn

  public int getContainerVersion();
    Code:
       0: aload_0
       1: getfield      #24                 // Field containerVersion_:I
       4: ireturn

  public org.apache.hadoop.yarn.proto.YarnServiceProtos$UpdateContainerRequestProto$Builder setContainerVersion(int);
    Code:
       0: aload_0
       1: dup
       2: getfield      #25                 // Field bitField0_:I
       5: iconst_1
       6: ior
       7: putfield      #25                 // Field bitField0_:I
      10: aload_0
      11: iload_1
      12: putfield      #24                 // Field containerVersion_:I
      15: aload_0
      16: invokevirtual #73                 // Method onChanged:()V
      19: aload_0
      20: areturn

  public org.apache.hadoop.yarn.proto.YarnServiceProtos$UpdateContainerRequestProto$Builder clearContainerVersion();
    Code:
       0: aload_0
       1: aload_0
       2: getfield      #25                 // Field bitField0_:I
       5: bipush        -2
       7: iand
       8: putfield      #25                 // Field bitField0_:I
      11: aload_0
      12: iconst_0
      13: putfield      #24                 // Field containerVersion_:I
      16: aload_0
      17: invokevirtual #73                 // Method onChanged:()V
      20: aload_0
      21: areturn

  public boolean hasContainerId();
    Code:
       0: aload_0
       1: getfield      #25                 // Field bitField0_:I
       4: iconst_2
       5: iand
       6: iconst_2
       7: if_icmpne     14
      10: iconst_1
      11: goto          15
      14: iconst_0
      15: ireturn

  public org.apache.hadoop.yarn.proto.YarnProtos$ContainerIdProto getContainerId();
    Code:
       0: aload_0
       1: getfield      #26                 // Field containerIdBuilder_:Lcom/google/protobuf/SingleFieldBuilder;
       4: ifnonnull     12
       7: aload_0
       8: getfield      #10                 // Field containerId_:Lorg/apache/hadoop/yarn/proto/YarnProtos$ContainerIdProto;
      11: areturn
      12: aload_0
      13: getfield      #26                 // Field containerIdBuilder_:Lcom/google/protobuf/SingleFieldBuilder;
      16: invokevirtual #74                 // Method com/google/protobuf/SingleFieldBuilder.getMessage:()Lcom/google/protobuf/GeneratedMessage;
      19: checkcast     #38                 // class org/apache/hadoop/yarn/proto/YarnProtos$ContainerIdProto
      22: areturn

  public org.apache.hadoop.yarn.proto.YarnServiceProtos$UpdateContainerRequestProto$Builder setContainerId(org.apache.hadoop.yarn.proto.YarnProtos$ContainerIdProto);
    Code:
       0: aload_0
       1: getfield      #26                 // Field containerIdBuilder_:Lcom/google/protobuf/SingleFieldBuilder;
       4: ifnonnull     31
       7: aload_1
       8: ifnonnull     19
      11: new           #75                 // class java/lang/NullPointerException
      14: dup
      15: invokespecial #76                 // Method java/lang/NullPointerException."<init>":()V
      18: athrow
      19: aload_0
      20: aload_1
      21: putfield      #10                 // Field containerId_:Lorg/apache/hadoop/yarn/proto/YarnProtos$ContainerIdProto;
      24: aload_0
      25: invokevirtual #73                 // Method onChanged:()V
      28: goto          40
      31: aload_0
      32: getfield      #26                 // Field containerIdBuilder_:Lcom/google/protobuf/SingleFieldBuilder;
      35: aload_1
      36: invokevirtual #77                 // Method com/google/protobuf/SingleFieldBuilder.setMessage:(Lcom/google/protobuf/GeneratedMessage;)Lcom/google/protobuf/SingleFieldBuilder;
      39: pop
      40: aload_0
      41: dup
      42: getfield      #25                 // Field bitField0_:I
      45: iconst_2
      46: ior
      47: putfield      #25                 // Field bitField0_:I
      50: aload_0
      51: areturn

  public org.apache.hadoop.yarn.proto.YarnServiceProtos$UpdateContainerRequestProto$Builder setContainerId(org.apache.hadoop.yarn.proto.YarnProtos$ContainerIdProto$Builder);
    Code:
       0: aload_0
       1: getfield      #26                 // Field containerIdBuilder_:Lcom/google/protobuf/SingleFieldBuilder;
       4: ifnonnull     22
       7: aload_0
       8: aload_1
       9: invokevirtual #78                 // Method org/apache/hadoop/yarn/proto/YarnProtos$ContainerIdProto$Builder.build:()Lorg/apache/hadoop/yarn/proto/YarnProtos$ContainerIdProto;
      12: putfield      #10                 // Field containerId_:Lorg/apache/hadoop/yarn/proto/YarnProtos$ContainerIdProto;
      15: aload_0
      16: invokevirtual #73                 // Method onChanged:()V
      19: goto          34
      22: aload_0
      23: getfield      #26                 // Field containerIdBuilder_:Lcom/google/protobuf/SingleFieldBuilder;
      26: aload_1
      27: invokevirtual #78                 // Method org/apache/hadoop/yarn/proto/YarnProtos$ContainerIdProto$Builder.build:()Lorg/apache/hadoop/yarn/proto/YarnProtos$ContainerIdProto;
      30: invokevirtual #77                 // Method com/google/protobuf/SingleFieldBuilder.setMessage:(Lcom/google/protobuf/GeneratedMessage;)Lcom/google/protobuf/SingleFieldBuilder;
      33: pop
      34: aload_0
      35: dup
      36: getfield      #25                 // Field bitField0_:I
      39: iconst_2
      40: ior
      41: putfield      #25                 // Field bitField0_:I
      44: aload_0
      45: areturn

  public org.apache.hadoop.yarn.proto.YarnServiceProtos$UpdateContainerRequestProto$Builder mergeContainerId(org.apache.hadoop.yarn.proto.YarnProtos$ContainerIdProto);
    Code:
       0: aload_0
       1: getfield      #26                 // Field containerIdBuilder_:Lcom/google/protobuf/SingleFieldBuilder;
       4: ifnonnull     60
       7: aload_0
       8: getfield      #25                 // Field bitField0_:I
      11: iconst_2
      12: iand
      13: iconst_2
      14: if_icmpne     48
      17: aload_0
      18: getfield      #10                 // Field containerId_:Lorg/apache/hadoop/yarn/proto/YarnProtos$ContainerIdProto;
      21: invokestatic  #9                  // Method org/apache/hadoop/yarn/proto/YarnProtos$ContainerIdProto.getDefaultInstance:()Lorg/apache/hadoop/yarn/proto/YarnProtos$ContainerIdProto;
      24: if_acmpeq     48
      27: aload_0
      28: aload_0
      29: getfield      #10                 // Field containerId_:Lorg/apache/hadoop/yarn/proto/YarnProtos$ContainerIdProto;
      32: invokestatic  #79                 // Method org/apache/hadoop/yarn/proto/YarnProtos$ContainerIdProto.newBuilder:(Lorg/apache/hadoop/yarn/proto/YarnProtos$ContainerIdProto;)Lorg/apache/hadoop/yarn/proto/YarnProtos$ContainerIdProto$Builder;
      35: aload_1
      36: invokevirtual #80                 // Method org/apache/hadoop/yarn/proto/YarnProtos$ContainerIdProto$Builder.mergeFrom:(Lorg/apache/hadoop/yarn/proto/YarnProtos$ContainerIdProto;)Lorg/apache/hadoop/yarn/proto/YarnProtos$ContainerIdProto$Builder;
      39: invokevirtual #81                 // Method org/apache/hadoop/yarn/proto/YarnProtos$ContainerIdProto$Builder.buildPartial:()Lorg/apache/hadoop/yarn/proto/YarnProtos$ContainerIdProto;
      42: putfield      #10                 // Field containerId_:Lorg/apache/hadoop/yarn/proto/YarnProtos$ContainerIdProto;
      45: goto          53
      48: aload_0
      49: aload_1
      50: putfield      #10                 // Field containerId_:Lorg/apache/hadoop/yarn/proto/YarnProtos$ContainerIdProto;
      53: aload_0
      54: invokevirtual #73                 // Method onChanged:()V
      57: goto          69
      60: aload_0
      61: getfield      #26                 // Field containerIdBuilder_:Lcom/google/protobuf/SingleFieldBuilder;
      64: aload_1
      65: invokevirtual #82                 // Method com/google/protobuf/SingleFieldBuilder.mergeFrom:(Lcom/google/protobuf/GeneratedMessage;)Lcom/google/protobuf/SingleFieldBuilder;
      68: pop
      69: aload_0
      70: dup
      71: getfield      #25                 // Field bitField0_:I
      74: iconst_2
      75: ior
      76: putfield      #25                 // Field bitField0_:I
      79: aload_0
      80: areturn

  public org.apache.hadoop.yarn.proto.YarnServiceProtos$UpdateContainerRequestProto$Builder clearContainerId();
    Code:
       0: aload_0
       1: getfield      #26                 // Field containerIdBuilder_:Lcom/google/protobuf/SingleFieldBuilder;
       4: ifnonnull     21
       7: aload_0
       8: invokestatic  #9                  // Method org/apache/hadoop/yarn/proto/YarnProtos$ContainerIdProto.getDefaultInstance:()Lorg/apache/hadoop/yarn/proto/YarnProtos$ContainerIdProto;
      11: putfield      #10                 // Field containerId_:Lorg/apache/hadoop/yarn/proto/YarnProtos$ContainerIdProto;
      14: aload_0
      15: invokevirtual #73                 // Method onChanged:()V
      18: goto          29
      21: aload_0
      22: getfield      #26                 // Field containerIdBuilder_:Lcom/google/protobuf/SingleFieldBuilder;
      25: invokevirtual #27                 // Method com/google/protobuf/SingleFieldBuilder.clear:()Lcom/google/protobuf/SingleFieldBuilder;
      28: pop
      29: aload_0
      30: aload_0
      31: getfield      #25                 // Field bitField0_:I
      34: bipush        -3
      36: iand
      37: putfield      #25                 // Field bitField0_:I
      40: aload_0
      41: areturn

  public org.apache.hadoop.yarn.proto.YarnProtos$ContainerIdProto$Builder getContainerIdBuilder();
    Code:
       0: aload_0
       1: dup
       2: getfield      #25                 // Field bitField0_:I
       5: iconst_2
       6: ior
       7: putfield      #25                 // Field bitField0_:I
      10: aload_0
      11: invokevirtual #73                 // Method onChanged:()V
      14: aload_0
      15: invokespecial #20                 // Method getContainerIdFieldBuilder:()Lcom/google/protobuf/SingleFieldBuilder;
      18: invokevirtual #83                 // Method com/google/protobuf/SingleFieldBuilder.getBuilder:()Lcom/google/protobuf/GeneratedMessage$Builder;
      21: checkcast     #84                 // class org/apache/hadoop/yarn/proto/YarnProtos$ContainerIdProto$Builder
      24: areturn

  public org.apache.hadoop.yarn.proto.YarnProtos$ContainerIdProtoOrBuilder getContainerIdOrBuilder();
    Code:
       0: aload_0
       1: getfield      #26                 // Field containerIdBuilder_:Lcom/google/protobuf/SingleFieldBuilder;
       4: ifnull        18
       7: aload_0
       8: getfield      #26                 // Field containerIdBuilder_:Lcom/google/protobuf/SingleFieldBuilder;
      11: invokevirtual #85                 // Method com/google/protobuf/SingleFieldBuilder.getMessageOrBuilder:()Lcom/google/protobuf/MessageOrBuilder;
      14: checkcast     #86                 // class org/apache/hadoop/yarn/proto/YarnProtos$ContainerIdProtoOrBuilder
      17: areturn
      18: aload_0
      19: getfield      #10                 // Field containerId_:Lorg/apache/hadoop/yarn/proto/YarnProtos$ContainerIdProto;
      22: areturn

  private com.google.protobuf.SingleFieldBuilder<org.apache.hadoop.yarn.proto.YarnProtos$ContainerIdProto, org.apache.hadoop.yarn.proto.YarnProtos$ContainerIdProto$Builder, org.apache.hadoop.yarn.proto.YarnProtos$ContainerIdProtoOrBuilder> getContainerIdFieldBuilder();
    Code:
       0: aload_0
       1: getfield      #26                 // Field containerIdBuilder_:Lcom/google/protobuf/SingleFieldBuilder;
       4: ifnonnull     35
       7: aload_0
       8: new           #87                 // class com/google/protobuf/SingleFieldBuilder
      11: dup
      12: aload_0
      13: getfield      #10                 // Field containerId_:Lorg/apache/hadoop/yarn/proto/YarnProtos$ContainerIdProto;
      16: aload_0
      17: invokevirtual #88                 // Method getParentForChildren:()Lcom/google/protobuf/GeneratedMessage$BuilderParent;
      20: aload_0
      21: invokevirtual #89                 // Method isClean:()Z
      24: invokespecial #90                 // Method com/google/protobuf/SingleFieldBuilder."<init>":(Lcom/google/protobuf/GeneratedMessage;Lcom/google/protobuf/GeneratedMessage$BuilderParent;Z)V
      27: putfield      #26                 // Field containerIdBuilder_:Lcom/google/protobuf/SingleFieldBuilder;
      30: aload_0
      31: aconst_null
      32: putfield      #10                 // Field containerId_:Lorg/apache/hadoop/yarn/proto/YarnProtos$ContainerIdProto;
      35: aload_0
      36: getfield      #26                 // Field containerIdBuilder_:Lcom/google/protobuf/SingleFieldBuilder;
      39: areturn

  public boolean hasUpdateType();
    Code:
       0: aload_0
       1: getfield      #25                 // Field bitField0_:I
       4: iconst_4
       5: iand
       6: iconst_4
       7: if_icmpne     14
      10: iconst_1
      11: goto          15
      14: iconst_0
      15: ireturn

  public org.apache.hadoop.yarn.proto.YarnServiceProtos$ContainerUpdateTypeProto getUpdateType();
    Code:
       0: aload_0
       1: getfield      #12                 // Field updateType_:Lorg/apache/hadoop/yarn/proto/YarnServiceProtos$ContainerUpdateTypeProto;
       4: areturn

  public org.apache.hadoop.yarn.proto.YarnServiceProtos$UpdateContainerRequestProto$Builder setUpdateType(org.apache.hadoop.yarn.proto.YarnServiceProtos$ContainerUpdateTypeProto);
    Code:
       0: aload_1
       1: ifnonnull     12
       4: new           #75                 // class java/lang/NullPointerException
       7: dup
       8: invokespecial #76                 // Method java/lang/NullPointerException."<init>":()V
      11: athrow
      12: aload_0
      13: dup
      14: getfield      #25                 // Field bitField0_:I
      17: iconst_4
      18: ior
      19: putfield      #25                 // Field bitField0_:I
      22: aload_0
      23: aload_1
      24: putfield      #12                 // Field updateType_:Lorg/apache/hadoop/yarn/proto/YarnServiceProtos$ContainerUpdateTypeProto;
      27: aload_0
      28: invokevirtual #73                 // Method onChanged:()V
      31: aload_0
      32: areturn

  public org.apache.hadoop.yarn.proto.YarnServiceProtos$UpdateContainerRequestProto$Builder clearUpdateType();
    Code:
       0: aload_0
       1: aload_0
       2: getfield      #25                 // Field bitField0_:I
       5: bipush        -5
       7: iand
       8: putfield      #25                 // Field bitField0_:I
      11: aload_0
      12: getstatic     #11                 // Field org/apache/hadoop/yarn/proto/YarnServiceProtos$ContainerUpdateTypeProto.INCREASE_RESOURCE:Lorg/apache/hadoop/yarn/proto/YarnServiceProtos$ContainerUpdateTypeProto;
      15: putfield      #12                 // Field updateType_:Lorg/apache/hadoop/yarn/proto/YarnServiceProtos$ContainerUpdateTypeProto;
      18: aload_0
      19: invokevirtual #73                 // Method onChanged:()V
      22: aload_0
      23: areturn

  public boolean hasCapability();
    Code:
       0: aload_0
       1: getfield      #25                 // Field bitField0_:I
       4: bipush        8
       6: iand
       7: bipush        8
       9: if_icmpne     16
      12: iconst_1
      13: goto          17
      16: iconst_0
      17: ireturn

  public org.apache.hadoop.yarn.proto.YarnProtos$ResourceProto getCapability();
    Code:
       0: aload_0
       1: getfield      #28                 // Field capabilityBuilder_:Lcom/google/protobuf/SingleFieldBuilder;
       4: ifnonnull     12
       7: aload_0
       8: getfield      #14                 // Field capability_:Lorg/apache/hadoop/yarn/proto/YarnProtos$ResourceProto;
      11: areturn
      12: aload_0
      13: getfield      #28                 // Field capabilityBuilder_:Lcom/google/protobuf/SingleFieldBuilder;
      16: invokevirtual #74                 // Method com/google/protobuf/SingleFieldBuilder.getMessage:()Lcom/google/protobuf/GeneratedMessage;
      19: checkcast     #41                 // class org/apache/hadoop/yarn/proto/YarnProtos$ResourceProto
      22: areturn

  public org.apache.hadoop.yarn.proto.YarnServiceProtos$UpdateContainerRequestProto$Builder setCapability(org.apache.hadoop.yarn.proto.YarnProtos$ResourceProto);
    Code:
       0: aload_0
       1: getfield      #28                 // Field capabilityBuilder_:Lcom/google/protobuf/SingleFieldBuilder;
       4: ifnonnull     31
       7: aload_1
       8: ifnonnull     19
      11: new           #75                 // class java/lang/NullPointerException
      14: dup
      15: invokespecial #76                 // Method java/lang/NullPointerException."<init>":()V
      18: athrow
      19: aload_0
      20: aload_1
      21: putfield      #14                 // Field capability_:Lorg/apache/hadoop/yarn/proto/YarnProtos$ResourceProto;
      24: aload_0
      25: invokevirtual #73                 // Method onChanged:()V
      28: goto          40
      31: aload_0
      32: getfield      #28                 // Field capabilityBuilder_:Lcom/google/protobuf/SingleFieldBuilder;
      35: aload_1
      36: invokevirtual #77                 // Method com/google/protobuf/SingleFieldBuilder.setMessage:(Lcom/google/protobuf/GeneratedMessage;)Lcom/google/protobuf/SingleFieldBuilder;
      39: pop
      40: aload_0
      41: dup
      42: getfield      #25                 // Field bitField0_:I
      45: bipush        8
      47: ior
      48: putfield      #25                 // Field bitField0_:I
      51: aload_0
      52: areturn

  public org.apache.hadoop.yarn.proto.YarnServiceProtos$UpdateContainerRequestProto$Builder setCapability(org.apache.hadoop.yarn.proto.YarnProtos$ResourceProto$Builder);
    Code:
       0: aload_0
       1: getfield      #28                 // Field capabilityBuilder_:Lcom/google/protobuf/SingleFieldBuilder;
       4: ifnonnull     22
       7: aload_0
       8: aload_1
       9: invokevirtual #91                 // Method org/apache/hadoop/yarn/proto/YarnProtos$ResourceProto$Builder.build:()Lorg/apache/hadoop/yarn/proto/YarnProtos$ResourceProto;
      12: putfield      #14                 // Field capability_:Lorg/apache/hadoop/yarn/proto/YarnProtos$ResourceProto;
      15: aload_0
      16: invokevirtual #73                 // Method onChanged:()V
      19: goto          34
      22: aload_0
      23: getfield      #28                 // Field capabilityBuilder_:Lcom/google/protobuf/SingleFieldBuilder;
      26: aload_1
      27: invokevirtual #91                 // Method org/apache/hadoop/yarn/proto/YarnProtos$ResourceProto$Builder.build:()Lorg/apache/hadoop/yarn/proto/YarnProtos$ResourceProto;
      30: invokevirtual #77                 // Method com/google/protobuf/SingleFieldBuilder.setMessage:(Lcom/google/protobuf/GeneratedMessage;)Lcom/google/protobuf/SingleFieldBuilder;
      33: pop
      34: aload_0
      35: dup
      36: getfield      #25                 // Field bitField0_:I
      39: bipush        8
      41: ior
      42: putfield      #25                 // Field bitField0_:I
      45: aload_0
      46: areturn

  public org.apache.hadoop.yarn.proto.YarnServiceProtos$UpdateContainerRequestProto$Builder mergeCapability(org.apache.hadoop.yarn.proto.YarnProtos$ResourceProto);
    Code:
       0: aload_0
       1: getfield      #28                 // Field capabilityBuilder_:Lcom/google/protobuf/SingleFieldBuilder;
       4: ifnonnull     62
       7: aload_0
       8: getfield      #25                 // Field bitField0_:I
      11: bipush        8
      13: iand
      14: bipush        8
      16: if_icmpne     50
      19: aload_0
      20: getfield      #14                 // Field capability_:Lorg/apache/hadoop/yarn/proto/YarnProtos$ResourceProto;
      23: invokestatic  #13                 // Method org/apache/hadoop/yarn/proto/YarnProtos$ResourceProto.getDefaultInstance:()Lorg/apache/hadoop/yarn/proto/YarnProtos$ResourceProto;
      26: if_acmpeq     50
      29: aload_0
      30: aload_0
      31: getfield      #14                 // Field capability_:Lorg/apache/hadoop/yarn/proto/YarnProtos$ResourceProto;
      34: invokestatic  #92                 // Method org/apache/hadoop/yarn/proto/YarnProtos$ResourceProto.newBuilder:(Lorg/apache/hadoop/yarn/proto/YarnProtos$ResourceProto;)Lorg/apache/hadoop/yarn/proto/YarnProtos$ResourceProto$Builder;
      37: aload_1
      38: invokevirtual #93                 // Method org/apache/hadoop/yarn/proto/YarnProtos$ResourceProto$Builder.mergeFrom:(Lorg/apache/hadoop/yarn/proto/YarnProtos$ResourceProto;)Lorg/apache/hadoop/yarn/proto/YarnProtos$ResourceProto$Builder;
      41: invokevirtual #94                 // Method org/apache/hadoop/yarn/proto/YarnProtos$ResourceProto$Builder.buildPartial:()Lorg/apache/hadoop/yarn/proto/YarnProtos$ResourceProto;
      44: putfield      #14                 // Field capability_:Lorg/apache/hadoop/yarn/proto/YarnProtos$ResourceProto;
      47: goto          55
      50: aload_0
      51: aload_1
      52: putfield      #14                 // Field capability_:Lorg/apache/hadoop/yarn/proto/YarnProtos$ResourceProto;
      55: aload_0
      56: invokevirtual #73                 // Method onChanged:()V
      59: goto          71
      62: aload_0
      63: getfield      #28                 // Field capabilityBuilder_:Lcom/google/protobuf/SingleFieldBuilder;
      66: aload_1
      67: invokevirtual #82                 // Method com/google/protobuf/SingleFieldBuilder.mergeFrom:(Lcom/google/protobuf/GeneratedMessage;)Lcom/google/protobuf/SingleFieldBuilder;
      70: pop
      71: aload_0
      72: dup
      73: getfield      #25                 // Field bitField0_:I
      76: bipush        8
      78: ior
      79: putfield      #25                 // Field bitField0_:I
      82: aload_0
      83: areturn

  public org.apache.hadoop.yarn.proto.YarnServiceProtos$UpdateContainerRequestProto$Builder clearCapability();
    Code:
       0: aload_0
       1: getfield      #28                 // Field capabilityBuilder_:Lcom/google/protobuf/SingleFieldBuilder;
       4: ifnonnull     21
       7: aload_0
       8: invokestatic  #13                 // Method org/apache/hadoop/yarn/proto/YarnProtos$ResourceProto.getDefaultInstance:()Lorg/apache/hadoop/yarn/proto/YarnProtos$ResourceProto;
      11: putfield      #14                 // Field capability_:Lorg/apache/hadoop/yarn/proto/YarnProtos$ResourceProto;
      14: aload_0
      15: invokevirtual #73                 // Method onChanged:()V
      18: goto          29
      21: aload_0
      22: getfield      #28                 // Field capabilityBuilder_:Lcom/google/protobuf/SingleFieldBuilder;
      25: invokevirtual #27                 // Method com/google/protobuf/SingleFieldBuilder.clear:()Lcom/google/protobuf/SingleFieldBuilder;
      28: pop
      29: aload_0
      30: aload_0
      31: getfield      #25                 // Field bitField0_:I
      34: bipush        -9
      36: iand
      37: putfield      #25                 // Field bitField0_:I
      40: aload_0
      41: areturn

  public org.apache.hadoop.yarn.proto.YarnProtos$ResourceProto$Builder getCapabilityBuilder();
    Code:
       0: aload_0
       1: dup
       2: getfield      #25                 // Field bitField0_:I
       5: bipush        8
       7: ior
       8: putfield      #25                 // Field bitField0_:I
      11: aload_0
      12: invokevirtual #73                 // Method onChanged:()V
      15: aload_0
      16: invokespecial #21                 // Method getCapabilityFieldBuilder:()Lcom/google/protobuf/SingleFieldBuilder;
      19: invokevirtual #83                 // Method com/google/protobuf/SingleFieldBuilder.getBuilder:()Lcom/google/protobuf/GeneratedMessage$Builder;
      22: checkcast     #95                 // class org/apache/hadoop/yarn/proto/YarnProtos$ResourceProto$Builder
      25: areturn

  public org.apache.hadoop.yarn.proto.YarnProtos$ResourceProtoOrBuilder getCapabilityOrBuilder();
    Code:
       0: aload_0
       1: getfield      #28                 // Field capabilityBuilder_:Lcom/google/protobuf/SingleFieldBuilder;
       4: ifnull        18
       7: aload_0
       8: getfield      #28                 // Field capabilityBuilder_:Lcom/google/protobuf/SingleFieldBuilder;
      11: invokevirtual #85                 // Method com/google/protobuf/SingleFieldBuilder.getMessageOrBuilder:()Lcom/google/protobuf/MessageOrBuilder;
      14: checkcast     #96                 // class org/apache/hadoop/yarn/proto/YarnProtos$ResourceProtoOrBuilder
      17: areturn
      18: aload_0
      19: getfield      #14                 // Field capability_:Lorg/apache/hadoop/yarn/proto/YarnProtos$ResourceProto;
      22: areturn

  private com.google.protobuf.SingleFieldBuilder<org.apache.hadoop.yarn.proto.YarnProtos$ResourceProto, org.apache.hadoop.yarn.proto.YarnProtos$ResourceProto$Builder, org.apache.hadoop.yarn.proto.YarnProtos$ResourceProtoOrBuilder> getCapabilityFieldBuilder();
    Code:
       0: aload_0
       1: getfield      #28                 // Field capabilityBuilder_:Lcom/google/protobuf/SingleFieldBuilder;
       4: ifnonnull     35
       7: aload_0
       8: new           #87                 // class com/google/protobuf/SingleFieldBuilder
      11: dup
      12: aload_0
      13: getfield      #14                 // Field capability_:Lorg/apache/hadoop/yarn/proto/YarnProtos$ResourceProto;
      16: aload_0
      17: invokevirtual #88                 // Method getParentForChildren:()Lcom/google/protobuf/GeneratedMessage$BuilderParent;
      20: aload_0
      21: invokevirtual #89                 // Method isClean:()Z
      24: invokespecial #90                 // Method com/google/protobuf/SingleFieldBuilder."<init>":(Lcom/google/protobuf/GeneratedMessage;Lcom/google/protobuf/GeneratedMessage$BuilderParent;Z)V
      27: putfield      #28                 // Field capabilityBuilder_:Lcom/google/protobuf/SingleFieldBuilder;
      30: aload_0
      31: aconst_null
      32: putfield      #14                 // Field capability_:Lorg/apache/hadoop/yarn/proto/YarnProtos$ResourceProto;
      35: aload_0
      36: getfield      #28                 // Field capabilityBuilder_:Lcom/google/protobuf/SingleFieldBuilder;
      39: areturn

  public boolean hasExecutionType();
    Code:
       0: aload_0
       1: getfield      #25                 // Field bitField0_:I
       4: bipush        16
       6: iand
       7: bipush        16
       9: if_icmpne     16
      12: iconst_1
      13: goto          17
      16: iconst_0
      17: ireturn

  public org.apache.hadoop.yarn.proto.YarnProtos$ExecutionTypeProto getExecutionType();
    Code:
       0: aload_0
       1: getfield      #16                 // Field executionType_:Lorg/apache/hadoop/yarn/proto/YarnProtos$ExecutionTypeProto;
       4: areturn

  public org.apache.hadoop.yarn.proto.YarnServiceProtos$UpdateContainerRequestProto$Builder setExecutionType(org.apache.hadoop.yarn.proto.YarnProtos$ExecutionTypeProto);
    Code:
       0: aload_1
       1: ifnonnull     12
       4: new           #75                 // class java/lang/NullPointerException
       7: dup
       8: invokespecial #76                 // Method java/lang/NullPointerException."<init>":()V
      11: athrow
      12: aload_0
      13: dup
      14: getfield      #25                 // Field bitField0_:I
      17: bipush        16
      19: ior
      20: putfield      #25                 // Field bitField0_:I
      23: aload_0
      24: aload_1
      25: putfield      #16                 // Field executionType_:Lorg/apache/hadoop/yarn/proto/YarnProtos$ExecutionTypeProto;
      28: aload_0
      29: invokevirtual #73                 // Method onChanged:()V
      32: aload_0
      33: areturn

  public org.apache.hadoop.yarn.proto.YarnServiceProtos$UpdateContainerRequestProto$Builder clearExecutionType();
    Code:
       0: aload_0
       1: aload_0
       2: getfield      #25                 // Field bitField0_:I
       5: bipush        -17
       7: iand
       8: putfield      #25                 // Field bitField0_:I
      11: aload_0
      12: getstatic     #15                 // Field org/apache/hadoop/yarn/proto/YarnProtos$ExecutionTypeProto.GUARANTEED:Lorg/apache/hadoop/yarn/proto/YarnProtos$ExecutionTypeProto;
      15: putfield      #16                 // Field executionType_:Lorg/apache/hadoop/yarn/proto/YarnProtos$ExecutionTypeProto;
      18: aload_0
      19: invokevirtual #73                 // Method onChanged:()V
      22: aload_0
      23: areturn

  public com.google.protobuf.GeneratedMessage$Builder clear();
    Code:
       0: aload_0
       1: invokevirtual #97                 // Method clear:()Lorg/apache/hadoop/yarn/proto/YarnServiceProtos$UpdateContainerRequestProto$Builder;
       4: areturn

  public com.google.protobuf.GeneratedMessage$Builder clone();
    Code:
       0: aload_0
       1: invokevirtual #98                 // Method clone:()Lorg/apache/hadoop/yarn/proto/YarnServiceProtos$UpdateContainerRequestProto$Builder;
       4: areturn

  public com.google.protobuf.AbstractMessage$Builder mergeFrom(com.google.protobuf.CodedInputStream, com.google.protobuf.ExtensionRegistryLite) throws java.io.IOException;
    Code:
       0: aload_0
       1: aload_1
       2: aload_2
       3: invokevirtual #99                 // Method mergeFrom:(Lcom/google/protobuf/CodedInputStream;Lcom/google/protobuf/ExtensionRegistryLite;)Lorg/apache/hadoop/yarn/proto/YarnServiceProtos$UpdateContainerRequestProto$Builder;
       6: areturn

  public com.google.protobuf.AbstractMessage$Builder mergeFrom(com.google.protobuf.Message);
    Code:
       0: aload_0
       1: aload_1
       2: invokevirtual #100                // Method mergeFrom:(Lcom/google/protobuf/Message;)Lorg/apache/hadoop/yarn/proto/YarnServiceProtos$UpdateContainerRequestProto$Builder;
       5: areturn

  public com.google.protobuf.AbstractMessage$Builder clear();
    Code:
       0: aload_0
       1: invokevirtual #97                 // Method clear:()Lorg/apache/hadoop/yarn/proto/YarnServiceProtos$UpdateContainerRequestProto$Builder;
       4: areturn

  public com.google.protobuf.AbstractMessage$Builder clone();
    Code:
       0: aload_0
       1: invokevirtual #98                 // Method clone:()Lorg/apache/hadoop/yarn/proto/YarnServiceProtos$UpdateContainerRequestProto$Builder;
       4: areturn

  public com.google.protobuf.Message$Builder mergeFrom(com.google.protobuf.CodedInputStream, com.google.protobuf.ExtensionRegistryLite) throws java.io.IOException;
    Code:
       0: aload_0
       1: aload_1
       2: aload_2
       3: invokevirtual #99                 // Method mergeFrom:(Lcom/google/protobuf/CodedInputStream;Lcom/google/protobuf/ExtensionRegistryLite;)Lorg/apache/hadoop/yarn/proto/YarnServiceProtos$UpdateContainerRequestProto$Builder;
       6: areturn

  public com.google.protobuf.Message$Builder clone();
    Code:
       0: aload_0
       1: invokevirtual #98                 // Method clone:()Lorg/apache/hadoop/yarn/proto/YarnServiceProtos$UpdateContainerRequestProto$Builder;
       4: areturn

  public com.google.protobuf.Message buildPartial();
    Code:
       0: aload_0
       1: invokevirtual #29                 // Method buildPartial:()Lorg/apache/hadoop/yarn/proto/YarnServiceProtos$UpdateContainerRequestProto;
       4: areturn

  public com.google.protobuf.Message build();
    Code:
       0: aload_0
       1: invokevirtual #101                // Method build:()Lorg/apache/hadoop/yarn/proto/YarnServiceProtos$UpdateContainerRequestProto;
       4: areturn

  public com.google.protobuf.Message$Builder mergeFrom(com.google.protobuf.Message);
    Code:
       0: aload_0
       1: aload_1
       2: invokevirtual #100                // Method mergeFrom:(Lcom/google/protobuf/Message;)Lorg/apache/hadoop/yarn/proto/YarnServiceProtos$UpdateContainerRequestProto$Builder;
       5: areturn

  public com.google.protobuf.Message$Builder clear();
    Code:
       0: aload_0
       1: invokevirtual #97                 // Method clear:()Lorg/apache/hadoop/yarn/proto/YarnServiceProtos$UpdateContainerRequestProto$Builder;
       4: areturn

  public com.google.protobuf.MessageLite$Builder mergeFrom(com.google.protobuf.CodedInputStream, com.google.protobuf.ExtensionRegistryLite) throws java.io.IOException;
    Code:
       0: aload_0
       1: aload_1
       2: aload_2
       3: invokevirtual #99                 // Method mergeFrom:(Lcom/google/protobuf/CodedInputStream;Lcom/google/protobuf/ExtensionRegistryLite;)Lorg/apache/hadoop/yarn/proto/YarnServiceProtos$UpdateContainerRequestProto$Builder;
       6: areturn

  public com.google.protobuf.MessageLite$Builder clone();
    Code:
       0: aload_0
       1: invokevirtual #98                 // Method clone:()Lorg/apache/hadoop/yarn/proto/YarnServiceProtos$UpdateContainerRequestProto$Builder;
       4: areturn

  public com.google.protobuf.MessageLite buildPartial();
    Code:
       0: aload_0
       1: invokevirtual #29                 // Method buildPartial:()Lorg/apache/hadoop/yarn/proto/YarnServiceProtos$UpdateContainerRequestProto;
       4: areturn

  public com.google.protobuf.MessageLite build();
    Code:
       0: aload_0
       1: invokevirtual #101                // Method build:()Lorg/apache/hadoop/yarn/proto/YarnServiceProtos$UpdateContainerRequestProto;
       4: areturn

  public com.google.protobuf.MessageLite$Builder clear();
    Code:
       0: aload_0
       1: invokevirtual #97                 // Method clear:()Lorg/apache/hadoop/yarn/proto/YarnServiceProtos$UpdateContainerRequestProto$Builder;
       4: areturn

  public com.google.protobuf.MessageLite getDefaultInstanceForType();
    Code:
       0: aload_0
       1: invokevirtual #102                // Method getDefaultInstanceForType:()Lorg/apache/hadoop/yarn/proto/YarnServiceProtos$UpdateContainerRequestProto;
       4: areturn

  public com.google.protobuf.Message getDefaultInstanceForType();
    Code:
       0: aload_0
       1: invokevirtual #102                // Method getDefaultInstanceForType:()Lorg/apache/hadoop/yarn/proto/YarnServiceProtos$UpdateContainerRequestProto;
       4: areturn

  public com.google.protobuf.AbstractMessageLite$Builder mergeFrom(com.google.protobuf.CodedInputStream, com.google.protobuf.ExtensionRegistryLite) throws java.io.IOException;
    Code:
       0: aload_0
       1: aload_1
       2: aload_2
       3: invokevirtual #99                 // Method mergeFrom:(Lcom/google/protobuf/CodedInputStream;Lcom/google/protobuf/ExtensionRegistryLite;)Lorg/apache/hadoop/yarn/proto/YarnServiceProtos$UpdateContainerRequestProto$Builder;
       6: areturn

  public com.google.protobuf.AbstractMessageLite$Builder clone();
    Code:
       0: aload_0
       1: invokevirtual #98                 // Method clone:()Lorg/apache/hadoop/yarn/proto/YarnServiceProtos$UpdateContainerRequestProto$Builder;
       4: areturn

  public java.lang.Object clone() throws java.lang.CloneNotSupportedException;
    Code:
       0: aload_0
       1: invokevirtual #98                 // Method clone:()Lorg/apache/hadoop/yarn/proto/YarnServiceProtos$UpdateContainerRequestProto$Builder;
       4: areturn

  static org.apache.hadoop.yarn.proto.YarnServiceProtos$UpdateContainerRequestProto$Builder access$5700();
    Code:
       0: invokestatic  #2                  // Method create:()Lorg/apache/hadoop/yarn/proto/YarnServiceProtos$UpdateContainerRequestProto$Builder;
       3: areturn

  org.apache.hadoop.yarn.proto.YarnServiceProtos$UpdateContainerRequestProto$Builder(com.google.protobuf.GeneratedMessage$BuilderParent, org.apache.hadoop.yarn.proto.YarnServiceProtos$1);
    Code:
       0: aload_0
       1: aload_1
       2: invokespecial #1                  // Method "<init>":(Lcom/google/protobuf/GeneratedMessage$BuilderParent;)V
       5: return
}
