Compiled from "YarnProtos.java"
public final class org.apache.hadoop.yarn.proto.YarnProtos$NodeReportProto extends com.google.protobuf.GeneratedMessage implements org.apache.hadoop.yarn.proto.YarnProtos$NodeReportProtoOrBuilder {
  private static final org.apache.hadoop.yarn.proto.YarnProtos$NodeReportProto defaultInstance;

  private final com.google.protobuf.UnknownFieldSet unknownFields;

  public static com.google.protobuf.Parser<org.apache.hadoop.yarn.proto.YarnProtos$NodeReportProto> PARSER;

  private int bitField0_;

  public static final int NODEID_FIELD_NUMBER;

  private org.apache.hadoop.yarn.proto.YarnProtos$NodeIdProto nodeId_;

  public static final int HTTPADDRESS_FIELD_NUMBER;

  private java.lang.Object httpAddress_;

  public static final int RACKNAME_FIELD_NUMBER;

  private java.lang.Object rackName_;

  public static final int USED_FIELD_NUMBER;

  private org.apache.hadoop.yarn.proto.YarnProtos$ResourceProto used_;

  public static final int CAPABILITY_FIELD_NUMBER;

  private org.apache.hadoop.yarn.proto.YarnProtos$ResourceProto capability_;

  public static final int NUMCONTAINERS_FIELD_NUMBER;

  private int numContainers_;

  public static final int NODE_STATE_FIELD_NUMBER;

  private org.apache.hadoop.yarn.proto.YarnProtos$NodeStateProto nodeState_;

  public static final int HEALTH_REPORT_FIELD_NUMBER;

  private java.lang.Object healthReport_;

  public static final int LAST_HEALTH_REPORT_TIME_FIELD_NUMBER;

  private long lastHealthReportTime_;

  public static final int NODE_LABELS_FIELD_NUMBER;

  private com.google.protobuf.LazyStringList nodeLabels_;

  public static final int CONTAINERS_UTILIZATION_FIELD_NUMBER;

  private org.apache.hadoop.yarn.proto.YarnProtos$ResourceUtilizationProto containersUtilization_;

  public static final int NODE_UTILIZATION_FIELD_NUMBER;

  private org.apache.hadoop.yarn.proto.YarnProtos$ResourceUtilizationProto nodeUtilization_;

  public static final int DECOMMISSIONING_TIMEOUT_FIELD_NUMBER;

  private int decommissioningTimeout_;

  public static final int NODE_UPDATE_TYPE_FIELD_NUMBER;

  private org.apache.hadoop.yarn.proto.YarnProtos$NodeUpdateTypeProto nodeUpdateType_;

  public static final int NODE_ATTRIBUTES_FIELD_NUMBER;

  private java.util.List<org.apache.hadoop.yarn.proto.YarnProtos$NodeAttributeProto> nodeAttributes_;

  private byte memoizedIsInitialized;

  private int memoizedSerializedSize;

  private static final long serialVersionUID;

  private int memoizedHashCode;

  private org.apache.hadoop.yarn.proto.YarnProtos$NodeReportProto(com.google.protobuf.GeneratedMessage$Builder<?>);
    Code:
       0: aload_0
       1: aload_1
       2: invokespecial #20                 // Method com/google/protobuf/GeneratedMessage."<init>":(Lcom/google/protobuf/GeneratedMessage$Builder;)V
       5: aload_0
       6: iconst_m1
       7: putfield      #21                 // Field memoizedIsInitialized:B
      10: aload_0
      11: iconst_m1
      12: putfield      #22                 // Field memoizedSerializedSize:I
      15: aload_0
      16: iconst_0
      17: putfield      #23                 // Field memoizedHashCode:I
      20: aload_0
      21: aload_1
      22: invokevirtual #24                 // Method com/google/protobuf/GeneratedMessage$Builder.getUnknownFields:()Lcom/google/protobuf/UnknownFieldSet;
      25: putfield      #25                 // Field unknownFields:Lcom/google/protobuf/UnknownFieldSet;
      28: return

  private org.apache.hadoop.yarn.proto.YarnProtos$NodeReportProto(boolean);
    Code:
       0: aload_0
       1: invokespecial #26                 // Method com/google/protobuf/GeneratedMessage."<init>":()V
       4: aload_0
       5: iconst_m1
       6: putfield      #21                 // Field memoizedIsInitialized:B
       9: aload_0
      10: iconst_m1
      11: putfield      #22                 // Field memoizedSerializedSize:I
      14: aload_0
      15: iconst_0
      16: putfield      #23                 // Field memoizedHashCode:I
      19: aload_0
      20: invokestatic  #27                 // Method com/google/protobuf/UnknownFieldSet.getDefaultInstance:()Lcom/google/protobuf/UnknownFieldSet;
      23: putfield      #25                 // Field unknownFields:Lcom/google/protobuf/UnknownFieldSet;
      26: return

  public static org.apache.hadoop.yarn.proto.YarnProtos$NodeReportProto getDefaultInstance();
    Code:
       0: getstatic     #28                 // Field defaultInstance:Lorg/apache/hadoop/yarn/proto/YarnProtos$NodeReportProto;
       3: areturn

  public org.apache.hadoop.yarn.proto.YarnProtos$NodeReportProto getDefaultInstanceForType();
    Code:
       0: getstatic     #28                 // Field defaultInstance:Lorg/apache/hadoop/yarn/proto/YarnProtos$NodeReportProto;
       3: areturn

  public final com.google.protobuf.UnknownFieldSet getUnknownFields();
    Code:
       0: aload_0
       1: getfield      #25                 // Field unknownFields:Lcom/google/protobuf/UnknownFieldSet;
       4: areturn

  private org.apache.hadoop.yarn.proto.YarnProtos$NodeReportProto(com.google.protobuf.CodedInputStream, com.google.protobuf.ExtensionRegistryLite) throws com.google.protobuf.InvalidProtocolBufferException;
    Code:
       0: aload_0
       1: invokespecial #26                 // Method com/google/protobuf/GeneratedMessage."<init>":()V
       4: aload_0
       5: iconst_m1
       6: putfield      #21                 // Field memoizedIsInitialized:B
       9: aload_0
      10: iconst_m1
      11: putfield      #22                 // Field memoizedSerializedSize:I
      14: aload_0
      15: iconst_0
      16: putfield      #23                 // Field memoizedHashCode:I
      19: aload_0
      20: invokespecial #29                 // Method initFields:()V
      23: iconst_0
      24: istore_3
      25: invokestatic  #30                 // Method com/google/protobuf/UnknownFieldSet.newBuilder:()Lcom/google/protobuf/UnknownFieldSet$Builder;
      28: astore        4
      30: iconst_0
      31: istore        5
      33: iload         5
      35: ifne          926
      38: aload_1
      39: invokevirtual #31                 // Method com/google/protobuf/CodedInputStream.readTag:()I
      42: istore        6
      44: iload         6
      46: lookupswitch  { // 16
                     0: 184
                    10: 209
                    18: 283
                    26: 304
                    34: 325
                    42: 402
                    48: 479
                    56: 501
                    66: 552
                    72: 575
                    82: 598
                    90: 642
                    98: 722
                   104: 802
                   112: 825
                   122: 877
               default: 190
          }
     184: iconst_1
     185: istore        5
     187: goto          923
     190: aload_0
     191: aload_1
     192: aload         4
     194: aload_2
     195: iload         6
     197: invokevirtual #32                 // Method parseUnknownField:(Lcom/google/protobuf/CodedInputStream;Lcom/google/protobuf/UnknownFieldSet$Builder;Lcom/google/protobuf/ExtensionRegistryLite;I)Z
     200: ifne          923
     203: iconst_1
     204: istore        5
     206: goto          923
     209: aconst_null
     210: astore        7
     212: aload_0
     213: getfield      #2                  // Field bitField0_:I
     216: iconst_1
     217: iand
     218: iconst_1
     219: if_icmpne     231
     222: aload_0
     223: getfield      #17                 // Field nodeId_:Lorg/apache/hadoop/yarn/proto/YarnProtos$NodeIdProto;
     226: invokevirtual #33                 // Method org/apache/hadoop/yarn/proto/YarnProtos$NodeIdProto.toBuilder:()Lorg/apache/hadoop/yarn/proto/YarnProtos$NodeIdProto$Builder;
     229: astore        7
     231: aload_0
     232: aload_1
     233: getstatic     #34                 // Field org/apache/hadoop/yarn/proto/YarnProtos$NodeIdProto.PARSER:Lcom/google/protobuf/Parser;
     236: aload_2
     237: invokevirtual #35                 // Method com/google/protobuf/CodedInputStream.readMessage:(Lcom/google/protobuf/Parser;Lcom/google/protobuf/ExtensionRegistryLite;)Lcom/google/protobuf/MessageLite;
     240: checkcast     #36                 // class org/apache/hadoop/yarn/proto/YarnProtos$NodeIdProto
     243: putfield      #17                 // Field nodeId_:Lorg/apache/hadoop/yarn/proto/YarnProtos$NodeIdProto;
     246: aload         7
     248: ifnull        270
     251: aload         7
     253: aload_0
     254: getfield      #17                 // Field nodeId_:Lorg/apache/hadoop/yarn/proto/YarnProtos$NodeIdProto;
     257: invokevirtual #37                 // Method org/apache/hadoop/yarn/proto/YarnProtos$NodeIdProto$Builder.mergeFrom:(Lorg/apache/hadoop/yarn/proto/YarnProtos$NodeIdProto;)Lorg/apache/hadoop/yarn/proto/YarnProtos$NodeIdProto$Builder;
     260: pop
     261: aload_0
     262: aload         7
     264: invokevirtual #38                 // Method org/apache/hadoop/yarn/proto/YarnProtos$NodeIdProto$Builder.buildPartial:()Lorg/apache/hadoop/yarn/proto/YarnProtos$NodeIdProto;
     267: putfield      #17                 // Field nodeId_:Lorg/apache/hadoop/yarn/proto/YarnProtos$NodeIdProto;
     270: aload_0
     271: dup
     272: getfield      #2                  // Field bitField0_:I
     275: iconst_1
     276: ior
     277: putfield      #2                  // Field bitField0_:I
     280: goto          923
     283: aload_0
     284: dup
     285: getfield      #2                  // Field bitField0_:I
     288: iconst_2
     289: ior
     290: putfield      #2                  // Field bitField0_:I
     293: aload_0
     294: aload_1
     295: invokevirtual #39                 // Method com/google/protobuf/CodedInputStream.readBytes:()Lcom/google/protobuf/ByteString;
     298: putfield      #16                 // Field httpAddress_:Ljava/lang/Object;
     301: goto          923
     304: aload_0
     305: dup
     306: getfield      #2                  // Field bitField0_:I
     309: iconst_4
     310: ior
     311: putfield      #2                  // Field bitField0_:I
     314: aload_0
     315: aload_1
     316: invokevirtual #39                 // Method com/google/protobuf/CodedInputStream.readBytes:()Lcom/google/protobuf/ByteString;
     319: putfield      #15                 // Field rackName_:Ljava/lang/Object;
     322: goto          923
     325: aconst_null
     326: astore        7
     328: aload_0
     329: getfield      #2                  // Field bitField0_:I
     332: bipush        8
     334: iand
     335: bipush        8
     337: if_icmpne     349
     340: aload_0
     341: getfield      #14                 // Field used_:Lorg/apache/hadoop/yarn/proto/YarnProtos$ResourceProto;
     344: invokevirtual #40                 // Method org/apache/hadoop/yarn/proto/YarnProtos$ResourceProto.toBuilder:()Lorg/apache/hadoop/yarn/proto/YarnProtos$ResourceProto$Builder;
     347: astore        7
     349: aload_0
     350: aload_1
     351: getstatic     #41                 // Field org/apache/hadoop/yarn/proto/YarnProtos$ResourceProto.PARSER:Lcom/google/protobuf/Parser;
     354: aload_2
     355: invokevirtual #35                 // Method com/google/protobuf/CodedInputStream.readMessage:(Lcom/google/protobuf/Parser;Lcom/google/protobuf/ExtensionRegistryLite;)Lcom/google/protobuf/MessageLite;
     358: checkcast     #42                 // class org/apache/hadoop/yarn/proto/YarnProtos$ResourceProto
     361: putfield      #14                 // Field used_:Lorg/apache/hadoop/yarn/proto/YarnProtos$ResourceProto;
     364: aload         7
     366: ifnull        388
     369: aload         7
     371: aload_0
     372: getfield      #14                 // Field used_:Lorg/apache/hadoop/yarn/proto/YarnProtos$ResourceProto;
     375: invokevirtual #43                 // Method org/apache/hadoop/yarn/proto/YarnProtos$ResourceProto$Builder.mergeFrom:(Lorg/apache/hadoop/yarn/proto/YarnProtos$ResourceProto;)Lorg/apache/hadoop/yarn/proto/YarnProtos$ResourceProto$Builder;
     378: pop
     379: aload_0
     380: aload         7
     382: invokevirtual #44                 // Method org/apache/hadoop/yarn/proto/YarnProtos$ResourceProto$Builder.buildPartial:()Lorg/apache/hadoop/yarn/proto/YarnProtos$ResourceProto;
     385: putfield      #14                 // Field used_:Lorg/apache/hadoop/yarn/proto/YarnProtos$ResourceProto;
     388: aload_0
     389: dup
     390: getfield      #2                  // Field bitField0_:I
     393: bipush        8
     395: ior
     396: putfield      #2                  // Field bitField0_:I
     399: goto          923
     402: aconst_null
     403: astore        7
     405: aload_0
     406: getfield      #2                  // Field bitField0_:I
     409: bipush        16
     411: iand
     412: bipush        16
     414: if_icmpne     426
     417: aload_0
     418: getfield      #13                 // Field capability_:Lorg/apache/hadoop/yarn/proto/YarnProtos$ResourceProto;
     421: invokevirtual #40                 // Method org/apache/hadoop/yarn/proto/YarnProtos$ResourceProto.toBuilder:()Lorg/apache/hadoop/yarn/proto/YarnProtos$ResourceProto$Builder;
     424: astore        7
     426: aload_0
     427: aload_1
     428: getstatic     #41                 // Field org/apache/hadoop/yarn/proto/YarnProtos$ResourceProto.PARSER:Lcom/google/protobuf/Parser;
     431: aload_2
     432: invokevirtual #35                 // Method com/google/protobuf/CodedInputStream.readMessage:(Lcom/google/protobuf/Parser;Lcom/google/protobuf/ExtensionRegistryLite;)Lcom/google/protobuf/MessageLite;
     435: checkcast     #42                 // class org/apache/hadoop/yarn/proto/YarnProtos$ResourceProto
     438: putfield      #13                 // Field capability_:Lorg/apache/hadoop/yarn/proto/YarnProtos$ResourceProto;
     441: aload         7
     443: ifnull        465
     446: aload         7
     448: aload_0
     449: getfield      #13                 // Field capability_:Lorg/apache/hadoop/yarn/proto/YarnProtos$ResourceProto;
     452: invokevirtual #43                 // Method org/apache/hadoop/yarn/proto/YarnProtos$ResourceProto$Builder.mergeFrom:(Lorg/apache/hadoop/yarn/proto/YarnProtos$ResourceProto;)Lorg/apache/hadoop/yarn/proto/YarnProtos$ResourceProto$Builder;
     455: pop
     456: aload_0
     457: aload         7
     459: invokevirtual #44                 // Method org/apache/hadoop/yarn/proto/YarnProtos$ResourceProto$Builder.buildPartial:()Lorg/apache/hadoop/yarn/proto/YarnProtos$ResourceProto;
     462: putfield      #13                 // Field capability_:Lorg/apache/hadoop/yarn/proto/YarnProtos$ResourceProto;
     465: aload_0
     466: dup
     467: getfield      #2                  // Field bitField0_:I
     470: bipush        16
     472: ior
     473: putfield      #2                  // Field bitField0_:I
     476: goto          923
     479: aload_0
     480: dup
     481: getfield      #2                  // Field bitField0_:I
     484: bipush        32
     486: ior
     487: putfield      #2                  // Field bitField0_:I
     490: aload_0
     491: aload_1
     492: invokevirtual #45                 // Method com/google/protobuf/CodedInputStream.readInt32:()I
     495: putfield      #12                 // Field numContainers_:I
     498: goto          923
     501: aload_1
     502: invokevirtual #46                 // Method com/google/protobuf/CodedInputStream.readEnum:()I
     505: istore        7
     507: iload         7
     509: invokestatic  #47                 // Method org/apache/hadoop/yarn/proto/YarnProtos$NodeStateProto.valueOf:(I)Lorg/apache/hadoop/yarn/proto/YarnProtos$NodeStateProto;
     512: astore        8
     514: aload         8
     516: ifnonnull     532
     519: aload         4
     521: bipush        7
     523: iload         7
     525: invokevirtual #48                 // Method com/google/protobuf/UnknownFieldSet$Builder.mergeVarintField:(II)Lcom/google/protobuf/UnknownFieldSet$Builder;
     528: pop
     529: goto          923
     532: aload_0
     533: dup
     534: getfield      #2                  // Field bitField0_:I
     537: bipush        64
     539: ior
     540: putfield      #2                  // Field bitField0_:I
     543: aload_0
     544: aload         8
     546: putfield      #11                 // Field nodeState_:Lorg/apache/hadoop/yarn/proto/YarnProtos$NodeStateProto;
     549: goto          923
     552: aload_0
     553: dup
     554: getfield      #2                  // Field bitField0_:I
     557: sipush        128
     560: ior
     561: putfield      #2                  // Field bitField0_:I
     564: aload_0
     565: aload_1
     566: invokevirtual #39                 // Method com/google/protobuf/CodedInputStream.readBytes:()Lcom/google/protobuf/ByteString;
     569: putfield      #10                 // Field healthReport_:Ljava/lang/Object;
     572: goto          923
     575: aload_0
     576: dup
     577: getfield      #2                  // Field bitField0_:I
     580: sipush        256
     583: ior
     584: putfield      #2                  // Field bitField0_:I
     587: aload_0
     588: aload_1
     589: invokevirtual #49                 // Method com/google/protobuf/CodedInputStream.readInt64:()J
     592: putfield      #9                  // Field lastHealthReportTime_:J
     595: goto          923
     598: iload_3
     599: sipush        512
     602: iand
     603: sipush        512
     606: if_icmpeq     626
     609: aload_0
     610: new           #50                 // class com/google/protobuf/LazyStringArrayList
     613: dup
     614: invokespecial #51                 // Method com/google/protobuf/LazyStringArrayList."<init>":()V
     617: putfield      #8                  // Field nodeLabels_:Lcom/google/protobuf/LazyStringList;
     620: iload_3
     621: sipush        512
     624: ior
     625: istore_3
     626: aload_0
     627: getfield      #8                  // Field nodeLabels_:Lcom/google/protobuf/LazyStringList;
     630: aload_1
     631: invokevirtual #39                 // Method com/google/protobuf/CodedInputStream.readBytes:()Lcom/google/protobuf/ByteString;
     634: invokeinterface #52,  2           // InterfaceMethod com/google/protobuf/LazyStringList.add:(Lcom/google/protobuf/ByteString;)V
     639: goto          923
     642: aconst_null
     643: astore        7
     645: aload_0
     646: getfield      #2                  // Field bitField0_:I
     649: sipush        512
     652: iand
     653: sipush        512
     656: if_icmpne     668
     659: aload_0
     660: getfield      #7                  // Field containersUtilization_:Lorg/apache/hadoop/yarn/proto/YarnProtos$ResourceUtilizationProto;
     663: invokevirtual #53                 // Method org/apache/hadoop/yarn/proto/YarnProtos$ResourceUtilizationProto.toBuilder:()Lorg/apache/hadoop/yarn/proto/YarnProtos$ResourceUtilizationProto$Builder;
     666: astore        7
     668: aload_0
     669: aload_1
     670: getstatic     #54                 // Field org/apache/hadoop/yarn/proto/YarnProtos$ResourceUtilizationProto.PARSER:Lcom/google/protobuf/Parser;
     673: aload_2
     674: invokevirtual #35                 // Method com/google/protobuf/CodedInputStream.readMessage:(Lcom/google/protobuf/Parser;Lcom/google/protobuf/ExtensionRegistryLite;)Lcom/google/protobuf/MessageLite;
     677: checkcast     #55                 // class org/apache/hadoop/yarn/proto/YarnProtos$ResourceUtilizationProto
     680: putfield      #7                  // Field containersUtilization_:Lorg/apache/hadoop/yarn/proto/YarnProtos$ResourceUtilizationProto;
     683: aload         7
     685: ifnull        707
     688: aload         7
     690: aload_0
     691: getfield      #7                  // Field containersUtilization_:Lorg/apache/hadoop/yarn/proto/YarnProtos$ResourceUtilizationProto;
     694: invokevirtual #56                 // Method org/apache/hadoop/yarn/proto/YarnProtos$ResourceUtilizationProto$Builder.mergeFrom:(Lorg/apache/hadoop/yarn/proto/YarnProtos$ResourceUtilizationProto;)Lorg/apache/hadoop/yarn/proto/YarnProtos$ResourceUtilizationProto$Builder;
     697: pop
     698: aload_0
     699: aload         7
     701: invokevirtual #57                 // Method org/apache/hadoop/yarn/proto/YarnProtos$ResourceUtilizationProto$Builder.buildPartial:()Lorg/apache/hadoop/yarn/proto/YarnProtos$ResourceUtilizationProto;
     704: putfield      #7                  // Field containersUtilization_:Lorg/apache/hadoop/yarn/proto/YarnProtos$ResourceUtilizationProto;
     707: aload_0
     708: dup
     709: getfield      #2                  // Field bitField0_:I
     712: sipush        512
     715: ior
     716: putfield      #2                  // Field bitField0_:I
     719: goto          923
     722: aconst_null
     723: astore        7
     725: aload_0
     726: getfield      #2                  // Field bitField0_:I
     729: sipush        1024
     732: iand
     733: sipush        1024
     736: if_icmpne     748
     739: aload_0
     740: getfield      #6                  // Field nodeUtilization_:Lorg/apache/hadoop/yarn/proto/YarnProtos$ResourceUtilizationProto;
     743: invokevirtual #53                 // Method org/apache/hadoop/yarn/proto/YarnProtos$ResourceUtilizationProto.toBuilder:()Lorg/apache/hadoop/yarn/proto/YarnProtos$ResourceUtilizationProto$Builder;
     746: astore        7
     748: aload_0
     749: aload_1
     750: getstatic     #54                 // Field org/apache/hadoop/yarn/proto/YarnProtos$ResourceUtilizationProto.PARSER:Lcom/google/protobuf/Parser;
     753: aload_2
     754: invokevirtual #35                 // Method com/google/protobuf/CodedInputStream.readMessage:(Lcom/google/protobuf/Parser;Lcom/google/protobuf/ExtensionRegistryLite;)Lcom/google/protobuf/MessageLite;
     757: checkcast     #55                 // class org/apache/hadoop/yarn/proto/YarnProtos$ResourceUtilizationProto
     760: putfield      #6                  // Field nodeUtilization_:Lorg/apache/hadoop/yarn/proto/YarnProtos$ResourceUtilizationProto;
     763: aload         7
     765: ifnull        787
     768: aload         7
     770: aload_0
     771: getfield      #6                  // Field nodeUtilization_:Lorg/apache/hadoop/yarn/proto/YarnProtos$ResourceUtilizationProto;
     774: invokevirtual #56                 // Method org/apache/hadoop/yarn/proto/YarnProtos$ResourceUtilizationProto$Builder.mergeFrom:(Lorg/apache/hadoop/yarn/proto/YarnProtos$ResourceUtilizationProto;)Lorg/apache/hadoop/yarn/proto/YarnProtos$ResourceUtilizationProto$Builder;
     777: pop
     778: aload_0
     779: aload         7
     781: invokevirtual #57                 // Method org/apache/hadoop/yarn/proto/YarnProtos$ResourceUtilizationProto$Builder.buildPartial:()Lorg/apache/hadoop/yarn/proto/YarnProtos$ResourceUtilizationProto;
     784: putfield      #6                  // Field nodeUtilization_:Lorg/apache/hadoop/yarn/proto/YarnProtos$ResourceUtilizationProto;
     787: aload_0
     788: dup
     789: getfield      #2                  // Field bitField0_:I
     792: sipush        1024
     795: ior
     796: putfield      #2                  // Field bitField0_:I
     799: goto          923
     802: aload_0
     803: dup
     804: getfield      #2                  // Field bitField0_:I
     807: sipush        2048
     810: ior
     811: putfield      #2                  // Field bitField0_:I
     814: aload_0
     815: aload_1
     816: invokevirtual #58                 // Method com/google/protobuf/CodedInputStream.readUInt32:()I
     819: putfield      #5                  // Field decommissioningTimeout_:I
     822: goto          923
     825: aload_1
     826: invokevirtual #46                 // Method com/google/protobuf/CodedInputStream.readEnum:()I
     829: istore        7
     831: iload         7
     833: invokestatic  #59                 // Method org/apache/hadoop/yarn/proto/YarnProtos$NodeUpdateTypeProto.valueOf:(I)Lorg/apache/hadoop/yarn/proto/YarnProtos$NodeUpdateTypeProto;
     836: astore        8
     838: aload         8
     840: ifnonnull     856
     843: aload         4
     845: bipush        14
     847: iload         7
     849: invokevirtual #48                 // Method com/google/protobuf/UnknownFieldSet$Builder.mergeVarintField:(II)Lcom/google/protobuf/UnknownFieldSet$Builder;
     852: pop
     853: goto          923
     856: aload_0
     857: dup
     858: getfield      #2                  // Field bitField0_:I
     861: sipush        4096
     864: ior
     865: putfield      #2                  // Field bitField0_:I
     868: aload_0
     869: aload         8
     871: putfield      #4                  // Field nodeUpdateType_:Lorg/apache/hadoop/yarn/proto/YarnProtos$NodeUpdateTypeProto;
     874: goto          923
     877: iload_3
     878: sipush        16384
     881: iand
     882: sipush        16384
     885: if_icmpeq     905
     888: aload_0
     889: new           #60                 // class java/util/ArrayList
     892: dup
     893: invokespecial #61                 // Method java/util/ArrayList."<init>":()V
     896: putfield      #3                  // Field nodeAttributes_:Ljava/util/List;
     899: iload_3
     900: sipush        16384
     903: ior
     904: istore_3
     905: aload_0
     906: getfield      #3                  // Field nodeAttributes_:Ljava/util/List;
     909: aload_1
     910: getstatic     #62                 // Field org/apache/hadoop/yarn/proto/YarnProtos$NodeAttributeProto.PARSER:Lcom/google/protobuf/Parser;
     913: aload_2
     914: invokevirtual #35                 // Method com/google/protobuf/CodedInputStream.readMessage:(Lcom/google/protobuf/Parser;Lcom/google/protobuf/ExtensionRegistryLite;)Lcom/google/protobuf/MessageLite;
     917: invokeinterface #63,  2           // InterfaceMethod java/util/List.add:(Ljava/lang/Object;)Z
     922: pop
     923: goto          33
     926: iload_3
     927: sipush        512
     930: iand
     931: sipush        512
     934: if_icmpne     952
     937: aload_0
     938: new           #64                 // class com/google/protobuf/UnmodifiableLazyStringList
     941: dup
     942: aload_0
     943: getfield      #8                  // Field nodeLabels_:Lcom/google/protobuf/LazyStringList;
     946: invokespecial #65                 // Method com/google/protobuf/UnmodifiableLazyStringList."<init>":(Lcom/google/protobuf/LazyStringList;)V
     949: putfield      #8                  // Field nodeLabels_:Lcom/google/protobuf/LazyStringList;
     952: iload_3
     953: sipush        16384
     956: iand
     957: sipush        16384
     960: if_icmpne     974
     963: aload_0
     964: aload_0
     965: getfield      #3                  // Field nodeAttributes_:Ljava/util/List;
     968: invokestatic  #66                 // Method java/util/Collections.unmodifiableList:(Ljava/util/List;)Ljava/util/List;
     971: putfield      #3                  // Field nodeAttributes_:Ljava/util/List;
     974: aload_0
     975: aload         4
     977: invokevirtual #67                 // Method com/google/protobuf/UnknownFieldSet$Builder.build:()Lcom/google/protobuf/UnknownFieldSet;
     980: putfield      #25                 // Field unknownFields:Lcom/google/protobuf/UnknownFieldSet;
     983: aload_0
     984: invokevirtual #68                 // Method makeExtensionsImmutable:()V
     987: goto          1084
     990: astore        5
     992: aload         5
     994: aload_0
     995: invokevirtual #70                 // Method com/google/protobuf/InvalidProtocolBufferException.setUnfinishedMessage:(Lcom/google/protobuf/MessageLite;)Lcom/google/protobuf/InvalidProtocolBufferException;
     998: athrow
     999: astore        5
    1001: new           #69                 // class com/google/protobuf/InvalidProtocolBufferException
    1004: dup
    1005: aload         5
    1007: invokevirtual #72                 // Method java/io/IOException.getMessage:()Ljava/lang/String;
    1010: invokespecial #73                 // Method com/google/protobuf/InvalidProtocolBufferException."<init>":(Ljava/lang/String;)V
    1013: aload_0
    1014: invokevirtual #70                 // Method com/google/protobuf/InvalidProtocolBufferException.setUnfinishedMessage:(Lcom/google/protobuf/MessageLite;)Lcom/google/protobuf/InvalidProtocolBufferException;
    1017: athrow
    1018: astore        9
    1020: iload_3
    1021: sipush        512
    1024: iand
    1025: sipush        512
    1028: if_icmpne     1046
    1031: aload_0
    1032: new           #64                 // class com/google/protobuf/UnmodifiableLazyStringList
    1035: dup
    1036: aload_0
    1037: getfield      #8                  // Field nodeLabels_:Lcom/google/protobuf/LazyStringList;
    1040: invokespecial #65                 // Method com/google/protobuf/UnmodifiableLazyStringList."<init>":(Lcom/google/protobuf/LazyStringList;)V
    1043: putfield      #8                  // Field nodeLabels_:Lcom/google/protobuf/LazyStringList;
    1046: iload_3
    1047: sipush        16384
    1050: iand
    1051: sipush        16384
    1054: if_icmpne     1068
    1057: aload_0
    1058: aload_0
    1059: getfield      #3                  // Field nodeAttributes_:Ljava/util/List;
    1062: invokestatic  #66                 // Method java/util/Collections.unmodifiableList:(Ljava/util/List;)Ljava/util/List;
    1065: putfield      #3                  // Field nodeAttributes_:Ljava/util/List;
    1068: aload_0
    1069: aload         4
    1071: invokevirtual #67                 // Method com/google/protobuf/UnknownFieldSet$Builder.build:()Lcom/google/protobuf/UnknownFieldSet;
    1074: putfield      #25                 // Field unknownFields:Lcom/google/protobuf/UnknownFieldSet;
    1077: aload_0
    1078: invokevirtual #68                 // Method makeExtensionsImmutable:()V
    1081: aload         9
    1083: athrow
    1084: return
    Exception table:
       from    to  target type
          30   926   990   Class com/google/protobuf/InvalidProtocolBufferException
          30   926   999   Class java/io/IOException
          30   926  1018   any
         990  1020  1018   any

  public static final com.google.protobuf.Descriptors$Descriptor getDescriptor();
    Code:
       0: invokestatic  #74                 // Method org/apache/hadoop/yarn/proto/YarnProtos.access$32200:()Lcom/google/protobuf/Descriptors$Descriptor;
       3: areturn

  protected com.google.protobuf.GeneratedMessage$FieldAccessorTable internalGetFieldAccessorTable();
    Code:
       0: invokestatic  #75                 // Method org/apache/hadoop/yarn/proto/YarnProtos.access$32300:()Lcom/google/protobuf/GeneratedMessage$FieldAccessorTable;
       3: ldc           #76                 // class org/apache/hadoop/yarn/proto/YarnProtos$NodeReportProto
       5: ldc           #77                 // class org/apache/hadoop/yarn/proto/YarnProtos$NodeReportProto$Builder
       7: invokevirtual #78                 // Method com/google/protobuf/GeneratedMessage$FieldAccessorTable.ensureFieldAccessorsInitialized:(Ljava/lang/Class;Ljava/lang/Class;)Lcom/google/protobuf/GeneratedMessage$FieldAccessorTable;
      10: areturn

  public com.google.protobuf.Parser<org.apache.hadoop.yarn.proto.YarnProtos$NodeReportProto> getParserForType();
    Code:
       0: getstatic     #79                 // Field PARSER:Lcom/google/protobuf/Parser;
       3: areturn

  public boolean hasNodeId();
    Code:
       0: aload_0
       1: getfield      #2                  // Field bitField0_:I
       4: iconst_1
       5: iand
       6: iconst_1
       7: if_icmpne     14
      10: iconst_1
      11: goto          15
      14: iconst_0
      15: ireturn

  public org.apache.hadoop.yarn.proto.YarnProtos$NodeIdProto getNodeId();
    Code:
       0: aload_0
       1: getfield      #17                 // Field nodeId_:Lorg/apache/hadoop/yarn/proto/YarnProtos$NodeIdProto;
       4: areturn

  public org.apache.hadoop.yarn.proto.YarnProtos$NodeIdProtoOrBuilder getNodeIdOrBuilder();
    Code:
       0: aload_0
       1: getfield      #17                 // Field nodeId_:Lorg/apache/hadoop/yarn/proto/YarnProtos$NodeIdProto;
       4: areturn

  public boolean hasHttpAddress();
    Code:
       0: aload_0
       1: getfield      #2                  // Field bitField0_:I
       4: iconst_2
       5: iand
       6: iconst_2
       7: if_icmpne     14
      10: iconst_1
      11: goto          15
      14: iconst_0
      15: ireturn

  public java.lang.String getHttpAddress();
    Code:
       0: aload_0
       1: getfield      #16                 // Field httpAddress_:Ljava/lang/Object;
       4: astore_1
       5: aload_1
       6: instanceof    #80                 // class java/lang/String
       9: ifeq          17
      12: aload_1
      13: checkcast     #80                 // class java/lang/String
      16: areturn
      17: aload_1
      18: checkcast     #81                 // class com/google/protobuf/ByteString
      21: astore_2
      22: aload_2
      23: invokevirtual #82                 // Method com/google/protobuf/ByteString.toStringUtf8:()Ljava/lang/String;
      26: astore_3
      27: aload_2
      28: invokevirtual #83                 // Method com/google/protobuf/ByteString.isValidUtf8:()Z
      31: ifeq          39
      34: aload_0
      35: aload_3
      36: putfield      #16                 // Field httpAddress_:Ljava/lang/Object;
      39: aload_3
      40: areturn

  public com.google.protobuf.ByteString getHttpAddressBytes();
    Code:
       0: aload_0
       1: getfield      #16                 // Field httpAddress_:Ljava/lang/Object;
       4: astore_1
       5: aload_1
       6: instanceof    #80                 // class java/lang/String
       9: ifeq          27
      12: aload_1
      13: checkcast     #80                 // class java/lang/String
      16: invokestatic  #84                 // Method com/google/protobuf/ByteString.copyFromUtf8:(Ljava/lang/String;)Lcom/google/protobuf/ByteString;
      19: astore_2
      20: aload_0
      21: aload_2
      22: putfield      #16                 // Field httpAddress_:Ljava/lang/Object;
      25: aload_2
      26: areturn
      27: aload_1
      28: checkcast     #81                 // class com/google/protobuf/ByteString
      31: areturn

  public boolean hasRackName();
    Code:
       0: aload_0
       1: getfield      #2                  // Field bitField0_:I
       4: iconst_4
       5: iand
       6: iconst_4
       7: if_icmpne     14
      10: iconst_1
      11: goto          15
      14: iconst_0
      15: ireturn

  public java.lang.String getRackName();
    Code:
       0: aload_0
       1: getfield      #15                 // Field rackName_:Ljava/lang/Object;
       4: astore_1
       5: aload_1
       6: instanceof    #80                 // class java/lang/String
       9: ifeq          17
      12: aload_1
      13: checkcast     #80                 // class java/lang/String
      16: areturn
      17: aload_1
      18: checkcast     #81                 // class com/google/protobuf/ByteString
      21: astore_2
      22: aload_2
      23: invokevirtual #82                 // Method com/google/protobuf/ByteString.toStringUtf8:()Ljava/lang/String;
      26: astore_3
      27: aload_2
      28: invokevirtual #83                 // Method com/google/protobuf/ByteString.isValidUtf8:()Z
      31: ifeq          39
      34: aload_0
      35: aload_3
      36: putfield      #15                 // Field rackName_:Ljava/lang/Object;
      39: aload_3
      40: areturn

  public com.google.protobuf.ByteString getRackNameBytes();
    Code:
       0: aload_0
       1: getfield      #15                 // Field rackName_:Ljava/lang/Object;
       4: astore_1
       5: aload_1
       6: instanceof    #80                 // class java/lang/String
       9: ifeq          27
      12: aload_1
      13: checkcast     #80                 // class java/lang/String
      16: invokestatic  #84                 // Method com/google/protobuf/ByteString.copyFromUtf8:(Ljava/lang/String;)Lcom/google/protobuf/ByteString;
      19: astore_2
      20: aload_0
      21: aload_2
      22: putfield      #15                 // Field rackName_:Ljava/lang/Object;
      25: aload_2
      26: areturn
      27: aload_1
      28: checkcast     #81                 // class com/google/protobuf/ByteString
      31: areturn

  public boolean hasUsed();
    Code:
       0: aload_0
       1: getfield      #2                  // Field bitField0_:I
       4: bipush        8
       6: iand
       7: bipush        8
       9: if_icmpne     16
      12: iconst_1
      13: goto          17
      16: iconst_0
      17: ireturn

  public org.apache.hadoop.yarn.proto.YarnProtos$ResourceProto getUsed();
    Code:
       0: aload_0
       1: getfield      #14                 // Field used_:Lorg/apache/hadoop/yarn/proto/YarnProtos$ResourceProto;
       4: areturn

  public org.apache.hadoop.yarn.proto.YarnProtos$ResourceProtoOrBuilder getUsedOrBuilder();
    Code:
       0: aload_0
       1: getfield      #14                 // Field used_:Lorg/apache/hadoop/yarn/proto/YarnProtos$ResourceProto;
       4: areturn

  public boolean hasCapability();
    Code:
       0: aload_0
       1: getfield      #2                  // Field bitField0_:I
       4: bipush        16
       6: iand
       7: bipush        16
       9: if_icmpne     16
      12: iconst_1
      13: goto          17
      16: iconst_0
      17: ireturn

  public org.apache.hadoop.yarn.proto.YarnProtos$ResourceProto getCapability();
    Code:
       0: aload_0
       1: getfield      #13                 // Field capability_:Lorg/apache/hadoop/yarn/proto/YarnProtos$ResourceProto;
       4: areturn

  public org.apache.hadoop.yarn.proto.YarnProtos$ResourceProtoOrBuilder getCapabilityOrBuilder();
    Code:
       0: aload_0
       1: getfield      #13                 // Field capability_:Lorg/apache/hadoop/yarn/proto/YarnProtos$ResourceProto;
       4: areturn

  public boolean hasNumContainers();
    Code:
       0: aload_0
       1: getfield      #2                  // Field bitField0_:I
       4: bipush        32
       6: iand
       7: bipush        32
       9: if_icmpne     16
      12: iconst_1
      13: goto          17
      16: iconst_0
      17: ireturn

  public int getNumContainers();
    Code:
       0: aload_0
       1: getfield      #12                 // Field numContainers_:I
       4: ireturn

  public boolean hasNodeState();
    Code:
       0: aload_0
       1: getfield      #2                  // Field bitField0_:I
       4: bipush        64
       6: iand
       7: bipush        64
       9: if_icmpne     16
      12: iconst_1
      13: goto          17
      16: iconst_0
      17: ireturn

  public org.apache.hadoop.yarn.proto.YarnProtos$NodeStateProto getNodeState();
    Code:
       0: aload_0
       1: getfield      #11                 // Field nodeState_:Lorg/apache/hadoop/yarn/proto/YarnProtos$NodeStateProto;
       4: areturn

  public boolean hasHealthReport();
    Code:
       0: aload_0
       1: getfield      #2                  // Field bitField0_:I
       4: sipush        128
       7: iand
       8: sipush        128
      11: if_icmpne     18
      14: iconst_1
      15: goto          19
      18: iconst_0
      19: ireturn

  public java.lang.String getHealthReport();
    Code:
       0: aload_0
       1: getfield      #10                 // Field healthReport_:Ljava/lang/Object;
       4: astore_1
       5: aload_1
       6: instanceof    #80                 // class java/lang/String
       9: ifeq          17
      12: aload_1
      13: checkcast     #80                 // class java/lang/String
      16: areturn
      17: aload_1
      18: checkcast     #81                 // class com/google/protobuf/ByteString
      21: astore_2
      22: aload_2
      23: invokevirtual #82                 // Method com/google/protobuf/ByteString.toStringUtf8:()Ljava/lang/String;
      26: astore_3
      27: aload_2
      28: invokevirtual #83                 // Method com/google/protobuf/ByteString.isValidUtf8:()Z
      31: ifeq          39
      34: aload_0
      35: aload_3
      36: putfield      #10                 // Field healthReport_:Ljava/lang/Object;
      39: aload_3
      40: areturn

  public com.google.protobuf.ByteString getHealthReportBytes();
    Code:
       0: aload_0
       1: getfield      #10                 // Field healthReport_:Ljava/lang/Object;
       4: astore_1
       5: aload_1
       6: instanceof    #80                 // class java/lang/String
       9: ifeq          27
      12: aload_1
      13: checkcast     #80                 // class java/lang/String
      16: invokestatic  #84                 // Method com/google/protobuf/ByteString.copyFromUtf8:(Ljava/lang/String;)Lcom/google/protobuf/ByteString;
      19: astore_2
      20: aload_0
      21: aload_2
      22: putfield      #10                 // Field healthReport_:Ljava/lang/Object;
      25: aload_2
      26: areturn
      27: aload_1
      28: checkcast     #81                 // class com/google/protobuf/ByteString
      31: areturn

  public boolean hasLastHealthReportTime();
    Code:
       0: aload_0
       1: getfield      #2                  // Field bitField0_:I
       4: sipush        256
       7: iand
       8: sipush        256
      11: if_icmpne     18
      14: iconst_1
      15: goto          19
      18: iconst_0
      19: ireturn

  public long getLastHealthReportTime();
    Code:
       0: aload_0
       1: getfield      #9                  // Field lastHealthReportTime_:J
       4: lreturn

  public java.util.List<java.lang.String> getNodeLabelsList();
    Code:
       0: aload_0
       1: getfield      #8                  // Field nodeLabels_:Lcom/google/protobuf/LazyStringList;
       4: areturn

  public int getNodeLabelsCount();
    Code:
       0: aload_0
       1: getfield      #8                  // Field nodeLabels_:Lcom/google/protobuf/LazyStringList;
       4: invokeinterface #85,  1           // InterfaceMethod com/google/protobuf/LazyStringList.size:()I
       9: ireturn

  public java.lang.String getNodeLabels(int);
    Code:
       0: aload_0
       1: getfield      #8                  // Field nodeLabels_:Lcom/google/protobuf/LazyStringList;
       4: iload_1
       5: invokeinterface #86,  2           // InterfaceMethod com/google/protobuf/LazyStringList.get:(I)Ljava/lang/Object;
      10: checkcast     #80                 // class java/lang/String
      13: areturn

  public com.google.protobuf.ByteString getNodeLabelsBytes(int);
    Code:
       0: aload_0
       1: getfield      #8                  // Field nodeLabels_:Lcom/google/protobuf/LazyStringList;
       4: iload_1
       5: invokeinterface #87,  2           // InterfaceMethod com/google/protobuf/LazyStringList.getByteString:(I)Lcom/google/protobuf/ByteString;
      10: areturn

  public boolean hasContainersUtilization();
    Code:
       0: aload_0
       1: getfield      #2                  // Field bitField0_:I
       4: sipush        512
       7: iand
       8: sipush        512
      11: if_icmpne     18
      14: iconst_1
      15: goto          19
      18: iconst_0
      19: ireturn

  public org.apache.hadoop.yarn.proto.YarnProtos$ResourceUtilizationProto getContainersUtilization();
    Code:
       0: aload_0
       1: getfield      #7                  // Field containersUtilization_:Lorg/apache/hadoop/yarn/proto/YarnProtos$ResourceUtilizationProto;
       4: areturn

  public org.apache.hadoop.yarn.proto.YarnProtos$ResourceUtilizationProtoOrBuilder getContainersUtilizationOrBuilder();
    Code:
       0: aload_0
       1: getfield      #7                  // Field containersUtilization_:Lorg/apache/hadoop/yarn/proto/YarnProtos$ResourceUtilizationProto;
       4: areturn

  public boolean hasNodeUtilization();
    Code:
       0: aload_0
       1: getfield      #2                  // Field bitField0_:I
       4: sipush        1024
       7: iand
       8: sipush        1024
      11: if_icmpne     18
      14: iconst_1
      15: goto          19
      18: iconst_0
      19: ireturn

  public org.apache.hadoop.yarn.proto.YarnProtos$ResourceUtilizationProto getNodeUtilization();
    Code:
       0: aload_0
       1: getfield      #6                  // Field nodeUtilization_:Lorg/apache/hadoop/yarn/proto/YarnProtos$ResourceUtilizationProto;
       4: areturn

  public org.apache.hadoop.yarn.proto.YarnProtos$ResourceUtilizationProtoOrBuilder getNodeUtilizationOrBuilder();
    Code:
       0: aload_0
       1: getfield      #6                  // Field nodeUtilization_:Lorg/apache/hadoop/yarn/proto/YarnProtos$ResourceUtilizationProto;
       4: areturn

  public boolean hasDecommissioningTimeout();
    Code:
       0: aload_0
       1: getfield      #2                  // Field bitField0_:I
       4: sipush        2048
       7: iand
       8: sipush        2048
      11: if_icmpne     18
      14: iconst_1
      15: goto          19
      18: iconst_0
      19: ireturn

  public int getDecommissioningTimeout();
    Code:
       0: aload_0
       1: getfield      #5                  // Field decommissioningTimeout_:I
       4: ireturn

  public boolean hasNodeUpdateType();
    Code:
       0: aload_0
       1: getfield      #2                  // Field bitField0_:I
       4: sipush        4096
       7: iand
       8: sipush        4096
      11: if_icmpne     18
      14: iconst_1
      15: goto          19
      18: iconst_0
      19: ireturn

  public org.apache.hadoop.yarn.proto.YarnProtos$NodeUpdateTypeProto getNodeUpdateType();
    Code:
       0: aload_0
       1: getfield      #4                  // Field nodeUpdateType_:Lorg/apache/hadoop/yarn/proto/YarnProtos$NodeUpdateTypeProto;
       4: areturn

  public java.util.List<org.apache.hadoop.yarn.proto.YarnProtos$NodeAttributeProto> getNodeAttributesList();
    Code:
       0: aload_0
       1: getfield      #3                  // Field nodeAttributes_:Ljava/util/List;
       4: areturn

  public java.util.List<? extends org.apache.hadoop.yarn.proto.YarnProtos$NodeAttributeProtoOrBuilder> getNodeAttributesOrBuilderList();
    Code:
       0: aload_0
       1: getfield      #3                  // Field nodeAttributes_:Ljava/util/List;
       4: areturn

  public int getNodeAttributesCount();
    Code:
       0: aload_0
       1: getfield      #3                  // Field nodeAttributes_:Ljava/util/List;
       4: invokeinterface #88,  1           // InterfaceMethod java/util/List.size:()I
       9: ireturn

  public org.apache.hadoop.yarn.proto.YarnProtos$NodeAttributeProto getNodeAttributes(int);
    Code:
       0: aload_0
       1: getfield      #3                  // Field nodeAttributes_:Ljava/util/List;
       4: iload_1
       5: invokeinterface #89,  2           // InterfaceMethod java/util/List.get:(I)Ljava/lang/Object;
      10: checkcast     #90                 // class org/apache/hadoop/yarn/proto/YarnProtos$NodeAttributeProto
      13: areturn

  public org.apache.hadoop.yarn.proto.YarnProtos$NodeAttributeProtoOrBuilder getNodeAttributesOrBuilder(int);
    Code:
       0: aload_0
       1: getfield      #3                  // Field nodeAttributes_:Ljava/util/List;
       4: iload_1
       5: invokeinterface #89,  2           // InterfaceMethod java/util/List.get:(I)Ljava/lang/Object;
      10: checkcast     #91                 // class org/apache/hadoop/yarn/proto/YarnProtos$NodeAttributeProtoOrBuilder
      13: areturn

  private void initFields();
    Code:
       0: aload_0
       1: invokestatic  #92                 // Method org/apache/hadoop/yarn/proto/YarnProtos$NodeIdProto.getDefaultInstance:()Lorg/apache/hadoop/yarn/proto/YarnProtos$NodeIdProto;
       4: putfield      #17                 // Field nodeId_:Lorg/apache/hadoop/yarn/proto/YarnProtos$NodeIdProto;
       7: aload_0
       8: ldc           #93                 // String
      10: putfield      #16                 // Field httpAddress_:Ljava/lang/Object;
      13: aload_0
      14: ldc           #93                 // String
      16: putfield      #15                 // Field rackName_:Ljava/lang/Object;
      19: aload_0
      20: invokestatic  #94                 // Method org/apache/hadoop/yarn/proto/YarnProtos$ResourceProto.getDefaultInstance:()Lorg/apache/hadoop/yarn/proto/YarnProtos$ResourceProto;
      23: putfield      #14                 // Field used_:Lorg/apache/hadoop/yarn/proto/YarnProtos$ResourceProto;
      26: aload_0
      27: invokestatic  #94                 // Method org/apache/hadoop/yarn/proto/YarnProtos$ResourceProto.getDefaultInstance:()Lorg/apache/hadoop/yarn/proto/YarnProtos$ResourceProto;
      30: putfield      #13                 // Field capability_:Lorg/apache/hadoop/yarn/proto/YarnProtos$ResourceProto;
      33: aload_0
      34: iconst_0
      35: putfield      #12                 // Field numContainers_:I
      38: aload_0
      39: getstatic     #95                 // Field org/apache/hadoop/yarn/proto/YarnProtos$NodeStateProto.NS_NEW:Lorg/apache/hadoop/yarn/proto/YarnProtos$NodeStateProto;
      42: putfield      #11                 // Field nodeState_:Lorg/apache/hadoop/yarn/proto/YarnProtos$NodeStateProto;
      45: aload_0
      46: ldc           #93                 // String
      48: putfield      #10                 // Field healthReport_:Ljava/lang/Object;
      51: aload_0
      52: lconst_0
      53: putfield      #9                  // Field lastHealthReportTime_:J
      56: aload_0
      57: getstatic     #96                 // Field com/google/protobuf/LazyStringArrayList.EMPTY:Lcom/google/protobuf/LazyStringList;
      60: putfield      #8                  // Field nodeLabels_:Lcom/google/protobuf/LazyStringList;
      63: aload_0
      64: invokestatic  #97                 // Method org/apache/hadoop/yarn/proto/YarnProtos$ResourceUtilizationProto.getDefaultInstance:()Lorg/apache/hadoop/yarn/proto/YarnProtos$ResourceUtilizationProto;
      67: putfield      #7                  // Field containersUtilization_:Lorg/apache/hadoop/yarn/proto/YarnProtos$ResourceUtilizationProto;
      70: aload_0
      71: invokestatic  #97                 // Method org/apache/hadoop/yarn/proto/YarnProtos$ResourceUtilizationProto.getDefaultInstance:()Lorg/apache/hadoop/yarn/proto/YarnProtos$ResourceUtilizationProto;
      74: putfield      #6                  // Field nodeUtilization_:Lorg/apache/hadoop/yarn/proto/YarnProtos$ResourceUtilizationProto;
      77: aload_0
      78: iconst_0
      79: putfield      #5                  // Field decommissioningTimeout_:I
      82: aload_0
      83: getstatic     #98                 // Field org/apache/hadoop/yarn/proto/YarnProtos$NodeUpdateTypeProto.NODE_USABLE:Lorg/apache/hadoop/yarn/proto/YarnProtos$NodeUpdateTypeProto;
      86: putfield      #4                  // Field nodeUpdateType_:Lorg/apache/hadoop/yarn/proto/YarnProtos$NodeUpdateTypeProto;
      89: aload_0
      90: invokestatic  #99                 // Method java/util/Collections.emptyList:()Ljava/util/List;
      93: putfield      #3                  // Field nodeAttributes_:Ljava/util/List;
      96: return

  public final boolean isInitialized();
    Code:
       0: aload_0
       1: getfield      #21                 // Field memoizedIsInitialized:B
       4: istore_1
       5: iload_1
       6: iconst_m1
       7: if_icmpeq     21
      10: iload_1
      11: iconst_1
      12: if_icmpne     19
      15: iconst_1
      16: goto          20
      19: iconst_0
      20: ireturn
      21: aload_0
      22: invokevirtual #100                // Method hasUsed:()Z
      25: ifeq          45
      28: aload_0
      29: invokevirtual #101                // Method getUsed:()Lorg/apache/hadoop/yarn/proto/YarnProtos$ResourceProto;
      32: invokevirtual #102                // Method org/apache/hadoop/yarn/proto/YarnProtos$ResourceProto.isInitialized:()Z
      35: ifne          45
      38: aload_0
      39: iconst_0
      40: putfield      #21                 // Field memoizedIsInitialized:B
      43: iconst_0
      44: ireturn
      45: aload_0
      46: invokevirtual #103                // Method hasCapability:()Z
      49: ifeq          69
      52: aload_0
      53: invokevirtual #104                // Method getCapability:()Lorg/apache/hadoop/yarn/proto/YarnProtos$ResourceProto;
      56: invokevirtual #102                // Method org/apache/hadoop/yarn/proto/YarnProtos$ResourceProto.isInitialized:()Z
      59: ifne          69
      62: aload_0
      63: iconst_0
      64: putfield      #21                 // Field memoizedIsInitialized:B
      67: iconst_0
      68: ireturn
      69: iconst_0
      70: istore_2
      71: iload_2
      72: aload_0
      73: invokevirtual #105                // Method getNodeAttributesCount:()I
      76: if_icmpge     103
      79: aload_0
      80: iload_2
      81: invokevirtual #106                // Method getNodeAttributes:(I)Lorg/apache/hadoop/yarn/proto/YarnProtos$NodeAttributeProto;
      84: invokevirtual #107                // Method org/apache/hadoop/yarn/proto/YarnProtos$NodeAttributeProto.isInitialized:()Z
      87: ifne          97
      90: aload_0
      91: iconst_0
      92: putfield      #21                 // Field memoizedIsInitialized:B
      95: iconst_0
      96: ireturn
      97: iinc          2, 1
     100: goto          71
     103: aload_0
     104: iconst_1
     105: putfield      #21                 // Field memoizedIsInitialized:B
     108: iconst_1
     109: ireturn

  public void writeTo(com.google.protobuf.CodedOutputStream) throws java.io.IOException;
    Code:
       0: aload_0
       1: invokevirtual #108                // Method getSerializedSize:()I
       4: pop
       5: aload_0
       6: getfield      #2                  // Field bitField0_:I
       9: iconst_1
      10: iand
      11: iconst_1
      12: if_icmpne     24
      15: aload_1
      16: iconst_1
      17: aload_0
      18: getfield      #17                 // Field nodeId_:Lorg/apache/hadoop/yarn/proto/YarnProtos$NodeIdProto;
      21: invokevirtual #109                // Method com/google/protobuf/CodedOutputStream.writeMessage:(ILcom/google/protobuf/MessageLite;)V
      24: aload_0
      25: getfield      #2                  // Field bitField0_:I
      28: iconst_2
      29: iand
      30: iconst_2
      31: if_icmpne     43
      34: aload_1
      35: iconst_2
      36: aload_0
      37: invokevirtual #110                // Method getHttpAddressBytes:()Lcom/google/protobuf/ByteString;
      40: invokevirtual #111                // Method com/google/protobuf/CodedOutputStream.writeBytes:(ILcom/google/protobuf/ByteString;)V
      43: aload_0
      44: getfield      #2                  // Field bitField0_:I
      47: iconst_4
      48: iand
      49: iconst_4
      50: if_icmpne     62
      53: aload_1
      54: iconst_3
      55: aload_0
      56: invokevirtual #112                // Method getRackNameBytes:()Lcom/google/protobuf/ByteString;
      59: invokevirtual #111                // Method com/google/protobuf/CodedOutputStream.writeBytes:(ILcom/google/protobuf/ByteString;)V
      62: aload_0
      63: getfield      #2                  // Field bitField0_:I
      66: bipush        8
      68: iand
      69: bipush        8
      71: if_icmpne     83
      74: aload_1
      75: iconst_4
      76: aload_0
      77: getfield      #14                 // Field used_:Lorg/apache/hadoop/yarn/proto/YarnProtos$ResourceProto;
      80: invokevirtual #109                // Method com/google/protobuf/CodedOutputStream.writeMessage:(ILcom/google/protobuf/MessageLite;)V
      83: aload_0
      84: getfield      #2                  // Field bitField0_:I
      87: bipush        16
      89: iand
      90: bipush        16
      92: if_icmpne     104
      95: aload_1
      96: iconst_5
      97: aload_0
      98: getfield      #13                 // Field capability_:Lorg/apache/hadoop/yarn/proto/YarnProtos$ResourceProto;
     101: invokevirtual #109                // Method com/google/protobuf/CodedOutputStream.writeMessage:(ILcom/google/protobuf/MessageLite;)V
     104: aload_0
     105: getfield      #2                  // Field bitField0_:I
     108: bipush        32
     110: iand
     111: bipush        32
     113: if_icmpne     126
     116: aload_1
     117: bipush        6
     119: aload_0
     120: getfield      #12                 // Field numContainers_:I
     123: invokevirtual #113                // Method com/google/protobuf/CodedOutputStream.writeInt32:(II)V
     126: aload_0
     127: getfield      #2                  // Field bitField0_:I
     130: bipush        64
     132: iand
     133: bipush        64
     135: if_icmpne     151
     138: aload_1
     139: bipush        7
     141: aload_0
     142: getfield      #11                 // Field nodeState_:Lorg/apache/hadoop/yarn/proto/YarnProtos$NodeStateProto;
     145: invokevirtual #114                // Method org/apache/hadoop/yarn/proto/YarnProtos$NodeStateProto.getNumber:()I
     148: invokevirtual #115                // Method com/google/protobuf/CodedOutputStream.writeEnum:(II)V
     151: aload_0
     152: getfield      #2                  // Field bitField0_:I
     155: sipush        128
     158: iand
     159: sipush        128
     162: if_icmpne     175
     165: aload_1
     166: bipush        8
     168: aload_0
     169: invokevirtual #116                // Method getHealthReportBytes:()Lcom/google/protobuf/ByteString;
     172: invokevirtual #111                // Method com/google/protobuf/CodedOutputStream.writeBytes:(ILcom/google/protobuf/ByteString;)V
     175: aload_0
     176: getfield      #2                  // Field bitField0_:I
     179: sipush        256
     182: iand
     183: sipush        256
     186: if_icmpne     199
     189: aload_1
     190: bipush        9
     192: aload_0
     193: getfield      #9                  // Field lastHealthReportTime_:J
     196: invokevirtual #117                // Method com/google/protobuf/CodedOutputStream.writeInt64:(IJ)V
     199: iconst_0
     200: istore_2
     201: iload_2
     202: aload_0
     203: getfield      #8                  // Field nodeLabels_:Lcom/google/protobuf/LazyStringList;
     206: invokeinterface #85,  1           // InterfaceMethod com/google/protobuf/LazyStringList.size:()I
     211: if_icmpge     236
     214: aload_1
     215: bipush        10
     217: aload_0
     218: getfield      #8                  // Field nodeLabels_:Lcom/google/protobuf/LazyStringList;
     221: iload_2
     222: invokeinterface #87,  2           // InterfaceMethod com/google/protobuf/LazyStringList.getByteString:(I)Lcom/google/protobuf/ByteString;
     227: invokevirtual #111                // Method com/google/protobuf/CodedOutputStream.writeBytes:(ILcom/google/protobuf/ByteString;)V
     230: iinc          2, 1
     233: goto          201
     236: aload_0
     237: getfield      #2                  // Field bitField0_:I
     240: sipush        512
     243: iand
     244: sipush        512
     247: if_icmpne     260
     250: aload_1
     251: bipush        11
     253: aload_0
     254: getfield      #7                  // Field containersUtilization_:Lorg/apache/hadoop/yarn/proto/YarnProtos$ResourceUtilizationProto;
     257: invokevirtual #109                // Method com/google/protobuf/CodedOutputStream.writeMessage:(ILcom/google/protobuf/MessageLite;)V
     260: aload_0
     261: getfield      #2                  // Field bitField0_:I
     264: sipush        1024
     267: iand
     268: sipush        1024
     271: if_icmpne     284
     274: aload_1
     275: bipush        12
     277: aload_0
     278: getfield      #6                  // Field nodeUtilization_:Lorg/apache/hadoop/yarn/proto/YarnProtos$ResourceUtilizationProto;
     281: invokevirtual #109                // Method com/google/protobuf/CodedOutputStream.writeMessage:(ILcom/google/protobuf/MessageLite;)V
     284: aload_0
     285: getfield      #2                  // Field bitField0_:I
     288: sipush        2048
     291: iand
     292: sipush        2048
     295: if_icmpne     308
     298: aload_1
     299: bipush        13
     301: aload_0
     302: getfield      #5                  // Field decommissioningTimeout_:I
     305: invokevirtual #118                // Method com/google/protobuf/CodedOutputStream.writeUInt32:(II)V
     308: aload_0
     309: getfield      #2                  // Field bitField0_:I
     312: sipush        4096
     315: iand
     316: sipush        4096
     319: if_icmpne     335
     322: aload_1
     323: bipush        14
     325: aload_0
     326: getfield      #4                  // Field nodeUpdateType_:Lorg/apache/hadoop/yarn/proto/YarnProtos$NodeUpdateTypeProto;
     329: invokevirtual #119                // Method org/apache/hadoop/yarn/proto/YarnProtos$NodeUpdateTypeProto.getNumber:()I
     332: invokevirtual #115                // Method com/google/protobuf/CodedOutputStream.writeEnum:(II)V
     335: iconst_0
     336: istore_2
     337: iload_2
     338: aload_0
     339: getfield      #3                  // Field nodeAttributes_:Ljava/util/List;
     342: invokeinterface #88,  1           // InterfaceMethod java/util/List.size:()I
     347: if_icmpge     375
     350: aload_1
     351: bipush        15
     353: aload_0
     354: getfield      #3                  // Field nodeAttributes_:Ljava/util/List;
     357: iload_2
     358: invokeinterface #89,  2           // InterfaceMethod java/util/List.get:(I)Ljava/lang/Object;
     363: checkcast     #120                // class com/google/protobuf/MessageLite
     366: invokevirtual #109                // Method com/google/protobuf/CodedOutputStream.writeMessage:(ILcom/google/protobuf/MessageLite;)V
     369: iinc          2, 1
     372: goto          337
     375: aload_0
     376: invokevirtual #121                // Method getUnknownFields:()Lcom/google/protobuf/UnknownFieldSet;
     379: aload_1
     380: invokevirtual #122                // Method com/google/protobuf/UnknownFieldSet.writeTo:(Lcom/google/protobuf/CodedOutputStream;)V
     383: return

  public int getSerializedSize();
    Code:
       0: aload_0
       1: getfield      #22                 // Field memoizedSerializedSize:I
       4: istore_1
       5: iload_1
       6: iconst_m1
       7: if_icmpeq     12
      10: iload_1
      11: ireturn
      12: iconst_0
      13: istore_1
      14: aload_0
      15: getfield      #2                  // Field bitField0_:I
      18: iconst_1
      19: iand
      20: iconst_1
      21: if_icmpne     35
      24: iload_1
      25: iconst_1
      26: aload_0
      27: getfield      #17                 // Field nodeId_:Lorg/apache/hadoop/yarn/proto/YarnProtos$NodeIdProto;
      30: invokestatic  #123                // Method com/google/protobuf/CodedOutputStream.computeMessageSize:(ILcom/google/protobuf/MessageLite;)I
      33: iadd
      34: istore_1
      35: aload_0
      36: getfield      #2                  // Field bitField0_:I
      39: iconst_2
      40: iand
      41: iconst_2
      42: if_icmpne     56
      45: iload_1
      46: iconst_2
      47: aload_0
      48: invokevirtual #110                // Method getHttpAddressBytes:()Lcom/google/protobuf/ByteString;
      51: invokestatic  #124                // Method com/google/protobuf/CodedOutputStream.computeBytesSize:(ILcom/google/protobuf/ByteString;)I
      54: iadd
      55: istore_1
      56: aload_0
      57: getfield      #2                  // Field bitField0_:I
      60: iconst_4
      61: iand
      62: iconst_4
      63: if_icmpne     77
      66: iload_1
      67: iconst_3
      68: aload_0
      69: invokevirtual #112                // Method getRackNameBytes:()Lcom/google/protobuf/ByteString;
      72: invokestatic  #124                // Method com/google/protobuf/CodedOutputStream.computeBytesSize:(ILcom/google/protobuf/ByteString;)I
      75: iadd
      76: istore_1
      77: aload_0
      78: getfield      #2                  // Field bitField0_:I
      81: bipush        8
      83: iand
      84: bipush        8
      86: if_icmpne     100
      89: iload_1
      90: iconst_4
      91: aload_0
      92: getfield      #14                 // Field used_:Lorg/apache/hadoop/yarn/proto/YarnProtos$ResourceProto;
      95: invokestatic  #123                // Method com/google/protobuf/CodedOutputStream.computeMessageSize:(ILcom/google/protobuf/MessageLite;)I
      98: iadd
      99: istore_1
     100: aload_0
     101: getfield      #2                  // Field bitField0_:I
     104: bipush        16
     106: iand
     107: bipush        16
     109: if_icmpne     123
     112: iload_1
     113: iconst_5
     114: aload_0
     115: getfield      #13                 // Field capability_:Lorg/apache/hadoop/yarn/proto/YarnProtos$ResourceProto;
     118: invokestatic  #123                // Method com/google/protobuf/CodedOutputStream.computeMessageSize:(ILcom/google/protobuf/MessageLite;)I
     121: iadd
     122: istore_1
     123: aload_0
     124: getfield      #2                  // Field bitField0_:I
     127: bipush        32
     129: iand
     130: bipush        32
     132: if_icmpne     147
     135: iload_1
     136: bipush        6
     138: aload_0
     139: getfield      #12                 // Field numContainers_:I
     142: invokestatic  #125                // Method com/google/protobuf/CodedOutputStream.computeInt32Size:(II)I
     145: iadd
     146: istore_1
     147: aload_0
     148: getfield      #2                  // Field bitField0_:I
     151: bipush        64
     153: iand
     154: bipush        64
     156: if_icmpne     174
     159: iload_1
     160: bipush        7
     162: aload_0
     163: getfield      #11                 // Field nodeState_:Lorg/apache/hadoop/yarn/proto/YarnProtos$NodeStateProto;
     166: invokevirtual #114                // Method org/apache/hadoop/yarn/proto/YarnProtos$NodeStateProto.getNumber:()I
     169: invokestatic  #126                // Method com/google/protobuf/CodedOutputStream.computeEnumSize:(II)I
     172: iadd
     173: istore_1
     174: aload_0
     175: getfield      #2                  // Field bitField0_:I
     178: sipush        128
     181: iand
     182: sipush        128
     185: if_icmpne     200
     188: iload_1
     189: bipush        8
     191: aload_0
     192: invokevirtual #116                // Method getHealthReportBytes:()Lcom/google/protobuf/ByteString;
     195: invokestatic  #124                // Method com/google/protobuf/CodedOutputStream.computeBytesSize:(ILcom/google/protobuf/ByteString;)I
     198: iadd
     199: istore_1
     200: aload_0
     201: getfield      #2                  // Field bitField0_:I
     204: sipush        256
     207: iand
     208: sipush        256
     211: if_icmpne     226
     214: iload_1
     215: bipush        9
     217: aload_0
     218: getfield      #9                  // Field lastHealthReportTime_:J
     221: invokestatic  #127                // Method com/google/protobuf/CodedOutputStream.computeInt64Size:(IJ)I
     224: iadd
     225: istore_1
     226: iconst_0
     227: istore_2
     228: iconst_0
     229: istore_3
     230: iload_3
     231: aload_0
     232: getfield      #8                  // Field nodeLabels_:Lcom/google/protobuf/LazyStringList;
     235: invokeinterface #85,  1           // InterfaceMethod com/google/protobuf/LazyStringList.size:()I
     240: if_icmpge     265
     243: iload_2
     244: aload_0
     245: getfield      #8                  // Field nodeLabels_:Lcom/google/protobuf/LazyStringList;
     248: iload_3
     249: invokeinterface #87,  2           // InterfaceMethod com/google/protobuf/LazyStringList.getByteString:(I)Lcom/google/protobuf/ByteString;
     254: invokestatic  #128                // Method com/google/protobuf/CodedOutputStream.computeBytesSizeNoTag:(Lcom/google/protobuf/ByteString;)I
     257: iadd
     258: istore_2
     259: iinc          3, 1
     262: goto          230
     265: iload_1
     266: iload_2
     267: iadd
     268: istore_1
     269: iload_1
     270: iconst_1
     271: aload_0
     272: invokevirtual #129                // Method getNodeLabelsList:()Ljava/util/List;
     275: invokeinterface #88,  1           // InterfaceMethod java/util/List.size:()I
     280: imul
     281: iadd
     282: istore_1
     283: aload_0
     284: getfield      #2                  // Field bitField0_:I
     287: sipush        512
     290: iand
     291: sipush        512
     294: if_icmpne     309
     297: iload_1
     298: bipush        11
     300: aload_0
     301: getfield      #7                  // Field containersUtilization_:Lorg/apache/hadoop/yarn/proto/YarnProtos$ResourceUtilizationProto;
     304: invokestatic  #123                // Method com/google/protobuf/CodedOutputStream.computeMessageSize:(ILcom/google/protobuf/MessageLite;)I
     307: iadd
     308: istore_1
     309: aload_0
     310: getfield      #2                  // Field bitField0_:I
     313: sipush        1024
     316: iand
     317: sipush        1024
     320: if_icmpne     335
     323: iload_1
     324: bipush        12
     326: aload_0
     327: getfield      #6                  // Field nodeUtilization_:Lorg/apache/hadoop/yarn/proto/YarnProtos$ResourceUtilizationProto;
     330: invokestatic  #123                // Method com/google/protobuf/CodedOutputStream.computeMessageSize:(ILcom/google/protobuf/MessageLite;)I
     333: iadd
     334: istore_1
     335: aload_0
     336: getfield      #2                  // Field bitField0_:I
     339: sipush        2048
     342: iand
     343: sipush        2048
     346: if_icmpne     361
     349: iload_1
     350: bipush        13
     352: aload_0
     353: getfield      #5                  // Field decommissioningTimeout_:I
     356: invokestatic  #130                // Method com/google/protobuf/CodedOutputStream.computeUInt32Size:(II)I
     359: iadd
     360: istore_1
     361: aload_0
     362: getfield      #2                  // Field bitField0_:I
     365: sipush        4096
     368: iand
     369: sipush        4096
     372: if_icmpne     390
     375: iload_1
     376: bipush        14
     378: aload_0
     379: getfield      #4                  // Field nodeUpdateType_:Lorg/apache/hadoop/yarn/proto/YarnProtos$NodeUpdateTypeProto;
     382: invokevirtual #119                // Method org/apache/hadoop/yarn/proto/YarnProtos$NodeUpdateTypeProto.getNumber:()I
     385: invokestatic  #126                // Method com/google/protobuf/CodedOutputStream.computeEnumSize:(II)I
     388: iadd
     389: istore_1
     390: iconst_0
     391: istore_2
     392: iload_2
     393: aload_0
     394: getfield      #3                  // Field nodeAttributes_:Ljava/util/List;
     397: invokeinterface #88,  1           // InterfaceMethod java/util/List.size:()I
     402: if_icmpge     432
     405: iload_1
     406: bipush        15
     408: aload_0
     409: getfield      #3                  // Field nodeAttributes_:Ljava/util/List;
     412: iload_2
     413: invokeinterface #89,  2           // InterfaceMethod java/util/List.get:(I)Ljava/lang/Object;
     418: checkcast     #120                // class com/google/protobuf/MessageLite
     421: invokestatic  #123                // Method com/google/protobuf/CodedOutputStream.computeMessageSize:(ILcom/google/protobuf/MessageLite;)I
     424: iadd
     425: istore_1
     426: iinc          2, 1
     429: goto          392
     432: iload_1
     433: aload_0
     434: invokevirtual #121                // Method getUnknownFields:()Lcom/google/protobuf/UnknownFieldSet;
     437: invokevirtual #131                // Method com/google/protobuf/UnknownFieldSet.getSerializedSize:()I
     440: iadd
     441: istore_1
     442: aload_0
     443: iload_1
     444: putfield      #22                 // Field memoizedSerializedSize:I
     447: iload_1
     448: ireturn

  protected java.lang.Object writeReplace() throws java.io.ObjectStreamException;
    Code:
       0: aload_0
       1: invokespecial #132                // Method com/google/protobuf/GeneratedMessage.writeReplace:()Ljava/lang/Object;
       4: areturn

  public boolean equals(java.lang.Object);
    Code:
       0: aload_1
       1: aload_0
       2: if_acmpne     7
       5: iconst_1
       6: ireturn
       7: aload_1
       8: instanceof    #76                 // class org/apache/hadoop/yarn/proto/YarnProtos$NodeReportProto
      11: ifne          20
      14: aload_0
      15: aload_1
      16: invokespecial #133                // Method com/google/protobuf/GeneratedMessage.equals:(Ljava/lang/Object;)Z
      19: ireturn
      20: aload_1
      21: checkcast     #76                 // class org/apache/hadoop/yarn/proto/YarnProtos$NodeReportProto
      24: astore_2
      25: iconst_1
      26: istore_3
      27: iload_3
      28: ifeq          46
      31: aload_0
      32: invokevirtual #134                // Method hasNodeId:()Z
      35: aload_2
      36: invokevirtual #134                // Method hasNodeId:()Z
      39: if_icmpne     46
      42: iconst_1
      43: goto          47
      46: iconst_0
      47: istore_3
      48: aload_0
      49: invokevirtual #134                // Method hasNodeId:()Z
      52: ifeq          79
      55: iload_3
      56: ifeq          77
      59: aload_0
      60: invokevirtual #135                // Method getNodeId:()Lorg/apache/hadoop/yarn/proto/YarnProtos$NodeIdProto;
      63: aload_2
      64: invokevirtual #135                // Method getNodeId:()Lorg/apache/hadoop/yarn/proto/YarnProtos$NodeIdProto;
      67: invokevirtual #136                // Method org/apache/hadoop/yarn/proto/YarnProtos$NodeIdProto.equals:(Ljava/lang/Object;)Z
      70: ifeq          77
      73: iconst_1
      74: goto          78
      77: iconst_0
      78: istore_3
      79: iload_3
      80: ifeq          98
      83: aload_0
      84: invokevirtual #137                // Method hasHttpAddress:()Z
      87: aload_2
      88: invokevirtual #137                // Method hasHttpAddress:()Z
      91: if_icmpne     98
      94: iconst_1
      95: goto          99
      98: iconst_0
      99: istore_3
     100: aload_0
     101: invokevirtual #137                // Method hasHttpAddress:()Z
     104: ifeq          131
     107: iload_3
     108: ifeq          129
     111: aload_0
     112: invokevirtual #138                // Method getHttpAddress:()Ljava/lang/String;
     115: aload_2
     116: invokevirtual #138                // Method getHttpAddress:()Ljava/lang/String;
     119: invokevirtual #139                // Method java/lang/String.equals:(Ljava/lang/Object;)Z
     122: ifeq          129
     125: iconst_1
     126: goto          130
     129: iconst_0
     130: istore_3
     131: iload_3
     132: ifeq          150
     135: aload_0
     136: invokevirtual #140                // Method hasRackName:()Z
     139: aload_2
     140: invokevirtual #140                // Method hasRackName:()Z
     143: if_icmpne     150
     146: iconst_1
     147: goto          151
     150: iconst_0
     151: istore_3
     152: aload_0
     153: invokevirtual #140                // Method hasRackName:()Z
     156: ifeq          183
     159: iload_3
     160: ifeq          181
     163: aload_0
     164: invokevirtual #141                // Method getRackName:()Ljava/lang/String;
     167: aload_2
     168: invokevirtual #141                // Method getRackName:()Ljava/lang/String;
     171: invokevirtual #139                // Method java/lang/String.equals:(Ljava/lang/Object;)Z
     174: ifeq          181
     177: iconst_1
     178: goto          182
     181: iconst_0
     182: istore_3
     183: iload_3
     184: ifeq          202
     187: aload_0
     188: invokevirtual #100                // Method hasUsed:()Z
     191: aload_2
     192: invokevirtual #100                // Method hasUsed:()Z
     195: if_icmpne     202
     198: iconst_1
     199: goto          203
     202: iconst_0
     203: istore_3
     204: aload_0
     205: invokevirtual #100                // Method hasUsed:()Z
     208: ifeq          235
     211: iload_3
     212: ifeq          233
     215: aload_0
     216: invokevirtual #101                // Method getUsed:()Lorg/apache/hadoop/yarn/proto/YarnProtos$ResourceProto;
     219: aload_2
     220: invokevirtual #101                // Method getUsed:()Lorg/apache/hadoop/yarn/proto/YarnProtos$ResourceProto;
     223: invokevirtual #142                // Method org/apache/hadoop/yarn/proto/YarnProtos$ResourceProto.equals:(Ljava/lang/Object;)Z
     226: ifeq          233
     229: iconst_1
     230: goto          234
     233: iconst_0
     234: istore_3
     235: iload_3
     236: ifeq          254
     239: aload_0
     240: invokevirtual #103                // Method hasCapability:()Z
     243: aload_2
     244: invokevirtual #103                // Method hasCapability:()Z
     247: if_icmpne     254
     250: iconst_1
     251: goto          255
     254: iconst_0
     255: istore_3
     256: aload_0
     257: invokevirtual #103                // Method hasCapability:()Z
     260: ifeq          287
     263: iload_3
     264: ifeq          285
     267: aload_0
     268: invokevirtual #104                // Method getCapability:()Lorg/apache/hadoop/yarn/proto/YarnProtos$ResourceProto;
     271: aload_2
     272: invokevirtual #104                // Method getCapability:()Lorg/apache/hadoop/yarn/proto/YarnProtos$ResourceProto;
     275: invokevirtual #142                // Method org/apache/hadoop/yarn/proto/YarnProtos$ResourceProto.equals:(Ljava/lang/Object;)Z
     278: ifeq          285
     281: iconst_1
     282: goto          286
     285: iconst_0
     286: istore_3
     287: iload_3
     288: ifeq          306
     291: aload_0
     292: invokevirtual #143                // Method hasNumContainers:()Z
     295: aload_2
     296: invokevirtual #143                // Method hasNumContainers:()Z
     299: if_icmpne     306
     302: iconst_1
     303: goto          307
     306: iconst_0
     307: istore_3
     308: aload_0
     309: invokevirtual #143                // Method hasNumContainers:()Z
     312: ifeq          336
     315: iload_3
     316: ifeq          334
     319: aload_0
     320: invokevirtual #144                // Method getNumContainers:()I
     323: aload_2
     324: invokevirtual #144                // Method getNumContainers:()I
     327: if_icmpne     334
     330: iconst_1
     331: goto          335
     334: iconst_0
     335: istore_3
     336: iload_3
     337: ifeq          355
     340: aload_0
     341: invokevirtual #145                // Method hasNodeState:()Z
     344: aload_2
     345: invokevirtual #145                // Method hasNodeState:()Z
     348: if_icmpne     355
     351: iconst_1
     352: goto          356
     355: iconst_0
     356: istore_3
     357: aload_0
     358: invokevirtual #145                // Method hasNodeState:()Z
     361: ifeq          385
     364: iload_3
     365: ifeq          383
     368: aload_0
     369: invokevirtual #146                // Method getNodeState:()Lorg/apache/hadoop/yarn/proto/YarnProtos$NodeStateProto;
     372: aload_2
     373: invokevirtual #146                // Method getNodeState:()Lorg/apache/hadoop/yarn/proto/YarnProtos$NodeStateProto;
     376: if_acmpne     383
     379: iconst_1
     380: goto          384
     383: iconst_0
     384: istore_3
     385: iload_3
     386: ifeq          404
     389: aload_0
     390: invokevirtual #147                // Method hasHealthReport:()Z
     393: aload_2
     394: invokevirtual #147                // Method hasHealthReport:()Z
     397: if_icmpne     404
     400: iconst_1
     401: goto          405
     404: iconst_0
     405: istore_3
     406: aload_0
     407: invokevirtual #147                // Method hasHealthReport:()Z
     410: ifeq          437
     413: iload_3
     414: ifeq          435
     417: aload_0
     418: invokevirtual #148                // Method getHealthReport:()Ljava/lang/String;
     421: aload_2
     422: invokevirtual #148                // Method getHealthReport:()Ljava/lang/String;
     425: invokevirtual #139                // Method java/lang/String.equals:(Ljava/lang/Object;)Z
     428: ifeq          435
     431: iconst_1
     432: goto          436
     435: iconst_0
     436: istore_3
     437: iload_3
     438: ifeq          456
     441: aload_0
     442: invokevirtual #149                // Method hasLastHealthReportTime:()Z
     445: aload_2
     446: invokevirtual #149                // Method hasLastHealthReportTime:()Z
     449: if_icmpne     456
     452: iconst_1
     453: goto          457
     456: iconst_0
     457: istore_3
     458: aload_0
     459: invokevirtual #149                // Method hasLastHealthReportTime:()Z
     462: ifeq          487
     465: iload_3
     466: ifeq          485
     469: aload_0
     470: invokevirtual #150                // Method getLastHealthReportTime:()J
     473: aload_2
     474: invokevirtual #150                // Method getLastHealthReportTime:()J
     477: lcmp
     478: ifne          485
     481: iconst_1
     482: goto          486
     485: iconst_0
     486: istore_3
     487: iload_3
     488: ifeq          511
     491: aload_0
     492: invokevirtual #129                // Method getNodeLabelsList:()Ljava/util/List;
     495: aload_2
     496: invokevirtual #129                // Method getNodeLabelsList:()Ljava/util/List;
     499: invokeinterface #151,  2          // InterfaceMethod java/util/List.equals:(Ljava/lang/Object;)Z
     504: ifeq          511
     507: iconst_1
     508: goto          512
     511: iconst_0
     512: istore_3
     513: iload_3
     514: ifeq          532
     517: aload_0
     518: invokevirtual #152                // Method hasContainersUtilization:()Z
     521: aload_2
     522: invokevirtual #152                // Method hasContainersUtilization:()Z
     525: if_icmpne     532
     528: iconst_1
     529: goto          533
     532: iconst_0
     533: istore_3
     534: aload_0
     535: invokevirtual #152                // Method hasContainersUtilization:()Z
     538: ifeq          565
     541: iload_3
     542: ifeq          563
     545: aload_0
     546: invokevirtual #153                // Method getContainersUtilization:()Lorg/apache/hadoop/yarn/proto/YarnProtos$ResourceUtilizationProto;
     549: aload_2
     550: invokevirtual #153                // Method getContainersUtilization:()Lorg/apache/hadoop/yarn/proto/YarnProtos$ResourceUtilizationProto;
     553: invokevirtual #154                // Method org/apache/hadoop/yarn/proto/YarnProtos$ResourceUtilizationProto.equals:(Ljava/lang/Object;)Z
     556: ifeq          563
     559: iconst_1
     560: goto          564
     563: iconst_0
     564: istore_3
     565: iload_3
     566: ifeq          584
     569: aload_0
     570: invokevirtual #155                // Method hasNodeUtilization:()Z
     573: aload_2
     574: invokevirtual #155                // Method hasNodeUtilization:()Z
     577: if_icmpne     584
     580: iconst_1
     581: goto          585
     584: iconst_0
     585: istore_3
     586: aload_0
     587: invokevirtual #155                // Method hasNodeUtilization:()Z
     590: ifeq          617
     593: iload_3
     594: ifeq          615
     597: aload_0
     598: invokevirtual #156                // Method getNodeUtilization:()Lorg/apache/hadoop/yarn/proto/YarnProtos$ResourceUtilizationProto;
     601: aload_2
     602: invokevirtual #156                // Method getNodeUtilization:()Lorg/apache/hadoop/yarn/proto/YarnProtos$ResourceUtilizationProto;
     605: invokevirtual #154                // Method org/apache/hadoop/yarn/proto/YarnProtos$ResourceUtilizationProto.equals:(Ljava/lang/Object;)Z
     608: ifeq          615
     611: iconst_1
     612: goto          616
     615: iconst_0
     616: istore_3
     617: iload_3
     618: ifeq          636
     621: aload_0
     622: invokevirtual #157                // Method hasDecommissioningTimeout:()Z
     625: aload_2
     626: invokevirtual #157                // Method hasDecommissioningTimeout:()Z
     629: if_icmpne     636
     632: iconst_1
     633: goto          637
     636: iconst_0
     637: istore_3
     638: aload_0
     639: invokevirtual #157                // Method hasDecommissioningTimeout:()Z
     642: ifeq          666
     645: iload_3
     646: ifeq          664
     649: aload_0
     650: invokevirtual #158                // Method getDecommissioningTimeout:()I
     653: aload_2
     654: invokevirtual #158                // Method getDecommissioningTimeout:()I
     657: if_icmpne     664
     660: iconst_1
     661: goto          665
     664: iconst_0
     665: istore_3
     666: iload_3
     667: ifeq          685
     670: aload_0
     671: invokevirtual #159                // Method hasNodeUpdateType:()Z
     674: aload_2
     675: invokevirtual #159                // Method hasNodeUpdateType:()Z
     678: if_icmpne     685
     681: iconst_1
     682: goto          686
     685: iconst_0
     686: istore_3
     687: aload_0
     688: invokevirtual #159                // Method hasNodeUpdateType:()Z
     691: ifeq          715
     694: iload_3
     695: ifeq          713
     698: aload_0
     699: invokevirtual #160                // Method getNodeUpdateType:()Lorg/apache/hadoop/yarn/proto/YarnProtos$NodeUpdateTypeProto;
     702: aload_2
     703: invokevirtual #160                // Method getNodeUpdateType:()Lorg/apache/hadoop/yarn/proto/YarnProtos$NodeUpdateTypeProto;
     706: if_acmpne     713
     709: iconst_1
     710: goto          714
     713: iconst_0
     714: istore_3
     715: iload_3
     716: ifeq          739
     719: aload_0
     720: invokevirtual #161                // Method getNodeAttributesList:()Ljava/util/List;
     723: aload_2
     724: invokevirtual #161                // Method getNodeAttributesList:()Ljava/util/List;
     727: invokeinterface #151,  2          // InterfaceMethod java/util/List.equals:(Ljava/lang/Object;)Z
     732: ifeq          739
     735: iconst_1
     736: goto          740
     739: iconst_0
     740: istore_3
     741: iload_3
     742: ifeq          763
     745: aload_0
     746: invokevirtual #121                // Method getUnknownFields:()Lcom/google/protobuf/UnknownFieldSet;
     749: aload_2
     750: invokevirtual #121                // Method getUnknownFields:()Lcom/google/protobuf/UnknownFieldSet;
     753: invokevirtual #162                // Method com/google/protobuf/UnknownFieldSet.equals:(Ljava/lang/Object;)Z
     756: ifeq          763
     759: iconst_1
     760: goto          764
     763: iconst_0
     764: istore_3
     765: iload_3
     766: ireturn

  public int hashCode();
    Code:
       0: aload_0
       1: getfield      #23                 // Field memoizedHashCode:I
       4: ifeq          12
       7: aload_0
       8: getfield      #23                 // Field memoizedHashCode:I
      11: ireturn
      12: bipush        41
      14: istore_1
      15: bipush        19
      17: iload_1
      18: imul
      19: aload_0
      20: invokevirtual #163                // Method getDescriptorForType:()Lcom/google/protobuf/Descriptors$Descriptor;
      23: invokevirtual #164                // Method java/lang/Object.hashCode:()I
      26: iadd
      27: istore_1
      28: aload_0
      29: invokevirtual #134                // Method hasNodeId:()Z
      32: ifeq          55
      35: bipush        37
      37: iload_1
      38: imul
      39: iconst_1
      40: iadd
      41: istore_1
      42: bipush        53
      44: iload_1
      45: imul
      46: aload_0
      47: invokevirtual #135                // Method getNodeId:()Lorg/apache/hadoop/yarn/proto/YarnProtos$NodeIdProto;
      50: invokevirtual #165                // Method org/apache/hadoop/yarn/proto/YarnProtos$NodeIdProto.hashCode:()I
      53: iadd
      54: istore_1
      55: aload_0
      56: invokevirtual #137                // Method hasHttpAddress:()Z
      59: ifeq          82
      62: bipush        37
      64: iload_1
      65: imul
      66: iconst_2
      67: iadd
      68: istore_1
      69: bipush        53
      71: iload_1
      72: imul
      73: aload_0
      74: invokevirtual #138                // Method getHttpAddress:()Ljava/lang/String;
      77: invokevirtual #166                // Method java/lang/String.hashCode:()I
      80: iadd
      81: istore_1
      82: aload_0
      83: invokevirtual #140                // Method hasRackName:()Z
      86: ifeq          109
      89: bipush        37
      91: iload_1
      92: imul
      93: iconst_3
      94: iadd
      95: istore_1
      96: bipush        53
      98: iload_1
      99: imul
     100: aload_0
     101: invokevirtual #141                // Method getRackName:()Ljava/lang/String;
     104: invokevirtual #166                // Method java/lang/String.hashCode:()I
     107: iadd
     108: istore_1
     109: aload_0
     110: invokevirtual #100                // Method hasUsed:()Z
     113: ifeq          136
     116: bipush        37
     118: iload_1
     119: imul
     120: iconst_4
     121: iadd
     122: istore_1
     123: bipush        53
     125: iload_1
     126: imul
     127: aload_0
     128: invokevirtual #101                // Method getUsed:()Lorg/apache/hadoop/yarn/proto/YarnProtos$ResourceProto;
     131: invokevirtual #167                // Method org/apache/hadoop/yarn/proto/YarnProtos$ResourceProto.hashCode:()I
     134: iadd
     135: istore_1
     136: aload_0
     137: invokevirtual #103                // Method hasCapability:()Z
     140: ifeq          163
     143: bipush        37
     145: iload_1
     146: imul
     147: iconst_5
     148: iadd
     149: istore_1
     150: bipush        53
     152: iload_1
     153: imul
     154: aload_0
     155: invokevirtual #104                // Method getCapability:()Lorg/apache/hadoop/yarn/proto/YarnProtos$ResourceProto;
     158: invokevirtual #167                // Method org/apache/hadoop/yarn/proto/YarnProtos$ResourceProto.hashCode:()I
     161: iadd
     162: istore_1
     163: aload_0
     164: invokevirtual #143                // Method hasNumContainers:()Z
     167: ifeq          188
     170: bipush        37
     172: iload_1
     173: imul
     174: bipush        6
     176: iadd
     177: istore_1
     178: bipush        53
     180: iload_1
     181: imul
     182: aload_0
     183: invokevirtual #144                // Method getNumContainers:()I
     186: iadd
     187: istore_1
     188: aload_0
     189: invokevirtual #145                // Method hasNodeState:()Z
     192: ifeq          216
     195: bipush        37
     197: iload_1
     198: imul
     199: bipush        7
     201: iadd
     202: istore_1
     203: bipush        53
     205: iload_1
     206: imul
     207: aload_0
     208: invokevirtual #146                // Method getNodeState:()Lorg/apache/hadoop/yarn/proto/YarnProtos$NodeStateProto;
     211: invokestatic  #168                // Method hashEnum:(Lcom/google/protobuf/Internal$EnumLite;)I
     214: iadd
     215: istore_1
     216: aload_0
     217: invokevirtual #147                // Method hasHealthReport:()Z
     220: ifeq          244
     223: bipush        37
     225: iload_1
     226: imul
     227: bipush        8
     229: iadd
     230: istore_1
     231: bipush        53
     233: iload_1
     234: imul
     235: aload_0
     236: invokevirtual #148                // Method getHealthReport:()Ljava/lang/String;
     239: invokevirtual #166                // Method java/lang/String.hashCode:()I
     242: iadd
     243: istore_1
     244: aload_0
     245: invokevirtual #149                // Method hasLastHealthReportTime:()Z
     248: ifeq          272
     251: bipush        37
     253: iload_1
     254: imul
     255: bipush        9
     257: iadd
     258: istore_1
     259: bipush        53
     261: iload_1
     262: imul
     263: aload_0
     264: invokevirtual #150                // Method getLastHealthReportTime:()J
     267: invokestatic  #169                // Method hashLong:(J)I
     270: iadd
     271: istore_1
     272: aload_0
     273: invokevirtual #170                // Method getNodeLabelsCount:()I
     276: ifle          302
     279: bipush        37
     281: iload_1
     282: imul
     283: bipush        10
     285: iadd
     286: istore_1
     287: bipush        53
     289: iload_1
     290: imul
     291: aload_0
     292: invokevirtual #129                // Method getNodeLabelsList:()Ljava/util/List;
     295: invokeinterface #171,  1          // InterfaceMethod java/util/List.hashCode:()I
     300: iadd
     301: istore_1
     302: aload_0
     303: invokevirtual #152                // Method hasContainersUtilization:()Z
     306: ifeq          330
     309: bipush        37
     311: iload_1
     312: imul
     313: bipush        11
     315: iadd
     316: istore_1
     317: bipush        53
     319: iload_1
     320: imul
     321: aload_0
     322: invokevirtual #153                // Method getContainersUtilization:()Lorg/apache/hadoop/yarn/proto/YarnProtos$ResourceUtilizationProto;
     325: invokevirtual #172                // Method org/apache/hadoop/yarn/proto/YarnProtos$ResourceUtilizationProto.hashCode:()I
     328: iadd
     329: istore_1
     330: aload_0
     331: invokevirtual #155                // Method hasNodeUtilization:()Z
     334: ifeq          358
     337: bipush        37
     339: iload_1
     340: imul
     341: bipush        12
     343: iadd
     344: istore_1
     345: bipush        53
     347: iload_1
     348: imul
     349: aload_0
     350: invokevirtual #156                // Method getNodeUtilization:()Lorg/apache/hadoop/yarn/proto/YarnProtos$ResourceUtilizationProto;
     353: invokevirtual #172                // Method org/apache/hadoop/yarn/proto/YarnProtos$ResourceUtilizationProto.hashCode:()I
     356: iadd
     357: istore_1
     358: aload_0
     359: invokevirtual #157                // Method hasDecommissioningTimeout:()Z
     362: ifeq          383
     365: bipush        37
     367: iload_1
     368: imul
     369: bipush        13
     371: iadd
     372: istore_1
     373: bipush        53
     375: iload_1
     376: imul
     377: aload_0
     378: invokevirtual #158                // Method getDecommissioningTimeout:()I
     381: iadd
     382: istore_1
     383: aload_0
     384: invokevirtual #159                // Method hasNodeUpdateType:()Z
     387: ifeq          411
     390: bipush        37
     392: iload_1
     393: imul
     394: bipush        14
     396: iadd
     397: istore_1
     398: bipush        53
     400: iload_1
     401: imul
     402: aload_0
     403: invokevirtual #160                // Method getNodeUpdateType:()Lorg/apache/hadoop/yarn/proto/YarnProtos$NodeUpdateTypeProto;
     406: invokestatic  #168                // Method hashEnum:(Lcom/google/protobuf/Internal$EnumLite;)I
     409: iadd
     410: istore_1
     411: aload_0
     412: invokevirtual #105                // Method getNodeAttributesCount:()I
     415: ifle          441
     418: bipush        37
     420: iload_1
     421: imul
     422: bipush        15
     424: iadd
     425: istore_1
     426: bipush        53
     428: iload_1
     429: imul
     430: aload_0
     431: invokevirtual #161                // Method getNodeAttributesList:()Ljava/util/List;
     434: invokeinterface #171,  1          // InterfaceMethod java/util/List.hashCode:()I
     439: iadd
     440: istore_1
     441: bipush        29
     443: iload_1
     444: imul
     445: aload_0
     446: invokevirtual #121                // Method getUnknownFields:()Lcom/google/protobuf/UnknownFieldSet;
     449: invokevirtual #173                // Method com/google/protobuf/UnknownFieldSet.hashCode:()I
     452: iadd
     453: istore_1
     454: aload_0
     455: iload_1
     456: putfield      #23                 // Field memoizedHashCode:I
     459: iload_1
     460: ireturn

  public static org.apache.hadoop.yarn.proto.YarnProtos$NodeReportProto parseFrom(com.google.protobuf.ByteString) throws com.google.protobuf.InvalidProtocolBufferException;
    Code:
       0: getstatic     #79                 // Field PARSER:Lcom/google/protobuf/Parser;
       3: aload_0
       4: invokeinterface #174,  2          // InterfaceMethod com/google/protobuf/Parser.parseFrom:(Lcom/google/protobuf/ByteString;)Ljava/lang/Object;
       9: checkcast     #76                 // class org/apache/hadoop/yarn/proto/YarnProtos$NodeReportProto
      12: areturn

  public static org.apache.hadoop.yarn.proto.YarnProtos$NodeReportProto parseFrom(com.google.protobuf.ByteString, com.google.protobuf.ExtensionRegistryLite) throws com.google.protobuf.InvalidProtocolBufferException;
    Code:
       0: getstatic     #79                 // Field PARSER:Lcom/google/protobuf/Parser;
       3: aload_0
       4: aload_1
       5: invokeinterface #175,  3          // InterfaceMethod com/google/protobuf/Parser.parseFrom:(Lcom/google/protobuf/ByteString;Lcom/google/protobuf/ExtensionRegistryLite;)Ljava/lang/Object;
      10: checkcast     #76                 // class org/apache/hadoop/yarn/proto/YarnProtos$NodeReportProto
      13: areturn

  public static org.apache.hadoop.yarn.proto.YarnProtos$NodeReportProto parseFrom(byte[]) throws com.google.protobuf.InvalidProtocolBufferException;
    Code:
       0: getstatic     #79                 // Field PARSER:Lcom/google/protobuf/Parser;
       3: aload_0
       4: invokeinterface #176,  2          // InterfaceMethod com/google/protobuf/Parser.parseFrom:([B)Ljava/lang/Object;
       9: checkcast     #76                 // class org/apache/hadoop/yarn/proto/YarnProtos$NodeReportProto
      12: areturn

  public static org.apache.hadoop.yarn.proto.YarnProtos$NodeReportProto parseFrom(byte[], com.google.protobuf.ExtensionRegistryLite) throws com.google.protobuf.InvalidProtocolBufferException;
    Code:
       0: getstatic     #79                 // Field PARSER:Lcom/google/protobuf/Parser;
       3: aload_0
       4: aload_1
       5: invokeinterface #177,  3          // InterfaceMethod com/google/protobuf/Parser.parseFrom:([BLcom/google/protobuf/ExtensionRegistryLite;)Ljava/lang/Object;
      10: checkcast     #76                 // class org/apache/hadoop/yarn/proto/YarnProtos$NodeReportProto
      13: areturn

  public static org.apache.hadoop.yarn.proto.YarnProtos$NodeReportProto parseFrom(java.io.InputStream) throws java.io.IOException;
    Code:
       0: getstatic     #79                 // Field PARSER:Lcom/google/protobuf/Parser;
       3: aload_0
       4: invokeinterface #178,  2          // InterfaceMethod com/google/protobuf/Parser.parseFrom:(Ljava/io/InputStream;)Ljava/lang/Object;
       9: checkcast     #76                 // class org/apache/hadoop/yarn/proto/YarnProtos$NodeReportProto
      12: areturn

  public static org.apache.hadoop.yarn.proto.YarnProtos$NodeReportProto parseFrom(java.io.InputStream, com.google.protobuf.ExtensionRegistryLite) throws java.io.IOException;
    Code:
       0: getstatic     #79                 // Field PARSER:Lcom/google/protobuf/Parser;
       3: aload_0
       4: aload_1
       5: invokeinterface #179,  3          // InterfaceMethod com/google/protobuf/Parser.parseFrom:(Ljava/io/InputStream;Lcom/google/protobuf/ExtensionRegistryLite;)Ljava/lang/Object;
      10: checkcast     #76                 // class org/apache/hadoop/yarn/proto/YarnProtos$NodeReportProto
      13: areturn

  public static org.apache.hadoop.yarn.proto.YarnProtos$NodeReportProto parseDelimitedFrom(java.io.InputStream) throws java.io.IOException;
    Code:
       0: getstatic     #79                 // Field PARSER:Lcom/google/protobuf/Parser;
       3: aload_0
       4: invokeinterface #180,  2          // InterfaceMethod com/google/protobuf/Parser.parseDelimitedFrom:(Ljava/io/InputStream;)Ljava/lang/Object;
       9: checkcast     #76                 // class org/apache/hadoop/yarn/proto/YarnProtos$NodeReportProto
      12: areturn

  public static org.apache.hadoop.yarn.proto.YarnProtos$NodeReportProto parseDelimitedFrom(java.io.InputStream, com.google.protobuf.ExtensionRegistryLite) throws java.io.IOException;
    Code:
       0: getstatic     #79                 // Field PARSER:Lcom/google/protobuf/Parser;
       3: aload_0
       4: aload_1
       5: invokeinterface #181,  3          // InterfaceMethod com/google/protobuf/Parser.parseDelimitedFrom:(Ljava/io/InputStream;Lcom/google/protobuf/ExtensionRegistryLite;)Ljava/lang/Object;
      10: checkcast     #76                 // class org/apache/hadoop/yarn/proto/YarnProtos$NodeReportProto
      13: areturn

  public static org.apache.hadoop.yarn.proto.YarnProtos$NodeReportProto parseFrom(com.google.protobuf.CodedInputStream) throws java.io.IOException;
    Code:
       0: getstatic     #79                 // Field PARSER:Lcom/google/protobuf/Parser;
       3: aload_0
       4: invokeinterface #182,  2          // InterfaceMethod com/google/protobuf/Parser.parseFrom:(Lcom/google/protobuf/CodedInputStream;)Ljava/lang/Object;
       9: checkcast     #76                 // class org/apache/hadoop/yarn/proto/YarnProtos$NodeReportProto
      12: areturn

  public static org.apache.hadoop.yarn.proto.YarnProtos$NodeReportProto parseFrom(com.google.protobuf.CodedInputStream, com.google.protobuf.ExtensionRegistryLite) throws java.io.IOException;
    Code:
       0: getstatic     #79                 // Field PARSER:Lcom/google/protobuf/Parser;
       3: aload_0
       4: aload_1
       5: invokeinterface #183,  3          // InterfaceMethod com/google/protobuf/Parser.parseFrom:(Lcom/google/protobuf/CodedInputStream;Lcom/google/protobuf/ExtensionRegistryLite;)Ljava/lang/Object;
      10: checkcast     #76                 // class org/apache/hadoop/yarn/proto/YarnProtos$NodeReportProto
      13: areturn

  public static org.apache.hadoop.yarn.proto.YarnProtos$NodeReportProto$Builder newBuilder();
    Code:
       0: invokestatic  #184                // Method org/apache/hadoop/yarn/proto/YarnProtos$NodeReportProto$Builder.access$32500:()Lorg/apache/hadoop/yarn/proto/YarnProtos$NodeReportProto$Builder;
       3: areturn

  public org.apache.hadoop.yarn.proto.YarnProtos$NodeReportProto$Builder newBuilderForType();
    Code:
       0: invokestatic  #185                // Method newBuilder:()Lorg/apache/hadoop/yarn/proto/YarnProtos$NodeReportProto$Builder;
       3: areturn

  public static org.apache.hadoop.yarn.proto.YarnProtos$NodeReportProto$Builder newBuilder(org.apache.hadoop.yarn.proto.YarnProtos$NodeReportProto);
    Code:
       0: invokestatic  #185                // Method newBuilder:()Lorg/apache/hadoop/yarn/proto/YarnProtos$NodeReportProto$Builder;
       3: aload_0
       4: invokevirtual #186                // Method org/apache/hadoop/yarn/proto/YarnProtos$NodeReportProto$Builder.mergeFrom:(Lorg/apache/hadoop/yarn/proto/YarnProtos$NodeReportProto;)Lorg/apache/hadoop/yarn/proto/YarnProtos$NodeReportProto$Builder;
       7: areturn

  public org.apache.hadoop.yarn.proto.YarnProtos$NodeReportProto$Builder toBuilder();
    Code:
       0: aload_0
       1: invokestatic  #187                // Method newBuilder:(Lorg/apache/hadoop/yarn/proto/YarnProtos$NodeReportProto;)Lorg/apache/hadoop/yarn/proto/YarnProtos$NodeReportProto$Builder;
       4: areturn

  protected org.apache.hadoop.yarn.proto.YarnProtos$NodeReportProto$Builder newBuilderForType(com.google.protobuf.GeneratedMessage$BuilderParent);
    Code:
       0: new           #77                 // class org/apache/hadoop/yarn/proto/YarnProtos$NodeReportProto$Builder
       3: dup
       4: aload_1
       5: aconst_null
       6: invokespecial #188                // Method org/apache/hadoop/yarn/proto/YarnProtos$NodeReportProto$Builder."<init>":(Lcom/google/protobuf/GeneratedMessage$BuilderParent;Lorg/apache/hadoop/yarn/proto/YarnProtos$1;)V
       9: astore_2
      10: aload_2
      11: areturn

  protected com.google.protobuf.Message$Builder newBuilderForType(com.google.protobuf.GeneratedMessage$BuilderParent);
    Code:
       0: aload_0
       1: aload_1
       2: invokevirtual #189                // Method newBuilderForType:(Lcom/google/protobuf/GeneratedMessage$BuilderParent;)Lorg/apache/hadoop/yarn/proto/YarnProtos$NodeReportProto$Builder;
       5: areturn

  public com.google.protobuf.Message$Builder toBuilder();
    Code:
       0: aload_0
       1: invokevirtual #190                // Method toBuilder:()Lorg/apache/hadoop/yarn/proto/YarnProtos$NodeReportProto$Builder;
       4: areturn

  public com.google.protobuf.Message$Builder newBuilderForType();
    Code:
       0: aload_0
       1: invokevirtual #191                // Method newBuilderForType:()Lorg/apache/hadoop/yarn/proto/YarnProtos$NodeReportProto$Builder;
       4: areturn

  public com.google.protobuf.MessageLite$Builder toBuilder();
    Code:
       0: aload_0
       1: invokevirtual #190                // Method toBuilder:()Lorg/apache/hadoop/yarn/proto/YarnProtos$NodeReportProto$Builder;
       4: areturn

  public com.google.protobuf.MessageLite$Builder newBuilderForType();
    Code:
       0: aload_0
       1: invokevirtual #191                // Method newBuilderForType:()Lorg/apache/hadoop/yarn/proto/YarnProtos$NodeReportProto$Builder;
       4: areturn

  public com.google.protobuf.MessageLite getDefaultInstanceForType();
    Code:
       0: aload_0
       1: invokevirtual #192                // Method getDefaultInstanceForType:()Lorg/apache/hadoop/yarn/proto/YarnProtos$NodeReportProto;
       4: areturn

  public com.google.protobuf.Message getDefaultInstanceForType();
    Code:
       0: aload_0
       1: invokevirtual #192                // Method getDefaultInstanceForType:()Lorg/apache/hadoop/yarn/proto/YarnProtos$NodeReportProto;
       4: areturn

  org.apache.hadoop.yarn.proto.YarnProtos$NodeReportProto(com.google.protobuf.CodedInputStream, com.google.protobuf.ExtensionRegistryLite, org.apache.hadoop.yarn.proto.YarnProtos$1) throws com.google.protobuf.InvalidProtocolBufferException;
    Code:
       0: aload_0
       1: aload_1
       2: aload_2
       3: invokespecial #19                 // Method "<init>":(Lcom/google/protobuf/CodedInputStream;Lcom/google/protobuf/ExtensionRegistryLite;)V
       6: return

  static boolean access$32700();
    Code:
       0: getstatic     #1                  // Field alwaysUseFieldBuilders:Z
       3: ireturn

  org.apache.hadoop.yarn.proto.YarnProtos$NodeReportProto(com.google.protobuf.GeneratedMessage$Builder, org.apache.hadoop.yarn.proto.YarnProtos$1);
    Code:
       0: aload_0
       1: aload_1
       2: invokespecial #18                 // Method "<init>":(Lcom/google/protobuf/GeneratedMessage$Builder;)V
       5: return

  static org.apache.hadoop.yarn.proto.YarnProtos$NodeIdProto access$32902(org.apache.hadoop.yarn.proto.YarnProtos$NodeReportProto, org.apache.hadoop.yarn.proto.YarnProtos$NodeIdProto);
    Code:
       0: aload_0
       1: aload_1
       2: dup_x1
       3: putfield      #17                 // Field nodeId_:Lorg/apache/hadoop/yarn/proto/YarnProtos$NodeIdProto;
       6: areturn

  static java.lang.Object access$33002(org.apache.hadoop.yarn.proto.YarnProtos$NodeReportProto, java.lang.Object);
    Code:
       0: aload_0
       1: aload_1
       2: dup_x1
       3: putfield      #16                 // Field httpAddress_:Ljava/lang/Object;
       6: areturn

  static java.lang.Object access$33102(org.apache.hadoop.yarn.proto.YarnProtos$NodeReportProto, java.lang.Object);
    Code:
       0: aload_0
       1: aload_1
       2: dup_x1
       3: putfield      #15                 // Field rackName_:Ljava/lang/Object;
       6: areturn

  static org.apache.hadoop.yarn.proto.YarnProtos$ResourceProto access$33202(org.apache.hadoop.yarn.proto.YarnProtos$NodeReportProto, org.apache.hadoop.yarn.proto.YarnProtos$ResourceProto);
    Code:
       0: aload_0
       1: aload_1
       2: dup_x1
       3: putfield      #14                 // Field used_:Lorg/apache/hadoop/yarn/proto/YarnProtos$ResourceProto;
       6: areturn

  static org.apache.hadoop.yarn.proto.YarnProtos$ResourceProto access$33302(org.apache.hadoop.yarn.proto.YarnProtos$NodeReportProto, org.apache.hadoop.yarn.proto.YarnProtos$ResourceProto);
    Code:
       0: aload_0
       1: aload_1
       2: dup_x1
       3: putfield      #13                 // Field capability_:Lorg/apache/hadoop/yarn/proto/YarnProtos$ResourceProto;
       6: areturn

  static int access$33402(org.apache.hadoop.yarn.proto.YarnProtos$NodeReportProto, int);
    Code:
       0: aload_0
       1: iload_1
       2: dup_x1
       3: putfield      #12                 // Field numContainers_:I
       6: ireturn

  static org.apache.hadoop.yarn.proto.YarnProtos$NodeStateProto access$33502(org.apache.hadoop.yarn.proto.YarnProtos$NodeReportProto, org.apache.hadoop.yarn.proto.YarnProtos$NodeStateProto);
    Code:
       0: aload_0
       1: aload_1
       2: dup_x1
       3: putfield      #11                 // Field nodeState_:Lorg/apache/hadoop/yarn/proto/YarnProtos$NodeStateProto;
       6: areturn

  static java.lang.Object access$33602(org.apache.hadoop.yarn.proto.YarnProtos$NodeReportProto, java.lang.Object);
    Code:
       0: aload_0
       1: aload_1
       2: dup_x1
       3: putfield      #10                 // Field healthReport_:Ljava/lang/Object;
       6: areturn

  static long access$33702(org.apache.hadoop.yarn.proto.YarnProtos$NodeReportProto, long);
    Code:
       0: aload_0
       1: lload_1
       2: dup2_x1
       3: putfield      #9                  // Field lastHealthReportTime_:J
       6: lreturn

  static com.google.protobuf.LazyStringList access$33802(org.apache.hadoop.yarn.proto.YarnProtos$NodeReportProto, com.google.protobuf.LazyStringList);
    Code:
       0: aload_0
       1: aload_1
       2: dup_x1
       3: putfield      #8                  // Field nodeLabels_:Lcom/google/protobuf/LazyStringList;
       6: areturn

  static org.apache.hadoop.yarn.proto.YarnProtos$ResourceUtilizationProto access$33902(org.apache.hadoop.yarn.proto.YarnProtos$NodeReportProto, org.apache.hadoop.yarn.proto.YarnProtos$ResourceUtilizationProto);
    Code:
       0: aload_0
       1: aload_1
       2: dup_x1
       3: putfield      #7                  // Field containersUtilization_:Lorg/apache/hadoop/yarn/proto/YarnProtos$ResourceUtilizationProto;
       6: areturn

  static org.apache.hadoop.yarn.proto.YarnProtos$ResourceUtilizationProto access$34002(org.apache.hadoop.yarn.proto.YarnProtos$NodeReportProto, org.apache.hadoop.yarn.proto.YarnProtos$ResourceUtilizationProto);
    Code:
       0: aload_0
       1: aload_1
       2: dup_x1
       3: putfield      #6                  // Field nodeUtilization_:Lorg/apache/hadoop/yarn/proto/YarnProtos$ResourceUtilizationProto;
       6: areturn

  static int access$34102(org.apache.hadoop.yarn.proto.YarnProtos$NodeReportProto, int);
    Code:
       0: aload_0
       1: iload_1
       2: dup_x1
       3: putfield      #5                  // Field decommissioningTimeout_:I
       6: ireturn

  static org.apache.hadoop.yarn.proto.YarnProtos$NodeUpdateTypeProto access$34202(org.apache.hadoop.yarn.proto.YarnProtos$NodeReportProto, org.apache.hadoop.yarn.proto.YarnProtos$NodeUpdateTypeProto);
    Code:
       0: aload_0
       1: aload_1
       2: dup_x1
       3: putfield      #4                  // Field nodeUpdateType_:Lorg/apache/hadoop/yarn/proto/YarnProtos$NodeUpdateTypeProto;
       6: areturn

  static java.util.List access$34302(org.apache.hadoop.yarn.proto.YarnProtos$NodeReportProto, java.util.List);
    Code:
       0: aload_0
       1: aload_1
       2: dup_x1
       3: putfield      #3                  // Field nodeAttributes_:Ljava/util/List;
       6: areturn

  static int access$34402(org.apache.hadoop.yarn.proto.YarnProtos$NodeReportProto, int);
    Code:
       0: aload_0
       1: iload_1
       2: dup_x1
       3: putfield      #2                  // Field bitField0_:I
       6: ireturn

  static java.lang.Object access$33000(org.apache.hadoop.yarn.proto.YarnProtos$NodeReportProto);
    Code:
       0: aload_0
       1: getfield      #16                 // Field httpAddress_:Ljava/lang/Object;
       4: areturn

  static java.lang.Object access$33100(org.apache.hadoop.yarn.proto.YarnProtos$NodeReportProto);
    Code:
       0: aload_0
       1: getfield      #15                 // Field rackName_:Ljava/lang/Object;
       4: areturn

  static java.lang.Object access$33600(org.apache.hadoop.yarn.proto.YarnProtos$NodeReportProto);
    Code:
       0: aload_0
       1: getfield      #10                 // Field healthReport_:Ljava/lang/Object;
       4: areturn

  static com.google.protobuf.LazyStringList access$33800(org.apache.hadoop.yarn.proto.YarnProtos$NodeReportProto);
    Code:
       0: aload_0
       1: getfield      #8                  // Field nodeLabels_:Lcom/google/protobuf/LazyStringList;
       4: areturn

  static java.util.List access$34300(org.apache.hadoop.yarn.proto.YarnProtos$NodeReportProto);
    Code:
       0: aload_0
       1: getfield      #3                  // Field nodeAttributes_:Ljava/util/List;
       4: areturn

  static boolean access$34500();
    Code:
       0: getstatic     #1                  // Field alwaysUseFieldBuilders:Z
       3: ireturn

  static {};
    Code:
       0: new           #193                // class org/apache/hadoop/yarn/proto/YarnProtos$NodeReportProto$1
       3: dup
       4: invokespecial #194                // Method org/apache/hadoop/yarn/proto/YarnProtos$NodeReportProto$1."<init>":()V
       7: putstatic     #79                 // Field PARSER:Lcom/google/protobuf/Parser;
      10: new           #76                 // class org/apache/hadoop/yarn/proto/YarnProtos$NodeReportProto
      13: dup
      14: iconst_1
      15: invokespecial #195                // Method "<init>":(Z)V
      18: putstatic     #28                 // Field defaultInstance:Lorg/apache/hadoop/yarn/proto/YarnProtos$NodeReportProto;
      21: getstatic     #28                 // Field defaultInstance:Lorg/apache/hadoop/yarn/proto/YarnProtos$NodeReportProto;
      24: invokespecial #29                 // Method initFields:()V
      27: return
}
