Compiled from "OptimisticLockFailureException.java"
public class org.leo.aws.ddb.exceptions.OptimisticLockFailureException extends org.leo.aws.ddb.exceptions.DbException {
  public org.leo.aws.ddb.exceptions.OptimisticLockFailureException();
    Code:
       0: aload_0
       1: getstatic     #9                  // Field org/leo/aws/ddb/utils/exceptions/Issue.OPTIMISTIC_LOCK_ERROR:Lorg/leo/aws/ddb/utils/exceptions/Issue;
       4: invokevirtual #15                 // Method org/leo/aws/ddb/utils/exceptions/Issue.name:()Ljava/lang/String;
       7: invokespecial #19                 // Method org/leo/aws/ddb/exceptions/DbException."<init>":(Ljava/lang/String;)V
      10: return

  public org.leo.aws.ddb.exceptions.OptimisticLockFailureException(java.lang.Throwable);
    Code:
       0: aload_0
       1: getstatic     #9                  // Field org/leo/aws/ddb/utils/exceptions/Issue.OPTIMISTIC_LOCK_ERROR:Lorg/leo/aws/ddb/utils/exceptions/Issue;
       4: invokevirtual #15                 // Method org/leo/aws/ddb/utils/exceptions/Issue.name:()Ljava/lang/String;
       7: aload_1
       8: invokespecial #27                 // Method org/leo/aws/ddb/exceptions/DbException."<init>":(Ljava/lang/String;Ljava/lang/Throwable;)V
      11: return

  public org.leo.aws.ddb.exceptions.OptimisticLockFailureException(java.lang.Throwable, boolean, boolean);
    Code:
       0: aload_0
       1: getstatic     #9                  // Field org/leo/aws/ddb/utils/exceptions/Issue.OPTIMISTIC_LOCK_ERROR:Lorg/leo/aws/ddb/utils/exceptions/Issue;
       4: invokevirtual #15                 // Method org/leo/aws/ddb/utils/exceptions/Issue.name:()Ljava/lang/String;
       7: aload_1
       8: iload_2
       9: iload_3
      10: invokespecial #33                 // Method org/leo/aws/ddb/exceptions/DbException."<init>":(Ljava/lang/String;Ljava/lang/Throwable;ZZ)V
      13: return
}
