Compiled from "SimpleAlarmListenerForm.java"
class org.mobicents.protocols.ss7.oam.tools.alarmlistener.SimpleAlarmListenerForm$7 extends javax.swing.table.DefaultTableModel {
  java.lang.Class[] columnTypes;

  boolean[] columnEditables;

  final org.mobicents.protocols.ss7.oam.tools.alarmlistener.SimpleAlarmListenerForm this$0;

  org.mobicents.protocols.ss7.oam.tools.alarmlistener.SimpleAlarmListenerForm$7(org.mobicents.protocols.ss7.oam.tools.alarmlistener.SimpleAlarmListenerForm, java.lang.Object[][], java.lang.Object[]);
    Code:
       0: aload_0
       1: aload_1
       2: putfield      #1                  // Field this$0:Lorg/mobicents/protocols/ss7/oam/tools/alarmlistener/SimpleAlarmListenerForm;
       5: aload_0
       6: aload_2
       7: aload_3
       8: invokespecial #2                  // Method javax/swing/table/DefaultTableModel."<init>":([[Ljava/lang/Object;[Ljava/lang/Object;)V
      11: aload_0
      12: bipush        9
      14: anewarray     #3                  // class java/lang/Class
      17: dup
      18: iconst_0
      19: ldc_w         #4                  // class java/lang/String
      22: aastore
      23: dup
      24: iconst_1
      25: ldc_w         #4                  // class java/lang/String
      28: aastore
      29: dup
      30: iconst_2
      31: ldc_w         #4                  // class java/lang/String
      34: aastore
      35: dup
      36: iconst_3
      37: ldc_w         #4                  // class java/lang/String
      40: aastore
      41: dup
      42: iconst_4
      43: ldc_w         #4                  // class java/lang/String
      46: aastore
      47: dup
      48: iconst_5
      49: ldc_w         #4                  // class java/lang/String
      52: aastore
      53: dup
      54: bipush        6
      56: ldc_w         #4                  // class java/lang/String
      59: aastore
      60: dup
      61: bipush        7
      63: ldc_w         #4                  // class java/lang/String
      66: aastore
      67: dup
      68: bipush        8
      70: ldc_w         #4                  // class java/lang/String
      73: aastore
      74: putfield      #5                  // Field columnTypes:[Ljava/lang/Class;
      77: aload_0
      78: bipush        9
      80: newarray       boolean
      82: dup
      83: iconst_0
      84: iconst_0
      85: bastore
      86: dup
      87: iconst_1
      88: iconst_0
      89: bastore
      90: dup
      91: iconst_2
      92: iconst_0
      93: bastore
      94: dup
      95: iconst_3
      96: iconst_0
      97: bastore
      98: dup
      99: iconst_4
     100: iconst_0
     101: bastore
     102: dup
     103: iconst_5
     104: iconst_0
     105: bastore
     106: dup
     107: bipush        6
     109: iconst_0
     110: bastore
     111: dup
     112: bipush        7
     114: iconst_0
     115: bastore
     116: dup
     117: bipush        8
     119: iconst_0
     120: bastore
     121: putfield      #6                  // Field columnEditables:[Z
     124: return

  public java.lang.Class getColumnClass(int);
    Code:
       0: aload_0
       1: getfield      #5                  // Field columnTypes:[Ljava/lang/Class;
       4: iload_1
       5: aaload
       6: areturn

  public boolean isCellEditable(int, int);
    Code:
       0: aload_0
       1: getfield      #6                  // Field columnEditables:[Z
       4: iload_2
       5: baload
       6: ireturn
}
