Compiled from "ClientHSSecurityInfo.java"
class org.apache.hadoop.mapreduce.v2.security.client.ClientHSSecurityInfo$2 implements org.apache.hadoop.security.token.TokenInfo {
  final org.apache.hadoop.mapreduce.v2.security.client.ClientHSSecurityInfo this$0;

  org.apache.hadoop.mapreduce.v2.security.client.ClientHSSecurityInfo$2(org.apache.hadoop.mapreduce.v2.security.client.ClientHSSecurityInfo);
    Code:
       0: aload_0
       1: aload_1
       2: putfield      #1                  // Field this$0:Lorg/apache/hadoop/mapreduce/v2/security/client/ClientHSSecurityInfo;
       5: aload_0
       6: invokespecial #2                  // Method java/lang/Object."<init>":()V
       9: return

  public java.lang.Class<? extends java.lang.annotation.Annotation> annotationType();
    Code:
       0: aconst_null
       1: areturn

  public java.lang.Class<? extends org.apache.hadoop.security.token.TokenSelector<? extends org.apache.hadoop.security.token.TokenIdentifier>> value();
    Code:
       0: ldc           #3                  // class org/apache/hadoop/mapreduce/v2/security/client/ClientHSTokenSelector
       2: areturn
}
