Compiled from "AbstractOWLTreeAction.java"
public abstract class org.protege.editor.owl.ui.action.AbstractOWLTreeAction<E extends org.semanticweb.owlapi.model.OWLEntity> extends org.protege.editor.core.ui.view.DisposableAction implements org.protege.editor.core.HasUpdateState {
  private javax.swing.tree.TreeSelectionModel selectionModel;

  private javax.swing.event.TreeSelectionListener selectionListener;

  public org.protege.editor.owl.ui.action.AbstractOWLTreeAction(java.lang.String, javax.swing.Icon, javax.swing.tree.TreeSelectionModel);
    Code:
       0: aload_0
       1: aload_1
       2: aload_2
       3: invokespecial #1                  // Method org/protege/editor/core/ui/view/DisposableAction."<init>":(Ljava/lang/String;Ljavax/swing/Icon;)V
       6: aload_0
       7: aload_3
       8: putfield      #2                  // Field selectionModel:Ljavax/swing/tree/TreeSelectionModel;
      11: aload_0
      12: aload_0
      13: invokedynamic #3,  0              // InvokeDynamic #0:valueChanged:(Lorg/protege/editor/owl/ui/action/AbstractOWLTreeAction;)Ljavax/swing/event/TreeSelectionListener;
      18: putfield      #4                  // Field selectionListener:Ljavax/swing/event/TreeSelectionListener;
      21: aload_3
      22: aload_0
      23: getfield      #4                  // Field selectionListener:Ljavax/swing/event/TreeSelectionListener;
      26: invokeinterface #5,  2            // InterfaceMethod javax/swing/tree/TreeSelectionModel.addTreeSelectionListener:(Ljavax/swing/event/TreeSelectionListener;)V
      31: aload_0
      32: aload_0
      33: aload_0
      34: invokevirtual #6                  // Method getSelectedOWLEntity:()Lorg/semanticweb/owlapi/model/OWLEntity;
      37: invokevirtual #7                  // Method canPerform:(Lorg/semanticweb/owlapi/model/OWLEntity;)Z
      40: invokevirtual #8                  // Method setEnabled:(Z)V
      43: return

  public void updateState();
    Code:
       0: aload_0
       1: aload_0
       2: aload_0
       3: invokevirtual #6                  // Method getSelectedOWLEntity:()Lorg/semanticweb/owlapi/model/OWLEntity;
       6: invokevirtual #7                  // Method canPerform:(Lorg/semanticweb/owlapi/model/OWLEntity;)Z
       9: invokevirtual #8                  // Method setEnabled:(Z)V
      12: return

  private void reactToSelection();
    Code:
       0: aload_0
       1: invokevirtual #9                  // Method updateState:()V
       4: return

  protected abstract boolean canPerform(E);

  protected javax.swing.tree.TreePath getSelectionPath();
    Code:
       0: aload_0
       1: getfield      #2                  // Field selectionModel:Ljavax/swing/tree/TreeSelectionModel;
       4: invokeinterface #10,  1           // InterfaceMethod javax/swing/tree/TreeSelectionModel.getSelectionPath:()Ljavax/swing/tree/TreePath;
       9: areturn

  protected void setSelectionPath(javax.swing.tree.TreePath);
    Code:
       0: aload_0
       1: getfield      #2                  // Field selectionModel:Ljavax/swing/tree/TreeSelectionModel;
       4: aload_1
       5: invokeinterface #11,  2           // InterfaceMethod javax/swing/tree/TreeSelectionModel.setSelectionPath:(Ljavax/swing/tree/TreePath;)V
      10: return

  protected E getSelectedOWLEntity();
    Code:
       0: aload_0
       1: getfield      #2                  // Field selectionModel:Ljavax/swing/tree/TreeSelectionModel;
       4: invokeinterface #10,  1           // InterfaceMethod javax/swing/tree/TreeSelectionModel.getSelectionPath:()Ljavax/swing/tree/TreePath;
       9: astore_1
      10: aload_1
      11: ifnonnull     16
      14: aconst_null
      15: areturn
      16: aload_1
      17: invokevirtual #12                 // Method javax/swing/tree/TreePath.getLastPathComponent:()Ljava/lang/Object;
      20: checkcast     #13                 // class org/protege/editor/owl/ui/tree/OWLObjectTreeNode
      23: invokevirtual #14                 // Method org/protege/editor/owl/ui/tree/OWLObjectTreeNode.getUserObject:()Ljava/lang/Object;
      26: checkcast     #15                 // class org/semanticweb/owlapi/model/OWLEntity
      29: areturn

  public void dispose();
    Code:
       0: aload_0
       1: getfield      #2                  // Field selectionModel:Ljavax/swing/tree/TreeSelectionModel;
       4: aload_0
       5: getfield      #4                  // Field selectionListener:Ljavax/swing/event/TreeSelectionListener;
       8: invokeinterface #16,  2           // InterfaceMethod javax/swing/tree/TreeSelectionModel.removeTreeSelectionListener:(Ljavax/swing/event/TreeSelectionListener;)V
      13: return

  public void initialise() throws java.lang.Exception;
    Code:
       0: return

  private void lambda$new$0(javax.swing.event.TreeSelectionEvent);
    Code:
       0: aload_0
       1: invokespecial #17                 // Method reactToSelection:()V
       4: return
}
