Compiled from "CopySubHierarchyToClipboardAction.java"
public class org.protege.editor.owl.ui.action.CopySubHierarchyToClipboardAction extends org.protege.editor.owl.ui.action.FocusedComponentAction<org.protege.editor.owl.ui.view.HasCopySubHierarchyToClipboard> {
  public org.protege.editor.owl.ui.action.CopySubHierarchyToClipboardAction();
    Code:
       0: aload_0
       1: invokespecial #1                  // Method org/protege/editor/owl/ui/action/FocusedComponentAction."<init>":()V
       4: return

  protected java.lang.Class<org.protege.editor.owl.ui.view.HasCopySubHierarchyToClipboard> initialiseAction();
    Code:
       0: ldc           #2                  // class org/protege/editor/owl/ui/view/HasCopySubHierarchyToClipboard
       2: areturn

  protected boolean canPerform();
    Code:
       0: aload_0
       1: invokevirtual #3                  // Method getCurrentTarget:()Lorg/protege/editor/owl/ui/action/ActionTarget;
       4: checkcast     #2                  // class org/protege/editor/owl/ui/view/HasCopySubHierarchyToClipboard
       7: invokeinterface #4,  1            // InterfaceMethod org/protege/editor/owl/ui/view/HasCopySubHierarchyToClipboard.canPerformCopySubHierarchyToClipboard:()Z
      12: ireturn

  public void actionPerformed(java.awt.event.ActionEvent);
    Code:
       0: aload_0
       1: invokevirtual #3                  // Method getCurrentTarget:()Lorg/protege/editor/owl/ui/action/ActionTarget;
       4: checkcast     #2                  // class org/protege/editor/owl/ui/view/HasCopySubHierarchyToClipboard
       7: invokeinterface #5,  1            // InterfaceMethod org/protege/editor/owl/ui/view/HasCopySubHierarchyToClipboard.copySubHierarchyToClipboard:()V
      12: return
}
