Compiled from "MoveAxiomsToOntologyAction.java"
public class org.protege.editor.owl.ui.action.MoveAxiomsToOntologyAction extends org.protege.editor.owl.ui.action.ProtegeOWLAction {
  private org.slf4j.Logger logger;

  public org.protege.editor.owl.ui.action.MoveAxiomsToOntologyAction();
    Code:
       0: aload_0
       1: invokespecial #1                  // Method org/protege/editor/owl/ui/action/ProtegeOWLAction."<init>":()V
       4: aload_0
       5: ldc           #2                  // class org/protege/editor/owl/ui/action/MoveAxiomsToOntologyAction
       7: invokestatic  #3                  // Method org/slf4j/LoggerFactory.getLogger:(Ljava/lang/Class;)Lorg/slf4j/Logger;
      10: putfield      #4                  // Field logger:Lorg/slf4j/Logger;
      13: return

  public void actionPerformed(java.awt.event.ActionEvent);
    Code:
       0: new           #5                  // class org/protege/editor/owl/ui/ontology/wizard/move/MoveAxiomsWizard
       3: dup
       4: aload_0
       5: invokevirtual #6                  // Method getOWLEditorKit:()Lorg/protege/editor/owl/OWLEditorKit;
       8: invokespecial #7                  // Method org/protege/editor/owl/ui/ontology/wizard/move/MoveAxiomsWizard."<init>":(Lorg/protege/editor/owl/OWLEditorKit;)V
      11: astore_2
      12: aload_2
      13: invokevirtual #8                  // Method org/protege/editor/owl/ui/ontology/wizard/move/MoveAxiomsWizard.showModalDialog:()I
      16: ifne          39
      19: aload_2
      20: invokevirtual #9                  // Method org/protege/editor/owl/ui/ontology/wizard/move/MoveAxiomsWizard.applyChanges:()V
      23: goto          39
      26: astore_3
      27: aload_0
      28: getfield      #4                  // Field logger:Lorg/slf4j/Logger;
      31: ldc           #11                 // String An error occurred whilst applying the changes to move axiom to ontology.
      33: aload_3
      34: invokeinterface #12,  3           // InterfaceMethod org/slf4j/Logger.error:(Ljava/lang/String;Ljava/lang/Throwable;)V
      39: aload_2
      40: invokevirtual #13                 // Method org/protege/editor/owl/ui/ontology/wizard/move/MoveAxiomsWizard.dispose:()V
      43: return
    Exception table:
       from    to  target type
          19    23    26   Class org/semanticweb/owlapi/model/OWLOntologyCreationException

  public void initialise() throws java.lang.Exception;
    Code:
       0: return

  public void dispose() throws java.lang.Exception;
    Code:
       0: return
}
