Compiled from "OWLObjectHierarchyCreator.java"
public abstract class org.protege.editor.owl.ui.action.OWLObjectHierarchyCreator<E extends org.semanticweb.owlapi.model.OWLEntity> {
  private org.protege.editor.owl.OWLEditorKit editorKit;

  private org.semanticweb.owlapi.util.OWLEntitySetProvider<E> entitySetProvider;

  private org.protege.editor.owl.model.hierarchy.OWLObjectHierarchyProvider<E> hierarchyProvider;

  protected org.protege.editor.owl.ui.action.OWLObjectHierarchyCreator(org.protege.editor.owl.OWLEditorKit, org.semanticweb.owlapi.util.OWLEntitySetProvider<E>, org.protege.editor.owl.model.hierarchy.OWLObjectHierarchyProvider<E>);
    Code:
       0: aload_0
       1: invokespecial #1                  // Method java/lang/Object."<init>":()V
       4: aload_0
       5: aload_1
       6: putfield      #2                  // Field editorKit:Lorg/protege/editor/owl/OWLEditorKit;
       9: aload_0
      10: aload_2
      11: putfield      #3                  // Field entitySetProvider:Lorg/semanticweb/owlapi/util/OWLEntitySetProvider;
      14: aload_0
      15: aload_3
      16: putfield      #4                  // Field hierarchyProvider:Lorg/protege/editor/owl/model/hierarchy/OWLObjectHierarchyProvider;
      19: return

  public abstract org.protege.editor.owl.model.entity.OWLEntityCreationSet<E> createEntity();

  public void createNewEntity();
    Code:
       0: aload_0
       1: invokevirtual #5                  // Method createEntity:()Lorg/protege/editor/owl/model/entity/OWLEntityCreationSet;
       4: astore_1
       5: aload_0
       6: getfield      #2                  // Field editorKit:Lorg/protege/editor/owl/OWLEditorKit;
       9: invokevirtual #6                  // Method org/protege/editor/owl/OWLEditorKit.getModelManager:()Lorg/protege/editor/owl/model/OWLModelManager;
      12: aload_1
      13: invokevirtual #7                  // Method org/protege/editor/owl/model/entity/OWLEntityCreationSet.getOntologyChanges:()Ljava/util/List;
      16: invokeinterface #8,  2            // InterfaceMethod org/protege/editor/owl/model/OWLModelManager.applyChanges:(Ljava/util/List;)V
      21: return

  public void createChildEntity();
    Code:
       0: aload_0
       1: invokevirtual #5                  // Method createEntity:()Lorg/protege/editor/owl/model/entity/OWLEntityCreationSet;
       4: astore_1
       5: new           #9                  // class java/util/ArrayList
       8: dup
       9: invokespecial #10                 // Method java/util/ArrayList."<init>":()V
      12: astore_2
      13: aload_2
      14: aload_2
      15: invokeinterface #11,  2           // InterfaceMethod java/util/List.addAll:(Ljava/util/Collection;)Z
      20: pop
      21: aload_2
      22: aload_0
      23: aload_0
      24: getfield      #3                  // Field entitySetProvider:Lorg/semanticweb/owlapi/util/OWLEntitySetProvider;
      27: invokeinterface #12,  1           // InterfaceMethod org/semanticweb/owlapi/util/OWLEntitySetProvider.getEntities:()Ljava/util/Set;
      32: aload_1
      33: invokevirtual #13                 // Method org/protege/editor/owl/model/entity/OWLEntityCreationSet.getOWLEntity:()Lorg/semanticweb/owlapi/model/OWLEntity;
      36: invokevirtual #14                 // Method createChild:(Ljava/util/Set;Lorg/semanticweb/owlapi/model/OWLEntity;)Ljava/util/List;
      39: invokeinterface #11,  2           // InterfaceMethod java/util/List.addAll:(Ljava/util/Collection;)Z
      44: pop
      45: aload_0
      46: getfield      #2                  // Field editorKit:Lorg/protege/editor/owl/OWLEditorKit;
      49: invokevirtual #6                  // Method org/protege/editor/owl/OWLEditorKit.getModelManager:()Lorg/protege/editor/owl/model/OWLModelManager;
      52: aload_2
      53: invokeinterface #8,  2            // InterfaceMethod org/protege/editor/owl/model/OWLModelManager.applyChanges:(Ljava/util/List;)V
      58: return

  protected abstract java.util.List<org.semanticweb.owlapi.model.OWLOntologyChange> createChild(java.util.Set<E>, E);

  protected abstract java.util.List<org.semanticweb.owlapi.model.OWLOntologyChange> createSibling(java.util.Set<E>, E);
}
