Compiled from "HSSKeyGenerationParameters.java"
public class org.bouncycastle.pqc.crypto.lms.HSSKeyGenerationParameters extends org.bouncycastle.crypto.KeyGenerationParameters {
  private final org.bouncycastle.pqc.crypto.lms.LMSParameters[] lmsParameters;

  public org.bouncycastle.pqc.crypto.lms.HSSKeyGenerationParameters(org.bouncycastle.pqc.crypto.lms.LMSParameters[], java.security.SecureRandom);
    Code:
       0: aload_0
       1: aload_2
       2: aload_1
       3: iconst_0
       4: aaload
       5: invokestatic  #1                  // Method org/bouncycastle/pqc/crypto/lms/LmsUtils.calculateStrength:(Lorg/bouncycastle/pqc/crypto/lms/LMSParameters;)I
       8: invokespecial #2                  // Method org/bouncycastle/crypto/KeyGenerationParameters."<init>":(Ljava/security/SecureRandom;I)V
      11: aload_1
      12: arraylength
      13: ifeq          23
      16: aload_1
      17: arraylength
      18: bipush        8
      20: if_icmple     33
      23: new           #3                  // class java/lang/IllegalArgumentException
      26: dup
      27: ldc           #4                  // String lmsParameters length should be between 1 and 8 inclusive
      29: invokespecial #5                  // Method java/lang/IllegalArgumentException."<init>":(Ljava/lang/String;)V
      32: athrow
      33: aload_0
      34: aload_1
      35: putfield      #6                  // Field lmsParameters:[Lorg/bouncycastle/pqc/crypto/lms/LMSParameters;
      38: return

  public int getDepth();
    Code:
       0: aload_0
       1: getfield      #6                  // Field lmsParameters:[Lorg/bouncycastle/pqc/crypto/lms/LMSParameters;
       4: arraylength
       5: ireturn

  public org.bouncycastle.pqc.crypto.lms.LMSParameters[] getLmsParameters();
    Code:
       0: aload_0
       1: getfield      #6                  // Field lmsParameters:[Lorg/bouncycastle/pqc/crypto/lms/LMSParameters;
       4: areturn
}
