Compiled from "Http2ConnectionHandler.java"
final class io.netty.handler.codec.http2.Http2ConnectionHandler$PrefaceDecoder extends io.netty.handler.codec.http2.Http2ConnectionHandler$BaseDecoder {
  private io.netty.buffer.ByteBuf clientPrefaceString;

  private boolean prefaceSent;

  final io.netty.handler.codec.http2.Http2ConnectionHandler this$0;

  public io.netty.handler.codec.http2.Http2ConnectionHandler$PrefaceDecoder(io.netty.handler.codec.http2.Http2ConnectionHandler, io.netty.channel.ChannelHandlerContext);
    Code:
       0: aload_0
       1: aload_1
       2: putfield      #2                  // Field this$0:Lio/netty/handler/codec/http2/Http2ConnectionHandler;
       5: aload_0
       6: aload_1
       7: aconst_null
       8: invokespecial #3                  // Method io/netty/handler/codec/http2/Http2ConnectionHandler$BaseDecoder."<init>":(Lio/netty/handler/codec/http2/Http2ConnectionHandler;Lio/netty/handler/codec/http2/Http2ConnectionHandler$1;)V
      11: aload_0
      12: aload_1
      13: invokestatic  #4                  // Method io/netty/handler/codec/http2/Http2ConnectionHandler.access$100:(Lio/netty/handler/codec/http2/Http2ConnectionHandler;)Lio/netty/handler/codec/http2/Http2ConnectionEncoder;
      16: invokeinterface #5,  1            // InterfaceMethod io/netty/handler/codec/http2/Http2ConnectionEncoder.connection:()Lio/netty/handler/codec/http2/Http2Connection;
      21: invokestatic  #6                  // Method io/netty/handler/codec/http2/Http2ConnectionHandler.access$200:(Lio/netty/handler/codec/http2/Http2Connection;)Lio/netty/buffer/ByteBuf;
      24: putfield      #7                  // Field clientPrefaceString:Lio/netty/buffer/ByteBuf;
      27: aload_0
      28: aload_2
      29: invokespecial #8                  // Method sendPreface:(Lio/netty/channel/ChannelHandlerContext;)V
      32: return

  public boolean prefaceSent();
    Code:
       0: aload_0
       1: getfield      #9                  // Field prefaceSent:Z
       4: ireturn

  public void decode(io.netty.channel.ChannelHandlerContext, io.netty.buffer.ByteBuf, java.util.List<java.lang.Object>) throws java.lang.Exception;
    Code:
       0: aload_1
       1: invokeinterface #10,  1           // InterfaceMethod io/netty/channel/ChannelHandlerContext.channel:()Lio/netty/channel/Channel;
       6: invokeinterface #11,  1           // InterfaceMethod io/netty/channel/Channel.isActive:()Z
      11: ifeq          63
      14: aload_0
      15: aload_2
      16: invokespecial #12                 // Method readClientPrefaceString:(Lio/netty/buffer/ByteBuf;)Z
      19: ifeq          63
      22: aload_0
      23: aload_2
      24: invokespecial #13                 // Method verifyFirstFrameIsSettings:(Lio/netty/buffer/ByteBuf;)Z
      27: ifeq          63
      30: aload_0
      31: getfield      #2                  // Field this$0:Lio/netty/handler/codec/http2/Http2ConnectionHandler;
      34: new           #14                 // class io/netty/handler/codec/http2/Http2ConnectionHandler$FrameDecoder
      37: dup
      38: aload_0
      39: getfield      #2                  // Field this$0:Lio/netty/handler/codec/http2/Http2ConnectionHandler;
      42: aconst_null
      43: invokespecial #15                 // Method io/netty/handler/codec/http2/Http2ConnectionHandler$FrameDecoder."<init>":(Lio/netty/handler/codec/http2/Http2ConnectionHandler;Lio/netty/handler/codec/http2/Http2ConnectionHandler$1;)V
      46: invokestatic  #16                 // Method io/netty/handler/codec/http2/Http2ConnectionHandler.access$302:(Lio/netty/handler/codec/http2/Http2ConnectionHandler;Lio/netty/handler/codec/http2/Http2ConnectionHandler$BaseDecoder;)Lio/netty/handler/codec/http2/Http2ConnectionHandler$BaseDecoder;
      49: pop
      50: aload_0
      51: getfield      #2                  // Field this$0:Lio/netty/handler/codec/http2/Http2ConnectionHandler;
      54: invokestatic  #17                 // Method io/netty/handler/codec/http2/Http2ConnectionHandler.access$300:(Lio/netty/handler/codec/http2/Http2ConnectionHandler;)Lio/netty/handler/codec/http2/Http2ConnectionHandler$BaseDecoder;
      57: aload_1
      58: aload_2
      59: aload_3
      60: invokevirtual #18                 // Method io/netty/handler/codec/http2/Http2ConnectionHandler$BaseDecoder.decode:(Lio/netty/channel/ChannelHandlerContext;Lio/netty/buffer/ByteBuf;Ljava/util/List;)V
      63: goto          78
      66: astore        4
      68: aload_0
      69: getfield      #2                  // Field this$0:Lio/netty/handler/codec/http2/Http2ConnectionHandler;
      72: aload_1
      73: aload         4
      75: invokevirtual #20                 // Method io/netty/handler/codec/http2/Http2ConnectionHandler.onError:(Lio/netty/channel/ChannelHandlerContext;Ljava/lang/Throwable;)V
      78: return
    Exception table:
       from    to  target type
           0    63    66   Class java/lang/Throwable

  public void channelActive(io.netty.channel.ChannelHandlerContext) throws java.lang.Exception;
    Code:
       0: aload_0
       1: aload_1
       2: invokespecial #8                  // Method sendPreface:(Lio/netty/channel/ChannelHandlerContext;)V
       5: return

  public void channelInactive(io.netty.channel.ChannelHandlerContext) throws java.lang.Exception;
    Code:
       0: aload_0
       1: invokespecial #21                 // Method cleanup:()V
       4: aload_0
       5: aload_1
       6: invokespecial #22                 // Method io/netty/handler/codec/http2/Http2ConnectionHandler$BaseDecoder.channelInactive:(Lio/netty/channel/ChannelHandlerContext;)V
       9: return

  public void handlerRemoved(io.netty.channel.ChannelHandlerContext) throws java.lang.Exception;
    Code:
       0: aload_0
       1: invokespecial #21                 // Method cleanup:()V
       4: return

  private void cleanup();
    Code:
       0: aload_0
       1: getfield      #7                  // Field clientPrefaceString:Lio/netty/buffer/ByteBuf;
       4: ifnull        20
       7: aload_0
       8: getfield      #7                  // Field clientPrefaceString:Lio/netty/buffer/ByteBuf;
      11: invokevirtual #23                 // Method io/netty/buffer/ByteBuf.release:()Z
      14: pop
      15: aload_0
      16: aconst_null
      17: putfield      #7                  // Field clientPrefaceString:Lio/netty/buffer/ByteBuf;
      20: return

  private boolean readClientPrefaceString(io.netty.buffer.ByteBuf) throws io.netty.handler.codec.http2.Http2Exception;
    Code:
       0: aload_0
       1: getfield      #7                  // Field clientPrefaceString:Lio/netty/buffer/ByteBuf;
       4: ifnonnull     9
       7: iconst_1
       8: ireturn
       9: aload_0
      10: getfield      #7                  // Field clientPrefaceString:Lio/netty/buffer/ByteBuf;
      13: invokevirtual #24                 // Method io/netty/buffer/ByteBuf.readableBytes:()I
      16: istore_2
      17: aload_1
      18: invokevirtual #24                 // Method io/netty/buffer/ByteBuf.readableBytes:()I
      21: iload_2
      22: invokestatic  #25                 // Method java/lang/Math.min:(II)I
      25: istore_3
      26: iload_3
      27: ifeq          53
      30: aload_1
      31: aload_1
      32: invokevirtual #26                 // Method io/netty/buffer/ByteBuf.readerIndex:()I
      35: aload_0
      36: getfield      #7                  // Field clientPrefaceString:Lio/netty/buffer/ByteBuf;
      39: aload_0
      40: getfield      #7                  // Field clientPrefaceString:Lio/netty/buffer/ByteBuf;
      43: invokevirtual #26                 // Method io/netty/buffer/ByteBuf.readerIndex:()I
      46: iload_3
      47: invokestatic  #27                 // Method io/netty/buffer/ByteBufUtil.equals:(Lio/netty/buffer/ByteBuf;ILio/netty/buffer/ByteBuf;II)Z
      50: ifne          169
      53: sipush        1024
      56: istore        4
      58: invokestatic  #28                 // Method io/netty/handler/codec/http2/Http2ConnectionHandler.access$500:()Lio/netty/buffer/ByteBuf;
      61: aload_1
      62: aload_1
      63: invokevirtual #26                 // Method io/netty/buffer/ByteBuf.readerIndex:()I
      66: aload_1
      67: invokevirtual #24                 // Method io/netty/buffer/ByteBuf.readableBytes:()I
      70: iload         4
      72: invokestatic  #25                 // Method java/lang/Math.min:(II)I
      75: invokevirtual #29                 // Method io/netty/buffer/ByteBuf.slice:(II)Lio/netty/buffer/ByteBuf;
      78: invokestatic  #30                 // Method io/netty/buffer/ByteBufUtil.indexOf:(Lio/netty/buffer/ByteBuf;Lio/netty/buffer/ByteBuf;)I
      81: istore        5
      83: iload         5
      85: iconst_m1
      86: if_icmpeq     127
      89: aload_1
      90: aload_1
      91: invokevirtual #26                 // Method io/netty/buffer/ByteBuf.readerIndex:()I
      94: iload         5
      96: aload_1
      97: invokevirtual #26                 // Method io/netty/buffer/ByteBuf.readerIndex:()I
     100: isub
     101: getstatic     #31                 // Field io/netty/util/CharsetUtil.US_ASCII:Ljava/nio/charset/Charset;
     104: invokevirtual #32                 // Method io/netty/buffer/ByteBuf.toString:(IILjava/nio/charset/Charset;)Ljava/lang/String;
     107: astore        6
     109: getstatic     #33                 // Field io/netty/handler/codec/http2/Http2Error.PROTOCOL_ERROR:Lio/netty/handler/codec/http2/Http2Error;
     112: ldc           #34                 // String Unexpected HTTP/1.x request: %s
     114: iconst_1
     115: anewarray     #35                 // class java/lang/Object
     118: dup
     119: iconst_0
     120: aload         6
     122: aastore
     123: invokestatic  #36                 // Method io/netty/handler/codec/http2/Http2Exception.connectionError:(Lio/netty/handler/codec/http2/Http2Error;Ljava/lang/String;[Ljava/lang/Object;)Lio/netty/handler/codec/http2/Http2Exception;
     126: athrow
     127: aload_1
     128: aload_1
     129: invokevirtual #26                 // Method io/netty/buffer/ByteBuf.readerIndex:()I
     132: aload_1
     133: invokevirtual #24                 // Method io/netty/buffer/ByteBuf.readableBytes:()I
     136: aload_0
     137: getfield      #7                  // Field clientPrefaceString:Lio/netty/buffer/ByteBuf;
     140: invokevirtual #24                 // Method io/netty/buffer/ByteBuf.readableBytes:()I
     143: invokestatic  #25                 // Method java/lang/Math.min:(II)I
     146: invokestatic  #37                 // Method io/netty/buffer/ByteBufUtil.hexDump:(Lio/netty/buffer/ByteBuf;II)Ljava/lang/String;
     149: astore        6
     151: getstatic     #33                 // Field io/netty/handler/codec/http2/Http2Error.PROTOCOL_ERROR:Lio/netty/handler/codec/http2/Http2Error;
     154: ldc           #38                 // String HTTP/2 client preface string missing or corrupt. Hex dump for received bytes: %s
     156: iconst_1
     157: anewarray     #35                 // class java/lang/Object
     160: dup
     161: iconst_0
     162: aload         6
     164: aastore
     165: invokestatic  #36                 // Method io/netty/handler/codec/http2/Http2Exception.connectionError:(Lio/netty/handler/codec/http2/Http2Error;Ljava/lang/String;[Ljava/lang/Object;)Lio/netty/handler/codec/http2/Http2Exception;
     168: athrow
     169: aload_1
     170: iload_3
     171: invokevirtual #39                 // Method io/netty/buffer/ByteBuf.skipBytes:(I)Lio/netty/buffer/ByteBuf;
     174: pop
     175: aload_0
     176: getfield      #7                  // Field clientPrefaceString:Lio/netty/buffer/ByteBuf;
     179: iload_3
     180: invokevirtual #39                 // Method io/netty/buffer/ByteBuf.skipBytes:(I)Lio/netty/buffer/ByteBuf;
     183: pop
     184: aload_0
     185: getfield      #7                  // Field clientPrefaceString:Lio/netty/buffer/ByteBuf;
     188: invokevirtual #40                 // Method io/netty/buffer/ByteBuf.isReadable:()Z
     191: ifne          209
     194: aload_0
     195: getfield      #7                  // Field clientPrefaceString:Lio/netty/buffer/ByteBuf;
     198: invokevirtual #23                 // Method io/netty/buffer/ByteBuf.release:()Z
     201: pop
     202: aload_0
     203: aconst_null
     204: putfield      #7                  // Field clientPrefaceString:Lio/netty/buffer/ByteBuf;
     207: iconst_1
     208: ireturn
     209: iconst_0
     210: ireturn

  private boolean verifyFirstFrameIsSettings(io.netty.buffer.ByteBuf) throws io.netty.handler.codec.http2.Http2Exception;
    Code:
       0: aload_1
       1: invokevirtual #24                 // Method io/netty/buffer/ByteBuf.readableBytes:()I
       4: iconst_5
       5: if_icmpge     10
       8: iconst_0
       9: ireturn
      10: aload_1
      11: aload_1
      12: invokevirtual #26                 // Method io/netty/buffer/ByteBuf.readerIndex:()I
      15: iconst_3
      16: iadd
      17: invokevirtual #41                 // Method io/netty/buffer/ByteBuf.getUnsignedByte:(I)S
      20: istore_2
      21: aload_1
      22: aload_1
      23: invokevirtual #26                 // Method io/netty/buffer/ByteBuf.readerIndex:()I
      26: iconst_4
      27: iadd
      28: invokevirtual #41                 // Method io/netty/buffer/ByteBuf.getUnsignedByte:(I)S
      31: istore_3
      32: iload_2
      33: iconst_4
      34: if_icmpne     43
      37: iload_3
      38: iconst_1
      39: iand
      40: ifeq          68
      43: getstatic     #33                 // Field io/netty/handler/codec/http2/Http2Error.PROTOCOL_ERROR:Lio/netty/handler/codec/http2/Http2Error;
      46: ldc           #43                 // String First received frame was not SETTINGS. Hex dump for first 5 bytes: %s
      48: iconst_1
      49: anewarray     #35                 // class java/lang/Object
      52: dup
      53: iconst_0
      54: aload_1
      55: aload_1
      56: invokevirtual #26                 // Method io/netty/buffer/ByteBuf.readerIndex:()I
      59: iconst_5
      60: invokestatic  #37                 // Method io/netty/buffer/ByteBufUtil.hexDump:(Lio/netty/buffer/ByteBuf;II)Ljava/lang/String;
      63: aastore
      64: invokestatic  #36                 // Method io/netty/handler/codec/http2/Http2Exception.connectionError:(Lio/netty/handler/codec/http2/Http2Error;Ljava/lang/String;[Ljava/lang/Object;)Lio/netty/handler/codec/http2/Http2Exception;
      67: athrow
      68: iconst_1
      69: ireturn

  private void sendPreface(io.netty.channel.ChannelHandlerContext);
    Code:
       0: aload_0
       1: getfield      #9                  // Field prefaceSent:Z
       4: ifne          21
       7: aload_1
       8: invokeinterface #10,  1           // InterfaceMethod io/netty/channel/ChannelHandlerContext.channel:()Lio/netty/channel/Channel;
      13: invokeinterface #11,  1           // InterfaceMethod io/netty/channel/Channel.isActive:()Z
      18: ifne          22
      21: return
      22: aload_0
      23: iconst_1
      24: putfield      #9                  // Field prefaceSent:Z
      27: aload_0
      28: getfield      #2                  // Field this$0:Lio/netty/handler/codec/http2/Http2ConnectionHandler;
      31: invokevirtual #44                 // Method io/netty/handler/codec/http2/Http2ConnectionHandler.connection:()Lio/netty/handler/codec/http2/Http2Connection;
      34: invokeinterface #45,  1           // InterfaceMethod io/netty/handler/codec/http2/Http2Connection.isServer:()Z
      39: ifne          70
      42: aload_1
      43: invokestatic  #46                 // Method io/netty/handler/codec/http2/Http2CodecUtil.connectionPrefaceBuf:()Lio/netty/buffer/ByteBuf;
      46: invokeinterface #47,  2           // InterfaceMethod io/netty/channel/ChannelHandlerContext.write:(Ljava/lang/Object;)Lio/netty/channel/ChannelFuture;
      51: getstatic     #48                 // Field io/netty/channel/ChannelFutureListener.CLOSE_ON_FAILURE:Lio/netty/channel/ChannelFutureListener;
      54: invokeinterface #49,  2           // InterfaceMethod io/netty/channel/ChannelFuture.addListener:(Lio/netty/util/concurrent/GenericFutureListener;)Lio/netty/channel/ChannelFuture;
      59: pop
      60: aload_1
      61: getstatic     #50                 // Field io/netty/handler/codec/http2/Http2ConnectionPrefaceWrittenEvent.INSTANCE:Lio/netty/handler/codec/http2/Http2ConnectionPrefaceWrittenEvent;
      64: invokeinterface #51,  2           // InterfaceMethod io/netty/channel/ChannelHandlerContext.fireUserEventTriggered:(Ljava/lang/Object;)Lio/netty/channel/ChannelHandlerContext;
      69: pop
      70: aload_0
      71: getfield      #2                  // Field this$0:Lio/netty/handler/codec/http2/Http2ConnectionHandler;
      74: invokestatic  #4                  // Method io/netty/handler/codec/http2/Http2ConnectionHandler.access$100:(Lio/netty/handler/codec/http2/Http2ConnectionHandler;)Lio/netty/handler/codec/http2/Http2ConnectionEncoder;
      77: aload_1
      78: aload_0
      79: getfield      #2                  // Field this$0:Lio/netty/handler/codec/http2/Http2ConnectionHandler;
      82: invokestatic  #52                 // Method io/netty/handler/codec/http2/Http2ConnectionHandler.access$600:(Lio/netty/handler/codec/http2/Http2ConnectionHandler;)Lio/netty/handler/codec/http2/Http2Settings;
      85: aload_1
      86: invokeinterface #53,  1           // InterfaceMethod io/netty/channel/ChannelHandlerContext.newPromise:()Lio/netty/channel/ChannelPromise;
      91: invokeinterface #54,  4           // InterfaceMethod io/netty/handler/codec/http2/Http2ConnectionEncoder.writeSettings:(Lio/netty/channel/ChannelHandlerContext;Lio/netty/handler/codec/http2/Http2Settings;Lio/netty/channel/ChannelPromise;)Lio/netty/channel/ChannelFuture;
      96: getstatic     #48                 // Field io/netty/channel/ChannelFutureListener.CLOSE_ON_FAILURE:Lio/netty/channel/ChannelFutureListener;
      99: invokeinterface #49,  2           // InterfaceMethod io/netty/channel/ChannelFuture.addListener:(Lio/netty/util/concurrent/GenericFutureListener;)Lio/netty/channel/ChannelFuture;
     104: pop
     105: return
}
