Compiled from "Http2InboundFrameLogger.java"
class io.netty.handler.codec.http2.Http2InboundFrameLogger$1 implements io.netty.handler.codec.http2.Http2FrameListener {
  final io.netty.handler.codec.http2.Http2FrameListener val$listener;

  final io.netty.handler.codec.http2.Http2InboundFrameLogger this$0;

  io.netty.handler.codec.http2.Http2InboundFrameLogger$1(io.netty.handler.codec.http2.Http2InboundFrameLogger, io.netty.handler.codec.http2.Http2FrameListener);
    Code:
       0: aload_0
       1: aload_1
       2: putfield      #1                  // Field this$0:Lio/netty/handler/codec/http2/Http2InboundFrameLogger;
       5: aload_0
       6: aload_2
       7: putfield      #2                  // Field val$listener:Lio/netty/handler/codec/http2/Http2FrameListener;
      10: aload_0
      11: invokespecial #3                  // Method java/lang/Object."<init>":()V
      14: return

  public int onDataRead(io.netty.channel.ChannelHandlerContext, int, io.netty.buffer.ByteBuf, int, boolean) throws io.netty.handler.codec.http2.Http2Exception;
    Code:
       0: aload_0
       1: getfield      #1                  // Field this$0:Lio/netty/handler/codec/http2/Http2InboundFrameLogger;
       4: invokestatic  #4                  // Method io/netty/handler/codec/http2/Http2InboundFrameLogger.access$000:(Lio/netty/handler/codec/http2/Http2InboundFrameLogger;)Lio/netty/handler/codec/http2/Http2FrameLogger;
       7: getstatic     #5                  // Field io/netty/handler/codec/http2/Http2FrameLogger$Direction.INBOUND:Lio/netty/handler/codec/http2/Http2FrameLogger$Direction;
      10: aload_1
      11: iload_2
      12: aload_3
      13: iload         4
      15: iload         5
      17: invokevirtual #6                  // Method io/netty/handler/codec/http2/Http2FrameLogger.logData:(Lio/netty/handler/codec/http2/Http2FrameLogger$Direction;Lio/netty/channel/ChannelHandlerContext;ILio/netty/buffer/ByteBuf;IZ)V
      20: aload_0
      21: getfield      #2                  // Field val$listener:Lio/netty/handler/codec/http2/Http2FrameListener;
      24: aload_1
      25: iload_2
      26: aload_3
      27: iload         4
      29: iload         5
      31: invokeinterface #7,  6            // InterfaceMethod io/netty/handler/codec/http2/Http2FrameListener.onDataRead:(Lio/netty/channel/ChannelHandlerContext;ILio/netty/buffer/ByteBuf;IZ)I
      36: ireturn

  public void onHeadersRead(io.netty.channel.ChannelHandlerContext, int, io.netty.handler.codec.http2.Http2Headers, int, boolean) throws io.netty.handler.codec.http2.Http2Exception;
    Code:
       0: aload_0
       1: getfield      #1                  // Field this$0:Lio/netty/handler/codec/http2/Http2InboundFrameLogger;
       4: invokestatic  #4                  // Method io/netty/handler/codec/http2/Http2InboundFrameLogger.access$000:(Lio/netty/handler/codec/http2/Http2InboundFrameLogger;)Lio/netty/handler/codec/http2/Http2FrameLogger;
       7: getstatic     #5                  // Field io/netty/handler/codec/http2/Http2FrameLogger$Direction.INBOUND:Lio/netty/handler/codec/http2/Http2FrameLogger$Direction;
      10: aload_1
      11: iload_2
      12: aload_3
      13: iload         4
      15: iload         5
      17: invokevirtual #8                  // Method io/netty/handler/codec/http2/Http2FrameLogger.logHeaders:(Lio/netty/handler/codec/http2/Http2FrameLogger$Direction;Lio/netty/channel/ChannelHandlerContext;ILio/netty/handler/codec/http2/Http2Headers;IZ)V
      20: aload_0
      21: getfield      #2                  // Field val$listener:Lio/netty/handler/codec/http2/Http2FrameListener;
      24: aload_1
      25: iload_2
      26: aload_3
      27: iload         4
      29: iload         5
      31: invokeinterface #9,  6            // InterfaceMethod io/netty/handler/codec/http2/Http2FrameListener.onHeadersRead:(Lio/netty/channel/ChannelHandlerContext;ILio/netty/handler/codec/http2/Http2Headers;IZ)V
      36: return

  public void onHeadersRead(io.netty.channel.ChannelHandlerContext, int, io.netty.handler.codec.http2.Http2Headers, int, short, boolean, int, boolean) throws io.netty.handler.codec.http2.Http2Exception;
    Code:
       0: aload_0
       1: getfield      #1                  // Field this$0:Lio/netty/handler/codec/http2/Http2InboundFrameLogger;
       4: invokestatic  #4                  // Method io/netty/handler/codec/http2/Http2InboundFrameLogger.access$000:(Lio/netty/handler/codec/http2/Http2InboundFrameLogger;)Lio/netty/handler/codec/http2/Http2FrameLogger;
       7: getstatic     #5                  // Field io/netty/handler/codec/http2/Http2FrameLogger$Direction.INBOUND:Lio/netty/handler/codec/http2/Http2FrameLogger$Direction;
      10: aload_1
      11: iload_2
      12: aload_3
      13: iload         4
      15: iload         5
      17: iload         6
      19: iload         7
      21: iload         8
      23: invokevirtual #10                 // Method io/netty/handler/codec/http2/Http2FrameLogger.logHeaders:(Lio/netty/handler/codec/http2/Http2FrameLogger$Direction;Lio/netty/channel/ChannelHandlerContext;ILio/netty/handler/codec/http2/Http2Headers;ISZIZ)V
      26: aload_0
      27: getfield      #2                  // Field val$listener:Lio/netty/handler/codec/http2/Http2FrameListener;
      30: aload_1
      31: iload_2
      32: aload_3
      33: iload         4
      35: iload         5
      37: iload         6
      39: iload         7
      41: iload         8
      43: invokeinterface #11,  9           // InterfaceMethod io/netty/handler/codec/http2/Http2FrameListener.onHeadersRead:(Lio/netty/channel/ChannelHandlerContext;ILio/netty/handler/codec/http2/Http2Headers;ISZIZ)V
      48: return

  public void onPriorityRead(io.netty.channel.ChannelHandlerContext, int, int, short, boolean) throws io.netty.handler.codec.http2.Http2Exception;
    Code:
       0: aload_0
       1: getfield      #1                  // Field this$0:Lio/netty/handler/codec/http2/Http2InboundFrameLogger;
       4: invokestatic  #4                  // Method io/netty/handler/codec/http2/Http2InboundFrameLogger.access$000:(Lio/netty/handler/codec/http2/Http2InboundFrameLogger;)Lio/netty/handler/codec/http2/Http2FrameLogger;
       7: getstatic     #5                  // Field io/netty/handler/codec/http2/Http2FrameLogger$Direction.INBOUND:Lio/netty/handler/codec/http2/Http2FrameLogger$Direction;
      10: aload_1
      11: iload_2
      12: iload_3
      13: iload         4
      15: iload         5
      17: invokevirtual #12                 // Method io/netty/handler/codec/http2/Http2FrameLogger.logPriority:(Lio/netty/handler/codec/http2/Http2FrameLogger$Direction;Lio/netty/channel/ChannelHandlerContext;IISZ)V
      20: aload_0
      21: getfield      #2                  // Field val$listener:Lio/netty/handler/codec/http2/Http2FrameListener;
      24: aload_1
      25: iload_2
      26: iload_3
      27: iload         4
      29: iload         5
      31: invokeinterface #13,  6           // InterfaceMethod io/netty/handler/codec/http2/Http2FrameListener.onPriorityRead:(Lio/netty/channel/ChannelHandlerContext;IISZ)V
      36: return

  public void onRstStreamRead(io.netty.channel.ChannelHandlerContext, int, long) throws io.netty.handler.codec.http2.Http2Exception;
    Code:
       0: aload_0
       1: getfield      #1                  // Field this$0:Lio/netty/handler/codec/http2/Http2InboundFrameLogger;
       4: invokestatic  #4                  // Method io/netty/handler/codec/http2/Http2InboundFrameLogger.access$000:(Lio/netty/handler/codec/http2/Http2InboundFrameLogger;)Lio/netty/handler/codec/http2/Http2FrameLogger;
       7: getstatic     #5                  // Field io/netty/handler/codec/http2/Http2FrameLogger$Direction.INBOUND:Lio/netty/handler/codec/http2/Http2FrameLogger$Direction;
      10: aload_1
      11: iload_2
      12: lload_3
      13: invokevirtual #14                 // Method io/netty/handler/codec/http2/Http2FrameLogger.logRstStream:(Lio/netty/handler/codec/http2/Http2FrameLogger$Direction;Lio/netty/channel/ChannelHandlerContext;IJ)V
      16: aload_0
      17: getfield      #2                  // Field val$listener:Lio/netty/handler/codec/http2/Http2FrameListener;
      20: aload_1
      21: iload_2
      22: lload_3
      23: invokeinterface #15,  5           // InterfaceMethod io/netty/handler/codec/http2/Http2FrameListener.onRstStreamRead:(Lio/netty/channel/ChannelHandlerContext;IJ)V
      28: return

  public void onSettingsAckRead(io.netty.channel.ChannelHandlerContext) throws io.netty.handler.codec.http2.Http2Exception;
    Code:
       0: aload_0
       1: getfield      #1                  // Field this$0:Lio/netty/handler/codec/http2/Http2InboundFrameLogger;
       4: invokestatic  #4                  // Method io/netty/handler/codec/http2/Http2InboundFrameLogger.access$000:(Lio/netty/handler/codec/http2/Http2InboundFrameLogger;)Lio/netty/handler/codec/http2/Http2FrameLogger;
       7: getstatic     #5                  // Field io/netty/handler/codec/http2/Http2FrameLogger$Direction.INBOUND:Lio/netty/handler/codec/http2/Http2FrameLogger$Direction;
      10: aload_1
      11: invokevirtual #16                 // Method io/netty/handler/codec/http2/Http2FrameLogger.logSettingsAck:(Lio/netty/handler/codec/http2/Http2FrameLogger$Direction;Lio/netty/channel/ChannelHandlerContext;)V
      14: aload_0
      15: getfield      #2                  // Field val$listener:Lio/netty/handler/codec/http2/Http2FrameListener;
      18: aload_1
      19: invokeinterface #17,  2           // InterfaceMethod io/netty/handler/codec/http2/Http2FrameListener.onSettingsAckRead:(Lio/netty/channel/ChannelHandlerContext;)V
      24: return

  public void onSettingsRead(io.netty.channel.ChannelHandlerContext, io.netty.handler.codec.http2.Http2Settings) throws io.netty.handler.codec.http2.Http2Exception;
    Code:
       0: aload_0
       1: getfield      #1                  // Field this$0:Lio/netty/handler/codec/http2/Http2InboundFrameLogger;
       4: invokestatic  #4                  // Method io/netty/handler/codec/http2/Http2InboundFrameLogger.access$000:(Lio/netty/handler/codec/http2/Http2InboundFrameLogger;)Lio/netty/handler/codec/http2/Http2FrameLogger;
       7: getstatic     #5                  // Field io/netty/handler/codec/http2/Http2FrameLogger$Direction.INBOUND:Lio/netty/handler/codec/http2/Http2FrameLogger$Direction;
      10: aload_1
      11: aload_2
      12: invokevirtual #18                 // Method io/netty/handler/codec/http2/Http2FrameLogger.logSettings:(Lio/netty/handler/codec/http2/Http2FrameLogger$Direction;Lio/netty/channel/ChannelHandlerContext;Lio/netty/handler/codec/http2/Http2Settings;)V
      15: aload_0
      16: getfield      #2                  // Field val$listener:Lio/netty/handler/codec/http2/Http2FrameListener;
      19: aload_1
      20: aload_2
      21: invokeinterface #19,  3           // InterfaceMethod io/netty/handler/codec/http2/Http2FrameListener.onSettingsRead:(Lio/netty/channel/ChannelHandlerContext;Lio/netty/handler/codec/http2/Http2Settings;)V
      26: return

  public void onPingRead(io.netty.channel.ChannelHandlerContext, io.netty.buffer.ByteBuf) throws io.netty.handler.codec.http2.Http2Exception;
    Code:
       0: aload_0
       1: getfield      #1                  // Field this$0:Lio/netty/handler/codec/http2/Http2InboundFrameLogger;
       4: invokestatic  #4                  // Method io/netty/handler/codec/http2/Http2InboundFrameLogger.access$000:(Lio/netty/handler/codec/http2/Http2InboundFrameLogger;)Lio/netty/handler/codec/http2/Http2FrameLogger;
       7: getstatic     #5                  // Field io/netty/handler/codec/http2/Http2FrameLogger$Direction.INBOUND:Lio/netty/handler/codec/http2/Http2FrameLogger$Direction;
      10: aload_1
      11: aload_2
      12: invokevirtual #20                 // Method io/netty/handler/codec/http2/Http2FrameLogger.logPing:(Lio/netty/handler/codec/http2/Http2FrameLogger$Direction;Lio/netty/channel/ChannelHandlerContext;Lio/netty/buffer/ByteBuf;)V
      15: aload_0
      16: getfield      #2                  // Field val$listener:Lio/netty/handler/codec/http2/Http2FrameListener;
      19: aload_1
      20: aload_2
      21: invokeinterface #21,  3           // InterfaceMethod io/netty/handler/codec/http2/Http2FrameListener.onPingRead:(Lio/netty/channel/ChannelHandlerContext;Lio/netty/buffer/ByteBuf;)V
      26: return

  public void onPingAckRead(io.netty.channel.ChannelHandlerContext, io.netty.buffer.ByteBuf) throws io.netty.handler.codec.http2.Http2Exception;
    Code:
       0: aload_0
       1: getfield      #1                  // Field this$0:Lio/netty/handler/codec/http2/Http2InboundFrameLogger;
       4: invokestatic  #4                  // Method io/netty/handler/codec/http2/Http2InboundFrameLogger.access$000:(Lio/netty/handler/codec/http2/Http2InboundFrameLogger;)Lio/netty/handler/codec/http2/Http2FrameLogger;
       7: getstatic     #5                  // Field io/netty/handler/codec/http2/Http2FrameLogger$Direction.INBOUND:Lio/netty/handler/codec/http2/Http2FrameLogger$Direction;
      10: aload_1
      11: aload_2
      12: invokevirtual #22                 // Method io/netty/handler/codec/http2/Http2FrameLogger.logPingAck:(Lio/netty/handler/codec/http2/Http2FrameLogger$Direction;Lio/netty/channel/ChannelHandlerContext;Lio/netty/buffer/ByteBuf;)V
      15: aload_0
      16: getfield      #2                  // Field val$listener:Lio/netty/handler/codec/http2/Http2FrameListener;
      19: aload_1
      20: aload_2
      21: invokeinterface #23,  3           // InterfaceMethod io/netty/handler/codec/http2/Http2FrameListener.onPingAckRead:(Lio/netty/channel/ChannelHandlerContext;Lio/netty/buffer/ByteBuf;)V
      26: return

  public void onPushPromiseRead(io.netty.channel.ChannelHandlerContext, int, int, io.netty.handler.codec.http2.Http2Headers, int) throws io.netty.handler.codec.http2.Http2Exception;
    Code:
       0: aload_0
       1: getfield      #1                  // Field this$0:Lio/netty/handler/codec/http2/Http2InboundFrameLogger;
       4: invokestatic  #4                  // Method io/netty/handler/codec/http2/Http2InboundFrameLogger.access$000:(Lio/netty/handler/codec/http2/Http2InboundFrameLogger;)Lio/netty/handler/codec/http2/Http2FrameLogger;
       7: getstatic     #5                  // Field io/netty/handler/codec/http2/Http2FrameLogger$Direction.INBOUND:Lio/netty/handler/codec/http2/Http2FrameLogger$Direction;
      10: aload_1
      11: iload_2
      12: iload_3
      13: aload         4
      15: iload         5
      17: invokevirtual #24                 // Method io/netty/handler/codec/http2/Http2FrameLogger.logPushPromise:(Lio/netty/handler/codec/http2/Http2FrameLogger$Direction;Lio/netty/channel/ChannelHandlerContext;IILio/netty/handler/codec/http2/Http2Headers;I)V
      20: aload_0
      21: getfield      #2                  // Field val$listener:Lio/netty/handler/codec/http2/Http2FrameListener;
      24: aload_1
      25: iload_2
      26: iload_3
      27: aload         4
      29: iload         5
      31: invokeinterface #25,  6           // InterfaceMethod io/netty/handler/codec/http2/Http2FrameListener.onPushPromiseRead:(Lio/netty/channel/ChannelHandlerContext;IILio/netty/handler/codec/http2/Http2Headers;I)V
      36: return

  public void onGoAwayRead(io.netty.channel.ChannelHandlerContext, int, long, io.netty.buffer.ByteBuf) throws io.netty.handler.codec.http2.Http2Exception;
    Code:
       0: aload_0
       1: getfield      #1                  // Field this$0:Lio/netty/handler/codec/http2/Http2InboundFrameLogger;
       4: invokestatic  #4                  // Method io/netty/handler/codec/http2/Http2InboundFrameLogger.access$000:(Lio/netty/handler/codec/http2/Http2InboundFrameLogger;)Lio/netty/handler/codec/http2/Http2FrameLogger;
       7: getstatic     #5                  // Field io/netty/handler/codec/http2/Http2FrameLogger$Direction.INBOUND:Lio/netty/handler/codec/http2/Http2FrameLogger$Direction;
      10: aload_1
      11: iload_2
      12: lload_3
      13: aload         5
      15: invokevirtual #26                 // Method io/netty/handler/codec/http2/Http2FrameLogger.logGoAway:(Lio/netty/handler/codec/http2/Http2FrameLogger$Direction;Lio/netty/channel/ChannelHandlerContext;IJLio/netty/buffer/ByteBuf;)V
      18: aload_0
      19: getfield      #2                  // Field val$listener:Lio/netty/handler/codec/http2/Http2FrameListener;
      22: aload_1
      23: iload_2
      24: lload_3
      25: aload         5
      27: invokeinterface #27,  6           // InterfaceMethod io/netty/handler/codec/http2/Http2FrameListener.onGoAwayRead:(Lio/netty/channel/ChannelHandlerContext;IJLio/netty/buffer/ByteBuf;)V
      32: return

  public void onWindowUpdateRead(io.netty.channel.ChannelHandlerContext, int, int) throws io.netty.handler.codec.http2.Http2Exception;
    Code:
       0: aload_0
       1: getfield      #1                  // Field this$0:Lio/netty/handler/codec/http2/Http2InboundFrameLogger;
       4: invokestatic  #4                  // Method io/netty/handler/codec/http2/Http2InboundFrameLogger.access$000:(Lio/netty/handler/codec/http2/Http2InboundFrameLogger;)Lio/netty/handler/codec/http2/Http2FrameLogger;
       7: getstatic     #5                  // Field io/netty/handler/codec/http2/Http2FrameLogger$Direction.INBOUND:Lio/netty/handler/codec/http2/Http2FrameLogger$Direction;
      10: aload_1
      11: iload_2
      12: iload_3
      13: invokevirtual #28                 // Method io/netty/handler/codec/http2/Http2FrameLogger.logWindowsUpdate:(Lio/netty/handler/codec/http2/Http2FrameLogger$Direction;Lio/netty/channel/ChannelHandlerContext;II)V
      16: aload_0
      17: getfield      #2                  // Field val$listener:Lio/netty/handler/codec/http2/Http2FrameListener;
      20: aload_1
      21: iload_2
      22: iload_3
      23: invokeinterface #29,  4           // InterfaceMethod io/netty/handler/codec/http2/Http2FrameListener.onWindowUpdateRead:(Lio/netty/channel/ChannelHandlerContext;II)V
      28: return

  public void onUnknownFrame(io.netty.channel.ChannelHandlerContext, byte, int, io.netty.handler.codec.http2.Http2Flags, io.netty.buffer.ByteBuf) throws io.netty.handler.codec.http2.Http2Exception;
    Code:
       0: aload_0
       1: getfield      #1                  // Field this$0:Lio/netty/handler/codec/http2/Http2InboundFrameLogger;
       4: invokestatic  #4                  // Method io/netty/handler/codec/http2/Http2InboundFrameLogger.access$000:(Lio/netty/handler/codec/http2/Http2InboundFrameLogger;)Lio/netty/handler/codec/http2/Http2FrameLogger;
       7: getstatic     #5                  // Field io/netty/handler/codec/http2/Http2FrameLogger$Direction.INBOUND:Lio/netty/handler/codec/http2/Http2FrameLogger$Direction;
      10: aload_1
      11: iload_2
      12: iload_3
      13: aload         4
      15: aload         5
      17: invokevirtual #30                 // Method io/netty/handler/codec/http2/Http2FrameLogger.logUnknownFrame:(Lio/netty/handler/codec/http2/Http2FrameLogger$Direction;Lio/netty/channel/ChannelHandlerContext;BILio/netty/handler/codec/http2/Http2Flags;Lio/netty/buffer/ByteBuf;)V
      20: aload_0
      21: getfield      #2                  // Field val$listener:Lio/netty/handler/codec/http2/Http2FrameListener;
      24: aload_1
      25: iload_2
      26: iload_3
      27: aload         4
      29: aload         5
      31: invokeinterface #31,  6           // InterfaceMethod io/netty/handler/codec/http2/Http2FrameListener.onUnknownFrame:(Lio/netty/channel/ChannelHandlerContext;BILio/netty/handler/codec/http2/Http2Flags;Lio/netty/buffer/ByteBuf;)V
      36: return
}
