Compiled from "WrappersProto.java"
public final class com.google.protobuf.WrappersProto {
  static com.google.protobuf.Descriptors$Descriptor internal_static_google_protobuf_DoubleValue_descriptor;

  static com.google.protobuf.GeneratedMessage$FieldAccessorTable internal_static_google_protobuf_DoubleValue_fieldAccessorTable;

  static com.google.protobuf.Descriptors$Descriptor internal_static_google_protobuf_FloatValue_descriptor;

  static com.google.protobuf.GeneratedMessage$FieldAccessorTable internal_static_google_protobuf_FloatValue_fieldAccessorTable;

  static com.google.protobuf.Descriptors$Descriptor internal_static_google_protobuf_Int64Value_descriptor;

  static com.google.protobuf.GeneratedMessage$FieldAccessorTable internal_static_google_protobuf_Int64Value_fieldAccessorTable;

  static com.google.protobuf.Descriptors$Descriptor internal_static_google_protobuf_UInt64Value_descriptor;

  static com.google.protobuf.GeneratedMessage$FieldAccessorTable internal_static_google_protobuf_UInt64Value_fieldAccessorTable;

  static com.google.protobuf.Descriptors$Descriptor internal_static_google_protobuf_Int32Value_descriptor;

  static com.google.protobuf.GeneratedMessage$FieldAccessorTable internal_static_google_protobuf_Int32Value_fieldAccessorTable;

  static com.google.protobuf.Descriptors$Descriptor internal_static_google_protobuf_UInt32Value_descriptor;

  static com.google.protobuf.GeneratedMessage$FieldAccessorTable internal_static_google_protobuf_UInt32Value_fieldAccessorTable;

  static com.google.protobuf.Descriptors$Descriptor internal_static_google_protobuf_BoolValue_descriptor;

  static com.google.protobuf.GeneratedMessage$FieldAccessorTable internal_static_google_protobuf_BoolValue_fieldAccessorTable;

  static com.google.protobuf.Descriptors$Descriptor internal_static_google_protobuf_StringValue_descriptor;

  static com.google.protobuf.GeneratedMessage$FieldAccessorTable internal_static_google_protobuf_StringValue_fieldAccessorTable;

  static com.google.protobuf.Descriptors$Descriptor internal_static_google_protobuf_BytesValue_descriptor;

  static com.google.protobuf.GeneratedMessage$FieldAccessorTable internal_static_google_protobuf_BytesValue_fieldAccessorTable;

  private static com.google.protobuf.Descriptors$FileDescriptor descriptor;

  private com.google.protobuf.WrappersProto();
    Code:
       0: aload_0
       1: invokespecial #2                  // Method java/lang/Object."<init>":()V
       4: return

  public static void registerAllExtensions(com.google.protobuf.ExtensionRegistry);
    Code:
       0: return

  public static com.google.protobuf.Descriptors$FileDescriptor getDescriptor();
    Code:
       0: getstatic     #1                  // Field descriptor:Lcom/google/protobuf/Descriptors$FileDescriptor;
       3: areturn

  static com.google.protobuf.Descriptors$FileDescriptor access$002(com.google.protobuf.Descriptors$FileDescriptor);
    Code:
       0: aload_0
       1: dup
       2: putstatic     #1                  // Field descriptor:Lcom/google/protobuf/Descriptors$FileDescriptor;
       5: areturn

  static {};
    Code:
       0: iconst_2
       1: anewarray     #3                  // class java/lang/String
       4: dup
       5: iconst_0
       6: ldc           #4                  // String \n\u001egoogle/protobuf/wrappers.proto\u0012\u000fgoogle.protobuf\"\u001c\n\u000bDoubleValue\u0012\r\n\u0005value\u0018\u0001 \u0001(\u0001\"\u001b\n\nFloatValue\u0012\r\n\u0005value\u0018\u0001 \u0001(\u0002\"\u001b\n\nInt64Value\u0012\r\n\u0005value\u0018\u0001 \u0001(\u0003\"\u001c\n\u000bUInt64Value\u0012\r\n\u0005value\u0018\u0001 \u0001(\u0004\"\u001b\n\nInt32Value\u0012\r\n\u0005value\u0018\u0001 \u0001(\u0005\"\u001c\n\u000bUInt32Value\u0012\r\n\u0005value\u0018\u0001 \u0001(\r\"\u001a\n\tBoolValue\u0012\r\n\u0005value\u0018\u0001 \u0001(\b\"\u001c\n\u000bStringValue\u0012\r\n\u0005value\u0018\u0001 \u0001(\t\"\u001b\n\nBytesValue\u0012\r\n\u0005value\u0018\u0001 \u0001(\fBS\n\u0013com.google.protobufB\rWrappersProtoP\u0001 \u0001\u0001ø\u0001\u0001¢\u0002\u0003GPBª\u0002\u001eGoogle.Protobuf.WellKnownTypesb\u0006
       8: aastore
       9: dup
      10: iconst_1
      11: ldc           #5                  // String proto3
      13: aastore
      14: astore_0
      15: new           #6                  // class com/google/protobuf/WrappersProto$1
      18: dup
      19: invokespecial #7                  // Method com/google/protobuf/WrappersProto$1."<init>":()V
      22: astore_1
      23: aload_0
      24: iconst_0
      25: anewarray     #8                  // class com/google/protobuf/Descriptors$FileDescriptor
      28: aload_1
      29: invokestatic  #9                  // Method com/google/protobuf/Descriptors$FileDescriptor.internalBuildGeneratedFileFrom:([Ljava/lang/String;[Lcom/google/protobuf/Descriptors$FileDescriptor;Lcom/google/protobuf/Descriptors$FileDescriptor$InternalDescriptorAssigner;)V
      32: invokestatic  #10                 // Method getDescriptor:()Lcom/google/protobuf/Descriptors$FileDescriptor;
      35: invokevirtual #11                 // Method com/google/protobuf/Descriptors$FileDescriptor.getMessageTypes:()Ljava/util/List;
      38: iconst_0
      39: invokeinterface #12,  2           // InterfaceMethod java/util/List.get:(I)Ljava/lang/Object;
      44: checkcast     #13                 // class com/google/protobuf/Descriptors$Descriptor
      47: putstatic     #14                 // Field internal_static_google_protobuf_DoubleValue_descriptor:Lcom/google/protobuf/Descriptors$Descriptor;
      50: new           #15                 // class com/google/protobuf/GeneratedMessage$FieldAccessorTable
      53: dup
      54: getstatic     #14                 // Field internal_static_google_protobuf_DoubleValue_descriptor:Lcom/google/protobuf/Descriptors$Descriptor;
      57: iconst_1
      58: anewarray     #3                  // class java/lang/String
      61: dup
      62: iconst_0
      63: ldc           #16                 // String Value
      65: aastore
      66: invokespecial #17                 // Method com/google/protobuf/GeneratedMessage$FieldAccessorTable."<init>":(Lcom/google/protobuf/Descriptors$Descriptor;[Ljava/lang/String;)V
      69: putstatic     #18                 // Field internal_static_google_protobuf_DoubleValue_fieldAccessorTable:Lcom/google/protobuf/GeneratedMessage$FieldAccessorTable;
      72: invokestatic  #10                 // Method getDescriptor:()Lcom/google/protobuf/Descriptors$FileDescriptor;
      75: invokevirtual #11                 // Method com/google/protobuf/Descriptors$FileDescriptor.getMessageTypes:()Ljava/util/List;
      78: iconst_1
      79: invokeinterface #12,  2           // InterfaceMethod java/util/List.get:(I)Ljava/lang/Object;
      84: checkcast     #13                 // class com/google/protobuf/Descriptors$Descriptor
      87: putstatic     #19                 // Field internal_static_google_protobuf_FloatValue_descriptor:Lcom/google/protobuf/Descriptors$Descriptor;
      90: new           #15                 // class com/google/protobuf/GeneratedMessage$FieldAccessorTable
      93: dup
      94: getstatic     #19                 // Field internal_static_google_protobuf_FloatValue_descriptor:Lcom/google/protobuf/Descriptors$Descriptor;
      97: iconst_1
      98: anewarray     #3                  // class java/lang/String
     101: dup
     102: iconst_0
     103: ldc           #16                 // String Value
     105: aastore
     106: invokespecial #17                 // Method com/google/protobuf/GeneratedMessage$FieldAccessorTable."<init>":(Lcom/google/protobuf/Descriptors$Descriptor;[Ljava/lang/String;)V
     109: putstatic     #20                 // Field internal_static_google_protobuf_FloatValue_fieldAccessorTable:Lcom/google/protobuf/GeneratedMessage$FieldAccessorTable;
     112: invokestatic  #10                 // Method getDescriptor:()Lcom/google/protobuf/Descriptors$FileDescriptor;
     115: invokevirtual #11                 // Method com/google/protobuf/Descriptors$FileDescriptor.getMessageTypes:()Ljava/util/List;
     118: iconst_2
     119: invokeinterface #12,  2           // InterfaceMethod java/util/List.get:(I)Ljava/lang/Object;
     124: checkcast     #13                 // class com/google/protobuf/Descriptors$Descriptor
     127: putstatic     #21                 // Field internal_static_google_protobuf_Int64Value_descriptor:Lcom/google/protobuf/Descriptors$Descriptor;
     130: new           #15                 // class com/google/protobuf/GeneratedMessage$FieldAccessorTable
     133: dup
     134: getstatic     #21                 // Field internal_static_google_protobuf_Int64Value_descriptor:Lcom/google/protobuf/Descriptors$Descriptor;
     137: iconst_1
     138: anewarray     #3                  // class java/lang/String
     141: dup
     142: iconst_0
     143: ldc           #16                 // String Value
     145: aastore
     146: invokespecial #17                 // Method com/google/protobuf/GeneratedMessage$FieldAccessorTable."<init>":(Lcom/google/protobuf/Descriptors$Descriptor;[Ljava/lang/String;)V
     149: putstatic     #22                 // Field internal_static_google_protobuf_Int64Value_fieldAccessorTable:Lcom/google/protobuf/GeneratedMessage$FieldAccessorTable;
     152: invokestatic  #10                 // Method getDescriptor:()Lcom/google/protobuf/Descriptors$FileDescriptor;
     155: invokevirtual #11                 // Method com/google/protobuf/Descriptors$FileDescriptor.getMessageTypes:()Ljava/util/List;
     158: iconst_3
     159: invokeinterface #12,  2           // InterfaceMethod java/util/List.get:(I)Ljava/lang/Object;
     164: checkcast     #13                 // class com/google/protobuf/Descriptors$Descriptor
     167: putstatic     #23                 // Field internal_static_google_protobuf_UInt64Value_descriptor:Lcom/google/protobuf/Descriptors$Descriptor;
     170: new           #15                 // class com/google/protobuf/GeneratedMessage$FieldAccessorTable
     173: dup
     174: getstatic     #23                 // Field internal_static_google_protobuf_UInt64Value_descriptor:Lcom/google/protobuf/Descriptors$Descriptor;
     177: iconst_1
     178: anewarray     #3                  // class java/lang/String
     181: dup
     182: iconst_0
     183: ldc           #16                 // String Value
     185: aastore
     186: invokespecial #17                 // Method com/google/protobuf/GeneratedMessage$FieldAccessorTable."<init>":(Lcom/google/protobuf/Descriptors$Descriptor;[Ljava/lang/String;)V
     189: putstatic     #24                 // Field internal_static_google_protobuf_UInt64Value_fieldAccessorTable:Lcom/google/protobuf/GeneratedMessage$FieldAccessorTable;
     192: invokestatic  #10                 // Method getDescriptor:()Lcom/google/protobuf/Descriptors$FileDescriptor;
     195: invokevirtual #11                 // Method com/google/protobuf/Descriptors$FileDescriptor.getMessageTypes:()Ljava/util/List;
     198: iconst_4
     199: invokeinterface #12,  2           // InterfaceMethod java/util/List.get:(I)Ljava/lang/Object;
     204: checkcast     #13                 // class com/google/protobuf/Descriptors$Descriptor
     207: putstatic     #25                 // Field internal_static_google_protobuf_Int32Value_descriptor:Lcom/google/protobuf/Descriptors$Descriptor;
     210: new           #15                 // class com/google/protobuf/GeneratedMessage$FieldAccessorTable
     213: dup
     214: getstatic     #25                 // Field internal_static_google_protobuf_Int32Value_descriptor:Lcom/google/protobuf/Descriptors$Descriptor;
     217: iconst_1
     218: anewarray     #3                  // class java/lang/String
     221: dup
     222: iconst_0
     223: ldc           #16                 // String Value
     225: aastore
     226: invokespecial #17                 // Method com/google/protobuf/GeneratedMessage$FieldAccessorTable."<init>":(Lcom/google/protobuf/Descriptors$Descriptor;[Ljava/lang/String;)V
     229: putstatic     #26                 // Field internal_static_google_protobuf_Int32Value_fieldAccessorTable:Lcom/google/protobuf/GeneratedMessage$FieldAccessorTable;
     232: invokestatic  #10                 // Method getDescriptor:()Lcom/google/protobuf/Descriptors$FileDescriptor;
     235: invokevirtual #11                 // Method com/google/protobuf/Descriptors$FileDescriptor.getMessageTypes:()Ljava/util/List;
     238: iconst_5
     239: invokeinterface #12,  2           // InterfaceMethod java/util/List.get:(I)Ljava/lang/Object;
     244: checkcast     #13                 // class com/google/protobuf/Descriptors$Descriptor
     247: putstatic     #27                 // Field internal_static_google_protobuf_UInt32Value_descriptor:Lcom/google/protobuf/Descriptors$Descriptor;
     250: new           #15                 // class com/google/protobuf/GeneratedMessage$FieldAccessorTable
     253: dup
     254: getstatic     #27                 // Field internal_static_google_protobuf_UInt32Value_descriptor:Lcom/google/protobuf/Descriptors$Descriptor;
     257: iconst_1
     258: anewarray     #3                  // class java/lang/String
     261: dup
     262: iconst_0
     263: ldc           #16                 // String Value
     265: aastore
     266: invokespecial #17                 // Method com/google/protobuf/GeneratedMessage$FieldAccessorTable."<init>":(Lcom/google/protobuf/Descriptors$Descriptor;[Ljava/lang/String;)V
     269: putstatic     #28                 // Field internal_static_google_protobuf_UInt32Value_fieldAccessorTable:Lcom/google/protobuf/GeneratedMessage$FieldAccessorTable;
     272: invokestatic  #10                 // Method getDescriptor:()Lcom/google/protobuf/Descriptors$FileDescriptor;
     275: invokevirtual #11                 // Method com/google/protobuf/Descriptors$FileDescriptor.getMessageTypes:()Ljava/util/List;
     278: bipush        6
     280: invokeinterface #12,  2           // InterfaceMethod java/util/List.get:(I)Ljava/lang/Object;
     285: checkcast     #13                 // class com/google/protobuf/Descriptors$Descriptor
     288: putstatic     #29                 // Field internal_static_google_protobuf_BoolValue_descriptor:Lcom/google/protobuf/Descriptors$Descriptor;
     291: new           #15                 // class com/google/protobuf/GeneratedMessage$FieldAccessorTable
     294: dup
     295: getstatic     #29                 // Field internal_static_google_protobuf_BoolValue_descriptor:Lcom/google/protobuf/Descriptors$Descriptor;
     298: iconst_1
     299: anewarray     #3                  // class java/lang/String
     302: dup
     303: iconst_0
     304: ldc           #16                 // String Value
     306: aastore
     307: invokespecial #17                 // Method com/google/protobuf/GeneratedMessage$FieldAccessorTable."<init>":(Lcom/google/protobuf/Descriptors$Descriptor;[Ljava/lang/String;)V
     310: putstatic     #30                 // Field internal_static_google_protobuf_BoolValue_fieldAccessorTable:Lcom/google/protobuf/GeneratedMessage$FieldAccessorTable;
     313: invokestatic  #10                 // Method getDescriptor:()Lcom/google/protobuf/Descriptors$FileDescriptor;
     316: invokevirtual #11                 // Method com/google/protobuf/Descriptors$FileDescriptor.getMessageTypes:()Ljava/util/List;
     319: bipush        7
     321: invokeinterface #12,  2           // InterfaceMethod java/util/List.get:(I)Ljava/lang/Object;
     326: checkcast     #13                 // class com/google/protobuf/Descriptors$Descriptor
     329: putstatic     #31                 // Field internal_static_google_protobuf_StringValue_descriptor:Lcom/google/protobuf/Descriptors$Descriptor;
     332: new           #15                 // class com/google/protobuf/GeneratedMessage$FieldAccessorTable
     335: dup
     336: getstatic     #31                 // Field internal_static_google_protobuf_StringValue_descriptor:Lcom/google/protobuf/Descriptors$Descriptor;
     339: iconst_1
     340: anewarray     #3                  // class java/lang/String
     343: dup
     344: iconst_0
     345: ldc           #16                 // String Value
     347: aastore
     348: invokespecial #17                 // Method com/google/protobuf/GeneratedMessage$FieldAccessorTable."<init>":(Lcom/google/protobuf/Descriptors$Descriptor;[Ljava/lang/String;)V
     351: putstatic     #32                 // Field internal_static_google_protobuf_StringValue_fieldAccessorTable:Lcom/google/protobuf/GeneratedMessage$FieldAccessorTable;
     354: invokestatic  #10                 // Method getDescriptor:()Lcom/google/protobuf/Descriptors$FileDescriptor;
     357: invokevirtual #11                 // Method com/google/protobuf/Descriptors$FileDescriptor.getMessageTypes:()Ljava/util/List;
     360: bipush        8
     362: invokeinterface #12,  2           // InterfaceMethod java/util/List.get:(I)Ljava/lang/Object;
     367: checkcast     #13                 // class com/google/protobuf/Descriptors$Descriptor
     370: putstatic     #33                 // Field internal_static_google_protobuf_BytesValue_descriptor:Lcom/google/protobuf/Descriptors$Descriptor;
     373: new           #15                 // class com/google/protobuf/GeneratedMessage$FieldAccessorTable
     376: dup
     377: getstatic     #33                 // Field internal_static_google_protobuf_BytesValue_descriptor:Lcom/google/protobuf/Descriptors$Descriptor;
     380: iconst_1
     381: anewarray     #3                  // class java/lang/String
     384: dup
     385: iconst_0
     386: ldc           #16                 // String Value
     388: aastore
     389: invokespecial #17                 // Method com/google/protobuf/GeneratedMessage$FieldAccessorTable."<init>":(Lcom/google/protobuf/Descriptors$Descriptor;[Ljava/lang/String;)V
     392: putstatic     #34                 // Field internal_static_google_protobuf_BytesValue_fieldAccessorTable:Lcom/google/protobuf/GeneratedMessage$FieldAccessorTable;
     395: return
}
