Compiled from "GroupHandlingAbstract.java"
public abstract class org.apache.activemq.artemis.core.server.group.impl.GroupHandlingAbstract implements org.apache.activemq.artemis.core.server.group.GroupingHandler {
  protected final java.util.concurrent.Executor executor;

  protected final org.apache.activemq.artemis.core.server.management.ManagementService managementService;

  protected final org.apache.activemq.artemis.api.core.SimpleString address;

  final java.util.Set<org.apache.activemq.artemis.core.server.group.UnproposalListener> listeners;

  public org.apache.activemq.artemis.core.server.group.impl.GroupHandlingAbstract(java.util.concurrent.Executor, org.apache.activemq.artemis.core.server.management.ManagementService, org.apache.activemq.artemis.api.core.SimpleString);
    Code:
       0: aload_0
       1: invokespecial #1                  // Method java/lang/Object."<init>":()V
       4: aload_0
       5: new           #2                  // class java/util/WeakHashMap
       8: dup
       9: invokespecial #3                  // Method java/util/WeakHashMap."<init>":()V
      12: invokestatic  #4                  // Method java/util/Collections.newSetFromMap:(Ljava/util/Map;)Ljava/util/Set;
      15: putfield      #5                  // Field listeners:Ljava/util/Set;
      18: aload_0
      19: aload_1
      20: putfield      #6                  // Field executor:Ljava/util/concurrent/Executor;
      23: aload_0
      24: aload_2
      25: putfield      #7                  // Field managementService:Lorg/apache/activemq/artemis/core/server/management/ManagementService;
      28: aload_0
      29: aload_3
      30: putfield      #8                  // Field address:Lorg/apache/activemq/artemis/api/core/SimpleString;
      33: return

  public void addListener(org.apache.activemq.artemis.core.server.group.UnproposalListener);
    Code:
       0: aload_0
       1: getfield      #6                  // Field executor:Ljava/util/concurrent/Executor;
       4: ifnonnull     21
       7: aload_0
       8: getfield      #5                  // Field listeners:Ljava/util/Set;
      11: aload_1
      12: invokeinterface #9,  2            // InterfaceMethod java/util/Set.add:(Ljava/lang/Object;)Z
      17: pop
      18: goto          39
      21: aload_0
      22: getfield      #6                  // Field executor:Ljava/util/concurrent/Executor;
      25: new           #10                 // class org/apache/activemq/artemis/core/server/group/impl/GroupHandlingAbstract$1
      28: dup
      29: aload_0
      30: aload_1
      31: invokespecial #11                 // Method org/apache/activemq/artemis/core/server/group/impl/GroupHandlingAbstract$1."<init>":(Lorg/apache/activemq/artemis/core/server/group/impl/GroupHandlingAbstract;Lorg/apache/activemq/artemis/core/server/group/UnproposalListener;)V
      34: invokeinterface #12,  2           // InterfaceMethod java/util/concurrent/Executor.execute:(Ljava/lang/Runnable;)V
      39: return

  protected void fireUnproposed(org.apache.activemq.artemis.api.core.SimpleString);
    Code:
       0: new           #13                 // class org/apache/activemq/artemis/core/server/group/impl/GroupHandlingAbstract$2
       3: dup
       4: aload_0
       5: aload_1
       6: invokespecial #14                 // Method org/apache/activemq/artemis/core/server/group/impl/GroupHandlingAbstract$2."<init>":(Lorg/apache/activemq/artemis/core/server/group/impl/GroupHandlingAbstract;Lorg/apache/activemq/artemis/api/core/SimpleString;)V
       9: astore_2
      10: aload_0
      11: getfield      #6                  // Field executor:Ljava/util/concurrent/Executor;
      14: ifnull        30
      17: aload_0
      18: getfield      #6                  // Field executor:Ljava/util/concurrent/Executor;
      21: aload_2
      22: invokeinterface #12,  2           // InterfaceMethod java/util/concurrent/Executor.execute:(Ljava/lang/Runnable;)V
      27: goto          36
      30: aload_2
      31: invokeinterface #15,  1           // InterfaceMethod java/lang/Runnable.run:()V
      36: return

  public void forceRemove(org.apache.activemq.artemis.api.core.SimpleString, org.apache.activemq.artemis.api.core.SimpleString) throws java.lang.Exception;
    Code:
       0: aload_0
       1: aload_1
       2: aload_2
       3: invokevirtual #16                 // Method remove:(Lorg/apache/activemq/artemis/api/core/SimpleString;Lorg/apache/activemq/artemis/api/core/SimpleString;)V
       6: aload_0
       7: aload_1
       8: aload_2
       9: iconst_0
      10: invokevirtual #17                 // Method sendUnproposal:(Lorg/apache/activemq/artemis/api/core/SimpleString;Lorg/apache/activemq/artemis/api/core/SimpleString;I)V
      13: return

  protected void sendUnproposal(org.apache.activemq.artemis.api.core.SimpleString, org.apache.activemq.artemis.api.core.SimpleString, int);
    Code:
       0: new           #18                 // class org/apache/activemq/artemis/utils/TypedProperties
       3: dup
       4: invokespecial #19                 // Method org/apache/activemq/artemis/utils/TypedProperties."<init>":()V
       7: astore        4
       9: aload         4
      11: getstatic     #20                 // Field org/apache/activemq/artemis/api/core/management/ManagementHelper.HDR_PROPOSAL_GROUP_ID:Lorg/apache/activemq/artemis/api/core/SimpleString;
      14: aload_1
      15: invokevirtual #21                 // Method org/apache/activemq/artemis/utils/TypedProperties.putSimpleStringProperty:(Lorg/apache/activemq/artemis/api/core/SimpleString;Lorg/apache/activemq/artemis/api/core/SimpleString;)V
      18: aload         4
      20: getstatic     #22                 // Field org/apache/activemq/artemis/api/core/management/ManagementHelper.HDR_PROPOSAL_VALUE:Lorg/apache/activemq/artemis/api/core/SimpleString;
      23: aload_2
      24: invokevirtual #21                 // Method org/apache/activemq/artemis/utils/TypedProperties.putSimpleStringProperty:(Lorg/apache/activemq/artemis/api/core/SimpleString;Lorg/apache/activemq/artemis/api/core/SimpleString;)V
      27: aload         4
      29: getstatic     #23                 // Field org/apache/activemq/artemis/api/core/management/ManagementHelper.HDR_BINDING_TYPE:Lorg/apache/activemq/artemis/api/core/SimpleString;
      32: iconst_0
      33: invokevirtual #25                 // Method org/apache/activemq/artemis/utils/TypedProperties.putIntProperty:(Lorg/apache/activemq/artemis/api/core/SimpleString;I)V
      36: aload         4
      38: getstatic     #26                 // Field org/apache/activemq/artemis/api/core/management/ManagementHelper.HDR_ADDRESS:Lorg/apache/activemq/artemis/api/core/SimpleString;
      41: aload_0
      42: getfield      #8                  // Field address:Lorg/apache/activemq/artemis/api/core/SimpleString;
      45: invokevirtual #21                 // Method org/apache/activemq/artemis/utils/TypedProperties.putSimpleStringProperty:(Lorg/apache/activemq/artemis/api/core/SimpleString;Lorg/apache/activemq/artemis/api/core/SimpleString;)V
      48: aload         4
      50: getstatic     #27                 // Field org/apache/activemq/artemis/api/core/management/ManagementHelper.HDR_DISTANCE:Lorg/apache/activemq/artemis/api/core/SimpleString;
      53: iload_3
      54: invokevirtual #25                 // Method org/apache/activemq/artemis/utils/TypedProperties.putIntProperty:(Lorg/apache/activemq/artemis/api/core/SimpleString;I)V
      57: new           #28                 // class org/apache/activemq/artemis/core/server/management/Notification
      60: dup
      61: aconst_null
      62: getstatic     #29                 // Field org/apache/activemq/artemis/api/core/management/CoreNotificationType.UNPROPOSAL:Lorg/apache/activemq/artemis/api/core/management/CoreNotificationType;
      65: aload         4
      67: invokespecial #30                 // Method org/apache/activemq/artemis/core/server/management/Notification."<init>":(Ljava/lang/String;Lorg/apache/activemq/artemis/api/core/management/NotificationType;Lorg/apache/activemq/artemis/utils/TypedProperties;)V
      70: astore        5
      72: aload_0
      73: getfield      #7                  // Field managementService:Lorg/apache/activemq/artemis/core/server/management/ManagementService;
      76: aload         5
      78: invokeinterface #31,  2           // InterfaceMethod org/apache/activemq/artemis/core/server/management/ManagementService.sendNotification:(Lorg/apache/activemq/artemis/core/server/management/Notification;)V
      83: goto          98
      86: astore        6
      88: getstatic     #33                 // Field org/apache/activemq/artemis/core/server/ActiveMQServerLogger.LOGGER:Lorg/apache/activemq/artemis/core/server/ActiveMQServerLogger;
      91: aload         6
      93: invokeinterface #34,  2           // InterfaceMethod org/apache/activemq/artemis/core/server/ActiveMQServerLogger.errorHandlingMessage:(Ljava/lang/Exception;)V
      98: return
    Exception table:
       from    to  target type
          72    83    86   Class java/lang/Exception
}
