Compiled from "LocalGroupingHandler.java"
final class org.apache.activemq.artemis.core.server.group.impl.LocalGroupingHandler$GroupReaperScheduler implements java.lang.Runnable {
  final org.apache.activemq.artemis.core.server.group.impl.LocalGroupingHandler$GroupIdReaper reaper;

  final org.apache.activemq.artemis.core.server.group.impl.LocalGroupingHandler this$0;

  private org.apache.activemq.artemis.core.server.group.impl.LocalGroupingHandler$GroupReaperScheduler(org.apache.activemq.artemis.core.server.group.impl.LocalGroupingHandler);
    Code:
       0: aload_0
       1: aload_1
       2: putfield      #2                  // Field this$0:Lorg/apache/activemq/artemis/core/server/group/impl/LocalGroupingHandler;
       5: aload_0
       6: invokespecial #3                  // Method java/lang/Object."<init>":()V
       9: aload_0
      10: new           #4                  // class org/apache/activemq/artemis/core/server/group/impl/LocalGroupingHandler$GroupIdReaper
      13: dup
      14: aload_0
      15: getfield      #2                  // Field this$0:Lorg/apache/activemq/artemis/core/server/group/impl/LocalGroupingHandler;
      18: aconst_null
      19: invokespecial #5                  // Method org/apache/activemq/artemis/core/server/group/impl/LocalGroupingHandler$GroupIdReaper."<init>":(Lorg/apache/activemq/artemis/core/server/group/impl/LocalGroupingHandler;Lorg/apache/activemq/artemis/core/server/group/impl/LocalGroupingHandler$1;)V
      22: putfield      #6                  // Field reaper:Lorg/apache/activemq/artemis/core/server/group/impl/LocalGroupingHandler$GroupIdReaper;
      25: return

  public void run();
    Code:
       0: aload_0
       1: getfield      #2                  // Field this$0:Lorg/apache/activemq/artemis/core/server/group/impl/LocalGroupingHandler;
       4: getfield      #7                  // Field org/apache/activemq/artemis/core/server/group/impl/LocalGroupingHandler.executor:Ljava/util/concurrent/Executor;
       7: aload_0
       8: getfield      #6                  // Field reaper:Lorg/apache/activemq/artemis/core/server/group/impl/LocalGroupingHandler$GroupIdReaper;
      11: invokeinterface #8,  2            // InterfaceMethod java/util/concurrent/Executor.execute:(Ljava/lang/Runnable;)V
      16: return

  org.apache.activemq.artemis.core.server.group.impl.LocalGroupingHandler$GroupReaperScheduler(org.apache.activemq.artemis.core.server.group.impl.LocalGroupingHandler, org.apache.activemq.artemis.core.server.group.impl.LocalGroupingHandler$1);
    Code:
       0: aload_0
       1: aload_1
       2: invokespecial #1                  // Method "<init>":(Lorg/apache/activemq/artemis/core/server/group/impl/LocalGroupingHandler;)V
       5: return
}
