Compiled from "EncodingPatternConverter.java"
final class org.apache.logging.log4j.core.pattern.EncodingPatternConverter$EscapeFormat$3 extends org.apache.logging.log4j.core.pattern.EncodingPatternConverter$EscapeFormat {
  org.apache.logging.log4j.core.pattern.EncodingPatternConverter$EscapeFormat$3(java.lang.String, int);
    Code:
       0: aload_0
       1: aload_1
       2: iload_2
       3: aconst_null
       4: invokespecial #1                  // Method org/apache/logging/log4j/core/pattern/EncodingPatternConverter$EscapeFormat."<init>":(Ljava/lang/String;ILorg/apache/logging/log4j/core/pattern/EncodingPatternConverter$1;)V
       7: return

  void escape(java.lang.StringBuilder, int);
    Code:
       0: aload_1
       1: invokevirtual #2                  // Method java/lang/StringBuilder.length:()I
       4: istore_3
       5: iload_3
       6: istore        4
       8: iload_3
       9: iconst_1
      10: isub
      11: istore        5
      13: iload         5
      15: iload_2
      16: if_icmplt     58
      19: aload_1
      20: iload         5
      22: invokevirtual #3                  // Method java/lang/StringBuilder.charAt:(I)C
      25: istore        6
      27: iload         6
      29: bipush        13
      31: if_icmpeq     41
      34: iload         6
      36: bipush        10
      38: if_icmpne     52
      41: iload         5
      43: istore        4
      45: aload_1
      46: bipush        32
      48: invokevirtual #4                  // Method java/lang/StringBuilder.append:(C)Ljava/lang/StringBuilder;
      51: pop
      52: iinc          5, -1
      55: goto          13
      58: iload_3
      59: iconst_1
      60: isub
      61: istore        5
      63: aload_1
      64: invokevirtual #2                  // Method java/lang/StringBuilder.length:()I
      67: istore        6
      69: iload         5
      71: iload         4
      73: if_icmplt     179
      76: aload_1
      77: iload         5
      79: invokevirtual #3                  // Method java/lang/StringBuilder.charAt:(I)C
      82: istore        7
      84: iload         7
      86: lookupswitch  { // 2
                    10: 137
                    13: 112
               default: 162
          }
     112: aload_1
     113: iinc          6, -1
     116: iload         6
     118: bipush        114
     120: invokevirtual #5                  // Method java/lang/StringBuilder.setCharAt:(IC)V
     123: aload_1
     124: iinc          6, -1
     127: iload         6
     129: bipush        92
     131: invokevirtual #5                  // Method java/lang/StringBuilder.setCharAt:(IC)V
     134: goto          173
     137: aload_1
     138: iinc          6, -1
     141: iload         6
     143: bipush        110
     145: invokevirtual #5                  // Method java/lang/StringBuilder.setCharAt:(IC)V
     148: aload_1
     149: iinc          6, -1
     152: iload         6
     154: bipush        92
     156: invokevirtual #5                  // Method java/lang/StringBuilder.setCharAt:(IC)V
     159: goto          173
     162: aload_1
     163: iinc          6, -1
     166: iload         6
     168: iload         7
     170: invokevirtual #5                  // Method java/lang/StringBuilder.setCharAt:(IC)V
     173: iinc          5, -1
     176: goto          69
     179: return
}
