Compiled from "RepeatPatternConverter.java"
public final class org.apache.logging.log4j.core.pattern.RepeatPatternConverter extends org.apache.logging.log4j.core.pattern.LogEventPatternConverter {
  private final java.lang.String result;

  public static org.apache.logging.log4j.core.pattern.RepeatPatternConverter newInstance(org.apache.logging.log4j.core.config.Configuration, java.lang.String[]);
    Code:
       0: aload_1
       1: arraylength
       2: iconst_2
       3: if_icmpeq     36
       6: getstatic     #1                  // Field LOGGER:Lorg/apache/logging/log4j/Logger;
       9: new           #2                  // class java/lang/StringBuilder
      12: dup
      13: invokespecial #3                  // Method java/lang/StringBuilder."<init>":()V
      16: ldc           #4                  // String Incorrect number of options on repeat. Expected 2 received
      18: invokevirtual #5                  // Method java/lang/StringBuilder.append:(Ljava/lang/String;)Ljava/lang/StringBuilder;
      21: aload_1
      22: arraylength
      23: invokevirtual #6                  // Method java/lang/StringBuilder.append:(I)Ljava/lang/StringBuilder;
      26: invokevirtual #7                  // Method java/lang/StringBuilder.toString:()Ljava/lang/String;
      29: invokeinterface #8,  2            // InterfaceMethod org/apache/logging/log4j/Logger.error:(Ljava/lang/String;)V
      34: aconst_null
      35: areturn
      36: aload_1
      37: iconst_0
      38: aaload
      39: ifnonnull     54
      42: getstatic     #1                  // Field LOGGER:Lorg/apache/logging/log4j/Logger;
      45: ldc           #9                  // String No string supplied on repeat
      47: invokeinterface #8,  2            // InterfaceMethod org/apache/logging/log4j/Logger.error:(Ljava/lang/String;)V
      52: aconst_null
      53: areturn
      54: aload_1
      55: iconst_1
      56: aaload
      57: ifnonnull     72
      60: getstatic     #1                  // Field LOGGER:Lorg/apache/logging/log4j/Logger;
      63: ldc           #10                 // String No repeat count supplied on repeat
      65: invokeinterface #8,  2            // InterfaceMethod org/apache/logging/log4j/Logger.error:(Ljava/lang/String;)V
      70: aconst_null
      71: areturn
      72: iconst_0
      73: istore_2
      74: aload_1
      75: iconst_0
      76: aaload
      77: astore_3
      78: aload_1
      79: iconst_1
      80: aaload
      81: invokevirtual #11                 // Method java/lang/String.trim:()Ljava/lang/String;
      84: invokestatic  #12                 // Method java/lang/Integer.parseInt:(Ljava/lang/String;)I
      87: istore_2
      88: aload_1
      89: iconst_0
      90: aaload
      91: iload_2
      92: invokestatic  #13                 // Method org/apache/logging/log4j/util/Strings.repeat:(Ljava/lang/String;I)Ljava/lang/String;
      95: astore_3
      96: goto          117
      99: astore        4
     101: getstatic     #1                  // Field LOGGER:Lorg/apache/logging/log4j/Logger;
     104: ldc           #15                 // String The repeat count is not an integer: {}
     106: aload_1
     107: iconst_1
     108: aaload
     109: invokevirtual #11                 // Method java/lang/String.trim:()Ljava/lang/String;
     112: invokeinterface #16,  3           // InterfaceMethod org/apache/logging/log4j/Logger.error:(Ljava/lang/String;Ljava/lang/Object;)V
     117: new           #17                 // class org/apache/logging/log4j/core/pattern/RepeatPatternConverter
     120: dup
     121: aload_3
     122: invokespecial #18                 // Method "<init>":(Ljava/lang/String;)V
     125: areturn
    Exception table:
       from    to  target type
          78    96    99   Class java/lang/Exception

  private org.apache.logging.log4j.core.pattern.RepeatPatternConverter(java.lang.String);
    Code:
       0: aload_0
       1: ldc           #19                 // String repeat
       3: ldc           #19                 // String repeat
       5: invokespecial #20                 // Method org/apache/logging/log4j/core/pattern/LogEventPatternConverter."<init>":(Ljava/lang/String;Ljava/lang/String;)V
       8: aload_0
       9: aload_1
      10: putfield      #21                 // Field result:Ljava/lang/String;
      13: return

  public void format(java.lang.Object, java.lang.StringBuilder);
    Code:
       0: aload_0
       1: aload_2
       2: invokespecial #22                 // Method format:(Ljava/lang/StringBuilder;)V
       5: return

  public void format(org.apache.logging.log4j.core.LogEvent, java.lang.StringBuilder);
    Code:
       0: aload_0
       1: aload_2
       2: invokespecial #22                 // Method format:(Ljava/lang/StringBuilder;)V
       5: return

  private void format(java.lang.StringBuilder);
    Code:
       0: aload_0
       1: getfield      #21                 // Field result:Ljava/lang/String;
       4: ifnull        16
       7: aload_1
       8: aload_0
       9: getfield      #21                 // Field result:Ljava/lang/String;
      12: invokevirtual #5                  // Method java/lang/StringBuilder.append:(Ljava/lang/String;)Ljava/lang/StringBuilder;
      15: pop
      16: return
}
