Compiled from "PosNeg.scala"
public final class es.weso.depgraphs.Both {
  public static boolean canEqual(java.lang.Object);
    Code:
       0: getstatic     #18                 // Field es/weso/depgraphs/Both$.MODULE$:Les/weso/depgraphs/Both$;
       3: aload_0
       4: invokevirtual #20                 // Method es/weso/depgraphs/Both$.canEqual:(Ljava/lang/Object;)Z
       7: ireturn

  public static es.weso.depgraphs.PosNeg change();
    Code:
       0: getstatic     #18                 // Field es/weso/depgraphs/Both$.MODULE$:Les/weso/depgraphs/Both$;
       3: invokevirtual #24                 // Method es/weso/depgraphs/Both$.change:()Les/weso/depgraphs/PosNeg;
       6: areturn

  public static es.weso.depgraphs.PosNeg combine(es.weso.depgraphs.PosNeg);
    Code:
       0: getstatic     #18                 // Field es/weso/depgraphs/Both$.MODULE$:Les/weso/depgraphs/Both$;
       3: aload_0
       4: invokevirtual #28                 // Method es/weso/depgraphs/Both$.combine:(Les/weso/depgraphs/PosNeg;)Les/weso/depgraphs/PosNeg;
       7: areturn

  public static scala.deriving.Mirror$Singleton fromProduct(scala.Product);
    Code:
       0: getstatic     #18                 // Field es/weso/depgraphs/Both$.MODULE$:Les/weso/depgraphs/Both$;
       3: aload_0
       4: invokevirtual #32                 // Method es/weso/depgraphs/Both$.fromProduct:(Lscala/Product;)Lscala/deriving/Mirror$Singleton;
       7: areturn

  public static int hashCode();
    Code:
       0: getstatic     #18                 // Field es/weso/depgraphs/Both$.MODULE$:Les/weso/depgraphs/Both$;
       3: invokevirtual #36                 // Method es/weso/depgraphs/Both$.hashCode:()I
       6: ireturn

  public static int productArity();
    Code:
       0: getstatic     #18                 // Field es/weso/depgraphs/Both$.MODULE$:Les/weso/depgraphs/Both$;
       3: invokevirtual #39                 // Method es/weso/depgraphs/Both$.productArity:()I
       6: ireturn

  public static java.lang.Object productElement(int);
    Code:
       0: getstatic     #18                 // Field es/weso/depgraphs/Both$.MODULE$:Les/weso/depgraphs/Both$;
       3: iload_0
       4: invokevirtual #43                 // Method es/weso/depgraphs/Both$.productElement:(I)Ljava/lang/Object;
       7: areturn

  public static java.lang.String productElementName(int);
    Code:
       0: getstatic     #18                 // Field es/weso/depgraphs/Both$.MODULE$:Les/weso/depgraphs/Both$;
       3: iload_0
       4: invokevirtual #47                 // Method es/weso/depgraphs/Both$.productElementName:(I)Ljava/lang/String;
       7: areturn

  public static scala.collection.Iterator<java.lang.String> productElementNames();
    Code:
       0: getstatic     #18                 // Field es/weso/depgraphs/Both$.MODULE$:Les/weso/depgraphs/Both$;
       3: invokevirtual #52                 // Method es/weso/depgraphs/Both$.productElementNames:()Lscala/collection/Iterator;
       6: areturn

  public static scala.collection.Iterator<java.lang.Object> productIterator();
    Code:
       0: getstatic     #18                 // Field es/weso/depgraphs/Both$.MODULE$:Les/weso/depgraphs/Both$;
       3: invokevirtual #56                 // Method es/weso/depgraphs/Both$.productIterator:()Lscala/collection/Iterator;
       6: areturn

  public static java.lang.String productPrefix();
    Code:
       0: getstatic     #18                 // Field es/weso/depgraphs/Both$.MODULE$:Les/weso/depgraphs/Both$;
       3: invokevirtual #60                 // Method es/weso/depgraphs/Both$.productPrefix:()Ljava/lang/String;
       6: areturn

  public static java.lang.String toString();
    Code:
       0: getstatic     #18                 // Field es/weso/depgraphs/Both$.MODULE$:Les/weso/depgraphs/Both$;
       3: invokevirtual #63                 // Method es/weso/depgraphs/Both$.toString:()Ljava/lang/String;
       6: areturn
}
