Compiled from "NetworkTopologyWithNodeGroup.java"
class org.apache.hadoop.net.NetworkTopologyWithNodeGroup$InnerNodeWithNodeGroup extends org.apache.hadoop.net.InnerNodeImpl {
  public org.apache.hadoop.net.NetworkTopologyWithNodeGroup$InnerNodeWithNodeGroup(java.lang.String);
    Code:
       0: aload_0
       1: aload_1
       2: invokespecial #1                  // Method org/apache/hadoop/net/InnerNodeImpl."<init>":(Ljava/lang/String;)V
       5: return

  public boolean isRack();
    Code:
       0: aload_0
       1: invokevirtual #2                  // Method getChildren:()Ljava/util/List;
       4: invokeinterface #3,  1            // InterfaceMethod java/util/List.isEmpty:()Z
       9: ifeq          14
      12: iconst_0
      13: ireturn
      14: aload_0
      15: invokevirtual #2                  // Method getChildren:()Ljava/util/List;
      18: iconst_0
      19: invokeinterface #4,  2            // InterfaceMethod java/util/List.get:(I)Ljava/lang/Object;
      24: checkcast     #5                  // class org/apache/hadoop/net/Node
      27: astore_1
      28: aload_1
      29: instanceof    #6                  // class org/apache/hadoop/net/InnerNode
      32: ifeq          65
      35: aload_1
      36: checkcast     #6                  // class org/apache/hadoop/net/InnerNode
      39: invokeinterface #7,  1            // InterfaceMethod org/apache/hadoop/net/InnerNode.getChildren:()Ljava/util/List;
      44: iconst_0
      45: invokeinterface #4,  2            // InterfaceMethod java/util/List.get:(I)Ljava/lang/Object;
      50: checkcast     #5                  // class org/apache/hadoop/net/Node
      53: astore_2
      54: aload_2
      55: instanceof    #6                  // class org/apache/hadoop/net/InnerNode
      58: ifeq          63
      61: iconst_0
      62: ireturn
      63: iconst_1
      64: ireturn
      65: iconst_0
      66: ireturn

  boolean isNodeGroup();
    Code:
       0: aload_0
       1: invokevirtual #2                  // Method getChildren:()Ljava/util/List;
       4: invokeinterface #3,  1            // InterfaceMethod java/util/List.isEmpty:()Z
       9: ifeq          14
      12: iconst_1
      13: ireturn
      14: aload_0
      15: invokevirtual #2                  // Method getChildren:()Ljava/util/List;
      18: iconst_0
      19: invokeinterface #4,  2            // InterfaceMethod java/util/List.get:(I)Ljava/lang/Object;
      24: checkcast     #5                  // class org/apache/hadoop/net/Node
      27: astore_1
      28: aload_1
      29: instanceof    #6                  // class org/apache/hadoop/net/InnerNode
      32: ifeq          37
      35: iconst_0
      36: ireturn
      37: iconst_1
      38: ireturn
}
