Compiled from "SocksSocketFactory.java"
public class org.apache.hadoop.net.SocksSocketFactory extends javax.net.SocketFactory implements org.apache.hadoop.conf.Configurable {
  private org.apache.hadoop.conf.Configuration conf;

  private java.net.Proxy proxy;

  public org.apache.hadoop.net.SocksSocketFactory();
    Code:
       0: aload_0
       1: invokespecial #2                  // Method javax/net/SocketFactory."<init>":()V
       4: aload_0
       5: getstatic     #3                  // Field java/net/Proxy.NO_PROXY:Ljava/net/Proxy;
       8: putfield      #4                  // Field proxy:Ljava/net/Proxy;
      11: return

  public org.apache.hadoop.net.SocksSocketFactory(java.net.Proxy);
    Code:
       0: aload_0
       1: invokespecial #2                  // Method javax/net/SocketFactory."<init>":()V
       4: aload_0
       5: aload_1
       6: putfield      #4                  // Field proxy:Ljava/net/Proxy;
       9: return

  public java.net.Socket createSocket() throws java.io.IOException;
    Code:
       0: new           #5                  // class java/net/Socket
       3: dup
       4: aload_0
       5: getfield      #4                  // Field proxy:Ljava/net/Proxy;
       8: invokespecial #6                  // Method java/net/Socket."<init>":(Ljava/net/Proxy;)V
      11: areturn

  public java.net.Socket createSocket(java.net.InetAddress, int) throws java.io.IOException;
    Code:
       0: aload_0
       1: invokevirtual #7                  // Method createSocket:()Ljava/net/Socket;
       4: astore_3
       5: aload_3
       6: new           #8                  // class java/net/InetSocketAddress
       9: dup
      10: aload_1
      11: iload_2
      12: invokespecial #9                  // Method java/net/InetSocketAddress."<init>":(Ljava/net/InetAddress;I)V
      15: invokevirtual #10                 // Method java/net/Socket.connect:(Ljava/net/SocketAddress;)V
      18: aload_3
      19: areturn

  public java.net.Socket createSocket(java.net.InetAddress, int, java.net.InetAddress, int) throws java.io.IOException;
    Code:
       0: aload_0
       1: invokevirtual #7                  // Method createSocket:()Ljava/net/Socket;
       4: astore        5
       6: aload         5
       8: new           #8                  // class java/net/InetSocketAddress
      11: dup
      12: aload_3
      13: iload         4
      15: invokespecial #9                  // Method java/net/InetSocketAddress."<init>":(Ljava/net/InetAddress;I)V
      18: invokevirtual #11                 // Method java/net/Socket.bind:(Ljava/net/SocketAddress;)V
      21: aload         5
      23: new           #8                  // class java/net/InetSocketAddress
      26: dup
      27: aload_1
      28: iload_2
      29: invokespecial #9                  // Method java/net/InetSocketAddress."<init>":(Ljava/net/InetAddress;I)V
      32: invokevirtual #10                 // Method java/net/Socket.connect:(Ljava/net/SocketAddress;)V
      35: aload         5
      37: areturn

  public java.net.Socket createSocket(java.lang.String, int) throws java.io.IOException, java.net.UnknownHostException;
    Code:
       0: aload_0
       1: invokevirtual #7                  // Method createSocket:()Ljava/net/Socket;
       4: astore_3
       5: aload_3
       6: new           #8                  // class java/net/InetSocketAddress
       9: dup
      10: aload_1
      11: iload_2
      12: invokespecial #12                 // Method java/net/InetSocketAddress."<init>":(Ljava/lang/String;I)V
      15: invokevirtual #10                 // Method java/net/Socket.connect:(Ljava/net/SocketAddress;)V
      18: aload_3
      19: areturn

  public java.net.Socket createSocket(java.lang.String, int, java.net.InetAddress, int) throws java.io.IOException, java.net.UnknownHostException;
    Code:
       0: aload_0
       1: invokevirtual #7                  // Method createSocket:()Ljava/net/Socket;
       4: astore        5
       6: aload         5
       8: new           #8                  // class java/net/InetSocketAddress
      11: dup
      12: aload_3
      13: iload         4
      15: invokespecial #9                  // Method java/net/InetSocketAddress."<init>":(Ljava/net/InetAddress;I)V
      18: invokevirtual #11                 // Method java/net/Socket.bind:(Ljava/net/SocketAddress;)V
      21: aload         5
      23: new           #8                  // class java/net/InetSocketAddress
      26: dup
      27: aload_1
      28: iload_2
      29: invokespecial #12                 // Method java/net/InetSocketAddress."<init>":(Ljava/lang/String;I)V
      32: invokevirtual #10                 // Method java/net/Socket.connect:(Ljava/net/SocketAddress;)V
      35: aload         5
      37: areturn

  public int hashCode();
    Code:
       0: aload_0
       1: getfield      #4                  // Field proxy:Ljava/net/Proxy;
       4: invokevirtual #13                 // Method java/net/Proxy.hashCode:()I
       7: ireturn

  public boolean equals(java.lang.Object);
    Code:
       0: aload_0
       1: aload_1
       2: if_acmpne     7
       5: iconst_1
       6: ireturn
       7: aload_1
       8: ifnonnull     13
      11: iconst_0
      12: ireturn
      13: aload_1
      14: instanceof    #14                 // class org/apache/hadoop/net/SocksSocketFactory
      17: ifne          22
      20: iconst_0
      21: ireturn
      22: aload_1
      23: checkcast     #14                 // class org/apache/hadoop/net/SocksSocketFactory
      26: astore_2
      27: aload_0
      28: getfield      #4                  // Field proxy:Ljava/net/Proxy;
      31: ifnonnull     43
      34: aload_2
      35: getfield      #4                  // Field proxy:Ljava/net/Proxy;
      38: ifnull        59
      41: iconst_0
      42: ireturn
      43: aload_0
      44: getfield      #4                  // Field proxy:Ljava/net/Proxy;
      47: aload_2
      48: getfield      #4                  // Field proxy:Ljava/net/Proxy;
      51: invokevirtual #15                 // Method java/net/Proxy.equals:(Ljava/lang/Object;)Z
      54: ifne          59
      57: iconst_0
      58: ireturn
      59: iconst_1
      60: ireturn

  public org.apache.hadoop.conf.Configuration getConf();
    Code:
       0: aload_0
       1: getfield      #16                 // Field conf:Lorg/apache/hadoop/conf/Configuration;
       4: areturn

  public void setConf(org.apache.hadoop.conf.Configuration);
    Code:
       0: aload_0
       1: aload_1
       2: putfield      #16                 // Field conf:Lorg/apache/hadoop/conf/Configuration;
       5: aload_1
       6: ldc           #17                 // String hadoop.socks.server
       8: invokevirtual #18                 // Method org/apache/hadoop/conf/Configuration.get:(Ljava/lang/String;)Ljava/lang/String;
      11: astore_2
      12: aload_2
      13: ifnull        28
      16: aload_2
      17: invokevirtual #19                 // Method java/lang/String.length:()I
      20: ifle          28
      23: aload_0
      24: aload_2
      25: invokespecial #20                 // Method setProxy:(Ljava/lang/String;)V
      28: return

  private void setProxy(java.lang.String);
    Code:
       0: aload_1
       1: ldc           #21                 // String :
       3: iconst_2
       4: invokevirtual #22                 // Method java/lang/String.split:(Ljava/lang/String;I)[Ljava/lang/String;
       7: astore_2
       8: aload_2
       9: arraylength
      10: iconst_2
      11: if_icmpeq     41
      14: new           #23                 // class java/lang/RuntimeException
      17: dup
      18: new           #24                 // class java/lang/StringBuilder
      21: dup
      22: invokespecial #25                 // Method java/lang/StringBuilder."<init>":()V
      25: ldc           #26                 // String Bad SOCKS proxy parameter:
      27: invokevirtual #27                 // Method java/lang/StringBuilder.append:(Ljava/lang/String;)Ljava/lang/StringBuilder;
      30: aload_1
      31: invokevirtual #27                 // Method java/lang/StringBuilder.append:(Ljava/lang/String;)Ljava/lang/StringBuilder;
      34: invokevirtual #28                 // Method java/lang/StringBuilder.toString:()Ljava/lang/String;
      37: invokespecial #29                 // Method java/lang/RuntimeException."<init>":(Ljava/lang/String;)V
      40: athrow
      41: aload_2
      42: iconst_0
      43: aaload
      44: astore_3
      45: aload_2
      46: iconst_1
      47: aaload
      48: invokestatic  #30                 // Method java/lang/Integer.parseInt:(Ljava/lang/String;)I
      51: istore        4
      53: aload_0
      54: new           #31                 // class java/net/Proxy
      57: dup
      58: getstatic     #32                 // Field java/net/Proxy$Type.SOCKS:Ljava/net/Proxy$Type;
      61: aload_3
      62: iload         4
      64: invokestatic  #33                 // Method java/net/InetSocketAddress.createUnresolved:(Ljava/lang/String;I)Ljava/net/InetSocketAddress;
      67: invokespecial #34                 // Method java/net/Proxy."<init>":(Ljava/net/Proxy$Type;Ljava/net/SocketAddress;)V
      70: putfield      #4                  // Field proxy:Ljava/net/Proxy;
      73: return
}
