Compiled from "OnImmediateReceiver.kt"
public final class kweb.html.events.OnImmediateReceiverKt {
  public static final void main();
    Code:
       0: new           #8                  // class kweb/Kweb
       3: dup
       4: sipush        7660
       7: iconst_0
       8: aconst_null
       9: aconst_null
      10: aconst_null
      11: getstatic     #14                 // Field kweb/html/events/OnImmediateReceiverKt$main$server$1.INSTANCE:Lkweb/html/events/OnImmediateReceiverKt$main$server$1;
      14: checkcast     #16                 // class kotlin/jvm/functions/Function1
      17: bipush        30
      19: aconst_null
      20: invokespecial #20                 // Method kweb/Kweb."<init>":(IZLjava/util/List;Lio/ktor/server/engine/EngineSSLConnectorConfig;Lkweb/config/KwebConfiguration;Lkotlin/jvm/functions/Function1;ILkotlin/jvm/internal/DefaultConstructorMarker;)V
      23: astore_0
      24: return

  public static void main(java.lang.String[]);
    Code:
       0: invokestatic  #25                 // Method main:()V
       3: return
}
