Compiled from "MicAlg.java"
public class sop.MicAlg {
  private final java.lang.String micAlg;

  public sop.MicAlg(java.lang.String);
    Code:
       0: aload_0
       1: invokespecial #1                  // Method java/lang/Object."<init>":()V
       4: aload_1
       5: ifnonnull     18
       8: new           #7                  // class java/lang/IllegalArgumentException
      11: dup
      12: ldc           #9                  // String MicAlg String cannot be null.
      14: invokespecial #11                 // Method java/lang/IllegalArgumentException."<init>":(Ljava/lang/String;)V
      17: athrow
      18: aload_0
      19: aload_1
      20: putfield      #14                 // Field micAlg:Ljava/lang/String;
      23: return

  public static sop.MicAlg empty();
    Code:
       0: new           #15                 // class sop/MicAlg
       3: dup
       4: ldc           #20                 // String
       6: invokespecial #22                 // Method "<init>":(Ljava/lang/String;)V
       9: areturn

  public static sop.MicAlg fromHashAlgorithmId(int);
    Code:
       0: iload_0
       1: tableswitch   { // 1 to 11
                     1: 60
                     2: 70
                     3: 80
                     4: 130
                     5: 130
                     6: 130
                     7: 130
                     8: 90
                     9: 100
                    10: 110
                    11: 120
               default: 130
          }
      60: new           #15                 // class sop/MicAlg
      63: dup
      64: ldc           #23                 // String pgp-md5
      66: invokespecial #22                 // Method "<init>":(Ljava/lang/String;)V
      69: areturn
      70: new           #15                 // class sop/MicAlg
      73: dup
      74: ldc           #25                 // String pgp-sha1
      76: invokespecial #22                 // Method "<init>":(Ljava/lang/String;)V
      79: areturn
      80: new           #15                 // class sop/MicAlg
      83: dup
      84: ldc           #27                 // String pgp-ripemd160
      86: invokespecial #22                 // Method "<init>":(Ljava/lang/String;)V
      89: areturn
      90: new           #15                 // class sop/MicAlg
      93: dup
      94: ldc           #29                 // String pgp-sha256
      96: invokespecial #22                 // Method "<init>":(Ljava/lang/String;)V
      99: areturn
     100: new           #15                 // class sop/MicAlg
     103: dup
     104: ldc           #31                 // String pgp-sha384
     106: invokespecial #22                 // Method "<init>":(Ljava/lang/String;)V
     109: areturn
     110: new           #15                 // class sop/MicAlg
     113: dup
     114: ldc           #33                 // String pgp-sha512
     116: invokespecial #22                 // Method "<init>":(Ljava/lang/String;)V
     119: areturn
     120: new           #15                 // class sop/MicAlg
     123: dup
     124: ldc           #35                 // String pgp-sha224
     126: invokespecial #22                 // Method "<init>":(Ljava/lang/String;)V
     129: areturn
     130: new           #7                  // class java/lang/IllegalArgumentException
     133: dup
     134: new           #37                 // class java/lang/StringBuilder
     137: dup
     138: invokespecial #39                 // Method java/lang/StringBuilder."<init>":()V
     141: ldc           #40                 // String Unsupported hash algorithm ID:
     143: invokevirtual #42                 // Method java/lang/StringBuilder.append:(Ljava/lang/String;)Ljava/lang/StringBuilder;
     146: iload_0
     147: invokevirtual #46                 // Method java/lang/StringBuilder.append:(I)Ljava/lang/StringBuilder;
     150: invokevirtual #49                 // Method java/lang/StringBuilder.toString:()Ljava/lang/String;
     153: invokespecial #11                 // Method java/lang/IllegalArgumentException."<init>":(Ljava/lang/String;)V
     156: athrow

  public java.lang.String getMicAlg();
    Code:
       0: aload_0
       1: getfield      #14                 // Field micAlg:Ljava/lang/String;
       4: areturn

  public void writeTo(java.io.OutputStream);
    Code:
       0: new           #53                 // class java/io/PrintWriter
       3: dup
       4: aload_1
       5: invokespecial #55                 // Method java/io/PrintWriter."<init>":(Ljava/io/OutputStream;)V
       8: astore_2
       9: aload_2
      10: aload_0
      11: invokevirtual #58                 // Method getMicAlg:()Ljava/lang/String;
      14: invokevirtual #61                 // Method java/io/PrintWriter.write:(Ljava/lang/String;)V
      17: aload_2
      18: invokevirtual #64                 // Method java/io/PrintWriter.close:()V
      21: return
}
