Compiled from "ProtocolServer.java"
class org.jboss.as.process.protocol.ProtocolServer$1 implements java.lang.Runnable {
  final java.net.ServerSocket val$serverSocket;

  final org.jboss.as.process.protocol.ProtocolServer this$0;

  org.jboss.as.process.protocol.ProtocolServer$1(org.jboss.as.process.protocol.ProtocolServer, java.net.ServerSocket);
    Code:
       0: aload_0
       1: aload_1
       2: putfield      #1                  // Field this$0:Lorg/jboss/as/process/protocol/ProtocolServer;
       5: aload_0
       6: aload_2
       7: putfield      #2                  // Field val$serverSocket:Ljava/net/ServerSocket;
      10: aload_0
      11: invokespecial #3                  // Method java/lang/Object."<init>":()V
      14: return

  public void run();
    Code:
       0: aload_0
       1: getfield      #2                  // Field val$serverSocket:Ljava/net/ServerSocket;
       4: invokevirtual #4                  // Method java/net/ServerSocket.isClosed:()Z
       7: ifne          142
      10: aload_0
      11: getfield      #1                  // Field this$0:Lorg/jboss/as/process/protocol/ProtocolServer;
      14: invokestatic  #5                  // Method org/jboss/as/process/protocol/ProtocolServer.access$000:(Lorg/jboss/as/process/protocol/ProtocolServer;)Z
      17: ifne          142
      20: aload_0
      21: getfield      #2                  // Field val$serverSocket:Ljava/net/ServerSocket;
      24: invokevirtual #6                  // Method java/net/ServerSocket.accept:()Ljava/net/Socket;
      27: astore_1
      28: iconst_0
      29: istore_2
      30: aload_1
      31: aload_0
      32: getfield      #1                  // Field this$0:Lorg/jboss/as/process/protocol/ProtocolServer;
      35: invokestatic  #7                  // Method org/jboss/as/process/protocol/ProtocolServer.access$100:(Lorg/jboss/as/process/protocol/ProtocolServer;)I
      38: invokevirtual #8                  // Method java/net/Socket.setSoTimeout:(I)V
      41: iconst_1
      42: istore_2
      43: iload_2
      44: ifne          95
      47: aload_1
      48: invokevirtual #9                  // Method java/net/Socket.close:()V
      51: goto          95
      54: astore_3
      55: getstatic     #11                 // Field org/jboss/as/process/logging/ProcessLogger.PROTOCOL_CLIENT_LOGGER:Lorg/jboss/as/process/logging/ProcessLogger;
      58: aload_3
      59: invokeinterface #12,  2           // InterfaceMethod org/jboss/as/process/logging/ProcessLogger.failedToCloseSocket:(Ljava/lang/Throwable;)V
      64: goto          95
      67: astore        4
      69: iload_2
      70: ifne          92
      73: aload_1
      74: invokevirtual #9                  // Method java/net/Socket.close:()V
      77: goto          92
      80: astore        5
      82: getstatic     #11                 // Field org/jboss/as/process/logging/ProcessLogger.PROTOCOL_CLIENT_LOGGER:Lorg/jboss/as/process/logging/ProcessLogger;
      85: aload         5
      87: invokeinterface #12,  2           // InterfaceMethod org/jboss/as/process/logging/ProcessLogger.failedToCloseSocket:(Ljava/lang/Throwable;)V
      92: aload         4
      94: athrow
      95: aload_0
      96: getfield      #1                  // Field this$0:Lorg/jboss/as/process/protocol/ProtocolServer;
      99: aload_1
     100: invokestatic  #13                 // Method org/jboss/as/process/protocol/ProtocolServer.access$200:(Lorg/jboss/as/process/protocol/ProtocolServer;Ljava/net/Socket;)V
     103: goto          0
     106: astore_1
     107: aload_0
     108: getfield      #1                  // Field this$0:Lorg/jboss/as/process/protocol/ProtocolServer;
     111: invokestatic  #5                  // Method org/jboss/as/process/protocol/ProtocolServer.access$000:(Lorg/jboss/as/process/protocol/ProtocolServer;)Z
     114: ifne          126
     117: getstatic     #11                 // Field org/jboss/as/process/logging/ProcessLogger.PROTOCOL_CLIENT_LOGGER:Lorg/jboss/as/process/logging/ProcessLogger;
     120: aload_1
     121: invokeinterface #15,  2           // InterfaceMethod org/jboss/as/process/logging/ProcessLogger.failedToAcceptConnection:(Ljava/lang/Throwable;)V
     126: goto          0
     129: astore_1
     130: getstatic     #11                 // Field org/jboss/as/process/logging/ProcessLogger.PROTOCOL_CLIENT_LOGGER:Lorg/jboss/as/process/logging/ProcessLogger;
     133: aload_1
     134: invokeinterface #15,  2           // InterfaceMethod org/jboss/as/process/logging/ProcessLogger.failedToAcceptConnection:(Ljava/lang/Throwable;)V
     139: goto          0
     142: aload_0
     143: getfield      #2                  // Field val$serverSocket:Ljava/net/ServerSocket;
     146: invokestatic  #16                 // Method org/jboss/as/process/protocol/StreamUtils.safeClose:(Ljava/net/ServerSocket;)V
     149: goto          164
     152: astore        6
     154: aload_0
     155: getfield      #2                  // Field val$serverSocket:Ljava/net/ServerSocket;
     158: invokestatic  #16                 // Method org/jboss/as/process/protocol/StreamUtils.safeClose:(Ljava/net/ServerSocket;)V
     161: aload         6
     163: athrow
     164: return
    Exception table:
       from    to  target type
          47    51    54   Class java/io/IOException
          30    43    67   any
          73    77    80   Class java/io/IOException
          67    69    67   any
          20   103   106   Class java/net/SocketException
          20   103   129   Class java/io/IOException
           0   142   152   any
         152   154   152   any
}
