Compiled from "Constants.scala"
public final class ammonite.Constants {
  public static java.lang.String unstableCurlUrl();
    Code:
       0: getstatic     #16                 // Field ammonite/Constants$.MODULE$:Lammonite/Constants$;
       3: invokevirtual #18                 // Method ammonite/Constants$.unstableCurlUrl:()Ljava/lang/String;
       6: areturn

  public static java.lang.String curlUrl();
    Code:
       0: getstatic     #16                 // Field ammonite/Constants$.MODULE$:Lammonite/Constants$;
       3: invokevirtual #21                 // Method ammonite/Constants$.curlUrl:()Ljava/lang/String;
       6: areturn

  public static java.lang.String unstableVersion();
    Code:
       0: getstatic     #16                 // Field ammonite/Constants$.MODULE$:Lammonite/Constants$;
       3: invokevirtual #24                 // Method ammonite/Constants$.unstableVersion:()Ljava/lang/String;
       6: areturn

  public static java.lang.String version();
    Code:
       0: getstatic     #16                 // Field ammonite/Constants$.MODULE$:Lammonite/Constants$;
       3: invokevirtual #27                 // Method ammonite/Constants$.version:()Ljava/lang/String;
       6: areturn
}
