Compiled from "XACMLPolicyStatementTypeImpl.java"
public class org.opensaml.xacml.profile.saml.impl.XACMLPolicyStatementTypeImpl extends org.opensaml.saml.common.AbstractSAMLObject implements org.opensaml.xacml.profile.saml.XACMLPolicyStatementType {
  private org.opensaml.core.xml.util.IndexedXMLObjectChildrenList<org.opensaml.xacml.XACMLObject> choiceGroup;

  private org.opensaml.xacml.profile.saml.ReferencedPoliciesType referencedPolicies;

  protected org.opensaml.xacml.profile.saml.impl.XACMLPolicyStatementTypeImpl(java.lang.String, java.lang.String, java.lang.String);
    Code:
       0: aload_0
       1: aload_1
       2: aload_2
       3: aload_3
       4: invokespecial #1                  // Method org/opensaml/saml/common/AbstractSAMLObject."<init>":(Ljava/lang/String;Ljava/lang/String;Ljava/lang/String;)V
       7: aload_0
       8: new           #2                  // class org/opensaml/core/xml/util/IndexedXMLObjectChildrenList
      11: dup
      12: aload_0
      13: invokespecial #3                  // Method org/opensaml/core/xml/util/IndexedXMLObjectChildrenList."<init>":(Lorg/opensaml/core/xml/XMLObject;)V
      16: putfield      #4                  // Field choiceGroup:Lorg/opensaml/core/xml/util/IndexedXMLObjectChildrenList;
      19: return

  public java.util.List<org.opensaml.core.xml.XMLObject> getOrderedChildren();
    Code:
       0: new           #5                  // class java/util/ArrayList
       3: dup
       4: invokespecial #6                  // Method java/util/ArrayList."<init>":()V
       7: astore_1
       8: aload_1
       9: aload_0
      10: getfield      #4                  // Field choiceGroup:Lorg/opensaml/core/xml/util/IndexedXMLObjectChildrenList;
      13: invokevirtual #7                  // Method java/util/ArrayList.addAll:(Ljava/util/Collection;)Z
      16: pop
      17: aload_0
      18: getfield      #8                  // Field referencedPolicies:Lorg/opensaml/xacml/profile/saml/ReferencedPoliciesType;
      21: ifnull        33
      24: aload_1
      25: aload_0
      26: getfield      #8                  // Field referencedPolicies:Lorg/opensaml/xacml/profile/saml/ReferencedPoliciesType;
      29: invokevirtual #9                  // Method java/util/ArrayList.add:(Ljava/lang/Object;)Z
      32: pop
      33: aload_1
      34: invokestatic  #10                 // Method java/util/Collections.unmodifiableList:(Ljava/util/List;)Ljava/util/List;
      37: areturn

  public java.util.List<org.opensaml.xacml.policy.PolicyType> getPolicies();
    Code:
       0: aload_0
       1: getfield      #4                  // Field choiceGroup:Lorg/opensaml/core/xml/util/IndexedXMLObjectChildrenList;
       4: getstatic     #11                 // Field org/opensaml/xacml/policy/PolicyType.DEFAULT_ELEMENT_NAME:Ljavax/xml/namespace/QName;
       7: invokevirtual #12                 // Method org/opensaml/core/xml/util/IndexedXMLObjectChildrenList.subList:(Ljavax/xml/namespace/QName;)Ljava/util/List;
      10: areturn

  public java.util.List<org.opensaml.xacml.policy.PolicySetType> getPolicySets();
    Code:
       0: aload_0
       1: getfield      #4                  // Field choiceGroup:Lorg/opensaml/core/xml/util/IndexedXMLObjectChildrenList;
       4: getstatic     #13                 // Field org/opensaml/xacml/policy/PolicySetType.DEFAULT_ELEMENT_NAME:Ljavax/xml/namespace/QName;
       7: invokevirtual #12                 // Method org/opensaml/core/xml/util/IndexedXMLObjectChildrenList.subList:(Ljavax/xml/namespace/QName;)Ljava/util/List;
      10: areturn

  public org.opensaml.xacml.profile.saml.ReferencedPoliciesType getReferencedPolicies();
    Code:
       0: aload_0
       1: getfield      #8                  // Field referencedPolicies:Lorg/opensaml/xacml/profile/saml/ReferencedPoliciesType;
       4: areturn

  public void setReferencedPolicies(org.opensaml.xacml.profile.saml.ReferencedPoliciesType);
    Code:
       0: aload_0
       1: aload_0
       2: aload_0
       3: getfield      #8                  // Field referencedPolicies:Lorg/opensaml/xacml/profile/saml/ReferencedPoliciesType;
       6: aload_1
       7: invokevirtual #14                 // Method prepareForAssignment:(Lorg/opensaml/core/xml/XMLObject;Lorg/opensaml/core/xml/XMLObject;)Lorg/opensaml/core/xml/XMLObject;
      10: checkcast     #15                 // class org/opensaml/xacml/profile/saml/ReferencedPoliciesType
      13: putfield      #8                  // Field referencedPolicies:Lorg/opensaml/xacml/profile/saml/ReferencedPoliciesType;
      16: return
}
