Compiled from "Guild.kt"
public interface love.forte.simbot.kaiheila.objects.Guild extends love.forte.simbot.kaiheila.objects.KhlObjects,love.forte.simbot.definition.GuildInfo {
  public static final love.forte.simbot.kaiheila.objects.Guild$Companion Companion;

  public abstract love.forte.simbot.ID getId();

  public abstract java.lang.String getName();

  public abstract java.lang.String getIcon();

  public abstract java.lang.String getTopic();

  public abstract love.forte.simbot.ID getMasterId();

  public abstract int getNotifyType();

  public abstract java.lang.String getRegion();

  public abstract boolean getEnableOpen();

  public abstract love.forte.simbot.ID getOpenId();

  public abstract love.forte.simbot.ID getDefaultChannelId();

  public abstract love.forte.simbot.ID getWelcomeChannelId();

  public abstract java.util.List<love.forte.simbot.kaiheila.objects.Role> getRoles();

  public abstract java.util.List<love.forte.simbot.kaiheila.objects.Channel> getChannels();

  public default love.forte.simbot.ID getOwnerId();
    Code:
       0: aload_0
       1: invokeinterface #32,  1           // InterfaceMethod getMasterId:()Llove/forte/simbot/ID;
       6: areturn

  public default java.lang.String getDescription();
    Code:
       0: aload_0
       1: invokeinterface #37,  1           // InterfaceMethod getTopic:()Ljava/lang/String;
       6: areturn

  public default int getCurrentChannel();
    Code:
       0: aload_0
       1: invokeinterface #40,  1           // InterfaceMethod getChannels:()Ljava/util/List;
       6: invokeinterface #45,  1           // InterfaceMethod java/util/List.size:()I
      11: ireturn

  static {};
    Code:
       0: getstatic     #53                 // Field love/forte/simbot/kaiheila/objects/Guild$Companion.$$INSTANCE:Llove/forte/simbot/kaiheila/objects/Guild$Companion;
       3: putstatic     #56                 // Field Companion:Llove/forte/simbot/kaiheila/objects/Guild$Companion;
       6: return
}
