Compiled from "FacesCompatibleAuthenticationRedirectStrategy.java"
public final class org.jasig.cas.client.authentication.FacesCompatibleAuthenticationRedirectStrategy implements org.jasig.cas.client.authentication.AuthenticationRedirectStrategy {
  private static final java.lang.String FACES_PARTIAL_AJAX_PARAMETER;

  public org.jasig.cas.client.authentication.FacesCompatibleAuthenticationRedirectStrategy();
    Code:
       0: aload_0
       1: invokespecial #1                  // Method java/lang/Object."<init>":()V
       4: return

  public void redirect(javax.servlet.http.HttpServletRequest, javax.servlet.http.HttpServletResponse, java.lang.String) throws java.io.IOException;
    Code:
       0: aload_1
       1: ldc           #3                  // String javax.faces.partial.ajax
       3: invokeinterface #4,  2            // InterfaceMethod javax/servlet/http/HttpServletRequest.getParameter:(Ljava/lang/String;)Ljava/lang/String;
       8: invokestatic  #5                  // Method org/jasig/cas/client/util/CommonUtils.isNotBlank:(Ljava/lang/String;)Z
      11: ifeq          67
      14: aload_2
      15: ldc           #6                  // String text/xml
      17: invokeinterface #7,  2            // InterfaceMethod javax/servlet/http/HttpServletResponse.setContentType:(Ljava/lang/String;)V
      22: aload_2
      23: sipush        200
      26: invokeinterface #8,  2            // InterfaceMethod javax/servlet/http/HttpServletResponse.setStatus:(I)V
      31: aload_2
      32: invokeinterface #9,  1            // InterfaceMethod javax/servlet/http/HttpServletResponse.getWriter:()Ljava/io/PrintWriter;
      37: astore        4
      39: aload         4
      41: ldc           #10                 // String <?xml version=\'1.0\' encoding=\'UTF-8\'?>
      43: invokevirtual #11                 // Method java/io/PrintWriter.write:(Ljava/lang/String;)V
      46: aload         4
      48: ldc           #12                 // String <partial-response><redirect url=\"%s\"></redirect></partial-response>
      50: iconst_1
      51: anewarray     #13                 // class java/lang/Object
      54: dup
      55: iconst_0
      56: aload_3
      57: aastore
      58: invokestatic  #14                 // Method java/lang/String.format:(Ljava/lang/String;[Ljava/lang/Object;)Ljava/lang/String;
      61: invokevirtual #11                 // Method java/io/PrintWriter.write:(Ljava/lang/String;)V
      64: goto          74
      67: aload_2
      68: aload_3
      69: invokeinterface #15,  2           // InterfaceMethod javax/servlet/http/HttpServletResponse.sendRedirect:(Ljava/lang/String;)V
      74: return
}
