Compiled from "PathParser.scala"
public final class org.sisioh.trinity.domain.routing.RailsPathPatternParser$$anonfun$target$1 extends scala.runtime.AbstractFunction1<org.sisioh.trinity.domain.routing.RegexPathPatternParser$PartialPathPattern, org.sisioh.trinity.domain.routing.PathPattern> implements scala.Serializable {
  public static final long serialVersionUID;

  private final org.sisioh.trinity.domain.routing.RailsPathPatternParser $outer;

  public final org.sisioh.trinity.domain.routing.PathPattern apply(org.sisioh.trinity.domain.routing.RegexPathPatternParser$PartialPathPattern);
    Code:
       0: new           #23                 // class org/sisioh/trinity/domain/routing/RegexPathPatternParser$PartialPathPattern
       3: dup
       4: aload_0
       5: getfield      #25                 // Field $outer:Lorg/sisioh/trinity/domain/routing/RailsPathPatternParser;
       8: new           #27                 // class scala/collection/mutable/StringBuilder
      11: dup
      12: invokespecial #31                 // Method scala/collection/mutable/StringBuilder."<init>":()V
      15: ldc           #33                 // String \\A
      17: invokevirtual #37                 // Method scala/collection/mutable/StringBuilder.append:(Ljava/lang/Object;)Lscala/collection/mutable/StringBuilder;
      20: aload_1
      21: invokevirtual #41                 // Method org/sisioh/trinity/domain/routing/RegexPathPatternParser$PartialPathPattern.regex:()Ljava/lang/String;
      24: invokevirtual #37                 // Method scala/collection/mutable/StringBuilder.append:(Ljava/lang/Object;)Lscala/collection/mutable/StringBuilder;
      27: ldc           #43                 // String \\Z
      29: invokevirtual #37                 // Method scala/collection/mutable/StringBuilder.append:(Ljava/lang/Object;)Lscala/collection/mutable/StringBuilder;
      32: invokevirtual #46                 // Method scala/collection/mutable/StringBuilder.toString:()Ljava/lang/String;
      35: aload_1
      36: invokevirtual #50                 // Method org/sisioh/trinity/domain/routing/RegexPathPatternParser$PartialPathPattern.captureGroupNames:()Lscala/collection/immutable/List;
      39: invokespecial #53                 // Method org/sisioh/trinity/domain/routing/RegexPathPatternParser$PartialPathPattern."<init>":(Lorg/sisioh/trinity/domain/routing/RegexPathPatternParser;Ljava/lang/String;Lscala/collection/immutable/List;)V
      42: invokevirtual #57                 // Method org/sisioh/trinity/domain/routing/RegexPathPatternParser$PartialPathPattern.toPathPattern:()Lorg/sisioh/trinity/domain/routing/PathPattern;
      45: areturn

  public final java.lang.Object apply(java.lang.Object);
    Code:
       0: aload_0
       1: aload_1
       2: checkcast     #23                 // class org/sisioh/trinity/domain/routing/RegexPathPatternParser$PartialPathPattern
       5: invokevirtual #64                 // Method apply:(Lorg/sisioh/trinity/domain/routing/RegexPathPatternParser$PartialPathPattern;)Lorg/sisioh/trinity/domain/routing/PathPattern;
       8: areturn

  public org.sisioh.trinity.domain.routing.RailsPathPatternParser$$anonfun$target$1(org.sisioh.trinity.domain.routing.RailsPathPatternParser);
    Code:
       0: aload_1
       1: ifnonnull     12
       4: new           #69                 // class java/lang/NullPointerException
       7: dup
       8: invokespecial #70                 // Method java/lang/NullPointerException."<init>":()V
      11: athrow
      12: aload_0
      13: aload_1
      14: putfield      #25                 // Field $outer:Lorg/sisioh/trinity/domain/routing/RailsPathPatternParser;
      17: aload_0
      18: invokespecial #71                 // Method scala/runtime/AbstractFunction1."<init>":()V
      21: return
}
