Compiled from "UnsupportedEntityFacade.java"
public class org.graylog2.contentpacks.facades.UnsupportedEntityFacade implements org.graylog2.contentpacks.facades.EntityFacade<java.lang.Void> {
  private static final org.slf4j.Logger LOG;

  public static final org.graylog2.contentpacks.facades.UnsupportedEntityFacade INSTANCE;

  public org.graylog2.contentpacks.facades.UnsupportedEntityFacade();
    Code:
       0: aload_0
       1: invokespecial #1                  // Method java/lang/Object."<init>":()V
       4: return

  public org.graylog2.contentpacks.model.entities.NativeEntity<java.lang.Void> createNativeEntity(org.graylog2.contentpacks.model.entities.Entity, java.util.Map<java.lang.String, org.graylog2.contentpacks.model.entities.references.ValueReference>, java.util.Map<org.graylog2.contentpacks.model.entities.EntityDescriptor, java.lang.Object>, java.lang.String);
    Code:
       0: new           #2                  // class java/lang/UnsupportedOperationException
       3: dup
       4: new           #3                  // class java/lang/StringBuilder
       7: dup
       8: invokespecial #4                  // Method java/lang/StringBuilder."<init>":()V
      11: ldc           #5                  // String Unsupported entity
      13: invokevirtual #6                  // Method java/lang/StringBuilder.append:(Ljava/lang/String;)Ljava/lang/StringBuilder;
      16: aload_1
      17: invokeinterface #7,  1            // InterfaceMethod org/graylog2/contentpacks/model/entities/Entity.toEntityDescriptor:()Lorg/graylog2/contentpacks/model/entities/EntityDescriptor;
      22: invokevirtual #8                  // Method java/lang/StringBuilder.append:(Ljava/lang/Object;)Ljava/lang/StringBuilder;
      25: invokevirtual #9                  // Method java/lang/StringBuilder.toString:()Ljava/lang/String;
      28: invokespecial #10                 // Method java/lang/UnsupportedOperationException."<init>":(Ljava/lang/String;)V
      31: athrow

  public java.util.Optional<org.graylog2.contentpacks.model.entities.NativeEntity<java.lang.Void>> loadNativeEntity(org.graylog2.contentpacks.model.entities.NativeEntityDescriptor);
    Code:
       0: invokestatic  #11                 // Method java/util/Optional.empty:()Ljava/util/Optional;
       3: areturn

  public void delete(java.lang.Void);
    Code:
       0: new           #2                  // class java/lang/UnsupportedOperationException
       3: dup
       4: ldc           #12                 // String Unsupported entity
       6: invokespecial #10                 // Method java/lang/UnsupportedOperationException."<init>":(Ljava/lang/String;)V
       9: athrow

  public org.graylog2.contentpacks.model.entities.EntityExcerpt createExcerpt(java.lang.Void);
    Code:
       0: new           #2                  // class java/lang/UnsupportedOperationException
       3: dup
       4: ldc           #12                 // String Unsupported entity
       6: invokespecial #10                 // Method java/lang/UnsupportedOperationException."<init>":(Ljava/lang/String;)V
       9: athrow

  public java.util.Set<org.graylog2.contentpacks.model.entities.EntityExcerpt> listEntityExcerpts();
    Code:
       0: invokestatic  #13                 // Method java/util/Collections.emptySet:()Ljava/util/Set;
       3: areturn

  public java.util.Optional<org.graylog2.contentpacks.model.entities.Entity> exportEntity(org.graylog2.contentpacks.model.entities.EntityDescriptor, org.graylog2.contentpacks.EntityDescriptorIds);
    Code:
       0: getstatic     #14                 // Field LOG:Lorg/slf4j/Logger;
       3: ldc           #15                 // String Couldn\'t collect entity {}
       5: aload_1
       6: invokeinterface #16,  3           // InterfaceMethod org/slf4j/Logger.warn:(Ljava/lang/String;Ljava/lang/Object;)V
      11: invokestatic  #11                 // Method java/util/Optional.empty:()Ljava/util/Optional;
      14: areturn

  public com.google.common.graph.Graph<org.graylog2.contentpacks.model.entities.EntityDescriptor> resolveNativeEntity(org.graylog2.contentpacks.model.entities.EntityDescriptor);
    Code:
       0: getstatic     #14                 // Field LOG:Lorg/slf4j/Logger;
       3: ldc           #17                 // String Couldn\'t resolve entity {}
       5: aload_1
       6: invokeinterface #16,  3           // InterfaceMethod org/slf4j/Logger.warn:(Ljava/lang/String;Ljava/lang/Object;)V
      11: invokestatic  #18                 // Method org/graylog2/utilities/Graphs.emptyDirectedGraph:()Lcom/google/common/graph/ImmutableGraph;
      14: areturn

  public com.google.common.graph.Graph<org.graylog2.contentpacks.model.entities.Entity> resolveForInstallation(org.graylog2.contentpacks.model.entities.Entity, java.util.Map<java.lang.String, org.graylog2.contentpacks.model.entities.references.ValueReference>, java.util.Map<org.graylog2.contentpacks.model.entities.EntityDescriptor, org.graylog2.contentpacks.model.entities.Entity>);
    Code:
       0: getstatic     #14                 // Field LOG:Lorg/slf4j/Logger;
       3: ldc           #17                 // String Couldn\'t resolve entity {}
       5: aload_1
       6: invokeinterface #7,  1            // InterfaceMethod org/graylog2/contentpacks/model/entities/Entity.toEntityDescriptor:()Lorg/graylog2/contentpacks/model/entities/EntityDescriptor;
      11: invokeinterface #16,  3           // InterfaceMethod org/slf4j/Logger.warn:(Ljava/lang/String;Ljava/lang/Object;)V
      16: invokestatic  #18                 // Method org/graylog2/utilities/Graphs.emptyDirectedGraph:()Lcom/google/common/graph/ImmutableGraph;
      19: areturn

  public org.graylog2.contentpacks.model.entities.EntityExcerpt createExcerpt(java.lang.Object);
    Code:
       0: aload_0
       1: aload_1
       2: checkcast     #19                 // class java/lang/Void
       5: invokevirtual #20                 // Method createExcerpt:(Ljava/lang/Void;)Lorg/graylog2/contentpacks/model/entities/EntityExcerpt;
       8: areturn

  public void delete(java.lang.Object);
    Code:
       0: aload_0
       1: aload_1
       2: checkcast     #19                 // class java/lang/Void
       5: invokevirtual #21                 // Method delete:(Ljava/lang/Void;)V
       8: return

  static {};
    Code:
       0: ldc           #22                 // class org/graylog2/contentpacks/facades/UnsupportedEntityFacade
       2: invokestatic  #23                 // Method org/slf4j/LoggerFactory.getLogger:(Ljava/lang/Class;)Lorg/slf4j/Logger;
       5: putstatic     #14                 // Field LOG:Lorg/slf4j/Logger;
       8: new           #22                 // class org/graylog2/contentpacks/facades/UnsupportedEntityFacade
      11: dup
      12: invokespecial #24                 // Method "<init>":()V
      15: putstatic     #25                 // Field INSTANCE:Lorg/graylog2/contentpacks/facades/UnsupportedEntityFacade;
      18: return
}
