Compiled from "EmailMessage.java"
public class org.sonar.plugins.emailnotifications.api.EmailMessage {
  private java.lang.String from;

  private java.lang.String to;

  private java.lang.String subject;

  private java.lang.String message;

  private java.lang.String messageId;

  public org.sonar.plugins.emailnotifications.api.EmailMessage();
    Code:
       0: aload_0
       1: invokespecial #15                 // Method java/lang/Object."<init>":()V
       4: return

  public org.sonar.plugins.emailnotifications.api.EmailMessage setFrom(java.lang.String);
    Code:
       0: aload_0
       1: aload_1
       2: putfield      #21                 // Field from:Ljava/lang/String;
       5: aload_0
       6: areturn

  public java.lang.String getFrom();
    Code:
       0: aload_0
       1: getfield      #21                 // Field from:Ljava/lang/String;
       4: areturn

  public org.sonar.plugins.emailnotifications.api.EmailMessage setTo(java.lang.String);
    Code:
       0: aload_0
       1: aload_1
       2: putfield      #26                 // Field to:Ljava/lang/String;
       5: aload_0
       6: areturn

  public java.lang.String getTo();
    Code:
       0: aload_0
       1: getfield      #26                 // Field to:Ljava/lang/String;
       4: areturn

  public org.sonar.plugins.emailnotifications.api.EmailMessage setSubject(java.lang.String);
    Code:
       0: aload_0
       1: aload_1
       2: putfield      #30                 // Field subject:Ljava/lang/String;
       5: aload_0
       6: areturn

  public java.lang.String getSubject();
    Code:
       0: aload_0
       1: getfield      #30                 // Field subject:Ljava/lang/String;
       4: areturn

  public org.sonar.plugins.emailnotifications.api.EmailMessage setMessage(java.lang.String);
    Code:
       0: aload_0
       1: aload_1
       2: putfield      #34                 // Field message:Ljava/lang/String;
       5: aload_0
       6: areturn

  public java.lang.String getMessage();
    Code:
       0: aload_0
       1: getfield      #34                 // Field message:Ljava/lang/String;
       4: areturn

  public org.sonar.plugins.emailnotifications.api.EmailMessage setMessageId(java.lang.String);
    Code:
       0: aload_0
       1: aload_1
       2: putfield      #38                 // Field messageId:Ljava/lang/String;
       5: aload_0
       6: areturn

  public java.lang.String getMessageId();
    Code:
       0: aload_0
       1: getfield      #38                 // Field messageId:Ljava/lang/String;
       4: areturn

  public java.lang.String toString();
    Code:
       0: aload_0
       1: invokestatic  #46                 // Method org/sonar/api/internal/apachecommons/lang/builder/ToStringBuilder.reflectionToString:(Ljava/lang/Object;)Ljava/lang/String;
       4: areturn
}
