Compiled from "Types.java"
final class org.sonar.api.internal.google.common.reflect.Types$JavaVersion$3 extends org.sonar.api.internal.google.common.reflect.Types$JavaVersion {
  org.sonar.api.internal.google.common.reflect.Types$JavaVersion$3(java.lang.String, int);
    Code:
       0: aload_0
       1: aload_1
       2: iload_2
       3: aconst_null
       4: invokespecial #15                 // Method org/sonar/api/internal/google/common/reflect/Types$JavaVersion."<init>":(Ljava/lang/String;ILorg/sonar/api/internal/google/common/reflect/Types$1;)V
       7: return

  java.lang.reflect.Type newArrayType(java.lang.reflect.Type);
    Code:
       0: getstatic     #23                 // Field JAVA7:Lorg/sonar/api/internal/google/common/reflect/Types$JavaVersion;
       3: aload_1
       4: invokevirtual #25                 // Method org/sonar/api/internal/google/common/reflect/Types$JavaVersion.newArrayType:(Ljava/lang/reflect/Type;)Ljava/lang/reflect/Type;
       7: areturn

  java.lang.reflect.Type usedInGenericType(java.lang.reflect.Type);
    Code:
       0: getstatic     #23                 // Field JAVA7:Lorg/sonar/api/internal/google/common/reflect/Types$JavaVersion;
       3: aload_1
       4: invokevirtual #30                 // Method org/sonar/api/internal/google/common/reflect/Types$JavaVersion.usedInGenericType:(Ljava/lang/reflect/Type;)Ljava/lang/reflect/Type;
       7: areturn

  java.lang.String typeName(java.lang.reflect.Type);
    Code:
       0: ldc           #41                 // class java/lang/reflect/Type
       2: ldc           #43                 // String getTypeName
       4: iconst_0
       5: anewarray     #45                 // class java/lang/Class
       8: invokevirtual #49                 // Method java/lang/Class.getMethod:(Ljava/lang/String;[Ljava/lang/Class;)Ljava/lang/reflect/Method;
      11: astore_2
      12: aload_2
      13: aload_1
      14: iconst_0
      15: anewarray     #51                 // class java/lang/Object
      18: invokevirtual #57                 // Method java/lang/reflect/Method.invoke:(Ljava/lang/Object;[Ljava/lang/Object;)Ljava/lang/Object;
      21: checkcast     #59                 // class java/lang/String
      24: areturn
      25: astore_2
      26: new           #61                 // class java/lang/AssertionError
      29: dup
      30: ldc           #63                 // String Type.getTypeName should be available in Java 8
      32: invokespecial #66                 // Method java/lang/AssertionError."<init>":(Ljava/lang/Object;)V
      35: athrow
      36: astore_2
      37: new           #68                 // class java/lang/RuntimeException
      40: dup
      41: aload_2
      42: invokespecial #71                 // Method java/lang/RuntimeException."<init>":(Ljava/lang/Throwable;)V
      45: athrow
      46: astore_2
      47: new           #68                 // class java/lang/RuntimeException
      50: dup
      51: aload_2
      52: invokespecial #71                 // Method java/lang/RuntimeException."<init>":(Ljava/lang/Throwable;)V
      55: athrow
    Exception table:
       from    to  target type
           0    24    25   Class java/lang/NoSuchMethodException
           0    24    36   Class java/lang/reflect/InvocationTargetException
           0    24    46   Class java/lang/IllegalAccessException
}
