Compiled from "DerbyConcatFunction.java"
public class org.hibernate.dialect.function.DerbyConcatFunction implements org.hibernate.dialect.function.SQLFunction {
  private static final org.hibernate.dialect.function.DerbyConcatFunction$StringTransformer CAST_STRING_TRANSFORMER;

  private static final org.hibernate.dialect.function.DerbyConcatFunction$StringTransformer NO_TRANSFORM_STRING_TRANSFORMER;

  public org.hibernate.dialect.function.DerbyConcatFunction();
    Code:
       0: aload_0
       1: invokespecial #1                  // Method java/lang/Object."<init>":()V
       4: return

  public boolean hasArguments();
    Code:
       0: iconst_1
       1: ireturn

  public boolean hasParenthesesIfNoArguments();
    Code:
       0: iconst_1
       1: ireturn

  public org.hibernate.type.Type getReturnType(org.hibernate.type.Type, org.hibernate.engine.spi.Mapping) throws org.hibernate.QueryException;
    Code:
       0: getstatic     #2                  // Field org/hibernate/type/StandardBasicTypes.STRING:Lorg/hibernate/type/StringType;
       3: areturn

  public java.lang.String render(org.hibernate.type.Type, java.util.List, org.hibernate.engine.spi.SessionFactoryImplementor) throws org.hibernate.QueryException;
    Code:
       0: iconst_1
       1: istore        4
       3: aload_2
       4: invokeinterface #3,  1            // InterfaceMethod java/util/List.iterator:()Ljava/util/Iterator;
       9: astore        5
      11: aload         5
      13: invokeinterface #4,  1            // InterfaceMethod java/util/Iterator.hasNext:()Z
      18: ifeq          56
      21: aload         5
      23: invokeinterface #5,  1            // InterfaceMethod java/util/Iterator.next:()Ljava/lang/Object;
      28: astore        6
      30: aload         6
      32: checkcast     #6                  // class java/lang/String
      35: astore        7
      37: ldc           #7                  // String ?
      39: aload         7
      41: invokevirtual #8                  // Method java/lang/String.equals:(Ljava/lang/Object;)Z
      44: ifne          53
      47: iconst_0
      48: istore        4
      50: goto          56
      53: goto          11
      56: iload         4
      58: ifeq          82
      61: aload_2
      62: invokeinterface #3,  1            // InterfaceMethod java/util/List.iterator:()Ljava/util/Iterator;
      67: getstatic     #9                  // Field CAST_STRING_TRANSFORMER:Lorg/hibernate/dialect/function/DerbyConcatFunction$StringTransformer;
      70: new           #10                 // class org/hibernate/dialect/function/DerbyConcatFunction$1
      73: dup
      74: aload_0
      75: invokespecial #11                 // Method org/hibernate/dialect/function/DerbyConcatFunction$1."<init>":(Lorg/hibernate/dialect/function/DerbyConcatFunction;)V
      78: invokestatic  #12                 // Method join:(Ljava/util/Iterator;Lorg/hibernate/dialect/function/DerbyConcatFunction$StringTransformer;Lorg/hibernate/dialect/function/DerbyConcatFunction$StringJoinTemplate;)Ljava/lang/String;
      81: areturn
      82: aload_2
      83: invokeinterface #3,  1            // InterfaceMethod java/util/List.iterator:()Ljava/util/Iterator;
      88: getstatic     #13                 // Field NO_TRANSFORM_STRING_TRANSFORMER:Lorg/hibernate/dialect/function/DerbyConcatFunction$StringTransformer;
      91: new           #14                 // class org/hibernate/dialect/function/DerbyConcatFunction$2
      94: dup
      95: aload_0
      96: invokespecial #15                 // Method org/hibernate/dialect/function/DerbyConcatFunction$2."<init>":(Lorg/hibernate/dialect/function/DerbyConcatFunction;)V
      99: invokestatic  #12                 // Method join:(Ljava/util/Iterator;Lorg/hibernate/dialect/function/DerbyConcatFunction$StringTransformer;Lorg/hibernate/dialect/function/DerbyConcatFunction$StringJoinTemplate;)Ljava/lang/String;
     102: areturn

  private static java.lang.String join(java.util.Iterator, org.hibernate.dialect.function.DerbyConcatFunction$StringTransformer, org.hibernate.dialect.function.DerbyConcatFunction$StringJoinTemplate);
    Code:
       0: new           #16                 // class java/lang/StringBuilder
       3: dup
       4: aload_2
       5: invokeinterface #17,  1           // InterfaceMethod org/hibernate/dialect/function/DerbyConcatFunction$StringJoinTemplate.getBeginning:()Ljava/lang/String;
      10: invokespecial #18                 // Method java/lang/StringBuilder."<init>":(Ljava/lang/String;)V
      13: astore_3
      14: aload_0
      15: invokeinterface #4,  1            // InterfaceMethod java/util/Iterator.hasNext:()Z
      20: ifeq          70
      23: aload_0
      24: invokeinterface #5,  1            // InterfaceMethod java/util/Iterator.next:()Ljava/lang/Object;
      29: checkcast     #6                  // class java/lang/String
      32: astore        4
      34: aload_3
      35: aload_1
      36: aload         4
      38: invokeinterface #19,  2           // InterfaceMethod org/hibernate/dialect/function/DerbyConcatFunction$StringTransformer.transform:(Ljava/lang/String;)Ljava/lang/String;
      43: invokevirtual #20                 // Method java/lang/StringBuilder.append:(Ljava/lang/String;)Ljava/lang/StringBuilder;
      46: pop
      47: aload_0
      48: invokeinterface #4,  1            // InterfaceMethod java/util/Iterator.hasNext:()Z
      53: ifeq          67
      56: aload_3
      57: aload_2
      58: invokeinterface #21,  1           // InterfaceMethod org/hibernate/dialect/function/DerbyConcatFunction$StringJoinTemplate.getSeparator:()Ljava/lang/String;
      63: invokevirtual #20                 // Method java/lang/StringBuilder.append:(Ljava/lang/String;)Ljava/lang/StringBuilder;
      66: pop
      67: goto          14
      70: aload_3
      71: aload_2
      72: invokeinterface #22,  1           // InterfaceMethod org/hibernate/dialect/function/DerbyConcatFunction$StringJoinTemplate.getEnding:()Ljava/lang/String;
      77: invokevirtual #20                 // Method java/lang/StringBuilder.append:(Ljava/lang/String;)Ljava/lang/StringBuilder;
      80: invokevirtual #23                 // Method java/lang/StringBuilder.toString:()Ljava/lang/String;
      83: areturn

  static {};
    Code:
       0: new           #24                 // class org/hibernate/dialect/function/DerbyConcatFunction$3
       3: dup
       4: invokespecial #25                 // Method org/hibernate/dialect/function/DerbyConcatFunction$3."<init>":()V
       7: putstatic     #9                  // Field CAST_STRING_TRANSFORMER:Lorg/hibernate/dialect/function/DerbyConcatFunction$StringTransformer;
      10: new           #26                 // class org/hibernate/dialect/function/DerbyConcatFunction$4
      13: dup
      14: invokespecial #27                 // Method org/hibernate/dialect/function/DerbyConcatFunction$4."<init>":()V
      17: putstatic     #13                 // Field NO_TRANSFORM_STRING_TRANSFORMER:Lorg/hibernate/dialect/function/DerbyConcatFunction$StringTransformer;
      20: return
}
