Compiled from "ArtifactoryConnectorStatusIndicator.kt"
public class net.nemerosa.ontrack.extension.artifactory.ArtifactoryConnectorStatusIndicator extends net.nemerosa.ontrack.extension.support.ConfigurationConnectorStatusIndicator<net.nemerosa.ontrack.extension.artifactory.configuration.ArtifactoryConfiguration> {
  private final java.lang.String type;

  private final net.nemerosa.ontrack.extension.artifactory.client.ArtifactoryClientFactory clientFactory;

  public java.lang.String getType();
    Code:
       0: aload_0
       1: getfield      #15                 // Field type:Ljava/lang/String;
       4: areturn

  protected void connect(net.nemerosa.ontrack.extension.artifactory.configuration.ArtifactoryConfiguration);
    Code:
       0: aload_1
       1: ldc           #26                 // String config
       3: invokestatic  #32                 // Method kotlin/jvm/internal/Intrinsics.checkParameterIsNotNull:(Ljava/lang/Object;Ljava/lang/String;)V
       6: aload_0
       7: getfield      #36                 // Field clientFactory:Lnet/nemerosa/ontrack/extension/artifactory/client/ArtifactoryClientFactory;
      10: aload_1
      11: invokeinterface #42,  2           // InterfaceMethod net/nemerosa/ontrack/extension/artifactory/client/ArtifactoryClientFactory.getClient:(Lnet/nemerosa/ontrack/extension/artifactory/configuration/ArtifactoryConfiguration;)Lnet/nemerosa/ontrack/extension/artifactory/client/ArtifactoryClient;
      16: dup
      17: ldc           #44                 // String clientFactory.getClient(config)
      19: invokestatic  #47                 // Method kotlin/jvm/internal/Intrinsics.checkExpressionValueIsNotNull:(Ljava/lang/Object;Ljava/lang/String;)V
      22: invokeinterface #53,  1           // InterfaceMethod net/nemerosa/ontrack/extension/artifactory/client/ArtifactoryClient.getBuildNames:()Ljava/util/List;
      27: pop
      28: return

  public void connect(net.nemerosa.ontrack.model.support.UserPasswordConfiguration);
    Code:
       0: aload_0
       1: aload_1
       2: checkcast     #22                 // class net/nemerosa/ontrack/extension/artifactory/configuration/ArtifactoryConfiguration
       5: invokevirtual #24                 // Method connect:(Lnet/nemerosa/ontrack/extension/artifactory/configuration/ArtifactoryConfiguration;)V
       8: return

  protected net.nemerosa.ontrack.model.support.ConnectorDescription connectorDescription(net.nemerosa.ontrack.extension.artifactory.configuration.ArtifactoryConfiguration);
    Code:
       0: aload_1
       1: ldc           #26                 // String config
       3: invokestatic  #32                 // Method kotlin/jvm/internal/Intrinsics.checkParameterIsNotNull:(Ljava/lang/Object;Ljava/lang/String;)V
       6: new           #61                 // class net/nemerosa/ontrack/model/support/ConnectorDescription
       9: dup
      10: new           #63                 // class net/nemerosa/ontrack/model/support/Connector
      13: dup
      14: aload_0
      15: invokevirtual #65                 // Method getType:()Ljava/lang/String;
      18: aload_1
      19: invokevirtual #68                 // Method net/nemerosa/ontrack/extension/artifactory/configuration/ArtifactoryConfiguration.getName:()Ljava/lang/String;
      22: invokespecial #72                 // Method net/nemerosa/ontrack/model/support/Connector."<init>":(Ljava/lang/String;Ljava/lang/String;)V
      25: aload_1
      26: invokevirtual #75                 // Method net/nemerosa/ontrack/extension/artifactory/configuration/ArtifactoryConfiguration.getUrl:()Ljava/lang/String;
      29: invokespecial #78                 // Method net/nemerosa/ontrack/model/support/ConnectorDescription."<init>":(Lnet/nemerosa/ontrack/model/support/Connector;Ljava/lang/String;)V
      32: areturn

  public net.nemerosa.ontrack.model.support.ConnectorDescription connectorDescription(net.nemerosa.ontrack.model.support.UserPasswordConfiguration);
    Code:
       0: aload_0
       1: aload_1
       2: checkcast     #22                 // class net/nemerosa/ontrack/extension/artifactory/configuration/ArtifactoryConfiguration
       5: invokevirtual #59                 // Method connectorDescription:(Lnet/nemerosa/ontrack/extension/artifactory/configuration/ArtifactoryConfiguration;)Lnet/nemerosa/ontrack/model/support/ConnectorDescription;
       8: areturn

  public net.nemerosa.ontrack.extension.artifactory.ArtifactoryConnectorStatusIndicator(net.nemerosa.ontrack.model.support.ConfigurationService<net.nemerosa.ontrack.extension.artifactory.configuration.ArtifactoryConfiguration>, net.nemerosa.ontrack.model.security.SecurityService, net.nemerosa.ontrack.extension.artifactory.client.ArtifactoryClientFactory);
    Code:
       0: aload_1
       1: ldc           #82                 // String configurationService
       3: invokestatic  #32                 // Method kotlin/jvm/internal/Intrinsics.checkParameterIsNotNull:(Ljava/lang/Object;Ljava/lang/String;)V
       6: aload_2
       7: ldc           #84                 // String securityService
       9: invokestatic  #32                 // Method kotlin/jvm/internal/Intrinsics.checkParameterIsNotNull:(Ljava/lang/Object;Ljava/lang/String;)V
      12: aload_3
      13: ldc           #85                 // String clientFactory
      15: invokestatic  #32                 // Method kotlin/jvm/internal/Intrinsics.checkParameterIsNotNull:(Ljava/lang/Object;Ljava/lang/String;)V
      18: aload_0
      19: aload_1
      20: aload_2
      21: invokespecial #88                 // Method net/nemerosa/ontrack/extension/support/ConfigurationConnectorStatusIndicator."<init>":(Lnet/nemerosa/ontrack/model/support/ConfigurationService;Lnet/nemerosa/ontrack/model/security/SecurityService;)V
      24: aload_0
      25: aload_3
      26: putfield      #36                 // Field clientFactory:Lnet/nemerosa/ontrack/extension/artifactory/client/ArtifactoryClientFactory;
      29: aload_0
      30: ldc           #10                 // String artifactory
      32: putfield      #15                 // Field type:Ljava/lang/String;
      35: return
}
