Compiled from "ClientConfigFactory.java"
public class com.cloudera.nav.sdk.client.ClientConfigFactory {
  public static final java.lang.String APP_URL;

  public static final java.lang.String FILE_FORMAT;

  public static final java.lang.String METADATA_URI;

  public static final java.lang.String NAMESPACE;

  public static final java.lang.String NAV_URL;

  public static final java.lang.String USERNAME;

  public static final java.lang.String PASSWORD;

  public static final java.lang.String AUTOCOMMIT;

  public static final java.lang.String DISABLE_SSL_VALIDATION;

  public static final java.lang.String SSL_KEYSTORE_LOCATION;

  public static final java.lang.String SSL_KEYSTORE_PASSWORD;

  public com.cloudera.nav.sdk.client.ClientConfigFactory();
    Code:
       0: aload_0
       1: invokespecial #1                  // Method java/lang/Object."<init>":()V
       4: return

  public com.cloudera.nav.sdk.client.ClientConfig readConfigurations(java.lang.String);
    Code:
       0: new           #2                  // class org/apache/commons/configuration/PropertiesConfiguration
       3: dup
       4: aload_1
       5: invokespecial #3                  // Method org/apache/commons/configuration/PropertiesConfiguration."<init>":(Ljava/lang/String;)V
       8: astore_2
       9: new           #4                  // class com/cloudera/nav/sdk/client/ClientConfig
      12: dup
      13: invokespecial #5                  // Method com/cloudera/nav/sdk/client/ClientConfig."<init>":()V
      16: astore_3
      17: aload_3
      18: aload_2
      19: ldc           #6                  // String application_url
      21: invokevirtual #7                  // Method org/apache/commons/configuration/PropertiesConfiguration.getString:(Ljava/lang/String;)Ljava/lang/String;
      24: invokevirtual #8                  // Method com/cloudera/nav/sdk/client/ClientConfig.setApplicationUrl:(Ljava/lang/String;)V
      27: aload_3
      28: aload_2
      29: ldc           #9                  // String file_format
      31: getstatic     #10                 // Field com/cloudera/nav/sdk/client/Format.JSON:Lcom/cloudera/nav/sdk/client/Format;
      34: invokevirtual #11                 // Method com/cloudera/nav/sdk/client/Format.name:()Ljava/lang/String;
      37: invokevirtual #12                 // Method org/apache/commons/configuration/PropertiesConfiguration.getString:(Ljava/lang/String;Ljava/lang/String;)Ljava/lang/String;
      40: invokestatic  #13                 // Method com/cloudera/nav/sdk/client/Format.valueOf:(Ljava/lang/String;)Lcom/cloudera/nav/sdk/client/Format;
      43: invokevirtual #14                 // Method com/cloudera/nav/sdk/client/ClientConfig.setFormat:(Lcom/cloudera/nav/sdk/client/Format;)V
      46: aload_3
      47: aload_2
      48: ldc           #15                 // String metadata_parent_uri
      50: invokevirtual #7                  // Method org/apache/commons/configuration/PropertiesConfiguration.getString:(Ljava/lang/String;)Ljava/lang/String;
      53: invokestatic  #16                 // Method java/net/URI.create:(Ljava/lang/String;)Ljava/net/URI;
      56: invokevirtual #17                 // Method com/cloudera/nav/sdk/client/ClientConfig.setMetadataParentUri:(Ljava/net/URI;)V
      59: aload_3
      60: aload_2
      61: ldc           #18                 // String namespace
      63: invokevirtual #7                  // Method org/apache/commons/configuration/PropertiesConfiguration.getString:(Ljava/lang/String;)Ljava/lang/String;
      66: invokevirtual #19                 // Method com/cloudera/nav/sdk/client/ClientConfig.setNamespace:(Ljava/lang/String;)V
      69: aload_3
      70: aload_2
      71: ldc           #20                 // String navigator_url
      73: invokevirtual #7                  // Method org/apache/commons/configuration/PropertiesConfiguration.getString:(Ljava/lang/String;)Ljava/lang/String;
      76: invokevirtual #21                 // Method com/cloudera/nav/sdk/client/ClientConfig.setNavigatorUrl:(Ljava/lang/String;)V
      79: aload_3
      80: aload_2
      81: ldc           #22                 // String username
      83: invokevirtual #7                  // Method org/apache/commons/configuration/PropertiesConfiguration.getString:(Ljava/lang/String;)Ljava/lang/String;
      86: invokevirtual #23                 // Method com/cloudera/nav/sdk/client/ClientConfig.setUsername:(Ljava/lang/String;)V
      89: aload_3
      90: aload_2
      91: ldc           #24                 // String password
      93: invokevirtual #7                  // Method org/apache/commons/configuration/PropertiesConfiguration.getString:(Ljava/lang/String;)Ljava/lang/String;
      96: invokevirtual #25                 // Method com/cloudera/nav/sdk/client/ClientConfig.setPassword:(Ljava/lang/String;)V
      99: aload_3
     100: aload_2
     101: ldc           #26                 // String autocommit
     103: iconst_0
     104: invokevirtual #27                 // Method org/apache/commons/configuration/PropertiesConfiguration.getBoolean:(Ljava/lang/String;Z)Z
     107: invokevirtual #28                 // Method com/cloudera/nav/sdk/client/ClientConfig.setAutocommit:(Z)V
     110: aload_3
     111: aload_2
     112: ldc           #29                 // String disable_ssl_validation
     114: iconst_0
     115: invokevirtual #27                 // Method org/apache/commons/configuration/PropertiesConfiguration.getBoolean:(Ljava/lang/String;Z)Z
     118: invokevirtual #30                 // Method com/cloudera/nav/sdk/client/ClientConfig.setDisableSSLValidation:(Z)V
     121: aload_3
     122: aload_2
     123: ldc           #31                 // String ssl_truststore_location
     125: aconst_null
     126: invokevirtual #12                 // Method org/apache/commons/configuration/PropertiesConfiguration.getString:(Ljava/lang/String;Ljava/lang/String;)Ljava/lang/String;
     129: invokevirtual #32                 // Method com/cloudera/nav/sdk/client/ClientConfig.setSSLTrustStoreLocation:(Ljava/lang/String;)V
     132: aload_3
     133: aload_2
     134: ldc           #33                 // String ssl_truststore_password
     136: aconst_null
     137: invokevirtual #12                 // Method org/apache/commons/configuration/PropertiesConfiguration.getString:(Ljava/lang/String;Ljava/lang/String;)Ljava/lang/String;
     140: invokevirtual #34                 // Method com/cloudera/nav/sdk/client/ClientConfig.setSSLTrustStorePassword:(Ljava/lang/String;)V
     143: aload_3
     144: areturn
     145: astore_2
     146: aload_2
     147: invokestatic  #36                 // Method com/google/common/base/Throwables.propagate:(Ljava/lang/Throwable;)Ljava/lang/RuntimeException;
     150: athrow
    Exception table:
       from    to  target type
           0   144   145   Class org/apache/commons/configuration/ConfigurationException

  public com.cloudera.nav.sdk.client.ClientConfig fromConfigMap(java.util.Map<java.lang.String, java.lang.Object>);
    Code:
       0: new           #4                  // class com/cloudera/nav/sdk/client/ClientConfig
       3: dup
       4: invokespecial #5                  // Method com/cloudera/nav/sdk/client/ClientConfig."<init>":()V
       7: astore_2
       8: aload_2
       9: aload_1
      10: ldc           #6                  // String application_url
      12: invokeinterface #37,  2           // InterfaceMethod java/util/Map.get:(Ljava/lang/Object;)Ljava/lang/Object;
      17: invokevirtual #38                 // Method java/lang/Object.toString:()Ljava/lang/String;
      20: invokevirtual #8                  // Method com/cloudera/nav/sdk/client/ClientConfig.setApplicationUrl:(Ljava/lang/String;)V
      23: aload_1
      24: ldc           #9                  // String file_format
      26: invokeinterface #39,  2           // InterfaceMethod java/util/Map.containsKey:(Ljava/lang/Object;)Z
      31: ifeq          51
      34: aload_1
      35: ldc           #9                  // String file_format
      37: invokeinterface #37,  2           // InterfaceMethod java/util/Map.get:(Ljava/lang/Object;)Ljava/lang/Object;
      42: invokevirtual #38                 // Method java/lang/Object.toString:()Ljava/lang/String;
      45: invokestatic  #13                 // Method com/cloudera/nav/sdk/client/Format.valueOf:(Ljava/lang/String;)Lcom/cloudera/nav/sdk/client/Format;
      48: goto          54
      51: getstatic     #10                 // Field com/cloudera/nav/sdk/client/Format.JSON:Lcom/cloudera/nav/sdk/client/Format;
      54: astore_3
      55: aload_2
      56: aload_3
      57: invokevirtual #14                 // Method com/cloudera/nav/sdk/client/ClientConfig.setFormat:(Lcom/cloudera/nav/sdk/client/Format;)V
      60: aload_2
      61: aload_1
      62: ldc           #15                 // String metadata_parent_uri
      64: invokeinterface #37,  2           // InterfaceMethod java/util/Map.get:(Ljava/lang/Object;)Ljava/lang/Object;
      69: invokevirtual #38                 // Method java/lang/Object.toString:()Ljava/lang/String;
      72: invokestatic  #16                 // Method java/net/URI.create:(Ljava/lang/String;)Ljava/net/URI;
      75: invokevirtual #17                 // Method com/cloudera/nav/sdk/client/ClientConfig.setMetadataParentUri:(Ljava/net/URI;)V
      78: aload_2
      79: aload_1
      80: ldc           #18                 // String namespace
      82: invokeinterface #37,  2           // InterfaceMethod java/util/Map.get:(Ljava/lang/Object;)Ljava/lang/Object;
      87: invokevirtual #38                 // Method java/lang/Object.toString:()Ljava/lang/String;
      90: invokevirtual #19                 // Method com/cloudera/nav/sdk/client/ClientConfig.setNamespace:(Ljava/lang/String;)V
      93: aload_2
      94: aload_1
      95: ldc           #20                 // String navigator_url
      97: invokeinterface #37,  2           // InterfaceMethod java/util/Map.get:(Ljava/lang/Object;)Ljava/lang/Object;
     102: invokevirtual #38                 // Method java/lang/Object.toString:()Ljava/lang/String;
     105: invokevirtual #21                 // Method com/cloudera/nav/sdk/client/ClientConfig.setNavigatorUrl:(Ljava/lang/String;)V
     108: aload_2
     109: aload_1
     110: ldc           #22                 // String username
     112: invokeinterface #37,  2           // InterfaceMethod java/util/Map.get:(Ljava/lang/Object;)Ljava/lang/Object;
     117: invokevirtual #38                 // Method java/lang/Object.toString:()Ljava/lang/String;
     120: invokevirtual #23                 // Method com/cloudera/nav/sdk/client/ClientConfig.setUsername:(Ljava/lang/String;)V
     123: aload_2
     124: aload_1
     125: ldc           #24                 // String password
     127: invokeinterface #37,  2           // InterfaceMethod java/util/Map.get:(Ljava/lang/Object;)Ljava/lang/Object;
     132: invokevirtual #38                 // Method java/lang/Object.toString:()Ljava/lang/String;
     135: invokevirtual #25                 // Method com/cloudera/nav/sdk/client/ClientConfig.setPassword:(Ljava/lang/String;)V
     138: aload_2
     139: aload_1
     140: ldc           #26                 // String autocommit
     142: invokeinterface #39,  2           // InterfaceMethod java/util/Map.containsKey:(Ljava/lang/Object;)Z
     147: ifeq          170
     150: aload_1
     151: ldc           #26                 // String autocommit
     153: invokeinterface #37,  2           // InterfaceMethod java/util/Map.get:(Ljava/lang/Object;)Ljava/lang/Object;
     158: invokevirtual #38                 // Method java/lang/Object.toString:()Ljava/lang/String;
     161: invokestatic  #40                 // Method java/lang/Boolean.valueOf:(Ljava/lang/String;)Ljava/lang/Boolean;
     164: invokevirtual #41                 // Method java/lang/Boolean.booleanValue:()Z
     167: goto          171
     170: iconst_0
     171: invokevirtual #28                 // Method com/cloudera/nav/sdk/client/ClientConfig.setAutocommit:(Z)V
     174: aload_2
     175: aload_1
     176: ldc           #29                 // String disable_ssl_validation
     178: invokeinterface #39,  2           // InterfaceMethod java/util/Map.containsKey:(Ljava/lang/Object;)Z
     183: ifeq          206
     186: aload_1
     187: ldc           #29                 // String disable_ssl_validation
     189: invokeinterface #37,  2           // InterfaceMethod java/util/Map.get:(Ljava/lang/Object;)Ljava/lang/Object;
     194: invokevirtual #38                 // Method java/lang/Object.toString:()Ljava/lang/String;
     197: invokestatic  #40                 // Method java/lang/Boolean.valueOf:(Ljava/lang/String;)Ljava/lang/Boolean;
     200: invokevirtual #41                 // Method java/lang/Boolean.booleanValue:()Z
     203: goto          207
     206: iconst_0
     207: invokevirtual #30                 // Method com/cloudera/nav/sdk/client/ClientConfig.setDisableSSLValidation:(Z)V
     210: aload_2
     211: aload_1
     212: ldc           #31                 // String ssl_truststore_location
     214: invokeinterface #39,  2           // InterfaceMethod java/util/Map.containsKey:(Ljava/lang/Object;)Z
     219: ifeq          236
     222: aload_1
     223: ldc           #31                 // String ssl_truststore_location
     225: invokeinterface #37,  2           // InterfaceMethod java/util/Map.get:(Ljava/lang/Object;)Ljava/lang/Object;
     230: invokevirtual #38                 // Method java/lang/Object.toString:()Ljava/lang/String;
     233: goto          237
     236: aconst_null
     237: invokevirtual #32                 // Method com/cloudera/nav/sdk/client/ClientConfig.setSSLTrustStoreLocation:(Ljava/lang/String;)V
     240: aload_2
     241: aload_1
     242: ldc           #33                 // String ssl_truststore_password
     244: invokeinterface #39,  2           // InterfaceMethod java/util/Map.containsKey:(Ljava/lang/Object;)Z
     249: ifeq          266
     252: aload_1
     253: ldc           #33                 // String ssl_truststore_password
     255: invokeinterface #37,  2           // InterfaceMethod java/util/Map.get:(Ljava/lang/Object;)Ljava/lang/Object;
     260: invokevirtual #38                 // Method java/lang/Object.toString:()Ljava/lang/String;
     263: goto          267
     266: aconst_null
     267: invokevirtual #34                 // Method com/cloudera/nav/sdk/client/ClientConfig.setSSLTrustStorePassword:(Ljava/lang/String;)V
     270: aload_2
     271: areturn
}
