Compiled from "NavApiCient.java"
public class com.cloudera.nav.sdk.client.NavApiCient {
  private static final org.slf4j.Logger LOG;

  private static final java.lang.String SOURCE_QUERY;

  private final com.cloudera.nav.sdk.client.ClientConfig config;

  private final com.google.common.cache.Cache<java.lang.String, com.cloudera.nav.sdk.model.Source> sourceCacheByUrl;

  private final com.google.common.cache.Cache<com.cloudera.nav.sdk.model.SourceType, java.util.Collection<com.cloudera.nav.sdk.model.Source>> sourceCacheByType;

  private final boolean isSSL;

  private final javax.net.ssl.SSLContext sslContext;

  private final javax.net.ssl.HostnameVerifier hostnameVerifier;

  public com.cloudera.nav.sdk.client.NavApiCient(com.cloudera.nav.sdk.client.ClientConfig);
    Code:
       0: aload_0
       1: invokespecial #1                  // Method java/lang/Object."<init>":()V
       4: aload_0
       5: aload_1
       6: putfield      #2                  // Field config:Lcom/cloudera/nav/sdk/client/ClientConfig;
       9: aload_0
      10: invokestatic  #3                  // Method com/google/common/cache/CacheBuilder.newBuilder:()Lcom/google/common/cache/CacheBuilder;
      13: invokevirtual #4                  // Method com/google/common/cache/CacheBuilder.build:()Lcom/google/common/cache/Cache;
      16: putfield      #5                  // Field sourceCacheByUrl:Lcom/google/common/cache/Cache;
      19: aload_0
      20: invokestatic  #3                  // Method com/google/common/cache/CacheBuilder.newBuilder:()Lcom/google/common/cache/CacheBuilder;
      23: invokevirtual #4                  // Method com/google/common/cache/CacheBuilder.build:()Lcom/google/common/cache/Cache;
      26: putfield      #6                  // Field sourceCacheByType:Lcom/google/common/cache/Cache;
      29: aload_0
      30: aload_1
      31: invokevirtual #7                  // Method com/cloudera/nav/sdk/client/ClientConfig.getNavigatorUrl:()Ljava/lang/String;
      34: invokestatic  #8                  // Method com/cloudera/nav/sdk/client/SSLUtils.isSSL:(Ljava/lang/String;)Z
      37: putfield      #9                  // Field isSSL:Z
      40: aload_0
      41: aload_0
      42: getfield      #9                  // Field isSSL:Z
      45: ifeq          55
      48: aload_1
      49: invokestatic  #10                 // Method com/cloudera/nav/sdk/client/SSLUtils.getSSLContext:(Lcom/cloudera/nav/sdk/client/ClientConfig;)Ljavax/net/ssl/SSLContext;
      52: goto          56
      55: aconst_null
      56: putfield      #11                 // Field sslContext:Ljavax/net/ssl/SSLContext;
      59: aload_0
      60: aload_0
      61: getfield      #9                  // Field isSSL:Z
      64: ifeq          74
      67: aload_1
      68: invokestatic  #12                 // Method com/cloudera/nav/sdk/client/SSLUtils.getHostnameVerifier:(Lcom/cloudera/nav/sdk/client/ClientConfig;)Ljavax/net/ssl/HostnameVerifier;
      71: goto          75
      74: aconst_null
      75: putfield      #13                 // Field hostnameVerifier:Ljavax/net/ssl/HostnameVerifier;
      78: return

  public void registerModels(java.util.Collection<java.lang.Object>);
    Code:
       0: new           #14                 // class java/lang/UnsupportedOperationException
       3: dup
       4: ldc           #15                 // String not yet implemented
       6: invokespecial #16                 // Method java/lang/UnsupportedOperationException."<init>":(Ljava/lang/String;)V
       9: athrow

  public java.util.Collection<com.cloudera.nav.sdk.model.Source> getAllSources();
    Code:
       0: aload_0
       1: invokespecial #17                 // Method newRestTemplate:()Lorg/springframework/web/client/RestTemplate;
       4: astore_1
       5: aload_0
       6: invokespecial #18                 // Method getUrl:()Ljava/lang/String;
       9: astore_2
      10: aload_0
      11: invokespecial #19                 // Method getAuthHeaders:()Lorg/springframework/http/HttpHeaders;
      14: astore_3
      15: new           #20                 // class org/springframework/http/HttpEntity
      18: dup
      19: aload_3
      20: invokespecial #21                 // Method org/springframework/http/HttpEntity."<init>":(Lorg/springframework/util/MultiValueMap;)V
      23: astore        4
      25: aload_1
      26: aload_2
      27: getstatic     #22                 // Field org/springframework/http/HttpMethod.GET:Lorg/springframework/http/HttpMethod;
      30: aload         4
      32: ldc_w         #23                 // class "[Lcom/cloudera/nav/sdk/client/SourceAttrs;"
      35: iconst_0
      36: anewarray     #24                 // class java/lang/Object
      39: invokevirtual #25                 // Method org/springframework/web/client/RestTemplate.exchange:(Ljava/lang/String;Lorg/springframework/http/HttpMethod;Lorg/springframework/http/HttpEntity;Ljava/lang/Class;[Ljava/lang/Object;)Lorg/springframework/http/ResponseEntity;
      42: astore        5
      44: invokestatic  #26                 // Method com/google/common/collect/Lists.newArrayList:()Ljava/util/ArrayList;
      47: astore        6
      49: aload         5
      51: invokevirtual #27                 // Method org/springframework/http/ResponseEntity.getBody:()Ljava/lang/Object;
      54: checkcast     #23                 // class "[Lcom/cloudera/nav/sdk/client/SourceAttrs;"
      57: astore        7
      59: aload         7
      61: arraylength
      62: istore        8
      64: iconst_0
      65: istore        9
      67: iload         9
      69: iload         8
      71: if_icmpge     100
      74: aload         7
      76: iload         9
      78: aaload
      79: astore        10
      81: aload         6
      83: aload         10
      85: invokevirtual #28                 // Method com/cloudera/nav/sdk/client/SourceAttrs.createSource:()Lcom/cloudera/nav/sdk/model/Source;
      88: invokeinterface #29,  2           // InterfaceMethod java/util/Collection.add:(Ljava/lang/Object;)Z
      93: pop
      94: iinc          9, 1
      97: goto          67
     100: aload         6
     102: areturn

  public com.cloudera.nav.sdk.client.ResultsBatch<java.util.Map<java.lang.String, java.lang.Object>> getRelationBatch(com.cloudera.nav.sdk.client.MetadataQuery);
    Code:
       0: aload_0
       1: ldc           #30                 // String relations
       3: invokespecial #31                 // Method getUrl:(Ljava/lang/String;)Ljava/lang/String;
       6: astore_2
       7: aload_0
       8: aload_2
       9: aload_1
      10: ldc_w         #32                 // class com/cloudera/nav/sdk/client/RelationResultsBatch
      13: invokevirtual #33                 // Method queryNav:(Ljava/lang/String;Lcom/cloudera/nav/sdk/client/MetadataQuery;Ljava/lang/Class;)Lcom/cloudera/nav/sdk/client/ResultsBatch;
      16: areturn

  public com.cloudera.nav.sdk.client.ResultsBatch<java.util.Map<java.lang.String, java.lang.Object>> getEntityBatch(com.cloudera.nav.sdk.client.MetadataQuery);
    Code:
       0: aload_0
       1: ldc           #34                 // String entities
       3: invokespecial #31                 // Method getUrl:(Ljava/lang/String;)Ljava/lang/String;
       6: astore_2
       7: aload_0
       8: aload_2
       9: aload_1
      10: ldc_w         #35                 // class com/cloudera/nav/sdk/client/EntityResultsBatch
      13: invokevirtual #33                 // Method queryNav:(Ljava/lang/String;Lcom/cloudera/nav/sdk/client/MetadataQuery;Ljava/lang/Class;)Lcom/cloudera/nav/sdk/client/ResultsBatch;
      16: areturn

  public com.cloudera.nav.sdk.client.ResultsBatch<java.util.Map<java.lang.String, java.lang.Object>> queryNav(java.lang.String, com.cloudera.nav.sdk.client.MetadataQuery, java.lang.Class<? extends com.cloudera.nav.sdk.client.ResultsBatch<java.util.Map<java.lang.String, java.lang.Object>>>);
    Code:
       0: aload_0
       1: invokespecial #17                 // Method newRestTemplate:()Lorg/springframework/web/client/RestTemplate;
       4: astore        4
       6: aload_0
       7: invokespecial #19                 // Method getAuthHeaders:()Lorg/springframework/http/HttpHeaders;
      10: astore        5
      12: new           #20                 // class org/springframework/http/HttpEntity
      15: dup
      16: aload_2
      17: aload         5
      19: invokespecial #36                 // Method org/springframework/http/HttpEntity."<init>":(Ljava/lang/Object;Lorg/springframework/util/MultiValueMap;)V
      22: astore        6
      24: aload         4
      26: aload_1
      27: getstatic     #37                 // Field org/springframework/http/HttpMethod.POST:Lorg/springframework/http/HttpMethod;
      30: aload         6
      32: aload_3
      33: iconst_0
      34: anewarray     #24                 // class java/lang/Object
      37: invokevirtual #25                 // Method org/springframework/web/client/RestTemplate.exchange:(Ljava/lang/String;Lorg/springframework/http/HttpMethod;Lorg/springframework/http/HttpEntity;Ljava/lang/Class;[Ljava/lang/Object;)Lorg/springframework/http/ResponseEntity;
      40: invokevirtual #27                 // Method org/springframework/http/ResponseEntity.getBody:()Ljava/lang/Object;
      43: checkcast     #38                 // class com/cloudera/nav/sdk/client/ResultsBatch
      46: areturn

  private org.springframework.web.client.RestTemplate newRestTemplate();
    Code:
       0: aload_0
       1: getfield      #9                  // Field isSSL:Z
       4: ifeq          50
       7: invokestatic  #39                 // Method org/apache/http/impl/client/HttpClients.custom:()Lorg/apache/http/impl/client/HttpClientBuilder;
      10: aload_0
      11: getfield      #11                 // Field sslContext:Ljavax/net/ssl/SSLContext;
      14: invokevirtual #40                 // Method org/apache/http/impl/client/HttpClientBuilder.setSSLContext:(Ljavax/net/ssl/SSLContext;)Lorg/apache/http/impl/client/HttpClientBuilder;
      17: aload_0
      18: getfield      #13                 // Field hostnameVerifier:Ljavax/net/ssl/HostnameVerifier;
      21: invokevirtual #41                 // Method org/apache/http/impl/client/HttpClientBuilder.setSSLHostnameVerifier:(Ljavax/net/ssl/HostnameVerifier;)Lorg/apache/http/impl/client/HttpClientBuilder;
      24: invokevirtual #42                 // Method org/apache/http/impl/client/HttpClientBuilder.build:()Lorg/apache/http/impl/client/CloseableHttpClient;
      27: astore_1
      28: new           #43                 // class org/springframework/http/client/HttpComponentsClientHttpRequestFactory
      31: dup
      32: invokespecial #44                 // Method org/springframework/http/client/HttpComponentsClientHttpRequestFactory."<init>":()V
      35: astore_2
      36: aload_2
      37: aload_1
      38: invokevirtual #45                 // Method org/springframework/http/client/HttpComponentsClientHttpRequestFactory.setHttpClient:(Lorg/apache/http/client/HttpClient;)V
      41: new           #46                 // class org/springframework/web/client/RestTemplate
      44: dup
      45: aload_2
      46: invokespecial #47                 // Method org/springframework/web/client/RestTemplate."<init>":(Lorg/springframework/http/client/ClientHttpRequestFactory;)V
      49: areturn
      50: new           #46                 // class org/springframework/web/client/RestTemplate
      53: dup
      54: invokespecial #48                 // Method org/springframework/web/client/RestTemplate."<init>":()V
      57: areturn

  public com.cloudera.nav.sdk.model.Source getSourceForUrl(java.lang.String);
    Code:
       0: aload_0
       1: getfield      #5                  // Field sourceCacheByUrl:Lcom/google/common/cache/Cache;
       4: aload_1
       5: invokeinterface #49,  2           // InterfaceMethod com/google/common/cache/Cache.getIfPresent:(Ljava/lang/Object;)Ljava/lang/Object;
      10: checkcast     #50                 // class com/cloudera/nav/sdk/model/Source
      13: astore_2
      14: aload_2
      15: ifnonnull     22
      18: aload_0
      19: invokespecial #51                 // Method loadAllSources:()V
      22: aload_0
      23: getfield      #5                  // Field sourceCacheByUrl:Lcom/google/common/cache/Cache;
      26: aload_1
      27: invokeinterface #49,  2           // InterfaceMethod com/google/common/cache/Cache.getIfPresent:(Ljava/lang/Object;)Ljava/lang/Object;
      32: checkcast     #50                 // class com/cloudera/nav/sdk/model/Source
      35: astore_2
      36: aload_2
      37: ifnull        44
      40: iconst_1
      41: goto          45
      44: iconst_0
      45: new           #52                 // class java/lang/StringBuilder
      48: dup
      49: invokespecial #53                 // Method java/lang/StringBuilder."<init>":()V
      52: ldc           #54                 // String Could not find Source at
      54: invokevirtual #55                 // Method java/lang/StringBuilder.append:(Ljava/lang/String;)Ljava/lang/StringBuilder;
      57: aload_1
      58: invokevirtual #55                 // Method java/lang/StringBuilder.append:(Ljava/lang/String;)Ljava/lang/StringBuilder;
      61: invokevirtual #56                 // Method java/lang/StringBuilder.toString:()Ljava/lang/String;
      64: invokestatic  #57                 // Method com/google/common/base/Preconditions.checkArgument:(ZLjava/lang/Object;)V
      67: aload_2
      68: areturn

  public com.cloudera.nav.sdk.model.Source getOnlySource(com.cloudera.nav.sdk.model.SourceType);
    Code:
       0: aload_0
       1: aload_1
       2: invokevirtual #58                 // Method getSourcesForType:(Lcom/cloudera/nav/sdk/model/SourceType;)Ljava/util/Collection;
       5: astore_2
       6: aload_2
       7: new           #52                 // class java/lang/StringBuilder
      10: dup
      11: invokespecial #53                 // Method java/lang/StringBuilder."<init>":()V
      14: ldc           #59                 // String Could not find sources for source type
      16: invokevirtual #55                 // Method java/lang/StringBuilder.append:(Ljava/lang/String;)Ljava/lang/StringBuilder;
      19: aload_1
      20: invokevirtual #60                 // Method com/cloudera/nav/sdk/model/SourceType.name:()Ljava/lang/String;
      23: invokevirtual #55                 // Method java/lang/StringBuilder.append:(Ljava/lang/String;)Ljava/lang/StringBuilder;
      26: invokevirtual #56                 // Method java/lang/StringBuilder.toString:()Ljava/lang/String;
      29: invokestatic  #61                 // Method com/google/common/base/Preconditions.checkNotNull:(Ljava/lang/Object;Ljava/lang/Object;)Ljava/lang/Object;
      32: pop
      33: aload_2
      34: invokestatic  #62                 // Method com/google/common/collect/Iterables.getOnlyElement:(Ljava/lang/Iterable;)Ljava/lang/Object;
      37: checkcast     #50                 // class com/cloudera/nav/sdk/model/Source
      40: areturn

  public java.util.Collection<com.cloudera.nav.sdk.model.Source> getSourcesForType(com.cloudera.nav.sdk.model.SourceType);
    Code:
       0: aload_0
       1: getfield      #6                  // Field sourceCacheByType:Lcom/google/common/cache/Cache;
       4: aload_1
       5: invokeinterface #49,  2           // InterfaceMethod com/google/common/cache/Cache.getIfPresent:(Ljava/lang/Object;)Ljava/lang/Object;
      10: checkcast     #63                 // class java/util/Collection
      13: astore_2
      14: aload_2
      15: ifnonnull     36
      18: aload_0
      19: invokespecial #51                 // Method loadAllSources:()V
      22: aload_0
      23: getfield      #6                  // Field sourceCacheByType:Lcom/google/common/cache/Cache;
      26: aload_1
      27: invokeinterface #49,  2           // InterfaceMethod com/google/common/cache/Cache.getIfPresent:(Ljava/lang/Object;)Ljava/lang/Object;
      32: checkcast     #63                 // class java/util/Collection
      35: astore_2
      36: aload_2
      37: areturn

  public void resetSources();
    Code:
       0: aload_0
       1: getfield      #5                  // Field sourceCacheByUrl:Lcom/google/common/cache/Cache;
       4: invokeinterface #64,  1           // InterfaceMethod com/google/common/cache/Cache.invalidateAll:()V
       9: aload_0
      10: getfield      #6                  // Field sourceCacheByType:Lcom/google/common/cache/Cache;
      13: invokeinterface #64,  1           // InterfaceMethod com/google/common/cache/Cache.invalidateAll:()V
      18: return

  private org.springframework.http.HttpHeaders getAuthHeaders();
    Code:
       0: ldc           #65                 // String %s:%s
       2: iconst_2
       3: anewarray     #24                 // class java/lang/Object
       6: dup
       7: iconst_0
       8: aload_0
       9: getfield      #2                  // Field config:Lcom/cloudera/nav/sdk/client/ClientConfig;
      12: invokevirtual #66                 // Method com/cloudera/nav/sdk/client/ClientConfig.getUsername:()Ljava/lang/String;
      15: aastore
      16: dup
      17: iconst_1
      18: aload_0
      19: getfield      #2                  // Field config:Lcom/cloudera/nav/sdk/client/ClientConfig;
      22: invokevirtual #67                 // Method com/cloudera/nav/sdk/client/ClientConfig.getPassword:()Ljava/lang/String;
      25: aastore
      26: invokestatic  #68                 // Method java/lang/String.format:(Ljava/lang/String;[Ljava/lang/Object;)Ljava/lang/String;
      29: astore_1
      30: aload_1
      31: invokevirtual #69                 // Method java/lang/String.getBytes:()[B
      34: astore_2
      35: aload_2
      36: invokestatic  #70                 // Method org/apache/commons/codec/binary/Base64.encodeBase64:([B)[B
      39: astore_3
      40: new           #71                 // class java/lang/String
      43: dup
      44: aload_3
      45: invokespecial #72                 // Method java/lang/String."<init>":([B)V
      48: astore        4
      50: new           #73                 // class org/springframework/http/HttpHeaders
      53: dup
      54: invokespecial #74                 // Method org/springframework/http/HttpHeaders."<init>":()V
      57: astore        5
      59: aload         5
      61: ldc           #75                 // String Authorization
      63: new           #52                 // class java/lang/StringBuilder
      66: dup
      67: invokespecial #53                 // Method java/lang/StringBuilder."<init>":()V
      70: ldc           #76                 // String Basic
      72: invokevirtual #55                 // Method java/lang/StringBuilder.append:(Ljava/lang/String;)Ljava/lang/StringBuilder;
      75: aload         4
      77: invokevirtual #55                 // Method java/lang/StringBuilder.append:(Ljava/lang/String;)Ljava/lang/StringBuilder;
      80: invokevirtual #56                 // Method java/lang/StringBuilder.toString:()Ljava/lang/String;
      83: invokevirtual #77                 // Method org/springframework/http/HttpHeaders.add:(Ljava/lang/String;Ljava/lang/String;)V
      86: aload         5
      88: areturn

  private java.lang.String getUrl();
    Code:
       0: aload_0
       1: getfield      #2                  // Field config:Lcom/cloudera/nav/sdk/client/ClientConfig;
       4: invokevirtual #7                  // Method com/cloudera/nav/sdk/client/ClientConfig.getNavigatorUrl:()Ljava/lang/String;
       7: astore_1
       8: aload_1
       9: ldc           #34                 // String entities
      11: invokestatic  #78                 // Method joinUrlPath:(Ljava/lang/String;Ljava/lang/String;)Ljava/lang/String;
      14: astore_2
      15: ldc           #79                 // String %s?query=%s
      17: iconst_2
      18: anewarray     #24                 // class java/lang/Object
      21: dup
      22: iconst_0
      23: aload_2
      24: aastore
      25: dup
      26: iconst_1
      27: ldc           #80                 // String type:SOURCE
      29: aastore
      30: invokestatic  #68                 // Method java/lang/String.format:(Ljava/lang/String;[Ljava/lang/Object;)Ljava/lang/String;
      33: areturn

  private java.lang.String getUrl(java.lang.String);
    Code:
       0: aload_0
       1: getfield      #2                  // Field config:Lcom/cloudera/nav/sdk/client/ClientConfig;
       4: invokevirtual #7                  // Method com/cloudera/nav/sdk/client/ClientConfig.getNavigatorUrl:()Ljava/lang/String;
       7: astore_2
       8: aload_2
       9: aload_1
      10: invokestatic  #78                 // Method joinUrlPath:(Ljava/lang/String;Ljava/lang/String;)Ljava/lang/String;
      13: astore_3
      14: new           #52                 // class java/lang/StringBuilder
      17: dup
      18: invokespecial #53                 // Method java/lang/StringBuilder."<init>":()V
      21: aload_3
      22: invokevirtual #55                 // Method java/lang/StringBuilder.append:(Ljava/lang/String;)Ljava/lang/StringBuilder;
      25: ldc           #81                 // String /paging
      27: invokevirtual #55                 // Method java/lang/StringBuilder.append:(Ljava/lang/String;)Ljava/lang/StringBuilder;
      30: invokevirtual #56                 // Method java/lang/StringBuilder.toString:()Ljava/lang/String;
      33: areturn

  private void loadAllSources();
    Code:
       0: aload_0
       1: invokevirtual #82                 // Method getAllSources:()Ljava/util/Collection;
       4: astore_1
       5: aload_1
       6: invokeinterface #83,  1           // InterfaceMethod java/util/Collection.iterator:()Ljava/util/Iterator;
      11: astore_2
      12: aload_2
      13: invokeinterface #84,  1           // InterfaceMethod java/util/Iterator.hasNext:()Z
      18: ifeq          142
      21: aload_2
      22: invokeinterface #85,  1           // InterfaceMethod java/util/Iterator.next:()Ljava/lang/Object;
      27: checkcast     #50                 // class com/cloudera/nav/sdk/model/Source
      30: astore_3
      31: aload_3
      32: invokevirtual #86                 // Method com/cloudera/nav/sdk/model/Source.getSourceUrl:()Ljava/lang/String;
      35: ifnonnull     79
      38: getstatic     #87                 // Field LOG:Lorg/slf4j/Logger;
      41: ldc           #88                 // String Source %s did not have a source url
      43: iconst_1
      44: anewarray     #24                 // class java/lang/Object
      47: dup
      48: iconst_0
      49: aload_3
      50: invokevirtual #89                 // Method com/cloudera/nav/sdk/model/Source.getName:()Ljava/lang/String;
      53: ifnull        63
      56: aload_3
      57: invokevirtual #89                 // Method com/cloudera/nav/sdk/model/Source.getName:()Ljava/lang/String;
      60: goto          67
      63: aload_3
      64: invokevirtual #90                 // Method com/cloudera/nav/sdk/model/Source.getIdentity:()Ljava/lang/String;
      67: aastore
      68: invokestatic  #68                 // Method java/lang/String.format:(Ljava/lang/String;[Ljava/lang/Object;)Ljava/lang/String;
      71: invokeinterface #91,  2           // InterfaceMethod org/slf4j/Logger.warn:(Ljava/lang/String;)V
      76: goto          12
      79: aload_0
      80: getfield      #5                  // Field sourceCacheByUrl:Lcom/google/common/cache/Cache;
      83: aload_3
      84: invokevirtual #86                 // Method com/cloudera/nav/sdk/model/Source.getSourceUrl:()Ljava/lang/String;
      87: aload_3
      88: invokeinterface #92,  3           // InterfaceMethod com/google/common/cache/Cache.put:(Ljava/lang/Object;Ljava/lang/Object;)V
      93: aload_0
      94: getfield      #6                  // Field sourceCacheByType:Lcom/google/common/cache/Cache;
      97: aload_3
      98: invokevirtual #93                 // Method com/cloudera/nav/sdk/model/Source.getSourceType:()Lcom/cloudera/nav/sdk/model/SourceType;
     101: new           #94                 // class com/cloudera/nav/sdk/client/NavApiCient$1
     104: dup
     105: aload_0
     106: invokespecial #95                 // Method com/cloudera/nav/sdk/client/NavApiCient$1."<init>":(Lcom/cloudera/nav/sdk/client/NavApiCient;)V
     109: invokeinterface #96,  3           // InterfaceMethod com/google/common/cache/Cache.get:(Ljava/lang/Object;Ljava/util/concurrent/Callable;)Ljava/lang/Object;
     114: checkcast     #63                 // class java/util/Collection
     117: astore        4
     119: aload         4
     121: aload_3
     122: invokeinterface #29,  2           // InterfaceMethod java/util/Collection.add:(Ljava/lang/Object;)Z
     127: pop
     128: goto          139
     131: astore        4
     133: aload         4
     135: invokestatic  #98                 // Method com/google/common/base/Throwables.propagate:(Ljava/lang/Throwable;)Ljava/lang/RuntimeException;
     138: athrow
     139: goto          12
     142: return
    Exception table:
       from    to  target type
          93   128   131   Class java/util/concurrent/ExecutionException

  private static java.lang.String joinUrlPath(java.lang.String, java.lang.String);
    Code:
       0: new           #52                 // class java/lang/StringBuilder
       3: dup
       4: invokespecial #53                 // Method java/lang/StringBuilder."<init>":()V
       7: aload_0
       8: invokevirtual #55                 // Method java/lang/StringBuilder.append:(Ljava/lang/String;)Ljava/lang/StringBuilder;
      11: aload_0
      12: ldc           #99                 // String /
      14: invokevirtual #100                // Method java/lang/String.endsWith:(Ljava/lang/String;)Z
      17: ifeq          25
      20: ldc           #101                // String
      22: goto          27
      25: ldc           #99                 // String /
      27: invokevirtual #55                 // Method java/lang/StringBuilder.append:(Ljava/lang/String;)Ljava/lang/StringBuilder;
      30: aload_1
      31: invokevirtual #55                 // Method java/lang/StringBuilder.append:(Ljava/lang/String;)Ljava/lang/StringBuilder;
      34: invokevirtual #56                 // Method java/lang/StringBuilder.toString:()Ljava/lang/String;
      37: areturn

  static {};
    Code:
       0: ldc_w         #102                // class com/cloudera/nav/sdk/client/NavApiCient
       3: invokestatic  #103                // Method org/slf4j/LoggerFactory.getLogger:(Ljava/lang/Class;)Lorg/slf4j/Logger;
       6: putstatic     #87                 // Field LOG:Lorg/slf4j/Logger;
       9: return
}
