Compiled from "EnumSingleValueConverter.java"
public class com.thoughtworks.xstream.converters.enums.EnumSingleValueConverter extends com.thoughtworks.xstream.converters.basic.AbstractSingleValueConverter {
  private final java.lang.Class<? extends java.lang.Enum> enumType;

  public com.thoughtworks.xstream.converters.enums.EnumSingleValueConverter(java.lang.Class<? extends java.lang.Enum>);
    Code:
       0: aload_0
       1: invokespecial #1                  // Method com/thoughtworks/xstream/converters/basic/AbstractSingleValueConverter."<init>":()V
       4: ldc_w         #2                  // class java/lang/Enum
       7: aload_1
       8: invokevirtual #3                  // Method java/lang/Class.isAssignableFrom:(Ljava/lang/Class;)Z
      11: ifne          31
      14: aload_1
      15: ldc_w         #2                  // class java/lang/Enum
      18: if_acmpeq     31
      21: new           #4                  // class java/lang/IllegalArgumentException
      24: dup
      25: ldc           #5                  // String Converter can only handle defined enums
      27: invokespecial #6                  // Method java/lang/IllegalArgumentException."<init>":(Ljava/lang/String;)V
      30: athrow
      31: aload_0
      32: aload_1
      33: putfield      #7                  // Field enumType:Ljava/lang/Class;
      36: return

  public boolean canConvert(java.lang.Class);
    Code:
       0: aload_0
       1: getfield      #7                  // Field enumType:Ljava/lang/Class;
       4: aload_1
       5: invokevirtual #3                  // Method java/lang/Class.isAssignableFrom:(Ljava/lang/Class;)Z
       8: ireturn

  public java.lang.String toString(java.lang.Object);
    Code:
       0: ldc_w         #2                  // class java/lang/Enum
       3: aload_1
       4: invokevirtual #8                  // Method java/lang/Class.cast:(Ljava/lang/Object;)Ljava/lang/Object;
       7: checkcast     #2                  // class java/lang/Enum
      10: invokevirtual #9                  // Method java/lang/Enum.name:()Ljava/lang/String;
      13: areturn

  public java.lang.Object fromString(java.lang.String);
    Code:
       0: aload_0
       1: getfield      #7                  // Field enumType:Ljava/lang/Class;
       4: aload_1
       5: invokestatic  #10                 // Method java/lang/Enum.valueOf:(Ljava/lang/Class;Ljava/lang/String;)Ljava/lang/Enum;
       8: astore_2
       9: aload_2
      10: areturn
}
