Compiled from "EnumSetConverter.java"
public class com.thoughtworks.xstream.converters.enums.EnumSetConverter implements com.thoughtworks.xstream.converters.Converter {
  private static final java.lang.reflect.Field typeField;

  private final com.thoughtworks.xstream.mapper.Mapper mapper;

  public com.thoughtworks.xstream.converters.enums.EnumSetConverter(com.thoughtworks.xstream.mapper.Mapper);
    Code:
       0: aload_0
       1: invokespecial #1                  // Method java/lang/Object."<init>":()V
       4: aload_0
       5: aload_1
       6: putfield      #2                  // Field mapper:Lcom/thoughtworks/xstream/mapper/Mapper;
       9: return

  public boolean canConvert(java.lang.Class);
    Code:
       0: getstatic     #3                  // Field typeField:Ljava/lang/reflect/Field;
       3: ifnull        20
       6: ldc_w         #4                  // class java/util/EnumSet
       9: aload_1
      10: invokevirtual #5                  // Method java/lang/Class.isAssignableFrom:(Ljava/lang/Class;)Z
      13: ifeq          20
      16: iconst_1
      17: goto          21
      20: iconst_0
      21: ireturn

  public void marshal(java.lang.Object, com.thoughtworks.xstream.io.HierarchicalStreamWriter, com.thoughtworks.xstream.converters.MarshallingContext);
    Code:
       0: aload_1
       1: checkcast     #4                  // class java/util/EnumSet
       4: astore        4
       6: getstatic     #3                  // Field typeField:Ljava/lang/reflect/Field;
       9: aload         4
      11: invokestatic  #6                  // Method com/thoughtworks/xstream/core/util/Fields.read:(Ljava/lang/reflect/Field;Ljava/lang/Object;)Ljava/lang/Object;
      14: checkcast     #7                  // class java/lang/Class
      17: astore        5
      19: aload_0
      20: getfield      #2                  // Field mapper:Lcom/thoughtworks/xstream/mapper/Mapper;
      23: ldc           #8                  // String enum-type
      25: invokeinterface #9,  2            // InterfaceMethod com/thoughtworks/xstream/mapper/Mapper.aliasForSystemAttribute:(Ljava/lang/String;)Ljava/lang/String;
      30: astore        6
      32: aload         6
      34: ifnull        56
      37: aload_2
      38: aload         6
      40: aload_0
      41: getfield      #2                  // Field mapper:Lcom/thoughtworks/xstream/mapper/Mapper;
      44: aload         5
      46: invokeinterface #10,  2           // InterfaceMethod com/thoughtworks/xstream/mapper/Mapper.serializedClass:(Ljava/lang/Class;)Ljava/lang/String;
      51: invokeinterface #11,  3           // InterfaceMethod com/thoughtworks/xstream/io/HierarchicalStreamWriter.addAttribute:(Ljava/lang/String;Ljava/lang/String;)V
      56: aload_2
      57: aload_0
      58: aload         4
      60: invokespecial #12                 // Method joinEnumValues:(Ljava/util/EnumSet;)Ljava/lang/String;
      63: invokeinterface #13,  2           // InterfaceMethod com/thoughtworks/xstream/io/HierarchicalStreamWriter.setValue:(Ljava/lang/String;)V
      68: return

  private java.lang.String joinEnumValues(java.util.EnumSet);
    Code:
       0: iconst_0
       1: istore_2
       2: new           #14                 // class java/lang/StringBuffer
       5: dup
       6: invokespecial #15                 // Method java/lang/StringBuffer."<init>":()V
       9: astore_3
      10: aload_1
      11: invokevirtual #16                 // Method java/util/EnumSet.iterator:()Ljava/util/Iterator;
      14: astore        4
      16: aload         4
      18: invokeinterface #17,  1           // InterfaceMethod java/util/Iterator.hasNext:()Z
      23: ifeq          67
      26: aload         4
      28: invokeinterface #18,  1           // InterfaceMethod java/util/Iterator.next:()Ljava/lang/Object;
      33: checkcast     #19                 // class java/lang/Enum
      36: astore        5
      38: iload_2
      39: ifeq          52
      42: aload_3
      43: bipush        44
      45: invokevirtual #20                 // Method java/lang/StringBuffer.append:(C)Ljava/lang/StringBuffer;
      48: pop
      49: goto          54
      52: iconst_1
      53: istore_2
      54: aload_3
      55: aload         5
      57: invokevirtual #21                 // Method java/lang/Enum.name:()Ljava/lang/String;
      60: invokevirtual #22                 // Method java/lang/StringBuffer.append:(Ljava/lang/String;)Ljava/lang/StringBuffer;
      63: pop
      64: goto          16
      67: aload_3
      68: invokevirtual #23                 // Method java/lang/StringBuffer.toString:()Ljava/lang/String;
      71: areturn

  public java.lang.Object unmarshal(com.thoughtworks.xstream.io.HierarchicalStreamReader, com.thoughtworks.xstream.converters.UnmarshallingContext);
    Code:
       0: aload_0
       1: getfield      #2                  // Field mapper:Lcom/thoughtworks/xstream/mapper/Mapper;
       4: ldc           #8                  // String enum-type
       6: invokeinterface #9,  2            // InterfaceMethod com/thoughtworks/xstream/mapper/Mapper.aliasForSystemAttribute:(Ljava/lang/String;)Ljava/lang/String;
      11: astore_3
      12: aload_3
      13: ifnonnull     26
      16: new           #24                 // class com/thoughtworks/xstream/converters/ConversionException
      19: dup
      20: ldc           #25                 // String No EnumType specified for EnumSet
      22: invokespecial #26                 // Method com/thoughtworks/xstream/converters/ConversionException."<init>":(Ljava/lang/String;)V
      25: athrow
      26: aload_0
      27: getfield      #2                  // Field mapper:Lcom/thoughtworks/xstream/mapper/Mapper;
      30: aload_1
      31: aload_3
      32: invokeinterface #27,  2           // InterfaceMethod com/thoughtworks/xstream/io/HierarchicalStreamReader.getAttribute:(Ljava/lang/String;)Ljava/lang/String;
      37: invokeinterface #28,  2           // InterfaceMethod com/thoughtworks/xstream/mapper/Mapper.realClass:(Ljava/lang/String;)Ljava/lang/Class;
      42: astore        4
      44: aload         4
      46: invokestatic  #29                 // Method java/util/EnumSet.noneOf:(Ljava/lang/Class;)Ljava/util/EnumSet;
      49: astore        5
      51: aload_1
      52: invokeinterface #30,  1           // InterfaceMethod com/thoughtworks/xstream/io/HierarchicalStreamReader.getValue:()Ljava/lang/String;
      57: ldc           #31                 // String ,
      59: invokevirtual #32                 // Method java/lang/String.split:(Ljava/lang/String;)[Ljava/lang/String;
      62: astore        6
      64: iconst_0
      65: istore        7
      67: iload         7
      69: aload         6
      71: arraylength
      72: if_icmpge     109
      75: aload         6
      77: iload         7
      79: aaload
      80: astore        8
      82: aload         8
      84: invokevirtual #33                 // Method java/lang/String.length:()I
      87: ifle          103
      90: aload         5
      92: aload         4
      94: aload         8
      96: invokestatic  #34                 // Method java/lang/Enum.valueOf:(Ljava/lang/Class;Ljava/lang/String;)Ljava/lang/Enum;
      99: invokevirtual #35                 // Method java/util/EnumSet.add:(Ljava/lang/Object;)Z
     102: pop
     103: iinc          7, 1
     106: goto          67
     109: aload         5
     111: areturn

  static {};
    Code:
       0: aconst_null
       1: astore_0
       2: ldc_w         #4                  // class java/util/EnumSet
       5: invokevirtual #36                 // Method java/lang/Class.getDeclaredFields:()[Ljava/lang/reflect/Field;
       8: astore_1
       9: iconst_0
      10: istore_2
      11: iload_2
      12: aload_1
      13: arraylength
      14: if_icmpge     47
      17: aload_1
      18: iload_2
      19: aaload
      20: invokevirtual #37                 // Method java/lang/reflect/Field.getType:()Ljava/lang/Class;
      23: ldc_w         #7                  // class java/lang/Class
      26: if_acmpne     41
      29: aload_1
      30: iload_2
      31: aaload
      32: astore_0
      33: aload_0
      34: iconst_1
      35: invokevirtual #38                 // Method java/lang/reflect/Field.setAccessible:(Z)V
      38: goto          47
      41: iinc          2, 1
      44: goto          11
      47: aload_0
      48: ifnonnull     61
      51: new           #39                 // class java/lang/ExceptionInInitializerError
      54: dup
      55: ldc           #40                 // String Cannot detect element type of EnumSet
      57: invokespecial #41                 // Method java/lang/ExceptionInInitializerError."<init>":(Ljava/lang/String;)V
      60: athrow
      61: goto          65
      64: astore_1
      65: aload_0
      66: putstatic     #3                  // Field typeField:Ljava/lang/reflect/Field;
      69: return
    Exception table:
       from    to  target type
           2    61    64   Class java/lang/SecurityException
}
