Compiled from "WebSockets.java"
class io.undertow.websockets.core.WebSockets$3 implements java.lang.Runnable {
  final io.undertow.websockets.core.StreamSinkFrameChannel val$channel;

  io.undertow.websockets.core.WebSockets$3(io.undertow.websockets.core.StreamSinkFrameChannel);
    Code:
       0: aload_0
       1: aload_1
       2: putfield      #1                  // Field val$channel:Lio/undertow/websockets/core/StreamSinkFrameChannel;
       5: aload_0
       6: invokespecial #2                  // Method java/lang/Object."<init>":()V
       9: return

  public void run();
    Code:
       0: aload_0
       1: getfield      #1                  // Field val$channel:Lio/undertow/websockets/core/StreamSinkFrameChannel;
       4: invokevirtual #3                  // Method io/undertow/websockets/core/StreamSinkFrameChannel.isOpen:()Z
       7: ifeq          17
      10: aload_0
      11: getfield      #1                  // Field val$channel:Lio/undertow/websockets/core/StreamSinkFrameChannel;
      14: invokestatic  #4                  // Method org/xnio/IoUtils.safeClose:(Ljava/io/Closeable;)V
      17: return
}
