Compiled from "TypedField.java"
final class nl.mauritssilvis.darts.java.core.boards.TypedField implements nl.mauritssilvis.darts.java.api.boards.Field {
  private final nl.mauritssilvis.darts.java.api.boards.FieldType fieldType;

  private final java.lang.String name;

  private final int score;

  private nl.mauritssilvis.darts.java.core.boards.TypedField(nl.mauritssilvis.darts.java.api.boards.FieldType, int);
    Code:
       0: aload_0
       1: invokespecial #1                  // Method java/lang/Object."<init>":()V
       4: aload_0
       5: aload_1
       6: putfield      #7                  // Field fieldType:Lnl/mauritssilvis/darts/java/api/boards/FieldType;
       9: aload_0
      10: aload_1
      11: invokestatic  #13                 // Method getShorthand:(Lnl/mauritssilvis/darts/java/api/boards/FieldType;)Ljava/lang/String;
      14: iload_2
      15: invokedynamic #17,  0             // InvokeDynamic #0:makeConcatWithConstants:(Ljava/lang/String;I)Ljava/lang/String;
      20: putfield      #21                 // Field name:Ljava/lang/String;
      23: aload_0
      24: aload_1
      25: invokestatic  #25                 // Method getMultiplier:(Lnl/mauritssilvis/darts/java/api/boards/FieldType;)I
      28: iload_2
      29: imul
      30: putfield      #29                 // Field score:I
      33: return

  public static nl.mauritssilvis.darts.java.api.boards.Field of(nl.mauritssilvis.darts.java.api.boards.FieldType, int);
    Code:
       0: new           #8                  // class nl/mauritssilvis/darts/java/core/boards/TypedField
       3: dup
       4: aload_0
       5: iload_1
       6: invokespecial #33                 // Method "<init>":(Lnl/mauritssilvis/darts/java/api/boards/FieldType;I)V
       9: areturn

  public nl.mauritssilvis.darts.java.api.boards.FieldType getFieldType();
    Code:
       0: aload_0
       1: getfield      #7                  // Field fieldType:Lnl/mauritssilvis/darts/java/api/boards/FieldType;
       4: areturn

  public java.lang.String getName();
    Code:
       0: aload_0
       1: getfield      #21                 // Field name:Ljava/lang/String;
       4: areturn

  public int getScore();
    Code:
       0: aload_0
       1: getfield      #29                 // Field score:I
       4: ireturn

  private static java.lang.String getShorthand(nl.mauritssilvis.darts.java.api.boards.FieldType);
    Code:
       0: getstatic     #36                 // Field nl/mauritssilvis/darts/java/core/boards/TypedField$1.$SwitchMap$nl$mauritssilvis$darts$java$api$boards$FieldType:[I
       3: aload_0
       4: invokevirtual #42                 // Method nl/mauritssilvis/darts/java/api/boards/FieldType.ordinal:()I
       7: iaload
       8: tableswitch   { // 1 to 4
                     1: 48
                     2: 53
                     3: 58
                     4: 63
               default: 40
          }
      40: new           #48                 // class java/lang/IncompatibleClassChangeError
      43: dup
      44: invokespecial #50                 // Method java/lang/IncompatibleClassChangeError."<init>":()V
      47: athrow
      48: ldc           #51                 // String
      50: goto          65
      53: ldc           #53                 // String D
      55: goto          65
      58: ldc           #55                 // String T
      60: goto          65
      63: ldc           #57                 // String Q
      65: areturn

  private static int getMultiplier(nl.mauritssilvis.darts.java.api.boards.FieldType);
    Code:
       0: getstatic     #36                 // Field nl/mauritssilvis/darts/java/core/boards/TypedField$1.$SwitchMap$nl$mauritssilvis$darts$java$api$boards$FieldType:[I
       3: aload_0
       4: invokevirtual #42                 // Method nl/mauritssilvis/darts/java/api/boards/FieldType.ordinal:()I
       7: iaload
       8: tableswitch   { // 1 to 4
                     1: 48
                     2: 52
                     3: 56
                     4: 60
               default: 40
          }
      40: new           #48                 // class java/lang/IncompatibleClassChangeError
      43: dup
      44: invokespecial #50                 // Method java/lang/IncompatibleClassChangeError."<init>":()V
      47: athrow
      48: iconst_1
      49: goto          61
      52: iconst_2
      53: goto          61
      56: iconst_3
      57: goto          61
      60: iconst_4
      61: ireturn

  public boolean equals(java.lang.Object);
    Code:
       0: aload_1
       1: aload_0
       2: if_acmpne     7
       5: iconst_1
       6: ireturn
       7: aload_1
       8: instanceof    #8                  // class nl/mauritssilvis/darts/java/core/boards/TypedField
      11: ifne          16
      14: iconst_0
      15: ireturn
      16: aload_1
      17: checkcast     #8                  // class nl/mauritssilvis/darts/java/core/boards/TypedField
      20: astore_2
      21: aload_0
      22: invokevirtual #59                 // Method getScore:()I
      25: aload_2
      26: invokevirtual #59                 // Method getScore:()I
      29: if_icmpeq     34
      32: iconst_0
      33: ireturn
      34: aload_0
      35: invokevirtual #62                 // Method getFieldType:()Lnl/mauritssilvis/darts/java/api/boards/FieldType;
      38: astore_3
      39: aload_2
      40: invokevirtual #62                 // Method getFieldType:()Lnl/mauritssilvis/darts/java/api/boards/FieldType;
      43: astore        4
      45: aload_3
      46: ifnonnull     57
      49: aload         4
      51: ifnull        68
      54: goto          66
      57: aload_3
      58: aload         4
      60: invokevirtual #66                 // Method java/lang/Object.equals:(Ljava/lang/Object;)Z
      63: ifne          68
      66: iconst_0
      67: ireturn
      68: aload_0
      69: invokevirtual #70                 // Method getName:()Ljava/lang/String;
      72: astore        5
      74: aload_2
      75: invokevirtual #70                 // Method getName:()Ljava/lang/String;
      78: astore        6
      80: aload         5
      82: ifnonnull     93
      85: aload         6
      87: ifnull        105
      90: goto          103
      93: aload         5
      95: aload         6
      97: invokevirtual #66                 // Method java/lang/Object.equals:(Ljava/lang/Object;)Z
     100: ifne          105
     103: iconst_0
     104: ireturn
     105: iconst_1
     106: ireturn

  public int hashCode();
    Code:
       0: bipush        59
       2: istore_1
       3: iconst_1
       4: istore_2
       5: iload_2
       6: bipush        59
       8: imul
       9: aload_0
      10: invokevirtual #59                 // Method getScore:()I
      13: iadd
      14: istore_2
      15: aload_0
      16: invokevirtual #62                 // Method getFieldType:()Lnl/mauritssilvis/darts/java/api/boards/FieldType;
      19: astore_3
      20: iload_2
      21: bipush        59
      23: imul
      24: aload_3
      25: ifnonnull     33
      28: bipush        43
      30: goto          37
      33: aload_3
      34: invokevirtual #74                 // Method java/lang/Object.hashCode:()I
      37: iadd
      38: istore_2
      39: aload_0
      40: invokevirtual #70                 // Method getName:()Ljava/lang/String;
      43: astore        4
      45: iload_2
      46: bipush        59
      48: imul
      49: aload         4
      51: ifnonnull     59
      54: bipush        43
      56: goto          64
      59: aload         4
      61: invokevirtual #74                 // Method java/lang/Object.hashCode:()I
      64: iadd
      65: istore_2
      66: iload_2
      67: ireturn

  public java.lang.String toString();
    Code:
       0: aload_0
       1: invokevirtual #62                 // Method getFieldType:()Lnl/mauritssilvis/darts/java/api/boards/FieldType;
       4: aload_0
       5: invokevirtual #70                 // Method getName:()Ljava/lang/String;
       8: aload_0
       9: invokevirtual #59                 // Method getScore:()I
      12: invokedynamic #77,  0             // InvokeDynamic #1:makeConcatWithConstants:(Lnl/mauritssilvis/darts/java/api/boards/FieldType;Ljava/lang/String;I)Ljava/lang/String;
      17: areturn
}
