Compiled from "LoggerMailbox.scala"
public class akka.event.LoggerMailboxType implements akka.dispatch.MailboxType, akka.dispatch.ProducesMessageQueue<akka.event.LoggerMailbox> {
  public akka.dispatch.MessageQueue create(scala.Option<akka.actor.ActorRef>, scala.Option<akka.actor.ActorSystem>);
    Code:
       0: new           #17                 // class scala/Tuple2
       3: dup
       4: aload_1
       5: aload_2
       6: invokespecial #21                 // Method scala/Tuple2."<init>":(Ljava/lang/Object;Ljava/lang/Object;)V
       9: astore_3
      10: aload_3
      11: ifnull        98
      14: aload_3
      15: invokevirtual #25                 // Method scala/Tuple2._1:()Ljava/lang/Object;
      18: checkcast     #27                 // class scala/Option
      21: astore        4
      23: aload_3
      24: invokevirtual #30                 // Method scala/Tuple2._2:()Ljava/lang/Object;
      27: checkcast     #27                 // class scala/Option
      30: astore        5
      32: aload         4
      34: instanceof    #32                 // class scala/Some
      37: ifeq          98
      40: aload         4
      42: checkcast     #32                 // class scala/Some
      45: astore        6
      47: aload         6
      49: invokevirtual #35                 // Method scala/Some.x:()Ljava/lang/Object;
      52: checkcast     #37                 // class akka/actor/ActorRef
      55: astore        7
      57: aload         5
      59: instanceof    #32                 // class scala/Some
      62: ifeq          98
      65: aload         5
      67: checkcast     #32                 // class scala/Some
      70: astore        8
      72: aload         8
      74: invokevirtual #35                 // Method scala/Some.x:()Ljava/lang/Object;
      77: checkcast     #39                 // class akka/actor/ActorSystem
      80: astore        9
      82: new           #41                 // class akka/event/LoggerMailbox
      85: dup
      86: aload         7
      88: aload         9
      90: invokespecial #44                 // Method akka/event/LoggerMailbox."<init>":(Lakka/actor/ActorRef;Lakka/actor/ActorSystem;)V
      93: astore        10
      95: aload         10
      97: areturn
      98: new           #46                 // class java/lang/IllegalArgumentException
     101: dup
     102: ldc           #48                 // String no mailbox owner or system given
     104: invokespecial #51                 // Method java/lang/IllegalArgumentException."<init>":(Ljava/lang/String;)V
     107: athrow

  public akka.event.LoggerMailboxType(akka.actor.ActorSystem$Settings, com.typesafe.config.Config);
    Code:
       0: aload_0
       1: invokespecial #64                 // Method java/lang/Object."<init>":()V
       4: return
}
