Compiled from "EventBus.scala"
public final class akka.event.LookupClassification$$anon$1 implements java.util.Comparator<java.lang.Object> {
  private final akka.event.LookupClassification $outer;

  public int compare(java.lang.Object, java.lang.Object);
    Code:
       0: aload_0
       1: getfield      #16                 // Field $outer:Lakka/event/LookupClassification;
       4: aload_1
       5: aload_2
       6: invokeinterface #19,  3           // InterfaceMethod akka/event/LookupClassification.compareSubscribers:(Ljava/lang/Object;Ljava/lang/Object;)I
      11: ireturn

  public akka.event.LookupClassification$$anon$1(akka.event.LookupClassification);
    Code:
       0: aload_1
       1: ifnonnull     6
       4: aconst_null
       5: athrow
       6: aload_0
       7: aload_1
       8: putfield      #16                 // Field $outer:Lakka/event/LookupClassification;
      11: aload_0
      12: invokespecial #29                 // Method java/lang/Object."<init>":()V
      15: return
}
