Compiled from "MavenModuleSetBuild.java"
public final class hudson.maven.MavenModuleSetBuild extends hudson.model.AbstractBuild<hudson.maven.MavenModuleSet, hudson.maven.MavenModuleSetBuild> {
  private static final java.util.logging.Logger LOGGER;

  public static boolean debug;

  public hudson.maven.MavenModuleSetBuild(hudson.maven.MavenModuleSet) throws java.io.IOException;
    Code:
       0: aload_0
       1: aload_1
       2: invokespecial #2                  // Method hudson/model/AbstractBuild."<init>":(Lhudson/model/AbstractProject;)V
       5: return

  public hudson.maven.MavenModuleSetBuild(hudson.maven.MavenModuleSet, java.io.File) throws java.io.IOException;
    Code:
       0: aload_0
       1: aload_1
       2: aload_2
       3: invokespecial #3                  // Method hudson/model/AbstractBuild."<init>":(Lhudson/model/AbstractProject;Ljava/io/File;)V
       6: return

  public hudson.model.Result getResult();
    Code:
       0: aload_0
       1: invokespecial #4                  // Method hudson/model/AbstractBuild.getResult:()Lhudson/model/Result;
       4: astore_1
       5: aload_0
       6: invokevirtual #5                  // Method getModuleLastBuilds:()Ljava/util/Map;
       9: invokeinterface #6,  1            // InterfaceMethod java/util/Map.values:()Ljava/util/Collection;
      14: invokeinterface #7,  1            // InterfaceMethod java/util/Collection.iterator:()Ljava/util/Iterator;
      19: astore_2
      20: aload_2
      21: invokeinterface #8,  1            // InterfaceMethod java/util/Iterator.hasNext:()Z
      26: ifeq          81
      29: aload_2
      30: invokeinterface #9,  1            // InterfaceMethod java/util/Iterator.next:()Ljava/lang/Object;
      35: checkcast     #10                 // class hudson/maven/MavenBuild
      38: astore_3
      39: aload_3
      40: invokevirtual #11                 // Method hudson/maven/MavenBuild.getResult:()Lhudson/model/Result;
      43: astore        4
      45: aload_1
      46: ifnonnull     55
      49: aload         4
      51: astore_1
      52: goto          78
      55: aload         4
      57: getstatic     #12                 // Field hudson/model/Result.NOT_BUILT:Lhudson/model/Result;
      60: if_acmpne     66
      63: goto          20
      66: aload         4
      68: ifnull        78
      71: aload_1
      72: aload         4
      74: invokevirtual #13                 // Method hudson/model/Result.combine:(Lhudson/model/Result;)Lhudson/model/Result;
      77: astore_1
      78: goto          20
      81: aload_1
      82: areturn

  public java.util.Map<hudson.maven.MavenModule, java.util.List<hudson.maven.MavenBuild>> getModuleBuilds();
    Code:
       0: aload_0
       1: invokevirtual #14                 // Method getParent:()Lhudson/model/Job;
       4: checkcast     #15                 // class hudson/maven/MavenModuleSet
       7: invokevirtual #16                 // Method hudson/maven/MavenModuleSet.getModules:()Ljava/util/Collection;
      10: astore_1
      11: aload_0
      12: invokevirtual #17                 // Method getNextBuild:()Lhudson/model/Run;
      15: checkcast     #18                 // class hudson/maven/MavenModuleSetBuild
      18: astore_2
      19: aload_2
      20: ifnull        30
      23: aload_2
      24: invokevirtual #19                 // Method getNumber:()I
      27: goto          32
      30: ldc           #20                 // int 2147483647
      32: istore_3
      33: new           #21                 // class java/util/LinkedHashMap
      36: dup
      37: aload_1
      38: invokeinterface #22,  1           // InterfaceMethod java/util/Collection.size:()I
      43: invokespecial #23                 // Method java/util/LinkedHashMap."<init>":(I)V
      46: astore        4
      48: aload_1
      49: invokeinterface #7,  1            // InterfaceMethod java/util/Collection.iterator:()Ljava/util/Iterator;
      54: astore        5
      56: aload         5
      58: invokeinterface #8,  1            // InterfaceMethod java/util/Iterator.hasNext:()Z
      63: ifeq          153
      66: aload         5
      68: invokeinterface #9,  1            // InterfaceMethod java/util/Iterator.next:()Ljava/lang/Object;
      73: checkcast     #24                 // class hudson/maven/MavenModule
      76: astore        6
      78: new           #25                 // class java/util/ArrayList
      81: dup
      82: invokespecial #26                 // Method java/util/ArrayList."<init>":()V
      85: astore        7
      87: aload         6
      89: aload_0
      90: getfield      #27                 // Field number:I
      93: invokevirtual #28                 // Method hudson/maven/MavenModule.getNearestBuild:(I)Lhudson/model/Run;
      96: checkcast     #10                 // class hudson/maven/MavenBuild
      99: astore        8
     101: aload         8
     103: ifnull        138
     106: aload         8
     108: invokevirtual #29                 // Method hudson/maven/MavenBuild.getNumber:()I
     111: iload_3
     112: if_icmpge     138
     115: aload         7
     117: aload         8
     119: invokeinterface #30,  2           // InterfaceMethod java/util/List.add:(Ljava/lang/Object;)Z
     124: pop
     125: aload         8
     127: invokevirtual #31                 // Method hudson/maven/MavenBuild.getNextBuild:()Lhudson/model/Run;
     130: checkcast     #10                 // class hudson/maven/MavenBuild
     133: astore        8
     135: goto          101
     138: aload         4
     140: aload         6
     142: aload         7
     144: invokeinterface #32,  3           // InterfaceMethod java/util/Map.put:(Ljava/lang/Object;Ljava/lang/Object;)Ljava/lang/Object;
     149: pop
     150: goto          56
     153: aload         4
     155: areturn

  public java.lang.Object getDynamic(java.lang.String, org.kohsuke.stapler.StaplerRequest, org.kohsuke.stapler.StaplerResponse);
    Code:
       0: aload_1
       1: bipush        36
       3: invokevirtual #33                 // Method java/lang/String.indexOf:(I)I
       6: ifle          37
       9: aload_0
      10: invokevirtual #34                 // Method getProject:()Lhudson/model/AbstractProject;
      13: checkcast     #15                 // class hudson/maven/MavenModuleSet
      16: aload_1
      17: invokevirtual #35                 // Method hudson/maven/MavenModuleSet.getModule:(Ljava/lang/String;)Lhudson/maven/MavenModule;
      20: astore        4
      22: aload         4
      24: ifnull        37
      27: aload         4
      29: aload_0
      30: invokevirtual #19                 // Method getNumber:()I
      33: invokevirtual #36                 // Method hudson/maven/MavenModule.getBuildByNumber:(I)Lhudson/model/Run;
      36: areturn
      37: aload_0
      38: aload_1
      39: aload_2
      40: aload_3
      41: invokespecial #37                 // Method hudson/model/AbstractBuild.getDynamic:(Ljava/lang/String;Lorg/kohsuke/stapler/StaplerRequest;Lorg/kohsuke/stapler/StaplerResponse;)Ljava/lang/Object;
      44: areturn

  public java.util.Map<hudson.maven.MavenModule, hudson.maven.MavenBuild> getModuleLastBuilds();
    Code:
       0: aload_0
       1: invokevirtual #14                 // Method getParent:()Lhudson/model/Job;
       4: checkcast     #15                 // class hudson/maven/MavenModuleSet
       7: invokevirtual #16                 // Method hudson/maven/MavenModuleSet.getModules:()Ljava/util/Collection;
      10: astore_1
      11: aload_0
      12: invokevirtual #17                 // Method getNextBuild:()Lhudson/model/Run;
      15: checkcast     #18                 // class hudson/maven/MavenModuleSetBuild
      18: astore_2
      19: aload_2
      20: ifnull        30
      23: aload_2
      24: invokevirtual #19                 // Method getNumber:()I
      27: goto          32
      30: ldc           #20                 // int 2147483647
      32: istore_3
      33: new           #21                 // class java/util/LinkedHashMap
      36: dup
      37: aload_1
      38: invokeinterface #22,  1           // InterfaceMethod java/util/Collection.size:()I
      43: invokespecial #23                 // Method java/util/LinkedHashMap."<init>":(I)V
      46: astore        4
      48: aload_1
      49: invokeinterface #7,  1            // InterfaceMethod java/util/Collection.iterator:()Ljava/util/Iterator;
      54: astore        5
      56: aload         5
      58: invokeinterface #8,  1            // InterfaceMethod java/util/Iterator.hasNext:()Z
      63: ifeq          123
      66: aload         5
      68: invokeinterface #9,  1            // InterfaceMethod java/util/Iterator.next:()Ljava/lang/Object;
      73: checkcast     #24                 // class hudson/maven/MavenModule
      76: astore        6
      78: aload         6
      80: iload_3
      81: iconst_1
      82: isub
      83: invokevirtual #38                 // Method hudson/maven/MavenModule.getNearestOldBuild:(I)Lhudson/model/Run;
      86: checkcast     #10                 // class hudson/maven/MavenBuild
      89: astore        7
      91: aload         7
      93: ifnull        120
      96: aload         7
      98: invokevirtual #29                 // Method hudson/maven/MavenBuild.getNumber:()I
     101: aload_0
     102: invokevirtual #19                 // Method getNumber:()I
     105: if_icmplt     120
     108: aload         4
     110: aload         6
     112: aload         7
     114: invokeinterface #32,  3           // InterfaceMethod java/util/Map.put:(Ljava/lang/Object;Ljava/lang/Object;)Ljava/lang/Object;
     119: pop
     120: goto          56
     123: aload         4
     125: areturn

  public <T extends hudson.model.Action> java.util.List<T> findModuleBuildActions(java.lang.Class<T>);
    Code:
       0: aload_0
       1: invokevirtual #14                 // Method getParent:()Lhudson/model/Job;
       4: checkcast     #15                 // class hudson/maven/MavenModuleSet
       7: invokevirtual #16                 // Method hudson/maven/MavenModuleSet.getModules:()Ljava/util/Collection;
      10: astore_2
      11: new           #25                 // class java/util/ArrayList
      14: dup
      15: aload_2
      16: invokeinterface #22,  1           // InterfaceMethod java/util/Collection.size:()I
      21: invokespecial #39                 // Method java/util/ArrayList."<init>":(I)V
      24: astore_3
      25: aload_0
      26: invokevirtual #17                 // Method getNextBuild:()Lhudson/model/Run;
      29: checkcast     #18                 // class hudson/maven/MavenModuleSetBuild
      32: astore        4
      34: aload         4
      36: ifnull        49
      39: aload         4
      41: invokevirtual #19                 // Method getNumber:()I
      44: iconst_1
      45: isub
      46: goto          51
      49: ldc           #20                 // int 2147483647
      51: istore        5
      53: aload_2
      54: invokeinterface #7,  1            // InterfaceMethod java/util/Collection.iterator:()Ljava/util/Iterator;
      59: astore        6
      61: aload         6
      63: invokeinterface #8,  1            // InterfaceMethod java/util/Iterator.hasNext:()Z
      68: ifeq          153
      71: aload         6
      73: invokeinterface #9,  1            // InterfaceMethod java/util/Iterator.next:()Ljava/lang/Object;
      78: checkcast     #24                 // class hudson/maven/MavenModule
      81: astore        7
      83: aload         7
      85: iload         5
      87: invokevirtual #38                 // Method hudson/maven/MavenModule.getNearestOldBuild:(I)Lhudson/model/Run;
      90: checkcast     #10                 // class hudson/maven/MavenBuild
      93: astore        8
      95: aload         8
      97: ifnull        150
     100: aload         8
     102: invokevirtual #29                 // Method hudson/maven/MavenBuild.getNumber:()I
     105: aload_0
     106: getfield      #27                 // Field number:I
     109: if_icmplt     150
     112: aload         8
     114: aload_1
     115: invokevirtual #40                 // Method hudson/maven/MavenBuild.getAction:(Ljava/lang/Class;)Lhudson/model/Action;
     118: astore        9
     120: aload         9
     122: ifnull        137
     125: aload_3
     126: aload         9
     128: invokeinterface #30,  2           // InterfaceMethod java/util/List.add:(Ljava/lang/Object;)Z
     133: pop
     134: goto          150
     137: aload         8
     139: invokevirtual #41                 // Method hudson/maven/MavenBuild.getPreviousBuild:()Lhudson/model/Run;
     142: checkcast     #10                 // class hudson/maven/MavenBuild
     145: astore        8
     147: goto          95
     150: goto          61
     153: aload_3
     154: areturn

  public void run();
    Code:
       0: aload_0
       1: new           #42                 // class hudson/maven/MavenModuleSetBuild$RunnerImpl
       4: dup
       5: aload_0
       6: aconst_null
       7: invokespecial #43                 // Method hudson/maven/MavenModuleSetBuild$RunnerImpl."<init>":(Lhudson/maven/MavenModuleSetBuild;Lhudson/maven/MavenModuleSetBuild$1;)V
      10: invokevirtual #44                 // Method run:(Lhudson/model/Run$Runner;)V
      13: aload_0
      14: invokevirtual #34                 // Method getProject:()Lhudson/model/AbstractProject;
      17: checkcast     #15                 // class hudson/maven/MavenModuleSet
      20: invokevirtual #45                 // Method hudson/maven/MavenModuleSet.updateTransientActions:()V
      23: return

  public hudson.model.Fingerprint$RangeSet getDownstreamRelationship(hudson.model.AbstractProject);
    Code:
       0: aload_0
       1: aload_1
       2: invokespecial #46                 // Method hudson/model/AbstractBuild.getDownstreamRelationship:(Lhudson/model/AbstractProject;)Lhudson/model/Fingerprint$RangeSet;
       5: astore_2
       6: aload_0
       7: invokevirtual #47                 // Method getModuleBuilds:()Ljava/util/Map;
      10: invokeinterface #6,  1            // InterfaceMethod java/util/Map.values:()Ljava/util/Collection;
      15: invokeinterface #7,  1            // InterfaceMethod java/util/Collection.iterator:()Ljava/util/Iterator;
      20: astore_3
      21: aload_3
      22: invokeinterface #8,  1            // InterfaceMethod java/util/Iterator.hasNext:()Z
      27: ifeq          88
      30: aload_3
      31: invokeinterface #9,  1            // InterfaceMethod java/util/Iterator.next:()Ljava/lang/Object;
      36: checkcast     #48                 // class java/util/List
      39: astore        4
      41: aload         4
      43: invokeinterface #49,  1           // InterfaceMethod java/util/List.iterator:()Ljava/util/Iterator;
      48: astore        5
      50: aload         5
      52: invokeinterface #8,  1            // InterfaceMethod java/util/Iterator.hasNext:()Z
      57: ifeq          85
      60: aload         5
      62: invokeinterface #9,  1            // InterfaceMethod java/util/Iterator.next:()Ljava/lang/Object;
      67: checkcast     #10                 // class hudson/maven/MavenBuild
      70: astore        6
      72: aload_2
      73: aload         6
      75: aload_1
      76: invokevirtual #50                 // Method hudson/maven/MavenBuild.getDownstreamRelationship:(Lhudson/model/AbstractProject;)Lhudson/model/Fingerprint$RangeSet;
      79: invokevirtual #51                 // Method hudson/model/Fingerprint$RangeSet.add:(Lhudson/model/Fingerprint$RangeSet;)V
      82: goto          50
      85: goto          21
      88: aload_2
      89: areturn

  void notifyModuleBuild(hudson.maven.MavenBuild);
    Code:
       0: aload_0
       1: invokevirtual #14                 // Method getParent:()Lhudson/model/Job;
       4: checkcast     #15                 // class hudson/maven/MavenModuleSet
       7: invokevirtual #52                 // Method hudson/maven/MavenModuleSet.updateNextBuildNumber:()V
      10: aload_0
      11: invokevirtual #47                 // Method getModuleBuilds:()Ljava/util/Map;
      14: astore_2
      15: aload_0
      16: dup
      17: astore_3
      18: monitorenter
      19: iconst_0
      20: istore        4
      22: aload_0
      23: invokevirtual #53                 // Method getActions:()Ljava/util/List;
      26: astore        5
      28: new           #54                 // class java/util/HashSet
      31: dup
      32: invokespecial #55                 // Method java/util/HashSet."<init>":()V
      35: astore        6
      37: aload         5
      39: invokeinterface #49,  1           // InterfaceMethod java/util/List.iterator:()Ljava/util/Iterator;
      44: astore        7
      46: aload         7
      48: invokeinterface #8,  1            // InterfaceMethod java/util/Iterator.hasNext:()Z
      53: ifeq          113
      56: aload         7
      58: invokeinterface #9,  1            // InterfaceMethod java/util/Iterator.next:()Ljava/lang/Object;
      63: checkcast     #56                 // class hudson/model/Action
      66: astore        8
      68: aload         8
      70: instanceof    #57                 // class hudson/maven/MavenAggregatedReport
      73: ifeq          110
      76: aload         8
      78: checkcast     #57                 // class hudson/maven/MavenAggregatedReport
      81: astore        9
      83: aload         9
      85: aload_2
      86: aload_1
      87: invokeinterface #58,  3           // InterfaceMethod hudson/maven/MavenAggregatedReport.update:(Ljava/util/Map;Lhudson/maven/MavenBuild;)V
      92: aload         6
      94: aload         9
      96: invokeinterface #59,  1           // InterfaceMethod hudson/maven/MavenAggregatedReport.getIndividualActionType:()Ljava/lang/Class;
     101: invokeinterface #60,  2           // InterfaceMethod java/util/Set.add:(Ljava/lang/Object;)Z
     106: pop
     107: iconst_1
     108: istore        4
     110: goto          46
     113: aload_1
     114: ldc_w         #61                 // class hudson/maven/AggregatableAction
     117: invokevirtual #62                 // Method hudson/maven/MavenBuild.getActions:(Ljava/lang/Class;)Ljava/util/List;
     120: invokeinterface #49,  1           // InterfaceMethod java/util/List.iterator:()Ljava/util/Iterator;
     125: astore        7
     127: aload         7
     129: invokeinterface #8,  1            // InterfaceMethod java/util/Iterator.hasNext:()Z
     134: ifeq          200
     137: aload         7
     139: invokeinterface #9,  1            // InterfaceMethod java/util/Iterator.next:()Ljava/lang/Object;
     144: checkcast     #61                 // class hudson/maven/AggregatableAction
     147: astore        8
     149: aload         6
     151: aload         8
     153: invokevirtual #63                 // Method java/lang/Object.getClass:()Ljava/lang/Class;
     156: invokeinterface #60,  2           // InterfaceMethod java/util/Set.add:(Ljava/lang/Object;)Z
     161: ifeq          197
     164: aload         8
     166: aload_0
     167: aload_2
     168: invokeinterface #64,  3           // InterfaceMethod hudson/maven/AggregatableAction.createAggregatedAction:(Lhudson/maven/MavenModuleSetBuild;Ljava/util/Map;)Lhudson/maven/MavenAggregatedReport;
     173: astore        9
     175: aload         9
     177: aload_2
     178: aload_1
     179: invokeinterface #58,  3           // InterfaceMethod hudson/maven/MavenAggregatedReport.update:(Ljava/util/Map;Lhudson/maven/MavenBuild;)V
     184: aload         5
     186: aload         9
     188: invokeinterface #30,  2           // InterfaceMethod java/util/List.add:(Ljava/lang/Object;)Z
     193: pop
     194: iconst_1
     195: istore        4
     197: goto          127
     200: iload         4
     202: ifeq          219
     205: aload_0
     206: invokevirtual #65                 // Method save:()V
     209: aload_0
     210: invokevirtual #34                 // Method getProject:()Lhudson/model/AbstractProject;
     213: checkcast     #15                 // class hudson/maven/MavenModuleSet
     216: invokevirtual #45                 // Method hudson/maven/MavenModuleSet.updateTransientActions:()V
     219: aload_3
     220: monitorexit
     221: goto          231
     224: astore        10
     226: aload_3
     227: monitorexit
     228: aload         10
     230: athrow
     231: aload_1
     232: invokevirtual #66                 // Method hudson/maven/MavenBuild.getProject:()Lhudson/model/AbstractProject;
     235: checkcast     #24                 // class hudson/maven/MavenModule
     238: invokevirtual #67                 // Method hudson/maven/MavenModule.getModuleName:()Lhudson/maven/ModuleName;
     241: invokevirtual #68                 // Method hudson/maven/ModuleName.toFileSystemName:()Ljava/lang/String;
     244: astore_3
     245: aload_0
     246: invokevirtual #69                 // Method getRootDir:()Ljava/io/File;
     249: new           #70                 // class java/lang/StringBuilder
     252: dup
     253: invokespecial #71                 // Method java/lang/StringBuilder."<init>":()V
     256: ldc           #72                 // String ../../modules/
     258: invokevirtual #73                 // Method java/lang/StringBuilder.append:(Ljava/lang/String;)Ljava/lang/StringBuilder;
     261: aload_3
     262: invokevirtual #73                 // Method java/lang/StringBuilder.append:(Ljava/lang/String;)Ljava/lang/StringBuilder;
     265: ldc           #74                 // String /builds/
     267: invokevirtual #73                 // Method java/lang/StringBuilder.append:(Ljava/lang/String;)Ljava/lang/StringBuilder;
     270: aload_1
     271: invokevirtual #75                 // Method hudson/maven/MavenBuild.getId:()Ljava/lang/String;
     274: invokevirtual #73                 // Method java/lang/StringBuilder.append:(Ljava/lang/String;)Ljava/lang/StringBuilder;
     277: invokevirtual #76                 // Method java/lang/StringBuilder.toString:()Ljava/lang/String;
     280: aload_3
     281: new           #77                 // class hudson/util/StreamTaskListener
     284: dup
     285: invokespecial #78                 // Method hudson/util/StreamTaskListener."<init>":()V
     288: invokestatic  #79                 // Method hudson/Util.createSymlink:(Ljava/io/File;Ljava/lang/String;Ljava/lang/String;Lhudson/model/TaskListener;)V
     291: goto          357
     294: astore_2
     295: getstatic     #81                 // Field LOGGER:Ljava/util/logging/Logger;
     298: getstatic     #82                 // Field java/util/logging/Level.WARNING:Ljava/util/logging/Level;
     301: new           #70                 // class java/lang/StringBuilder
     304: dup
     305: invokespecial #71                 // Method java/lang/StringBuilder."<init>":()V
     308: ldc           #83                 // String Failed to update
     310: invokevirtual #73                 // Method java/lang/StringBuilder.append:(Ljava/lang/String;)Ljava/lang/StringBuilder;
     313: aload_0
     314: invokevirtual #84                 // Method java/lang/StringBuilder.append:(Ljava/lang/Object;)Ljava/lang/StringBuilder;
     317: invokevirtual #76                 // Method java/lang/StringBuilder.toString:()Ljava/lang/String;
     320: aload_2
     321: invokevirtual #85                 // Method java/util/logging/Logger.log:(Ljava/util/logging/Level;Ljava/lang/String;Ljava/lang/Throwable;)V
     324: goto          357
     327: astore_2
     328: getstatic     #81                 // Field LOGGER:Ljava/util/logging/Logger;
     331: getstatic     #82                 // Field java/util/logging/Level.WARNING:Ljava/util/logging/Level;
     334: new           #70                 // class java/lang/StringBuilder
     337: dup
     338: invokespecial #71                 // Method java/lang/StringBuilder."<init>":()V
     341: ldc           #83                 // String Failed to update
     343: invokevirtual #73                 // Method java/lang/StringBuilder.append:(Ljava/lang/String;)Ljava/lang/StringBuilder;
     346: aload_0
     347: invokevirtual #84                 // Method java/lang/StringBuilder.append:(Ljava/lang/Object;)Ljava/lang/StringBuilder;
     350: invokevirtual #76                 // Method java/lang/StringBuilder.toString:()Ljava/lang/String;
     353: aload_2
     354: invokevirtual #85                 // Method java/util/logging/Logger.log:(Ljava/util/logging/Level;Ljava/lang/String;Ljava/lang/Throwable;)V
     357: return
    Exception table:
       from    to  target type
          19   221   224   any
         224   228   224   any
           0   291   294   Class java/io/IOException
           0   291   327   Class java/lang/InterruptedException

  static hudson.model.Job access$100(hudson.maven.MavenModuleSetBuild);
    Code:
       0: aload_0
       1: getfield      #1                  // Field project:Lhudson/model/Job;
       4: areturn

  static hudson.model.Job access$200(hudson.maven.MavenModuleSetBuild);
    Code:
       0: aload_0
       1: getfield      #1                  // Field project:Lhudson/model/Job;
       4: areturn

  static hudson.model.Job access$300(hudson.maven.MavenModuleSetBuild);
    Code:
       0: aload_0
       1: getfield      #1                  // Field project:Lhudson/model/Job;
       4: areturn

  static hudson.model.Job access$400(hudson.maven.MavenModuleSetBuild);
    Code:
       0: aload_0
       1: getfield      #1                  // Field project:Lhudson/model/Job;
       4: areturn

  static hudson.model.Job access$500(hudson.maven.MavenModuleSetBuild);
    Code:
       0: aload_0
       1: getfield      #1                  // Field project:Lhudson/model/Job;
       4: areturn

  static hudson.model.Job access$600(hudson.maven.MavenModuleSetBuild);
    Code:
       0: aload_0
       1: getfield      #1                  // Field project:Lhudson/model/Job;
       4: areturn

  static hudson.model.Job access$700(hudson.maven.MavenModuleSetBuild);
    Code:
       0: aload_0
       1: getfield      #1                  // Field project:Lhudson/model/Job;
       4: areturn

  static hudson.model.Job access$800(hudson.maven.MavenModuleSetBuild);
    Code:
       0: aload_0
       1: getfield      #1                  // Field project:Lhudson/model/Job;
       4: areturn

  static hudson.model.Job access$900(hudson.maven.MavenModuleSetBuild);
    Code:
       0: aload_0
       1: getfield      #1                  // Field project:Lhudson/model/Job;
       4: areturn

  static hudson.model.Job access$1000(hudson.maven.MavenModuleSetBuild);
    Code:
       0: aload_0
       1: getfield      #1                  // Field project:Lhudson/model/Job;
       4: areturn

  static hudson.model.Job access$1100(hudson.maven.MavenModuleSetBuild);
    Code:
       0: aload_0
       1: getfield      #1                  // Field project:Lhudson/model/Job;
       4: areturn

  static hudson.model.Job access$1200(hudson.maven.MavenModuleSetBuild);
    Code:
       0: aload_0
       1: getfield      #1                  // Field project:Lhudson/model/Job;
       4: areturn

  static hudson.model.Job access$1300(hudson.maven.MavenModuleSetBuild);
    Code:
       0: aload_0
       1: getfield      #1                  // Field project:Lhudson/model/Job;
       4: areturn

  static hudson.model.Job access$1400(hudson.maven.MavenModuleSetBuild);
    Code:
       0: aload_0
       1: getfield      #1                  // Field project:Lhudson/model/Job;
       4: areturn

  static hudson.model.Job access$1500(hudson.maven.MavenModuleSetBuild);
    Code:
       0: aload_0
       1: getfield      #1                  // Field project:Lhudson/model/Job;
       4: areturn

  static hudson.model.Job access$1600(hudson.maven.MavenModuleSetBuild);
    Code:
       0: aload_0
       1: getfield      #1                  // Field project:Lhudson/model/Job;
       4: areturn

  static hudson.model.Job access$1700(hudson.maven.MavenModuleSetBuild);
    Code:
       0: aload_0
       1: getfield      #1                  // Field project:Lhudson/model/Job;
       4: areturn

  static hudson.model.Job access$1800(hudson.maven.MavenModuleSetBuild);
    Code:
       0: aload_0
       1: getfield      #1                  // Field project:Lhudson/model/Job;
       4: areturn

  static hudson.model.Job access$1900(hudson.maven.MavenModuleSetBuild);
    Code:
       0: aload_0
       1: getfield      #1                  // Field project:Lhudson/model/Job;
       4: areturn

  static hudson.model.Job access$2000(hudson.maven.MavenModuleSetBuild);
    Code:
       0: aload_0
       1: getfield      #1                  // Field project:Lhudson/model/Job;
       4: areturn

  static hudson.model.Job access$2100(hudson.maven.MavenModuleSetBuild);
    Code:
       0: aload_0
       1: getfield      #1                  // Field project:Lhudson/model/Job;
       4: areturn

  static hudson.model.Job access$2200(hudson.maven.MavenModuleSetBuild);
    Code:
       0: aload_0
       1: getfield      #1                  // Field project:Lhudson/model/Job;
       4: areturn

  static hudson.model.Job access$2300(hudson.maven.MavenModuleSetBuild);
    Code:
       0: aload_0
       1: getfield      #1                  // Field project:Lhudson/model/Job;
       4: areturn

  static hudson.model.Job access$2400(hudson.maven.MavenModuleSetBuild);
    Code:
       0: aload_0
       1: getfield      #1                  // Field project:Lhudson/model/Job;
       4: areturn

  static hudson.model.Job access$2500(hudson.maven.MavenModuleSetBuild);
    Code:
       0: aload_0
       1: getfield      #1                  // Field project:Lhudson/model/Job;
       4: areturn

  static {};
    Code:
       0: ldc_w         #18                 // class hudson/maven/MavenModuleSetBuild
       3: invokevirtual #87                 // Method java/lang/Class.getName:()Ljava/lang/String;
       6: invokestatic  #88                 // Method java/util/logging/Logger.getLogger:(Ljava/lang/String;)Ljava/util/logging/Logger;
       9: putstatic     #81                 // Field LOGGER:Ljava/util/logging/Logger;
      12: iconst_0
      13: putstatic     #89                 // Field debug:Z
      16: return
}
