Compiled from "ModuleDependency.java"
public final class hudson.maven.ModuleDependency implements java.io.Serializable {
  public final java.lang.String groupId;

  public final java.lang.String artifactId;

  public final java.lang.String version;

  public static final java.lang.String UNKNOWN;

  public static final java.lang.String NONE;

  private static final long serialVersionUID;

  public hudson.maven.ModuleDependency(java.lang.String, java.lang.String, java.lang.String);
    Code:
       0: aload_0
       1: invokespecial #1                  // Method java/lang/Object."<init>":()V
       4: aload_0
       5: aload_1
       6: putfield      #2                  // Field groupId:Ljava/lang/String;
       9: aload_0
      10: aload_2
      11: putfield      #3                  // Field artifactId:Ljava/lang/String;
      14: aload_3
      15: ifnonnull     21
      18: ldc           #4                  // String *
      20: astore_3
      21: aload_0
      22: aload_3
      23: putfield      #5                  // Field version:Ljava/lang/String;
      26: return

  public hudson.maven.ModuleDependency(hudson.maven.ModuleName, java.lang.String);
    Code:
       0: aload_0
       1: aload_1
       2: getfield      #6                  // Field hudson/maven/ModuleName.groupId:Ljava/lang/String;
       5: aload_1
       6: getfield      #7                  // Field hudson/maven/ModuleName.artifactId:Ljava/lang/String;
       9: aload_2
      10: invokespecial #8                  // Method "<init>":(Ljava/lang/String;Ljava/lang/String;Ljava/lang/String;)V
      13: return

  public hudson.maven.ModuleDependency(org.apache.maven.model.Dependency);
    Code:
       0: aload_0
       1: aload_1
       2: invokevirtual #9                  // Method org/apache/maven/model/Dependency.getGroupId:()Ljava/lang/String;
       5: aload_1
       6: invokevirtual #10                 // Method org/apache/maven/model/Dependency.getArtifactId:()Ljava/lang/String;
       9: aload_1
      10: invokevirtual #11                 // Method org/apache/maven/model/Dependency.getVersion:()Ljava/lang/String;
      13: invokespecial #8                  // Method "<init>":(Ljava/lang/String;Ljava/lang/String;Ljava/lang/String;)V
      16: return

  public hudson.maven.ModuleDependency(org.apache.maven.project.MavenProject);
    Code:
       0: aload_0
       1: aload_1
       2: invokevirtual #12                 // Method org/apache/maven/project/MavenProject.getGroupId:()Ljava/lang/String;
       5: aload_1
       6: invokevirtual #13                 // Method org/apache/maven/project/MavenProject.getArtifactId:()Ljava/lang/String;
       9: aload_1
      10: invokevirtual #14                 // Method org/apache/maven/project/MavenProject.getVersion:()Ljava/lang/String;
      13: invokespecial #8                  // Method "<init>":(Ljava/lang/String;Ljava/lang/String;Ljava/lang/String;)V
      16: return

  public hudson.maven.ModuleDependency(org.apache.maven.model.Plugin);
    Code:
       0: aload_0
       1: aload_1
       2: invokevirtual #15                 // Method org/apache/maven/model/Plugin.getGroupId:()Ljava/lang/String;
       5: aload_1
       6: invokevirtual #16                 // Method org/apache/maven/model/Plugin.getArtifactId:()Ljava/lang/String;
       9: aload_1
      10: invokevirtual #17                 // Method org/apache/maven/model/Plugin.getVersion:()Ljava/lang/String;
      13: ldc           #18                 // String -
      15: invokestatic  #19                 // Method hudson/Functions.defaulted:(Ljava/lang/Object;Ljava/lang/Object;)Ljava/lang/Object;
      18: checkcast     #20                 // class java/lang/String
      21: invokespecial #8                  // Method "<init>":(Ljava/lang/String;Ljava/lang/String;Ljava/lang/String;)V
      24: return

  public hudson.maven.ModuleDependency(org.apache.maven.model.ReportPlugin);
    Code:
       0: aload_0
       1: aload_1
       2: invokevirtual #21                 // Method org/apache/maven/model/ReportPlugin.getGroupId:()Ljava/lang/String;
       5: aload_1
       6: invokevirtual #22                 // Method org/apache/maven/model/ReportPlugin.getArtifactId:()Ljava/lang/String;
       9: aload_1
      10: invokevirtual #23                 // Method org/apache/maven/model/ReportPlugin.getVersion:()Ljava/lang/String;
      13: invokespecial #8                  // Method "<init>":(Ljava/lang/String;Ljava/lang/String;Ljava/lang/String;)V
      16: return

  public hudson.maven.ModuleDependency(org.apache.maven.model.Extension);
    Code:
       0: aload_0
       1: aload_1
       2: invokevirtual #24                 // Method org/apache/maven/model/Extension.getGroupId:()Ljava/lang/String;
       5: aload_1
       6: invokevirtual #25                 // Method org/apache/maven/model/Extension.getArtifactId:()Ljava/lang/String;
       9: aload_1
      10: invokevirtual #26                 // Method org/apache/maven/model/Extension.getVersion:()Ljava/lang/String;
      13: invokespecial #8                  // Method "<init>":(Ljava/lang/String;Ljava/lang/String;Ljava/lang/String;)V
      16: return

  public hudson.maven.ModuleName getName();
    Code:
       0: new           #27                 // class hudson/maven/ModuleName
       3: dup
       4: aload_0
       5: getfield      #2                  // Field groupId:Ljava/lang/String;
       8: aload_0
       9: getfield      #3                  // Field artifactId:Ljava/lang/String;
      12: invokespecial #28                 // Method hudson/maven/ModuleName."<init>":(Ljava/lang/String;Ljava/lang/String;)V
      15: areturn

  public hudson.maven.ModuleDependency withUnknownVersion();
    Code:
       0: new           #29                 // class hudson/maven/ModuleDependency
       3: dup
       4: aload_0
       5: getfield      #2                  // Field groupId:Ljava/lang/String;
       8: aload_0
       9: getfield      #3                  // Field artifactId:Ljava/lang/String;
      12: ldc           #4                  // String *
      14: invokespecial #8                  // Method "<init>":(Ljava/lang/String;Ljava/lang/String;Ljava/lang/String;)V
      17: areturn

  public boolean equals(java.lang.Object);
    Code:
       0: aload_0
       1: aload_1
       2: if_acmpne     7
       5: iconst_1
       6: ireturn
       7: aload_1
       8: ifnull        22
      11: aload_0
      12: invokevirtual #30                 // Method java/lang/Object.getClass:()Ljava/lang/Class;
      15: aload_1
      16: invokevirtual #30                 // Method java/lang/Object.getClass:()Ljava/lang/Class;
      19: if_acmpeq     24
      22: iconst_0
      23: ireturn
      24: aload_1
      25: checkcast     #29                 // class hudson/maven/ModuleDependency
      28: astore_2
      29: aload_0
      30: getfield      #3                  // Field artifactId:Ljava/lang/String;
      33: aload_2
      34: getfield      #3                  // Field artifactId:Ljava/lang/String;
      37: invokevirtual #31                 // Method java/lang/String.equals:(Ljava/lang/Object;)Z
      40: ifeq          75
      43: aload_0
      44: getfield      #2                  // Field groupId:Ljava/lang/String;
      47: aload_2
      48: getfield      #2                  // Field groupId:Ljava/lang/String;
      51: invokevirtual #31                 // Method java/lang/String.equals:(Ljava/lang/Object;)Z
      54: ifeq          75
      57: aload_0
      58: getfield      #5                  // Field version:Ljava/lang/String;
      61: aload_2
      62: getfield      #5                  // Field version:Ljava/lang/String;
      65: invokevirtual #31                 // Method java/lang/String.equals:(Ljava/lang/Object;)Z
      68: ifeq          75
      71: iconst_1
      72: goto          76
      75: iconst_0
      76: ireturn

  public int hashCode();
    Code:
       0: aload_0
       1: getfield      #2                  // Field groupId:Ljava/lang/String;
       4: invokevirtual #32                 // Method java/lang/String.hashCode:()I
       7: istore_1
       8: bipush        31
      10: iload_1
      11: imul
      12: aload_0
      13: getfield      #3                  // Field artifactId:Ljava/lang/String;
      16: invokevirtual #32                 // Method java/lang/String.hashCode:()I
      19: iadd
      20: istore_1
      21: bipush        31
      23: iload_1
      24: imul
      25: aload_0
      26: getfield      #5                  // Field version:Ljava/lang/String;
      29: invokevirtual #32                 // Method java/lang/String.hashCode:()I
      32: iadd
      33: istore_1
      34: iload_1
      35: ireturn
}
