Compiled from "MAPServiceOamImpl.java"
public class org.mobicents.protocols.ss7.map.service.oam.MAPServiceOamImpl extends org.mobicents.protocols.ss7.map.MAPServiceBaseImpl implements org.mobicents.protocols.ss7.map.api.service.oam.MAPServiceOam {
  protected org.apache.log4j.Logger loger;

  public org.mobicents.protocols.ss7.map.service.oam.MAPServiceOamImpl(org.mobicents.protocols.ss7.map.MAPProviderImpl);
    Code:
       0: aload_0
       1: aload_1
       2: invokespecial #1                  // Method org/mobicents/protocols/ss7/map/MAPServiceBaseImpl."<init>":(Lorg/mobicents/protocols/ss7/map/MAPProviderImpl;)V
       5: aload_0
       6: ldc_w         #2                  // class org/mobicents/protocols/ss7/map/service/oam/MAPServiceOamImpl
       9: invokestatic  #3                  // Method org/apache/log4j/Logger.getLogger:(Ljava/lang/Class;)Lorg/apache/log4j/Logger;
      12: putfield      #4                  // Field loger:Lorg/apache/log4j/Logger;
      15: return

  public org.mobicents.protocols.ss7.map.api.service.oam.MAPDialogOam createNewDialog(org.mobicents.protocols.ss7.map.api.MAPApplicationContext, org.mobicents.protocols.ss7.sccp.parameter.SccpAddress, org.mobicents.protocols.ss7.map.api.primitives.AddressString, org.mobicents.protocols.ss7.sccp.parameter.SccpAddress, org.mobicents.protocols.ss7.map.api.primitives.AddressString) throws org.mobicents.protocols.ss7.map.api.MAPException;
    Code:
       0: aload_0
       1: aload_1
       2: aload_2
       3: aload_3
       4: aload         4
       6: aload         5
       8: aconst_null
       9: invokevirtual #5                  // Method createNewDialog:(Lorg/mobicents/protocols/ss7/map/api/MAPApplicationContext;Lorg/mobicents/protocols/ss7/sccp/parameter/SccpAddress;Lorg/mobicents/protocols/ss7/map/api/primitives/AddressString;Lorg/mobicents/protocols/ss7/sccp/parameter/SccpAddress;Lorg/mobicents/protocols/ss7/map/api/primitives/AddressString;Ljava/lang/Long;)Lorg/mobicents/protocols/ss7/map/api/service/oam/MAPDialogOam;
      12: areturn

  public org.mobicents.protocols.ss7.map.api.service.oam.MAPDialogOam createNewDialog(org.mobicents.protocols.ss7.map.api.MAPApplicationContext, org.mobicents.protocols.ss7.sccp.parameter.SccpAddress, org.mobicents.protocols.ss7.map.api.primitives.AddressString, org.mobicents.protocols.ss7.sccp.parameter.SccpAddress, org.mobicents.protocols.ss7.map.api.primitives.AddressString, java.lang.Long) throws org.mobicents.protocols.ss7.map.api.MAPException;
    Code:
       0: aload_0
       1: invokevirtual #6                  // Method isActivated:()Z
       4: ifne          17
       7: new           #7                  // class org/mobicents/protocols/ss7/map/api/MAPException
      10: dup
      11: ldc           #8                  // String Cannot create MAPDialogOam because MAPServiceOam is not activated
      13: invokespecial #9                  // Method org/mobicents/protocols/ss7/map/api/MAPException."<init>":(Ljava/lang/String;)V
      16: athrow
      17: aload_0
      18: aload_2
      19: aload         4
      21: aload         6
      23: invokevirtual #10                 // Method createNewTCAPDialog:(Lorg/mobicents/protocols/ss7/sccp/parameter/SccpAddress;Lorg/mobicents/protocols/ss7/sccp/parameter/SccpAddress;Ljava/lang/Long;)Lorg/mobicents/protocols/ss7/tcap/api/tc/dialog/Dialog;
      26: astore        7
      28: new           #11                 // class org/mobicents/protocols/ss7/map/service/oam/MAPDialogOamImpl
      31: dup
      32: aload_1
      33: aload         7
      35: aload_0
      36: getfield      #12                 // Field mapProviderImpl:Lorg/mobicents/protocols/ss7/map/MAPProviderImpl;
      39: aload_0
      40: aload_3
      41: aload         5
      43: invokespecial #13                 // Method org/mobicents/protocols/ss7/map/service/oam/MAPDialogOamImpl."<init>":(Lorg/mobicents/protocols/ss7/map/api/MAPApplicationContext;Lorg/mobicents/protocols/ss7/tcap/api/tc/dialog/Dialog;Lorg/mobicents/protocols/ss7/map/MAPProviderImpl;Lorg/mobicents/protocols/ss7/map/api/service/oam/MAPServiceOam;Lorg/mobicents/protocols/ss7/map/api/primitives/AddressString;Lorg/mobicents/protocols/ss7/map/api/primitives/AddressString;)V
      46: astore        8
      48: aload_0
      49: aload         8
      51: invokevirtual #14                 // Method putMAPDialogIntoCollection:(Lorg/mobicents/protocols/ss7/map/MAPDialogImpl;)V
      54: aload         8
      56: areturn

  protected org.mobicents.protocols.ss7.map.MAPDialogImpl createNewDialogIncoming(org.mobicents.protocols.ss7.map.api.MAPApplicationContext, org.mobicents.protocols.ss7.tcap.api.tc.dialog.Dialog);
    Code:
       0: new           #11                 // class org/mobicents/protocols/ss7/map/service/oam/MAPDialogOamImpl
       3: dup
       4: aload_1
       5: aload_2
       6: aload_0
       7: getfield      #12                 // Field mapProviderImpl:Lorg/mobicents/protocols/ss7/map/MAPProviderImpl;
      10: aload_0
      11: aconst_null
      12: aconst_null
      13: invokespecial #13                 // Method org/mobicents/protocols/ss7/map/service/oam/MAPDialogOamImpl."<init>":(Lorg/mobicents/protocols/ss7/map/api/MAPApplicationContext;Lorg/mobicents/protocols/ss7/tcap/api/tc/dialog/Dialog;Lorg/mobicents/protocols/ss7/map/MAPProviderImpl;Lorg/mobicents/protocols/ss7/map/api/service/oam/MAPServiceOam;Lorg/mobicents/protocols/ss7/map/api/primitives/AddressString;Lorg/mobicents/protocols/ss7/map/api/primitives/AddressString;)V
      16: areturn

  public void addMAPServiceListener(org.mobicents.protocols.ss7.map.api.service.oam.MAPServiceOamListener);
    Code:
       0: aload_0
       1: aload_1
       2: invokespecial #15                 // Method org/mobicents/protocols/ss7/map/MAPServiceBaseImpl.addMAPServiceListener:(Lorg/mobicents/protocols/ss7/map/api/MAPServiceListener;)V
       5: return

  public void removeMAPServiceListener(org.mobicents.protocols.ss7.map.api.service.oam.MAPServiceOamListener);
    Code:
       0: aload_0
       1: aload_1
       2: invokespecial #16                 // Method org/mobicents/protocols/ss7/map/MAPServiceBaseImpl.removeMAPServiceListener:(Lorg/mobicents/protocols/ss7/map/api/MAPServiceListener;)V
       5: return

  public org.mobicents.protocols.ss7.map.api.dialog.ServingCheckData isServingService(org.mobicents.protocols.ss7.map.api.MAPApplicationContext);
    Code:
       0: aload_1
       1: invokevirtual #17                 // Method org/mobicents/protocols/ss7/map/api/MAPApplicationContext.getApplicationContextName:()Lorg/mobicents/protocols/ss7/map/api/MAPApplicationContextName;
       4: astore_2
       5: aload_1
       6: invokevirtual #18                 // Method org/mobicents/protocols/ss7/map/api/MAPApplicationContext.getApplicationContextVersion:()Lorg/mobicents/protocols/ss7/map/api/MAPApplicationContextVersion;
       9: invokevirtual #19                 // Method org/mobicents/protocols/ss7/map/api/MAPApplicationContextVersion.getVersion:()I
      12: istore_3
      13: getstatic     #20                 // Field org/mobicents/protocols/ss7/map/service/oam/MAPServiceOamImpl$1.$SwitchMap$org$mobicents$protocols$ss7$map$api$MAPApplicationContextName:[I
      16: aload_2
      17: invokevirtual #21                 // Method org/mobicents/protocols/ss7/map/api/MAPApplicationContextName.ordinal:()I
      20: iaload
      21: lookupswitch  { // 2
                     1: 48
                     2: 119
               default: 190
          }
      48: iload_3
      49: iconst_2
      50: if_icmplt     69
      53: iload_3
      54: iconst_2
      55: if_icmpgt     69
      58: new           #22                 // class org/mobicents/protocols/ss7/map/dialog/ServingCheckDataImpl
      61: dup
      62: getstatic     #23                 // Field org/mobicents/protocols/ss7/map/api/dialog/ServingCheckResult.AC_Serving:Lorg/mobicents/protocols/ss7/map/api/dialog/ServingCheckResult;
      65: invokespecial #24                 // Method org/mobicents/protocols/ss7/map/dialog/ServingCheckDataImpl."<init>":(Lorg/mobicents/protocols/ss7/map/api/dialog/ServingCheckResult;)V
      68: areturn
      69: iload_3
      70: iconst_2
      71: if_icmple     108
      74: aload_1
      75: invokevirtual #25                 // Method org/mobicents/protocols/ss7/map/api/MAPApplicationContext.getOID:()[J
      78: astore        4
      80: aload         4
      82: bipush        7
      84: ldc2_w        #26                 // long 3l
      87: lastore
      88: aload         4
      90: invokestatic  #28                 // Method org/mobicents/protocols/ss7/tcap/asn/TcapFactory.createApplicationContextName:([J)Lorg/mobicents/protocols/ss7/tcap/asn/ApplicationContextName;
      93: astore        5
      95: new           #22                 // class org/mobicents/protocols/ss7/map/dialog/ServingCheckDataImpl
      98: dup
      99: getstatic     #29                 // Field org/mobicents/protocols/ss7/map/api/dialog/ServingCheckResult.AC_VersionIncorrect:Lorg/mobicents/protocols/ss7/map/api/dialog/ServingCheckResult;
     102: aload         5
     104: invokespecial #30                 // Method org/mobicents/protocols/ss7/map/dialog/ServingCheckDataImpl."<init>":(Lorg/mobicents/protocols/ss7/map/api/dialog/ServingCheckResult;Lorg/mobicents/protocols/ss7/tcap/asn/ApplicationContextName;)V
     107: areturn
     108: new           #22                 // class org/mobicents/protocols/ss7/map/dialog/ServingCheckDataImpl
     111: dup
     112: getstatic     #29                 // Field org/mobicents/protocols/ss7/map/api/dialog/ServingCheckResult.AC_VersionIncorrect:Lorg/mobicents/protocols/ss7/map/api/dialog/ServingCheckResult;
     115: invokespecial #24                 // Method org/mobicents/protocols/ss7/map/dialog/ServingCheckDataImpl."<init>":(Lorg/mobicents/protocols/ss7/map/api/dialog/ServingCheckResult;)V
     118: areturn
     119: iload_3
     120: iconst_1
     121: if_icmplt     140
     124: iload_3
     125: iconst_3
     126: if_icmpgt     140
     129: new           #22                 // class org/mobicents/protocols/ss7/map/dialog/ServingCheckDataImpl
     132: dup
     133: getstatic     #23                 // Field org/mobicents/protocols/ss7/map/api/dialog/ServingCheckResult.AC_Serving:Lorg/mobicents/protocols/ss7/map/api/dialog/ServingCheckResult;
     136: invokespecial #24                 // Method org/mobicents/protocols/ss7/map/dialog/ServingCheckDataImpl."<init>":(Lorg/mobicents/protocols/ss7/map/api/dialog/ServingCheckResult;)V
     139: areturn
     140: iload_3
     141: iconst_3
     142: if_icmple     179
     145: aload_1
     146: invokevirtual #25                 // Method org/mobicents/protocols/ss7/map/api/MAPApplicationContext.getOID:()[J
     149: astore        4
     151: aload         4
     153: bipush        7
     155: ldc2_w        #26                 // long 3l
     158: lastore
     159: aload         4
     161: invokestatic  #28                 // Method org/mobicents/protocols/ss7/tcap/asn/TcapFactory.createApplicationContextName:([J)Lorg/mobicents/protocols/ss7/tcap/asn/ApplicationContextName;
     164: astore        5
     166: new           #22                 // class org/mobicents/protocols/ss7/map/dialog/ServingCheckDataImpl
     169: dup
     170: getstatic     #29                 // Field org/mobicents/protocols/ss7/map/api/dialog/ServingCheckResult.AC_VersionIncorrect:Lorg/mobicents/protocols/ss7/map/api/dialog/ServingCheckResult;
     173: aload         5
     175: invokespecial #30                 // Method org/mobicents/protocols/ss7/map/dialog/ServingCheckDataImpl."<init>":(Lorg/mobicents/protocols/ss7/map/api/dialog/ServingCheckResult;Lorg/mobicents/protocols/ss7/tcap/asn/ApplicationContextName;)V
     178: areturn
     179: new           #22                 // class org/mobicents/protocols/ss7/map/dialog/ServingCheckDataImpl
     182: dup
     183: getstatic     #29                 // Field org/mobicents/protocols/ss7/map/api/dialog/ServingCheckResult.AC_VersionIncorrect:Lorg/mobicents/protocols/ss7/map/api/dialog/ServingCheckResult;
     186: invokespecial #24                 // Method org/mobicents/protocols/ss7/map/dialog/ServingCheckDataImpl."<init>":(Lorg/mobicents/protocols/ss7/map/api/dialog/ServingCheckResult;)V
     189: areturn
     190: new           #22                 // class org/mobicents/protocols/ss7/map/dialog/ServingCheckDataImpl
     193: dup
     194: getstatic     #31                 // Field org/mobicents/protocols/ss7/map/api/dialog/ServingCheckResult.AC_NotServing:Lorg/mobicents/protocols/ss7/map/api/dialog/ServingCheckResult;
     197: invokespecial #24                 // Method org/mobicents/protocols/ss7/map/dialog/ServingCheckDataImpl."<init>":(Lorg/mobicents/protocols/ss7/map/api/dialog/ServingCheckResult;)V
     200: areturn

  public org.mobicents.protocols.ss7.map.api.MAPApplicationContext getMAPv1ApplicationContext(int, org.mobicents.protocols.ss7.tcap.asn.comp.Invoke);
    Code:
       0: iload_1
       1: lookupswitch  { // 1
                    50: 20
               default: 30
          }
      20: getstatic     #32                 // Field org/mobicents/protocols/ss7/map/api/MAPApplicationContextName.tracingContext:Lorg/mobicents/protocols/ss7/map/api/MAPApplicationContextName;
      23: getstatic     #33                 // Field org/mobicents/protocols/ss7/map/api/MAPApplicationContextVersion.version1:Lorg/mobicents/protocols/ss7/map/api/MAPApplicationContextVersion;
      26: invokestatic  #34                 // Method org/mobicents/protocols/ss7/map/api/MAPApplicationContext.getInstance:(Lorg/mobicents/protocols/ss7/map/api/MAPApplicationContextName;Lorg/mobicents/protocols/ss7/map/api/MAPApplicationContextVersion;)Lorg/mobicents/protocols/ss7/map/api/MAPApplicationContext;
      29: areturn
      30: aconst_null
      31: areturn

  public void processComponent(org.mobicents.protocols.ss7.tcap.asn.comp.ComponentType, org.mobicents.protocols.ss7.tcap.asn.comp.OperationCode, org.mobicents.protocols.ss7.tcap.asn.comp.Parameter, org.mobicents.protocols.ss7.map.api.MAPDialog, java.lang.Long, java.lang.Long, org.mobicents.protocols.ss7.tcap.asn.comp.Invoke) throws org.mobicents.protocols.ss7.map.api.MAPParsingComponentException;
    Code:
       0: aload_1
       1: getstatic     #35                 // Field org/mobicents/protocols/ss7/tcap/asn/comp/ComponentType.Invoke:Lorg/mobicents/protocols/ss7/tcap/asn/comp/ComponentType;
       4: if_acmpne     17
       7: aload_0
       8: getfield      #12                 // Field mapProviderImpl:Lorg/mobicents/protocols/ss7/map/MAPProviderImpl;
      11: invokevirtual #36                 // Method org/mobicents/protocols/ss7/map/MAPProviderImpl.isCongested:()Z
      14: ifeq          17
      17: aload         4
      19: checkcast     #11                 // class org/mobicents/protocols/ss7/map/service/oam/MAPDialogOamImpl
      22: astore        8
      24: aload_2
      25: invokeinterface #37,  1           // InterfaceMethod org/mobicents/protocols/ss7/tcap/asn/comp/OperationCode.getLocalOperationCode:()Ljava/lang/Long;
      30: astore        9
      32: aload         9
      34: ifnonnull     50
      37: new           #38                 // class org/mobicents/protocols/ss7/map/api/MAPParsingComponentException
      40: dup
      41: ldc           #39                 // String
      43: getstatic     #40                 // Field org/mobicents/protocols/ss7/map/api/MAPParsingComponentExceptionReason.UnrecognizedOperation:Lorg/mobicents/protocols/ss7/map/api/MAPParsingComponentExceptionReason;
      46: invokespecial #41                 // Method org/mobicents/protocols/ss7/map/api/MAPParsingComponentException."<init>":(Ljava/lang/String;Lorg/mobicents/protocols/ss7/map/api/MAPParsingComponentExceptionReason;)V
      49: pop
      50: aload         4
      52: invokeinterface #42,  1           // InterfaceMethod org/mobicents/protocols/ss7/map/api/MAPDialog.getApplicationContext:()Lorg/mobicents/protocols/ss7/map/api/MAPApplicationContext;
      57: invokevirtual #17                 // Method org/mobicents/protocols/ss7/map/api/MAPApplicationContext.getApplicationContextName:()Lorg/mobicents/protocols/ss7/map/api/MAPApplicationContextName;
      60: astore        10
      62: aload         4
      64: invokeinterface #42,  1           // InterfaceMethod org/mobicents/protocols/ss7/map/api/MAPDialog.getApplicationContext:()Lorg/mobicents/protocols/ss7/map/api/MAPApplicationContext;
      69: invokevirtual #18                 // Method org/mobicents/protocols/ss7/map/api/MAPApplicationContext.getApplicationContextVersion:()Lorg/mobicents/protocols/ss7/map/api/MAPApplicationContextVersion;
      72: invokevirtual #19                 // Method org/mobicents/protocols/ss7/map/api/MAPApplicationContextVersion.getVersion:()I
      75: istore        11
      77: aload         9
      79: invokevirtual #43                 // Method java/lang/Long.longValue:()J
      82: l2i
      83: istore        12
      85: iload         12
      87: lookupswitch  { // 2
                    50: 112
                    58: 151
               default: 190
          }
     112: aload         10
     114: getstatic     #32                 // Field org/mobicents/protocols/ss7/map/api/MAPApplicationContextName.tracingContext:Lorg/mobicents/protocols/ss7/map/api/MAPApplicationContextName;
     117: if_acmpne     221
     120: aload_1
     121: getstatic     #35                 // Field org/mobicents/protocols/ss7/tcap/asn/comp/ComponentType.Invoke:Lorg/mobicents/protocols/ss7/tcap/asn/comp/ComponentType;
     124: if_acmpne     139
     127: aload_0
     128: aload_3
     129: aload         8
     131: aload         5
     133: invokespecial #44                 // Method processActivateTraceModeRequest:(Lorg/mobicents/protocols/ss7/tcap/asn/comp/Parameter;Lorg/mobicents/protocols/ss7/map/service/oam/MAPDialogOamImpl;Ljava/lang/Long;)V
     136: goto          221
     139: aload_0
     140: aload_3
     141: aload         8
     143: aload         5
     145: invokespecial #45                 // Method processActivateTraceModeResponse:(Lorg/mobicents/protocols/ss7/tcap/asn/comp/Parameter;Lorg/mobicents/protocols/ss7/map/service/oam/MAPDialogOamImpl;Ljava/lang/Long;)V
     148: goto          221
     151: aload         10
     153: getstatic     #46                 // Field org/mobicents/protocols/ss7/map/api/MAPApplicationContextName.imsiRetrievalContext:Lorg/mobicents/protocols/ss7/map/api/MAPApplicationContextName;
     156: if_acmpne     221
     159: aload_1
     160: getstatic     #35                 // Field org/mobicents/protocols/ss7/tcap/asn/comp/ComponentType.Invoke:Lorg/mobicents/protocols/ss7/tcap/asn/comp/ComponentType;
     163: if_acmpne     178
     166: aload_0
     167: aload_3
     168: aload         8
     170: aload         5
     172: invokespecial #47                 // Method processSendImsiRequest:(Lorg/mobicents/protocols/ss7/tcap/asn/comp/Parameter;Lorg/mobicents/protocols/ss7/map/service/oam/MAPDialogOamImpl;Ljava/lang/Long;)V
     175: goto          221
     178: aload_0
     179: aload_3
     180: aload         8
     182: aload         5
     184: invokespecial #48                 // Method processSendImsiResponse:(Lorg/mobicents/protocols/ss7/tcap/asn/comp/Parameter;Lorg/mobicents/protocols/ss7/map/service/oam/MAPDialogOamImpl;Ljava/lang/Long;)V
     187: goto          221
     190: new           #38                 // class org/mobicents/protocols/ss7/map/api/MAPParsingComponentException
     193: dup
     194: new           #49                 // class java/lang/StringBuilder
     197: dup
     198: invokespecial #50                 // Method java/lang/StringBuilder."<init>":()V
     201: ldc           #51                 // String MAPServiceOam: unknown incoming operation code:
     203: invokevirtual #52                 // Method java/lang/StringBuilder.append:(Ljava/lang/String;)Ljava/lang/StringBuilder;
     206: iload         12
     208: invokevirtual #53                 // Method java/lang/StringBuilder.append:(I)Ljava/lang/StringBuilder;
     211: invokevirtual #54                 // Method java/lang/StringBuilder.toString:()Ljava/lang/String;
     214: getstatic     #40                 // Field org/mobicents/protocols/ss7/map/api/MAPParsingComponentExceptionReason.UnrecognizedOperation:Lorg/mobicents/protocols/ss7/map/api/MAPParsingComponentExceptionReason;
     217: invokespecial #41                 // Method org/mobicents/protocols/ss7/map/api/MAPParsingComponentException."<init>":(Ljava/lang/String;Lorg/mobicents/protocols/ss7/map/api/MAPParsingComponentExceptionReason;)V
     220: athrow
     221: return

  private void processActivateTraceModeRequest(org.mobicents.protocols.ss7.tcap.asn.comp.Parameter, org.mobicents.protocols.ss7.map.service.oam.MAPDialogOamImpl, java.lang.Long) throws org.mobicents.protocols.ss7.map.api.MAPParsingComponentException;
    Code:
       0: aload_1
       1: ifnonnull     17
       4: new           #38                 // class org/mobicents/protocols/ss7/map/api/MAPParsingComponentException
       7: dup
       8: ldc           #55                 // String Error while decoding processActivateTraceModeRequest: Parameter is mandatory but not found
      10: getstatic     #56                 // Field org/mobicents/protocols/ss7/map/api/MAPParsingComponentExceptionReason.MistypedParameter:Lorg/mobicents/protocols/ss7/map/api/MAPParsingComponentExceptionReason;
      13: invokespecial #41                 // Method org/mobicents/protocols/ss7/map/api/MAPParsingComponentException."<init>":(Ljava/lang/String;Lorg/mobicents/protocols/ss7/map/api/MAPParsingComponentExceptionReason;)V
      16: athrow
      17: aload_1
      18: invokeinterface #57,  1           // InterfaceMethod org/mobicents/protocols/ss7/tcap/asn/comp/Parameter.getTag:()I
      23: bipush        16
      25: if_icmpne     46
      28: aload_1
      29: invokeinterface #58,  1           // InterfaceMethod org/mobicents/protocols/ss7/tcap/asn/comp/Parameter.getTagClass:()I
      34: ifne          46
      37: aload_1
      38: invokeinterface #59,  1           // InterfaceMethod org/mobicents/protocols/ss7/tcap/asn/comp/Parameter.isPrimitive:()Z
      43: ifeq          81
      46: new           #38                 // class org/mobicents/protocols/ss7/map/api/MAPParsingComponentException
      49: dup
      50: new           #49                 // class java/lang/StringBuilder
      53: dup
      54: invokespecial #50                 // Method java/lang/StringBuilder."<init>":()V
      57: ldc           #60                 // String Error while decoding processActivateTraceModeRequest: Bad tag or tagClass or parameter is primitive, received tag=
      59: invokevirtual #52                 // Method java/lang/StringBuilder.append:(Ljava/lang/String;)Ljava/lang/StringBuilder;
      62: aload_1
      63: invokeinterface #57,  1           // InterfaceMethod org/mobicents/protocols/ss7/tcap/asn/comp/Parameter.getTag:()I
      68: invokevirtual #53                 // Method java/lang/StringBuilder.append:(I)Ljava/lang/StringBuilder;
      71: invokevirtual #54                 // Method java/lang/StringBuilder.toString:()Ljava/lang/String;
      74: getstatic     #56                 // Field org/mobicents/protocols/ss7/map/api/MAPParsingComponentExceptionReason.MistypedParameter:Lorg/mobicents/protocols/ss7/map/api/MAPParsingComponentExceptionReason;
      77: invokespecial #41                 // Method org/mobicents/protocols/ss7/map/api/MAPParsingComponentException."<init>":(Ljava/lang/String;Lorg/mobicents/protocols/ss7/map/api/MAPParsingComponentExceptionReason;)V
      80: athrow
      81: aload_1
      82: invokeinterface #61,  1           // InterfaceMethod org/mobicents/protocols/ss7/tcap/asn/comp/Parameter.getData:()[B
      87: astore        4
      89: new           #62                 // class org/mobicents/protocols/asn/AsnInputStream
      92: dup
      93: aload         4
      95: invokespecial #63                 // Method org/mobicents/protocols/asn/AsnInputStream."<init>":([B)V
      98: astore        5
     100: new           #64                 // class org/mobicents/protocols/ss7/map/service/oam/ActivateTraceModeRequestImpl_Oam
     103: dup
     104: invokespecial #65                 // Method org/mobicents/protocols/ss7/map/service/oam/ActivateTraceModeRequestImpl_Oam."<init>":()V
     107: astore        6
     109: aload         6
     111: aload         5
     113: aload         4
     115: arraylength
     116: invokevirtual #66                 // Method org/mobicents/protocols/ss7/map/service/oam/ActivateTraceModeRequestImpl_Oam.decodeData:(Lorg/mobicents/protocols/asn/AsnInputStream;I)V
     119: aload         6
     121: aload_3
     122: invokevirtual #43                 // Method java/lang/Long.longValue:()J
     125: invokevirtual #67                 // Method org/mobicents/protocols/ss7/map/service/oam/ActivateTraceModeRequestImpl_Oam.setInvokeId:(J)V
     128: aload         6
     130: aload_2
     131: invokevirtual #68                 // Method org/mobicents/protocols/ss7/map/service/oam/ActivateTraceModeRequestImpl_Oam.setMAPDialog:(Lorg/mobicents/protocols/ss7/map/api/MAPDialog;)V
     134: aload_0
     135: getfield      #69                 // Field serviceListeners:Ljava/util/List;
     138: invokeinterface #70,  1           // InterfaceMethod java/util/List.iterator:()Ljava/util/Iterator;
     143: astore        7
     145: aload         7
     147: invokeinterface #71,  1           // InterfaceMethod java/util/Iterator.hasNext:()Z
     152: ifeq          228
     155: aload         7
     157: invokeinterface #72,  1           // InterfaceMethod java/util/Iterator.next:()Ljava/lang/Object;
     162: checkcast     #73                 // class org/mobicents/protocols/ss7/map/api/MAPServiceListener
     165: astore        8
     167: aload         8
     169: aload         6
     171: invokeinterface #74,  2           // InterfaceMethod org/mobicents/protocols/ss7/map/api/MAPServiceListener.onMAPMessage:(Lorg/mobicents/protocols/ss7/map/api/MAPMessage;)V
     176: aload         8
     178: checkcast     #75                 // class org/mobicents/protocols/ss7/map/api/service/oam/MAPServiceOamListener
     181: aload         6
     183: invokeinterface #76,  2           // InterfaceMethod org/mobicents/protocols/ss7/map/api/service/oam/MAPServiceOamListener.onActivateTraceModeRequest_Oam:(Lorg/mobicents/protocols/ss7/map/api/service/oam/ActivateTraceModeRequest_Oam;)V
     188: goto          225
     191: astore        9
     193: aload_0
     194: getfield      #4                  // Field loger:Lorg/apache/log4j/Logger;
     197: new           #49                 // class java/lang/StringBuilder
     200: dup
     201: invokespecial #50                 // Method java/lang/StringBuilder."<init>":()V
     204: ldc           #78                 // String Error processing processActivateTraceModeRequest:
     206: invokevirtual #52                 // Method java/lang/StringBuilder.append:(Ljava/lang/String;)Ljava/lang/StringBuilder;
     209: aload         9
     211: invokevirtual #79                 // Method java/lang/Exception.getMessage:()Ljava/lang/String;
     214: invokevirtual #52                 // Method java/lang/StringBuilder.append:(Ljava/lang/String;)Ljava/lang/StringBuilder;
     217: invokevirtual #54                 // Method java/lang/StringBuilder.toString:()Ljava/lang/String;
     220: aload         9
     222: invokevirtual #80                 // Method org/apache/log4j/Logger.error:(Ljava/lang/Object;Ljava/lang/Throwable;)V
     225: goto          145
     228: return
    Exception table:
       from    to  target type
         167   188   191   Class java/lang/Exception

  private void processActivateTraceModeResponse(org.mobicents.protocols.ss7.tcap.asn.comp.Parameter, org.mobicents.protocols.ss7.map.service.oam.MAPDialogOamImpl, java.lang.Long) throws org.mobicents.protocols.ss7.map.api.MAPParsingComponentException;
    Code:
       0: new           #81                 // class org/mobicents/protocols/ss7/map/service/oam/ActivateTraceModeResponseImpl_Oam
       3: dup
       4: invokespecial #82                 // Method org/mobicents/protocols/ss7/map/service/oam/ActivateTraceModeResponseImpl_Oam."<init>":()V
       7: astore        4
       9: aload_1
      10: ifnull        106
      13: aload_1
      14: invokeinterface #57,  1           // InterfaceMethod org/mobicents/protocols/ss7/tcap/asn/comp/Parameter.getTag:()I
      19: bipush        16
      21: if_icmpne     42
      24: aload_1
      25: invokeinterface #58,  1           // InterfaceMethod org/mobicents/protocols/ss7/tcap/asn/comp/Parameter.getTagClass:()I
      30: ifne          42
      33: aload_1
      34: invokeinterface #59,  1           // InterfaceMethod org/mobicents/protocols/ss7/tcap/asn/comp/Parameter.isPrimitive:()Z
      39: ifeq          77
      42: new           #38                 // class org/mobicents/protocols/ss7/map/api/MAPParsingComponentException
      45: dup
      46: new           #49                 // class java/lang/StringBuilder
      49: dup
      50: invokespecial #50                 // Method java/lang/StringBuilder."<init>":()V
      53: ldc           #83                 // String Error while decoding processActivateTraceModeResponse: Bad tag or tagClass or parameter is primitive, received tag=
      55: invokevirtual #52                 // Method java/lang/StringBuilder.append:(Ljava/lang/String;)Ljava/lang/StringBuilder;
      58: aload_1
      59: invokeinterface #57,  1           // InterfaceMethod org/mobicents/protocols/ss7/tcap/asn/comp/Parameter.getTag:()I
      64: invokevirtual #53                 // Method java/lang/StringBuilder.append:(I)Ljava/lang/StringBuilder;
      67: invokevirtual #54                 // Method java/lang/StringBuilder.toString:()Ljava/lang/String;
      70: getstatic     #56                 // Field org/mobicents/protocols/ss7/map/api/MAPParsingComponentExceptionReason.MistypedParameter:Lorg/mobicents/protocols/ss7/map/api/MAPParsingComponentExceptionReason;
      73: invokespecial #41                 // Method org/mobicents/protocols/ss7/map/api/MAPParsingComponentException."<init>":(Ljava/lang/String;Lorg/mobicents/protocols/ss7/map/api/MAPParsingComponentExceptionReason;)V
      76: athrow
      77: aload_1
      78: invokeinterface #61,  1           // InterfaceMethod org/mobicents/protocols/ss7/tcap/asn/comp/Parameter.getData:()[B
      83: astore        5
      85: new           #62                 // class org/mobicents/protocols/asn/AsnInputStream
      88: dup
      89: aload         5
      91: invokespecial #63                 // Method org/mobicents/protocols/asn/AsnInputStream."<init>":([B)V
      94: astore        6
      96: aload         4
      98: aload         6
     100: aload         5
     102: arraylength
     103: invokevirtual #84                 // Method org/mobicents/protocols/ss7/map/service/oam/ActivateTraceModeResponseImpl_Oam.decodeData:(Lorg/mobicents/protocols/asn/AsnInputStream;I)V
     106: aload         4
     108: aload_3
     109: invokevirtual #43                 // Method java/lang/Long.longValue:()J
     112: invokevirtual #85                 // Method org/mobicents/protocols/ss7/map/service/oam/ActivateTraceModeResponseImpl_Oam.setInvokeId:(J)V
     115: aload         4
     117: aload_2
     118: invokevirtual #86                 // Method org/mobicents/protocols/ss7/map/service/oam/ActivateTraceModeResponseImpl_Oam.setMAPDialog:(Lorg/mobicents/protocols/ss7/map/api/MAPDialog;)V
     121: aload_0
     122: getfield      #69                 // Field serviceListeners:Ljava/util/List;
     125: invokeinterface #70,  1           // InterfaceMethod java/util/List.iterator:()Ljava/util/Iterator;
     130: astore        5
     132: aload         5
     134: invokeinterface #71,  1           // InterfaceMethod java/util/Iterator.hasNext:()Z
     139: ifeq          206
     142: aload         5
     144: invokeinterface #72,  1           // InterfaceMethod java/util/Iterator.next:()Ljava/lang/Object;
     149: checkcast     #73                 // class org/mobicents/protocols/ss7/map/api/MAPServiceListener
     152: astore        6
     154: aload         6
     156: checkcast     #75                 // class org/mobicents/protocols/ss7/map/api/service/oam/MAPServiceOamListener
     159: aload         4
     161: invokeinterface #87,  2           // InterfaceMethod org/mobicents/protocols/ss7/map/api/service/oam/MAPServiceOamListener.onActivateTraceModeResponse_Oam:(Lorg/mobicents/protocols/ss7/map/api/service/oam/ActivateTraceModeResponse_Oam;)V
     166: goto          203
     169: astore        7
     171: aload_0
     172: getfield      #4                  // Field loger:Lorg/apache/log4j/Logger;
     175: new           #49                 // class java/lang/StringBuilder
     178: dup
     179: invokespecial #50                 // Method java/lang/StringBuilder."<init>":()V
     182: ldc           #88                 // String Error processing processActivateTraceModeResponse:
     184: invokevirtual #52                 // Method java/lang/StringBuilder.append:(Ljava/lang/String;)Ljava/lang/StringBuilder;
     187: aload         7
     189: invokevirtual #79                 // Method java/lang/Exception.getMessage:()Ljava/lang/String;
     192: invokevirtual #52                 // Method java/lang/StringBuilder.append:(Ljava/lang/String;)Ljava/lang/StringBuilder;
     195: invokevirtual #54                 // Method java/lang/StringBuilder.toString:()Ljava/lang/String;
     198: aload         7
     200: invokevirtual #80                 // Method org/apache/log4j/Logger.error:(Ljava/lang/Object;Ljava/lang/Throwable;)V
     203: goto          132
     206: return
    Exception table:
       from    to  target type
         154   166   169   Class java/lang/Exception

  private void processSendImsiRequest(org.mobicents.protocols.ss7.tcap.asn.comp.Parameter, org.mobicents.protocols.ss7.map.service.oam.MAPDialogOamImpl, java.lang.Long) throws org.mobicents.protocols.ss7.map.api.MAPParsingComponentException;
    Code:
       0: aload_1
       1: ifnonnull     17
       4: new           #38                 // class org/mobicents/protocols/ss7/map/api/MAPParsingComponentException
       7: dup
       8: ldc           #89                 // String Error while decoding processSendImsiRequest: Parameter is mandatory but not found
      10: getstatic     #56                 // Field org/mobicents/protocols/ss7/map/api/MAPParsingComponentExceptionReason.MistypedParameter:Lorg/mobicents/protocols/ss7/map/api/MAPParsingComponentExceptionReason;
      13: invokespecial #41                 // Method org/mobicents/protocols/ss7/map/api/MAPParsingComponentException."<init>":(Ljava/lang/String;Lorg/mobicents/protocols/ss7/map/api/MAPParsingComponentExceptionReason;)V
      16: athrow
      17: aload_1
      18: invokeinterface #57,  1           // InterfaceMethod org/mobicents/protocols/ss7/tcap/asn/comp/Parameter.getTag:()I
      23: iconst_4
      24: if_icmpne     45
      27: aload_1
      28: invokeinterface #58,  1           // InterfaceMethod org/mobicents/protocols/ss7/tcap/asn/comp/Parameter.getTagClass:()I
      33: ifne          45
      36: aload_1
      37: invokeinterface #59,  1           // InterfaceMethod org/mobicents/protocols/ss7/tcap/asn/comp/Parameter.isPrimitive:()Z
      42: ifne          80
      45: new           #38                 // class org/mobicents/protocols/ss7/map/api/MAPParsingComponentException
      48: dup
      49: new           #49                 // class java/lang/StringBuilder
      52: dup
      53: invokespecial #50                 // Method java/lang/StringBuilder."<init>":()V
      56: ldc           #90                 // String Error while decoding processSendImsiRequest: Bad tag or tagClass or parameter is not primitive, received tag=
      58: invokevirtual #52                 // Method java/lang/StringBuilder.append:(Ljava/lang/String;)Ljava/lang/StringBuilder;
      61: aload_1
      62: invokeinterface #57,  1           // InterfaceMethod org/mobicents/protocols/ss7/tcap/asn/comp/Parameter.getTag:()I
      67: invokevirtual #53                 // Method java/lang/StringBuilder.append:(I)Ljava/lang/StringBuilder;
      70: invokevirtual #54                 // Method java/lang/StringBuilder.toString:()Ljava/lang/String;
      73: getstatic     #56                 // Field org/mobicents/protocols/ss7/map/api/MAPParsingComponentExceptionReason.MistypedParameter:Lorg/mobicents/protocols/ss7/map/api/MAPParsingComponentExceptionReason;
      76: invokespecial #41                 // Method org/mobicents/protocols/ss7/map/api/MAPParsingComponentException."<init>":(Ljava/lang/String;Lorg/mobicents/protocols/ss7/map/api/MAPParsingComponentExceptionReason;)V
      79: athrow
      80: aload_1
      81: invokeinterface #61,  1           // InterfaceMethod org/mobicents/protocols/ss7/tcap/asn/comp/Parameter.getData:()[B
      86: astore        4
      88: new           #62                 // class org/mobicents/protocols/asn/AsnInputStream
      91: dup
      92: aload         4
      94: invokespecial #63                 // Method org/mobicents/protocols/asn/AsnInputStream."<init>":([B)V
      97: astore        5
      99: new           #91                 // class org/mobicents/protocols/ss7/map/service/oam/SendImsiRequestImpl
     102: dup
     103: invokespecial #92                 // Method org/mobicents/protocols/ss7/map/service/oam/SendImsiRequestImpl."<init>":()V
     106: astore        6
     108: aload         6
     110: aload         5
     112: aload         4
     114: arraylength
     115: invokevirtual #93                 // Method org/mobicents/protocols/ss7/map/service/oam/SendImsiRequestImpl.decodeData:(Lorg/mobicents/protocols/asn/AsnInputStream;I)V
     118: aload         6
     120: aload_3
     121: invokevirtual #43                 // Method java/lang/Long.longValue:()J
     124: invokevirtual #94                 // Method org/mobicents/protocols/ss7/map/service/oam/SendImsiRequestImpl.setInvokeId:(J)V
     127: aload         6
     129: aload_2
     130: invokevirtual #95                 // Method org/mobicents/protocols/ss7/map/service/oam/SendImsiRequestImpl.setMAPDialog:(Lorg/mobicents/protocols/ss7/map/api/MAPDialog;)V
     133: aload_0
     134: getfield      #69                 // Field serviceListeners:Ljava/util/List;
     137: invokeinterface #70,  1           // InterfaceMethod java/util/List.iterator:()Ljava/util/Iterator;
     142: astore        7
     144: aload         7
     146: invokeinterface #71,  1           // InterfaceMethod java/util/Iterator.hasNext:()Z
     151: ifeq          227
     154: aload         7
     156: invokeinterface #72,  1           // InterfaceMethod java/util/Iterator.next:()Ljava/lang/Object;
     161: checkcast     #73                 // class org/mobicents/protocols/ss7/map/api/MAPServiceListener
     164: astore        8
     166: aload         8
     168: aload         6
     170: invokeinterface #74,  2           // InterfaceMethod org/mobicents/protocols/ss7/map/api/MAPServiceListener.onMAPMessage:(Lorg/mobicents/protocols/ss7/map/api/MAPMessage;)V
     175: aload         8
     177: checkcast     #75                 // class org/mobicents/protocols/ss7/map/api/service/oam/MAPServiceOamListener
     180: aload         6
     182: invokeinterface #96,  2           // InterfaceMethod org/mobicents/protocols/ss7/map/api/service/oam/MAPServiceOamListener.onSendImsiRequest:(Lorg/mobicents/protocols/ss7/map/api/service/oam/SendImsiRequest;)V
     187: goto          224
     190: astore        9
     192: aload_0
     193: getfield      #4                  // Field loger:Lorg/apache/log4j/Logger;
     196: new           #49                 // class java/lang/StringBuilder
     199: dup
     200: invokespecial #50                 // Method java/lang/StringBuilder."<init>":()V
     203: ldc           #97                 // String Error processing processSendImsiRequest:
     205: invokevirtual #52                 // Method java/lang/StringBuilder.append:(Ljava/lang/String;)Ljava/lang/StringBuilder;
     208: aload         9
     210: invokevirtual #79                 // Method java/lang/Exception.getMessage:()Ljava/lang/String;
     213: invokevirtual #52                 // Method java/lang/StringBuilder.append:(Ljava/lang/String;)Ljava/lang/StringBuilder;
     216: invokevirtual #54                 // Method java/lang/StringBuilder.toString:()Ljava/lang/String;
     219: aload         9
     221: invokevirtual #80                 // Method org/apache/log4j/Logger.error:(Ljava/lang/Object;Ljava/lang/Throwable;)V
     224: goto          144
     227: return
    Exception table:
       from    to  target type
         166   187   190   Class java/lang/Exception

  private void processSendImsiResponse(org.mobicents.protocols.ss7.tcap.asn.comp.Parameter, org.mobicents.protocols.ss7.map.service.oam.MAPDialogOamImpl, java.lang.Long) throws org.mobicents.protocols.ss7.map.api.MAPParsingComponentException;
    Code:
       0: aload_1
       1: ifnonnull     17
       4: new           #38                 // class org/mobicents/protocols/ss7/map/api/MAPParsingComponentException
       7: dup
       8: ldc           #98                 // String Error while decoding processSendImsiResponse: Parameter is mandatory but not found
      10: getstatic     #56                 // Field org/mobicents/protocols/ss7/map/api/MAPParsingComponentExceptionReason.MistypedParameter:Lorg/mobicents/protocols/ss7/map/api/MAPParsingComponentExceptionReason;
      13: invokespecial #41                 // Method org/mobicents/protocols/ss7/map/api/MAPParsingComponentException."<init>":(Ljava/lang/String;Lorg/mobicents/protocols/ss7/map/api/MAPParsingComponentExceptionReason;)V
      16: athrow
      17: aload_1
      18: invokeinterface #57,  1           // InterfaceMethod org/mobicents/protocols/ss7/tcap/asn/comp/Parameter.getTag:()I
      23: iconst_4
      24: if_icmpne     45
      27: aload_1
      28: invokeinterface #58,  1           // InterfaceMethod org/mobicents/protocols/ss7/tcap/asn/comp/Parameter.getTagClass:()I
      33: ifne          45
      36: aload_1
      37: invokeinterface #59,  1           // InterfaceMethod org/mobicents/protocols/ss7/tcap/asn/comp/Parameter.isPrimitive:()Z
      42: ifne          80
      45: new           #38                 // class org/mobicents/protocols/ss7/map/api/MAPParsingComponentException
      48: dup
      49: new           #49                 // class java/lang/StringBuilder
      52: dup
      53: invokespecial #50                 // Method java/lang/StringBuilder."<init>":()V
      56: ldc           #99                 // String Error while decoding processSendImsiResponse: Bad tag or tagClass or parameter is not primitive, received tag=
      58: invokevirtual #52                 // Method java/lang/StringBuilder.append:(Ljava/lang/String;)Ljava/lang/StringBuilder;
      61: aload_1
      62: invokeinterface #57,  1           // InterfaceMethod org/mobicents/protocols/ss7/tcap/asn/comp/Parameter.getTag:()I
      67: invokevirtual #53                 // Method java/lang/StringBuilder.append:(I)Ljava/lang/StringBuilder;
      70: invokevirtual #54                 // Method java/lang/StringBuilder.toString:()Ljava/lang/String;
      73: getstatic     #56                 // Field org/mobicents/protocols/ss7/map/api/MAPParsingComponentExceptionReason.MistypedParameter:Lorg/mobicents/protocols/ss7/map/api/MAPParsingComponentExceptionReason;
      76: invokespecial #41                 // Method org/mobicents/protocols/ss7/map/api/MAPParsingComponentException."<init>":(Ljava/lang/String;Lorg/mobicents/protocols/ss7/map/api/MAPParsingComponentExceptionReason;)V
      79: athrow
      80: aload_1
      81: invokeinterface #61,  1           // InterfaceMethod org/mobicents/protocols/ss7/tcap/asn/comp/Parameter.getData:()[B
      86: astore        4
      88: new           #62                 // class org/mobicents/protocols/asn/AsnInputStream
      91: dup
      92: aload         4
      94: invokespecial #63                 // Method org/mobicents/protocols/asn/AsnInputStream."<init>":([B)V
      97: astore        5
      99: new           #100                // class org/mobicents/protocols/ss7/map/service/oam/SendImsiResponseImpl
     102: dup
     103: invokespecial #101                // Method org/mobicents/protocols/ss7/map/service/oam/SendImsiResponseImpl."<init>":()V
     106: astore        6
     108: aload         6
     110: aload         5
     112: aload         4
     114: arraylength
     115: invokevirtual #102                // Method org/mobicents/protocols/ss7/map/service/oam/SendImsiResponseImpl.decodeData:(Lorg/mobicents/protocols/asn/AsnInputStream;I)V
     118: aload         6
     120: aload_3
     121: invokevirtual #43                 // Method java/lang/Long.longValue:()J
     124: invokevirtual #103                // Method org/mobicents/protocols/ss7/map/service/oam/SendImsiResponseImpl.setInvokeId:(J)V
     127: aload         6
     129: aload_2
     130: invokevirtual #104                // Method org/mobicents/protocols/ss7/map/service/oam/SendImsiResponseImpl.setMAPDialog:(Lorg/mobicents/protocols/ss7/map/api/MAPDialog;)V
     133: aload_0
     134: getfield      #69                 // Field serviceListeners:Ljava/util/List;
     137: invokeinterface #70,  1           // InterfaceMethod java/util/List.iterator:()Ljava/util/Iterator;
     142: astore        7
     144: aload         7
     146: invokeinterface #71,  1           // InterfaceMethod java/util/Iterator.hasNext:()Z
     151: ifeq          227
     154: aload         7
     156: invokeinterface #72,  1           // InterfaceMethod java/util/Iterator.next:()Ljava/lang/Object;
     161: checkcast     #73                 // class org/mobicents/protocols/ss7/map/api/MAPServiceListener
     164: astore        8
     166: aload         8
     168: aload         6
     170: invokeinterface #74,  2           // InterfaceMethod org/mobicents/protocols/ss7/map/api/MAPServiceListener.onMAPMessage:(Lorg/mobicents/protocols/ss7/map/api/MAPMessage;)V
     175: aload         8
     177: checkcast     #75                 // class org/mobicents/protocols/ss7/map/api/service/oam/MAPServiceOamListener
     180: aload         6
     182: invokeinterface #105,  2          // InterfaceMethod org/mobicents/protocols/ss7/map/api/service/oam/MAPServiceOamListener.onSendImsiResponse:(Lorg/mobicents/protocols/ss7/map/api/service/oam/SendImsiResponse;)V
     187: goto          224
     190: astore        9
     192: aload_0
     193: getfield      #4                  // Field loger:Lorg/apache/log4j/Logger;
     196: new           #49                 // class java/lang/StringBuilder
     199: dup
     200: invokespecial #50                 // Method java/lang/StringBuilder."<init>":()V
     203: ldc           #106                // String Error processing processSendImsiResponse:
     205: invokevirtual #52                 // Method java/lang/StringBuilder.append:(Ljava/lang/String;)Ljava/lang/StringBuilder;
     208: aload         9
     210: invokevirtual #79                 // Method java/lang/Exception.getMessage:()Ljava/lang/String;
     213: invokevirtual #52                 // Method java/lang/StringBuilder.append:(Ljava/lang/String;)Ljava/lang/StringBuilder;
     216: invokevirtual #54                 // Method java/lang/StringBuilder.toString:()Ljava/lang/String;
     219: aload         9
     221: invokevirtual #80                 // Method org/apache/log4j/Logger.error:(Ljava/lang/Object;Ljava/lang/Throwable;)V
     224: goto          144
     227: return
    Exception table:
       from    to  target type
         166   187   190   Class java/lang/Exception

  public org.mobicents.protocols.ss7.map.api.MAPDialog createNewDialog(org.mobicents.protocols.ss7.map.api.MAPApplicationContext, org.mobicents.protocols.ss7.sccp.parameter.SccpAddress, org.mobicents.protocols.ss7.map.api.primitives.AddressString, org.mobicents.protocols.ss7.sccp.parameter.SccpAddress, org.mobicents.protocols.ss7.map.api.primitives.AddressString, java.lang.Long) throws org.mobicents.protocols.ss7.map.api.MAPException;
    Code:
       0: aload_0
       1: aload_1
       2: aload_2
       3: aload_3
       4: aload         4
       6: aload         5
       8: aload         6
      10: invokevirtual #5                  // Method createNewDialog:(Lorg/mobicents/protocols/ss7/map/api/MAPApplicationContext;Lorg/mobicents/protocols/ss7/sccp/parameter/SccpAddress;Lorg/mobicents/protocols/ss7/map/api/primitives/AddressString;Lorg/mobicents/protocols/ss7/sccp/parameter/SccpAddress;Lorg/mobicents/protocols/ss7/map/api/primitives/AddressString;Ljava/lang/Long;)Lorg/mobicents/protocols/ss7/map/api/service/oam/MAPDialogOam;
      13: areturn

  public org.mobicents.protocols.ss7.map.api.MAPDialog createNewDialog(org.mobicents.protocols.ss7.map.api.MAPApplicationContext, org.mobicents.protocols.ss7.sccp.parameter.SccpAddress, org.mobicents.protocols.ss7.map.api.primitives.AddressString, org.mobicents.protocols.ss7.sccp.parameter.SccpAddress, org.mobicents.protocols.ss7.map.api.primitives.AddressString) throws org.mobicents.protocols.ss7.map.api.MAPException;
    Code:
       0: aload_0
       1: aload_1
       2: aload_2
       3: aload_3
       4: aload         4
       6: aload         5
       8: invokevirtual #107                // Method createNewDialog:(Lorg/mobicents/protocols/ss7/map/api/MAPApplicationContext;Lorg/mobicents/protocols/ss7/sccp/parameter/SccpAddress;Lorg/mobicents/protocols/ss7/map/api/primitives/AddressString;Lorg/mobicents/protocols/ss7/sccp/parameter/SccpAddress;Lorg/mobicents/protocols/ss7/map/api/primitives/AddressString;)Lorg/mobicents/protocols/ss7/map/api/service/oam/MAPDialogOam;
      11: areturn
}
