Compiled from "ProtocolInfoProtos.java"
final class org.apache.hadoop.ipc.protobuf.ProtocolInfoProtos$ProtocolInfoService$1 extends org.apache.hadoop.ipc.protobuf.ProtocolInfoProtos$ProtocolInfoService {
  final org.apache.hadoop.ipc.protobuf.ProtocolInfoProtos$ProtocolInfoService$Interface val$impl;

  org.apache.hadoop.ipc.protobuf.ProtocolInfoProtos$ProtocolInfoService$1(org.apache.hadoop.ipc.protobuf.ProtocolInfoProtos$ProtocolInfoService$Interface);
    Code:
       0: aload_0
       1: aload_1
       2: putfield      #1                  // Field val$impl:Lorg/apache/hadoop/ipc/protobuf/ProtocolInfoProtos$ProtocolInfoService$Interface;
       5: aload_0
       6: invokespecial #2                  // Method org/apache/hadoop/ipc/protobuf/ProtocolInfoProtos$ProtocolInfoService."<init>":()V
       9: return

  public void getProtocolVersions(com.google.protobuf.RpcController, org.apache.hadoop.ipc.protobuf.ProtocolInfoProtos$GetProtocolVersionsRequestProto, com.google.protobuf.RpcCallback<org.apache.hadoop.ipc.protobuf.ProtocolInfoProtos$GetProtocolVersionsResponseProto>);
    Code:
       0: aload_0
       1: getfield      #1                  // Field val$impl:Lorg/apache/hadoop/ipc/protobuf/ProtocolInfoProtos$ProtocolInfoService$Interface;
       4: aload_1
       5: aload_2
       6: aload_3
       7: invokeinterface #3,  4            // InterfaceMethod org/apache/hadoop/ipc/protobuf/ProtocolInfoProtos$ProtocolInfoService$Interface.getProtocolVersions:(Lcom/google/protobuf/RpcController;Lorg/apache/hadoop/ipc/protobuf/ProtocolInfoProtos$GetProtocolVersionsRequestProto;Lcom/google/protobuf/RpcCallback;)V
      12: return

  public void getProtocolSignature(com.google.protobuf.RpcController, org.apache.hadoop.ipc.protobuf.ProtocolInfoProtos$GetProtocolSignatureRequestProto, com.google.protobuf.RpcCallback<org.apache.hadoop.ipc.protobuf.ProtocolInfoProtos$GetProtocolSignatureResponseProto>);
    Code:
       0: aload_0
       1: getfield      #1                  // Field val$impl:Lorg/apache/hadoop/ipc/protobuf/ProtocolInfoProtos$ProtocolInfoService$Interface;
       4: aload_1
       5: aload_2
       6: aload_3
       7: invokeinterface #4,  4            // InterfaceMethod org/apache/hadoop/ipc/protobuf/ProtocolInfoProtos$ProtocolInfoService$Interface.getProtocolSignature:(Lcom/google/protobuf/RpcController;Lorg/apache/hadoop/ipc/protobuf/ProtocolInfoProtos$GetProtocolSignatureRequestProto;Lcom/google/protobuf/RpcCallback;)V
      12: return
}
