Compiled from "BreakParsingException.java"
public class de.alpharogroup.xml.sax.handler.BreakParsingException extends java.lang.RuntimeException {
  private static final long serialVersionUID;

  public de.alpharogroup.xml.sax.handler.BreakParsingException();
    Code:
       0: aload_0
       1: invokespecial #1                  // Method java/lang/RuntimeException."<init>":()V
       4: return

  public de.alpharogroup.xml.sax.handler.BreakParsingException(java.lang.String);
    Code:
       0: aload_0
       1: aload_1
       2: invokespecial #2                  // Method java/lang/RuntimeException."<init>":(Ljava/lang/String;)V
       5: return

  public de.alpharogroup.xml.sax.handler.BreakParsingException(java.lang.String, java.lang.Throwable);
    Code:
       0: aload_0
       1: aload_1
       2: aload_2
       3: invokespecial #3                  // Method java/lang/RuntimeException."<init>":(Ljava/lang/String;Ljava/lang/Throwable;)V
       6: return

  public de.alpharogroup.xml.sax.handler.BreakParsingException(java.lang.Throwable);
    Code:
       0: aload_0
       1: aload_1
       2: invokespecial #4                  // Method java/lang/RuntimeException."<init>":(Ljava/lang/Throwable;)V
       5: return
}
