Compiled from "PrefixMapping.java"
public interface org.apache.jena.shared.PrefixMapping {
  public static final org.apache.jena.shared.PrefixMapping Standard;

  public static final org.apache.jena.shared.PrefixMapping Extended;

  public abstract org.apache.jena.shared.PrefixMapping setNsPrefix(java.lang.String, java.lang.String);

  public abstract org.apache.jena.shared.PrefixMapping removeNsPrefix(java.lang.String);

  public abstract org.apache.jena.shared.PrefixMapping clearNsPrefixMap();

  public abstract org.apache.jena.shared.PrefixMapping setNsPrefixes(org.apache.jena.shared.PrefixMapping);

  public abstract org.apache.jena.shared.PrefixMapping setNsPrefixes(java.util.Map<java.lang.String, java.lang.String>);

  public abstract org.apache.jena.shared.PrefixMapping withDefaultMappings(org.apache.jena.shared.PrefixMapping);

  public abstract java.lang.String getNsPrefixURI(java.lang.String);

  public abstract java.lang.String getNsURIPrefix(java.lang.String);

  public abstract java.util.Map<java.lang.String, java.lang.String> getNsPrefixMap();

  public abstract java.lang.String expandPrefix(java.lang.String);

  public abstract java.lang.String shortForm(java.lang.String);

  public abstract java.lang.String qnameFor(java.lang.String);

  public abstract org.apache.jena.shared.PrefixMapping lock();

  public default boolean hasNoMappings();
    Code:
       0: aload_0
       1: invokeinterface #1,  1            // InterfaceMethod numPrefixes:()I
       6: ifne          13
       9: iconst_1
      10: goto          14
      13: iconst_0
      14: ireturn

  public abstract int numPrefixes();

  public abstract boolean samePrefixMappingAs(org.apache.jena.shared.PrefixMapping);

  static {};
    Code:
       0: invokestatic  #2                  // Method org/apache/jena/shared/PrefixMapping$Factory.create:()Lorg/apache/jena/shared/PrefixMapping;
       3: ldc           #3                  // String rdfs
       5: invokestatic  #4                  // Method org/apache/jena/vocabulary/RDFS.getURI:()Ljava/lang/String;
       8: invokeinterface #5,  3            // InterfaceMethod setNsPrefix:(Ljava/lang/String;Ljava/lang/String;)Lorg/apache/jena/shared/PrefixMapping;
      13: ldc           #6                  // String rdf
      15: invokestatic  #7                  // Method org/apache/jena/vocabulary/RDF.getURI:()Ljava/lang/String;
      18: invokeinterface #5,  3            // InterfaceMethod setNsPrefix:(Ljava/lang/String;Ljava/lang/String;)Lorg/apache/jena/shared/PrefixMapping;
      23: ldc           #8                  // String dc
      25: invokestatic  #9                  // Method org/apache/jena/vocabulary/DC_11.getURI:()Ljava/lang/String;
      28: invokeinterface #5,  3            // InterfaceMethod setNsPrefix:(Ljava/lang/String;Ljava/lang/String;)Lorg/apache/jena/shared/PrefixMapping;
      33: ldc           #10                 // String owl
      35: invokestatic  #11                 // Method org/apache/jena/vocabulary/OWL.getURI:()Ljava/lang/String;
      38: invokeinterface #5,  3            // InterfaceMethod setNsPrefix:(Ljava/lang/String;Ljava/lang/String;)Lorg/apache/jena/shared/PrefixMapping;
      43: ldc           #12                 // String xsd
      45: invokestatic  #13                 // Method org/apache/jena/vocabulary/XSD.getURI:()Ljava/lang/String;
      48: invokeinterface #5,  3            // InterfaceMethod setNsPrefix:(Ljava/lang/String;Ljava/lang/String;)Lorg/apache/jena/shared/PrefixMapping;
      53: invokeinterface #14,  1           // InterfaceMethod lock:()Lorg/apache/jena/shared/PrefixMapping;
      58: putstatic     #15                 // Field Standard:Lorg/apache/jena/shared/PrefixMapping;
      61: invokestatic  #2                  // Method org/apache/jena/shared/PrefixMapping$Factory.create:()Lorg/apache/jena/shared/PrefixMapping;
      64: getstatic     #15                 // Field Standard:Lorg/apache/jena/shared/PrefixMapping;
      67: invokeinterface #16,  2           // InterfaceMethod setNsPrefixes:(Lorg/apache/jena/shared/PrefixMapping;)Lorg/apache/jena/shared/PrefixMapping;
      72: ldc           #17                 // String rss
      74: invokestatic  #18                 // Method org/apache/jena/vocabulary/RSS.getURI:()Ljava/lang/String;
      77: invokeinterface #5,  3            // InterfaceMethod setNsPrefix:(Ljava/lang/String;Ljava/lang/String;)Lorg/apache/jena/shared/PrefixMapping;
      82: ldc           #19                 // String vcard
      84: invokestatic  #20                 // Method org/apache/jena/vocabulary/VCARD.getURI:()Ljava/lang/String;
      87: invokeinterface #5,  3            // InterfaceMethod setNsPrefix:(Ljava/lang/String;Ljava/lang/String;)Lorg/apache/jena/shared/PrefixMapping;
      92: ldc           #21                 // String ja
      94: invokestatic  #22                 // Method org/apache/jena/assembler/JA.getURI:()Ljava/lang/String;
      97: invokeinterface #5,  3            // InterfaceMethod setNsPrefix:(Ljava/lang/String;Ljava/lang/String;)Lorg/apache/jena/shared/PrefixMapping;
     102: ldc           #23                 // String eg
     104: ldc           #24                 // String http://www.example.org/
     106: invokeinterface #5,  3            // InterfaceMethod setNsPrefix:(Ljava/lang/String;Ljava/lang/String;)Lorg/apache/jena/shared/PrefixMapping;
     111: invokeinterface #14,  1           // InterfaceMethod lock:()Lorg/apache/jena/shared/PrefixMapping;
     116: putstatic     #25                 // Field Extended:Lorg/apache/jena/shared/PrefixMapping;
     119: return
}
