Compiled from "ReadableIntervalConverter.java"
class org.joda.time.convert.ReadableIntervalConverter extends org.joda.time.convert.AbstractConverter implements org.joda.time.convert.IntervalConverter,org.joda.time.convert.DurationConverter,org.joda.time.convert.PeriodConverter {
  static final org.joda.time.convert.ReadableIntervalConverter INSTANCE;

  protected org.joda.time.convert.ReadableIntervalConverter();
    Code:
       0: aload_0
       1: invokespecial #1                  // Method org/joda/time/convert/AbstractConverter."<init>":()V
       4: return

  public long getDurationMillis(java.lang.Object);
    Code:
       0: aload_1
       1: checkcast     #2                  // class org/joda/time/ReadableInterval
       4: invokeinterface #3,  1            // InterfaceMethod org/joda/time/ReadableInterval.toDurationMillis:()J
       9: lreturn

  public void setInto(org.joda.time.ReadWritablePeriod, java.lang.Object, org.joda.time.Chronology);
    Code:
       0: aload_2
       1: checkcast     #2                  // class org/joda/time/ReadableInterval
       4: astore        4
       6: aload_3
       7: ifnull        14
      10: aload_3
      11: goto          19
      14: aload         4
      16: invokestatic  #4                  // Method org/joda/time/DateTimeUtils.getIntervalChronology:(Lorg/joda/time/ReadableInterval;)Lorg/joda/time/Chronology;
      19: astore_3
      20: aload         4
      22: invokeinterface #5,  1            // InterfaceMethod org/joda/time/ReadableInterval.getStartMillis:()J
      27: lstore        5
      29: aload         4
      31: invokeinterface #6,  1            // InterfaceMethod org/joda/time/ReadableInterval.getEndMillis:()J
      36: lstore        7
      38: aload_3
      39: aload_1
      40: lload         5
      42: lload         7
      44: invokevirtual #7                  // Method org/joda/time/Chronology.get:(Lorg/joda/time/ReadablePeriod;JJ)[I
      47: astore        9
      49: iconst_0
      50: istore        10
      52: iload         10
      54: aload         9
      56: arraylength
      57: if_icmpge     79
      60: aload_1
      61: iload         10
      63: aload         9
      65: iload         10
      67: iaload
      68: invokeinterface #8,  3            // InterfaceMethod org/joda/time/ReadWritablePeriod.setValue:(II)V
      73: iinc          10, 1
      76: goto          52
      79: return

  public boolean isReadableInterval(java.lang.Object, org.joda.time.Chronology);
    Code:
       0: iconst_1
       1: ireturn

  public void setInto(org.joda.time.ReadWritableInterval, java.lang.Object, org.joda.time.Chronology);
    Code:
       0: aload_2
       1: checkcast     #2                  // class org/joda/time/ReadableInterval
       4: astore        4
       6: aload_1
       7: aload         4
       9: invokeinterface #9,  2            // InterfaceMethod org/joda/time/ReadWritableInterval.setInterval:(Lorg/joda/time/ReadableInterval;)V
      14: aload_3
      15: ifnull        28
      18: aload_1
      19: aload_3
      20: invokeinterface #10,  2           // InterfaceMethod org/joda/time/ReadWritableInterval.setChronology:(Lorg/joda/time/Chronology;)V
      25: goto          41
      28: aload_1
      29: aload         4
      31: invokeinterface #11,  1           // InterfaceMethod org/joda/time/ReadableInterval.getChronology:()Lorg/joda/time/Chronology;
      36: invokeinterface #10,  2           // InterfaceMethod org/joda/time/ReadWritableInterval.setChronology:(Lorg/joda/time/Chronology;)V
      41: return

  public java.lang.Class<?> getSupportedType();
    Code:
       0: ldc_w         #2                  // class org/joda/time/ReadableInterval
       3: areturn

  static {};
    Code:
       0: new           #12                 // class org/joda/time/convert/ReadableIntervalConverter
       3: dup
       4: invokespecial #13                 // Method "<init>":()V
       7: putstatic     #14                 // Field INSTANCE:Lorg/joda/time/convert/ReadableIntervalConverter;
      10: return
}
