Compiled from "MpscCompoundQueue.java"
abstract class org.jctools.queues.MpscCompoundQueueColdFields<E> extends org.jctools.queues.MpscCompoundQueueL0Pad<E> {
  protected final int parallelQueues;

  protected final int parallelQueuesMask;

  protected final org.jctools.queues.MpscArrayQueue<E>[] queues;

  org.jctools.queues.MpscCompoundQueueColdFields(int, int);
    Code:
       0: aload_0
       1: invokespecial #1                  // Method org/jctools/queues/MpscCompoundQueueL0Pad."<init>":()V
       4: aload_0
       5: iload_2
       6: invokestatic  #2                  // Method org/jctools/util/Pow2.isPowerOfTwo:(I)Z
       9: ifeq          16
      12: iload_2
      13: goto          22
      16: iload_2
      17: invokestatic  #3                  // Method org/jctools/util/Pow2.roundToPowerOfTwo:(I)I
      20: iconst_2
      21: idiv
      22: putfield      #4                  // Field parallelQueues:I
      25: aload_0
      26: aload_0
      27: getfield      #4                  // Field parallelQueues:I
      30: iconst_1
      31: isub
      32: putfield      #5                  // Field parallelQueuesMask:I
      35: aload_0
      36: aload_0
      37: getfield      #4                  // Field parallelQueues:I
      40: anewarray     #6                  // class org/jctools/queues/MpscArrayQueue
      43: putfield      #7                  // Field queues:[Lorg/jctools/queues/MpscArrayQueue;
      46: iload_1
      47: invokestatic  #3                  // Method org/jctools/util/Pow2.roundToPowerOfTwo:(I)I
      50: istore_3
      51: iload_3
      52: aload_0
      53: getfield      #4                  // Field parallelQueues:I
      56: ldc           #8                  // String fullCapacity
      58: invokestatic  #9                  // Method org/jctools/util/RangeUtil.checkGreaterThanOrEqual:(IILjava/lang/String;)I
      61: pop
      62: iconst_0
      63: istore        4
      65: iload         4
      67: aload_0
      68: getfield      #4                  // Field parallelQueues:I
      71: if_icmpge     100
      74: aload_0
      75: getfield      #7                  // Field queues:[Lorg/jctools/queues/MpscArrayQueue;
      78: iload         4
      80: new           #6                  // class org/jctools/queues/MpscArrayQueue
      83: dup
      84: iload_3
      85: aload_0
      86: getfield      #4                  // Field parallelQueues:I
      89: idiv
      90: invokespecial #10                 // Method org/jctools/queues/MpscArrayQueue."<init>":(I)V
      93: aastore
      94: iinc          4, 1
      97: goto          65
     100: return
}
