Compiled from "CachedAuthenticatedSessionHandler.java"
public class io.undertow.servlet.handlers.security.CachedAuthenticatedSessionHandler implements io.undertow.server.HttpHandler {
  public static final java.lang.String ATTRIBUTE_NAME;

  public static final java.lang.String NO_ID_CHANGE_REQUIRED;

  private final io.undertow.security.api.NotificationReceiver NOTIFICATION_RECEIVER;

  private final io.undertow.security.api.AuthenticatedSessionManager SESSION_MANAGER;

  private final io.undertow.server.HttpHandler next;

  private final io.undertow.servlet.spec.ServletContextImpl servletContext;

  public io.undertow.servlet.handlers.security.CachedAuthenticatedSessionHandler(io.undertow.server.HttpHandler, io.undertow.servlet.spec.ServletContextImpl);
    Code:
       0: aload_0
       1: invokespecial #3                  // Method java/lang/Object."<init>":()V
       4: aload_0
       5: new           #4                  // class io/undertow/servlet/handlers/security/CachedAuthenticatedSessionHandler$SecurityNotificationReceiver
       8: dup
       9: aload_0
      10: aconst_null
      11: invokespecial #5                  // Method io/undertow/servlet/handlers/security/CachedAuthenticatedSessionHandler$SecurityNotificationReceiver."<init>":(Lio/undertow/servlet/handlers/security/CachedAuthenticatedSessionHandler;Lio/undertow/servlet/handlers/security/CachedAuthenticatedSessionHandler$1;)V
      14: putfield      #6                  // Field NOTIFICATION_RECEIVER:Lio/undertow/security/api/NotificationReceiver;
      17: aload_0
      18: new           #7                  // class io/undertow/servlet/handlers/security/CachedAuthenticatedSessionHandler$ServletAuthenticatedSessionManager
      21: dup
      22: aload_0
      23: aconst_null
      24: invokespecial #8                  // Method io/undertow/servlet/handlers/security/CachedAuthenticatedSessionHandler$ServletAuthenticatedSessionManager."<init>":(Lio/undertow/servlet/handlers/security/CachedAuthenticatedSessionHandler;Lio/undertow/servlet/handlers/security/CachedAuthenticatedSessionHandler$1;)V
      27: putfield      #9                  // Field SESSION_MANAGER:Lio/undertow/security/api/AuthenticatedSessionManager;
      30: aload_0
      31: aload_1
      32: putfield      #10                 // Field next:Lio/undertow/server/HttpHandler;
      35: aload_0
      36: aload_2
      37: putfield      #2                  // Field servletContext:Lio/undertow/servlet/spec/ServletContextImpl;
      40: return

  public void handleRequest(io.undertow.server.HttpServerExchange) throws java.lang.Exception;
    Code:
       0: aload_1
       1: invokevirtual #11                 // Method io/undertow/server/HttpServerExchange.getSecurityContext:()Lio/undertow/security/api/SecurityContext;
       4: astore_2
       5: aload_2
       6: aload_0
       7: getfield      #6                  // Field NOTIFICATION_RECEIVER:Lio/undertow/security/api/NotificationReceiver;
      10: invokeinterface #12,  2           // InterfaceMethod io/undertow/security/api/SecurityContext.registerNotificationReceiver:(Lio/undertow/security/api/NotificationReceiver;)V
      15: aload_0
      16: getfield      #2                  // Field servletContext:Lio/undertow/servlet/spec/ServletContextImpl;
      19: aload_1
      20: iconst_0
      21: invokevirtual #13                 // Method io/undertow/servlet/spec/ServletContextImpl.getSession:(Lio/undertow/server/HttpServerExchange;Z)Lio/undertow/servlet/spec/HttpSessionImpl;
      24: astore_3
      25: aload_3
      26: ifnull        46
      29: aload_1
      30: getstatic     #14                 // Field io/undertow/security/api/AuthenticatedSessionManager.ATTACHMENT_KEY:Lio/undertow/util/AttachmentKey;
      33: aload_0
      34: getfield      #9                  // Field SESSION_MANAGER:Lio/undertow/security/api/AuthenticatedSessionManager;
      37: invokevirtual #15                 // Method io/undertow/server/HttpServerExchange.putAttachment:(Lio/undertow/util/AttachmentKey;Ljava/lang/Object;)Ljava/lang/Object;
      40: pop
      41: aload_1
      42: aload_3
      43: invokestatic  #16                 // Method io/undertow/servlet/util/SavedRequest.tryRestoreRequest:(Lio/undertow/server/HttpServerExchange;Ljavax/servlet/http/HttpSession;)V
      46: aload_0
      47: getfield      #10                 // Field next:Lio/undertow/server/HttpHandler;
      50: aload_1
      51: invokeinterface #17,  2           // InterfaceMethod io/undertow/server/HttpHandler.handleRequest:(Lio/undertow/server/HttpServerExchange;)V
      56: return

  protected io.undertow.server.session.Session underlyingSession(io.undertow.servlet.spec.HttpSessionImpl);
    Code:
       0: invokestatic  #18                 // Method java/lang/System.getSecurityManager:()Ljava/lang/SecurityManager;
       3: ifnonnull     14
       6: aload_1
       7: invokevirtual #19                 // Method io/undertow/servlet/spec/HttpSessionImpl.getSession:()Lio/undertow/server/session/Session;
      10: astore_2
      11: goto          29
      14: new           #20                 // class io/undertow/servlet/spec/HttpSessionImpl$UnwrapSessionAction
      17: dup
      18: aload_1
      19: invokespecial #21                 // Method io/undertow/servlet/spec/HttpSessionImpl$UnwrapSessionAction."<init>":(Ljavax/servlet/http/HttpSession;)V
      22: invokestatic  #22                 // Method java/security/AccessController.doPrivileged:(Ljava/security/PrivilegedAction;)Ljava/lang/Object;
      25: checkcast     #23                 // class io/undertow/server/session/Session
      28: astore_2
      29: aload_2
      30: areturn

  private boolean isCacheable(io.undertow.security.api.SecurityNotification);
    Code:
       0: aload_1
       1: invokevirtual #24                 // Method io/undertow/security/api/SecurityNotification.isProgramatic:()Z
       4: ifne          14
       7: aload_1
       8: invokevirtual #25                 // Method io/undertow/security/api/SecurityNotification.isCachingRequired:()Z
      11: ifeq          18
      14: iconst_1
      15: goto          19
      18: iconst_0
      19: ireturn

  static io.undertow.servlet.spec.ServletContextImpl access$200(io.undertow.servlet.handlers.security.CachedAuthenticatedSessionHandler);
    Code:
       0: aload_0
       1: getfield      #2                  // Field servletContext:Lio/undertow/servlet/spec/ServletContextImpl;
       4: areturn

  static boolean access$300(io.undertow.servlet.handlers.security.CachedAuthenticatedSessionHandler, io.undertow.security.api.SecurityNotification);
    Code:
       0: aload_0
       1: aload_1
       2: invokespecial #1                  // Method isCacheable:(Lio/undertow/security/api/SecurityNotification;)Z
       5: ireturn

  static {};
    Code:
       0: new           #26                 // class java/lang/StringBuilder
       3: dup
       4: invokespecial #27                 // Method java/lang/StringBuilder."<init>":()V
       7: ldc           #28                 // class io/undertow/servlet/handlers/security/CachedAuthenticatedSessionHandler
       9: invokevirtual #29                 // Method java/lang/Class.getName:()Ljava/lang/String;
      12: invokevirtual #30                 // Method java/lang/StringBuilder.append:(Ljava/lang/String;)Ljava/lang/StringBuilder;
      15: ldc           #31                 // String .AuthenticatedSession
      17: invokevirtual #30                 // Method java/lang/StringBuilder.append:(Ljava/lang/String;)Ljava/lang/StringBuilder;
      20: invokevirtual #32                 // Method java/lang/StringBuilder.toString:()Ljava/lang/String;
      23: putstatic     #33                 // Field ATTRIBUTE_NAME:Ljava/lang/String;
      26: new           #26                 // class java/lang/StringBuilder
      29: dup
      30: invokespecial #27                 // Method java/lang/StringBuilder."<init>":()V
      33: ldc           #28                 // class io/undertow/servlet/handlers/security/CachedAuthenticatedSessionHandler
      35: invokevirtual #29                 // Method java/lang/Class.getName:()Ljava/lang/String;
      38: invokevirtual #30                 // Method java/lang/StringBuilder.append:(Ljava/lang/String;)Ljava/lang/StringBuilder;
      41: ldc           #34                 // String .NoIdChangeRequired
      43: invokevirtual #30                 // Method java/lang/StringBuilder.append:(Ljava/lang/String;)Ljava/lang/StringBuilder;
      46: invokevirtual #32                 // Method java/lang/StringBuilder.toString:()Ljava/lang/String;
      49: putstatic     #35                 // Field NO_ID_CHANGE_REQUIRED:Ljava/lang/String;
      52: return
}
