Compiled from "LatencyStats.java"
class org.LatencyUtils.LatencyStats$PauseTracker extends java.lang.ref.WeakReference<org.LatencyUtils.LatencyStats> implements org.LatencyUtils.PauseDetectorListener {
  final org.LatencyUtils.PauseDetector pauseDetector;

  org.LatencyUtils.LatencyStats$PauseTracker(org.LatencyUtils.PauseDetector, org.LatencyUtils.LatencyStats);
    Code:
       0: aload_0
       1: aload_2
       2: invokespecial #1                  // Method java/lang/ref/WeakReference."<init>":(Ljava/lang/Object;)V
       5: aload_0
       6: aload_1
       7: putfield      #2                  // Field pauseDetector:Lorg/LatencyUtils/PauseDetector;
      10: aload_1
      11: aload_0
      12: invokevirtual #3                  // Method org/LatencyUtils/PauseDetector.addListener:(Lorg/LatencyUtils/PauseDetectorListener;)V
      15: return

  public void stop();
    Code:
       0: aload_0
       1: getfield      #2                  // Field pauseDetector:Lorg/LatencyUtils/PauseDetector;
       4: aload_0
       5: invokevirtual #4                  // Method org/LatencyUtils/PauseDetector.removeListener:(Lorg/LatencyUtils/PauseDetectorListener;)V
       8: return

  public void handlePauseEvent(long, long);
    Code:
       0: aload_0
       1: invokevirtual #5                  // Method get:()Ljava/lang/Object;
       4: checkcast     #6                  // class org/LatencyUtils/LatencyStats
       7: astore        5
       9: aload         5
      11: ifnull        24
      14: aload         5
      16: lload_1
      17: lload_3
      18: invokestatic  #7                  // Method org/LatencyUtils/LatencyStats.access$600:(Lorg/LatencyUtils/LatencyStats;JJ)V
      21: goto          28
      24: aload_0
      25: invokevirtual #8                  // Method stop:()V
      28: return
}
