Compiled from "TimeServices.java"
class org.LatencyUtils.TimeServices$ScheduledExecutor$CompareRunnableTaskEntryByStartTime implements java.util.Comparator<org.LatencyUtils.TimeServices$ScheduledExecutor$RunnableTaskEntry> {
  org.LatencyUtils.TimeServices$ScheduledExecutor$CompareRunnableTaskEntryByStartTime();
    Code:
       0: aload_0
       1: invokespecial #1                  // Method java/lang/Object."<init>":()V
       4: return

  public int compare(org.LatencyUtils.TimeServices$ScheduledExecutor$RunnableTaskEntry, org.LatencyUtils.TimeServices$ScheduledExecutor$RunnableTaskEntry);
    Code:
       0: aload_1
       1: getfield      #2                  // Field org/LatencyUtils/TimeServices$ScheduledExecutor$RunnableTaskEntry.startTime:J
       4: lstore_3
       5: aload_2
       6: getfield      #2                  // Field org/LatencyUtils/TimeServices$ScheduledExecutor$RunnableTaskEntry.startTime:J
       9: lstore        5
      11: lload_3
      12: lload         5
      14: lcmp
      15: ifle          22
      18: iconst_1
      19: goto          34
      22: lload_3
      23: lload         5
      25: lcmp
      26: ifge          33
      29: iconst_m1
      30: goto          34
      33: iconst_0
      34: ireturn

  public int compare(java.lang.Object, java.lang.Object);
    Code:
       0: aload_0
       1: aload_1
       2: checkcast     #3                  // class org/LatencyUtils/TimeServices$ScheduledExecutor$RunnableTaskEntry
       5: aload_2
       6: checkcast     #3                  // class org/LatencyUtils/TimeServices$ScheduledExecutor$RunnableTaskEntry
       9: invokevirtual #4                  // Method compare:(Lorg/LatencyUtils/TimeServices$ScheduledExecutor$RunnableTaskEntry;Lorg/LatencyUtils/TimeServices$ScheduledExecutor$RunnableTaskEntry;)I
      12: ireturn
}
