Compiled from "DefaultPostLoadBeanValidationInterceptor.java"
public class info.archinnov.achilles.internals.interceptor.DefaultPostLoadBeanValidationInterceptor extends info.archinnov.achilles.internals.interceptor.DefaultPreMutateBeanValidationInterceptor {
  public info.archinnov.achilles.internals.interceptor.DefaultPostLoadBeanValidationInterceptor(javax.validation.Validator);
    Code:
       0: aload_0
       1: aload_1
       2: invokespecial #1                  // Method info/archinnov/achilles/internals/interceptor/DefaultPreMutateBeanValidationInterceptor."<init>":(Ljavax/validation/Validator;)V
       5: return

  public java.util.List<info.archinnov.achilles.type.interceptor.Event> interceptOnEvents();
    Code:
       0: iconst_1
       1: anewarray     #2                  // class info/archinnov/achilles/type/interceptor/Event
       4: dup
       5: iconst_0
       6: getstatic     #3                  // Field info/archinnov/achilles/type/interceptor/Event.POST_LOAD:Linfo/archinnov/achilles/type/interceptor/Event;
       9: aastore
      10: invokestatic  #4                  // Method java/util/Arrays.asList:([Ljava/lang/Object;)Ljava/util/List;
      13: areturn
}
