Compiled from "ClientBuilder.java"
public class org.sonatype.sisu.siesta.client.ClientBuilder {
  public org.sonatype.sisu.siesta.client.ClientBuilder();
    Code:
       0: aload_0
       1: invokespecial #1                  // Method java/lang/Object."<init>":()V
       4: return

  public static org.sonatype.sisu.siesta.client.ClientBuilder$Target using(com.sun.jersey.api.client.Client);
    Code:
       0: new           #2                  // class org/sonatype/sisu/siesta/client/ClientBuilder$Target
       3: dup
       4: aload_0
       5: invokespecial #3                  // Method org/sonatype/sisu/siesta/client/ClientBuilder$Target."<init>":(Lcom/sun/jersey/api/client/Client;)V
       8: areturn
}
