Compiled from "TypeDescription.java"
public class net.bytebuddy.description.type.TypeDescription$Generic$LazyProjection$OfConstructorParameter extends net.bytebuddy.description.type.TypeDescription$Generic$LazyProjection$WithEagerNavigation$OfAnnotatedElement {
  private final java.lang.reflect.Constructor<?> constructor;

  private final int index;

  private final java.lang.Class<?>[] erasure;

  public net.bytebuddy.description.type.TypeDescription$Generic$LazyProjection$OfConstructorParameter(java.lang.reflect.Constructor<?>, int, java.lang.Class<?>[]);
    Code:
       0: aload_0
       1: invokespecial #55                 // Method net/bytebuddy/description/type/TypeDescription$Generic$LazyProjection$WithEagerNavigation$OfAnnotatedElement."<init>":()V
       4: aload_0
       5: aload_1
       6: putfield      #57                 // Field constructor:Ljava/lang/reflect/Constructor;
       9: aload_0
      10: iload_2
      11: putfield      #59                 // Field index:I
      14: aload_0
      15: aload_3
      16: putfield      #61                 // Field erasure:[Ljava/lang/Class;
      19: return

  protected net.bytebuddy.description.type.TypeDescription$Generic resolve();
    Code:
       0: aload_0
       1: getfield      #57                 // Field constructor:Ljava/lang/reflect/Constructor;
       4: invokevirtual #71                 // Method java/lang/reflect/Constructor.getGenericParameterTypes:()[Ljava/lang/reflect/Type;
       7: astore_1
       8: aload_0
       9: getfield      #61                 // Field erasure:[Ljava/lang/Class;
      12: arraylength
      13: aload_1
      14: arraylength
      15: if_icmpne     34
      18: aload_1
      19: aload_0
      20: getfield      #59                 // Field index:I
      23: aaload
      24: aload_0
      25: invokevirtual #75                 // Method getAnnotationReader:()Lnet/bytebuddy/description/type/TypeDescription$Generic$AnnotationReader;
      28: invokestatic  #79                 // Method net/bytebuddy/description/type/TypeDefinition$Sort.describe:(Ljava/lang/reflect/Type;Lnet/bytebuddy/description/type/TypeDescription$Generic$AnnotationReader;)Lnet/bytebuddy/description/type/TypeDescription$Generic;
      31: goto          50
      34: new           #22                 // class net/bytebuddy/description/type/TypeDescription$Generic$OfNonGenericType$ForLoadedType
      37: dup
      38: aload_0
      39: getfield      #61                 // Field erasure:[Ljava/lang/Class;
      42: aload_0
      43: getfield      #59                 // Field index:I
      46: aaload
      47: invokespecial #84                 // Method net/bytebuddy/description/type/TypeDescription$Generic$OfNonGenericType$ForLoadedType."<init>":(Ljava/lang/Class;)V
      50: areturn

  public net.bytebuddy.description.type.TypeDescription asErasure();
    Code:
       0: new           #25                 // class net/bytebuddy/description/type/TypeDescription$ForLoadedType
       3: dup
       4: aload_0
       5: getfield      #61                 // Field erasure:[Ljava/lang/Class;
       8: aload_0
       9: getfield      #59                 // Field index:I
      12: aaload
      13: invokespecial #88                 // Method net/bytebuddy/description/type/TypeDescription$ForLoadedType."<init>":(Ljava/lang/Class;)V
      16: areturn

  protected net.bytebuddy.description.type.TypeDescription$Generic$AnnotationReader getAnnotationReader();
    Code:
       0: getstatic     #92                 // Field net/bytebuddy/description/type/TypeDescription$Generic$AnnotationReader.DISPATCHER:Lnet/bytebuddy/description/type/TypeDescription$Generic$AnnotationReader$Dispatcher;
       3: aload_0
       4: getfield      #57                 // Field constructor:Ljava/lang/reflect/Constructor;
       7: aload_0
       8: getfield      #59                 // Field index:I
      11: invokeinterface #96,  3           // InterfaceMethod net/bytebuddy/description/type/TypeDescription$Generic$AnnotationReader$Dispatcher.resolveParameterType:(Ljava/lang/reflect/AccessibleObject;I)Lnet/bytebuddy/description/type/TypeDescription$Generic$AnnotationReader;
      16: areturn

  public net.bytebuddy.description.annotation.AnnotationList getDeclaredAnnotations();
    Code:
       0: aload_0
       1: invokespecial #100                // Method net/bytebuddy/description/type/TypeDescription$Generic$LazyProjection$WithEagerNavigation$OfAnnotatedElement.getDeclaredAnnotations:()Lnet/bytebuddy/description/annotation/AnnotationList;
       4: areturn
}
