Compiled from "TypeDescription.java"
public class net.bytebuddy.description.type.TypeDescription$Generic$AnnotationReader$Dispatcher$ForJava8CapableVm implements net.bytebuddy.description.type.TypeDescription$Generic$AnnotationReader$Dispatcher {
  private final java.lang.reflect.Method getAnnotatedSuperclass;

  private final java.lang.reflect.Method getAnnotatedInterfaces;

  private final java.lang.reflect.Method getAnnotatedType;

  private final java.lang.reflect.Method getAnnotatedReturnType;

  private final java.lang.reflect.Method getAnnotatedParameterTypes;

  private final java.lang.reflect.Method getAnnotatedExceptionTypes;

  private final java.lang.reflect.Method getAnnotatedReceiverType;

  private final java.lang.reflect.Method getType;

  protected net.bytebuddy.description.type.TypeDescription$Generic$AnnotationReader$Dispatcher$ForJava8CapableVm(java.lang.reflect.Method, java.lang.reflect.Method, java.lang.reflect.Method, java.lang.reflect.Method, java.lang.reflect.Method, java.lang.reflect.Method, java.lang.reflect.Method, java.lang.reflect.Method);
    Code:
       0: aload_0
       1: invokespecial #60                 // Method java/lang/Object."<init>":()V
       4: aload_0
       5: aload_1
       6: putfield      #62                 // Field getAnnotatedSuperclass:Ljava/lang/reflect/Method;
       9: aload_0
      10: aload_2
      11: putfield      #64                 // Field getAnnotatedInterfaces:Ljava/lang/reflect/Method;
      14: aload_0
      15: aload_3
      16: putfield      #66                 // Field getAnnotatedType:Ljava/lang/reflect/Method;
      19: aload_0
      20: aload         4
      22: putfield      #68                 // Field getAnnotatedReturnType:Ljava/lang/reflect/Method;
      25: aload_0
      26: aload         5
      28: putfield      #70                 // Field getAnnotatedParameterTypes:Ljava/lang/reflect/Method;
      31: aload_0
      32: aload         6
      34: putfield      #72                 // Field getAnnotatedExceptionTypes:Ljava/lang/reflect/Method;
      37: aload_0
      38: aload         7
      40: putfield      #74                 // Field getAnnotatedReceiverType:Ljava/lang/reflect/Method;
      43: aload_0
      44: aload         8
      46: putfield      #76                 // Field getType:Ljava/lang/reflect/Method;
      49: return

  public net.bytebuddy.description.type.TypeDescription$Generic$AnnotationReader resolveTypeVariable(java.lang.reflect.TypeVariable<?>);
    Code:
       0: new           #37                 // class net/bytebuddy/description/type/TypeDescription$Generic$AnnotationReader$Dispatcher$ForJava8CapableVm$AnnotatedTypeVariableType
       3: dup
       4: aload_1
       5: invokespecial #83                 // Method net/bytebuddy/description/type/TypeDescription$Generic$AnnotationReader$Dispatcher$ForJava8CapableVm$AnnotatedTypeVariableType."<init>":(Ljava/lang/reflect/TypeVariable;)V
       8: areturn

  public net.bytebuddy.description.type.TypeDescription$Generic$AnnotationReader resolveSuperClassType(java.lang.Class<?>);
    Code:
       0: new           #34                 // class net/bytebuddy/description/type/TypeDescription$Generic$AnnotationReader$Dispatcher$ForJava8CapableVm$AnnotatedSuperClass
       3: dup
       4: aload_0
       5: aload_1
       6: invokespecial #91                 // Method net/bytebuddy/description/type/TypeDescription$Generic$AnnotationReader$Dispatcher$ForJava8CapableVm$AnnotatedSuperClass."<init>":(Lnet/bytebuddy/description/type/TypeDescription$Generic$AnnotationReader$Dispatcher$ForJava8CapableVm;Ljava/lang/Class;)V
       9: areturn

  public net.bytebuddy.description.type.TypeDescription$Generic$AnnotationReader resolveInterfaceType(java.lang.Class<?>, int);
    Code:
       0: new           #31                 // class net/bytebuddy/description/type/TypeDescription$Generic$AnnotationReader$Dispatcher$ForJava8CapableVm$AnnotatedInterfaceType
       3: dup
       4: aload_0
       5: aload_1
       6: iload_2
       7: invokespecial #99                 // Method net/bytebuddy/description/type/TypeDescription$Generic$AnnotationReader$Dispatcher$ForJava8CapableVm$AnnotatedInterfaceType."<init>":(Lnet/bytebuddy/description/type/TypeDescription$Generic$AnnotationReader$Dispatcher$ForJava8CapableVm;Ljava/lang/Class;I)V
      10: areturn

  public net.bytebuddy.description.type.TypeDescription$Generic$AnnotationReader resolveFieldType(java.lang.reflect.Field);
    Code:
       0: new           #28                 // class net/bytebuddy/description/type/TypeDescription$Generic$AnnotationReader$Dispatcher$ForJava8CapableVm$AnnotatedFieldType
       3: dup
       4: aload_0
       5: aload_1
       6: invokespecial #106                // Method net/bytebuddy/description/type/TypeDescription$Generic$AnnotationReader$Dispatcher$ForJava8CapableVm$AnnotatedFieldType."<init>":(Lnet/bytebuddy/description/type/TypeDescription$Generic$AnnotationReader$Dispatcher$ForJava8CapableVm;Ljava/lang/reflect/Field;)V
       9: areturn

  public net.bytebuddy.description.type.TypeDescription$Generic$AnnotationReader resolveReturnType(java.lang.reflect.Method);
    Code:
       0: new           #25                 // class net/bytebuddy/description/type/TypeDescription$Generic$AnnotationReader$Dispatcher$ForJava8CapableVm$AnnotatedReturnType
       3: dup
       4: aload_0
       5: aload_1
       6: invokespecial #113                // Method net/bytebuddy/description/type/TypeDescription$Generic$AnnotationReader$Dispatcher$ForJava8CapableVm$AnnotatedReturnType."<init>":(Lnet/bytebuddy/description/type/TypeDescription$Generic$AnnotationReader$Dispatcher$ForJava8CapableVm;Ljava/lang/reflect/Method;)V
       9: areturn

  public net.bytebuddy.description.type.TypeDescription$Generic$AnnotationReader resolveParameterType(java.lang.reflect.AccessibleObject, int);
    Code:
       0: new           #22                 // class net/bytebuddy/description/type/TypeDescription$Generic$AnnotationReader$Dispatcher$ForJava8CapableVm$AnnotatedParameterizedType
       3: dup
       4: aload_0
       5: aload_1
       6: iload_2
       7: invokespecial #119                // Method net/bytebuddy/description/type/TypeDescription$Generic$AnnotationReader$Dispatcher$ForJava8CapableVm$AnnotatedParameterizedType."<init>":(Lnet/bytebuddy/description/type/TypeDescription$Generic$AnnotationReader$Dispatcher$ForJava8CapableVm;Ljava/lang/reflect/AccessibleObject;I)V
      10: areturn

  public net.bytebuddy.description.type.TypeDescription$Generic$AnnotationReader resolveExceptionType(java.lang.reflect.AccessibleObject, int);
    Code:
       0: new           #19                 // class net/bytebuddy/description/type/TypeDescription$Generic$AnnotationReader$Dispatcher$ForJava8CapableVm$AnnotatedExceptionType
       3: dup
       4: aload_0
       5: aload_1
       6: iload_2
       7: invokespecial #123                // Method net/bytebuddy/description/type/TypeDescription$Generic$AnnotationReader$Dispatcher$ForJava8CapableVm$AnnotatedExceptionType."<init>":(Lnet/bytebuddy/description/type/TypeDescription$Generic$AnnotationReader$Dispatcher$ForJava8CapableVm;Ljava/lang/reflect/AccessibleObject;I)V
      10: areturn

  public net.bytebuddy.description.type.TypeDescription$Generic resolveReceiverType(java.lang.reflect.AccessibleObject);
    Code:
       0: aload_0
       1: aload_0
       2: getfield      #74                 // Field getAnnotatedReceiverType:Ljava/lang/reflect/Method;
       5: aload_1
       6: iconst_0
       7: anewarray     #4                  // class java/lang/Object
      10: invokevirtual #135                // Method java/lang/reflect/Method.invoke:(Ljava/lang/Object;[Ljava/lang/Object;)Ljava/lang/Object;
      13: checkcast     #137                // class java/lang/reflect/AnnotatedElement
      16: invokevirtual #141                // Method resolve:(Ljava/lang/reflect/AnnotatedElement;)Lnet/bytebuddy/description/type/TypeDescription$Generic;
      19: areturn
      20: astore_2
      21: new           #143                // class java/lang/IllegalStateException
      24: dup
      25: ldc           #145                // String Cannot access java.lang.reflect.Executable#getAnnotatedReceiverType
      27: aload_2
      28: invokespecial #148                // Method java/lang/IllegalStateException."<init>":(Ljava/lang/String;Ljava/lang/Throwable;)V
      31: athrow
      32: astore_2
      33: new           #143                // class java/lang/IllegalStateException
      36: dup
      37: ldc           #150                // String Error invoking java.lang.reflect.Executable#getAnnotatedReceiverType
      39: aload_2
      40: invokevirtual #154                // Method java/lang/reflect/InvocationTargetException.getCause:()Ljava/lang/Throwable;
      43: invokespecial #148                // Method java/lang/IllegalStateException."<init>":(Ljava/lang/String;Ljava/lang/Throwable;)V
      46: athrow
    Exception table:
       from    to  target type
           0    19    20   Class java/lang/IllegalAccessException
           0    19    32   Class java/lang/reflect/InvocationTargetException

  public net.bytebuddy.description.type.TypeDescription$Generic resolve(java.lang.reflect.AnnotatedElement);
    Code:
       0: aload_1
       1: ifnonnull     10
       4: getstatic     #161                // Field net/bytebuddy/description/type/TypeDescription$Generic.UNDEFINED:Lnet/bytebuddy/description/type/TypeDescription$Generic;
       7: goto          36
      10: aload_0
      11: getfield      #76                 // Field getType:Ljava/lang/reflect/Method;
      14: aload_1
      15: iconst_0
      16: anewarray     #4                  // class java/lang/Object
      19: invokevirtual #135                // Method java/lang/reflect/Method.invoke:(Ljava/lang/Object;[Ljava/lang/Object;)Ljava/lang/Object;
      22: checkcast     #163                // class java/lang/reflect/Type
      25: new           #40                 // class net/bytebuddy/description/type/TypeDescription$Generic$AnnotationReader$Dispatcher$ForJava8CapableVm$Resolved
      28: dup
      29: aload_1
      30: invokespecial #166                // Method net/bytebuddy/description/type/TypeDescription$Generic$AnnotationReader$Dispatcher$ForJava8CapableVm$Resolved."<init>":(Ljava/lang/reflect/AnnotatedElement;)V
      33: invokestatic  #170                // Method net/bytebuddy/description/type/TypeDefinition$Sort.describe:(Ljava/lang/reflect/Type;Lnet/bytebuddy/description/type/TypeDescription$Generic$AnnotationReader;)Lnet/bytebuddy/description/type/TypeDescription$Generic;
      36: areturn
      37: astore_2
      38: new           #143                // class java/lang/IllegalStateException
      41: dup
      42: ldc           #172                // String Cannot access java.lang.reflect.AnnotatedType#getType
      44: aload_2
      45: invokespecial #148                // Method java/lang/IllegalStateException."<init>":(Ljava/lang/String;Ljava/lang/Throwable;)V
      48: athrow
      49: astore_2
      50: new           #143                // class java/lang/IllegalStateException
      53: dup
      54: ldc           #174                // String Error invoking java.lang.reflect.AnnotatedType#getType
      56: aload_2
      57: invokevirtual #154                // Method java/lang/reflect/InvocationTargetException.getCause:()Ljava/lang/Throwable;
      60: invokespecial #148                // Method java/lang/IllegalStateException."<init>":(Ljava/lang/String;Ljava/lang/Throwable;)V
      63: athrow
    Exception table:
       from    to  target type
           0    36    37   Class java/lang/IllegalAccessException
           0    36    49   Class java/lang/reflect/InvocationTargetException

  public boolean equals(java.lang.Object);
    Code:
       0: aload_1
       1: aload_0
       2: if_acmpne     7
       5: iconst_1
       6: ireturn
       7: aload_1
       8: instanceof    #2                  // class net/bytebuddy/description/type/TypeDescription$Generic$AnnotationReader$Dispatcher$ForJava8CapableVm
      11: ifne          16
      14: iconst_0
      15: ireturn
      16: aload_1
      17: checkcast     #2                  // class net/bytebuddy/description/type/TypeDescription$Generic$AnnotationReader$Dispatcher$ForJava8CapableVm
      20: astore_2
      21: aload_2
      22: aload_0
      23: invokevirtual #181                // Method canEqual:(Ljava/lang/Object;)Z
      26: ifne          31
      29: iconst_0
      30: ireturn
      31: aload_0
      32: getfield      #62                 // Field getAnnotatedSuperclass:Ljava/lang/reflect/Method;
      35: astore_3
      36: aload_2
      37: getfield      #62                 // Field getAnnotatedSuperclass:Ljava/lang/reflect/Method;
      40: astore        4
      42: aload_3
      43: ifnonnull     54
      46: aload         4
      48: ifnull        65
      51: goto          63
      54: aload_3
      55: aload         4
      57: invokevirtual #183                // Method java/lang/Object.equals:(Ljava/lang/Object;)Z
      60: ifne          65
      63: iconst_0
      64: ireturn
      65: aload_0
      66: getfield      #64                 // Field getAnnotatedInterfaces:Ljava/lang/reflect/Method;
      69: astore        5
      71: aload_2
      72: getfield      #64                 // Field getAnnotatedInterfaces:Ljava/lang/reflect/Method;
      75: astore        6
      77: aload         5
      79: ifnonnull     90
      82: aload         6
      84: ifnull        102
      87: goto          100
      90: aload         5
      92: aload         6
      94: invokevirtual #183                // Method java/lang/Object.equals:(Ljava/lang/Object;)Z
      97: ifne          102
     100: iconst_0
     101: ireturn
     102: aload_0
     103: getfield      #66                 // Field getAnnotatedType:Ljava/lang/reflect/Method;
     106: astore        7
     108: aload_2
     109: getfield      #66                 // Field getAnnotatedType:Ljava/lang/reflect/Method;
     112: astore        8
     114: aload         7
     116: ifnonnull     127
     119: aload         8
     121: ifnull        139
     124: goto          137
     127: aload         7
     129: aload         8
     131: invokevirtual #183                // Method java/lang/Object.equals:(Ljava/lang/Object;)Z
     134: ifne          139
     137: iconst_0
     138: ireturn
     139: aload_0
     140: getfield      #68                 // Field getAnnotatedReturnType:Ljava/lang/reflect/Method;
     143: astore        9
     145: aload_2
     146: getfield      #68                 // Field getAnnotatedReturnType:Ljava/lang/reflect/Method;
     149: astore        10
     151: aload         9
     153: ifnonnull     164
     156: aload         10
     158: ifnull        176
     161: goto          174
     164: aload         9
     166: aload         10
     168: invokevirtual #183                // Method java/lang/Object.equals:(Ljava/lang/Object;)Z
     171: ifne          176
     174: iconst_0
     175: ireturn
     176: aload_0
     177: getfield      #70                 // Field getAnnotatedParameterTypes:Ljava/lang/reflect/Method;
     180: astore        11
     182: aload_2
     183: getfield      #70                 // Field getAnnotatedParameterTypes:Ljava/lang/reflect/Method;
     186: astore        12
     188: aload         11
     190: ifnonnull     201
     193: aload         12
     195: ifnull        213
     198: goto          211
     201: aload         11
     203: aload         12
     205: invokevirtual #183                // Method java/lang/Object.equals:(Ljava/lang/Object;)Z
     208: ifne          213
     211: iconst_0
     212: ireturn
     213: aload_0
     214: getfield      #72                 // Field getAnnotatedExceptionTypes:Ljava/lang/reflect/Method;
     217: astore        13
     219: aload_2
     220: getfield      #72                 // Field getAnnotatedExceptionTypes:Ljava/lang/reflect/Method;
     223: astore        14
     225: aload         13
     227: ifnonnull     238
     230: aload         14
     232: ifnull        250
     235: goto          248
     238: aload         13
     240: aload         14
     242: invokevirtual #183                // Method java/lang/Object.equals:(Ljava/lang/Object;)Z
     245: ifne          250
     248: iconst_0
     249: ireturn
     250: aload_0
     251: getfield      #74                 // Field getAnnotatedReceiverType:Ljava/lang/reflect/Method;
     254: astore        15
     256: aload_2
     257: getfield      #74                 // Field getAnnotatedReceiverType:Ljava/lang/reflect/Method;
     260: astore        16
     262: aload         15
     264: ifnonnull     275
     267: aload         16
     269: ifnull        287
     272: goto          285
     275: aload         15
     277: aload         16
     279: invokevirtual #183                // Method java/lang/Object.equals:(Ljava/lang/Object;)Z
     282: ifne          287
     285: iconst_0
     286: ireturn
     287: aload_0
     288: getfield      #76                 // Field getType:Ljava/lang/reflect/Method;
     291: astore        17
     293: aload_2
     294: getfield      #76                 // Field getType:Ljava/lang/reflect/Method;
     297: astore        18
     299: aload         17
     301: ifnonnull     312
     304: aload         18
     306: ifnull        324
     309: goto          322
     312: aload         17
     314: aload         18
     316: invokevirtual #183                // Method java/lang/Object.equals:(Ljava/lang/Object;)Z
     319: ifne          324
     322: iconst_0
     323: ireturn
     324: iconst_1
     325: ireturn

  protected boolean canEqual(java.lang.Object);
    Code:
       0: aload_1
       1: instanceof    #2                  // class net/bytebuddy/description/type/TypeDescription$Generic$AnnotationReader$Dispatcher$ForJava8CapableVm
       4: ireturn

  public int hashCode();
    Code:
       0: bipush        59
       2: istore_1
       3: iconst_1
       4: istore_2
       5: aload_0
       6: getfield      #62                 // Field getAnnotatedSuperclass:Ljava/lang/reflect/Method;
       9: astore_3
      10: iload_2
      11: bipush        59
      13: imul
      14: aload_3
      15: ifnonnull     23
      18: bipush        43
      20: goto          27
      23: aload_3
      24: invokevirtual #206                // Method java/lang/Object.hashCode:()I
      27: iadd
      28: istore_2
      29: aload_0
      30: getfield      #64                 // Field getAnnotatedInterfaces:Ljava/lang/reflect/Method;
      33: astore        4
      35: iload_2
      36: bipush        59
      38: imul
      39: aload         4
      41: ifnonnull     49
      44: bipush        43
      46: goto          54
      49: aload         4
      51: invokevirtual #206                // Method java/lang/Object.hashCode:()I
      54: iadd
      55: istore_2
      56: aload_0
      57: getfield      #66                 // Field getAnnotatedType:Ljava/lang/reflect/Method;
      60: astore        5
      62: iload_2
      63: bipush        59
      65: imul
      66: aload         5
      68: ifnonnull     76
      71: bipush        43
      73: goto          81
      76: aload         5
      78: invokevirtual #206                // Method java/lang/Object.hashCode:()I
      81: iadd
      82: istore_2
      83: aload_0
      84: getfield      #68                 // Field getAnnotatedReturnType:Ljava/lang/reflect/Method;
      87: astore        6
      89: iload_2
      90: bipush        59
      92: imul
      93: aload         6
      95: ifnonnull     103
      98: bipush        43
     100: goto          108
     103: aload         6
     105: invokevirtual #206                // Method java/lang/Object.hashCode:()I
     108: iadd
     109: istore_2
     110: aload_0
     111: getfield      #70                 // Field getAnnotatedParameterTypes:Ljava/lang/reflect/Method;
     114: astore        7
     116: iload_2
     117: bipush        59
     119: imul
     120: aload         7
     122: ifnonnull     130
     125: bipush        43
     127: goto          135
     130: aload         7
     132: invokevirtual #206                // Method java/lang/Object.hashCode:()I
     135: iadd
     136: istore_2
     137: aload_0
     138: getfield      #72                 // Field getAnnotatedExceptionTypes:Ljava/lang/reflect/Method;
     141: astore        8
     143: iload_2
     144: bipush        59
     146: imul
     147: aload         8
     149: ifnonnull     157
     152: bipush        43
     154: goto          162
     157: aload         8
     159: invokevirtual #206                // Method java/lang/Object.hashCode:()I
     162: iadd
     163: istore_2
     164: aload_0
     165: getfield      #74                 // Field getAnnotatedReceiverType:Ljava/lang/reflect/Method;
     168: astore        9
     170: iload_2
     171: bipush        59
     173: imul
     174: aload         9
     176: ifnonnull     184
     179: bipush        43
     181: goto          189
     184: aload         9
     186: invokevirtual #206                // Method java/lang/Object.hashCode:()I
     189: iadd
     190: istore_2
     191: aload_0
     192: getfield      #76                 // Field getType:Ljava/lang/reflect/Method;
     195: astore        10
     197: iload_2
     198: bipush        59
     200: imul
     201: aload         10
     203: ifnonnull     211
     206: bipush        43
     208: goto          216
     211: aload         10
     213: invokevirtual #206                // Method java/lang/Object.hashCode:()I
     216: iadd
     217: istore_2
     218: iload_2
     219: ireturn

  static java.lang.reflect.Method access$300(net.bytebuddy.description.type.TypeDescription$Generic$AnnotationReader$Dispatcher$ForJava8CapableVm);
    Code:
       0: aload_0
       1: getfield      #62                 // Field getAnnotatedSuperclass:Ljava/lang/reflect/Method;
       4: areturn

  static java.lang.reflect.Method access$400(net.bytebuddy.description.type.TypeDescription$Generic$AnnotationReader$Dispatcher$ForJava8CapableVm);
    Code:
       0: aload_0
       1: getfield      #64                 // Field getAnnotatedInterfaces:Ljava/lang/reflect/Method;
       4: areturn

  static java.lang.reflect.Method access$500(net.bytebuddy.description.type.TypeDescription$Generic$AnnotationReader$Dispatcher$ForJava8CapableVm);
    Code:
       0: aload_0
       1: getfield      #66                 // Field getAnnotatedType:Ljava/lang/reflect/Method;
       4: areturn

  static java.lang.reflect.Method access$600(net.bytebuddy.description.type.TypeDescription$Generic$AnnotationReader$Dispatcher$ForJava8CapableVm);
    Code:
       0: aload_0
       1: getfield      #68                 // Field getAnnotatedReturnType:Ljava/lang/reflect/Method;
       4: areturn

  static java.lang.reflect.Method access$700(net.bytebuddy.description.type.TypeDescription$Generic$AnnotationReader$Dispatcher$ForJava8CapableVm);
    Code:
       0: aload_0
       1: getfield      #70                 // Field getAnnotatedParameterTypes:Ljava/lang/reflect/Method;
       4: areturn

  static java.lang.reflect.Method access$800(net.bytebuddy.description.type.TypeDescription$Generic$AnnotationReader$Dispatcher$ForJava8CapableVm);
    Code:
       0: aload_0
       1: getfield      #72                 // Field getAnnotatedExceptionTypes:Ljava/lang/reflect/Method;
       4: areturn
}
