Compiled from "DefaultWebSessionContext.java"
public class org.apache.shiro.web.session.mgt.DefaultWebSessionContext extends org.apache.shiro.session.mgt.DefaultSessionContext implements org.apache.shiro.web.session.mgt.WebSessionContext {
  private static final long serialVersionUID;

  private static final java.lang.String SERVLET_REQUEST;

  private static final java.lang.String SERVLET_RESPONSE;

  public org.apache.shiro.web.session.mgt.DefaultWebSessionContext();
    Code:
       0: aload_0
       1: invokespecial #1                  // Method org/apache/shiro/session/mgt/DefaultSessionContext."<init>":()V
       4: return

  public org.apache.shiro.web.session.mgt.DefaultWebSessionContext(java.util.Map<java.lang.String, java.lang.Object>);
    Code:
       0: aload_0
       1: aload_1
       2: invokespecial #2                  // Method org/apache/shiro/session/mgt/DefaultSessionContext."<init>":(Ljava/util/Map;)V
       5: return

  public void setServletRequest(javax.servlet.ServletRequest);
    Code:
       0: aload_1
       1: ifnull        13
       4: aload_0
       5: getstatic     #3                  // Field SERVLET_REQUEST:Ljava/lang/String;
       8: aload_1
       9: invokevirtual #4                  // Method put:(Ljava/lang/String;Ljava/lang/Object;)Ljava/lang/Object;
      12: pop
      13: return

  public javax.servlet.ServletRequest getServletRequest();
    Code:
       0: aload_0
       1: getstatic     #3                  // Field SERVLET_REQUEST:Ljava/lang/String;
       4: ldc_w         #5                  // class javax/servlet/ServletRequest
       7: invokevirtual #6                  // Method getTypedValue:(Ljava/lang/String;Ljava/lang/Class;)Ljava/lang/Object;
      10: checkcast     #5                  // class javax/servlet/ServletRequest
      13: areturn

  public void setServletResponse(javax.servlet.ServletResponse);
    Code:
       0: aload_1
       1: ifnull        13
       4: aload_0
       5: getstatic     #7                  // Field SERVLET_RESPONSE:Ljava/lang/String;
       8: aload_1
       9: invokevirtual #4                  // Method put:(Ljava/lang/String;Ljava/lang/Object;)Ljava/lang/Object;
      12: pop
      13: return

  public javax.servlet.ServletResponse getServletResponse();
    Code:
       0: aload_0
       1: getstatic     #7                  // Field SERVLET_RESPONSE:Ljava/lang/String;
       4: ldc_w         #8                  // class javax/servlet/ServletResponse
       7: invokevirtual #6                  // Method getTypedValue:(Ljava/lang/String;Ljava/lang/Class;)Ljava/lang/Object;
      10: checkcast     #8                  // class javax/servlet/ServletResponse
      13: areturn

  static {};
    Code:
       0: new           #9                  // class java/lang/StringBuilder
       3: dup
       4: invokespecial #10                 // Method java/lang/StringBuilder."<init>":()V
       7: ldc_w         #11                 // class org/apache/shiro/web/session/mgt/DefaultWebSessionContext
      10: invokevirtual #12                 // Method java/lang/Class.getName:()Ljava/lang/String;
      13: invokevirtual #13                 // Method java/lang/StringBuilder.append:(Ljava/lang/String;)Ljava/lang/StringBuilder;
      16: ldc           #14                 // String .SERVLET_REQUEST
      18: invokevirtual #13                 // Method java/lang/StringBuilder.append:(Ljava/lang/String;)Ljava/lang/StringBuilder;
      21: invokevirtual #15                 // Method java/lang/StringBuilder.toString:()Ljava/lang/String;
      24: putstatic     #3                  // Field SERVLET_REQUEST:Ljava/lang/String;
      27: new           #9                  // class java/lang/StringBuilder
      30: dup
      31: invokespecial #10                 // Method java/lang/StringBuilder."<init>":()V
      34: ldc_w         #11                 // class org/apache/shiro/web/session/mgt/DefaultWebSessionContext
      37: invokevirtual #12                 // Method java/lang/Class.getName:()Ljava/lang/String;
      40: invokevirtual #13                 // Method java/lang/StringBuilder.append:(Ljava/lang/String;)Ljava/lang/StringBuilder;
      43: ldc           #16                 // String .SERVLET_RESPONSE
      45: invokevirtual #13                 // Method java/lang/StringBuilder.append:(Ljava/lang/String;)Ljava/lang/StringBuilder;
      48: invokevirtual #15                 // Method java/lang/StringBuilder.toString:()Ljava/lang/String;
      51: putstatic     #7                  // Field SERVLET_RESPONSE:Ljava/lang/String;
      54: return
}
