Compiled from "VolatileTwoPhaseCommitParticipant.java"
public class com.arjuna.mwlabs.wst.at.participants.VolatileTwoPhaseCommitParticipant implements com.arjuna.mw.wscf.model.twophase.participants.Synchronization {
  private com.arjuna.wst.Volatile2PCParticipant _resource;

  private boolean _readonly;

  public com.arjuna.mwlabs.wst.at.participants.VolatileTwoPhaseCommitParticipant(com.arjuna.wst.Volatile2PCParticipant);
    Code:
       0: aload_0
       1: invokespecial #1                  // Method java/lang/Object."<init>":()V
       4: aload_0
       5: aconst_null
       6: putfield      #2                  // Field _resource:Lcom/arjuna/wst/Volatile2PCParticipant;
       9: aload_0
      10: iconst_0
      11: putfield      #3                  // Field _readonly:Z
      14: aload_0
      15: aload_1
      16: putfield      #2                  // Field _resource:Lcom/arjuna/wst/Volatile2PCParticipant;
      19: return

  public void beforeCompletion() throws com.arjuna.mw.wsas.exceptions.SystemException;
    Code:
       0: aload_0
       1: getfield      #2                  // Field _resource:Lcom/arjuna/wst/Volatile2PCParticipant;
       4: ifnull        53
       7: aload_0
       8: getfield      #2                  // Field _resource:Lcom/arjuna/wst/Volatile2PCParticipant;
      11: invokeinterface #4,  1            // InterfaceMethod com/arjuna/wst/Volatile2PCParticipant.prepare:()Lcom/arjuna/wst/Vote;
      16: astore_1
      17: aload_1
      18: instanceof    #5                  // class com/arjuna/wst/ReadOnly
      21: ifeq          32
      24: aload_0
      25: iconst_1
      26: putfield      #3                  // Field _readonly:Z
      29: goto          50
      32: aload_1
      33: instanceof    #6                  // class com/arjuna/wst/Prepared
      36: ifeq          42
      39: goto          50
      42: new           #7                  // class com/arjuna/mw/wsas/exceptions/SystemException
      45: dup
      46: invokespecial #8                  // Method com/arjuna/mw/wsas/exceptions/SystemException."<init>":()V
      49: athrow
      50: goto          61
      53: new           #7                  // class com/arjuna/mw/wsas/exceptions/SystemException
      56: dup
      57: invokespecial #8                  // Method com/arjuna/mw/wsas/exceptions/SystemException."<init>":()V
      60: athrow
      61: goto          80
      64: astore_1
      65: aload_1
      66: athrow
      67: astore_1
      68: new           #7                  // class com/arjuna/mw/wsas/exceptions/SystemException
      71: dup
      72: aload_1
      73: invokevirtual #10                 // Method java/lang/Exception.toString:()Ljava/lang/String;
      76: invokespecial #11                 // Method com/arjuna/mw/wsas/exceptions/SystemException."<init>":(Ljava/lang/String;)V
      79: athrow
      80: return
    Exception table:
       from    to  target type
           0    61    64   Class com/arjuna/mw/wsas/exceptions/SystemException
           0    61    67   Class java/lang/Exception

  public void afterCompletion(int) throws com.arjuna.mw.wsas.exceptions.SystemException;
    Code:
       0: aload_0
       1: getfield      #3                  // Field _readonly:Z
       4: ifne          58
       7: iload_1
       8: lookupswitch  { // 1
                     0: 28
               default: 35
          }
      28: aload_0
      29: invokespecial #12                 // Method confirm:()V
      32: goto          39
      35: aload_0
      36: invokespecial #13                 // Method cancel:()V
      39: goto          58
      42: astore_2
      43: aload_2
      44: athrow
      45: astore_2
      46: new           #7                  // class com/arjuna/mw/wsas/exceptions/SystemException
      49: dup
      50: aload_2
      51: invokevirtual #10                 // Method java/lang/Exception.toString:()Ljava/lang/String;
      54: invokespecial #11                 // Method com/arjuna/mw/wsas/exceptions/SystemException."<init>":(Ljava/lang/String;)V
      57: athrow
      58: return
    Exception table:
       from    to  target type
           7    39    42   Class com/arjuna/mw/wsas/exceptions/SystemException
           7    39    45   Class java/lang/Exception

  private final void confirm() throws com.arjuna.mw.wscf.exceptions.InvalidParticipantException, com.arjuna.mw.wsas.exceptions.WrongStateException, com.arjuna.mw.wscf.model.twophase.exceptions.HeuristicHazardException, com.arjuna.mw.wscf.model.twophase.exceptions.HeuristicMixedException, com.arjuna.mw.wscf.model.twophase.exceptions.HeuristicCancelException, com.arjuna.mw.wsas.exceptions.SystemException;
    Code:
       0: aload_0
       1: getfield      #2                  // Field _resource:Lcom/arjuna/wst/Volatile2PCParticipant;
       4: ifnull        45
       7: aload_0
       8: getfield      #2                  // Field _resource:Lcom/arjuna/wst/Volatile2PCParticipant;
      11: invokeinterface #14,  1           // InterfaceMethod com/arjuna/wst/Volatile2PCParticipant.commit:()V
      16: goto          53
      19: astore_1
      20: new           #16                 // class com/arjuna/mw/wsas/exceptions/WrongStateException
      23: dup
      24: aload_1
      25: invokevirtual #17                 // Method com/arjuna/wst/WrongStateException.toString:()Ljava/lang/String;
      28: invokespecial #18                 // Method com/arjuna/mw/wsas/exceptions/WrongStateException."<init>":(Ljava/lang/String;)V
      31: athrow
      32: astore_1
      33: new           #7                  // class com/arjuna/mw/wsas/exceptions/SystemException
      36: dup
      37: aload_1
      38: invokevirtual #20                 // Method com/arjuna/wst/SystemException.toString:()Ljava/lang/String;
      41: invokespecial #11                 // Method com/arjuna/mw/wsas/exceptions/SystemException."<init>":(Ljava/lang/String;)V
      44: athrow
      45: new           #21                 // class com/arjuna/mw/wscf/exceptions/InvalidParticipantException
      48: dup
      49: invokespecial #22                 // Method com/arjuna/mw/wscf/exceptions/InvalidParticipantException."<init>":()V
      52: athrow
      53: return
    Exception table:
       from    to  target type
           7    16    19   Class com/arjuna/wst/WrongStateException
           7    16    32   Class com/arjuna/wst/SystemException

  private final void cancel() throws com.arjuna.mw.wscf.exceptions.InvalidParticipantException, com.arjuna.mw.wsas.exceptions.WrongStateException, com.arjuna.mw.wscf.model.twophase.exceptions.HeuristicHazardException, com.arjuna.mw.wscf.model.twophase.exceptions.HeuristicMixedException, com.arjuna.mw.wscf.model.twophase.exceptions.HeuristicConfirmException, com.arjuna.mw.wsas.exceptions.SystemException;
    Code:
       0: aload_0
       1: getfield      #2                  // Field _resource:Lcom/arjuna/wst/Volatile2PCParticipant;
       4: ifnull        45
       7: aload_0
       8: getfield      #2                  // Field _resource:Lcom/arjuna/wst/Volatile2PCParticipant;
      11: invokeinterface #23,  1           // InterfaceMethod com/arjuna/wst/Volatile2PCParticipant.rollback:()V
      16: goto          53
      19: astore_1
      20: new           #16                 // class com/arjuna/mw/wsas/exceptions/WrongStateException
      23: dup
      24: aload_1
      25: invokevirtual #17                 // Method com/arjuna/wst/WrongStateException.toString:()Ljava/lang/String;
      28: invokespecial #18                 // Method com/arjuna/mw/wsas/exceptions/WrongStateException."<init>":(Ljava/lang/String;)V
      31: athrow
      32: astore_1
      33: new           #7                  // class com/arjuna/mw/wsas/exceptions/SystemException
      36: dup
      37: aload_1
      38: invokevirtual #20                 // Method com/arjuna/wst/SystemException.toString:()Ljava/lang/String;
      41: invokespecial #11                 // Method com/arjuna/mw/wsas/exceptions/SystemException."<init>":(Ljava/lang/String;)V
      44: athrow
      45: new           #21                 // class com/arjuna/mw/wscf/exceptions/InvalidParticipantException
      48: dup
      49: invokespecial #22                 // Method com/arjuna/mw/wscf/exceptions/InvalidParticipantException."<init>":()V
      52: athrow
      53: return
    Exception table:
       from    to  target type
           7    16    19   Class com/arjuna/wst/WrongStateException
           7    16    32   Class com/arjuna/wst/SystemException
}
