Compiled from "OntologyImportsItemRenderer.java"
public class org.protege.editor.owl.ui.ontology.imports.OntologyImportsItemRenderer extends org.protege.editor.owl.ui.renderer.layout.PageCellRenderer {
  private org.protege.editor.owl.OWLEditorKit editorKit;

  public org.protege.editor.owl.ui.ontology.imports.OntologyImportsItemRenderer(org.protege.editor.owl.OWLEditorKit);
    Code:
       0: aload_0
       1: invokespecial #1                  // Method org/protege/editor/owl/ui/renderer/layout/PageCellRenderer."<init>":()V
       4: aload_0
       5: aload_1
       6: putfield      #2                  // Field editorKit:Lorg/protege/editor/owl/OWLEditorKit;
       9: return

  protected void fillPage(org.protege.editor.owl.ui.renderer.layout.Page, javax.swing.JList, java.lang.Object, int, boolean, boolean);
    Code:
       0: aload_0
       1: aload_2
       2: invokevirtual #3                  // Method javax/swing/JList.getSelectionForeground:()Ljava/awt/Color;
       5: aload_2
       6: invokevirtual #4                  // Method javax/swing/JList.getSelectionBackground:()Ljava/awt/Color;
       9: aload_1
      10: aload_3
      11: iload         5
      13: invokespecial #5                  // Method render:(Ljava/awt/Color;Ljava/awt/Color;Lorg/protege/editor/owl/ui/renderer/layout/Page;Ljava/lang/Object;Z)V
      16: return

  public java.awt.Component getListCellRendererComponent(javax.swing.JList, java.lang.Object, int, boolean, boolean);
    Code:
       0: aload_0
       1: aload_1
       2: aload_2
       3: iload_3
       4: iload         4
       6: iload         5
       8: invokespecial #6                  // Method org/protege/editor/owl/ui/renderer/layout/PageCellRenderer.getListCellRendererComponent:(Ljavax/swing/JList;Ljava/lang/Object;IZZ)Ljava/awt/Component;
      11: astore        6
      13: aload         6
      15: areturn

  private void render(java.awt.Color, java.awt.Color, org.protege.editor.owl.ui.renderer.layout.Page, java.lang.Object, boolean);
    Code:
       0: aload         4
       2: instanceof    #7                  // class org/protege/editor/owl/ui/ontology/imports/OntologyImportItem
       5: ifne          21
       8: aload_3
       9: aload         4
      11: invokevirtual #8                  // Method java/lang/Object.toString:()Ljava/lang/String;
      14: invokevirtual #9                  // Method org/protege/editor/owl/ui/renderer/layout/Page.addParagraph:(Ljava/lang/String;)Lorg/protege/editor/owl/ui/renderer/layout/Paragraph;
      17: pop
      18: goto          451
      21: iload         5
      23: ifeq          30
      26: aload_1
      27: goto          33
      30: getstatic     #10                 // Field java/awt/Color.DARK_GRAY:Ljava/awt/Color;
      33: astore        6
      35: aload         4
      37: checkcast     #7                  // class org/protege/editor/owl/ui/ontology/imports/OntologyImportItem
      40: astore        7
      42: aload_0
      43: getfield      #2                  // Field editorKit:Lorg/protege/editor/owl/OWLEditorKit;
      46: invokevirtual #11                 // Method org/protege/editor/owl/OWLEditorKit.getOWLModelManager:()Lorg/protege/editor/owl/model/OWLModelManager;
      49: invokeinterface #12,  1           // InterfaceMethod org/protege/editor/owl/model/OWLModelManager.getOWLOntologyManager:()Lorg/semanticweb/owlapi/model/OWLOntologyManager;
      54: astore        8
      56: aload         8
      58: aload         7
      60: invokevirtual #13                 // Method org/protege/editor/owl/ui/ontology/imports/OntologyImportItem.getImportDeclaration:()Lorg/semanticweb/owlapi/model/OWLImportsDeclaration;
      63: invokeinterface #14,  2           // InterfaceMethod org/semanticweb/owlapi/model/OWLOntologyManager.getImportedOntology:(Lorg/semanticweb/owlapi/model/OWLImportsDeclaration;)Lorg/semanticweb/owlapi/model/OWLOntology;
      68: astore        9
      70: new           #15                 // class org/semanticweb/owlapi/util/OntologyIRIShortFormProvider
      73: dup
      74: invokespecial #16                 // Method org/semanticweb/owlapi/util/OntologyIRIShortFormProvider."<init>":()V
      77: astore        10
      79: iload         5
      81: ifeq          88
      84: aload_1
      85: goto          91
      88: getstatic     #17                 // Field java/awt/Color.BLACK:Ljava/awt/Color;
      91: astore        11
      93: aload         7
      95: invokevirtual #13                 // Method org/protege/editor/owl/ui/ontology/imports/OntologyImportItem.getImportDeclaration:()Lorg/semanticweb/owlapi/model/OWLImportsDeclaration;
      98: invokeinterface #18,  1           // InterfaceMethod org/semanticweb/owlapi/model/OWLImportsDeclaration.getIRI:()Lorg/semanticweb/owlapi/model/IRI;
     103: astore        12
     105: aload_3
     106: aload         12
     108: invokevirtual #19                 // Method org/semanticweb/owlapi/model/IRI.toQuotedString:()Ljava/lang/String;
     111: aload         11
     113: invokevirtual #20                 // Method org/protege/editor/owl/ui/renderer/layout/Page.addParagraph:(Ljava/lang/String;Ljava/awt/Color;)Lorg/protege/editor/owl/ui/renderer/layout/Paragraph;
     116: pop
     117: aload_3
     118: iconst_5
     119: invokevirtual #21                 // Method org/protege/editor/owl/ui/renderer/layout/Page.setMarginBottom:(I)V
     122: aload         9
     124: ifnull        451
     127: aload         10
     129: aload         9
     131: invokevirtual #22                 // Method org/semanticweb/owlapi/util/OntologyIRIShortFormProvider.getShortForm:(Lorg/semanticweb/owlapi/model/OWLOntology;)Ljava/lang/String;
     134: astore        13
     136: aload_3
     137: aload         13
     139: aload         11
     141: invokevirtual #20                 // Method org/protege/editor/owl/ui/renderer/layout/Page.addParagraph:(Ljava/lang/String;Ljava/awt/Color;)Lorg/protege/editor/owl/ui/renderer/layout/Paragraph;
     144: astore        14
     146: aload         14
     148: iconst_5
     149: invokevirtual #23                 // Method org/protege/editor/owl/ui/renderer/layout/Paragraph.setMarginTop:(I)V
     152: aload         14
     154: bipush        40
     156: invokevirtual #24                 // Method org/protege/editor/owl/ui/renderer/layout/Paragraph.setMarginLeft:(I)V
     159: aload         9
     161: invokeinterface #25,  1           // InterfaceMethod org/semanticweb/owlapi/model/OWLOntology.getOntologyID:()Lorg/semanticweb/owlapi/model/OWLOntologyID;
     166: astore        15
     168: aload         15
     170: invokevirtual #26                 // Method org/semanticweb/owlapi/model/OWLOntologyID.isAnonymous:()Z
     173: ifne          282
     176: aload_3
     177: ldc           #27                 // String Ontology IRI:
     179: getstatic     #28                 // Field java/awt/Color.GRAY:Ljava/awt/Color;
     182: invokevirtual #20                 // Method org/protege/editor/owl/ui/renderer/layout/Page.addParagraph:(Ljava/lang/String;Ljava/awt/Color;)Lorg/protege/editor/owl/ui/renderer/layout/Paragraph;
     185: astore        16
     187: aload         16
     189: bipush        40
     191: invokevirtual #24                 // Method org/protege/editor/owl/ui/renderer/layout/Paragraph.setMarginLeft:(I)V
     194: aload         15
     196: invokevirtual #29                 // Method org/semanticweb/owlapi/model/OWLOntologyID.getOntologyIRI:()Lcom/google/common/base/Optional;
     199: invokevirtual #30                 // Method com/google/common/base/Optional.get:()Ljava/lang/Object;
     202: checkcast     #31                 // class org/semanticweb/owlapi/model/IRI
     205: astore        17
     207: aload         16
     209: aload         17
     211: invokevirtual #19                 // Method org/semanticweb/owlapi/model/IRI.toQuotedString:()Ljava/lang/String;
     214: aload         6
     216: invokevirtual #32                 // Method org/protege/editor/owl/ui/renderer/layout/Paragraph.append:(Ljava/lang/String;Ljava/awt/Color;)V
     219: aload         16
     221: iconst_2
     222: invokevirtual #23                 // Method org/protege/editor/owl/ui/renderer/layout/Paragraph.setMarginTop:(I)V
     225: aload         15
     227: invokevirtual #33                 // Method org/semanticweb/owlapi/model/OWLOntologyID.getVersionIRI:()Lcom/google/common/base/Optional;
     230: astore        18
     232: aload         18
     234: invokevirtual #34                 // Method com/google/common/base/Optional.isPresent:()Z
     237: ifeq          282
     240: aload_3
     241: ldc           #35                 // String Version IRI:
     243: getstatic     #28                 // Field java/awt/Color.GRAY:Ljava/awt/Color;
     246: invokevirtual #20                 // Method org/protege/editor/owl/ui/renderer/layout/Page.addParagraph:(Ljava/lang/String;Ljava/awt/Color;)Lorg/protege/editor/owl/ui/renderer/layout/Paragraph;
     249: astore        19
     251: aload         19
     253: bipush        40
     255: invokevirtual #24                 // Method org/protege/editor/owl/ui/renderer/layout/Paragraph.setMarginLeft:(I)V
     258: aload         19
     260: iconst_2
     261: invokevirtual #23                 // Method org/protege/editor/owl/ui/renderer/layout/Paragraph.setMarginTop:(I)V
     264: aload         19
     266: aload         18
     268: invokevirtual #30                 // Method com/google/common/base/Optional.get:()Ljava/lang/Object;
     271: checkcast     #31                 // class org/semanticweb/owlapi/model/IRI
     274: invokevirtual #19                 // Method org/semanticweb/owlapi/model/IRI.toQuotedString:()Ljava/lang/String;
     277: aload         6
     279: invokevirtual #32                 // Method org/protege/editor/owl/ui/renderer/layout/Paragraph.append:(Ljava/lang/String;Ljava/awt/Color;)V
     282: aload_3
     283: ldc           #36                 // String Location:
     285: getstatic     #28                 // Field java/awt/Color.GRAY:Ljava/awt/Color;
     288: invokevirtual #20                 // Method org/protege/editor/owl/ui/renderer/layout/Page.addParagraph:(Ljava/lang/String;Ljava/awt/Color;)Lorg/protege/editor/owl/ui/renderer/layout/Paragraph;
     291: astore        16
     293: aload         16
     295: bipush        40
     297: invokevirtual #24                 // Method org/protege/editor/owl/ui/renderer/layout/Paragraph.setMarginLeft:(I)V
     300: aload         16
     302: iconst_2
     303: invokevirtual #23                 // Method org/protege/editor/owl/ui/renderer/layout/Paragraph.setMarginTop:(I)V
     306: aload         8
     308: aload         9
     310: invokeinterface #37,  2           // InterfaceMethod org/semanticweb/owlapi/model/OWLOntologyManager.getOntologyDocumentIRI:(Lorg/semanticweb/owlapi/model/OWLOntology;)Lorg/semanticweb/owlapi/model/IRI;
     315: astore        17
     317: aload         16
     319: invokevirtual #38                 // Method org/protege/editor/owl/ui/renderer/layout/Paragraph.getLength:()I
     322: istore        18
     324: ldc           #39                 // String file
     326: aload         17
     328: invokevirtual #40                 // Method org/semanticweb/owlapi/model/IRI.getScheme:()Ljava/lang/String;
     331: invokevirtual #41                 // Method java/lang/String.equalsIgnoreCase:(Ljava/lang/String;)Z
     334: ifeq          401
     337: new           #42                 // class java/io/File
     340: dup
     341: aload         17
     343: invokevirtual #43                 // Method org/semanticweb/owlapi/model/IRI.toURI:()Ljava/net/URI;
     346: invokespecial #44                 // Method java/io/File."<init>":(Ljava/net/URI;)V
     349: astore        19
     351: aload         16
     353: aload         19
     355: invokevirtual #45                 // Method java/io/File.getAbsolutePath:()Ljava/lang/String;
     358: aload         6
     360: invokevirtual #32                 // Method org/protege/editor/owl/ui/renderer/layout/Paragraph.append:(Ljava/lang/String;Ljava/awt/Color;)V
     363: aload         16
     365: new           #46                 // class org/protege/editor/owl/ui/renderer/layout/LinkSpan
     368: dup
     369: new           #47                 // class org/protege/editor/owl/ui/renderer/layout/FileLink
     372: dup
     373: aload         19
     375: invokespecial #48                 // Method org/protege/editor/owl/ui/renderer/layout/FileLink."<init>":(Ljava/io/File;)V
     378: new           #49                 // class org/protege/editor/owl/ui/renderer/layout/Span
     381: dup
     382: iload         18
     384: aload         16
     386: invokevirtual #38                 // Method org/protege/editor/owl/ui/renderer/layout/Paragraph.getLength:()I
     389: invokespecial #50                 // Method org/protege/editor/owl/ui/renderer/layout/Span."<init>":(II)V
     392: invokespecial #51                 // Method org/protege/editor/owl/ui/renderer/layout/LinkSpan."<init>":(Lorg/protege/editor/owl/ui/renderer/layout/Link;Lorg/protege/editor/owl/ui/renderer/layout/Span;)V
     395: invokevirtual #52                 // Method org/protege/editor/owl/ui/renderer/layout/Paragraph.addLink:(Lorg/protege/editor/owl/ui/renderer/layout/LinkSpan;)V
     398: goto          451
     401: aload         16
     403: aload         17
     405: invokevirtual #53                 // Method org/semanticweb/owlapi/model/IRI.toString:()Ljava/lang/String;
     408: aload         6
     410: invokevirtual #32                 // Method org/protege/editor/owl/ui/renderer/layout/Paragraph.append:(Ljava/lang/String;Ljava/awt/Color;)V
     413: aload         16
     415: new           #46                 // class org/protege/editor/owl/ui/renderer/layout/LinkSpan
     418: dup
     419: new           #54                 // class org/protege/editor/owl/ui/renderer/layout/HTTPLink
     422: dup
     423: aload         17
     425: invokevirtual #43                 // Method org/semanticweb/owlapi/model/IRI.toURI:()Ljava/net/URI;
     428: invokespecial #55                 // Method org/protege/editor/owl/ui/renderer/layout/HTTPLink."<init>":(Ljava/net/URI;)V
     431: new           #49                 // class org/protege/editor/owl/ui/renderer/layout/Span
     434: dup
     435: iload         18
     437: aload         16
     439: invokevirtual #38                 // Method org/protege/editor/owl/ui/renderer/layout/Paragraph.getLength:()I
     442: invokespecial #50                 // Method org/protege/editor/owl/ui/renderer/layout/Span."<init>":(II)V
     445: invokespecial #51                 // Method org/protege/editor/owl/ui/renderer/layout/LinkSpan."<init>":(Lorg/protege/editor/owl/ui/renderer/layout/Link;Lorg/protege/editor/owl/ui/renderer/layout/Span;)V
     448: invokevirtual #52                 // Method org/protege/editor/owl/ui/renderer/layout/Paragraph.addLink:(Lorg/protege/editor/owl/ui/renderer/layout/LinkSpan;)V
     451: return

  protected int getMaxAvailablePageWidth(javax.swing.JList, java.lang.Object, int, boolean, boolean);
    Code:
       0: aload_1
       1: invokevirtual #56                 // Method javax/swing/JList.getInsets:()Ljava/awt/Insets;
       4: astore        6
       6: aload_1
       7: invokevirtual #57                 // Method javax/swing/JList.getWidth:()I
      10: istore        7
      12: ldc           #58                 // class javax/swing/JViewport
      14: aload_1
      15: invokestatic  #59                 // Method javax/swing/SwingUtilities.getAncestorOfClass:(Ljava/lang/Class;Ljava/awt/Component;)Ljava/awt/Container;
      18: checkcast     #58                 // class javax/swing/JViewport
      21: astore        8
      23: aload         8
      25: ifnull        38
      28: aload         8
      30: invokevirtual #60                 // Method javax/swing/JViewport.getViewRect:()Ljava/awt/Rectangle;
      33: getfield      #61                 // Field java/awt/Rectangle.width:I
      36: istore        7
      38: iload         7
      40: aload_1
      41: invokevirtual #56                 // Method javax/swing/JList.getInsets:()Ljava/awt/Insets;
      44: getfield      #62                 // Field java/awt/Insets.left:I
      47: isub
      48: aload_1
      49: invokevirtual #56                 // Method javax/swing/JList.getInsets:()Ljava/awt/Insets;
      52: getfield      #63                 // Field java/awt/Insets.right:I
      55: isub
      56: aload         6
      58: getfield      #62                 // Field java/awt/Insets.left:I
      61: isub
      62: aload         6
      64: getfield      #63                 // Field java/awt/Insets.right:I
      67: iadd
      68: bipush        20
      70: isub
      71: istore        9
      73: iload         9
      75: ifle          83
      78: iload         9
      80: goto          86
      83: sipush        500
      86: ireturn

  protected void fillPage(org.protege.editor.owl.ui.renderer.layout.Page, javax.swing.JTable, java.lang.Object, boolean, boolean, int, int);
    Code:
       0: aload_0
       1: aload_2
       2: invokevirtual #64                 // Method javax/swing/JTable.getSelectionForeground:()Ljava/awt/Color;
       5: aload_2
       6: invokevirtual #65                 // Method javax/swing/JTable.getSelectionBackground:()Ljava/awt/Color;
       9: aload_1
      10: aload_3
      11: iload         4
      13: invokespecial #5                  // Method render:(Ljava/awt/Color;Ljava/awt/Color;Lorg/protege/editor/owl/ui/renderer/layout/Page;Ljava/lang/Object;Z)V
      16: return

  protected int getMaxAvailablePageWidth(org.protege.editor.owl.ui.renderer.layout.Page, javax.swing.JTable, java.lang.Object, boolean, boolean, int, int);
    Code:
       0: aload_2
       1: invokevirtual #66                 // Method javax/swing/JTable.getColumnModel:()Ljavax/swing/table/TableColumnModel;
       4: iload         7
       6: invokeinterface #67,  2           // InterfaceMethod javax/swing/table/TableColumnModel.getColumn:(I)Ljavax/swing/table/TableColumn;
      11: invokevirtual #68                 // Method javax/swing/table/TableColumn.getWidth:()I
      14: iconst_5
      15: isub
      16: ireturn
}
