Compiled from "RedisConnection.scala"
public class dev.profunktor.redis4cats.connection.OperationNotSupported extends java.lang.Throwable implements scala.util.control.NoStackTrace,scala.Product {
  private final java.lang.String value;

  public static scala.Option<java.lang.String> unapply(dev.profunktor.redis4cats.connection.OperationNotSupported);
    Code:
       0: getstatic     #24                 // Field dev/profunktor/redis4cats/connection/OperationNotSupported$.MODULE$:Ldev/profunktor/redis4cats/connection/OperationNotSupported$;
       3: aload_0
       4: invokevirtual #26                 // Method dev/profunktor/redis4cats/connection/OperationNotSupported$.unapply:(Ldev/profunktor/redis4cats/connection/OperationNotSupported;)Lscala/Option;
       7: areturn

  public static dev.profunktor.redis4cats.connection.OperationNotSupported apply(java.lang.String);
    Code:
       0: getstatic     #24                 // Field dev/profunktor/redis4cats/connection/OperationNotSupported$.MODULE$:Ldev/profunktor/redis4cats/connection/OperationNotSupported$;
       3: aload_0
       4: invokevirtual #30                 // Method dev/profunktor/redis4cats/connection/OperationNotSupported$.apply:(Ljava/lang/String;)Ldev/profunktor/redis4cats/connection/OperationNotSupported;
       7: areturn

  public static <A$> scala.Function1<java.lang.String, A$> andThen(scala.Function1<dev.profunktor.redis4cats.connection.OperationNotSupported, A$>);
    Code:
       0: getstatic     #24                 // Field dev/profunktor/redis4cats/connection/OperationNotSupported$.MODULE$:Ldev/profunktor/redis4cats/connection/OperationNotSupported$;
       3: aload_0
       4: invokevirtual #36                 // Method dev/profunktor/redis4cats/connection/OperationNotSupported$.andThen:(Lscala/Function1;)Lscala/Function1;
       7: areturn

  public static <A$> scala.Function1<A$, dev.profunktor.redis4cats.connection.OperationNotSupported> compose(scala.Function1<A$, java.lang.String>);
    Code:
       0: getstatic     #24                 // Field dev/profunktor/redis4cats/connection/OperationNotSupported$.MODULE$:Ldev/profunktor/redis4cats/connection/OperationNotSupported$;
       3: aload_0
       4: invokevirtual #40                 // Method dev/profunktor/redis4cats/connection/OperationNotSupported$.compose:(Lscala/Function1;)Lscala/Function1;
       7: areturn

  public scala.collection.Iterator<java.lang.String> productElementNames();
    Code:
       0: aload_0
       1: invokestatic  #47                 // InterfaceMethod scala/Product.productElementNames$:(Lscala/Product;)Lscala/collection/Iterator;
       4: areturn

  public java.lang.Throwable scala$util$control$NoStackTrace$$super$fillInStackTrace();
    Code:
       0: aload_0
       1: invokespecial #54                 // Method java/lang/Throwable.fillInStackTrace:()Ljava/lang/Throwable;
       4: areturn

  public java.lang.Throwable fillInStackTrace();
    Code:
       0: aload_0
       1: invokestatic  #58                 // InterfaceMethod scala/util/control/NoStackTrace.fillInStackTrace$:(Lscala/util/control/NoStackTrace;)Ljava/lang/Throwable;
       4: areturn

  public java.lang.String value();
    Code:
       0: aload_0
       1: getfield      #61                 // Field value:Ljava/lang/String;
       4: areturn

  public java.lang.String toString();
    Code:
       0: new           #64                 // class java/lang/StringBuilder
       3: dup
       4: ldc           #65                 // int 23
       6: invokespecial #69                 // Method java/lang/StringBuilder."<init>":(I)V
       9: ldc           #71                 // String OperationNotSupported(
      11: invokevirtual #75                 // Method java/lang/StringBuilder.append:(Ljava/lang/String;)Ljava/lang/StringBuilder;
      14: aload_0
      15: invokevirtual #77                 // Method value:()Ljava/lang/String;
      18: invokevirtual #75                 // Method java/lang/StringBuilder.append:(Ljava/lang/String;)Ljava/lang/StringBuilder;
      21: ldc           #79                 // String )
      23: invokevirtual #75                 // Method java/lang/StringBuilder.append:(Ljava/lang/String;)Ljava/lang/StringBuilder;
      26: invokevirtual #81                 // Method java/lang/StringBuilder.toString:()Ljava/lang/String;
      29: areturn

  public dev.profunktor.redis4cats.connection.OperationNotSupported copy(java.lang.String);
    Code:
       0: new           #2                  // class dev/profunktor/redis4cats/connection/OperationNotSupported
       3: dup
       4: aload_1
       5: invokespecial #85                 // Method "<init>":(Ljava/lang/String;)V
       8: areturn

  public java.lang.String copy$default$1();
    Code:
       0: aload_0
       1: invokevirtual #77                 // Method value:()Ljava/lang/String;
       4: areturn

  public java.lang.String productPrefix();
    Code:
       0: ldc           #89                 // String OperationNotSupported
       2: areturn

  public int productArity();
    Code:
       0: iconst_1
       1: ireturn

  public java.lang.Object productElement(int);
    Code:
       0: iload_1
       1: istore_2
       2: iload_2
       3: tableswitch   { // 0 to 0
                     0: 20
               default: 27
          }
      20: aload_0
      21: invokevirtual #77                 // Method value:()Ljava/lang/String;
      24: goto          34
      27: iload_1
      28: invokestatic  #99                 // Method scala/runtime/Statics.ioobe:(I)Ljava/lang/Object;
      31: goto          34
      34: areturn

  public scala.collection.Iterator<java.lang.Object> productIterator();
    Code:
       0: getstatic     #109                // Field scala/runtime/ScalaRunTime$.MODULE$:Lscala/runtime/ScalaRunTime$;
       3: aload_0
       4: invokevirtual #112                // Method scala/runtime/ScalaRunTime$.typedProductIterator:(Lscala/Product;)Lscala/collection/Iterator;
       7: areturn

  public boolean canEqual(java.lang.Object);
    Code:
       0: aload_1
       1: instanceof    #2                  // class dev/profunktor/redis4cats/connection/OperationNotSupported
       4: ireturn

  public java.lang.String productElementName(int);
    Code:
       0: iload_1
       1: istore_2
       2: iload_2
       3: tableswitch   { // 0 to 0
                     0: 20
               default: 25
          }
      20: ldc           #118                // String value
      22: goto          35
      25: iload_1
      26: invokestatic  #99                 // Method scala/runtime/Statics.ioobe:(I)Ljava/lang/Object;
      29: checkcast     #120                // class java/lang/String
      32: goto          35
      35: areturn

  public int hashCode();
    Code:
       0: getstatic     #109                // Field scala/runtime/ScalaRunTime$.MODULE$:Lscala/runtime/ScalaRunTime$;
       3: aload_0
       4: invokevirtual #125                // Method scala/runtime/ScalaRunTime$._hashCode:(Lscala/Product;)I
       7: ireturn

  public boolean equals(java.lang.Object);
    Code:
       0: aload_0
       1: aload_1
       2: if_acmpeq     86
       5: aload_1
       6: astore_3
       7: aload_3
       8: instanceof    #2                  // class dev/profunktor/redis4cats/connection/OperationNotSupported
      11: ifeq          19
      14: iconst_1
      15: istore_2
      16: goto          27
      19: goto          22
      22: iconst_0
      23: istore_2
      24: goto          27
      27: iload_2
      28: ifeq          90
      31: aload_1
      32: checkcast     #2                  // class dev/profunktor/redis4cats/connection/OperationNotSupported
      35: astore        4
      37: aload_0
      38: invokevirtual #77                 // Method value:()Ljava/lang/String;
      41: aload         4
      43: invokevirtual #77                 // Method value:()Ljava/lang/String;
      46: astore        5
      48: dup
      49: ifnonnull     61
      52: pop
      53: aload         5
      55: ifnull        69
      58: goto          82
      61: aload         5
      63: invokevirtual #128                // Method java/lang/Object.equals:(Ljava/lang/Object;)Z
      66: ifeq          82
      69: aload         4
      71: aload_0
      72: invokevirtual #130                // Method canEqual:(Ljava/lang/Object;)Z
      75: ifeq          82
      78: iconst_1
      79: goto          83
      82: iconst_0
      83: ifeq          90
      86: iconst_1
      87: goto          91
      90: iconst_0
      91: ireturn

  public dev.profunktor.redis4cats.connection.OperationNotSupported(java.lang.String);
    Code:
       0: aload_0
       1: aload_1
       2: putfield      #61                 // Field value:Ljava/lang/String;
       5: aload_0
       6: invokespecial #133                // Method java/lang/Throwable."<init>":()V
       9: aload_0
      10: invokestatic  #137                // InterfaceMethod scala/util/control/NoStackTrace.$init$:(Lscala/util/control/NoStackTrace;)V
      13: aload_0
      14: invokestatic  #140                // InterfaceMethod scala/Product.$init$:(Lscala/Product;)V
      17: return
}
