Compiled from "RedisClusterClient.scala"
public class dev.profunktor.redis4cats.connection.RedisClusterClient$Sync$F$3$ {
  private final cats.effect.Sync evidence$11$1;

  public cats.effect.Sync E$F$Def$Sync(dev.profunktor.redis4cats.connection.RedisClusterClient$E$F$Def$5);
    Code:
       0: aload_0
       1: getfield      #21                 // Field evidence$11$1:Lcats/effect/Sync;
       4: areturn

  public dev.profunktor.redis4cats.connection.RedisClusterClient$Sync$F$3$(cats.effect.Sync);
    Code:
       0: aload_0
       1: aload_1
       2: putfield      #21                 // Field evidence$11$1:Lcats/effect/Sync;
       5: aload_0
       6: invokespecial #29                 // Method java/lang/Object."<init>":()V
       9: return
}
