Compiled from "RedisConnection.scala"
public class dev.profunktor.redis4cats.connection.RedisStatefulClusterConnection<F, K, V> implements dev.profunktor.redis4cats.connection.RedisConnection<F, K, V> {
  private volatile dev.profunktor.redis4cats.connection.RedisStatefulClusterConnection<F, K, V>.Concurrent$F$ Concurrent$F$module;

  private final io.lettuce.core.cluster.api.StatefulRedisClusterConnection<K, V> conn;

  private final scala.concurrent.ExecutionContext blocker;

  public final cats.effect.Concurrent<F> dev$profunktor$redis4cats$connection$RedisStatefulClusterConnection$$evidence$7;

  public final cats.effect.ContextShift<F> dev$profunktor$redis4cats$connection$RedisStatefulClusterConnection$$evidence$8;

  private final dev.profunktor.redis4cats.connection.RedisStatefulClusterConnection$E$F$RedisStatefulClusterConnection F;

  private volatile byte bitmap$init$0;

  private dev.profunktor.redis4cats.connection.RedisStatefulClusterConnection$Concurrent$F$ Concurrent$F();
    Code:
       0: aload_0
       1: getfield      #70                 // Field Concurrent$F$module:Ldev/profunktor/redis4cats/connection/RedisStatefulClusterConnection$Concurrent$F$;
       4: ifnonnull     11
       7: aload_0
       8: invokespecial #74                 // Method Concurrent$F$lzycompute$2:()V
      11: aload_0
      12: getfield      #70                 // Field Concurrent$F$module:Ldev/profunktor/redis4cats/connection/RedisStatefulClusterConnection$Concurrent$F$;
      15: areturn

  public F sync();
    Code:
       0: aload_0
       1: invokespecial #81                 // Method Concurrent$F:()Ldev/profunktor/redis4cats/connection/RedisStatefulClusterConnection$Concurrent$F$;
       4: aload_0
       5: getfield      #83                 // Field F:Ldev/profunktor/redis4cats/connection/RedisStatefulClusterConnection$E$F$RedisStatefulClusterConnection;
       8: invokevirtual #87                 // Method dev/profunktor/redis4cats/connection/RedisStatefulClusterConnection$Concurrent$F$.E$F$RedisStatefulClusterConnection$Concurrent:(Ldev/profunktor/redis4cats/connection/RedisStatefulClusterConnection$E$F$RedisStatefulClusterConnection;)Lcats/effect/Concurrent;
      11: new           #89                 // class dev/profunktor/redis4cats/connection/OperationNotSupported
      14: dup
      15: ldc           #91                 // String Transactions are not supported in a cluster. You must select a single node.
      17: invokespecial #95                 // Method dev/profunktor/redis4cats/connection/OperationNotSupported."<init>":(Ljava/lang/String;)V
      20: invokeinterface #101,  2          // InterfaceMethod cats/effect/Concurrent.raiseError:(Ljava/lang/Object;)Ljava/lang/Object;
      25: areturn

  public F async();
    Code:
       0: aload_0
       1: invokespecial #81                 // Method Concurrent$F:()Ldev/profunktor/redis4cats/connection/RedisStatefulClusterConnection$Concurrent$F$;
       4: aload_0
       5: getfield      #83                 // Field F:Ldev/profunktor/redis4cats/connection/RedisStatefulClusterConnection$E$F$RedisStatefulClusterConnection;
       8: invokevirtual #87                 // Method dev/profunktor/redis4cats/connection/RedisStatefulClusterConnection$Concurrent$F$.E$F$RedisStatefulClusterConnection$Concurrent:(Ldev/profunktor/redis4cats/connection/RedisStatefulClusterConnection$E$F$RedisStatefulClusterConnection;)Lcats/effect/Concurrent;
      11: new           #89                 // class dev/profunktor/redis4cats/connection/OperationNotSupported
      14: dup
      15: ldc           #91                 // String Transactions are not supported in a cluster. You must select a single node.
      17: invokespecial #95                 // Method dev/profunktor/redis4cats/connection/OperationNotSupported."<init>":(Ljava/lang/String;)V
      20: invokeinterface #101,  2          // InterfaceMethod cats/effect/Concurrent.raiseError:(Ljava/lang/Object;)Ljava/lang/Object;
      25: areturn

  public F clusterAsync();
    Code:
       0: aload_0
       1: invokespecial #81                 // Method Concurrent$F:()Ldev/profunktor/redis4cats/connection/RedisStatefulClusterConnection$Concurrent$F$;
       4: aload_0
       5: getfield      #83                 // Field F:Ldev/profunktor/redis4cats/connection/RedisStatefulClusterConnection$E$F$RedisStatefulClusterConnection;
       8: invokevirtual #87                 // Method dev/profunktor/redis4cats/connection/RedisStatefulClusterConnection$Concurrent$F$.E$F$RedisStatefulClusterConnection$Concurrent:(Ldev/profunktor/redis4cats/connection/RedisStatefulClusterConnection$E$F$RedisStatefulClusterConnection;)Lcats/effect/Concurrent;
      11: aload_0
      12: invokedynamic #124,  0            // InvokeDynamic #0:apply:(Ldev/profunktor/redis4cats/connection/RedisStatefulClusterConnection;)Lscala/Function0;
      17: invokeinterface #128,  2          // InterfaceMethod cats/effect/Concurrent.delay:(Lscala/Function0;)Ljava/lang/Object;
      22: areturn

  public F clusterSync();
    Code:
       0: aload_0
       1: invokespecial #81                 // Method Concurrent$F:()Ldev/profunktor/redis4cats/connection/RedisStatefulClusterConnection$Concurrent$F$;
       4: aload_0
       5: getfield      #83                 // Field F:Ldev/profunktor/redis4cats/connection/RedisStatefulClusterConnection$E$F$RedisStatefulClusterConnection;
       8: invokevirtual #87                 // Method dev/profunktor/redis4cats/connection/RedisStatefulClusterConnection$Concurrent$F$.E$F$RedisStatefulClusterConnection$Concurrent:(Ldev/profunktor/redis4cats/connection/RedisStatefulClusterConnection$E$F$RedisStatefulClusterConnection;)Lcats/effect/Concurrent;
      11: aload_0
      12: invokedynamic #137,  0            // InvokeDynamic #1:apply:(Ldev/profunktor/redis4cats/connection/RedisStatefulClusterConnection;)Lscala/Function0;
      17: invokeinterface #128,  2          // InterfaceMethod cats/effect/Concurrent.delay:(Lscala/Function0;)Ljava/lang/Object;
      22: areturn

  public F close();
    Code:
       0: getstatic     #142                // Field cats/syntax/package$all$.MODULE$:Lcats/syntax/package$all$;
       3: getstatic     #147                // Field dev/profunktor/redis4cats/effect/JRFuture$.MODULE$:Ldev/profunktor/redis4cats/effect/JRFuture$;
       6: aload_0
       7: invokespecial #81                 // Method Concurrent$F:()Ldev/profunktor/redis4cats/connection/RedisStatefulClusterConnection$Concurrent$F$;
      10: aload_0
      11: getfield      #83                 // Field F:Ldev/profunktor/redis4cats/connection/RedisStatefulClusterConnection$E$F$RedisStatefulClusterConnection;
      14: invokevirtual #87                 // Method dev/profunktor/redis4cats/connection/RedisStatefulClusterConnection$Concurrent$F$.E$F$RedisStatefulClusterConnection$Concurrent:(Ldev/profunktor/redis4cats/connection/RedisStatefulClusterConnection$E$F$RedisStatefulClusterConnection;)Lcats/effect/Concurrent;
      17: aload_0
      18: invokedynamic #155,  0            // InvokeDynamic #2:apply:(Ldev/profunktor/redis4cats/connection/RedisStatefulClusterConnection;)Lscala/Function0;
      23: invokeinterface #128,  2          // InterfaceMethod cats/effect/Concurrent.delay:(Lscala/Function0;)Ljava/lang/Object;
      28: aload_0
      29: getfield      #157                // Field blocker:Lscala/concurrent/ExecutionContext;
      32: aload_0
      33: getfield      #159                // Field dev$profunktor$redis4cats$connection$RedisStatefulClusterConnection$$evidence$7:Lcats/effect/Concurrent;
      36: aload_0
      37: getfield      #161                // Field dev$profunktor$redis4cats$connection$RedisStatefulClusterConnection$$evidence$8:Lcats/effect/ContextShift;
      40: invokevirtual #165                // Method dev/profunktor/redis4cats/effect/JRFuture$.fromCompletableFuture:(Ljava/lang/Object;Lscala/concurrent/ExecutionContext;Lcats/effect/Concurrent;Lcats/effect/ContextShift;)Ljava/lang/Object;
      43: aload_0
      44: getfield      #159                // Field dev$profunktor$redis4cats$connection$RedisStatefulClusterConnection$$evidence$7:Lcats/effect/Concurrent;
      47: invokevirtual #169                // Method cats/syntax/package$all$.toFunctorOps:(Ljava/lang/Object;Lcats/Functor;)Lcats/Functor$Ops;
      50: invokeinterface #172,  1          // InterfaceMethod cats/Functor$Ops.void:()Ljava/lang/Object;
      55: areturn

  public F byNode(java.lang.String);
    Code:
       0: getstatic     #142                // Field cats/syntax/package$all$.MODULE$:Lcats/syntax/package$all$;
       3: getstatic     #147                // Field dev/profunktor/redis4cats/effect/JRFuture$.MODULE$:Ldev/profunktor/redis4cats/effect/JRFuture$;
       6: aload_0
       7: invokespecial #81                 // Method Concurrent$F:()Ldev/profunktor/redis4cats/connection/RedisStatefulClusterConnection$Concurrent$F$;
      10: aload_0
      11: getfield      #83                 // Field F:Ldev/profunktor/redis4cats/connection/RedisStatefulClusterConnection$E$F$RedisStatefulClusterConnection;
      14: invokevirtual #87                 // Method dev/profunktor/redis4cats/connection/RedisStatefulClusterConnection$Concurrent$F$.E$F$RedisStatefulClusterConnection$Concurrent:(Ldev/profunktor/redis4cats/connection/RedisStatefulClusterConnection$E$F$RedisStatefulClusterConnection;)Lcats/effect/Concurrent;
      17: aload_0
      18: aload_1
      19: invokedynamic #184,  0            // InvokeDynamic #3:apply:(Ldev/profunktor/redis4cats/connection/RedisStatefulClusterConnection;Ljava/lang/String;)Lscala/Function0;
      24: invokeinterface #128,  2          // InterfaceMethod cats/effect/Concurrent.delay:(Lscala/Function0;)Ljava/lang/Object;
      29: aload_0
      30: getfield      #157                // Field blocker:Lscala/concurrent/ExecutionContext;
      33: aload_0
      34: getfield      #159                // Field dev$profunktor$redis4cats$connection$RedisStatefulClusterConnection$$evidence$7:Lcats/effect/Concurrent;
      37: aload_0
      38: getfield      #161                // Field dev$profunktor$redis4cats$connection$RedisStatefulClusterConnection$$evidence$8:Lcats/effect/ContextShift;
      41: invokevirtual #165                // Method dev/profunktor/redis4cats/effect/JRFuture$.fromCompletableFuture:(Ljava/lang/Object;Lscala/concurrent/ExecutionContext;Lcats/effect/Concurrent;Lcats/effect/ContextShift;)Ljava/lang/Object;
      44: aload_0
      45: getfield      #159                // Field dev$profunktor$redis4cats$connection$RedisStatefulClusterConnection$$evidence$7:Lcats/effect/Concurrent;
      48: invokevirtual #188                // Method cats/syntax/package$all$.toFlatMapOps:(Ljava/lang/Object;Lcats/FlatMap;)Lcats/FlatMap$Ops;
      51: aload_0
      52: invokedynamic #199,  0            // InvokeDynamic #4:apply:(Ldev/profunktor/redis4cats/connection/RedisStatefulClusterConnection;)Lscala/Function1;
      57: invokeinterface #203,  2          // InterfaceMethod cats/FlatMap$Ops.flatMap:(Lscala/Function1;)Ljava/lang/Object;
      62: areturn

  public <G> dev.profunktor.redis4cats.connection.RedisConnection<G, K, V> liftK(cats.effect.Concurrent<G>, cats.effect.ContextShift<G>);
    Code:
       0: new           #211                // class scala/runtime/LazyRef
       3: dup
       4: invokespecial #213                // Method scala/runtime/LazyRef."<init>":()V
       7: astore_3
       8: aconst_null
       9: astore        4
      11: new           #2                  // class dev/profunktor/redis4cats/connection/RedisStatefulClusterConnection
      14: dup
      15: aload_0
      16: getfield      #215                // Field conn:Lio/lettuce/core/cluster/api/StatefulRedisClusterConnection;
      19: aload_0
      20: getfield      #157                // Field blocker:Lscala/concurrent/ExecutionContext;
      23: aload_1
      24: aload_2
      25: invokespecial #218                // Method "<init>":(Lio/lettuce/core/cluster/api/StatefulRedisClusterConnection;Lscala/concurrent/ExecutionContext;Lcats/effect/Concurrent;Lcats/effect/ContextShift;)V
      28: areturn

  private final void Concurrent$F$lzycompute$2();
    Code:
       0: aload_0
       1: dup
       2: astore_1
       3: monitorenter
       4: aload_0
       5: getfield      #70                 // Field Concurrent$F$module:Ldev/profunktor/redis4cats/connection/RedisStatefulClusterConnection$Concurrent$F$;
       8: ifnonnull     23
      11: aload_0
      12: new           #27                 // class dev/profunktor/redis4cats/connection/RedisStatefulClusterConnection$Concurrent$F$
      15: dup
      16: aload_0
      17: invokespecial #223                // Method dev/profunktor/redis4cats/connection/RedisStatefulClusterConnection$Concurrent$F$."<init>":(Ldev/profunktor/redis4cats/connection/RedisStatefulClusterConnection;)V
      20: putfield      #70                 // Field Concurrent$F$module:Ldev/profunktor/redis4cats/connection/RedisStatefulClusterConnection$Concurrent$F$;
      23: aload_1
      24: monitorexit
      25: goto          31
      28: aload_1
      29: monitorexit
      30: athrow
      31: return
    Exception table:
       from    to  target type
           4    23    28   any

  public static final io.lettuce.core.cluster.api.async.RedisAdvancedClusterAsyncCommands $anonfun$clusterAsync$1(dev.profunktor.redis4cats.connection.RedisStatefulClusterConnection);
    Code:
       0: aload_0
       1: getfield      #215                // Field conn:Lio/lettuce/core/cluster/api/StatefulRedisClusterConnection;
       4: invokeinterface #230,  1          // InterfaceMethod io/lettuce/core/cluster/api/StatefulRedisClusterConnection.async:()Lio/lettuce/core/cluster/api/async/RedisAdvancedClusterAsyncCommands;
       9: areturn

  public static final io.lettuce.core.cluster.api.sync.RedisAdvancedClusterCommands $anonfun$clusterSync$1(dev.profunktor.redis4cats.connection.RedisStatefulClusterConnection);
    Code:
       0: aload_0
       1: getfield      #215                // Field conn:Lio/lettuce/core/cluster/api/StatefulRedisClusterConnection;
       4: invokeinterface #232,  1          // InterfaceMethod io/lettuce/core/cluster/api/StatefulRedisClusterConnection.sync:()Lio/lettuce/core/cluster/api/sync/RedisAdvancedClusterCommands;
       9: areturn

  public static final java.util.concurrent.CompletableFuture $anonfun$close$2(dev.profunktor.redis4cats.connection.RedisStatefulClusterConnection);
    Code:
       0: aload_0
       1: getfield      #215                // Field conn:Lio/lettuce/core/cluster/api/StatefulRedisClusterConnection;
       4: invokeinterface #235,  1          // InterfaceMethod io/lettuce/core/cluster/api/StatefulRedisClusterConnection.closeAsync:()Ljava/util/concurrent/CompletableFuture;
       9: areturn

  public static final java.util.concurrent.CompletableFuture $anonfun$byNode$1(dev.profunktor.redis4cats.connection.RedisStatefulClusterConnection, java.lang.String);
    Code:
       0: aload_0
       1: getfield      #215                // Field conn:Lio/lettuce/core/cluster/api/StatefulRedisClusterConnection;
       4: aload_1
       5: invokeinterface #240,  2          // InterfaceMethod io/lettuce/core/cluster/api/StatefulRedisClusterConnection.getConnectionAsync:(Ljava/lang/String;)Ljava/util/concurrent/CompletableFuture;
      10: areturn

  public static final io.lettuce.core.api.async.RedisAsyncCommands $anonfun$byNode$3(io.lettuce.core.api.StatefulRedisConnection);
    Code:
       0: aload_0
       1: invokeinterface #248,  1          // InterfaceMethod io/lettuce/core/api/StatefulRedisConnection.async:()Lio/lettuce/core/api/async/RedisAsyncCommands;
       6: areturn

  public static final java.lang.Object $anonfun$byNode$2(dev.profunktor.redis4cats.connection.RedisStatefulClusterConnection, io.lettuce.core.api.StatefulRedisConnection);
    Code:
       0: aload_0
       1: invokespecial #81                 // Method Concurrent$F:()Ldev/profunktor/redis4cats/connection/RedisStatefulClusterConnection$Concurrent$F$;
       4: aload_0
       5: getfield      #83                 // Field F:Ldev/profunktor/redis4cats/connection/RedisStatefulClusterConnection$E$F$RedisStatefulClusterConnection;
       8: invokevirtual #87                 // Method dev/profunktor/redis4cats/connection/RedisStatefulClusterConnection$Concurrent$F$.E$F$RedisStatefulClusterConnection$Concurrent:(Ldev/profunktor/redis4cats/connection/RedisStatefulClusterConnection$E$F$RedisStatefulClusterConnection;)Lcats/effect/Concurrent;
      11: aload_1
      12: invokedynamic #257,  0            // InvokeDynamic #5:apply:(Lio/lettuce/core/api/StatefulRedisConnection;)Lscala/Function0;
      17: invokeinterface #128,  2          // InterfaceMethod cats/effect/Concurrent.delay:(Lscala/Function0;)Ljava/lang/Object;
      22: areturn

  private final dev.profunktor.redis4cats.connection.RedisStatefulClusterConnection$Concurrent$G$3$ Concurrent$G$lzycompute$2(scala.runtime.LazyRef, cats.effect.Concurrent, cats.effect.ContextShift);
    Code:
       0: aload_1
       1: dup
       2: astore        4
       4: monitorenter
       5: aload_1
       6: invokevirtual #266                // Method scala/runtime/LazyRef.initialized:()Z
       9: ifeq          22
      12: aload_1
      13: invokevirtual #269                // Method scala/runtime/LazyRef.value:()Ljava/lang/Object;
      16: checkcast     #30                 // class dev/profunktor/redis4cats/connection/RedisStatefulClusterConnection$Concurrent$G$3$
      19: goto          39
      22: aload_1
      23: new           #30                 // class dev/profunktor/redis4cats/connection/RedisStatefulClusterConnection$Concurrent$G$3$
      26: dup
      27: aload_0
      28: aload_2
      29: aload_3
      30: invokespecial #272                // Method dev/profunktor/redis4cats/connection/RedisStatefulClusterConnection$Concurrent$G$3$."<init>":(Ldev/profunktor/redis4cats/connection/RedisStatefulClusterConnection;Lcats/effect/Concurrent;Lcats/effect/ContextShift;)V
      33: invokevirtual #275                // Method scala/runtime/LazyRef.initialize:(Ljava/lang/Object;)Ljava/lang/Object;
      36: checkcast     #30                 // class dev/profunktor/redis4cats/connection/RedisStatefulClusterConnection$Concurrent$G$3$
      39: astore        5
      41: aload         4
      43: monitorexit
      44: aload         5
      46: goto          53
      49: aload         4
      51: monitorexit
      52: athrow
      53: areturn
    Exception table:
       from    to  target type
           5    41    49   any

  private final dev.profunktor.redis4cats.connection.RedisStatefulClusterConnection$Concurrent$G$3$ Concurrent$G$4(scala.runtime.LazyRef, cats.effect.Concurrent, cats.effect.ContextShift);
    Code:
       0: aload_1
       1: invokevirtual #266                // Method scala/runtime/LazyRef.initialized:()Z
       4: ifeq          17
       7: aload_1
       8: invokevirtual #269                // Method scala/runtime/LazyRef.value:()Ljava/lang/Object;
      11: checkcast     #30                 // class dev/profunktor/redis4cats/connection/RedisStatefulClusterConnection$Concurrent$G$3$
      14: goto          24
      17: aload_0
      18: aload_1
      19: aload_2
      20: aload_3
      21: invokespecial #280                // Method Concurrent$G$lzycompute$2:(Lscala/runtime/LazyRef;Lcats/effect/Concurrent;Lcats/effect/ContextShift;)Ldev/profunktor/redis4cats/connection/RedisStatefulClusterConnection$Concurrent$G$3$;
      24: areturn

  public dev.profunktor.redis4cats.connection.RedisStatefulClusterConnection(io.lettuce.core.cluster.api.StatefulRedisClusterConnection<K, V>, scala.concurrent.ExecutionContext, cats.effect.Concurrent<F>, cats.effect.ContextShift<F>);
    Code:
       0: aload_0
       1: aload_1
       2: putfield      #215                // Field conn:Lio/lettuce/core/cluster/api/StatefulRedisClusterConnection;
       5: aload_0
       6: aload_2
       7: putfield      #157                // Field blocker:Lscala/concurrent/ExecutionContext;
      10: aload_0
      11: aload_3
      12: putfield      #159                // Field dev$profunktor$redis4cats$connection$RedisStatefulClusterConnection$$evidence$7:Lcats/effect/Concurrent;
      15: aload_0
      16: aload         4
      18: putfield      #161                // Field dev$profunktor$redis4cats$connection$RedisStatefulClusterConnection$$evidence$8:Lcats/effect/ContextShift;
      21: aload_0
      22: invokespecial #284                // Method java/lang/Object."<init>":()V
      25: aload_0
      26: aconst_null
      27: putfield      #83                 // Field F:Ldev/profunktor/redis4cats/connection/RedisStatefulClusterConnection$E$F$RedisStatefulClusterConnection;
      30: aload_0
      31: aload_0
      32: getfield      #286                // Field bitmap$init$0:B
      35: iconst_2
      36: ior
      37: i2b
      38: putfield      #286                // Field bitmap$init$0:B
      41: return

  private static java.lang.Object $deserializeLambda$(java.lang.invoke.SerializedLambda);
    Code:
       0: aload_0
       1: invokedynamic #298,  0            // InvokeDynamic #6:lambdaDeserialize:(Ljava/lang/invoke/SerializedLambda;)Ljava/lang/Object;
       6: areturn
}
