Compiled from "CertificatePinner.java"
public final class io.dekorate.deps.okhttp3.CertificatePinner$Builder {
  private final java.util.List<io.dekorate.deps.okhttp3.CertificatePinner$Pin> pins;

  public io.dekorate.deps.okhttp3.CertificatePinner$Builder();
    Code:
       0: aload_0
       1: invokespecial #18                 // Method java/lang/Object."<init>":()V
       4: aload_0
       5: new           #20                 // class java/util/ArrayList
       8: dup
       9: invokespecial #21                 // Method java/util/ArrayList."<init>":()V
      12: putfield      #23                 // Field pins:Ljava/util/List;
      15: return

  public io.dekorate.deps.okhttp3.CertificatePinner$Builder add(java.lang.String, java.lang.String...);
    Code:
       0: aload_1
       1: ifnonnull     14
       4: new           #29                 // class java/lang/NullPointerException
       7: dup
       8: ldc           #31                 // String pattern == null
      10: invokespecial #34                 // Method java/lang/NullPointerException."<init>":(Ljava/lang/String;)V
      13: athrow
      14: aload_2
      15: astore_3
      16: aload_3
      17: arraylength
      18: istore        4
      20: iconst_0
      21: istore        5
      23: iload         5
      25: iload         4
      27: if_icmpge     62
      30: aload_3
      31: iload         5
      33: aaload
      34: astore        6
      36: aload_0
      37: getfield      #23                 // Field pins:Ljava/util/List;
      40: new           #7                  // class io/dekorate/deps/okhttp3/CertificatePinner$Pin
      43: dup
      44: aload_1
      45: aload         6
      47: invokespecial #39                 // Method io/dekorate/deps/okhttp3/CertificatePinner$Pin."<init>":(Ljava/lang/String;Ljava/lang/String;)V
      50: invokeinterface #44,  2           // InterfaceMethod java/util/List.add:(Ljava/lang/Object;)Z
      55: pop
      56: iinc          5, 1
      59: goto          23
      62: aload_0
      63: areturn

  public io.dekorate.deps.okhttp3.CertificatePinner build();
    Code:
       0: new           #9                  // class io/dekorate/deps/okhttp3/CertificatePinner
       3: dup
       4: new           #51                 // class java/util/LinkedHashSet
       7: dup
       8: aload_0
       9: getfield      #23                 // Field pins:Ljava/util/List;
      12: invokespecial #54                 // Method java/util/LinkedHashSet."<init>":(Ljava/util/Collection;)V
      15: aconst_null
      16: invokespecial #57                 // Method io/dekorate/deps/okhttp3/CertificatePinner."<init>":(Ljava/util/Set;Lio/dekorate/deps/okhttp3/internal/tls/CertificateChainCleaner;)V
      19: areturn
}
