Compiled from "Request.java"
public final class io.dekorate.deps.okhttp3.Request {
  final io.dekorate.deps.okhttp3.HttpUrl url;

  final java.lang.String method;

  final io.dekorate.deps.okhttp3.Headers headers;

  final io.dekorate.deps.okhttp3.RequestBody body;

  final java.util.Map<java.lang.Class<?>, java.lang.Object> tags;

  private volatile io.dekorate.deps.okhttp3.CacheControl cacheControl;

  io.dekorate.deps.okhttp3.Request(io.dekorate.deps.okhttp3.Request$Builder);
    Code:
       0: aload_0
       1: invokespecial #31                 // Method java/lang/Object."<init>":()V
       4: aload_0
       5: aload_1
       6: getfield      #33                 // Field io/dekorate/deps/okhttp3/Request$Builder.url:Lio/dekorate/deps/okhttp3/HttpUrl;
       9: putfield      #34                 // Field url:Lio/dekorate/deps/okhttp3/HttpUrl;
      12: aload_0
      13: aload_1
      14: getfield      #36                 // Field io/dekorate/deps/okhttp3/Request$Builder.method:Ljava/lang/String;
      17: putfield      #37                 // Field method:Ljava/lang/String;
      20: aload_0
      21: aload_1
      22: getfield      #40                 // Field io/dekorate/deps/okhttp3/Request$Builder.headers:Lio/dekorate/deps/okhttp3/Headers$Builder;
      25: invokevirtual #44                 // Method io/dekorate/deps/okhttp3/Headers$Builder.build:()Lio/dekorate/deps/okhttp3/Headers;
      28: putfield      #46                 // Field headers:Lio/dekorate/deps/okhttp3/Headers;
      31: aload_0
      32: aload_1
      33: getfield      #48                 // Field io/dekorate/deps/okhttp3/Request$Builder.body:Lio/dekorate/deps/okhttp3/RequestBody;
      36: putfield      #49                 // Field body:Lio/dekorate/deps/okhttp3/RequestBody;
      39: aload_0
      40: aload_1
      41: getfield      #51                 // Field io/dekorate/deps/okhttp3/Request$Builder.tags:Ljava/util/Map;
      44: invokestatic  #57                 // Method io/dekorate/deps/okhttp3/internal/Util.immutableMap:(Ljava/util/Map;)Ljava/util/Map;
      47: putfield      #58                 // Field tags:Ljava/util/Map;
      50: return

  public io.dekorate.deps.okhttp3.HttpUrl url();
    Code:
       0: aload_0
       1: getfield      #34                 // Field url:Lio/dekorate/deps/okhttp3/HttpUrl;
       4: areturn

  public java.lang.String method();
    Code:
       0: aload_0
       1: getfield      #37                 // Field method:Ljava/lang/String;
       4: areturn

  public io.dekorate.deps.okhttp3.Headers headers();
    Code:
       0: aload_0
       1: getfield      #46                 // Field headers:Lio/dekorate/deps/okhttp3/Headers;
       4: areturn

  public java.lang.String header(java.lang.String);
    Code:
       0: aload_0
       1: getfield      #46                 // Field headers:Lio/dekorate/deps/okhttp3/Headers;
       4: aload_1
       5: invokevirtual #69                 // Method io/dekorate/deps/okhttp3/Headers.get:(Ljava/lang/String;)Ljava/lang/String;
       8: areturn

  public java.util.List<java.lang.String> headers(java.lang.String);
    Code:
       0: aload_0
       1: getfield      #46                 // Field headers:Lio/dekorate/deps/okhttp3/Headers;
       4: aload_1
       5: invokevirtual #75                 // Method io/dekorate/deps/okhttp3/Headers.values:(Ljava/lang/String;)Ljava/util/List;
       8: areturn

  public io.dekorate.deps.okhttp3.RequestBody body();
    Code:
       0: aload_0
       1: getfield      #49                 // Field body:Lio/dekorate/deps/okhttp3/RequestBody;
       4: areturn

  public java.lang.Object tag();
    Code:
       0: aload_0
       1: ldc           #4                  // class java/lang/Object
       3: invokevirtual #81                 // Method tag:(Ljava/lang/Class;)Ljava/lang/Object;
       6: areturn

  public <T> T tag(java.lang.Class<? extends T>);
    Code:
       0: aload_1
       1: aload_0
       2: getfield      #58                 // Field tags:Ljava/util/Map;
       5: aload_1
       6: invokeinterface #87,  2           // InterfaceMethod java/util/Map.get:(Ljava/lang/Object;)Ljava/lang/Object;
      11: invokevirtual #92                 // Method java/lang/Class.cast:(Ljava/lang/Object;)Ljava/lang/Object;
      14: areturn

  public io.dekorate.deps.okhttp3.Request$Builder newBuilder();
    Code:
       0: new           #7                  // class io/dekorate/deps/okhttp3/Request$Builder
       3: dup
       4: aload_0
       5: invokespecial #100                // Method io/dekorate/deps/okhttp3/Request$Builder."<init>":(Lio/dekorate/deps/okhttp3/Request;)V
       8: areturn

  public io.dekorate.deps.okhttp3.CacheControl cacheControl();
    Code:
       0: aload_0
       1: getfield      #103                // Field cacheControl:Lio/dekorate/deps/okhttp3/CacheControl;
       4: astore_1
       5: aload_1
       6: ifnull        13
       9: aload_1
      10: goto          25
      13: aload_0
      14: aload_0
      15: getfield      #46                 // Field headers:Lio/dekorate/deps/okhttp3/Headers;
      18: invokestatic  #109                // Method io/dekorate/deps/okhttp3/CacheControl.parse:(Lio/dekorate/deps/okhttp3/Headers;)Lio/dekorate/deps/okhttp3/CacheControl;
      21: dup_x1
      22: putfield      #103                // Field cacheControl:Lio/dekorate/deps/okhttp3/CacheControl;
      25: areturn

  public boolean isHttps();
    Code:
       0: aload_0
       1: getfield      #34                 // Field url:Lio/dekorate/deps/okhttp3/HttpUrl;
       4: invokevirtual #116                // Method io/dekorate/deps/okhttp3/HttpUrl.isHttps:()Z
       7: ireturn

  public java.lang.String toString();
    Code:
       0: new           #119                // class java/lang/StringBuilder
       3: dup
       4: invokespecial #120                // Method java/lang/StringBuilder."<init>":()V
       7: ldc           #122                // String Request{method=
       9: invokevirtual #126                // Method java/lang/StringBuilder.append:(Ljava/lang/String;)Ljava/lang/StringBuilder;
      12: aload_0
      13: getfield      #37                 // Field method:Ljava/lang/String;
      16: invokevirtual #126                // Method java/lang/StringBuilder.append:(Ljava/lang/String;)Ljava/lang/StringBuilder;
      19: ldc           #128                // String , url=
      21: invokevirtual #126                // Method java/lang/StringBuilder.append:(Ljava/lang/String;)Ljava/lang/StringBuilder;
      24: aload_0
      25: getfield      #34                 // Field url:Lio/dekorate/deps/okhttp3/HttpUrl;
      28: invokevirtual #131                // Method java/lang/StringBuilder.append:(Ljava/lang/Object;)Ljava/lang/StringBuilder;
      31: ldc           #133                // String , tags=
      33: invokevirtual #126                // Method java/lang/StringBuilder.append:(Ljava/lang/String;)Ljava/lang/StringBuilder;
      36: aload_0
      37: getfield      #58                 // Field tags:Ljava/util/Map;
      40: invokevirtual #131                // Method java/lang/StringBuilder.append:(Ljava/lang/Object;)Ljava/lang/StringBuilder;
      43: bipush        125
      45: invokevirtual #136                // Method java/lang/StringBuilder.append:(C)Ljava/lang/StringBuilder;
      48: invokevirtual #138                // Method java/lang/StringBuilder.toString:()Ljava/lang/String;
      51: areturn
}
