Compiled from "WebSocketListener.java"
public abstract class io.dekorate.deps.okhttp3.WebSocketListener {
  public io.dekorate.deps.okhttp3.WebSocketListener();
    Code:
       0: aload_0
       1: invokespecial #9                  // Method java/lang/Object."<init>":()V
       4: return

  public void onOpen(io.dekorate.deps.okhttp3.WebSocket, io.dekorate.deps.okhttp3.Response);
    Code:
       0: return

  public void onMessage(io.dekorate.deps.okhttp3.WebSocket, java.lang.String);
    Code:
       0: return

  public void onMessage(io.dekorate.deps.okhttp3.WebSocket, io.dekorate.deps.okio.ByteString);
    Code:
       0: return

  public void onClosing(io.dekorate.deps.okhttp3.WebSocket, int, java.lang.String);
    Code:
       0: return

  public void onClosed(io.dekorate.deps.okhttp3.WebSocket, int, java.lang.String);
    Code:
       0: return

  public void onFailure(io.dekorate.deps.okhttp3.WebSocket, java.lang.Throwable, io.dekorate.deps.okhttp3.Response);
    Code:
       0: return
}
