Compiled from "ConstantScoreQueryBuilderFactory.java"
class io.manbang.ebatis.core.builder.ConstantScoreQueryBuilderFactory extends io.manbang.ebatis.core.builder.AbstractQueryBuilderFactory<org.elasticsearch.index.query.ConstantScoreQueryBuilder, io.manbang.ebatis.core.annotation.ConstantScore> {
  static final io.manbang.ebatis.core.builder.ConstantScoreQueryBuilderFactory INSTANCE;

  private io.manbang.ebatis.core.builder.ConstantScoreQueryBuilderFactory();
    Code:
       0: aload_0
       1: invokespecial #1                  // Method io/manbang/ebatis/core/builder/AbstractQueryBuilderFactory."<init>":()V
       4: return

  protected org.elasticsearch.index.query.ConstantScoreQueryBuilder doCreate(io.manbang.ebatis.core.meta.ConditionMeta, java.lang.Object);
    Code:
       0: getstatic     #2                  // Field io/manbang/ebatis/core/builder/AutoQueryBuilderFactory.INSTANCE:Lio/manbang/ebatis/core/builder/AutoQueryBuilderFactory;
       3: aload_1
       4: aload_2
       5: invokevirtual #3                  // Method io/manbang/ebatis/core/builder/AutoQueryBuilderFactory.create:(Lio/manbang/ebatis/core/meta/ConditionMeta;Ljava/lang/Object;)Lorg/elasticsearch/index/query/QueryBuilder;
       8: astore_3
       9: aload_3
      10: invokestatic  #4                  // Method org/elasticsearch/index/query/QueryBuilders.constantScoreQuery:(Lorg/elasticsearch/index/query/QueryBuilder;)Lorg/elasticsearch/index/query/ConstantScoreQueryBuilder;
      13: areturn

  protected org.elasticsearch.index.query.QueryBuilder doCreate(io.manbang.ebatis.core.meta.ConditionMeta, java.lang.Object);
    Code:
       0: aload_0
       1: aload_1
       2: aload_2
       3: invokevirtual #5                  // Method doCreate:(Lio/manbang/ebatis/core/meta/ConditionMeta;Ljava/lang/Object;)Lorg/elasticsearch/index/query/ConstantScoreQueryBuilder;
       6: areturn

  static {};
    Code:
       0: new           #6                  // class io/manbang/ebatis/core/builder/ConstantScoreQueryBuilderFactory
       3: dup
       4: invokespecial #7                  // Method "<init>":()V
       7: putstatic     #8                  // Field INSTANCE:Lio/manbang/ebatis/core/builder/ConstantScoreQueryBuilderFactory;
      10: return
}
