Compiled from "WildcardQueryBuilderFactory.java"
class io.manbang.ebatis.core.builder.WildcardQueryBuilderFactory extends io.manbang.ebatis.core.builder.AbstractQueryBuilderFactory<org.elasticsearch.index.query.WildcardQueryBuilder, io.manbang.ebatis.core.annotation.Wildcard> {
  static final io.manbang.ebatis.core.builder.WildcardQueryBuilderFactory INSTANCE;

  io.manbang.ebatis.core.builder.WildcardQueryBuilderFactory();
    Code:
       0: aload_0
       1: invokespecial #1                  // Method io/manbang/ebatis/core/builder/AbstractQueryBuilderFactory."<init>":()V
       4: return

  protected void setAnnotationMeta(org.elasticsearch.index.query.WildcardQueryBuilder, io.manbang.ebatis.core.annotation.Wildcard);
    Code:
       0: aload_1
       1: aload_2
       2: invokeinterface #2,  1            // InterfaceMethod io/manbang/ebatis/core/annotation/Wildcard.rewrite:()Ljava/lang/String;
       7: invokestatic  #3                  // Method org/apache/commons/lang3/StringUtils.trimToNull:(Ljava/lang/String;)Ljava/lang/String;
      10: invokevirtual #4                  // Method org/elasticsearch/index/query/WildcardQueryBuilder.rewrite:(Ljava/lang/String;)Lorg/elasticsearch/index/query/WildcardQueryBuilder;
      13: pop
      14: return

  protected org.elasticsearch.index.query.WildcardQueryBuilder doCreate(io.manbang.ebatis.core.meta.ConditionMeta, java.lang.Object);
    Code:
       0: aload_1
       1: invokeinterface #5,  1            // InterfaceMethod io/manbang/ebatis/core/meta/ConditionMeta.getName:()Ljava/lang/String;
       6: aload_2
       7: invokestatic  #6                  // Method java/lang/String.valueOf:(Ljava/lang/Object;)Ljava/lang/String;
      10: invokestatic  #7                  // Method org/elasticsearch/index/query/QueryBuilders.wildcardQuery:(Ljava/lang/String;Ljava/lang/String;)Lorg/elasticsearch/index/query/WildcardQueryBuilder;
      13: areturn

  protected org.elasticsearch.index.query.QueryBuilder doCreate(io.manbang.ebatis.core.meta.ConditionMeta, java.lang.Object);
    Code:
       0: aload_0
       1: aload_1
       2: aload_2
       3: invokevirtual #8                  // Method doCreate:(Lio/manbang/ebatis/core/meta/ConditionMeta;Ljava/lang/Object;)Lorg/elasticsearch/index/query/WildcardQueryBuilder;
       6: areturn

  protected void setAnnotationMeta(org.elasticsearch.index.query.QueryBuilder, java.lang.annotation.Annotation);
    Code:
       0: aload_0
       1: aload_1
       2: checkcast     #9                  // class org/elasticsearch/index/query/WildcardQueryBuilder
       5: aload_2
       6: checkcast     #10                 // class io/manbang/ebatis/core/annotation/Wildcard
       9: invokevirtual #11                 // Method setAnnotationMeta:(Lorg/elasticsearch/index/query/WildcardQueryBuilder;Lio/manbang/ebatis/core/annotation/Wildcard;)V
      12: return

  static {};
    Code:
       0: new           #12                 // class io/manbang/ebatis/core/builder/WildcardQueryBuilderFactory
       3: dup
       4: invokespecial #13                 // Method "<init>":()V
       7: putstatic     #14                 // Field INSTANCE:Lio/manbang/ebatis/core/builder/WildcardQueryBuilderFactory;
      10: return
}
