Compiled from "TypePatternBasedPerClauseImpl.java"
public class org.aspectj.internal.lang.reflect.TypePatternBasedPerClauseImpl extends org.aspectj.internal.lang.reflect.PerClauseImpl implements org.aspectj.lang.reflect.TypePatternBasedPerClause {
  private org.aspectj.lang.reflect.TypePattern typePattern;

  public org.aspectj.internal.lang.reflect.TypePatternBasedPerClauseImpl(org.aspectj.lang.reflect.PerClauseKind, java.lang.String);
    Code:
       0: aload_0
       1: aload_1
       2: invokespecial #1                  // Method org/aspectj/internal/lang/reflect/PerClauseImpl."<init>":(Lorg/aspectj/lang/reflect/PerClauseKind;)V
       5: aload_0
       6: new           #2                  // class org/aspectj/internal/lang/reflect/TypePatternImpl
       9: dup
      10: aload_2
      11: invokespecial #3                  // Method org/aspectj/internal/lang/reflect/TypePatternImpl."<init>":(Ljava/lang/String;)V
      14: putfield      #4                  // Field typePattern:Lorg/aspectj/lang/reflect/TypePattern;
      17: return

  public org.aspectj.lang.reflect.TypePattern getTypePattern();
    Code:
       0: aload_0
       1: getfield      #4                  // Field typePattern:Lorg/aspectj/lang/reflect/TypePattern;
       4: areturn

  public java.lang.String toString();
    Code:
       0: new           #5                  // class java/lang/StringBuilder
       3: dup
       4: invokespecial #6                  // Method java/lang/StringBuilder."<init>":()V
       7: ldc           #7                  // String pertypewithin(
       9: invokevirtual #8                  // Method java/lang/StringBuilder.append:(Ljava/lang/String;)Ljava/lang/StringBuilder;
      12: aload_0
      13: getfield      #4                  // Field typePattern:Lorg/aspectj/lang/reflect/TypePattern;
      16: invokeinterface #9,  1            // InterfaceMethod org/aspectj/lang/reflect/TypePattern.asString:()Ljava/lang/String;
      21: invokevirtual #8                  // Method java/lang/StringBuilder.append:(Ljava/lang/String;)Ljava/lang/StringBuilder;
      24: ldc           #10                 // String )
      26: invokevirtual #8                  // Method java/lang/StringBuilder.append:(Ljava/lang/String;)Ljava/lang/StringBuilder;
      29: invokevirtual #11                 // Method java/lang/StringBuilder.toString:()Ljava/lang/String;
      32: areturn
}
