Compiled from "ObjectArrays.java"
final class org.glassfish.jersey.internal.guava.ObjectArrays {
  static final java.lang.Object[] EMPTY_ARRAY;

  private org.glassfish.jersey.internal.guava.ObjectArrays();
    Code:
       0: aload_0
       1: invokespecial #1                  // Method java/lang/Object."<init>":()V
       4: return

  public static <T> T[] newArray(T[], int);
    Code:
       0: aload_0
       1: iload_1
       2: invokestatic  #2                  // Method org/glassfish/jersey/internal/guava/Platform.newArray:([Ljava/lang/Object;I)[Ljava/lang/Object;
       5: areturn

  static <T> T[] arraysCopyOf(T[], int);
    Code:
       0: aload_0
       1: iload_1
       2: invokestatic  #3                  // Method newArray:([Ljava/lang/Object;I)[Ljava/lang/Object;
       5: astore_2
       6: aload_0
       7: iconst_0
       8: aload_2
       9: iconst_0
      10: aload_0
      11: arraylength
      12: iload_1
      13: invokestatic  #4                  // Method java/lang/Math.min:(II)I
      16: invokestatic  #5                  // Method java/lang/System.arraycopy:(Ljava/lang/Object;ILjava/lang/Object;II)V
      19: aload_2
      20: areturn

  static {};
    Code:
       0: iconst_0
       1: anewarray     #6                  // class java/lang/Object
       4: putstatic     #7                  // Field EMPTY_ARRAY:[Ljava/lang/Object;
       7: return
}
