Compiled from "StandardTable.java"
abstract class org.glassfish.jersey.internal.guava.StandardTable$TableSet<T> extends org.glassfish.jersey.internal.guava.Sets$ImprovedAbstractSet<T> {
  final org.glassfish.jersey.internal.guava.StandardTable this$0;

  private org.glassfish.jersey.internal.guava.StandardTable$TableSet(org.glassfish.jersey.internal.guava.StandardTable);
    Code:
       0: aload_0
       1: aload_1
       2: putfield      #2                  // Field this$0:Lorg/glassfish/jersey/internal/guava/StandardTable;
       5: aload_0
       6: invokespecial #3                  // Method org/glassfish/jersey/internal/guava/Sets$ImprovedAbstractSet."<init>":()V
       9: return

  public boolean isEmpty();
    Code:
       0: aload_0
       1: getfield      #2                  // Field this$0:Lorg/glassfish/jersey/internal/guava/StandardTable;
       4: invokestatic  #4                  // Method org/glassfish/jersey/internal/guava/StandardTable.access$400:(Lorg/glassfish/jersey/internal/guava/StandardTable;)Ljava/util/Map;
       7: invokeinterface #5,  1            // InterfaceMethod java/util/Map.isEmpty:()Z
      12: ireturn

  public void clear();
    Code:
       0: aload_0
       1: getfield      #2                  // Field this$0:Lorg/glassfish/jersey/internal/guava/StandardTable;
       4: invokestatic  #4                  // Method org/glassfish/jersey/internal/guava/StandardTable.access$400:(Lorg/glassfish/jersey/internal/guava/StandardTable;)Ljava/util/Map;
       7: invokeinterface #6,  1            // InterfaceMethod java/util/Map.clear:()V
      12: return

  org.glassfish.jersey.internal.guava.StandardTable$TableSet(org.glassfish.jersey.internal.guava.StandardTable, org.glassfish.jersey.internal.guava.StandardTable$1);
    Code:
       0: aload_0
       1: aload_1
       2: invokespecial #1                  // Method "<init>":(Lorg/glassfish/jersey/internal/guava/StandardTable;)V
       5: return
}
