Compiled from "Tables.java"
final class org.glassfish.jersey.internal.guava.Tables$TransposeTable$1 implements java.util.function.Function<org.glassfish.jersey.internal.guava.Table$Cell<?, ?, ?>, org.glassfish.jersey.internal.guava.Table$Cell<?, ?, ?>> {
  org.glassfish.jersey.internal.guava.Tables$TransposeTable$1();
    Code:
       0: aload_0
       1: invokespecial #1                  // Method java/lang/Object."<init>":()V
       4: return

  public org.glassfish.jersey.internal.guava.Table$Cell<?, ?, ?> apply(org.glassfish.jersey.internal.guava.Table$Cell<?, ?, ?>);
    Code:
       0: aload_1
       1: invokeinterface #2,  1            // InterfaceMethod org/glassfish/jersey/internal/guava/Table$Cell.getColumnKey:()Ljava/lang/Object;
       6: aload_1
       7: invokeinterface #3,  1            // InterfaceMethod org/glassfish/jersey/internal/guava/Table$Cell.getRowKey:()Ljava/lang/Object;
      12: aload_1
      13: invokeinterface #4,  1            // InterfaceMethod org/glassfish/jersey/internal/guava/Table$Cell.getValue:()Ljava/lang/Object;
      18: invokestatic  #5                  // Method org/glassfish/jersey/internal/guava/Tables.immutableCell:(Ljava/lang/Object;Ljava/lang/Object;Ljava/lang/Object;)Lorg/glassfish/jersey/internal/guava/Table$Cell;
      21: areturn

  public java.lang.Object apply(java.lang.Object);
    Code:
       0: aload_0
       1: aload_1
       2: checkcast     #6                  // class org/glassfish/jersey/internal/guava/Table$Cell
       5: invokevirtual #7                  // Method apply:(Lorg/glassfish/jersey/internal/guava/Table$Cell;)Lorg/glassfish/jersey/internal/guava/Table$Cell;
       8: areturn
}
