Compiled from "StaticClaimsHandler.java"
public class org.apache.cxf.sts.claims.StaticClaimsHandler implements org.apache.cxf.sts.claims.ClaimsHandler {
  private static final java.util.logging.Logger LOG;

  private java.util.Map<java.lang.String, java.lang.String> globalClaims;

  public org.apache.cxf.sts.claims.StaticClaimsHandler();
    Code:
       0: aload_0
       1: invokespecial #1                  // Method java/lang/Object."<init>":()V
       4: return

  public void setGlobalClaims(java.util.Map<java.lang.String, java.lang.String>);
    Code:
       0: aload_0
       1: aload_1
       2: putfield      #2                  // Field globalClaims:Ljava/util/Map;
       5: return

  public java.util.Map<java.lang.String, java.lang.String> getGlobalClaims();
    Code:
       0: aload_0
       1: getfield      #2                  // Field globalClaims:Ljava/util/Map;
       4: areturn

  public java.util.List<java.net.URI> getSupportedClaimTypes();
    Code:
       0: new           #3                  // class java/util/ArrayList
       3: dup
       4: invokespecial #4                  // Method java/util/ArrayList."<init>":()V
       7: astore_1
       8: aload_0
       9: invokevirtual #5                  // Method getGlobalClaims:()Ljava/util/Map;
      12: invokeinterface #6,  1            // InterfaceMethod java/util/Map.keySet:()Ljava/util/Set;
      17: invokeinterface #7,  1            // InterfaceMethod java/util/Set.iterator:()Ljava/util/Iterator;
      22: astore_2
      23: aload_2
      24: invokeinterface #8,  1            // InterfaceMethod java/util/Iterator.hasNext:()Z
      29: ifeq          70
      32: aload_2
      33: invokeinterface #9,  1            // InterfaceMethod java/util/Iterator.next:()Ljava/lang/Object;
      38: checkcast     #10                 // class java/lang/String
      41: astore_3
      42: aload_1
      43: new           #11                 // class java/net/URI
      46: dup
      47: aload_3
      48: invokespecial #12                 // Method java/net/URI."<init>":(Ljava/lang/String;)V
      51: invokeinterface #13,  2           // InterfaceMethod java/util/List.add:(Ljava/lang/Object;)Z
      56: pop
      57: goto          67
      60: astore        4
      62: aload         4
      64: invokevirtual #15                 // Method java/net/URISyntaxException.printStackTrace:()V
      67: goto          23
      70: aload_1
      71: areturn
    Exception table:
       from    to  target type
          42    57    60   Class java/net/URISyntaxException

  public org.apache.cxf.sts.claims.ProcessedClaimCollection retrieveClaimValues(org.apache.cxf.rt.security.claims.ClaimCollection, org.apache.cxf.sts.claims.ClaimsParameters);
    Code:
       0: new           #16                 // class org/apache/cxf/sts/claims/ProcessedClaimCollection
       3: dup
       4: invokespecial #17                 // Method org/apache/cxf/sts/claims/ProcessedClaimCollection."<init>":()V
       7: astore_3
       8: aload_1
       9: invokevirtual #18                 // Method org/apache/cxf/rt/security/claims/ClaimCollection.iterator:()Ljava/util/Iterator;
      12: astore        4
      14: aload         4
      16: invokeinterface #8,  1            // InterfaceMethod java/util/Iterator.hasNext:()Z
      21: ifeq          165
      24: aload         4
      26: invokeinterface #9,  1            // InterfaceMethod java/util/Iterator.next:()Ljava/lang/Object;
      31: checkcast     #19                 // class org/apache/cxf/rt/security/claims/Claim
      34: astore        5
      36: aload_0
      37: invokevirtual #5                  // Method getGlobalClaims:()Ljava/util/Map;
      40: invokeinterface #6,  1            // InterfaceMethod java/util/Map.keySet:()Ljava/util/Set;
      45: aload         5
      47: invokevirtual #20                 // Method org/apache/cxf/rt/security/claims/Claim.getClaimType:()Ljava/net/URI;
      50: invokevirtual #21                 // Method java/net/URI.toString:()Ljava/lang/String;
      53: invokeinterface #22,  2           // InterfaceMethod java/util/Set.contains:(Ljava/lang/Object;)Z
      58: ifeq          121
      61: new           #23                 // class org/apache/cxf/sts/claims/ProcessedClaim
      64: dup
      65: invokespecial #24                 // Method org/apache/cxf/sts/claims/ProcessedClaim."<init>":()V
      68: astore        6
      70: aload         6
      72: aload         5
      74: invokevirtual #20                 // Method org/apache/cxf/rt/security/claims/Claim.getClaimType:()Ljava/net/URI;
      77: invokevirtual #25                 // Method org/apache/cxf/sts/claims/ProcessedClaim.setClaimType:(Ljava/net/URI;)V
      80: aload         6
      82: aload_2
      83: invokevirtual #26                 // Method org/apache/cxf/sts/claims/ClaimsParameters.getPrincipal:()Ljava/security/Principal;
      86: invokevirtual #27                 // Method org/apache/cxf/sts/claims/ProcessedClaim.setPrincipal:(Ljava/security/Principal;)V
      89: aload         6
      91: aload_0
      92: invokevirtual #5                  // Method getGlobalClaims:()Ljava/util/Map;
      95: aload         5
      97: invokevirtual #20                 // Method org/apache/cxf/rt/security/claims/Claim.getClaimType:()Ljava/net/URI;
     100: invokevirtual #21                 // Method java/net/URI.toString:()Ljava/lang/String;
     103: invokeinterface #28,  2           // InterfaceMethod java/util/Map.get:(Ljava/lang/Object;)Ljava/lang/Object;
     108: invokevirtual #29                 // Method org/apache/cxf/sts/claims/ProcessedClaim.addValue:(Ljava/lang/Object;)V
     111: aload_3
     112: aload         6
     114: invokevirtual #30                 // Method org/apache/cxf/sts/claims/ProcessedClaimCollection.add:(Ljava/lang/Object;)Z
     117: pop
     118: goto          162
     121: getstatic     #31                 // Field LOG:Ljava/util/logging/Logger;
     124: getstatic     #32                 // Field java/util/logging/Level.FINER:Ljava/util/logging/Level;
     127: invokevirtual #33                 // Method java/util/logging/Logger.isLoggable:(Ljava/util/logging/Level;)Z
     130: ifeq          162
     133: getstatic     #31                 // Field LOG:Ljava/util/logging/Logger;
     136: new           #34                 // class java/lang/StringBuilder
     139: dup
     140: invokespecial #35                 // Method java/lang/StringBuilder."<init>":()V
     143: ldc           #36                 // String Unsupported claim:
     145: invokevirtual #37                 // Method java/lang/StringBuilder.append:(Ljava/lang/String;)Ljava/lang/StringBuilder;
     148: aload         5
     150: invokevirtual #20                 // Method org/apache/cxf/rt/security/claims/Claim.getClaimType:()Ljava/net/URI;
     153: invokevirtual #38                 // Method java/lang/StringBuilder.append:(Ljava/lang/Object;)Ljava/lang/StringBuilder;
     156: invokevirtual #39                 // Method java/lang/StringBuilder.toString:()Ljava/lang/String;
     159: invokevirtual #40                 // Method java/util/logging/Logger.finer:(Ljava/lang/String;)V
     162: goto          14
     165: aload_3
     166: areturn

  static {};
    Code:
       0: ldc_w         #41                 // class org/apache/cxf/sts/claims/StaticClaimsHandler
       3: invokestatic  #42                 // Method org/apache/cxf/common/logging/LogUtils.getL7dLogger:(Ljava/lang/Class;)Ljava/util/logging/Logger;
       6: putstatic     #31                 // Field LOG:Ljava/util/logging/Logger;
       9: return
}
