Compiled from "PgForeignKey.java"
public class net.sf.xsd2pgschema.PgForeignKey {
  java.lang.String name;

  java.lang.String child_table;

  java.lang.String child_fields;

  java.lang.String parent_table;

  java.lang.String parent_fields;

  public net.sf.xsd2pgschema.PgForeignKey();
    Code:
       0: aload_0
       1: invokespecial #1                  // Method java/lang/Object."<init>":()V
       4: aload_0
       5: ldc           #2                  // String
       7: putfield      #3                  // Field name:Ljava/lang/String;
      10: aload_0
      11: aconst_null
      12: putfield      #4                  // Field child_table:Ljava/lang/String;
      15: aload_0
      16: aconst_null
      17: putfield      #5                  // Field child_fields:Ljava/lang/String;
      20: aload_0
      21: aconst_null
      22: putfield      #6                  // Field parent_table:Ljava/lang/String;
      25: aload_0
      26: aconst_null
      27: putfield      #7                  // Field parent_fields:Ljava/lang/String;
      30: return

  public void extractChildTable(net.sf.xsd2pgschema.PgSchema, org.w3c.dom.Node);
    Code:
       0: aload_0
       1: aload_0
       2: aload_1
       3: aload_2
       4: invokespecial #8                  // Method extractTable:(Lnet/sf/xsd2pgschema/PgSchema;Lorg/w3c/dom/Node;)Ljava/lang/String;
       7: putfield      #4                  // Field child_table:Ljava/lang/String;
      10: return

  public void extractParentTable(net.sf.xsd2pgschema.PgSchema, org.w3c.dom.Node, java.lang.String);
    Code:
       0: aload_1
       1: getfield      #9                  // Field net/sf/xsd2pgschema/PgSchema.xs_prefix_:Ljava/lang/String;
       4: astore        4
       6: aload_0
       7: aconst_null
       8: putfield      #6                  // Field parent_table:Ljava/lang/String;
      11: aload_2
      12: invokeinterface #10,  1           // InterfaceMethod org/w3c/dom/Node.getFirstChild:()Lorg/w3c/dom/Node;
      17: astore        5
      19: aload         5
      21: ifnull        112
      24: aload         5
      26: invokeinterface #11,  1           // InterfaceMethod org/w3c/dom/Node.getNodeName:()Ljava/lang/String;
      31: new           #12                 // class java/lang/StringBuilder
      34: dup
      35: invokespecial #13                 // Method java/lang/StringBuilder."<init>":()V
      38: aload         4
      40: invokevirtual #14                 // Method java/lang/StringBuilder.append:(Ljava/lang/String;)Ljava/lang/StringBuilder;
      43: ldc           #15                 // String key
      45: invokevirtual #14                 // Method java/lang/StringBuilder.append:(Ljava/lang/String;)Ljava/lang/StringBuilder;
      48: invokevirtual #16                 // Method java/lang/StringBuilder.toString:()Ljava/lang/String;
      51: invokevirtual #17                 // Method java/lang/String.equals:(Ljava/lang/Object;)Z
      54: ifne          60
      57: goto          100
      60: aload         5
      62: checkcast     #18                 // class org/w3c/dom/Element
      65: astore        6
      67: aload_3
      68: aload         6
      70: ldc           #19                 // String name
      72: invokeinterface #20,  2           // InterfaceMethod org/w3c/dom/Element.getAttribute:(Ljava/lang/String;)Ljava/lang/String;
      77: invokevirtual #17                 // Method java/lang/String.equals:(Ljava/lang/Object;)Z
      80: ifne          86
      83: goto          100
      86: aload_0
      87: aload_0
      88: aload_1
      89: aload         5
      91: invokespecial #8                  // Method extractTable:(Lnet/sf/xsd2pgschema/PgSchema;Lorg/w3c/dom/Node;)Ljava/lang/String;
      94: putfield      #6                  // Field parent_table:Ljava/lang/String;
      97: goto          112
     100: aload         5
     102: invokeinterface #21,  1           // InterfaceMethod org/w3c/dom/Node.getNextSibling:()Lorg/w3c/dom/Node;
     107: astore        5
     109: goto          19
     112: return

  private java.lang.String extractFields(net.sf.xsd2pgschema.PgSchema, org.w3c.dom.Node);
    Code:
       0: aload_1
       1: getfield      #9                  // Field net/sf/xsd2pgschema/PgSchema.xs_prefix_:Ljava/lang/String;
       4: astore_3
       5: ldc           #2                  // String
       7: astore        4
       9: aload_2
      10: invokeinterface #10,  1           // InterfaceMethod org/w3c/dom/Node.getFirstChild:()Lorg/w3c/dom/Node;
      15: astore        5
      17: aload         5
      19: ifnull        160
      22: aload         5
      24: invokeinterface #11,  1           // InterfaceMethod org/w3c/dom/Node.getNodeName:()Ljava/lang/String;
      29: new           #12                 // class java/lang/StringBuilder
      32: dup
      33: invokespecial #13                 // Method java/lang/StringBuilder."<init>":()V
      36: aload_3
      37: invokevirtual #14                 // Method java/lang/StringBuilder.append:(Ljava/lang/String;)Ljava/lang/StringBuilder;
      40: ldc           #22                 // String field
      42: invokevirtual #14                 // Method java/lang/StringBuilder.append:(Ljava/lang/String;)Ljava/lang/StringBuilder;
      45: invokevirtual #16                 // Method java/lang/StringBuilder.toString:()Ljava/lang/String;
      48: invokevirtual #17                 // Method java/lang/String.equals:(Ljava/lang/Object;)Z
      51: ifne          57
      54: goto          148
      57: aload         5
      59: checkcast     #18                 // class org/w3c/dom/Element
      62: astore        6
      64: aload         6
      66: ldc           #23                 // String xpath
      68: invokeinterface #20,  2           // InterfaceMethod org/w3c/dom/Element.getAttribute:(Ljava/lang/String;)Ljava/lang/String;
      73: ldc           #24                 // String :
      75: invokevirtual #25                 // Method java/lang/String.split:(Ljava/lang/String;)[Ljava/lang/String;
      78: astore        7
      80: aload         4
      82: invokevirtual #26                 // Method java/lang/String.isEmpty:()Z
      85: ifeq          108
      88: aload         7
      90: aload         7
      92: arraylength
      93: iconst_1
      94: isub
      95: aaload
      96: ldc           #27                 // String @
      98: ldc           #2                  // String
     100: invokevirtual #28                 // Method java/lang/String.replaceAll:(Ljava/lang/String;Ljava/lang/String;)Ljava/lang/String;
     103: astore        4
     105: goto          148
     108: aload         4
     110: new           #12                 // class java/lang/StringBuilder
     113: dup
     114: invokespecial #13                 // Method java/lang/StringBuilder."<init>":()V
     117: ldc           #29                 // String ,
     119: invokevirtual #14                 // Method java/lang/StringBuilder.append:(Ljava/lang/String;)Ljava/lang/StringBuilder;
     122: aload         7
     124: aload         7
     126: arraylength
     127: iconst_1
     128: isub
     129: aaload
     130: invokevirtual #14                 // Method java/lang/StringBuilder.append:(Ljava/lang/String;)Ljava/lang/StringBuilder;
     133: invokevirtual #16                 // Method java/lang/StringBuilder.toString:()Ljava/lang/String;
     136: invokevirtual #30                 // Method java/lang/String.concat:(Ljava/lang/String;)Ljava/lang/String;
     139: ldc           #27                 // String @
     141: ldc           #2                  // String
     143: invokevirtual #28                 // Method java/lang/String.replaceAll:(Ljava/lang/String;Ljava/lang/String;)Ljava/lang/String;
     146: astore        4
     148: aload         5
     150: invokeinterface #21,  1           // InterfaceMethod org/w3c/dom/Node.getNextSibling:()Lorg/w3c/dom/Node;
     155: astore        5
     157: goto          17
     160: aload         4
     162: areturn

  public void extractChildFields(net.sf.xsd2pgschema.PgSchema, org.w3c.dom.Node);
    Code:
       0: aload_0
       1: aload_0
       2: aload_1
       3: aload_2
       4: invokespecial #31                 // Method extractFields:(Lnet/sf/xsd2pgschema/PgSchema;Lorg/w3c/dom/Node;)Ljava/lang/String;
       7: putfield      #5                  // Field child_fields:Ljava/lang/String;
      10: return

  public void extractParentFields(net.sf.xsd2pgschema.PgSchema, org.w3c.dom.Node, java.lang.String);
    Code:
       0: aload_1
       1: getfield      #9                  // Field net/sf/xsd2pgschema/PgSchema.xs_prefix_:Ljava/lang/String;
       4: astore        4
       6: aload_0
       7: aconst_null
       8: putfield      #7                  // Field parent_fields:Ljava/lang/String;
      11: aload_2
      12: invokeinterface #10,  1           // InterfaceMethod org/w3c/dom/Node.getFirstChild:()Lorg/w3c/dom/Node;
      17: astore        5
      19: aload         5
      21: ifnull        112
      24: aload         5
      26: invokeinterface #11,  1           // InterfaceMethod org/w3c/dom/Node.getNodeName:()Ljava/lang/String;
      31: new           #12                 // class java/lang/StringBuilder
      34: dup
      35: invokespecial #13                 // Method java/lang/StringBuilder."<init>":()V
      38: aload         4
      40: invokevirtual #14                 // Method java/lang/StringBuilder.append:(Ljava/lang/String;)Ljava/lang/StringBuilder;
      43: ldc           #15                 // String key
      45: invokevirtual #14                 // Method java/lang/StringBuilder.append:(Ljava/lang/String;)Ljava/lang/StringBuilder;
      48: invokevirtual #16                 // Method java/lang/StringBuilder.toString:()Ljava/lang/String;
      51: invokevirtual #17                 // Method java/lang/String.equals:(Ljava/lang/Object;)Z
      54: ifne          60
      57: goto          100
      60: aload         5
      62: checkcast     #18                 // class org/w3c/dom/Element
      65: astore        6
      67: aload_3
      68: aload         6
      70: ldc           #19                 // String name
      72: invokeinterface #20,  2           // InterfaceMethod org/w3c/dom/Element.getAttribute:(Ljava/lang/String;)Ljava/lang/String;
      77: invokevirtual #17                 // Method java/lang/String.equals:(Ljava/lang/Object;)Z
      80: ifne          86
      83: goto          100
      86: aload_0
      87: aload_0
      88: aload_1
      89: aload         5
      91: invokespecial #31                 // Method extractFields:(Lnet/sf/xsd2pgschema/PgSchema;Lorg/w3c/dom/Node;)Ljava/lang/String;
      94: putfield      #7                  // Field parent_fields:Ljava/lang/String;
      97: goto          112
     100: aload         5
     102: invokeinterface #21,  1           // InterfaceMethod org/w3c/dom/Node.getNextSibling:()Lorg/w3c/dom/Node;
     107: astore        5
     109: goto          19
     112: return

  private java.lang.String extractTable(net.sf.xsd2pgschema.PgSchema, org.w3c.dom.Node);
    Code:
       0: aload_1
       1: getfield      #9                  // Field net/sf/xsd2pgschema/PgSchema.xs_prefix_:Ljava/lang/String;
       4: astore_3
       5: aload_2
       6: invokeinterface #10,  1           // InterfaceMethod org/w3c/dom/Node.getFirstChild:()Lorg/w3c/dom/Node;
      11: astore        4
      13: aload         4
      15: ifnull        108
      18: aload         4
      20: invokeinterface #11,  1           // InterfaceMethod org/w3c/dom/Node.getNodeName:()Ljava/lang/String;
      25: new           #12                 // class java/lang/StringBuilder
      28: dup
      29: invokespecial #13                 // Method java/lang/StringBuilder."<init>":()V
      32: aload_3
      33: invokevirtual #14                 // Method java/lang/StringBuilder.append:(Ljava/lang/String;)Ljava/lang/StringBuilder;
      36: ldc           #32                 // String selector
      38: invokevirtual #14                 // Method java/lang/StringBuilder.append:(Ljava/lang/String;)Ljava/lang/StringBuilder;
      41: invokevirtual #16                 // Method java/lang/StringBuilder.toString:()Ljava/lang/String;
      44: invokevirtual #17                 // Method java/lang/String.equals:(Ljava/lang/Object;)Z
      47: ifne          53
      50: goto          96
      53: aload         4
      55: checkcast     #18                 // class org/w3c/dom/Element
      58: astore        5
      60: aload         5
      62: ldc           #23                 // String xpath
      64: invokeinterface #20,  2           // InterfaceMethod org/w3c/dom/Element.getAttribute:(Ljava/lang/String;)Ljava/lang/String;
      69: ldc           #33                 // String /
      71: invokevirtual #25                 // Method java/lang/String.split:(Ljava/lang/String;)[Ljava/lang/String;
      74: astore        6
      76: aload_1
      77: aload         6
      79: aload         6
      81: arraylength
      82: iconst_1
      83: isub
      84: aaload
      85: invokevirtual #34                 // Method net/sf/xsd2pgschema/PgSchema.getUnqualifiedName:(Ljava/lang/String;)Ljava/lang/String;
      88: ldc           #27                 // String @
      90: ldc           #2                  // String
      92: invokevirtual #28                 // Method java/lang/String.replaceAll:(Ljava/lang/String;Ljava/lang/String;)Ljava/lang/String;
      95: areturn
      96: aload         4
      98: invokeinterface #21,  1           // InterfaceMethod org/w3c/dom/Node.getNextSibling:()Lorg/w3c/dom/Node;
     103: astore        4
     105: goto          13
     108: aconst_null
     109: areturn
}
