Compiled from "JmsHealthIndicator.java"
public class org.springframework.boot.actuate.jms.JmsHealthIndicator extends org.springframework.boot.actuate.health.AbstractHealthIndicator {
  private final javax.jms.ConnectionFactory connectionFactory;

  public org.springframework.boot.actuate.jms.JmsHealthIndicator(javax.jms.ConnectionFactory);
    Code:
       0: aload_0
       1: ldc           #1                  // String JMS health check failed
       3: invokespecial #2                  // Method org/springframework/boot/actuate/health/AbstractHealthIndicator."<init>":(Ljava/lang/String;)V
       6: aload_0
       7: aload_1
       8: putfield      #3                  // Field connectionFactory:Ljavax/jms/ConnectionFactory;
      11: return

  protected void doHealthCheck(org.springframework.boot.actuate.health.Health$Builder) throws java.lang.Exception;
    Code:
       0: aload_0
       1: getfield      #3                  // Field connectionFactory:Ljavax/jms/ConnectionFactory;
       4: invokeinterface #4,  1            // InterfaceMethod javax/jms/ConnectionFactory.createConnection:()Ljavax/jms/Connection;
       9: astore_2
      10: aconst_null
      11: astore_3
      12: aload_2
      13: invokeinterface #5,  1            // InterfaceMethod javax/jms/Connection.start:()V
      18: aload_1
      19: invokevirtual #6                  // Method org/springframework/boot/actuate/health/Health$Builder.up:()Lorg/springframework/boot/actuate/health/Health$Builder;
      22: ldc           #7                  // String provider
      24: aload_2
      25: invokeinterface #8,  1            // InterfaceMethod javax/jms/Connection.getMetaData:()Ljavax/jms/ConnectionMetaData;
      30: invokeinterface #9,  1            // InterfaceMethod javax/jms/ConnectionMetaData.getJMSProviderName:()Ljava/lang/String;
      35: invokevirtual #10                 // Method org/springframework/boot/actuate/health/Health$Builder.withDetail:(Ljava/lang/String;Ljava/lang/Object;)Lorg/springframework/boot/actuate/health/Health$Builder;
      38: pop
      39: aload_2
      40: ifnull        123
      43: aload_3
      44: ifnull        67
      47: aload_2
      48: invokeinterface #11,  1           // InterfaceMethod javax/jms/Connection.close:()V
      53: goto          123
      56: astore        4
      58: aload_3
      59: aload         4
      61: invokevirtual #13                 // Method java/lang/Throwable.addSuppressed:(Ljava/lang/Throwable;)V
      64: goto          123
      67: aload_2
      68: invokeinterface #11,  1           // InterfaceMethod javax/jms/Connection.close:()V
      73: goto          123
      76: astore        4
      78: aload         4
      80: astore_3
      81: aload         4
      83: athrow
      84: astore        5
      86: aload_2
      87: ifnull        120
      90: aload_3
      91: ifnull        114
      94: aload_2
      95: invokeinterface #11,  1           // InterfaceMethod javax/jms/Connection.close:()V
     100: goto          120
     103: astore        6
     105: aload_3
     106: aload         6
     108: invokevirtual #13                 // Method java/lang/Throwable.addSuppressed:(Ljava/lang/Throwable;)V
     111: goto          120
     114: aload_2
     115: invokeinterface #11,  1           // InterfaceMethod javax/jms/Connection.close:()V
     120: aload         5
     122: athrow
     123: return
    Exception table:
       from    to  target type
          47    53    56   Class java/lang/Throwable
          12    39    76   Class java/lang/Throwable
          12    39    84   any
          94   100   103   Class java/lang/Throwable
          76    86    84   any
}
