Compiled from "EventBus.java"
public class org.apache.jena.ext.com.google.common.eventbus.EventBus {
  private static final java.util.logging.Logger logger;

  private final java.lang.String identifier;

  private final java.util.concurrent.Executor executor;

  private final org.apache.jena.ext.com.google.common.eventbus.SubscriberExceptionHandler exceptionHandler;

  private final org.apache.jena.ext.com.google.common.eventbus.SubscriberRegistry subscribers;

  private final org.apache.jena.ext.com.google.common.eventbus.Dispatcher dispatcher;

  public org.apache.jena.ext.com.google.common.eventbus.EventBus();
    Code:
       0: aload_0
       1: ldc           #30                 // String default
       3: invokespecial #33                 // Method "<init>":(Ljava/lang/String;)V
       6: return

  public org.apache.jena.ext.com.google.common.eventbus.EventBus(java.lang.String);
    Code:
       0: aload_0
       1: aload_1
       2: invokestatic  #41                 // Method org/apache/jena/ext/com/google/common/util/concurrent/MoreExecutors.directExecutor:()Ljava/util/concurrent/Executor;
       5: invokestatic  #47                 // Method org/apache/jena/ext/com/google/common/eventbus/Dispatcher.perThreadDispatchQueue:()Lorg/apache/jena/ext/com/google/common/eventbus/Dispatcher;
       8: getstatic     #51                 // Field org/apache/jena/ext/com/google/common/eventbus/EventBus$LoggingHandler.INSTANCE:Lorg/apache/jena/ext/com/google/common/eventbus/EventBus$LoggingHandler;
      11: invokespecial #54                 // Method "<init>":(Ljava/lang/String;Ljava/util/concurrent/Executor;Lorg/apache/jena/ext/com/google/common/eventbus/Dispatcher;Lorg/apache/jena/ext/com/google/common/eventbus/SubscriberExceptionHandler;)V
      14: return

  public org.apache.jena.ext.com.google.common.eventbus.EventBus(org.apache.jena.ext.com.google.common.eventbus.SubscriberExceptionHandler);
    Code:
       0: aload_0
       1: ldc           #30                 // String default
       3: invokestatic  #41                 // Method org/apache/jena/ext/com/google/common/util/concurrent/MoreExecutors.directExecutor:()Ljava/util/concurrent/Executor;
       6: invokestatic  #47                 // Method org/apache/jena/ext/com/google/common/eventbus/Dispatcher.perThreadDispatchQueue:()Lorg/apache/jena/ext/com/google/common/eventbus/Dispatcher;
       9: aload_1
      10: invokespecial #54                 // Method "<init>":(Ljava/lang/String;Ljava/util/concurrent/Executor;Lorg/apache/jena/ext/com/google/common/eventbus/Dispatcher;Lorg/apache/jena/ext/com/google/common/eventbus/SubscriberExceptionHandler;)V
      13: return

  org.apache.jena.ext.com.google.common.eventbus.EventBus(java.lang.String, java.util.concurrent.Executor, org.apache.jena.ext.com.google.common.eventbus.Dispatcher, org.apache.jena.ext.com.google.common.eventbus.SubscriberExceptionHandler);
    Code:
       0: aload_0
       1: invokespecial #57                 // Method java/lang/Object."<init>":()V
       4: aload_0
       5: new           #59                 // class org/apache/jena/ext/com/google/common/eventbus/SubscriberRegistry
       8: dup
       9: aload_0
      10: invokespecial #62                 // Method org/apache/jena/ext/com/google/common/eventbus/SubscriberRegistry."<init>":(Lorg/apache/jena/ext/com/google/common/eventbus/EventBus;)V
      13: putfield      #64                 // Field subscribers:Lorg/apache/jena/ext/com/google/common/eventbus/SubscriberRegistry;
      16: aload_0
      17: aload_1
      18: invokestatic  #70                 // Method org/apache/jena/ext/com/google/common/base/Preconditions.checkNotNull:(Ljava/lang/Object;)Ljava/lang/Object;
      21: checkcast     #72                 // class java/lang/String
      24: putfield      #74                 // Field identifier:Ljava/lang/String;
      27: aload_0
      28: aload_2
      29: invokestatic  #70                 // Method org/apache/jena/ext/com/google/common/base/Preconditions.checkNotNull:(Ljava/lang/Object;)Ljava/lang/Object;
      32: checkcast     #76                 // class java/util/concurrent/Executor
      35: putfield      #78                 // Field executor:Ljava/util/concurrent/Executor;
      38: aload_0
      39: aload_3
      40: invokestatic  #70                 // Method org/apache/jena/ext/com/google/common/base/Preconditions.checkNotNull:(Ljava/lang/Object;)Ljava/lang/Object;
      43: checkcast     #43                 // class org/apache/jena/ext/com/google/common/eventbus/Dispatcher
      46: putfield      #80                 // Field dispatcher:Lorg/apache/jena/ext/com/google/common/eventbus/Dispatcher;
      49: aload_0
      50: aload         4
      52: invokestatic  #70                 // Method org/apache/jena/ext/com/google/common/base/Preconditions.checkNotNull:(Ljava/lang/Object;)Ljava/lang/Object;
      55: checkcast     #82                 // class org/apache/jena/ext/com/google/common/eventbus/SubscriberExceptionHandler
      58: putfield      #84                 // Field exceptionHandler:Lorg/apache/jena/ext/com/google/common/eventbus/SubscriberExceptionHandler;
      61: return

  public final java.lang.String identifier();
    Code:
       0: aload_0
       1: getfield      #74                 // Field identifier:Ljava/lang/String;
       4: areturn

  final java.util.concurrent.Executor executor();
    Code:
       0: aload_0
       1: getfield      #78                 // Field executor:Ljava/util/concurrent/Executor;
       4: areturn

  void handleSubscriberException(java.lang.Throwable, org.apache.jena.ext.com.google.common.eventbus.SubscriberExceptionContext);
    Code:
       0: aload_1
       1: invokestatic  #70                 // Method org/apache/jena/ext/com/google/common/base/Preconditions.checkNotNull:(Ljava/lang/Object;)Ljava/lang/Object;
       4: pop
       5: aload_2
       6: invokestatic  #70                 // Method org/apache/jena/ext/com/google/common/base/Preconditions.checkNotNull:(Ljava/lang/Object;)Ljava/lang/Object;
       9: pop
      10: aload_0
      11: getfield      #84                 // Field exceptionHandler:Lorg/apache/jena/ext/com/google/common/eventbus/SubscriberExceptionHandler;
      14: aload_1
      15: aload_2
      16: invokeinterface #92,  3           // InterfaceMethod org/apache/jena/ext/com/google/common/eventbus/SubscriberExceptionHandler.handleException:(Ljava/lang/Throwable;Lorg/apache/jena/ext/com/google/common/eventbus/SubscriberExceptionContext;)V
      21: goto          55
      24: astore_3
      25: getstatic     #94                 // Field logger:Ljava/util/logging/Logger;
      28: getstatic     #100                // Field java/util/logging/Level.SEVERE:Ljava/util/logging/Level;
      31: getstatic     #106                // Field java/util/Locale.ROOT:Ljava/util/Locale;
      34: ldc           #108                // String Exception %s thrown while handling exception: %s
      36: iconst_2
      37: anewarray     #4                  // class java/lang/Object
      40: dup
      41: iconst_0
      42: aload_3
      43: aastore
      44: dup
      45: iconst_1
      46: aload_1
      47: aastore
      48: invokestatic  #112                // Method java/lang/String.format:(Ljava/util/Locale;Ljava/lang/String;[Ljava/lang/Object;)Ljava/lang/String;
      51: aload_3
      52: invokevirtual #118                // Method java/util/logging/Logger.log:(Ljava/util/logging/Level;Ljava/lang/String;Ljava/lang/Throwable;)V
      55: return
    Exception table:
       from    to  target type
          10    21    24   Class java/lang/Throwable

  public void register(java.lang.Object);
    Code:
       0: aload_0
       1: getfield      #64                 // Field subscribers:Lorg/apache/jena/ext/com/google/common/eventbus/SubscriberRegistry;
       4: aload_1
       5: invokevirtual #127                // Method org/apache/jena/ext/com/google/common/eventbus/SubscriberRegistry.register:(Ljava/lang/Object;)V
       8: return

  public void unregister(java.lang.Object);
    Code:
       0: aload_0
       1: getfield      #64                 // Field subscribers:Lorg/apache/jena/ext/com/google/common/eventbus/SubscriberRegistry;
       4: aload_1
       5: invokevirtual #132                // Method org/apache/jena/ext/com/google/common/eventbus/SubscriberRegistry.unregister:(Ljava/lang/Object;)V
       8: return

  public void post(java.lang.Object);
    Code:
       0: aload_0
       1: getfield      #64                 // Field subscribers:Lorg/apache/jena/ext/com/google/common/eventbus/SubscriberRegistry;
       4: aload_1
       5: invokevirtual #137                // Method org/apache/jena/ext/com/google/common/eventbus/SubscriberRegistry.getSubscribers:(Ljava/lang/Object;)Ljava/util/Iterator;
       8: astore_2
       9: aload_2
      10: invokeinterface #143,  1          // InterfaceMethod java/util/Iterator.hasNext:()Z
      15: ifeq          30
      18: aload_0
      19: getfield      #80                 // Field dispatcher:Lorg/apache/jena/ext/com/google/common/eventbus/Dispatcher;
      22: aload_1
      23: aload_2
      24: invokevirtual #147                // Method org/apache/jena/ext/com/google/common/eventbus/Dispatcher.dispatch:(Ljava/lang/Object;Ljava/util/Iterator;)V
      27: goto          50
      30: aload_1
      31: instanceof    #149                // class org/apache/jena/ext/com/google/common/eventbus/DeadEvent
      34: ifne          50
      37: aload_0
      38: new           #149                // class org/apache/jena/ext/com/google/common/eventbus/DeadEvent
      41: dup
      42: aload_0
      43: aload_1
      44: invokespecial #152                // Method org/apache/jena/ext/com/google/common/eventbus/DeadEvent."<init>":(Ljava/lang/Object;Ljava/lang/Object;)V
      47: invokevirtual #154                // Method post:(Ljava/lang/Object;)V
      50: return

  public java.lang.String toString();
    Code:
       0: aload_0
       1: invokestatic  #163                // Method org/apache/jena/ext/com/google/common/base/MoreObjects.toStringHelper:(Ljava/lang/Object;)Lorg/apache/jena/ext/com/google/common/base/MoreObjects$ToStringHelper;
       4: aload_0
       5: getfield      #74                 // Field identifier:Ljava/lang/String;
       8: invokevirtual #166                // Method org/apache/jena/ext/com/google/common/base/MoreObjects$ToStringHelper.addValue:(Ljava/lang/Object;)Lorg/apache/jena/ext/com/google/common/base/MoreObjects$ToStringHelper;
      11: invokevirtual #168                // Method org/apache/jena/ext/com/google/common/base/MoreObjects$ToStringHelper.toString:()Ljava/lang/String;
      14: areturn

  static {};
    Code:
       0: ldc           #2                  // class org/apache/jena/ext/com/google/common/eventbus/EventBus
       2: invokevirtual #174                // Method java/lang/Class.getName:()Ljava/lang/String;
       5: invokestatic  #178                // Method java/util/logging/Logger.getLogger:(Ljava/lang/String;)Ljava/util/logging/Logger;
       8: putstatic     #94                 // Field logger:Ljava/util/logging/Logger;
      11: return
}
