Compiled from "AddKeysFromTransformFluentImpl.java"
public class io.dekorate.deps.servicecatalog.api.model.AddKeysFromTransformFluentImpl$SecretRefNestedImpl<N> extends io.dekorate.deps.servicecatalog.api.model.ObjectReferenceFluentImpl<io.dekorate.deps.servicecatalog.api.model.AddKeysFromTransformFluent$SecretRefNested<N>> implements io.dekorate.deps.servicecatalog.api.model.AddKeysFromTransformFluent$SecretRefNested<N>, io.dekorate.deps.kubernetes.api.builder.Nested<N> {
  private final io.dekorate.deps.servicecatalog.api.model.ObjectReferenceBuilder builder;

  final io.dekorate.deps.servicecatalog.api.model.AddKeysFromTransformFluentImpl this$0;

  io.dekorate.deps.servicecatalog.api.model.AddKeysFromTransformFluentImpl$SecretRefNestedImpl(io.dekorate.deps.servicecatalog.api.model.AddKeysFromTransformFluentImpl, io.dekorate.deps.servicecatalog.api.model.ObjectReference);
    Code:
       0: aload_0
       1: aload_1
       2: putfield      #24                 // Field this$0:Lio/dekorate/deps/servicecatalog/api/model/AddKeysFromTransformFluentImpl;
       5: aload_0
       6: invokespecial #27                 // Method io/dekorate/deps/servicecatalog/api/model/ObjectReferenceFluentImpl."<init>":()V
       9: aload_0
      10: new           #29                 // class io/dekorate/deps/servicecatalog/api/model/ObjectReferenceBuilder
      13: dup
      14: aload_0
      15: aload_2
      16: invokespecial #32                 // Method io/dekorate/deps/servicecatalog/api/model/ObjectReferenceBuilder."<init>":(Lio/dekorate/deps/servicecatalog/api/model/ObjectReferenceFluent;Lio/dekorate/deps/servicecatalog/api/model/ObjectReference;)V
      19: putfield      #34                 // Field builder:Lio/dekorate/deps/servicecatalog/api/model/ObjectReferenceBuilder;
      22: return

  io.dekorate.deps.servicecatalog.api.model.AddKeysFromTransformFluentImpl$SecretRefNestedImpl(io.dekorate.deps.servicecatalog.api.model.AddKeysFromTransformFluentImpl);
    Code:
       0: aload_0
       1: aload_1
       2: putfield      #24                 // Field this$0:Lio/dekorate/deps/servicecatalog/api/model/AddKeysFromTransformFluentImpl;
       5: aload_0
       6: invokespecial #27                 // Method io/dekorate/deps/servicecatalog/api/model/ObjectReferenceFluentImpl."<init>":()V
       9: aload_0
      10: new           #29                 // class io/dekorate/deps/servicecatalog/api/model/ObjectReferenceBuilder
      13: dup
      14: aload_0
      15: invokespecial #43                 // Method io/dekorate/deps/servicecatalog/api/model/ObjectReferenceBuilder."<init>":(Lio/dekorate/deps/servicecatalog/api/model/ObjectReferenceFluent;)V
      18: putfield      #34                 // Field builder:Lio/dekorate/deps/servicecatalog/api/model/ObjectReferenceBuilder;
      21: return

  public N and();
    Code:
       0: aload_0
       1: getfield      #24                 // Field this$0:Lio/dekorate/deps/servicecatalog/api/model/AddKeysFromTransformFluentImpl;
       4: aload_0
       5: getfield      #34                 // Field builder:Lio/dekorate/deps/servicecatalog/api/model/ObjectReferenceBuilder;
       8: invokevirtual #50                 // Method io/dekorate/deps/servicecatalog/api/model/ObjectReferenceBuilder.build:()Lio/dekorate/deps/servicecatalog/api/model/ObjectReference;
      11: invokevirtual #54                 // Method io/dekorate/deps/servicecatalog/api/model/AddKeysFromTransformFluentImpl.withSecretRef:(Lio/dekorate/deps/servicecatalog/api/model/ObjectReference;)Lio/dekorate/deps/servicecatalog/api/model/AddKeysFromTransformFluent;
      14: areturn

  public N endSecretRef();
    Code:
       0: aload_0
       1: invokevirtual #57                 // Method and:()Ljava/lang/Object;
       4: areturn
}
