Compiled from "ClusterServiceClassSpecBuilder.java"
public class io.dekorate.deps.servicecatalog.api.model.ClusterServiceClassSpecBuilder extends io.dekorate.deps.servicecatalog.api.model.ClusterServiceClassSpecFluentImpl<io.dekorate.deps.servicecatalog.api.model.ClusterServiceClassSpecBuilder> implements io.dekorate.deps.kubernetes.api.builder.VisitableBuilder<io.dekorate.deps.servicecatalog.api.model.ClusterServiceClassSpec, io.dekorate.deps.servicecatalog.api.model.ClusterServiceClassSpecBuilder> {
  io.dekorate.deps.servicecatalog.api.model.ClusterServiceClassSpecFluent<?> fluent;

  java.lang.Boolean validationEnabled;

  public io.dekorate.deps.servicecatalog.api.model.ClusterServiceClassSpecBuilder();
    Code:
       0: aload_0
       1: iconst_1
       2: invokestatic  #21                 // Method java/lang/Boolean.valueOf:(Z)Ljava/lang/Boolean;
       5: invokespecial #24                 // Method "<init>":(Ljava/lang/Boolean;)V
       8: return

  public io.dekorate.deps.servicecatalog.api.model.ClusterServiceClassSpecBuilder(java.lang.Boolean);
    Code:
       0: aload_0
       1: new           #28                 // class io/dekorate/deps/servicecatalog/api/model/ClusterServiceClassSpec
       4: dup
       5: invokespecial #30                 // Method io/dekorate/deps/servicecatalog/api/model/ClusterServiceClassSpec."<init>":()V
       8: aload_1
       9: invokespecial #33                 // Method "<init>":(Lio/dekorate/deps/servicecatalog/api/model/ClusterServiceClassSpec;Ljava/lang/Boolean;)V
      12: return

  public io.dekorate.deps.servicecatalog.api.model.ClusterServiceClassSpecBuilder(io.dekorate.deps.servicecatalog.api.model.ClusterServiceClassSpecFluent<?>);
    Code:
       0: aload_0
       1: aload_1
       2: iconst_1
       3: invokestatic  #21                 // Method java/lang/Boolean.valueOf:(Z)Ljava/lang/Boolean;
       6: invokespecial #38                 // Method "<init>":(Lio/dekorate/deps/servicecatalog/api/model/ClusterServiceClassSpecFluent;Ljava/lang/Boolean;)V
       9: return

  public io.dekorate.deps.servicecatalog.api.model.ClusterServiceClassSpecBuilder(io.dekorate.deps.servicecatalog.api.model.ClusterServiceClassSpecFluent<?>, java.lang.Boolean);
    Code:
       0: aload_0
       1: aload_1
       2: new           #28                 // class io/dekorate/deps/servicecatalog/api/model/ClusterServiceClassSpec
       5: dup
       6: invokespecial #30                 // Method io/dekorate/deps/servicecatalog/api/model/ClusterServiceClassSpec."<init>":()V
       9: aload_2
      10: invokespecial #42                 // Method "<init>":(Lio/dekorate/deps/servicecatalog/api/model/ClusterServiceClassSpecFluent;Lio/dekorate/deps/servicecatalog/api/model/ClusterServiceClassSpec;Ljava/lang/Boolean;)V
      13: return

  public io.dekorate.deps.servicecatalog.api.model.ClusterServiceClassSpecBuilder(io.dekorate.deps.servicecatalog.api.model.ClusterServiceClassSpecFluent<?>, io.dekorate.deps.servicecatalog.api.model.ClusterServiceClassSpec);
    Code:
       0: aload_0
       1: aload_1
       2: aload_2
       3: iconst_1
       4: invokestatic  #21                 // Method java/lang/Boolean.valueOf:(Z)Ljava/lang/Boolean;
       7: invokespecial #42                 // Method "<init>":(Lio/dekorate/deps/servicecatalog/api/model/ClusterServiceClassSpecFluent;Lio/dekorate/deps/servicecatalog/api/model/ClusterServiceClassSpec;Ljava/lang/Boolean;)V
      10: return

  public io.dekorate.deps.servicecatalog.api.model.ClusterServiceClassSpecBuilder(io.dekorate.deps.servicecatalog.api.model.ClusterServiceClassSpecFluent<?>, io.dekorate.deps.servicecatalog.api.model.ClusterServiceClassSpec, java.lang.Boolean);
    Code:
       0: aload_0
       1: invokespecial #48                 // Method io/dekorate/deps/servicecatalog/api/model/ClusterServiceClassSpecFluentImpl."<init>":()V
       4: aload_0
       5: aload_1
       6: putfield      #50                 // Field fluent:Lio/dekorate/deps/servicecatalog/api/model/ClusterServiceClassSpecFluent;
       9: aload_1
      10: aload_2
      11: invokevirtual #54                 // Method io/dekorate/deps/servicecatalog/api/model/ClusterServiceClassSpec.getBindable:()Ljava/lang/Boolean;
      14: invokeinterface #60,  2           // InterfaceMethod io/dekorate/deps/servicecatalog/api/model/ClusterServiceClassSpecFluent.withBindable:(Ljava/lang/Boolean;)Lio/dekorate/deps/servicecatalog/api/model/ClusterServiceClassSpecFluent;
      19: pop
      20: aload_1
      21: aload_2
      22: invokevirtual #63                 // Method io/dekorate/deps/servicecatalog/api/model/ClusterServiceClassSpec.getBindingRetrievable:()Ljava/lang/Boolean;
      25: invokeinterface #66,  2           // InterfaceMethod io/dekorate/deps/servicecatalog/api/model/ClusterServiceClassSpecFluent.withBindingRetrievable:(Ljava/lang/Boolean;)Lio/dekorate/deps/servicecatalog/api/model/ClusterServiceClassSpecFluent;
      30: pop
      31: aload_1
      32: aload_2
      33: invokevirtual #70                 // Method io/dekorate/deps/servicecatalog/api/model/ClusterServiceClassSpec.getClusterServiceBrokerName:()Ljava/lang/String;
      36: invokeinterface #74,  2           // InterfaceMethod io/dekorate/deps/servicecatalog/api/model/ClusterServiceClassSpecFluent.withClusterServiceBrokerName:(Ljava/lang/String;)Lio/dekorate/deps/servicecatalog/api/model/ClusterServiceClassSpecFluent;
      41: pop
      42: aload_1
      43: aload_2
      44: invokevirtual #77                 // Method io/dekorate/deps/servicecatalog/api/model/ClusterServiceClassSpec.getDescription:()Ljava/lang/String;
      47: invokeinterface #80,  2           // InterfaceMethod io/dekorate/deps/servicecatalog/api/model/ClusterServiceClassSpecFluent.withDescription:(Ljava/lang/String;)Lio/dekorate/deps/servicecatalog/api/model/ClusterServiceClassSpecFluent;
      52: pop
      53: aload_1
      54: aload_2
      55: invokevirtual #83                 // Method io/dekorate/deps/servicecatalog/api/model/ClusterServiceClassSpec.getExternalID:()Ljava/lang/String;
      58: invokeinterface #86,  2           // InterfaceMethod io/dekorate/deps/servicecatalog/api/model/ClusterServiceClassSpecFluent.withExternalID:(Ljava/lang/String;)Lio/dekorate/deps/servicecatalog/api/model/ClusterServiceClassSpecFluent;
      63: pop
      64: aload_1
      65: aload_2
      66: invokevirtual #90                 // Method io/dekorate/deps/servicecatalog/api/model/ClusterServiceClassSpec.getExternalMetadata:()Ljava/util/Map;
      69: invokeinterface #94,  2           // InterfaceMethod io/dekorate/deps/servicecatalog/api/model/ClusterServiceClassSpecFluent.withExternalMetadata:(Ljava/util/Map;)Lio/dekorate/deps/servicecatalog/api/model/ClusterServiceClassSpecFluent;
      74: pop
      75: aload_1
      76: aload_2
      77: invokevirtual #97                 // Method io/dekorate/deps/servicecatalog/api/model/ClusterServiceClassSpec.getExternalName:()Ljava/lang/String;
      80: invokeinterface #100,  2          // InterfaceMethod io/dekorate/deps/servicecatalog/api/model/ClusterServiceClassSpecFluent.withExternalName:(Ljava/lang/String;)Lio/dekorate/deps/servicecatalog/api/model/ClusterServiceClassSpecFluent;
      85: pop
      86: aload_1
      87: aload_2
      88: invokevirtual #103                // Method io/dekorate/deps/servicecatalog/api/model/ClusterServiceClassSpec.getPlanUpdatable:()Ljava/lang/Boolean;
      91: invokeinterface #106,  2          // InterfaceMethod io/dekorate/deps/servicecatalog/api/model/ClusterServiceClassSpecFluent.withPlanUpdatable:(Ljava/lang/Boolean;)Lio/dekorate/deps/servicecatalog/api/model/ClusterServiceClassSpecFluent;
      96: pop
      97: aload_1
      98: aload_2
      99: invokevirtual #110                // Method io/dekorate/deps/servicecatalog/api/model/ClusterServiceClassSpec.getRequires:()Ljava/util/List;
     102: invokeinterface #114,  2          // InterfaceMethod io/dekorate/deps/servicecatalog/api/model/ClusterServiceClassSpecFluent.withRequires:(Ljava/util/List;)Lio/dekorate/deps/servicecatalog/api/model/ClusterServiceClassSpecFluent;
     107: pop
     108: aload_1
     109: aload_2
     110: invokevirtual #117                // Method io/dekorate/deps/servicecatalog/api/model/ClusterServiceClassSpec.getTags:()Ljava/util/List;
     113: invokeinterface #120,  2          // InterfaceMethod io/dekorate/deps/servicecatalog/api/model/ClusterServiceClassSpecFluent.withTags:(Ljava/util/List;)Lio/dekorate/deps/servicecatalog/api/model/ClusterServiceClassSpecFluent;
     118: pop
     119: aload_0
     120: aload_3
     121: putfield      #122                // Field validationEnabled:Ljava/lang/Boolean;
     124: return

  public io.dekorate.deps.servicecatalog.api.model.ClusterServiceClassSpecBuilder(io.dekorate.deps.servicecatalog.api.model.ClusterServiceClassSpec);
    Code:
       0: aload_0
       1: aload_1
       2: iconst_1
       3: invokestatic  #21                 // Method java/lang/Boolean.valueOf:(Z)Ljava/lang/Boolean;
       6: invokespecial #33                 // Method "<init>":(Lio/dekorate/deps/servicecatalog/api/model/ClusterServiceClassSpec;Ljava/lang/Boolean;)V
       9: return

  public io.dekorate.deps.servicecatalog.api.model.ClusterServiceClassSpecBuilder(io.dekorate.deps.servicecatalog.api.model.ClusterServiceClassSpec, java.lang.Boolean);
    Code:
       0: aload_0
       1: invokespecial #48                 // Method io/dekorate/deps/servicecatalog/api/model/ClusterServiceClassSpecFluentImpl."<init>":()V
       4: aload_0
       5: aload_0
       6: putfield      #50                 // Field fluent:Lio/dekorate/deps/servicecatalog/api/model/ClusterServiceClassSpecFluent;
       9: aload_0
      10: aload_1
      11: invokevirtual #54                 // Method io/dekorate/deps/servicecatalog/api/model/ClusterServiceClassSpec.getBindable:()Ljava/lang/Boolean;
      14: invokevirtual #124                // Method withBindable:(Ljava/lang/Boolean;)Lio/dekorate/deps/servicecatalog/api/model/ClusterServiceClassSpecFluent;
      17: pop
      18: aload_0
      19: aload_1
      20: invokevirtual #63                 // Method io/dekorate/deps/servicecatalog/api/model/ClusterServiceClassSpec.getBindingRetrievable:()Ljava/lang/Boolean;
      23: invokevirtual #125                // Method withBindingRetrievable:(Ljava/lang/Boolean;)Lio/dekorate/deps/servicecatalog/api/model/ClusterServiceClassSpecFluent;
      26: pop
      27: aload_0
      28: aload_1
      29: invokevirtual #70                 // Method io/dekorate/deps/servicecatalog/api/model/ClusterServiceClassSpec.getClusterServiceBrokerName:()Ljava/lang/String;
      32: invokevirtual #126                // Method withClusterServiceBrokerName:(Ljava/lang/String;)Lio/dekorate/deps/servicecatalog/api/model/ClusterServiceClassSpecFluent;
      35: pop
      36: aload_0
      37: aload_1
      38: invokevirtual #77                 // Method io/dekorate/deps/servicecatalog/api/model/ClusterServiceClassSpec.getDescription:()Ljava/lang/String;
      41: invokevirtual #127                // Method withDescription:(Ljava/lang/String;)Lio/dekorate/deps/servicecatalog/api/model/ClusterServiceClassSpecFluent;
      44: pop
      45: aload_0
      46: aload_1
      47: invokevirtual #83                 // Method io/dekorate/deps/servicecatalog/api/model/ClusterServiceClassSpec.getExternalID:()Ljava/lang/String;
      50: invokevirtual #128                // Method withExternalID:(Ljava/lang/String;)Lio/dekorate/deps/servicecatalog/api/model/ClusterServiceClassSpecFluent;
      53: pop
      54: aload_0
      55: aload_1
      56: invokevirtual #90                 // Method io/dekorate/deps/servicecatalog/api/model/ClusterServiceClassSpec.getExternalMetadata:()Ljava/util/Map;
      59: invokevirtual #129                // Method withExternalMetadata:(Ljava/util/Map;)Lio/dekorate/deps/servicecatalog/api/model/ClusterServiceClassSpecFluent;
      62: pop
      63: aload_0
      64: aload_1
      65: invokevirtual #97                 // Method io/dekorate/deps/servicecatalog/api/model/ClusterServiceClassSpec.getExternalName:()Ljava/lang/String;
      68: invokevirtual #130                // Method withExternalName:(Ljava/lang/String;)Lio/dekorate/deps/servicecatalog/api/model/ClusterServiceClassSpecFluent;
      71: pop
      72: aload_0
      73: aload_1
      74: invokevirtual #103                // Method io/dekorate/deps/servicecatalog/api/model/ClusterServiceClassSpec.getPlanUpdatable:()Ljava/lang/Boolean;
      77: invokevirtual #131                // Method withPlanUpdatable:(Ljava/lang/Boolean;)Lio/dekorate/deps/servicecatalog/api/model/ClusterServiceClassSpecFluent;
      80: pop
      81: aload_0
      82: aload_1
      83: invokevirtual #110                // Method io/dekorate/deps/servicecatalog/api/model/ClusterServiceClassSpec.getRequires:()Ljava/util/List;
      86: invokevirtual #132                // Method withRequires:(Ljava/util/List;)Lio/dekorate/deps/servicecatalog/api/model/ClusterServiceClassSpecFluent;
      89: pop
      90: aload_0
      91: aload_1
      92: invokevirtual #117                // Method io/dekorate/deps/servicecatalog/api/model/ClusterServiceClassSpec.getTags:()Ljava/util/List;
      95: invokevirtual #133                // Method withTags:(Ljava/util/List;)Lio/dekorate/deps/servicecatalog/api/model/ClusterServiceClassSpecFluent;
      98: pop
      99: aload_0
     100: aload_2
     101: putfield      #122                // Field validationEnabled:Ljava/lang/Boolean;
     104: return

  public io.dekorate.deps.servicecatalog.api.model.ClusterServiceClassSpec build();
    Code:
       0: new           #28                 // class io/dekorate/deps/servicecatalog/api/model/ClusterServiceClassSpec
       3: dup
       4: aload_0
       5: getfield      #50                 // Field fluent:Lio/dekorate/deps/servicecatalog/api/model/ClusterServiceClassSpecFluent;
       8: invokeinterface #138,  1          // InterfaceMethod io/dekorate/deps/servicecatalog/api/model/ClusterServiceClassSpecFluent.isBindable:()Ljava/lang/Boolean;
      13: aload_0
      14: getfield      #50                 // Field fluent:Lio/dekorate/deps/servicecatalog/api/model/ClusterServiceClassSpecFluent;
      17: invokeinterface #141,  1          // InterfaceMethod io/dekorate/deps/servicecatalog/api/model/ClusterServiceClassSpecFluent.isBindingRetrievable:()Ljava/lang/Boolean;
      22: aload_0
      23: getfield      #50                 // Field fluent:Lio/dekorate/deps/servicecatalog/api/model/ClusterServiceClassSpecFluent;
      26: invokeinterface #142,  1          // InterfaceMethod io/dekorate/deps/servicecatalog/api/model/ClusterServiceClassSpecFluent.getClusterServiceBrokerName:()Ljava/lang/String;
      31: aload_0
      32: getfield      #50                 // Field fluent:Lio/dekorate/deps/servicecatalog/api/model/ClusterServiceClassSpecFluent;
      35: invokeinterface #143,  1          // InterfaceMethod io/dekorate/deps/servicecatalog/api/model/ClusterServiceClassSpecFluent.getDescription:()Ljava/lang/String;
      40: aload_0
      41: getfield      #50                 // Field fluent:Lio/dekorate/deps/servicecatalog/api/model/ClusterServiceClassSpecFluent;
      44: invokeinterface #144,  1          // InterfaceMethod io/dekorate/deps/servicecatalog/api/model/ClusterServiceClassSpecFluent.getExternalID:()Ljava/lang/String;
      49: aload_0
      50: getfield      #50                 // Field fluent:Lio/dekorate/deps/servicecatalog/api/model/ClusterServiceClassSpecFluent;
      53: invokeinterface #145,  1          // InterfaceMethod io/dekorate/deps/servicecatalog/api/model/ClusterServiceClassSpecFluent.getExternalMetadata:()Ljava/util/Map;
      58: aload_0
      59: getfield      #50                 // Field fluent:Lio/dekorate/deps/servicecatalog/api/model/ClusterServiceClassSpecFluent;
      62: invokeinterface #146,  1          // InterfaceMethod io/dekorate/deps/servicecatalog/api/model/ClusterServiceClassSpecFluent.getExternalName:()Ljava/lang/String;
      67: aload_0
      68: getfield      #50                 // Field fluent:Lio/dekorate/deps/servicecatalog/api/model/ClusterServiceClassSpecFluent;
      71: invokeinterface #149,  1          // InterfaceMethod io/dekorate/deps/servicecatalog/api/model/ClusterServiceClassSpecFluent.isPlanUpdatable:()Ljava/lang/Boolean;
      76: aload_0
      77: getfield      #50                 // Field fluent:Lio/dekorate/deps/servicecatalog/api/model/ClusterServiceClassSpecFluent;
      80: invokeinterface #150,  1          // InterfaceMethod io/dekorate/deps/servicecatalog/api/model/ClusterServiceClassSpecFluent.getRequires:()Ljava/util/List;
      85: aload_0
      86: getfield      #50                 // Field fluent:Lio/dekorate/deps/servicecatalog/api/model/ClusterServiceClassSpecFluent;
      89: invokeinterface #151,  1          // InterfaceMethod io/dekorate/deps/servicecatalog/api/model/ClusterServiceClassSpecFluent.getTags:()Ljava/util/List;
      94: invokespecial #154                // Method io/dekorate/deps/servicecatalog/api/model/ClusterServiceClassSpec."<init>":(Ljava/lang/Boolean;Ljava/lang/Boolean;Ljava/lang/String;Ljava/lang/String;Ljava/lang/String;Ljava/util/Map;Ljava/lang/String;Ljava/lang/Boolean;Ljava/util/List;Ljava/util/List;)V
      97: astore_1
      98: aload_1
      99: areturn

  public boolean equals(java.lang.Object);
    Code:
       0: aload_0
       1: aload_1
       2: if_acmpne     7
       5: iconst_1
       6: ireturn
       7: aload_1
       8: ifnull        22
      11: aload_0
      12: invokevirtual #163                // Method java/lang/Object.getClass:()Ljava/lang/Class;
      15: aload_1
      16: invokevirtual #163                // Method java/lang/Object.getClass:()Ljava/lang/Class;
      19: if_acmpeq     24
      22: iconst_0
      23: ireturn
      24: aload_0
      25: aload_1
      26: invokespecial #165                // Method io/dekorate/deps/servicecatalog/api/model/ClusterServiceClassSpecFluentImpl.equals:(Ljava/lang/Object;)Z
      29: ifne          34
      32: iconst_0
      33: ireturn
      34: aload_1
      35: checkcast     #2                  // class io/dekorate/deps/servicecatalog/api/model/ClusterServiceClassSpecBuilder
      38: astore_2
      39: aload_0
      40: getfield      #50                 // Field fluent:Lio/dekorate/deps/servicecatalog/api/model/ClusterServiceClassSpecFluent;
      43: ifnull        71
      46: aload_0
      47: getfield      #50                 // Field fluent:Lio/dekorate/deps/servicecatalog/api/model/ClusterServiceClassSpecFluent;
      50: aload_0
      51: if_acmpeq     71
      54: aload_0
      55: getfield      #50                 // Field fluent:Lio/dekorate/deps/servicecatalog/api/model/ClusterServiceClassSpecFluent;
      58: aload_2
      59: getfield      #50                 // Field fluent:Lio/dekorate/deps/servicecatalog/api/model/ClusterServiceClassSpecFluent;
      62: invokevirtual #166                // Method java/lang/Object.equals:(Ljava/lang/Object;)Z
      65: ifne          88
      68: goto          86
      71: aload_2
      72: getfield      #50                 // Field fluent:Lio/dekorate/deps/servicecatalog/api/model/ClusterServiceClassSpecFluent;
      75: ifnull        88
      78: aload_0
      79: getfield      #50                 // Field fluent:Lio/dekorate/deps/servicecatalog/api/model/ClusterServiceClassSpecFluent;
      82: aload_0
      83: if_acmpeq     88
      86: iconst_0
      87: ireturn
      88: aload_0
      89: getfield      #122                // Field validationEnabled:Ljava/lang/Boolean;
      92: ifnull        112
      95: aload_0
      96: getfield      #122                // Field validationEnabled:Ljava/lang/Boolean;
      99: aload_2
     100: getfield      #122                // Field validationEnabled:Ljava/lang/Boolean;
     103: invokevirtual #167                // Method java/lang/Boolean.equals:(Ljava/lang/Object;)Z
     106: ifne          121
     109: goto          119
     112: aload_2
     113: getfield      #122                // Field validationEnabled:Ljava/lang/Boolean;
     116: ifnull        121
     119: iconst_0
     120: ireturn
     121: iconst_1
     122: ireturn

  public java.lang.Object build();
    Code:
       0: aload_0
       1: invokevirtual #173                // Method build:()Lio/dekorate/deps/servicecatalog/api/model/ClusterServiceClassSpec;
       4: areturn
}
