Compiled from "ValidationSchemaFluentImpl.java"
public class io.dekorate.deps.servicecatalog.api.model.ValidationSchemaFluentImpl<A extends io.dekorate.deps.servicecatalog.api.model.ValidationSchemaFluent<A>> extends io.dekorate.deps.kubernetes.api.builder.BaseFluent<A> implements io.dekorate.deps.servicecatalog.api.model.ValidationSchemaFluent<A> {
  private io.dekorate.deps.servicecatalog.api.model.ClusterServiceBrokerBuilder clusterServiceBroker;

  private io.dekorate.deps.servicecatalog.api.model.ClusterServiceBrokerListBuilder clusterServiceBrokerList;

  private io.dekorate.deps.servicecatalog.api.model.ClusterServiceClassBuilder clusterServiceClass;

  private io.dekorate.deps.servicecatalog.api.model.ClusterServiceClassListBuilder clusterServiceClassList;

  private io.dekorate.deps.servicecatalog.api.model.ClusterServicePlanBuilder clusterServicePlan;

  private io.dekorate.deps.servicecatalog.api.model.ClusterServicePlanListBuilder clusterServicePlanList;

  private io.dekorate.deps.servicecatalog.api.model.ServiceBindingBuilder serviceBinding;

  private io.dekorate.deps.servicecatalog.api.model.ServiceBindingListBuilder serviceBindingList;

  private io.dekorate.deps.servicecatalog.api.model.ServiceBrokerBuilder serviceBroker;

  private io.dekorate.deps.servicecatalog.api.model.ServiceBrokerListBuilder serviceBrokerList;

  private io.dekorate.deps.servicecatalog.api.model.ServiceInstanceBuilder serviceInstance;

  private io.dekorate.deps.servicecatalog.api.model.ServiceInstanceListBuilder serviceInstanceList;

  public io.dekorate.deps.servicecatalog.api.model.ValidationSchemaFluentImpl();
    Code:
       0: aload_0
       1: invokespecial #108                // Method io/dekorate/deps/kubernetes/api/builder/BaseFluent."<init>":()V
       4: return

  public io.dekorate.deps.servicecatalog.api.model.ValidationSchemaFluentImpl(io.dekorate.deps.servicecatalog.api.model.ValidationSchema);
    Code:
       0: aload_0
       1: invokespecial #108                // Method io/dekorate/deps/kubernetes/api/builder/BaseFluent."<init>":()V
       4: aload_0
       5: aload_1
       6: invokevirtual #118                // Method io/dekorate/deps/servicecatalog/api/model/ValidationSchema.getClusterServiceBroker:()Lio/dekorate/deps/servicecatalog/api/model/ClusterServiceBroker;
       9: invokevirtual #122                // Method withClusterServiceBroker:(Lio/dekorate/deps/servicecatalog/api/model/ClusterServiceBroker;)Lio/dekorate/deps/servicecatalog/api/model/ValidationSchemaFluent;
      12: pop
      13: aload_0
      14: aload_1
      15: invokevirtual #126                // Method io/dekorate/deps/servicecatalog/api/model/ValidationSchema.getClusterServiceBrokerList:()Lio/dekorate/deps/servicecatalog/api/model/ClusterServiceBrokerList;
      18: invokevirtual #130                // Method withClusterServiceBrokerList:(Lio/dekorate/deps/servicecatalog/api/model/ClusterServiceBrokerList;)Lio/dekorate/deps/servicecatalog/api/model/ValidationSchemaFluent;
      21: pop
      22: aload_0
      23: aload_1
      24: invokevirtual #134                // Method io/dekorate/deps/servicecatalog/api/model/ValidationSchema.getClusterServiceClass:()Lio/dekorate/deps/servicecatalog/api/model/ClusterServiceClass;
      27: invokevirtual #138                // Method withClusterServiceClass:(Lio/dekorate/deps/servicecatalog/api/model/ClusterServiceClass;)Lio/dekorate/deps/servicecatalog/api/model/ValidationSchemaFluent;
      30: pop
      31: aload_0
      32: aload_1
      33: invokevirtual #142                // Method io/dekorate/deps/servicecatalog/api/model/ValidationSchema.getClusterServiceClassList:()Lio/dekorate/deps/servicecatalog/api/model/ClusterServiceClassList;
      36: invokevirtual #146                // Method withClusterServiceClassList:(Lio/dekorate/deps/servicecatalog/api/model/ClusterServiceClassList;)Lio/dekorate/deps/servicecatalog/api/model/ValidationSchemaFluent;
      39: pop
      40: aload_0
      41: aload_1
      42: invokevirtual #150                // Method io/dekorate/deps/servicecatalog/api/model/ValidationSchema.getClusterServicePlan:()Lio/dekorate/deps/servicecatalog/api/model/ClusterServicePlan;
      45: invokevirtual #154                // Method withClusterServicePlan:(Lio/dekorate/deps/servicecatalog/api/model/ClusterServicePlan;)Lio/dekorate/deps/servicecatalog/api/model/ValidationSchemaFluent;
      48: pop
      49: aload_0
      50: aload_1
      51: invokevirtual #158                // Method io/dekorate/deps/servicecatalog/api/model/ValidationSchema.getClusterServicePlanList:()Lio/dekorate/deps/servicecatalog/api/model/ClusterServicePlanList;
      54: invokevirtual #162                // Method withClusterServicePlanList:(Lio/dekorate/deps/servicecatalog/api/model/ClusterServicePlanList;)Lio/dekorate/deps/servicecatalog/api/model/ValidationSchemaFluent;
      57: pop
      58: aload_0
      59: aload_1
      60: invokevirtual #166                // Method io/dekorate/deps/servicecatalog/api/model/ValidationSchema.getServiceBinding:()Lio/dekorate/deps/servicecatalog/api/model/ServiceBinding;
      63: invokevirtual #170                // Method withServiceBinding:(Lio/dekorate/deps/servicecatalog/api/model/ServiceBinding;)Lio/dekorate/deps/servicecatalog/api/model/ValidationSchemaFluent;
      66: pop
      67: aload_0
      68: aload_1
      69: invokevirtual #174                // Method io/dekorate/deps/servicecatalog/api/model/ValidationSchema.getServiceBindingList:()Lio/dekorate/deps/servicecatalog/api/model/ServiceBindingList;
      72: invokevirtual #178                // Method withServiceBindingList:(Lio/dekorate/deps/servicecatalog/api/model/ServiceBindingList;)Lio/dekorate/deps/servicecatalog/api/model/ValidationSchemaFluent;
      75: pop
      76: aload_0
      77: aload_1
      78: invokevirtual #182                // Method io/dekorate/deps/servicecatalog/api/model/ValidationSchema.getServiceBroker:()Lio/dekorate/deps/servicecatalog/api/model/ServiceBroker;
      81: invokevirtual #186                // Method withServiceBroker:(Lio/dekorate/deps/servicecatalog/api/model/ServiceBroker;)Lio/dekorate/deps/servicecatalog/api/model/ValidationSchemaFluent;
      84: pop
      85: aload_0
      86: aload_1
      87: invokevirtual #190                // Method io/dekorate/deps/servicecatalog/api/model/ValidationSchema.getServiceBrokerList:()Lio/dekorate/deps/servicecatalog/api/model/ServiceBrokerList;
      90: invokevirtual #194                // Method withServiceBrokerList:(Lio/dekorate/deps/servicecatalog/api/model/ServiceBrokerList;)Lio/dekorate/deps/servicecatalog/api/model/ValidationSchemaFluent;
      93: pop
      94: aload_0
      95: aload_1
      96: invokevirtual #198                // Method io/dekorate/deps/servicecatalog/api/model/ValidationSchema.getServiceInstance:()Lio/dekorate/deps/servicecatalog/api/model/ServiceInstance;
      99: invokevirtual #202                // Method withServiceInstance:(Lio/dekorate/deps/servicecatalog/api/model/ServiceInstance;)Lio/dekorate/deps/servicecatalog/api/model/ValidationSchemaFluent;
     102: pop
     103: aload_0
     104: aload_1
     105: invokevirtual #206                // Method io/dekorate/deps/servicecatalog/api/model/ValidationSchema.getServiceInstanceList:()Lio/dekorate/deps/servicecatalog/api/model/ServiceInstanceList;
     108: invokevirtual #210                // Method withServiceInstanceList:(Lio/dekorate/deps/servicecatalog/api/model/ServiceInstanceList;)Lio/dekorate/deps/servicecatalog/api/model/ValidationSchemaFluent;
     111: pop
     112: return

  public io.dekorate.deps.servicecatalog.api.model.ClusterServiceBroker getClusterServiceBroker();
    Code:
       0: aload_0
       1: getfield      #215                // Field clusterServiceBroker:Lio/dekorate/deps/servicecatalog/api/model/ClusterServiceBrokerBuilder;
       4: ifnull        17
       7: aload_0
       8: getfield      #215                // Field clusterServiceBroker:Lio/dekorate/deps/servicecatalog/api/model/ClusterServiceBrokerBuilder;
      11: invokevirtual #220                // Method io/dekorate/deps/servicecatalog/api/model/ClusterServiceBrokerBuilder.build:()Lio/dekorate/deps/servicecatalog/api/model/ClusterServiceBroker;
      14: goto          18
      17: aconst_null
      18: areturn

  public io.dekorate.deps.servicecatalog.api.model.ClusterServiceBroker buildClusterServiceBroker();
    Code:
       0: aload_0
       1: getfield      #215                // Field clusterServiceBroker:Lio/dekorate/deps/servicecatalog/api/model/ClusterServiceBrokerBuilder;
       4: ifnull        17
       7: aload_0
       8: getfield      #215                // Field clusterServiceBroker:Lio/dekorate/deps/servicecatalog/api/model/ClusterServiceBrokerBuilder;
      11: invokevirtual #220                // Method io/dekorate/deps/servicecatalog/api/model/ClusterServiceBrokerBuilder.build:()Lio/dekorate/deps/servicecatalog/api/model/ClusterServiceBroker;
      14: goto          18
      17: aconst_null
      18: areturn

  public A withClusterServiceBroker(io.dekorate.deps.servicecatalog.api.model.ClusterServiceBroker);
    Code:
       0: aload_0
       1: getfield      #228                // Field _visitables:Lio/dekorate/deps/kubernetes/api/builder/VisitableMap;
       4: ldc           #229                // String clusterServiceBroker
       6: invokevirtual #235                // Method io/dekorate/deps/kubernetes/api/builder/VisitableMap.get:(Ljava/lang/Object;)Ljava/util/List;
       9: aload_0
      10: getfield      #215                // Field clusterServiceBroker:Lio/dekorate/deps/servicecatalog/api/model/ClusterServiceBrokerBuilder;
      13: invokeinterface #241,  2          // InterfaceMethod java/util/List.remove:(Ljava/lang/Object;)Z
      18: pop
      19: aload_1
      20: ifnull        54
      23: aload_0
      24: new           #217                // class io/dekorate/deps/servicecatalog/api/model/ClusterServiceBrokerBuilder
      27: dup
      28: aload_1
      29: invokespecial #244                // Method io/dekorate/deps/servicecatalog/api/model/ClusterServiceBrokerBuilder."<init>":(Lio/dekorate/deps/servicecatalog/api/model/ClusterServiceBroker;)V
      32: putfield      #215                // Field clusterServiceBroker:Lio/dekorate/deps/servicecatalog/api/model/ClusterServiceBrokerBuilder;
      35: aload_0
      36: getfield      #228                // Field _visitables:Lio/dekorate/deps/kubernetes/api/builder/VisitableMap;
      39: ldc           #229                // String clusterServiceBroker
      41: invokevirtual #235                // Method io/dekorate/deps/kubernetes/api/builder/VisitableMap.get:(Ljava/lang/Object;)Ljava/util/List;
      44: aload_0
      45: getfield      #215                // Field clusterServiceBroker:Lio/dekorate/deps/servicecatalog/api/model/ClusterServiceBrokerBuilder;
      48: invokeinterface #247,  2          // InterfaceMethod java/util/List.add:(Ljava/lang/Object;)Z
      53: pop
      54: aload_0
      55: areturn

  public java.lang.Boolean hasClusterServiceBroker();
    Code:
       0: aload_0
       1: getfield      #215                // Field clusterServiceBroker:Lio/dekorate/deps/servicecatalog/api/model/ClusterServiceBrokerBuilder;
       4: ifnull        11
       7: iconst_1
       8: goto          12
      11: iconst_0
      12: invokestatic  #256                // Method java/lang/Boolean.valueOf:(Z)Ljava/lang/Boolean;
      15: areturn

  public io.dekorate.deps.servicecatalog.api.model.ValidationSchemaFluent$ClusterServiceBrokerNested<A> withNewClusterServiceBroker();
    Code:
       0: new           #43                 // class io/dekorate/deps/servicecatalog/api/model/ValidationSchemaFluentImpl$ClusterServiceBrokerNestedImpl
       3: dup
       4: aload_0
       5: invokespecial #262                // Method io/dekorate/deps/servicecatalog/api/model/ValidationSchemaFluentImpl$ClusterServiceBrokerNestedImpl."<init>":(Lio/dekorate/deps/servicecatalog/api/model/ValidationSchemaFluentImpl;)V
       8: areturn

  public io.dekorate.deps.servicecatalog.api.model.ValidationSchemaFluent$ClusterServiceBrokerNested<A> withNewClusterServiceBrokerLike(io.dekorate.deps.servicecatalog.api.model.ClusterServiceBroker);
    Code:
       0: new           #43                 // class io/dekorate/deps/servicecatalog/api/model/ValidationSchemaFluentImpl$ClusterServiceBrokerNestedImpl
       3: dup
       4: aload_0
       5: aload_1
       6: invokespecial #268                // Method io/dekorate/deps/servicecatalog/api/model/ValidationSchemaFluentImpl$ClusterServiceBrokerNestedImpl."<init>":(Lio/dekorate/deps/servicecatalog/api/model/ValidationSchemaFluentImpl;Lio/dekorate/deps/servicecatalog/api/model/ClusterServiceBroker;)V
       9: areturn

  public io.dekorate.deps.servicecatalog.api.model.ValidationSchemaFluent$ClusterServiceBrokerNested<A> editClusterServiceBroker();
    Code:
       0: aload_0
       1: aload_0
       2: invokevirtual #271                // Method getClusterServiceBroker:()Lio/dekorate/deps/servicecatalog/api/model/ClusterServiceBroker;
       5: invokevirtual #273                // Method withNewClusterServiceBrokerLike:(Lio/dekorate/deps/servicecatalog/api/model/ClusterServiceBroker;)Lio/dekorate/deps/servicecatalog/api/model/ValidationSchemaFluent$ClusterServiceBrokerNested;
       8: areturn

  public io.dekorate.deps.servicecatalog.api.model.ValidationSchemaFluent$ClusterServiceBrokerNested<A> editOrNewClusterServiceBroker();
    Code:
       0: aload_0
       1: aload_0
       2: invokevirtual #271                // Method getClusterServiceBroker:()Lio/dekorate/deps/servicecatalog/api/model/ClusterServiceBroker;
       5: ifnull        15
       8: aload_0
       9: invokevirtual #271                // Method getClusterServiceBroker:()Lio/dekorate/deps/servicecatalog/api/model/ClusterServiceBroker;
      12: goto          25
      15: new           #217                // class io/dekorate/deps/servicecatalog/api/model/ClusterServiceBrokerBuilder
      18: dup
      19: invokespecial #275                // Method io/dekorate/deps/servicecatalog/api/model/ClusterServiceBrokerBuilder."<init>":()V
      22: invokevirtual #220                // Method io/dekorate/deps/servicecatalog/api/model/ClusterServiceBrokerBuilder.build:()Lio/dekorate/deps/servicecatalog/api/model/ClusterServiceBroker;
      25: invokevirtual #273                // Method withNewClusterServiceBrokerLike:(Lio/dekorate/deps/servicecatalog/api/model/ClusterServiceBroker;)Lio/dekorate/deps/servicecatalog/api/model/ValidationSchemaFluent$ClusterServiceBrokerNested;
      28: areturn

  public io.dekorate.deps.servicecatalog.api.model.ValidationSchemaFluent$ClusterServiceBrokerNested<A> editOrNewClusterServiceBrokerLike(io.dekorate.deps.servicecatalog.api.model.ClusterServiceBroker);
    Code:
       0: aload_0
       1: aload_0
       2: invokevirtual #271                // Method getClusterServiceBroker:()Lio/dekorate/deps/servicecatalog/api/model/ClusterServiceBroker;
       5: ifnull        15
       8: aload_0
       9: invokevirtual #271                // Method getClusterServiceBroker:()Lio/dekorate/deps/servicecatalog/api/model/ClusterServiceBroker;
      12: goto          16
      15: aload_1
      16: invokevirtual #273                // Method withNewClusterServiceBrokerLike:(Lio/dekorate/deps/servicecatalog/api/model/ClusterServiceBroker;)Lio/dekorate/deps/servicecatalog/api/model/ValidationSchemaFluent$ClusterServiceBrokerNested;
      19: areturn

  public io.dekorate.deps.servicecatalog.api.model.ClusterServiceBrokerList getClusterServiceBrokerList();
    Code:
       0: aload_0
       1: getfield      #278                // Field clusterServiceBrokerList:Lio/dekorate/deps/servicecatalog/api/model/ClusterServiceBrokerListBuilder;
       4: ifnull        17
       7: aload_0
       8: getfield      #278                // Field clusterServiceBrokerList:Lio/dekorate/deps/servicecatalog/api/model/ClusterServiceBrokerListBuilder;
      11: invokevirtual #282                // Method io/dekorate/deps/servicecatalog/api/model/ClusterServiceBrokerListBuilder.build:()Lio/dekorate/deps/servicecatalog/api/model/ClusterServiceBrokerList;
      14: goto          18
      17: aconst_null
      18: areturn

  public io.dekorate.deps.servicecatalog.api.model.ClusterServiceBrokerList buildClusterServiceBrokerList();
    Code:
       0: aload_0
       1: getfield      #278                // Field clusterServiceBrokerList:Lio/dekorate/deps/servicecatalog/api/model/ClusterServiceBrokerListBuilder;
       4: ifnull        17
       7: aload_0
       8: getfield      #278                // Field clusterServiceBrokerList:Lio/dekorate/deps/servicecatalog/api/model/ClusterServiceBrokerListBuilder;
      11: invokevirtual #282                // Method io/dekorate/deps/servicecatalog/api/model/ClusterServiceBrokerListBuilder.build:()Lio/dekorate/deps/servicecatalog/api/model/ClusterServiceBrokerList;
      14: goto          18
      17: aconst_null
      18: areturn

  public A withClusterServiceBrokerList(io.dekorate.deps.servicecatalog.api.model.ClusterServiceBrokerList);
    Code:
       0: aload_0
       1: getfield      #228                // Field _visitables:Lio/dekorate/deps/kubernetes/api/builder/VisitableMap;
       4: ldc_w         #287                // String clusterServiceBrokerList
       7: invokevirtual #235                // Method io/dekorate/deps/kubernetes/api/builder/VisitableMap.get:(Ljava/lang/Object;)Ljava/util/List;
      10: aload_0
      11: getfield      #278                // Field clusterServiceBrokerList:Lio/dekorate/deps/servicecatalog/api/model/ClusterServiceBrokerListBuilder;
      14: invokeinterface #241,  2          // InterfaceMethod java/util/List.remove:(Ljava/lang/Object;)Z
      19: pop
      20: aload_1
      21: ifnull        56
      24: aload_0
      25: new           #280                // class io/dekorate/deps/servicecatalog/api/model/ClusterServiceBrokerListBuilder
      28: dup
      29: aload_1
      30: invokespecial #290                // Method io/dekorate/deps/servicecatalog/api/model/ClusterServiceBrokerListBuilder."<init>":(Lio/dekorate/deps/servicecatalog/api/model/ClusterServiceBrokerList;)V
      33: putfield      #278                // Field clusterServiceBrokerList:Lio/dekorate/deps/servicecatalog/api/model/ClusterServiceBrokerListBuilder;
      36: aload_0
      37: getfield      #228                // Field _visitables:Lio/dekorate/deps/kubernetes/api/builder/VisitableMap;
      40: ldc_w         #287                // String clusterServiceBrokerList
      43: invokevirtual #235                // Method io/dekorate/deps/kubernetes/api/builder/VisitableMap.get:(Ljava/lang/Object;)Ljava/util/List;
      46: aload_0
      47: getfield      #278                // Field clusterServiceBrokerList:Lio/dekorate/deps/servicecatalog/api/model/ClusterServiceBrokerListBuilder;
      50: invokeinterface #247,  2          // InterfaceMethod java/util/List.add:(Ljava/lang/Object;)Z
      55: pop
      56: aload_0
      57: areturn

  public java.lang.Boolean hasClusterServiceBrokerList();
    Code:
       0: aload_0
       1: getfield      #278                // Field clusterServiceBrokerList:Lio/dekorate/deps/servicecatalog/api/model/ClusterServiceBrokerListBuilder;
       4: ifnull        11
       7: iconst_1
       8: goto          12
      11: iconst_0
      12: invokestatic  #256                // Method java/lang/Boolean.valueOf:(Z)Ljava/lang/Boolean;
      15: areturn

  public io.dekorate.deps.servicecatalog.api.model.ValidationSchemaFluent$ClusterServiceBrokerListNested<A> withNewClusterServiceBrokerList();
    Code:
       0: new           #40                 // class io/dekorate/deps/servicecatalog/api/model/ValidationSchemaFluentImpl$ClusterServiceBrokerListNestedImpl
       3: dup
       4: aload_0
       5: invokespecial #296                // Method io/dekorate/deps/servicecatalog/api/model/ValidationSchemaFluentImpl$ClusterServiceBrokerListNestedImpl."<init>":(Lio/dekorate/deps/servicecatalog/api/model/ValidationSchemaFluentImpl;)V
       8: areturn

  public io.dekorate.deps.servicecatalog.api.model.ValidationSchemaFluent$ClusterServiceBrokerListNested<A> withNewClusterServiceBrokerListLike(io.dekorate.deps.servicecatalog.api.model.ClusterServiceBrokerList);
    Code:
       0: new           #40                 // class io/dekorate/deps/servicecatalog/api/model/ValidationSchemaFluentImpl$ClusterServiceBrokerListNestedImpl
       3: dup
       4: aload_0
       5: aload_1
       6: invokespecial #302                // Method io/dekorate/deps/servicecatalog/api/model/ValidationSchemaFluentImpl$ClusterServiceBrokerListNestedImpl."<init>":(Lio/dekorate/deps/servicecatalog/api/model/ValidationSchemaFluentImpl;Lio/dekorate/deps/servicecatalog/api/model/ClusterServiceBrokerList;)V
       9: areturn

  public io.dekorate.deps.servicecatalog.api.model.ValidationSchemaFluent$ClusterServiceBrokerListNested<A> editClusterServiceBrokerList();
    Code:
       0: aload_0
       1: aload_0
       2: invokevirtual #304                // Method getClusterServiceBrokerList:()Lio/dekorate/deps/servicecatalog/api/model/ClusterServiceBrokerList;
       5: invokevirtual #306                // Method withNewClusterServiceBrokerListLike:(Lio/dekorate/deps/servicecatalog/api/model/ClusterServiceBrokerList;)Lio/dekorate/deps/servicecatalog/api/model/ValidationSchemaFluent$ClusterServiceBrokerListNested;
       8: areturn

  public io.dekorate.deps.servicecatalog.api.model.ValidationSchemaFluent$ClusterServiceBrokerListNested<A> editOrNewClusterServiceBrokerList();
    Code:
       0: aload_0
       1: aload_0
       2: invokevirtual #304                // Method getClusterServiceBrokerList:()Lio/dekorate/deps/servicecatalog/api/model/ClusterServiceBrokerList;
       5: ifnull        15
       8: aload_0
       9: invokevirtual #304                // Method getClusterServiceBrokerList:()Lio/dekorate/deps/servicecatalog/api/model/ClusterServiceBrokerList;
      12: goto          25
      15: new           #280                // class io/dekorate/deps/servicecatalog/api/model/ClusterServiceBrokerListBuilder
      18: dup
      19: invokespecial #308                // Method io/dekorate/deps/servicecatalog/api/model/ClusterServiceBrokerListBuilder."<init>":()V
      22: invokevirtual #282                // Method io/dekorate/deps/servicecatalog/api/model/ClusterServiceBrokerListBuilder.build:()Lio/dekorate/deps/servicecatalog/api/model/ClusterServiceBrokerList;
      25: invokevirtual #306                // Method withNewClusterServiceBrokerListLike:(Lio/dekorate/deps/servicecatalog/api/model/ClusterServiceBrokerList;)Lio/dekorate/deps/servicecatalog/api/model/ValidationSchemaFluent$ClusterServiceBrokerListNested;
      28: areturn

  public io.dekorate.deps.servicecatalog.api.model.ValidationSchemaFluent$ClusterServiceBrokerListNested<A> editOrNewClusterServiceBrokerListLike(io.dekorate.deps.servicecatalog.api.model.ClusterServiceBrokerList);
    Code:
       0: aload_0
       1: aload_0
       2: invokevirtual #304                // Method getClusterServiceBrokerList:()Lio/dekorate/deps/servicecatalog/api/model/ClusterServiceBrokerList;
       5: ifnull        15
       8: aload_0
       9: invokevirtual #304                // Method getClusterServiceBrokerList:()Lio/dekorate/deps/servicecatalog/api/model/ClusterServiceBrokerList;
      12: goto          16
      15: aload_1
      16: invokevirtual #306                // Method withNewClusterServiceBrokerListLike:(Lio/dekorate/deps/servicecatalog/api/model/ClusterServiceBrokerList;)Lio/dekorate/deps/servicecatalog/api/model/ValidationSchemaFluent$ClusterServiceBrokerListNested;
      19: areturn

  public io.dekorate.deps.servicecatalog.api.model.ClusterServiceClass getClusterServiceClass();
    Code:
       0: aload_0
       1: getfield      #311                // Field clusterServiceClass:Lio/dekorate/deps/servicecatalog/api/model/ClusterServiceClassBuilder;
       4: ifnull        17
       7: aload_0
       8: getfield      #311                // Field clusterServiceClass:Lio/dekorate/deps/servicecatalog/api/model/ClusterServiceClassBuilder;
      11: invokevirtual #315                // Method io/dekorate/deps/servicecatalog/api/model/ClusterServiceClassBuilder.build:()Lio/dekorate/deps/servicecatalog/api/model/ClusterServiceClass;
      14: goto          18
      17: aconst_null
      18: areturn

  public io.dekorate.deps.servicecatalog.api.model.ClusterServiceClass buildClusterServiceClass();
    Code:
       0: aload_0
       1: getfield      #311                // Field clusterServiceClass:Lio/dekorate/deps/servicecatalog/api/model/ClusterServiceClassBuilder;
       4: ifnull        17
       7: aload_0
       8: getfield      #311                // Field clusterServiceClass:Lio/dekorate/deps/servicecatalog/api/model/ClusterServiceClassBuilder;
      11: invokevirtual #315                // Method io/dekorate/deps/servicecatalog/api/model/ClusterServiceClassBuilder.build:()Lio/dekorate/deps/servicecatalog/api/model/ClusterServiceClass;
      14: goto          18
      17: aconst_null
      18: areturn

  public A withClusterServiceClass(io.dekorate.deps.servicecatalog.api.model.ClusterServiceClass);
    Code:
       0: aload_0
       1: getfield      #228                // Field _visitables:Lio/dekorate/deps/kubernetes/api/builder/VisitableMap;
       4: ldc_w         #320                // String clusterServiceClass
       7: invokevirtual #235                // Method io/dekorate/deps/kubernetes/api/builder/VisitableMap.get:(Ljava/lang/Object;)Ljava/util/List;
      10: aload_0
      11: getfield      #311                // Field clusterServiceClass:Lio/dekorate/deps/servicecatalog/api/model/ClusterServiceClassBuilder;
      14: invokeinterface #241,  2          // InterfaceMethod java/util/List.remove:(Ljava/lang/Object;)Z
      19: pop
      20: aload_1
      21: ifnull        56
      24: aload_0
      25: new           #313                // class io/dekorate/deps/servicecatalog/api/model/ClusterServiceClassBuilder
      28: dup
      29: aload_1
      30: invokespecial #323                // Method io/dekorate/deps/servicecatalog/api/model/ClusterServiceClassBuilder."<init>":(Lio/dekorate/deps/servicecatalog/api/model/ClusterServiceClass;)V
      33: putfield      #311                // Field clusterServiceClass:Lio/dekorate/deps/servicecatalog/api/model/ClusterServiceClassBuilder;
      36: aload_0
      37: getfield      #228                // Field _visitables:Lio/dekorate/deps/kubernetes/api/builder/VisitableMap;
      40: ldc_w         #320                // String clusterServiceClass
      43: invokevirtual #235                // Method io/dekorate/deps/kubernetes/api/builder/VisitableMap.get:(Ljava/lang/Object;)Ljava/util/List;
      46: aload_0
      47: getfield      #311                // Field clusterServiceClass:Lio/dekorate/deps/servicecatalog/api/model/ClusterServiceClassBuilder;
      50: invokeinterface #247,  2          // InterfaceMethod java/util/List.add:(Ljava/lang/Object;)Z
      55: pop
      56: aload_0
      57: areturn

  public java.lang.Boolean hasClusterServiceClass();
    Code:
       0: aload_0
       1: getfield      #311                // Field clusterServiceClass:Lio/dekorate/deps/servicecatalog/api/model/ClusterServiceClassBuilder;
       4: ifnull        11
       7: iconst_1
       8: goto          12
      11: iconst_0
      12: invokestatic  #256                // Method java/lang/Boolean.valueOf:(Z)Ljava/lang/Boolean;
      15: areturn

  public io.dekorate.deps.servicecatalog.api.model.ValidationSchemaFluent$ClusterServiceClassNested<A> withNewClusterServiceClass();
    Code:
       0: new           #37                 // class io/dekorate/deps/servicecatalog/api/model/ValidationSchemaFluentImpl$ClusterServiceClassNestedImpl
       3: dup
       4: aload_0
       5: invokespecial #329                // Method io/dekorate/deps/servicecatalog/api/model/ValidationSchemaFluentImpl$ClusterServiceClassNestedImpl."<init>":(Lio/dekorate/deps/servicecatalog/api/model/ValidationSchemaFluentImpl;)V
       8: areturn

  public io.dekorate.deps.servicecatalog.api.model.ValidationSchemaFluent$ClusterServiceClassNested<A> withNewClusterServiceClassLike(io.dekorate.deps.servicecatalog.api.model.ClusterServiceClass);
    Code:
       0: new           #37                 // class io/dekorate/deps/servicecatalog/api/model/ValidationSchemaFluentImpl$ClusterServiceClassNestedImpl
       3: dup
       4: aload_0
       5: aload_1
       6: invokespecial #335                // Method io/dekorate/deps/servicecatalog/api/model/ValidationSchemaFluentImpl$ClusterServiceClassNestedImpl."<init>":(Lio/dekorate/deps/servicecatalog/api/model/ValidationSchemaFluentImpl;Lio/dekorate/deps/servicecatalog/api/model/ClusterServiceClass;)V
       9: areturn

  public io.dekorate.deps.servicecatalog.api.model.ValidationSchemaFluent$ClusterServiceClassNested<A> editClusterServiceClass();
    Code:
       0: aload_0
       1: aload_0
       2: invokevirtual #337                // Method getClusterServiceClass:()Lio/dekorate/deps/servicecatalog/api/model/ClusterServiceClass;
       5: invokevirtual #339                // Method withNewClusterServiceClassLike:(Lio/dekorate/deps/servicecatalog/api/model/ClusterServiceClass;)Lio/dekorate/deps/servicecatalog/api/model/ValidationSchemaFluent$ClusterServiceClassNested;
       8: areturn

  public io.dekorate.deps.servicecatalog.api.model.ValidationSchemaFluent$ClusterServiceClassNested<A> editOrNewClusterServiceClass();
    Code:
       0: aload_0
       1: aload_0
       2: invokevirtual #337                // Method getClusterServiceClass:()Lio/dekorate/deps/servicecatalog/api/model/ClusterServiceClass;
       5: ifnull        15
       8: aload_0
       9: invokevirtual #337                // Method getClusterServiceClass:()Lio/dekorate/deps/servicecatalog/api/model/ClusterServiceClass;
      12: goto          25
      15: new           #313                // class io/dekorate/deps/servicecatalog/api/model/ClusterServiceClassBuilder
      18: dup
      19: invokespecial #341                // Method io/dekorate/deps/servicecatalog/api/model/ClusterServiceClassBuilder."<init>":()V
      22: invokevirtual #315                // Method io/dekorate/deps/servicecatalog/api/model/ClusterServiceClassBuilder.build:()Lio/dekorate/deps/servicecatalog/api/model/ClusterServiceClass;
      25: invokevirtual #339                // Method withNewClusterServiceClassLike:(Lio/dekorate/deps/servicecatalog/api/model/ClusterServiceClass;)Lio/dekorate/deps/servicecatalog/api/model/ValidationSchemaFluent$ClusterServiceClassNested;
      28: areturn

  public io.dekorate.deps.servicecatalog.api.model.ValidationSchemaFluent$ClusterServiceClassNested<A> editOrNewClusterServiceClassLike(io.dekorate.deps.servicecatalog.api.model.ClusterServiceClass);
    Code:
       0: aload_0
       1: aload_0
       2: invokevirtual #337                // Method getClusterServiceClass:()Lio/dekorate/deps/servicecatalog/api/model/ClusterServiceClass;
       5: ifnull        15
       8: aload_0
       9: invokevirtual #337                // Method getClusterServiceClass:()Lio/dekorate/deps/servicecatalog/api/model/ClusterServiceClass;
      12: goto          16
      15: aload_1
      16: invokevirtual #339                // Method withNewClusterServiceClassLike:(Lio/dekorate/deps/servicecatalog/api/model/ClusterServiceClass;)Lio/dekorate/deps/servicecatalog/api/model/ValidationSchemaFluent$ClusterServiceClassNested;
      19: areturn

  public io.dekorate.deps.servicecatalog.api.model.ClusterServiceClassList getClusterServiceClassList();
    Code:
       0: aload_0
       1: getfield      #344                // Field clusterServiceClassList:Lio/dekorate/deps/servicecatalog/api/model/ClusterServiceClassListBuilder;
       4: ifnull        17
       7: aload_0
       8: getfield      #344                // Field clusterServiceClassList:Lio/dekorate/deps/servicecatalog/api/model/ClusterServiceClassListBuilder;
      11: invokevirtual #348                // Method io/dekorate/deps/servicecatalog/api/model/ClusterServiceClassListBuilder.build:()Lio/dekorate/deps/servicecatalog/api/model/ClusterServiceClassList;
      14: goto          18
      17: aconst_null
      18: areturn

  public io.dekorate.deps.servicecatalog.api.model.ClusterServiceClassList buildClusterServiceClassList();
    Code:
       0: aload_0
       1: getfield      #344                // Field clusterServiceClassList:Lio/dekorate/deps/servicecatalog/api/model/ClusterServiceClassListBuilder;
       4: ifnull        17
       7: aload_0
       8: getfield      #344                // Field clusterServiceClassList:Lio/dekorate/deps/servicecatalog/api/model/ClusterServiceClassListBuilder;
      11: invokevirtual #348                // Method io/dekorate/deps/servicecatalog/api/model/ClusterServiceClassListBuilder.build:()Lio/dekorate/deps/servicecatalog/api/model/ClusterServiceClassList;
      14: goto          18
      17: aconst_null
      18: areturn

  public A withClusterServiceClassList(io.dekorate.deps.servicecatalog.api.model.ClusterServiceClassList);
    Code:
       0: aload_0
       1: getfield      #228                // Field _visitables:Lio/dekorate/deps/kubernetes/api/builder/VisitableMap;
       4: ldc_w         #353                // String clusterServiceClassList
       7: invokevirtual #235                // Method io/dekorate/deps/kubernetes/api/builder/VisitableMap.get:(Ljava/lang/Object;)Ljava/util/List;
      10: aload_0
      11: getfield      #344                // Field clusterServiceClassList:Lio/dekorate/deps/servicecatalog/api/model/ClusterServiceClassListBuilder;
      14: invokeinterface #241,  2          // InterfaceMethod java/util/List.remove:(Ljava/lang/Object;)Z
      19: pop
      20: aload_1
      21: ifnull        56
      24: aload_0
      25: new           #346                // class io/dekorate/deps/servicecatalog/api/model/ClusterServiceClassListBuilder
      28: dup
      29: aload_1
      30: invokespecial #356                // Method io/dekorate/deps/servicecatalog/api/model/ClusterServiceClassListBuilder."<init>":(Lio/dekorate/deps/servicecatalog/api/model/ClusterServiceClassList;)V
      33: putfield      #344                // Field clusterServiceClassList:Lio/dekorate/deps/servicecatalog/api/model/ClusterServiceClassListBuilder;
      36: aload_0
      37: getfield      #228                // Field _visitables:Lio/dekorate/deps/kubernetes/api/builder/VisitableMap;
      40: ldc_w         #353                // String clusterServiceClassList
      43: invokevirtual #235                // Method io/dekorate/deps/kubernetes/api/builder/VisitableMap.get:(Ljava/lang/Object;)Ljava/util/List;
      46: aload_0
      47: getfield      #344                // Field clusterServiceClassList:Lio/dekorate/deps/servicecatalog/api/model/ClusterServiceClassListBuilder;
      50: invokeinterface #247,  2          // InterfaceMethod java/util/List.add:(Ljava/lang/Object;)Z
      55: pop
      56: aload_0
      57: areturn

  public java.lang.Boolean hasClusterServiceClassList();
    Code:
       0: aload_0
       1: getfield      #344                // Field clusterServiceClassList:Lio/dekorate/deps/servicecatalog/api/model/ClusterServiceClassListBuilder;
       4: ifnull        11
       7: iconst_1
       8: goto          12
      11: iconst_0
      12: invokestatic  #256                // Method java/lang/Boolean.valueOf:(Z)Ljava/lang/Boolean;
      15: areturn

  public io.dekorate.deps.servicecatalog.api.model.ValidationSchemaFluent$ClusterServiceClassListNested<A> withNewClusterServiceClassList();
    Code:
       0: new           #34                 // class io/dekorate/deps/servicecatalog/api/model/ValidationSchemaFluentImpl$ClusterServiceClassListNestedImpl
       3: dup
       4: aload_0
       5: invokespecial #362                // Method io/dekorate/deps/servicecatalog/api/model/ValidationSchemaFluentImpl$ClusterServiceClassListNestedImpl."<init>":(Lio/dekorate/deps/servicecatalog/api/model/ValidationSchemaFluentImpl;)V
       8: areturn

  public io.dekorate.deps.servicecatalog.api.model.ValidationSchemaFluent$ClusterServiceClassListNested<A> withNewClusterServiceClassListLike(io.dekorate.deps.servicecatalog.api.model.ClusterServiceClassList);
    Code:
       0: new           #34                 // class io/dekorate/deps/servicecatalog/api/model/ValidationSchemaFluentImpl$ClusterServiceClassListNestedImpl
       3: dup
       4: aload_0
       5: aload_1
       6: invokespecial #368                // Method io/dekorate/deps/servicecatalog/api/model/ValidationSchemaFluentImpl$ClusterServiceClassListNestedImpl."<init>":(Lio/dekorate/deps/servicecatalog/api/model/ValidationSchemaFluentImpl;Lio/dekorate/deps/servicecatalog/api/model/ClusterServiceClassList;)V
       9: areturn

  public io.dekorate.deps.servicecatalog.api.model.ValidationSchemaFluent$ClusterServiceClassListNested<A> editClusterServiceClassList();
    Code:
       0: aload_0
       1: aload_0
       2: invokevirtual #370                // Method getClusterServiceClassList:()Lio/dekorate/deps/servicecatalog/api/model/ClusterServiceClassList;
       5: invokevirtual #372                // Method withNewClusterServiceClassListLike:(Lio/dekorate/deps/servicecatalog/api/model/ClusterServiceClassList;)Lio/dekorate/deps/servicecatalog/api/model/ValidationSchemaFluent$ClusterServiceClassListNested;
       8: areturn

  public io.dekorate.deps.servicecatalog.api.model.ValidationSchemaFluent$ClusterServiceClassListNested<A> editOrNewClusterServiceClassList();
    Code:
       0: aload_0
       1: aload_0
       2: invokevirtual #370                // Method getClusterServiceClassList:()Lio/dekorate/deps/servicecatalog/api/model/ClusterServiceClassList;
       5: ifnull        15
       8: aload_0
       9: invokevirtual #370                // Method getClusterServiceClassList:()Lio/dekorate/deps/servicecatalog/api/model/ClusterServiceClassList;
      12: goto          25
      15: new           #346                // class io/dekorate/deps/servicecatalog/api/model/ClusterServiceClassListBuilder
      18: dup
      19: invokespecial #374                // Method io/dekorate/deps/servicecatalog/api/model/ClusterServiceClassListBuilder."<init>":()V
      22: invokevirtual #348                // Method io/dekorate/deps/servicecatalog/api/model/ClusterServiceClassListBuilder.build:()Lio/dekorate/deps/servicecatalog/api/model/ClusterServiceClassList;
      25: invokevirtual #372                // Method withNewClusterServiceClassListLike:(Lio/dekorate/deps/servicecatalog/api/model/ClusterServiceClassList;)Lio/dekorate/deps/servicecatalog/api/model/ValidationSchemaFluent$ClusterServiceClassListNested;
      28: areturn

  public io.dekorate.deps.servicecatalog.api.model.ValidationSchemaFluent$ClusterServiceClassListNested<A> editOrNewClusterServiceClassListLike(io.dekorate.deps.servicecatalog.api.model.ClusterServiceClassList);
    Code:
       0: aload_0
       1: aload_0
       2: invokevirtual #370                // Method getClusterServiceClassList:()Lio/dekorate/deps/servicecatalog/api/model/ClusterServiceClassList;
       5: ifnull        15
       8: aload_0
       9: invokevirtual #370                // Method getClusterServiceClassList:()Lio/dekorate/deps/servicecatalog/api/model/ClusterServiceClassList;
      12: goto          16
      15: aload_1
      16: invokevirtual #372                // Method withNewClusterServiceClassListLike:(Lio/dekorate/deps/servicecatalog/api/model/ClusterServiceClassList;)Lio/dekorate/deps/servicecatalog/api/model/ValidationSchemaFluent$ClusterServiceClassListNested;
      19: areturn

  public io.dekorate.deps.servicecatalog.api.model.ClusterServicePlan getClusterServicePlan();
    Code:
       0: aload_0
       1: getfield      #377                // Field clusterServicePlan:Lio/dekorate/deps/servicecatalog/api/model/ClusterServicePlanBuilder;
       4: ifnull        17
       7: aload_0
       8: getfield      #377                // Field clusterServicePlan:Lio/dekorate/deps/servicecatalog/api/model/ClusterServicePlanBuilder;
      11: invokevirtual #381                // Method io/dekorate/deps/servicecatalog/api/model/ClusterServicePlanBuilder.build:()Lio/dekorate/deps/servicecatalog/api/model/ClusterServicePlan;
      14: goto          18
      17: aconst_null
      18: areturn

  public io.dekorate.deps.servicecatalog.api.model.ClusterServicePlan buildClusterServicePlan();
    Code:
       0: aload_0
       1: getfield      #377                // Field clusterServicePlan:Lio/dekorate/deps/servicecatalog/api/model/ClusterServicePlanBuilder;
       4: ifnull        17
       7: aload_0
       8: getfield      #377                // Field clusterServicePlan:Lio/dekorate/deps/servicecatalog/api/model/ClusterServicePlanBuilder;
      11: invokevirtual #381                // Method io/dekorate/deps/servicecatalog/api/model/ClusterServicePlanBuilder.build:()Lio/dekorate/deps/servicecatalog/api/model/ClusterServicePlan;
      14: goto          18
      17: aconst_null
      18: areturn

  public A withClusterServicePlan(io.dekorate.deps.servicecatalog.api.model.ClusterServicePlan);
    Code:
       0: aload_0
       1: getfield      #228                // Field _visitables:Lio/dekorate/deps/kubernetes/api/builder/VisitableMap;
       4: ldc_w         #386                // String clusterServicePlan
       7: invokevirtual #235                // Method io/dekorate/deps/kubernetes/api/builder/VisitableMap.get:(Ljava/lang/Object;)Ljava/util/List;
      10: aload_0
      11: getfield      #377                // Field clusterServicePlan:Lio/dekorate/deps/servicecatalog/api/model/ClusterServicePlanBuilder;
      14: invokeinterface #241,  2          // InterfaceMethod java/util/List.remove:(Ljava/lang/Object;)Z
      19: pop
      20: aload_1
      21: ifnull        56
      24: aload_0
      25: new           #379                // class io/dekorate/deps/servicecatalog/api/model/ClusterServicePlanBuilder
      28: dup
      29: aload_1
      30: invokespecial #389                // Method io/dekorate/deps/servicecatalog/api/model/ClusterServicePlanBuilder."<init>":(Lio/dekorate/deps/servicecatalog/api/model/ClusterServicePlan;)V
      33: putfield      #377                // Field clusterServicePlan:Lio/dekorate/deps/servicecatalog/api/model/ClusterServicePlanBuilder;
      36: aload_0
      37: getfield      #228                // Field _visitables:Lio/dekorate/deps/kubernetes/api/builder/VisitableMap;
      40: ldc_w         #386                // String clusterServicePlan
      43: invokevirtual #235                // Method io/dekorate/deps/kubernetes/api/builder/VisitableMap.get:(Ljava/lang/Object;)Ljava/util/List;
      46: aload_0
      47: getfield      #377                // Field clusterServicePlan:Lio/dekorate/deps/servicecatalog/api/model/ClusterServicePlanBuilder;
      50: invokeinterface #247,  2          // InterfaceMethod java/util/List.add:(Ljava/lang/Object;)Z
      55: pop
      56: aload_0
      57: areturn

  public java.lang.Boolean hasClusterServicePlan();
    Code:
       0: aload_0
       1: getfield      #377                // Field clusterServicePlan:Lio/dekorate/deps/servicecatalog/api/model/ClusterServicePlanBuilder;
       4: ifnull        11
       7: iconst_1
       8: goto          12
      11: iconst_0
      12: invokestatic  #256                // Method java/lang/Boolean.valueOf:(Z)Ljava/lang/Boolean;
      15: areturn

  public io.dekorate.deps.servicecatalog.api.model.ValidationSchemaFluent$ClusterServicePlanNested<A> withNewClusterServicePlan();
    Code:
       0: new           #31                 // class io/dekorate/deps/servicecatalog/api/model/ValidationSchemaFluentImpl$ClusterServicePlanNestedImpl
       3: dup
       4: aload_0
       5: invokespecial #395                // Method io/dekorate/deps/servicecatalog/api/model/ValidationSchemaFluentImpl$ClusterServicePlanNestedImpl."<init>":(Lio/dekorate/deps/servicecatalog/api/model/ValidationSchemaFluentImpl;)V
       8: areturn

  public io.dekorate.deps.servicecatalog.api.model.ValidationSchemaFluent$ClusterServicePlanNested<A> withNewClusterServicePlanLike(io.dekorate.deps.servicecatalog.api.model.ClusterServicePlan);
    Code:
       0: new           #31                 // class io/dekorate/deps/servicecatalog/api/model/ValidationSchemaFluentImpl$ClusterServicePlanNestedImpl
       3: dup
       4: aload_0
       5: aload_1
       6: invokespecial #401                // Method io/dekorate/deps/servicecatalog/api/model/ValidationSchemaFluentImpl$ClusterServicePlanNestedImpl."<init>":(Lio/dekorate/deps/servicecatalog/api/model/ValidationSchemaFluentImpl;Lio/dekorate/deps/servicecatalog/api/model/ClusterServicePlan;)V
       9: areturn

  public io.dekorate.deps.servicecatalog.api.model.ValidationSchemaFluent$ClusterServicePlanNested<A> editClusterServicePlan();
    Code:
       0: aload_0
       1: aload_0
       2: invokevirtual #403                // Method getClusterServicePlan:()Lio/dekorate/deps/servicecatalog/api/model/ClusterServicePlan;
       5: invokevirtual #405                // Method withNewClusterServicePlanLike:(Lio/dekorate/deps/servicecatalog/api/model/ClusterServicePlan;)Lio/dekorate/deps/servicecatalog/api/model/ValidationSchemaFluent$ClusterServicePlanNested;
       8: areturn

  public io.dekorate.deps.servicecatalog.api.model.ValidationSchemaFluent$ClusterServicePlanNested<A> editOrNewClusterServicePlan();
    Code:
       0: aload_0
       1: aload_0
       2: invokevirtual #403                // Method getClusterServicePlan:()Lio/dekorate/deps/servicecatalog/api/model/ClusterServicePlan;
       5: ifnull        15
       8: aload_0
       9: invokevirtual #403                // Method getClusterServicePlan:()Lio/dekorate/deps/servicecatalog/api/model/ClusterServicePlan;
      12: goto          25
      15: new           #379                // class io/dekorate/deps/servicecatalog/api/model/ClusterServicePlanBuilder
      18: dup
      19: invokespecial #407                // Method io/dekorate/deps/servicecatalog/api/model/ClusterServicePlanBuilder."<init>":()V
      22: invokevirtual #381                // Method io/dekorate/deps/servicecatalog/api/model/ClusterServicePlanBuilder.build:()Lio/dekorate/deps/servicecatalog/api/model/ClusterServicePlan;
      25: invokevirtual #405                // Method withNewClusterServicePlanLike:(Lio/dekorate/deps/servicecatalog/api/model/ClusterServicePlan;)Lio/dekorate/deps/servicecatalog/api/model/ValidationSchemaFluent$ClusterServicePlanNested;
      28: areturn

  public io.dekorate.deps.servicecatalog.api.model.ValidationSchemaFluent$ClusterServicePlanNested<A> editOrNewClusterServicePlanLike(io.dekorate.deps.servicecatalog.api.model.ClusterServicePlan);
    Code:
       0: aload_0
       1: aload_0
       2: invokevirtual #403                // Method getClusterServicePlan:()Lio/dekorate/deps/servicecatalog/api/model/ClusterServicePlan;
       5: ifnull        15
       8: aload_0
       9: invokevirtual #403                // Method getClusterServicePlan:()Lio/dekorate/deps/servicecatalog/api/model/ClusterServicePlan;
      12: goto          16
      15: aload_1
      16: invokevirtual #405                // Method withNewClusterServicePlanLike:(Lio/dekorate/deps/servicecatalog/api/model/ClusterServicePlan;)Lio/dekorate/deps/servicecatalog/api/model/ValidationSchemaFluent$ClusterServicePlanNested;
      19: areturn

  public io.dekorate.deps.servicecatalog.api.model.ClusterServicePlanList getClusterServicePlanList();
    Code:
       0: aload_0
       1: getfield      #410                // Field clusterServicePlanList:Lio/dekorate/deps/servicecatalog/api/model/ClusterServicePlanListBuilder;
       4: ifnull        17
       7: aload_0
       8: getfield      #410                // Field clusterServicePlanList:Lio/dekorate/deps/servicecatalog/api/model/ClusterServicePlanListBuilder;
      11: invokevirtual #414                // Method io/dekorate/deps/servicecatalog/api/model/ClusterServicePlanListBuilder.build:()Lio/dekorate/deps/servicecatalog/api/model/ClusterServicePlanList;
      14: goto          18
      17: aconst_null
      18: areturn

  public io.dekorate.deps.servicecatalog.api.model.ClusterServicePlanList buildClusterServicePlanList();
    Code:
       0: aload_0
       1: getfield      #410                // Field clusterServicePlanList:Lio/dekorate/deps/servicecatalog/api/model/ClusterServicePlanListBuilder;
       4: ifnull        17
       7: aload_0
       8: getfield      #410                // Field clusterServicePlanList:Lio/dekorate/deps/servicecatalog/api/model/ClusterServicePlanListBuilder;
      11: invokevirtual #414                // Method io/dekorate/deps/servicecatalog/api/model/ClusterServicePlanListBuilder.build:()Lio/dekorate/deps/servicecatalog/api/model/ClusterServicePlanList;
      14: goto          18
      17: aconst_null
      18: areturn

  public A withClusterServicePlanList(io.dekorate.deps.servicecatalog.api.model.ClusterServicePlanList);
    Code:
       0: aload_0
       1: getfield      #228                // Field _visitables:Lio/dekorate/deps/kubernetes/api/builder/VisitableMap;
       4: ldc_w         #419                // String clusterServicePlanList
       7: invokevirtual #235                // Method io/dekorate/deps/kubernetes/api/builder/VisitableMap.get:(Ljava/lang/Object;)Ljava/util/List;
      10: aload_0
      11: getfield      #410                // Field clusterServicePlanList:Lio/dekorate/deps/servicecatalog/api/model/ClusterServicePlanListBuilder;
      14: invokeinterface #241,  2          // InterfaceMethod java/util/List.remove:(Ljava/lang/Object;)Z
      19: pop
      20: aload_1
      21: ifnull        56
      24: aload_0
      25: new           #412                // class io/dekorate/deps/servicecatalog/api/model/ClusterServicePlanListBuilder
      28: dup
      29: aload_1
      30: invokespecial #422                // Method io/dekorate/deps/servicecatalog/api/model/ClusterServicePlanListBuilder."<init>":(Lio/dekorate/deps/servicecatalog/api/model/ClusterServicePlanList;)V
      33: putfield      #410                // Field clusterServicePlanList:Lio/dekorate/deps/servicecatalog/api/model/ClusterServicePlanListBuilder;
      36: aload_0
      37: getfield      #228                // Field _visitables:Lio/dekorate/deps/kubernetes/api/builder/VisitableMap;
      40: ldc_w         #419                // String clusterServicePlanList
      43: invokevirtual #235                // Method io/dekorate/deps/kubernetes/api/builder/VisitableMap.get:(Ljava/lang/Object;)Ljava/util/List;
      46: aload_0
      47: getfield      #410                // Field clusterServicePlanList:Lio/dekorate/deps/servicecatalog/api/model/ClusterServicePlanListBuilder;
      50: invokeinterface #247,  2          // InterfaceMethod java/util/List.add:(Ljava/lang/Object;)Z
      55: pop
      56: aload_0
      57: areturn

  public java.lang.Boolean hasClusterServicePlanList();
    Code:
       0: aload_0
       1: getfield      #410                // Field clusterServicePlanList:Lio/dekorate/deps/servicecatalog/api/model/ClusterServicePlanListBuilder;
       4: ifnull        11
       7: iconst_1
       8: goto          12
      11: iconst_0
      12: invokestatic  #256                // Method java/lang/Boolean.valueOf:(Z)Ljava/lang/Boolean;
      15: areturn

  public io.dekorate.deps.servicecatalog.api.model.ValidationSchemaFluent$ClusterServicePlanListNested<A> withNewClusterServicePlanList();
    Code:
       0: new           #28                 // class io/dekorate/deps/servicecatalog/api/model/ValidationSchemaFluentImpl$ClusterServicePlanListNestedImpl
       3: dup
       4: aload_0
       5: invokespecial #428                // Method io/dekorate/deps/servicecatalog/api/model/ValidationSchemaFluentImpl$ClusterServicePlanListNestedImpl."<init>":(Lio/dekorate/deps/servicecatalog/api/model/ValidationSchemaFluentImpl;)V
       8: areturn

  public io.dekorate.deps.servicecatalog.api.model.ValidationSchemaFluent$ClusterServicePlanListNested<A> withNewClusterServicePlanListLike(io.dekorate.deps.servicecatalog.api.model.ClusterServicePlanList);
    Code:
       0: new           #28                 // class io/dekorate/deps/servicecatalog/api/model/ValidationSchemaFluentImpl$ClusterServicePlanListNestedImpl
       3: dup
       4: aload_0
       5: aload_1
       6: invokespecial #434                // Method io/dekorate/deps/servicecatalog/api/model/ValidationSchemaFluentImpl$ClusterServicePlanListNestedImpl."<init>":(Lio/dekorate/deps/servicecatalog/api/model/ValidationSchemaFluentImpl;Lio/dekorate/deps/servicecatalog/api/model/ClusterServicePlanList;)V
       9: areturn

  public io.dekorate.deps.servicecatalog.api.model.ValidationSchemaFluent$ClusterServicePlanListNested<A> editClusterServicePlanList();
    Code:
       0: aload_0
       1: aload_0
       2: invokevirtual #436                // Method getClusterServicePlanList:()Lio/dekorate/deps/servicecatalog/api/model/ClusterServicePlanList;
       5: invokevirtual #438                // Method withNewClusterServicePlanListLike:(Lio/dekorate/deps/servicecatalog/api/model/ClusterServicePlanList;)Lio/dekorate/deps/servicecatalog/api/model/ValidationSchemaFluent$ClusterServicePlanListNested;
       8: areturn

  public io.dekorate.deps.servicecatalog.api.model.ValidationSchemaFluent$ClusterServicePlanListNested<A> editOrNewClusterServicePlanList();
    Code:
       0: aload_0
       1: aload_0
       2: invokevirtual #436                // Method getClusterServicePlanList:()Lio/dekorate/deps/servicecatalog/api/model/ClusterServicePlanList;
       5: ifnull        15
       8: aload_0
       9: invokevirtual #436                // Method getClusterServicePlanList:()Lio/dekorate/deps/servicecatalog/api/model/ClusterServicePlanList;
      12: goto          25
      15: new           #412                // class io/dekorate/deps/servicecatalog/api/model/ClusterServicePlanListBuilder
      18: dup
      19: invokespecial #440                // Method io/dekorate/deps/servicecatalog/api/model/ClusterServicePlanListBuilder."<init>":()V
      22: invokevirtual #414                // Method io/dekorate/deps/servicecatalog/api/model/ClusterServicePlanListBuilder.build:()Lio/dekorate/deps/servicecatalog/api/model/ClusterServicePlanList;
      25: invokevirtual #438                // Method withNewClusterServicePlanListLike:(Lio/dekorate/deps/servicecatalog/api/model/ClusterServicePlanList;)Lio/dekorate/deps/servicecatalog/api/model/ValidationSchemaFluent$ClusterServicePlanListNested;
      28: areturn

  public io.dekorate.deps.servicecatalog.api.model.ValidationSchemaFluent$ClusterServicePlanListNested<A> editOrNewClusterServicePlanListLike(io.dekorate.deps.servicecatalog.api.model.ClusterServicePlanList);
    Code:
       0: aload_0
       1: aload_0
       2: invokevirtual #436                // Method getClusterServicePlanList:()Lio/dekorate/deps/servicecatalog/api/model/ClusterServicePlanList;
       5: ifnull        15
       8: aload_0
       9: invokevirtual #436                // Method getClusterServicePlanList:()Lio/dekorate/deps/servicecatalog/api/model/ClusterServicePlanList;
      12: goto          16
      15: aload_1
      16: invokevirtual #438                // Method withNewClusterServicePlanListLike:(Lio/dekorate/deps/servicecatalog/api/model/ClusterServicePlanList;)Lio/dekorate/deps/servicecatalog/api/model/ValidationSchemaFluent$ClusterServicePlanListNested;
      19: areturn

  public io.dekorate.deps.servicecatalog.api.model.ServiceBinding getServiceBinding();
    Code:
       0: aload_0
       1: getfield      #443                // Field serviceBinding:Lio/dekorate/deps/servicecatalog/api/model/ServiceBindingBuilder;
       4: ifnull        17
       7: aload_0
       8: getfield      #443                // Field serviceBinding:Lio/dekorate/deps/servicecatalog/api/model/ServiceBindingBuilder;
      11: invokevirtual #447                // Method io/dekorate/deps/servicecatalog/api/model/ServiceBindingBuilder.build:()Lio/dekorate/deps/servicecatalog/api/model/ServiceBinding;
      14: goto          18
      17: aconst_null
      18: areturn

  public io.dekorate.deps.servicecatalog.api.model.ServiceBinding buildServiceBinding();
    Code:
       0: aload_0
       1: getfield      #443                // Field serviceBinding:Lio/dekorate/deps/servicecatalog/api/model/ServiceBindingBuilder;
       4: ifnull        17
       7: aload_0
       8: getfield      #443                // Field serviceBinding:Lio/dekorate/deps/servicecatalog/api/model/ServiceBindingBuilder;
      11: invokevirtual #447                // Method io/dekorate/deps/servicecatalog/api/model/ServiceBindingBuilder.build:()Lio/dekorate/deps/servicecatalog/api/model/ServiceBinding;
      14: goto          18
      17: aconst_null
      18: areturn

  public A withServiceBinding(io.dekorate.deps.servicecatalog.api.model.ServiceBinding);
    Code:
       0: aload_0
       1: getfield      #228                // Field _visitables:Lio/dekorate/deps/kubernetes/api/builder/VisitableMap;
       4: ldc_w         #452                // String serviceBinding
       7: invokevirtual #235                // Method io/dekorate/deps/kubernetes/api/builder/VisitableMap.get:(Ljava/lang/Object;)Ljava/util/List;
      10: aload_0
      11: getfield      #443                // Field serviceBinding:Lio/dekorate/deps/servicecatalog/api/model/ServiceBindingBuilder;
      14: invokeinterface #241,  2          // InterfaceMethod java/util/List.remove:(Ljava/lang/Object;)Z
      19: pop
      20: aload_1
      21: ifnull        56
      24: aload_0
      25: new           #445                // class io/dekorate/deps/servicecatalog/api/model/ServiceBindingBuilder
      28: dup
      29: aload_1
      30: invokespecial #455                // Method io/dekorate/deps/servicecatalog/api/model/ServiceBindingBuilder."<init>":(Lio/dekorate/deps/servicecatalog/api/model/ServiceBinding;)V
      33: putfield      #443                // Field serviceBinding:Lio/dekorate/deps/servicecatalog/api/model/ServiceBindingBuilder;
      36: aload_0
      37: getfield      #228                // Field _visitables:Lio/dekorate/deps/kubernetes/api/builder/VisitableMap;
      40: ldc_w         #452                // String serviceBinding
      43: invokevirtual #235                // Method io/dekorate/deps/kubernetes/api/builder/VisitableMap.get:(Ljava/lang/Object;)Ljava/util/List;
      46: aload_0
      47: getfield      #443                // Field serviceBinding:Lio/dekorate/deps/servicecatalog/api/model/ServiceBindingBuilder;
      50: invokeinterface #247,  2          // InterfaceMethod java/util/List.add:(Ljava/lang/Object;)Z
      55: pop
      56: aload_0
      57: areturn

  public java.lang.Boolean hasServiceBinding();
    Code:
       0: aload_0
       1: getfield      #443                // Field serviceBinding:Lio/dekorate/deps/servicecatalog/api/model/ServiceBindingBuilder;
       4: ifnull        11
       7: iconst_1
       8: goto          12
      11: iconst_0
      12: invokestatic  #256                // Method java/lang/Boolean.valueOf:(Z)Ljava/lang/Boolean;
      15: areturn

  public io.dekorate.deps.servicecatalog.api.model.ValidationSchemaFluent$ServiceBindingNested<A> withNewServiceBinding();
    Code:
       0: new           #25                 // class io/dekorate/deps/servicecatalog/api/model/ValidationSchemaFluentImpl$ServiceBindingNestedImpl
       3: dup
       4: aload_0
       5: invokespecial #461                // Method io/dekorate/deps/servicecatalog/api/model/ValidationSchemaFluentImpl$ServiceBindingNestedImpl."<init>":(Lio/dekorate/deps/servicecatalog/api/model/ValidationSchemaFluentImpl;)V
       8: areturn

  public io.dekorate.deps.servicecatalog.api.model.ValidationSchemaFluent$ServiceBindingNested<A> withNewServiceBindingLike(io.dekorate.deps.servicecatalog.api.model.ServiceBinding);
    Code:
       0: new           #25                 // class io/dekorate/deps/servicecatalog/api/model/ValidationSchemaFluentImpl$ServiceBindingNestedImpl
       3: dup
       4: aload_0
       5: aload_1
       6: invokespecial #467                // Method io/dekorate/deps/servicecatalog/api/model/ValidationSchemaFluentImpl$ServiceBindingNestedImpl."<init>":(Lio/dekorate/deps/servicecatalog/api/model/ValidationSchemaFluentImpl;Lio/dekorate/deps/servicecatalog/api/model/ServiceBinding;)V
       9: areturn

  public io.dekorate.deps.servicecatalog.api.model.ValidationSchemaFluent$ServiceBindingNested<A> editServiceBinding();
    Code:
       0: aload_0
       1: aload_0
       2: invokevirtual #469                // Method getServiceBinding:()Lio/dekorate/deps/servicecatalog/api/model/ServiceBinding;
       5: invokevirtual #471                // Method withNewServiceBindingLike:(Lio/dekorate/deps/servicecatalog/api/model/ServiceBinding;)Lio/dekorate/deps/servicecatalog/api/model/ValidationSchemaFluent$ServiceBindingNested;
       8: areturn

  public io.dekorate.deps.servicecatalog.api.model.ValidationSchemaFluent$ServiceBindingNested<A> editOrNewServiceBinding();
    Code:
       0: aload_0
       1: aload_0
       2: invokevirtual #469                // Method getServiceBinding:()Lio/dekorate/deps/servicecatalog/api/model/ServiceBinding;
       5: ifnull        15
       8: aload_0
       9: invokevirtual #469                // Method getServiceBinding:()Lio/dekorate/deps/servicecatalog/api/model/ServiceBinding;
      12: goto          25
      15: new           #445                // class io/dekorate/deps/servicecatalog/api/model/ServiceBindingBuilder
      18: dup
      19: invokespecial #473                // Method io/dekorate/deps/servicecatalog/api/model/ServiceBindingBuilder."<init>":()V
      22: invokevirtual #447                // Method io/dekorate/deps/servicecatalog/api/model/ServiceBindingBuilder.build:()Lio/dekorate/deps/servicecatalog/api/model/ServiceBinding;
      25: invokevirtual #471                // Method withNewServiceBindingLike:(Lio/dekorate/deps/servicecatalog/api/model/ServiceBinding;)Lio/dekorate/deps/servicecatalog/api/model/ValidationSchemaFluent$ServiceBindingNested;
      28: areturn

  public io.dekorate.deps.servicecatalog.api.model.ValidationSchemaFluent$ServiceBindingNested<A> editOrNewServiceBindingLike(io.dekorate.deps.servicecatalog.api.model.ServiceBinding);
    Code:
       0: aload_0
       1: aload_0
       2: invokevirtual #469                // Method getServiceBinding:()Lio/dekorate/deps/servicecatalog/api/model/ServiceBinding;
       5: ifnull        15
       8: aload_0
       9: invokevirtual #469                // Method getServiceBinding:()Lio/dekorate/deps/servicecatalog/api/model/ServiceBinding;
      12: goto          16
      15: aload_1
      16: invokevirtual #471                // Method withNewServiceBindingLike:(Lio/dekorate/deps/servicecatalog/api/model/ServiceBinding;)Lio/dekorate/deps/servicecatalog/api/model/ValidationSchemaFluent$ServiceBindingNested;
      19: areturn

  public io.dekorate.deps.servicecatalog.api.model.ServiceBindingList getServiceBindingList();
    Code:
       0: aload_0
       1: getfield      #476                // Field serviceBindingList:Lio/dekorate/deps/servicecatalog/api/model/ServiceBindingListBuilder;
       4: ifnull        17
       7: aload_0
       8: getfield      #476                // Field serviceBindingList:Lio/dekorate/deps/servicecatalog/api/model/ServiceBindingListBuilder;
      11: invokevirtual #480                // Method io/dekorate/deps/servicecatalog/api/model/ServiceBindingListBuilder.build:()Lio/dekorate/deps/servicecatalog/api/model/ServiceBindingList;
      14: goto          18
      17: aconst_null
      18: areturn

  public io.dekorate.deps.servicecatalog.api.model.ServiceBindingList buildServiceBindingList();
    Code:
       0: aload_0
       1: getfield      #476                // Field serviceBindingList:Lio/dekorate/deps/servicecatalog/api/model/ServiceBindingListBuilder;
       4: ifnull        17
       7: aload_0
       8: getfield      #476                // Field serviceBindingList:Lio/dekorate/deps/servicecatalog/api/model/ServiceBindingListBuilder;
      11: invokevirtual #480                // Method io/dekorate/deps/servicecatalog/api/model/ServiceBindingListBuilder.build:()Lio/dekorate/deps/servicecatalog/api/model/ServiceBindingList;
      14: goto          18
      17: aconst_null
      18: areturn

  public A withServiceBindingList(io.dekorate.deps.servicecatalog.api.model.ServiceBindingList);
    Code:
       0: aload_0
       1: getfield      #228                // Field _visitables:Lio/dekorate/deps/kubernetes/api/builder/VisitableMap;
       4: ldc_w         #485                // String serviceBindingList
       7: invokevirtual #235                // Method io/dekorate/deps/kubernetes/api/builder/VisitableMap.get:(Ljava/lang/Object;)Ljava/util/List;
      10: aload_0
      11: getfield      #476                // Field serviceBindingList:Lio/dekorate/deps/servicecatalog/api/model/ServiceBindingListBuilder;
      14: invokeinterface #241,  2          // InterfaceMethod java/util/List.remove:(Ljava/lang/Object;)Z
      19: pop
      20: aload_1
      21: ifnull        56
      24: aload_0
      25: new           #478                // class io/dekorate/deps/servicecatalog/api/model/ServiceBindingListBuilder
      28: dup
      29: aload_1
      30: invokespecial #488                // Method io/dekorate/deps/servicecatalog/api/model/ServiceBindingListBuilder."<init>":(Lio/dekorate/deps/servicecatalog/api/model/ServiceBindingList;)V
      33: putfield      #476                // Field serviceBindingList:Lio/dekorate/deps/servicecatalog/api/model/ServiceBindingListBuilder;
      36: aload_0
      37: getfield      #228                // Field _visitables:Lio/dekorate/deps/kubernetes/api/builder/VisitableMap;
      40: ldc_w         #485                // String serviceBindingList
      43: invokevirtual #235                // Method io/dekorate/deps/kubernetes/api/builder/VisitableMap.get:(Ljava/lang/Object;)Ljava/util/List;
      46: aload_0
      47: getfield      #476                // Field serviceBindingList:Lio/dekorate/deps/servicecatalog/api/model/ServiceBindingListBuilder;
      50: invokeinterface #247,  2          // InterfaceMethod java/util/List.add:(Ljava/lang/Object;)Z
      55: pop
      56: aload_0
      57: areturn

  public java.lang.Boolean hasServiceBindingList();
    Code:
       0: aload_0
       1: getfield      #476                // Field serviceBindingList:Lio/dekorate/deps/servicecatalog/api/model/ServiceBindingListBuilder;
       4: ifnull        11
       7: iconst_1
       8: goto          12
      11: iconst_0
      12: invokestatic  #256                // Method java/lang/Boolean.valueOf:(Z)Ljava/lang/Boolean;
      15: areturn

  public io.dekorate.deps.servicecatalog.api.model.ValidationSchemaFluent$ServiceBindingListNested<A> withNewServiceBindingList();
    Code:
       0: new           #22                 // class io/dekorate/deps/servicecatalog/api/model/ValidationSchemaFluentImpl$ServiceBindingListNestedImpl
       3: dup
       4: aload_0
       5: invokespecial #494                // Method io/dekorate/deps/servicecatalog/api/model/ValidationSchemaFluentImpl$ServiceBindingListNestedImpl."<init>":(Lio/dekorate/deps/servicecatalog/api/model/ValidationSchemaFluentImpl;)V
       8: areturn

  public io.dekorate.deps.servicecatalog.api.model.ValidationSchemaFluent$ServiceBindingListNested<A> withNewServiceBindingListLike(io.dekorate.deps.servicecatalog.api.model.ServiceBindingList);
    Code:
       0: new           #22                 // class io/dekorate/deps/servicecatalog/api/model/ValidationSchemaFluentImpl$ServiceBindingListNestedImpl
       3: dup
       4: aload_0
       5: aload_1
       6: invokespecial #500                // Method io/dekorate/deps/servicecatalog/api/model/ValidationSchemaFluentImpl$ServiceBindingListNestedImpl."<init>":(Lio/dekorate/deps/servicecatalog/api/model/ValidationSchemaFluentImpl;Lio/dekorate/deps/servicecatalog/api/model/ServiceBindingList;)V
       9: areturn

  public io.dekorate.deps.servicecatalog.api.model.ValidationSchemaFluent$ServiceBindingListNested<A> editServiceBindingList();
    Code:
       0: aload_0
       1: aload_0
       2: invokevirtual #502                // Method getServiceBindingList:()Lio/dekorate/deps/servicecatalog/api/model/ServiceBindingList;
       5: invokevirtual #504                // Method withNewServiceBindingListLike:(Lio/dekorate/deps/servicecatalog/api/model/ServiceBindingList;)Lio/dekorate/deps/servicecatalog/api/model/ValidationSchemaFluent$ServiceBindingListNested;
       8: areturn

  public io.dekorate.deps.servicecatalog.api.model.ValidationSchemaFluent$ServiceBindingListNested<A> editOrNewServiceBindingList();
    Code:
       0: aload_0
       1: aload_0
       2: invokevirtual #502                // Method getServiceBindingList:()Lio/dekorate/deps/servicecatalog/api/model/ServiceBindingList;
       5: ifnull        15
       8: aload_0
       9: invokevirtual #502                // Method getServiceBindingList:()Lio/dekorate/deps/servicecatalog/api/model/ServiceBindingList;
      12: goto          25
      15: new           #478                // class io/dekorate/deps/servicecatalog/api/model/ServiceBindingListBuilder
      18: dup
      19: invokespecial #506                // Method io/dekorate/deps/servicecatalog/api/model/ServiceBindingListBuilder."<init>":()V
      22: invokevirtual #480                // Method io/dekorate/deps/servicecatalog/api/model/ServiceBindingListBuilder.build:()Lio/dekorate/deps/servicecatalog/api/model/ServiceBindingList;
      25: invokevirtual #504                // Method withNewServiceBindingListLike:(Lio/dekorate/deps/servicecatalog/api/model/ServiceBindingList;)Lio/dekorate/deps/servicecatalog/api/model/ValidationSchemaFluent$ServiceBindingListNested;
      28: areturn

  public io.dekorate.deps.servicecatalog.api.model.ValidationSchemaFluent$ServiceBindingListNested<A> editOrNewServiceBindingListLike(io.dekorate.deps.servicecatalog.api.model.ServiceBindingList);
    Code:
       0: aload_0
       1: aload_0
       2: invokevirtual #502                // Method getServiceBindingList:()Lio/dekorate/deps/servicecatalog/api/model/ServiceBindingList;
       5: ifnull        15
       8: aload_0
       9: invokevirtual #502                // Method getServiceBindingList:()Lio/dekorate/deps/servicecatalog/api/model/ServiceBindingList;
      12: goto          16
      15: aload_1
      16: invokevirtual #504                // Method withNewServiceBindingListLike:(Lio/dekorate/deps/servicecatalog/api/model/ServiceBindingList;)Lio/dekorate/deps/servicecatalog/api/model/ValidationSchemaFluent$ServiceBindingListNested;
      19: areturn

  public io.dekorate.deps.servicecatalog.api.model.ServiceBroker getServiceBroker();
    Code:
       0: aload_0
       1: getfield      #509                // Field serviceBroker:Lio/dekorate/deps/servicecatalog/api/model/ServiceBrokerBuilder;
       4: ifnull        17
       7: aload_0
       8: getfield      #509                // Field serviceBroker:Lio/dekorate/deps/servicecatalog/api/model/ServiceBrokerBuilder;
      11: invokevirtual #513                // Method io/dekorate/deps/servicecatalog/api/model/ServiceBrokerBuilder.build:()Lio/dekorate/deps/servicecatalog/api/model/ServiceBroker;
      14: goto          18
      17: aconst_null
      18: areturn

  public io.dekorate.deps.servicecatalog.api.model.ServiceBroker buildServiceBroker();
    Code:
       0: aload_0
       1: getfield      #509                // Field serviceBroker:Lio/dekorate/deps/servicecatalog/api/model/ServiceBrokerBuilder;
       4: ifnull        17
       7: aload_0
       8: getfield      #509                // Field serviceBroker:Lio/dekorate/deps/servicecatalog/api/model/ServiceBrokerBuilder;
      11: invokevirtual #513                // Method io/dekorate/deps/servicecatalog/api/model/ServiceBrokerBuilder.build:()Lio/dekorate/deps/servicecatalog/api/model/ServiceBroker;
      14: goto          18
      17: aconst_null
      18: areturn

  public A withServiceBroker(io.dekorate.deps.servicecatalog.api.model.ServiceBroker);
    Code:
       0: aload_0
       1: getfield      #228                // Field _visitables:Lio/dekorate/deps/kubernetes/api/builder/VisitableMap;
       4: ldc_w         #518                // String serviceBroker
       7: invokevirtual #235                // Method io/dekorate/deps/kubernetes/api/builder/VisitableMap.get:(Ljava/lang/Object;)Ljava/util/List;
      10: aload_0
      11: getfield      #509                // Field serviceBroker:Lio/dekorate/deps/servicecatalog/api/model/ServiceBrokerBuilder;
      14: invokeinterface #241,  2          // InterfaceMethod java/util/List.remove:(Ljava/lang/Object;)Z
      19: pop
      20: aload_1
      21: ifnull        56
      24: aload_0
      25: new           #511                // class io/dekorate/deps/servicecatalog/api/model/ServiceBrokerBuilder
      28: dup
      29: aload_1
      30: invokespecial #521                // Method io/dekorate/deps/servicecatalog/api/model/ServiceBrokerBuilder."<init>":(Lio/dekorate/deps/servicecatalog/api/model/ServiceBroker;)V
      33: putfield      #509                // Field serviceBroker:Lio/dekorate/deps/servicecatalog/api/model/ServiceBrokerBuilder;
      36: aload_0
      37: getfield      #228                // Field _visitables:Lio/dekorate/deps/kubernetes/api/builder/VisitableMap;
      40: ldc_w         #518                // String serviceBroker
      43: invokevirtual #235                // Method io/dekorate/deps/kubernetes/api/builder/VisitableMap.get:(Ljava/lang/Object;)Ljava/util/List;
      46: aload_0
      47: getfield      #509                // Field serviceBroker:Lio/dekorate/deps/servicecatalog/api/model/ServiceBrokerBuilder;
      50: invokeinterface #247,  2          // InterfaceMethod java/util/List.add:(Ljava/lang/Object;)Z
      55: pop
      56: aload_0
      57: areturn

  public java.lang.Boolean hasServiceBroker();
    Code:
       0: aload_0
       1: getfield      #509                // Field serviceBroker:Lio/dekorate/deps/servicecatalog/api/model/ServiceBrokerBuilder;
       4: ifnull        11
       7: iconst_1
       8: goto          12
      11: iconst_0
      12: invokestatic  #256                // Method java/lang/Boolean.valueOf:(Z)Ljava/lang/Boolean;
      15: areturn

  public io.dekorate.deps.servicecatalog.api.model.ValidationSchemaFluent$ServiceBrokerNested<A> withNewServiceBroker();
    Code:
       0: new           #19                 // class io/dekorate/deps/servicecatalog/api/model/ValidationSchemaFluentImpl$ServiceBrokerNestedImpl
       3: dup
       4: aload_0
       5: invokespecial #527                // Method io/dekorate/deps/servicecatalog/api/model/ValidationSchemaFluentImpl$ServiceBrokerNestedImpl."<init>":(Lio/dekorate/deps/servicecatalog/api/model/ValidationSchemaFluentImpl;)V
       8: areturn

  public io.dekorate.deps.servicecatalog.api.model.ValidationSchemaFluent$ServiceBrokerNested<A> withNewServiceBrokerLike(io.dekorate.deps.servicecatalog.api.model.ServiceBroker);
    Code:
       0: new           #19                 // class io/dekorate/deps/servicecatalog/api/model/ValidationSchemaFluentImpl$ServiceBrokerNestedImpl
       3: dup
       4: aload_0
       5: aload_1
       6: invokespecial #533                // Method io/dekorate/deps/servicecatalog/api/model/ValidationSchemaFluentImpl$ServiceBrokerNestedImpl."<init>":(Lio/dekorate/deps/servicecatalog/api/model/ValidationSchemaFluentImpl;Lio/dekorate/deps/servicecatalog/api/model/ServiceBroker;)V
       9: areturn

  public io.dekorate.deps.servicecatalog.api.model.ValidationSchemaFluent$ServiceBrokerNested<A> editServiceBroker();
    Code:
       0: aload_0
       1: aload_0
       2: invokevirtual #535                // Method getServiceBroker:()Lio/dekorate/deps/servicecatalog/api/model/ServiceBroker;
       5: invokevirtual #537                // Method withNewServiceBrokerLike:(Lio/dekorate/deps/servicecatalog/api/model/ServiceBroker;)Lio/dekorate/deps/servicecatalog/api/model/ValidationSchemaFluent$ServiceBrokerNested;
       8: areturn

  public io.dekorate.deps.servicecatalog.api.model.ValidationSchemaFluent$ServiceBrokerNested<A> editOrNewServiceBroker();
    Code:
       0: aload_0
       1: aload_0
       2: invokevirtual #535                // Method getServiceBroker:()Lio/dekorate/deps/servicecatalog/api/model/ServiceBroker;
       5: ifnull        15
       8: aload_0
       9: invokevirtual #535                // Method getServiceBroker:()Lio/dekorate/deps/servicecatalog/api/model/ServiceBroker;
      12: goto          25
      15: new           #511                // class io/dekorate/deps/servicecatalog/api/model/ServiceBrokerBuilder
      18: dup
      19: invokespecial #539                // Method io/dekorate/deps/servicecatalog/api/model/ServiceBrokerBuilder."<init>":()V
      22: invokevirtual #513                // Method io/dekorate/deps/servicecatalog/api/model/ServiceBrokerBuilder.build:()Lio/dekorate/deps/servicecatalog/api/model/ServiceBroker;
      25: invokevirtual #537                // Method withNewServiceBrokerLike:(Lio/dekorate/deps/servicecatalog/api/model/ServiceBroker;)Lio/dekorate/deps/servicecatalog/api/model/ValidationSchemaFluent$ServiceBrokerNested;
      28: areturn

  public io.dekorate.deps.servicecatalog.api.model.ValidationSchemaFluent$ServiceBrokerNested<A> editOrNewServiceBrokerLike(io.dekorate.deps.servicecatalog.api.model.ServiceBroker);
    Code:
       0: aload_0
       1: aload_0
       2: invokevirtual #535                // Method getServiceBroker:()Lio/dekorate/deps/servicecatalog/api/model/ServiceBroker;
       5: ifnull        15
       8: aload_0
       9: invokevirtual #535                // Method getServiceBroker:()Lio/dekorate/deps/servicecatalog/api/model/ServiceBroker;
      12: goto          16
      15: aload_1
      16: invokevirtual #537                // Method withNewServiceBrokerLike:(Lio/dekorate/deps/servicecatalog/api/model/ServiceBroker;)Lio/dekorate/deps/servicecatalog/api/model/ValidationSchemaFluent$ServiceBrokerNested;
      19: areturn

  public io.dekorate.deps.servicecatalog.api.model.ServiceBrokerList getServiceBrokerList();
    Code:
       0: aload_0
       1: getfield      #542                // Field serviceBrokerList:Lio/dekorate/deps/servicecatalog/api/model/ServiceBrokerListBuilder;
       4: ifnull        17
       7: aload_0
       8: getfield      #542                // Field serviceBrokerList:Lio/dekorate/deps/servicecatalog/api/model/ServiceBrokerListBuilder;
      11: invokevirtual #546                // Method io/dekorate/deps/servicecatalog/api/model/ServiceBrokerListBuilder.build:()Lio/dekorate/deps/servicecatalog/api/model/ServiceBrokerList;
      14: goto          18
      17: aconst_null
      18: areturn

  public io.dekorate.deps.servicecatalog.api.model.ServiceBrokerList buildServiceBrokerList();
    Code:
       0: aload_0
       1: getfield      #542                // Field serviceBrokerList:Lio/dekorate/deps/servicecatalog/api/model/ServiceBrokerListBuilder;
       4: ifnull        17
       7: aload_0
       8: getfield      #542                // Field serviceBrokerList:Lio/dekorate/deps/servicecatalog/api/model/ServiceBrokerListBuilder;
      11: invokevirtual #546                // Method io/dekorate/deps/servicecatalog/api/model/ServiceBrokerListBuilder.build:()Lio/dekorate/deps/servicecatalog/api/model/ServiceBrokerList;
      14: goto          18
      17: aconst_null
      18: areturn

  public A withServiceBrokerList(io.dekorate.deps.servicecatalog.api.model.ServiceBrokerList);
    Code:
       0: aload_0
       1: getfield      #228                // Field _visitables:Lio/dekorate/deps/kubernetes/api/builder/VisitableMap;
       4: ldc_w         #551                // String serviceBrokerList
       7: invokevirtual #235                // Method io/dekorate/deps/kubernetes/api/builder/VisitableMap.get:(Ljava/lang/Object;)Ljava/util/List;
      10: aload_0
      11: getfield      #542                // Field serviceBrokerList:Lio/dekorate/deps/servicecatalog/api/model/ServiceBrokerListBuilder;
      14: invokeinterface #241,  2          // InterfaceMethod java/util/List.remove:(Ljava/lang/Object;)Z
      19: pop
      20: aload_1
      21: ifnull        56
      24: aload_0
      25: new           #544                // class io/dekorate/deps/servicecatalog/api/model/ServiceBrokerListBuilder
      28: dup
      29: aload_1
      30: invokespecial #554                // Method io/dekorate/deps/servicecatalog/api/model/ServiceBrokerListBuilder."<init>":(Lio/dekorate/deps/servicecatalog/api/model/ServiceBrokerList;)V
      33: putfield      #542                // Field serviceBrokerList:Lio/dekorate/deps/servicecatalog/api/model/ServiceBrokerListBuilder;
      36: aload_0
      37: getfield      #228                // Field _visitables:Lio/dekorate/deps/kubernetes/api/builder/VisitableMap;
      40: ldc_w         #551                // String serviceBrokerList
      43: invokevirtual #235                // Method io/dekorate/deps/kubernetes/api/builder/VisitableMap.get:(Ljava/lang/Object;)Ljava/util/List;
      46: aload_0
      47: getfield      #542                // Field serviceBrokerList:Lio/dekorate/deps/servicecatalog/api/model/ServiceBrokerListBuilder;
      50: invokeinterface #247,  2          // InterfaceMethod java/util/List.add:(Ljava/lang/Object;)Z
      55: pop
      56: aload_0
      57: areturn

  public java.lang.Boolean hasServiceBrokerList();
    Code:
       0: aload_0
       1: getfield      #542                // Field serviceBrokerList:Lio/dekorate/deps/servicecatalog/api/model/ServiceBrokerListBuilder;
       4: ifnull        11
       7: iconst_1
       8: goto          12
      11: iconst_0
      12: invokestatic  #256                // Method java/lang/Boolean.valueOf:(Z)Ljava/lang/Boolean;
      15: areturn

  public io.dekorate.deps.servicecatalog.api.model.ValidationSchemaFluent$ServiceBrokerListNested<A> withNewServiceBrokerList();
    Code:
       0: new           #16                 // class io/dekorate/deps/servicecatalog/api/model/ValidationSchemaFluentImpl$ServiceBrokerListNestedImpl
       3: dup
       4: aload_0
       5: invokespecial #560                // Method io/dekorate/deps/servicecatalog/api/model/ValidationSchemaFluentImpl$ServiceBrokerListNestedImpl."<init>":(Lio/dekorate/deps/servicecatalog/api/model/ValidationSchemaFluentImpl;)V
       8: areturn

  public io.dekorate.deps.servicecatalog.api.model.ValidationSchemaFluent$ServiceBrokerListNested<A> withNewServiceBrokerListLike(io.dekorate.deps.servicecatalog.api.model.ServiceBrokerList);
    Code:
       0: new           #16                 // class io/dekorate/deps/servicecatalog/api/model/ValidationSchemaFluentImpl$ServiceBrokerListNestedImpl
       3: dup
       4: aload_0
       5: aload_1
       6: invokespecial #566                // Method io/dekorate/deps/servicecatalog/api/model/ValidationSchemaFluentImpl$ServiceBrokerListNestedImpl."<init>":(Lio/dekorate/deps/servicecatalog/api/model/ValidationSchemaFluentImpl;Lio/dekorate/deps/servicecatalog/api/model/ServiceBrokerList;)V
       9: areturn

  public io.dekorate.deps.servicecatalog.api.model.ValidationSchemaFluent$ServiceBrokerListNested<A> editServiceBrokerList();
    Code:
       0: aload_0
       1: aload_0
       2: invokevirtual #568                // Method getServiceBrokerList:()Lio/dekorate/deps/servicecatalog/api/model/ServiceBrokerList;
       5: invokevirtual #570                // Method withNewServiceBrokerListLike:(Lio/dekorate/deps/servicecatalog/api/model/ServiceBrokerList;)Lio/dekorate/deps/servicecatalog/api/model/ValidationSchemaFluent$ServiceBrokerListNested;
       8: areturn

  public io.dekorate.deps.servicecatalog.api.model.ValidationSchemaFluent$ServiceBrokerListNested<A> editOrNewServiceBrokerList();
    Code:
       0: aload_0
       1: aload_0
       2: invokevirtual #568                // Method getServiceBrokerList:()Lio/dekorate/deps/servicecatalog/api/model/ServiceBrokerList;
       5: ifnull        15
       8: aload_0
       9: invokevirtual #568                // Method getServiceBrokerList:()Lio/dekorate/deps/servicecatalog/api/model/ServiceBrokerList;
      12: goto          25
      15: new           #544                // class io/dekorate/deps/servicecatalog/api/model/ServiceBrokerListBuilder
      18: dup
      19: invokespecial #572                // Method io/dekorate/deps/servicecatalog/api/model/ServiceBrokerListBuilder."<init>":()V
      22: invokevirtual #546                // Method io/dekorate/deps/servicecatalog/api/model/ServiceBrokerListBuilder.build:()Lio/dekorate/deps/servicecatalog/api/model/ServiceBrokerList;
      25: invokevirtual #570                // Method withNewServiceBrokerListLike:(Lio/dekorate/deps/servicecatalog/api/model/ServiceBrokerList;)Lio/dekorate/deps/servicecatalog/api/model/ValidationSchemaFluent$ServiceBrokerListNested;
      28: areturn

  public io.dekorate.deps.servicecatalog.api.model.ValidationSchemaFluent$ServiceBrokerListNested<A> editOrNewServiceBrokerListLike(io.dekorate.deps.servicecatalog.api.model.ServiceBrokerList);
    Code:
       0: aload_0
       1: aload_0
       2: invokevirtual #568                // Method getServiceBrokerList:()Lio/dekorate/deps/servicecatalog/api/model/ServiceBrokerList;
       5: ifnull        15
       8: aload_0
       9: invokevirtual #568                // Method getServiceBrokerList:()Lio/dekorate/deps/servicecatalog/api/model/ServiceBrokerList;
      12: goto          16
      15: aload_1
      16: invokevirtual #570                // Method withNewServiceBrokerListLike:(Lio/dekorate/deps/servicecatalog/api/model/ServiceBrokerList;)Lio/dekorate/deps/servicecatalog/api/model/ValidationSchemaFluent$ServiceBrokerListNested;
      19: areturn

  public io.dekorate.deps.servicecatalog.api.model.ServiceInstance getServiceInstance();
    Code:
       0: aload_0
       1: getfield      #575                // Field serviceInstance:Lio/dekorate/deps/servicecatalog/api/model/ServiceInstanceBuilder;
       4: ifnull        17
       7: aload_0
       8: getfield      #575                // Field serviceInstance:Lio/dekorate/deps/servicecatalog/api/model/ServiceInstanceBuilder;
      11: invokevirtual #579                // Method io/dekorate/deps/servicecatalog/api/model/ServiceInstanceBuilder.build:()Lio/dekorate/deps/servicecatalog/api/model/ServiceInstance;
      14: goto          18
      17: aconst_null
      18: areturn

  public io.dekorate.deps.servicecatalog.api.model.ServiceInstance buildServiceInstance();
    Code:
       0: aload_0
       1: getfield      #575                // Field serviceInstance:Lio/dekorate/deps/servicecatalog/api/model/ServiceInstanceBuilder;
       4: ifnull        17
       7: aload_0
       8: getfield      #575                // Field serviceInstance:Lio/dekorate/deps/servicecatalog/api/model/ServiceInstanceBuilder;
      11: invokevirtual #579                // Method io/dekorate/deps/servicecatalog/api/model/ServiceInstanceBuilder.build:()Lio/dekorate/deps/servicecatalog/api/model/ServiceInstance;
      14: goto          18
      17: aconst_null
      18: areturn

  public A withServiceInstance(io.dekorate.deps.servicecatalog.api.model.ServiceInstance);
    Code:
       0: aload_0
       1: getfield      #228                // Field _visitables:Lio/dekorate/deps/kubernetes/api/builder/VisitableMap;
       4: ldc_w         #584                // String serviceInstance
       7: invokevirtual #235                // Method io/dekorate/deps/kubernetes/api/builder/VisitableMap.get:(Ljava/lang/Object;)Ljava/util/List;
      10: aload_0
      11: getfield      #575                // Field serviceInstance:Lio/dekorate/deps/servicecatalog/api/model/ServiceInstanceBuilder;
      14: invokeinterface #241,  2          // InterfaceMethod java/util/List.remove:(Ljava/lang/Object;)Z
      19: pop
      20: aload_1
      21: ifnull        56
      24: aload_0
      25: new           #577                // class io/dekorate/deps/servicecatalog/api/model/ServiceInstanceBuilder
      28: dup
      29: aload_1
      30: invokespecial #587                // Method io/dekorate/deps/servicecatalog/api/model/ServiceInstanceBuilder."<init>":(Lio/dekorate/deps/servicecatalog/api/model/ServiceInstance;)V
      33: putfield      #575                // Field serviceInstance:Lio/dekorate/deps/servicecatalog/api/model/ServiceInstanceBuilder;
      36: aload_0
      37: getfield      #228                // Field _visitables:Lio/dekorate/deps/kubernetes/api/builder/VisitableMap;
      40: ldc_w         #584                // String serviceInstance
      43: invokevirtual #235                // Method io/dekorate/deps/kubernetes/api/builder/VisitableMap.get:(Ljava/lang/Object;)Ljava/util/List;
      46: aload_0
      47: getfield      #575                // Field serviceInstance:Lio/dekorate/deps/servicecatalog/api/model/ServiceInstanceBuilder;
      50: invokeinterface #247,  2          // InterfaceMethod java/util/List.add:(Ljava/lang/Object;)Z
      55: pop
      56: aload_0
      57: areturn

  public java.lang.Boolean hasServiceInstance();
    Code:
       0: aload_0
       1: getfield      #575                // Field serviceInstance:Lio/dekorate/deps/servicecatalog/api/model/ServiceInstanceBuilder;
       4: ifnull        11
       7: iconst_1
       8: goto          12
      11: iconst_0
      12: invokestatic  #256                // Method java/lang/Boolean.valueOf:(Z)Ljava/lang/Boolean;
      15: areturn

  public io.dekorate.deps.servicecatalog.api.model.ValidationSchemaFluent$ServiceInstanceNested<A> withNewServiceInstance();
    Code:
       0: new           #13                 // class io/dekorate/deps/servicecatalog/api/model/ValidationSchemaFluentImpl$ServiceInstanceNestedImpl
       3: dup
       4: aload_0
       5: invokespecial #593                // Method io/dekorate/deps/servicecatalog/api/model/ValidationSchemaFluentImpl$ServiceInstanceNestedImpl."<init>":(Lio/dekorate/deps/servicecatalog/api/model/ValidationSchemaFluentImpl;)V
       8: areturn

  public io.dekorate.deps.servicecatalog.api.model.ValidationSchemaFluent$ServiceInstanceNested<A> withNewServiceInstanceLike(io.dekorate.deps.servicecatalog.api.model.ServiceInstance);
    Code:
       0: new           #13                 // class io/dekorate/deps/servicecatalog/api/model/ValidationSchemaFluentImpl$ServiceInstanceNestedImpl
       3: dup
       4: aload_0
       5: aload_1
       6: invokespecial #599                // Method io/dekorate/deps/servicecatalog/api/model/ValidationSchemaFluentImpl$ServiceInstanceNestedImpl."<init>":(Lio/dekorate/deps/servicecatalog/api/model/ValidationSchemaFluentImpl;Lio/dekorate/deps/servicecatalog/api/model/ServiceInstance;)V
       9: areturn

  public io.dekorate.deps.servicecatalog.api.model.ValidationSchemaFluent$ServiceInstanceNested<A> editServiceInstance();
    Code:
       0: aload_0
       1: aload_0
       2: invokevirtual #601                // Method getServiceInstance:()Lio/dekorate/deps/servicecatalog/api/model/ServiceInstance;
       5: invokevirtual #603                // Method withNewServiceInstanceLike:(Lio/dekorate/deps/servicecatalog/api/model/ServiceInstance;)Lio/dekorate/deps/servicecatalog/api/model/ValidationSchemaFluent$ServiceInstanceNested;
       8: areturn

  public io.dekorate.deps.servicecatalog.api.model.ValidationSchemaFluent$ServiceInstanceNested<A> editOrNewServiceInstance();
    Code:
       0: aload_0
       1: aload_0
       2: invokevirtual #601                // Method getServiceInstance:()Lio/dekorate/deps/servicecatalog/api/model/ServiceInstance;
       5: ifnull        15
       8: aload_0
       9: invokevirtual #601                // Method getServiceInstance:()Lio/dekorate/deps/servicecatalog/api/model/ServiceInstance;
      12: goto          25
      15: new           #577                // class io/dekorate/deps/servicecatalog/api/model/ServiceInstanceBuilder
      18: dup
      19: invokespecial #605                // Method io/dekorate/deps/servicecatalog/api/model/ServiceInstanceBuilder."<init>":()V
      22: invokevirtual #579                // Method io/dekorate/deps/servicecatalog/api/model/ServiceInstanceBuilder.build:()Lio/dekorate/deps/servicecatalog/api/model/ServiceInstance;
      25: invokevirtual #603                // Method withNewServiceInstanceLike:(Lio/dekorate/deps/servicecatalog/api/model/ServiceInstance;)Lio/dekorate/deps/servicecatalog/api/model/ValidationSchemaFluent$ServiceInstanceNested;
      28: areturn

  public io.dekorate.deps.servicecatalog.api.model.ValidationSchemaFluent$ServiceInstanceNested<A> editOrNewServiceInstanceLike(io.dekorate.deps.servicecatalog.api.model.ServiceInstance);
    Code:
       0: aload_0
       1: aload_0
       2: invokevirtual #601                // Method getServiceInstance:()Lio/dekorate/deps/servicecatalog/api/model/ServiceInstance;
       5: ifnull        15
       8: aload_0
       9: invokevirtual #601                // Method getServiceInstance:()Lio/dekorate/deps/servicecatalog/api/model/ServiceInstance;
      12: goto          16
      15: aload_1
      16: invokevirtual #603                // Method withNewServiceInstanceLike:(Lio/dekorate/deps/servicecatalog/api/model/ServiceInstance;)Lio/dekorate/deps/servicecatalog/api/model/ValidationSchemaFluent$ServiceInstanceNested;
      19: areturn

  public io.dekorate.deps.servicecatalog.api.model.ServiceInstanceList getServiceInstanceList();
    Code:
       0: aload_0
       1: getfield      #608                // Field serviceInstanceList:Lio/dekorate/deps/servicecatalog/api/model/ServiceInstanceListBuilder;
       4: ifnull        17
       7: aload_0
       8: getfield      #608                // Field serviceInstanceList:Lio/dekorate/deps/servicecatalog/api/model/ServiceInstanceListBuilder;
      11: invokevirtual #612                // Method io/dekorate/deps/servicecatalog/api/model/ServiceInstanceListBuilder.build:()Lio/dekorate/deps/servicecatalog/api/model/ServiceInstanceList;
      14: goto          18
      17: aconst_null
      18: areturn

  public io.dekorate.deps.servicecatalog.api.model.ServiceInstanceList buildServiceInstanceList();
    Code:
       0: aload_0
       1: getfield      #608                // Field serviceInstanceList:Lio/dekorate/deps/servicecatalog/api/model/ServiceInstanceListBuilder;
       4: ifnull        17
       7: aload_0
       8: getfield      #608                // Field serviceInstanceList:Lio/dekorate/deps/servicecatalog/api/model/ServiceInstanceListBuilder;
      11: invokevirtual #612                // Method io/dekorate/deps/servicecatalog/api/model/ServiceInstanceListBuilder.build:()Lio/dekorate/deps/servicecatalog/api/model/ServiceInstanceList;
      14: goto          18
      17: aconst_null
      18: areturn

  public A withServiceInstanceList(io.dekorate.deps.servicecatalog.api.model.ServiceInstanceList);
    Code:
       0: aload_0
       1: getfield      #228                // Field _visitables:Lio/dekorate/deps/kubernetes/api/builder/VisitableMap;
       4: ldc_w         #617                // String serviceInstanceList
       7: invokevirtual #235                // Method io/dekorate/deps/kubernetes/api/builder/VisitableMap.get:(Ljava/lang/Object;)Ljava/util/List;
      10: aload_0
      11: getfield      #608                // Field serviceInstanceList:Lio/dekorate/deps/servicecatalog/api/model/ServiceInstanceListBuilder;
      14: invokeinterface #241,  2          // InterfaceMethod java/util/List.remove:(Ljava/lang/Object;)Z
      19: pop
      20: aload_1
      21: ifnull        56
      24: aload_0
      25: new           #610                // class io/dekorate/deps/servicecatalog/api/model/ServiceInstanceListBuilder
      28: dup
      29: aload_1
      30: invokespecial #620                // Method io/dekorate/deps/servicecatalog/api/model/ServiceInstanceListBuilder."<init>":(Lio/dekorate/deps/servicecatalog/api/model/ServiceInstanceList;)V
      33: putfield      #608                // Field serviceInstanceList:Lio/dekorate/deps/servicecatalog/api/model/ServiceInstanceListBuilder;
      36: aload_0
      37: getfield      #228                // Field _visitables:Lio/dekorate/deps/kubernetes/api/builder/VisitableMap;
      40: ldc_w         #617                // String serviceInstanceList
      43: invokevirtual #235                // Method io/dekorate/deps/kubernetes/api/builder/VisitableMap.get:(Ljava/lang/Object;)Ljava/util/List;
      46: aload_0
      47: getfield      #608                // Field serviceInstanceList:Lio/dekorate/deps/servicecatalog/api/model/ServiceInstanceListBuilder;
      50: invokeinterface #247,  2          // InterfaceMethod java/util/List.add:(Ljava/lang/Object;)Z
      55: pop
      56: aload_0
      57: areturn

  public java.lang.Boolean hasServiceInstanceList();
    Code:
       0: aload_0
       1: getfield      #608                // Field serviceInstanceList:Lio/dekorate/deps/servicecatalog/api/model/ServiceInstanceListBuilder;
       4: ifnull        11
       7: iconst_1
       8: goto          12
      11: iconst_0
      12: invokestatic  #256                // Method java/lang/Boolean.valueOf:(Z)Ljava/lang/Boolean;
      15: areturn

  public io.dekorate.deps.servicecatalog.api.model.ValidationSchemaFluent$ServiceInstanceListNested<A> withNewServiceInstanceList();
    Code:
       0: new           #10                 // class io/dekorate/deps/servicecatalog/api/model/ValidationSchemaFluentImpl$ServiceInstanceListNestedImpl
       3: dup
       4: aload_0
       5: invokespecial #626                // Method io/dekorate/deps/servicecatalog/api/model/ValidationSchemaFluentImpl$ServiceInstanceListNestedImpl."<init>":(Lio/dekorate/deps/servicecatalog/api/model/ValidationSchemaFluentImpl;)V
       8: areturn

  public io.dekorate.deps.servicecatalog.api.model.ValidationSchemaFluent$ServiceInstanceListNested<A> withNewServiceInstanceListLike(io.dekorate.deps.servicecatalog.api.model.ServiceInstanceList);
    Code:
       0: new           #10                 // class io/dekorate/deps/servicecatalog/api/model/ValidationSchemaFluentImpl$ServiceInstanceListNestedImpl
       3: dup
       4: aload_0
       5: aload_1
       6: invokespecial #632                // Method io/dekorate/deps/servicecatalog/api/model/ValidationSchemaFluentImpl$ServiceInstanceListNestedImpl."<init>":(Lio/dekorate/deps/servicecatalog/api/model/ValidationSchemaFluentImpl;Lio/dekorate/deps/servicecatalog/api/model/ServiceInstanceList;)V
       9: areturn

  public io.dekorate.deps.servicecatalog.api.model.ValidationSchemaFluent$ServiceInstanceListNested<A> editServiceInstanceList();
    Code:
       0: aload_0
       1: aload_0
       2: invokevirtual #634                // Method getServiceInstanceList:()Lio/dekorate/deps/servicecatalog/api/model/ServiceInstanceList;
       5: invokevirtual #636                // Method withNewServiceInstanceListLike:(Lio/dekorate/deps/servicecatalog/api/model/ServiceInstanceList;)Lio/dekorate/deps/servicecatalog/api/model/ValidationSchemaFluent$ServiceInstanceListNested;
       8: areturn

  public io.dekorate.deps.servicecatalog.api.model.ValidationSchemaFluent$ServiceInstanceListNested<A> editOrNewServiceInstanceList();
    Code:
       0: aload_0
       1: aload_0
       2: invokevirtual #634                // Method getServiceInstanceList:()Lio/dekorate/deps/servicecatalog/api/model/ServiceInstanceList;
       5: ifnull        15
       8: aload_0
       9: invokevirtual #634                // Method getServiceInstanceList:()Lio/dekorate/deps/servicecatalog/api/model/ServiceInstanceList;
      12: goto          25
      15: new           #610                // class io/dekorate/deps/servicecatalog/api/model/ServiceInstanceListBuilder
      18: dup
      19: invokespecial #638                // Method io/dekorate/deps/servicecatalog/api/model/ServiceInstanceListBuilder."<init>":()V
      22: invokevirtual #612                // Method io/dekorate/deps/servicecatalog/api/model/ServiceInstanceListBuilder.build:()Lio/dekorate/deps/servicecatalog/api/model/ServiceInstanceList;
      25: invokevirtual #636                // Method withNewServiceInstanceListLike:(Lio/dekorate/deps/servicecatalog/api/model/ServiceInstanceList;)Lio/dekorate/deps/servicecatalog/api/model/ValidationSchemaFluent$ServiceInstanceListNested;
      28: areturn

  public io.dekorate.deps.servicecatalog.api.model.ValidationSchemaFluent$ServiceInstanceListNested<A> editOrNewServiceInstanceListLike(io.dekorate.deps.servicecatalog.api.model.ServiceInstanceList);
    Code:
       0: aload_0
       1: aload_0
       2: invokevirtual #634                // Method getServiceInstanceList:()Lio/dekorate/deps/servicecatalog/api/model/ServiceInstanceList;
       5: ifnull        15
       8: aload_0
       9: invokevirtual #634                // Method getServiceInstanceList:()Lio/dekorate/deps/servicecatalog/api/model/ServiceInstanceList;
      12: goto          16
      15: aload_1
      16: invokevirtual #636                // Method withNewServiceInstanceListLike:(Lio/dekorate/deps/servicecatalog/api/model/ServiceInstanceList;)Lio/dekorate/deps/servicecatalog/api/model/ValidationSchemaFluent$ServiceInstanceListNested;
      19: areturn

  public boolean equals(java.lang.Object);
    Code:
       0: aload_0
       1: aload_1
       2: if_acmpne     7
       5: iconst_1
       6: ireturn
       7: aload_1
       8: ifnull        22
      11: aload_0
      12: invokevirtual #646                // Method java/lang/Object.getClass:()Ljava/lang/Class;
      15: aload_1
      16: invokevirtual #646                // Method java/lang/Object.getClass:()Ljava/lang/Class;
      19: if_acmpeq     24
      22: iconst_0
      23: ireturn
      24: aload_1
      25: checkcast     #2                  // class io/dekorate/deps/servicecatalog/api/model/ValidationSchemaFluentImpl
      28: astore_2
      29: aload_0
      30: getfield      #215                // Field clusterServiceBroker:Lio/dekorate/deps/servicecatalog/api/model/ClusterServiceBrokerBuilder;
      33: ifnull        53
      36: aload_0
      37: getfield      #215                // Field clusterServiceBroker:Lio/dekorate/deps/servicecatalog/api/model/ClusterServiceBrokerBuilder;
      40: aload_2
      41: getfield      #215                // Field clusterServiceBroker:Lio/dekorate/deps/servicecatalog/api/model/ClusterServiceBrokerBuilder;
      44: invokevirtual #648                // Method io/dekorate/deps/servicecatalog/api/model/ClusterServiceBrokerBuilder.equals:(Ljava/lang/Object;)Z
      47: ifne          62
      50: goto          60
      53: aload_2
      54: getfield      #215                // Field clusterServiceBroker:Lio/dekorate/deps/servicecatalog/api/model/ClusterServiceBrokerBuilder;
      57: ifnull        62
      60: iconst_0
      61: ireturn
      62: aload_0
      63: getfield      #278                // Field clusterServiceBrokerList:Lio/dekorate/deps/servicecatalog/api/model/ClusterServiceBrokerListBuilder;
      66: ifnull        86
      69: aload_0
      70: getfield      #278                // Field clusterServiceBrokerList:Lio/dekorate/deps/servicecatalog/api/model/ClusterServiceBrokerListBuilder;
      73: aload_2
      74: getfield      #278                // Field clusterServiceBrokerList:Lio/dekorate/deps/servicecatalog/api/model/ClusterServiceBrokerListBuilder;
      77: invokevirtual #649                // Method io/dekorate/deps/servicecatalog/api/model/ClusterServiceBrokerListBuilder.equals:(Ljava/lang/Object;)Z
      80: ifne          95
      83: goto          93
      86: aload_2
      87: getfield      #278                // Field clusterServiceBrokerList:Lio/dekorate/deps/servicecatalog/api/model/ClusterServiceBrokerListBuilder;
      90: ifnull        95
      93: iconst_0
      94: ireturn
      95: aload_0
      96: getfield      #311                // Field clusterServiceClass:Lio/dekorate/deps/servicecatalog/api/model/ClusterServiceClassBuilder;
      99: ifnull        119
     102: aload_0
     103: getfield      #311                // Field clusterServiceClass:Lio/dekorate/deps/servicecatalog/api/model/ClusterServiceClassBuilder;
     106: aload_2
     107: getfield      #311                // Field clusterServiceClass:Lio/dekorate/deps/servicecatalog/api/model/ClusterServiceClassBuilder;
     110: invokevirtual #650                // Method io/dekorate/deps/servicecatalog/api/model/ClusterServiceClassBuilder.equals:(Ljava/lang/Object;)Z
     113: ifne          128
     116: goto          126
     119: aload_2
     120: getfield      #311                // Field clusterServiceClass:Lio/dekorate/deps/servicecatalog/api/model/ClusterServiceClassBuilder;
     123: ifnull        128
     126: iconst_0
     127: ireturn
     128: aload_0
     129: getfield      #344                // Field clusterServiceClassList:Lio/dekorate/deps/servicecatalog/api/model/ClusterServiceClassListBuilder;
     132: ifnull        152
     135: aload_0
     136: getfield      #344                // Field clusterServiceClassList:Lio/dekorate/deps/servicecatalog/api/model/ClusterServiceClassListBuilder;
     139: aload_2
     140: getfield      #344                // Field clusterServiceClassList:Lio/dekorate/deps/servicecatalog/api/model/ClusterServiceClassListBuilder;
     143: invokevirtual #651                // Method io/dekorate/deps/servicecatalog/api/model/ClusterServiceClassListBuilder.equals:(Ljava/lang/Object;)Z
     146: ifne          161
     149: goto          159
     152: aload_2
     153: getfield      #344                // Field clusterServiceClassList:Lio/dekorate/deps/servicecatalog/api/model/ClusterServiceClassListBuilder;
     156: ifnull        161
     159: iconst_0
     160: ireturn
     161: aload_0
     162: getfield      #377                // Field clusterServicePlan:Lio/dekorate/deps/servicecatalog/api/model/ClusterServicePlanBuilder;
     165: ifnull        185
     168: aload_0
     169: getfield      #377                // Field clusterServicePlan:Lio/dekorate/deps/servicecatalog/api/model/ClusterServicePlanBuilder;
     172: aload_2
     173: getfield      #377                // Field clusterServicePlan:Lio/dekorate/deps/servicecatalog/api/model/ClusterServicePlanBuilder;
     176: invokevirtual #652                // Method io/dekorate/deps/servicecatalog/api/model/ClusterServicePlanBuilder.equals:(Ljava/lang/Object;)Z
     179: ifne          194
     182: goto          192
     185: aload_2
     186: getfield      #377                // Field clusterServicePlan:Lio/dekorate/deps/servicecatalog/api/model/ClusterServicePlanBuilder;
     189: ifnull        194
     192: iconst_0
     193: ireturn
     194: aload_0
     195: getfield      #410                // Field clusterServicePlanList:Lio/dekorate/deps/servicecatalog/api/model/ClusterServicePlanListBuilder;
     198: ifnull        218
     201: aload_0
     202: getfield      #410                // Field clusterServicePlanList:Lio/dekorate/deps/servicecatalog/api/model/ClusterServicePlanListBuilder;
     205: aload_2
     206: getfield      #410                // Field clusterServicePlanList:Lio/dekorate/deps/servicecatalog/api/model/ClusterServicePlanListBuilder;
     209: invokevirtual #653                // Method io/dekorate/deps/servicecatalog/api/model/ClusterServicePlanListBuilder.equals:(Ljava/lang/Object;)Z
     212: ifne          227
     215: goto          225
     218: aload_2
     219: getfield      #410                // Field clusterServicePlanList:Lio/dekorate/deps/servicecatalog/api/model/ClusterServicePlanListBuilder;
     222: ifnull        227
     225: iconst_0
     226: ireturn
     227: aload_0
     228: getfield      #443                // Field serviceBinding:Lio/dekorate/deps/servicecatalog/api/model/ServiceBindingBuilder;
     231: ifnull        251
     234: aload_0
     235: getfield      #443                // Field serviceBinding:Lio/dekorate/deps/servicecatalog/api/model/ServiceBindingBuilder;
     238: aload_2
     239: getfield      #443                // Field serviceBinding:Lio/dekorate/deps/servicecatalog/api/model/ServiceBindingBuilder;
     242: invokevirtual #654                // Method io/dekorate/deps/servicecatalog/api/model/ServiceBindingBuilder.equals:(Ljava/lang/Object;)Z
     245: ifne          260
     248: goto          258
     251: aload_2
     252: getfield      #443                // Field serviceBinding:Lio/dekorate/deps/servicecatalog/api/model/ServiceBindingBuilder;
     255: ifnull        260
     258: iconst_0
     259: ireturn
     260: aload_0
     261: getfield      #476                // Field serviceBindingList:Lio/dekorate/deps/servicecatalog/api/model/ServiceBindingListBuilder;
     264: ifnull        284
     267: aload_0
     268: getfield      #476                // Field serviceBindingList:Lio/dekorate/deps/servicecatalog/api/model/ServiceBindingListBuilder;
     271: aload_2
     272: getfield      #476                // Field serviceBindingList:Lio/dekorate/deps/servicecatalog/api/model/ServiceBindingListBuilder;
     275: invokevirtual #655                // Method io/dekorate/deps/servicecatalog/api/model/ServiceBindingListBuilder.equals:(Ljava/lang/Object;)Z
     278: ifne          293
     281: goto          291
     284: aload_2
     285: getfield      #476                // Field serviceBindingList:Lio/dekorate/deps/servicecatalog/api/model/ServiceBindingListBuilder;
     288: ifnull        293
     291: iconst_0
     292: ireturn
     293: aload_0
     294: getfield      #509                // Field serviceBroker:Lio/dekorate/deps/servicecatalog/api/model/ServiceBrokerBuilder;
     297: ifnull        317
     300: aload_0
     301: getfield      #509                // Field serviceBroker:Lio/dekorate/deps/servicecatalog/api/model/ServiceBrokerBuilder;
     304: aload_2
     305: getfield      #509                // Field serviceBroker:Lio/dekorate/deps/servicecatalog/api/model/ServiceBrokerBuilder;
     308: invokevirtual #656                // Method io/dekorate/deps/servicecatalog/api/model/ServiceBrokerBuilder.equals:(Ljava/lang/Object;)Z
     311: ifne          326
     314: goto          324
     317: aload_2
     318: getfield      #509                // Field serviceBroker:Lio/dekorate/deps/servicecatalog/api/model/ServiceBrokerBuilder;
     321: ifnull        326
     324: iconst_0
     325: ireturn
     326: aload_0
     327: getfield      #542                // Field serviceBrokerList:Lio/dekorate/deps/servicecatalog/api/model/ServiceBrokerListBuilder;
     330: ifnull        350
     333: aload_0
     334: getfield      #542                // Field serviceBrokerList:Lio/dekorate/deps/servicecatalog/api/model/ServiceBrokerListBuilder;
     337: aload_2
     338: getfield      #542                // Field serviceBrokerList:Lio/dekorate/deps/servicecatalog/api/model/ServiceBrokerListBuilder;
     341: invokevirtual #657                // Method io/dekorate/deps/servicecatalog/api/model/ServiceBrokerListBuilder.equals:(Ljava/lang/Object;)Z
     344: ifne          359
     347: goto          357
     350: aload_2
     351: getfield      #542                // Field serviceBrokerList:Lio/dekorate/deps/servicecatalog/api/model/ServiceBrokerListBuilder;
     354: ifnull        359
     357: iconst_0
     358: ireturn
     359: aload_0
     360: getfield      #575                // Field serviceInstance:Lio/dekorate/deps/servicecatalog/api/model/ServiceInstanceBuilder;
     363: ifnull        383
     366: aload_0
     367: getfield      #575                // Field serviceInstance:Lio/dekorate/deps/servicecatalog/api/model/ServiceInstanceBuilder;
     370: aload_2
     371: getfield      #575                // Field serviceInstance:Lio/dekorate/deps/servicecatalog/api/model/ServiceInstanceBuilder;
     374: invokevirtual #658                // Method io/dekorate/deps/servicecatalog/api/model/ServiceInstanceBuilder.equals:(Ljava/lang/Object;)Z
     377: ifne          392
     380: goto          390
     383: aload_2
     384: getfield      #575                // Field serviceInstance:Lio/dekorate/deps/servicecatalog/api/model/ServiceInstanceBuilder;
     387: ifnull        392
     390: iconst_0
     391: ireturn
     392: aload_0
     393: getfield      #608                // Field serviceInstanceList:Lio/dekorate/deps/servicecatalog/api/model/ServiceInstanceListBuilder;
     396: ifnull        416
     399: aload_0
     400: getfield      #608                // Field serviceInstanceList:Lio/dekorate/deps/servicecatalog/api/model/ServiceInstanceListBuilder;
     403: aload_2
     404: getfield      #608                // Field serviceInstanceList:Lio/dekorate/deps/servicecatalog/api/model/ServiceInstanceListBuilder;
     407: invokevirtual #659                // Method io/dekorate/deps/servicecatalog/api/model/ServiceInstanceListBuilder.equals:(Ljava/lang/Object;)Z
     410: ifne          425
     413: goto          423
     416: aload_2
     417: getfield      #608                // Field serviceInstanceList:Lio/dekorate/deps/servicecatalog/api/model/ServiceInstanceListBuilder;
     420: ifnull        425
     423: iconst_0
     424: ireturn
     425: iconst_1
     426: ireturn
}
