Compiled from "AtomContent.java"
public class com.google.api.client.http.xml.atom.AtomContent extends com.google.api.client.http.xml.AbstractXmlHttpContent {
  private final boolean isEntry;

  private final java.lang.Object entry;

  protected com.google.api.client.http.xml.atom.AtomContent(com.google.api.client.xml.XmlNamespaceDictionary, java.lang.Object, boolean);
    Code:
       0: aload_0
       1: aload_1
       2: invokespecial #2                  // Method com/google/api/client/http/xml/AbstractXmlHttpContent."<init>":(Lcom/google/api/client/xml/XmlNamespaceDictionary;)V
       5: aload_0
       6: new           #3                  // class com/google/api/client/http/HttpMediaType
       9: dup
      10: getstatic     #4                  // Field com/google/api/client/xml/atom/Atom.MEDIA_TYPE:Ljava/lang/String;
      13: invokespecial #5                  // Method com/google/api/client/http/HttpMediaType."<init>":(Ljava/lang/String;)V
      16: invokevirtual #6                  // Method setMediaType:(Lcom/google/api/client/http/HttpMediaType;)Lcom/google/api/client/http/xml/atom/AtomContent;
      19: pop
      20: aload_0
      21: aload_2
      22: invokestatic  #7                  // Method com/google/api/client/util/Preconditions.checkNotNull:(Ljava/lang/Object;)Ljava/lang/Object;
      25: putfield      #8                  // Field entry:Ljava/lang/Object;
      28: aload_0
      29: iload_3
      30: putfield      #9                  // Field isEntry:Z
      33: return

  public static com.google.api.client.http.xml.atom.AtomContent forEntry(com.google.api.client.xml.XmlNamespaceDictionary, java.lang.Object);
    Code:
       0: new           #10                 // class com/google/api/client/http/xml/atom/AtomContent
       3: dup
       4: aload_0
       5: aload_1
       6: iconst_1
       7: invokespecial #11                 // Method "<init>":(Lcom/google/api/client/xml/XmlNamespaceDictionary;Ljava/lang/Object;Z)V
      10: areturn

  public static com.google.api.client.http.xml.atom.AtomContent forFeed(com.google.api.client.xml.XmlNamespaceDictionary, java.lang.Object);
    Code:
       0: new           #10                 // class com/google/api/client/http/xml/atom/AtomContent
       3: dup
       4: aload_0
       5: aload_1
       6: iconst_0
       7: invokespecial #11                 // Method "<init>":(Lcom/google/api/client/xml/XmlNamespaceDictionary;Ljava/lang/Object;Z)V
      10: areturn

  public com.google.api.client.http.xml.atom.AtomContent setMediaType(com.google.api.client.http.HttpMediaType);
    Code:
       0: aload_0
       1: aload_1
       2: invokespecial #12                 // Method com/google/api/client/http/xml/AbstractXmlHttpContent.setMediaType:(Lcom/google/api/client/http/HttpMediaType;)Lcom/google/api/client/http/xml/AbstractXmlHttpContent;
       5: pop
       6: aload_0
       7: areturn

  public final void writeTo(org.xmlpull.v1.XmlSerializer) throws java.io.IOException;
    Code:
       0: aload_0
       1: invokevirtual #13                 // Method getNamespaceDictionary:()Lcom/google/api/client/xml/XmlNamespaceDictionary;
       4: aload_1
       5: ldc           #14                 // String http://www.w3.org/2005/Atom
       7: aload_0
       8: getfield      #9                  // Field isEntry:Z
      11: ifeq          19
      14: ldc           #15                 // String entry
      16: goto          21
      19: ldc           #16                 // String feed
      21: aload_0
      22: getfield      #8                  // Field entry:Ljava/lang/Object;
      25: invokevirtual #17                 // Method com/google/api/client/xml/XmlNamespaceDictionary.serialize:(Lorg/xmlpull/v1/XmlSerializer;Ljava/lang/String;Ljava/lang/String;Ljava/lang/Object;)V
      28: return

  public final boolean isEntry();
    Code:
       0: aload_0
       1: getfield      #9                  // Field isEntry:Z
       4: ireturn

  public final java.lang.Object getData();
    Code:
       0: aload_0
       1: getfield      #8                  // Field entry:Ljava/lang/Object;
       4: areturn

  public com.google.api.client.http.xml.AbstractXmlHttpContent setMediaType(com.google.api.client.http.HttpMediaType);
    Code:
       0: aload_0
       1: aload_1
       2: invokevirtual #6                  // Method setMediaType:(Lcom/google/api/client/http/HttpMediaType;)Lcom/google/api/client/http/xml/atom/AtomContent;
       5: areturn

  public com.google.api.client.http.AbstractHttpContent setMediaType(com.google.api.client.http.HttpMediaType);
    Code:
       0: aload_0
       1: aload_1
       2: invokevirtual #6                  // Method setMediaType:(Lcom/google/api/client/http/HttpMediaType;)Lcom/google/api/client/http/xml/atom/AtomContent;
       5: areturn
}
