Compiled from "TrinityApplication.scala"
public final class org.sisioh.trinity.application.TrinityApplication$$anonfun$registerFilters$1 extends scala.runtime.AbstractFunction1<com.twitter.finagle.SimpleFilter<com.twitter.finagle.http.Request, com.twitter.finagle.http.Response>, scala.runtime.BoxedUnit> implements scala.Serializable {
  public static final long serialVersionUID;

  private final org.sisioh.trinity.application.TrinityApplication $outer;

  public final void apply(com.twitter.finagle.SimpleFilter<com.twitter.finagle.http.Request, com.twitter.finagle.http.Response>);
    Code:
       0: aload_0
       1: getfield      #23                 // Field $outer:Lorg/sisioh/trinity/application/TrinityApplication;
       4: aload_1
       5: invokeinterface #26,  2           // InterfaceMethod org/sisioh/trinity/application/TrinityApplication.registerFilter:(Lcom/twitter/finagle/SimpleFilter;)V
      10: return

  public final java.lang.Object apply(java.lang.Object);
    Code:
       0: aload_0
       1: aload_1
       2: checkcast     #33                 // class com/twitter/finagle/SimpleFilter
       5: invokevirtual #35                 // Method apply:(Lcom/twitter/finagle/SimpleFilter;)V
       8: getstatic     #41                 // Field scala/runtime/BoxedUnit.UNIT:Lscala/runtime/BoxedUnit;
      11: areturn

  public org.sisioh.trinity.application.TrinityApplication$$anonfun$registerFilters$1(org.sisioh.trinity.application.TrinityApplication);
    Code:
       0: aload_1
       1: ifnonnull     12
       4: new           #47                 // class java/lang/NullPointerException
       7: dup
       8: invokespecial #50                 // Method java/lang/NullPointerException."<init>":()V
      11: athrow
      12: aload_0
      13: aload_1
      14: putfield      #23                 // Field $outer:Lorg/sisioh/trinity/application/TrinityApplication;
      17: aload_0
      18: invokespecial #51                 // Method scala/runtime/AbstractFunction1."<init>":()V
      21: return
}
