Compiled from "IsDType.java"
public class org.apache.jena.reasoner.rulesys.builtins.IsDType extends org.apache.jena.reasoner.rulesys.builtins.BaseBuiltin {
  public org.apache.jena.reasoner.rulesys.builtins.IsDType();
    Code:
       0: aload_0
       1: invokespecial #1                  // Method org/apache/jena/reasoner/rulesys/builtins/BaseBuiltin."<init>":()V
       4: return

  public java.lang.String getName();
    Code:
       0: ldc           #2                  // String isDType
       2: areturn

  public int getArgLength();
    Code:
       0: iconst_2
       1: ireturn

  public boolean bodyCall(org.apache.jena.graph.Node[], int, org.apache.jena.reasoner.rulesys.RuleContext);
    Code:
       0: aload_0
       1: iload_2
       2: aload_3
       3: invokevirtual #3                  // Method checkArgs:(ILorg/apache/jena/reasoner/rulesys/RuleContext;)V
       6: aload_0
       7: iconst_0
       8: aload_1
       9: aload_3
      10: invokevirtual #4                  // Method getArg:(I[Lorg/apache/jena/graph/Node;Lorg/apache/jena/reasoner/rulesys/RuleContext;)Lorg/apache/jena/graph/Node;
      13: astore        4
      15: aload_0
      16: iconst_1
      17: aload_1
      18: aload_3
      19: invokevirtual #4                  // Method getArg:(I[Lorg/apache/jena/graph/Node;Lorg/apache/jena/reasoner/rulesys/RuleContext;)Lorg/apache/jena/graph/Node;
      22: astore        5
      24: aload         4
      26: aload         5
      28: invokestatic  #5                  // Method isTypeOK:(Lorg/apache/jena/graph/Node;Lorg/apache/jena/graph/Node;)Z
      31: ireturn

  public static boolean isTypeOK(org.apache.jena.graph.Node, org.apache.jena.graph.Node);
    Code:
       0: aload_1
       1: invokevirtual #6                  // Method org/apache/jena/graph/Node.isURI:()Z
       4: ifne          9
       7: iconst_0
       8: ireturn
       9: aload_0
      10: invokevirtual #7                  // Method org/apache/jena/graph/Node.isBlank:()Z
      13: ifeq          18
      16: iconst_1
      17: ireturn
      18: aload_0
      19: invokevirtual #8                  // Method org/apache/jena/graph/Node.isLiteral:()Z
      22: ifeq          84
      25: aload_0
      26: invokevirtual #9                  // Method org/apache/jena/graph/Node.getLiteral:()Lorg/apache/jena/graph/impl/LiteralLabel;
      29: astore_2
      30: aload_2
      31: invokeinterface #10,  1           // InterfaceMethod org/apache/jena/graph/impl/LiteralLabel.getDatatype:()Lorg/apache/jena/datatypes/RDFDatatype;
      36: ifnull        50
      39: aload_2
      40: invokeinterface #11,  1           // InterfaceMethod org/apache/jena/graph/impl/LiteralLabel.isWellFormed:()Z
      45: ifne          50
      48: iconst_0
      49: ireturn
      50: aload_1
      51: getstatic     #12                 // Field org/apache/jena/vocabulary/RDFS$Nodes.Literal:Lorg/apache/jena/graph/Node;
      54: invokevirtual #13                 // Method org/apache/jena/graph/Node.equals:(Ljava/lang/Object;)Z
      57: ifeq          62
      60: iconst_1
      61: ireturn
      62: invokestatic  #14                 // Method org/apache/jena/datatypes/TypeMapper.getInstance:()Lorg/apache/jena/datatypes/TypeMapper;
      65: aload_1
      66: invokevirtual #15                 // Method org/apache/jena/graph/Node.getURI:()Ljava/lang/String;
      69: invokevirtual #16                 // Method org/apache/jena/datatypes/TypeMapper.getSafeTypeByName:(Ljava/lang/String;)Lorg/apache/jena/datatypes/RDFDatatype;
      72: astore_3
      73: aload_3
      74: aload_0
      75: invokevirtual #9                  // Method org/apache/jena/graph/Node.getLiteral:()Lorg/apache/jena/graph/impl/LiteralLabel;
      78: invokeinterface #17,  2           // InterfaceMethod org/apache/jena/datatypes/RDFDatatype.isValidLiteral:(Lorg/apache/jena/graph/impl/LiteralLabel;)Z
      83: ireturn
      84: iconst_0
      85: ireturn
}
