Compiled from "StrConcat.java"
public class org.apache.jena.reasoner.rulesys.builtins.StrConcat extends org.apache.jena.reasoner.rulesys.builtins.BaseBuiltin {
  public org.apache.jena.reasoner.rulesys.builtins.StrConcat();
    Code:
       0: aload_0
       1: invokespecial #1                  // Method org/apache/jena/reasoner/rulesys/builtins/BaseBuiltin."<init>":()V
       4: return

  public java.lang.String getName();
    Code:
       0: ldc           #2                  // String strConcat
       2: areturn

  public int getArgLength();
    Code:
       0: iconst_0
       1: ireturn

  public boolean bodyCall(org.apache.jena.graph.Node[], int, org.apache.jena.reasoner.rulesys.RuleContext);
    Code:
       0: iload_2
       1: iconst_1
       2: if_icmpge     37
       5: new           #3                  // class org/apache/jena/reasoner/rulesys/BuiltinException
       8: dup
       9: aload_0
      10: aload_3
      11: new           #4                  // class java/lang/StringBuilder
      14: dup
      15: invokespecial #5                  // Method java/lang/StringBuilder."<init>":()V
      18: ldc           #6                  // String Must have at least 1 argument to
      20: invokevirtual #7                  // Method java/lang/StringBuilder.append:(Ljava/lang/String;)Ljava/lang/StringBuilder;
      23: aload_0
      24: invokevirtual #8                  // Method getName:()Ljava/lang/String;
      27: invokevirtual #7                  // Method java/lang/StringBuilder.append:(Ljava/lang/String;)Ljava/lang/StringBuilder;
      30: invokevirtual #9                  // Method java/lang/StringBuilder.toString:()Ljava/lang/String;
      33: invokespecial #10                 // Method org/apache/jena/reasoner/rulesys/BuiltinException."<init>":(Lorg/apache/jena/reasoner/rulesys/Builtin;Lorg/apache/jena/reasoner/rulesys/RuleContext;Ljava/lang/String;)V
      36: athrow
      37: new           #4                  // class java/lang/StringBuilder
      40: dup
      41: invokespecial #5                  // Method java/lang/StringBuilder."<init>":()V
      44: astore        4
      46: iconst_0
      47: istore        5
      49: iload         5
      51: iload_2
      52: iconst_1
      53: isub
      54: if_icmpge     82
      57: aload         4
      59: aload_0
      60: aload_0
      61: iload         5
      63: aload_1
      64: aload_3
      65: invokevirtual #11                 // Method getArg:(I[Lorg/apache/jena/graph/Node;Lorg/apache/jena/reasoner/rulesys/RuleContext;)Lorg/apache/jena/graph/Node;
      68: aload_3
      69: invokevirtual #12                 // Method lex:(Lorg/apache/jena/graph/Node;Lorg/apache/jena/reasoner/rulesys/RuleContext;)Ljava/lang/String;
      72: invokevirtual #7                  // Method java/lang/StringBuilder.append:(Ljava/lang/String;)Ljava/lang/StringBuilder;
      75: pop
      76: iinc          5, 1
      79: goto          49
      82: aload         4
      84: invokevirtual #9                  // Method java/lang/StringBuilder.toString:()Ljava/lang/String;
      87: invokestatic  #13                 // Method org/apache/jena/graph/NodeFactory.createLiteral:(Ljava/lang/String;)Lorg/apache/jena/graph/Node;
      90: astore        5
      92: aload_3
      93: invokeinterface #14,  1           // InterfaceMethod org/apache/jena/reasoner/rulesys/RuleContext.getEnv:()Lorg/apache/jena/reasoner/rulesys/BindingEnvironment;
      98: aload_1
      99: iload_2
     100: iconst_1
     101: isub
     102: aaload
     103: aload         5
     105: invokeinterface #15,  3           // InterfaceMethod org/apache/jena/reasoner/rulesys/BindingEnvironment.bind:(Lorg/apache/jena/graph/Node;Lorg/apache/jena/graph/Node;)Z
     110: ireturn

  protected java.lang.String lex(org.apache.jena.graph.Node, org.apache.jena.reasoner.rulesys.RuleContext);
    Code:
       0: aload_1
       1: invokevirtual #16                 // Method org/apache/jena/graph/Node.isBlank:()Z
       4: ifeq          12
       7: aload_1
       8: invokevirtual #17                 // Method org/apache/jena/graph/Node.getBlankNodeLabel:()Ljava/lang/String;
      11: areturn
      12: aload_1
      13: invokevirtual #18                 // Method org/apache/jena/graph/Node.isURI:()Z
      16: ifeq          24
      19: aload_1
      20: invokevirtual #19                 // Method org/apache/jena/graph/Node.getURI:()Ljava/lang/String;
      23: areturn
      24: aload_1
      25: invokevirtual #20                 // Method org/apache/jena/graph/Node.isLiteral:()Z
      28: ifeq          36
      31: aload_1
      32: invokevirtual #21                 // Method org/apache/jena/graph/Node.getLiteralLexicalForm:()Ljava/lang/String;
      35: areturn
      36: new           #3                  // class org/apache/jena/reasoner/rulesys/BuiltinException
      39: dup
      40: aload_0
      41: aload_2
      42: new           #4                  // class java/lang/StringBuilder
      45: dup
      46: invokespecial #5                  // Method java/lang/StringBuilder."<init>":()V
      49: ldc           #22                 // String Illegal node type:
      51: invokevirtual #7                  // Method java/lang/StringBuilder.append:(Ljava/lang/String;)Ljava/lang/StringBuilder;
      54: aload_1
      55: invokevirtual #23                 // Method java/lang/StringBuilder.append:(Ljava/lang/Object;)Ljava/lang/StringBuilder;
      58: invokevirtual #9                  // Method java/lang/StringBuilder.toString:()Ljava/lang/String;
      61: invokespecial #10                 // Method org/apache/jena/reasoner/rulesys/BuiltinException."<init>":(Lorg/apache/jena/reasoner/rulesys/Builtin;Lorg/apache/jena/reasoner/rulesys/RuleContext;Ljava/lang/String;)V
      64: athrow
}
