Compiled from "SelectorWorker.java"
public class org.apache.activemq.transport.nio.SelectorWorker implements java.lang.Runnable {
  private static final java.util.concurrent.atomic.AtomicInteger NEXT_ID;

  final org.apache.activemq.transport.nio.SelectorManager manager;

  final java.nio.channels.Selector selector;

  final int id;

  private final int maxChannelsPerWorker;

  final java.util.concurrent.atomic.AtomicInteger retainCounter;

  private final java.util.concurrent.ConcurrentLinkedQueue<java.lang.Runnable> ioTasks;

  public org.apache.activemq.transport.nio.SelectorWorker(org.apache.activemq.transport.nio.SelectorManager) throws java.io.IOException;
    Code:
       0: aload_0
       1: invokespecial #1                  // Method java/lang/Object."<init>":()V
       4: aload_0
       5: getstatic     #2                  // Field NEXT_ID:Ljava/util/concurrent/atomic/AtomicInteger;
       8: invokevirtual #3                  // Method java/util/concurrent/atomic/AtomicInteger.getAndIncrement:()I
      11: putfield      #4                  // Field id:I
      14: aload_0
      15: new           #5                  // class java/util/concurrent/atomic/AtomicInteger
      18: dup
      19: iconst_1
      20: invokespecial #6                  // Method java/util/concurrent/atomic/AtomicInteger."<init>":(I)V
      23: putfield      #7                  // Field retainCounter:Ljava/util/concurrent/atomic/AtomicInteger;
      26: aload_0
      27: new           #8                  // class java/util/concurrent/ConcurrentLinkedQueue
      30: dup
      31: invokespecial #9                  // Method java/util/concurrent/ConcurrentLinkedQueue."<init>":()V
      34: putfield      #10                 // Field ioTasks:Ljava/util/concurrent/ConcurrentLinkedQueue;
      37: aload_0
      38: aload_1
      39: putfield      #11                 // Field manager:Lorg/apache/activemq/transport/nio/SelectorManager;
      42: aload_0
      43: invokestatic  #12                 // Method java/nio/channels/Selector.open:()Ljava/nio/channels/Selector;
      46: putfield      #13                 // Field selector:Ljava/nio/channels/Selector;
      49: aload_0
      50: aload_1
      51: invokevirtual #14                 // Method org/apache/activemq/transport/nio/SelectorManager.getMaxChannelsPerWorker:()I
      54: putfield      #15                 // Field maxChannelsPerWorker:I
      57: aload_1
      58: invokevirtual #16                 // Method org/apache/activemq/transport/nio/SelectorManager.getSelectorExecutor:()Ljava/util/concurrent/Executor;
      61: aload_0
      62: invokeinterface #17,  2           // InterfaceMethod java/util/concurrent/Executor.execute:(Ljava/lang/Runnable;)V
      67: return

  void retain();
    Code:
       0: aload_0
       1: getfield      #7                  // Field retainCounter:Ljava/util/concurrent/atomic/AtomicInteger;
       4: invokevirtual #18                 // Method java/util/concurrent/atomic/AtomicInteger.incrementAndGet:()I
       7: aload_0
       8: getfield      #15                 // Field maxChannelsPerWorker:I
      11: if_icmpne     22
      14: aload_0
      15: getfield      #11                 // Field manager:Lorg/apache/activemq/transport/nio/SelectorManager;
      18: aload_0
      19: invokevirtual #19                 // Method org/apache/activemq/transport/nio/SelectorManager.onWorkerFullEvent:(Lorg/apache/activemq/transport/nio/SelectorWorker;)V
      22: return

  void release();
    Code:
       0: aload_0
       1: getfield      #7                  // Field retainCounter:Ljava/util/concurrent/atomic/AtomicInteger;
       4: invokevirtual #20                 // Method java/util/concurrent/atomic/AtomicInteger.decrementAndGet:()I
       7: istore_1
       8: iload_1
       9: ifne          23
      12: aload_0
      13: getfield      #11                 // Field manager:Lorg/apache/activemq/transport/nio/SelectorManager;
      16: aload_0
      17: invokevirtual #21                 // Method org/apache/activemq/transport/nio/SelectorManager.onWorkerEmptyEvent:(Lorg/apache/activemq/transport/nio/SelectorWorker;)V
      20: goto          41
      23: iload_1
      24: aload_0
      25: getfield      #15                 // Field maxChannelsPerWorker:I
      28: iconst_1
      29: isub
      30: if_icmpne     41
      33: aload_0
      34: getfield      #11                 // Field manager:Lorg/apache/activemq/transport/nio/SelectorManager;
      37: aload_0
      38: invokevirtual #22                 // Method org/apache/activemq/transport/nio/SelectorManager.onWorkerNotFullEvent:(Lorg/apache/activemq/transport/nio/SelectorWorker;)V
      41: return

  boolean isReleased();
    Code:
       0: aload_0
       1: getfield      #7                  // Field retainCounter:Ljava/util/concurrent/atomic/AtomicInteger;
       4: invokevirtual #23                 // Method java/util/concurrent/atomic/AtomicInteger.get:()I
       7: ifne          14
      10: iconst_1
      11: goto          15
      14: iconst_0
      15: ireturn

  public void addIoTask(java.lang.Runnable);
    Code:
       0: aload_0
       1: getfield      #10                 // Field ioTasks:Ljava/util/concurrent/ConcurrentLinkedQueue;
       4: aload_1
       5: invokevirtual #24                 // Method java/util/concurrent/ConcurrentLinkedQueue.add:(Ljava/lang/Object;)Z
       8: pop
       9: aload_0
      10: getfield      #13                 // Field selector:Ljava/nio/channels/Selector;
      13: invokevirtual #25                 // Method java/nio/channels/Selector.wakeup:()Ljava/nio/channels/Selector;
      16: pop
      17: return

  private void processIoTasks();
    Code:
       0: aload_0
       1: getfield      #10                 // Field ioTasks:Ljava/util/concurrent/ConcurrentLinkedQueue;
       4: invokevirtual #26                 // Method java/util/concurrent/ConcurrentLinkedQueue.poll:()Ljava/lang/Object;
       7: checkcast     #27                 // class java/lang/Runnable
      10: dup
      11: astore_1
      12: ifnull        32
      15: aload_1
      16: invokeinterface #28,  1           // InterfaceMethod java/lang/Runnable.run:()V
      21: goto          0
      24: astore_2
      25: aload_2
      26: invokevirtual #30                 // Method java/lang/Throwable.printStackTrace:()V
      29: goto          0
      32: return
    Exception table:
       from    to  target type
          15    21    24   Class java/lang/Throwable

  public void run();
    Code:
       0: invokestatic  #31                 // Method java/lang/Thread.currentThread:()Ljava/lang/Thread;
       3: invokevirtual #32                 // Method java/lang/Thread.getName:()Ljava/lang/String;
       6: astore_1
       7: invokestatic  #31                 // Method java/lang/Thread.currentThread:()Ljava/lang/Thread;
      10: new           #33                 // class java/lang/StringBuilder
      13: dup
      14: invokespecial #34                 // Method java/lang/StringBuilder."<init>":()V
      17: ldc           #35                 // String Selector Worker:
      19: invokevirtual #36                 // Method java/lang/StringBuilder.append:(Ljava/lang/String;)Ljava/lang/StringBuilder;
      22: aload_0
      23: getfield      #4                  // Field id:I
      26: invokevirtual #37                 // Method java/lang/StringBuilder.append:(I)Ljava/lang/StringBuilder;
      29: invokevirtual #38                 // Method java/lang/StringBuilder.toString:()Ljava/lang/String;
      32: invokevirtual #39                 // Method java/lang/Thread.setName:(Ljava/lang/String;)V
      35: aload_0
      36: invokevirtual #40                 // Method isReleased:()Z
      39: ifne          174
      42: aload_0
      43: invokespecial #41                 // Method processIoTasks:()V
      46: aload_0
      47: getfield      #13                 // Field selector:Ljava/nio/channels/Selector;
      50: ldc2_w        #42                 // long 10l
      53: invokevirtual #44                 // Method java/nio/channels/Selector.select:(J)I
      56: istore_2
      57: iload_2
      58: ifne          64
      61: goto          35
      64: aload_0
      65: getfield      #13                 // Field selector:Ljava/nio/channels/Selector;
      68: invokevirtual #45                 // Method java/nio/channels/Selector.selectedKeys:()Ljava/util/Set;
      71: astore_3
      72: aload_3
      73: invokeinterface #46,  1           // InterfaceMethod java/util/Set.iterator:()Ljava/util/Iterator;
      78: astore        4
      80: aload         4
      82: invokeinterface #47,  1           // InterfaceMethod java/util/Iterator.hasNext:()Z
      87: ifeq          171
      90: aload         4
      92: invokeinterface #48,  1           // InterfaceMethod java/util/Iterator.next:()Ljava/lang/Object;
      97: checkcast     #49                 // class java/nio/channels/SelectionKey
     100: astore        5
     102: aload         4
     104: invokeinterface #50,  1           // InterfaceMethod java/util/Iterator.remove:()V
     109: aload         5
     111: invokevirtual #51                 // Method java/nio/channels/SelectionKey.attachment:()Ljava/lang/Object;
     114: checkcast     #52                 // class org/apache/activemq/transport/nio/SelectorSelection
     117: astore        6
     119: aload         5
     121: invokevirtual #53                 // Method java/nio/channels/SelectionKey.isValid:()Z
     124: ifeq          134
     127: aload         5
     129: iconst_0
     130: invokevirtual #54                 // Method java/nio/channels/SelectionKey.interestOps:(I)Ljava/nio/channels/SelectionKey;
     133: pop
     134: aload_0
     135: getfield      #11                 // Field manager:Lorg/apache/activemq/transport/nio/SelectorManager;
     138: invokevirtual #55                 // Method org/apache/activemq/transport/nio/SelectorManager.getChannelExecutor:()Ljava/util/concurrent/Executor;
     141: new           #56                 // class org/apache/activemq/transport/nio/SelectorWorker$1
     144: dup
     145: aload_0
     146: aload         6
     148: invokespecial #57                 // Method org/apache/activemq/transport/nio/SelectorWorker$1."<init>":(Lorg/apache/activemq/transport/nio/SelectorWorker;Lorg/apache/activemq/transport/nio/SelectorSelection;)V
     151: invokeinterface #17,  2           // InterfaceMethod java/util/concurrent/Executor.execute:(Ljava/lang/Runnable;)V
     156: goto          168
     159: astore        7
     161: aload         6
     163: aload         7
     165: invokevirtual #58                 // Method org/apache/activemq/transport/nio/SelectorSelection.onError:(Ljava/lang/Throwable;)V
     168: goto          80
     171: goto          35
     174: aload_0
     175: getfield      #11                 // Field manager:Lorg/apache/activemq/transport/nio/SelectorManager;
     178: aload_0
     179: invokevirtual #21                 // Method org/apache/activemq/transport/nio/SelectorManager.onWorkerEmptyEvent:(Lorg/apache/activemq/transport/nio/SelectorWorker;)V
     182: aload_0
     183: getfield      #13                 // Field selector:Ljava/nio/channels/Selector;
     186: invokevirtual #59                 // Method java/nio/channels/Selector.close:()V
     189: goto          197
     192: astore_2
     193: aload_2
     194: invokevirtual #61                 // Method java/io/IOException.printStackTrace:()V
     197: invokestatic  #31                 // Method java/lang/Thread.currentThread:()Ljava/lang/Thread;
     200: aload_1
     201: invokevirtual #39                 // Method java/lang/Thread.setName:(Ljava/lang/String;)V
     204: goto          339
     207: astore_2
     208: aload_2
     209: invokevirtual #30                 // Method java/lang/Throwable.printStackTrace:()V
     212: aload_0
     213: getfield      #13                 // Field selector:Ljava/nio/channels/Selector;
     216: invokevirtual #62                 // Method java/nio/channels/Selector.keys:()Ljava/util/Set;
     219: astore_3
     220: aload_3
     221: invokeinterface #46,  1           // InterfaceMethod java/util/Set.iterator:()Ljava/util/Iterator;
     226: astore        4
     228: aload         4
     230: invokeinterface #47,  1           // InterfaceMethod java/util/Iterator.hasNext:()Z
     235: ifeq          269
     238: aload         4
     240: invokeinterface #48,  1           // InterfaceMethod java/util/Iterator.next:()Ljava/lang/Object;
     245: checkcast     #49                 // class java/nio/channels/SelectionKey
     248: astore        5
     250: aload         5
     252: invokevirtual #51                 // Method java/nio/channels/SelectionKey.attachment:()Ljava/lang/Object;
     255: checkcast     #52                 // class org/apache/activemq/transport/nio/SelectorSelection
     258: astore        6
     260: aload         6
     262: aload_2
     263: invokevirtual #58                 // Method org/apache/activemq/transport/nio/SelectorSelection.onError:(Ljava/lang/Throwable;)V
     266: goto          228
     269: aload_0
     270: getfield      #11                 // Field manager:Lorg/apache/activemq/transport/nio/SelectorManager;
     273: aload_0
     274: invokevirtual #21                 // Method org/apache/activemq/transport/nio/SelectorManager.onWorkerEmptyEvent:(Lorg/apache/activemq/transport/nio/SelectorWorker;)V
     277: aload_0
     278: getfield      #13                 // Field selector:Ljava/nio/channels/Selector;
     281: invokevirtual #59                 // Method java/nio/channels/Selector.close:()V
     284: goto          292
     287: astore_2
     288: aload_2
     289: invokevirtual #61                 // Method java/io/IOException.printStackTrace:()V
     292: invokestatic  #31                 // Method java/lang/Thread.currentThread:()Ljava/lang/Thread;
     295: aload_1
     296: invokevirtual #39                 // Method java/lang/Thread.setName:(Ljava/lang/String;)V
     299: goto          339
     302: astore        8
     304: aload_0
     305: getfield      #11                 // Field manager:Lorg/apache/activemq/transport/nio/SelectorManager;
     308: aload_0
     309: invokevirtual #21                 // Method org/apache/activemq/transport/nio/SelectorManager.onWorkerEmptyEvent:(Lorg/apache/activemq/transport/nio/SelectorWorker;)V
     312: aload_0
     313: getfield      #13                 // Field selector:Ljava/nio/channels/Selector;
     316: invokevirtual #59                 // Method java/nio/channels/Selector.close:()V
     319: goto          329
     322: astore        9
     324: aload         9
     326: invokevirtual #61                 // Method java/io/IOException.printStackTrace:()V
     329: invokestatic  #31                 // Method java/lang/Thread.currentThread:()Ljava/lang/Thread;
     332: aload_1
     333: invokevirtual #39                 // Method java/lang/Thread.setName:(Ljava/lang/String;)V
     336: aload         8
     338: athrow
     339: return
    Exception table:
       from    to  target type
         119   156   159   Class java/lang/Throwable
         174   189   192   Class java/io/IOException
           7   174   207   Class java/lang/Throwable
         269   284   287   Class java/io/IOException
           7   174   302   any
         207   269   302   any
         304   319   322   Class java/io/IOException
         302   304   302   any

  static {};
    Code:
       0: new           #5                  // class java/util/concurrent/atomic/AtomicInteger
       3: dup
       4: invokespecial #63                 // Method java/util/concurrent/atomic/AtomicInteger."<init>":()V
       7: putstatic     #2                  // Field NEXT_ID:Ljava/util/concurrent/atomic/AtomicInteger;
      10: return
}
