Compiled from "AttributeMap.java"
public class org.opensaml.xml.util.AttributeMap implements java.util.Map<javax.xml.namespace.QName, java.lang.String> {
  private final org.slf4j.Logger log;

  private org.opensaml.xml.XMLObject attributeOwner;

  private java.util.Map<javax.xml.namespace.QName, java.lang.String> attributes;

  private java.util.Set<javax.xml.namespace.QName> idAttribNames;

  private java.util.Set<javax.xml.namespace.QName> qnameAttribNames;

  private boolean inferQNameValues;

  public org.opensaml.xml.util.AttributeMap(org.opensaml.xml.XMLObject) throws java.lang.NullPointerException;
    Code:
       0: aload_0
       1: invokespecial #1                  // Method java/lang/Object."<init>":()V
       4: aload_0
       5: ldc_w         #2                  // class org/opensaml/xml/util/AttributeMap
       8: invokestatic  #3                  // Method org/slf4j/LoggerFactory.getLogger:(Ljava/lang/Class;)Lorg/slf4j/Logger;
      11: putfield      #4                  // Field log:Lorg/slf4j/Logger;
      14: aload_1
      15: ifnonnull     28
      18: new           #5                  // class java/lang/NullPointerException
      21: dup
      22: ldc           #6                  // String Attribute owner XMLObject may not be null
      24: invokespecial #7                  // Method java/lang/NullPointerException."<init>":(Ljava/lang/String;)V
      27: athrow
      28: aload_0
      29: aload_1
      30: putfield      #8                  // Field attributeOwner:Lorg/opensaml/xml/XMLObject;
      33: aload_0
      34: new           #9                  // class org/opensaml/xml/util/LazyMap
      37: dup
      38: invokespecial #10                 // Method org/opensaml/xml/util/LazyMap."<init>":()V
      41: putfield      #11                 // Field attributes:Ljava/util/Map;
      44: aload_0
      45: new           #12                 // class org/opensaml/xml/util/LazySet
      48: dup
      49: invokespecial #13                 // Method org/opensaml/xml/util/LazySet."<init>":()V
      52: putfield      #14                 // Field idAttribNames:Ljava/util/Set;
      55: aload_0
      56: new           #12                 // class org/opensaml/xml/util/LazySet
      59: dup
      60: invokespecial #13                 // Method org/opensaml/xml/util/LazySet."<init>":()V
      63: putfield      #15                 // Field qnameAttribNames:Ljava/util/Set;
      66: return

  public java.lang.String put(javax.xml.namespace.QName, java.lang.String);
    Code:
       0: aload_0
       1: aload_1
       2: invokevirtual #16                 // Method get:(Ljava/lang/Object;)Ljava/lang/String;
       5: astore_3
       6: aload_2
       7: aload_3
       8: invokestatic  #17                 // Method org/opensaml/xml/util/DatatypeHelper.safeEquals:(Ljava/lang/Object;Ljava/lang/Object;)Z
      11: ifne          130
      14: aload_0
      15: invokespecial #18                 // Method releaseDOM:()V
      18: aload_0
      19: getfield      #11                 // Field attributes:Ljava/util/Map;
      22: aload_1
      23: aload_2
      24: invokeinterface #19,  3           // InterfaceMethod java/util/Map.put:(Ljava/lang/Object;Ljava/lang/Object;)Ljava/lang/Object;
      29: pop
      30: aload_0
      31: aload_1
      32: invokevirtual #20                 // Method isIDAttribute:(Ljavax/xml/namespace/QName;)Z
      35: ifne          45
      38: aload_1
      39: invokestatic  #21                 // Method org/opensaml/xml/Configuration.isIDAttribute:(Ljavax/xml/namespace/QName;)Z
      42: ifeq          75
      45: aload_0
      46: getfield      #8                  // Field attributeOwner:Lorg/opensaml/xml/XMLObject;
      49: invokeinterface #22,  1           // InterfaceMethod org/opensaml/xml/XMLObject.getIDIndex:()Lorg/opensaml/xml/util/IDIndex;
      54: aload_3
      55: invokevirtual #23                 // Method org/opensaml/xml/util/IDIndex.deregisterIDMapping:(Ljava/lang/String;)V
      58: aload_0
      59: getfield      #8                  // Field attributeOwner:Lorg/opensaml/xml/XMLObject;
      62: invokeinterface #22,  1           // InterfaceMethod org/opensaml/xml/XMLObject.getIDIndex:()Lorg/opensaml/xml/util/IDIndex;
      67: aload_2
      68: aload_0
      69: getfield      #8                  // Field attributeOwner:Lorg/opensaml/xml/XMLObject;
      72: invokevirtual #24                 // Method org/opensaml/xml/util/IDIndex.registerIDMapping:(Ljava/lang/String;Lorg/opensaml/xml/XMLObject;)V
      75: aload_1
      76: invokevirtual #25                 // Method javax/xml/namespace/QName.getNamespaceURI:()Ljava/lang/String;
      79: invokestatic  #26                 // Method org/opensaml/xml/util/DatatypeHelper.isEmpty:(Ljava/lang/String;)Z
      82: ifne          118
      85: aload_2
      86: ifnonnull     105
      89: aload_0
      90: getfield      #8                  // Field attributeOwner:Lorg/opensaml/xml/XMLObject;
      93: invokeinterface #27,  1           // InterfaceMethod org/opensaml/xml/XMLObject.getNamespaceManager:()Lorg/opensaml/xml/NamespaceManager;
      98: aload_1
      99: invokevirtual #28                 // Method org/opensaml/xml/NamespaceManager.deregisterAttributeName:(Ljavax/xml/namespace/QName;)V
     102: goto          118
     105: aload_0
     106: getfield      #8                  // Field attributeOwner:Lorg/opensaml/xml/XMLObject;
     109: invokeinterface #27,  1           // InterfaceMethod org/opensaml/xml/XMLObject.getNamespaceManager:()Lorg/opensaml/xml/NamespaceManager;
     114: aload_1
     115: invokevirtual #29                 // Method org/opensaml/xml/NamespaceManager.registerAttributeName:(Ljavax/xml/namespace/QName;)V
     118: aload_0
     119: aload_1
     120: aload_3
     121: invokespecial #30                 // Method checkAndDeregisterQNameValue:(Ljavax/xml/namespace/QName;Ljava/lang/String;)V
     124: aload_0
     125: aload_1
     126: aload_2
     127: invokespecial #31                 // Method checkAndRegisterQNameValue:(Ljavax/xml/namespace/QName;Ljava/lang/String;)V
     130: aload_3
     131: areturn

  public javax.xml.namespace.QName put(javax.xml.namespace.QName, javax.xml.namespace.QName);
    Code:
       0: aload_0
       1: aload_1
       2: invokevirtual #16                 // Method get:(Ljava/lang/Object;)Ljava/lang/String;
       5: astore_3
       6: aconst_null
       7: astore        4
       9: aload_3
      10: invokestatic  #26                 // Method org/opensaml/xml/util/DatatypeHelper.isEmpty:(Ljava/lang/String;)Z
      13: ifne          24
      16: aload_0
      17: aload_3
      18: iconst_1
      19: invokespecial #32                 // Method resolveQName:(Ljava/lang/String;Z)Ljavax/xml/namespace/QName;
      22: astore        4
      24: aload         4
      26: aload_2
      27: invokestatic  #17                 // Method org/opensaml/xml/util/DatatypeHelper.safeEquals:(Ljava/lang/Object;Ljava/lang/Object;)Z
      30: ifne          101
      33: aload_0
      34: invokespecial #18                 // Method releaseDOM:()V
      37: aload_2
      38: ifnull        83
      41: aload_0
      42: aload_2
      43: invokespecial #33                 // Method constructAttributeValue:(Ljavax/xml/namespace/QName;)Ljava/lang/String;
      46: astore        5
      48: aload_0
      49: getfield      #11                 // Field attributes:Ljava/util/Map;
      52: aload_1
      53: aload         5
      55: invokeinterface #19,  3           // InterfaceMethod java/util/Map.put:(Ljava/lang/Object;Ljava/lang/Object;)Ljava/lang/Object;
      60: pop
      61: aload_0
      62: aload_1
      63: aload_2
      64: invokespecial #34                 // Method registerQNameValue:(Ljavax/xml/namespace/QName;Ljavax/xml/namespace/QName;)V
      67: aload_0
      68: getfield      #8                  // Field attributeOwner:Lorg/opensaml/xml/XMLObject;
      71: invokeinterface #27,  1           // InterfaceMethod org/opensaml/xml/XMLObject.getNamespaceManager:()Lorg/opensaml/xml/NamespaceManager;
      76: aload_1
      77: invokevirtual #29                 // Method org/opensaml/xml/NamespaceManager.registerAttributeName:(Ljavax/xml/namespace/QName;)V
      80: goto          101
      83: aload_0
      84: aload_1
      85: invokespecial #35                 // Method deregisterQNameValue:(Ljavax/xml/namespace/QName;)V
      88: aload_0
      89: getfield      #8                  // Field attributeOwner:Lorg/opensaml/xml/XMLObject;
      92: invokeinterface #27,  1           // InterfaceMethod org/opensaml/xml/XMLObject.getNamespaceManager:()Lorg/opensaml/xml/NamespaceManager;
      97: aload_1
      98: invokevirtual #28                 // Method org/opensaml/xml/NamespaceManager.deregisterAttributeName:(Ljavax/xml/namespace/QName;)V
     101: aload         4
     103: areturn

  public void clear();
    Code:
       0: new           #12                 // class org/opensaml/xml/util/LazySet
       3: dup
       4: invokespecial #13                 // Method org/opensaml/xml/util/LazySet."<init>":()V
       7: astore_1
       8: aload_1
       9: aload_0
      10: getfield      #11                 // Field attributes:Ljava/util/Map;
      13: invokeinterface #36,  1           // InterfaceMethod java/util/Map.keySet:()Ljava/util/Set;
      18: invokevirtual #37                 // Method org/opensaml/xml/util/LazySet.addAll:(Ljava/util/Collection;)Z
      21: pop
      22: aload_1
      23: invokevirtual #38                 // Method org/opensaml/xml/util/LazySet.iterator:()Ljava/util/Iterator;
      26: astore_2
      27: aload_2
      28: invokeinterface #39,  1           // InterfaceMethod java/util/Iterator.hasNext:()Z
      33: ifeq          55
      36: aload_2
      37: invokeinterface #40,  1           // InterfaceMethod java/util/Iterator.next:()Ljava/lang/Object;
      42: checkcast     #41                 // class javax/xml/namespace/QName
      45: astore_3
      46: aload_0
      47: aload_3
      48: invokevirtual #42                 // Method remove:(Ljava/lang/Object;)Ljava/lang/String;
      51: pop
      52: goto          27
      55: return

  public java.util.Set<javax.xml.namespace.QName> keySet();
    Code:
       0: aload_0
       1: getfield      #11                 // Field attributes:Ljava/util/Map;
       4: invokeinterface #36,  1           // InterfaceMethod java/util/Map.keySet:()Ljava/util/Set;
       9: invokestatic  #43                 // Method java/util/Collections.unmodifiableSet:(Ljava/util/Set;)Ljava/util/Set;
      12: areturn

  public int size();
    Code:
       0: aload_0
       1: getfield      #11                 // Field attributes:Ljava/util/Map;
       4: invokeinterface #44,  1           // InterfaceMethod java/util/Map.size:()I
       9: ireturn

  public boolean isEmpty();
    Code:
       0: aload_0
       1: getfield      #11                 // Field attributes:Ljava/util/Map;
       4: invokeinterface #45,  1           // InterfaceMethod java/util/Map.isEmpty:()Z
       9: ireturn

  public boolean containsKey(java.lang.Object);
    Code:
       0: aload_0
       1: getfield      #11                 // Field attributes:Ljava/util/Map;
       4: aload_1
       5: invokeinterface #46,  2           // InterfaceMethod java/util/Map.containsKey:(Ljava/lang/Object;)Z
      10: ireturn

  public boolean containsValue(java.lang.Object);
    Code:
       0: aload_0
       1: getfield      #11                 // Field attributes:Ljava/util/Map;
       4: aload_1
       5: invokeinterface #47,  2           // InterfaceMethod java/util/Map.containsValue:(Ljava/lang/Object;)Z
      10: ireturn

  public java.lang.String get(java.lang.Object);
    Code:
       0: aload_0
       1: getfield      #11                 // Field attributes:Ljava/util/Map;
       4: aload_1
       5: invokeinterface #48,  2           // InterfaceMethod java/util/Map.get:(Ljava/lang/Object;)Ljava/lang/Object;
      10: checkcast     #49                 // class java/lang/String
      13: areturn

  public java.lang.String remove(java.lang.Object);
    Code:
       0: aload_0
       1: getfield      #11                 // Field attributes:Ljava/util/Map;
       4: aload_1
       5: invokeinterface #50,  2           // InterfaceMethod java/util/Map.remove:(Ljava/lang/Object;)Ljava/lang/Object;
      10: checkcast     #49                 // class java/lang/String
      13: astore_2
      14: aload_2
      15: ifnull        74
      18: aload_0
      19: invokespecial #18                 // Method releaseDOM:()V
      22: aload_1
      23: checkcast     #41                 // class javax/xml/namespace/QName
      26: astore_3
      27: aload_0
      28: aload_3
      29: invokevirtual #20                 // Method isIDAttribute:(Ljavax/xml/namespace/QName;)Z
      32: ifne          42
      35: aload_3
      36: invokestatic  #21                 // Method org/opensaml/xml/Configuration.isIDAttribute:(Ljavax/xml/namespace/QName;)Z
      39: ifeq          55
      42: aload_0
      43: getfield      #8                  // Field attributeOwner:Lorg/opensaml/xml/XMLObject;
      46: invokeinterface #22,  1           // InterfaceMethod org/opensaml/xml/XMLObject.getIDIndex:()Lorg/opensaml/xml/util/IDIndex;
      51: aload_2
      52: invokevirtual #23                 // Method org/opensaml/xml/util/IDIndex.deregisterIDMapping:(Ljava/lang/String;)V
      55: aload_0
      56: getfield      #8                  // Field attributeOwner:Lorg/opensaml/xml/XMLObject;
      59: invokeinterface #27,  1           // InterfaceMethod org/opensaml/xml/XMLObject.getNamespaceManager:()Lorg/opensaml/xml/NamespaceManager;
      64: aload_3
      65: invokevirtual #28                 // Method org/opensaml/xml/NamespaceManager.deregisterAttributeName:(Ljavax/xml/namespace/QName;)V
      68: aload_0
      69: aload_3
      70: aload_2
      71: invokespecial #30                 // Method checkAndDeregisterQNameValue:(Ljavax/xml/namespace/QName;Ljava/lang/String;)V
      74: aload_2
      75: areturn

  public void putAll(java.util.Map<? extends javax.xml.namespace.QName, ? extends java.lang.String>);
    Code:
       0: aload_1
       1: ifnull        70
       4: aload_1
       5: invokeinterface #44,  1           // InterfaceMethod java/util/Map.size:()I
      10: ifle          70
      13: aload_1
      14: invokeinterface #51,  1           // InterfaceMethod java/util/Map.entrySet:()Ljava/util/Set;
      19: invokeinterface #52,  1           // InterfaceMethod java/util/Set.iterator:()Ljava/util/Iterator;
      24: astore_2
      25: aload_2
      26: invokeinterface #39,  1           // InterfaceMethod java/util/Iterator.hasNext:()Z
      31: ifeq          70
      34: aload_2
      35: invokeinterface #40,  1           // InterfaceMethod java/util/Iterator.next:()Ljava/lang/Object;
      40: checkcast     #53                 // class java/util/Map$Entry
      43: astore_3
      44: aload_0
      45: aload_3
      46: invokeinterface #54,  1           // InterfaceMethod java/util/Map$Entry.getKey:()Ljava/lang/Object;
      51: checkcast     #41                 // class javax/xml/namespace/QName
      54: aload_3
      55: invokeinterface #55,  1           // InterfaceMethod java/util/Map$Entry.getValue:()Ljava/lang/Object;
      60: checkcast     #49                 // class java/lang/String
      63: invokevirtual #56                 // Method put:(Ljavax/xml/namespace/QName;Ljava/lang/String;)Ljava/lang/String;
      66: pop
      67: goto          25
      70: return

  public java.util.Collection<java.lang.String> values();
    Code:
       0: aload_0
       1: getfield      #11                 // Field attributes:Ljava/util/Map;
       4: invokeinterface #57,  1           // InterfaceMethod java/util/Map.values:()Ljava/util/Collection;
       9: invokestatic  #58                 // Method java/util/Collections.unmodifiableCollection:(Ljava/util/Collection;)Ljava/util/Collection;
      12: areturn

  public java.util.Set<java.util.Map$Entry<javax.xml.namespace.QName, java.lang.String>> entrySet();
    Code:
       0: aload_0
       1: getfield      #11                 // Field attributes:Ljava/util/Map;
       4: invokeinterface #51,  1           // InterfaceMethod java/util/Map.entrySet:()Ljava/util/Set;
       9: invokestatic  #43                 // Method java/util/Collections.unmodifiableSet:(Ljava/util/Set;)Ljava/util/Set;
      12: areturn

  public void registerID(javax.xml.namespace.QName);
    Code:
       0: aload_0
       1: getfield      #14                 // Field idAttribNames:Ljava/util/Set;
       4: aload_1
       5: invokeinterface #59,  2           // InterfaceMethod java/util/Set.contains:(Ljava/lang/Object;)Z
      10: ifne          24
      13: aload_0
      14: getfield      #14                 // Field idAttribNames:Ljava/util/Set;
      17: aload_1
      18: invokeinterface #60,  2           // InterfaceMethod java/util/Set.add:(Ljava/lang/Object;)Z
      23: pop
      24: aload_0
      25: aload_1
      26: invokevirtual #61                 // Method containsKey:(Ljava/lang/Object;)Z
      29: ifeq          53
      32: aload_0
      33: getfield      #8                  // Field attributeOwner:Lorg/opensaml/xml/XMLObject;
      36: invokeinterface #22,  1           // InterfaceMethod org/opensaml/xml/XMLObject.getIDIndex:()Lorg/opensaml/xml/util/IDIndex;
      41: aload_0
      42: aload_1
      43: invokevirtual #16                 // Method get:(Ljava/lang/Object;)Ljava/lang/String;
      46: aload_0
      47: getfield      #8                  // Field attributeOwner:Lorg/opensaml/xml/XMLObject;
      50: invokevirtual #24                 // Method org/opensaml/xml/util/IDIndex.registerIDMapping:(Ljava/lang/String;Lorg/opensaml/xml/XMLObject;)V
      53: return

  public void deregisterID(javax.xml.namespace.QName);
    Code:
       0: aload_0
       1: getfield      #14                 // Field idAttribNames:Ljava/util/Set;
       4: aload_1
       5: invokeinterface #59,  2           // InterfaceMethod java/util/Set.contains:(Ljava/lang/Object;)Z
      10: ifeq          24
      13: aload_0
      14: getfield      #14                 // Field idAttribNames:Ljava/util/Set;
      17: aload_1
      18: invokeinterface #62,  2           // InterfaceMethod java/util/Set.remove:(Ljava/lang/Object;)Z
      23: pop
      24: aload_0
      25: aload_1
      26: invokevirtual #61                 // Method containsKey:(Ljava/lang/Object;)Z
      29: ifeq          49
      32: aload_0
      33: getfield      #8                  // Field attributeOwner:Lorg/opensaml/xml/XMLObject;
      36: invokeinterface #22,  1           // InterfaceMethod org/opensaml/xml/XMLObject.getIDIndex:()Lorg/opensaml/xml/util/IDIndex;
      41: aload_0
      42: aload_1
      43: invokevirtual #16                 // Method get:(Ljava/lang/Object;)Ljava/lang/String;
      46: invokevirtual #23                 // Method org/opensaml/xml/util/IDIndex.deregisterIDMapping:(Ljava/lang/String;)V
      49: return

  public boolean isIDAttribute(javax.xml.namespace.QName);
    Code:
       0: aload_0
       1: getfield      #14                 // Field idAttribNames:Ljava/util/Set;
       4: aload_1
       5: invokeinterface #59,  2           // InterfaceMethod java/util/Set.contains:(Ljava/lang/Object;)Z
      10: ireturn

  public void registerQNameAttribute(javax.xml.namespace.QName);
    Code:
       0: aload_0
       1: getfield      #15                 // Field qnameAttribNames:Ljava/util/Set;
       4: aload_1
       5: invokeinterface #60,  2           // InterfaceMethod java/util/Set.add:(Ljava/lang/Object;)Z
      10: pop
      11: return

  public void deregisterQNameAttribute(javax.xml.namespace.QName);
    Code:
       0: aload_0
       1: getfield      #15                 // Field qnameAttribNames:Ljava/util/Set;
       4: aload_1
       5: invokeinterface #62,  2           // InterfaceMethod java/util/Set.remove:(Ljava/lang/Object;)Z
      10: pop
      11: return

  public boolean isQNameAttribute(javax.xml.namespace.QName);
    Code:
       0: aload_0
       1: getfield      #15                 // Field qnameAttribNames:Ljava/util/Set;
       4: aload_1
       5: invokeinterface #59,  2           // InterfaceMethod java/util/Set.contains:(Ljava/lang/Object;)Z
      10: ireturn

  public boolean isInferQNameValues();
    Code:
       0: aload_0
       1: getfield      #63                 // Field inferQNameValues:Z
       4: ireturn

  public void setInferQNameValues(boolean);
    Code:
       0: aload_0
       1: iload_1
       2: putfield      #63                 // Field inferQNameValues:Z
       5: return

  private void releaseDOM();
    Code:
       0: aload_0
       1: getfield      #8                  // Field attributeOwner:Lorg/opensaml/xml/XMLObject;
       4: invokeinterface #64,  1           // InterfaceMethod org/opensaml/xml/XMLObject.releaseDOM:()V
       9: aload_0
      10: getfield      #8                  // Field attributeOwner:Lorg/opensaml/xml/XMLObject;
      13: iconst_1
      14: invokeinterface #65,  2           // InterfaceMethod org/opensaml/xml/XMLObject.releaseParentDOM:(Z)V
      19: return

  private void checkAndRegisterQNameValue(javax.xml.namespace.QName, java.lang.String);
    Code:
       0: aload_2
       1: ifnonnull     5
       4: return
       5: aload_0
       6: aload_1
       7: aload_2
       8: invokespecial #66                 // Method checkQName:(Ljavax/xml/namespace/QName;Ljava/lang/String;)Ljavax/xml/namespace/QName;
      11: astore_3
      12: aload_3
      13: ifnull        38
      16: aload_0
      17: getfield      #4                  // Field log:Lorg/slf4j/Logger;
      20: ldc           #67                 // String Attribute \'{}\' with value \'{}\' was evaluated to be QName type
      22: aload_1
      23: aload_2
      24: invokeinterface #68,  4           // InterfaceMethod org/slf4j/Logger.trace:(Ljava/lang/String;Ljava/lang/Object;Ljava/lang/Object;)V
      29: aload_0
      30: aload_1
      31: aload_3
      32: invokespecial #34                 // Method registerQNameValue:(Ljavax/xml/namespace/QName;Ljavax/xml/namespace/QName;)V
      35: goto          51
      38: aload_0
      39: getfield      #4                  // Field log:Lorg/slf4j/Logger;
      42: ldc           #69                 // String Attribute \'{}\' with value \'{}\' was not evaluated to be QName type
      44: aload_1
      45: aload_2
      46: invokeinterface #68,  4           // InterfaceMethod org/slf4j/Logger.trace:(Ljava/lang/String;Ljava/lang/Object;Ljava/lang/Object;)V
      51: return

  private void registerQNameValue(javax.xml.namespace.QName, javax.xml.namespace.QName);
    Code:
       0: aload_2
       1: ifnonnull     5
       4: return
       5: aload_1
       6: invokestatic  #70                 // Method org/opensaml/xml/NamespaceManager.generateAttributeID:(Ljavax/xml/namespace/QName;)Ljava/lang/String;
       9: astore_3
      10: aload_0
      11: getfield      #4                  // Field log:Lorg/slf4j/Logger;
      14: ldc           #71                 // String Registering QName attribute value \'{}\' under attibute ID \'{}\'
      16: aload_2
      17: aload_3
      18: invokeinterface #68,  4           // InterfaceMethod org/slf4j/Logger.trace:(Ljava/lang/String;Ljava/lang/Object;Ljava/lang/Object;)V
      23: aload_0
      24: getfield      #8                  // Field attributeOwner:Lorg/opensaml/xml/XMLObject;
      27: invokeinterface #27,  1           // InterfaceMethod org/opensaml/xml/XMLObject.getNamespaceManager:()Lorg/opensaml/xml/NamespaceManager;
      32: aload_3
      33: aload_2
      34: invokevirtual #72                 // Method org/opensaml/xml/NamespaceManager.registerAttributeValue:(Ljava/lang/String;Ljavax/xml/namespace/QName;)V
      37: return

  private void checkAndDeregisterQNameValue(javax.xml.namespace.QName, java.lang.String);
    Code:
       0: aload_2
       1: ifnonnull     5
       4: return
       5: aload_0
       6: aload_1
       7: aload_2
       8: invokespecial #66                 // Method checkQName:(Ljavax/xml/namespace/QName;Ljava/lang/String;)Ljavax/xml/namespace/QName;
      11: astore_3
      12: aload_3
      13: ifnull        37
      16: aload_0
      17: getfield      #4                  // Field log:Lorg/slf4j/Logger;
      20: ldc           #67                 // String Attribute \'{}\' with value \'{}\' was evaluated to be QName type
      22: aload_1
      23: aload_2
      24: invokeinterface #68,  4           // InterfaceMethod org/slf4j/Logger.trace:(Ljava/lang/String;Ljava/lang/Object;Ljava/lang/Object;)V
      29: aload_0
      30: aload_1
      31: invokespecial #35                 // Method deregisterQNameValue:(Ljavax/xml/namespace/QName;)V
      34: goto          50
      37: aload_0
      38: getfield      #4                  // Field log:Lorg/slf4j/Logger;
      41: ldc           #69                 // String Attribute \'{}\' with value \'{}\' was not evaluated to be QName type
      43: aload_1
      44: aload_2
      45: invokeinterface #68,  4           // InterfaceMethod org/slf4j/Logger.trace:(Ljava/lang/String;Ljava/lang/Object;Ljava/lang/Object;)V
      50: return

  private void deregisterQNameValue(javax.xml.namespace.QName);
    Code:
       0: aload_1
       1: invokestatic  #70                 // Method org/opensaml/xml/NamespaceManager.generateAttributeID:(Ljavax/xml/namespace/QName;)Ljava/lang/String;
       4: astore_2
       5: aload_0
       6: getfield      #4                  // Field log:Lorg/slf4j/Logger;
       9: ldc           #73                 // String Deregistering QName attribute with attibute ID \'{}\'
      11: aload_2
      12: invokeinterface #74,  3           // InterfaceMethod org/slf4j/Logger.trace:(Ljava/lang/String;Ljava/lang/Object;)V
      17: aload_0
      18: getfield      #8                  // Field attributeOwner:Lorg/opensaml/xml/XMLObject;
      21: invokeinterface #27,  1           // InterfaceMethod org/opensaml/xml/XMLObject.getNamespaceManager:()Lorg/opensaml/xml/NamespaceManager;
      26: aload_2
      27: invokevirtual #75                 // Method org/opensaml/xml/NamespaceManager.deregisterAttributeValue:(Ljava/lang/String;)V
      30: return

  private javax.xml.namespace.QName checkQName(javax.xml.namespace.QName, java.lang.String);
    Code:
       0: aload_0
       1: getfield      #4                  // Field log:Lorg/slf4j/Logger;
       4: ldc           #76                 // String Checking whether attribute \'{}\' with value {} is a QName type
       6: aload_1
       7: aload_2
       8: invokeinterface #68,  4           // InterfaceMethod org/slf4j/Logger.trace:(Ljava/lang/String;Ljava/lang/Object;Ljava/lang/Object;)V
      13: aload_2
      14: ifnonnull     30
      17: aload_0
      18: getfield      #4                  // Field log:Lorg/slf4j/Logger;
      21: ldc           #77                 // String Attribute value was null, returning null
      23: invokeinterface #78,  2           // InterfaceMethod org/slf4j/Logger.trace:(Ljava/lang/String;)V
      28: aconst_null
      29: areturn
      30: aload_0
      31: aload_1
      32: invokevirtual #79                 // Method isQNameAttribute:(Ljavax/xml/namespace/QName;)Z
      35: ifeq          89
      38: aload_0
      39: getfield      #4                  // Field log:Lorg/slf4j/Logger;
      42: ldc           #80                 // String Configuration indicates attribute with name \'{}\' is a QName type, resolving value QName
      44: aload_1
      45: invokeinterface #74,  3           // InterfaceMethod org/slf4j/Logger.trace:(Ljava/lang/String;Ljava/lang/Object;)V
      50: aload_0
      51: aload_2
      52: iconst_1
      53: invokespecial #32                 // Method resolveQName:(Ljava/lang/String;Z)Ljavax/xml/namespace/QName;
      56: astore_3
      57: aload_3
      58: ifnull        76
      61: aload_0
      62: getfield      #4                  // Field log:Lorg/slf4j/Logger;
      65: ldc           #81                 // String Successfully resolved attribute value to QName: {}
      67: aload_3
      68: invokeinterface #74,  3           // InterfaceMethod org/slf4j/Logger.trace:(Ljava/lang/String;Ljava/lang/Object;)V
      73: goto          87
      76: aload_0
      77: getfield      #4                  // Field log:Lorg/slf4j/Logger;
      80: ldc           #82                 // String Could not resolve attribute value to QName, returning null
      82: invokeinterface #78,  2           // InterfaceMethod org/slf4j/Logger.trace:(Ljava/lang/String;)V
      87: aload_3
      88: areturn
      89: aload_0
      90: invokevirtual #83                 // Method isInferQNameValues:()Z
      93: ifeq          146
      96: aload_0
      97: getfield      #4                  // Field log:Lorg/slf4j/Logger;
     100: ldc           #84                 // String Attempting to infer whether attribute value is a QName
     102: invokeinterface #78,  2           // InterfaceMethod org/slf4j/Logger.trace:(Ljava/lang/String;)V
     107: aload_0
     108: aload_2
     109: iconst_0
     110: invokespecial #32                 // Method resolveQName:(Ljava/lang/String;Z)Ljavax/xml/namespace/QName;
     113: astore_3
     114: aload_3
     115: ifnull        133
     118: aload_0
     119: getfield      #4                  // Field log:Lorg/slf4j/Logger;
     122: ldc           #85                 // String Resolved attribute as a QName: \'{}\'
     124: aload_3
     125: invokeinterface #74,  3           // InterfaceMethod org/slf4j/Logger.trace:(Ljava/lang/String;Ljava/lang/Object;)V
     130: goto          144
     133: aload_0
     134: getfield      #4                  // Field log:Lorg/slf4j/Logger;
     137: ldc           #86                 // String Attribute value was not resolveable to a QName, returning null
     139: invokeinterface #78,  2           // InterfaceMethod org/slf4j/Logger.trace:(Ljava/lang/String;)V
     144: aload_3
     145: areturn
     146: aload_0
     147: getfield      #4                  // Field log:Lorg/slf4j/Logger;
     150: ldc           #87                 // String Attribute was not registered in configuration as a QName type and QName inference is disabled
     152: invokeinterface #78,  2           // InterfaceMethod org/slf4j/Logger.trace:(Ljava/lang/String;)V
     157: aconst_null
     158: areturn

  private javax.xml.namespace.QName resolveQName(java.lang.String, boolean);
    Code:
       0: aload_1
       1: ifnonnull     6
       4: aconst_null
       5: areturn
       6: aload_0
       7: getfield      #4                  // Field log:Lorg/slf4j/Logger;
      10: ldc           #88                 // String Attemtping to resolve QName from attribute value \'{}\'
      12: aload_1
      13: invokeinterface #74,  3           // InterfaceMethod org/slf4j/Logger.trace:(Ljava/lang/String;Ljava/lang/Object;)V
      18: aconst_null
      19: astore_3
      20: aconst_null
      21: astore        4
      23: aload_1
      24: bipush        58
      26: invokevirtual #89                 // Method java/lang/String.indexOf:(I)I
      29: istore        5
      31: iload         5
      33: iconst_m1
      34: if_icmple     70
      37: aload_1
      38: iconst_0
      39: iload         5
      41: invokevirtual #90                 // Method java/lang/String.substring:(II)Ljava/lang/String;
      44: astore_3
      45: aload_0
      46: getfield      #4                  // Field log:Lorg/slf4j/Logger;
      49: ldc           #91                 // String Evaluating candiate namespace prefix \'{}\'
      51: aload_3
      52: invokeinterface #74,  3           // InterfaceMethod org/slf4j/Logger.trace:(Ljava/lang/String;Ljava/lang/Object;)V
      57: aload_1
      58: iload         5
      60: iconst_1
      61: iadd
      62: invokevirtual #92                 // Method java/lang/String.substring:(I)Ljava/lang/String;
      65: astore        4
      67: goto          106
      70: iload_2
      71: ifeq          93
      74: aconst_null
      75: astore_3
      76: aload_0
      77: getfield      #4                  // Field log:Lorg/slf4j/Logger;
      80: ldc           #93                 // String Value did not contain a colon, evaluating as default namespace
      82: invokeinterface #78,  2           // InterfaceMethod org/slf4j/Logger.trace:(Ljava/lang/String;)V
      87: aload_1
      88: astore        4
      90: goto          106
      93: aload_0
      94: getfield      #4                  // Field log:Lorg/slf4j/Logger;
      97: ldc           #94                 // String Value did not contain a colon, default namespace is disallowed, returning null
      99: invokeinterface #78,  2           // InterfaceMethod org/slf4j/Logger.trace:(Ljava/lang/String;)V
     104: aconst_null
     105: areturn
     106: aload_0
     107: getfield      #4                  // Field log:Lorg/slf4j/Logger;
     110: ldc           #95                 // String Evaluated QName local part as \'{}\'
     112: aload         4
     114: invokeinterface #74,  3           // InterfaceMethod org/slf4j/Logger.trace:(Ljava/lang/String;Ljava/lang/Object;)V
     119: aload_0
     120: getfield      #8                  // Field attributeOwner:Lorg/opensaml/xml/XMLObject;
     123: aload_3
     124: invokestatic  #96                 // Method org/opensaml/xml/util/XMLObjectHelper.lookupNamespaceURI:(Lorg/opensaml/xml/XMLObject;Ljava/lang/String;)Ljava/lang/String;
     127: astore        6
     129: aload_0
     130: getfield      #4                  // Field log:Lorg/slf4j/Logger;
     133: ldc           #97                 // String Resolved namespace URI \'{}\'
     135: aload         6
     137: invokeinterface #74,  3           // InterfaceMethod org/slf4j/Logger.trace:(Ljava/lang/String;Ljava/lang/Object;)V
     142: aload         6
     144: ifnull        173
     147: aload         6
     149: aload         4
     151: aload_3
     152: invokestatic  #98                 // Method org/opensaml/xml/util/XMLHelper.constructQName:(Ljava/lang/String;Ljava/lang/String;Ljava/lang/String;)Ljavax/xml/namespace/QName;
     155: astore        7
     157: aload_0
     158: getfield      #4                  // Field log:Lorg/slf4j/Logger;
     161: ldc           #99                 // String Resolved QName \'{}\'
     163: aload         7
     165: invokeinterface #74,  3           // InterfaceMethod org/slf4j/Logger.trace:(Ljava/lang/String;Ljava/lang/Object;)V
     170: aload         7
     172: areturn
     173: aload_0
     174: getfield      #4                  // Field log:Lorg/slf4j/Logger;
     177: ldc           #100                // String Namespace URI for candidate prefix \'{}\' could not be resolved
     179: aload_3
     180: invokeinterface #74,  3           // InterfaceMethod org/slf4j/Logger.trace:(Ljava/lang/String;Ljava/lang/Object;)V
     185: aload_0
     186: getfield      #4                  // Field log:Lorg/slf4j/Logger;
     189: ldc           #101                // String Value was either not a QName, or namespace URI could not be resolved
     191: invokeinterface #78,  2           // InterfaceMethod org/slf4j/Logger.trace:(Ljava/lang/String;)V
     196: aconst_null
     197: areturn

  private java.lang.String constructAttributeValue(javax.xml.namespace.QName);
    Code:
       0: aload_1
       1: invokevirtual #102                // Method javax/xml/namespace/QName.getLocalPart:()Ljava/lang/String;
       4: invokestatic  #103                // Method org/opensaml/xml/util/DatatypeHelper.safeTrimOrNullString:(Ljava/lang/String;)Ljava/lang/String;
       7: astore_2
       8: aload_2
       9: ifnonnull     22
      12: new           #104                // class java/lang/IllegalArgumentException
      15: dup
      16: ldc           #105                // String Local name may not be null or empty
      18: invokespecial #106                // Method java/lang/IllegalArgumentException."<init>":(Ljava/lang/String;)V
      21: athrow
      22: aload_1
      23: invokevirtual #107                // Method javax/xml/namespace/QName.getPrefix:()Ljava/lang/String;
      26: invokestatic  #103                // Method org/opensaml/xml/util/DatatypeHelper.safeTrimOrNullString:(Ljava/lang/String;)Ljava/lang/String;
      29: astore        4
      31: aload         4
      33: ifnull        67
      36: new           #108                // class java/lang/StringBuilder
      39: dup
      40: invokespecial #109                // Method java/lang/StringBuilder."<init>":()V
      43: aload         4
      45: invokevirtual #110                // Method java/lang/StringBuilder.append:(Ljava/lang/String;)Ljava/lang/StringBuilder;
      48: ldc           #111                // String :
      50: invokevirtual #110                // Method java/lang/StringBuilder.append:(Ljava/lang/String;)Ljava/lang/StringBuilder;
      53: aload_2
      54: invokestatic  #103                // Method org/opensaml/xml/util/DatatypeHelper.safeTrimOrNullString:(Ljava/lang/String;)Ljava/lang/String;
      57: invokevirtual #110                // Method java/lang/StringBuilder.append:(Ljava/lang/String;)Ljava/lang/StringBuilder;
      60: invokevirtual #112                // Method java/lang/StringBuilder.toString:()Ljava/lang/String;
      63: astore_3
      64: goto          72
      67: aload_2
      68: invokestatic  #103                // Method org/opensaml/xml/util/DatatypeHelper.safeTrimOrNullString:(Ljava/lang/String;)Ljava/lang/String;
      71: astore_3
      72: aload_3
      73: areturn

  public java.lang.Object remove(java.lang.Object);
    Code:
       0: aload_0
       1: aload_1
       2: invokevirtual #42                 // Method remove:(Ljava/lang/Object;)Ljava/lang/String;
       5: areturn

  public java.lang.Object put(java.lang.Object, java.lang.Object);
    Code:
       0: aload_0
       1: aload_1
       2: checkcast     #41                 // class javax/xml/namespace/QName
       5: aload_2
       6: checkcast     #49                 // class java/lang/String
       9: invokevirtual #56                 // Method put:(Ljavax/xml/namespace/QName;Ljava/lang/String;)Ljava/lang/String;
      12: areturn

  public java.lang.Object get(java.lang.Object);
    Code:
       0: aload_0
       1: aload_1
       2: invokevirtual #16                 // Method get:(Ljava/lang/Object;)Ljava/lang/String;
       5: areturn
}
