Compiled from "TruthValue.java"
public final class org.hibernate.query.criteria.internal.predicate.TruthValue extends java.lang.Enum<org.hibernate.query.criteria.internal.predicate.TruthValue> {
  public static final org.hibernate.query.criteria.internal.predicate.TruthValue TRUE;

  public static final org.hibernate.query.criteria.internal.predicate.TruthValue FALSE;

  public static final org.hibernate.query.criteria.internal.predicate.TruthValue UNKNOWN;

  private static final org.hibernate.query.criteria.internal.predicate.TruthValue[] $VALUES;

  public static org.hibernate.query.criteria.internal.predicate.TruthValue[] values();
    Code:
       0: getstatic     #1                  // Field $VALUES:[Lorg/hibernate/query/criteria/internal/predicate/TruthValue;
       3: invokevirtual #2                  // Method "[Lorg/hibernate/query/criteria/internal/predicate/TruthValue;".clone:()Ljava/lang/Object;
       6: checkcast     #3                  // class "[Lorg/hibernate/query/criteria/internal/predicate/TruthValue;"
       9: areturn

  public static org.hibernate.query.criteria.internal.predicate.TruthValue valueOf(java.lang.String);
    Code:
       0: ldc           #4                  // class org/hibernate/query/criteria/internal/predicate/TruthValue
       2: aload_0
       3: invokestatic  #5                  // Method java/lang/Enum.valueOf:(Ljava/lang/Class;Ljava/lang/String;)Ljava/lang/Enum;
       6: checkcast     #4                  // class org/hibernate/query/criteria/internal/predicate/TruthValue
       9: areturn

  private org.hibernate.query.criteria.internal.predicate.TruthValue();
    Code:
       0: aload_0
       1: aload_1
       2: iload_2
       3: invokespecial #6                  // Method java/lang/Enum."<init>":(Ljava/lang/String;I)V
       6: return

  static {};
    Code:
       0: new           #4                  // class org/hibernate/query/criteria/internal/predicate/TruthValue
       3: dup
       4: ldc           #7                  // String TRUE
       6: iconst_0
       7: invokespecial #8                  // Method "<init>":(Ljava/lang/String;I)V
      10: putstatic     #9                  // Field TRUE:Lorg/hibernate/query/criteria/internal/predicate/TruthValue;
      13: new           #4                  // class org/hibernate/query/criteria/internal/predicate/TruthValue
      16: dup
      17: ldc           #10                 // String FALSE
      19: iconst_1
      20: invokespecial #8                  // Method "<init>":(Ljava/lang/String;I)V
      23: putstatic     #11                 // Field FALSE:Lorg/hibernate/query/criteria/internal/predicate/TruthValue;
      26: new           #4                  // class org/hibernate/query/criteria/internal/predicate/TruthValue
      29: dup
      30: ldc           #12                 // String UNKNOWN
      32: iconst_2
      33: invokespecial #8                  // Method "<init>":(Ljava/lang/String;I)V
      36: putstatic     #13                 // Field UNKNOWN:Lorg/hibernate/query/criteria/internal/predicate/TruthValue;
      39: iconst_3
      40: anewarray     #4                  // class org/hibernate/query/criteria/internal/predicate/TruthValue
      43: dup
      44: iconst_0
      45: getstatic     #9                  // Field TRUE:Lorg/hibernate/query/criteria/internal/predicate/TruthValue;
      48: aastore
      49: dup
      50: iconst_1
      51: getstatic     #11                 // Field FALSE:Lorg/hibernate/query/criteria/internal/predicate/TruthValue;
      54: aastore
      55: dup
      56: iconst_2
      57: getstatic     #13                 // Field UNKNOWN:Lorg/hibernate/query/criteria/internal/predicate/TruthValue;
      60: aastore
      61: putstatic     #1                  // Field $VALUES:[Lorg/hibernate/query/criteria/internal/predicate/TruthValue;
      64: return
}
