Compiled from "HuffmanCompressor.java"
class io.airlift.compress.zstd.HuffmanCompressor {
  private io.airlift.compress.zstd.HuffmanCompressor();
    Code:
       0: aload_0
       1: invokespecial #5                  // Method java/lang/Object."<init>":()V
       4: return

  public static int compress4streams(java.lang.Object, long, int, java.lang.Object, long, int, io.airlift.compress.zstd.HuffmanCompressionTable);
    Code:
       0: lload         5
       2: lstore        9
       4: lload         5
       6: iload         7
       8: i2l
       9: ladd
      10: lstore        11
      12: lload_1
      13: lstore        13
      15: lload_1
      16: iload_3
      17: i2l
      18: ladd
      19: lstore        15
      21: iload         7
      23: iconst_3
      24: iadd
      25: iconst_4
      26: idiv
      27: istore        17
      29: iload_3
      30: bipush        17
      32: if_icmpge     37
      35: iconst_0
      36: ireturn
      37: iload         7
      39: bipush        9
      41: if_icmpgt     46
      44: iconst_0
      45: ireturn
      46: lload         13
      48: ldc2_w        #11                 // long 6l
      51: ladd
      52: lstore        13
      54: aload_0
      55: lload         13
      57: lload         15
      59: lload         13
      61: lsub
      62: l2i
      63: aload         4
      65: lload         9
      67: iload         17
      69: aload         8
      71: invokestatic  #13                 // Method compressSingleStream:(Ljava/lang/Object;JILjava/lang/Object;JILio/airlift/compress/zstd/HuffmanCompressionTable;)I
      74: istore        18
      76: iload         18
      78: ifne          83
      81: iconst_0
      82: ireturn
      83: getstatic     #19                 // Field io/airlift/compress/zstd/UnsafeUtil.UNSAFE:Lsun/misc/Unsafe;
      86: aload_0
      87: lload_1
      88: iload         18
      90: i2s
      91: invokevirtual #25                 // Method sun/misc/Unsafe.putShort:(Ljava/lang/Object;JS)V
      94: lload         13
      96: iload         18
      98: i2l
      99: ladd
     100: lstore        13
     102: lload         9
     104: iload         17
     106: i2l
     107: ladd
     108: lstore        9
     110: aload_0
     111: lload         13
     113: lload         15
     115: lload         13
     117: lsub
     118: l2i
     119: aload         4
     121: lload         9
     123: iload         17
     125: aload         8
     127: invokestatic  #13                 // Method compressSingleStream:(Ljava/lang/Object;JILjava/lang/Object;JILio/airlift/compress/zstd/HuffmanCompressionTable;)I
     130: istore        18
     132: iload         18
     134: ifne          139
     137: iconst_0
     138: ireturn
     139: getstatic     #19                 // Field io/airlift/compress/zstd/UnsafeUtil.UNSAFE:Lsun/misc/Unsafe;
     142: aload_0
     143: lload_1
     144: ldc2_w        #31                 // long 2l
     147: ladd
     148: iload         18
     150: i2s
     151: invokevirtual #25                 // Method sun/misc/Unsafe.putShort:(Ljava/lang/Object;JS)V
     154: lload         13
     156: iload         18
     158: i2l
     159: ladd
     160: lstore        13
     162: lload         9
     164: iload         17
     166: i2l
     167: ladd
     168: lstore        9
     170: aload_0
     171: lload         13
     173: lload         15
     175: lload         13
     177: lsub
     178: l2i
     179: aload         4
     181: lload         9
     183: iload         17
     185: aload         8
     187: invokestatic  #13                 // Method compressSingleStream:(Ljava/lang/Object;JILjava/lang/Object;JILio/airlift/compress/zstd/HuffmanCompressionTable;)I
     190: istore        18
     192: iload         18
     194: ifne          199
     197: iconst_0
     198: ireturn
     199: getstatic     #19                 // Field io/airlift/compress/zstd/UnsafeUtil.UNSAFE:Lsun/misc/Unsafe;
     202: aload_0
     203: lload_1
     204: ldc2_w        #31                 // long 2l
     207: ladd
     208: ldc2_w        #31                 // long 2l
     211: ladd
     212: iload         18
     214: i2s
     215: invokevirtual #25                 // Method sun/misc/Unsafe.putShort:(Ljava/lang/Object;JS)V
     218: lload         13
     220: iload         18
     222: i2l
     223: ladd
     224: lstore        13
     226: lload         9
     228: iload         17
     230: i2l
     231: ladd
     232: lstore        9
     234: aload_0
     235: lload         13
     237: lload         15
     239: lload         13
     241: lsub
     242: l2i
     243: aload         4
     245: lload         9
     247: lload         11
     249: lload         9
     251: lsub
     252: l2i
     253: aload         8
     255: invokestatic  #13                 // Method compressSingleStream:(Ljava/lang/Object;JILjava/lang/Object;JILio/airlift/compress/zstd/HuffmanCompressionTable;)I
     258: istore        18
     260: iload         18
     262: ifne          267
     265: iconst_0
     266: ireturn
     267: lload         13
     269: iload         18
     271: i2l
     272: ladd
     273: lstore        13
     275: lload         13
     277: lload_1
     278: lsub
     279: l2i
     280: ireturn

  public static int compressSingleStream(java.lang.Object, long, int, java.lang.Object, long, int, io.airlift.compress.zstd.HuffmanCompressionTable);
    Code:
       0: new           #33                 // class io/airlift/compress/zstd/BitOutputStream
       3: dup
       4: aload_0
       5: lload_1
       6: iload_3
       7: invokespecial #35                 // Method io/airlift/compress/zstd/BitOutputStream."<init>":(Ljava/lang/Object;JI)V
      10: astore        9
      12: lload         5
      14: lstore        10
      16: iload         7
      18: bipush        -4
      20: iand
      21: istore        12
      23: iload         7
      25: iconst_3
      26: iand
      27: tableswitch   { // 0 to 3
                     0: 144
                     1: 112
                     2: 85
                     3: 56
               default: 144
          }
      56: aload         8
      58: aload         9
      60: getstatic     #19                 // Field io/airlift/compress/zstd/UnsafeUtil.UNSAFE:Lsun/misc/Unsafe;
      63: aload         4
      65: lload         10
      67: iload         12
      69: i2l
      70: ladd
      71: ldc2_w        #31                 // long 2l
      74: ladd
      75: invokevirtual #38                 // Method sun/misc/Unsafe.getByte:(Ljava/lang/Object;J)B
      78: sipush        255
      81: iand
      82: invokevirtual #42                 // Method io/airlift/compress/zstd/HuffmanCompressionTable.encodeSymbol:(Lio/airlift/compress/zstd/BitOutputStream;I)V
      85: aload         8
      87: aload         9
      89: getstatic     #19                 // Field io/airlift/compress/zstd/UnsafeUtil.UNSAFE:Lsun/misc/Unsafe;
      92: aload         4
      94: lload         10
      96: iload         12
      98: i2l
      99: ladd
     100: lconst_1
     101: ladd
     102: invokevirtual #38                 // Method sun/misc/Unsafe.getByte:(Ljava/lang/Object;J)B
     105: sipush        255
     108: iand
     109: invokevirtual #42                 // Method io/airlift/compress/zstd/HuffmanCompressionTable.encodeSymbol:(Lio/airlift/compress/zstd/BitOutputStream;I)V
     112: aload         8
     114: aload         9
     116: getstatic     #19                 // Field io/airlift/compress/zstd/UnsafeUtil.UNSAFE:Lsun/misc/Unsafe;
     119: aload         4
     121: lload         10
     123: iload         12
     125: i2l
     126: ladd
     127: lconst_0
     128: ladd
     129: invokevirtual #38                 // Method sun/misc/Unsafe.getByte:(Ljava/lang/Object;J)B
     132: sipush        255
     135: iand
     136: invokevirtual #42                 // Method io/airlift/compress/zstd/HuffmanCompressionTable.encodeSymbol:(Lio/airlift/compress/zstd/BitOutputStream;I)V
     139: aload         9
     141: invokevirtual #48                 // Method io/airlift/compress/zstd/BitOutputStream.flush:()V
     144: iload         12
     146: ifle          274
     149: aload         8
     151: aload         9
     153: getstatic     #19                 // Field io/airlift/compress/zstd/UnsafeUtil.UNSAFE:Lsun/misc/Unsafe;
     156: aload         4
     158: lload         10
     160: iload         12
     162: i2l
     163: ladd
     164: lconst_1
     165: lsub
     166: invokevirtual #38                 // Method sun/misc/Unsafe.getByte:(Ljava/lang/Object;J)B
     169: sipush        255
     172: iand
     173: invokevirtual #42                 // Method io/airlift/compress/zstd/HuffmanCompressionTable.encodeSymbol:(Lio/airlift/compress/zstd/BitOutputStream;I)V
     176: aload         8
     178: aload         9
     180: getstatic     #19                 // Field io/airlift/compress/zstd/UnsafeUtil.UNSAFE:Lsun/misc/Unsafe;
     183: aload         4
     185: lload         10
     187: iload         12
     189: i2l
     190: ladd
     191: ldc2_w        #31                 // long 2l
     194: lsub
     195: invokevirtual #38                 // Method sun/misc/Unsafe.getByte:(Ljava/lang/Object;J)B
     198: sipush        255
     201: iand
     202: invokevirtual #42                 // Method io/airlift/compress/zstd/HuffmanCompressionTable.encodeSymbol:(Lio/airlift/compress/zstd/BitOutputStream;I)V
     205: aload         8
     207: aload         9
     209: getstatic     #19                 // Field io/airlift/compress/zstd/UnsafeUtil.UNSAFE:Lsun/misc/Unsafe;
     212: aload         4
     214: lload         10
     216: iload         12
     218: i2l
     219: ladd
     220: ldc2_w        #51                 // long 3l
     223: lsub
     224: invokevirtual #38                 // Method sun/misc/Unsafe.getByte:(Ljava/lang/Object;J)B
     227: sipush        255
     230: iand
     231: invokevirtual #42                 // Method io/airlift/compress/zstd/HuffmanCompressionTable.encodeSymbol:(Lio/airlift/compress/zstd/BitOutputStream;I)V
     234: aload         8
     236: aload         9
     238: getstatic     #19                 // Field io/airlift/compress/zstd/UnsafeUtil.UNSAFE:Lsun/misc/Unsafe;
     241: aload         4
     243: lload         10
     245: iload         12
     247: i2l
     248: ladd
     249: ldc2_w        #53                 // long 4l
     252: lsub
     253: invokevirtual #38                 // Method sun/misc/Unsafe.getByte:(Ljava/lang/Object;J)B
     256: sipush        255
     259: iand
     260: invokevirtual #42                 // Method io/airlift/compress/zstd/HuffmanCompressionTable.encodeSymbol:(Lio/airlift/compress/zstd/BitOutputStream;I)V
     263: aload         9
     265: invokevirtual #48                 // Method io/airlift/compress/zstd/BitOutputStream.flush:()V
     268: iinc          12, -4
     271: goto          144
     274: aload         9
     276: invokevirtual #55                 // Method io/airlift/compress/zstd/BitOutputStream.close:()I
     279: ireturn
}
