Compiled from "OptionalIdentifiedDefinition.java"
public abstract class org.apache.camel.model.OptionalIdentifiedDefinition<T extends org.apache.camel.model.OptionalIdentifiedDefinition<T>> implements org.apache.camel.NamedNode {
  private transient java.lang.String shortName;

  private java.lang.String id;

  private java.lang.Boolean customId;

  private org.apache.camel.model.DescriptionDefinition description;

  public org.apache.camel.model.OptionalIdentifiedDefinition();
    Code:
       0: aload_0
       1: invokespecial #26                 // Method java/lang/Object."<init>":()V
       4: return

  public java.lang.String getId();
    Code:
       0: aload_0
       1: getfield      #33                 // Field id:Ljava/lang/String;
       4: areturn

  public void setId(java.lang.String);
    Code:
       0: aload_0
       1: aload_1
       2: putfield      #33                 // Field id:Ljava/lang/String;
       5: aload_0
       6: iconst_1
       7: invokestatic  #42                 // Method java/lang/Boolean.valueOf:(Z)Ljava/lang/Boolean;
      10: putfield      #44                 // Field customId:Ljava/lang/Boolean;
      13: return

  public org.apache.camel.model.DescriptionDefinition getDescription();
    Code:
       0: aload_0
       1: getfield      #48                 // Field description:Lorg/apache/camel/model/DescriptionDefinition;
       4: areturn

  public void setDescription(org.apache.camel.model.DescriptionDefinition);
    Code:
       0: aload_0
       1: aload_1
       2: putfield      #48                 // Field description:Lorg/apache/camel/model/DescriptionDefinition;
       5: return

  public java.lang.String getShortName();
    Code:
       0: aload_0
       1: getfield      #54                 // Field shortName:Ljava/lang/String;
       4: ifnonnull     68
       7: aload_0
       8: invokevirtual #58                 // Method java/lang/Object.getClass:()Ljava/lang/Class;
      11: ldc           #60                 // class javax/xml/bind/annotation/XmlRootElement
      13: invokevirtual #66                 // Method java/lang/Class.getAnnotation:(Ljava/lang/Class;)Ljava/lang/annotation/Annotation;
      16: checkcast     #60                 // class javax/xml/bind/annotation/XmlRootElement
      19: astore_1
      20: aload_1
      21: ifnull        34
      24: aload_0
      25: aload_1
      26: invokeinterface #68,  1           // InterfaceMethod javax/xml/bind/annotation/XmlRootElement.name:()Ljava/lang/String;
      31: putfield      #54                 // Field shortName:Ljava/lang/String;
      34: aload_0
      35: getfield      #54                 // Field shortName:Ljava/lang/String;
      38: ifnonnull     68
      41: aload_0
      42: invokevirtual #58                 // Method java/lang/Object.getClass:()Ljava/lang/Class;
      45: ldc           #70                 // class javax/xml/bind/annotation/XmlType
      47: invokevirtual #66                 // Method java/lang/Class.getAnnotation:(Ljava/lang/Class;)Ljava/lang/annotation/Annotation;
      50: checkcast     #70                 // class javax/xml/bind/annotation/XmlType
      53: astore_2
      54: aload_2
      55: ifnull        68
      58: aload_0
      59: aload_2
      60: invokeinterface #71,  1           // InterfaceMethod javax/xml/bind/annotation/XmlType.name:()Ljava/lang/String;
      65: putfield      #54                 // Field shortName:Ljava/lang/String;
      68: aload_0
      69: getfield      #54                 // Field shortName:Ljava/lang/String;
      72: areturn

  public T description(java.lang.String);
    Code:
       0: aload_1
       1: ifnull        30
       4: aload_0
       5: getfield      #48                 // Field description:Lorg/apache/camel/model/DescriptionDefinition;
       8: ifnonnull     22
      11: aload_0
      12: new           #77                 // class org/apache/camel/model/DescriptionDefinition
      15: dup
      16: invokespecial #78                 // Method org/apache/camel/model/DescriptionDefinition."<init>":()V
      19: putfield      #48                 // Field description:Lorg/apache/camel/model/DescriptionDefinition;
      22: aload_0
      23: getfield      #48                 // Field description:Lorg/apache/camel/model/DescriptionDefinition;
      26: aload_1
      27: invokevirtual #81                 // Method org/apache/camel/model/DescriptionDefinition.setText:(Ljava/lang/String;)V
      30: aload_0
      31: areturn

  public T description(java.lang.String, java.lang.String, java.lang.String);
    Code:
       0: aload_1
       1: ifnull        9
       4: aload_0
       5: aload_1
       6: invokevirtual #85                 // Method setId:(Ljava/lang/String;)V
       9: aload_2
      10: ifnull        39
      13: aload_0
      14: getfield      #48                 // Field description:Lorg/apache/camel/model/DescriptionDefinition;
      17: ifnonnull     31
      20: aload_0
      21: new           #77                 // class org/apache/camel/model/DescriptionDefinition
      24: dup
      25: invokespecial #78                 // Method org/apache/camel/model/DescriptionDefinition."<init>":()V
      28: putfield      #48                 // Field description:Lorg/apache/camel/model/DescriptionDefinition;
      31: aload_0
      32: getfield      #48                 // Field description:Lorg/apache/camel/model/DescriptionDefinition;
      35: aload_2
      36: invokevirtual #81                 // Method org/apache/camel/model/DescriptionDefinition.setText:(Ljava/lang/String;)V
      39: aload_3
      40: ifnull        69
      43: aload_0
      44: getfield      #48                 // Field description:Lorg/apache/camel/model/DescriptionDefinition;
      47: ifnonnull     61
      50: aload_0
      51: new           #77                 // class org/apache/camel/model/DescriptionDefinition
      54: dup
      55: invokespecial #78                 // Method org/apache/camel/model/DescriptionDefinition."<init>":()V
      58: putfield      #48                 // Field description:Lorg/apache/camel/model/DescriptionDefinition;
      61: aload_0
      62: getfield      #48                 // Field description:Lorg/apache/camel/model/DescriptionDefinition;
      65: aload_3
      66: invokevirtual #88                 // Method org/apache/camel/model/DescriptionDefinition.setLang:(Ljava/lang/String;)V
      69: aload_0
      70: areturn

  public T id(java.lang.String);
    Code:
       0: aload_0
       1: aload_1
       2: invokevirtual #85                 // Method setId:(Ljava/lang/String;)V
       5: aload_0
       6: areturn

  public java.lang.String idOrCreate(org.apache.camel.spi.NodeIdFactory);
    Code:
       0: aload_0
       1: getfield      #33                 // Field id:Ljava/lang/String;
       4: ifnonnull     18
       7: aload_0
       8: aload_1
       9: aload_0
      10: invokeinterface #97,  2           // InterfaceMethod org/apache/camel/spi/NodeIdFactory.createId:(Lorg/apache/camel/NamedNode;)Ljava/lang/String;
      15: putfield      #33                 // Field id:Ljava/lang/String;
      18: aload_0
      19: invokevirtual #99                 // Method getId:()Ljava/lang/String;
      22: areturn

  public java.lang.Boolean getCustomId();
    Code:
       0: aload_0
       1: getfield      #44                 // Field customId:Ljava/lang/Boolean;
       4: areturn

  public void setCustomId(java.lang.Boolean);
    Code:
       0: aload_0
       1: aload_1
       2: putfield      #44                 // Field customId:Ljava/lang/Boolean;
       5: return

  public boolean hasCustomIdAssigned();
    Code:
       0: aload_0
       1: getfield      #44                 // Field customId:Ljava/lang/Boolean;
       4: ifnull        21
       7: aload_0
       8: getfield      #44                 // Field customId:Ljava/lang/Boolean;
      11: invokevirtual #110                // Method java/lang/Boolean.booleanValue:()Z
      14: ifeq          21
      17: iconst_1
      18: goto          22
      21: iconst_0
      22: ireturn

  public java.lang.String getDescriptionText();
    Code:
       0: aload_0
       1: getfield      #48                 // Field description:Lorg/apache/camel/model/DescriptionDefinition;
       4: ifnull        17
       7: aload_0
       8: getfield      #48                 // Field description:Lorg/apache/camel/model/DescriptionDefinition;
      11: invokevirtual #114                // Method org/apache/camel/model/DescriptionDefinition.getText:()Ljava/lang/String;
      14: goto          18
      17: aconst_null
      18: areturn
}
