Compiled from "SendDefinition.java"
public abstract class org.apache.camel.model.SendDefinition<Type extends org.apache.camel.model.ProcessorDefinition<Type>> extends org.apache.camel.model.NoOutputDefinition<Type> implements org.apache.camel.model.EndpointRequiredDefinition {
  protected java.lang.String uri;

  protected java.lang.String ref;

  protected org.apache.camel.Endpoint endpoint;

  public org.apache.camel.model.SendDefinition();
    Code:
       0: aload_0
       1: invokespecial #27                 // Method org/apache/camel/model/NoOutputDefinition."<init>":()V
       4: return

  public org.apache.camel.model.SendDefinition(java.lang.String);
    Code:
       0: aload_0
       1: invokespecial #27                 // Method org/apache/camel/model/NoOutputDefinition."<init>":()V
       4: aload_0
       5: aload_1
       6: putfield      #33                 // Field uri:Ljava/lang/String;
       9: return

  public org.apache.camel.Processor createProcessor(org.apache.camel.spi.RouteContext) throws java.lang.Exception;
    Code:
       0: aload_0
       1: aload_1
       2: invokevirtual #41                 // Method resolveEndpoint:(Lorg/apache/camel/spi/RouteContext;)Lorg/apache/camel/Endpoint;
       5: astore_2
       6: new           #43                 // class org/apache/camel/processor/SendProcessor
       9: dup
      10: aload_2
      11: aload_0
      12: invokevirtual #47                 // Method getPattern:()Lorg/apache/camel/ExchangePattern;
      15: invokespecial #50                 // Method org/apache/camel/processor/SendProcessor."<init>":(Lorg/apache/camel/Endpoint;Lorg/apache/camel/ExchangePattern;)V
      18: areturn

  public org.apache.camel.Endpoint resolveEndpoint(org.apache.camel.spi.RouteContext);
    Code:
       0: aload_0
       1: getfield      #54                 // Field endpoint:Lorg/apache/camel/Endpoint;
       4: ifnonnull     22
       7: aload_1
       8: aload_0
       9: invokevirtual #58                 // Method getUri:()Ljava/lang/String;
      12: aload_0
      13: invokevirtual #61                 // Method getRef:()Ljava/lang/String;
      16: invokeinterface #66,  3           // InterfaceMethod org/apache/camel/spi/RouteContext.resolveEndpoint:(Ljava/lang/String;Ljava/lang/String;)Lorg/apache/camel/Endpoint;
      21: areturn
      22: aload_0
      23: getfield      #54                 // Field endpoint:Lorg/apache/camel/Endpoint;
      26: areturn

  public java.lang.String getEndpointUri();
    Code:
       0: aload_0
       1: getfield      #33                 // Field uri:Ljava/lang/String;
       4: ifnull        12
       7: aload_0
       8: getfield      #33                 // Field uri:Ljava/lang/String;
      11: areturn
      12: aconst_null
      13: areturn

  public java.lang.String getRef();
    Code:
       0: aload_0
       1: getfield      #70                 // Field ref:Ljava/lang/String;
       4: areturn

  public void setRef(java.lang.String);
    Code:
       0: aload_0
       1: aload_1
       2: putfield      #70                 // Field ref:Ljava/lang/String;
       5: return

  public java.lang.String getUri();
    Code:
       0: aload_0
       1: getfield      #33                 // Field uri:Ljava/lang/String;
       4: areturn

  public void setUri(java.lang.String);
    Code:
       0: aload_0
       1: aload_1
       2: putfield      #33                 // Field uri:Ljava/lang/String;
       5: return

  public org.apache.camel.Endpoint getEndpoint();
    Code:
       0: aload_0
       1: getfield      #54                 // Field endpoint:Lorg/apache/camel/Endpoint;
       4: areturn

  public void setEndpoint(org.apache.camel.Endpoint);
    Code:
       0: aload_0
       1: aload_1
       2: putfield      #54                 // Field endpoint:Lorg/apache/camel/Endpoint;
       5: aload_0
       6: aconst_null
       7: putfield      #33                 // Field uri:Ljava/lang/String;
      10: aload_1
      11: ifnull        24
      14: aload_0
      15: aload_1
      16: invokeinterface #80,  1           // InterfaceMethod org/apache/camel/Endpoint.getEndpointUri:()Ljava/lang/String;
      21: putfield      #33                 // Field uri:Ljava/lang/String;
      24: return

  public org.apache.camel.ExchangePattern getPattern();
    Code:
       0: aconst_null
       1: areturn

  public java.lang.String getUriOrRef();
    Code:
       0: aload_0
       1: invokevirtual #58                 // Method getUri:()Ljava/lang/String;
       4: astore_1
       5: aload_1
       6: invokestatic  #87                 // Method org/apache/camel/util/ObjectHelper.isNotEmpty:(Ljava/lang/Object;)Z
       9: ifeq          14
      12: aload_1
      13: areturn
      14: aload_0
      15: getfield      #54                 // Field endpoint:Lorg/apache/camel/Endpoint;
      18: ifnull        31
      21: aload_0
      22: getfield      #54                 // Field endpoint:Lorg/apache/camel/Endpoint;
      25: invokeinterface #80,  1           // InterfaceMethod org/apache/camel/Endpoint.getEndpointUri:()Ljava/lang/String;
      30: areturn
      31: aload_0
      32: invokevirtual #61                 // Method getRef:()Ljava/lang/String;
      35: areturn

  public java.lang.String getLabel();
    Code:
       0: aload_0
       1: invokevirtual #58                 // Method getUri:()Ljava/lang/String;
       4: aload_0
       5: invokevirtual #61                 // Method getRef:()Ljava/lang/String;
       8: aload_0
       9: invokevirtual #92                 // Method getEndpoint:()Lorg/apache/camel/Endpoint;
      12: invokestatic  #98                 // Method org/apache/camel/model/FromDefinition.description:(Ljava/lang/String;Ljava/lang/String;Lorg/apache/camel/Endpoint;)Ljava/lang/String;
      15: areturn
}
