Compiled from "SAXResultContentHandler.java"
public class org.apache.axiom.om.impl.common.SAXResultContentHandler extends org.apache.axiom.om.impl.common.OMContentHandler {
  private final org.apache.axiom.om.OMContainer root;

  private final org.apache.axiom.om.OMFactory factory;

  public org.apache.axiom.om.impl.common.SAXResultContentHandler(org.apache.axiom.om.OMContainer);
    Code:
       0: aload_0
       1: iconst_1
       2: invokespecial #13                 // Method org/apache/axiom/om/impl/common/OMContentHandler."<init>":(Z)V
       5: aload_0
       6: aload_1
       7: putfield      #16                 // Field root:Lorg/apache/axiom/om/OMContainer;
      10: aload_0
      11: aload_1
      12: invokeinterface #18,  1           // InterfaceMethod org/apache/axiom/om/OMContainer.getOMFactory:()Lorg/apache/axiom/om/OMFactory;
      17: putfield      #24                 // Field factory:Lorg/apache/axiom/om/OMFactory;
      20: return

  protected org.apache.axiom.om.OMContainer doStartDocument();
    Code:
       0: aload_0
       1: getfield      #16                 // Field root:Lorg/apache/axiom/om/OMContainer;
       4: areturn

  protected void doEndDocument();
    Code:
       0: return

  protected void createOMDocType(org.apache.axiom.om.OMContainer, java.lang.String, java.lang.String, java.lang.String, java.lang.String);
    Code:
       0: aload_1
       1: instanceof    #36                 // class org/apache/axiom/om/OMDocument
       4: ifeq          24
       7: aload_0
       8: getfield      #24                 // Field factory:Lorg/apache/axiom/om/OMFactory;
      11: aload_1
      12: aload_2
      13: aload_3
      14: aload         4
      16: aload         5
      18: invokeinterface #38,  6           // InterfaceMethod org/apache/axiom/om/OMFactory.createOMDocType:(Lorg/apache/axiom/om/OMContainer;Ljava/lang/String;Ljava/lang/String;Ljava/lang/String;Ljava/lang/String;)Lorg/apache/axiom/om/OMDocType;
      23: pop
      24: return

  protected org.apache.axiom.om.OMElement createOMElement(org.apache.axiom.om.OMContainer, java.lang.String, java.lang.String, java.lang.String, java.lang.String[], int);
    Code:
       0: aload_0
       1: getfield      #24                 // Field factory:Lorg/apache/axiom/om/OMFactory;
       4: aload_2
       5: aload_0
       6: getfield      #24                 // Field factory:Lorg/apache/axiom/om/OMFactory;
       9: aload_3
      10: aload         4
      12: invokeinterface #51,  3           // InterfaceMethod org/apache/axiom/om/OMFactory.createOMNamespace:(Ljava/lang/String;Ljava/lang/String;)Lorg/apache/axiom/om/OMNamespace;
      17: aload_1
      18: invokeinterface #55,  4           // InterfaceMethod org/apache/axiom/om/OMFactory.createOMElement:(Ljava/lang/String;Lorg/apache/axiom/om/OMNamespace;Lorg/apache/axiom/om/OMContainer;)Lorg/apache/axiom/om/OMElement;
      23: astore        7
      25: iconst_0
      26: istore        8
      28: goto          87
      31: aload         5
      33: iconst_2
      34: iload         8
      36: imul
      37: aaload
      38: astore        9
      40: aload         5
      42: iconst_2
      43: iload         8
      45: imul
      46: iconst_1
      47: iadd
      48: aaload
      49: astore        10
      51: aload         9
      53: invokevirtual #58                 // Method java/lang/String.length:()I
      56: ifne          72
      59: aload         7
      61: aload         10
      63: invokeinterface #64,  2           // InterfaceMethod org/apache/axiom/om/OMElement.declareDefaultNamespace:(Ljava/lang/String;)Lorg/apache/axiom/om/OMNamespace;
      68: pop
      69: goto          84
      72: aload         7
      74: aload         10
      76: aload         9
      78: invokeinterface #70,  3           // InterfaceMethod org/apache/axiom/om/OMElement.declareNamespace:(Ljava/lang/String;Ljava/lang/String;)Lorg/apache/axiom/om/OMNamespace;
      83: pop
      84: iinc          8, 1
      87: iload         8
      89: iload         6
      91: if_icmplt     31
      94: aload         7
      96: areturn

  protected void completed(org.apache.axiom.om.OMElement);
    Code:
       0: return

  protected void createOMText(org.apache.axiom.om.OMContainer, java.lang.String, int);
    Code:
       0: aload_0
       1: getfield      #24                 // Field factory:Lorg/apache/axiom/om/OMFactory;
       4: aload_1
       5: aload_2
       6: iload_3
       7: invokeinterface #89,  4           // InterfaceMethod org/apache/axiom/om/OMFactory.createOMText:(Lorg/apache/axiom/om/OMContainer;Ljava/lang/String;I)Lorg/apache/axiom/om/OMText;
      12: pop
      13: return

  protected void createOMProcessingInstruction(org.apache.axiom.om.OMContainer, java.lang.String, java.lang.String);
    Code:
       0: aload_0
       1: getfield      #24                 // Field factory:Lorg/apache/axiom/om/OMFactory;
       4: aload_1
       5: aload_2
       6: aload_3
       7: invokeinterface #96,  4           // InterfaceMethod org/apache/axiom/om/OMFactory.createOMProcessingInstruction:(Lorg/apache/axiom/om/OMContainer;Ljava/lang/String;Ljava/lang/String;)Lorg/apache/axiom/om/OMProcessingInstruction;
      12: pop
      13: return

  protected void createOMComment(org.apache.axiom.om.OMContainer, java.lang.String);
    Code:
       0: aload_0
       1: getfield      #24                 // Field factory:Lorg/apache/axiom/om/OMFactory;
       4: aload_1
       5: aload_2
       6: invokeinterface #103,  3          // InterfaceMethod org/apache/axiom/om/OMFactory.createOMComment:(Lorg/apache/axiom/om/OMContainer;Ljava/lang/String;)Lorg/apache/axiom/om/OMComment;
      11: pop
      12: return

  protected void createOMEntityReference(org.apache.axiom.om.OMContainer, java.lang.String, java.lang.String);
    Code:
       0: aload_3
       1: ifnonnull     19
       4: aload_0
       5: getfield      #24                 // Field factory:Lorg/apache/axiom/om/OMFactory;
       8: aload_1
       9: aload_2
      10: invokeinterface #108,  3          // InterfaceMethod org/apache/axiom/om/OMFactory.createOMEntityReference:(Lorg/apache/axiom/om/OMContainer;Ljava/lang/String;)Lorg/apache/axiom/om/OMEntityReference;
      15: pop
      16: goto          27
      19: new           #111                // class java/lang/UnsupportedOperationException
      22: dup
      23: invokespecial #113                // Method java/lang/UnsupportedOperationException."<init>":()V
      26: athrow
      27: return
}
