Compiled from "WhereSQLUtil.java"
public class cloud.agileframework.elasticsearch.proxy.common.WhereSQLUtil {
  public cloud.agileframework.elasticsearch.proxy.common.WhereSQLUtil();
    Code:
       0: aload_0
       1: invokespecial #1                  // Method java/lang/Object."<init>":()V
       4: return

  public static com.alibaba.fastjson.JSONObject to(com.alibaba.druid.sql.ast.SQLExpr) throws java.sql.SQLFeatureNotSupportedException;
    Code:
       0: aload_0
       1: ifnonnull     6
       4: aconst_null
       5: areturn
       6: aload_0
       7: instanceof    #2                  // class com/alibaba/druid/sql/ast/expr/SQLBinaryOpExpr
      10: ifeq          21
      13: aload_0
      14: checkcast     #2                  // class com/alibaba/druid/sql/ast/expr/SQLBinaryOpExpr
      17: invokestatic  #3                  // Method toSQLBinaryOpExpr:(Lcom/alibaba/druid/sql/ast/expr/SQLBinaryOpExpr;)Lcom/alibaba/fastjson/JSONObject;
      20: areturn
      21: aload_0
      22: instanceof    #4                  // class com/alibaba/druid/sql/ast/expr/SQLInListExpr
      25: ifeq          36
      28: aload_0
      29: checkcast     #4                  // class com/alibaba/druid/sql/ast/expr/SQLInListExpr
      32: invokestatic  #5                  // Method toSQLInListExpr:(Lcom/alibaba/druid/sql/ast/expr/SQLInListExpr;)Lcom/alibaba/fastjson/JSONObject;
      35: areturn
      36: aload_0
      37: instanceof    #6                  // class com/alibaba/druid/sql/ast/expr/SQLBetweenExpr
      40: ifeq          51
      43: aload_0
      44: checkcast     #6                  // class com/alibaba/druid/sql/ast/expr/SQLBetweenExpr
      47: invokestatic  #7                  // Method toSQLBetweenExpr:(Lcom/alibaba/druid/sql/ast/expr/SQLBetweenExpr;)Lcom/alibaba/fastjson/JSONObject;
      50: areturn
      51: new           #8                  // class java/sql/SQLFeatureNotSupportedException
      54: dup
      55: aload_0
      56: invokestatic  #9                  // Method com/alibaba/druid/sql/SQLUtils.toSQLString:(Lcom/alibaba/druid/sql/ast/SQLObject;)Ljava/lang/String;
      59: invokespecial #10                 // Method java/sql/SQLFeatureNotSupportedException."<init>":(Ljava/lang/String;)V
      62: athrow

  public static com.alibaba.fastjson.JSONObject toSQLBinaryOpExpr(com.alibaba.druid.sql.ast.expr.SQLBinaryOpExpr) throws java.sql.SQLFeatureNotSupportedException;
    Code:
       0: new           #11                 // class com/alibaba/fastjson/JSONObject
       3: dup
       4: invokespecial #12                 // Method com/alibaba/fastjson/JSONObject."<init>":()V
       7: astore_1
       8: getstatic     #13                 // Field com/alibaba/druid/sql/ast/expr/SQLBinaryOperator.BooleanAnd:Lcom/alibaba/druid/sql/ast/expr/SQLBinaryOperator;
      11: aload_0
      12: invokevirtual #14                 // Method com/alibaba/druid/sql/ast/expr/SQLBinaryOpExpr.getOperator:()Lcom/alibaba/druid/sql/ast/expr/SQLBinaryOperator;
      15: if_acmpne     77
      18: new           #11                 // class com/alibaba/fastjson/JSONObject
      21: dup
      22: invokespecial #12                 // Method com/alibaba/fastjson/JSONObject."<init>":()V
      25: astore_2
      26: new           #15                 // class com/alibaba/fastjson/JSONArray
      29: dup
      30: invokespecial #16                 // Method com/alibaba/fastjson/JSONArray."<init>":()V
      33: astore_3
      34: aload_1
      35: ldc           #17                 // String bool
      37: aload_2
      38: invokevirtual #18                 // Method com/alibaba/fastjson/JSONObject.put:(Ljava/lang/String;Ljava/lang/Object;)Ljava/lang/Object;
      41: pop
      42: aload_3
      43: aload_0
      44: invokevirtual #19                 // Method com/alibaba/druid/sql/ast/expr/SQLBinaryOpExpr.getLeft:()Lcom/alibaba/druid/sql/ast/SQLExpr;
      47: invokestatic  #20                 // Method to:(Lcom/alibaba/druid/sql/ast/SQLExpr;)Lcom/alibaba/fastjson/JSONObject;
      50: invokevirtual #21                 // Method com/alibaba/fastjson/JSONArray.add:(Ljava/lang/Object;)Z
      53: pop
      54: aload_3
      55: aload_0
      56: invokevirtual #22                 // Method com/alibaba/druid/sql/ast/expr/SQLBinaryOpExpr.getRight:()Lcom/alibaba/druid/sql/ast/SQLExpr;
      59: invokestatic  #20                 // Method to:(Lcom/alibaba/druid/sql/ast/SQLExpr;)Lcom/alibaba/fastjson/JSONObject;
      62: invokevirtual #21                 // Method com/alibaba/fastjson/JSONArray.add:(Ljava/lang/Object;)Z
      65: pop
      66: aload_2
      67: ldc           #23                 // String must
      69: aload_3
      70: invokevirtual #18                 // Method com/alibaba/fastjson/JSONObject.put:(Ljava/lang/String;Ljava/lang/Object;)Ljava/lang/Object;
      73: pop
      74: goto          398
      77: getstatic     #24                 // Field com/alibaba/druid/sql/ast/expr/SQLBinaryOperator.BooleanOr:Lcom/alibaba/druid/sql/ast/expr/SQLBinaryOperator;
      80: aload_0
      81: invokevirtual #14                 // Method com/alibaba/druid/sql/ast/expr/SQLBinaryOpExpr.getOperator:()Lcom/alibaba/druid/sql/ast/expr/SQLBinaryOperator;
      84: if_acmpne     146
      87: new           #11                 // class com/alibaba/fastjson/JSONObject
      90: dup
      91: invokespecial #12                 // Method com/alibaba/fastjson/JSONObject."<init>":()V
      94: astore_2
      95: new           #15                 // class com/alibaba/fastjson/JSONArray
      98: dup
      99: invokespecial #16                 // Method com/alibaba/fastjson/JSONArray."<init>":()V
     102: astore_3
     103: aload_1
     104: ldc           #17                 // String bool
     106: aload_2
     107: invokevirtual #18                 // Method com/alibaba/fastjson/JSONObject.put:(Ljava/lang/String;Ljava/lang/Object;)Ljava/lang/Object;
     110: pop
     111: aload_3
     112: aload_0
     113: invokevirtual #19                 // Method com/alibaba/druid/sql/ast/expr/SQLBinaryOpExpr.getLeft:()Lcom/alibaba/druid/sql/ast/SQLExpr;
     116: invokestatic  #20                 // Method to:(Lcom/alibaba/druid/sql/ast/SQLExpr;)Lcom/alibaba/fastjson/JSONObject;
     119: invokevirtual #21                 // Method com/alibaba/fastjson/JSONArray.add:(Ljava/lang/Object;)Z
     122: pop
     123: aload_3
     124: aload_0
     125: invokevirtual #22                 // Method com/alibaba/druid/sql/ast/expr/SQLBinaryOpExpr.getRight:()Lcom/alibaba/druid/sql/ast/SQLExpr;
     128: invokestatic  #20                 // Method to:(Lcom/alibaba/druid/sql/ast/SQLExpr;)Lcom/alibaba/fastjson/JSONObject;
     131: invokevirtual #21                 // Method com/alibaba/fastjson/JSONArray.add:(Ljava/lang/Object;)Z
     134: pop
     135: aload_2
     136: ldc           #25                 // String should
     138: aload_3
     139: invokevirtual #18                 // Method com/alibaba/fastjson/JSONObject.put:(Ljava/lang/String;Ljava/lang/Object;)Ljava/lang/Object;
     142: pop
     143: goto          398
     146: getstatic     #26                 // Field com/alibaba/druid/sql/ast/expr/SQLBinaryOperator.NotEqual:Lcom/alibaba/druid/sql/ast/expr/SQLBinaryOperator;
     149: aload_0
     150: invokevirtual #14                 // Method com/alibaba/druid/sql/ast/expr/SQLBinaryOpExpr.getOperator:()Lcom/alibaba/druid/sql/ast/expr/SQLBinaryOperator;
     153: if_acmpeq     166
     156: getstatic     #27                 // Field com/alibaba/druid/sql/ast/expr/SQLBinaryOperator.LessThanOrGreater:Lcom/alibaba/druid/sql/ast/expr/SQLBinaryOperator;
     159: aload_0
     160: invokevirtual #14                 // Method com/alibaba/druid/sql/ast/expr/SQLBinaryOpExpr.getOperator:()Lcom/alibaba/druid/sql/ast/expr/SQLBinaryOperator;
     163: if_acmpne     225
     166: new           #11                 // class com/alibaba/fastjson/JSONObject
     169: dup
     170: invokespecial #12                 // Method com/alibaba/fastjson/JSONObject."<init>":()V
     173: astore_2
     174: new           #15                 // class com/alibaba/fastjson/JSONArray
     177: dup
     178: invokespecial #16                 // Method com/alibaba/fastjson/JSONArray."<init>":()V
     181: astore_3
     182: aload_1
     183: ldc           #17                 // String bool
     185: aload_2
     186: invokevirtual #18                 // Method com/alibaba/fastjson/JSONObject.put:(Ljava/lang/String;Ljava/lang/Object;)Ljava/lang/Object;
     189: pop
     190: aload_3
     191: aload_0
     192: invokevirtual #19                 // Method com/alibaba/druid/sql/ast/expr/SQLBinaryOpExpr.getLeft:()Lcom/alibaba/druid/sql/ast/SQLExpr;
     195: invokestatic  #20                 // Method to:(Lcom/alibaba/druid/sql/ast/SQLExpr;)Lcom/alibaba/fastjson/JSONObject;
     198: invokevirtual #21                 // Method com/alibaba/fastjson/JSONArray.add:(Ljava/lang/Object;)Z
     201: pop
     202: aload_3
     203: aload_0
     204: invokevirtual #22                 // Method com/alibaba/druid/sql/ast/expr/SQLBinaryOpExpr.getRight:()Lcom/alibaba/druid/sql/ast/SQLExpr;
     207: invokestatic  #20                 // Method to:(Lcom/alibaba/druid/sql/ast/SQLExpr;)Lcom/alibaba/fastjson/JSONObject;
     210: invokevirtual #21                 // Method com/alibaba/fastjson/JSONArray.add:(Ljava/lang/Object;)Z
     213: pop
     214: aload_2
     215: ldc           #28                 // String must_not
     217: aload_3
     218: invokevirtual #18                 // Method com/alibaba/fastjson/JSONObject.put:(Ljava/lang/String;Ljava/lang/Object;)Ljava/lang/Object;
     221: pop
     222: goto          398
     225: aload_0
     226: invokevirtual #19                 // Method com/alibaba/druid/sql/ast/expr/SQLBinaryOpExpr.getLeft:()Lcom/alibaba/druid/sql/ast/SQLExpr;
     229: invokestatic  #9                  // Method com/alibaba/druid/sql/SQLUtils.toSQLString:(Lcom/alibaba/druid/sql/ast/SQLObject;)Ljava/lang/String;
     232: astore_2
     233: aload_0
     234: invokevirtual #22                 // Method com/alibaba/druid/sql/ast/expr/SQLBinaryOpExpr.getRight:()Lcom/alibaba/druid/sql/ast/SQLExpr;
     237: invokestatic  #9                  // Method com/alibaba/druid/sql/SQLUtils.toSQLString:(Lcom/alibaba/druid/sql/ast/SQLObject;)Ljava/lang/String;
     240: astore_3
     241: getstatic     #29                 // Field cloud/agileframework/elasticsearch/proxy/common/WhereSQLUtil$1.$SwitchMap$com$alibaba$druid$sql$ast$expr$SQLBinaryOperator:[I
     244: aload_0
     245: invokevirtual #14                 // Method com/alibaba/druid/sql/ast/expr/SQLBinaryOpExpr.getOperator:()Lcom/alibaba/druid/sql/ast/expr/SQLBinaryOperator;
     248: invokevirtual #30                 // Method com/alibaba/druid/sql/ast/expr/SQLBinaryOperator.ordinal:()I
     251: iaload
     252: tableswitch   { // 1 to 8
                     1: 300
                     2: 307
                     3: 314
                     4: 321
                     5: 328
                     6: 335
                     7: 351
                     8: 358
               default: 365
          }
     300: ldc           #31                 // String {\n    \"term\": {\n        \"$_Key_\": {\n            \"value\": $_Value_\n        }\n    }\n}
     302: astore        4
     304: goto          380
     307: ldc           #32                 // String {\n    \"range\": {\n        \"$_Key_\": {\n            \"from\": $_Value_\n        }\n    }\n}
     309: astore        4
     311: goto          380
     314: ldc           #33                 // String {\n    \"range\": {\n        \"$_Key_\": {\n            \"to\": $_Value_\n        }\n    }\n}
     316: astore        4
     318: goto          380
     321: ldc           #34                 // String {\n    \"range\": {\n        \"$_Key_\": {\n            \"gt\": $_Value_,\n        }\n    }\n}
     323: astore        4
     325: goto          380
     328: ldc           #35                 // String {\n    \"range\": {\n        \"$_Key_\": {\n            \"lt\": $_Value_,\n        }\n    }\n}
     330: astore        4
     332: goto          380
     335: aload_3
     336: ldc           #36                 // String %
     338: ldc           #37                 // String *
     340: invokevirtual #38                 // Method java/lang/String.replace:(Ljava/lang/CharSequence;Ljava/lang/CharSequence;)Ljava/lang/String;
     343: astore_3
     344: ldc           #39                 // String {\n    \"wildcard\": {\n        \"$_Key_.keyword\": $_Value_\n    }\n}
     346: astore        4
     348: goto          380
     351: ldc           #40                 // String {\n        \"bool\": {\n            \"must\": {\n                \"exists\": {\n                    \"field\": \"$_Key_\"\n                }\n            }\n        }\n    }
     353: astore        4
     355: goto          380
     358: ldc           #41                 // String {\n        \"bool\": {\n            \"must_not\": {\n                \"exists\": {\n                    \"field\": \"$_Key_\"\n                }\n            }\n        }\n    }
     360: astore        4
     362: goto          380
     365: new           #8                  // class java/sql/SQLFeatureNotSupportedException
     368: dup
     369: aload_0
     370: invokevirtual #14                 // Method com/alibaba/druid/sql/ast/expr/SQLBinaryOpExpr.getOperator:()Lcom/alibaba/druid/sql/ast/expr/SQLBinaryOperator;
     373: getfield      #42                 // Field com/alibaba/druid/sql/ast/expr/SQLBinaryOperator.name:Ljava/lang/String;
     376: invokespecial #10                 // Method java/sql/SQLFeatureNotSupportedException."<init>":(Ljava/lang/String;)V
     379: athrow
     380: aload         4
     382: ldc           #43                 // String $_Key_
     384: aload_2
     385: invokevirtual #38                 // Method java/lang/String.replace:(Ljava/lang/CharSequence;Ljava/lang/CharSequence;)Ljava/lang/String;
     388: ldc           #44                 // String $_Value_
     390: aload_3
     391: invokevirtual #38                 // Method java/lang/String.replace:(Ljava/lang/CharSequence;Ljava/lang/CharSequence;)Ljava/lang/String;
     394: invokestatic  #45                 // Method com/alibaba/fastjson/JSON.parseObject:(Ljava/lang/String;)Lcom/alibaba/fastjson/JSONObject;
     397: areturn
     398: aload_1
     399: areturn

  private static com.alibaba.fastjson.JSONObject toSQLBetweenExpr(com.alibaba.druid.sql.ast.expr.SQLBetweenExpr);
    Code:
       0: aload_0
       1: invokevirtual #46                 // Method com/alibaba/druid/sql/ast/expr/SQLBetweenExpr.getTestExpr:()Lcom/alibaba/druid/sql/ast/SQLExpr;
       4: invokestatic  #9                  // Method com/alibaba/druid/sql/SQLUtils.toSQLString:(Lcom/alibaba/druid/sql/ast/SQLObject;)Ljava/lang/String;
       7: astore_1
       8: aload_0
       9: invokevirtual #47                 // Method com/alibaba/druid/sql/ast/expr/SQLBetweenExpr.getBeginExpr:()Lcom/alibaba/druid/sql/ast/SQLExpr;
      12: invokestatic  #9                  // Method com/alibaba/druid/sql/SQLUtils.toSQLString:(Lcom/alibaba/druid/sql/ast/SQLObject;)Ljava/lang/String;
      15: astore_2
      16: aload_0
      17: invokevirtual #48                 // Method com/alibaba/druid/sql/ast/expr/SQLBetweenExpr.getEndExpr:()Lcom/alibaba/druid/sql/ast/SQLExpr;
      20: invokestatic  #9                  // Method com/alibaba/druid/sql/SQLUtils.toSQLString:(Lcom/alibaba/druid/sql/ast/SQLObject;)Ljava/lang/String;
      23: astore_3
      24: ldc           #49                 // String {\n    \"range\": {\n        \"$_Key_\": {\n            \"from\": $_Begin_,\n            \"to\": $_End_,\n        }\n    }\n}
      26: astore        4
      28: aload         4
      30: ldc           #43                 // String $_Key_
      32: aload_1
      33: invokevirtual #38                 // Method java/lang/String.replace:(Ljava/lang/CharSequence;Ljava/lang/CharSequence;)Ljava/lang/String;
      36: ldc           #50                 // String $_Begin_
      38: aload_2
      39: invokevirtual #38                 // Method java/lang/String.replace:(Ljava/lang/CharSequence;Ljava/lang/CharSequence;)Ljava/lang/String;
      42: ldc           #51                 // String $_End_
      44: aload_3
      45: invokevirtual #38                 // Method java/lang/String.replace:(Ljava/lang/CharSequence;Ljava/lang/CharSequence;)Ljava/lang/String;
      48: invokestatic  #45                 // Method com/alibaba/fastjson/JSON.parseObject:(Ljava/lang/String;)Lcom/alibaba/fastjson/JSONObject;
      51: areturn

  public static com.alibaba.fastjson.JSONObject toSQLInListExpr(com.alibaba.druid.sql.ast.expr.SQLInListExpr);
    Code:
       0: aload_0
       1: invokevirtual #52                 // Method com/alibaba/druid/sql/ast/expr/SQLInListExpr.getExpr:()Lcom/alibaba/druid/sql/ast/SQLExpr;
       4: invokestatic  #9                  // Method com/alibaba/druid/sql/SQLUtils.toSQLString:(Lcom/alibaba/druid/sql/ast/SQLObject;)Ljava/lang/String;
       7: astore_1
       8: aload_0
       9: invokevirtual #53                 // Method com/alibaba/druid/sql/ast/expr/SQLInListExpr.getTargetList:()Ljava/util/List;
      12: invokeinterface #54,  1           // InterfaceMethod java/util/List.stream:()Ljava/util/stream/Stream;
      17: invokedynamic #55,  0             // InvokeDynamic #0:apply:()Ljava/util/function/Function;
      22: invokeinterface #56,  2           // InterfaceMethod java/util/stream/Stream.map:(Ljava/util/function/Function;)Ljava/util/stream/Stream;
      27: ldc           #57                 // String ,
      29: invokestatic  #58                 // Method java/util/stream/Collectors.joining:(Ljava/lang/CharSequence;)Ljava/util/stream/Collector;
      32: invokeinterface #59,  2           // InterfaceMethod java/util/stream/Stream.collect:(Ljava/util/stream/Collector;)Ljava/lang/Object;
      37: checkcast     #60                 // class java/lang/String
      40: astore_2
      41: ldc           #61                 // String {\n    \"terms\": {\n        \"$_Key_\": [$_Value_]\n    }\n}
      43: astore_3
      44: aload_3
      45: ldc           #43                 // String $_Key_
      47: aload_1
      48: invokevirtual #38                 // Method java/lang/String.replace:(Ljava/lang/CharSequence;Ljava/lang/CharSequence;)Ljava/lang/String;
      51: ldc           #44                 // String $_Value_
      53: aload_2
      54: invokevirtual #38                 // Method java/lang/String.replace:(Ljava/lang/CharSequence;Ljava/lang/CharSequence;)Ljava/lang/String;
      57: invokestatic  #45                 // Method com/alibaba/fastjson/JSON.parseObject:(Ljava/lang/String;)Lcom/alibaba/fastjson/JSONObject;
      60: areturn
}
