Compiled from "ApplicationMasterProtocolPBClientImpl.java"
public class org.apache.hadoop.yarn.api.impl.pb.client.ApplicationMasterProtocolPBClientImpl implements org.apache.hadoop.yarn.api.ApplicationMasterProtocol,java.io.Closeable {
  private org.apache.hadoop.yarn.api.ApplicationMasterProtocolPB proxy;

  public org.apache.hadoop.yarn.api.impl.pb.client.ApplicationMasterProtocolPBClientImpl(long, java.net.InetSocketAddress, org.apache.hadoop.conf.Configuration) throws java.io.IOException;
    Code:
       0: aload_0
       1: invokespecial #1                  // Method java/lang/Object."<init>":()V
       4: aload         4
       6: ldc           #2                  // class org/apache/hadoop/yarn/api/ApplicationMasterProtocolPB
       8: ldc           #3                  // class org/apache/hadoop/ipc/ProtobufRpcEngine
      10: invokestatic  #4                  // Method org/apache/hadoop/ipc/RPC.setProtocolEngine:(Lorg/apache/hadoop/conf/Configuration;Ljava/lang/Class;Ljava/lang/Class;)V
      13: aload_0
      14: ldc           #2                  // class org/apache/hadoop/yarn/api/ApplicationMasterProtocolPB
      16: lload_1
      17: aload_3
      18: aload         4
      20: invokestatic  #5                  // Method org/apache/hadoop/ipc/RPC.getProxy:(Ljava/lang/Class;JLjava/net/InetSocketAddress;Lorg/apache/hadoop/conf/Configuration;)Ljava/lang/Object;
      23: checkcast     #2                  // class org/apache/hadoop/yarn/api/ApplicationMasterProtocolPB
      26: putfield      #6                  // Field proxy:Lorg/apache/hadoop/yarn/api/ApplicationMasterProtocolPB;
      29: return

  public void close();
    Code:
       0: aload_0
       1: getfield      #6                  // Field proxy:Lorg/apache/hadoop/yarn/api/ApplicationMasterProtocolPB;
       4: ifnull        14
       7: aload_0
       8: getfield      #6                  // Field proxy:Lorg/apache/hadoop/yarn/api/ApplicationMasterProtocolPB;
      11: invokestatic  #7                  // Method org/apache/hadoop/ipc/RPC.stopProxy:(Ljava/lang/Object;)V
      14: return

  public org.apache.hadoop.yarn.api.protocolrecords.AllocateResponse allocate(org.apache.hadoop.yarn.api.protocolrecords.AllocateRequest) throws org.apache.hadoop.yarn.exceptions.YarnException, java.io.IOException;
    Code:
       0: aload_1
       1: checkcast     #8                  // class org/apache/hadoop/yarn/api/protocolrecords/impl/pb/AllocateRequestPBImpl
       4: invokevirtual #9                  // Method org/apache/hadoop/yarn/api/protocolrecords/impl/pb/AllocateRequestPBImpl.getProto:()Lorg/apache/hadoop/yarn/proto/YarnServiceProtos$AllocateRequestProto;
       7: astore_2
       8: new           #10                 // class org/apache/hadoop/yarn/api/protocolrecords/impl/pb/AllocateResponsePBImpl
      11: dup
      12: aload_0
      13: getfield      #6                  // Field proxy:Lorg/apache/hadoop/yarn/api/ApplicationMasterProtocolPB;
      16: aconst_null
      17: aload_2
      18: invokeinterface #11,  3           // InterfaceMethod org/apache/hadoop/yarn/api/ApplicationMasterProtocolPB.allocate:(Lcom/google/protobuf/RpcController;Lorg/apache/hadoop/yarn/proto/YarnServiceProtos$AllocateRequestProto;)Lorg/apache/hadoop/yarn/proto/YarnServiceProtos$AllocateResponseProto;
      23: invokespecial #12                 // Method org/apache/hadoop/yarn/api/protocolrecords/impl/pb/AllocateResponsePBImpl."<init>":(Lorg/apache/hadoop/yarn/proto/YarnServiceProtos$AllocateResponseProto;)V
      26: areturn
      27: astore_3
      28: aload_3
      29: invokestatic  #14                 // Method org/apache/hadoop/yarn/ipc/RPCUtil.unwrapAndThrowException:(Lcom/google/protobuf/ServiceException;)Ljava/lang/Void;
      32: pop
      33: aconst_null
      34: areturn
    Exception table:
       from    to  target type
           8    26    27   Class com/google/protobuf/ServiceException

  public org.apache.hadoop.yarn.api.protocolrecords.FinishApplicationMasterResponse finishApplicationMaster(org.apache.hadoop.yarn.api.protocolrecords.FinishApplicationMasterRequest) throws org.apache.hadoop.yarn.exceptions.YarnException, java.io.IOException;
    Code:
       0: aload_1
       1: checkcast     #15                 // class org/apache/hadoop/yarn/api/protocolrecords/impl/pb/FinishApplicationMasterRequestPBImpl
       4: invokevirtual #16                 // Method org/apache/hadoop/yarn/api/protocolrecords/impl/pb/FinishApplicationMasterRequestPBImpl.getProto:()Lorg/apache/hadoop/yarn/proto/YarnServiceProtos$FinishApplicationMasterRequestProto;
       7: astore_2
       8: new           #17                 // class org/apache/hadoop/yarn/api/protocolrecords/impl/pb/FinishApplicationMasterResponsePBImpl
      11: dup
      12: aload_0
      13: getfield      #6                  // Field proxy:Lorg/apache/hadoop/yarn/api/ApplicationMasterProtocolPB;
      16: aconst_null
      17: aload_2
      18: invokeinterface #18,  3           // InterfaceMethod org/apache/hadoop/yarn/api/ApplicationMasterProtocolPB.finishApplicationMaster:(Lcom/google/protobuf/RpcController;Lorg/apache/hadoop/yarn/proto/YarnServiceProtos$FinishApplicationMasterRequestProto;)Lorg/apache/hadoop/yarn/proto/YarnServiceProtos$FinishApplicationMasterResponseProto;
      23: invokespecial #19                 // Method org/apache/hadoop/yarn/api/protocolrecords/impl/pb/FinishApplicationMasterResponsePBImpl."<init>":(Lorg/apache/hadoop/yarn/proto/YarnServiceProtos$FinishApplicationMasterResponseProto;)V
      26: areturn
      27: astore_3
      28: aload_3
      29: invokestatic  #14                 // Method org/apache/hadoop/yarn/ipc/RPCUtil.unwrapAndThrowException:(Lcom/google/protobuf/ServiceException;)Ljava/lang/Void;
      32: pop
      33: aconst_null
      34: areturn
    Exception table:
       from    to  target type
           8    26    27   Class com/google/protobuf/ServiceException

  public org.apache.hadoop.yarn.api.protocolrecords.RegisterApplicationMasterResponse registerApplicationMaster(org.apache.hadoop.yarn.api.protocolrecords.RegisterApplicationMasterRequest) throws org.apache.hadoop.yarn.exceptions.YarnException, java.io.IOException;
    Code:
       0: aload_1
       1: checkcast     #20                 // class org/apache/hadoop/yarn/api/protocolrecords/impl/pb/RegisterApplicationMasterRequestPBImpl
       4: invokevirtual #21                 // Method org/apache/hadoop/yarn/api/protocolrecords/impl/pb/RegisterApplicationMasterRequestPBImpl.getProto:()Lorg/apache/hadoop/yarn/proto/YarnServiceProtos$RegisterApplicationMasterRequestProto;
       7: astore_2
       8: new           #22                 // class org/apache/hadoop/yarn/api/protocolrecords/impl/pb/RegisterApplicationMasterResponsePBImpl
      11: dup
      12: aload_0
      13: getfield      #6                  // Field proxy:Lorg/apache/hadoop/yarn/api/ApplicationMasterProtocolPB;
      16: aconst_null
      17: aload_2
      18: invokeinterface #23,  3           // InterfaceMethod org/apache/hadoop/yarn/api/ApplicationMasterProtocolPB.registerApplicationMaster:(Lcom/google/protobuf/RpcController;Lorg/apache/hadoop/yarn/proto/YarnServiceProtos$RegisterApplicationMasterRequestProto;)Lorg/apache/hadoop/yarn/proto/YarnServiceProtos$RegisterApplicationMasterResponseProto;
      23: invokespecial #24                 // Method org/apache/hadoop/yarn/api/protocolrecords/impl/pb/RegisterApplicationMasterResponsePBImpl."<init>":(Lorg/apache/hadoop/yarn/proto/YarnServiceProtos$RegisterApplicationMasterResponseProto;)V
      26: areturn
      27: astore_3
      28: aload_3
      29: invokestatic  #14                 // Method org/apache/hadoop/yarn/ipc/RPCUtil.unwrapAndThrowException:(Lcom/google/protobuf/ServiceException;)Ljava/lang/Void;
      32: pop
      33: aconst_null
      34: areturn
    Exception table:
       from    to  target type
           8    26    27   Class com/google/protobuf/ServiceException
}
