Compiled from "FixedValue.java"
public final class net.bytebuddy.implementation.FixedValue$ForNullValue extends java.lang.Enum<net.bytebuddy.implementation.FixedValue$ForNullValue> implements net.bytebuddy.implementation.Implementation, net.bytebuddy.implementation.bytecode.ByteCodeAppender {
  public static final net.bytebuddy.implementation.FixedValue$ForNullValue INSTANCE;

  private static final net.bytebuddy.implementation.FixedValue$ForNullValue[] $VALUES;

  public static net.bytebuddy.implementation.FixedValue$ForNullValue[] values();
    Code:
       0: getstatic     #38                 // Field $VALUES:[Lnet/bytebuddy/implementation/FixedValue$ForNullValue;
       3: invokevirtual #43                 // Method "[Lnet/bytebuddy/implementation/FixedValue$ForNullValue;".clone:()Ljava/lang/Object;
       6: checkcast     #39                 // class "[Lnet/bytebuddy/implementation/FixedValue$ForNullValue;"
       9: areturn

  public static net.bytebuddy.implementation.FixedValue$ForNullValue valueOf(java.lang.String);
    Code:
       0: ldc           #2                  // class net/bytebuddy/implementation/FixedValue$ForNullValue
       2: aload_0
       3: invokestatic  #48                 // Method java/lang/Enum.valueOf:(Ljava/lang/Class;Ljava/lang/String;)Ljava/lang/Enum;
       6: checkcast     #2                  // class net/bytebuddy/implementation/FixedValue$ForNullValue
       9: areturn

  private net.bytebuddy.implementation.FixedValue$ForNullValue();
    Code:
       0: aload_0
       1: aload_1
       2: iload_2
       3: invokespecial #54                 // Method java/lang/Enum."<init>":(Ljava/lang/String;I)V
       6: return

  public net.bytebuddy.implementation.bytecode.ByteCodeAppender appender(net.bytebuddy.implementation.Implementation$Target);
    Code:
       0: aload_0
       1: areturn

  public net.bytebuddy.dynamic.scaffold.InstrumentedType prepare(net.bytebuddy.dynamic.scaffold.InstrumentedType);
    Code:
       0: aload_1
       1: areturn

  public net.bytebuddy.implementation.bytecode.ByteCodeAppender$Size apply(net.bytebuddy.jar.asm.MethodVisitor, net.bytebuddy.implementation.Implementation$Context, net.bytebuddy.description.method.MethodDescription);
    Code:
       0: aload_3
       1: invokeinterface #71,  1           // InterfaceMethod net/bytebuddy/description/method/MethodDescription.getReturnType:()Lnet/bytebuddy/description/type/TypeDescription$Generic;
       6: invokeinterface #75,  1           // InterfaceMethod net/bytebuddy/description/type/TypeDescription$Generic.isPrimitive:()Z
      11: ifeq          41
      14: new           #77                 // class java/lang/IllegalStateException
      17: dup
      18: new           #79                 // class java/lang/StringBuilder
      21: dup
      22: invokespecial #82                 // Method java/lang/StringBuilder."<init>":()V
      25: ldc           #84                 // String Cannot return null from
      27: invokevirtual #88                 // Method java/lang/StringBuilder.append:(Ljava/lang/String;)Ljava/lang/StringBuilder;
      30: aload_3
      31: invokevirtual #91                 // Method java/lang/StringBuilder.append:(Ljava/lang/Object;)Ljava/lang/StringBuilder;
      34: invokevirtual #95                 // Method java/lang/StringBuilder.toString:()Ljava/lang/String;
      37: invokespecial #98                 // Method java/lang/IllegalStateException."<init>":(Ljava/lang/String;)V
      40: athrow
      41: new           #24                 // class net/bytebuddy/implementation/bytecode/ByteCodeAppender$Simple
      44: dup
      45: iconst_2
      46: anewarray     #100                // class net/bytebuddy/implementation/bytecode/StackManipulation
      49: dup
      50: iconst_0
      51: getstatic     #105                // Field net/bytebuddy/implementation/bytecode/constant/NullConstant.INSTANCE:Lnet/bytebuddy/implementation/bytecode/constant/NullConstant;
      54: aastore
      55: dup
      56: iconst_1
      57: getstatic     #111                // Field net/bytebuddy/implementation/bytecode/member/MethodReturn.REFERENCE:Lnet/bytebuddy/implementation/bytecode/member/MethodReturn;
      60: aastore
      61: invokespecial #114                // Method net/bytebuddy/implementation/bytecode/ByteCodeAppender$Simple."<init>":([Lnet/bytebuddy/implementation/bytecode/StackManipulation;)V
      64: aload_1
      65: aload_2
      66: aload_3
      67: invokevirtual #116                // Method net/bytebuddy/implementation/bytecode/ByteCodeAppender$Simple.apply:(Lnet/bytebuddy/jar/asm/MethodVisitor;Lnet/bytebuddy/implementation/Implementation$Context;Lnet/bytebuddy/description/method/MethodDescription;)Lnet/bytebuddy/implementation/bytecode/ByteCodeAppender$Size;
      70: areturn

  static {};
    Code:
       0: new           #2                  // class net/bytebuddy/implementation/FixedValue$ForNullValue
       3: dup
       4: ldc           #124                // String INSTANCE
       6: iconst_0
       7: invokespecial #125                // Method "<init>":(Ljava/lang/String;I)V
      10: putstatic     #127                // Field INSTANCE:Lnet/bytebuddy/implementation/FixedValue$ForNullValue;
      13: iconst_1
      14: anewarray     #2                  // class net/bytebuddy/implementation/FixedValue$ForNullValue
      17: dup
      18: iconst_0
      19: getstatic     #127                // Field INSTANCE:Lnet/bytebuddy/implementation/FixedValue$ForNullValue;
      22: aastore
      23: putstatic     #38                 // Field $VALUES:[Lnet/bytebuddy/implementation/FixedValue$ForNullValue;
      26: return
}
