Compiled from "InvokeDynamic.java"
public class net.bytebuddy.implementation.InvokeDynamic$WithImplicitType$OfField extends net.bytebuddy.implementation.InvokeDynamic$WithImplicitType {
  private final java.lang.String fieldName;

  private final net.bytebuddy.dynamic.scaffold.FieldLocator$Factory fieldLocatorFactory;

  protected net.bytebuddy.implementation.InvokeDynamic$WithImplicitType$OfField(net.bytebuddy.description.method.MethodDescription$InDefinedShape, java.util.List<?>, net.bytebuddy.implementation.InvokeDynamic$InvocationProvider, net.bytebuddy.implementation.InvokeDynamic$TerminationHandler, net.bytebuddy.implementation.bytecode.assign.Assigner, net.bytebuddy.implementation.bytecode.assign.Assigner$Typing, java.lang.String, net.bytebuddy.dynamic.scaffold.FieldLocator$Factory);
    Code:
       0: aload_0
       1: aload_1
       2: aload_2
       3: aload_3
       4: aload         4
       6: aload         5
       8: aload         6
      10: invokespecial #53                 // Method net/bytebuddy/implementation/InvokeDynamic$WithImplicitType."<init>":(Lnet/bytebuddy/description/method/MethodDescription$InDefinedShape;Ljava/util/List;Lnet/bytebuddy/implementation/InvokeDynamic$InvocationProvider;Lnet/bytebuddy/implementation/InvokeDynamic$TerminationHandler;Lnet/bytebuddy/implementation/bytecode/assign/Assigner;Lnet/bytebuddy/implementation/bytecode/assign/Assigner$Typing;)V
      13: aload_0
      14: aload         7
      16: putfield      #55                 // Field fieldName:Ljava/lang/String;
      19: aload_0
      20: aload         8
      22: putfield      #57                 // Field fieldLocatorFactory:Lnet/bytebuddy/dynamic/scaffold/FieldLocator$Factory;
      25: return

  public net.bytebuddy.implementation.InvokeDynamic as(net.bytebuddy.description.type.TypeDescription);
    Code:
       0: new           #24                 // class net/bytebuddy/implementation/InvokeDynamic
       3: dup
       4: aload_0
       5: getfield      #76                 // Field bootstrapMethod:Lnet/bytebuddy/description/method/MethodDescription$InDefinedShape;
       8: aload_0
       9: getfield      #78                 // Field handleArguments:Ljava/util/List;
      12: aload_0
      13: getfield      #80                 // Field invocationProvider:Lnet/bytebuddy/implementation/InvokeDynamic$InvocationProvider;
      16: new           #43                 // class net/bytebuddy/implementation/InvokeDynamic$InvocationProvider$ArgumentProvider$ForField$WithExplicitType
      19: dup
      20: aload_0
      21: getfield      #55                 // Field fieldName:Ljava/lang/String;
      24: aload_0
      25: getfield      #57                 // Field fieldLocatorFactory:Lnet/bytebuddy/dynamic/scaffold/FieldLocator$Factory;
      28: aload_1
      29: invokespecial #83                 // Method net/bytebuddy/implementation/InvokeDynamic$InvocationProvider$ArgumentProvider$ForField$WithExplicitType."<init>":(Ljava/lang/String;Lnet/bytebuddy/dynamic/scaffold/FieldLocator$Factory;Lnet/bytebuddy/description/type/TypeDescription;)V
      32: invokeinterface #87,  2           // InterfaceMethod net/bytebuddy/implementation/InvokeDynamic$InvocationProvider.appendArgument:(Lnet/bytebuddy/implementation/InvokeDynamic$InvocationProvider$ArgumentProvider;)Lnet/bytebuddy/implementation/InvokeDynamic$InvocationProvider;
      37: aload_0
      38: getfield      #89                 // Field terminationHandler:Lnet/bytebuddy/implementation/InvokeDynamic$TerminationHandler;
      41: aload_0
      42: getfield      #91                 // Field assigner:Lnet/bytebuddy/implementation/bytecode/assign/Assigner;
      45: aload_0
      46: getfield      #93                 // Field typing:Lnet/bytebuddy/implementation/bytecode/assign/Assigner$Typing;
      49: invokespecial #94                 // Method net/bytebuddy/implementation/InvokeDynamic."<init>":(Lnet/bytebuddy/description/method/MethodDescription$InDefinedShape;Ljava/util/List;Lnet/bytebuddy/implementation/InvokeDynamic$InvocationProvider;Lnet/bytebuddy/implementation/InvokeDynamic$TerminationHandler;Lnet/bytebuddy/implementation/bytecode/assign/Assigner;Lnet/bytebuddy/implementation/bytecode/assign/Assigner$Typing;)V
      52: areturn

  protected net.bytebuddy.implementation.InvokeDynamic materialize();
    Code:
       0: new           #24                 // class net/bytebuddy/implementation/InvokeDynamic
       3: dup
       4: aload_0
       5: getfield      #76                 // Field bootstrapMethod:Lnet/bytebuddy/description/method/MethodDescription$InDefinedShape;
       8: aload_0
       9: getfield      #78                 // Field handleArguments:Ljava/util/List;
      12: aload_0
      13: getfield      #80                 // Field invocationProvider:Lnet/bytebuddy/implementation/InvokeDynamic$InvocationProvider;
      16: new           #40                 // class net/bytebuddy/implementation/InvokeDynamic$InvocationProvider$ArgumentProvider$ForField
      19: dup
      20: aload_0
      21: getfield      #55                 // Field fieldName:Ljava/lang/String;
      24: aload_0
      25: getfield      #57                 // Field fieldLocatorFactory:Lnet/bytebuddy/dynamic/scaffold/FieldLocator$Factory;
      28: invokespecial #101                // Method net/bytebuddy/implementation/InvokeDynamic$InvocationProvider$ArgumentProvider$ForField."<init>":(Ljava/lang/String;Lnet/bytebuddy/dynamic/scaffold/FieldLocator$Factory;)V
      31: invokeinterface #87,  2           // InterfaceMethod net/bytebuddy/implementation/InvokeDynamic$InvocationProvider.appendArgument:(Lnet/bytebuddy/implementation/InvokeDynamic$InvocationProvider$ArgumentProvider;)Lnet/bytebuddy/implementation/InvokeDynamic$InvocationProvider;
      36: aload_0
      37: getfield      #89                 // Field terminationHandler:Lnet/bytebuddy/implementation/InvokeDynamic$TerminationHandler;
      40: aload_0
      41: getfield      #91                 // Field assigner:Lnet/bytebuddy/implementation/bytecode/assign/Assigner;
      44: aload_0
      45: getfield      #93                 // Field typing:Lnet/bytebuddy/implementation/bytecode/assign/Assigner$Typing;
      48: invokespecial #94                 // Method net/bytebuddy/implementation/InvokeDynamic."<init>":(Lnet/bytebuddy/description/method/MethodDescription$InDefinedShape;Ljava/util/List;Lnet/bytebuddy/implementation/InvokeDynamic$InvocationProvider;Lnet/bytebuddy/implementation/InvokeDynamic$TerminationHandler;Lnet/bytebuddy/implementation/bytecode/assign/Assigner;Lnet/bytebuddy/implementation/bytecode/assign/Assigner$Typing;)V
      51: areturn
}
