Compiled from "InitLoader.java"
abstract class com.arjuna.orbportability.internal.utils.InitLoader {
  private java.lang.String initName;

  private java.lang.String propertyName;

  private java.lang.Object initObj;

  protected com.arjuna.orbportability.internal.utils.InitLoader(java.lang.String, java.lang.String, java.lang.Object);
    Code:
       0: aload_0
       1: invokespecial #1                  // Method java/lang/Object."<init>":()V
       4: aload_0
       5: aload_1
       6: putfield      #2                  // Field initName:Ljava/lang/String;
       9: aload_0
      10: aload_2
      11: putfield      #3                  // Field propertyName:Ljava/lang/String;
      14: aload_0
      15: aload_3
      16: putfield      #4                  // Field initObj:Ljava/lang/Object;
      19: return

  protected void initialise();
    Code:
       0: invokestatic  #5                  // Method com/arjuna/orbportability/common/opPropertyManager.getOrbPortabilityEnvironmentBean:()Lcom/arjuna/orbportability/common/OrbPortabilityEnvironmentBean;
       3: invokevirtual #6                  // Method com/arjuna/orbportability/common/OrbPortabilityEnvironmentBean.getOrbInitializationProperties:()Ljava/util/Map;
       6: astore_1
       7: aload_1
       8: invokeinterface #7,  1            // InterfaceMethod java/util/Map.keySet:()Ljava/util/Set;
      13: invokeinterface #8,  1            // InterfaceMethod java/util/Set.iterator:()Ljava/util/Iterator;
      18: astore_2
      19: aload_2
      20: invokeinterface #9,  1            // InterfaceMethod java/util/Iterator.hasNext:()Z
      25: ifeq          68
      28: aload_2
      29: invokeinterface #10,  1           // InterfaceMethod java/util/Iterator.next:()Ljava/lang/Object;
      34: checkcast     #11                 // class java/lang/String
      37: astore_3
      38: aload_3
      39: aload_0
      40: getfield      #3                  // Field propertyName:Ljava/lang/String;
      43: invokevirtual #12                 // Method java/lang/String.indexOf:(Ljava/lang/String;)I
      46: iconst_m1
      47: if_icmpeq     65
      50: aload_0
      51: aload_3
      52: aload_1
      53: aload_3
      54: invokeinterface #13,  2           // InterfaceMethod java/util/Map.get:(Ljava/lang/Object;)Ljava/lang/Object;
      59: checkcast     #11                 // class java/lang/String
      62: invokespecial #14                 // Method createInstance:(Ljava/lang/String;Ljava/lang/String;)V
      65: goto          19
      68: return

  private void createInstance(java.lang.String, java.lang.String);
    Code:
       0: aload_2
       1: ifnonnull     18
       4: getstatic     #15                 // Field com/arjuna/orbportability/logging/opLogger.i18NLogger:Lcom/arjuna/orbportability/logging/orbportabilityI18NLogger;
       7: aload_0
       8: getfield      #2                  // Field initName:Ljava/lang/String;
      11: aload_1
      12: invokeinterface #16,  3           // InterfaceMethod com/arjuna/orbportability/logging/orbportabilityI18NLogger.warn_internal_utils_InitLoader_initfailed:(Ljava/lang/String;Ljava/lang/String;)V
      17: return
      18: getstatic     #17                 // Field com/arjuna/orbportability/logging/opLogger.logger:Lorg/jboss/logging/Logger;
      21: ldc           #18                 // String Loading %s class - %s
      23: aload_0
      24: getfield      #2                  // Field initName:Ljava/lang/String;
      27: aload_2
      28: invokevirtual #19                 // Method org/jboss/logging/Logger.debugf:(Ljava/lang/String;Ljava/lang/Object;Ljava/lang/Object;)V
      31: aload_2
      32: invokestatic  #20                 // Method com/arjuna/common/internal/util/ClassloadingUtility.loadClass:(Ljava/lang/String;)Ljava/lang/Class;
      35: astore_3
      36: aload_3
      37: ifnonnull     41
      40: return
      41: aload_3
      42: invokevirtual #21                 // Method java/lang/Class.newInstance:()Ljava/lang/Object;
      45: astore        4
      47: aload         4
      49: instanceof    #22                 // class com/arjuna/orbportability/utils/InitClassInterface
      52: ifeq          69
      55: aload         4
      57: checkcast     #22                 // class com/arjuna/orbportability/utils/InitClassInterface
      60: aload_0
      61: getfield      #4                  // Field initObj:Ljava/lang/Object;
      64: invokeinterface #23,  2           // InterfaceMethod com/arjuna/orbportability/utils/InitClassInterface.invoke:(Ljava/lang/Object;)V
      69: aconst_null
      70: astore        4
      72: goto          110
      75: astore        4
      77: getstatic     #15                 // Field com/arjuna/orbportability/logging/opLogger.i18NLogger:Lcom/arjuna/orbportability/logging/orbportabilityI18NLogger;
      80: aload_0
      81: getfield      #2                  // Field initName:Ljava/lang/String;
      84: aload         4
      86: invokeinterface #25,  3           // InterfaceMethod com/arjuna/orbportability/logging/orbportabilityI18NLogger.warn_internal_utils_InitLoader_exception:(Ljava/lang/String;Ljava/lang/Throwable;)V
      91: goto          110
      94: astore        4
      96: getstatic     #15                 // Field com/arjuna/orbportability/logging/opLogger.i18NLogger:Lcom/arjuna/orbportability/logging/orbportabilityI18NLogger;
      99: aload_0
     100: getfield      #2                  // Field initName:Ljava/lang/String;
     103: aload         4
     105: invokeinterface #25,  3           // InterfaceMethod com/arjuna/orbportability/logging/orbportabilityI18NLogger.warn_internal_utils_InitLoader_exception:(Ljava/lang/String;Ljava/lang/Throwable;)V
     110: return
    Exception table:
       from    to  target type
          41    72    75   Class java/lang/IllegalAccessException
          41    72    94   Class java/lang/InstantiationException
}
