Compiled from "NativeLibraryUtil.java"
final class io.netty.util.internal.NativeLibraryUtil {
  public static void loadLibrary(java.lang.String, boolean);
    Code:
       0: iload_1
       1: ifeq          11
       4: aload_0
       5: invokestatic  #13                 // Method java/lang/System.load:(Ljava/lang/String;)V
       8: goto          15
      11: aload_0
      12: invokestatic  #15                 // Method java/lang/System.loadLibrary:(Ljava/lang/String;)V
      15: return

  private io.netty.util.internal.NativeLibraryUtil();
    Code:
       0: aload_0
       1: invokespecial #23                 // Method java/lang/Object."<init>":()V
       4: return
}
