Compiled from "ClassUtils.java"
public final class com.mchange.v1.lang.ClassUtils {
  static final java.lang.String[] EMPTY_SA;

  static java.util.Map primitivesToClasses;

  public static java.util.Set publicSupertypesForMethods(java.lang.Class, java.lang.reflect.Method[]);
    Code:
       0: aload_0
       1: invokestatic  #1                  // Method allAssignableFrom:(Ljava/lang/Class;)Ljava/util/Set;
       4: astore_2
       5: new           #2                  // class java/util/HashSet
       8: dup
       9: invokespecial #3                  // Method java/util/HashSet."<init>":()V
      12: astore_3
      13: aload_2
      14: invokeinterface #4,  1            // InterfaceMethod java/util/Set.iterator:()Ljava/util/Iterator;
      19: astore        4
      21: aload         4
      23: invokeinterface #5,  1            // InterfaceMethod java/util/Iterator.hasNext:()Z
      28: ifeq          72
      31: aload         4
      33: invokeinterface #6,  1            // InterfaceMethod java/util/Iterator.next:()Ljava/lang/Object;
      38: checkcast     #7                  // class java/lang/Class
      41: astore        5
      43: aload         5
      45: invokestatic  #8                  // Method isPublic:(Ljava/lang/Class;)Z
      48: ifeq          69
      51: aload         5
      53: aload_1
      54: invokestatic  #9                  // Method hasAllMethodsAsSupertype:(Ljava/lang/Class;[Ljava/lang/reflect/Method;)Z
      57: ifeq          69
      60: aload_3
      61: aload         5
      63: invokeinterface #10,  2           // InterfaceMethod java/util/Set.add:(Ljava/lang/Object;)Z
      68: pop
      69: goto          21
      72: aload_3
      73: invokestatic  #11                 // Method java/util/Collections.unmodifiableSet:(Ljava/util/Set;)Ljava/util/Set;
      76: areturn

  public static boolean isPublic(java.lang.Class);
    Code:
       0: aload_0
       1: invokevirtual #12                 // Method java/lang/Class.getModifiers:()I
       4: iconst_1
       5: iand
       6: ifeq          13
       9: iconst_1
      10: goto          14
      13: iconst_0
      14: ireturn

  public static boolean hasAllMethodsAsSupertype(java.lang.Class, java.lang.reflect.Method[]);
    Code:
       0: aload_0
       1: aload_1
       2: iconst_1
       3: invokestatic  #14                 // Method hasAllMethods:(Ljava/lang/Class;[Ljava/lang/reflect/Method;Z)Z
       6: ireturn

  public static boolean hasAllMethodsAsSubtype(java.lang.Class, java.lang.reflect.Method[]);
    Code:
       0: aload_0
       1: aload_1
       2: iconst_0
       3: invokestatic  #14                 // Method hasAllMethods:(Ljava/lang/Class;[Ljava/lang/reflect/Method;Z)Z
       6: ireturn

  private static boolean hasAllMethods(java.lang.Class, java.lang.reflect.Method[], boolean);
    Code:
       0: iconst_0
       1: istore_3
       2: aload_1
       3: arraylength
       4: istore        4
       6: iload_3
       7: iload         4
       9: if_icmpge     31
      12: aload_0
      13: aload_1
      14: iload_3
      15: aaload
      16: iload_2
      17: invokestatic  #15                 // Method containsMethod:(Ljava/lang/Class;Ljava/lang/reflect/Method;Z)Z
      20: ifne          25
      23: iconst_0
      24: ireturn
      25: iinc          3, 1
      28: goto          6
      31: iconst_1
      32: ireturn

  public static boolean containsMethodAsSupertype(java.lang.Class, java.lang.reflect.Method);
    Code:
       0: aload_0
       1: aload_1
       2: iconst_1
       3: invokestatic  #15                 // Method containsMethod:(Ljava/lang/Class;Ljava/lang/reflect/Method;Z)Z
       6: ireturn

  public static boolean containsMethodAsSubtype(java.lang.Class, java.lang.reflect.Method);
    Code:
       0: aload_0
       1: aload_1
       2: iconst_0
       3: invokestatic  #15                 // Method containsMethod:(Ljava/lang/Class;Ljava/lang/reflect/Method;Z)Z
       6: ireturn

  private static boolean containsMethod(java.lang.Class, java.lang.reflect.Method, boolean);
    Code:
       0: aload_0
       1: aload_1
       2: invokevirtual #16                 // Method java/lang/reflect/Method.getName:()Ljava/lang/String;
       5: aload_1
       6: invokevirtual #17                 // Method java/lang/reflect/Method.getParameterTypes:()[Ljava/lang/Class;
       9: invokevirtual #18                 // Method java/lang/Class.getMethod:(Ljava/lang/String;[Ljava/lang/Class;)Ljava/lang/reflect/Method;
      12: astore_3
      13: aload_1
      14: invokevirtual #19                 // Method java/lang/reflect/Method.getReturnType:()Ljava/lang/Class;
      17: astore        4
      19: aload_3
      20: invokevirtual #19                 // Method java/lang/reflect/Method.getReturnType:()Ljava/lang/Class;
      23: astore        5
      25: aload         4
      27: aload         5
      29: invokevirtual #20                 // Method java/lang/Object.equals:(Ljava/lang/Object;)Z
      32: ifne          63
      35: iload_2
      36: ifeq          49
      39: aload         5
      41: aload         4
      43: invokevirtual #21                 // Method java/lang/Class.isAssignableFrom:(Ljava/lang/Class;)Z
      46: ifne          63
      49: iload_2
      50: ifne          67
      53: aload         4
      55: aload         5
      57: invokevirtual #21                 // Method java/lang/Class.isAssignableFrom:(Ljava/lang/Class;)Z
      60: ifeq          67
      63: iconst_1
      64: goto          68
      67: iconst_0
      68: ireturn
      69: astore        4
      71: iconst_0
      72: ireturn
    Exception table:
       from    to  target type
           0    68    69   Class java/lang/NoSuchMethodException

  public static java.util.Set allAssignableFrom(java.lang.Class);
    Code:
       0: new           #2                  // class java/util/HashSet
       3: dup
       4: invokespecial #3                  // Method java/util/HashSet."<init>":()V
       7: astore_1
       8: aload_0
       9: astore_2
      10: aload_2
      11: ifnull        30
      14: aload_1
      15: aload_2
      16: invokeinterface #10,  2           // InterfaceMethod java/util/Set.add:(Ljava/lang/Object;)Z
      21: pop
      22: aload_2
      23: invokevirtual #23                 // Method java/lang/Class.getSuperclass:()Ljava/lang/Class;
      26: astore_2
      27: goto          10
      30: aload_0
      31: aload_1
      32: invokestatic  #24                 // Method addSuperInterfacesToSet:(Ljava/lang/Class;Ljava/util/Set;)V
      35: aload_1
      36: areturn

  public static java.lang.String simpleClassName(java.lang.Class);
    Code:
       0: iconst_0
       1: istore_2
       2: aload_0
       3: invokevirtual #25                 // Method java/lang/Class.isArray:()Z
       6: ifeq          20
       9: iinc          2, 1
      12: aload_0
      13: invokevirtual #26                 // Method java/lang/Class.getComponentType:()Ljava/lang/Class;
      16: astore_0
      17: goto          2
      20: aload_0
      21: invokevirtual #27                 // Method java/lang/Class.getName:()Ljava/lang/String;
      24: invokestatic  #28                 // Method simpleClassName:(Ljava/lang/String;)Ljava/lang/String;
      27: astore_1
      28: iload_2
      29: ifle          75
      32: new           #29                 // class java/lang/StringBuffer
      35: dup
      36: bipush        16
      38: invokespecial #30                 // Method java/lang/StringBuffer."<init>":(I)V
      41: astore_3
      42: aload_3
      43: aload_1
      44: invokevirtual #31                 // Method java/lang/StringBuffer.append:(Ljava/lang/String;)Ljava/lang/StringBuffer;
      47: pop
      48: iconst_0
      49: istore        4
      51: iload         4
      53: iload_2
      54: if_icmpge     70
      57: aload_3
      58: ldc           #32                 // String []
      60: invokevirtual #31                 // Method java/lang/StringBuffer.append:(Ljava/lang/String;)Ljava/lang/StringBuffer;
      63: pop
      64: iinc          4, 1
      67: goto          51
      70: aload_3
      71: invokevirtual #33                 // Method java/lang/StringBuffer.toString:()Ljava/lang/String;
      74: areturn
      75: aload_1
      76: areturn

  private static java.lang.String simpleClassName(java.lang.String);
    Code:
       0: aload_0
       1: bipush        46
       3: invokevirtual #34                 // Method java/lang/String.lastIndexOf:(I)I
       6: istore_1
       7: iload_1
       8: ifge          13
      11: aload_0
      12: areturn
      13: aload_0
      14: iload_1
      15: iconst_1
      16: iadd
      17: invokevirtual #35                 // Method java/lang/String.substring:(I)Ljava/lang/String;
      20: astore_2
      21: aload_2
      22: bipush        36
      24: invokevirtual #36                 // Method java/lang/String.indexOf:(I)I
      27: iflt          85
      30: new           #29                 // class java/lang/StringBuffer
      33: dup
      34: aload_2
      35: invokespecial #37                 // Method java/lang/StringBuffer."<init>":(Ljava/lang/String;)V
      38: astore_3
      39: iconst_0
      40: istore        4
      42: aload_3
      43: invokevirtual #38                 // Method java/lang/StringBuffer.length:()I
      46: istore        5
      48: iload         4
      50: iload         5
      52: if_icmpge     80
      55: aload_3
      56: iload         4
      58: invokevirtual #39                 // Method java/lang/StringBuffer.charAt:(I)C
      61: bipush        36
      63: if_icmpne     74
      66: aload_3
      67: iload         4
      69: bipush        46
      71: invokevirtual #40                 // Method java/lang/StringBuffer.setCharAt:(IC)V
      74: iinc          4, 1
      77: goto          48
      80: aload_3
      81: invokevirtual #33                 // Method java/lang/StringBuffer.toString:()Ljava/lang/String;
      84: areturn
      85: aload_2
      86: areturn

  public static boolean isPrimitive(java.lang.String);
    Code:
       0: getstatic     #41                 // Field primitivesToClasses:Ljava/util/Map;
       3: aload_0
       4: invokeinterface #42,  2           // InterfaceMethod java/util/Map.get:(Ljava/lang/Object;)Ljava/lang/Object;
       9: ifnull        16
      12: iconst_1
      13: goto          17
      16: iconst_0
      17: ireturn

  public static java.lang.Class classForPrimitive(java.lang.String);
    Code:
       0: getstatic     #41                 // Field primitivesToClasses:Ljava/util/Map;
       3: aload_0
       4: invokeinterface #42,  2           // InterfaceMethod java/util/Map.get:(Ljava/lang/Object;)Ljava/lang/Object;
       9: checkcast     #7                  // class java/lang/Class
      12: areturn

  public static java.lang.Class forName(java.lang.String) throws java.lang.ClassNotFoundException;
    Code:
       0: aload_0
       1: invokestatic  #43                 // Method classForPrimitive:(Ljava/lang/String;)Ljava/lang/Class;
       4: astore_1
       5: aload_1
       6: ifnonnull     14
       9: aload_0
      10: invokestatic  #44                 // Method java/lang/Class.forName:(Ljava/lang/String;)Ljava/lang/Class;
      13: astore_1
      14: aload_1
      15: areturn

  public static java.lang.Class forName(java.lang.String, java.lang.String[], java.lang.String[]) throws com.mchange.v1.lang.AmbiguousClassNameException, java.lang.ClassNotFoundException;
    Code:
       0: aload_0
       1: invokestatic  #44                 // Method java/lang/Class.forName:(Ljava/lang/String;)Ljava/lang/Class;
       4: areturn
       5: astore_3
       6: aload_0
       7: aload_1
       8: aload_2
       9: invokestatic  #46                 // Method classForSimpleName:(Ljava/lang/String;[Ljava/lang/String;[Ljava/lang/String;)Ljava/lang/Class;
      12: areturn
    Exception table:
       from    to  target type
           0     4     5   Class java/lang/ClassNotFoundException

  public static java.lang.Class classForSimpleName(java.lang.String, java.lang.String[], java.lang.String[]) throws com.mchange.v1.lang.AmbiguousClassNameException, java.lang.ClassNotFoundException;
    Code:
       0: new           #2                  // class java/util/HashSet
       3: dup
       4: invokespecial #3                  // Method java/util/HashSet."<init>":()V
       7: astore_3
       8: aload_0
       9: invokestatic  #43                 // Method classForPrimitive:(Ljava/lang/String;)Ljava/lang/Class;
      12: astore        4
      14: aload         4
      16: ifnonnull     240
      19: aload_1
      20: ifnonnull     27
      23: getstatic     #47                 // Field EMPTY_SA:[Ljava/lang/String;
      26: astore_1
      27: aload_2
      28: ifnonnull     35
      31: getstatic     #47                 // Field EMPTY_SA:[Ljava/lang/String;
      34: astore_2
      35: iconst_0
      36: istore        5
      38: aload_2
      39: arraylength
      40: istore        6
      42: iload         5
      44: iload         6
      46: if_icmpge     121
      49: aload_2
      50: iload         5
      52: aaload
      53: invokestatic  #48                 // Method fqcnLastElement:(Ljava/lang/String;)Ljava/lang/String;
      56: astore        7
      58: aload_3
      59: aload         7
      61: invokeinterface #10,  2           // InterfaceMethod java/util/Set.add:(Ljava/lang/Object;)Z
      66: ifne          97
      69: new           #49                 // class java/lang/IllegalArgumentException
      72: dup
      73: new           #50                 // class java/lang/StringBuilder
      76: dup
      77: invokespecial #51                 // Method java/lang/StringBuilder."<init>":()V
      80: ldc           #52                 // String Duplicate imported classes:
      82: invokevirtual #53                 // Method java/lang/StringBuilder.append:(Ljava/lang/String;)Ljava/lang/StringBuilder;
      85: aload         7
      87: invokevirtual #53                 // Method java/lang/StringBuilder.append:(Ljava/lang/String;)Ljava/lang/StringBuilder;
      90: invokevirtual #54                 // Method java/lang/StringBuilder.toString:()Ljava/lang/String;
      93: invokespecial #55                 // Method java/lang/IllegalArgumentException."<init>":(Ljava/lang/String;)V
      96: athrow
      97: aload_0
      98: aload         7
     100: invokevirtual #56                 // Method java/lang/String.equals:(Ljava/lang/Object;)Z
     103: ifeq          115
     106: aload_2
     107: iload         5
     109: aaload
     110: invokestatic  #44                 // Method java/lang/Class.forName:(Ljava/lang/String;)Ljava/lang/Class;
     113: astore        4
     115: iinc          5, 1
     118: goto          42
     121: aload         4
     123: ifnonnull     240
     126: new           #50                 // class java/lang/StringBuilder
     129: dup
     130: invokespecial #51                 // Method java/lang/StringBuilder."<init>":()V
     133: ldc           #57                 // String java.lang.
     135: invokevirtual #53                 // Method java/lang/StringBuilder.append:(Ljava/lang/String;)Ljava/lang/StringBuilder;
     138: aload_0
     139: invokevirtual #53                 // Method java/lang/StringBuilder.append:(Ljava/lang/String;)Ljava/lang/StringBuilder;
     142: invokevirtual #54                 // Method java/lang/StringBuilder.toString:()Ljava/lang/String;
     145: invokestatic  #44                 // Method java/lang/Class.forName:(Ljava/lang/String;)Ljava/lang/Class;
     148: astore        4
     150: goto          155
     153: astore        5
     155: iconst_0
     156: istore        5
     158: aload_1
     159: arraylength
     160: istore        6
     162: iload         5
     164: iload         6
     166: if_icmpge     240
     169: new           #50                 // class java/lang/StringBuilder
     172: dup
     173: invokespecial #51                 // Method java/lang/StringBuilder."<init>":()V
     176: aload_1
     177: iload         5
     179: aaload
     180: invokevirtual #53                 // Method java/lang/StringBuilder.append:(Ljava/lang/String;)Ljava/lang/StringBuilder;
     183: bipush        46
     185: invokevirtual #58                 // Method java/lang/StringBuilder.append:(C)Ljava/lang/StringBuilder;
     188: aload_0
     189: invokevirtual #53                 // Method java/lang/StringBuilder.append:(Ljava/lang/String;)Ljava/lang/StringBuilder;
     192: invokevirtual #54                 // Method java/lang/StringBuilder.toString:()Ljava/lang/String;
     195: astore        7
     197: aload         7
     199: invokestatic  #44                 // Method java/lang/Class.forName:(Ljava/lang/String;)Ljava/lang/Class;
     202: astore        8
     204: aload         4
     206: ifnonnull     216
     209: aload         8
     211: astore        4
     213: goto          229
     216: new           #59                 // class com/mchange/v1/lang/AmbiguousClassNameException
     219: dup
     220: aload_0
     221: aload         4
     223: aload         8
     225: invokespecial #60                 // Method com/mchange/v1/lang/AmbiguousClassNameException."<init>":(Ljava/lang/String;Ljava/lang/Class;Ljava/lang/Class;)V
     228: athrow
     229: goto          234
     232: astore        7
     234: iinc          5, 1
     237: goto          162
     240: aload         4
     242: ifnonnull     296
     245: new           #45                 // class java/lang/ClassNotFoundException
     248: dup
     249: new           #50                 // class java/lang/StringBuilder
     252: dup
     253: invokespecial #51                 // Method java/lang/StringBuilder."<init>":()V
     256: ldc           #61                 // String Could not find a class whose unqualified name is \"
     258: invokevirtual #53                 // Method java/lang/StringBuilder.append:(Ljava/lang/String;)Ljava/lang/StringBuilder;
     261: aload_0
     262: invokevirtual #53                 // Method java/lang/StringBuilder.append:(Ljava/lang/String;)Ljava/lang/StringBuilder;
     265: ldc           #62                 // String \" with the imports supplied. Import packages are
     267: invokevirtual #53                 // Method java/lang/StringBuilder.append:(Ljava/lang/String;)Ljava/lang/StringBuilder;
     270: aload_1
     271: invokestatic  #63                 // Method java/util/Arrays.asList:([Ljava/lang/Object;)Ljava/util/List;
     274: invokevirtual #64                 // Method java/lang/StringBuilder.append:(Ljava/lang/Object;)Ljava/lang/StringBuilder;
     277: ldc           #65                 // String ; class imports are
     279: invokevirtual #53                 // Method java/lang/StringBuilder.append:(Ljava/lang/String;)Ljava/lang/StringBuilder;
     282: aload_2
     283: invokestatic  #63                 // Method java/util/Arrays.asList:([Ljava/lang/Object;)Ljava/util/List;
     286: invokevirtual #64                 // Method java/lang/StringBuilder.append:(Ljava/lang/Object;)Ljava/lang/StringBuilder;
     289: invokevirtual #54                 // Method java/lang/StringBuilder.toString:()Ljava/lang/String;
     292: invokespecial #66                 // Method java/lang/ClassNotFoundException."<init>":(Ljava/lang/String;)V
     295: athrow
     296: aload         4
     298: areturn
    Exception table:
       from    to  target type
         126   150   153   Class java/lang/ClassNotFoundException
         169   229   232   Class java/lang/ClassNotFoundException

  public static java.lang.String resolvableTypeName(java.lang.Class, java.lang.String[], java.lang.String[]) throws java.lang.ClassNotFoundException;
    Code:
       0: aload_0
       1: invokestatic  #67                 // Method simpleClassName:(Ljava/lang/Class;)Ljava/lang/String;
       4: astore_3
       5: aload_3
       6: aload_1
       7: aload_2
       8: invokestatic  #46                 // Method classForSimpleName:(Ljava/lang/String;[Ljava/lang/String;[Ljava/lang/String;)Ljava/lang/Class;
      11: pop
      12: goto          22
      15: astore        4
      17: aload_0
      18: invokevirtual #27                 // Method java/lang/Class.getName:()Ljava/lang/String;
      21: areturn
      22: aload_3
      23: areturn
    Exception table:
       from    to  target type
           5    12    15   Class com/mchange/v1/lang/AmbiguousClassNameException

  public static java.lang.String fqcnLastElement(java.lang.String);
    Code:
       0: aload_0
       1: bipush        46
       3: invokevirtual #34                 // Method java/lang/String.lastIndexOf:(I)I
       6: istore_1
       7: iload_1
       8: ifge          13
      11: aload_0
      12: areturn
      13: aload_0
      14: iload_1
      15: iconst_1
      16: iadd
      17: invokevirtual #35                 // Method java/lang/String.substring:(I)Ljava/lang/String;
      20: areturn

  private static void addSuperInterfacesToSet(java.lang.Class, java.util.Set);
    Code:
       0: aload_0
       1: invokevirtual #68                 // Method java/lang/Class.getInterfaces:()[Ljava/lang/Class;
       4: astore_2
       5: iconst_0
       6: istore_3
       7: aload_2
       8: arraylength
       9: istore        4
      11: iload_3
      12: iload         4
      14: if_icmpge     40
      17: aload_1
      18: aload_2
      19: iload_3
      20: aaload
      21: invokeinterface #10,  2           // InterfaceMethod java/util/Set.add:(Ljava/lang/Object;)Z
      26: pop
      27: aload_2
      28: iload_3
      29: aaload
      30: aload_1
      31: invokestatic  #24                 // Method addSuperInterfacesToSet:(Ljava/lang/Class;Ljava/util/Set;)V
      34: iinc          3, 1
      37: goto          11
      40: return

  private com.mchange.v1.lang.ClassUtils();
    Code:
       0: aload_0
       1: invokespecial #69                 // Method java/lang/Object."<init>":()V
       4: return

  static {};
    Code:
       0: iconst_0
       1: anewarray     #70                 // class java/lang/String
       4: putstatic     #47                 // Field EMPTY_SA:[Ljava/lang/String;
       7: new           #71                 // class java/util/HashMap
      10: dup
      11: invokespecial #72                 // Method java/util/HashMap."<init>":()V
      14: astore_0
      15: aload_0
      16: ldc           #73                 // String boolean
      18: getstatic     #74                 // Field java/lang/Boolean.TYPE:Ljava/lang/Class;
      21: invokevirtual #75                 // Method java/util/HashMap.put:(Ljava/lang/Object;Ljava/lang/Object;)Ljava/lang/Object;
      24: pop
      25: aload_0
      26: ldc           #76                 // String int
      28: getstatic     #77                 // Field java/lang/Integer.TYPE:Ljava/lang/Class;
      31: invokevirtual #75                 // Method java/util/HashMap.put:(Ljava/lang/Object;Ljava/lang/Object;)Ljava/lang/Object;
      34: pop
      35: aload_0
      36: ldc           #78                 // String char
      38: getstatic     #79                 // Field java/lang/Character.TYPE:Ljava/lang/Class;
      41: invokevirtual #75                 // Method java/util/HashMap.put:(Ljava/lang/Object;Ljava/lang/Object;)Ljava/lang/Object;
      44: pop
      45: aload_0
      46: ldc           #80                 // String short
      48: getstatic     #81                 // Field java/lang/Short.TYPE:Ljava/lang/Class;
      51: invokevirtual #75                 // Method java/util/HashMap.put:(Ljava/lang/Object;Ljava/lang/Object;)Ljava/lang/Object;
      54: pop
      55: aload_0
      56: ldc           #76                 // String int
      58: getstatic     #77                 // Field java/lang/Integer.TYPE:Ljava/lang/Class;
      61: invokevirtual #75                 // Method java/util/HashMap.put:(Ljava/lang/Object;Ljava/lang/Object;)Ljava/lang/Object;
      64: pop
      65: aload_0
      66: ldc           #82                 // String long
      68: getstatic     #83                 // Field java/lang/Long.TYPE:Ljava/lang/Class;
      71: invokevirtual #75                 // Method java/util/HashMap.put:(Ljava/lang/Object;Ljava/lang/Object;)Ljava/lang/Object;
      74: pop
      75: aload_0
      76: ldc           #84                 // String float
      78: getstatic     #85                 // Field java/lang/Float.TYPE:Ljava/lang/Class;
      81: invokevirtual #75                 // Method java/util/HashMap.put:(Ljava/lang/Object;Ljava/lang/Object;)Ljava/lang/Object;
      84: pop
      85: aload_0
      86: ldc           #86                 // String double
      88: getstatic     #87                 // Field java/lang/Double.TYPE:Ljava/lang/Class;
      91: invokevirtual #75                 // Method java/util/HashMap.put:(Ljava/lang/Object;Ljava/lang/Object;)Ljava/lang/Object;
      94: pop
      95: aload_0
      96: ldc           #88                 // String void
      98: getstatic     #89                 // Field java/lang/Void.TYPE:Ljava/lang/Class;
     101: invokevirtual #75                 // Method java/util/HashMap.put:(Ljava/lang/Object;Ljava/lang/Object;)Ljava/lang/Object;
     104: pop
     105: aload_0
     106: invokestatic  #90                 // Method java/util/Collections.unmodifiableMap:(Ljava/util/Map;)Ljava/util/Map;
     109: putstatic     #41                 // Field primitivesToClasses:Ljava/util/Map;
     112: return
}
