Compiled from "DaemonMsgCreateSerializer.scala"
public final class akka.remote.serialization.DaemonMsgCreateSerializer$$anonfun$1 extends scala.runtime.AbstractFunction1<scala.Tuple2<akka.protobuf.ByteString, java.lang.String>, java.lang.Object> implements scala.Serializable {
  public static final long serialVersionUID;

  private final akka.remote.serialization.DaemonMsgCreateSerializer $outer;

  public final java.lang.Object apply(scala.Tuple2<akka.protobuf.ByteString, java.lang.String>);
    Code:
       0: aload_0
       1: getfield      #23                 // Field $outer:Lakka/remote/serialization/DaemonMsgCreateSerializer;
       4: aload_1
       5: invokevirtual #26                 // Method akka/remote/serialization/DaemonMsgCreateSerializer.deserialize:(Lscala/Tuple2;)Ljava/lang/Object;
       8: areturn

  public final java.lang.Object apply(java.lang.Object);
    Code:
       0: aload_0
       1: aload_1
       2: checkcast     #33                 // class scala/Tuple2
       5: invokevirtual #35                 // Method apply:(Lscala/Tuple2;)Ljava/lang/Object;
       8: areturn

  public akka.remote.serialization.DaemonMsgCreateSerializer$$anonfun$1(akka.remote.serialization.DaemonMsgCreateSerializer);
    Code:
       0: aload_1
       1: ifnonnull     6
       4: aconst_null
       5: athrow
       6: aload_0
       7: aload_1
       8: putfield      #23                 // Field $outer:Lakka/remote/serialization/DaemonMsgCreateSerializer;
      11: aload_0
      12: invokespecial #42                 // Method scala/runtime/AbstractFunction1."<init>":()V
      15: return
}
