Compiled from "AbstractJsseEndpoint.java"
public abstract class org.apache.tomcat.util.net.AbstractJsseEndpoint<S> extends org.apache.tomcat.util.net.AbstractEndpoint<S> {
  private java.lang.String sslImplementationName;

  private int sniParseLimit;

  private org.apache.tomcat.util.net.SSLImplementation sslImplementation;

  public org.apache.tomcat.util.net.AbstractJsseEndpoint();
    Code:
       0: aload_0
       1: invokespecial #1                  // Method org/apache/tomcat/util/net/AbstractEndpoint."<init>":()V
       4: aload_0
       5: aconst_null
       6: putfield      #2                  // Field sslImplementationName:Ljava/lang/String;
       9: aload_0
      10: ldc           #3                  // int 65536
      12: putfield      #4                  // Field sniParseLimit:I
      15: aload_0
      16: aconst_null
      17: putfield      #5                  // Field sslImplementation:Lorg/apache/tomcat/util/net/SSLImplementation;
      20: return

  public java.lang.String getSslImplementationName();
    Code:
       0: aload_0
       1: getfield      #2                  // Field sslImplementationName:Ljava/lang/String;
       4: areturn

  public void setSslImplementationName(java.lang.String);
    Code:
       0: aload_0
       1: aload_1
       2: putfield      #2                  // Field sslImplementationName:Ljava/lang/String;
       5: return

  public org.apache.tomcat.util.net.SSLImplementation getSslImplementation();
    Code:
       0: aload_0
       1: getfield      #5                  // Field sslImplementation:Lorg/apache/tomcat/util/net/SSLImplementation;
       4: areturn

  public int getSniParseLimit();
    Code:
       0: aload_0
       1: getfield      #4                  // Field sniParseLimit:I
       4: ireturn

  public void setSniParseLimit(int);
    Code:
       0: aload_0
       1: iload_1
       2: putfield      #4                  // Field sniParseLimit:I
       5: return

  protected org.apache.tomcat.util.net.SSLHostConfig$Type getSslConfigType();
    Code:
       0: ldc_w         #6                  // class org/apache/tomcat/util/net/openssl/OpenSSLImplementation
       3: invokevirtual #7                  // Method java/lang/Class.getName:()Ljava/lang/String;
       6: aload_0
       7: getfield      #2                  // Field sslImplementationName:Ljava/lang/String;
      10: invokevirtual #8                  // Method java/lang/String.equals:(Ljava/lang/Object;)Z
      13: ifeq          20
      16: getstatic     #9                  // Field org/apache/tomcat/util/net/SSLHostConfig$Type.EITHER:Lorg/apache/tomcat/util/net/SSLHostConfig$Type;
      19: areturn
      20: getstatic     #10                 // Field org/apache/tomcat/util/net/SSLHostConfig$Type.JSSE:Lorg/apache/tomcat/util/net/SSLHostConfig$Type;
      23: areturn

  protected void initialiseSsl() throws java.lang.Exception;
    Code:
       0: aload_0
       1: invokevirtual #11                 // Method isSSLEnabled:()Z
       4: ifeq          118
       7: aload_0
       8: aload_0
       9: invokevirtual #12                 // Method getSslImplementationName:()Ljava/lang/String;
      12: invokestatic  #13                 // Method org/apache/tomcat/util/net/SSLImplementation.getInstance:(Ljava/lang/String;)Lorg/apache/tomcat/util/net/SSLImplementation;
      15: putfield      #5                  // Field sslImplementation:Lorg/apache/tomcat/util/net/SSLImplementation;
      18: aload_0
      19: getfield      #14                 // Field sslHostConfigs:Ljava/util/concurrent/ConcurrentMap;
      22: invokeinterface #15,  1           // InterfaceMethod java/util/concurrent/ConcurrentMap.values:()Ljava/util/Collection;
      27: invokeinterface #16,  1           // InterfaceMethod java/util/Collection.iterator:()Ljava/util/Iterator;
      32: astore_1
      33: aload_1
      34: invokeinterface #17,  1           // InterfaceMethod java/util/Iterator.hasNext:()Z
      39: ifeq          68
      42: aload_1
      43: invokeinterface #18,  1           // InterfaceMethod java/util/Iterator.next:()Ljava/lang/Object;
      48: checkcast     #19                 // class org/apache/tomcat/util/net/SSLHostConfig
      51: astore_2
      52: aload_2
      53: aload_0
      54: invokevirtual #20                 // Method getSslConfigType:()Lorg/apache/tomcat/util/net/SSLHostConfig$Type;
      57: invokevirtual #21                 // Method org/apache/tomcat/util/net/SSLHostConfig.setConfigType:(Lorg/apache/tomcat/util/net/SSLHostConfig$Type;)V
      60: aload_0
      61: aload_2
      62: invokevirtual #22                 // Method createSSLContext:(Lorg/apache/tomcat/util/net/SSLHostConfig;)V
      65: goto          33
      68: aload_0
      69: getfield      #14                 // Field sslHostConfigs:Ljava/util/concurrent/ConcurrentMap;
      72: aload_0
      73: invokevirtual #23                 // Method getDefaultSSLHostConfigName:()Ljava/lang/String;
      76: invokeinterface #24,  2           // InterfaceMethod java/util/concurrent/ConcurrentMap.get:(Ljava/lang/Object;)Ljava/lang/Object;
      81: ifnonnull     118
      84: new           #25                 // class java/lang/IllegalArgumentException
      87: dup
      88: getstatic     #26                 // Field sm:Lorg/apache/tomcat/util/res/StringManager;
      91: ldc           #27                 // String endpoint.noSslHostConfig
      93: iconst_2
      94: anewarray     #28                 // class java/lang/Object
      97: dup
      98: iconst_0
      99: aload_0
     100: invokevirtual #23                 // Method getDefaultSSLHostConfigName:()Ljava/lang/String;
     103: aastore
     104: dup
     105: iconst_1
     106: aload_0
     107: invokevirtual #29                 // Method getName:()Ljava/lang/String;
     110: aastore
     111: invokevirtual #30                 // Method org/apache/tomcat/util/res/StringManager.getString:(Ljava/lang/String;[Ljava/lang/Object;)Ljava/lang/String;
     114: invokespecial #31                 // Method java/lang/IllegalArgumentException."<init>":(Ljava/lang/String;)V
     117: athrow
     118: return

  protected void createSSLContext(org.apache.tomcat.util.net.SSLHostConfig) throws java.lang.IllegalArgumentException;
    Code:
       0: iconst_1
       1: istore_2
       2: aload_1
       3: iconst_1
       4: invokevirtual #32                 // Method org/apache/tomcat/util/net/SSLHostConfig.getCertificates:(Z)Ljava/util/Set;
       7: invokeinterface #33,  1           // InterfaceMethod java/util/Set.iterator:()Ljava/util/Iterator;
      12: astore_3
      13: aload_3
      14: invokeinterface #17,  1           // InterfaceMethod java/util/Iterator.hasNext:()Z
      19: ifeq          160
      22: aload_3
      23: invokeinterface #18,  1           // InterfaceMethod java/util/Iterator.next:()Ljava/lang/Object;
      28: checkcast     #34                 // class org/apache/tomcat/util/net/SSLHostConfigCertificate
      31: astore        4
      33: aload_0
      34: getfield      #5                  // Field sslImplementation:Lorg/apache/tomcat/util/net/SSLImplementation;
      37: aload         4
      39: invokevirtual #35                 // Method org/apache/tomcat/util/net/SSLImplementation.getSSLUtil:(Lorg/apache/tomcat/util/net/SSLHostConfigCertificate;)Lorg/apache/tomcat/util/net/SSLUtil;
      42: astore        5
      44: iload_2
      45: ifeq          72
      48: iconst_0
      49: istore_2
      50: aload_1
      51: aload         5
      53: invokeinterface #36,  1           // InterfaceMethod org/apache/tomcat/util/net/SSLUtil.getEnabledProtocols:()[Ljava/lang/String;
      58: invokevirtual #37                 // Method org/apache/tomcat/util/net/SSLHostConfig.setEnabledProtocols:([Ljava/lang/String;)V
      61: aload_1
      62: aload         5
      64: invokeinterface #38,  1           // InterfaceMethod org/apache/tomcat/util/net/SSLUtil.getEnabledCiphers:()[Ljava/lang/String;
      69: invokevirtual #39                 // Method org/apache/tomcat/util/net/SSLHostConfig.setEnabledCiphers:([Ljava/lang/String;)V
      72: aload         5
      74: aload_0
      75: getfield      #40                 // Field negotiableProtocols:Ljava/util/List;
      78: invokeinterface #41,  2           // InterfaceMethod org/apache/tomcat/util/net/SSLUtil.createSSLContext:(Ljava/util/List;)Lorg/apache/tomcat/util/net/SSLContext;
      83: astore        6
      85: aload         6
      87: aload         5
      89: invokeinterface #42,  1           // InterfaceMethod org/apache/tomcat/util/net/SSLUtil.getKeyManagers:()[Ljavax/net/ssl/KeyManager;
      94: aload         5
      96: invokeinterface #43,  1           // InterfaceMethod org/apache/tomcat/util/net/SSLUtil.getTrustManagers:()[Ljavax/net/ssl/TrustManager;
     101: aconst_null
     102: invokeinterface #44,  4           // InterfaceMethod org/apache/tomcat/util/net/SSLContext.init:([Ljavax/net/ssl/KeyManager;[Ljavax/net/ssl/TrustManager;Ljava/security/SecureRandom;)V
     107: goto          127
     110: astore        7
     112: new           #25                 // class java/lang/IllegalArgumentException
     115: dup
     116: aload         7
     118: invokevirtual #46                 // Method java/lang/Exception.getMessage:()Ljava/lang/String;
     121: aload         7
     123: invokespecial #47                 // Method java/lang/IllegalArgumentException."<init>":(Ljava/lang/String;Ljava/lang/Throwable;)V
     126: athrow
     127: aload         6
     129: invokeinterface #48,  1           // InterfaceMethod org/apache/tomcat/util/net/SSLContext.getServerSessionContext:()Ljavax/net/ssl/SSLSessionContext;
     134: astore        7
     136: aload         7
     138: ifnull        150
     141: aload         5
     143: aload         7
     145: invokeinterface #49,  2           // InterfaceMethod org/apache/tomcat/util/net/SSLUtil.configureSessionContext:(Ljavax/net/ssl/SSLSessionContext;)V
     150: aload         4
     152: aload         6
     154: invokevirtual #50                 // Method org/apache/tomcat/util/net/SSLHostConfigCertificate.setSslContext:(Lorg/apache/tomcat/util/net/SSLContext;)V
     157: goto          13
     160: return
    Exception table:
       from    to  target type
          72   107   110   Class java/lang/Exception

  protected void destroySsl() throws java.lang.Exception;
    Code:
       0: aload_0
       1: invokevirtual #11                 // Method isSSLEnabled:()Z
       4: ifeq          49
       7: aload_0
       8: getfield      #14                 // Field sslHostConfigs:Ljava/util/concurrent/ConcurrentMap;
      11: invokeinterface #15,  1           // InterfaceMethod java/util/concurrent/ConcurrentMap.values:()Ljava/util/Collection;
      16: invokeinterface #16,  1           // InterfaceMethod java/util/Collection.iterator:()Ljava/util/Iterator;
      21: astore_1
      22: aload_1
      23: invokeinterface #17,  1           // InterfaceMethod java/util/Iterator.hasNext:()Z
      28: ifeq          49
      31: aload_1
      32: invokeinterface #18,  1           // InterfaceMethod java/util/Iterator.next:()Ljava/lang/Object;
      37: checkcast     #19                 // class org/apache/tomcat/util/net/SSLHostConfig
      40: astore_2
      41: aload_0
      42: aload_2
      43: invokevirtual #51                 // Method releaseSSLContext:(Lorg/apache/tomcat/util/net/SSLHostConfig;)V
      46: goto          22
      49: return

  protected void releaseSSLContext(org.apache.tomcat.util.net.SSLHostConfig);
    Code:
       0: aload_1
       1: iconst_1
       2: invokevirtual #32                 // Method org/apache/tomcat/util/net/SSLHostConfig.getCertificates:(Z)Ljava/util/Set;
       5: invokeinterface #33,  1           // InterfaceMethod java/util/Set.iterator:()Ljava/util/Iterator;
      10: astore_2
      11: aload_2
      12: invokeinterface #17,  1           // InterfaceMethod java/util/Iterator.hasNext:()Z
      17: ifeq          58
      20: aload_2
      21: invokeinterface #18,  1           // InterfaceMethod java/util/Iterator.next:()Ljava/lang/Object;
      26: checkcast     #34                 // class org/apache/tomcat/util/net/SSLHostConfigCertificate
      29: astore_3
      30: aload_3
      31: invokevirtual #52                 // Method org/apache/tomcat/util/net/SSLHostConfigCertificate.getSslContext:()Lorg/apache/tomcat/util/net/SSLContext;
      34: ifnull        55
      37: aload_3
      38: invokevirtual #52                 // Method org/apache/tomcat/util/net/SSLHostConfigCertificate.getSslContext:()Lorg/apache/tomcat/util/net/SSLContext;
      41: astore        4
      43: aload         4
      45: ifnull        55
      48: aload         4
      50: invokeinterface #53,  1           // InterfaceMethod org/apache/tomcat/util/net/SSLContext.destroy:()V
      55: goto          11
      58: return

  protected javax.net.ssl.SSLEngine createSSLEngine(java.lang.String, java.util.List<org.apache.tomcat.util.net.openssl.ciphers.Cipher>, java.util.List<java.lang.String>);
    Code:
       0: aload_0
       1: aload_1
       2: invokevirtual #54                 // Method getSSLHostConfig:(Ljava/lang/String;)Lorg/apache/tomcat/util/net/SSLHostConfig;
       5: astore        4
       7: aload_0
       8: aload         4
      10: aload_2
      11: invokespecial #55                 // Method selectCertificate:(Lorg/apache/tomcat/util/net/SSLHostConfig;Ljava/util/List;)Lorg/apache/tomcat/util/net/SSLHostConfigCertificate;
      14: astore        5
      16: aload         5
      18: invokevirtual #52                 // Method org/apache/tomcat/util/net/SSLHostConfigCertificate.getSslContext:()Lorg/apache/tomcat/util/net/SSLContext;
      21: astore        6
      23: aload         6
      25: ifnonnull     52
      28: new           #56                 // class java/lang/IllegalStateException
      31: dup
      32: getstatic     #26                 // Field sm:Lorg/apache/tomcat/util/res/StringManager;
      35: ldc           #57                 // String endpoint.jsse.noSslContext
      37: iconst_1
      38: anewarray     #28                 // class java/lang/Object
      41: dup
      42: iconst_0
      43: aload_1
      44: aastore
      45: invokevirtual #30                 // Method org/apache/tomcat/util/res/StringManager.getString:(Ljava/lang/String;[Ljava/lang/Object;)Ljava/lang/String;
      48: invokespecial #58                 // Method java/lang/IllegalStateException."<init>":(Ljava/lang/String;)V
      51: athrow
      52: aload         6
      54: invokeinterface #59,  1           // InterfaceMethod org/apache/tomcat/util/net/SSLContext.createSSLEngine:()Ljavax/net/ssl/SSLEngine;
      59: astore        7
      61: getstatic     #60                 // Field org/apache/tomcat/util/net/AbstractJsseEndpoint$1.$SwitchMap$org$apache$tomcat$util$net$SSLHostConfig$CertificateVerification:[I
      64: aload         4
      66: invokevirtual #61                 // Method org/apache/tomcat/util/net/SSLHostConfig.getCertificateVerification:()Lorg/apache/tomcat/util/net/SSLHostConfig$CertificateVerification;
      69: invokevirtual #62                 // Method org/apache/tomcat/util/net/SSLHostConfig$CertificateVerification.ordinal:()I
      72: iaload
      73: tableswitch   { // 1 to 4
                     1: 104
                     2: 119
                     3: 119
                     4: 128
               default: 134
          }
     104: aload         7
     106: iconst_0
     107: invokevirtual #63                 // Method javax/net/ssl/SSLEngine.setNeedClientAuth:(Z)V
     110: aload         7
     112: iconst_0
     113: invokevirtual #64                 // Method javax/net/ssl/SSLEngine.setWantClientAuth:(Z)V
     116: goto          134
     119: aload         7
     121: iconst_1
     122: invokevirtual #64                 // Method javax/net/ssl/SSLEngine.setWantClientAuth:(Z)V
     125: goto          134
     128: aload         7
     130: iconst_1
     131: invokevirtual #63                 // Method javax/net/ssl/SSLEngine.setNeedClientAuth:(Z)V
     134: aload         7
     136: iconst_0
     137: invokevirtual #65                 // Method javax/net/ssl/SSLEngine.setUseClientMode:(Z)V
     140: aload         7
     142: aload         4
     144: invokevirtual #66                 // Method org/apache/tomcat/util/net/SSLHostConfig.getEnabledCiphers:()[Ljava/lang/String;
     147: invokevirtual #67                 // Method javax/net/ssl/SSLEngine.setEnabledCipherSuites:([Ljava/lang/String;)V
     150: aload         7
     152: aload         4
     154: invokevirtual #68                 // Method org/apache/tomcat/util/net/SSLHostConfig.getEnabledProtocols:()[Ljava/lang/String;
     157: invokevirtual #69                 // Method javax/net/ssl/SSLEngine.setEnabledProtocols:([Ljava/lang/String;)V
     160: aload         4
     162: invokevirtual #70                 // Method org/apache/tomcat/util/net/SSLHostConfig.getHonorCipherOrder:()Ljava/lang/String;
     165: astore        8
     167: aload         8
     169: ifnull        189
     172: aload         8
     174: invokestatic  #71                 // Method java/lang/Boolean.parseBoolean:(Ljava/lang/String;)Z
     177: istore        9
     179: invokestatic  #72                 // Method org/apache/tomcat/util/compat/JreCompat.getInstance:()Lorg/apache/tomcat/util/compat/JreCompat;
     182: aload         7
     184: iload         9
     186: invokevirtual #73                 // Method org/apache/tomcat/util/compat/JreCompat.setUseServerCipherSuitesOrder:(Ljavax/net/ssl/SSLEngine;Z)V
     189: invokestatic  #74                 // Method org/apache/tomcat/util/compat/JreCompat.isJre9Available:()Z
     192: ifeq          306
     195: aload_3
     196: ifnull        306
     199: aload_3
     200: invokeinterface #75,  1           // InterfaceMethod java/util/List.size:()I
     205: ifle          306
     208: aload_0
     209: getfield      #40                 // Field negotiableProtocols:Ljava/util/List;
     212: invokeinterface #75,  1           // InterfaceMethod java/util/List.size:()I
     217: ifle          306
     220: aload         7
     222: invokevirtual #76                 // Method javax/net/ssl/SSLEngine.getSSLParameters:()Ljavax/net/ssl/SSLParameters;
     225: astore        9
     227: new           #77                 // class java/util/ArrayList
     230: dup
     231: invokespecial #78                 // Method java/util/ArrayList."<init>":()V
     234: astore        10
     236: aload         10
     238: aload_0
     239: getfield      #40                 // Field negotiableProtocols:Ljava/util/List;
     242: invokeinterface #79,  2           // InterfaceMethod java/util/List.addAll:(Ljava/util/Collection;)Z
     247: pop
     248: aload         10
     250: aload_3
     251: invokeinterface #80,  2           // InterfaceMethod java/util/List.retainAll:(Ljava/util/Collection;)Z
     256: pop
     257: aload         10
     259: invokeinterface #75,  1           // InterfaceMethod java/util/List.size:()I
     264: ifle          299
     267: aload         10
     269: aload         10
     271: invokeinterface #75,  1           // InterfaceMethod java/util/List.size:()I
     276: anewarray     #81                 // class java/lang/String
     279: invokeinterface #82,  2           // InterfaceMethod java/util/List.toArray:([Ljava/lang/Object;)[Ljava/lang/Object;
     284: checkcast     #83                 // class "[Ljava/lang/String;"
     287: astore        11
     289: invokestatic  #72                 // Method org/apache/tomcat/util/compat/JreCompat.getInstance:()Lorg/apache/tomcat/util/compat/JreCompat;
     292: aload         9
     294: aload         11
     296: invokevirtual #84                 // Method org/apache/tomcat/util/compat/JreCompat.setApplicationProtocols:(Ljavax/net/ssl/SSLParameters;[Ljava/lang/String;)V
     299: aload         7
     301: aload         9
     303: invokevirtual #85                 // Method javax/net/ssl/SSLEngine.setSSLParameters:(Ljavax/net/ssl/SSLParameters;)V
     306: aload         7
     308: areturn

  private org.apache.tomcat.util.net.SSLHostConfigCertificate selectCertificate(org.apache.tomcat.util.net.SSLHostConfig, java.util.List<org.apache.tomcat.util.net.openssl.ciphers.Cipher>);
    Code:
       0: aload_1
       1: iconst_1
       2: invokevirtual #32                 // Method org/apache/tomcat/util/net/SSLHostConfig.getCertificates:(Z)Ljava/util/Set;
       5: astore_3
       6: aload_3
       7: invokeinterface #86,  1           // InterfaceMethod java/util/Set.size:()I
      12: iconst_1
      13: if_icmpne     31
      16: aload_3
      17: invokeinterface #87,  1           // InterfaceMethod java/util/Set.iterator:()Ljava/util/Iterator;
      22: invokeinterface #18,  1           // InterfaceMethod java/util/Iterator.next:()Ljava/lang/Object;
      27: checkcast     #34                 // class org/apache/tomcat/util/net/SSLHostConfigCertificate
      30: areturn
      31: aload_1
      32: invokevirtual #88                 // Method org/apache/tomcat/util/net/SSLHostConfig.getCipherList:()Ljava/util/LinkedHashSet;
      35: astore        4
      37: new           #77                 // class java/util/ArrayList
      40: dup
      41: invokespecial #78                 // Method java/util/ArrayList."<init>":()V
      44: astore        5
      46: aload_1
      47: invokevirtual #70                 // Method org/apache/tomcat/util/net/SSLHostConfig.getHonorCipherOrder:()Ljava/lang/String;
      50: invokestatic  #71                 // Method java/lang/Boolean.parseBoolean:(Ljava/lang/String;)Z
      53: ifeq          78
      56: aload         5
      58: aload         4
      60: invokeinterface #79,  2           // InterfaceMethod java/util/List.addAll:(Ljava/util/Collection;)Z
      65: pop
      66: aload         5
      68: aload_2
      69: invokeinterface #80,  2           // InterfaceMethod java/util/List.retainAll:(Ljava/util/Collection;)Z
      74: pop
      75: goto          97
      78: aload         5
      80: aload_2
      81: invokeinterface #79,  2           // InterfaceMethod java/util/List.addAll:(Ljava/util/Collection;)Z
      86: pop
      87: aload         5
      89: aload         4
      91: invokeinterface #80,  2           // InterfaceMethod java/util/List.retainAll:(Ljava/util/Collection;)Z
      96: pop
      97: aload         5
      99: invokeinterface #89,  1           // InterfaceMethod java/util/List.iterator:()Ljava/util/Iterator;
     104: astore        6
     106: aload         6
     108: invokeinterface #17,  1           // InterfaceMethod java/util/Iterator.hasNext:()Z
     113: ifeq          183
     116: aload         6
     118: invokeinterface #18,  1           // InterfaceMethod java/util/Iterator.next:()Ljava/lang/Object;
     123: checkcast     #90                 // class org/apache/tomcat/util/net/openssl/ciphers/Cipher
     126: astore        7
     128: aload_3
     129: invokeinterface #33,  1           // InterfaceMethod java/util/Set.iterator:()Ljava/util/Iterator;
     134: astore        8
     136: aload         8
     138: invokeinterface #17,  1           // InterfaceMethod java/util/Iterator.hasNext:()Z
     143: ifeq          180
     146: aload         8
     148: invokeinterface #18,  1           // InterfaceMethod java/util/Iterator.next:()Ljava/lang/Object;
     153: checkcast     #34                 // class org/apache/tomcat/util/net/SSLHostConfigCertificate
     156: astore        9
     158: aload         9
     160: invokevirtual #91                 // Method org/apache/tomcat/util/net/SSLHostConfigCertificate.getType:()Lorg/apache/tomcat/util/net/SSLHostConfigCertificate$Type;
     163: aload         7
     165: invokevirtual #92                 // Method org/apache/tomcat/util/net/openssl/ciphers/Cipher.getAu:()Lorg/apache/tomcat/util/net/openssl/ciphers/Authentication;
     168: invokevirtual #93                 // Method org/apache/tomcat/util/net/SSLHostConfigCertificate$Type.isCompatibleWith:(Lorg/apache/tomcat/util/net/openssl/ciphers/Authentication;)Z
     171: ifeq          177
     174: aload         9
     176: areturn
     177: goto          136
     180: goto          106
     183: aload_3
     184: invokeinterface #87,  1           // InterfaceMethod java/util/Set.iterator:()Ljava/util/Iterator;
     189: invokeinterface #18,  1           // InterfaceMethod java/util/Iterator.next:()Ljava/lang/Object;
     194: checkcast     #34                 // class org/apache/tomcat/util/net/SSLHostConfigCertificate
     197: areturn

  public boolean isAlpnSupported();
    Code:
       0: aload_0
       1: invokevirtual #11                 // Method isSSLEnabled:()Z
       4: ifne          9
       7: iconst_0
       8: ireturn
       9: aload_0
      10: invokevirtual #12                 // Method getSslImplementationName:()Ljava/lang/String;
      13: invokestatic  #13                 // Method org/apache/tomcat/util/net/SSLImplementation.getInstance:(Ljava/lang/String;)Lorg/apache/tomcat/util/net/SSLImplementation;
      16: astore_1
      17: goto          23
      20: astore_2
      21: iconst_0
      22: ireturn
      23: aload_1
      24: invokevirtual #95                 // Method org/apache/tomcat/util/net/SSLImplementation.isAlpnSupported:()Z
      27: ireturn
    Exception table:
       from    to  target type
           9    17    20   Class java/lang/ClassNotFoundException

  public void init() throws java.lang.Exception;
    Code:
       0: aload_0
       1: invokespecial #96                 // Method testServerCipherSuitesOrderSupport:()V
       4: aload_0
       5: invokespecial #97                 // Method org/apache/tomcat/util/net/AbstractEndpoint.init:()V
       8: return

  private void testServerCipherSuitesOrderSupport();
    Code:
       0: invokestatic  #98                 // Method org/apache/tomcat/util/compat/JreCompat.isJre8Available:()Z
       3: ifne          82
       6: ldc_w         #6                  // class org/apache/tomcat/util/net/openssl/OpenSSLImplementation
       9: invokevirtual #7                  // Method java/lang/Class.getName:()Ljava/lang/String;
      12: aload_0
      13: invokevirtual #12                 // Method getSslImplementationName:()Ljava/lang/String;
      16: invokevirtual #8                  // Method java/lang/String.equals:(Ljava/lang/Object;)Z
      19: ifne          82
      22: aload_0
      23: getfield      #14                 // Field sslHostConfigs:Ljava/util/concurrent/ConcurrentMap;
      26: invokeinterface #15,  1           // InterfaceMethod java/util/concurrent/ConcurrentMap.values:()Ljava/util/Collection;
      31: invokeinterface #16,  1           // InterfaceMethod java/util/Collection.iterator:()Ljava/util/Iterator;
      36: astore_1
      37: aload_1
      38: invokeinterface #17,  1           // InterfaceMethod java/util/Iterator.hasNext:()Z
      43: ifeq          82
      46: aload_1
      47: invokeinterface #18,  1           // InterfaceMethod java/util/Iterator.next:()Ljava/lang/Object;
      52: checkcast     #19                 // class org/apache/tomcat/util/net/SSLHostConfig
      55: astore_2
      56: aload_2
      57: invokevirtual #70                 // Method org/apache/tomcat/util/net/SSLHostConfig.getHonorCipherOrder:()Ljava/lang/String;
      60: ifnull        79
      63: new           #99                 // class java/lang/UnsupportedOperationException
      66: dup
      67: getstatic     #26                 // Field sm:Lorg/apache/tomcat/util/res/StringManager;
      70: ldc           #100                // String endpoint.jsse.cannotHonorServerCipherOrder
      72: invokevirtual #101                // Method org/apache/tomcat/util/res/StringManager.getString:(Ljava/lang/String;)Ljava/lang/String;
      75: invokespecial #102                // Method java/lang/UnsupportedOperationException."<init>":(Ljava/lang/String;)V
      78: athrow
      79: goto          37
      82: return

  public void unbind() throws java.lang.Exception;
    Code:
       0: aload_0
       1: getfield      #14                 // Field sslHostConfigs:Ljava/util/concurrent/ConcurrentMap;
       4: invokeinterface #15,  1           // InterfaceMethod java/util/concurrent/ConcurrentMap.values:()Ljava/util/Collection;
       9: invokeinterface #16,  1           // InterfaceMethod java/util/Collection.iterator:()Ljava/util/Iterator;
      14: astore_1
      15: aload_1
      16: invokeinterface #17,  1           // InterfaceMethod java/util/Iterator.hasNext:()Z
      21: ifeq          77
      24: aload_1
      25: invokeinterface #18,  1           // InterfaceMethod java/util/Iterator.next:()Ljava/lang/Object;
      30: checkcast     #19                 // class org/apache/tomcat/util/net/SSLHostConfig
      33: astore_2
      34: aload_2
      35: iconst_1
      36: invokevirtual #32                 // Method org/apache/tomcat/util/net/SSLHostConfig.getCertificates:(Z)Ljava/util/Set;
      39: invokeinterface #33,  1           // InterfaceMethod java/util/Set.iterator:()Ljava/util/Iterator;
      44: astore_3
      45: aload_3
      46: invokeinterface #17,  1           // InterfaceMethod java/util/Iterator.hasNext:()Z
      51: ifeq          74
      54: aload_3
      55: invokeinterface #18,  1           // InterfaceMethod java/util/Iterator.next:()Ljava/lang/Object;
      60: checkcast     #34                 // class org/apache/tomcat/util/net/SSLHostConfigCertificate
      63: astore        4
      65: aload         4
      67: aconst_null
      68: invokevirtual #50                 // Method org/apache/tomcat/util/net/SSLHostConfigCertificate.setSslContext:(Lorg/apache/tomcat/util/net/SSLContext;)V
      71: goto          45
      74: goto          15
      77: return

  protected abstract java.nio.channels.NetworkChannel getServerSocket();

  protected final java.net.InetSocketAddress getLocalAddress() throws java.io.IOException;
    Code:
       0: aload_0
       1: invokevirtual #103                // Method getServerSocket:()Ljava/nio/channels/NetworkChannel;
       4: astore_1
       5: aload_1
       6: ifnonnull     11
       9: aconst_null
      10: areturn
      11: aload_1
      12: invokeinterface #104,  1          // InterfaceMethod java/nio/channels/NetworkChannel.getLocalAddress:()Ljava/net/SocketAddress;
      17: astore_2
      18: aload_2
      19: instanceof    #105                // class java/net/InetSocketAddress
      22: ifeq          30
      25: aload_2
      26: checkcast     #105                // class java/net/InetSocketAddress
      29: areturn
      30: aconst_null
      31: areturn
}
