Compiled from "AprEndpoint.java"
public class org.apache.tomcat.util.net.AprEndpoint$Poller implements java.lang.Runnable {
  private long[] pollers;

  private int actualPollerSize;

  private int[] pollerSpace;

  private int pollerCount;

  private int pollerTime;

  private int nextPollerTime;

  private long pool;

  private long[] desc;

  private org.apache.tomcat.util.net.AprEndpoint$SocketList addList;

  private org.apache.tomcat.util.net.AprEndpoint$SocketList closeList;

  private org.apache.tomcat.util.net.AprEndpoint$SocketTimeouts timeouts;

  private long lastMaintain;

  private java.util.concurrent.atomic.AtomicInteger connectionCount;

  private volatile boolean pollerRunning;

  final org.apache.tomcat.util.net.AprEndpoint this$0;

  public org.apache.tomcat.util.net.AprEndpoint$Poller(org.apache.tomcat.util.net.AprEndpoint);
    Code:
       0: aload_0
       1: aload_1
       2: putfield      #3                  // Field this$0:Lorg/apache/tomcat/util/net/AprEndpoint;
       5: aload_0
       6: invokespecial #4                  // Method java/lang/Object."<init>":()V
       9: aload_0
      10: aconst_null
      11: putfield      #5                  // Field pollers:[J
      14: aload_0
      15: iconst_0
      16: putfield      #6                  // Field actualPollerSize:I
      19: aload_0
      20: aconst_null
      21: putfield      #7                  // Field pollerSpace:[I
      24: aload_0
      25: lconst_0
      26: putfield      #8                  // Field pool:J
      29: aload_0
      30: aconst_null
      31: putfield      #9                  // Field addList:Lorg/apache/tomcat/util/net/AprEndpoint$SocketList;
      34: aload_0
      35: aconst_null
      36: putfield      #10                 // Field closeList:Lorg/apache/tomcat/util/net/AprEndpoint$SocketList;
      39: aload_0
      40: aconst_null
      41: putfield      #11                 // Field timeouts:Lorg/apache/tomcat/util/net/AprEndpoint$SocketTimeouts;
      44: aload_0
      45: invokestatic  #12                 // Method java/lang/System.currentTimeMillis:()J
      48: putfield      #13                 // Field lastMaintain:J
      51: aload_0
      52: new           #14                 // class java/util/concurrent/atomic/AtomicInteger
      55: dup
      56: iconst_0
      57: invokespecial #15                 // Method java/util/concurrent/atomic/AtomicInteger."<init>":(I)V
      60: putfield      #16                 // Field connectionCount:Ljava/util/concurrent/atomic/AtomicInteger;
      63: aload_0
      64: iconst_1
      65: putfield      #17                 // Field pollerRunning:Z
      68: return

  public int getConnectionCount();
    Code:
       0: aload_0
       1: getfield      #16                 // Field connectionCount:Ljava/util/concurrent/atomic/AtomicInteger;
       4: invokevirtual #18                 // Method java/util/concurrent/atomic/AtomicInteger.get:()I
       7: ireturn

  protected synchronized void init();
    Code:
       0: aload_0
       1: aload_0
       2: getfield      #3                  // Field this$0:Lorg/apache/tomcat/util/net/AprEndpoint;
       5: getfield      #19                 // Field org/apache/tomcat/util/net/AprEndpoint.serverSockPool:J
       8: invokestatic  #20                 // Method org/apache/tomcat/jni/Pool.create:(J)J
      11: putfield      #8                  // Field pool:J
      14: aload_0
      15: getfield      #3                  // Field this$0:Lorg/apache/tomcat/util/net/AprEndpoint;
      18: invokevirtual #21                 // Method org/apache/tomcat/util/net/AprEndpoint.getMaxConnections:()I
      21: istore_1
      22: getstatic     #22                 // Field org/apache/tomcat/jni/OS.IS_WIN32:Z
      25: ifne          34
      28: getstatic     #23                 // Field org/apache/tomcat/jni/OS.IS_WIN64:Z
      31: ifeq          51
      34: iload_1
      35: sipush        1024
      38: if_icmple     51
      41: aload_0
      42: sipush        1024
      45: putfield      #6                  // Field actualPollerSize:I
      48: goto          56
      51: aload_0
      52: iload_1
      53: putfield      #6                  // Field actualPollerSize:I
      56: aload_0
      57: new           #24                 // class org/apache/tomcat/util/net/AprEndpoint$SocketTimeouts
      60: dup
      61: iload_1
      62: invokespecial #25                 // Method org/apache/tomcat/util/net/AprEndpoint$SocketTimeouts."<init>":(I)V
      65: putfield      #11                 // Field timeouts:Lorg/apache/tomcat/util/net/AprEndpoint$SocketTimeouts;
      68: aload_0
      69: getfield      #3                  // Field this$0:Lorg/apache/tomcat/util/net/AprEndpoint;
      72: aload_0
      73: getfield      #6                  // Field actualPollerSize:I
      76: aload_0
      77: getfield      #8                  // Field pool:J
      80: iconst_m1
      81: invokevirtual #26                 // Method org/apache/tomcat/util/net/AprEndpoint.allocatePoller:(IJI)J
      84: lstore_2
      85: lload_2
      86: lconst_0
      87: lcmp
      88: ifne          125
      91: aload_0
      92: getfield      #6                  // Field actualPollerSize:I
      95: sipush        1024
      98: if_icmple     125
     101: aload_0
     102: sipush        1024
     105: putfield      #6                  // Field actualPollerSize:I
     108: aload_0
     109: getfield      #3                  // Field this$0:Lorg/apache/tomcat/util/net/AprEndpoint;
     112: aload_0
     113: getfield      #6                  // Field actualPollerSize:I
     116: aload_0
     117: getfield      #8                  // Field pool:J
     120: iconst_m1
     121: invokevirtual #26                 // Method org/apache/tomcat/util/net/AprEndpoint.allocatePoller:(IJI)J
     124: lstore_2
     125: lload_2
     126: lconst_0
     127: lcmp
     128: ifne          154
     131: aload_0
     132: bipush        62
     134: putfield      #6                  // Field actualPollerSize:I
     137: aload_0
     138: getfield      #3                  // Field this$0:Lorg/apache/tomcat/util/net/AprEndpoint;
     141: aload_0
     142: getfield      #6                  // Field actualPollerSize:I
     145: aload_0
     146: getfield      #8                  // Field pool:J
     149: iconst_m1
     150: invokevirtual #26                 // Method org/apache/tomcat/util/net/AprEndpoint.allocatePoller:(IJI)J
     153: lstore_2
     154: aload_0
     155: iload_1
     156: aload_0
     157: getfield      #6                  // Field actualPollerSize:I
     160: idiv
     161: putfield      #27                 // Field pollerCount:I
     164: aload_0
     165: aload_0
     166: getfield      #3                  // Field this$0:Lorg/apache/tomcat/util/net/AprEndpoint;
     169: getfield      #28                 // Field org/apache/tomcat/util/net/AprEndpoint.pollTime:I
     172: aload_0
     173: getfield      #27                 // Field pollerCount:I
     176: idiv
     177: putfield      #29                 // Field pollerTime:I
     180: aload_0
     181: aload_0
     182: getfield      #29                 // Field pollerTime:I
     185: putfield      #30                 // Field nextPollerTime:I
     188: aload_0
     189: aload_0
     190: getfield      #27                 // Field pollerCount:I
     193: newarray       long
     195: putfield      #5                  // Field pollers:[J
     198: aload_0
     199: getfield      #5                  // Field pollers:[J
     202: iconst_0
     203: lload_2
     204: lastore
     205: iconst_1
     206: istore        4
     208: iload         4
     210: aload_0
     211: getfield      #27                 // Field pollerCount:I
     214: if_icmpge     246
     217: aload_0
     218: getfield      #5                  // Field pollers:[J
     221: iload         4
     223: aload_0
     224: getfield      #3                  // Field this$0:Lorg/apache/tomcat/util/net/AprEndpoint;
     227: aload_0
     228: getfield      #6                  // Field actualPollerSize:I
     231: aload_0
     232: getfield      #8                  // Field pool:J
     235: iconst_m1
     236: invokevirtual #26                 // Method org/apache/tomcat/util/net/AprEndpoint.allocatePoller:(IJI)J
     239: lastore
     240: iinc          4, 1
     243: goto          208
     246: aload_0
     247: aload_0
     248: getfield      #27                 // Field pollerCount:I
     251: newarray       int
     253: putfield      #7                  // Field pollerSpace:[I
     256: iconst_0
     257: istore        4
     259: iload         4
     261: aload_0
     262: getfield      #27                 // Field pollerCount:I
     265: if_icmpge     285
     268: aload_0
     269: getfield      #7                  // Field pollerSpace:[I
     272: iload         4
     274: aload_0
     275: getfield      #6                  // Field actualPollerSize:I
     278: iastore
     279: iinc          4, 1
     282: goto          259
     285: aload_0
     286: aload_0
     287: getfield      #6                  // Field actualPollerSize:I
     290: iconst_4
     291: imul
     292: newarray       long
     294: putfield      #31                 // Field desc:[J
     297: aload_0
     298: getfield      #16                 // Field connectionCount:Ljava/util/concurrent/atomic/AtomicInteger;
     301: iconst_0
     302: invokevirtual #32                 // Method java/util/concurrent/atomic/AtomicInteger.set:(I)V
     305: aload_0
     306: new           #33                 // class org/apache/tomcat/util/net/AprEndpoint$SocketList
     309: dup
     310: iload_1
     311: invokespecial #34                 // Method org/apache/tomcat/util/net/AprEndpoint$SocketList."<init>":(I)V
     314: putfield      #9                  // Field addList:Lorg/apache/tomcat/util/net/AprEndpoint$SocketList;
     317: aload_0
     318: new           #33                 // class org/apache/tomcat/util/net/AprEndpoint$SocketList
     321: dup
     322: iload_1
     323: invokespecial #34                 // Method org/apache/tomcat/util/net/AprEndpoint$SocketList."<init>":(I)V
     326: putfield      #10                 // Field closeList:Lorg/apache/tomcat/util/net/AprEndpoint$SocketList;
     329: return

  protected synchronized void stop();
    Code:
       0: aload_0
       1: iconst_0
       2: putfield      #17                 // Field pollerRunning:Z
       5: return

  protected synchronized void destroy();
    Code:
       0: aload_0
       1: invokevirtual #35                 // Method java/lang/Object.notify:()V
       4: aload_0
       5: aload_0
       6: getfield      #27                 // Field pollerCount:I
       9: aload_0
      10: getfield      #3                  // Field this$0:Lorg/apache/tomcat/util/net/AprEndpoint;
      13: getfield      #28                 // Field org/apache/tomcat/util/net/AprEndpoint.pollTime:I
      16: imul
      17: sipush        1000
      20: idiv
      21: i2l
      22: invokevirtual #36                 // Method java/lang/Object.wait:(J)V
      25: goto          29
      28: astore_1
      29: aload_0
      30: getfield      #10                 // Field closeList:Lorg/apache/tomcat/util/net/AprEndpoint$SocketList;
      33: invokevirtual #38                 // Method org/apache/tomcat/util/net/AprEndpoint$SocketList.get:()Lorg/apache/tomcat/util/net/AprEndpoint$SocketInfo;
      36: astore_1
      37: aload_1
      38: ifnull        83
      41: aload_0
      42: getfield      #9                  // Field addList:Lorg/apache/tomcat/util/net/AprEndpoint$SocketList;
      45: aload_1
      46: getfield      #39                 // Field org/apache/tomcat/util/net/AprEndpoint$SocketInfo.socket:J
      49: invokevirtual #40                 // Method org/apache/tomcat/util/net/AprEndpoint$SocketList.remove:(J)Z
      52: pop
      53: aload_0
      54: aload_1
      55: getfield      #39                 // Field org/apache/tomcat/util/net/AprEndpoint$SocketInfo.socket:J
      58: invokespecial #41                 // Method removeFromPoller:(J)V
      61: aload_0
      62: getfield      #3                  // Field this$0:Lorg/apache/tomcat/util/net/AprEndpoint;
      65: aload_1
      66: getfield      #39                 // Field org/apache/tomcat/util/net/AprEndpoint$SocketInfo.socket:J
      69: invokestatic  #42                 // Method org/apache/tomcat/util/net/AprEndpoint.access$100:(Lorg/apache/tomcat/util/net/AprEndpoint;J)V
      72: aload_0
      73: getfield      #10                 // Field closeList:Lorg/apache/tomcat/util/net/AprEndpoint$SocketList;
      76: invokevirtual #38                 // Method org/apache/tomcat/util/net/AprEndpoint$SocketList.get:()Lorg/apache/tomcat/util/net/AprEndpoint$SocketInfo;
      79: astore_1
      80: goto          37
      83: aload_0
      84: getfield      #10                 // Field closeList:Lorg/apache/tomcat/util/net/AprEndpoint$SocketList;
      87: invokevirtual #43                 // Method org/apache/tomcat/util/net/AprEndpoint$SocketList.clear:()V
      90: aload_0
      91: getfield      #9                  // Field addList:Lorg/apache/tomcat/util/net/AprEndpoint$SocketList;
      94: invokevirtual #38                 // Method org/apache/tomcat/util/net/AprEndpoint$SocketList.get:()Lorg/apache/tomcat/util/net/AprEndpoint$SocketInfo;
      97: astore_1
      98: aload_1
      99: ifnull        132
     102: aload_0
     103: aload_1
     104: getfield      #39                 // Field org/apache/tomcat/util/net/AprEndpoint$SocketInfo.socket:J
     107: invokespecial #41                 // Method removeFromPoller:(J)V
     110: aload_0
     111: getfield      #3                  // Field this$0:Lorg/apache/tomcat/util/net/AprEndpoint;
     114: aload_1
     115: getfield      #39                 // Field org/apache/tomcat/util/net/AprEndpoint$SocketInfo.socket:J
     118: invokestatic  #42                 // Method org/apache/tomcat/util/net/AprEndpoint.access$100:(Lorg/apache/tomcat/util/net/AprEndpoint;J)V
     121: aload_0
     122: getfield      #9                  // Field addList:Lorg/apache/tomcat/util/net/AprEndpoint$SocketList;
     125: invokevirtual #38                 // Method org/apache/tomcat/util/net/AprEndpoint$SocketList.get:()Lorg/apache/tomcat/util/net/AprEndpoint$SocketInfo;
     128: astore_1
     129: goto          98
     132: aload_0
     133: getfield      #9                  // Field addList:Lorg/apache/tomcat/util/net/AprEndpoint$SocketList;
     136: invokevirtual #43                 // Method org/apache/tomcat/util/net/AprEndpoint$SocketList.clear:()V
     139: iconst_0
     140: istore_2
     141: iload_2
     142: aload_0
     143: getfield      #27                 // Field pollerCount:I
     146: if_icmpge     206
     149: aload_0
     150: getfield      #5                  // Field pollers:[J
     153: iload_2
     154: laload
     155: aload_0
     156: getfield      #31                 // Field desc:[J
     159: invokestatic  #44                 // Method org/apache/tomcat/jni/Poll.pollset:(J[J)I
     162: istore_3
     163: iload_3
     164: ifle          200
     167: iconst_0
     168: istore        4
     170: iload         4
     172: iload_3
     173: if_icmpge     200
     176: aload_0
     177: getfield      #3                  // Field this$0:Lorg/apache/tomcat/util/net/AprEndpoint;
     180: aload_0
     181: getfield      #31                 // Field desc:[J
     184: iload         4
     186: iconst_2
     187: imul
     188: iconst_1
     189: iadd
     190: laload
     191: invokestatic  #42                 // Method org/apache/tomcat/util/net/AprEndpoint.access$100:(Lorg/apache/tomcat/util/net/AprEndpoint;J)V
     194: iinc          4, 1
     197: goto          170
     200: iinc          2, 1
     203: goto          141
     206: aload_0
     207: getfield      #8                  // Field pool:J
     210: invokestatic  #45                 // Method org/apache/tomcat/jni/Pool.destroy:(J)V
     213: aload_0
     214: getfield      #16                 // Field connectionCount:Ljava/util/concurrent/atomic/AtomicInteger;
     217: iconst_0
     218: invokevirtual #32                 // Method java/util/concurrent/atomic/AtomicInteger.set:(I)V
     221: return
    Exception table:
       from    to  target type
           0    25    28   Class java/lang/InterruptedException

  private void add(long, long, int);
    Code:
       0: invokestatic  #46                 // Method org/apache/tomcat/util/net/AprEndpoint.access$200:()Lorg/apache/juli/logging/Log;
       3: invokeinterface #47,  1           // InterfaceMethod org/apache/juli/logging/Log.isDebugEnabled:()Z
       8: ifeq          88
      11: getstatic     #48                 // Field org/apache/tomcat/util/net/AbstractEndpoint.sm:Lorg/apache/tomcat/util/res/StringManager;
      14: ldc           #49                 // String endpoint.debug.pollerAdd
      16: iconst_3
      17: anewarray     #50                 // class java/lang/Object
      20: dup
      21: iconst_0
      22: lload_1
      23: invokestatic  #51                 // Method java/lang/Long.valueOf:(J)Ljava/lang/Long;
      26: aastore
      27: dup
      28: iconst_1
      29: lload_3
      30: invokestatic  #51                 // Method java/lang/Long.valueOf:(J)Ljava/lang/Long;
      33: aastore
      34: dup
      35: iconst_2
      36: iload         5
      38: invokestatic  #52                 // Method java/lang/Integer.valueOf:(I)Ljava/lang/Integer;
      41: aastore
      42: invokevirtual #53                 // Method org/apache/tomcat/util/res/StringManager.getString:(Ljava/lang/String;[Ljava/lang/Object;)Ljava/lang/String;
      45: astore        6
      47: invokestatic  #46                 // Method org/apache/tomcat/util/net/AprEndpoint.access$200:()Lorg/apache/juli/logging/Log;
      50: invokeinterface #54,  1           // InterfaceMethod org/apache/juli/logging/Log.isTraceEnabled:()Z
      55: ifeq          78
      58: invokestatic  #46                 // Method org/apache/tomcat/util/net/AprEndpoint.access$200:()Lorg/apache/juli/logging/Log;
      61: aload         6
      63: new           #55                 // class java/lang/Exception
      66: dup
      67: invokespecial #56                 // Method java/lang/Exception."<init>":()V
      70: invokeinterface #57,  3           // InterfaceMethod org/apache/juli/logging/Log.trace:(Ljava/lang/Object;Ljava/lang/Throwable;)V
      75: goto          88
      78: invokestatic  #46                 // Method org/apache/tomcat/util/net/AprEndpoint.access$200:()Lorg/apache/juli/logging/Log;
      81: aload         6
      83: invokeinterface #58,  2           // InterfaceMethod org/apache/juli/logging/Log.debug:(Ljava/lang/Object;)V
      88: lload_3
      89: lconst_0
      90: lcmp
      91: ifgt          98
      94: ldc2_w        #59                 // long 2147483647l
      97: lstore_3
      98: aload_0
      99: dup
     100: astore        6
     102: monitorenter
     103: aload_0
     104: getfield      #9                  // Field addList:Lorg/apache/tomcat/util/net/AprEndpoint$SocketList;
     107: lload_1
     108: lload_3
     109: iload         5
     111: invokevirtual #61                 // Method org/apache/tomcat/util/net/AprEndpoint$SocketList.add:(JJI)Z
     114: ifeq          121
     117: aload_0
     118: invokevirtual #35                 // Method java/lang/Object.notify:()V
     121: aload         6
     123: monitorexit
     124: goto          135
     127: astore        7
     129: aload         6
     131: monitorexit
     132: aload         7
     134: athrow
     135: return
    Exception table:
       from    to  target type
         103   124   127   any
         127   132   127   any

  private boolean addToPoller(long, int);
    Code:
       0: iconst_m1
       1: istore        4
       3: iconst_0
       4: istore        5
       6: iload         5
       8: aload_0
       9: getfield      #5                  // Field pollers:[J
      12: arraylength
      13: if_icmpge     72
      16: aload_0
      17: getfield      #7                  // Field pollerSpace:[I
      20: iload         5
      22: iaload
      23: ifle          66
      26: aload_0
      27: getfield      #5                  // Field pollers:[J
      30: iload         5
      32: laload
      33: lload_1
      34: iload_3
      35: invokestatic  #62                 // Method org/apache/tomcat/jni/Poll.add:(JJI)I
      38: istore        4
      40: iload         4
      42: ifne          66
      45: aload_0
      46: getfield      #7                  // Field pollerSpace:[I
      49: iload         5
      51: dup2
      52: iaload
      53: iconst_1
      54: isub
      55: iastore
      56: aload_0
      57: getfield      #16                 // Field connectionCount:Ljava/util/concurrent/atomic/AtomicInteger;
      60: invokevirtual #63                 // Method java/util/concurrent/atomic/AtomicInteger.incrementAndGet:()I
      63: pop
      64: iconst_1
      65: ireturn
      66: iinc          5, 1
      69: goto          6
      72: iconst_0
      73: ireturn

  private synchronized void close(long);
    Code:
       0: aload_0
       1: getfield      #10                 // Field closeList:Lorg/apache/tomcat/util/net/AprEndpoint$SocketList;
       4: lload_1
       5: lconst_0
       6: iconst_0
       7: invokevirtual #61                 // Method org/apache/tomcat/util/net/AprEndpoint$SocketList.add:(JJI)Z
      10: pop
      11: aload_0
      12: invokevirtual #35                 // Method java/lang/Object.notify:()V
      15: return

  private void removeFromPoller(long);
    Code:
       0: invokestatic  #46                 // Method org/apache/tomcat/util/net/AprEndpoint.access$200:()Lorg/apache/juli/logging/Log;
       3: invokeinterface #47,  1           // InterfaceMethod org/apache/juli/logging/Log.isDebugEnabled:()Z
       8: ifeq          38
      11: invokestatic  #46                 // Method org/apache/tomcat/util/net/AprEndpoint.access$200:()Lorg/apache/juli/logging/Log;
      14: getstatic     #48                 // Field org/apache/tomcat/util/net/AbstractEndpoint.sm:Lorg/apache/tomcat/util/res/StringManager;
      17: ldc           #64                 // String endpoint.debug.pollerRemove
      19: iconst_1
      20: anewarray     #50                 // class java/lang/Object
      23: dup
      24: iconst_0
      25: lload_1
      26: invokestatic  #51                 // Method java/lang/Long.valueOf:(J)Ljava/lang/Long;
      29: aastore
      30: invokevirtual #53                 // Method org/apache/tomcat/util/res/StringManager.getString:(Ljava/lang/String;[Ljava/lang/Object;)Ljava/lang/String;
      33: invokeinterface #58,  2           // InterfaceMethod org/apache/juli/logging/Log.debug:(Ljava/lang/Object;)V
      38: iconst_m1
      39: istore_3
      40: iconst_0
      41: istore        4
      43: iload         4
      45: aload_0
      46: getfield      #5                  // Field pollers:[J
      49: arraylength
      50: if_icmpge     151
      53: aload_0
      54: getfield      #7                  // Field pollerSpace:[I
      57: iload         4
      59: iaload
      60: aload_0
      61: getfield      #6                  // Field actualPollerSize:I
      64: if_icmpge     145
      67: aload_0
      68: getfield      #5                  // Field pollers:[J
      71: iload         4
      73: laload
      74: lload_1
      75: invokestatic  #65                 // Method org/apache/tomcat/jni/Poll.remove:(JJ)I
      78: istore_3
      79: iload_3
      80: ldc           #66                 // int 70015
      82: if_icmpeq     145
      85: aload_0
      86: getfield      #7                  // Field pollerSpace:[I
      89: iload         4
      91: dup2
      92: iaload
      93: iconst_1
      94: iadd
      95: iastore
      96: aload_0
      97: getfield      #16                 // Field connectionCount:Ljava/util/concurrent/atomic/AtomicInteger;
     100: invokevirtual #67                 // Method java/util/concurrent/atomic/AtomicInteger.decrementAndGet:()I
     103: pop
     104: invokestatic  #46                 // Method org/apache/tomcat/util/net/AprEndpoint.access$200:()Lorg/apache/juli/logging/Log;
     107: invokeinterface #47,  1           // InterfaceMethod org/apache/juli/logging/Log.isDebugEnabled:()Z
     112: ifeq          151
     115: invokestatic  #46                 // Method org/apache/tomcat/util/net/AprEndpoint.access$200:()Lorg/apache/juli/logging/Log;
     118: getstatic     #48                 // Field org/apache/tomcat/util/net/AbstractEndpoint.sm:Lorg/apache/tomcat/util/res/StringManager;
     121: ldc           #68                 // String endpoint.debug.pollerRemoved
     123: iconst_1
     124: anewarray     #50                 // class java/lang/Object
     127: dup
     128: iconst_0
     129: lload_1
     130: invokestatic  #51                 // Method java/lang/Long.valueOf:(J)Ljava/lang/Long;
     133: aastore
     134: invokevirtual #53                 // Method org/apache/tomcat/util/res/StringManager.getString:(Ljava/lang/String;[Ljava/lang/Object;)Ljava/lang/String;
     137: invokeinterface #58,  2           // InterfaceMethod org/apache/juli/logging/Log.debug:(Ljava/lang/Object;)V
     142: goto          151
     145: iinc          4, 1
     148: goto          43
     151: aload_0
     152: getfield      #11                 // Field timeouts:Lorg/apache/tomcat/util/net/AprEndpoint$SocketTimeouts;
     155: lload_1
     156: invokevirtual #69                 // Method org/apache/tomcat/util/net/AprEndpoint$SocketTimeouts.remove:(J)J
     159: pop2
     160: return

  private synchronized void maintain();
    Code:
       0: invokestatic  #12                 // Method java/lang/System.currentTimeMillis:()J
       3: lstore_1
       4: lload_1
       5: aload_0
       6: getfield      #13                 // Field lastMaintain:J
       9: lsub
      10: ldc2_w        #70                 // long 1000l
      13: lcmp
      14: ifge          18
      17: return
      18: aload_0
      19: lload_1
      20: putfield      #13                 // Field lastMaintain:J
      23: aload_0
      24: getfield      #11                 // Field timeouts:Lorg/apache/tomcat/util/net/AprEndpoint$SocketTimeouts;
      27: lload_1
      28: invokevirtual #72                 // Method org/apache/tomcat/util/net/AprEndpoint$SocketTimeouts.check:(J)J
      31: lstore_3
      32: lload_3
      33: lconst_0
      34: lcmp
      35: ifeq          135
      38: invokestatic  #46                 // Method org/apache/tomcat/util/net/AprEndpoint.access$200:()Lorg/apache/juli/logging/Log;
      41: invokeinterface #47,  1           // InterfaceMethod org/apache/juli/logging/Log.isDebugEnabled:()Z
      46: ifeq          76
      49: invokestatic  #46                 // Method org/apache/tomcat/util/net/AprEndpoint.access$200:()Lorg/apache/juli/logging/Log;
      52: getstatic     #48                 // Field org/apache/tomcat/util/net/AbstractEndpoint.sm:Lorg/apache/tomcat/util/res/StringManager;
      55: ldc           #73                 // String endpoint.debug.socketTimeout
      57: iconst_1
      58: anewarray     #50                 // class java/lang/Object
      61: dup
      62: iconst_0
      63: lload_3
      64: invokestatic  #51                 // Method java/lang/Long.valueOf:(J)Ljava/lang/Long;
      67: aastore
      68: invokevirtual #53                 // Method org/apache/tomcat/util/res/StringManager.getString:(Ljava/lang/String;[Ljava/lang/Object;)Ljava/lang/String;
      71: invokeinterface #58,  2           // InterfaceMethod org/apache/juli/logging/Log.debug:(Ljava/lang/Object;)V
      76: aload_0
      77: getfield      #3                  // Field this$0:Lorg/apache/tomcat/util/net/AprEndpoint;
      80: invokestatic  #74                 // Method org/apache/tomcat/util/net/AprEndpoint.access$300:(Lorg/apache/tomcat/util/net/AprEndpoint;)Ljava/util/Map;
      83: lload_3
      84: invokestatic  #51                 // Method java/lang/Long.valueOf:(J)Ljava/lang/Long;
      87: invokeinterface #75,  2           // InterfaceMethod java/util/Map.get:(Ljava/lang/Object;)Ljava/lang/Object;
      92: checkcast     #76                 // class org/apache/tomcat/util/net/SocketWrapperBase
      95: astore        5
      97: aload         5
      99: new           #77                 // class java/net/SocketTimeoutException
     102: dup
     103: invokespecial #78                 // Method java/net/SocketTimeoutException."<init>":()V
     106: invokevirtual #79                 // Method org/apache/tomcat/util/net/SocketWrapperBase.setError:(Ljava/io/IOException;)V
     109: aload_0
     110: getfield      #3                  // Field this$0:Lorg/apache/tomcat/util/net/AprEndpoint;
     113: aload         5
     115: getstatic     #80                 // Field org/apache/tomcat/util/net/SocketEvent.ERROR:Lorg/apache/tomcat/util/net/SocketEvent;
     118: iconst_1
     119: invokevirtual #81                 // Method org/apache/tomcat/util/net/AprEndpoint.processSocket:(Lorg/apache/tomcat/util/net/SocketWrapperBase;Lorg/apache/tomcat/util/net/SocketEvent;Z)Z
     122: pop
     123: aload_0
     124: getfield      #11                 // Field timeouts:Lorg/apache/tomcat/util/net/AprEndpoint$SocketTimeouts;
     127: lload_1
     128: invokevirtual #72                 // Method org/apache/tomcat/util/net/AprEndpoint$SocketTimeouts.check:(J)J
     131: lstore_3
     132: goto          32
     135: return

  public java.lang.String toString();
    Code:
       0: new           #82                 // class java/lang/StringBuffer
       3: dup
       4: invokespecial #83                 // Method java/lang/StringBuffer."<init>":()V
       7: astore_1
       8: aload_1
       9: ldc           #84                 // String Poller
      11: invokevirtual #85                 // Method java/lang/StringBuffer.append:(Ljava/lang/String;)Ljava/lang/StringBuffer;
      14: pop
      15: aload_0
      16: getfield      #6                  // Field actualPollerSize:I
      19: iconst_2
      20: imul
      21: newarray       long
      23: astore_2
      24: iconst_0
      25: istore_3
      26: iload_3
      27: aload_0
      28: getfield      #5                  // Field pollers:[J
      31: arraylength
      32: if_icmpge     104
      35: aload_0
      36: getfield      #5                  // Field pollers:[J
      39: iload_3
      40: laload
      41: aload_2
      42: invokestatic  #44                 // Method org/apache/tomcat/jni/Poll.pollset:(J[J)I
      45: istore        4
      47: aload_1
      48: ldc           #86                 // String  [
      50: invokevirtual #85                 // Method java/lang/StringBuffer.append:(Ljava/lang/String;)Ljava/lang/StringBuffer;
      53: pop
      54: iconst_0
      55: istore        5
      57: iload         5
      59: iload         4
      61: if_icmpge     91
      64: aload_1
      65: aload_0
      66: getfield      #31                 // Field desc:[J
      69: iconst_2
      70: iload         5
      72: imul
      73: iconst_1
      74: iadd
      75: laload
      76: invokevirtual #87                 // Method java/lang/StringBuffer.append:(J)Ljava/lang/StringBuffer;
      79: ldc           #88                 // String
      81: invokevirtual #85                 // Method java/lang/StringBuffer.append:(Ljava/lang/String;)Ljava/lang/StringBuffer;
      84: pop
      85: iinc          5, 1
      88: goto          57
      91: aload_1
      92: ldc           #89                 // String ]
      94: invokevirtual #85                 // Method java/lang/StringBuffer.append:(Ljava/lang/String;)Ljava/lang/StringBuffer;
      97: pop
      98: iinc          3, 1
     101: goto          26
     104: aload_1
     105: invokevirtual #90                 // Method java/lang/StringBuffer.toString:()Ljava/lang/String;
     108: areturn

  public void run();
    Code:
       0: new           #33                 // class org/apache/tomcat/util/net/AprEndpoint$SocketList
       3: dup
       4: aload_0
       5: getfield      #3                  // Field this$0:Lorg/apache/tomcat/util/net/AprEndpoint;
       8: invokevirtual #21                 // Method org/apache/tomcat/util/net/AprEndpoint.getMaxConnections:()I
      11: invokespecial #34                 // Method org/apache/tomcat/util/net/AprEndpoint$SocketList."<init>":(I)V
      14: astore_1
      15: new           #33                 // class org/apache/tomcat/util/net/AprEndpoint$SocketList
      18: dup
      19: aload_0
      20: getfield      #3                  // Field this$0:Lorg/apache/tomcat/util/net/AprEndpoint;
      23: invokevirtual #21                 // Method org/apache/tomcat/util/net/AprEndpoint.getMaxConnections:()I
      26: invokespecial #34                 // Method org/apache/tomcat/util/net/AprEndpoint$SocketList."<init>":(I)V
      29: astore_2
      30: aload_0
      31: getfield      #17                 // Field pollerRunning:Z
      34: ifeq          1756
      37: aload_0
      38: getfield      #17                 // Field pollerRunning:Z
      41: ifeq          178
      44: aload_0
      45: getfield      #16                 // Field connectionCount:Ljava/util/concurrent/atomic/AtomicInteger;
      48: invokevirtual #18                 // Method java/util/concurrent/atomic/AtomicInteger.get:()I
      51: iconst_1
      52: if_icmpge     178
      55: aload_0
      56: getfield      #9                  // Field addList:Lorg/apache/tomcat/util/net/AprEndpoint$SocketList;
      59: invokevirtual #91                 // Method org/apache/tomcat/util/net/AprEndpoint$SocketList.size:()I
      62: iconst_1
      63: if_icmpge     178
      66: aload_0
      67: getfield      #10                 // Field closeList:Lorg/apache/tomcat/util/net/AprEndpoint$SocketList;
      70: invokevirtual #91                 // Method org/apache/tomcat/util/net/AprEndpoint$SocketList.size:()I
      73: iconst_1
      74: if_icmpge     178
      77: aload_0
      78: getfield      #3                  // Field this$0:Lorg/apache/tomcat/util/net/AprEndpoint;
      81: invokevirtual #92                 // Method org/apache/tomcat/util/net/AprEndpoint.getConnectionTimeout:()I
      84: ifle          98
      87: aload_0
      88: getfield      #17                 // Field pollerRunning:Z
      91: ifeq          98
      94: aload_0
      95: invokespecial #93                 // Method maintain:()V
      98: aload_0
      99: dup
     100: astore_3
     101: monitorenter
     102: aload_0
     103: getfield      #9                  // Field addList:Lorg/apache/tomcat/util/net/AprEndpoint$SocketList;
     106: invokevirtual #91                 // Method org/apache/tomcat/util/net/AprEndpoint$SocketList.size:()I
     109: iconst_1
     110: if_icmpge     131
     113: aload_0
     114: getfield      #10                 // Field closeList:Lorg/apache/tomcat/util/net/AprEndpoint$SocketList;
     117: invokevirtual #91                 // Method org/apache/tomcat/util/net/AprEndpoint$SocketList.size:()I
     120: iconst_1
     121: if_icmpge     131
     124: aload_0
     125: ldc2_w        #94                 // long 10000l
     128: invokevirtual #36                 // Method java/lang/Object.wait:(J)V
     131: aload_3
     132: monitorexit
     133: goto          143
     136: astore        4
     138: aload_3
     139: monitorexit
     140: aload         4
     142: athrow
     143: goto          37
     146: astore_3
     147: goto          37
     150: astore_3
     151: aload_3
     152: invokestatic  #97                 // Method org/apache/tomcat/util/ExceptionUtils.handleThrowable:(Ljava/lang/Throwable;)V
     155: aload_0
     156: getfield      #3                  // Field this$0:Lorg/apache/tomcat/util/net/AprEndpoint;
     159: invokevirtual #98                 // Method org/apache/tomcat/util/net/AprEndpoint.getLog:()Lorg/apache/juli/logging/Log;
     162: getstatic     #48                 // Field org/apache/tomcat/util/net/AbstractEndpoint.sm:Lorg/apache/tomcat/util/res/StringManager;
     165: ldc           #99                 // String endpoint.timeout.err
     167: invokevirtual #100                // Method org/apache/tomcat/util/res/StringManager.getString:(Ljava/lang/String;)Ljava/lang/String;
     170: invokeinterface #101,  2          // InterfaceMethod org/apache/juli/logging/Log.warn:(Ljava/lang/Object;)V
     175: goto          37
     178: aload_0
     179: getfield      #17                 // Field pollerRunning:Z
     182: ifne          188
     185: goto          1756
     188: aload_0
     189: dup
     190: astore_3
     191: monitorenter
     192: aload_0
     193: getfield      #10                 // Field closeList:Lorg/apache/tomcat/util/net/AprEndpoint$SocketList;
     196: invokevirtual #91                 // Method org/apache/tomcat/util/net/AprEndpoint$SocketList.size:()I
     199: ifle          220
     202: aload_0
     203: getfield      #10                 // Field closeList:Lorg/apache/tomcat/util/net/AprEndpoint$SocketList;
     206: aload_2
     207: invokevirtual #102                // Method org/apache/tomcat/util/net/AprEndpoint$SocketList.duplicate:(Lorg/apache/tomcat/util/net/AprEndpoint$SocketList;)V
     210: aload_0
     211: getfield      #10                 // Field closeList:Lorg/apache/tomcat/util/net/AprEndpoint$SocketList;
     214: invokevirtual #43                 // Method org/apache/tomcat/util/net/AprEndpoint$SocketList.clear:()V
     217: goto          224
     220: aload_2
     221: invokevirtual #43                 // Method org/apache/tomcat/util/net/AprEndpoint$SocketList.clear:()V
     224: aload_3
     225: monitorexit
     226: goto          236
     229: astore        5
     231: aload_3
     232: monitorexit
     233: aload         5
     235: athrow
     236: aload_0
     237: dup
     238: astore_3
     239: monitorenter
     240: aload_0
     241: getfield      #9                  // Field addList:Lorg/apache/tomcat/util/net/AprEndpoint$SocketList;
     244: invokevirtual #91                 // Method org/apache/tomcat/util/net/AprEndpoint$SocketList.size:()I
     247: ifle          268
     250: aload_0
     251: getfield      #9                  // Field addList:Lorg/apache/tomcat/util/net/AprEndpoint$SocketList;
     254: aload_1
     255: invokevirtual #102                // Method org/apache/tomcat/util/net/AprEndpoint$SocketList.duplicate:(Lorg/apache/tomcat/util/net/AprEndpoint$SocketList;)V
     258: aload_0
     259: getfield      #9                  // Field addList:Lorg/apache/tomcat/util/net/AprEndpoint$SocketList;
     262: invokevirtual #43                 // Method org/apache/tomcat/util/net/AprEndpoint$SocketList.clear:()V
     265: goto          272
     268: aload_1
     269: invokevirtual #43                 // Method org/apache/tomcat/util/net/AprEndpoint$SocketList.clear:()V
     272: aload_3
     273: monitorexit
     274: goto          284
     277: astore        6
     279: aload_3
     280: monitorexit
     281: aload         6
     283: athrow
     284: aload_2
     285: invokevirtual #91                 // Method org/apache/tomcat/util/net/AprEndpoint$SocketList.size:()I
     288: ifle          336
     291: aload_2
     292: invokevirtual #38                 // Method org/apache/tomcat/util/net/AprEndpoint$SocketList.get:()Lorg/apache/tomcat/util/net/AprEndpoint$SocketInfo;
     295: astore_3
     296: aload_3
     297: ifnull        336
     300: aload_1
     301: aload_3
     302: getfield      #39                 // Field org/apache/tomcat/util/net/AprEndpoint$SocketInfo.socket:J
     305: invokevirtual #40                 // Method org/apache/tomcat/util/net/AprEndpoint$SocketList.remove:(J)Z
     308: pop
     309: aload_0
     310: aload_3
     311: getfield      #39                 // Field org/apache/tomcat/util/net/AprEndpoint$SocketInfo.socket:J
     314: invokespecial #41                 // Method removeFromPoller:(J)V
     317: aload_0
     318: getfield      #3                  // Field this$0:Lorg/apache/tomcat/util/net/AprEndpoint;
     321: aload_3
     322: getfield      #39                 // Field org/apache/tomcat/util/net/AprEndpoint$SocketInfo.socket:J
     325: invokestatic  #42                 // Method org/apache/tomcat/util/net/AprEndpoint.access$100:(Lorg/apache/tomcat/util/net/AprEndpoint;J)V
     328: aload_2
     329: invokevirtual #38                 // Method org/apache/tomcat/util/net/AprEndpoint$SocketList.get:()Lorg/apache/tomcat/util/net/AprEndpoint$SocketInfo;
     332: astore_3
     333: goto          296
     336: aload_1
     337: invokevirtual #91                 // Method org/apache/tomcat/util/net/AprEndpoint$SocketList.size:()I
     340: ifle          595
     343: aload_1
     344: invokevirtual #38                 // Method org/apache/tomcat/util/net/AprEndpoint$SocketList.get:()Lorg/apache/tomcat/util/net/AprEndpoint$SocketInfo;
     347: astore_3
     348: aload_3
     349: ifnull        595
     352: invokestatic  #46                 // Method org/apache/tomcat/util/net/AprEndpoint.access$200:()Lorg/apache/juli/logging/Log;
     355: invokeinterface #47,  1           // InterfaceMethod org/apache/juli/logging/Log.isDebugEnabled:()Z
     360: ifeq          393
     363: invokestatic  #46                 // Method org/apache/tomcat/util/net/AprEndpoint.access$200:()Lorg/apache/juli/logging/Log;
     366: getstatic     #48                 // Field org/apache/tomcat/util/net/AbstractEndpoint.sm:Lorg/apache/tomcat/util/res/StringManager;
     369: ldc           #103                // String endpoint.debug.pollerAddDo
     371: iconst_1
     372: anewarray     #50                 // class java/lang/Object
     375: dup
     376: iconst_0
     377: aload_3
     378: getfield      #39                 // Field org/apache/tomcat/util/net/AprEndpoint$SocketInfo.socket:J
     381: invokestatic  #51                 // Method java/lang/Long.valueOf:(J)Ljava/lang/Long;
     384: aastore
     385: invokevirtual #53                 // Method org/apache/tomcat/util/res/StringManager.getString:(Ljava/lang/String;[Ljava/lang/Object;)Ljava/lang/String;
     388: invokeinterface #58,  2           // InterfaceMethod org/apache/juli/logging/Log.debug:(Ljava/lang/Object;)V
     393: aload_0
     394: getfield      #11                 // Field timeouts:Lorg/apache/tomcat/util/net/AprEndpoint$SocketTimeouts;
     397: aload_3
     398: getfield      #39                 // Field org/apache/tomcat/util/net/AprEndpoint$SocketInfo.socket:J
     401: invokevirtual #69                 // Method org/apache/tomcat/util/net/AprEndpoint$SocketTimeouts.remove:(J)J
     404: pop2
     405: aload_0
     406: getfield      #3                  // Field this$0:Lorg/apache/tomcat/util/net/AprEndpoint;
     409: invokestatic  #74                 // Method org/apache/tomcat/util/net/AprEndpoint.access$300:(Lorg/apache/tomcat/util/net/AprEndpoint;)Ljava/util/Map;
     412: aload_3
     413: getfield      #39                 // Field org/apache/tomcat/util/net/AprEndpoint$SocketInfo.socket:J
     416: invokestatic  #51                 // Method java/lang/Long.valueOf:(J)Ljava/lang/Long;
     419: invokeinterface #75,  2           // InterfaceMethod java/util/Map.get:(Ljava/lang/Object;)Ljava/lang/Object;
     424: checkcast     #104                // class org/apache/tomcat/util/net/AprEndpoint$AprSocketWrapper
     427: astore        4
     429: aload         4
     431: ifnonnull     437
     434: goto          348
     437: aload_3
     438: invokevirtual #105                // Method org/apache/tomcat/util/net/AprEndpoint$SocketInfo.read:()Z
     441: ifne          451
     444: aload_3
     445: invokevirtual #106                // Method org/apache/tomcat/util/net/AprEndpoint$SocketInfo.write:()Z
     448: ifeq          548
     451: aload         4
     453: aload         4
     455: invokestatic  #107                // Method org/apache/tomcat/util/net/AprEndpoint$AprSocketWrapper.access$400:(Lorg/apache/tomcat/util/net/AprEndpoint$AprSocketWrapper;)I
     458: aload_3
     459: invokevirtual #105                // Method org/apache/tomcat/util/net/AprEndpoint$SocketInfo.read:()Z
     462: ifeq          469
     465: iconst_1
     466: goto          470
     469: iconst_0
     470: ior
     471: aload_3
     472: invokevirtual #106                // Method org/apache/tomcat/util/net/AprEndpoint$SocketInfo.write:()Z
     475: ifeq          482
     478: iconst_4
     479: goto          483
     482: iconst_0
     483: ior
     484: invokestatic  #108                // Method org/apache/tomcat/util/net/AprEndpoint$AprSocketWrapper.access$402:(Lorg/apache/tomcat/util/net/AprEndpoint$AprSocketWrapper;I)I
     487: pop
     488: aload_0
     489: aload_3
     490: getfield      #39                 // Field org/apache/tomcat/util/net/AprEndpoint$SocketInfo.socket:J
     493: invokespecial #41                 // Method removeFromPoller:(J)V
     496: aload_0
     497: aload_3
     498: getfield      #39                 // Field org/apache/tomcat/util/net/AprEndpoint$SocketInfo.socket:J
     501: aload         4
     503: invokestatic  #107                // Method org/apache/tomcat/util/net/AprEndpoint$AprSocketWrapper.access$400:(Lorg/apache/tomcat/util/net/AprEndpoint$AprSocketWrapper;)I
     506: invokespecial #109                // Method addToPoller:(JI)Z
     509: ifne          526
     512: aload_0
     513: getfield      #3                  // Field this$0:Lorg/apache/tomcat/util/net/AprEndpoint;
     516: aload_3
     517: getfield      #39                 // Field org/apache/tomcat/util/net/AprEndpoint$SocketInfo.socket:J
     520: invokestatic  #110                // Method org/apache/tomcat/util/net/AprEndpoint.access$000:(Lorg/apache/tomcat/util/net/AprEndpoint;J)V
     523: goto          587
     526: aload_0
     527: getfield      #11                 // Field timeouts:Lorg/apache/tomcat/util/net/AprEndpoint$SocketTimeouts;
     530: aload_3
     531: getfield      #39                 // Field org/apache/tomcat/util/net/AprEndpoint$SocketInfo.socket:J
     534: invokestatic  #12                 // Method java/lang/System.currentTimeMillis:()J
     537: aload_3
     538: getfield      #111                // Field org/apache/tomcat/util/net/AprEndpoint$SocketInfo.timeout:J
     541: ladd
     542: invokevirtual #112                // Method org/apache/tomcat/util/net/AprEndpoint$SocketTimeouts.add:(JJ)V
     545: goto          587
     548: aload_0
     549: getfield      #3                  // Field this$0:Lorg/apache/tomcat/util/net/AprEndpoint;
     552: aload_3
     553: getfield      #39                 // Field org/apache/tomcat/util/net/AprEndpoint$SocketInfo.socket:J
     556: invokestatic  #110                // Method org/apache/tomcat/util/net/AprEndpoint.access$000:(Lorg/apache/tomcat/util/net/AprEndpoint;J)V
     559: aload_0
     560: getfield      #3                  // Field this$0:Lorg/apache/tomcat/util/net/AprEndpoint;
     563: invokevirtual #98                 // Method org/apache/tomcat/util/net/AprEndpoint.getLog:()Lorg/apache/juli/logging/Log;
     566: getstatic     #48                 // Field org/apache/tomcat/util/net/AbstractEndpoint.sm:Lorg/apache/tomcat/util/res/StringManager;
     569: ldc           #113                // String endpoint.apr.pollAddInvalid
     571: iconst_1
     572: anewarray     #50                 // class java/lang/Object
     575: dup
     576: iconst_0
     577: aload_3
     578: aastore
     579: invokevirtual #53                 // Method org/apache/tomcat/util/res/StringManager.getString:(Ljava/lang/String;[Ljava/lang/Object;)Ljava/lang/String;
     582: invokeinterface #101,  2          // InterfaceMethod org/apache/juli/logging/Log.warn:(Ljava/lang/Object;)V
     587: aload_1
     588: invokevirtual #38                 // Method org/apache/tomcat/util/net/AprEndpoint$SocketList.get:()Lorg/apache/tomcat/util/net/AprEndpoint$SocketInfo;
     591: astore_3
     592: goto          348
     595: iconst_0
     596: istore_3
     597: iload_3
     598: aload_0
     599: getfield      #5                  // Field pollers:[J
     602: arraylength
     603: if_icmpge     1674
     606: iconst_0
     607: istore        4
     609: iconst_0
     610: istore        5
     612: aload_0
     613: getfield      #7                  // Field pollerSpace:[I
     616: iload_3
     617: iaload
     618: aload_0
     619: getfield      #6                  // Field actualPollerSize:I
     622: if_icmpge     657
     625: aload_0
     626: getfield      #5                  // Field pollers:[J
     629: iload_3
     630: laload
     631: aload_0
     632: getfield      #30                 // Field nextPollerTime:I
     635: i2l
     636: aload_0
     637: getfield      #31                 // Field desc:[J
     640: iconst_1
     641: invokestatic  #114                // Method org/apache/tomcat/jni/Poll.poll:(JJ[JZ)I
     644: istore        5
     646: aload_0
     647: aload_0
     648: getfield      #29                 // Field pollerTime:I
     651: putfield      #30                 // Field nextPollerTime:I
     654: goto          670
     657: aload_0
     658: dup
     659: getfield      #30                 // Field nextPollerTime:I
     662: aload_0
     663: getfield      #29                 // Field pollerTime:I
     666: iadd
     667: putfield      #30                 // Field nextPollerTime:I
     670: iload         5
     672: ifle          1503
     675: aload_0
     676: aload_0
     677: getfield      #31                 // Field desc:[J
     680: iload         5
     682: invokespecial #115                // Method mergeDescriptors:([JI)I
     685: istore        5
     687: aload_0
     688: getfield      #7                  // Field pollerSpace:[I
     691: iload_3
     692: dup2
     693: iaload
     694: iload         5
     696: iadd
     697: iastore
     698: aload_0
     699: getfield      #16                 // Field connectionCount:Ljava/util/concurrent/atomic/AtomicInteger;
     702: iload         5
     704: ineg
     705: invokevirtual #116                // Method java/util/concurrent/atomic/AtomicInteger.addAndGet:(I)I
     708: pop
     709: iconst_0
     710: istore        6
     712: iload         6
     714: iload         5
     716: if_icmpge     1500
     719: aload_0
     720: getfield      #3                  // Field this$0:Lorg/apache/tomcat/util/net/AprEndpoint;
     723: invokevirtual #98                 // Method org/apache/tomcat/util/net/AprEndpoint.getLog:()Lorg/apache/juli/logging/Log;
     726: invokeinterface #47,  1           // InterfaceMethod org/apache/juli/logging/Log.isDebugEnabled:()Z
     731: ifeq          786
     734: invokestatic  #46                 // Method org/apache/tomcat/util/net/AprEndpoint.access$200:()Lorg/apache/juli/logging/Log;
     737: getstatic     #48                 // Field org/apache/tomcat/util/net/AbstractEndpoint.sm:Lorg/apache/tomcat/util/res/StringManager;
     740: ldc           #117                // String endpoint.debug.pollerProcess
     742: iconst_2
     743: anewarray     #50                 // class java/lang/Object
     746: dup
     747: iconst_0
     748: aload_0
     749: getfield      #31                 // Field desc:[J
     752: iload         6
     754: iconst_2
     755: imul
     756: iconst_1
     757: iadd
     758: laload
     759: invokestatic  #51                 // Method java/lang/Long.valueOf:(J)Ljava/lang/Long;
     762: aastore
     763: dup
     764: iconst_1
     765: aload_0
     766: getfield      #31                 // Field desc:[J
     769: iload         6
     771: iconst_2
     772: imul
     773: laload
     774: invokestatic  #51                 // Method java/lang/Long.valueOf:(J)Ljava/lang/Long;
     777: aastore
     778: invokevirtual #53                 // Method org/apache/tomcat/util/res/StringManager.getString:(Ljava/lang/String;[Ljava/lang/Object;)Ljava/lang/String;
     781: invokeinterface #58,  2           // InterfaceMethod org/apache/juli/logging/Log.debug:(Ljava/lang/Object;)V
     786: aload_0
     787: getfield      #11                 // Field timeouts:Lorg/apache/tomcat/util/net/AprEndpoint$SocketTimeouts;
     790: aload_0
     791: getfield      #31                 // Field desc:[J
     794: iload         6
     796: iconst_2
     797: imul
     798: iconst_1
     799: iadd
     800: laload
     801: invokevirtual #69                 // Method org/apache/tomcat/util/net/AprEndpoint$SocketTimeouts.remove:(J)J
     804: lstore        7
     806: aload_0
     807: getfield      #3                  // Field this$0:Lorg/apache/tomcat/util/net/AprEndpoint;
     810: invokestatic  #74                 // Method org/apache/tomcat/util/net/AprEndpoint.access$300:(Lorg/apache/tomcat/util/net/AprEndpoint;)Ljava/util/Map;
     813: aload_0
     814: getfield      #31                 // Field desc:[J
     817: iload         6
     819: iconst_2
     820: imul
     821: iconst_1
     822: iadd
     823: laload
     824: invokestatic  #51                 // Method java/lang/Long.valueOf:(J)Ljava/lang/Long;
     827: invokeinterface #75,  2           // InterfaceMethod java/util/Map.get:(Ljava/lang/Object;)Ljava/lang/Object;
     832: checkcast     #104                // class org/apache/tomcat/util/net/AprEndpoint$AprSocketWrapper
     835: astore        9
     837: aload         9
     839: ifnonnull     845
     842: goto          1494
     845: aload         9
     847: aload         9
     849: invokestatic  #107                // Method org/apache/tomcat/util/net/AprEndpoint$AprSocketWrapper.access$400:(Lorg/apache/tomcat/util/net/AprEndpoint$AprSocketWrapper;)I
     852: aload_0
     853: getfield      #31                 // Field desc:[J
     856: iload         6
     858: iconst_2
     859: imul
     860: laload
     861: l2i
     862: iconst_m1
     863: ixor
     864: iand
     865: invokestatic  #108                // Method org/apache/tomcat/util/net/AprEndpoint$AprSocketWrapper.access$402:(Lorg/apache/tomcat/util/net/AprEndpoint$AprSocketWrapper;I)I
     868: pop
     869: aload_0
     870: getfield      #31                 // Field desc:[J
     873: iload         6
     875: iconst_2
     876: imul
     877: laload
     878: ldc2_w        #118                // long 32l
     881: land
     882: ldc2_w        #118                // long 32l
     885: lcmp
     886: ifeq          929
     889: aload_0
     890: getfield      #31                 // Field desc:[J
     893: iload         6
     895: iconst_2
     896: imul
     897: laload
     898: ldc2_w        #120                // long 16l
     901: land
     902: ldc2_w        #120                // long 16l
     905: lcmp
     906: ifeq          929
     909: aload_0
     910: getfield      #31                 // Field desc:[J
     913: iload         6
     915: iconst_2
     916: imul
     917: laload
     918: ldc2_w        #122                // long 64l
     921: land
     922: ldc2_w        #122                // long 64l
     925: lcmp
     926: ifne          1188
     929: aload_0
     930: getfield      #31                 // Field desc:[J
     933: iload         6
     935: iconst_2
     936: imul
     937: laload
     938: lconst_1
     939: land
     940: lconst_1
     941: lcmp
     942: ifne          990
     945: aload_0
     946: getfield      #3                  // Field this$0:Lorg/apache/tomcat/util/net/AprEndpoint;
     949: aload_0
     950: getfield      #31                 // Field desc:[J
     953: iload         6
     955: iconst_2
     956: imul
     957: iconst_1
     958: iadd
     959: laload
     960: getstatic     #124                // Field org/apache/tomcat/util/net/SocketEvent.OPEN_READ:Lorg/apache/tomcat/util/net/SocketEvent;
     963: invokevirtual #125                // Method org/apache/tomcat/util/net/AprEndpoint.processSocket:(JLorg/apache/tomcat/util/net/SocketEvent;)Z
     966: ifne          1494
     969: aload_0
     970: getfield      #3                  // Field this$0:Lorg/apache/tomcat/util/net/AprEndpoint;
     973: aload_0
     974: getfield      #31                 // Field desc:[J
     977: iload         6
     979: iconst_2
     980: imul
     981: iconst_1
     982: iadd
     983: laload
     984: invokestatic  #110                // Method org/apache/tomcat/util/net/AprEndpoint.access$000:(Lorg/apache/tomcat/util/net/AprEndpoint;J)V
     987: goto          1494
     990: aload_0
     991: getfield      #31                 // Field desc:[J
     994: iload         6
     996: iconst_2
     997: imul
     998: laload
     999: ldc2_w        #126                // long 4l
    1002: land
    1003: ldc2_w        #126                // long 4l
    1006: lcmp
    1007: ifne          1055
    1010: aload_0
    1011: getfield      #3                  // Field this$0:Lorg/apache/tomcat/util/net/AprEndpoint;
    1014: aload_0
    1015: getfield      #31                 // Field desc:[J
    1018: iload         6
    1020: iconst_2
    1021: imul
    1022: iconst_1
    1023: iadd
    1024: laload
    1025: getstatic     #128                // Field org/apache/tomcat/util/net/SocketEvent.OPEN_WRITE:Lorg/apache/tomcat/util/net/SocketEvent;
    1028: invokevirtual #125                // Method org/apache/tomcat/util/net/AprEndpoint.processSocket:(JLorg/apache/tomcat/util/net/SocketEvent;)Z
    1031: ifne          1494
    1034: aload_0
    1035: getfield      #3                  // Field this$0:Lorg/apache/tomcat/util/net/AprEndpoint;
    1038: aload_0
    1039: getfield      #31                 // Field desc:[J
    1042: iload         6
    1044: iconst_2
    1045: imul
    1046: iconst_1
    1047: iadd
    1048: laload
    1049: invokestatic  #110                // Method org/apache/tomcat/util/net/AprEndpoint.access$000:(Lorg/apache/tomcat/util/net/AprEndpoint;J)V
    1052: goto          1494
    1055: aload         9
    1057: invokestatic  #107                // Method org/apache/tomcat/util/net/AprEndpoint$AprSocketWrapper.access$400:(Lorg/apache/tomcat/util/net/AprEndpoint$AprSocketWrapper;)I
    1060: iconst_1
    1061: iand
    1062: iconst_1
    1063: if_icmpne     1111
    1066: aload_0
    1067: getfield      #3                  // Field this$0:Lorg/apache/tomcat/util/net/AprEndpoint;
    1070: aload_0
    1071: getfield      #31                 // Field desc:[J
    1074: iload         6
    1076: iconst_2
    1077: imul
    1078: iconst_1
    1079: iadd
    1080: laload
    1081: getstatic     #124                // Field org/apache/tomcat/util/net/SocketEvent.OPEN_READ:Lorg/apache/tomcat/util/net/SocketEvent;
    1084: invokevirtual #125                // Method org/apache/tomcat/util/net/AprEndpoint.processSocket:(JLorg/apache/tomcat/util/net/SocketEvent;)Z
    1087: ifne          1494
    1090: aload_0
    1091: getfield      #3                  // Field this$0:Lorg/apache/tomcat/util/net/AprEndpoint;
    1094: aload_0
    1095: getfield      #31                 // Field desc:[J
    1098: iload         6
    1100: iconst_2
    1101: imul
    1102: iconst_1
    1103: iadd
    1104: laload
    1105: invokestatic  #110                // Method org/apache/tomcat/util/net/AprEndpoint.access$000:(Lorg/apache/tomcat/util/net/AprEndpoint;J)V
    1108: goto          1494
    1111: aload         9
    1113: invokestatic  #107                // Method org/apache/tomcat/util/net/AprEndpoint$AprSocketWrapper.access$400:(Lorg/apache/tomcat/util/net/AprEndpoint$AprSocketWrapper;)I
    1116: iconst_4
    1117: iand
    1118: iconst_4
    1119: if_icmpne     1167
    1122: aload_0
    1123: getfield      #3                  // Field this$0:Lorg/apache/tomcat/util/net/AprEndpoint;
    1126: aload_0
    1127: getfield      #31                 // Field desc:[J
    1130: iload         6
    1132: iconst_2
    1133: imul
    1134: iconst_1
    1135: iadd
    1136: laload
    1137: getstatic     #128                // Field org/apache/tomcat/util/net/SocketEvent.OPEN_WRITE:Lorg/apache/tomcat/util/net/SocketEvent;
    1140: invokevirtual #125                // Method org/apache/tomcat/util/net/AprEndpoint.processSocket:(JLorg/apache/tomcat/util/net/SocketEvent;)Z
    1143: ifne          1494
    1146: aload_0
    1147: getfield      #3                  // Field this$0:Lorg/apache/tomcat/util/net/AprEndpoint;
    1150: aload_0
    1151: getfield      #31                 // Field desc:[J
    1154: iload         6
    1156: iconst_2
    1157: imul
    1158: iconst_1
    1159: iadd
    1160: laload
    1161: invokestatic  #110                // Method org/apache/tomcat/util/net/AprEndpoint.access$000:(Lorg/apache/tomcat/util/net/AprEndpoint;J)V
    1164: goto          1494
    1167: aload_0
    1168: getfield      #3                  // Field this$0:Lorg/apache/tomcat/util/net/AprEndpoint;
    1171: aload_0
    1172: getfield      #31                 // Field desc:[J
    1175: iload         6
    1177: iconst_2
    1178: imul
    1179: iconst_1
    1180: iadd
    1181: laload
    1182: invokestatic  #110                // Method org/apache/tomcat/util/net/AprEndpoint.access$000:(Lorg/apache/tomcat/util/net/AprEndpoint;J)V
    1185: goto          1494
    1188: aload_0
    1189: getfield      #31                 // Field desc:[J
    1192: iload         6
    1194: iconst_2
    1195: imul
    1196: laload
    1197: lconst_1
    1198: land
    1199: lconst_1
    1200: lcmp
    1201: ifeq          1224
    1204: aload_0
    1205: getfield      #31                 // Field desc:[J
    1208: iload         6
    1210: iconst_2
    1211: imul
    1212: laload
    1213: ldc2_w        #126                // long 4l
    1216: land
    1217: ldc2_w        #126                // long 4l
    1220: lcmp
    1221: ifne          1437
    1224: iconst_0
    1225: istore        10
    1227: aload_0
    1228: getfield      #31                 // Field desc:[J
    1231: iload         6
    1233: iconst_2
    1234: imul
    1235: laload
    1236: lconst_1
    1237: land
    1238: lconst_1
    1239: lcmp
    1240: ifne          1288
    1243: aload_0
    1244: getfield      #3                  // Field this$0:Lorg/apache/tomcat/util/net/AprEndpoint;
    1247: aload_0
    1248: getfield      #31                 // Field desc:[J
    1251: iload         6
    1253: iconst_2
    1254: imul
    1255: iconst_1
    1256: iadd
    1257: laload
    1258: getstatic     #124                // Field org/apache/tomcat/util/net/SocketEvent.OPEN_READ:Lorg/apache/tomcat/util/net/SocketEvent;
    1261: invokevirtual #125                // Method org/apache/tomcat/util/net/AprEndpoint.processSocket:(JLorg/apache/tomcat/util/net/SocketEvent;)Z
    1264: ifne          1288
    1267: iconst_1
    1268: istore        10
    1270: aload_0
    1271: getfield      #3                  // Field this$0:Lorg/apache/tomcat/util/net/AprEndpoint;
    1274: aload_0
    1275: getfield      #31                 // Field desc:[J
    1278: iload         6
    1280: iconst_2
    1281: imul
    1282: iconst_1
    1283: iadd
    1284: laload
    1285: invokestatic  #110                // Method org/apache/tomcat/util/net/AprEndpoint.access$000:(Lorg/apache/tomcat/util/net/AprEndpoint;J)V
    1288: iload         10
    1290: ifne          1358
    1293: aload_0
    1294: getfield      #31                 // Field desc:[J
    1297: iload         6
    1299: iconst_2
    1300: imul
    1301: laload
    1302: ldc2_w        #126                // long 4l
    1305: land
    1306: ldc2_w        #126                // long 4l
    1309: lcmp
    1310: ifne          1358
    1313: aload_0
    1314: getfield      #3                  // Field this$0:Lorg/apache/tomcat/util/net/AprEndpoint;
    1317: aload_0
    1318: getfield      #31                 // Field desc:[J
    1321: iload         6
    1323: iconst_2
    1324: imul
    1325: iconst_1
    1326: iadd
    1327: laload
    1328: getstatic     #128                // Field org/apache/tomcat/util/net/SocketEvent.OPEN_WRITE:Lorg/apache/tomcat/util/net/SocketEvent;
    1331: invokevirtual #125                // Method org/apache/tomcat/util/net/AprEndpoint.processSocket:(JLorg/apache/tomcat/util/net/SocketEvent;)Z
    1334: ifne          1358
    1337: iconst_1
    1338: istore        10
    1340: aload_0
    1341: getfield      #3                  // Field this$0:Lorg/apache/tomcat/util/net/AprEndpoint;
    1344: aload_0
    1345: getfield      #31                 // Field desc:[J
    1348: iload         6
    1350: iconst_2
    1351: imul
    1352: iconst_1
    1353: iadd
    1354: laload
    1355: invokestatic  #110                // Method org/apache/tomcat/util/net/AprEndpoint.access$000:(Lorg/apache/tomcat/util/net/AprEndpoint;J)V
    1358: iload         10
    1360: ifne          1434
    1363: aload         9
    1365: invokestatic  #107                // Method org/apache/tomcat/util/net/AprEndpoint$AprSocketWrapper.access$400:(Lorg/apache/tomcat/util/net/AprEndpoint$AprSocketWrapper;)I
    1368: ifeq          1434
    1371: lload         7
    1373: lconst_0
    1374: lcmp
    1375: ifle          1386
    1378: lload         7
    1380: invokestatic  #12                 // Method java/lang/System.currentTimeMillis:()J
    1383: lsub
    1384: lstore        7
    1386: lload         7
    1388: lconst_0
    1389: lcmp
    1390: ifgt          1396
    1393: lconst_1
    1394: lstore        7
    1396: lload         7
    1398: ldc2_w        #59                 // long 2147483647l
    1401: lcmp
    1402: ifle          1410
    1405: ldc2_w        #59                 // long 2147483647l
    1408: lstore        7
    1410: aload_0
    1411: aload_0
    1412: getfield      #31                 // Field desc:[J
    1415: iload         6
    1417: iconst_2
    1418: imul
    1419: iconst_1
    1420: iadd
    1421: laload
    1422: lload         7
    1424: l2i
    1425: i2l
    1426: aload         9
    1428: invokestatic  #107                // Method org/apache/tomcat/util/net/AprEndpoint$AprSocketWrapper.access$400:(Lorg/apache/tomcat/util/net/AprEndpoint$AprSocketWrapper;)I
    1431: invokespecial #2                  // Method add:(JJI)V
    1434: goto          1494
    1437: aload_0
    1438: getfield      #3                  // Field this$0:Lorg/apache/tomcat/util/net/AprEndpoint;
    1441: invokevirtual #98                 // Method org/apache/tomcat/util/net/AprEndpoint.getLog:()Lorg/apache/juli/logging/Log;
    1444: getstatic     #48                 // Field org/apache/tomcat/util/net/AbstractEndpoint.sm:Lorg/apache/tomcat/util/res/StringManager;
    1447: ldc           #129                // String endpoint.apr.pollUnknownEvent
    1449: iconst_1
    1450: anewarray     #50                 // class java/lang/Object
    1453: dup
    1454: iconst_0
    1455: aload_0
    1456: getfield      #31                 // Field desc:[J
    1459: iload         6
    1461: iconst_2
    1462: imul
    1463: laload
    1464: invokestatic  #51                 // Method java/lang/Long.valueOf:(J)Ljava/lang/Long;
    1467: aastore
    1468: invokevirtual #53                 // Method org/apache/tomcat/util/res/StringManager.getString:(Ljava/lang/String;[Ljava/lang/Object;)Ljava/lang/String;
    1471: invokeinterface #101,  2          // InterfaceMethod org/apache/juli/logging/Log.warn:(Ljava/lang/Object;)V
    1476: aload_0
    1477: getfield      #3                  // Field this$0:Lorg/apache/tomcat/util/net/AprEndpoint;
    1480: aload_0
    1481: getfield      #31                 // Field desc:[J
    1484: iload         6
    1486: iconst_2
    1487: imul
    1488: iconst_1
    1489: iadd
    1490: laload
    1491: invokestatic  #110                // Method org/apache/tomcat/util/net/AprEndpoint.access$000:(Lorg/apache/tomcat/util/net/AprEndpoint;J)V
    1494: iinc          6, 1
    1497: goto          712
    1500: goto          1584
    1503: iload         5
    1505: ifge          1584
    1508: iload         5
    1510: ineg
    1511: istore        6
    1513: iload         6
    1515: ldc           #130                // int 120001
    1517: if_icmpeq     1584
    1520: iload         6
    1522: ldc           #131                // int 120003
    1524: if_icmpeq     1584
    1527: iload         6
    1529: ldc           #132                // int 120000
    1531: if_icmple     1541
    1534: iload         6
    1536: ldc           #132                // int 120000
    1538: isub
    1539: istore        6
    1541: aload_0
    1542: getfield      #3                  // Field this$0:Lorg/apache/tomcat/util/net/AprEndpoint;
    1545: invokevirtual #98                 // Method org/apache/tomcat/util/net/AprEndpoint.getLog:()Lorg/apache/juli/logging/Log;
    1548: getstatic     #48                 // Field org/apache/tomcat/util/net/AbstractEndpoint.sm:Lorg/apache/tomcat/util/res/StringManager;
    1551: ldc           #133                // String endpoint.apr.pollError
    1553: iconst_2
    1554: anewarray     #50                 // class java/lang/Object
    1557: dup
    1558: iconst_0
    1559: iload         6
    1561: invokestatic  #52                 // Method java/lang/Integer.valueOf:(I)Ljava/lang/Integer;
    1564: aastore
    1565: dup
    1566: iconst_1
    1567: iload         6
    1569: invokestatic  #134                // Method org/apache/tomcat/jni/Error.strerror:(I)Ljava/lang/String;
    1572: aastore
    1573: invokevirtual #53                 // Method org/apache/tomcat/util/res/StringManager.getString:(Ljava/lang/String;[Ljava/lang/Object;)Ljava/lang/String;
    1576: invokeinterface #135,  2          // InterfaceMethod org/apache/juli/logging/Log.error:(Ljava/lang/Object;)V
    1581: iconst_1
    1582: istore        4
    1584: iload         4
    1586: ifeq          1668
    1589: aload_0
    1590: getfield      #17                 // Field pollerRunning:Z
    1593: ifeq          1668
    1596: aload_0
    1597: getfield      #5                  // Field pollers:[J
    1600: iload_3
    1601: laload
    1602: aload_0
    1603: getfield      #31                 // Field desc:[J
    1606: invokestatic  #44                 // Method org/apache/tomcat/jni/Poll.pollset:(J[J)I
    1609: istore        6
    1611: aload_0
    1612: getfield      #3                  // Field this$0:Lorg/apache/tomcat/util/net/AprEndpoint;
    1615: aload_0
    1616: getfield      #6                  // Field actualPollerSize:I
    1619: aload_0
    1620: getfield      #8                  // Field pool:J
    1623: iconst_m1
    1624: invokevirtual #26                 // Method org/apache/tomcat/util/net/AprEndpoint.allocatePoller:(IJI)J
    1627: lstore        7
    1629: aload_0
    1630: getfield      #7                  // Field pollerSpace:[I
    1633: iload_3
    1634: aload_0
    1635: getfield      #6                  // Field actualPollerSize:I
    1638: iastore
    1639: aload_0
    1640: getfield      #16                 // Field connectionCount:Ljava/util/concurrent/atomic/AtomicInteger;
    1643: iload         6
    1645: ineg
    1646: invokevirtual #116                // Method java/util/concurrent/atomic/AtomicInteger.addAndGet:(I)I
    1649: pop
    1650: aload_0
    1651: getfield      #5                  // Field pollers:[J
    1654: iload_3
    1655: laload
    1656: invokestatic  #136                // Method org/apache/tomcat/jni/Poll.destroy:(J)I
    1659: pop
    1660: aload_0
    1661: getfield      #5                  // Field pollers:[J
    1664: iload_3
    1665: lload         7
    1667: lastore
    1668: iinc          3, 1
    1671: goto          597
    1674: goto          1703
    1677: astore_3
    1678: aload_3
    1679: invokestatic  #97                 // Method org/apache/tomcat/util/ExceptionUtils.handleThrowable:(Ljava/lang/Throwable;)V
    1682: aload_0
    1683: getfield      #3                  // Field this$0:Lorg/apache/tomcat/util/net/AprEndpoint;
    1686: invokevirtual #98                 // Method org/apache/tomcat/util/net/AprEndpoint.getLog:()Lorg/apache/juli/logging/Log;
    1689: getstatic     #48                 // Field org/apache/tomcat/util/net/AbstractEndpoint.sm:Lorg/apache/tomcat/util/res/StringManager;
    1692: ldc           #137                // String endpoint.poll.error
    1694: invokevirtual #100                // Method org/apache/tomcat/util/res/StringManager.getString:(Ljava/lang/String;)Ljava/lang/String;
    1697: aload_3
    1698: invokeinterface #138,  3          // InterfaceMethod org/apache/juli/logging/Log.warn:(Ljava/lang/Object;Ljava/lang/Throwable;)V
    1703: aload_0
    1704: getfield      #3                  // Field this$0:Lorg/apache/tomcat/util/net/AprEndpoint;
    1707: invokevirtual #92                 // Method org/apache/tomcat/util/net/AprEndpoint.getConnectionTimeout:()I
    1710: ifle          1724
    1713: aload_0
    1714: getfield      #17                 // Field pollerRunning:Z
    1717: ifeq          1724
    1720: aload_0
    1721: invokespecial #93                 // Method maintain:()V
    1724: goto          30
    1727: astore_3
    1728: aload_3
    1729: invokestatic  #97                 // Method org/apache/tomcat/util/ExceptionUtils.handleThrowable:(Ljava/lang/Throwable;)V
    1732: aload_0
    1733: getfield      #3                  // Field this$0:Lorg/apache/tomcat/util/net/AprEndpoint;
    1736: invokevirtual #98                 // Method org/apache/tomcat/util/net/AprEndpoint.getLog:()Lorg/apache/juli/logging/Log;
    1739: getstatic     #48                 // Field org/apache/tomcat/util/net/AbstractEndpoint.sm:Lorg/apache/tomcat/util/res/StringManager;
    1742: ldc           #99                 // String endpoint.timeout.err
    1744: invokevirtual #100                // Method org/apache/tomcat/util/res/StringManager.getString:(Ljava/lang/String;)Ljava/lang/String;
    1747: aload_3
    1748: invokeinterface #138,  3          // InterfaceMethod org/apache/juli/logging/Log.warn:(Ljava/lang/Object;Ljava/lang/Throwable;)V
    1753: goto          30
    1756: aload_0
    1757: dup
    1758: astore_3
    1759: monitorenter
    1760: aload_0
    1761: invokevirtual #139                // Method java/lang/Object.notifyAll:()V
    1764: aload_3
    1765: monitorexit
    1766: goto          1776
    1769: astore        11
    1771: aload_3
    1772: monitorexit
    1773: aload         11
    1775: athrow
    1776: return
    Exception table:
       from    to  target type
         102   133   136   any
         136   140   136   any
          77   143   146   Class java/lang/InterruptedException
          77   143   150   Class java/lang/Throwable
         192   226   229   any
         229   233   229   any
         240   274   277   any
         277   281   277   any
         188  1674  1677   Class java/lang/Throwable
        1703  1724  1727   Class java/lang/Throwable
        1760  1766  1769   any
        1769  1773  1769   any

  private int mergeDescriptors(long[], int);
    Code:
       0: new           #140                // class java/util/HashMap
       3: dup
       4: iload_2
       5: invokespecial #141                // Method java/util/HashMap."<init>":(I)V
       8: astore_3
       9: iconst_0
      10: istore        4
      12: iload         4
      14: iload_2
      15: if_icmpge     151
      18: aload_3
      19: aload_1
      20: iconst_2
      21: iload         4
      23: imul
      24: iconst_1
      25: iadd
      26: laload
      27: invokestatic  #51                 // Method java/lang/Long.valueOf:(J)Ljava/lang/Long;
      30: aload_1
      31: iconst_2
      32: iload         4
      34: imul
      35: laload
      36: invokestatic  #51                 // Method java/lang/Long.valueOf:(J)Ljava/lang/Long;
      39: invokevirtual #142                // Method java/util/HashMap.put:(Ljava/lang/Object;Ljava/lang/Object;)Ljava/lang/Object;
      42: checkcast     #143                // class java/lang/Long
      45: astore        5
      47: aload         5
      49: ifnull        145
      52: aload_3
      53: aload_1
      54: iconst_2
      55: iload         4
      57: imul
      58: iconst_1
      59: iadd
      60: laload
      61: invokestatic  #51                 // Method java/lang/Long.valueOf:(J)Ljava/lang/Long;
      64: aload_1
      65: iconst_2
      66: iload         4
      68: imul
      69: laload
      70: aload         5
      72: invokevirtual #144                // Method java/lang/Long.longValue:()J
      75: lor
      76: invokestatic  #51                 // Method java/lang/Long.valueOf:(J)Ljava/lang/Long;
      79: invokevirtual #142                // Method java/util/HashMap.put:(Ljava/lang/Object;Ljava/lang/Object;)Ljava/lang/Object;
      82: pop
      83: invokestatic  #46                 // Method org/apache/tomcat/util/net/AprEndpoint.access$200:()Lorg/apache/juli/logging/Log;
      86: invokeinterface #47,  1           // InterfaceMethod org/apache/juli/logging/Log.isDebugEnabled:()Z
      91: ifeq          145
      94: invokestatic  #46                 // Method org/apache/tomcat/util/net/AprEndpoint.access$200:()Lorg/apache/juli/logging/Log;
      97: getstatic     #48                 // Field org/apache/tomcat/util/net/AbstractEndpoint.sm:Lorg/apache/tomcat/util/res/StringManager;
     100: ldc           #145                // String endpoint.apr.pollMergeEvents
     102: iconst_3
     103: anewarray     #50                 // class java/lang/Object
     106: dup
     107: iconst_0
     108: aload_1
     109: iconst_2
     110: iload         4
     112: imul
     113: iconst_1
     114: iadd
     115: laload
     116: invokestatic  #51                 // Method java/lang/Long.valueOf:(J)Ljava/lang/Long;
     119: aastore
     120: dup
     121: iconst_1
     122: aload_1
     123: iconst_2
     124: iload         4
     126: imul
     127: laload
     128: invokestatic  #51                 // Method java/lang/Long.valueOf:(J)Ljava/lang/Long;
     131: aastore
     132: dup
     133: iconst_2
     134: aload         5
     136: aastore
     137: invokevirtual #53                 // Method org/apache/tomcat/util/res/StringManager.getString:(Ljava/lang/String;[Ljava/lang/Object;)Ljava/lang/String;
     140: invokeinterface #58,  2           // InterfaceMethod org/apache/juli/logging/Log.debug:(Ljava/lang/Object;)V
     145: iinc          4, 1
     148: goto          12
     151: iconst_0
     152: istore        4
     154: aload_3
     155: invokevirtual #146                // Method java/util/HashMap.entrySet:()Ljava/util/Set;
     158: invokeinterface #147,  1          // InterfaceMethod java/util/Set.iterator:()Ljava/util/Iterator;
     163: astore        5
     165: aload         5
     167: invokeinterface #148,  1          // InterfaceMethod java/util/Iterator.hasNext:()Z
     172: ifeq          230
     175: aload         5
     177: invokeinterface #149,  1          // InterfaceMethod java/util/Iterator.next:()Ljava/lang/Object;
     182: checkcast     #150                // class java/util/Map$Entry
     185: astore        6
     187: aload_1
     188: iload         4
     190: iinc          4, 1
     193: aload         6
     195: invokeinterface #151,  1          // InterfaceMethod java/util/Map$Entry.getValue:()Ljava/lang/Object;
     200: checkcast     #143                // class java/lang/Long
     203: invokevirtual #144                // Method java/lang/Long.longValue:()J
     206: lastore
     207: aload_1
     208: iload         4
     210: iinc          4, 1
     213: aload         6
     215: invokeinterface #152,  1          // InterfaceMethod java/util/Map$Entry.getKey:()Ljava/lang/Object;
     220: checkcast     #143                // class java/lang/Long
     223: invokevirtual #144                // Method java/lang/Long.longValue:()J
     226: lastore
     227: goto          165
     230: aload_3
     231: invokevirtual #153                // Method java/util/HashMap.size:()I
     234: ireturn

  static void access$500(org.apache.tomcat.util.net.AprEndpoint$Poller, long, long, int);
    Code:
       0: aload_0
       1: lload_1
       2: lload_3
       3: iload         5
       5: invokespecial #2                  // Method add:(JJI)V
       8: return

  static void access$600(org.apache.tomcat.util.net.AprEndpoint$Poller, long);
    Code:
       0: aload_0
       1: lload_1
       2: invokespecial #1                  // Method close:(J)V
       5: return
}
