Compiled from "NioEndpoint.java"
public class org.apache.tomcat.util.net.NioEndpoint$NioSocketWrapper extends org.apache.tomcat.util.net.SocketWrapperBase<org.apache.tomcat.util.net.NioChannel> {
  private final org.apache.tomcat.util.net.NioSelectorPool pool;

  private org.apache.tomcat.util.net.NioEndpoint$Poller poller;

  private int interestOps;

  private java.util.concurrent.CountDownLatch readLatch;

  private java.util.concurrent.CountDownLatch writeLatch;

  private volatile org.apache.tomcat.util.net.NioEndpoint$SendfileData sendfileData;

  private volatile long lastRead;

  private volatile long lastWrite;

  public org.apache.tomcat.util.net.NioEndpoint$NioSocketWrapper(org.apache.tomcat.util.net.NioChannel, org.apache.tomcat.util.net.NioEndpoint);
    Code:
       0: aload_0
       1: aload_1
       2: aload_2
       3: invokespecial #1                  // Method org/apache/tomcat/util/net/SocketWrapperBase."<init>":(Ljava/lang/Object;Lorg/apache/tomcat/util/net/AbstractEndpoint;)V
       6: aload_0
       7: aconst_null
       8: putfield      #2                  // Field poller:Lorg/apache/tomcat/util/net/NioEndpoint$Poller;
      11: aload_0
      12: iconst_0
      13: putfield      #3                  // Field interestOps:I
      16: aload_0
      17: aconst_null
      18: putfield      #4                  // Field readLatch:Ljava/util/concurrent/CountDownLatch;
      21: aload_0
      22: aconst_null
      23: putfield      #5                  // Field writeLatch:Ljava/util/concurrent/CountDownLatch;
      26: aload_0
      27: aconst_null
      28: putfield      #6                  // Field sendfileData:Lorg/apache/tomcat/util/net/NioEndpoint$SendfileData;
      31: aload_0
      32: invokestatic  #7                  // Method java/lang/System.currentTimeMillis:()J
      35: putfield      #8                  // Field lastRead:J
      38: aload_0
      39: aload_0
      40: getfield      #8                  // Field lastRead:J
      43: putfield      #9                  // Field lastWrite:J
      46: aload_0
      47: aload_2
      48: invokevirtual #10                 // Method org/apache/tomcat/util/net/NioEndpoint.getSelectorPool:()Lorg/apache/tomcat/util/net/NioSelectorPool;
      51: putfield      #11                 // Field pool:Lorg/apache/tomcat/util/net/NioSelectorPool;
      54: aload_0
      55: aload_1
      56: invokevirtual #12                 // Method org/apache/tomcat/util/net/NioChannel.getBufHandler:()Lorg/apache/tomcat/util/net/SocketBufferHandler;
      59: putfield      #13                 // Field socketBufferHandler:Lorg/apache/tomcat/util/net/SocketBufferHandler;
      62: return

  public org.apache.tomcat.util.net.NioEndpoint$Poller getPoller();
    Code:
       0: aload_0
       1: getfield      #2                  // Field poller:Lorg/apache/tomcat/util/net/NioEndpoint$Poller;
       4: areturn

  public void setPoller(org.apache.tomcat.util.net.NioEndpoint$Poller);
    Code:
       0: aload_0
       1: aload_1
       2: putfield      #2                  // Field poller:Lorg/apache/tomcat/util/net/NioEndpoint$Poller;
       5: return

  public int interestOps();
    Code:
       0: aload_0
       1: getfield      #3                  // Field interestOps:I
       4: ireturn

  public int interestOps(int);
    Code:
       0: aload_0
       1: iload_1
       2: putfield      #3                  // Field interestOps:I
       5: iload_1
       6: ireturn

  public java.util.concurrent.CountDownLatch getReadLatch();
    Code:
       0: aload_0
       1: getfield      #4                  // Field readLatch:Ljava/util/concurrent/CountDownLatch;
       4: areturn

  public java.util.concurrent.CountDownLatch getWriteLatch();
    Code:
       0: aload_0
       1: getfield      #5                  // Field writeLatch:Ljava/util/concurrent/CountDownLatch;
       4: areturn

  protected java.util.concurrent.CountDownLatch resetLatch(java.util.concurrent.CountDownLatch);
    Code:
       0: aload_1
       1: ifnull        13
       4: aload_1
       5: invokevirtual #14                 // Method java/util/concurrent/CountDownLatch.getCount:()J
       8: lconst_0
       9: lcmp
      10: ifne          15
      13: aconst_null
      14: areturn
      15: new           #15                 // class java/lang/IllegalStateException
      18: dup
      19: ldc           #16                 // String Latch must be at count 0
      21: invokespecial #17                 // Method java/lang/IllegalStateException."<init>":(Ljava/lang/String;)V
      24: athrow

  public void resetReadLatch();
    Code:
       0: aload_0
       1: aload_0
       2: aload_0
       3: getfield      #4                  // Field readLatch:Ljava/util/concurrent/CountDownLatch;
       6: invokevirtual #18                 // Method resetLatch:(Ljava/util/concurrent/CountDownLatch;)Ljava/util/concurrent/CountDownLatch;
       9: putfield      #4                  // Field readLatch:Ljava/util/concurrent/CountDownLatch;
      12: return

  public void resetWriteLatch();
    Code:
       0: aload_0
       1: aload_0
       2: aload_0
       3: getfield      #5                  // Field writeLatch:Ljava/util/concurrent/CountDownLatch;
       6: invokevirtual #18                 // Method resetLatch:(Ljava/util/concurrent/CountDownLatch;)Ljava/util/concurrent/CountDownLatch;
       9: putfield      #5                  // Field writeLatch:Ljava/util/concurrent/CountDownLatch;
      12: return

  protected java.util.concurrent.CountDownLatch startLatch(java.util.concurrent.CountDownLatch, int);
    Code:
       0: aload_1
       1: ifnull        13
       4: aload_1
       5: invokevirtual #14                 // Method java/util/concurrent/CountDownLatch.getCount:()J
       8: lconst_0
       9: lcmp
      10: ifne          22
      13: new           #19                 // class java/util/concurrent/CountDownLatch
      16: dup
      17: iload_2
      18: invokespecial #20                 // Method java/util/concurrent/CountDownLatch."<init>":(I)V
      21: areturn
      22: new           #15                 // class java/lang/IllegalStateException
      25: dup
      26: ldc           #21                 // String Latch must be at count 0 or null.
      28: invokespecial #17                 // Method java/lang/IllegalStateException."<init>":(Ljava/lang/String;)V
      31: athrow

  public void startReadLatch(int);
    Code:
       0: aload_0
       1: aload_0
       2: aload_0
       3: getfield      #4                  // Field readLatch:Ljava/util/concurrent/CountDownLatch;
       6: iload_1
       7: invokevirtual #22                 // Method startLatch:(Ljava/util/concurrent/CountDownLatch;I)Ljava/util/concurrent/CountDownLatch;
      10: putfield      #4                  // Field readLatch:Ljava/util/concurrent/CountDownLatch;
      13: return

  public void startWriteLatch(int);
    Code:
       0: aload_0
       1: aload_0
       2: aload_0
       3: getfield      #5                  // Field writeLatch:Ljava/util/concurrent/CountDownLatch;
       6: iload_1
       7: invokevirtual #22                 // Method startLatch:(Ljava/util/concurrent/CountDownLatch;I)Ljava/util/concurrent/CountDownLatch;
      10: putfield      #5                  // Field writeLatch:Ljava/util/concurrent/CountDownLatch;
      13: return

  protected void awaitLatch(java.util.concurrent.CountDownLatch, long, java.util.concurrent.TimeUnit) throws java.lang.InterruptedException;
    Code:
       0: aload_1
       1: ifnonnull     14
       4: new           #15                 // class java/lang/IllegalStateException
       7: dup
       8: ldc           #23                 // String Latch cannot be null
      10: invokespecial #17                 // Method java/lang/IllegalStateException."<init>":(Ljava/lang/String;)V
      13: athrow
      14: aload_1
      15: lload_2
      16: aload         4
      18: invokevirtual #24                 // Method java/util/concurrent/CountDownLatch.await:(JLjava/util/concurrent/TimeUnit;)Z
      21: pop
      22: return

  public void awaitReadLatch(long, java.util.concurrent.TimeUnit) throws java.lang.InterruptedException;
    Code:
       0: aload_0
       1: aload_0
       2: getfield      #4                  // Field readLatch:Ljava/util/concurrent/CountDownLatch;
       5: lload_1
       6: aload_3
       7: invokevirtual #25                 // Method awaitLatch:(Ljava/util/concurrent/CountDownLatch;JLjava/util/concurrent/TimeUnit;)V
      10: return

  public void awaitWriteLatch(long, java.util.concurrent.TimeUnit) throws java.lang.InterruptedException;
    Code:
       0: aload_0
       1: aload_0
       2: getfield      #5                  // Field writeLatch:Ljava/util/concurrent/CountDownLatch;
       5: lload_1
       6: aload_3
       7: invokevirtual #25                 // Method awaitLatch:(Ljava/util/concurrent/CountDownLatch;JLjava/util/concurrent/TimeUnit;)V
      10: return

  public void setSendfileData(org.apache.tomcat.util.net.NioEndpoint$SendfileData);
    Code:
       0: aload_0
       1: aload_1
       2: putfield      #6                  // Field sendfileData:Lorg/apache/tomcat/util/net/NioEndpoint$SendfileData;
       5: return

  public org.apache.tomcat.util.net.NioEndpoint$SendfileData getSendfileData();
    Code:
       0: aload_0
       1: getfield      #6                  // Field sendfileData:Lorg/apache/tomcat/util/net/NioEndpoint$SendfileData;
       4: areturn

  public void updateLastWrite();
    Code:
       0: aload_0
       1: invokestatic  #7                  // Method java/lang/System.currentTimeMillis:()J
       4: putfield      #9                  // Field lastWrite:J
       7: return

  public long getLastWrite();
    Code:
       0: aload_0
       1: getfield      #9                  // Field lastWrite:J
       4: lreturn

  public void updateLastRead();
    Code:
       0: aload_0
       1: invokestatic  #7                  // Method java/lang/System.currentTimeMillis:()J
       4: putfield      #8                  // Field lastRead:J
       7: return

  public long getLastRead();
    Code:
       0: aload_0
       1: getfield      #8                  // Field lastRead:J
       4: lreturn

  public boolean isReadyForRead() throws java.io.IOException;
    Code:
       0: aload_0
       1: getfield      #13                 // Field socketBufferHandler:Lorg/apache/tomcat/util/net/SocketBufferHandler;
       4: invokevirtual #26                 // Method org/apache/tomcat/util/net/SocketBufferHandler.configureReadBufferForRead:()V
       7: aload_0
       8: getfield      #13                 // Field socketBufferHandler:Lorg/apache/tomcat/util/net/SocketBufferHandler;
      11: invokevirtual #27                 // Method org/apache/tomcat/util/net/SocketBufferHandler.getReadBuffer:()Ljava/nio/ByteBuffer;
      14: invokevirtual #28                 // Method java/nio/ByteBuffer.remaining:()I
      17: ifle          22
      20: iconst_1
      21: ireturn
      22: aload_0
      23: iconst_0
      24: invokespecial #29                 // Method fillReadBuffer:(Z)I
      27: pop
      28: aload_0
      29: getfield      #13                 // Field socketBufferHandler:Lorg/apache/tomcat/util/net/SocketBufferHandler;
      32: invokevirtual #27                 // Method org/apache/tomcat/util/net/SocketBufferHandler.getReadBuffer:()Ljava/nio/ByteBuffer;
      35: invokevirtual #30                 // Method java/nio/ByteBuffer.position:()I
      38: ifle          45
      41: iconst_1
      42: goto          46
      45: iconst_0
      46: istore_1
      47: iload_1
      48: ireturn

  public int read(boolean, byte[], int, int) throws java.io.IOException;
    Code:
       0: aload_0
       1: aload_2
       2: iload_3
       3: iload         4
       5: invokevirtual #31                 // Method populateReadBuffer:([BII)I
       8: istore        5
      10: iload         5
      12: ifle          18
      15: iload         5
      17: ireturn
      18: aload_0
      19: iload_1
      20: invokespecial #29                 // Method fillReadBuffer:(Z)I
      23: istore        5
      25: aload_0
      26: invokevirtual #32                 // Method updateLastRead:()V
      29: iload         5
      31: ifle          65
      34: aload_0
      35: getfield      #13                 // Field socketBufferHandler:Lorg/apache/tomcat/util/net/SocketBufferHandler;
      38: invokevirtual #26                 // Method org/apache/tomcat/util/net/SocketBufferHandler.configureReadBufferForRead:()V
      41: iload         5
      43: iload         4
      45: invokestatic  #33                 // Method java/lang/Math.min:(II)I
      48: istore        5
      50: aload_0
      51: getfield      #13                 // Field socketBufferHandler:Lorg/apache/tomcat/util/net/SocketBufferHandler;
      54: invokevirtual #27                 // Method org/apache/tomcat/util/net/SocketBufferHandler.getReadBuffer:()Ljava/nio/ByteBuffer;
      57: aload_2
      58: iload_3
      59: iload         5
      61: invokevirtual #34                 // Method java/nio/ByteBuffer.get:([BII)Ljava/nio/ByteBuffer;
      64: pop
      65: iload         5
      67: ireturn

  public int read(boolean, java.nio.ByteBuffer) throws java.io.IOException;
    Code:
       0: aload_0
       1: aload_2
       2: invokevirtual #35                 // Method populateReadBuffer:(Ljava/nio/ByteBuffer;)I
       5: istore_3
       6: iload_3
       7: ifle          12
      10: iload_3
      11: ireturn
      12: aload_0
      13: getfield      #13                 // Field socketBufferHandler:Lorg/apache/tomcat/util/net/SocketBufferHandler;
      16: invokevirtual #27                 // Method org/apache/tomcat/util/net/SocketBufferHandler.getReadBuffer:()Ljava/nio/ByteBuffer;
      19: invokevirtual #36                 // Method java/nio/ByteBuffer.capacity:()I
      22: istore        4
      24: aload_2
      25: invokevirtual #28                 // Method java/nio/ByteBuffer.remaining:()I
      28: iload         4
      30: if_icmplt     59
      33: aload_2
      34: aload_2
      35: invokevirtual #30                 // Method java/nio/ByteBuffer.position:()I
      38: iload         4
      40: iadd
      41: invokevirtual #37                 // Method java/nio/ByteBuffer.limit:(I)Ljava/nio/Buffer;
      44: pop
      45: aload_0
      46: iload_1
      47: aload_2
      48: invokespecial #38                 // Method fillReadBuffer:(ZLjava/nio/ByteBuffer;)I
      51: istore_3
      52: aload_0
      53: invokevirtual #32                 // Method updateLastRead:()V
      56: goto          79
      59: aload_0
      60: iload_1
      61: invokespecial #29                 // Method fillReadBuffer:(Z)I
      64: istore_3
      65: aload_0
      66: invokevirtual #32                 // Method updateLastRead:()V
      69: iload_3
      70: ifle          79
      73: aload_0
      74: aload_2
      75: invokevirtual #35                 // Method populateReadBuffer:(Ljava/nio/ByteBuffer;)I
      78: istore_3
      79: iload_3
      80: ireturn

  public void close() throws java.io.IOException;
    Code:
       0: aload_0
       1: invokevirtual #39                 // Method getSocket:()Ljava/lang/Object;
       4: checkcast     #40                 // class org/apache/tomcat/util/net/NioChannel
       7: invokevirtual #41                 // Method org/apache/tomcat/util/net/NioChannel.close:()V
      10: return

  public boolean isClosed();
    Code:
       0: aload_0
       1: invokevirtual #39                 // Method getSocket:()Ljava/lang/Object;
       4: checkcast     #40                 // class org/apache/tomcat/util/net/NioChannel
       7: invokevirtual #42                 // Method org/apache/tomcat/util/net/NioChannel.isOpen:()Z
      10: ifne          17
      13: iconst_1
      14: goto          18
      17: iconst_0
      18: ireturn

  private int fillReadBuffer(boolean) throws java.io.IOException;
    Code:
       0: aload_0
       1: getfield      #13                 // Field socketBufferHandler:Lorg/apache/tomcat/util/net/SocketBufferHandler;
       4: invokevirtual #43                 // Method org/apache/tomcat/util/net/SocketBufferHandler.configureReadBufferForWrite:()V
       7: aload_0
       8: iload_1
       9: aload_0
      10: getfield      #13                 // Field socketBufferHandler:Lorg/apache/tomcat/util/net/SocketBufferHandler;
      13: invokevirtual #27                 // Method org/apache/tomcat/util/net/SocketBufferHandler.getReadBuffer:()Ljava/nio/ByteBuffer;
      16: invokespecial #38                 // Method fillReadBuffer:(ZLjava/nio/ByteBuffer;)I
      19: ireturn

  private int fillReadBuffer(boolean, java.nio.ByteBuffer) throws java.io.IOException;
    Code:
       0: aload_0
       1: invokevirtual #39                 // Method getSocket:()Ljava/lang/Object;
       4: checkcast     #40                 // class org/apache/tomcat/util/net/NioChannel
       7: astore        4
       9: iload_1
      10: ifeq          112
      13: aconst_null
      14: astore        5
      16: aload_0
      17: getfield      #11                 // Field pool:Lorg/apache/tomcat/util/net/NioSelectorPool;
      20: invokevirtual #44                 // Method org/apache/tomcat/util/net/NioSelectorPool.get:()Ljava/nio/channels/Selector;
      23: astore        5
      25: goto          30
      28: astore        6
      30: aload         4
      32: invokevirtual #46                 // Method org/apache/tomcat/util/net/NioChannel.getAttachment:()Ljava/lang/Object;
      35: checkcast     #47                 // class org/apache/tomcat/util/net/NioEndpoint$NioSocketWrapper
      38: astore        6
      40: aload         6
      42: ifnonnull     55
      45: new           #45                 // class java/io/IOException
      48: dup
      49: ldc           #48                 // String Key must be cancelled.
      51: invokespecial #49                 // Method java/io/IOException."<init>":(Ljava/lang/String;)V
      54: athrow
      55: aload_0
      56: getfield      #11                 // Field pool:Lorg/apache/tomcat/util/net/NioSelectorPool;
      59: aload_2
      60: aload         4
      62: aload         5
      64: aload         6
      66: invokevirtual #50                 // Method getReadTimeout:()J
      69: invokevirtual #51                 // Method org/apache/tomcat/util/net/NioSelectorPool.read:(Ljava/nio/ByteBuffer;Lorg/apache/tomcat/util/net/NioChannel;Ljava/nio/channels/Selector;J)I
      72: istore_3
      73: aload         5
      75: ifnull        109
      78: aload_0
      79: getfield      #11                 // Field pool:Lorg/apache/tomcat/util/net/NioSelectorPool;
      82: aload         5
      84: invokevirtual #52                 // Method org/apache/tomcat/util/net/NioSelectorPool.put:(Ljava/nio/channels/Selector;)V
      87: goto          109
      90: astore        7
      92: aload         5
      94: ifnull        106
      97: aload_0
      98: getfield      #11                 // Field pool:Lorg/apache/tomcat/util/net/NioSelectorPool;
     101: aload         5
     103: invokevirtual #52                 // Method org/apache/tomcat/util/net/NioSelectorPool.put:(Ljava/nio/channels/Selector;)V
     106: aload         7
     108: athrow
     109: goto          132
     112: aload         4
     114: aload_2
     115: invokevirtual #53                 // Method org/apache/tomcat/util/net/NioChannel.read:(Ljava/nio/ByteBuffer;)I
     118: istore_3
     119: iload_3
     120: iconst_m1
     121: if_icmpne     132
     124: new           #54                 // class java/io/EOFException
     127: dup
     128: invokespecial #55                 // Method java/io/EOFException."<init>":()V
     131: athrow
     132: iload_3
     133: ireturn
    Exception table:
       from    to  target type
          16    25    28   Class java/io/IOException
          30    73    90   any
          90    92    90   any

  protected void doWrite(boolean, java.nio.ByteBuffer) throws java.io.IOException;
    Code:
       0: aload_0
       1: invokevirtual #56                 // Method getWriteTimeout:()J
       4: lstore_3
       5: aconst_null
       6: astore        5
       8: aload_0
       9: getfield      #11                 // Field pool:Lorg/apache/tomcat/util/net/NioSelectorPool;
      12: invokevirtual #44                 // Method org/apache/tomcat/util/net/NioSelectorPool.get:()Ljava/nio/channels/Selector;
      15: astore        5
      17: goto          22
      20: astore        6
      22: aload_0
      23: getfield      #11                 // Field pool:Lorg/apache/tomcat/util/net/NioSelectorPool;
      26: aload_2
      27: aload_0
      28: invokevirtual #39                 // Method getSocket:()Ljava/lang/Object;
      31: checkcast     #40                 // class org/apache/tomcat/util/net/NioChannel
      34: aload         5
      36: lload_3
      37: iload_1
      38: invokevirtual #57                 // Method org/apache/tomcat/util/net/NioSelectorPool.write:(Ljava/nio/ByteBuffer;Lorg/apache/tomcat/util/net/NioChannel;Ljava/nio/channels/Selector;JZ)I
      41: pop
      42: iload_1
      43: ifeq          66
      46: aload_0
      47: invokevirtual #39                 // Method getSocket:()Ljava/lang/Object;
      50: checkcast     #40                 // class org/apache/tomcat/util/net/NioChannel
      53: iconst_1
      54: aload         5
      56: lload_3
      57: invokevirtual #58                 // Method org/apache/tomcat/util/net/NioChannel.flush:(ZLjava/nio/channels/Selector;J)Z
      60: ifeq          46
      63: goto          66
      66: aload_0
      67: invokevirtual #59                 // Method updateLastWrite:()V
      70: aload         5
      72: ifnull        106
      75: aload_0
      76: getfield      #11                 // Field pool:Lorg/apache/tomcat/util/net/NioSelectorPool;
      79: aload         5
      81: invokevirtual #52                 // Method org/apache/tomcat/util/net/NioSelectorPool.put:(Ljava/nio/channels/Selector;)V
      84: goto          106
      87: astore        7
      89: aload         5
      91: ifnull        103
      94: aload_0
      95: getfield      #11                 // Field pool:Lorg/apache/tomcat/util/net/NioSelectorPool;
      98: aload         5
     100: invokevirtual #52                 // Method org/apache/tomcat/util/net/NioSelectorPool.put:(Ljava/nio/channels/Selector;)V
     103: aload         7
     105: athrow
     106: return
    Exception table:
       from    to  target type
           8    17    20   Class java/io/IOException
          22    70    87   any
          87    89    87   any

  public void registerReadInterest();
    Code:
       0: aload_0
       1: invokevirtual #60                 // Method getPoller:()Lorg/apache/tomcat/util/net/NioEndpoint$Poller;
       4: aload_0
       5: invokevirtual #39                 // Method getSocket:()Ljava/lang/Object;
       8: checkcast     #40                 // class org/apache/tomcat/util/net/NioChannel
      11: iconst_1
      12: invokevirtual #61                 // Method org/apache/tomcat/util/net/NioEndpoint$Poller.add:(Lorg/apache/tomcat/util/net/NioChannel;I)V
      15: return

  public void registerWriteInterest();
    Code:
       0: aload_0
       1: invokevirtual #60                 // Method getPoller:()Lorg/apache/tomcat/util/net/NioEndpoint$Poller;
       4: aload_0
       5: invokevirtual #39                 // Method getSocket:()Ljava/lang/Object;
       8: checkcast     #40                 // class org/apache/tomcat/util/net/NioChannel
      11: iconst_4
      12: invokevirtual #61                 // Method org/apache/tomcat/util/net/NioEndpoint$Poller.add:(Lorg/apache/tomcat/util/net/NioChannel;I)V
      15: return

  public org.apache.tomcat.util.net.SendfileDataBase createSendfileData(java.lang.String, long, long);
    Code:
       0: new           #62                 // class org/apache/tomcat/util/net/NioEndpoint$SendfileData
       3: dup
       4: aload_1
       5: lload_2
       6: lload         4
       8: invokespecial #63                 // Method org/apache/tomcat/util/net/NioEndpoint$SendfileData."<init>":(Ljava/lang/String;JJ)V
      11: areturn

  public org.apache.tomcat.util.net.SendfileState processSendfile(org.apache.tomcat.util.net.SendfileDataBase);
    Code:
       0: aload_0
       1: aload_1
       2: checkcast     #62                 // class org/apache/tomcat/util/net/NioEndpoint$SendfileData
       5: invokevirtual #64                 // Method setSendfileData:(Lorg/apache/tomcat/util/net/NioEndpoint$SendfileData;)V
       8: aload_0
       9: invokevirtual #39                 // Method getSocket:()Ljava/lang/Object;
      12: checkcast     #40                 // class org/apache/tomcat/util/net/NioChannel
      15: invokevirtual #65                 // Method org/apache/tomcat/util/net/NioChannel.getIOChannel:()Ljava/nio/channels/SocketChannel;
      18: aload_0
      19: invokevirtual #39                 // Method getSocket:()Ljava/lang/Object;
      22: checkcast     #40                 // class org/apache/tomcat/util/net/NioChannel
      25: invokevirtual #66                 // Method org/apache/tomcat/util/net/NioChannel.getPoller:()Lorg/apache/tomcat/util/net/NioEndpoint$Poller;
      28: invokevirtual #67                 // Method org/apache/tomcat/util/net/NioEndpoint$Poller.getSelector:()Ljava/nio/channels/Selector;
      31: invokevirtual #68                 // Method java/nio/channels/SocketChannel.keyFor:(Ljava/nio/channels/Selector;)Ljava/nio/channels/SelectionKey;
      34: astore_2
      35: aload_0
      36: invokevirtual #39                 // Method getSocket:()Ljava/lang/Object;
      39: checkcast     #40                 // class org/apache/tomcat/util/net/NioChannel
      42: invokevirtual #66                 // Method org/apache/tomcat/util/net/NioChannel.getPoller:()Lorg/apache/tomcat/util/net/NioEndpoint$Poller;
      45: aload_2
      46: aload_0
      47: iconst_1
      48: invokevirtual #69                 // Method org/apache/tomcat/util/net/NioEndpoint$Poller.processSendfile:(Ljava/nio/channels/SelectionKey;Lorg/apache/tomcat/util/net/NioEndpoint$NioSocketWrapper;Z)Lorg/apache/tomcat/util/net/SendfileState;
      51: areturn

  protected void populateRemoteAddr();
    Code:
       0: aload_0
       1: invokevirtual #39                 // Method getSocket:()Ljava/lang/Object;
       4: checkcast     #40                 // class org/apache/tomcat/util/net/NioChannel
       7: invokevirtual #65                 // Method org/apache/tomcat/util/net/NioChannel.getIOChannel:()Ljava/nio/channels/SocketChannel;
      10: invokevirtual #70                 // Method java/nio/channels/SocketChannel.socket:()Ljava/net/Socket;
      13: invokevirtual #71                 // Method java/net/Socket.getInetAddress:()Ljava/net/InetAddress;
      16: astore_1
      17: aload_1
      18: ifnull        29
      21: aload_0
      22: aload_1
      23: invokevirtual #72                 // Method java/net/InetAddress.getHostAddress:()Ljava/lang/String;
      26: putfield      #73                 // Field remoteAddr:Ljava/lang/String;
      29: return

  protected void populateRemoteHost();
    Code:
       0: aload_0
       1: invokevirtual #39                 // Method getSocket:()Ljava/lang/Object;
       4: checkcast     #40                 // class org/apache/tomcat/util/net/NioChannel
       7: invokevirtual #65                 // Method org/apache/tomcat/util/net/NioChannel.getIOChannel:()Ljava/nio/channels/SocketChannel;
      10: invokevirtual #70                 // Method java/nio/channels/SocketChannel.socket:()Ljava/net/Socket;
      13: invokevirtual #71                 // Method java/net/Socket.getInetAddress:()Ljava/net/InetAddress;
      16: astore_1
      17: aload_1
      18: ifnull        44
      21: aload_0
      22: aload_1
      23: invokevirtual #74                 // Method java/net/InetAddress.getHostName:()Ljava/lang/String;
      26: putfield      #75                 // Field remoteHost:Ljava/lang/String;
      29: aload_0
      30: getfield      #73                 // Field remoteAddr:Ljava/lang/String;
      33: ifnonnull     44
      36: aload_0
      37: aload_1
      38: invokevirtual #72                 // Method java/net/InetAddress.getHostAddress:()Ljava/lang/String;
      41: putfield      #73                 // Field remoteAddr:Ljava/lang/String;
      44: return

  protected void populateRemotePort();
    Code:
       0: aload_0
       1: aload_0
       2: invokevirtual #39                 // Method getSocket:()Ljava/lang/Object;
       5: checkcast     #40                 // class org/apache/tomcat/util/net/NioChannel
       8: invokevirtual #65                 // Method org/apache/tomcat/util/net/NioChannel.getIOChannel:()Ljava/nio/channels/SocketChannel;
      11: invokevirtual #70                 // Method java/nio/channels/SocketChannel.socket:()Ljava/net/Socket;
      14: invokevirtual #76                 // Method java/net/Socket.getPort:()I
      17: putfield      #77                 // Field remotePort:I
      20: return

  protected void populateLocalName();
    Code:
       0: aload_0
       1: invokevirtual #39                 // Method getSocket:()Ljava/lang/Object;
       4: checkcast     #40                 // class org/apache/tomcat/util/net/NioChannel
       7: invokevirtual #65                 // Method org/apache/tomcat/util/net/NioChannel.getIOChannel:()Ljava/nio/channels/SocketChannel;
      10: invokevirtual #70                 // Method java/nio/channels/SocketChannel.socket:()Ljava/net/Socket;
      13: invokevirtual #78                 // Method java/net/Socket.getLocalAddress:()Ljava/net/InetAddress;
      16: astore_1
      17: aload_1
      18: ifnull        29
      21: aload_0
      22: aload_1
      23: invokevirtual #74                 // Method java/net/InetAddress.getHostName:()Ljava/lang/String;
      26: putfield      #79                 // Field localName:Ljava/lang/String;
      29: return

  protected void populateLocalAddr();
    Code:
       0: aload_0
       1: invokevirtual #39                 // Method getSocket:()Ljava/lang/Object;
       4: checkcast     #40                 // class org/apache/tomcat/util/net/NioChannel
       7: invokevirtual #65                 // Method org/apache/tomcat/util/net/NioChannel.getIOChannel:()Ljava/nio/channels/SocketChannel;
      10: invokevirtual #70                 // Method java/nio/channels/SocketChannel.socket:()Ljava/net/Socket;
      13: invokevirtual #78                 // Method java/net/Socket.getLocalAddress:()Ljava/net/InetAddress;
      16: astore_1
      17: aload_1
      18: ifnull        29
      21: aload_0
      22: aload_1
      23: invokevirtual #72                 // Method java/net/InetAddress.getHostAddress:()Ljava/lang/String;
      26: putfield      #80                 // Field localAddr:Ljava/lang/String;
      29: return

  protected void populateLocalPort();
    Code:
       0: aload_0
       1: aload_0
       2: invokevirtual #39                 // Method getSocket:()Ljava/lang/Object;
       5: checkcast     #40                 // class org/apache/tomcat/util/net/NioChannel
       8: invokevirtual #65                 // Method org/apache/tomcat/util/net/NioChannel.getIOChannel:()Ljava/nio/channels/SocketChannel;
      11: invokevirtual #70                 // Method java/nio/channels/SocketChannel.socket:()Ljava/net/Socket;
      14: invokevirtual #81                 // Method java/net/Socket.getLocalPort:()I
      17: putfield      #82                 // Field localPort:I
      20: return

  public org.apache.tomcat.util.net.SSLSupport getSslSupport(java.lang.String);
    Code:
       0: aload_0
       1: invokevirtual #39                 // Method getSocket:()Ljava/lang/Object;
       4: instanceof    #83                 // class org/apache/tomcat/util/net/SecureNioChannel
       7: ifeq          41
      10: aload_0
      11: invokevirtual #39                 // Method getSocket:()Ljava/lang/Object;
      14: checkcast     #83                 // class org/apache/tomcat/util/net/SecureNioChannel
      17: astore_2
      18: aload_2
      19: invokevirtual #84                 // Method org/apache/tomcat/util/net/SecureNioChannel.getSslEngine:()Ljavax/net/ssl/SSLEngine;
      22: invokevirtual #85                 // Method javax/net/ssl/SSLEngine.getSession:()Ljavax/net/ssl/SSLSession;
      25: astore_3
      26: aload_0
      27: invokevirtual #86                 // Method getEndpoint:()Lorg/apache/tomcat/util/net/AbstractEndpoint;
      30: checkcast     #87                 // class org/apache/tomcat/util/net/NioEndpoint
      33: invokevirtual #88                 // Method org/apache/tomcat/util/net/NioEndpoint.getSslImplementation:()Lorg/apache/tomcat/util/net/SSLImplementation;
      36: aload_3
      37: invokevirtual #89                 // Method org/apache/tomcat/util/net/SSLImplementation.getSSLSupport:(Ljavax/net/ssl/SSLSession;)Lorg/apache/tomcat/util/net/SSLSupport;
      40: areturn
      41: aconst_null
      42: areturn

  public void doClientAuth(org.apache.tomcat.util.net.SSLSupport) throws java.io.IOException;
    Code:
       0: aload_0
       1: invokevirtual #39                 // Method getSocket:()Ljava/lang/Object;
       4: checkcast     #83                 // class org/apache/tomcat/util/net/SecureNioChannel
       7: astore_2
       8: aload_2
       9: invokevirtual #84                 // Method org/apache/tomcat/util/net/SecureNioChannel.getSslEngine:()Ljavax/net/ssl/SSLEngine;
      12: astore_3
      13: aload_3
      14: invokevirtual #90                 // Method javax/net/ssl/SSLEngine.getNeedClientAuth:()Z
      17: ifne          48
      20: aload_3
      21: iconst_1
      22: invokevirtual #91                 // Method javax/net/ssl/SSLEngine.setNeedClientAuth:(Z)V
      25: aload_2
      26: aload_0
      27: invokevirtual #86                 // Method getEndpoint:()Lorg/apache/tomcat/util/net/AbstractEndpoint;
      30: invokevirtual #92                 // Method org/apache/tomcat/util/net/AbstractEndpoint.getConnectionTimeout:()I
      33: i2l
      34: invokevirtual #93                 // Method org/apache/tomcat/util/net/SecureNioChannel.rehandshake:(J)V
      37: aload_1
      38: checkcast     #94                 // class org/apache/tomcat/util/net/jsse/JSSESupport
      41: aload_3
      42: invokevirtual #85                 // Method javax/net/ssl/SSLEngine.getSession:()Ljavax/net/ssl/SSLSession;
      45: invokevirtual #95                 // Method org/apache/tomcat/util/net/jsse/JSSESupport.setSession:(Ljavax/net/ssl/SSLSession;)V
      48: return

  public void setAppReadBufHandler(org.apache.tomcat.util.net.ApplicationBufferHandler);
    Code:
       0: aload_0
       1: invokevirtual #39                 // Method getSocket:()Ljava/lang/Object;
       4: checkcast     #40                 // class org/apache/tomcat/util/net/NioChannel
       7: aload_1
       8: invokevirtual #96                 // Method org/apache/tomcat/util/net/NioChannel.setAppReadBufHandler:(Lorg/apache/tomcat/util/net/ApplicationBufferHandler;)V
      11: return
}
