Compiled from "NioEndpoint.java"
public class org.apache.tomcat.util.net.NioEndpoint$SocketProcessor extends org.apache.tomcat.util.net.SocketProcessorBase<org.apache.tomcat.util.net.NioChannel> {
  final org.apache.tomcat.util.net.NioEndpoint this$0;

  public org.apache.tomcat.util.net.NioEndpoint$SocketProcessor(org.apache.tomcat.util.net.SocketWrapperBase<org.apache.tomcat.util.net.NioChannel>, org.apache.tomcat.util.net.SocketEvent);
    Code:
       0: aload_0
       1: aload_1
       2: putfield      #1                  // Field this$0:Lorg/apache/tomcat/util/net/NioEndpoint;
       5: aload_0
       6: aload_2
       7: aload_3
       8: invokespecial #2                  // Method org/apache/tomcat/util/net/SocketProcessorBase."<init>":(Lorg/apache/tomcat/util/net/SocketWrapperBase;Lorg/apache/tomcat/util/net/SocketEvent;)V
      11: return

  protected void doRun();
    Code:
       0: aload_0
       1: getfield      #3                  // Field socketWrapper:Lorg/apache/tomcat/util/net/SocketWrapperBase;
       4: invokevirtual #4                  // Method org/apache/tomcat/util/net/SocketWrapperBase.getSocket:()Ljava/lang/Object;
       7: checkcast     #5                  // class org/apache/tomcat/util/net/NioChannel
      10: astore_1
      11: aload_1
      12: invokevirtual #6                  // Method org/apache/tomcat/util/net/NioChannel.getIOChannel:()Ljava/nio/channels/SocketChannel;
      15: aload_1
      16: invokevirtual #7                  // Method org/apache/tomcat/util/net/NioChannel.getPoller:()Lorg/apache/tomcat/util/net/NioEndpoint$Poller;
      19: invokevirtual #8                  // Method org/apache/tomcat/util/net/NioEndpoint$Poller.getSelector:()Ljava/nio/channels/Selector;
      22: invokevirtual #9                  // Method java/nio/channels/SocketChannel.keyFor:(Ljava/nio/channels/Selector;)Ljava/nio/channels/SelectionKey;
      25: astore_2
      26: iconst_m1
      27: istore_3
      28: aload_2
      29: ifnull        99
      32: aload_1
      33: invokevirtual #10                 // Method org/apache/tomcat/util/net/NioChannel.isHandshakeComplete:()Z
      36: ifeq          44
      39: iconst_0
      40: istore_3
      41: goto          99
      44: aload_0
      45: getfield      #11                 // Field event:Lorg/apache/tomcat/util/net/SocketEvent;
      48: getstatic     #12                 // Field org/apache/tomcat/util/net/SocketEvent.STOP:Lorg/apache/tomcat/util/net/SocketEvent;
      51: if_acmpeq     74
      54: aload_0
      55: getfield      #11                 // Field event:Lorg/apache/tomcat/util/net/SocketEvent;
      58: getstatic     #13                 // Field org/apache/tomcat/util/net/SocketEvent.DISCONNECT:Lorg/apache/tomcat/util/net/SocketEvent;
      61: if_acmpeq     74
      64: aload_0
      65: getfield      #11                 // Field event:Lorg/apache/tomcat/util/net/SocketEvent;
      68: getstatic     #14                 // Field org/apache/tomcat/util/net/SocketEvent.ERROR:Lorg/apache/tomcat/util/net/SocketEvent;
      71: if_acmpne     79
      74: iconst_m1
      75: istore_3
      76: goto          99
      79: aload_1
      80: aload_2
      81: invokevirtual #15                 // Method java/nio/channels/SelectionKey.isReadable:()Z
      84: aload_2
      85: invokevirtual #16                 // Method java/nio/channels/SelectionKey.isWritable:()Z
      88: invokevirtual #17                 // Method org/apache/tomcat/util/net/NioChannel.handshake:(ZZ)I
      91: istore_3
      92: aload_0
      93: getstatic     #18                 // Field org/apache/tomcat/util/net/SocketEvent.OPEN_READ:Lorg/apache/tomcat/util/net/SocketEvent;
      96: putfield      #11                 // Field event:Lorg/apache/tomcat/util/net/SocketEvent;
      99: goto          136
     102: astore        4
     104: iconst_m1
     105: istore_3
     106: invokestatic  #20                 // Method org/apache/tomcat/util/net/NioEndpoint.access$100:()Lorg/apache/juli/logging/Log;
     109: invokeinterface #21,  1           // InterfaceMethod org/apache/juli/logging/Log.isDebugEnabled:()Z
     114: ifeq          129
     117: invokestatic  #20                 // Method org/apache/tomcat/util/net/NioEndpoint.access$100:()Lorg/apache/juli/logging/Log;
     120: ldc           #22                 // String Error during SSL handshake
     122: aload         4
     124: invokeinterface #23,  3           // InterfaceMethod org/apache/juli/logging/Log.debug:(Ljava/lang/Object;Ljava/lang/Throwable;)V
     129: goto          136
     132: astore        4
     134: iconst_m1
     135: istore_3
     136: iload_3
     137: ifne          218
     140: getstatic     #25                 // Field org/apache/tomcat/util/net/AbstractEndpoint$Handler$SocketState.OPEN:Lorg/apache/tomcat/util/net/AbstractEndpoint$Handler$SocketState;
     143: astore        4
     145: aload_0
     146: getfield      #11                 // Field event:Lorg/apache/tomcat/util/net/SocketEvent;
     149: ifnonnull     176
     152: aload_0
     153: getfield      #1                  // Field this$0:Lorg/apache/tomcat/util/net/NioEndpoint;
     156: invokevirtual #26                 // Method org/apache/tomcat/util/net/NioEndpoint.getHandler:()Lorg/apache/tomcat/util/net/AbstractEndpoint$Handler;
     159: aload_0
     160: getfield      #3                  // Field socketWrapper:Lorg/apache/tomcat/util/net/SocketWrapperBase;
     163: getstatic     #18                 // Field org/apache/tomcat/util/net/SocketEvent.OPEN_READ:Lorg/apache/tomcat/util/net/SocketEvent;
     166: invokeinterface #27,  3           // InterfaceMethod org/apache/tomcat/util/net/AbstractEndpoint$Handler.process:(Lorg/apache/tomcat/util/net/SocketWrapperBase;Lorg/apache/tomcat/util/net/SocketEvent;)Lorg/apache/tomcat/util/net/AbstractEndpoint$Handler$SocketState;
     171: astore        4
     173: goto          198
     176: aload_0
     177: getfield      #1                  // Field this$0:Lorg/apache/tomcat/util/net/NioEndpoint;
     180: invokevirtual #26                 // Method org/apache/tomcat/util/net/NioEndpoint.getHandler:()Lorg/apache/tomcat/util/net/AbstractEndpoint$Handler;
     183: aload_0
     184: getfield      #3                  // Field socketWrapper:Lorg/apache/tomcat/util/net/SocketWrapperBase;
     187: aload_0
     188: getfield      #11                 // Field event:Lorg/apache/tomcat/util/net/SocketEvent;
     191: invokeinterface #27,  3           // InterfaceMethod org/apache/tomcat/util/net/AbstractEndpoint$Handler.process:(Lorg/apache/tomcat/util/net/SocketWrapperBase;Lorg/apache/tomcat/util/net/SocketEvent;)Lorg/apache/tomcat/util/net/AbstractEndpoint$Handler$SocketState;
     196: astore        4
     198: aload         4
     200: getstatic     #28                 // Field org/apache/tomcat/util/net/AbstractEndpoint$Handler$SocketState.CLOSED:Lorg/apache/tomcat/util/net/AbstractEndpoint$Handler$SocketState;
     203: if_acmpne     215
     206: aload_0
     207: getfield      #1                  // Field this$0:Lorg/apache/tomcat/util/net/NioEndpoint;
     210: aload_1
     211: aload_2
     212: invokestatic  #29                 // Method org/apache/tomcat/util/net/NioEndpoint.access$400:(Lorg/apache/tomcat/util/net/NioEndpoint;Lorg/apache/tomcat/util/net/NioChannel;Ljava/nio/channels/SelectionKey;)V
     215: goto          262
     218: iload_3
     219: iconst_m1
     220: if_icmpne     235
     223: aload_0
     224: getfield      #1                  // Field this$0:Lorg/apache/tomcat/util/net/NioEndpoint;
     227: aload_1
     228: aload_2
     229: invokestatic  #29                 // Method org/apache/tomcat/util/net/NioEndpoint.access$400:(Lorg/apache/tomcat/util/net/NioEndpoint;Lorg/apache/tomcat/util/net/NioChannel;Ljava/nio/channels/SelectionKey;)V
     232: goto          262
     235: iload_3
     236: iconst_1
     237: if_icmpne     250
     240: aload_0
     241: getfield      #3                  // Field socketWrapper:Lorg/apache/tomcat/util/net/SocketWrapperBase;
     244: invokevirtual #30                 // Method org/apache/tomcat/util/net/SocketWrapperBase.registerReadInterest:()V
     247: goto          262
     250: iload_3
     251: iconst_4
     252: if_icmpne     262
     255: aload_0
     256: getfield      #3                  // Field socketWrapper:Lorg/apache/tomcat/util/net/SocketWrapperBase;
     259: invokevirtual #31                 // Method org/apache/tomcat/util/net/SocketWrapperBase.registerWriteInterest:()V
     262: aload_0
     263: aconst_null
     264: putfield      #3                  // Field socketWrapper:Lorg/apache/tomcat/util/net/SocketWrapperBase;
     267: aload_0
     268: aconst_null
     269: putfield      #11                 // Field event:Lorg/apache/tomcat/util/net/SocketEvent;
     272: aload_0
     273: getfield      #1                  // Field this$0:Lorg/apache/tomcat/util/net/NioEndpoint;
     276: getfield      #32                 // Field org/apache/tomcat/util/net/NioEndpoint.running:Z
     279: ifeq          525
     282: aload_0
     283: getfield      #1                  // Field this$0:Lorg/apache/tomcat/util/net/NioEndpoint;
     286: getfield      #33                 // Field org/apache/tomcat/util/net/NioEndpoint.paused:Z
     289: ifne          525
     292: aload_0
     293: getfield      #1                  // Field this$0:Lorg/apache/tomcat/util/net/NioEndpoint;
     296: getfield      #34                 // Field org/apache/tomcat/util/net/NioEndpoint.processorCache:Lorg/apache/tomcat/util/collections/SynchronizedStack;
     299: aload_0
     300: invokevirtual #35                 // Method org/apache/tomcat/util/collections/SynchronizedStack.push:(Ljava/lang/Object;)Z
     303: pop
     304: goto          525
     307: astore_3
     308: aload_1
     309: invokevirtual #7                  // Method org/apache/tomcat/util/net/NioChannel.getPoller:()Lorg/apache/tomcat/util/net/NioEndpoint$Poller;
     312: aload_2
     313: invokevirtual #36                 // Method org/apache/tomcat/util/net/NioEndpoint$Poller.cancelledKey:(Ljava/nio/channels/SelectionKey;)Lorg/apache/tomcat/util/net/NioEndpoint$NioSocketWrapper;
     316: pop
     317: aload_0
     318: aconst_null
     319: putfield      #3                  // Field socketWrapper:Lorg/apache/tomcat/util/net/SocketWrapperBase;
     322: aload_0
     323: aconst_null
     324: putfield      #11                 // Field event:Lorg/apache/tomcat/util/net/SocketEvent;
     327: aload_0
     328: getfield      #1                  // Field this$0:Lorg/apache/tomcat/util/net/NioEndpoint;
     331: getfield      #32                 // Field org/apache/tomcat/util/net/NioEndpoint.running:Z
     334: ifeq          525
     337: aload_0
     338: getfield      #1                  // Field this$0:Lorg/apache/tomcat/util/net/NioEndpoint;
     341: getfield      #33                 // Field org/apache/tomcat/util/net/NioEndpoint.paused:Z
     344: ifne          525
     347: aload_0
     348: getfield      #1                  // Field this$0:Lorg/apache/tomcat/util/net/NioEndpoint;
     351: getfield      #34                 // Field org/apache/tomcat/util/net/NioEndpoint.processorCache:Lorg/apache/tomcat/util/collections/SynchronizedStack;
     354: aload_0
     355: invokevirtual #35                 // Method org/apache/tomcat/util/collections/SynchronizedStack.push:(Ljava/lang/Object;)Z
     358: pop
     359: goto          525
     362: astore_3
     363: aload_3
     364: invokestatic  #38                 // Method org/apache/tomcat/util/ExceptionUtils.handleThrowable:(Ljava/lang/Throwable;)V
     367: aload_0
     368: aconst_null
     369: putfield      #3                  // Field socketWrapper:Lorg/apache/tomcat/util/net/SocketWrapperBase;
     372: aload_0
     373: aconst_null
     374: putfield      #11                 // Field event:Lorg/apache/tomcat/util/net/SocketEvent;
     377: aload_0
     378: getfield      #1                  // Field this$0:Lorg/apache/tomcat/util/net/NioEndpoint;
     381: getfield      #32                 // Field org/apache/tomcat/util/net/NioEndpoint.running:Z
     384: ifeq          525
     387: aload_0
     388: getfield      #1                  // Field this$0:Lorg/apache/tomcat/util/net/NioEndpoint;
     391: getfield      #33                 // Field org/apache/tomcat/util/net/NioEndpoint.paused:Z
     394: ifne          525
     397: aload_0
     398: getfield      #1                  // Field this$0:Lorg/apache/tomcat/util/net/NioEndpoint;
     401: getfield      #34                 // Field org/apache/tomcat/util/net/NioEndpoint.processorCache:Lorg/apache/tomcat/util/collections/SynchronizedStack;
     404: aload_0
     405: invokevirtual #35                 // Method org/apache/tomcat/util/collections/SynchronizedStack.push:(Ljava/lang/Object;)Z
     408: pop
     409: goto          525
     412: astore_3
     413: invokestatic  #20                 // Method org/apache/tomcat/util/net/NioEndpoint.access$100:()Lorg/apache/juli/logging/Log;
     416: ldc           #40                 // String
     418: aload_3
     419: invokeinterface #41,  3           // InterfaceMethod org/apache/juli/logging/Log.error:(Ljava/lang/Object;Ljava/lang/Throwable;)V
     424: aload_1
     425: invokevirtual #7                  // Method org/apache/tomcat/util/net/NioChannel.getPoller:()Lorg/apache/tomcat/util/net/NioEndpoint$Poller;
     428: aload_2
     429: invokevirtual #36                 // Method org/apache/tomcat/util/net/NioEndpoint$Poller.cancelledKey:(Ljava/nio/channels/SelectionKey;)Lorg/apache/tomcat/util/net/NioEndpoint$NioSocketWrapper;
     432: pop
     433: aload_0
     434: aconst_null
     435: putfield      #3                  // Field socketWrapper:Lorg/apache/tomcat/util/net/SocketWrapperBase;
     438: aload_0
     439: aconst_null
     440: putfield      #11                 // Field event:Lorg/apache/tomcat/util/net/SocketEvent;
     443: aload_0
     444: getfield      #1                  // Field this$0:Lorg/apache/tomcat/util/net/NioEndpoint;
     447: getfield      #32                 // Field org/apache/tomcat/util/net/NioEndpoint.running:Z
     450: ifeq          525
     453: aload_0
     454: getfield      #1                  // Field this$0:Lorg/apache/tomcat/util/net/NioEndpoint;
     457: getfield      #33                 // Field org/apache/tomcat/util/net/NioEndpoint.paused:Z
     460: ifne          525
     463: aload_0
     464: getfield      #1                  // Field this$0:Lorg/apache/tomcat/util/net/NioEndpoint;
     467: getfield      #34                 // Field org/apache/tomcat/util/net/NioEndpoint.processorCache:Lorg/apache/tomcat/util/collections/SynchronizedStack;
     470: aload_0
     471: invokevirtual #35                 // Method org/apache/tomcat/util/collections/SynchronizedStack.push:(Ljava/lang/Object;)Z
     474: pop
     475: goto          525
     478: astore        5
     480: aload_0
     481: aconst_null
     482: putfield      #3                  // Field socketWrapper:Lorg/apache/tomcat/util/net/SocketWrapperBase;
     485: aload_0
     486: aconst_null
     487: putfield      #11                 // Field event:Lorg/apache/tomcat/util/net/SocketEvent;
     490: aload_0
     491: getfield      #1                  // Field this$0:Lorg/apache/tomcat/util/net/NioEndpoint;
     494: getfield      #32                 // Field org/apache/tomcat/util/net/NioEndpoint.running:Z
     497: ifeq          522
     500: aload_0
     501: getfield      #1                  // Field this$0:Lorg/apache/tomcat/util/net/NioEndpoint;
     504: getfield      #33                 // Field org/apache/tomcat/util/net/NioEndpoint.paused:Z
     507: ifne          522
     510: aload_0
     511: getfield      #1                  // Field this$0:Lorg/apache/tomcat/util/net/NioEndpoint;
     514: getfield      #34                 // Field org/apache/tomcat/util/net/NioEndpoint.processorCache:Lorg/apache/tomcat/util/collections/SynchronizedStack;
     517: aload_0
     518: invokevirtual #35                 // Method org/apache/tomcat/util/collections/SynchronizedStack.push:(Ljava/lang/Object;)Z
     521: pop
     522: aload         5
     524: athrow
     525: return
    Exception table:
       from    to  target type
          28    99   102   Class java/io/IOException
          28    99   132   Class java/nio/channels/CancelledKeyException
          26   262   307   Class java/nio/channels/CancelledKeyException
          26   262   362   Class java/lang/VirtualMachineError
          26   262   412   Class java/lang/Throwable
          26   262   478   any
         307   317   478   any
         362   367   478   any
         412   433   478   any
         478   480   478   any
}
