Compiled from "XmlResponsesSaxParser.java"
public class com.amazonaws.services.s3.model.transform.XmlResponsesSaxParser$ListAllMyBucketsHandler extends com.amazonaws.services.s3.model.transform.AbstractHandler {
  private final java.util.List<com.amazonaws.services.s3.model.Bucket> buckets;

  private com.amazonaws.services.s3.model.Owner bucketsOwner;

  private com.amazonaws.services.s3.model.Bucket currentBucket;

  public com.amazonaws.services.s3.model.transform.XmlResponsesSaxParser$ListAllMyBucketsHandler();
    Code:
       0: aload_0
       1: invokespecial #1                  // Method com/amazonaws/services/s3/model/transform/AbstractHandler."<init>":()V
       4: aload_0
       5: new           #2                  // class java/util/ArrayList
       8: dup
       9: invokespecial #3                  // Method java/util/ArrayList."<init>":()V
      12: putfield      #4                  // Field buckets:Ljava/util/List;
      15: aload_0
      16: aconst_null
      17: putfield      #5                  // Field bucketsOwner:Lcom/amazonaws/services/s3/model/Owner;
      20: aload_0
      21: aconst_null
      22: putfield      #6                  // Field currentBucket:Lcom/amazonaws/services/s3/model/Bucket;
      25: return

  public java.util.List<com.amazonaws.services.s3.model.Bucket> getBuckets();
    Code:
       0: aload_0
       1: getfield      #4                  // Field buckets:Ljava/util/List;
       4: areturn

  public com.amazonaws.services.s3.model.Owner getOwner();
    Code:
       0: aload_0
       1: getfield      #5                  // Field bucketsOwner:Lcom/amazonaws/services/s3/model/Owner;
       4: areturn

  protected void doStartElement(java.lang.String, java.lang.String, java.lang.String, org.xml.sax.Attributes);
    Code:
       0: aload_0
       1: iconst_1
       2: anewarray     #7                  // class java/lang/String
       5: dup
       6: iconst_0
       7: ldc           #8                  // String ListAllMyBucketsResult
       9: aastore
      10: invokevirtual #9                  // Method in:([Ljava/lang/String;)Z
      13: ifeq          39
      16: aload_2
      17: ldc           #10                 // String Owner
      19: invokevirtual #11                 // Method java/lang/String.equals:(Ljava/lang/Object;)Z
      22: ifeq          91
      25: aload_0
      26: new           #12                 // class com/amazonaws/services/s3/model/Owner
      29: dup
      30: invokespecial #13                 // Method com/amazonaws/services/s3/model/Owner."<init>":()V
      33: putfield      #5                  // Field bucketsOwner:Lcom/amazonaws/services/s3/model/Owner;
      36: goto          91
      39: aload_0
      40: iconst_2
      41: anewarray     #7                  // class java/lang/String
      44: dup
      45: iconst_0
      46: ldc           #8                  // String ListAllMyBucketsResult
      48: aastore
      49: dup
      50: iconst_1
      51: ldc           #14                 // String Buckets
      53: aastore
      54: invokevirtual #9                  // Method in:([Ljava/lang/String;)Z
      57: ifeq          91
      60: aload_2
      61: ldc           #15                 // String Bucket
      63: invokevirtual #11                 // Method java/lang/String.equals:(Ljava/lang/Object;)Z
      66: ifeq          91
      69: aload_0
      70: new           #16                 // class com/amazonaws/services/s3/model/Bucket
      73: dup
      74: invokespecial #17                 // Method com/amazonaws/services/s3/model/Bucket."<init>":()V
      77: putfield      #6                  // Field currentBucket:Lcom/amazonaws/services/s3/model/Bucket;
      80: aload_0
      81: getfield      #6                  // Field currentBucket:Lcom/amazonaws/services/s3/model/Bucket;
      84: aload_0
      85: getfield      #5                  // Field bucketsOwner:Lcom/amazonaws/services/s3/model/Owner;
      88: invokevirtual #18                 // Method com/amazonaws/services/s3/model/Bucket.setOwner:(Lcom/amazonaws/services/s3/model/Owner;)V
      91: return

  protected void doEndElement(java.lang.String, java.lang.String, java.lang.String);
    Code:
       0: aload_0
       1: iconst_2
       2: anewarray     #7                  // class java/lang/String
       5: dup
       6: iconst_0
       7: ldc           #8                  // String ListAllMyBucketsResult
       9: aastore
      10: dup
      11: iconst_1
      12: ldc           #10                 // String Owner
      14: aastore
      15: invokevirtual #9                  // Method in:([Ljava/lang/String;)Z
      18: ifeq          67
      21: aload_2
      22: ldc           #19                 // String ID
      24: invokevirtual #11                 // Method java/lang/String.equals:(Ljava/lang/Object;)Z
      27: ifeq          44
      30: aload_0
      31: getfield      #5                  // Field bucketsOwner:Lcom/amazonaws/services/s3/model/Owner;
      34: aload_0
      35: invokevirtual #20                 // Method getText:()Ljava/lang/String;
      38: invokevirtual #21                 // Method com/amazonaws/services/s3/model/Owner.setId:(Ljava/lang/String;)V
      41: goto          195
      44: aload_2
      45: ldc           #22                 // String DisplayName
      47: invokevirtual #11                 // Method java/lang/String.equals:(Ljava/lang/Object;)Z
      50: ifeq          195
      53: aload_0
      54: getfield      #5                  // Field bucketsOwner:Lcom/amazonaws/services/s3/model/Owner;
      57: aload_0
      58: invokevirtual #20                 // Method getText:()Ljava/lang/String;
      61: invokevirtual #23                 // Method com/amazonaws/services/s3/model/Owner.setDisplayName:(Ljava/lang/String;)V
      64: goto          195
      67: aload_0
      68: iconst_2
      69: anewarray     #7                  // class java/lang/String
      72: dup
      73: iconst_0
      74: ldc           #8                  // String ListAllMyBucketsResult
      76: aastore
      77: dup
      78: iconst_1
      79: ldc           #14                 // String Buckets
      81: aastore
      82: invokevirtual #9                  // Method in:([Ljava/lang/String;)Z
      85: ifeq          119
      88: aload_2
      89: ldc           #15                 // String Bucket
      91: invokevirtual #11                 // Method java/lang/String.equals:(Ljava/lang/Object;)Z
      94: ifeq          195
      97: aload_0
      98: getfield      #4                  // Field buckets:Ljava/util/List;
     101: aload_0
     102: getfield      #6                  // Field currentBucket:Lcom/amazonaws/services/s3/model/Bucket;
     105: invokeinterface #24,  2           // InterfaceMethod java/util/List.add:(Ljava/lang/Object;)Z
     110: pop
     111: aload_0
     112: aconst_null
     113: putfield      #6                  // Field currentBucket:Lcom/amazonaws/services/s3/model/Bucket;
     116: goto          195
     119: aload_0
     120: iconst_3
     121: anewarray     #7                  // class java/lang/String
     124: dup
     125: iconst_0
     126: ldc           #8                  // String ListAllMyBucketsResult
     128: aastore
     129: dup
     130: iconst_1
     131: ldc           #14                 // String Buckets
     133: aastore
     134: dup
     135: iconst_2
     136: ldc           #15                 // String Bucket
     138: aastore
     139: invokevirtual #9                  // Method in:([Ljava/lang/String;)Z
     142: ifeq          195
     145: aload_2
     146: ldc           #25                 // String Name
     148: invokevirtual #11                 // Method java/lang/String.equals:(Ljava/lang/Object;)Z
     151: ifeq          168
     154: aload_0
     155: getfield      #6                  // Field currentBucket:Lcom/amazonaws/services/s3/model/Bucket;
     158: aload_0
     159: invokevirtual #20                 // Method getText:()Ljava/lang/String;
     162: invokevirtual #26                 // Method com/amazonaws/services/s3/model/Bucket.setName:(Ljava/lang/String;)V
     165: goto          195
     168: aload_2
     169: ldc           #27                 // String CreationDate
     171: invokevirtual #11                 // Method java/lang/String.equals:(Ljava/lang/Object;)Z
     174: ifeq          195
     177: aload_0
     178: invokevirtual #20                 // Method getText:()Ljava/lang/String;
     181: invokestatic  #28                 // Method com/amazonaws/util/DateUtils.parseISO8601Date:(Ljava/lang/String;)Ljava/util/Date;
     184: astore        4
     186: aload_0
     187: getfield      #6                  // Field currentBucket:Lcom/amazonaws/services/s3/model/Bucket;
     190: aload         4
     192: invokevirtual #29                 // Method com/amazonaws/services/s3/model/Bucket.setCreationDate:(Ljava/util/Date;)V
     195: return
}
