Compiled from "LazyInitializationExcludeFilter.java"
public interface org.springframework.boot.LazyInitializationExcludeFilter {
  public abstract boolean isExcluded(java.lang.String, org.springframework.beans.factory.config.BeanDefinition, java.lang.Class<?>);

  public static org.springframework.boot.LazyInitializationExcludeFilter forBeanTypes(java.lang.Class<?>...);
    Code:
       0: aload_0
       1: invokedynamic #1,  0              // InvokeDynamic #0:isExcluded:([Ljava/lang/Class;)Lorg/springframework/boot/LazyInitializationExcludeFilter;
       6: areturn

  private static boolean lambda$forBeanTypes$0(java.lang.Class[], java.lang.String, org.springframework.beans.factory.config.BeanDefinition, java.lang.Class);
    Code:
       0: aload_0
       1: astore        4
       3: aload         4
       5: arraylength
       6: istore        5
       8: iconst_0
       9: istore        6
      11: iload         6
      13: iload         5
      15: if_icmpge     42
      18: aload         4
      20: iload         6
      22: aaload
      23: astore        7
      25: aload         7
      27: aload_3
      28: invokevirtual #2                  // Method java/lang/Class.isAssignableFrom:(Ljava/lang/Class;)Z
      31: ifeq          36
      34: iconst_1
      35: ireturn
      36: iinc          6, 1
      39: goto          11
      42: iconst_0
      43: ireturn
}
