Compiled from "TeeServletInputStream.java"
class ch.qos.logback.access.servlet.TeeServletInputStream extends javax.servlet.ServletInputStream {
  java.io.InputStream in;

  byte[] inputBuffer;

  ch.qos.logback.access.servlet.TeeServletInputStream(javax.servlet.http.HttpServletRequest);
    Code:
       0: aload_0
       1: invokespecial #1                  // Method javax/servlet/ServletInputStream."<init>":()V
       4: aload_0
       5: aload_1
       6: invokespecial #2                  // Method duplicateInputStream:(Ljavax/servlet/http/HttpServletRequest;)V
       9: return

  private void duplicateInputStream(javax.servlet.http.HttpServletRequest);
    Code:
       0: aconst_null
       1: astore_2
       2: aload_1
       3: invokeinterface #3,  1            // InterfaceMethod javax/servlet/http/HttpServletRequest.getInputStream:()Ljavax/servlet/ServletInputStream;
       8: astore_2
       9: aload_0
      10: aload_0
      11: aload_2
      12: invokevirtual #4                  // Method consumeBufferAndReturnAsByteArray:(Ljava/io/InputStream;)[B
      15: putfield      #5                  // Field inputBuffer:[B
      18: aload_0
      19: new           #6                  // class java/io/ByteArrayInputStream
      22: dup
      23: aload_0
      24: getfield      #5                  // Field inputBuffer:[B
      27: invokespecial #7                  // Method java/io/ByteArrayInputStream."<init>":([B)V
      30: putfield      #8                  // Field in:Ljava/io/InputStream;
      33: aload_0
      34: aload_2
      35: invokevirtual #9                  // Method closeStream:(Ljavax/servlet/ServletInputStream;)V
      38: goto          64
      41: astore_3
      42: aload_3
      43: invokevirtual #11                 // Method java/io/IOException.printStackTrace:()V
      46: aload_0
      47: aload_2
      48: invokevirtual #9                  // Method closeStream:(Ljavax/servlet/ServletInputStream;)V
      51: goto          64
      54: astore        4
      56: aload_0
      57: aload_2
      58: invokevirtual #9                  // Method closeStream:(Ljavax/servlet/ServletInputStream;)V
      61: aload         4
      63: athrow
      64: return
    Exception table:
       from    to  target type
           2    33    41   Class java/io/IOException
           2    33    54   any
          41    46    54   any
          54    56    54   any

  public int read() throws java.io.IOException;
    Code:
       0: aload_0
       1: getfield      #8                  // Field in:Ljava/io/InputStream;
       4: invokevirtual #12                 // Method java/io/InputStream.read:()I
       7: ireturn

  byte[] consumeBufferAndReturnAsByteArray(java.io.InputStream) throws java.io.IOException;
    Code:
       0: sipush        1024
       3: istore_2
       4: iload_2
       5: newarray       byte
       7: astore_3
       8: iconst_m1
       9: istore        4
      11: new           #13                 // class java/io/ByteArrayOutputStream
      14: dup
      15: invokespecial #14                 // Method java/io/ByteArrayOutputStream."<init>":()V
      18: astore        5
      20: aload_1
      21: aload_3
      22: iconst_0
      23: iload_2
      24: invokevirtual #15                 // Method java/io/InputStream.read:([BII)I
      27: dup
      28: istore        4
      30: iconst_m1
      31: if_icmpeq     46
      34: aload         5
      36: aload_3
      37: iconst_0
      38: iload         4
      40: invokevirtual #16                 // Method java/io/ByteArrayOutputStream.write:([BII)V
      43: goto          20
      46: aload         5
      48: invokevirtual #17                 // Method java/io/ByteArrayOutputStream.toByteArray:()[B
      51: areturn

  void closeStream(javax.servlet.ServletInputStream);
    Code:
       0: aload_1
       1: ifnull        12
       4: aload_1
       5: invokevirtual #18                 // Method javax/servlet/ServletInputStream.close:()V
       8: goto          12
      11: astore_2
      12: return
    Exception table:
       from    to  target type
           4     8    11   Class java/io/IOException

  byte[] getInputBuffer();
    Code:
       0: aload_0
       1: getfield      #5                  // Field inputBuffer:[B
       4: areturn

  public boolean isFinished();
    Code:
       0: new           #19                 // class java/lang/RuntimeException
       3: dup
       4: ldc           #20                 // String Not yet implemented
       6: invokespecial #21                 // Method java/lang/RuntimeException."<init>":(Ljava/lang/String;)V
       9: athrow

  public boolean isReady();
    Code:
       0: new           #19                 // class java/lang/RuntimeException
       3: dup
       4: ldc           #20                 // String Not yet implemented
       6: invokespecial #21                 // Method java/lang/RuntimeException."<init>":(Ljava/lang/String;)V
       9: athrow

  public void setReadListener(javax.servlet.ReadListener);
    Code:
       0: new           #19                 // class java/lang/RuntimeException
       3: dup
       4: ldc           #20                 // String Not yet implemented
       6: invokespecial #21                 // Method java/lang/RuntimeException."<init>":(Ljava/lang/String;)V
       9: athrow
}
