Compiled from "FileHandler.java"
final class org.apache.juli.FileHandler$1 implements java.util.concurrent.ThreadFactory {
  private static final java.lang.String NAME_PREFIX;

  private final boolean isSecurityEnabled;

  private final java.lang.ThreadGroup group;

  private final java.util.concurrent.atomic.AtomicInteger threadNumber;

  org.apache.juli.FileHandler$1();
    Code:
       0: aload_0
       1: invokespecial #1                  // Method java/lang/Object."<init>":()V
       4: aload_0
       5: new           #2                  // class java/util/concurrent/atomic/AtomicInteger
       8: dup
       9: iconst_1
      10: invokespecial #3                  // Method java/util/concurrent/atomic/AtomicInteger."<init>":(I)V
      13: putfield      #4                  // Field threadNumber:Ljava/util/concurrent/atomic/AtomicInteger;
      16: invokestatic  #5                  // Method java/lang/System.getSecurityManager:()Ljava/lang/SecurityManager;
      19: astore_1
      20: aload_1
      21: ifnonnull     42
      24: aload_0
      25: iconst_0
      26: putfield      #6                  // Field isSecurityEnabled:Z
      29: aload_0
      30: invokestatic  #7                  // Method java/lang/Thread.currentThread:()Ljava/lang/Thread;
      33: invokevirtual #8                  // Method java/lang/Thread.getThreadGroup:()Ljava/lang/ThreadGroup;
      36: putfield      #9                  // Field group:Ljava/lang/ThreadGroup;
      39: goto          55
      42: aload_0
      43: iconst_1
      44: putfield      #6                  // Field isSecurityEnabled:Z
      47: aload_0
      48: aload_1
      49: invokevirtual #10                 // Method java/lang/SecurityManager.getThreadGroup:()Ljava/lang/ThreadGroup;
      52: putfield      #9                  // Field group:Ljava/lang/ThreadGroup;
      55: return

  public java.lang.Thread newThread(java.lang.Runnable);
    Code:
       0: invokestatic  #7                  // Method java/lang/Thread.currentThread:()Ljava/lang/Thread;
       3: invokevirtual #11                 // Method java/lang/Thread.getContextClassLoader:()Ljava/lang/ClassLoader;
       6: astore_2
       7: aload_0
       8: getfield      #6                  // Field isSecurityEnabled:Z
      11: ifeq          27
      14: aload_0
      15: invokedynamic #12,  0             // InvokeDynamic #0:run:(Lorg/apache/juli/FileHandler$1;)Ljava/security/PrivilegedAction;
      20: invokestatic  #13                 // Method java/security/AccessController.doPrivileged:(Ljava/security/PrivilegedAction;)Ljava/lang/Object;
      23: pop
      24: goto          40
      27: invokestatic  #7                  // Method java/lang/Thread.currentThread:()Ljava/lang/Thread;
      30: aload_0
      31: invokevirtual #14                 // Method java/lang/Object.getClass:()Ljava/lang/Class;
      34: invokevirtual #15                 // Method java/lang/Class.getClassLoader:()Ljava/lang/ClassLoader;
      37: invokevirtual #16                 // Method java/lang/Thread.setContextClassLoader:(Ljava/lang/ClassLoader;)V
      40: new           #17                 // class java/lang/Thread
      43: dup
      44: aload_0
      45: getfield      #9                  // Field group:Ljava/lang/ThreadGroup;
      48: aload_1
      49: new           #18                 // class java/lang/StringBuilder
      52: dup
      53: invokespecial #19                 // Method java/lang/StringBuilder."<init>":()V
      56: ldc           #21                 // String FileHandlerLogFilesCleaner-
      58: invokevirtual #22                 // Method java/lang/StringBuilder.append:(Ljava/lang/String;)Ljava/lang/StringBuilder;
      61: aload_0
      62: getfield      #4                  // Field threadNumber:Ljava/util/concurrent/atomic/AtomicInteger;
      65: invokevirtual #23                 // Method java/util/concurrent/atomic/AtomicInteger.getAndIncrement:()I
      68: invokevirtual #24                 // Method java/lang/StringBuilder.append:(I)Ljava/lang/StringBuilder;
      71: invokevirtual #25                 // Method java/lang/StringBuilder.toString:()Ljava/lang/String;
      74: invokespecial #26                 // Method java/lang/Thread."<init>":(Ljava/lang/ThreadGroup;Ljava/lang/Runnable;Ljava/lang/String;)V
      77: astore_3
      78: aload_3
      79: iconst_1
      80: invokevirtual #27                 // Method java/lang/Thread.setDaemon:(Z)V
      83: aload_3
      84: astore        4
      86: aload_0
      87: getfield      #6                  // Field isSecurityEnabled:Z
      90: ifeq          106
      93: aload_2
      94: invokedynamic #28,  0             // InvokeDynamic #1:run:(Ljava/lang/ClassLoader;)Ljava/security/PrivilegedAction;
      99: invokestatic  #13                 // Method java/security/AccessController.doPrivileged:(Ljava/security/PrivilegedAction;)Ljava/lang/Object;
     102: pop
     103: goto          113
     106: invokestatic  #7                  // Method java/lang/Thread.currentThread:()Ljava/lang/Thread;
     109: aload_2
     110: invokevirtual #16                 // Method java/lang/Thread.setContextClassLoader:(Ljava/lang/ClassLoader;)V
     113: aload         4
     115: areturn
     116: astore        5
     118: aload_0
     119: getfield      #6                  // Field isSecurityEnabled:Z
     122: ifeq          138
     125: aload_2
     126: invokedynamic #28,  0             // InvokeDynamic #1:run:(Ljava/lang/ClassLoader;)Ljava/security/PrivilegedAction;
     131: invokestatic  #13                 // Method java/security/AccessController.doPrivileged:(Ljava/security/PrivilegedAction;)Ljava/lang/Object;
     134: pop
     135: goto          145
     138: invokestatic  #7                  // Method java/lang/Thread.currentThread:()Ljava/lang/Thread;
     141: aload_2
     142: invokevirtual #16                 // Method java/lang/Thread.setContextClassLoader:(Ljava/lang/ClassLoader;)V
     145: aload         5
     147: athrow
    Exception table:
       from    to  target type
           7    86   116   any
         116   118   116   any

  private static java.lang.Void lambda$newThread$1(java.lang.ClassLoader);
    Code:
       0: invokestatic  #7                  // Method java/lang/Thread.currentThread:()Ljava/lang/Thread;
       3: aload_0
       4: invokevirtual #16                 // Method java/lang/Thread.setContextClassLoader:(Ljava/lang/ClassLoader;)V
       7: aconst_null
       8: areturn

  private java.lang.Void lambda$newThread$0();
    Code:
       0: invokestatic  #7                  // Method java/lang/Thread.currentThread:()Ljava/lang/Thread;
       3: aload_0
       4: invokevirtual #14                 // Method java/lang/Object.getClass:()Ljava/lang/Class;
       7: invokevirtual #15                 // Method java/lang/Class.getClassLoader:()Ljava/lang/ClassLoader;
      10: invokevirtual #16                 // Method java/lang/Thread.setContextClassLoader:(Ljava/lang/ClassLoader;)V
      13: aconst_null
      14: areturn
}
