Compiled from "StripRedundantTerms.java"
public class net.serenitybdd.screenplay.formatting.StripRedundantTerms {
  private static final java.util.List<java.lang.String> REDUNDANT_HAMCREST_PREFIXES;

  public net.serenitybdd.screenplay.formatting.StripRedundantTerms();
    Code:
       0: aload_0
       1: invokespecial #1                  // Method java/lang/Object."<init>":()V
       4: return

  public static java.lang.String from(java.lang.String);
    Code:
       0: getstatic     #2                  // Field REDUNDANT_HAMCREST_PREFIXES:Ljava/util/List;
       3: invokeinterface #3,  1            // InterfaceMethod java/util/List.iterator:()Ljava/util/Iterator;
       8: astore_1
       9: aload_1
      10: invokeinterface #4,  1            // InterfaceMethod java/util/Iterator.hasNext:()Z
      15: ifeq          37
      18: aload_1
      19: invokeinterface #5,  1            // InterfaceMethod java/util/Iterator.next:()Ljava/lang/Object;
      24: checkcast     #6                  // class java/lang/String
      27: astore_2
      28: aload_2
      29: aload_0
      30: invokestatic  #7                  // Method removePrefix:(Ljava/lang/String;Ljava/lang/String;)Ljava/lang/String;
      33: astore_0
      34: goto          9
      37: aload_0
      38: areturn

  private static java.lang.String removePrefix(java.lang.String, java.lang.String);
    Code:
       0: aload_1
       1: aload_0
       2: invokevirtual #8                  // Method java/lang/String.startsWith:(Ljava/lang/String;)Z
       5: ifeq          14
       8: aload_1
       9: iconst_3
      10: invokevirtual #9                  // Method java/lang/String.substring:(I)Ljava/lang/String;
      13: astore_1
      14: aload_1
      15: areturn

  static {};
    Code:
       0: iconst_3
       1: anewarray     #6                  // class java/lang/String
       4: dup
       5: iconst_0
       6: ldc           #10                 // String is
       8: aastore
       9: dup
      10: iconst_1
      11: ldc           #11                 // String be
      13: aastore
      14: dup
      15: iconst_2
      16: ldc           #12                 // String should be
      18: aastore
      19: invokestatic  #13                 // Method net/serenitybdd/core/collect/NewList.of:([Ljava/lang/Object;)Ljava/util/List;
      22: putstatic     #2                  // Field REDUNDANT_HAMCREST_PREFIXES:Ljava/util/List;
      25: return
}
