Compiled from "StreamViewEntity.java"
public class co.cask.cdap.metadata.entity.StreamViewEntity extends com.cloudera.nav.sdk.model.entities.Entity {
  private final co.cask.cdap.proto.id.StreamViewId streamViewId;

  private final java.lang.String metaClassName;

  public co.cask.cdap.metadata.entity.StreamViewEntity(co.cask.cdap.proto.id.StreamViewId);
    Code:
       0: aload_0
       1: invokespecial #1                  // Method com/cloudera/nav/sdk/model/entities/Entity."<init>":()V
       4: aload_0
       5: aload_1
       6: putfield      #2                  // Field streamViewId:Lco/cask/cdap/proto/id/StreamViewId;
       9: aload_0
      10: ldc           #3                  // String streamviewMetaClassName
      12: putfield      #4                  // Field metaClassName:Ljava/lang/String;
      15: aload_0
      16: aload_1
      17: invokevirtual #5                  // Method co/cask/cdap/proto/id/StreamViewId.toString:()Ljava/lang/String;
      20: invokevirtual #6                  // Method setName:(Ljava/lang/String;)V
      23: return

  public java.lang.String getMetaClassName();
    Code:
       0: aload_0
       1: getfield      #4                  // Field metaClassName:Ljava/lang/String;
       4: areturn

  public com.cloudera.nav.sdk.model.SourceType getSourceType();
    Code:
       0: getstatic     #7                  // Field com/cloudera/nav/sdk/model/SourceType.SDK:Lcom/cloudera/nav/sdk/model/SourceType;
       3: areturn

  public com.cloudera.nav.sdk.model.entities.EntityType getEntityType();
    Code:
       0: getstatic     #8                  // Field com/cloudera/nav/sdk/model/entities/EntityType.TABLE:Lcom/cloudera/nav/sdk/model/entities/EntityType;
       3: areturn

  public java.lang.String generateId();
    Code:
       0: iconst_1
       1: anewarray     #9                  // class java/lang/String
       4: dup
       5: iconst_0
       6: aload_0
       7: getfield      #2                  // Field streamViewId:Lco/cask/cdap/proto/id/StreamViewId;
      10: invokevirtual #5                  // Method co/cask/cdap/proto/id/StreamViewId.toString:()Ljava/lang/String;
      13: aastore
      14: invokestatic  #10                 // Method com/cloudera/nav/sdk/model/MD5IdGenerator.generateIdentity:([Ljava/lang/String;)Ljava/lang/String;
      17: areturn
}
