class org.bouncycastle.mail.smime.handlers.multipart_signed$LineOutputStream extends java.io.FilterOutputStream {
  private static byte[] newline;

  public org.bouncycastle.mail.smime.handlers.multipart_signed$LineOutputStream(java.io.OutputStream);
    Code:
       0: aload_0
       1: aload_1
       2: invokespecial #43                 // Method java/io/FilterOutputStream."<init>":(Ljava/io/OutputStream;)V
       5: return

  public void writeln(java.lang.String) throws javax.mail.MessagingException;
    Code:
       0: aload_1
       1: invokestatic  #47                 // Method getBytes:(Ljava/lang/String;)[B
       4: astore_2
       5: aload_0
       6: getfield      #41                 // Field java/io/FilterOutputStream.out:Ljava/io/OutputStream;
       9: aload_2
      10: invokevirtual #44                 // Method java/io/OutputStream.write:([B)V
      13: aload_0
      14: getfield      #41                 // Field java/io/FilterOutputStream.out:Ljava/io/OutputStream;
      17: getstatic     #42                 // Field newline:[B
      20: invokevirtual #44                 // Method java/io/OutputStream.write:([B)V
      23: goto          38
      26: astore_2
      27: new           #26                 // class javax/mail/MessagingException
      30: dup
      31: ldc           #1                  // String IOException
      33: aload_2
      34: invokespecial #46                 // Method javax/mail/MessagingException."<init>":(Ljava/lang/String;Ljava/lang/Exception;)V
      37: athrow
      38: return
    Exception table:
       from    to  target type
           0    23    26   Class java/lang/Exception

  public void writeln() throws javax.mail.MessagingException;
    Code:
       0: aload_0
       1: getfield      #41                 // Field java/io/FilterOutputStream.out:Ljava/io/OutputStream;
       4: getstatic     #42                 // Field newline:[B
       7: invokevirtual #44                 // Method java/io/OutputStream.write:([B)V
      10: goto          25
      13: astore_1
      14: new           #26                 // class javax/mail/MessagingException
      17: dup
      18: ldc           #1                  // String IOException
      20: aload_1
      21: invokespecial #46                 // Method javax/mail/MessagingException."<init>":(Ljava/lang/String;Ljava/lang/Exception;)V
      24: athrow
      25: return
    Exception table:
       from    to  target type
           0    10    13   Class java/lang/Exception

  private static byte[] getBytes(java.lang.String);
    Code:
       0: aload_0
       1: invokevirtual #45                 // Method java/lang/String.toCharArray:()[C
       4: astore_1
       5: aload_1
       6: arraylength
       7: istore_2
       8: iload_2
       9: newarray       byte
      11: astore_3
      12: iconst_0
      13: istore        4
      15: iload         4
      17: iload_2
      18: if_icmpge     36
      21: aload_3
      22: iload         4
      24: aload_1
      25: iload         4
      27: iinc          4, 1
      30: caload
      31: i2b
      32: bastore
      33: goto          15
      36: aload_3
      37: areturn

  static {};
    Code:
       0: iconst_2
       1: newarray       byte
       3: putstatic     #42                 // Field newline:[B
       6: getstatic     #42                 // Field newline:[B
       9: iconst_0
      10: bipush        13
      12: bastore
      13: getstatic     #42                 // Field newline:[B
      16: iconst_1
      17: bipush        10
      19: bastore
      20: return
}
