Compiled from "JDBCDataSource.kt"
public final class io.vertx.kotlin.servicediscovery.types.JDBCDataSource {
  public static final io.vertx.kotlin.servicediscovery.types.JDBCDataSource INSTANCE;

  public final java.lang.Object getJDBCClientAwait(io.vertx.servicediscovery.ServiceDiscovery, io.vertx.core.json.JsonObject, kotlin.coroutines.Continuation<? super io.vertx.ext.jdbc.JDBCClient>);
    Code:
       0: new           #11                 // class io/vertx/kotlin/servicediscovery/types/JDBCDataSource$getJDBCClientAwait$2
       3: dup
       4: aload_1
       5: aload_2
       6: invokespecial #15                 // Method io/vertx/kotlin/servicediscovery/types/JDBCDataSource$getJDBCClientAwait$2."<init>":(Lio/vertx/servicediscovery/ServiceDiscovery;Lio/vertx/core/json/JsonObject;)V
       9: checkcast     #17                 // class kotlin/jvm/functions/Function1
      12: aload_3
      13: invokestatic  #23                 // Method io/vertx/kotlin/coroutines/VertxCoroutineKt.awaitResult:(Lkotlin/jvm/functions/Function1;Lkotlin/coroutines/Continuation;)Ljava/lang/Object;
      16: areturn

  public final java.lang.Object getJDBCClientAwait(io.vertx.servicediscovery.ServiceDiscovery, kotlin.jvm.functions.Function1<? super io.vertx.servicediscovery.Record, java.lang.Boolean>, kotlin.coroutines.Continuation<? super io.vertx.ext.jdbc.JDBCClient>);
    Code:
       0: new           #35                 // class io/vertx/kotlin/servicediscovery/types/JDBCDataSource$getJDBCClientAwait$4
       3: dup
       4: aload_1
       5: aload_2
       6: invokespecial #38                 // Method io/vertx/kotlin/servicediscovery/types/JDBCDataSource$getJDBCClientAwait$4."<init>":(Lio/vertx/servicediscovery/ServiceDiscovery;Lkotlin/jvm/functions/Function1;)V
       9: checkcast     #17                 // class kotlin/jvm/functions/Function1
      12: aload_3
      13: invokestatic  #23                 // Method io/vertx/kotlin/coroutines/VertxCoroutineKt.awaitResult:(Lkotlin/jvm/functions/Function1;Lkotlin/coroutines/Continuation;)Ljava/lang/Object;
      16: areturn

  public final java.lang.Object getJDBCClientAwait(io.vertx.servicediscovery.ServiceDiscovery, io.vertx.core.json.JsonObject, io.vertx.core.json.JsonObject, kotlin.coroutines.Continuation<? super io.vertx.ext.jdbc.JDBCClient>);
    Code:
       0: new           #43                 // class io/vertx/kotlin/servicediscovery/types/JDBCDataSource$getJDBCClientAwait$6
       3: dup
       4: aload_1
       5: aload_2
       6: aload_3
       7: invokespecial #46                 // Method io/vertx/kotlin/servicediscovery/types/JDBCDataSource$getJDBCClientAwait$6."<init>":(Lio/vertx/servicediscovery/ServiceDiscovery;Lio/vertx/core/json/JsonObject;Lio/vertx/core/json/JsonObject;)V
      10: checkcast     #17                 // class kotlin/jvm/functions/Function1
      13: aload         4
      15: invokestatic  #23                 // Method io/vertx/kotlin/coroutines/VertxCoroutineKt.awaitResult:(Lkotlin/jvm/functions/Function1;Lkotlin/coroutines/Continuation;)Ljava/lang/Object;
      18: areturn

  public final java.lang.Object getJDBCClientAwait(io.vertx.servicediscovery.ServiceDiscovery, kotlin.jvm.functions.Function1<? super io.vertx.servicediscovery.Record, java.lang.Boolean>, io.vertx.core.json.JsonObject, kotlin.coroutines.Continuation<? super io.vertx.ext.jdbc.JDBCClient>);
    Code:
       0: new           #51                 // class io/vertx/kotlin/servicediscovery/types/JDBCDataSource$getJDBCClientAwait$8
       3: dup
       4: aload_1
       5: aload_2
       6: aload_3
       7: invokespecial #54                 // Method io/vertx/kotlin/servicediscovery/types/JDBCDataSource$getJDBCClientAwait$8."<init>":(Lio/vertx/servicediscovery/ServiceDiscovery;Lkotlin/jvm/functions/Function1;Lio/vertx/core/json/JsonObject;)V
      10: checkcast     #17                 // class kotlin/jvm/functions/Function1
      13: aload         4
      15: invokestatic  #23                 // Method io/vertx/kotlin/coroutines/VertxCoroutineKt.awaitResult:(Lkotlin/jvm/functions/Function1;Lkotlin/coroutines/Continuation;)Ljava/lang/Object;
      18: areturn

  private io.vertx.kotlin.servicediscovery.types.JDBCDataSource();
    Code:
       0: aload_0
       1: invokespecial #57                 // Method java/lang/Object."<init>":()V
       4: return

  static {};
    Code:
       0: new           #2                  // class io/vertx/kotlin/servicediscovery/types/JDBCDataSource
       3: dup
       4: invokespecial #76                 // Method "<init>":()V
       7: astore_0
       8: aload_0
       9: putstatic     #78                 // Field INSTANCE:Lio/vertx/kotlin/servicediscovery/types/JDBCDataSource;
      12: return
}
