class org.bouncycastle.crypto.tls.DTLSReplayWindow {
  private static final long VALID_SEQ_MASK;

  private static final long WINDOW_SIZE;

  private long latestConfirmedSeq;

  private long bitmap;

  org.bouncycastle.crypto.tls.DTLSReplayWindow();
    Code:
       0: aload_0
       1: invokespecial #35                 // Method java/lang/Object."<init>":()V
       4: aload_0
       5: ldc2_w        #18                 // long -1l
       8: putfield      #33                 // Field latestConfirmedSeq:J
      11: aload_0
      12: lconst_0
      13: putfield      #32                 // Field bitmap:J
      16: return

  boolean shouldDiscard(long);
    Code:
       0: lload_1
       1: ldc2_w        #22                 // long 281474976710655l
       4: land
       5: lload_1
       6: lcmp
       7: ifeq          12
      10: iconst_1
      11: ireturn
      12: lload_1
      13: aload_0
      14: getfield      #33                 // Field latestConfirmedSeq:J
      17: lcmp
      18: ifgt          54
      21: aload_0
      22: getfield      #33                 // Field latestConfirmedSeq:J
      25: lload_1
      26: lsub
      27: lstore_3
      28: lload_3
      29: ldc2_w        #20                 // long 64l
      32: lcmp
      33: iflt          38
      36: iconst_1
      37: ireturn
      38: aload_0
      39: getfield      #32                 // Field bitmap:J
      42: lconst_1
      43: lload_3
      44: l2i
      45: lshl
      46: land
      47: lconst_0
      48: lcmp
      49: ifeq          54
      52: iconst_1
      53: ireturn
      54: iconst_0
      55: ireturn

  void reportAuthenticated(long);
    Code:
       0: lload_1
       1: ldc2_w        #22                 // long 281474976710655l
       4: land
       5: lload_1
       6: lcmp
       7: ifeq          20
      10: new           #24                 // class java/lang/IllegalArgumentException
      13: dup
      14: ldc           #1                  // String \'seq\' out of range
      16: invokespecial #34                 // Method java/lang/IllegalArgumentException."<init>":(Ljava/lang/String;)V
      19: athrow
      20: lload_1
      21: aload_0
      22: getfield      #33                 // Field latestConfirmedSeq:J
      25: lcmp
      26: ifgt          60
      29: aload_0
      30: getfield      #33                 // Field latestConfirmedSeq:J
      33: lload_1
      34: lsub
      35: lstore_3
      36: lload_3
      37: ldc2_w        #20                 // long 64l
      40: lcmp
      41: ifge          57
      44: aload_0
      45: dup
      46: getfield      #32                 // Field bitmap:J
      49: lconst_1
      50: lload_3
      51: l2i
      52: lshl
      53: lor
      54: putfield      #32                 // Field bitmap:J
      57: goto          109
      60: lload_1
      61: aload_0
      62: getfield      #33                 // Field latestConfirmedSeq:J
      65: lsub
      66: lstore_3
      67: lload_3
      68: ldc2_w        #20                 // long 64l
      71: lcmp
      72: iflt          83
      75: aload_0
      76: lconst_1
      77: putfield      #32                 // Field bitmap:J
      80: goto          104
      83: aload_0
      84: dup
      85: getfield      #32                 // Field bitmap:J
      88: lload_3
      89: l2i
      90: lshl
      91: putfield      #32                 // Field bitmap:J
      94: aload_0
      95: dup
      96: getfield      #32                 // Field bitmap:J
      99: lconst_1
     100: lor
     101: putfield      #32                 // Field bitmap:J
     104: aload_0
     105: lload_1
     106: putfield      #33                 // Field latestConfirmedSeq:J
     109: return

  void reset();
    Code:
       0: aload_0
       1: ldc2_w        #18                 // long -1l
       4: putfield      #33                 // Field latestConfirmedSeq:J
       7: aload_0
       8: lconst_0
       9: putfield      #32                 // Field bitmap:J
      12: return
}
