Compiled from "TextSnapshot.java"
public final class de.skuzzle.test.snapshots.data.text.TextSnapshot implements de.skuzzle.test.snapshots.StructuredDataProvider {
  private final de.skuzzle.test.snapshots.data.text.TextDiff$Settings settings;

  public static final de.skuzzle.test.snapshots.StructuredData text;

  private de.skuzzle.test.snapshots.data.text.TextSnapshot();
    Code:
       0: aload_0
       1: invokespecial #1                  // Method java/lang/Object."<init>":()V
       4: aload_0
       5: invokestatic  #2                  // Method de/skuzzle/test/snapshots/data/text/TextDiff$Settings.defaultSettings:()Lde/skuzzle/test/snapshots/data/text/TextDiff$Settings;
       8: putfield      #3                  // Field settings:Lde/skuzzle/test/snapshots/data/text/TextDiff$Settings;
      11: return

  public static de.skuzzle.test.snapshots.data.text.TextSnapshot text();
    Code:
       0: new           #4                  // class de/skuzzle/test/snapshots/data/text/TextSnapshot
       3: dup
       4: invokespecial #5                  // Method "<init>":()V
       7: areturn

  public de.skuzzle.test.snapshots.data.text.TextSnapshot withIgnoreWhitespaces(boolean);
    Code:
       0: aload_0
       1: getfield      #3                  // Field settings:Lde/skuzzle/test/snapshots/data/text/TextDiff$Settings;
       4: iload_1
       5: invokevirtual #6                  // Method de/skuzzle/test/snapshots/data/text/TextDiff$Settings.withIgnoreWhitespaces:(Z)Lde/skuzzle/test/snapshots/data/text/TextDiff$Settings;
       8: pop
       9: aload_0
      10: areturn

  public de.skuzzle.test.snapshots.data.text.TextSnapshot withContextLines(int);
    Code:
       0: aload_0
       1: getfield      #3                  // Field settings:Lde/skuzzle/test/snapshots/data/text/TextDiff$Settings;
       4: iload_1
       5: invokevirtual #7                  // Method de/skuzzle/test/snapshots/data/text/TextDiff$Settings.withContextLines:(I)Lde/skuzzle/test/snapshots/data/text/TextDiff$Settings;
       8: pop
       9: aload_0
      10: areturn

  public de.skuzzle.test.snapshots.data.text.TextSnapshot withDiffFormat(de.skuzzle.test.snapshots.data.text.TextSnapshot$DiffFormat);
    Code:
       0: aload_0
       1: getfield      #3                  // Field settings:Lde/skuzzle/test/snapshots/data/text/TextDiff$Settings;
       4: aload_1
       5: getfield      #8                  // Field de/skuzzle/test/snapshots/data/text/TextSnapshot$DiffFormat.renderer:Lde/skuzzle/test/snapshots/data/text/DiffRenderer;
       8: invokevirtual #9                  // Method de/skuzzle/test/snapshots/data/text/TextDiff$Settings.withDiffRenderer:(Lde/skuzzle/test/snapshots/data/text/DiffRenderer;)Lde/skuzzle/test/snapshots/data/text/TextDiff$Settings;
      11: pop
      12: aload_0
      13: areturn

  public de.skuzzle.test.snapshots.StructuredData build();
    Code:
       0: new           #10                 // class de/skuzzle/test/snapshots/data/text/TextDiffStructuralAssertions
       3: dup
       4: aload_0
       5: getfield      #3                  // Field settings:Lde/skuzzle/test/snapshots/data/text/TextDiff$Settings;
       8: invokespecial #11                 // Method de/skuzzle/test/snapshots/data/text/TextDiffStructuralAssertions."<init>":(Lde/skuzzle/test/snapshots/data/text/TextDiff$Settings;)V
      11: astore_1
      12: invokedynamic #12,  0             // InvokeDynamic #0:serialize:()Lde/skuzzle/test/snapshots/SnapshotSerializer;
      17: aload_1
      18: invokestatic  #13                 // Method de/skuzzle/test/snapshots/StructuredData.with:(Lde/skuzzle/test/snapshots/SnapshotSerializer;Lde/skuzzle/test/snapshots/StructuralAssertions;)Lde/skuzzle/test/snapshots/StructuredData;
      21: areturn

  static {};
    Code:
       0: invokestatic  #14                 // Method text:()Lde/skuzzle/test/snapshots/data/text/TextSnapshot;
       3: iconst_1
       4: invokevirtual #15                 // Method withIgnoreWhitespaces:(Z)Lde/skuzzle/test/snapshots/data/text/TextSnapshot;
       7: ldc           #17                 // int 2147483647
       9: invokevirtual #18                 // Method withContextLines:(I)Lde/skuzzle/test/snapshots/data/text/TextSnapshot;
      12: invokevirtual #19                 // Method build:()Lde/skuzzle/test/snapshots/StructuredData;
      15: putstatic     #20                 // Field text:Lde/skuzzle/test/snapshots/StructuredData;
      18: return
}
