Compiled from "RestConfiguration.java"
public final class org.apache.camel.spi.RestConfiguration$RestBindingMode extends java.lang.Enum<org.apache.camel.spi.RestConfiguration$RestBindingMode> {
  public static final org.apache.camel.spi.RestConfiguration$RestBindingMode auto;

  public static final org.apache.camel.spi.RestConfiguration$RestBindingMode off;

  public static final org.apache.camel.spi.RestConfiguration$RestBindingMode json;

  public static final org.apache.camel.spi.RestConfiguration$RestBindingMode xml;

  public static final org.apache.camel.spi.RestConfiguration$RestBindingMode json_xml;

  private static final org.apache.camel.spi.RestConfiguration$RestBindingMode[] $VALUES;

  public static org.apache.camel.spi.RestConfiguration$RestBindingMode[] values();
    Code:
       0: getstatic     #21                 // Field $VALUES:[Lorg/apache/camel/spi/RestConfiguration$RestBindingMode;
       3: invokevirtual #26                 // Method "[Lorg/apache/camel/spi/RestConfiguration$RestBindingMode;".clone:()Ljava/lang/Object;
       6: checkcast     #22                 // class "[Lorg/apache/camel/spi/RestConfiguration$RestBindingMode;"
       9: areturn

  public static org.apache.camel.spi.RestConfiguration$RestBindingMode valueOf(java.lang.String);
    Code:
       0: ldc           #2                  // class org/apache/camel/spi/RestConfiguration$RestBindingMode
       2: aload_0
       3: invokestatic  #31                 // Method java/lang/Enum.valueOf:(Ljava/lang/Class;Ljava/lang/String;)Ljava/lang/Enum;
       6: checkcast     #2                  // class org/apache/camel/spi/RestConfiguration$RestBindingMode
       9: areturn

  private org.apache.camel.spi.RestConfiguration$RestBindingMode();
    Code:
       0: aload_0
       1: aload_1
       2: iload_2
       3: invokespecial #37                 // Method java/lang/Enum."<init>":(Ljava/lang/String;I)V
       6: return

  static {};
    Code:
       0: new           #2                  // class org/apache/camel/spi/RestConfiguration$RestBindingMode
       3: dup
       4: ldc           #41                 // String auto
       6: iconst_0
       7: invokespecial #42                 // Method "<init>":(Ljava/lang/String;I)V
      10: putstatic     #44                 // Field auto:Lorg/apache/camel/spi/RestConfiguration$RestBindingMode;
      13: new           #2                  // class org/apache/camel/spi/RestConfiguration$RestBindingMode
      16: dup
      17: ldc           #45                 // String off
      19: iconst_1
      20: invokespecial #42                 // Method "<init>":(Ljava/lang/String;I)V
      23: putstatic     #47                 // Field off:Lorg/apache/camel/spi/RestConfiguration$RestBindingMode;
      26: new           #2                  // class org/apache/camel/spi/RestConfiguration$RestBindingMode
      29: dup
      30: ldc           #48                 // String json
      32: iconst_2
      33: invokespecial #42                 // Method "<init>":(Ljava/lang/String;I)V
      36: putstatic     #50                 // Field json:Lorg/apache/camel/spi/RestConfiguration$RestBindingMode;
      39: new           #2                  // class org/apache/camel/spi/RestConfiguration$RestBindingMode
      42: dup
      43: ldc           #51                 // String xml
      45: iconst_3
      46: invokespecial #42                 // Method "<init>":(Ljava/lang/String;I)V
      49: putstatic     #53                 // Field xml:Lorg/apache/camel/spi/RestConfiguration$RestBindingMode;
      52: new           #2                  // class org/apache/camel/spi/RestConfiguration$RestBindingMode
      55: dup
      56: ldc           #54                 // String json_xml
      58: iconst_4
      59: invokespecial #42                 // Method "<init>":(Ljava/lang/String;I)V
      62: putstatic     #56                 // Field json_xml:Lorg/apache/camel/spi/RestConfiguration$RestBindingMode;
      65: iconst_5
      66: anewarray     #2                  // class org/apache/camel/spi/RestConfiguration$RestBindingMode
      69: dup
      70: iconst_0
      71: getstatic     #44                 // Field auto:Lorg/apache/camel/spi/RestConfiguration$RestBindingMode;
      74: aastore
      75: dup
      76: iconst_1
      77: getstatic     #47                 // Field off:Lorg/apache/camel/spi/RestConfiguration$RestBindingMode;
      80: aastore
      81: dup
      82: iconst_2
      83: getstatic     #50                 // Field json:Lorg/apache/camel/spi/RestConfiguration$RestBindingMode;
      86: aastore
      87: dup
      88: iconst_3
      89: getstatic     #53                 // Field xml:Lorg/apache/camel/spi/RestConfiguration$RestBindingMode;
      92: aastore
      93: dup
      94: iconst_4
      95: getstatic     #56                 // Field json_xml:Lorg/apache/camel/spi/RestConfiguration$RestBindingMode;
      98: aastore
      99: putstatic     #21                 // Field $VALUES:[Lorg/apache/camel/spi/RestConfiguration$RestBindingMode;
     102: return
}
