Compiled from "ConfigKey.java"
public class org.apache.bookkeeper.common.conf.ConfigKey {
  private static final org.slf4j.Logger log;

  public static final java.util.Comparator<org.apache.bookkeeper.common.conf.ConfigKey> ORDERING;

  private boolean required;

  private java.lang.String name;

  private org.apache.bookkeeper.common.conf.Type type;

  private java.lang.String description;

  private java.lang.String documentation;

  private java.lang.Object defaultValue;

  private java.util.List<java.lang.String> optionValues;

  private org.apache.bookkeeper.common.conf.Validator validator;

  private org.apache.bookkeeper.common.conf.ConfigKeyGroup group;

  private int orderInGroup;

  private java.util.List<java.lang.String> dependents;

  private boolean deprecated;

  private java.lang.String deprecatedByConfigKey;

  private java.lang.String deprecatedSince;

  private java.lang.String since;

  public static org.apache.bookkeeper.common.conf.ConfigKey$ConfigKeyBuilder builder(java.lang.String);
    Code:
       0: invokestatic  #15                 // Method internalBuilder:()Lorg/apache/bookkeeper/common/conf/ConfigKey$ConfigKeyBuilder;
       3: aload_0
       4: invokevirtual #16                 // Method org/apache/bookkeeper/common/conf/ConfigKey$ConfigKeyBuilder.name:(Ljava/lang/String;)Lorg/apache/bookkeeper/common/conf/ConfigKey$ConfigKeyBuilder;
       7: areturn

  private java.lang.String defaultValueAsString();
    Code:
       0: aconst_null
       1: aload_0
       2: getfield      #17                 // Field defaultValue:Ljava/lang/Object;
       5: if_acmpne     10
       8: aconst_null
       9: areturn
      10: aload_0
      11: getfield      #17                 // Field defaultValue:Ljava/lang/Object;
      14: instanceof    #18                 // class java/lang/String
      17: ifeq          28
      20: aload_0
      21: getfield      #17                 // Field defaultValue:Ljava/lang/Object;
      24: checkcast     #18                 // class java/lang/String
      27: areturn
      28: aload_0
      29: getfield      #17                 // Field defaultValue:Ljava/lang/Object;
      32: instanceof    #19                 // class java/lang/Class
      35: ifeq          49
      38: aload_0
      39: getfield      #17                 // Field defaultValue:Ljava/lang/Object;
      42: checkcast     #19                 // class java/lang/Class
      45: invokevirtual #20                 // Method java/lang/Class.getName:()Ljava/lang/String;
      48: areturn
      49: aload_0
      50: getfield      #17                 // Field defaultValue:Ljava/lang/Object;
      53: invokevirtual #21                 // Method java/lang/Object.toString:()Ljava/lang/String;
      56: areturn

  public boolean equals(java.lang.Object);
    Code:
       0: aload_1
       1: instanceof    #22                 // class org/apache/bookkeeper/common/conf/ConfigKey
       4: ifne          9
       7: iconst_0
       8: ireturn
       9: aload_1
      10: checkcast     #22                 // class org/apache/bookkeeper/common/conf/ConfigKey
      13: astore_2
      14: aload_0
      15: getfield      #23                 // Field name:Ljava/lang/String;
      18: aload_2
      19: getfield      #23                 // Field name:Ljava/lang/String;
      22: invokestatic  #24                 // Method java/util/Objects.equals:(Ljava/lang/Object;Ljava/lang/Object;)Z
      25: ireturn

  public int hashCode();
    Code:
       0: aload_0
       1: getfield      #23                 // Field name:Ljava/lang/String;
       4: invokevirtual #25                 // Method java/lang/String.hashCode:()I
       7: ireturn

  public void validate(org.apache.commons.configuration.Configuration) throws org.apache.bookkeeper.common.conf.ConfigException;
    Code:
       0: aload_1
       1: aload_0
       2: invokevirtual #26                 // Method name:()Ljava/lang/String;
       5: invokeinterface #27,  2           // InterfaceMethod org/apache/commons/configuration/Configuration.containsKey:(Ljava/lang/String;)Z
      10: ifeq          102
      13: aload_0
      14: invokevirtual #28                 // Method validator:()Lorg/apache/bookkeeper/common/conf/Validator;
      17: ifnull        102
      20: aload_0
      21: aload_1
      22: invokevirtual #29                 // Method get:(Lorg/apache/commons/configuration/Configuration;)Ljava/lang/Object;
      25: astore_2
      26: aload_0
      27: invokevirtual #28                 // Method validator:()Lorg/apache/bookkeeper/common/conf/Validator;
      30: aload_0
      31: invokevirtual #26                 // Method name:()Ljava/lang/String;
      34: aload_2
      35: invokeinterface #30,  3           // InterfaceMethod org/apache/bookkeeper/common/conf/Validator.validate:(Ljava/lang/String;Ljava/lang/Object;)Z
      40: ifne          99
      43: new           #31                 // class org/apache/bookkeeper/common/conf/ConfigException
      46: dup
      47: new           #32                 // class java/lang/StringBuilder
      50: dup
      51: invokespecial #33                 // Method java/lang/StringBuilder."<init>":()V
      54: ldc           #34                 // String Invalid setting of \'
      56: invokevirtual #35                 // Method java/lang/StringBuilder.append:(Ljava/lang/String;)Ljava/lang/StringBuilder;
      59: aload_0
      60: invokevirtual #26                 // Method name:()Ljava/lang/String;
      63: invokevirtual #35                 // Method java/lang/StringBuilder.append:(Ljava/lang/String;)Ljava/lang/StringBuilder;
      66: ldc           #36                 // String \' found the configuration: value = \'
      68: invokevirtual #35                 // Method java/lang/StringBuilder.append:(Ljava/lang/String;)Ljava/lang/StringBuilder;
      71: aload_2
      72: invokevirtual #37                 // Method java/lang/StringBuilder.append:(Ljava/lang/Object;)Ljava/lang/StringBuilder;
      75: ldc           #38                 // String \', requirement = \'
      77: invokevirtual #35                 // Method java/lang/StringBuilder.append:(Ljava/lang/String;)Ljava/lang/StringBuilder;
      80: aload_0
      81: getfield      #39                 // Field validator:Lorg/apache/bookkeeper/common/conf/Validator;
      84: invokevirtual #37                 // Method java/lang/StringBuilder.append:(Ljava/lang/Object;)Ljava/lang/StringBuilder;
      87: ldc           #40                 // String \'
      89: invokevirtual #35                 // Method java/lang/StringBuilder.append:(Ljava/lang/String;)Ljava/lang/StringBuilder;
      92: invokevirtual #41                 // Method java/lang/StringBuilder.toString:()Ljava/lang/String;
      95: invokespecial #42                 // Method org/apache/bookkeeper/common/conf/ConfigException."<init>":(Ljava/lang/String;)V
      98: athrow
      99: goto          144
     102: aload_0
     103: invokevirtual #43                 // Method required:()Z
     106: ifeq          144
     109: new           #31                 // class org/apache/bookkeeper/common/conf/ConfigException
     112: dup
     113: new           #32                 // class java/lang/StringBuilder
     116: dup
     117: invokespecial #33                 // Method java/lang/StringBuilder."<init>":()V
     120: ldc           #44                 // String Setting \'
     122: invokevirtual #35                 // Method java/lang/StringBuilder.append:(Ljava/lang/String;)Ljava/lang/StringBuilder;
     125: aload_0
     126: invokevirtual #26                 // Method name:()Ljava/lang/String;
     129: invokevirtual #35                 // Method java/lang/StringBuilder.append:(Ljava/lang/String;)Ljava/lang/StringBuilder;
     132: ldc           #45                 // String \' is required but missing in the configuration
     134: invokevirtual #35                 // Method java/lang/StringBuilder.append:(Ljava/lang/String;)Ljava/lang/StringBuilder;
     137: invokevirtual #41                 // Method java/lang/StringBuilder.toString:()Ljava/lang/String;
     140: invokespecial #42                 // Method org/apache/bookkeeper/common/conf/ConfigException."<init>":(Ljava/lang/String;)V
     143: athrow
     144: return

  public void set(org.apache.commons.configuration.Configuration, java.lang.Object);
    Code:
       0: aload_0
       1: invokevirtual #46                 // Method type:()Lorg/apache/bookkeeper/common/conf/Type;
       4: invokevirtual #47                 // Method org/apache/bookkeeper/common/conf/Type.validator:()Lorg/apache/bookkeeper/common/conf/Validator;
       7: aload_0
       8: invokevirtual #26                 // Method name:()Ljava/lang/String;
      11: aload_2
      12: invokeinterface #30,  3           // InterfaceMethod org/apache/bookkeeper/common/conf/Validator.validate:(Ljava/lang/String;Ljava/lang/Object;)Z
      17: ifne          71
      20: new           #48                 // class java/lang/IllegalArgumentException
      23: dup
      24: new           #32                 // class java/lang/StringBuilder
      27: dup
      28: invokespecial #33                 // Method java/lang/StringBuilder."<init>":()V
      31: ldc           #49                 // String Invalid value \'
      33: invokevirtual #35                 // Method java/lang/StringBuilder.append:(Ljava/lang/String;)Ljava/lang/StringBuilder;
      36: aload_2
      37: invokevirtual #37                 // Method java/lang/StringBuilder.append:(Ljava/lang/Object;)Ljava/lang/StringBuilder;
      40: ldc           #50                 // String \' to set on setting \'
      42: invokevirtual #35                 // Method java/lang/StringBuilder.append:(Ljava/lang/String;)Ljava/lang/StringBuilder;
      45: aload_0
      46: invokevirtual #26                 // Method name:()Ljava/lang/String;
      49: invokevirtual #35                 // Method java/lang/StringBuilder.append:(Ljava/lang/String;)Ljava/lang/StringBuilder;
      52: ldc           #51                 // String \': expected type =
      54: invokevirtual #35                 // Method java/lang/StringBuilder.append:(Ljava/lang/String;)Ljava/lang/StringBuilder;
      57: aload_0
      58: getfield      #52                 // Field type:Lorg/apache/bookkeeper/common/conf/Type;
      61: invokevirtual #37                 // Method java/lang/StringBuilder.append:(Ljava/lang/Object;)Ljava/lang/StringBuilder;
      64: invokevirtual #41                 // Method java/lang/StringBuilder.toString:()Ljava/lang/String;
      67: invokespecial #53                 // Method java/lang/IllegalArgumentException."<init>":(Ljava/lang/String;)V
      70: athrow
      71: aconst_null
      72: aload_0
      73: invokevirtual #28                 // Method validator:()Lorg/apache/bookkeeper/common/conf/Validator;
      76: if_acmpeq     152
      79: aload_0
      80: invokevirtual #28                 // Method validator:()Lorg/apache/bookkeeper/common/conf/Validator;
      83: aload_0
      84: invokevirtual #26                 // Method name:()Ljava/lang/String;
      87: aload_2
      88: invokeinterface #30,  3           // InterfaceMethod org/apache/bookkeeper/common/conf/Validator.validate:(Ljava/lang/String;Ljava/lang/Object;)Z
      93: ifne          152
      96: new           #48                 // class java/lang/IllegalArgumentException
      99: dup
     100: new           #32                 // class java/lang/StringBuilder
     103: dup
     104: invokespecial #33                 // Method java/lang/StringBuilder."<init>":()V
     107: ldc           #49                 // String Invalid value \'
     109: invokevirtual #35                 // Method java/lang/StringBuilder.append:(Ljava/lang/String;)Ljava/lang/StringBuilder;
     112: aload_2
     113: invokevirtual #37                 // Method java/lang/StringBuilder.append:(Ljava/lang/Object;)Ljava/lang/StringBuilder;
     116: ldc           #50                 // String \' to set on setting \'
     118: invokevirtual #35                 // Method java/lang/StringBuilder.append:(Ljava/lang/String;)Ljava/lang/StringBuilder;
     121: aload_0
     122: invokevirtual #26                 // Method name:()Ljava/lang/String;
     125: invokevirtual #35                 // Method java/lang/StringBuilder.append:(Ljava/lang/String;)Ljava/lang/StringBuilder;
     128: ldc           #54                 // String \': required \'
     130: invokevirtual #35                 // Method java/lang/StringBuilder.append:(Ljava/lang/String;)Ljava/lang/StringBuilder;
     133: aload_0
     134: invokevirtual #28                 // Method validator:()Lorg/apache/bookkeeper/common/conf/Validator;
     137: invokevirtual #37                 // Method java/lang/StringBuilder.append:(Ljava/lang/Object;)Ljava/lang/StringBuilder;
     140: ldc           #40                 // String \'
     142: invokevirtual #35                 // Method java/lang/StringBuilder.append:(Ljava/lang/String;)Ljava/lang/StringBuilder;
     145: invokevirtual #41                 // Method java/lang/StringBuilder.toString:()Ljava/lang/String;
     148: invokespecial #53                 // Method java/lang/IllegalArgumentException."<init>":(Ljava/lang/String;)V
     151: athrow
     152: aload_2
     153: instanceof    #19                 // class java/lang/Class
     156: ifeq          179
     159: aload_1
     160: aload_0
     161: invokevirtual #26                 // Method name:()Ljava/lang/String;
     164: aload_2
     165: checkcast     #19                 // class java/lang/Class
     168: invokevirtual #20                 // Method java/lang/Class.getName:()Ljava/lang/String;
     171: invokeinterface #55,  3           // InterfaceMethod org/apache/commons/configuration/Configuration.setProperty:(Ljava/lang/String;Ljava/lang/Object;)V
     176: goto          190
     179: aload_1
     180: aload_0
     181: invokevirtual #26                 // Method name:()Ljava/lang/String;
     184: aload_2
     185: invokeinterface #55,  3           // InterfaceMethod org/apache/commons/configuration/Configuration.setProperty:(Ljava/lang/String;Ljava/lang/Object;)V
     190: return

  public long getLong(org.apache.commons.configuration.Configuration);
    Code:
       0: aload_0
       1: invokevirtual #46                 // Method type:()Lorg/apache/bookkeeper/common/conf/Type;
       4: getstatic     #56                 // Field org/apache/bookkeeper/common/conf/Type.LONG:Lorg/apache/bookkeeper/common/conf/Type;
       7: if_acmpne     14
      10: iconst_1
      11: goto          15
      14: iconst_0
      15: new           #32                 // class java/lang/StringBuilder
      18: dup
      19: invokespecial #33                 // Method java/lang/StringBuilder."<init>":()V
      22: ldc           #40                 // String \'
      24: invokevirtual #35                 // Method java/lang/StringBuilder.append:(Ljava/lang/String;)Ljava/lang/StringBuilder;
      27: aload_0
      28: invokevirtual #26                 // Method name:()Ljava/lang/String;
      31: invokevirtual #35                 // Method java/lang/StringBuilder.append:(Ljava/lang/String;)Ljava/lang/StringBuilder;
      34: ldc           #57                 // String \' is NOT a LONG numeric setting
      36: invokevirtual #35                 // Method java/lang/StringBuilder.append:(Ljava/lang/String;)Ljava/lang/StringBuilder;
      39: invokevirtual #41                 // Method java/lang/StringBuilder.toString:()Ljava/lang/String;
      42: invokestatic  #58                 // Method com/google/common/base/Preconditions.checkArgument:(ZLjava/lang/Object;)V
      45: aload_1
      46: aload_0
      47: invokevirtual #26                 // Method name:()Ljava/lang/String;
      50: aload_0
      51: invokevirtual #59                 // Method defaultValue:()Ljava/lang/Object;
      54: checkcast     #60                 // class java/lang/Long
      57: invokeinterface #61,  3           // InterfaceMethod org/apache/commons/configuration/Configuration.getLong:(Ljava/lang/String;Ljava/lang/Long;)Ljava/lang/Long;
      62: invokevirtual #62                 // Method java/lang/Long.longValue:()J
      65: lreturn

  public int getInt(org.apache.commons.configuration.Configuration);
    Code:
       0: aload_0
       1: invokevirtual #46                 // Method type:()Lorg/apache/bookkeeper/common/conf/Type;
       4: getstatic     #63                 // Field org/apache/bookkeeper/common/conf/Type.INT:Lorg/apache/bookkeeper/common/conf/Type;
       7: if_acmpne     14
      10: iconst_1
      11: goto          15
      14: iconst_0
      15: new           #32                 // class java/lang/StringBuilder
      18: dup
      19: invokespecial #33                 // Method java/lang/StringBuilder."<init>":()V
      22: ldc           #40                 // String \'
      24: invokevirtual #35                 // Method java/lang/StringBuilder.append:(Ljava/lang/String;)Ljava/lang/StringBuilder;
      27: aload_0
      28: invokevirtual #26                 // Method name:()Ljava/lang/String;
      31: invokevirtual #35                 // Method java/lang/StringBuilder.append:(Ljava/lang/String;)Ljava/lang/StringBuilder;
      34: ldc           #64                 // String \' is NOT a INT numeric setting
      36: invokevirtual #35                 // Method java/lang/StringBuilder.append:(Ljava/lang/String;)Ljava/lang/StringBuilder;
      39: invokevirtual #41                 // Method java/lang/StringBuilder.toString:()Ljava/lang/String;
      42: invokestatic  #58                 // Method com/google/common/base/Preconditions.checkArgument:(ZLjava/lang/Object;)V
      45: aload_1
      46: aload_0
      47: invokevirtual #26                 // Method name:()Ljava/lang/String;
      50: aload_0
      51: invokevirtual #59                 // Method defaultValue:()Ljava/lang/Object;
      54: checkcast     #65                 // class java/lang/Integer
      57: invokevirtual #66                 // Method java/lang/Integer.intValue:()I
      60: invokeinterface #67,  3           // InterfaceMethod org/apache/commons/configuration/Configuration.getInt:(Ljava/lang/String;I)I
      65: ireturn

  public short getShort(org.apache.commons.configuration.Configuration);
    Code:
       0: aload_0
       1: invokevirtual #46                 // Method type:()Lorg/apache/bookkeeper/common/conf/Type;
       4: getstatic     #68                 // Field org/apache/bookkeeper/common/conf/Type.SHORT:Lorg/apache/bookkeeper/common/conf/Type;
       7: if_acmpne     14
      10: iconst_1
      11: goto          15
      14: iconst_0
      15: new           #32                 // class java/lang/StringBuilder
      18: dup
      19: invokespecial #33                 // Method java/lang/StringBuilder."<init>":()V
      22: ldc           #40                 // String \'
      24: invokevirtual #35                 // Method java/lang/StringBuilder.append:(Ljava/lang/String;)Ljava/lang/StringBuilder;
      27: aload_0
      28: invokevirtual #26                 // Method name:()Ljava/lang/String;
      31: invokevirtual #35                 // Method java/lang/StringBuilder.append:(Ljava/lang/String;)Ljava/lang/StringBuilder;
      34: ldc           #69                 // String \' is NOT a SHORT numeric setting
      36: invokevirtual #35                 // Method java/lang/StringBuilder.append:(Ljava/lang/String;)Ljava/lang/StringBuilder;
      39: invokevirtual #41                 // Method java/lang/StringBuilder.toString:()Ljava/lang/String;
      42: invokestatic  #58                 // Method com/google/common/base/Preconditions.checkArgument:(ZLjava/lang/Object;)V
      45: aload_1
      46: aload_0
      47: invokevirtual #26                 // Method name:()Ljava/lang/String;
      50: aload_0
      51: invokevirtual #59                 // Method defaultValue:()Ljava/lang/Object;
      54: checkcast     #70                 // class java/lang/Short
      57: invokeinterface #71,  3           // InterfaceMethod org/apache/commons/configuration/Configuration.getShort:(Ljava/lang/String;Ljava/lang/Short;)Ljava/lang/Short;
      62: invokevirtual #72                 // Method java/lang/Short.shortValue:()S
      65: ireturn

  public boolean getBoolean(org.apache.commons.configuration.Configuration);
    Code:
       0: aload_0
       1: invokevirtual #46                 // Method type:()Lorg/apache/bookkeeper/common/conf/Type;
       4: getstatic     #73                 // Field org/apache/bookkeeper/common/conf/Type.BOOLEAN:Lorg/apache/bookkeeper/common/conf/Type;
       7: if_acmpne     14
      10: iconst_1
      11: goto          15
      14: iconst_0
      15: new           #32                 // class java/lang/StringBuilder
      18: dup
      19: invokespecial #33                 // Method java/lang/StringBuilder."<init>":()V
      22: ldc           #40                 // String \'
      24: invokevirtual #35                 // Method java/lang/StringBuilder.append:(Ljava/lang/String;)Ljava/lang/StringBuilder;
      27: aload_0
      28: invokevirtual #26                 // Method name:()Ljava/lang/String;
      31: invokevirtual #35                 // Method java/lang/StringBuilder.append:(Ljava/lang/String;)Ljava/lang/StringBuilder;
      34: ldc           #74                 // String \' is NOT a BOOL numeric setting
      36: invokevirtual #35                 // Method java/lang/StringBuilder.append:(Ljava/lang/String;)Ljava/lang/StringBuilder;
      39: invokevirtual #41                 // Method java/lang/StringBuilder.toString:()Ljava/lang/String;
      42: invokestatic  #58                 // Method com/google/common/base/Preconditions.checkArgument:(ZLjava/lang/Object;)V
      45: aload_1
      46: aload_0
      47: invokevirtual #26                 // Method name:()Ljava/lang/String;
      50: aload_0
      51: invokevirtual #59                 // Method defaultValue:()Ljava/lang/Object;
      54: checkcast     #75                 // class java/lang/Boolean
      57: invokeinterface #76,  3           // InterfaceMethod org/apache/commons/configuration/Configuration.getBoolean:(Ljava/lang/String;Ljava/lang/Boolean;)Ljava/lang/Boolean;
      62: invokevirtual #77                 // Method java/lang/Boolean.booleanValue:()Z
      65: ireturn

  public double getDouble(org.apache.commons.configuration.Configuration);
    Code:
       0: aload_0
       1: invokevirtual #46                 // Method type:()Lorg/apache/bookkeeper/common/conf/Type;
       4: getstatic     #78                 // Field org/apache/bookkeeper/common/conf/Type.DOUBLE:Lorg/apache/bookkeeper/common/conf/Type;
       7: if_acmpne     14
      10: iconst_1
      11: goto          15
      14: iconst_0
      15: new           #32                 // class java/lang/StringBuilder
      18: dup
      19: invokespecial #33                 // Method java/lang/StringBuilder."<init>":()V
      22: ldc           #40                 // String \'
      24: invokevirtual #35                 // Method java/lang/StringBuilder.append:(Ljava/lang/String;)Ljava/lang/StringBuilder;
      27: aload_0
      28: invokevirtual #26                 // Method name:()Ljava/lang/String;
      31: invokevirtual #35                 // Method java/lang/StringBuilder.append:(Ljava/lang/String;)Ljava/lang/StringBuilder;
      34: ldc           #79                 // String \' is NOT a DOUBLE numeric setting
      36: invokevirtual #35                 // Method java/lang/StringBuilder.append:(Ljava/lang/String;)Ljava/lang/StringBuilder;
      39: invokevirtual #41                 // Method java/lang/StringBuilder.toString:()Ljava/lang/String;
      42: invokestatic  #58                 // Method com/google/common/base/Preconditions.checkArgument:(ZLjava/lang/Object;)V
      45: aload_1
      46: aload_0
      47: invokevirtual #26                 // Method name:()Ljava/lang/String;
      50: aload_0
      51: invokevirtual #59                 // Method defaultValue:()Ljava/lang/Object;
      54: checkcast     #80                 // class java/lang/Double
      57: invokeinterface #81,  3           // InterfaceMethod org/apache/commons/configuration/Configuration.getDouble:(Ljava/lang/String;Ljava/lang/Double;)Ljava/lang/Double;
      62: invokevirtual #82                 // Method java/lang/Double.doubleValue:()D
      65: dreturn

  public java.lang.String getString(org.apache.commons.configuration.Configuration);
    Code:
       0: aload_1
       1: aload_0
       2: invokevirtual #26                 // Method name:()Ljava/lang/String;
       5: aload_0
       6: invokespecial #83                 // Method defaultValueAsString:()Ljava/lang/String;
       9: invokeinterface #84,  3           // InterfaceMethod org/apache/commons/configuration/Configuration.getString:(Ljava/lang/String;Ljava/lang/String;)Ljava/lang/String;
      14: areturn

  public <T> java.lang.Class<? extends T> getClass(org.apache.commons.configuration.Configuration, java.lang.Class<T>);
    Code:
       0: aload_0
       1: invokevirtual #46                 // Method type:()Lorg/apache/bookkeeper/common/conf/Type;
       4: getstatic     #85                 // Field org/apache/bookkeeper/common/conf/Type.CLASS:Lorg/apache/bookkeeper/common/conf/Type;
       7: if_acmpne     14
      10: iconst_1
      11: goto          15
      14: iconst_0
      15: new           #32                 // class java/lang/StringBuilder
      18: dup
      19: invokespecial #33                 // Method java/lang/StringBuilder."<init>":()V
      22: ldc           #40                 // String \'
      24: invokevirtual #35                 // Method java/lang/StringBuilder.append:(Ljava/lang/String;)Ljava/lang/StringBuilder;
      27: aload_0
      28: invokevirtual #26                 // Method name:()Ljava/lang/String;
      31: invokevirtual #35                 // Method java/lang/StringBuilder.append:(Ljava/lang/String;)Ljava/lang/StringBuilder;
      34: ldc           #86                 // String \' is NOT a CLASS setting
      36: invokevirtual #35                 // Method java/lang/StringBuilder.append:(Ljava/lang/String;)Ljava/lang/StringBuilder;
      39: invokevirtual #41                 // Method java/lang/StringBuilder.toString:()Ljava/lang/String;
      42: invokestatic  #58                 // Method com/google/common/base/Preconditions.checkArgument:(ZLjava/lang/Object;)V
      45: aload_0
      46: invokevirtual #59                 // Method defaultValue:()Ljava/lang/Object;
      49: checkcast     #19                 // class java/lang/Class
      52: astore_3
      53: aload_1
      54: aload_0
      55: invokevirtual #26                 // Method name:()Ljava/lang/String;
      58: aload_3
      59: aload_2
      60: aload_0
      61: invokevirtual #87                 // Method java/lang/Object.getClass:()Ljava/lang/Class;
      64: invokevirtual #88                 // Method java/lang/Class.getClassLoader:()Ljava/lang/ClassLoader;
      67: invokestatic  #89                 // Method org/apache/bookkeeper/common/util/ReflectionUtils.getClass:(Lorg/apache/commons/configuration/Configuration;Ljava/lang/String;Ljava/lang/Class;Ljava/lang/Class;Ljava/lang/ClassLoader;)Ljava/lang/Class;
      70: areturn
      71: astore_3
      72: new           #48                 // class java/lang/IllegalArgumentException
      75: dup
      76: new           #32                 // class java/lang/StringBuilder
      79: dup
      80: invokespecial #33                 // Method java/lang/StringBuilder."<init>":()V
      83: ldc           #91                 // String Invalid class is set to setting \'
      85: invokevirtual #35                 // Method java/lang/StringBuilder.append:(Ljava/lang/String;)Ljava/lang/StringBuilder;
      88: aload_0
      89: invokevirtual #26                 // Method name:()Ljava/lang/String;
      92: invokevirtual #35                 // Method java/lang/StringBuilder.append:(Ljava/lang/String;)Ljava/lang/StringBuilder;
      95: ldc           #92                 // String \':
      97: invokevirtual #35                 // Method java/lang/StringBuilder.append:(Ljava/lang/String;)Ljava/lang/StringBuilder;
     100: invokevirtual #41                 // Method java/lang/StringBuilder.toString:()Ljava/lang/String;
     103: aload_3
     104: invokespecial #93                 // Method java/lang/IllegalArgumentException."<init>":(Ljava/lang/String;Ljava/lang/Throwable;)V
     107: athrow
    Exception table:
       from    to  target type
          45    70    71   Class org/apache/commons/configuration/ConfigurationException

  public java.lang.Class<?> getClass(org.apache.commons.configuration.Configuration);
    Code:
       0: aload_0
       1: invokevirtual #46                 // Method type:()Lorg/apache/bookkeeper/common/conf/Type;
       4: getstatic     #85                 // Field org/apache/bookkeeper/common/conf/Type.CLASS:Lorg/apache/bookkeeper/common/conf/Type;
       7: if_acmpne     14
      10: iconst_1
      11: goto          15
      14: iconst_0
      15: new           #32                 // class java/lang/StringBuilder
      18: dup
      19: invokespecial #33                 // Method java/lang/StringBuilder."<init>":()V
      22: ldc           #40                 // String \'
      24: invokevirtual #35                 // Method java/lang/StringBuilder.append:(Ljava/lang/String;)Ljava/lang/StringBuilder;
      27: aload_0
      28: invokevirtual #26                 // Method name:()Ljava/lang/String;
      31: invokevirtual #35                 // Method java/lang/StringBuilder.append:(Ljava/lang/String;)Ljava/lang/StringBuilder;
      34: ldc           #86                 // String \' is NOT a CLASS setting
      36: invokevirtual #35                 // Method java/lang/StringBuilder.append:(Ljava/lang/String;)Ljava/lang/StringBuilder;
      39: invokevirtual #41                 // Method java/lang/StringBuilder.toString:()Ljava/lang/String;
      42: invokestatic  #58                 // Method com/google/common/base/Preconditions.checkArgument:(ZLjava/lang/Object;)V
      45: aload_0
      46: invokevirtual #59                 // Method defaultValue:()Ljava/lang/Object;
      49: checkcast     #19                 // class java/lang/Class
      52: astore_2
      53: aload_1
      54: aload_0
      55: invokevirtual #26                 // Method name:()Ljava/lang/String;
      58: aload_2
      59: aload_0
      60: invokevirtual #87                 // Method java/lang/Object.getClass:()Ljava/lang/Class;
      63: invokevirtual #88                 // Method java/lang/Class.getClassLoader:()Ljava/lang/ClassLoader;
      66: invokestatic  #94                 // Method org/apache/bookkeeper/common/util/ReflectionUtils.getClass:(Lorg/apache/commons/configuration/Configuration;Ljava/lang/String;Ljava/lang/Class;Ljava/lang/ClassLoader;)Ljava/lang/Class;
      69: areturn
      70: astore_2
      71: new           #48                 // class java/lang/IllegalArgumentException
      74: dup
      75: new           #32                 // class java/lang/StringBuilder
      78: dup
      79: invokespecial #33                 // Method java/lang/StringBuilder."<init>":()V
      82: ldc           #91                 // String Invalid class is set to setting \'
      84: invokevirtual #35                 // Method java/lang/StringBuilder.append:(Ljava/lang/String;)Ljava/lang/StringBuilder;
      87: aload_0
      88: invokevirtual #26                 // Method name:()Ljava/lang/String;
      91: invokevirtual #35                 // Method java/lang/StringBuilder.append:(Ljava/lang/String;)Ljava/lang/StringBuilder;
      94: ldc           #92                 // String \':
      96: invokevirtual #35                 // Method java/lang/StringBuilder.append:(Ljava/lang/String;)Ljava/lang/StringBuilder;
      99: invokevirtual #41                 // Method java/lang/StringBuilder.toString:()Ljava/lang/String;
     102: aload_2
     103: invokespecial #93                 // Method java/lang/IllegalArgumentException."<init>":(Ljava/lang/String;Ljava/lang/Throwable;)V
     106: athrow
    Exception table:
       from    to  target type
          45    69    70   Class org/apache/commons/configuration/ConfigurationException

  public java.util.List<java.lang.Object> getList(org.apache.commons.configuration.Configuration);
    Code:
       0: aload_0
       1: invokevirtual #46                 // Method type:()Lorg/apache/bookkeeper/common/conf/Type;
       4: getstatic     #95                 // Field org/apache/bookkeeper/common/conf/Type.LIST:Lorg/apache/bookkeeper/common/conf/Type;
       7: if_acmpne     14
      10: iconst_1
      11: goto          15
      14: iconst_0
      15: new           #32                 // class java/lang/StringBuilder
      18: dup
      19: invokespecial #33                 // Method java/lang/StringBuilder."<init>":()V
      22: ldc           #40                 // String \'
      24: invokevirtual #35                 // Method java/lang/StringBuilder.append:(Ljava/lang/String;)Ljava/lang/StringBuilder;
      27: aload_0
      28: invokevirtual #26                 // Method name:()Ljava/lang/String;
      31: invokevirtual #35                 // Method java/lang/StringBuilder.append:(Ljava/lang/String;)Ljava/lang/StringBuilder;
      34: ldc           #96                 // String \' is NOT a LIST setting
      36: invokevirtual #35                 // Method java/lang/StringBuilder.append:(Ljava/lang/String;)Ljava/lang/StringBuilder;
      39: invokevirtual #41                 // Method java/lang/StringBuilder.toString:()Ljava/lang/String;
      42: invokestatic  #58                 // Method com/google/common/base/Preconditions.checkArgument:(ZLjava/lang/Object;)V
      45: aload_0
      46: invokevirtual #59                 // Method defaultValue:()Ljava/lang/Object;
      49: checkcast     #97                 // class java/util/List
      52: astore_2
      53: aconst_null
      54: aload_2
      55: if_acmpne     62
      58: invokestatic  #98                 // Method java/util/Collections.emptyList:()Ljava/util/List;
      61: astore_2
      62: aload_1
      63: aload_0
      64: invokevirtual #26                 // Method name:()Ljava/lang/String;
      67: aload_2
      68: invokeinterface #99,  3           // InterfaceMethod org/apache/commons/configuration/Configuration.getList:(Ljava/lang/String;Ljava/util/List;)Ljava/util/List;
      73: areturn

  public java.lang.Object get(org.apache.commons.configuration.Configuration);
    Code:
       0: getstatic     #100                // Field org/apache/bookkeeper/common/conf/ConfigKey$1.$SwitchMap$org$apache$bookkeeper$common$conf$Type:[I
       3: aload_0
       4: invokevirtual #46                 // Method type:()Lorg/apache/bookkeeper/common/conf/Type;
       7: invokevirtual #101                // Method org/apache/bookkeeper/common/conf/Type.ordinal:()I
      10: iaload
      11: tableswitch   { // 1 to 7
                     1: 52
                     2: 61
                     3: 70
                     4: 79
                     5: 88
                     6: 97
                     7: 103
               default: 109
          }
      52: aload_0
      53: aload_1
      54: invokevirtual #102                // Method getLong:(Lorg/apache/commons/configuration/Configuration;)J
      57: invokestatic  #103                // Method java/lang/Long.valueOf:(J)Ljava/lang/Long;
      60: areturn
      61: aload_0
      62: aload_1
      63: invokevirtual #104                // Method getInt:(Lorg/apache/commons/configuration/Configuration;)I
      66: invokestatic  #105                // Method java/lang/Integer.valueOf:(I)Ljava/lang/Integer;
      69: areturn
      70: aload_0
      71: aload_1
      72: invokevirtual #106                // Method getShort:(Lorg/apache/commons/configuration/Configuration;)S
      75: invokestatic  #107                // Method java/lang/Short.valueOf:(S)Ljava/lang/Short;
      78: areturn
      79: aload_0
      80: aload_1
      81: invokevirtual #108                // Method getDouble:(Lorg/apache/commons/configuration/Configuration;)D
      84: invokestatic  #109                // Method java/lang/Double.valueOf:(D)Ljava/lang/Double;
      87: areturn
      88: aload_0
      89: aload_1
      90: invokevirtual #110                // Method getBoolean:(Lorg/apache/commons/configuration/Configuration;)Z
      93: invokestatic  #111                // Method java/lang/Boolean.valueOf:(Z)Ljava/lang/Boolean;
      96: areturn
      97: aload_0
      98: aload_1
      99: invokevirtual #112                // Method getList:(Lorg/apache/commons/configuration/Configuration;)Ljava/util/List;
     102: areturn
     103: aload_0
     104: aload_1
     105: invokevirtual #113                // Method getClass:(Lorg/apache/commons/configuration/Configuration;)Ljava/lang/Class;
     108: areturn
     109: aload_0
     110: aload_1
     111: invokevirtual #114                // Method getString:(Lorg/apache/commons/configuration/Configuration;)Ljava/lang/String;
     114: areturn

  private static boolean $default$required();
    Code:
       0: iconst_0
       1: ireturn

  private static org.apache.bookkeeper.common.conf.Type $default$type();
    Code:
       0: getstatic     #115                // Field org/apache/bookkeeper/common/conf/Type.STRING:Lorg/apache/bookkeeper/common/conf/Type;
       3: areturn

  private static java.lang.String $default$description();
    Code:
       0: ldc           #116                // String
       2: areturn

  private static java.lang.String $default$documentation();
    Code:
       0: ldc           #116                // String
       2: areturn

  private static java.lang.Object $default$defaultValue();
    Code:
       0: aconst_null
       1: areturn

  private static java.util.List<java.lang.String> $default$optionValues();
    Code:
       0: invokestatic  #98                 // Method java/util/Collections.emptyList:()Ljava/util/List;
       3: areturn

  private static org.apache.bookkeeper.common.conf.Validator $default$validator();
    Code:
       0: invokestatic  #117                // Method org/apache/bookkeeper/common/conf/validators/NullValidator.of:()Lorg/apache/bookkeeper/common/conf/validators/NullValidator;
       3: areturn

  private static org.apache.bookkeeper.common.conf.ConfigKeyGroup $default$group();
    Code:
       0: getstatic     #118                // Field org/apache/bookkeeper/common/conf/ConfigKeyGroup.DEFAULT:Lorg/apache/bookkeeper/common/conf/ConfigKeyGroup;
       3: areturn

  private static int $default$orderInGroup();
    Code:
       0: ldc           #119                // int -2147483648
       2: ireturn

  private static java.util.List<java.lang.String> $default$dependents();
    Code:
       0: invokestatic  #98                 // Method java/util/Collections.emptyList:()Ljava/util/List;
       3: areturn

  private static boolean $default$deprecated();
    Code:
       0: iconst_0
       1: ireturn

  private static java.lang.String $default$deprecatedByConfigKey();
    Code:
       0: ldc           #116                // String
       2: areturn

  private static java.lang.String $default$deprecatedSince();
    Code:
       0: ldc           #116                // String
       2: areturn

  private static java.lang.String $default$since();
    Code:
       0: ldc           #116                // String
       2: areturn

  org.apache.bookkeeper.common.conf.ConfigKey(boolean, java.lang.String, org.apache.bookkeeper.common.conf.Type, java.lang.String, java.lang.String, java.lang.Object, java.util.List<java.lang.String>, org.apache.bookkeeper.common.conf.Validator, org.apache.bookkeeper.common.conf.ConfigKeyGroup, int, java.util.List<java.lang.String>, boolean, java.lang.String, java.lang.String, java.lang.String);
    Code:
       0: aload_0
       1: invokespecial #120                // Method java/lang/Object."<init>":()V
       4: aload_0
       5: iload_1
       6: putfield      #121                // Field required:Z
       9: aload_0
      10: aload_2
      11: putfield      #23                 // Field name:Ljava/lang/String;
      14: aload_0
      15: aload_3
      16: putfield      #52                 // Field type:Lorg/apache/bookkeeper/common/conf/Type;
      19: aload_0
      20: aload         4
      22: putfield      #122                // Field description:Ljava/lang/String;
      25: aload_0
      26: aload         5
      28: putfield      #123                // Field documentation:Ljava/lang/String;
      31: aload_0
      32: aload         6
      34: putfield      #17                 // Field defaultValue:Ljava/lang/Object;
      37: aload_0
      38: aload         7
      40: putfield      #124                // Field optionValues:Ljava/util/List;
      43: aload_0
      44: aload         8
      46: putfield      #39                 // Field validator:Lorg/apache/bookkeeper/common/conf/Validator;
      49: aload_0
      50: aload         9
      52: putfield      #125                // Field group:Lorg/apache/bookkeeper/common/conf/ConfigKeyGroup;
      55: aload_0
      56: iload         10
      58: putfield      #126                // Field orderInGroup:I
      61: aload_0
      62: aload         11
      64: putfield      #127                // Field dependents:Ljava/util/List;
      67: aload_0
      68: iload         12
      70: putfield      #128                // Field deprecated:Z
      73: aload_0
      74: aload         13
      76: putfield      #129                // Field deprecatedByConfigKey:Ljava/lang/String;
      79: aload_0
      80: aload         14
      82: putfield      #130                // Field deprecatedSince:Ljava/lang/String;
      85: aload_0
      86: aload         15
      88: putfield      #131                // Field since:Ljava/lang/String;
      91: return

  public static org.apache.bookkeeper.common.conf.ConfigKey$ConfigKeyBuilder internalBuilder();
    Code:
       0: new           #132                // class org/apache/bookkeeper/common/conf/ConfigKey$ConfigKeyBuilder
       3: dup
       4: invokespecial #133                // Method org/apache/bookkeeper/common/conf/ConfigKey$ConfigKeyBuilder."<init>":()V
       7: areturn

  public boolean required();
    Code:
       0: aload_0
       1: getfield      #121                // Field required:Z
       4: ireturn

  public java.lang.String name();
    Code:
       0: aload_0
       1: getfield      #23                 // Field name:Ljava/lang/String;
       4: areturn

  public org.apache.bookkeeper.common.conf.Type type();
    Code:
       0: aload_0
       1: getfield      #52                 // Field type:Lorg/apache/bookkeeper/common/conf/Type;
       4: areturn

  public java.lang.String description();
    Code:
       0: aload_0
       1: getfield      #122                // Field description:Ljava/lang/String;
       4: areturn

  public java.lang.String documentation();
    Code:
       0: aload_0
       1: getfield      #123                // Field documentation:Ljava/lang/String;
       4: areturn

  public java.lang.Object defaultValue();
    Code:
       0: aload_0
       1: getfield      #17                 // Field defaultValue:Ljava/lang/Object;
       4: areturn

  public java.util.List<java.lang.String> optionValues();
    Code:
       0: aload_0
       1: getfield      #124                // Field optionValues:Ljava/util/List;
       4: areturn

  public org.apache.bookkeeper.common.conf.Validator validator();
    Code:
       0: aload_0
       1: getfield      #39                 // Field validator:Lorg/apache/bookkeeper/common/conf/Validator;
       4: areturn

  public org.apache.bookkeeper.common.conf.ConfigKeyGroup group();
    Code:
       0: aload_0
       1: getfield      #125                // Field group:Lorg/apache/bookkeeper/common/conf/ConfigKeyGroup;
       4: areturn

  public int orderInGroup();
    Code:
       0: aload_0
       1: getfield      #126                // Field orderInGroup:I
       4: ireturn

  public java.util.List<java.lang.String> dependents();
    Code:
       0: aload_0
       1: getfield      #127                // Field dependents:Ljava/util/List;
       4: areturn

  public boolean deprecated();
    Code:
       0: aload_0
       1: getfield      #128                // Field deprecated:Z
       4: ireturn

  public java.lang.String deprecatedByConfigKey();
    Code:
       0: aload_0
       1: getfield      #129                // Field deprecatedByConfigKey:Ljava/lang/String;
       4: areturn

  public java.lang.String deprecatedSince();
    Code:
       0: aload_0
       1: getfield      #130                // Field deprecatedSince:Ljava/lang/String;
       4: areturn

  public java.lang.String since();
    Code:
       0: aload_0
       1: getfield      #131                // Field since:Ljava/lang/String;
       4: areturn

  public org.apache.bookkeeper.common.conf.ConfigKey required(boolean);
    Code:
       0: aload_0
       1: iload_1
       2: putfield      #121                // Field required:Z
       5: aload_0
       6: areturn

  public org.apache.bookkeeper.common.conf.ConfigKey name(java.lang.String);
    Code:
       0: aload_0
       1: aload_1
       2: putfield      #23                 // Field name:Ljava/lang/String;
       5: aload_0
       6: areturn

  public org.apache.bookkeeper.common.conf.ConfigKey type(org.apache.bookkeeper.common.conf.Type);
    Code:
       0: aload_0
       1: aload_1
       2: putfield      #52                 // Field type:Lorg/apache/bookkeeper/common/conf/Type;
       5: aload_0
       6: areturn

  public org.apache.bookkeeper.common.conf.ConfigKey description(java.lang.String);
    Code:
       0: aload_0
       1: aload_1
       2: putfield      #122                // Field description:Ljava/lang/String;
       5: aload_0
       6: areturn

  public org.apache.bookkeeper.common.conf.ConfigKey documentation(java.lang.String);
    Code:
       0: aload_0
       1: aload_1
       2: putfield      #123                // Field documentation:Ljava/lang/String;
       5: aload_0
       6: areturn

  public org.apache.bookkeeper.common.conf.ConfigKey defaultValue(java.lang.Object);
    Code:
       0: aload_0
       1: aload_1
       2: putfield      #17                 // Field defaultValue:Ljava/lang/Object;
       5: aload_0
       6: areturn

  public org.apache.bookkeeper.common.conf.ConfigKey optionValues(java.util.List<java.lang.String>);
    Code:
       0: aload_0
       1: aload_1
       2: putfield      #124                // Field optionValues:Ljava/util/List;
       5: aload_0
       6: areturn

  public org.apache.bookkeeper.common.conf.ConfigKey validator(org.apache.bookkeeper.common.conf.Validator);
    Code:
       0: aload_0
       1: aload_1
       2: putfield      #39                 // Field validator:Lorg/apache/bookkeeper/common/conf/Validator;
       5: aload_0
       6: areturn

  public org.apache.bookkeeper.common.conf.ConfigKey group(org.apache.bookkeeper.common.conf.ConfigKeyGroup);
    Code:
       0: aload_0
       1: aload_1
       2: putfield      #125                // Field group:Lorg/apache/bookkeeper/common/conf/ConfigKeyGroup;
       5: aload_0
       6: areturn

  public org.apache.bookkeeper.common.conf.ConfigKey orderInGroup(int);
    Code:
       0: aload_0
       1: iload_1
       2: putfield      #126                // Field orderInGroup:I
       5: aload_0
       6: areturn

  public org.apache.bookkeeper.common.conf.ConfigKey dependents(java.util.List<java.lang.String>);
    Code:
       0: aload_0
       1: aload_1
       2: putfield      #127                // Field dependents:Ljava/util/List;
       5: aload_0
       6: areturn

  public org.apache.bookkeeper.common.conf.ConfigKey deprecated(boolean);
    Code:
       0: aload_0
       1: iload_1
       2: putfield      #128                // Field deprecated:Z
       5: aload_0
       6: areturn

  public org.apache.bookkeeper.common.conf.ConfigKey deprecatedByConfigKey(java.lang.String);
    Code:
       0: aload_0
       1: aload_1
       2: putfield      #129                // Field deprecatedByConfigKey:Ljava/lang/String;
       5: aload_0
       6: areturn

  public org.apache.bookkeeper.common.conf.ConfigKey deprecatedSince(java.lang.String);
    Code:
       0: aload_0
       1: aload_1
       2: putfield      #130                // Field deprecatedSince:Ljava/lang/String;
       5: aload_0
       6: areturn

  public org.apache.bookkeeper.common.conf.ConfigKey since(java.lang.String);
    Code:
       0: aload_0
       1: aload_1
       2: putfield      #131                // Field since:Ljava/lang/String;
       5: aload_0
       6: areturn

  public java.lang.String toString();
    Code:
       0: new           #32                 // class java/lang/StringBuilder
       3: dup
       4: invokespecial #33                 // Method java/lang/StringBuilder."<init>":()V
       7: ldc           #134                // String ConfigKey(required=
       9: invokevirtual #35                 // Method java/lang/StringBuilder.append:(Ljava/lang/String;)Ljava/lang/StringBuilder;
      12: aload_0
      13: invokevirtual #43                 // Method required:()Z
      16: invokevirtual #135                // Method java/lang/StringBuilder.append:(Z)Ljava/lang/StringBuilder;
      19: ldc           #136                // String , name=
      21: invokevirtual #35                 // Method java/lang/StringBuilder.append:(Ljava/lang/String;)Ljava/lang/StringBuilder;
      24: aload_0
      25: invokevirtual #26                 // Method name:()Ljava/lang/String;
      28: invokevirtual #35                 // Method java/lang/StringBuilder.append:(Ljava/lang/String;)Ljava/lang/StringBuilder;
      31: ldc           #137                // String , type=
      33: invokevirtual #35                 // Method java/lang/StringBuilder.append:(Ljava/lang/String;)Ljava/lang/StringBuilder;
      36: aload_0
      37: invokevirtual #46                 // Method type:()Lorg/apache/bookkeeper/common/conf/Type;
      40: invokevirtual #37                 // Method java/lang/StringBuilder.append:(Ljava/lang/Object;)Ljava/lang/StringBuilder;
      43: ldc           #138                // String , description=
      45: invokevirtual #35                 // Method java/lang/StringBuilder.append:(Ljava/lang/String;)Ljava/lang/StringBuilder;
      48: aload_0
      49: invokevirtual #139                // Method description:()Ljava/lang/String;
      52: invokevirtual #35                 // Method java/lang/StringBuilder.append:(Ljava/lang/String;)Ljava/lang/StringBuilder;
      55: ldc           #140                // String , documentation=
      57: invokevirtual #35                 // Method java/lang/StringBuilder.append:(Ljava/lang/String;)Ljava/lang/StringBuilder;
      60: aload_0
      61: invokevirtual #141                // Method documentation:()Ljava/lang/String;
      64: invokevirtual #35                 // Method java/lang/StringBuilder.append:(Ljava/lang/String;)Ljava/lang/StringBuilder;
      67: ldc           #142                // String , defaultValue=
      69: invokevirtual #35                 // Method java/lang/StringBuilder.append:(Ljava/lang/String;)Ljava/lang/StringBuilder;
      72: aload_0
      73: invokevirtual #59                 // Method defaultValue:()Ljava/lang/Object;
      76: invokevirtual #37                 // Method java/lang/StringBuilder.append:(Ljava/lang/Object;)Ljava/lang/StringBuilder;
      79: ldc           #143                // String , optionValues=
      81: invokevirtual #35                 // Method java/lang/StringBuilder.append:(Ljava/lang/String;)Ljava/lang/StringBuilder;
      84: aload_0
      85: invokevirtual #144                // Method optionValues:()Ljava/util/List;
      88: invokevirtual #37                 // Method java/lang/StringBuilder.append:(Ljava/lang/Object;)Ljava/lang/StringBuilder;
      91: ldc           #145                // String , validator=
      93: invokevirtual #35                 // Method java/lang/StringBuilder.append:(Ljava/lang/String;)Ljava/lang/StringBuilder;
      96: aload_0
      97: invokevirtual #28                 // Method validator:()Lorg/apache/bookkeeper/common/conf/Validator;
     100: invokevirtual #37                 // Method java/lang/StringBuilder.append:(Ljava/lang/Object;)Ljava/lang/StringBuilder;
     103: ldc           #146                // String , group=
     105: invokevirtual #35                 // Method java/lang/StringBuilder.append:(Ljava/lang/String;)Ljava/lang/StringBuilder;
     108: aload_0
     109: invokevirtual #147                // Method group:()Lorg/apache/bookkeeper/common/conf/ConfigKeyGroup;
     112: invokevirtual #37                 // Method java/lang/StringBuilder.append:(Ljava/lang/Object;)Ljava/lang/StringBuilder;
     115: ldc           #148                // String , orderInGroup=
     117: invokevirtual #35                 // Method java/lang/StringBuilder.append:(Ljava/lang/String;)Ljava/lang/StringBuilder;
     120: aload_0
     121: invokevirtual #149                // Method orderInGroup:()I
     124: invokevirtual #150                // Method java/lang/StringBuilder.append:(I)Ljava/lang/StringBuilder;
     127: ldc           #151                // String , dependents=
     129: invokevirtual #35                 // Method java/lang/StringBuilder.append:(Ljava/lang/String;)Ljava/lang/StringBuilder;
     132: aload_0
     133: invokevirtual #152                // Method dependents:()Ljava/util/List;
     136: invokevirtual #37                 // Method java/lang/StringBuilder.append:(Ljava/lang/Object;)Ljava/lang/StringBuilder;
     139: ldc           #153                // String , deprecated=
     141: invokevirtual #35                 // Method java/lang/StringBuilder.append:(Ljava/lang/String;)Ljava/lang/StringBuilder;
     144: aload_0
     145: invokevirtual #154                // Method deprecated:()Z
     148: invokevirtual #135                // Method java/lang/StringBuilder.append:(Z)Ljava/lang/StringBuilder;
     151: ldc           #155                // String , deprecatedByConfigKey=
     153: invokevirtual #35                 // Method java/lang/StringBuilder.append:(Ljava/lang/String;)Ljava/lang/StringBuilder;
     156: aload_0
     157: invokevirtual #156                // Method deprecatedByConfigKey:()Ljava/lang/String;
     160: invokevirtual #35                 // Method java/lang/StringBuilder.append:(Ljava/lang/String;)Ljava/lang/StringBuilder;
     163: ldc           #157                // String , deprecatedSince=
     165: invokevirtual #35                 // Method java/lang/StringBuilder.append:(Ljava/lang/String;)Ljava/lang/StringBuilder;
     168: aload_0
     169: invokevirtual #158                // Method deprecatedSince:()Ljava/lang/String;
     172: invokevirtual #35                 // Method java/lang/StringBuilder.append:(Ljava/lang/String;)Ljava/lang/StringBuilder;
     175: ldc           #159                // String , since=
     177: invokevirtual #35                 // Method java/lang/StringBuilder.append:(Ljava/lang/String;)Ljava/lang/StringBuilder;
     180: aload_0
     181: invokevirtual #160                // Method since:()Ljava/lang/String;
     184: invokevirtual #35                 // Method java/lang/StringBuilder.append:(Ljava/lang/String;)Ljava/lang/StringBuilder;
     187: ldc           #161                // String )
     189: invokevirtual #35                 // Method java/lang/StringBuilder.append:(Ljava/lang/String;)Ljava/lang/StringBuilder;
     192: invokevirtual #41                 // Method java/lang/StringBuilder.toString:()Ljava/lang/String;
     195: areturn

  private static int lambda$static$0(org.apache.bookkeeper.common.conf.ConfigKey, org.apache.bookkeeper.common.conf.ConfigKey);
    Code:
       0: aload_0
       1: getfield      #126                // Field orderInGroup:I
       4: aload_1
       5: getfield      #126                // Field orderInGroup:I
       8: invokestatic  #162                // Method java/lang/Integer.compare:(II)I
      11: istore_2
      12: iload_2
      13: ifne          28
      16: aload_0
      17: invokevirtual #26                 // Method name:()Ljava/lang/String;
      20: aload_1
      21: invokevirtual #26                 // Method name:()Ljava/lang/String;
      24: invokevirtual #163                // Method java/lang/String.compareTo:(Ljava/lang/String;)I
      27: ireturn
      28: iload_2
      29: ireturn

  static boolean access$000();
    Code:
       0: invokestatic  #14                 // Method $default$required:()Z
       3: ireturn

  static org.apache.bookkeeper.common.conf.Type access$100();
    Code:
       0: invokestatic  #13                 // Method $default$type:()Lorg/apache/bookkeeper/common/conf/Type;
       3: areturn

  static java.lang.String access$200();
    Code:
       0: invokestatic  #12                 // Method $default$description:()Ljava/lang/String;
       3: areturn

  static java.lang.String access$300();
    Code:
       0: invokestatic  #11                 // Method $default$documentation:()Ljava/lang/String;
       3: areturn

  static java.lang.Object access$400();
    Code:
       0: invokestatic  #10                 // Method $default$defaultValue:()Ljava/lang/Object;
       3: areturn

  static java.util.List access$500();
    Code:
       0: invokestatic  #9                  // Method $default$optionValues:()Ljava/util/List;
       3: areturn

  static org.apache.bookkeeper.common.conf.Validator access$600();
    Code:
       0: invokestatic  #8                  // Method $default$validator:()Lorg/apache/bookkeeper/common/conf/Validator;
       3: areturn

  static org.apache.bookkeeper.common.conf.ConfigKeyGroup access$700();
    Code:
       0: invokestatic  #7                  // Method $default$group:()Lorg/apache/bookkeeper/common/conf/ConfigKeyGroup;
       3: areturn

  static int access$800();
    Code:
       0: invokestatic  #6                  // Method $default$orderInGroup:()I
       3: ireturn

  static java.util.List access$900();
    Code:
       0: invokestatic  #5                  // Method $default$dependents:()Ljava/util/List;
       3: areturn

  static boolean access$1000();
    Code:
       0: invokestatic  #4                  // Method $default$deprecated:()Z
       3: ireturn

  static java.lang.String access$1100();
    Code:
       0: invokestatic  #3                  // Method $default$deprecatedByConfigKey:()Ljava/lang/String;
       3: areturn

  static java.lang.String access$1200();
    Code:
       0: invokestatic  #2                  // Method $default$deprecatedSince:()Ljava/lang/String;
       3: areturn

  static java.lang.String access$1300();
    Code:
       0: invokestatic  #1                  // Method $default$since:()Ljava/lang/String;
       3: areturn

  static {};
    Code:
       0: ldc           #22                 // class org/apache/bookkeeper/common/conf/ConfigKey
       2: invokestatic  #164                // Method org/slf4j/LoggerFactory.getLogger:(Ljava/lang/Class;)Lorg/slf4j/Logger;
       5: putstatic     #165                // Field log:Lorg/slf4j/Logger;
       8: invokedynamic #166,  0            // InvokeDynamic #0:compare:()Ljava/util/Comparator;
      13: putstatic     #167                // Field ORDERING:Ljava/util/Comparator;
      16: return
}
