Compiled from "NumberEvaluator.java"
public abstract class org.apache.solr.client.solrj.io.eval.NumberEvaluator extends org.apache.solr.client.solrj.io.eval.ComplexEvaluator {
  protected static final long serialVersionUID;

  public org.apache.solr.client.solrj.io.eval.NumberEvaluator(org.apache.solr.client.solrj.io.stream.expr.StreamExpression, org.apache.solr.client.solrj.io.stream.expr.StreamFactory) throws java.io.IOException;
    Code:
       0: aload_0
       1: aload_1
       2: aload_2
       3: invokespecial #1                  // Method org/apache/solr/client/solrj/io/eval/ComplexEvaluator."<init>":(Lorg/apache/solr/client/solrj/io/stream/expr/StreamExpression;Lorg/apache/solr/client/solrj/io/stream/expr/StreamFactory;)V
       6: return

  public abstract java.lang.Number evaluate(org.apache.solr.client.solrj.io.Tuple) throws java.io.IOException;

  public java.util.List<java.math.BigDecimal> evaluateAll(org.apache.solr.client.solrj.io.Tuple) throws java.io.IOException;
    Code:
       0: new           #2                  // class java/util/ArrayList
       3: dup
       4: invokespecial #3                  // Method java/util/ArrayList."<init>":()V
       7: astore_2
       8: aload_0
       9: getfield      #4                  // Field subEvaluators:Ljava/util/List;
      12: invokeinterface #5,  1            // InterfaceMethod java/util/List.iterator:()Ljava/util/Iterator;
      17: astore_3
      18: aload_3
      19: invokeinterface #6,  1            // InterfaceMethod java/util/Iterator.hasNext:()Z
      24: ifeq          155
      27: aload_3
      28: invokeinterface #7,  1            // InterfaceMethod java/util/Iterator.next:()Ljava/lang/Object;
      33: checkcast     #8                  // class org/apache/solr/client/solrj/io/eval/StreamEvaluator
      36: astore        4
      38: aload         4
      40: aload_1
      41: invokeinterface #9,  2            // InterfaceMethod org/apache/solr/client/solrj/io/eval/StreamEvaluator.evaluate:(Lorg/apache/solr/client/solrj/io/Tuple;)Ljava/lang/Object;
      46: astore        5
      48: aconst_null
      49: aload         5
      51: if_acmpne     65
      54: aload_2
      55: aconst_null
      56: invokeinterface #10,  2           // InterfaceMethod java/util/List.add:(Ljava/lang/Object;)Z
      61: pop
      62: goto          152
      65: aload         5
      67: instanceof    #11                 // class java/lang/Number
      70: ifeq          95
      73: aload_2
      74: new           #12                 // class java/math/BigDecimal
      77: dup
      78: aload         5
      80: invokevirtual #13                 // Method java/lang/Object.toString:()Ljava/lang/String;
      83: invokespecial #14                 // Method java/math/BigDecimal."<init>":(Ljava/lang/String;)V
      86: invokeinterface #10,  2           // InterfaceMethod java/util/List.add:(Ljava/lang/Object;)Z
      91: pop
      92: goto          152
      95: getstatic     #15                 // Field java/util/Locale.ROOT:Ljava/util/Locale;
      98: ldc           #16                 // String Failed to evaluate to a numeric value - evaluator \'%s\' resulted in type \'%s\' and value \'%s\'
     100: iconst_3
     101: anewarray     #17                 // class java/lang/Object
     104: dup
     105: iconst_0
     106: aload         4
     108: aload_0
     109: getfield      #18                 // Field constructingFactory:Lorg/apache/solr/client/solrj/io/stream/expr/StreamFactory;
     112: invokeinterface #19,  2           // InterfaceMethod org/apache/solr/client/solrj/io/eval/StreamEvaluator.toExpression:(Lorg/apache/solr/client/solrj/io/stream/expr/StreamFactory;)Lorg/apache/solr/client/solrj/io/stream/expr/StreamExpressionParameter;
     117: aastore
     118: dup
     119: iconst_1
     120: aload         5
     122: invokevirtual #20                 // Method java/lang/Object.getClass:()Ljava/lang/Class;
     125: invokevirtual #21                 // Method java/lang/Class.getName:()Ljava/lang/String;
     128: aastore
     129: dup
     130: iconst_2
     131: aload         5
     133: invokevirtual #13                 // Method java/lang/Object.toString:()Ljava/lang/String;
     136: aastore
     137: invokestatic  #22                 // Method java/lang/String.format:(Ljava/util/Locale;Ljava/lang/String;[Ljava/lang/Object;)Ljava/lang/String;
     140: astore        6
     142: new           #23                 // class java/io/IOException
     145: dup
     146: aload         6
     148: invokespecial #24                 // Method java/io/IOException."<init>":(Ljava/lang/String;)V
     151: athrow
     152: goto          18
     155: aload_2
     156: areturn

  public java.lang.Number normalizeType(java.math.BigDecimal);
    Code:
       0: aconst_null
       1: aload_1
       2: if_acmpne     7
       5: aconst_null
       6: areturn
       7: aload_1
       8: invokevirtual #25                 // Method java/math/BigDecimal.signum:()I
      11: ifeq          31
      14: aload_1
      15: invokevirtual #26                 // Method java/math/BigDecimal.scale:()I
      18: ifle          31
      21: aload_1
      22: invokevirtual #27                 // Method java/math/BigDecimal.stripTrailingZeros:()Ljava/math/BigDecimal;
      25: invokevirtual #26                 // Method java/math/BigDecimal.scale:()I
      28: ifgt          39
      31: aload_1
      32: invokevirtual #28                 // Method java/math/BigDecimal.longValue:()J
      35: invokestatic  #29                 // Method java/lang/Long.valueOf:(J)Ljava/lang/Long;
      38: areturn
      39: aload_1
      40: invokevirtual #30                 // Method java/math/BigDecimal.doubleValue:()D
      43: invokestatic  #31                 // Method java/lang/Double.valueOf:(D)Ljava/lang/Double;
      46: areturn

  public java.lang.Object evaluate(org.apache.solr.client.solrj.io.Tuple) throws java.io.IOException;
    Code:
       0: aload_0
       1: aload_1
       2: invokevirtual #32                 // Method evaluate:(Lorg/apache/solr/client/solrj/io/Tuple;)Ljava/lang/Number;
       5: areturn
}
