Compiled from "JmxAuditLoggerResourceDefinition.java"
class org.jboss.as.jmx.JmxAuditLoggerResourceDefinition$AuditLoggerAddHandler implements org.jboss.as.controller.OperationStepHandler {
  private final org.jboss.as.controller.audit.ManagedAuditLogger auditLoggerProvider;

  org.jboss.as.jmx.JmxAuditLoggerResourceDefinition$AuditLoggerAddHandler(org.jboss.as.controller.audit.ManagedAuditLogger);
    Code:
       0: aload_0
       1: invokespecial #2                  // Method java/lang/Object."<init>":()V
       4: aload_0
       5: aload_1
       6: putfield      #1                  // Field auditLoggerProvider:Lorg/jboss/as/controller/audit/ManagedAuditLogger;
       9: return

  public void execute(org.jboss.as.controller.OperationContext, org.jboss.dmr.ModelNode) throws org.jboss.as.controller.OperationFailedException;
    Code:
       0: aload_1
       1: getstatic     #3                  // Field org/jboss/as/controller/PathAddress.EMPTY_ADDRESS:Lorg/jboss/as/controller/PathAddress;
       4: invokeinterface #4,  2            // InterfaceMethod org/jboss/as/controller/OperationContext.createResource:(Lorg/jboss/as/controller/PathAddress;)Lorg/jboss/as/controller/registry/Resource;
       9: astore_3
      10: aload_3
      11: invokeinterface #5,  1            // InterfaceMethod org/jboss/as/controller/registry/Resource.getModel:()Lorg/jboss/dmr/ModelNode;
      16: astore        4
      18: getstatic     #6                  // Field org/jboss/as/jmx/JmxAuditLoggerResourceDefinition.AUDIT_LOG_ATTRIBUTE_DEFINITIONS:Ljava/util/List;
      21: invokeinterface #7,  1            // InterfaceMethod java/util/List.iterator:()Ljava/util/Iterator;
      26: astore        5
      28: aload         5
      30: invokeinterface #8,  1            // InterfaceMethod java/util/Iterator.hasNext:()Z
      35: ifeq          61
      38: aload         5
      40: invokeinterface #9,  1            // InterfaceMethod java/util/Iterator.next:()Ljava/lang/Object;
      45: checkcast     #10                 // class org/jboss/as/controller/AttributeDefinition
      48: astore        6
      50: aload         6
      52: aload_2
      53: aload         4
      55: invokevirtual #11                 // Method org/jboss/as/controller/AttributeDefinition.validateAndSet:(Lorg/jboss/dmr/ModelNode;Lorg/jboss/dmr/ModelNode;)V
      58: goto          28
      61: aload_1
      62: new           #12                 // class org/jboss/as/jmx/JmxAuditLoggerResourceDefinition$AuditLoggerAddHandler$1
      65: dup
      66: aload_0
      67: aload         4
      69: invokespecial #13                 // Method org/jboss/as/jmx/JmxAuditLoggerResourceDefinition$AuditLoggerAddHandler$1."<init>":(Lorg/jboss/as/jmx/JmxAuditLoggerResourceDefinition$AuditLoggerAddHandler;Lorg/jboss/dmr/ModelNode;)V
      72: getstatic     #14                 // Field org/jboss/as/controller/OperationContext$Stage.RUNTIME:Lorg/jboss/as/controller/OperationContext$Stage;
      75: invokeinterface #15,  3           // InterfaceMethod org/jboss/as/controller/OperationContext.addStep:(Lorg/jboss/as/controller/OperationStepHandler;Lorg/jboss/as/controller/OperationContext$Stage;)V
      80: aload_1
      81: getstatic     #16                 // Field org/jboss/as/controller/OperationContext$RollbackHandler.NOOP_ROLLBACK_HANDLER:Lorg/jboss/as/controller/OperationContext$RollbackHandler;
      84: invokeinterface #17,  2           // InterfaceMethod org/jboss/as/controller/OperationContext.completeStep:(Lorg/jboss/as/controller/OperationContext$RollbackHandler;)V
      89: return

  static org.jboss.as.controller.audit.ManagedAuditLogger access$000(org.jboss.as.jmx.JmxAuditLoggerResourceDefinition$AuditLoggerAddHandler);
    Code:
       0: aload_0
       1: getfield      #1                  // Field auditLoggerProvider:Lorg/jboss/as/controller/audit/ManagedAuditLogger;
       4: areturn
}
