Compiled from "JMXExtension.java"
public class org.jboss.as.jmx.JMXExtension implements org.jboss.as.controller.Extension {
  public static final java.lang.String SUBSYSTEM_NAME;

  private static final java.lang.String RESOURCE_NAME;

  static final org.jboss.as.controller.access.constraint.SensitivityClassification JMX_SENSITIVITY;

  static final org.jboss.as.controller.access.management.SensitiveTargetAccessConstraintDefinition JMX_SENSITIVITY_DEF;

  static final org.jboss.as.jmx.JMXExtension$JMXSubsystemParser_1_3 parserCurrent;

  static final org.jboss.as.jmx.JMXExtension$JMXSubsystemParser_1_2 parser12;

  static final org.jboss.as.jmx.JMXExtension$JMXSubsystemParser_1_1 parser11;

  static final org.jboss.as.jmx.JMXExtension$JMXSubsystemParser_1_0 parser10;

  static final org.jboss.as.jmx.JMXExtension$JMXSubsystemWriter writer;

  private static final int MANAGEMENT_API_MAJOR_VERSION;

  private static final int MANAGEMENT_API_MINOR_VERSION;

  private static final int MANAGEMENT_API_MICRO_VERSION;

  private static final org.jboss.as.controller.ModelVersion CURRENT_VERSION;

  public org.jboss.as.jmx.JMXExtension();
    Code:
       0: aload_0
       1: invokespecial #4                  // Method java/lang/Object."<init>":()V
       4: return

  static org.jboss.as.controller.descriptions.ResourceDescriptionResolver getResourceDescriptionResolver(java.lang.String);
    Code:
       0: new           #5                  // class org/jboss/as/controller/descriptions/StandardResourceDescriptionResolver
       3: dup
       4: aload_0
       5: getstatic     #6                  // Field RESOURCE_NAME:Ljava/lang/String;
       8: ldc           #7                  // class org/jboss/as/jmx/JMXExtension
      10: invokevirtual #8                  // Method java/lang/Class.getClassLoader:()Ljava/lang/ClassLoader;
      13: iconst_1
      14: iconst_0
      15: invokespecial #9                  // Method org/jboss/as/controller/descriptions/StandardResourceDescriptionResolver."<init>":(Ljava/lang/String;Ljava/lang/String;Ljava/lang/ClassLoader;ZZ)V
      18: areturn

  public void initialize(org.jboss.as.controller.ExtensionContext);
    Code:
       0: aload_1
       1: ldc           #10                 // String jmx
       3: getstatic     #11                 // Field CURRENT_VERSION:Lorg/jboss/as/controller/ModelVersion;
       6: invokeinterface #12,  3           // InterfaceMethod org/jboss/as/controller/ExtensionContext.registerSubsystem:(Ljava/lang/String;Lorg/jboss/as/controller/ModelVersion;)Lorg/jboss/as/controller/SubsystemRegistration;
      11: astore_2
      12: aload_2
      13: invokeinterface #13,  1           // InterfaceMethod org/jboss/as/controller/SubsystemRegistration.setHostCapable:()V
      18: aload_1
      19: checkcast     #14                 // class org/jboss/as/controller/extension/ExtensionContextSupplement
      22: iconst_0
      23: iconst_1
      24: invokeinterface #15,  3           // InterfaceMethod org/jboss/as/controller/extension/ExtensionContextSupplement.getAuditLogger:(ZZ)Lorg/jboss/as/controller/audit/AuditLogger;
      29: checkcast     #16                 // class org/jboss/as/controller/audit/ManagedAuditLogger
      32: astore_3
      33: aload_1
      34: checkcast     #14                 // class org/jboss/as/controller/extension/ExtensionContextSupplement
      37: invokeinterface #17,  1           // InterfaceMethod org/jboss/as/controller/extension/ExtensionContextSupplement.getAuthorizer:()Lorg/jboss/as/controller/access/management/JmxAuthorizer;
      42: astore        4
      44: aload_1
      45: checkcast     #14                 // class org/jboss/as/controller/extension/ExtensionContextSupplement
      48: invokeinterface #18,  1           // InterfaceMethod org/jboss/as/controller/extension/ExtensionContextSupplement.getHostControllerInfoAccessor:()Lorg/jboss/as/controller/extension/RuntimeHostControllerInfoAccessor;
      53: astore        5
      55: aload_2
      56: aload_3
      57: aload         4
      59: aload         5
      61: invokestatic  #19                 // Method org/jboss/as/jmx/JMXSubsystemRootResource.create:(Lorg/jboss/as/controller/audit/ManagedAuditLogger;Lorg/jboss/as/controller/access/management/JmxAuthorizer;Lorg/jboss/as/controller/extension/RuntimeHostControllerInfoAccessor;)Lorg/jboss/as/jmx/JMXSubsystemRootResource;
      64: invokeinterface #20,  2           // InterfaceMethod org/jboss/as/controller/SubsystemRegistration.registerSubsystemModel:(Lorg/jboss/as/controller/ResourceDefinition;)Lorg/jboss/as/controller/registry/ManagementResourceRegistration;
      69: pop
      70: aload_2
      71: getstatic     #21                 // Field writer:Lorg/jboss/as/jmx/JMXExtension$JMXSubsystemWriter;
      74: invokeinterface #22,  2           // InterfaceMethod org/jboss/as/controller/SubsystemRegistration.registerXMLElementWriter:(Lorg/jboss/staxmapper/XMLElementWriter;)V
      79: return

  public void initializeParsers(org.jboss.as.controller.parsing.ExtensionParsingContext);
    Code:
       0: aload_1
       1: ldc           #10                 // String jmx
       3: getstatic     #23                 // Field org/jboss/as/jmx/Namespace.JMX_1_0:Lorg/jboss/as/jmx/Namespace;
       6: invokevirtual #24                 // Method org/jboss/as/jmx/Namespace.getUriString:()Ljava/lang/String;
       9: getstatic     #25                 // Field parser10:Lorg/jboss/as/jmx/JMXExtension$JMXSubsystemParser_1_0;
      12: invokeinterface #26,  4           // InterfaceMethod org/jboss/as/controller/parsing/ExtensionParsingContext.setSubsystemXmlMapping:(Ljava/lang/String;Ljava/lang/String;Lorg/jboss/staxmapper/XMLElementReader;)V
      17: aload_1
      18: ldc           #10                 // String jmx
      20: getstatic     #27                 // Field org/jboss/as/jmx/Namespace.JMX_1_1:Lorg/jboss/as/jmx/Namespace;
      23: invokevirtual #24                 // Method org/jboss/as/jmx/Namespace.getUriString:()Ljava/lang/String;
      26: getstatic     #28                 // Field parser11:Lorg/jboss/as/jmx/JMXExtension$JMXSubsystemParser_1_1;
      29: invokeinterface #26,  4           // InterfaceMethod org/jboss/as/controller/parsing/ExtensionParsingContext.setSubsystemXmlMapping:(Ljava/lang/String;Ljava/lang/String;Lorg/jboss/staxmapper/XMLElementReader;)V
      34: aload_1
      35: ldc           #10                 // String jmx
      37: getstatic     #29                 // Field org/jboss/as/jmx/Namespace.JMX_1_2:Lorg/jboss/as/jmx/Namespace;
      40: invokevirtual #24                 // Method org/jboss/as/jmx/Namespace.getUriString:()Ljava/lang/String;
      43: getstatic     #30                 // Field parser12:Lorg/jboss/as/jmx/JMXExtension$JMXSubsystemParser_1_2;
      46: invokeinterface #26,  4           // InterfaceMethod org/jboss/as/controller/parsing/ExtensionParsingContext.setSubsystemXmlMapping:(Ljava/lang/String;Ljava/lang/String;Lorg/jboss/staxmapper/XMLElementReader;)V
      51: aload_1
      52: ldc           #10                 // String jmx
      54: getstatic     #31                 // Field org/jboss/as/jmx/Namespace.JMX_1_3:Lorg/jboss/as/jmx/Namespace;
      57: invokevirtual #24                 // Method org/jboss/as/jmx/Namespace.getUriString:()Ljava/lang/String;
      60: getstatic     #32                 // Field parserCurrent:Lorg/jboss/as/jmx/JMXExtension$JMXSubsystemParser_1_3;
      63: invokeinterface #26,  4           // InterfaceMethod org/jboss/as/controller/parsing/ExtensionParsingContext.setSubsystemXmlMapping:(Ljava/lang/String;Ljava/lang/String;Lorg/jboss/staxmapper/XMLElementReader;)V
      68: return

  private static org.jboss.dmr.ModelNode createAddOperation();
    Code:
       0: ldc           #33                 // String add
       2: iconst_0
       3: anewarray     #34                 // class java/lang/String
       6: invokestatic  #2                  // Method createOperation:(Ljava/lang/String;[Ljava/lang/String;)Lorg/jboss/dmr/ModelNode;
       9: areturn

  private static org.jboss.dmr.ModelNode createOperation(java.lang.String, java.lang.String...);
    Code:
       0: new           #35                 // class org/jboss/dmr/ModelNode
       3: dup
       4: invokespecial #36                 // Method org/jboss/dmr/ModelNode."<init>":()V
       7: astore_2
       8: aload_2
       9: ldc           #37                 // String operation
      11: invokevirtual #38                 // Method org/jboss/dmr/ModelNode.get:(Ljava/lang/String;)Lorg/jboss/dmr/ModelNode;
      14: aload_0
      15: invokevirtual #39                 // Method org/jboss/dmr/ModelNode.set:(Ljava/lang/String;)Lorg/jboss/dmr/ModelNode;
      18: pop
      19: aload_2
      20: ldc           #40                 // String address
      22: invokevirtual #38                 // Method org/jboss/dmr/ModelNode.get:(Ljava/lang/String;)Lorg/jboss/dmr/ModelNode;
      25: ldc           #41                 // String subsystem
      27: ldc           #10                 // String jmx
      29: invokevirtual #42                 // Method org/jboss/dmr/ModelNode.add:(Ljava/lang/String;Ljava/lang/String;)Lorg/jboss/dmr/ModelNode;
      32: pop
      33: iconst_0
      34: istore_3
      35: iload_3
      36: aload_1
      37: arraylength
      38: if_icmpge     66
      41: aload_2
      42: ldc           #40                 // String address
      44: invokevirtual #38                 // Method org/jboss/dmr/ModelNode.get:(Ljava/lang/String;)Lorg/jboss/dmr/ModelNode;
      47: aload_1
      48: iload_3
      49: aaload
      50: aload_1
      51: iinc          3, 1
      54: iload_3
      55: aaload
      56: invokevirtual #42                 // Method org/jboss/dmr/ModelNode.add:(Ljava/lang/String;Ljava/lang/String;)Lorg/jboss/dmr/ModelNode;
      59: pop
      60: iinc          3, 1
      63: goto          35
      66: aload_2
      67: areturn

  static org.jboss.dmr.ModelNode access$500();
    Code:
       0: invokestatic  #3                  // Method createAddOperation:()Lorg/jboss/dmr/ModelNode;
       3: areturn

  static org.jboss.dmr.ModelNode access$600(java.lang.String, java.lang.String[]);
    Code:
       0: aload_0
       1: aload_1
       2: invokestatic  #2                  // Method createOperation:(Ljava/lang/String;[Ljava/lang/String;)Lorg/jboss/dmr/ModelNode;
       5: areturn

  static {};
    Code:
       0: new           #43                 // class java/lang/StringBuilder
       3: dup
       4: invokespecial #44                 // Method java/lang/StringBuilder."<init>":()V
       7: ldc           #7                  // class org/jboss/as/jmx/JMXExtension
       9: invokevirtual #45                 // Method java/lang/Class.getPackage:()Ljava/lang/Package;
      12: invokevirtual #46                 // Method java/lang/Package.getName:()Ljava/lang/String;
      15: invokevirtual #47                 // Method java/lang/StringBuilder.append:(Ljava/lang/String;)Ljava/lang/StringBuilder;
      18: ldc           #48                 // String .LocalDescriptions
      20: invokevirtual #47                 // Method java/lang/StringBuilder.append:(Ljava/lang/String;)Ljava/lang/StringBuilder;
      23: invokevirtual #49                 // Method java/lang/StringBuilder.toString:()Ljava/lang/String;
      26: putstatic     #6                  // Field RESOURCE_NAME:Ljava/lang/String;
      29: new           #50                 // class org/jboss/as/controller/access/constraint/SensitivityClassification
      32: dup
      33: ldc           #10                 // String jmx
      35: ldc           #10                 // String jmx
      37: iconst_0
      38: iconst_0
      39: iconst_1
      40: invokespecial #51                 // Method org/jboss/as/controller/access/constraint/SensitivityClassification."<init>":(Ljava/lang/String;Ljava/lang/String;ZZZ)V
      43: putstatic     #52                 // Field JMX_SENSITIVITY:Lorg/jboss/as/controller/access/constraint/SensitivityClassification;
      46: new           #53                 // class org/jboss/as/controller/access/management/SensitiveTargetAccessConstraintDefinition
      49: dup
      50: getstatic     #52                 // Field JMX_SENSITIVITY:Lorg/jboss/as/controller/access/constraint/SensitivityClassification;
      53: invokespecial #54                 // Method org/jboss/as/controller/access/management/SensitiveTargetAccessConstraintDefinition."<init>":(Lorg/jboss/as/controller/access/constraint/SensitivityClassification;)V
      56: putstatic     #55                 // Field JMX_SENSITIVITY_DEF:Lorg/jboss/as/controller/access/management/SensitiveTargetAccessConstraintDefinition;
      59: new           #56                 // class org/jboss/as/jmx/JMXExtension$JMXSubsystemParser_1_3
      62: dup
      63: aconst_null
      64: invokespecial #57                 // Method org/jboss/as/jmx/JMXExtension$JMXSubsystemParser_1_3."<init>":(Lorg/jboss/as/jmx/JMXExtension$1;)V
      67: putstatic     #32                 // Field parserCurrent:Lorg/jboss/as/jmx/JMXExtension$JMXSubsystemParser_1_3;
      70: new           #58                 // class org/jboss/as/jmx/JMXExtension$JMXSubsystemParser_1_2
      73: dup
      74: aconst_null
      75: invokespecial #59                 // Method org/jboss/as/jmx/JMXExtension$JMXSubsystemParser_1_2."<init>":(Lorg/jboss/as/jmx/JMXExtension$1;)V
      78: putstatic     #30                 // Field parser12:Lorg/jboss/as/jmx/JMXExtension$JMXSubsystemParser_1_2;
      81: new           #60                 // class org/jboss/as/jmx/JMXExtension$JMXSubsystemParser_1_1
      84: dup
      85: aconst_null
      86: invokespecial #61                 // Method org/jboss/as/jmx/JMXExtension$JMXSubsystemParser_1_1."<init>":(Lorg/jboss/as/jmx/JMXExtension$1;)V
      89: putstatic     #28                 // Field parser11:Lorg/jboss/as/jmx/JMXExtension$JMXSubsystemParser_1_1;
      92: new           #62                 // class org/jboss/as/jmx/JMXExtension$JMXSubsystemParser_1_0
      95: dup
      96: aconst_null
      97: invokespecial #63                 // Method org/jboss/as/jmx/JMXExtension$JMXSubsystemParser_1_0."<init>":(Lorg/jboss/as/jmx/JMXExtension$1;)V
     100: putstatic     #25                 // Field parser10:Lorg/jboss/as/jmx/JMXExtension$JMXSubsystemParser_1_0;
     103: new           #64                 // class org/jboss/as/jmx/JMXExtension$JMXSubsystemWriter
     106: dup
     107: aconst_null
     108: invokespecial #65                 // Method org/jboss/as/jmx/JMXExtension$JMXSubsystemWriter."<init>":(Lorg/jboss/as/jmx/JMXExtension$1;)V
     111: putstatic     #21                 // Field writer:Lorg/jboss/as/jmx/JMXExtension$JMXSubsystemWriter;
     114: iconst_1
     115: iconst_2
     116: iconst_0
     117: invokestatic  #66                 // Method org/jboss/as/controller/ModelVersion.create:(III)Lorg/jboss/as/controller/ModelVersion;
     120: putstatic     #11                 // Field CURRENT_VERSION:Lorg/jboss/as/controller/ModelVersion;
     123: return
}
