Compiled from "SecurityActions.java"
final class org.jboss.as.jmx.SecurityActions$CallerActions$1 implements org.jboss.as.jmx.SecurityActions$CallerActions {
  org.jboss.as.jmx.SecurityActions$CallerActions$1();
    Code:
       0: aload_0
       1: invokespecial #1                  // Method java/lang/Object."<init>":()V
       4: return

  public org.jboss.as.controller.access.Caller createCaller(java.security.AccessControlContext);
    Code:
       0: aload_1
       1: invokestatic  #2                  // Method javax/security/auth/Subject.getSubject:(Ljava/security/AccessControlContext;)Ljavax/security/auth/Subject;
       4: astore_2
       5: aload_2
       6: invokestatic  #3                  // Method org/jboss/as/controller/access/Caller.createCaller:(Ljavax/security/auth/Subject;)Lorg/jboss/as/controller/access/Caller;
       9: areturn
}
