Compiled from "Escape.java"
public class org.apache.velocity.anakia.Escape {
  public static final java.lang.String LINE_SEPARATOR;

  public org.apache.velocity.anakia.Escape();
    Code:
       0: aload_0
       1: invokespecial #1                  // Method java/lang/Object."<init>":()V
       4: return

  public static final java.lang.String getText(java.lang.String);
    Code:
       0: new           #2                  // class java/lang/StringBuffer
       3: dup
       4: invokespecial #3                  // Method java/lang/StringBuffer."<init>":()V
       7: astore_1
       8: aload_0
       9: invokevirtual #4                  // Method java/lang/String.toCharArray:()[C
      12: astore_2
      13: aconst_null
      14: astore_3
      15: iconst_0
      16: istore        4
      18: iconst_0
      19: istore        5
      21: iload         4
      23: aload_2
      24: arraylength
      25: if_icmpge     152
      28: aload_2
      29: iload         4
      31: caload
      32: lookupswitch  { // 5
                    10: 108
                    34: 102
                    38: 96
                    60: 84
                    62: 90
               default: 115
          }
      84: ldc           #5                  // String &lt;
      86: astore_3
      87: goto          115
      90: ldc           #6                  // String &gt;
      92: astore_3
      93: goto          115
      96: ldc           #7                  // String &amp;
      98: astore_3
      99: goto          115
     102: ldc           #8                  // String &quot;
     104: astore_3
     105: goto          115
     108: getstatic     #9                  // Field LINE_SEPARATOR:Ljava/lang/String;
     111: astore_3
     112: goto          115
     115: aload_3
     116: ifnull        146
     119: aload_1
     120: aload_2
     121: iload         5
     123: iload         4
     125: iload         5
     127: isub
     128: invokevirtual #10                 // Method java/lang/StringBuffer.append:([CII)Ljava/lang/StringBuffer;
     131: pop
     132: aload_1
     133: aload_3
     134: invokevirtual #11                 // Method java/lang/StringBuffer.append:(Ljava/lang/String;)Ljava/lang/StringBuffer;
     137: pop
     138: aconst_null
     139: astore_3
     140: iload         4
     142: iconst_1
     143: iadd
     144: istore        5
     146: iinc          4, 1
     149: goto          21
     152: iload         5
     154: aload_2
     155: arraylength
     156: if_icmpge     172
     159: aload_1
     160: aload_2
     161: iload         5
     163: iload         4
     165: iload         5
     167: isub
     168: invokevirtual #10                 // Method java/lang/StringBuffer.append:([CII)Ljava/lang/StringBuffer;
     171: pop
     172: aload_1
     173: invokevirtual #12                 // Method java/lang/StringBuffer.toString:()Ljava/lang/String;
     176: areturn

  static {};
    Code:
       0: ldc           #13                 // String line.separator
       2: invokestatic  #14                 // Method java/lang/System.getProperty:(Ljava/lang/String;)Ljava/lang/String;
       5: putstatic     #9                  // Field LINE_SEPARATOR:Ljava/lang/String;
       8: return
}
