Compiled from "BranchingReaderSource.java"
public final class com.ctc.wstx.io.BranchingReaderSource extends com.ctc.wstx.io.ReaderSource {
  com.ctc.wstx.util.TextBuffer mBranchBuffer;

  int mBranchStartOffset;

  boolean mConvertLFs;

  boolean mGotCR;

  public com.ctc.wstx.io.BranchingReaderSource(com.ctc.wstx.api.ReaderConfig, java.lang.String, java.lang.String, java.net.URL, java.io.Reader, boolean);
    Code:
       0: aload_0
       1: aload_1
       2: aconst_null
       3: aconst_null
       4: aload_2
       5: aload_3
       6: aload         4
       8: aload         5
      10: iload         6
      12: invokespecial #1                  // Method com/ctc/wstx/io/ReaderSource."<init>":(Lcom/ctc/wstx/api/ReaderConfig;Lcom/ctc/wstx/io/WstxInputSource;Ljava/lang/String;Ljava/lang/String;Ljava/lang/String;Ljava/net/URL;Ljava/io/Reader;Z)V
      15: aload_0
      16: aconst_null
      17: putfield      #2                  // Field mBranchBuffer:Lcom/ctc/wstx/util/TextBuffer;
      20: aload_0
      21: iconst_0
      22: putfield      #3                  // Field mBranchStartOffset:I
      25: aload_0
      26: iconst_0
      27: putfield      #4                  // Field mConvertLFs:Z
      30: aload_0
      31: iconst_0
      32: putfield      #5                  // Field mGotCR:Z
      35: return

  public int readInto(com.ctc.wstx.io.WstxInputData) throws java.io.IOException, javax.xml.stream.XMLStreamException;
    Code:
       0: aload_0
       1: getfield      #2                  // Field mBranchBuffer:Lcom/ctc/wstx/util/TextBuffer;
       4: ifnull        35
       7: aload_0
       8: getfield      #6                  // Field mInputLast:I
      11: aload_0
      12: getfield      #3                  // Field mBranchStartOffset:I
      15: if_icmple     30
      18: aload_0
      19: aload_0
      20: getfield      #3                  // Field mBranchStartOffset:I
      23: aload_0
      24: getfield      #6                  // Field mInputLast:I
      27: invokespecial #7                  // Method appendBranched:(II)V
      30: aload_0
      31: iconst_0
      32: putfield      #3                  // Field mBranchStartOffset:I
      35: aload_0
      36: aload_1
      37: invokespecial #8                  // Method com/ctc/wstx/io/ReaderSource.readInto:(Lcom/ctc/wstx/io/WstxInputData;)I
      40: ireturn

  public boolean readMore(com.ctc.wstx.io.WstxInputData, int) throws java.io.IOException, javax.xml.stream.XMLStreamException;
    Code:
       0: aload_0
       1: getfield      #2                  // Field mBranchBuffer:Lcom/ctc/wstx/util/TextBuffer;
       4: ifnull        47
       7: aload_1
       8: getfield      #9                  // Field com/ctc/wstx/io/WstxInputData.mInputPtr:I
      11: istore_3
      12: aload_0
      13: getfield      #6                  // Field mInputLast:I
      16: iload_3
      17: isub
      18: istore        4
      20: iload         4
      22: ifle          47
      25: iload_3
      26: aload_0
      27: getfield      #3                  // Field mBranchStartOffset:I
      30: if_icmple     42
      33: aload_0
      34: aload_0
      35: getfield      #3                  // Field mBranchStartOffset:I
      38: iload_3
      39: invokespecial #7                  // Method appendBranched:(II)V
      42: aload_0
      43: iconst_0
      44: putfield      #3                  // Field mBranchStartOffset:I
      47: aload_0
      48: aload_1
      49: iload_2
      50: invokespecial #10                 // Method com/ctc/wstx/io/ReaderSource.readMore:(Lcom/ctc/wstx/io/WstxInputData;I)Z
      53: ireturn

  public void startBranch(com.ctc.wstx.util.TextBuffer, int, boolean);
    Code:
       0: aload_0
       1: aload_1
       2: putfield      #2                  // Field mBranchBuffer:Lcom/ctc/wstx/util/TextBuffer;
       5: aload_0
       6: iload_2
       7: putfield      #3                  // Field mBranchStartOffset:I
      10: aload_0
      11: iload_3
      12: putfield      #4                  // Field mConvertLFs:Z
      15: aload_0
      16: iconst_0
      17: putfield      #5                  // Field mGotCR:Z
      20: return

  public void endBranch(int);
    Code:
       0: aload_0
       1: getfield      #2                  // Field mBranchBuffer:Lcom/ctc/wstx/util/TextBuffer;
       4: ifnull        29
       7: iload_1
       8: aload_0
       9: getfield      #3                  // Field mBranchStartOffset:I
      12: if_icmple     24
      15: aload_0
      16: aload_0
      17: getfield      #3                  // Field mBranchStartOffset:I
      20: iload_1
      21: invokespecial #7                  // Method appendBranched:(II)V
      24: aload_0
      25: aconst_null
      26: putfield      #2                  // Field mBranchBuffer:Lcom/ctc/wstx/util/TextBuffer;
      29: return

  private void appendBranched(int, int);
    Code:
       0: aload_0
       1: getfield      #4                  // Field mConvertLFs:Z
       4: ifeq          141
       7: aload_0
       8: getfield      #11                 // Field mBuffer:[C
      11: astore_3
      12: aload_0
      13: getfield      #2                  // Field mBranchBuffer:Lcom/ctc/wstx/util/TextBuffer;
      16: invokevirtual #12                 // Method com/ctc/wstx/util/TextBuffer.getCurrentSegment:()[C
      19: astore        4
      21: aload_0
      22: getfield      #2                  // Field mBranchBuffer:Lcom/ctc/wstx/util/TextBuffer;
      25: invokevirtual #13                 // Method com/ctc/wstx/util/TextBuffer.getCurrentSegmentSize:()I
      28: istore        5
      30: aload_0
      31: getfield      #5                  // Field mGotCR:Z
      34: ifeq          48
      37: aload_3
      38: iload_1
      39: caload
      40: bipush        10
      42: if_icmpne     48
      45: iinc          1, 1
      48: iload_1
      49: iload_2
      50: if_icmpge     129
      53: aload_3
      54: iload_1
      55: iinc          1, 1
      58: caload
      59: istore        6
      61: iload         6
      63: bipush        13
      65: if_icmpne     96
      68: iload_1
      69: iload_2
      70: if_icmpge     87
      73: aload_3
      74: iload_1
      75: caload
      76: bipush        10
      78: if_icmpne     92
      81: iinc          1, 1
      84: goto          92
      87: aload_0
      88: iconst_1
      89: putfield      #5                  // Field mGotCR:Z
      92: bipush        10
      94: istore        6
      96: aload         4
      98: iload         5
     100: iinc          5, 1
     103: iload         6
     105: castore
     106: iload         5
     108: aload         4
     110: arraylength
     111: if_icmplt     126
     114: aload_0
     115: getfield      #2                  // Field mBranchBuffer:Lcom/ctc/wstx/util/TextBuffer;
     118: invokevirtual #14                 // Method com/ctc/wstx/util/TextBuffer.finishCurrentSegment:()[C
     121: astore        4
     123: iconst_0
     124: istore        5
     126: goto          48
     129: aload_0
     130: getfield      #2                  // Field mBranchBuffer:Lcom/ctc/wstx/util/TextBuffer;
     133: iload         5
     135: invokevirtual #15                 // Method com/ctc/wstx/util/TextBuffer.setCurrentLength:(I)V
     138: goto          156
     141: aload_0
     142: getfield      #2                  // Field mBranchBuffer:Lcom/ctc/wstx/util/TextBuffer;
     145: aload_0
     146: getfield      #11                 // Field mBuffer:[C
     149: iload_1
     150: iload_2
     151: iload_1
     152: isub
     153: invokevirtual #16                 // Method com/ctc/wstx/util/TextBuffer.append:([CII)V
     156: return
}
