Compiled from "CommandHandler.java"
public class io.lettuce.core.protocol.CommandHandler extends io.netty.channel.ChannelDuplexHandler implements io.lettuce.core.protocol.HasQueuedCommands {
  static final java.util.Set<java.lang.String> SUPPRESS_IO_EXCEPTION_MESSAGES;

  private static final io.netty.util.internal.logging.InternalLogger logger;

  private static final java.util.concurrent.atomic.AtomicLong COMMAND_HANDLER_COUNTER;

  private final io.lettuce.core.ClientOptions clientOptions;

  private final io.lettuce.core.resource.ClientResources clientResources;

  private final io.lettuce.core.protocol.Endpoint endpoint;

  private final java.util.Deque<io.lettuce.core.protocol.RedisCommand<?, ?, ?>> stack;

  private final long commandHandlerId;

  private final io.lettuce.core.protocol.RedisStateMachine rsm;

  private final boolean traceEnabled;

  private final boolean debugEnabled;

  private final boolean latencyMetricsEnabled;

  private final boolean boundedQueues;

  private final io.lettuce.core.protocol.CommandHandler$BackpressureSource backpressureSource;

  io.netty.channel.Channel channel;

  private io.netty.buffer.ByteBuf buffer;

  private io.lettuce.core.protocol.CommandHandler$LifecycleState lifecycleState;

  private java.lang.String logPrefix;

  private io.lettuce.core.protocol.PristineFallbackCommand fallbackCommand;

  private boolean pristine;

  public io.lettuce.core.protocol.CommandHandler(io.lettuce.core.ClientOptions, io.lettuce.core.resource.ClientResources, io.lettuce.core.protocol.Endpoint);
    Code:
       0: aload_0
       1: invokespecial #1                  // Method io/netty/channel/ChannelDuplexHandler."<init>":()V
       4: aload_0
       5: new           #2                  // class java/util/ArrayDeque
       8: dup
       9: invokespecial #3                  // Method java/util/ArrayDeque."<init>":()V
      12: putfield      #4                  // Field stack:Ljava/util/Deque;
      15: aload_0
      16: getstatic     #5                  // Field COMMAND_HANDLER_COUNTER:Ljava/util/concurrent/atomic/AtomicLong;
      19: invokevirtual #6                  // Method java/util/concurrent/atomic/AtomicLong.incrementAndGet:()J
      22: putfield      #7                  // Field commandHandlerId:J
      25: aload_0
      26: new           #8                  // class io/lettuce/core/protocol/RedisStateMachine
      29: dup
      30: invokespecial #9                  // Method io/lettuce/core/protocol/RedisStateMachine."<init>":()V
      33: putfield      #10                 // Field rsm:Lio/lettuce/core/protocol/RedisStateMachine;
      36: aload_0
      37: getstatic     #11                 // Field logger:Lio/netty/util/internal/logging/InternalLogger;
      40: invokeinterface #12,  1           // InterfaceMethod io/netty/util/internal/logging/InternalLogger.isTraceEnabled:()Z
      45: putfield      #13                 // Field traceEnabled:Z
      48: aload_0
      49: getstatic     #11                 // Field logger:Lio/netty/util/internal/logging/InternalLogger;
      52: invokeinterface #14,  1           // InterfaceMethod io/netty/util/internal/logging/InternalLogger.isDebugEnabled:()Z
      57: putfield      #15                 // Field debugEnabled:Z
      60: aload_0
      61: new           #16                 // class io/lettuce/core/protocol/CommandHandler$BackpressureSource
      64: dup
      65: aload_0
      66: invokespecial #17                 // Method io/lettuce/core/protocol/CommandHandler$BackpressureSource."<init>":(Lio/lettuce/core/protocol/CommandHandler;)V
      69: putfield      #18                 // Field backpressureSource:Lio/lettuce/core/protocol/CommandHandler$BackpressureSource;
      72: aload_0
      73: getstatic     #19                 // Field io/lettuce/core/protocol/CommandHandler$LifecycleState.NOT_CONNECTED:Lio/lettuce/core/protocol/CommandHandler$LifecycleState;
      76: putfield      #20                 // Field lifecycleState:Lio/lettuce/core/protocol/CommandHandler$LifecycleState;
      79: aload_1
      80: ldc           #21                 // String ClientOptions must not be null
      82: invokestatic  #22                 // Method io/lettuce/core/internal/LettuceAssert.notNull:(Ljava/lang/Object;Ljava/lang/String;)V
      85: aload_2
      86: ldc           #23                 // String ClientResources must not be null
      88: invokestatic  #22                 // Method io/lettuce/core/internal/LettuceAssert.notNull:(Ljava/lang/Object;Ljava/lang/String;)V
      91: aload_3
      92: ldc           #24                 // String RedisEndpoint must not be null
      94: invokestatic  #22                 // Method io/lettuce/core/internal/LettuceAssert.notNull:(Ljava/lang/Object;Ljava/lang/String;)V
      97: aload_0
      98: aload_1
      99: putfield      #25                 // Field clientOptions:Lio/lettuce/core/ClientOptions;
     102: aload_0
     103: aload_2
     104: putfield      #26                 // Field clientResources:Lio/lettuce/core/resource/ClientResources;
     107: aload_0
     108: aload_3
     109: putfield      #27                 // Field endpoint:Lio/lettuce/core/protocol/Endpoint;
     112: aload_0
     113: aload_2
     114: invokeinterface #28,  1           // InterfaceMethod io/lettuce/core/resource/ClientResources.commandLatencyCollector:()Lio/lettuce/core/metrics/CommandLatencyCollector;
     119: invokeinterface #29,  1           // InterfaceMethod io/lettuce/core/metrics/CommandLatencyCollector.isEnabled:()Z
     124: putfield      #30                 // Field latencyMetricsEnabled:Z
     127: aload_0
     128: aload_1
     129: invokevirtual #31                 // Method io/lettuce/core/ClientOptions.getRequestQueueSize:()I
     132: ldc           #33                 // int 2147483647
     134: if_icmpeq     141
     137: iconst_1
     138: goto          142
     141: iconst_0
     142: putfield      #34                 // Field boundedQueues:Z
     145: return

  public java.util.Queue<io.lettuce.core.protocol.RedisCommand<?, ?, ?>> getStack();
    Code:
       0: aload_0
       1: getfield      #4                  // Field stack:Ljava/util/Deque;
       4: areturn

  protected void setState(io.lettuce.core.protocol.CommandHandler$LifecycleState);
    Code:
       0: aload_0
       1: getfield      #20                 // Field lifecycleState:Lio/lettuce/core/protocol/CommandHandler$LifecycleState;
       4: getstatic     #35                 // Field io/lettuce/core/protocol/CommandHandler$LifecycleState.CLOSED:Lio/lettuce/core/protocol/CommandHandler$LifecycleState;
       7: if_acmpeq     15
      10: aload_0
      11: aload_1
      12: putfield      #20                 // Field lifecycleState:Lio/lettuce/core/protocol/CommandHandler$LifecycleState;
      15: return

  public java.util.Collection<io.lettuce.core.protocol.RedisCommand<?, ?, ?>> drainQueue();
    Code:
       0: aload_0
       1: getfield      #4                  // Field stack:Ljava/util/Deque;
       4: invokestatic  #36                 // Method drainCommands:(Ljava/util/Queue;)Ljava/util/List;
       7: areturn

  protected io.lettuce.core.protocol.CommandHandler$LifecycleState getState();
    Code:
       0: aload_0
       1: getfield      #20                 // Field lifecycleState:Lio/lettuce/core/protocol/CommandHandler$LifecycleState;
       4: areturn

  public boolean isClosed();
    Code:
       0: aload_0
       1: getfield      #20                 // Field lifecycleState:Lio/lettuce/core/protocol/CommandHandler$LifecycleState;
       4: getstatic     #35                 // Field io/lettuce/core/protocol/CommandHandler$LifecycleState.CLOSED:Lio/lettuce/core/protocol/CommandHandler$LifecycleState;
       7: if_acmpne     14
      10: iconst_1
      11: goto          15
      14: iconst_0
      15: ireturn

  public void channelRegistered(io.netty.channel.ChannelHandlerContext) throws java.lang.Exception;
    Code:
       0: aload_0
       1: invokevirtual #37                 // Method isClosed:()Z
       4: ifeq          21
       7: getstatic     #11                 // Field logger:Lio/netty/util/internal/logging/InternalLogger;
      10: ldc           #38                 // String {} Dropping register for a closed channel
      12: aload_0
      13: invokespecial #39                 // Method logPrefix:()Ljava/lang/String;
      16: invokeinterface #40,  3           // InterfaceMethod io/netty/util/internal/logging/InternalLogger.debug:(Ljava/lang/String;Ljava/lang/Object;)V
      21: aload_0
      22: aload_1
      23: invokeinterface #41,  1           // InterfaceMethod io/netty/channel/ChannelHandlerContext.channel:()Lio/netty/channel/Channel;
      28: putfield      #42                 // Field channel:Lio/netty/channel/Channel;
      31: aload_0
      32: getfield      #15                 // Field debugEnabled:Z
      35: ifeq          57
      38: aload_0
      39: aconst_null
      40: putfield      #43                 // Field logPrefix:Ljava/lang/String;
      43: getstatic     #11                 // Field logger:Lio/netty/util/internal/logging/InternalLogger;
      46: ldc           #44                 // String {} channelRegistered()
      48: aload_0
      49: invokespecial #39                 // Method logPrefix:()Ljava/lang/String;
      52: invokeinterface #40,  3           // InterfaceMethod io/netty/util/internal/logging/InternalLogger.debug:(Ljava/lang/String;Ljava/lang/Object;)V
      57: aload_0
      58: getstatic     #45                 // Field io/lettuce/core/protocol/CommandHandler$LifecycleState.REGISTERED:Lio/lettuce/core/protocol/CommandHandler$LifecycleState;
      61: invokevirtual #46                 // Method setState:(Lio/lettuce/core/protocol/CommandHandler$LifecycleState;)V
      64: aload_0
      65: aload_1
      66: invokeinterface #47,  1           // InterfaceMethod io/netty/channel/ChannelHandlerContext.alloc:()Lio/netty/buffer/ByteBufAllocator;
      71: ldc           #48                 // int 65536
      73: invokeinterface #49,  2           // InterfaceMethod io/netty/buffer/ByteBufAllocator.directBuffer:(I)Lio/netty/buffer/ByteBuf;
      78: putfield      #50                 // Field buffer:Lio/netty/buffer/ByteBuf;
      81: aload_1
      82: invokeinterface #51,  1           // InterfaceMethod io/netty/channel/ChannelHandlerContext.fireChannelRegistered:()Lio/netty/channel/ChannelHandlerContext;
      87: pop
      88: return

  public void channelUnregistered(io.netty.channel.ChannelHandlerContext) throws java.lang.Exception;
    Code:
       0: aload_0
       1: getfield      #15                 // Field debugEnabled:Z
       4: ifeq          21
       7: getstatic     #11                 // Field logger:Lio/netty/util/internal/logging/InternalLogger;
      10: ldc           #52                 // String {} channelUnregistered()
      12: aload_0
      13: invokespecial #39                 // Method logPrefix:()Ljava/lang/String;
      16: invokeinterface #40,  3           // InterfaceMethod io/netty/util/internal/logging/InternalLogger.debug:(Ljava/lang/String;Ljava/lang/Object;)V
      21: aload_0
      22: getfield      #42                 // Field channel:Lio/netty/channel/Channel;
      25: ifnull        63
      28: aload_1
      29: invokeinterface #41,  1           // InterfaceMethod io/netty/channel/ChannelHandlerContext.channel:()Lio/netty/channel/Channel;
      34: aload_0
      35: getfield      #42                 // Field channel:Lio/netty/channel/Channel;
      38: if_acmpeq     63
      41: getstatic     #11                 // Field logger:Lio/netty/util/internal/logging/InternalLogger;
      44: ldc           #53                 // String {} My channel and ctx.channel mismatch. Propagating event to other listeners
      46: aload_0
      47: invokespecial #39                 // Method logPrefix:()Ljava/lang/String;
      50: invokeinterface #40,  3           // InterfaceMethod io/netty/util/internal/logging/InternalLogger.debug:(Ljava/lang/String;Ljava/lang/Object;)V
      55: aload_1
      56: invokeinterface #54,  1           // InterfaceMethod io/netty/channel/ChannelHandlerContext.fireChannelUnregistered:()Lio/netty/channel/ChannelHandlerContext;
      61: pop
      62: return
      63: aload_0
      64: aconst_null
      65: putfield      #42                 // Field channel:Lio/netty/channel/Channel;
      68: aload_0
      69: getfield      #50                 // Field buffer:Lio/netty/buffer/ByteBuf;
      72: invokevirtual #55                 // Method io/netty/buffer/ByteBuf.release:()Z
      75: pop
      76: aload_0
      77: invokespecial #56                 // Method reset:()V
      80: aload_0
      81: getstatic     #35                 // Field io/lettuce/core/protocol/CommandHandler$LifecycleState.CLOSED:Lio/lettuce/core/protocol/CommandHandler$LifecycleState;
      84: invokevirtual #46                 // Method setState:(Lio/lettuce/core/protocol/CommandHandler$LifecycleState;)V
      87: aload_0
      88: getfield      #10                 // Field rsm:Lio/lettuce/core/protocol/RedisStateMachine;
      91: invokevirtual #57                 // Method io/lettuce/core/protocol/RedisStateMachine.close:()V
      94: aload_1
      95: invokeinterface #54,  1           // InterfaceMethod io/netty/channel/ChannelHandlerContext.fireChannelUnregistered:()Lio/netty/channel/ChannelHandlerContext;
     100: pop
     101: return

  public void userEventTriggered(io.netty.channel.ChannelHandlerContext, java.lang.Object) throws java.lang.Exception;
    Code:
       0: aload_2
       1: getstatic     #58                 // Field io/lettuce/core/protocol/CommandHandler$EnableAutoRead.INSTANCE:Lio/lettuce/core/protocol/CommandHandler$EnableAutoRead;
       4: if_acmpne     26
       7: aload_0
       8: getfield      #42                 // Field channel:Lio/netty/channel/Channel;
      11: invokeinterface #59,  1           // InterfaceMethod io/netty/channel/Channel.config:()Lio/netty/channel/ChannelConfig;
      16: iconst_1
      17: invokeinterface #60,  2           // InterfaceMethod io/netty/channel/ChannelConfig.setAutoRead:(Z)Lio/netty/channel/ChannelConfig;
      22: pop
      23: goto          77
      26: aload_2
      27: instanceof    #61                 // class io/lettuce/core/ConnectionEvents$Reset
      30: ifeq          40
      33: aload_0
      34: invokespecial #56                 // Method reset:()V
      37: goto          77
      40: aload_2
      41: instanceof    #62                 // class io/lettuce/core/ConnectionEvents$PingBeforeActivate
      44: ifeq          77
      47: aload_2
      48: checkcast     #62                 // class io/lettuce/core/ConnectionEvents$PingBeforeActivate
      51: astore_3
      52: aload_0
      53: getfield      #4                  // Field stack:Ljava/util/Deque;
      56: aload_3
      57: invokevirtual #63                 // Method io/lettuce/core/ConnectionEvents$PingBeforeActivate.getCommand:()Lio/lettuce/core/protocol/RedisCommand;
      60: invokeinterface #64,  2           // InterfaceMethod java/util/Deque.addFirst:(Ljava/lang/Object;)V
      65: aload_1
      66: aload_3
      67: invokevirtual #63                 // Method io/lettuce/core/ConnectionEvents$PingBeforeActivate.getCommand:()Lio/lettuce/core/protocol/RedisCommand;
      70: invokeinterface #65,  2           // InterfaceMethod io/netty/channel/ChannelHandlerContext.writeAndFlush:(Ljava/lang/Object;)Lio/netty/channel/ChannelFuture;
      75: pop
      76: return
      77: aload_0
      78: aload_1
      79: aload_2
      80: invokespecial #66                 // Method io/netty/channel/ChannelDuplexHandler.userEventTriggered:(Lio/netty/channel/ChannelHandlerContext;Ljava/lang/Object;)V
      83: return

  public void exceptionCaught(io.netty.channel.ChannelHandlerContext, java.lang.Throwable) throws java.lang.Exception;
    Code:
       0: getstatic     #67                 // Field io/netty/util/internal/logging/InternalLogLevel.WARN:Lio/netty/util/internal/logging/InternalLogLevel;
       3: astore_3
       4: aload_0
       5: getfield      #4                  // Field stack:Ljava/util/Deque;
       8: invokeinterface #68,  1           // InterfaceMethod java/util/Deque.isEmpty:()Z
      13: ifne          105
      16: aload_0
      17: getfield      #4                  // Field stack:Ljava/util/Deque;
      20: invokeinterface #69,  1           // InterfaceMethod java/util/Deque.poll:()Ljava/lang/Object;
      25: checkcast     #70                 // class io/lettuce/core/protocol/RedisCommand
      28: astore        4
      30: aload_0
      31: getfield      #15                 // Field debugEnabled:Z
      34: ifeq          53
      37: getstatic     #11                 // Field logger:Lio/netty/util/internal/logging/InternalLogger;
      40: ldc           #71                 // String {} Storing exception in {}
      42: aload_0
      43: invokespecial #39                 // Method logPrefix:()Ljava/lang/String;
      46: aload         4
      48: invokeinterface #72,  4           // InterfaceMethod io/netty/util/internal/logging/InternalLogger.debug:(Ljava/lang/String;Ljava/lang/Object;Ljava/lang/Object;)V
      53: getstatic     #73                 // Field io/netty/util/internal/logging/InternalLogLevel.DEBUG:Lio/netty/util/internal/logging/InternalLogLevel;
      56: astore_3
      57: aload         4
      59: aload_2
      60: invokeinterface #74,  2           // InterfaceMethod io/lettuce/core/protocol/RedisCommand.completeExceptionally:(Ljava/lang/Throwable;)Z
      65: pop
      66: goto          105
      69: astore        5
      71: getstatic     #11                 // Field logger:Lio/netty/util/internal/logging/InternalLogger;
      74: ldc           #76                 // String {} Unexpected exception during command completion exceptionally: {}
      76: iconst_3
      77: anewarray     #77                 // class java/lang/Object
      80: dup
      81: iconst_0
      82: aload_0
      83: getfield      #43                 // Field logPrefix:Ljava/lang/String;
      86: aastore
      87: dup
      88: iconst_1
      89: aload         5
      91: invokevirtual #78                 // Method java/lang/Exception.toString:()Ljava/lang/String;
      94: aastore
      95: dup
      96: iconst_2
      97: aload         5
      99: aastore
     100: invokeinterface #79,  3           // InterfaceMethod io/netty/util/internal/logging/InternalLogger.warn:(Ljava/lang/String;[Ljava/lang/Object;)V
     105: aload_0
     106: getfield      #42                 // Field channel:Lio/netty/channel/Channel;
     109: ifnull        131
     112: aload_0
     113: getfield      #42                 // Field channel:Lio/netty/channel/Channel;
     116: invokeinterface #80,  1           // InterfaceMethod io/netty/channel/Channel.isActive:()Z
     121: ifeq          131
     124: aload_0
     125: invokevirtual #81                 // Method isConnected:()Z
     128: ifne          166
     131: aload_0
     132: getfield      #15                 // Field debugEnabled:Z
     135: ifeq          152
     138: getstatic     #11                 // Field logger:Lio/netty/util/internal/logging/InternalLogger;
     141: ldc           #82                 // String {} Storing exception in connectionError
     143: aload_0
     144: invokespecial #39                 // Method logPrefix:()Ljava/lang/String;
     147: invokeinterface #40,  3           // InterfaceMethod io/netty/util/internal/logging/InternalLogger.debug:(Ljava/lang/String;Ljava/lang/Object;)V
     152: getstatic     #73                 // Field io/netty/util/internal/logging/InternalLogLevel.DEBUG:Lio/netty/util/internal/logging/InternalLogLevel;
     155: astore_3
     156: aload_0
     157: getfield      #27                 // Field endpoint:Lio/lettuce/core/protocol/Endpoint;
     160: aload_2
     161: invokeinterface #83,  2           // InterfaceMethod io/lettuce/core/protocol/Endpoint.notifyException:(Ljava/lang/Throwable;)V
     166: aload_2
     167: instanceof    #84                 // class java/io/IOException
     170: ifeq          209
     173: aload_3
     174: invokevirtual #85                 // Method io/netty/util/internal/logging/InternalLogLevel.ordinal:()I
     177: getstatic     #86                 // Field io/netty/util/internal/logging/InternalLogLevel.INFO:Lio/netty/util/internal/logging/InternalLogLevel;
     180: invokevirtual #85                 // Method io/netty/util/internal/logging/InternalLogLevel.ordinal:()I
     183: if_icmple     209
     186: getstatic     #86                 // Field io/netty/util/internal/logging/InternalLogLevel.INFO:Lio/netty/util/internal/logging/InternalLogLevel;
     189: astore_3
     190: getstatic     #87                 // Field SUPPRESS_IO_EXCEPTION_MESSAGES:Ljava/util/Set;
     193: aload_2
     194: invokevirtual #88                 // Method java/lang/Throwable.getMessage:()Ljava/lang/String;
     197: invokeinterface #89,  2           // InterfaceMethod java/util/Set.contains:(Ljava/lang/Object;)Z
     202: ifeq          209
     205: getstatic     #73                 // Field io/netty/util/internal/logging/InternalLogLevel.DEBUG:Lio/netty/util/internal/logging/InternalLogLevel;
     208: astore_3
     209: getstatic     #11                 // Field logger:Lio/netty/util/internal/logging/InternalLogger;
     212: aload_3
     213: ldc           #90                 // String {} Unexpected exception during request: {}
     215: iconst_3
     216: anewarray     #77                 // class java/lang/Object
     219: dup
     220: iconst_0
     221: aload_0
     222: getfield      #43                 // Field logPrefix:Ljava/lang/String;
     225: aastore
     226: dup
     227: iconst_1
     228: aload_2
     229: invokevirtual #91                 // Method java/lang/Throwable.toString:()Ljava/lang/String;
     232: aastore
     233: dup
     234: iconst_2
     235: aload_2
     236: aastore
     237: invokeinterface #92,  4           // InterfaceMethod io/netty/util/internal/logging/InternalLogger.log:(Lio/netty/util/internal/logging/InternalLogLevel;Ljava/lang/String;[Ljava/lang/Object;)V
     242: return
    Exception table:
       from    to  target type
          57    66    69   Class java/lang/Exception

  public void channelActive(io.netty.channel.ChannelHandlerContext) throws java.lang.Exception;
    Code:
       0: aload_0
       1: aconst_null
       2: putfield      #43                 // Field logPrefix:Ljava/lang/String;
       5: aload_0
       6: iconst_1
       7: putfield      #93                 // Field pristine:Z
      10: aload_0
      11: aconst_null
      12: putfield      #94                 // Field fallbackCommand:Lio/lettuce/core/protocol/PristineFallbackCommand;
      15: aload_0
      16: getfield      #15                 // Field debugEnabled:Z
      19: ifeq          36
      22: getstatic     #11                 // Field logger:Lio/netty/util/internal/logging/InternalLogger;
      25: ldc           #95                 // String {} channelActive()
      27: aload_0
      28: invokespecial #39                 // Method logPrefix:()Ljava/lang/String;
      31: invokeinterface #40,  3           // InterfaceMethod io/netty/util/internal/logging/InternalLogger.debug:(Ljava/lang/String;Ljava/lang/Object;)V
      36: aload_0
      37: getstatic     #96                 // Field io/lettuce/core/protocol/CommandHandler$LifecycleState.CONNECTED:Lio/lettuce/core/protocol/CommandHandler$LifecycleState;
      40: invokevirtual #46                 // Method setState:(Lio/lettuce/core/protocol/CommandHandler$LifecycleState;)V
      43: aload_0
      44: getfield      #27                 // Field endpoint:Lio/lettuce/core/protocol/Endpoint;
      47: aload_1
      48: invokeinterface #41,  1           // InterfaceMethod io/netty/channel/ChannelHandlerContext.channel:()Lio/netty/channel/Channel;
      53: invokeinterface #97,  2           // InterfaceMethod io/lettuce/core/protocol/Endpoint.notifyChannelActive:(Lio/netty/channel/Channel;)V
      58: aload_0
      59: aload_1
      60: invokespecial #98                 // Method io/netty/channel/ChannelDuplexHandler.channelActive:(Lio/netty/channel/ChannelHandlerContext;)V
      63: aload_0
      64: getfield      #42                 // Field channel:Lio/netty/channel/Channel;
      67: ifnull        91
      70: aload_0
      71: getfield      #42                 // Field channel:Lio/netty/channel/Channel;
      74: invokeinterface #99,  1           // InterfaceMethod io/netty/channel/Channel.eventLoop:()Lio/netty/channel/EventLoop;
      79: aload_0
      80: invokedynamic #100,  0            // InvokeDynamic #0:run:(Lio/lettuce/core/protocol/CommandHandler;)Ljava/lang/Runnable;
      85: invokeinterface #101,  2          // InterfaceMethod io/netty/channel/EventLoop.submit:(Ljava/lang/Runnable;)Lio/netty/util/concurrent/Future;
      90: pop
      91: aload_0
      92: getfield      #15                 // Field debugEnabled:Z
      95: ifeq          112
      98: getstatic     #11                 // Field logger:Lio/netty/util/internal/logging/InternalLogger;
     101: ldc           #102                // String {} channelActive() done
     103: aload_0
     104: invokespecial #39                 // Method logPrefix:()Ljava/lang/String;
     107: invokeinterface #40,  3           // InterfaceMethod io/netty/util/internal/logging/InternalLogger.debug:(Ljava/lang/String;Ljava/lang/Object;)V
     112: return

  private static <T> java.util.List<T> drainCommands(java.util.Queue<T>);
    Code:
       0: new           #103                // class java/util/ArrayList
       3: dup
       4: aload_0
       5: invokeinterface #104,  1          // InterfaceMethod java/util/Queue.size:()I
      10: invokespecial #105                // Method java/util/ArrayList."<init>":(I)V
      13: astore_1
      14: aload_0
      15: invokeinterface #106,  1          // InterfaceMethod java/util/Queue.poll:()Ljava/lang/Object;
      20: dup
      21: astore_2
      22: ifnull        36
      25: aload_1
      26: aload_2
      27: invokeinterface #107,  2          // InterfaceMethod java/util/List.add:(Ljava/lang/Object;)Z
      32: pop
      33: goto          14
      36: aload_1
      37: areturn

  public void channelInactive(io.netty.channel.ChannelHandlerContext) throws java.lang.Exception;
    Code:
       0: aload_0
       1: getfield      #15                 // Field debugEnabled:Z
       4: ifeq          21
       7: getstatic     #11                 // Field logger:Lio/netty/util/internal/logging/InternalLogger;
      10: ldc           #108                // String {} channelInactive()
      12: aload_0
      13: invokespecial #39                 // Method logPrefix:()Ljava/lang/String;
      16: invokeinterface #40,  3           // InterfaceMethod io/netty/util/internal/logging/InternalLogger.debug:(Ljava/lang/String;Ljava/lang/Object;)V
      21: aload_0
      22: getfield      #42                 // Field channel:Lio/netty/channel/Channel;
      25: ifnull        61
      28: aload_1
      29: invokeinterface #41,  1           // InterfaceMethod io/netty/channel/ChannelHandlerContext.channel:()Lio/netty/channel/Channel;
      34: aload_0
      35: getfield      #42                 // Field channel:Lio/netty/channel/Channel;
      38: if_acmpeq     61
      41: getstatic     #11                 // Field logger:Lio/netty/util/internal/logging/InternalLogger;
      44: ldc           #109                // String {} My channel and ctx.channel mismatch. Propagating event to other listeners.
      46: aload_0
      47: invokespecial #39                 // Method logPrefix:()Ljava/lang/String;
      50: invokeinterface #40,  3           // InterfaceMethod io/netty/util/internal/logging/InternalLogger.debug:(Ljava/lang/String;Ljava/lang/Object;)V
      55: aload_0
      56: aload_1
      57: invokespecial #110                // Method io/netty/channel/ChannelDuplexHandler.channelInactive:(Lio/netty/channel/ChannelHandlerContext;)V
      60: return
      61: aload_0
      62: getstatic     #111                // Field io/lettuce/core/protocol/CommandHandler$LifecycleState.DISCONNECTED:Lio/lettuce/core/protocol/CommandHandler$LifecycleState;
      65: invokevirtual #46                 // Method setState:(Lio/lettuce/core/protocol/CommandHandler$LifecycleState;)V
      68: aload_0
      69: getstatic     #112                // Field io/lettuce/core/protocol/CommandHandler$LifecycleState.DEACTIVATING:Lio/lettuce/core/protocol/CommandHandler$LifecycleState;
      72: invokevirtual #46                 // Method setState:(Lio/lettuce/core/protocol/CommandHandler$LifecycleState;)V
      75: aload_0
      76: getfield      #27                 // Field endpoint:Lio/lettuce/core/protocol/Endpoint;
      79: aload_1
      80: invokeinterface #41,  1           // InterfaceMethod io/netty/channel/ChannelHandlerContext.channel:()Lio/netty/channel/Channel;
      85: invokeinterface #113,  2          // InterfaceMethod io/lettuce/core/protocol/Endpoint.notifyChannelInactive:(Lio/netty/channel/Channel;)V
      90: aload_0
      91: getfield      #27                 // Field endpoint:Lio/lettuce/core/protocol/Endpoint;
      94: aload_0
      95: invokeinterface #114,  2          // InterfaceMethod io/lettuce/core/protocol/Endpoint.notifyDrainQueuedCommands:(Lio/lettuce/core/protocol/HasQueuedCommands;)V
     100: aload_0
     101: getstatic     #115                // Field io/lettuce/core/protocol/CommandHandler$LifecycleState.DEACTIVATED:Lio/lettuce/core/protocol/CommandHandler$LifecycleState;
     104: invokevirtual #46                 // Method setState:(Lio/lettuce/core/protocol/CommandHandler$LifecycleState;)V
     107: aload_0
     108: getfield      #94                 // Field fallbackCommand:Lio/lettuce/core/protocol/PristineFallbackCommand;
     111: astore_2
     112: aload_0
     113: aload_2
     114: invokespecial #116                // Method isProtectedMode:(Lio/lettuce/core/protocol/RedisCommand;)Z
     117: ifeq          131
     120: aload_0
     121: aload_2
     122: invokevirtual #117                // Method io/lettuce/core/protocol/PristineFallbackCommand.getOutput:()Lio/lettuce/core/output/CommandOutput;
     125: invokevirtual #118                // Method io/lettuce/core/output/CommandOutput.getError:()Ljava/lang/String;
     128: invokespecial #119                // Method onProtectedMode:(Ljava/lang/String;)V
     131: aload_0
     132: getfield      #10                 // Field rsm:Lio/lettuce/core/protocol/RedisStateMachine;
     135: invokevirtual #120                // Method io/lettuce/core/protocol/RedisStateMachine.reset:()V
     138: aload_0
     139: getfield      #15                 // Field debugEnabled:Z
     142: ifeq          159
     145: getstatic     #11                 // Field logger:Lio/netty/util/internal/logging/InternalLogger;
     148: ldc           #121                // String {} channelInactive() done
     150: aload_0
     151: invokespecial #39                 // Method logPrefix:()Ljava/lang/String;
     154: invokeinterface #40,  3           // InterfaceMethod io/netty/util/internal/logging/InternalLogger.debug:(Ljava/lang/String;Ljava/lang/Object;)V
     159: aload_0
     160: aload_1
     161: invokespecial #110                // Method io/netty/channel/ChannelDuplexHandler.channelInactive:(Lio/netty/channel/ChannelHandlerContext;)V
     164: return

  public void write(io.netty.channel.ChannelHandlerContext, java.lang.Object, io.netty.channel.ChannelPromise) throws java.lang.Exception;
    Code:
       0: aload_0
       1: getfield      #15                 // Field debugEnabled:Z
       4: ifeq          22
       7: getstatic     #11                 // Field logger:Lio/netty/util/internal/logging/InternalLogger;
      10: ldc           #122                // String {} write(ctx, {}, promise)
      12: aload_0
      13: invokespecial #39                 // Method logPrefix:()Ljava/lang/String;
      16: aload_2
      17: invokeinterface #72,  4           // InterfaceMethod io/netty/util/internal/logging/InternalLogger.debug:(Ljava/lang/String;Ljava/lang/Object;Ljava/lang/Object;)V
      22: aload_2
      23: instanceof    #70                 // class io/lettuce/core/protocol/RedisCommand
      26: ifeq          40
      29: aload_0
      30: aload_1
      31: aload_2
      32: checkcast     #70                 // class io/lettuce/core/protocol/RedisCommand
      35: aload_3
      36: invokespecial #123                // Method writeSingleCommand:(Lio/netty/channel/ChannelHandlerContext;Lio/lettuce/core/protocol/RedisCommand;Lio/netty/channel/ChannelPromise;)V
      39: return
      40: aload_2
      41: instanceof    #124                // class java/util/Collection
      44: ifeq          57
      47: aload_0
      48: aload_1
      49: aload_2
      50: checkcast     #124                // class java/util/Collection
      53: aload_3
      54: invokespecial #125                // Method writeBatch:(Lio/netty/channel/ChannelHandlerContext;Ljava/util/Collection;Lio/netty/channel/ChannelPromise;)V
      57: return

  private void writeSingleCommand(io.netty.channel.ChannelHandlerContext, io.lettuce.core.protocol.RedisCommand<?, ?, ?>, io.netty.channel.ChannelPromise) throws java.lang.Exception;
    Code:
       0: aload_2
       1: invokestatic  #126                // Method isWriteable:(Lio/lettuce/core/protocol/RedisCommand;)Z
       4: ifne          8
       7: return
       8: aload_0
       9: aload_2
      10: aload_3
      11: invokespecial #127                // Method addToStack:(Lio/lettuce/core/protocol/RedisCommand;Lio/netty/channel/ChannelPromise;)V
      14: aload_1
      15: aload_2
      16: aload_3
      17: invokeinterface #128,  3          // InterfaceMethod io/netty/channel/ChannelHandlerContext.write:(Ljava/lang/Object;Lio/netty/channel/ChannelPromise;)Lio/netty/channel/ChannelFuture;
      22: pop
      23: return

  private void writeBatch(io.netty.channel.ChannelHandlerContext, java.util.Collection<io.lettuce.core.protocol.RedisCommand<?, ?, ?>>, io.netty.channel.ChannelPromise) throws java.lang.Exception;
    Code:
       0: aload_2
       1: astore        4
       3: iconst_0
       4: istore        5
       6: iconst_0
       7: istore        6
       9: aload_2
      10: invokeinterface #129,  1          // InterfaceMethod java/util/Collection.iterator:()Ljava/util/Iterator;
      15: astore        7
      17: aload         7
      19: invokeinterface #130,  1          // InterfaceMethod java/util/Iterator.hasNext:()Z
      24: ifeq          59
      27: aload         7
      29: invokeinterface #131,  1          // InterfaceMethod java/util/Iterator.next:()Ljava/lang/Object;
      34: checkcast     #70                 // class io/lettuce/core/protocol/RedisCommand
      37: astore        8
      39: aload         8
      41: invokestatic  #126                // Method isWriteable:(Lio/lettuce/core/protocol/RedisCommand;)Z
      44: ifne          53
      47: iconst_1
      48: istore        6
      50: goto          59
      53: iinc          5, 1
      56: goto          17
      59: aload_0
      60: iload         5
      62: invokespecial #132                // Method validateWrite:(I)V
      65: goto          124
      68: astore        7
      70: aload         4
      72: invokeinterface #129,  1          // InterfaceMethod java/util/Collection.iterator:()Ljava/util/Iterator;
      77: astore        8
      79: aload         8
      81: invokeinterface #130,  1          // InterfaceMethod java/util/Iterator.hasNext:()Z
      86: ifeq          114
      89: aload         8
      91: invokeinterface #131,  1          // InterfaceMethod java/util/Iterator.next:()Ljava/lang/Object;
      96: checkcast     #70                 // class io/lettuce/core/protocol/RedisCommand
      99: astore        9
     101: aload         9
     103: aload         7
     105: invokeinterface #74,  2           // InterfaceMethod io/lettuce/core/protocol/RedisCommand.completeExceptionally:(Ljava/lang/Throwable;)Z
     110: pop
     111: goto          79
     114: aload_3
     115: aload         7
     117: invokeinterface #133,  2          // InterfaceMethod io/netty/channel/ChannelPromise.setFailure:(Ljava/lang/Throwable;)Lio/netty/channel/ChannelPromise;
     122: pop
     123: return
     124: iload         6
     126: ifeq          198
     129: new           #103                // class java/util/ArrayList
     132: dup
     133: aload_2
     134: invokeinterface #134,  1          // InterfaceMethod java/util/Collection.size:()I
     139: invokespecial #105                // Method java/util/ArrayList."<init>":(I)V
     142: astore        4
     144: aload_2
     145: invokeinterface #129,  1          // InterfaceMethod java/util/Collection.iterator:()Ljava/util/Iterator;
     150: astore        7
     152: aload         7
     154: invokeinterface #130,  1          // InterfaceMethod java/util/Iterator.hasNext:()Z
     159: ifeq          198
     162: aload         7
     164: invokeinterface #131,  1          // InterfaceMethod java/util/Iterator.next:()Ljava/lang/Object;
     169: checkcast     #70                 // class io/lettuce/core/protocol/RedisCommand
     172: astore        8
     174: aload         8
     176: invokestatic  #126                // Method isWriteable:(Lio/lettuce/core/protocol/RedisCommand;)Z
     179: ifne          185
     182: goto          152
     185: aload         4
     187: aload         8
     189: invokeinterface #135,  2          // InterfaceMethod java/util/Collection.add:(Ljava/lang/Object;)Z
     194: pop
     195: goto          152
     198: aload         4
     200: invokeinterface #129,  1          // InterfaceMethod java/util/Collection.iterator:()Ljava/util/Iterator;
     205: astore        7
     207: aload         7
     209: invokeinterface #130,  1          // InterfaceMethod java/util/Iterator.hasNext:()Z
     214: ifeq          239
     217: aload         7
     219: invokeinterface #131,  1          // InterfaceMethod java/util/Iterator.next:()Ljava/lang/Object;
     224: checkcast     #70                 // class io/lettuce/core/protocol/RedisCommand
     227: astore        8
     229: aload_0
     230: aload         8
     232: aload_3
     233: invokespecial #127                // Method addToStack:(Lio/lettuce/core/protocol/RedisCommand;Lio/netty/channel/ChannelPromise;)V
     236: goto          207
     239: aload         4
     241: invokeinterface #136,  1          // InterfaceMethod java/util/Collection.isEmpty:()Z
     246: ifne          259
     249: aload_1
     250: aload         4
     252: aload_3
     253: invokeinterface #128,  3          // InterfaceMethod io/netty/channel/ChannelHandlerContext.write:(Ljava/lang/Object;Lio/netty/channel/ChannelPromise;)Lio/netty/channel/ChannelFuture;
     258: pop
     259: return
    Exception table:
       from    to  target type
          59    65    68   Class java/lang/Exception

  private void addToStack(io.lettuce.core.protocol.RedisCommand<?, ?, ?>, io.netty.channel.ChannelPromise) throws java.lang.Exception;
    Code:
       0: aload_0
       1: iconst_1
       2: invokespecial #132                // Method validateWrite:(I)V
       5: aload_1
       6: invokeinterface #137,  1          // InterfaceMethod io/lettuce/core/protocol/RedisCommand.getOutput:()Lio/lettuce/core/output/CommandOutput;
      11: ifnonnull     23
      14: aload_1
      15: invokeinterface #138,  1          // InterfaceMethod io/lettuce/core/protocol/RedisCommand.complete:()V
      20: goto          63
      23: aload_0
      24: getfield      #4                  // Field stack:Ljava/util/Deque;
      27: aload_1
      28: invokeinterface #139,  2          // InterfaceMethod java/util/Deque.contains:(Ljava/lang/Object;)Z
      33: ifeq          63
      36: new           #140                // class io/lettuce/core/RedisException
      39: dup
      40: new           #141                // class java/lang/StringBuilder
      43: dup
      44: invokespecial #142                // Method java/lang/StringBuilder."<init>":()V
      47: ldc           #143                // String Attempting to write duplicate command that is already enqueued:
      49: invokevirtual #144                // Method java/lang/StringBuilder.append:(Ljava/lang/String;)Ljava/lang/StringBuilder;
      52: aload_1
      53: invokevirtual #145                // Method java/lang/StringBuilder.append:(Ljava/lang/Object;)Ljava/lang/StringBuilder;
      56: invokevirtual #146                // Method java/lang/StringBuilder.toString:()Ljava/lang/String;
      59: invokespecial #147                // Method io/lettuce/core/RedisException."<init>":(Ljava/lang/String;)V
      62: athrow
      63: aload_0
      64: aload_1
      65: invokespecial #148                // Method potentiallyWrapLatencyCommand:(Lio/lettuce/core/protocol/RedisCommand;)Lio/lettuce/core/protocol/RedisCommand;
      68: astore_3
      69: aload_2
      70: invokeinterface #149,  1          // InterfaceMethod io/netty/channel/ChannelPromise.isVoid:()Z
      75: ifeq          92
      78: aload_0
      79: getfield      #4                  // Field stack:Ljava/util/Deque;
      82: aload_3
      83: invokeinterface #150,  2          // InterfaceMethod java/util/Deque.add:(Ljava/lang/Object;)Z
      88: pop
      89: goto          106
      92: aload_2
      93: aload_0
      94: aload_3
      95: invokedynamic #151,  0            // InvokeDynamic #1:operationComplete:(Lio/lettuce/core/protocol/CommandHandler;Lio/lettuce/core/protocol/RedisCommand;)Lio/netty/util/concurrent/GenericFutureListener;
     100: invokeinterface #152,  2          // InterfaceMethod io/netty/channel/ChannelPromise.addListener:(Lio/netty/util/concurrent/GenericFutureListener;)Lio/netty/channel/ChannelPromise;
     105: pop
     106: goto          128
     109: astore_3
     110: aload_1
     111: aload_3
     112: invokeinterface #74,  2           // InterfaceMethod io/lettuce/core/protocol/RedisCommand.completeExceptionally:(Ljava/lang/Throwable;)Z
     117: pop
     118: aload_2
     119: aload_3
     120: invokeinterface #133,  2          // InterfaceMethod io/netty/channel/ChannelPromise.setFailure:(Ljava/lang/Throwable;)Lio/netty/channel/ChannelPromise;
     125: pop
     126: aload_3
     127: athrow
     128: return
    Exception table:
       from    to  target type
           0   106   109   Class java/lang/Exception

  private void validateWrite(int);
    Code:
       0: aload_0
       1: invokespecial #153                // Method usesBoundedQueues:()Z
       4: ifeq          72
       7: iconst_5
       8: istore_2
       9: aload_0
      10: getfield      #25                 // Field clientOptions:Lio/lettuce/core/ClientOptions;
      13: invokevirtual #31                 // Method io/lettuce/core/ClientOptions.getRequestQueueSize:()I
      16: iload_2
      17: iadd
      18: istore_3
      19: aload_0
      20: getfield      #4                  // Field stack:Ljava/util/Deque;
      23: invokeinterface #154,  1          // InterfaceMethod java/util/Deque.size:()I
      28: iload_1
      29: iadd
      30: iload_3
      31: if_icmple     72
      34: new           #140                // class io/lettuce/core/RedisException
      37: dup
      38: new           #141                // class java/lang/StringBuilder
      41: dup
      42: invokespecial #142                // Method java/lang/StringBuilder."<init>":()V
      45: ldc           #155                // String Internal stack size exceeded:
      47: invokevirtual #144                // Method java/lang/StringBuilder.append:(Ljava/lang/String;)Ljava/lang/StringBuilder;
      50: aload_0
      51: getfield      #25                 // Field clientOptions:Lio/lettuce/core/ClientOptions;
      54: invokevirtual #31                 // Method io/lettuce/core/ClientOptions.getRequestQueueSize:()I
      57: invokevirtual #156                // Method java/lang/StringBuilder.append:(I)Ljava/lang/StringBuilder;
      60: ldc           #157                // String . Commands are not accepted until the stack size drops.
      62: invokevirtual #144                // Method java/lang/StringBuilder.append:(Ljava/lang/String;)Ljava/lang/StringBuilder;
      65: invokevirtual #146                // Method java/lang/StringBuilder.toString:()Ljava/lang/String;
      68: invokespecial #147                // Method io/lettuce/core/RedisException."<init>":(Ljava/lang/String;)V
      71: athrow
      72: return

  private boolean usesBoundedQueues();
    Code:
       0: aload_0
       1: getfield      #34                 // Field boundedQueues:Z
       4: ireturn

  private static boolean isWriteable(io.lettuce.core.protocol.RedisCommand<?, ?, ?>);
    Code:
       0: aload_0
       1: invokeinterface #158,  1          // InterfaceMethod io/lettuce/core/protocol/RedisCommand.isDone:()Z
       6: ifne          13
       9: iconst_1
      10: goto          14
      13: iconst_0
      14: ireturn

  private io.lettuce.core.protocol.RedisCommand<?, ?, ?> potentiallyWrapLatencyCommand(io.lettuce.core.protocol.RedisCommand<?, ?, ?>);
    Code:
       0: aload_0
       1: getfield      #30                 // Field latencyMetricsEnabled:Z
       4: ifne          9
       7: aload_1
       8: areturn
       9: aload_1
      10: instanceof    #159                // class io/lettuce/core/protocol/WithLatency
      13: ifeq          41
      16: aload_1
      17: checkcast     #159                // class io/lettuce/core/protocol/WithLatency
      20: astore_2
      21: aload_2
      22: ldc2_w        #160                // long -1l
      25: invokeinterface #162,  3          // InterfaceMethod io/lettuce/core/protocol/WithLatency.firstResponse:(J)V
      30: aload_2
      31: invokestatic  #163                // Method nanoTime:()J
      34: invokeinterface #164,  3          // InterfaceMethod io/lettuce/core/protocol/WithLatency.sent:(J)V
      39: aload_1
      40: areturn
      41: new           #165                // class io/lettuce/core/protocol/LatencyMeteredCommand
      44: dup
      45: aload_1
      46: invokespecial #166                // Method io/lettuce/core/protocol/LatencyMeteredCommand."<init>":(Lio/lettuce/core/protocol/RedisCommand;)V
      49: astore_2
      50: aload_2
      51: ldc2_w        #160                // long -1l
      54: invokevirtual #167                // Method io/lettuce/core/protocol/LatencyMeteredCommand.firstResponse:(J)V
      57: aload_2
      58: invokestatic  #163                // Method nanoTime:()J
      61: invokevirtual #168                // Method io/lettuce/core/protocol/LatencyMeteredCommand.sent:(J)V
      64: aload_2
      65: areturn

  public void channelRead(io.netty.channel.ChannelHandlerContext, java.lang.Object) throws java.lang.Exception;
    Code:
       0: aload_2
       1: checkcast     #169                // class io/netty/buffer/ByteBuf
       4: astore_3
       5: aload_3
       6: invokevirtual #170                // Method io/netty/buffer/ByteBuf.isReadable:()Z
       9: ifeq          19
      12: aload_3
      13: invokevirtual #171                // Method io/netty/buffer/ByteBuf.refCnt:()I
      16: ifne          61
      19: getstatic     #11                 // Field logger:Lio/netty/util/internal/logging/InternalLogger;
      22: ldc           #172                // String {} Input not readable {}, {}
      24: iconst_3
      25: anewarray     #77                 // class java/lang/Object
      28: dup
      29: iconst_0
      30: aload_0
      31: invokespecial #39                 // Method logPrefix:()Ljava/lang/String;
      34: aastore
      35: dup
      36: iconst_1
      37: aload_3
      38: invokevirtual #170                // Method io/netty/buffer/ByteBuf.isReadable:()Z
      41: invokestatic  #173                // Method java/lang/Boolean.valueOf:(Z)Ljava/lang/Boolean;
      44: aastore
      45: dup
      46: iconst_2
      47: aload_3
      48: invokevirtual #171                // Method io/netty/buffer/ByteBuf.refCnt:()I
      51: invokestatic  #174                // Method java/lang/Integer.valueOf:(I)Ljava/lang/Integer;
      54: aastore
      55: invokeinterface #79,  3           // InterfaceMethod io/netty/util/internal/logging/InternalLogger.warn:(Ljava/lang/String;[Ljava/lang/Object;)V
      60: return
      61: aload_0
      62: getfield      #15                 // Field debugEnabled:Z
      65: ifeq          114
      68: getstatic     #11                 // Field logger:Lio/netty/util/internal/logging/InternalLogger;
      71: ldc           #175                // String {} Received: {} bytes, {} commands in the stack
      73: iconst_3
      74: anewarray     #77                 // class java/lang/Object
      77: dup
      78: iconst_0
      79: aload_0
      80: invokespecial #39                 // Method logPrefix:()Ljava/lang/String;
      83: aastore
      84: dup
      85: iconst_1
      86: aload_3
      87: invokevirtual #176                // Method io/netty/buffer/ByteBuf.readableBytes:()I
      90: invokestatic  #174                // Method java/lang/Integer.valueOf:(I)Ljava/lang/Integer;
      93: aastore
      94: dup
      95: iconst_2
      96: aload_0
      97: getfield      #4                  // Field stack:Ljava/util/Deque;
     100: invokeinterface #154,  1          // InterfaceMethod java/util/Deque.size:()I
     105: invokestatic  #174                // Method java/lang/Integer.valueOf:(I)Ljava/lang/Integer;
     108: aastore
     109: invokeinterface #177,  3          // InterfaceMethod io/netty/util/internal/logging/InternalLogger.debug:(Ljava/lang/String;[Ljava/lang/Object;)V
     114: aload_0
     115: getfield      #50                 // Field buffer:Lio/netty/buffer/ByteBuf;
     118: invokevirtual #171                // Method io/netty/buffer/ByteBuf.refCnt:()I
     121: iconst_1
     122: if_icmpge     145
     125: getstatic     #11                 // Field logger:Lio/netty/util/internal/logging/InternalLogger;
     128: ldc           #178                // String {} Ignoring received data for closed or abandoned connection
     130: aload_0
     131: invokespecial #39                 // Method logPrefix:()Ljava/lang/String;
     134: invokeinterface #179,  3          // InterfaceMethod io/netty/util/internal/logging/InternalLogger.warn:(Ljava/lang/String;Ljava/lang/Object;)V
     139: aload_3
     140: invokevirtual #55                 // Method io/netty/buffer/ByteBuf.release:()Z
     143: pop
     144: return
     145: aload_0
     146: getfield      #15                 // Field debugEnabled:Z
     149: ifeq          191
     152: aload_1
     153: invokeinterface #41,  1           // InterfaceMethod io/netty/channel/ChannelHandlerContext.channel:()Lio/netty/channel/Channel;
     158: aload_0
     159: getfield      #42                 // Field channel:Lio/netty/channel/Channel;
     162: if_acmpeq     191
     165: getstatic     #11                 // Field logger:Lio/netty/util/internal/logging/InternalLogger;
     168: ldc           #180                // String {} Ignoring data for a non-registered channel {}
     170: aload_0
     171: invokespecial #39                 // Method logPrefix:()Ljava/lang/String;
     174: aload_1
     175: invokeinterface #41,  1           // InterfaceMethod io/netty/channel/ChannelHandlerContext.channel:()Lio/netty/channel/Channel;
     180: invokeinterface #72,  4           // InterfaceMethod io/netty/util/internal/logging/InternalLogger.debug:(Ljava/lang/String;Ljava/lang/Object;Ljava/lang/Object;)V
     185: aload_3
     186: invokevirtual #55                 // Method io/netty/buffer/ByteBuf.release:()Z
     189: pop
     190: return
     191: aload_0
     192: getfield      #13                 // Field traceEnabled:Z
     195: ifeq          222
     198: getstatic     #11                 // Field logger:Lio/netty/util/internal/logging/InternalLogger;
     201: ldc           #181                // String {} Buffer: {}
     203: aload_0
     204: invokespecial #39                 // Method logPrefix:()Ljava/lang/String;
     207: aload_3
     208: invokestatic  #182                // Method java/nio/charset/Charset.defaultCharset:()Ljava/nio/charset/Charset;
     211: invokevirtual #183                // Method io/netty/buffer/ByteBuf.toString:(Ljava/nio/charset/Charset;)Ljava/lang/String;
     214: invokevirtual #184                // Method java/lang/String.trim:()Ljava/lang/String;
     217: invokeinterface #185,  4          // InterfaceMethod io/netty/util/internal/logging/InternalLogger.trace:(Ljava/lang/String;Ljava/lang/Object;Ljava/lang/Object;)V
     222: aload_0
     223: getfield      #50                 // Field buffer:Lio/netty/buffer/ByteBuf;
     226: aload_3
     227: invokevirtual #186                // Method io/netty/buffer/ByteBuf.writeBytes:(Lio/netty/buffer/ByteBuf;)Lio/netty/buffer/ByteBuf;
     230: pop
     231: aload_0
     232: aload_1
     233: aload_0
     234: getfield      #50                 // Field buffer:Lio/netty/buffer/ByteBuf;
     237: invokevirtual #187                // Method decode:(Lio/netty/channel/ChannelHandlerContext;Lio/netty/buffer/ByteBuf;)V
     240: aload_3
     241: invokevirtual #55                 // Method io/netty/buffer/ByteBuf.release:()Z
     244: pop
     245: goto          258
     248: astore        4
     250: aload_3
     251: invokevirtual #55                 // Method io/netty/buffer/ByteBuf.release:()Z
     254: pop
     255: aload         4
     257: athrow
     258: return
    Exception table:
       from    to  target type
         114   139   248   any
         145   185   248   any
         191   240   248   any
         248   250   248   any

  protected void decode(io.netty.channel.ChannelHandlerContext, io.netty.buffer.ByteBuf) throws java.lang.InterruptedException;
    Code:
       0: aload_0
       1: getfield      #93                 // Field pristine:Z
       4: ifeq          61
       7: aload_0
       8: getfield      #4                  // Field stack:Ljava/util/Deque;
      11: invokeinterface #68,  1           // InterfaceMethod java/util/Deque.isEmpty:()Z
      16: ifeq          61
      19: aload_2
      20: invokevirtual #170                // Method io/netty/buffer/ByteBuf.isReadable:()Z
      23: ifeq          61
      26: aload_0
      27: getfield      #15                 // Field debugEnabled:Z
      30: ifeq          47
      33: getstatic     #11                 // Field logger:Lio/netty/util/internal/logging/InternalLogger;
      36: ldc           #188                // String {} Received response without a command context (empty stack)
      38: aload_0
      39: invokespecial #39                 // Method logPrefix:()Ljava/lang/String;
      42: invokeinterface #40,  3           // InterfaceMethod io/netty/util/internal/logging/InternalLogger.debug:(Ljava/lang/String;Ljava/lang/Object;)V
      47: aload_0
      48: aload_2
      49: invokespecial #189                // Method consumeResponse:(Lio/netty/buffer/ByteBuf;)Z
      52: ifeq          60
      55: aload_0
      56: iconst_0
      57: putfield      #93                 // Field pristine:Z
      60: return
      61: aload_0
      62: aload_2
      63: invokevirtual #190                // Method canDecode:(Lio/netty/buffer/ByteBuf;)Z
      66: ifeq          246
      69: aload_0
      70: getfield      #4                  // Field stack:Ljava/util/Deque;
      73: invokeinterface #191,  1          // InterfaceMethod java/util/Deque.peek:()Ljava/lang/Object;
      78: checkcast     #70                 // class io/lettuce/core/protocol/RedisCommand
      81: astore_3
      82: aload_0
      83: getfield      #15                 // Field debugEnabled:Z
      86: ifeq          115
      89: getstatic     #11                 // Field logger:Lio/netty/util/internal/logging/InternalLogger;
      92: ldc           #192                // String {} Stack contains: {} commands
      94: aload_0
      95: invokespecial #39                 // Method logPrefix:()Ljava/lang/String;
      98: aload_0
      99: getfield      #4                  // Field stack:Ljava/util/Deque;
     102: invokeinterface #154,  1          // InterfaceMethod java/util/Deque.size:()I
     107: invokestatic  #174                // Method java/lang/Integer.valueOf:(I)Ljava/lang/Integer;
     110: invokeinterface #72,  4           // InterfaceMethod io/netty/util/internal/logging/InternalLogger.debug:(Ljava/lang/String;Ljava/lang/Object;Ljava/lang/Object;)V
     115: aload_0
     116: iconst_0
     117: putfield      #93                 // Field pristine:Z
     120: aload_0
     121: aload_1
     122: aload_2
     123: aload_3
     124: invokespecial #193                // Method decode:(Lio/netty/channel/ChannelHandlerContext;Lio/netty/buffer/ByteBuf;Lio/lettuce/core/protocol/RedisCommand;)Z
     127: ifne          131
     130: return
     131: goto          146
     134: astore        4
     136: aload_1
     137: invokeinterface #194,  1          // InterfaceMethod io/netty/channel/ChannelHandlerContext.close:()Lio/netty/channel/ChannelFuture;
     142: pop
     143: aload         4
     145: athrow
     146: aload_0
     147: aload_3
     148: invokespecial #116                // Method isProtectedMode:(Lio/lettuce/core/protocol/RedisCommand;)Z
     151: ifeq          170
     154: aload_0
     155: aload_3
     156: invokeinterface #137,  1          // InterfaceMethod io/lettuce/core/protocol/RedisCommand.getOutput:()Lio/lettuce/core/output/CommandOutput;
     161: invokevirtual #118                // Method io/lettuce/core/output/CommandOutput.getError:()Ljava/lang/String;
     164: invokespecial #119                // Method onProtectedMode:(Ljava/lang/String;)V
     167: goto          225
     170: aload_0
     171: getfield      #4                  // Field stack:Ljava/util/Deque;
     174: invokeinterface #69,  1           // InterfaceMethod java/util/Deque.poll:()Ljava/lang/Object;
     179: pop
     180: aload_3
     181: invokeinterface #138,  1          // InterfaceMethod io/lettuce/core/protocol/RedisCommand.complete:()V
     186: goto          225
     189: astore        4
     191: getstatic     #11                 // Field logger:Lio/netty/util/internal/logging/InternalLogger;
     194: ldc           #90                 // String {} Unexpected exception during request: {}
     196: iconst_3
     197: anewarray     #77                 // class java/lang/Object
     200: dup
     201: iconst_0
     202: aload_0
     203: getfield      #43                 // Field logPrefix:Ljava/lang/String;
     206: aastore
     207: dup
     208: iconst_1
     209: aload         4
     211: invokevirtual #78                 // Method java/lang/Exception.toString:()Ljava/lang/String;
     214: aastore
     215: dup
     216: iconst_2
     217: aload         4
     219: aastore
     220: invokeinterface #79,  3           // InterfaceMethod io/netty/util/internal/logging/InternalLogger.warn:(Ljava/lang/String;[Ljava/lang/Object;)V
     225: aload_2
     226: invokevirtual #171                // Method io/netty/buffer/ByteBuf.refCnt:()I
     229: ifeq          237
     232: aload_2
     233: invokevirtual #195                // Method io/netty/buffer/ByteBuf.discardReadBytes:()Lio/netty/buffer/ByteBuf;
     236: pop
     237: aload_0
     238: aload_1
     239: aload_3
     240: invokevirtual #196                // Method afterComplete:(Lio/netty/channel/ChannelHandlerContext;Lio/lettuce/core/protocol/RedisCommand;)V
     243: goto          61
     246: return
    Exception table:
       from    to  target type
         120   130   134   Class java/lang/Exception
         180   186   189   Class java/lang/Exception

  protected boolean canDecode(io.netty.buffer.ByteBuf);
    Code:
       0: aload_0
       1: getfield      #4                  // Field stack:Ljava/util/Deque;
       4: invokeinterface #68,  1           // InterfaceMethod java/util/Deque.isEmpty:()Z
       9: ifne          23
      12: aload_1
      13: invokevirtual #170                // Method io/netty/buffer/ByteBuf.isReadable:()Z
      16: ifeq          23
      19: iconst_1
      20: goto          24
      23: iconst_0
      24: ireturn

  private boolean decode(io.netty.channel.ChannelHandlerContext, io.netty.buffer.ByteBuf, io.lettuce.core.protocol.RedisCommand<?, ?, ?>);
    Code:
       0: aload_0
       1: getfield      #30                 // Field latencyMetricsEnabled:Z
       4: ifeq          70
       7: aload_3
       8: instanceof    #159                // class io/lettuce/core/protocol/WithLatency
      11: ifeq          70
      14: aload_3
      15: checkcast     #159                // class io/lettuce/core/protocol/WithLatency
      18: astore        4
      20: aload         4
      22: invokeinterface #197,  1          // InterfaceMethod io/lettuce/core/protocol/WithLatency.getFirstResponse:()J
      27: ldc2_w        #160                // long -1l
      30: lcmp
      31: ifne          44
      34: aload         4
      36: invokestatic  #163                // Method nanoTime:()J
      39: invokeinterface #162,  3          // InterfaceMethod io/lettuce/core/protocol/WithLatency.firstResponse:(J)V
      44: aload_0
      45: aload_1
      46: aload_2
      47: aload_3
      48: invokespecial #198                // Method decode0:(Lio/netty/channel/ChannelHandlerContext;Lio/netty/buffer/ByteBuf;Lio/lettuce/core/protocol/RedisCommand;)Z
      51: ifne          56
      54: iconst_0
      55: ireturn
      56: aload_0
      57: aload         4
      59: aload_3
      60: invokeinterface #199,  1          // InterfaceMethod io/lettuce/core/protocol/RedisCommand.getType:()Lio/lettuce/core/protocol/ProtocolKeyword;
      65: invokespecial #200                // Method recordLatency:(Lio/lettuce/core/protocol/WithLatency;Lio/lettuce/core/protocol/ProtocolKeyword;)V
      68: iconst_1
      69: ireturn
      70: aload_0
      71: aload_1
      72: aload_2
      73: aload_3
      74: invokespecial #198                // Method decode0:(Lio/netty/channel/ChannelHandlerContext;Lio/netty/buffer/ByteBuf;Lio/lettuce/core/protocol/RedisCommand;)Z
      77: ireturn

  private boolean decode0(io.netty.channel.ChannelHandlerContext, io.netty.buffer.ByteBuf, io.lettuce.core.protocol.RedisCommand<?, ?, ?>);
    Code:
       0: aload_0
       1: aload_2
       2: aload_3
       3: aload_3
       4: invokeinterface #137,  1          // InterfaceMethod io/lettuce/core/protocol/RedisCommand.getOutput:()Lio/lettuce/core/output/CommandOutput;
       9: invokevirtual #201                // Method decode:(Lio/netty/buffer/ByteBuf;Lio/lettuce/core/protocol/RedisCommand;Lio/lettuce/core/output/CommandOutput;)Z
      12: ifne          65
      15: aload_3
      16: instanceof    #202                // class io/lettuce/core/protocol/DemandAware$Sink
      19: ifeq          63
      22: aload_3
      23: checkcast     #202                // class io/lettuce/core/protocol/DemandAware$Sink
      26: astore        4
      28: aload         4
      30: aload_0
      31: getfield      #18                 // Field backpressureSource:Lio/lettuce/core/protocol/CommandHandler$BackpressureSource;
      34: invokeinterface #203,  2          // InterfaceMethod io/lettuce/core/protocol/DemandAware$Sink.setSource:(Lio/lettuce/core/protocol/DemandAware$Source;)V
      39: aload_1
      40: invokeinterface #41,  1           // InterfaceMethod io/netty/channel/ChannelHandlerContext.channel:()Lio/netty/channel/Channel;
      45: invokeinterface #59,  1           // InterfaceMethod io/netty/channel/Channel.config:()Lio/netty/channel/ChannelConfig;
      50: aload         4
      52: invokeinterface #204,  1          // InterfaceMethod io/lettuce/core/protocol/DemandAware$Sink.hasDemand:()Z
      57: invokeinterface #60,  2           // InterfaceMethod io/netty/channel/ChannelConfig.setAutoRead:(Z)Lio/netty/channel/ChannelConfig;
      62: pop
      63: iconst_0
      64: ireturn
      65: aload_1
      66: invokeinterface #41,  1           // InterfaceMethod io/netty/channel/ChannelHandlerContext.channel:()Lio/netty/channel/Channel;
      71: invokeinterface #59,  1           // InterfaceMethod io/netty/channel/Channel.config:()Lio/netty/channel/ChannelConfig;
      76: invokeinterface #205,  1          // InterfaceMethod io/netty/channel/ChannelConfig.isAutoRead:()Z
      81: ifne          102
      84: aload_1
      85: invokeinterface #41,  1           // InterfaceMethod io/netty/channel/ChannelHandlerContext.channel:()Lio/netty/channel/Channel;
      90: invokeinterface #59,  1           // InterfaceMethod io/netty/channel/Channel.config:()Lio/netty/channel/ChannelConfig;
      95: iconst_1
      96: invokeinterface #60,  2           // InterfaceMethod io/netty/channel/ChannelConfig.setAutoRead:(Z)Lio/netty/channel/ChannelConfig;
     101: pop
     102: iconst_1
     103: ireturn

  protected boolean decode(io.netty.buffer.ByteBuf, io.lettuce.core.output.CommandOutput<?, ?, ?>);
    Code:
       0: aload_0
       1: getfield      #10                 // Field rsm:Lio/lettuce/core/protocol/RedisStateMachine;
       4: aload_1
       5: aload_2
       6: invokevirtual #206                // Method io/lettuce/core/protocol/RedisStateMachine.decode:(Lio/netty/buffer/ByteBuf;Lio/lettuce/core/output/CommandOutput;)Z
       9: ireturn

  protected boolean decode(io.netty.buffer.ByteBuf, io.lettuce.core.protocol.RedisCommand<?, ?, ?>, io.lettuce.core.output.CommandOutput<?, ?, ?>);
    Code:
       0: aload_0
       1: getfield      #10                 // Field rsm:Lio/lettuce/core/protocol/RedisStateMachine;
       4: aload_1
       5: aload_2
       6: aload_3
       7: invokevirtual #207                // Method io/lettuce/core/protocol/RedisStateMachine.decode:(Lio/netty/buffer/ByteBuf;Lio/lettuce/core/protocol/RedisCommand;Lio/lettuce/core/output/CommandOutput;)Z
      10: ireturn

  private boolean consumeResponse(io.netty.buffer.ByteBuf);
    Code:
       0: aload_0
       1: getfield      #94                 // Field fallbackCommand:Lio/lettuce/core/protocol/PristineFallbackCommand;
       4: astore_2
       5: aload_2
       6: ifnull        16
       9: aload_2
      10: invokevirtual #208                // Method io/lettuce/core/protocol/PristineFallbackCommand.isDone:()Z
      13: ifne          87
      16: aload_0
      17: getfield      #15                 // Field debugEnabled:Z
      20: ifeq          37
      23: getstatic     #11                 // Field logger:Lio/netty/util/internal/logging/InternalLogger;
      26: ldc           #209                // String {} Consuming response using FallbackCommand
      28: aload_0
      29: invokespecial #39                 // Method logPrefix:()Ljava/lang/String;
      32: invokeinterface #40,  3           // InterfaceMethod io/netty/util/internal/logging/InternalLogger.debug:(Ljava/lang/String;Ljava/lang/Object;)V
      37: aload_2
      38: ifnonnull     54
      41: new           #210                // class io/lettuce/core/protocol/PristineFallbackCommand
      44: dup
      45: invokespecial #211                // Method io/lettuce/core/protocol/PristineFallbackCommand."<init>":()V
      48: astore_2
      49: aload_0
      50: aload_2
      51: putfield      #94                 // Field fallbackCommand:Lio/lettuce/core/protocol/PristineFallbackCommand;
      54: aload_0
      55: aload_1
      56: aload_2
      57: invokevirtual #117                // Method io/lettuce/core/protocol/PristineFallbackCommand.getOutput:()Lio/lettuce/core/output/CommandOutput;
      60: invokevirtual #212                // Method decode:(Lio/netty/buffer/ByteBuf;Lio/lettuce/core/output/CommandOutput;)Z
      63: ifne          68
      66: iconst_0
      67: ireturn
      68: aload_0
      69: aload_2
      70: invokespecial #116                // Method isProtectedMode:(Lio/lettuce/core/protocol/RedisCommand;)Z
      73: ifeq          87
      76: aload_0
      77: aload_2
      78: invokevirtual #117                // Method io/lettuce/core/protocol/PristineFallbackCommand.getOutput:()Lio/lettuce/core/output/CommandOutput;
      81: invokevirtual #118                // Method io/lettuce/core/output/CommandOutput.getError:()Ljava/lang/String;
      84: invokespecial #119                // Method onProtectedMode:(Ljava/lang/String;)V
      87: iconst_1
      88: ireturn

  private boolean isProtectedMode(io.lettuce.core.protocol.RedisCommand<?, ?, ?>);
    Code:
       0: aload_1
       1: ifnull        44
       4: aload_1
       5: invokeinterface #137,  1          // InterfaceMethod io/lettuce/core/protocol/RedisCommand.getOutput:()Lio/lettuce/core/output/CommandOutput;
      10: ifnull        44
      13: aload_1
      14: invokeinterface #137,  1          // InterfaceMethod io/lettuce/core/protocol/RedisCommand.getOutput:()Lio/lettuce/core/output/CommandOutput;
      19: invokevirtual #213                // Method io/lettuce/core/output/CommandOutput.hasError:()Z
      22: ifeq          44
      25: aload_1
      26: invokeinterface #137,  1          // InterfaceMethod io/lettuce/core/protocol/RedisCommand.getOutput:()Lio/lettuce/core/output/CommandOutput;
      31: invokevirtual #118                // Method io/lettuce/core/output/CommandOutput.getError:()Ljava/lang/String;
      34: invokestatic  #214                // Method io/lettuce/core/RedisConnectionException.isProtectedMode:(Ljava/lang/String;)Z
      37: ifeq          44
      40: iconst_1
      41: goto          45
      44: iconst_0
      45: ireturn

  private void onProtectedMode(java.lang.String);
    Code:
       0: new           #215                // class io/lettuce/core/RedisConnectionException
       3: dup
       4: aload_1
       5: invokespecial #216                // Method io/lettuce/core/RedisConnectionException."<init>":(Ljava/lang/String;)V
       8: astore_2
       9: aload_0
      10: getfield      #27                 // Field endpoint:Lio/lettuce/core/protocol/Endpoint;
      13: aload_2
      14: invokeinterface #83,  2           // InterfaceMethod io/lettuce/core/protocol/Endpoint.notifyException:(Ljava/lang/Throwable;)V
      19: aload_0
      20: getfield      #42                 // Field channel:Lio/netty/channel/Channel;
      23: ifnull        36
      26: aload_0
      27: getfield      #42                 // Field channel:Lio/netty/channel/Channel;
      30: invokeinterface #217,  1          // InterfaceMethod io/netty/channel/Channel.disconnect:()Lio/netty/channel/ChannelFuture;
      35: pop
      36: aload_0
      37: getfield      #4                  // Field stack:Ljava/util/Deque;
      40: aload_2
      41: invokedynamic #218,  0            // InvokeDynamic #2:accept:(Lio/lettuce/core/RedisConnectionException;)Ljava/util/function/Consumer;
      46: invokeinterface #219,  2          // InterfaceMethod java/util/Deque.forEach:(Ljava/util/function/Consumer;)V
      51: aload_0
      52: getfield      #4                  // Field stack:Ljava/util/Deque;
      55: invokeinterface #220,  1          // InterfaceMethod java/util/Deque.clear:()V
      60: return

  protected void afterComplete(io.netty.channel.ChannelHandlerContext, io.lettuce.core.protocol.RedisCommand<?, ?, ?>);
    Code:
       0: return

  private void recordLatency(io.lettuce.core.protocol.WithLatency, io.lettuce.core.protocol.ProtocolKeyword);
    Code:
       0: aload_1
       1: ifnull        87
       4: aload_0
       5: getfield      #26                 // Field clientResources:Lio/lettuce/core/resource/ClientResources;
       8: invokeinterface #28,  1           // InterfaceMethod io/lettuce/core/resource/ClientResources.commandLatencyCollector:()Lio/lettuce/core/metrics/CommandLatencyCollector;
      13: invokeinterface #29,  1           // InterfaceMethod io/lettuce/core/metrics/CommandLatencyCollector.isEnabled:()Z
      18: ifeq          87
      21: aload_0
      22: getfield      #42                 // Field channel:Lio/netty/channel/Channel;
      25: ifnull        87
      28: aload_0
      29: invokespecial #221                // Method remote:()Ljava/net/SocketAddress;
      32: ifnull        87
      35: aload_1
      36: invokeinterface #222,  1          // InterfaceMethod io/lettuce/core/protocol/WithLatency.getSent:()J
      41: aload_1
      42: invokeinterface #197,  1          // InterfaceMethod io/lettuce/core/protocol/WithLatency.getFirstResponse:()J
      47: lsub
      48: lstore_3
      49: invokestatic  #163                // Method nanoTime:()J
      52: aload_1
      53: invokeinterface #222,  1          // InterfaceMethod io/lettuce/core/protocol/WithLatency.getSent:()J
      58: lsub
      59: lstore        5
      61: aload_0
      62: getfield      #26                 // Field clientResources:Lio/lettuce/core/resource/ClientResources;
      65: invokeinterface #28,  1           // InterfaceMethod io/lettuce/core/resource/ClientResources.commandLatencyCollector:()Lio/lettuce/core/metrics/CommandLatencyCollector;
      70: aload_0
      71: invokespecial #223                // Method local:()Ljava/net/SocketAddress;
      74: aload_0
      75: invokespecial #221                // Method remote:()Ljava/net/SocketAddress;
      78: aload_2
      79: lload_3
      80: lload         5
      82: invokeinterface #224,  8          // InterfaceMethod io/lettuce/core/metrics/CommandLatencyCollector.recordCommandLatency:(Ljava/net/SocketAddress;Ljava/net/SocketAddress;Lio/lettuce/core/protocol/ProtocolKeyword;JJ)V
      87: return

  private java.net.SocketAddress remote();
    Code:
       0: aload_0
       1: getfield      #42                 // Field channel:Lio/netty/channel/Channel;
       4: invokeinterface #225,  1          // InterfaceMethod io/netty/channel/Channel.remoteAddress:()Ljava/net/SocketAddress;
       9: areturn

  private java.net.SocketAddress local();
    Code:
       0: aload_0
       1: getfield      #42                 // Field channel:Lio/netty/channel/Channel;
       4: invokeinterface #226,  1          // InterfaceMethod io/netty/channel/Channel.localAddress:()Ljava/net/SocketAddress;
       9: ifnull        22
      12: aload_0
      13: getfield      #42                 // Field channel:Lio/netty/channel/Channel;
      16: invokeinterface #226,  1          // InterfaceMethod io/netty/channel/Channel.localAddress:()Ljava/net/SocketAddress;
      21: areturn
      22: getstatic     #227                // Field io/netty/channel/local/LocalAddress.ANY:Lio/netty/channel/local/LocalAddress;
      25: areturn

  boolean isConnected();
    Code:
       0: aload_0
       1: getfield      #20                 // Field lifecycleState:Lio/lettuce/core/protocol/CommandHandler$LifecycleState;
       4: invokevirtual #228                // Method io/lettuce/core/protocol/CommandHandler$LifecycleState.ordinal:()I
       7: getstatic     #96                 // Field io/lettuce/core/protocol/CommandHandler$LifecycleState.CONNECTED:Lio/lettuce/core/protocol/CommandHandler$LifecycleState;
      10: invokevirtual #228                // Method io/lettuce/core/protocol/CommandHandler$LifecycleState.ordinal:()I
      13: if_icmplt     36
      16: aload_0
      17: getfield      #20                 // Field lifecycleState:Lio/lettuce/core/protocol/CommandHandler$LifecycleState;
      20: invokevirtual #228                // Method io/lettuce/core/protocol/CommandHandler$LifecycleState.ordinal:()I
      23: getstatic     #111                // Field io/lettuce/core/protocol/CommandHandler$LifecycleState.DISCONNECTED:Lio/lettuce/core/protocol/CommandHandler$LifecycleState;
      26: invokevirtual #228                // Method io/lettuce/core/protocol/CommandHandler$LifecycleState.ordinal:()I
      29: if_icmpge     36
      32: iconst_1
      33: goto          37
      36: iconst_0
      37: ireturn

  private void reset();
    Code:
       0: aload_0
       1: invokespecial #229                // Method resetInternals:()V
       4: ldc           #230                // String Reset
       6: aload_0
       7: getfield      #4                  // Field stack:Ljava/util/Deque;
      10: invokestatic  #36                 // Method drainCommands:(Ljava/util/Queue;)Ljava/util/List;
      13: invokestatic  #231                // Method cancelCommands:(Ljava/lang/String;Ljava/util/List;)V
      16: return

  private void resetInternals();
    Code:
       0: aload_0
       1: getfield      #10                 // Field rsm:Lio/lettuce/core/protocol/RedisStateMachine;
       4: invokevirtual #120                // Method io/lettuce/core/protocol/RedisStateMachine.reset:()V
       7: aload_0
       8: getfield      #50                 // Field buffer:Lio/netty/buffer/ByteBuf;
      11: invokevirtual #171                // Method io/netty/buffer/ByteBuf.refCnt:()I
      14: ifle          25
      17: aload_0
      18: getfield      #50                 // Field buffer:Lio/netty/buffer/ByteBuf;
      21: invokevirtual #232                // Method io/netty/buffer/ByteBuf.clear:()Lio/netty/buffer/ByteBuf;
      24: pop
      25: return

  private static void cancelCommands(java.lang.String, java.util.List<io.lettuce.core.protocol.RedisCommand<?, ?, ?>>);
    Code:
       0: aload_1
       1: invokeinterface #233,  1          // InterfaceMethod java/util/List.iterator:()Ljava/util/Iterator;
       6: astore_2
       7: aload_2
       8: invokeinterface #130,  1          // InterfaceMethod java/util/Iterator.hasNext:()Z
      13: ifeq          54
      16: aload_2
      17: invokeinterface #131,  1          // InterfaceMethod java/util/Iterator.next:()Ljava/lang/Object;
      22: checkcast     #70                 // class io/lettuce/core/protocol/RedisCommand
      25: astore_3
      26: aload_3
      27: invokeinterface #137,  1          // InterfaceMethod io/lettuce/core/protocol/RedisCommand.getOutput:()Lio/lettuce/core/output/CommandOutput;
      32: ifnull        45
      35: aload_3
      36: invokeinterface #137,  1          // InterfaceMethod io/lettuce/core/protocol/RedisCommand.getOutput:()Lio/lettuce/core/output/CommandOutput;
      41: aload_0
      42: invokevirtual #234                // Method io/lettuce/core/output/CommandOutput.setError:(Ljava/lang/String;)V
      45: aload_3
      46: invokeinterface #235,  1          // InterfaceMethod io/lettuce/core/protocol/RedisCommand.cancel:()V
      51: goto          7
      54: return

  private java.lang.String logPrefix();
    Code:
       0: aload_0
       1: getfield      #43                 // Field logPrefix:Ljava/lang/String;
       4: ifnull        12
       7: aload_0
       8: getfield      #43                 // Field logPrefix:Ljava/lang/String;
      11: areturn
      12: new           #141                // class java/lang/StringBuilder
      15: dup
      16: invokespecial #142                // Method java/lang/StringBuilder."<init>":()V
      19: ldc           #236                // String [
      21: invokevirtual #144                // Method java/lang/StringBuilder.append:(Ljava/lang/String;)Ljava/lang/StringBuilder;
      24: aload_0
      25: getfield      #42                 // Field channel:Lio/netty/channel/Channel;
      28: invokestatic  #237                // Method io/lettuce/core/protocol/ChannelLogDescriptor.logDescriptor:(Lio/netty/channel/Channel;)Ljava/lang/String;
      31: invokevirtual #144                // Method java/lang/StringBuilder.append:(Ljava/lang/String;)Ljava/lang/StringBuilder;
      34: ldc           #238                // String , chid=0x
      36: invokevirtual #144                // Method java/lang/StringBuilder.append:(Ljava/lang/String;)Ljava/lang/StringBuilder;
      39: aload_0
      40: getfield      #7                  // Field commandHandlerId:J
      43: invokestatic  #239                // Method java/lang/Long.toHexString:(J)Ljava/lang/String;
      46: invokevirtual #144                // Method java/lang/StringBuilder.append:(Ljava/lang/String;)Ljava/lang/StringBuilder;
      49: bipush        93
      51: invokevirtual #240                // Method java/lang/StringBuilder.append:(C)Ljava/lang/StringBuilder;
      54: invokevirtual #146                // Method java/lang/StringBuilder.toString:()Ljava/lang/String;
      57: astore_1
      58: aload_0
      59: aload_1
      60: dup_x1
      61: putfield      #43                 // Field logPrefix:Ljava/lang/String;
      64: areturn

  private static long nanoTime();
    Code:
       0: invokestatic  #241                // Method java/lang/System.nanoTime:()J
       3: lreturn

  private static void lambda$onProtectedMode$2(io.lettuce.core.RedisConnectionException, io.lettuce.core.protocol.RedisCommand);
    Code:
       0: aload_1
       1: aload_0
       2: invokeinterface #74,  2           // InterfaceMethod io/lettuce/core/protocol/RedisCommand.completeExceptionally:(Ljava/lang/Throwable;)Z
       7: pop
       8: return

  private void lambda$addToStack$1(io.lettuce.core.protocol.RedisCommand, io.netty.util.concurrent.Future) throws java.lang.Exception;
    Code:
       0: aload_2
       1: invokeinterface #242,  1          // InterfaceMethod io/netty/util/concurrent/Future.isSuccess:()Z
       6: ifeq          20
       9: aload_0
      10: getfield      #4                  // Field stack:Ljava/util/Deque;
      13: aload_1
      14: invokeinterface #150,  2          // InterfaceMethod java/util/Deque.add:(Ljava/lang/Object;)Z
      19: pop
      20: return

  private void lambda$channelActive$0();
    Code:
       0: aload_0
       1: getfield      #42                 // Field channel:Lio/netty/channel/Channel;
       4: invokeinterface #243,  1          // InterfaceMethod io/netty/channel/Channel.pipeline:()Lio/netty/channel/ChannelPipeline;
       9: new           #244                // class io/lettuce/core/ConnectionEvents$Activated
      12: dup
      13: invokespecial #245                // Method io/lettuce/core/ConnectionEvents$Activated."<init>":()V
      16: invokeinterface #246,  2          // InterfaceMethod io/netty/channel/ChannelPipeline.fireUserEventTriggered:(Ljava/lang/Object;)Lio/netty/channel/ChannelPipeline;
      21: pop
      22: return

  static {};
    Code:
       0: iconst_3
       1: anewarray     #247                // class java/lang/String
       4: dup
       5: iconst_0
       6: ldc           #248                // String Connection reset by peer
       8: aastore
       9: dup
      10: iconst_1
      11: ldc           #249                // String Broken pipe
      13: aastore
      14: dup
      15: iconst_2
      16: ldc           #250                // String Connection timed out
      18: aastore
      19: invokestatic  #251                // Method io/lettuce/core/internal/LettuceSets.unmodifiableSet:([Ljava/lang/Object;)Ljava/util/Set;
      22: putstatic     #87                 // Field SUPPRESS_IO_EXCEPTION_MESSAGES:Ljava/util/Set;
      25: ldc           #252                // class io/lettuce/core/protocol/CommandHandler
      27: invokestatic  #253                // Method io/netty/util/internal/logging/InternalLoggerFactory.getInstance:(Ljava/lang/Class;)Lio/netty/util/internal/logging/InternalLogger;
      30: putstatic     #11                 // Field logger:Lio/netty/util/internal/logging/InternalLogger;
      33: new           #254                // class java/util/concurrent/atomic/AtomicLong
      36: dup
      37: invokespecial #255                // Method java/util/concurrent/atomic/AtomicLong."<init>":()V
      40: putstatic     #5                  // Field COMMAND_HANDLER_COUNTER:Ljava/util/concurrent/atomic/AtomicLong;
      43: return
}
