Compiled from "CommandArgs.java"
class io.lettuce.core.protocol.CommandArgs$IntegerCache {
  static final io.lettuce.core.protocol.CommandArgs$IntegerArgument[] cache;

  static final io.lettuce.core.protocol.CommandArgs$IntegerArgument[] negativeCache;

  io.lettuce.core.protocol.CommandArgs$IntegerCache();
    Code:
       0: aload_0
       1: invokespecial #1                  // Method java/lang/Object."<init>":()V
       4: return

  static {};
    Code:
       0: ldc           #2                  // String io.lettuce.core.CommandArgs.IntegerCache
       2: sipush        128
       5: invokestatic  #3                  // Method java/lang/Integer.getInteger:(Ljava/lang/String;I)Ljava/lang/Integer;
       8: invokevirtual #4                  // Method java/lang/Integer.intValue:()I
      11: istore_0
      12: iload_0
      13: anewarray     #5                  // class io/lettuce/core/protocol/CommandArgs$IntegerArgument
      16: putstatic     #6                  // Field cache:[Lio/lettuce/core/protocol/CommandArgs$IntegerArgument;
      19: iload_0
      20: anewarray     #5                  // class io/lettuce/core/protocol/CommandArgs$IntegerArgument
      23: putstatic     #7                  // Field negativeCache:[Lio/lettuce/core/protocol/CommandArgs$IntegerArgument;
      26: iconst_0
      27: istore_1
      28: iload_1
      29: iload_0
      30: if_icmpge     70
      33: getstatic     #6                  // Field cache:[Lio/lettuce/core/protocol/CommandArgs$IntegerArgument;
      36: iload_1
      37: new           #5                  // class io/lettuce/core/protocol/CommandArgs$IntegerArgument
      40: dup
      41: iload_1
      42: i2l
      43: aconst_null
      44: invokespecial #8                  // Method io/lettuce/core/protocol/CommandArgs$IntegerArgument."<init>":(JLio/lettuce/core/protocol/CommandArgs$1;)V
      47: aastore
      48: getstatic     #7                  // Field negativeCache:[Lio/lettuce/core/protocol/CommandArgs$IntegerArgument;
      51: iload_1
      52: new           #5                  // class io/lettuce/core/protocol/CommandArgs$IntegerArgument
      55: dup
      56: iload_1
      57: ineg
      58: i2l
      59: aconst_null
      60: invokespecial #8                  // Method io/lettuce/core/protocol/CommandArgs$IntegerArgument."<init>":(JLio/lettuce/core/protocol/CommandArgs$1;)V
      63: aastore
      64: iinc          1, 1
      67: goto          28
      70: return
}
