Compiled from "AckedDelivery.scala"
public final class akka.remote.AckedSendBuffer<T extends akka.remote.HasSequenceNumber> implements scala.Product, scala.Serializable {
  private final int capacity;

  private final scala.collection.immutable.IndexedSeq<T> nonAcked;

  private final scala.collection.immutable.IndexedSeq<T> nacked;

  private final akka.remote.SeqNo maxSeq;

  public static <T extends akka.remote.HasSequenceNumber> akka.remote.SeqNo apply$default$4();
    Code:
       0: getstatic     #21                 // Field akka/remote/AckedSendBuffer$.MODULE$:Lakka/remote/AckedSendBuffer$;
       3: invokevirtual #23                 // Method akka/remote/AckedSendBuffer$.apply$default$4:()Lakka/remote/SeqNo;
       6: areturn

  public static <T extends akka.remote.HasSequenceNumber> scala.collection.immutable.Vector<T> apply$default$3();
    Code:
       0: getstatic     #21                 // Field akka/remote/AckedSendBuffer$.MODULE$:Lakka/remote/AckedSendBuffer$;
       3: invokevirtual #27                 // Method akka/remote/AckedSendBuffer$.apply$default$3:()Lscala/collection/immutable/Vector;
       6: areturn

  public static <T extends akka.remote.HasSequenceNumber> scala.collection.immutable.Vector<T> apply$default$2();
    Code:
       0: getstatic     #21                 // Field akka/remote/AckedSendBuffer$.MODULE$:Lakka/remote/AckedSendBuffer$;
       3: invokevirtual #30                 // Method akka/remote/AckedSendBuffer$.apply$default$2:()Lscala/collection/immutable/Vector;
       6: areturn

  public static <T extends akka.remote.HasSequenceNumber> akka.remote.SeqNo $lessinit$greater$default$4();
    Code:
       0: getstatic     #21                 // Field akka/remote/AckedSendBuffer$.MODULE$:Lakka/remote/AckedSendBuffer$;
       3: invokevirtual #33                 // Method akka/remote/AckedSendBuffer$.$lessinit$greater$default$4:()Lakka/remote/SeqNo;
       6: areturn

  public static <T extends akka.remote.HasSequenceNumber> scala.collection.immutable.Vector<T> $lessinit$greater$default$3();
    Code:
       0: getstatic     #21                 // Field akka/remote/AckedSendBuffer$.MODULE$:Lakka/remote/AckedSendBuffer$;
       3: invokevirtual #36                 // Method akka/remote/AckedSendBuffer$.$lessinit$greater$default$3:()Lscala/collection/immutable/Vector;
       6: areturn

  public static <T extends akka.remote.HasSequenceNumber> scala.collection.immutable.Vector<T> $lessinit$greater$default$2();
    Code:
       0: getstatic     #21                 // Field akka/remote/AckedSendBuffer$.MODULE$:Lakka/remote/AckedSendBuffer$;
       3: invokevirtual #39                 // Method akka/remote/AckedSendBuffer$.$lessinit$greater$default$2:()Lscala/collection/immutable/Vector;
       6: areturn

  public static <T extends akka.remote.HasSequenceNumber> scala.Option<scala.Tuple4<java.lang.Object, scala.collection.immutable.IndexedSeq<T>, scala.collection.immutable.IndexedSeq<T>, akka.remote.SeqNo>> unapply(akka.remote.AckedSendBuffer<T>);
    Code:
       0: getstatic     #21                 // Field akka/remote/AckedSendBuffer$.MODULE$:Lakka/remote/AckedSendBuffer$;
       3: aload_0
       4: invokevirtual #43                 // Method akka/remote/AckedSendBuffer$.unapply:(Lakka/remote/AckedSendBuffer;)Lscala/Option;
       7: areturn

  public static <T extends akka.remote.HasSequenceNumber> akka.remote.AckedSendBuffer<T> apply(int, scala.collection.immutable.IndexedSeq<T>, scala.collection.immutable.IndexedSeq<T>, akka.remote.SeqNo);
    Code:
       0: getstatic     #21                 // Field akka/remote/AckedSendBuffer$.MODULE$:Lakka/remote/AckedSendBuffer$;
       3: iload_0
       4: aload_1
       5: aload_2
       6: aload_3
       7: invokevirtual #47                 // Method akka/remote/AckedSendBuffer$.apply:(ILscala/collection/immutable/IndexedSeq;Lscala/collection/immutable/IndexedSeq;Lakka/remote/SeqNo;)Lakka/remote/AckedSendBuffer;
      10: areturn

  public int capacity();
    Code:
       0: aload_0
       1: getfield      #58                 // Field capacity:I
       4: ireturn

  public scala.collection.immutable.IndexedSeq<T> nonAcked();
    Code:
       0: aload_0
       1: getfield      #63                 // Field nonAcked:Lscala/collection/immutable/IndexedSeq;
       4: areturn

  public scala.collection.immutable.IndexedSeq<T> nacked();
    Code:
       0: aload_0
       1: getfield      #65                 // Field nacked:Lscala/collection/immutable/IndexedSeq;
       4: areturn

  public akka.remote.SeqNo maxSeq();
    Code:
       0: aload_0
       1: getfield      #67                 // Field maxSeq:Lakka/remote/SeqNo;
       4: areturn

  public akka.remote.AckedSendBuffer<T> acknowledge(akka.remote.Ack);
    Code:
       0: aload_1
       1: invokevirtual #74                 // Method akka/remote/Ack.cumulativeAck:()Lakka/remote/SeqNo;
       4: aload_0
       5: invokevirtual #76                 // Method maxSeq:()Lakka/remote/SeqNo;
       8: invokevirtual #82                 // Method akka/remote/SeqNo.$greater:(Ljava/lang/Object;)Z
      11: ifeq          84
      14: new           #84                 // class java/lang/IllegalArgumentException
      17: dup
      18: new           #86                 // class scala/StringContext
      21: dup
      22: getstatic     #91                 // Field scala/Predef$.MODULE$:Lscala/Predef$;
      25: iconst_3
      26: anewarray     #93                 // class java/lang/String
      29: dup
      30: iconst_0
      31: ldc           #95                 // String Highest SEQ so far was
      33: aastore
      34: dup
      35: iconst_1
      36: ldc           #97                 // String  but cumulative ACK is
      38: aastore
      39: dup
      40: iconst_2
      41: ldc           #99                 // String
      43: aastore
      44: checkcast     #101                // class "[Ljava/lang/Object;"
      47: invokevirtual #105                // Method scala/Predef$.wrapRefArray:([Ljava/lang/Object;)Lscala/collection/mutable/WrappedArray;
      50: invokespecial #109                // Method scala/StringContext."<init>":(Lscala/collection/Seq;)V
      53: getstatic     #91                 // Field scala/Predef$.MODULE$:Lscala/Predef$;
      56: iconst_2
      57: anewarray     #5                  // class java/lang/Object
      60: dup
      61: iconst_0
      62: aload_0
      63: invokevirtual #76                 // Method maxSeq:()Lakka/remote/SeqNo;
      66: aastore
      67: dup
      68: iconst_1
      69: aload_1
      70: invokevirtual #74                 // Method akka/remote/Ack.cumulativeAck:()Lakka/remote/SeqNo;
      73: aastore
      74: invokevirtual #113                // Method scala/Predef$.genericWrapArray:(Ljava/lang/Object;)Lscala/collection/mutable/WrappedArray;
      77: invokevirtual #117                // Method scala/StringContext.s:(Lscala/collection/Seq;)Ljava/lang/String;
      80: invokespecial #120                // Method java/lang/IllegalArgumentException."<init>":(Ljava/lang/String;)V
      83: athrow
      84: aload_1
      85: invokevirtual #124                // Method akka/remote/Ack.nacks:()Lscala/collection/immutable/Set;
      88: invokeinterface #130,  1          // InterfaceMethod scala/collection/immutable/Set.isEmpty:()Z
      93: ifeq          105
      96: getstatic     #135                // Field scala/collection/immutable/Vector$.MODULE$:Lscala/collection/immutable/Vector$;
      99: invokevirtual #138                // Method scala/collection/immutable/Vector$.empty:()Lscala/collection/immutable/Vector;
     102: goto          144
     105: aload_0
     106: invokevirtual #140                // Method nacked:()Lscala/collection/immutable/IndexedSeq;
     109: aload_0
     110: invokevirtual #142                // Method nonAcked:()Lscala/collection/immutable/IndexedSeq;
     113: getstatic     #147                // Field scala/collection/immutable/IndexedSeq$.MODULE$:Lscala/collection/immutable/IndexedSeq$;
     116: invokevirtual #151                // Method scala/collection/immutable/IndexedSeq$.canBuildFrom:()Lscala/collection/generic/CanBuildFrom;
     119: invokeinterface #157,  3          // InterfaceMethod scala/collection/immutable/IndexedSeq.$plus$plus:(Lscala/collection/GenTraversableOnce;Lscala/collection/generic/CanBuildFrom;)Ljava/lang/Object;
     124: checkcast     #159                // class scala/collection/TraversableLike
     127: new           #161                // class akka/remote/AckedSendBuffer$$anonfun$1
     130: dup
     131: aload_0
     132: aload_1
     133: invokespecial #164                // Method akka/remote/AckedSendBuffer$$anonfun$1."<init>":(Lakka/remote/AckedSendBuffer;Lakka/remote/Ack;)V
     136: invokeinterface #168,  2          // InterfaceMethod scala/collection/TraversableLike.filter:(Lscala/Function1;)Ljava/lang/Object;
     141: checkcast     #153                // class scala/collection/immutable/IndexedSeq
     144: astore_2
     145: aload_2
     146: invokeinterface #171,  1          // InterfaceMethod scala/collection/immutable/IndexedSeq.size:()I
     151: aload_1
     152: invokevirtual #124                // Method akka/remote/Ack.nacks:()Lscala/collection/immutable/Set;
     155: invokeinterface #172,  1          // InterfaceMethod scala/collection/immutable/Set.size:()I
     160: if_icmpge     171
     163: new           #174                // class akka/remote/ResendUnfulfillableException
     166: dup
     167: invokespecial #177                // Method akka/remote/ResendUnfulfillableException."<init>":()V
     170: athrow
     171: aload_0
     172: invokevirtual #142                // Method nonAcked:()Lscala/collection/immutable/IndexedSeq;
     175: new           #179                // class akka/remote/AckedSendBuffer$$anonfun$2
     178: dup
     179: aload_0
     180: aload_1
     181: invokespecial #180                // Method akka/remote/AckedSendBuffer$$anonfun$2."<init>":(Lakka/remote/AckedSendBuffer;Lakka/remote/Ack;)V
     184: invokeinterface #181,  2          // InterfaceMethod scala/collection/immutable/IndexedSeq.filter:(Lscala/Function1;)Ljava/lang/Object;
     189: checkcast     #153                // class scala/collection/immutable/IndexedSeq
     192: astore_3
     193: aload_2
     194: astore        4
     196: aload_0
     197: invokevirtual #184                // Method copy$default$1:()I
     200: istore        5
     202: aload_0
     203: invokevirtual #187                // Method copy$default$4:()Lakka/remote/SeqNo;
     206: astore        6
     208: aload_0
     209: iload         5
     211: aload_3
     212: aload         4
     214: aload         6
     216: invokevirtual #190                // Method copy:(ILscala/collection/immutable/IndexedSeq;Lscala/collection/immutable/IndexedSeq;Lakka/remote/SeqNo;)Lakka/remote/AckedSendBuffer;
     219: areturn

  public akka.remote.AckedSendBuffer<T> buffer(T);
    Code:
       0: aload_1
       1: invokeinterface #204,  1          // InterfaceMethod akka/remote/HasSequenceNumber.seq:()Lakka/remote/SeqNo;
       6: aload_0
       7: invokevirtual #76                 // Method maxSeq:()Lakka/remote/SeqNo;
      10: invokevirtual #207                // Method akka/remote/SeqNo.$less$eq:(Ljava/lang/Object;)Z
      13: ifeq          142
      16: new           #84                 // class java/lang/IllegalArgumentException
      19: dup
      20: new           #209                // class scala/collection/mutable/StringBuilder
      23: dup
      24: invokespecial #210                // Method scala/collection/mutable/StringBuilder."<init>":()V
      27: new           #86                 // class scala/StringContext
      30: dup
      31: getstatic     #91                 // Field scala/Predef$.MODULE$:Lscala/Predef$;
      34: iconst_2
      35: anewarray     #93                 // class java/lang/String
      38: dup
      39: iconst_0
      40: ldc           #212                // String Sequence number must be monotonic. Received [
      42: aastore
      43: dup
      44: iconst_1
      45: ldc           #214                // String ]
      47: aastore
      48: checkcast     #101                // class "[Ljava/lang/Object;"
      51: invokevirtual #105                // Method scala/Predef$.wrapRefArray:([Ljava/lang/Object;)Lscala/collection/mutable/WrappedArray;
      54: invokespecial #109                // Method scala/StringContext."<init>":(Lscala/collection/Seq;)V
      57: getstatic     #91                 // Field scala/Predef$.MODULE$:Lscala/Predef$;
      60: iconst_1
      61: anewarray     #5                  // class java/lang/Object
      64: dup
      65: iconst_0
      66: aload_1
      67: invokeinterface #204,  1          // InterfaceMethod akka/remote/HasSequenceNumber.seq:()Lakka/remote/SeqNo;
      72: aastore
      73: invokevirtual #113                // Method scala/Predef$.genericWrapArray:(Ljava/lang/Object;)Lscala/collection/mutable/WrappedArray;
      76: invokevirtual #117                // Method scala/StringContext.s:(Lscala/collection/Seq;)Ljava/lang/String;
      79: invokevirtual #218                // Method scala/collection/mutable/StringBuilder.append:(Ljava/lang/Object;)Lscala/collection/mutable/StringBuilder;
      82: new           #86                 // class scala/StringContext
      85: dup
      86: getstatic     #91                 // Field scala/Predef$.MODULE$:Lscala/Predef$;
      89: iconst_2
      90: anewarray     #93                 // class java/lang/String
      93: dup
      94: iconst_0
      95: ldc           #220                // String which is smaller than [
      97: aastore
      98: dup
      99: iconst_1
     100: ldc           #222                // String ]
     102: aastore
     103: checkcast     #101                // class "[Ljava/lang/Object;"
     106: invokevirtual #105                // Method scala/Predef$.wrapRefArray:([Ljava/lang/Object;)Lscala/collection/mutable/WrappedArray;
     109: invokespecial #109                // Method scala/StringContext."<init>":(Lscala/collection/Seq;)V
     112: getstatic     #91                 // Field scala/Predef$.MODULE$:Lscala/Predef$;
     115: iconst_1
     116: anewarray     #5                  // class java/lang/Object
     119: dup
     120: iconst_0
     121: aload_0
     122: invokevirtual #76                 // Method maxSeq:()Lakka/remote/SeqNo;
     125: aastore
     126: invokevirtual #113                // Method scala/Predef$.genericWrapArray:(Ljava/lang/Object;)Lscala/collection/mutable/WrappedArray;
     129: invokevirtual #117                // Method scala/StringContext.s:(Lscala/collection/Seq;)Ljava/lang/String;
     132: invokevirtual #218                // Method scala/collection/mutable/StringBuilder.append:(Ljava/lang/Object;)Lscala/collection/mutable/StringBuilder;
     135: invokevirtual #226                // Method scala/collection/mutable/StringBuilder.toString:()Ljava/lang/String;
     138: invokespecial #120                // Method java/lang/IllegalArgumentException."<init>":(Ljava/lang/String;)V
     141: athrow
     142: aload_0
     143: invokevirtual #142                // Method nonAcked:()Lscala/collection/immutable/IndexedSeq;
     146: invokeinterface #171,  1          // InterfaceMethod scala/collection/immutable/IndexedSeq.size:()I
     151: aload_0
     152: invokevirtual #228                // Method capacity:()I
     155: if_icmpne     170
     158: new           #230                // class akka/remote/ResendBufferCapacityReachedException
     161: dup
     162: aload_0
     163: invokevirtual #228                // Method capacity:()I
     166: invokespecial #233                // Method akka/remote/ResendBufferCapacityReachedException."<init>":(I)V
     169: athrow
     170: aload_0
     171: invokevirtual #142                // Method nonAcked:()Lscala/collection/immutable/IndexedSeq;
     174: aload_1
     175: getstatic     #147                // Field scala/collection/immutable/IndexedSeq$.MODULE$:Lscala/collection/immutable/IndexedSeq$;
     178: invokevirtual #151                // Method scala/collection/immutable/IndexedSeq$.canBuildFrom:()Lscala/collection/generic/CanBuildFrom;
     181: invokeinterface #237,  3          // InterfaceMethod scala/collection/immutable/IndexedSeq.$colon$plus:(Ljava/lang/Object;Lscala/collection/generic/CanBuildFrom;)Ljava/lang/Object;
     186: checkcast     #153                // class scala/collection/immutable/IndexedSeq
     189: astore_2
     190: aload_1
     191: invokeinterface #204,  1          // InterfaceMethod akka/remote/HasSequenceNumber.seq:()Lakka/remote/SeqNo;
     196: astore_3
     197: aload_0
     198: invokevirtual #184                // Method copy$default$1:()I
     201: istore        4
     203: aload_0
     204: invokevirtual #240                // Method copy$default$3:()Lscala/collection/immutable/IndexedSeq;
     207: astore        5
     209: aload_0
     210: iload         4
     212: aload_2
     213: aload         5
     215: aload_3
     216: invokevirtual #190                // Method copy:(ILscala/collection/immutable/IndexedSeq;Lscala/collection/immutable/IndexedSeq;Lakka/remote/SeqNo;)Lakka/remote/AckedSendBuffer;
     219: areturn

  public java.lang.String toString();
    Code:
       0: new           #86                 // class scala/StringContext
       3: dup
       4: getstatic     #91                 // Field scala/Predef$.MODULE$:Lscala/Predef$;
       7: iconst_3
       8: anewarray     #93                 // class java/lang/String
      11: dup
      12: iconst_0
      13: ldc           #248                // String [
      15: aastore
      16: dup
      17: iconst_1
      18: ldc           #250                // String
      20: aastore
      21: dup
      22: iconst_2
      23: ldc           #222                // String ]
      25: aastore
      26: checkcast     #101                // class "[Ljava/lang/Object;"
      29: invokevirtual #105                // Method scala/Predef$.wrapRefArray:([Ljava/lang/Object;)Lscala/collection/mutable/WrappedArray;
      32: invokespecial #109                // Method scala/StringContext."<init>":(Lscala/collection/Seq;)V
      35: getstatic     #91                 // Field scala/Predef$.MODULE$:Lscala/Predef$;
      38: iconst_2
      39: anewarray     #5                  // class java/lang/Object
      42: dup
      43: iconst_0
      44: aload_0
      45: invokevirtual #76                 // Method maxSeq:()Lakka/remote/SeqNo;
      48: aastore
      49: dup
      50: iconst_1
      51: aload_0
      52: invokevirtual #142                // Method nonAcked:()Lscala/collection/immutable/IndexedSeq;
      55: new           #252                // class akka/remote/AckedSendBuffer$$anonfun$toString$1
      58: dup
      59: aload_0
      60: invokespecial #255                // Method akka/remote/AckedSendBuffer$$anonfun$toString$1."<init>":(Lakka/remote/AckedSendBuffer;)V
      63: getstatic     #147                // Field scala/collection/immutable/IndexedSeq$.MODULE$:Lscala/collection/immutable/IndexedSeq$;
      66: invokevirtual #151                // Method scala/collection/immutable/IndexedSeq$.canBuildFrom:()Lscala/collection/generic/CanBuildFrom;
      69: invokeinterface #259,  3          // InterfaceMethod scala/collection/immutable/IndexedSeq.map:(Lscala/Function1;Lscala/collection/generic/CanBuildFrom;)Ljava/lang/Object;
      74: checkcast     #261                // class scala/collection/TraversableOnce
      77: ldc_w         #263                // String {
      80: ldc_w         #265                // String ,
      83: ldc_w         #267                // String }
      86: invokeinterface #271,  4          // InterfaceMethod scala/collection/TraversableOnce.mkString:(Ljava/lang/String;Ljava/lang/String;Ljava/lang/String;)Ljava/lang/String;
      91: aastore
      92: invokevirtual #113                // Method scala/Predef$.genericWrapArray:(Ljava/lang/Object;)Lscala/collection/mutable/WrappedArray;
      95: invokevirtual #117                // Method scala/StringContext.s:(Lscala/collection/Seq;)Ljava/lang/String;
      98: areturn

  public <T extends akka.remote.HasSequenceNumber> akka.remote.AckedSendBuffer<T> copy(int, scala.collection.immutable.IndexedSeq<T>, scala.collection.immutable.IndexedSeq<T>, akka.remote.SeqNo);
    Code:
       0: new           #2                  // class akka/remote/AckedSendBuffer
       3: dup
       4: iload_1
       5: aload_2
       6: aload_3
       7: aload         4
       9: invokespecial #274                // Method "<init>":(ILscala/collection/immutable/IndexedSeq;Lscala/collection/immutable/IndexedSeq;Lakka/remote/SeqNo;)V
      12: areturn

  public <T extends akka.remote.HasSequenceNumber> int copy$default$1();
    Code:
       0: aload_0
       1: invokevirtual #228                // Method capacity:()I
       4: ireturn

  public <T extends akka.remote.HasSequenceNumber> scala.collection.immutable.IndexedSeq<T> copy$default$2();
    Code:
       0: aload_0
       1: invokevirtual #142                // Method nonAcked:()Lscala/collection/immutable/IndexedSeq;
       4: areturn

  public <T extends akka.remote.HasSequenceNumber> scala.collection.immutable.IndexedSeq<T> copy$default$3();
    Code:
       0: aload_0
       1: invokevirtual #140                // Method nacked:()Lscala/collection/immutable/IndexedSeq;
       4: areturn

  public <T extends akka.remote.HasSequenceNumber> akka.remote.SeqNo copy$default$4();
    Code:
       0: aload_0
       1: invokevirtual #76                 // Method maxSeq:()Lakka/remote/SeqNo;
       4: areturn

  public java.lang.String productPrefix();
    Code:
       0: ldc_w         #278                // String AckedSendBuffer
       3: areturn

  public int productArity();
    Code:
       0: iconst_4
       1: ireturn

  public java.lang.Object productElement(int);
    Code:
       0: iload_1
       1: istore_2
       2: iload_2
       3: tableswitch   { // 0 to 3
                     0: 68
                     1: 61
                     2: 54
                     3: 47
               default: 32
          }
      32: new           #283                // class java/lang/IndexOutOfBoundsException
      35: dup
      36: iload_1
      37: invokestatic  #289                // Method scala/runtime/BoxesRunTime.boxToInteger:(I)Ljava/lang/Integer;
      40: invokevirtual #290                // Method java/lang/Object.toString:()Ljava/lang/String;
      43: invokespecial #291                // Method java/lang/IndexOutOfBoundsException."<init>":(Ljava/lang/String;)V
      46: athrow
      47: aload_0
      48: invokevirtual #76                 // Method maxSeq:()Lakka/remote/SeqNo;
      51: goto          75
      54: aload_0
      55: invokevirtual #140                // Method nacked:()Lscala/collection/immutable/IndexedSeq;
      58: goto          75
      61: aload_0
      62: invokevirtual #142                // Method nonAcked:()Lscala/collection/immutable/IndexedSeq;
      65: goto          75
      68: aload_0
      69: invokevirtual #228                // Method capacity:()I
      72: invokestatic  #289                // Method scala/runtime/BoxesRunTime.boxToInteger:(I)Ljava/lang/Integer;
      75: areturn

  public scala.collection.Iterator<java.lang.Object> productIterator();
    Code:
       0: getstatic     #299                // Field scala/runtime/ScalaRunTime$.MODULE$:Lscala/runtime/ScalaRunTime$;
       3: aload_0
       4: invokevirtual #303                // Method scala/runtime/ScalaRunTime$.typedProductIterator:(Lscala/Product;)Lscala/collection/Iterator;
       7: areturn

  public boolean canEqual(java.lang.Object);
    Code:
       0: aload_1
       1: instanceof    #2                  // class akka/remote/AckedSendBuffer
       4: ireturn

  public int hashCode();
    Code:
       0: ldc_w         #307                // int -889275714
       3: istore_1
       4: iload_1
       5: aload_0
       6: invokevirtual #228                // Method capacity:()I
       9: invokestatic  #313                // Method scala/runtime/Statics.mix:(II)I
      12: istore_1
      13: iload_1
      14: aload_0
      15: invokevirtual #142                // Method nonAcked:()Lscala/collection/immutable/IndexedSeq;
      18: invokestatic  #317                // Method scala/runtime/Statics.anyHash:(Ljava/lang/Object;)I
      21: invokestatic  #313                // Method scala/runtime/Statics.mix:(II)I
      24: istore_1
      25: iload_1
      26: aload_0
      27: invokevirtual #140                // Method nacked:()Lscala/collection/immutable/IndexedSeq;
      30: invokestatic  #317                // Method scala/runtime/Statics.anyHash:(Ljava/lang/Object;)I
      33: invokestatic  #313                // Method scala/runtime/Statics.mix:(II)I
      36: istore_1
      37: iload_1
      38: aload_0
      39: invokevirtual #76                 // Method maxSeq:()Lakka/remote/SeqNo;
      42: invokestatic  #317                // Method scala/runtime/Statics.anyHash:(Ljava/lang/Object;)I
      45: invokestatic  #313                // Method scala/runtime/Statics.mix:(II)I
      48: istore_1
      49: iload_1
      50: iconst_4
      51: invokestatic  #320                // Method scala/runtime/Statics.finalizeHash:(II)I
      54: ireturn

  public boolean equals(java.lang.Object);
    Code:
       0: aload_0
       1: aload_1
       2: if_acmpeq     147
       5: aload_1
       6: astore_2
       7: aload_2
       8: instanceof    #2                  // class akka/remote/AckedSendBuffer
      11: ifeq          19
      14: iconst_1
      15: istore_3
      16: goto          21
      19: iconst_0
      20: istore_3
      21: iload_3
      22: ifeq          151
      25: aload_1
      26: checkcast     #2                  // class akka/remote/AckedSendBuffer
      29: astore        4
      31: aload_0
      32: invokevirtual #228                // Method capacity:()I
      35: aload         4
      37: invokevirtual #228                // Method capacity:()I
      40: if_icmpne     143
      43: aload_0
      44: invokevirtual #142                // Method nonAcked:()Lscala/collection/immutable/IndexedSeq;
      47: aload         4
      49: invokevirtual #142                // Method nonAcked:()Lscala/collection/immutable/IndexedSeq;
      52: astore        5
      54: dup
      55: ifnonnull     67
      58: pop
      59: aload         5
      61: ifnull        75
      64: goto          143
      67: aload         5
      69: invokevirtual #323                // Method java/lang/Object.equals:(Ljava/lang/Object;)Z
      72: ifeq          143
      75: aload_0
      76: invokevirtual #140                // Method nacked:()Lscala/collection/immutable/IndexedSeq;
      79: aload         4
      81: invokevirtual #140                // Method nacked:()Lscala/collection/immutable/IndexedSeq;
      84: astore        6
      86: dup
      87: ifnonnull     99
      90: pop
      91: aload         6
      93: ifnull        107
      96: goto          143
      99: aload         6
     101: invokevirtual #323                // Method java/lang/Object.equals:(Ljava/lang/Object;)Z
     104: ifeq          143
     107: aload_0
     108: invokevirtual #76                 // Method maxSeq:()Lakka/remote/SeqNo;
     111: aload         4
     113: invokevirtual #76                 // Method maxSeq:()Lakka/remote/SeqNo;
     116: astore        7
     118: dup
     119: ifnonnull     131
     122: pop
     123: aload         7
     125: ifnull        139
     128: goto          143
     131: aload         7
     133: invokevirtual #323                // Method java/lang/Object.equals:(Ljava/lang/Object;)Z
     136: ifeq          143
     139: iconst_1
     140: goto          144
     143: iconst_0
     144: ifeq          151
     147: iconst_1
     148: goto          152
     151: iconst_0
     152: ireturn

  public akka.remote.AckedSendBuffer(int, scala.collection.immutable.IndexedSeq<T>, scala.collection.immutable.IndexedSeq<T>, akka.remote.SeqNo);
    Code:
       0: aload_0
       1: iload_1
       2: putfield      #58                 // Field capacity:I
       5: aload_0
       6: aload_2
       7: putfield      #63                 // Field nonAcked:Lscala/collection/immutable/IndexedSeq;
      10: aload_0
      11: aload_3
      12: putfield      #65                 // Field nacked:Lscala/collection/immutable/IndexedSeq;
      15: aload_0
      16: aload         4
      18: putfield      #67                 // Field maxSeq:Lakka/remote/SeqNo;
      21: aload_0
      22: invokespecial #324                // Method java/lang/Object."<init>":()V
      25: aload_0
      26: invokestatic  #330                // Method scala/Product$class.$init$:(Lscala/Product;)V
      29: return
}
