Compiled from "Remoting.scala"
public final class akka.remote.EndpointManager$$anonfun$10$$anonfun$11 extends scala.runtime.AbstractFunction1<java.lang.String, akka.remote.transport.TransportAdapterProvider> implements scala.Serializable {
  public static final long serialVersionUID;

  private final akka.remote.transport.TransportAdapters eta$0$1$1;

  public final akka.remote.transport.TransportAdapterProvider apply(java.lang.String);
    Code:
       0: aload_0
       1: getfield      #20                 // Field eta$0$1$1:Lakka/remote/transport/TransportAdapters;
       4: aload_1
       5: invokevirtual #25                 // Method akka/remote/transport/TransportAdapters.getAdapterProvider:(Ljava/lang/String;)Lakka/remote/transport/TransportAdapterProvider;
       8: areturn

  public final java.lang.Object apply(java.lang.Object);
    Code:
       0: aload_0
       1: aload_1
       2: checkcast     #32                 // class java/lang/String
       5: invokevirtual #34                 // Method apply:(Ljava/lang/String;)Lakka/remote/transport/TransportAdapterProvider;
       8: areturn

  public akka.remote.EndpointManager$$anonfun$10$$anonfun$11(akka.remote.EndpointManager$$anonfun$10, akka.remote.transport.TransportAdapters);
    Code:
       0: aload_0
       1: aload_2
       2: putfield      #20                 // Field eta$0$1$1:Lakka/remote/transport/TransportAdapters;
       5: aload_0
       6: invokespecial #41                 // Method scala/runtime/AbstractFunction1."<init>":()V
       9: return
}
