Compiled from "Endpoint.scala"
public final class akka.remote.EndpointWriter$$anonfun$delegate$1$1 extends scala.runtime.AbstractFunction1<akka.actor.ActorRef, scala.runtime.BoxedUnit> implements scala.Serializable {
  public static final long serialVersionUID;

  private final akka.actor.ActorRef replyTo$1;

  private final akka.remote.EndpointWriter$StopReading x2$1;

  public final void apply(akka.actor.ActorRef);
    Code:
       0: aload_1
       1: aload_0
       2: getfield      #25                 // Field x2$1:Lakka/remote/EndpointWriter$StopReading;
       5: aload_0
       6: getfield      #27                 // Field replyTo$1:Lakka/actor/ActorRef;
       9: invokevirtual #33                 // Method akka/actor/ActorRef.tell:(Ljava/lang/Object;Lakka/actor/ActorRef;)V
      12: return

  public final java.lang.Object apply(java.lang.Object);
    Code:
       0: aload_0
       1: aload_1
       2: checkcast     #29                 // class akka/actor/ActorRef
       5: invokevirtual #39                 // Method apply:(Lakka/actor/ActorRef;)V
       8: getstatic     #45                 // Field scala/runtime/BoxedUnit.UNIT:Lscala/runtime/BoxedUnit;
      11: areturn

  public akka.remote.EndpointWriter$$anonfun$delegate$1$1(akka.remote.EndpointWriter, akka.actor.ActorRef, akka.remote.EndpointWriter$StopReading);
    Code:
       0: aload_0
       1: aload_2
       2: putfield      #27                 // Field replyTo$1:Lakka/actor/ActorRef;
       5: aload_0
       6: aload_3
       7: putfield      #25                 // Field x2$1:Lakka/remote/EndpointWriter$StopReading;
      10: aload_0
      11: invokespecial #52                 // Method scala/runtime/AbstractFunction1."<init>":()V
      14: return
}
