Compiled from "Remoting.scala"
public class akka.remote.EndpointManager$ResendState$ extends scala.runtime.AbstractFunction2<java.lang.Object, akka.remote.AckedReceiveBuffer<akka.remote.transport.AkkaPduCodec$Message>, akka.remote.EndpointManager$ResendState> implements scala.Serializable {
  public static final akka.remote.EndpointManager$ResendState$ MODULE$;

  public static {};
    Code:
       0: new           #2                  // class akka/remote/EndpointManager$ResendState$
       3: invokespecial #15                 // Method "<init>":()V
       6: return

  public final java.lang.String toString();
    Code:
       0: ldc           #19                 // String ResendState
       2: areturn

  public akka.remote.EndpointManager$ResendState apply(int, akka.remote.AckedReceiveBuffer<akka.remote.transport.AkkaPduCodec$Message>);
    Code:
       0: new           #24                 // class akka/remote/EndpointManager$ResendState
       3: dup
       4: iload_1
       5: aload_2
       6: invokespecial #27                 // Method akka/remote/EndpointManager$ResendState."<init>":(ILakka/remote/AckedReceiveBuffer;)V
       9: areturn

  public scala.Option<scala.Tuple2<java.lang.Object, akka.remote.AckedReceiveBuffer<akka.remote.transport.AkkaPduCodec$Message>>> unapply(akka.remote.EndpointManager$ResendState);
    Code:
       0: aload_1
       1: ifnonnull     10
       4: getstatic     #38                 // Field scala/None$.MODULE$:Lscala/None$;
       7: goto          35
      10: new           #40                 // class scala/Some
      13: dup
      14: new           #42                 // class scala/Tuple2
      17: dup
      18: aload_1
      19: invokevirtual #45                 // Method akka/remote/EndpointManager$ResendState.uid:()I
      22: invokestatic  #51                 // Method scala/runtime/BoxesRunTime.boxToInteger:(I)Ljava/lang/Integer;
      25: aload_1
      26: invokevirtual #54                 // Method akka/remote/EndpointManager$ResendState.buffer:()Lakka/remote/AckedReceiveBuffer;
      29: invokespecial #57                 // Method scala/Tuple2."<init>":(Ljava/lang/Object;Ljava/lang/Object;)V
      32: invokespecial #60                 // Method scala/Some."<init>":(Ljava/lang/Object;)V
      35: areturn

  private java.lang.Object readResolve();
    Code:
       0: getstatic     #68                 // Field MODULE$:Lakka/remote/EndpointManager$ResendState$;
       3: areturn

  public java.lang.Object apply(java.lang.Object, java.lang.Object);
    Code:
       0: aload_0
       1: aload_1
       2: invokestatic  #73                 // Method scala/runtime/BoxesRunTime.unboxToInt:(Ljava/lang/Object;)I
       5: aload_2
       6: checkcast     #75                 // class akka/remote/AckedReceiveBuffer
       9: invokevirtual #77                 // Method apply:(ILakka/remote/AckedReceiveBuffer;)Lakka/remote/EndpointManager$ResendState;
      12: areturn

  public akka.remote.EndpointManager$ResendState$();
    Code:
       0: aload_0
       1: invokespecial #81                 // Method scala/runtime/AbstractFunction2."<init>":()V
       4: aload_0
       5: putstatic     #68                 // Field MODULE$:Lakka/remote/EndpointManager$ResendState$;
       8: return
}
