Compiled from "RemoteWatcher.scala"
public final class akka.remote.RemoteWatcher$$anonfun$reWatch$1 extends scala.runtime.AbstractFunction1<scala.collection.mutable.Set<akka.actor.InternalActorRef>, scala.runtime.BoxedUnit> implements scala.Serializable {
  public static final long serialVersionUID;

  private final akka.remote.RemoteWatcher $outer;

  public final void apply(scala.collection.mutable.Set<akka.actor.InternalActorRef>);
    Code:
       0: aload_1
       1: new           #23                 // class akka/remote/RemoteWatcher$$anonfun$reWatch$1$$anonfun$apply$3
       4: dup
       5: aload_0
       6: invokespecial #27                 // Method akka/remote/RemoteWatcher$$anonfun$reWatch$1$$anonfun$apply$3."<init>":(Lakka/remote/RemoteWatcher$$anonfun$reWatch$1;)V
       9: invokeinterface #33,  2           // InterfaceMethod scala/collection/mutable/Set.foreach:(Lscala/Function1;)V
      14: return

  public akka.remote.RemoteWatcher akka$remote$RemoteWatcher$$anonfun$$$outer();
    Code:
       0: aload_0
       1: getfield      #41                 // Field $outer:Lakka/remote/RemoteWatcher;
       4: areturn

  public final java.lang.Object apply(java.lang.Object);
    Code:
       0: aload_0
       1: aload_1
       2: checkcast     #29                 // class scala/collection/mutable/Set
       5: invokevirtual #44                 // Method apply:(Lscala/collection/mutable/Set;)V
       8: getstatic     #50                 // Field scala/runtime/BoxedUnit.UNIT:Lscala/runtime/BoxedUnit;
      11: areturn

  public akka.remote.RemoteWatcher$$anonfun$reWatch$1(akka.remote.RemoteWatcher);
    Code:
       0: aload_1
       1: ifnonnull     6
       4: aconst_null
       5: athrow
       6: aload_0
       7: aload_1
       8: putfield      #41                 // Field $outer:Lakka/remote/RemoteWatcher;
      11: aload_0
      12: invokespecial #56                 // Method scala/runtime/AbstractFunction1."<init>":()V
      15: return
}
