Compiled from "RMAssertion.java"
public class org.apache.cxf.ws.rmp.v200502.RMAssertion {
  protected org.apache.cxf.ws.rmp.v200502.RMAssertion$InactivityTimeout inactivityTimeout;

  protected org.apache.cxf.ws.rmp.v200502.RMAssertion$BaseRetransmissionInterval baseRetransmissionInterval;

  protected org.apache.cxf.ws.rmp.v200502.RMAssertion$ExponentialBackoff exponentialBackoff;

  protected org.apache.cxf.ws.rmp.v200502.RMAssertion$AcknowledgementInterval acknowledgementInterval;

  protected java.util.List<java.lang.Object> any;

  private java.util.Map<javax.xml.namespace.QName, java.lang.String> otherAttributes;

  public org.apache.cxf.ws.rmp.v200502.RMAssertion();
    Code:
       0: aload_0
       1: invokespecial #1                  // Method java/lang/Object."<init>":()V
       4: aload_0
       5: new           #2                  // class java/util/HashMap
       8: dup
       9: invokespecial #3                  // Method java/util/HashMap."<init>":()V
      12: putfield      #4                  // Field otherAttributes:Ljava/util/Map;
      15: return

  public org.apache.cxf.ws.rmp.v200502.RMAssertion$InactivityTimeout getInactivityTimeout();
    Code:
       0: aload_0
       1: getfield      #5                  // Field inactivityTimeout:Lorg/apache/cxf/ws/rmp/v200502/RMAssertion$InactivityTimeout;
       4: areturn

  public void setInactivityTimeout(org.apache.cxf.ws.rmp.v200502.RMAssertion$InactivityTimeout);
    Code:
       0: aload_0
       1: aload_1
       2: putfield      #5                  // Field inactivityTimeout:Lorg/apache/cxf/ws/rmp/v200502/RMAssertion$InactivityTimeout;
       5: return

  public boolean isSetInactivityTimeout();
    Code:
       0: aload_0
       1: getfield      #5                  // Field inactivityTimeout:Lorg/apache/cxf/ws/rmp/v200502/RMAssertion$InactivityTimeout;
       4: ifnull        11
       7: iconst_1
       8: goto          12
      11: iconst_0
      12: ireturn

  public org.apache.cxf.ws.rmp.v200502.RMAssertion$BaseRetransmissionInterval getBaseRetransmissionInterval();
    Code:
       0: aload_0
       1: getfield      #6                  // Field baseRetransmissionInterval:Lorg/apache/cxf/ws/rmp/v200502/RMAssertion$BaseRetransmissionInterval;
       4: areturn

  public void setBaseRetransmissionInterval(org.apache.cxf.ws.rmp.v200502.RMAssertion$BaseRetransmissionInterval);
    Code:
       0: aload_0
       1: aload_1
       2: putfield      #6                  // Field baseRetransmissionInterval:Lorg/apache/cxf/ws/rmp/v200502/RMAssertion$BaseRetransmissionInterval;
       5: return

  public boolean isSetBaseRetransmissionInterval();
    Code:
       0: aload_0
       1: getfield      #6                  // Field baseRetransmissionInterval:Lorg/apache/cxf/ws/rmp/v200502/RMAssertion$BaseRetransmissionInterval;
       4: ifnull        11
       7: iconst_1
       8: goto          12
      11: iconst_0
      12: ireturn

  public org.apache.cxf.ws.rmp.v200502.RMAssertion$ExponentialBackoff getExponentialBackoff();
    Code:
       0: aload_0
       1: getfield      #7                  // Field exponentialBackoff:Lorg/apache/cxf/ws/rmp/v200502/RMAssertion$ExponentialBackoff;
       4: areturn

  public void setExponentialBackoff(org.apache.cxf.ws.rmp.v200502.RMAssertion$ExponentialBackoff);
    Code:
       0: aload_0
       1: aload_1
       2: putfield      #7                  // Field exponentialBackoff:Lorg/apache/cxf/ws/rmp/v200502/RMAssertion$ExponentialBackoff;
       5: return

  public boolean isSetExponentialBackoff();
    Code:
       0: aload_0
       1: getfield      #7                  // Field exponentialBackoff:Lorg/apache/cxf/ws/rmp/v200502/RMAssertion$ExponentialBackoff;
       4: ifnull        11
       7: iconst_1
       8: goto          12
      11: iconst_0
      12: ireturn

  public org.apache.cxf.ws.rmp.v200502.RMAssertion$AcknowledgementInterval getAcknowledgementInterval();
    Code:
       0: aload_0
       1: getfield      #8                  // Field acknowledgementInterval:Lorg/apache/cxf/ws/rmp/v200502/RMAssertion$AcknowledgementInterval;
       4: areturn

  public void setAcknowledgementInterval(org.apache.cxf.ws.rmp.v200502.RMAssertion$AcknowledgementInterval);
    Code:
       0: aload_0
       1: aload_1
       2: putfield      #8                  // Field acknowledgementInterval:Lorg/apache/cxf/ws/rmp/v200502/RMAssertion$AcknowledgementInterval;
       5: return

  public boolean isSetAcknowledgementInterval();
    Code:
       0: aload_0
       1: getfield      #8                  // Field acknowledgementInterval:Lorg/apache/cxf/ws/rmp/v200502/RMAssertion$AcknowledgementInterval;
       4: ifnull        11
       7: iconst_1
       8: goto          12
      11: iconst_0
      12: ireturn

  public java.util.List<java.lang.Object> getAny();
    Code:
       0: aload_0
       1: getfield      #9                  // Field any:Ljava/util/List;
       4: ifnonnull     18
       7: aload_0
       8: new           #10                 // class java/util/ArrayList
      11: dup
      12: invokespecial #11                 // Method java/util/ArrayList."<init>":()V
      15: putfield      #9                  // Field any:Ljava/util/List;
      18: aload_0
      19: getfield      #9                  // Field any:Ljava/util/List;
      22: areturn

  public boolean isSetAny();
    Code:
       0: aload_0
       1: getfield      #9                  // Field any:Ljava/util/List;
       4: ifnull        23
       7: aload_0
       8: getfield      #9                  // Field any:Ljava/util/List;
      11: invokeinterface #12,  1           // InterfaceMethod java/util/List.isEmpty:()Z
      16: ifne          23
      19: iconst_1
      20: goto          24
      23: iconst_0
      24: ireturn

  public void unsetAny();
    Code:
       0: aload_0
       1: aconst_null
       2: putfield      #9                  // Field any:Ljava/util/List;
       5: return

  public java.util.Map<javax.xml.namespace.QName, java.lang.String> getOtherAttributes();
    Code:
       0: aload_0
       1: getfield      #4                  // Field otherAttributes:Ljava/util/Map;
       4: areturn
}
