Compiled from "DetachedThreadLocal.java"
class org.mockito.internal.util.concurrent.DetachedThreadLocal$1 extends org.mockito.internal.util.concurrent.WeakConcurrentMap<java.lang.Thread, T> {
  final org.mockito.internal.util.concurrent.DetachedThreadLocal this$0;

  org.mockito.internal.util.concurrent.DetachedThreadLocal$1(org.mockito.internal.util.concurrent.DetachedThreadLocal, boolean);
    Code:
       0: aload_0
       1: aload_1
       2: putfield      #1                  // Field this$0:Lorg/mockito/internal/util/concurrent/DetachedThreadLocal;
       5: aload_0
       6: iload_2
       7: invokespecial #2                  // Method org/mockito/internal/util/concurrent/WeakConcurrentMap."<init>":(Z)V
      10: return

  protected T defaultValue(java.lang.Thread);
    Code:
       0: aload_0
       1: getfield      #1                  // Field this$0:Lorg/mockito/internal/util/concurrent/DetachedThreadLocal;
       4: aload_1
       5: invokevirtual #3                  // Method org/mockito/internal/util/concurrent/DetachedThreadLocal.initialValue:(Ljava/lang/Thread;)Ljava/lang/Object;
       8: areturn

  protected java.lang.Object defaultValue(java.lang.Object);
    Code:
       0: aload_0
       1: aload_1
       2: checkcast     #4                  // class java/lang/Thread
       5: invokevirtual #5                  // Method defaultValue:(Ljava/lang/Thread;)Ljava/lang/Object;
       8: areturn
}
