Compiled from "DashboardsResource.java"
public class org.graylog2.rest.resources.dashboards.DashboardsResource extends org.graylog2.shared.rest.resources.RestResource {
  private static final org.slf4j.Logger LOG;

  private final org.graylog2.dashboards.DashboardService dashboardService;

  private final org.graylog2.shared.system.activities.ActivityWriter activityWriter;

  public org.graylog2.rest.resources.dashboards.DashboardsResource(org.graylog2.dashboards.DashboardService, org.graylog2.shared.system.activities.ActivityWriter);
    Code:
       0: aload_0
       1: invokespecial #1                  // Method org/graylog2/shared/rest/resources/RestResource."<init>":()V
       4: aload_0
       5: aload_1
       6: putfield      #2                  // Field dashboardService:Lorg/graylog2/dashboards/DashboardService;
       9: aload_0
      10: aload_2
      11: putfield      #3                  // Field activityWriter:Lorg/graylog2/shared/system/activities/ActivityWriter;
      14: return

  public javax.ws.rs.core.Response create(org.graylog2.rest.models.dashboards.requests.CreateDashboardRequest) throws org.graylog2.plugin.database.ValidationException;
    Code:
       0: aload_0
       1: getfield      #2                  // Field dashboardService:Lorg/graylog2/dashboards/DashboardService;
       4: aload_1
       5: invokevirtual #4                  // Method org/graylog2/rest/models/dashboards/requests/CreateDashboardRequest.title:()Ljava/lang/String;
       8: aload_1
       9: invokevirtual #5                  // Method org/graylog2/rest/models/dashboards/requests/CreateDashboardRequest.description:()Ljava/lang/String;
      12: aload_0
      13: invokevirtual #6                  // Method getCurrentUser:()Lorg/graylog2/plugin/database/users/User;
      16: invokeinterface #7,  1            // InterfaceMethod org/graylog2/plugin/database/users/User.getName:()Ljava/lang/String;
      21: invokestatic  #8                  // Method org/graylog2/plugin/Tools.nowUTC:()Lorg/joda/time/DateTime;
      24: invokeinterface #9,  5            // InterfaceMethod org/graylog2/dashboards/DashboardService.create:(Ljava/lang/String;Ljava/lang/String;Ljava/lang/String;Lorg/joda/time/DateTime;)Lorg/graylog2/dashboards/Dashboard;
      29: astore_2
      30: aload_0
      31: getfield      #2                  // Field dashboardService:Lorg/graylog2/dashboards/DashboardService;
      34: aload_2
      35: invokeinterface #10,  2           // InterfaceMethod org/graylog2/dashboards/DashboardService.save:(Lorg/graylog2/plugin/database/Persisted;)Ljava/lang/String;
      40: astore_3
      41: ldc           #11                 // String dashboard_id
      43: aload_3
      44: invokestatic  #12                 // Method com/google/common/collect/ImmutableMap.of:(Ljava/lang/Object;Ljava/lang/Object;)Lcom/google/common/collect/ImmutableMap;
      47: astore        4
      49: aload_0
      50: invokevirtual #13                 // Method getUriBuilderToSelf:()Ljavax/ws/rs/core/UriBuilder;
      53: ldc           #14                 // class org/graylog2/rest/resources/dashboards/DashboardsResource
      55: ldc           #15                 // String get
      57: invokevirtual #16                 // Method javax/ws/rs/core/UriBuilder.path:(Ljava/lang/Class;Ljava/lang/String;)Ljavax/ws/rs/core/UriBuilder;
      60: iconst_1
      61: anewarray     #17                 // class java/lang/Object
      64: dup
      65: iconst_0
      66: aload_3
      67: aastore
      68: invokevirtual #18                 // Method javax/ws/rs/core/UriBuilder.build:([Ljava/lang/Object;)Ljava/net/URI;
      71: astore        5
      73: aload_0
      74: invokevirtual #6                  // Method getCurrentUser:()Lorg/graylog2/plugin/database/users/User;
      77: astore        6
      79: aload         6
      81: invokeinterface #19,  1           // InterfaceMethod org/graylog2/plugin/database/users/User.isLocalAdmin:()Z
      86: ifne          172
      89: invokestatic  #20                 // Method com/google/common/collect/ImmutableList.builder:()Lcom/google/common/collect/ImmutableList$Builder;
      92: aload         6
      94: invokeinterface #21,  1           // InterfaceMethod org/graylog2/plugin/database/users/User.getPermissions:()Ljava/util/List;
      99: invokevirtual #22                 // Method com/google/common/collect/ImmutableList$Builder.addAll:(Ljava/lang/Iterable;)Lcom/google/common/collect/ImmutableList$Builder;
     102: new           #23                 // class java/lang/StringBuilder
     105: dup
     106: invokespecial #24                 // Method java/lang/StringBuilder."<init>":()V
     109: ldc           #26                 // String dashboards:read:
     111: invokevirtual #27                 // Method java/lang/StringBuilder.append:(Ljava/lang/String;)Ljava/lang/StringBuilder;
     114: aload_3
     115: invokevirtual #27                 // Method java/lang/StringBuilder.append:(Ljava/lang/String;)Ljava/lang/StringBuilder;
     118: invokevirtual #28                 // Method java/lang/StringBuilder.toString:()Ljava/lang/String;
     121: invokevirtual #29                 // Method com/google/common/collect/ImmutableList$Builder.add:(Ljava/lang/Object;)Lcom/google/common/collect/ImmutableList$Builder;
     124: new           #23                 // class java/lang/StringBuilder
     127: dup
     128: invokespecial #24                 // Method java/lang/StringBuilder."<init>":()V
     131: ldc           #30                 // String dashboards:edit:
     133: invokevirtual #27                 // Method java/lang/StringBuilder.append:(Ljava/lang/String;)Ljava/lang/StringBuilder;
     136: aload_3
     137: invokevirtual #27                 // Method java/lang/StringBuilder.append:(Ljava/lang/String;)Ljava/lang/StringBuilder;
     140: invokevirtual #28                 // Method java/lang/StringBuilder.toString:()Ljava/lang/String;
     143: invokevirtual #29                 // Method com/google/common/collect/ImmutableList$Builder.add:(Ljava/lang/Object;)Lcom/google/common/collect/ImmutableList$Builder;
     146: invokevirtual #31                 // Method com/google/common/collect/ImmutableList$Builder.build:()Lcom/google/common/collect/ImmutableList;
     149: astore        7
     151: aload         6
     153: aload         7
     155: invokeinterface #32,  2           // InterfaceMethod org/graylog2/plugin/database/users/User.setPermissions:(Ljava/util/List;)V
     160: aload_0
     161: getfield      #33                 // Field userService:Lorg/graylog2/shared/users/UserService;
     164: aload         6
     166: invokeinterface #34,  2           // InterfaceMethod org/graylog2/shared/users/UserService.save:(Lorg/graylog2/plugin/database/Persisted;)Ljava/lang/String;
     171: pop
     172: aload         5
     174: invokestatic  #35                 // Method javax/ws/rs/core/Response.created:(Ljava/net/URI;)Ljavax/ws/rs/core/Response$ResponseBuilder;
     177: aload         4
     179: invokevirtual #36                 // Method javax/ws/rs/core/Response$ResponseBuilder.entity:(Ljava/lang/Object;)Ljavax/ws/rs/core/Response$ResponseBuilder;
     182: invokevirtual #37                 // Method javax/ws/rs/core/Response$ResponseBuilder.build:()Ljavax/ws/rs/core/Response;
     185: areturn

  public org.graylog2.rest.models.dashboards.responses.DashboardList list();
    Code:
       0: invokestatic  #38                 // Method com/google/common/collect/Lists.newArrayList:()Ljava/util/ArrayList;
       3: astore_1
       4: aload_0
       5: getfield      #2                  // Field dashboardService:Lorg/graylog2/dashboards/DashboardService;
       8: invokeinterface #39,  1           // InterfaceMethod org/graylog2/dashboards/DashboardService.all:()Ljava/util/List;
      13: invokeinterface #40,  1           // InterfaceMethod java/util/List.iterator:()Ljava/util/Iterator;
      18: astore_2
      19: aload_2
      20: invokeinterface #41,  1           // InterfaceMethod java/util/Iterator.hasNext:()Z
      25: ifeq          69
      28: aload_2
      29: invokeinterface #42,  1           // InterfaceMethod java/util/Iterator.next:()Ljava/lang/Object;
      34: checkcast     #43                 // class org/graylog2/dashboards/Dashboard
      37: astore_3
      38: aload_0
      39: ldc           #44                 // String dashboards:read
      41: aload_3
      42: invokeinterface #45,  1           // InterfaceMethod org/graylog2/dashboards/Dashboard.getId:()Ljava/lang/String;
      47: invokevirtual #46                 // Method isPermitted:(Ljava/lang/String;Ljava/lang/String;)Z
      50: ifeq          66
      53: aload_1
      54: aload_3
      55: invokeinterface #47,  1           // InterfaceMethod org/graylog2/dashboards/Dashboard.asMap:()Ljava/util/Map;
      60: invokeinterface #48,  2           // InterfaceMethod java/util/List.add:(Ljava/lang/Object;)Z
      65: pop
      66: goto          19
      69: aload_1
      70: invokeinterface #49,  1           // InterfaceMethod java/util/List.size:()I
      75: aload_1
      76: invokestatic  #50                 // Method org/graylog2/rest/models/dashboards/responses/DashboardList.create:(ILjava/util/List;)Lorg/graylog2/rest/models/dashboards/responses/DashboardList;
      79: areturn

  public java.util.Map<java.lang.String, java.lang.Object> get(java.lang.String) throws org.graylog2.database.NotFoundException;
    Code:
       0: aload_0
       1: ldc           #44                 // String dashboards:read
       3: aload_1
       4: invokevirtual #51                 // Method checkPermission:(Ljava/lang/String;Ljava/lang/String;)V
       7: aload_0
       8: getfield      #2                  // Field dashboardService:Lorg/graylog2/dashboards/DashboardService;
      11: aload_1
      12: invokeinterface #52,  2           // InterfaceMethod org/graylog2/dashboards/DashboardService.load:(Ljava/lang/String;)Lorg/graylog2/dashboards/Dashboard;
      17: invokeinterface #47,  1           // InterfaceMethod org/graylog2/dashboards/Dashboard.asMap:()Ljava/util/Map;
      22: areturn

  public void delete(java.lang.String) throws org.graylog2.database.NotFoundException, org.graylog2.plugin.database.ValidationException;
    Code:
       0: aload_0
       1: ldc           #53                 // String dashboards:edit
       3: aload_1
       4: invokevirtual #51                 // Method checkPermission:(Ljava/lang/String;Ljava/lang/String;)V
       7: aload_0
       8: getfield      #2                  // Field dashboardService:Lorg/graylog2/dashboards/DashboardService;
      11: aload_1
      12: invokeinterface #52,  2           // InterfaceMethod org/graylog2/dashboards/DashboardService.load:(Ljava/lang/String;)Lorg/graylog2/dashboards/Dashboard;
      17: astore_2
      18: aload_0
      19: getfield      #2                  // Field dashboardService:Lorg/graylog2/dashboards/DashboardService;
      22: aload_2
      23: invokeinterface #54,  2           // InterfaceMethod org/graylog2/dashboards/DashboardService.destroy:(Lorg/graylog2/dashboards/Dashboard;)I
      28: pop
      29: new           #23                 // class java/lang/StringBuilder
      32: dup
      33: invokespecial #24                 // Method java/lang/StringBuilder."<init>":()V
      36: ldc           #55                 // String Deleted dashboard <
      38: invokevirtual #27                 // Method java/lang/StringBuilder.append:(Ljava/lang/String;)Ljava/lang/StringBuilder;
      41: aload_2
      42: invokeinterface #45,  1           // InterfaceMethod org/graylog2/dashboards/Dashboard.getId:()Ljava/lang/String;
      47: invokevirtual #27                 // Method java/lang/StringBuilder.append:(Ljava/lang/String;)Ljava/lang/StringBuilder;
      50: ldc           #56                 // String >. Reason: REST request.
      52: invokevirtual #27                 // Method java/lang/StringBuilder.append:(Ljava/lang/String;)Ljava/lang/StringBuilder;
      55: invokevirtual #28                 // Method java/lang/StringBuilder.toString:()Ljava/lang/String;
      58: astore_3
      59: getstatic     #57                 // Field LOG:Lorg/slf4j/Logger;
      62: aload_3
      63: invokeinterface #58,  2           // InterfaceMethod org/slf4j/Logger.info:(Ljava/lang/String;)V
      68: aload_0
      69: getfield      #3                  // Field activityWriter:Lorg/graylog2/shared/system/activities/ActivityWriter;
      72: new           #59                 // class org/graylog2/shared/system/activities/Activity
      75: dup
      76: aload_3
      77: ldc           #14                 // class org/graylog2/rest/resources/dashboards/DashboardsResource
      79: invokespecial #60                 // Method org/graylog2/shared/system/activities/Activity."<init>":(Ljava/lang/String;Ljava/lang/Class;)V
      82: invokeinterface #61,  2           // InterfaceMethod org/graylog2/shared/system/activities/ActivityWriter.write:(Lorg/graylog2/shared/system/activities/Activity;)V
      87: return

  public void update(java.lang.String, org.graylog2.rest.models.dashboards.requests.UpdateDashboardRequest) throws org.graylog2.plugin.database.ValidationException, org.graylog2.database.NotFoundException;
    Code:
       0: aload_0
       1: ldc           #53                 // String dashboards:edit
       3: aload_1
       4: invokevirtual #51                 // Method checkPermission:(Ljava/lang/String;Ljava/lang/String;)V
       7: aload_0
       8: getfield      #2                  // Field dashboardService:Lorg/graylog2/dashboards/DashboardService;
      11: aload_1
      12: invokeinterface #52,  2           // InterfaceMethod org/graylog2/dashboards/DashboardService.load:(Ljava/lang/String;)Lorg/graylog2/dashboards/Dashboard;
      17: astore_3
      18: aload_2
      19: invokevirtual #62                 // Method org/graylog2/rest/models/dashboards/requests/UpdateDashboardRequest.title:()Ljava/lang/String;
      22: ifnull        35
      25: aload_3
      26: aload_2
      27: invokevirtual #62                 // Method org/graylog2/rest/models/dashboards/requests/UpdateDashboardRequest.title:()Ljava/lang/String;
      30: invokeinterface #63,  2           // InterfaceMethod org/graylog2/dashboards/Dashboard.setTitle:(Ljava/lang/String;)V
      35: aload_2
      36: invokevirtual #64                 // Method org/graylog2/rest/models/dashboards/requests/UpdateDashboardRequest.description:()Ljava/lang/String;
      39: ifnull        52
      42: aload_3
      43: aload_2
      44: invokevirtual #64                 // Method org/graylog2/rest/models/dashboards/requests/UpdateDashboardRequest.description:()Ljava/lang/String;
      47: invokeinterface #65,  2           // InterfaceMethod org/graylog2/dashboards/Dashboard.setDescription:(Ljava/lang/String;)V
      52: aload_0
      53: getfield      #2                  // Field dashboardService:Lorg/graylog2/dashboards/DashboardService;
      56: aload_3
      57: invokeinterface #10,  2           // InterfaceMethod org/graylog2/dashboards/DashboardService.save:(Lorg/graylog2/plugin/database/Persisted;)Ljava/lang/String;
      62: pop
      63: return

  public void setPositions(java.lang.String, org.graylog2.rest.models.dashboards.requests.WidgetPositionsRequest) throws org.graylog2.database.NotFoundException, org.graylog2.plugin.database.ValidationException;
    Code:
       0: aload_0
       1: ldc           #53                 // String dashboards:edit
       3: aload_1
       4: invokevirtual #51                 // Method checkPermission:(Ljava/lang/String;Ljava/lang/String;)V
       7: aload_0
       8: getfield      #2                  // Field dashboardService:Lorg/graylog2/dashboards/DashboardService;
      11: aload_1
      12: invokeinterface #52,  2           // InterfaceMethod org/graylog2/dashboards/DashboardService.load:(Ljava/lang/String;)Lorg/graylog2/dashboards/Dashboard;
      17: astore_3
      18: aload_0
      19: getfield      #2                  // Field dashboardService:Lorg/graylog2/dashboards/DashboardService;
      22: aload_3
      23: aload_2
      24: invokeinterface #66,  3           // InterfaceMethod org/graylog2/dashboards/DashboardService.updateWidgetPositions:(Lorg/graylog2/dashboards/Dashboard;Lorg/graylog2/rest/models/dashboards/requests/WidgetPositionsRequest;)V
      29: return

  static {};
    Code:
       0: ldc           #14                 // class org/graylog2/rest/resources/dashboards/DashboardsResource
       2: invokestatic  #67                 // Method org/slf4j/LoggerFactory.getLogger:(Ljava/lang/Class;)Lorg/slf4j/Logger;
       5: putstatic     #57                 // Field LOG:Lorg/slf4j/Logger;
       8: return
}
