Compiled from "LazyJavaAnnotationDescriptor.kt"
final class kotlin.reflect.jvm.internal.impl.load.java.lazy.descriptors.LazyJavaAnnotationDescriptor$allValueArguments$2 extends kotlin.jvm.internal.Lambda implements kotlin.jvm.functions.Function0<java.util.Map<kotlin.reflect.jvm.internal.impl.name.Name, ? extends kotlin.reflect.jvm.internal.impl.resolve.constants.ConstantValue<?>>> {
  final kotlin.reflect.jvm.internal.impl.load.java.lazy.descriptors.LazyJavaAnnotationDescriptor this$0;

  kotlin.reflect.jvm.internal.impl.load.java.lazy.descriptors.LazyJavaAnnotationDescriptor$allValueArguments$2(kotlin.reflect.jvm.internal.impl.load.java.lazy.descriptors.LazyJavaAnnotationDescriptor);
    Code:
       0: aload_0
       1: aload_1
       2: putfield      #19                 // Field this$0:Lkotlin/reflect/jvm/internal/impl/load/java/lazy/descriptors/LazyJavaAnnotationDescriptor;
       5: aload_0
       6: iconst_0
       7: invokespecial #23                 // Method kotlin/jvm/internal/Lambda."<init>":(I)V
      10: return

  public final java.util.Map<kotlin.reflect.jvm.internal.impl.name.Name, kotlin.reflect.jvm.internal.impl.resolve.constants.ConstantValue<?>> invoke();
    Code:
       0: aload_0
       1: getfield      #19                 // Field this$0:Lkotlin/reflect/jvm/internal/impl/load/java/lazy/descriptors/LazyJavaAnnotationDescriptor;
       4: invokestatic  #24                 // Method kotlin/reflect/jvm/internal/impl/load/java/lazy/descriptors/LazyJavaAnnotationDescriptor.access$getJavaAnnotation$p:(Lkotlin/reflect/jvm/internal/impl/load/java/lazy/descriptors/LazyJavaAnnotationDescriptor;)Lkotlin/reflect/jvm/internal/impl/load/java/structure/JavaAnnotation;
       7: invokeinterface #31,  1           // InterfaceMethod kotlin/reflect/jvm/internal/impl/load/java/structure/JavaAnnotation.getArguments:()Ljava/util/Collection;
      12: checkcast     #1                  // class java/lang/Iterable
      15: astore_1
      16: aload_0
      17: getfield      #19                 // Field this$0:Lkotlin/reflect/jvm/internal/impl/load/java/lazy/descriptors/LazyJavaAnnotationDescriptor;
      20: astore_2
      21: iconst_0
      22: istore_3
      23: aload_1
      24: astore        4
      26: new           #2                  // class java/util/ArrayList
      29: dup
      30: invokespecial #20                 // Method java/util/ArrayList."<init>":()V
      33: checkcast     #3                  // class java/util/Collection
      36: astore        5
      38: iconst_0
      39: istore        6
      41: aload         4
      43: astore        7
      45: iconst_0
      46: istore        8
      48: aload         7
      50: invokeinterface #27,  1           // InterfaceMethod java/lang/Iterable.iterator:()Ljava/util/Iterator;
      55: astore        9
      57: aload         9
      59: invokeinterface #29,  1           // InterfaceMethod java/util/Iterator.hasNext:()Z
      64: ifeq          164
      67: aload         9
      69: invokeinterface #30,  1           // InterfaceMethod java/util/Iterator.next:()Ljava/lang/Object;
      74: astore        10
      76: aload         10
      78: astore        11
      80: iconst_0
      81: istore        12
      83: aload         11
      85: checkcast     #15                 // class kotlin/reflect/jvm/internal/impl/load/java/structure/JavaAnnotationArgument
      88: astore        13
      90: iconst_0
      91: istore        14
      93: aload         13
      95: invokeinterface #32,  1           // InterfaceMethod kotlin/reflect/jvm/internal/impl/load/java/structure/JavaAnnotationArgument.getName:()Lkotlin/reflect/jvm/internal/impl/name/Name;
     100: dup
     101: ifnonnull     108
     104: pop
     105: getstatic     #18                 // Field kotlin/reflect/jvm/internal/impl/load/java/JvmAnnotationNames.DEFAULT_ANNOTATION_MEMBER_NAME:Lkotlin/reflect/jvm/internal/impl/name/Name;
     108: astore        15
     110: aload_2
     111: aload         13
     113: invokestatic  #25                 // Method kotlin/reflect/jvm/internal/impl/load/java/lazy/descriptors/LazyJavaAnnotationDescriptor.access$resolveAnnotationArgument:(Lkotlin/reflect/jvm/internal/impl/load/java/lazy/descriptors/LazyJavaAnnotationDescriptor;Lkotlin/reflect/jvm/internal/impl/load/java/structure/JavaAnnotationArgument;)Lkotlin/reflect/jvm/internal/impl/resolve/constants/ConstantValue;
     116: dup
     117: ifnull        135
     120: astore        16
     122: iconst_0
     123: istore        17
     125: aload         15
     127: aload         16
     129: invokestatic  #21                 // Method kotlin/TuplesKt.to:(Ljava/lang/Object;Ljava/lang/Object;)Lkotlin/Pair;
     132: goto          137
     135: pop
     136: aconst_null
     137: dup
     138: ifnull        159
     141: astore        18
     143: iconst_0
     144: istore        19
     146: aload         5
     148: aload         18
     150: invokeinterface #28,  2           // InterfaceMethod java/util/Collection.add:(Ljava/lang/Object;)Z
     155: pop
     156: goto          160
     159: pop
     160: nop
     161: goto          57
     164: nop
     165: aload         5
     167: checkcast     #5                  // class java/util/List
     170: nop
     171: checkcast     #1                  // class java/lang/Iterable
     174: invokestatic  #22                 // Method kotlin/collections/MapsKt.toMap:(Ljava/lang/Iterable;)Ljava/util/Map;
     177: areturn

  public java.lang.Object invoke();
    Code:
       0: aload_0
       1: invokevirtual #26                 // Method invoke:()Ljava/util/Map;
       4: areturn
}
