Compiled from "LazyJavaScope.kt"
final class kotlin.reflect.jvm.internal.impl.load.java.lazy.descriptors.LazyJavaScope$declaredMemberIndex$1 extends kotlin.jvm.internal.Lambda implements kotlin.jvm.functions.Function0<kotlin.reflect.jvm.internal.impl.load.java.lazy.descriptors.DeclaredMemberIndex> {
  final kotlin.reflect.jvm.internal.impl.load.java.lazy.descriptors.LazyJavaScope this$0;

  kotlin.reflect.jvm.internal.impl.load.java.lazy.descriptors.LazyJavaScope$declaredMemberIndex$1(kotlin.reflect.jvm.internal.impl.load.java.lazy.descriptors.LazyJavaScope);
    Code:
       0: aload_0
       1: aload_1
       2: putfield      #5                  // Field this$0:Lkotlin/reflect/jvm/internal/impl/load/java/lazy/descriptors/LazyJavaScope;
       5: aload_0
       6: iconst_0
       7: invokespecial #6                  // Method kotlin/jvm/internal/Lambda."<init>":(I)V
      10: return

  public final kotlin.reflect.jvm.internal.impl.load.java.lazy.descriptors.DeclaredMemberIndex invoke();
    Code:
       0: aload_0
       1: getfield      #5                  // Field this$0:Lkotlin/reflect/jvm/internal/impl/load/java/lazy/descriptors/LazyJavaScope;
       4: invokevirtual #7                  // Method kotlin/reflect/jvm/internal/impl/load/java/lazy/descriptors/LazyJavaScope.computeMemberIndex:()Lkotlin/reflect/jvm/internal/impl/load/java/lazy/descriptors/DeclaredMemberIndex;
       7: areturn

  public java.lang.Object invoke();
    Code:
       0: aload_0
       1: invokevirtual #8                  // Method invoke:()Lkotlin/reflect/jvm/internal/impl/load/java/lazy/descriptors/DeclaredMemberIndex;
       4: areturn
}
