Compiled from "LazyJavaScope.kt"
final class kotlin.reflect.jvm.internal.impl.load.java.lazy.descriptors.LazyJavaScope$functions$1 extends kotlin.jvm.internal.Lambda implements kotlin.jvm.functions.Function1<kotlin.reflect.jvm.internal.impl.name.Name, java.util.Collection<? extends kotlin.reflect.jvm.internal.impl.descriptors.SimpleFunctionDescriptor>> {
  final kotlin.reflect.jvm.internal.impl.load.java.lazy.descriptors.LazyJavaScope this$0;

  kotlin.reflect.jvm.internal.impl.load.java.lazy.descriptors.LazyJavaScope$functions$1(kotlin.reflect.jvm.internal.impl.load.java.lazy.descriptors.LazyJavaScope);
    Code:
       0: aload_0
       1: aload_1
       2: putfield      #17                 // Field this$0:Lkotlin/reflect/jvm/internal/impl/load/java/lazy/descriptors/LazyJavaScope;
       5: aload_0
       6: iconst_1
       7: invokespecial #21                 // Method kotlin/jvm/internal/Lambda."<init>":(I)V
      10: return

  public final java.util.Collection<kotlin.reflect.jvm.internal.impl.descriptors.SimpleFunctionDescriptor> invoke(kotlin.reflect.jvm.internal.impl.name.Name);
    Code:
       0: aload_1
       1: ldc           #1                  // String name
       3: invokestatic  #20                 // Method kotlin/jvm/internal/Intrinsics.checkNotNullParameter:(Ljava/lang/Object;Ljava/lang/String;)V
       6: new           #4                  // class java/util/LinkedHashSet
       9: dup
      10: aload_0
      11: getfield      #17                 // Field this$0:Lkotlin/reflect/jvm/internal/impl/load/java/lazy/descriptors/LazyJavaScope;
      14: invokestatic  #24                 // Method kotlin/reflect/jvm/internal/impl/load/java/lazy/descriptors/LazyJavaScope.access$getDeclaredFunctions$p:(Lkotlin/reflect/jvm/internal/impl/load/java/lazy/descriptors/LazyJavaScope;)Lkotlin/reflect/jvm/internal/impl/storage/MemoizedFunctionToNotNull;
      17: aload_1
      18: invokeinterface #30,  2           // InterfaceMethod kotlin/reflect/jvm/internal/impl/storage/MemoizedFunctionToNotNull.invoke:(Ljava/lang/Object;)Ljava/lang/Object;
      23: checkcast     #3                  // class java/util/Collection
      26: invokespecial #18                 // Method java/util/LinkedHashSet."<init>":(Ljava/util/Collection;)V
      29: astore_2
      30: aload_0
      31: getfield      #17                 // Field this$0:Lkotlin/reflect/jvm/internal/impl/load/java/lazy/descriptors/LazyJavaScope;
      34: aload_2
      35: checkcast     #5                  // class java/util/Set
      38: invokestatic  #25                 // Method kotlin/reflect/jvm/internal/impl/load/java/lazy/descriptors/LazyJavaScope.access$retainMostSpecificMethods:(Lkotlin/reflect/jvm/internal/impl/load/java/lazy/descriptors/LazyJavaScope;Ljava/util/Set;)V
      41: aload_0
      42: getfield      #17                 // Field this$0:Lkotlin/reflect/jvm/internal/impl/load/java/lazy/descriptors/LazyJavaScope;
      45: aload_2
      46: checkcast     #3                  // class java/util/Collection
      49: aload_1
      50: invokevirtual #26                 // Method kotlin/reflect/jvm/internal/impl/load/java/lazy/descriptors/LazyJavaScope.computeNonDeclaredFunctions:(Ljava/util/Collection;Lkotlin/reflect/jvm/internal/impl/name/Name;)V
      53: aload_0
      54: getfield      #17                 // Field this$0:Lkotlin/reflect/jvm/internal/impl/load/java/lazy/descriptors/LazyJavaScope;
      57: invokevirtual #27                 // Method kotlin/reflect/jvm/internal/impl/load/java/lazy/descriptors/LazyJavaScope.getC:()Lkotlin/reflect/jvm/internal/impl/load/java/lazy/LazyJavaResolverContext;
      60: invokevirtual #23                 // Method kotlin/reflect/jvm/internal/impl/load/java/lazy/LazyJavaResolverContext.getComponents:()Lkotlin/reflect/jvm/internal/impl/load/java/lazy/JavaResolverComponents;
      63: invokevirtual #22                 // Method kotlin/reflect/jvm/internal/impl/load/java/lazy/JavaResolverComponents.getSignatureEnhancement:()Lkotlin/reflect/jvm/internal/impl/load/java/typeEnhancement/SignatureEnhancement;
      66: aload_0
      67: getfield      #17                 // Field this$0:Lkotlin/reflect/jvm/internal/impl/load/java/lazy/descriptors/LazyJavaScope;
      70: invokevirtual #27                 // Method kotlin/reflect/jvm/internal/impl/load/java/lazy/descriptors/LazyJavaScope.getC:()Lkotlin/reflect/jvm/internal/impl/load/java/lazy/LazyJavaResolverContext;
      73: aload_2
      74: checkcast     #3                  // class java/util/Collection
      77: invokevirtual #29                 // Method kotlin/reflect/jvm/internal/impl/load/java/typeEnhancement/SignatureEnhancement.enhanceSignatures:(Lkotlin/reflect/jvm/internal/impl/load/java/lazy/LazyJavaResolverContext;Ljava/util/Collection;)Ljava/util/Collection;
      80: checkcast     #2                  // class java/lang/Iterable
      83: invokestatic  #19                 // Method kotlin/collections/CollectionsKt.toList:(Ljava/lang/Iterable;)Ljava/util/List;
      86: checkcast     #3                  // class java/util/Collection
      89: areturn

  public java.lang.Object invoke(java.lang.Object);
    Code:
       0: aload_0
       1: aload_1
       2: checkcast     #15                 // class kotlin/reflect/jvm/internal/impl/name/Name
       5: invokevirtual #28                 // Method invoke:(Lkotlin/reflect/jvm/internal/impl/name/Name;)Ljava/util/Collection;
       8: areturn
}
