Compiled from "UndertowLogger_$logger.java"
public class io.undertow.UndertowLogger_$logger extends org.jboss.logging.DelegatingBasicLogger implements io.undertow.UndertowLogger,org.jboss.logging.BasicLogger,java.io.Serializable {
  private static final long serialVersionUID;

  private static final java.lang.String FQCN;

  private static final java.util.Locale LOCALE;

  public io.undertow.UndertowLogger_$logger(org.jboss.logging.Logger);
    Code:
       0: aload_0
       1: aload_1
       2: invokespecial #1                  // Method org/jboss/logging/DelegatingBasicLogger."<init>":(Lorg/jboss/logging/Logger;)V
       5: return

  protected java.util.Locale getLoggingLocale();
    Code:
       0: getstatic     #2                  // Field LOCALE:Ljava/util/Locale;
       3: areturn

  public final void exceptionProcessingRequest(java.lang.Throwable);
    Code:
       0: aload_0
       1: getfield      #3                  // Field org/jboss/logging/DelegatingBasicLogger.log:Lorg/jboss/logging/Logger;
       4: getstatic     #4                  // Field FQCN:Ljava/lang/String;
       7: getstatic     #5                  // Field org/jboss/logging/Logger$Level.ERROR:Lorg/jboss/logging/Logger$Level;
      10: aload_1
      11: aload_0
      12: invokevirtual #6                  // Method exceptionProcessingRequest$str:()Ljava/lang/String;
      15: iconst_0
      16: anewarray     #7                  // class java/lang/Object
      19: invokevirtual #8                  // Method org/jboss/logging/Logger.logf:(Ljava/lang/String;Lorg/jboss/logging/Logger$Level;Ljava/lang/Throwable;Ljava/lang/String;[Ljava/lang/Object;)V
      22: return

  protected java.lang.String exceptionProcessingRequest$str();
    Code:
       0: ldc           #9                  // String UT005001: An exception occurred processing the request
       2: areturn

  public final void ioExceptionReadingFromChannel(java.io.IOException);
    Code:
       0: aload_0
       1: getfield      #3                  // Field org/jboss/logging/DelegatingBasicLogger.log:Lorg/jboss/logging/Logger;
       4: getstatic     #4                  // Field FQCN:Ljava/lang/String;
       7: getstatic     #5                  // Field org/jboss/logging/Logger$Level.ERROR:Lorg/jboss/logging/Logger$Level;
      10: aload_1
      11: aload_0
      12: invokevirtual #10                 // Method ioExceptionReadingFromChannel$str:()Ljava/lang/String;
      15: iconst_0
      16: anewarray     #7                  // class java/lang/Object
      19: invokevirtual #8                  // Method org/jboss/logging/Logger.logf:(Ljava/lang/String;Lorg/jboss/logging/Logger$Level;Ljava/lang/Throwable;Ljava/lang/String;[Ljava/lang/Object;)V
      22: return

  protected java.lang.String ioExceptionReadingFromChannel$str();
    Code:
       0: ldc           #11                 // String UT005003: IOException reading from channel
       2: areturn

  public final void cannotRemoveUploadedFile(java.nio.file.Path);
    Code:
       0: aload_0
       1: getfield      #3                  // Field org/jboss/logging/DelegatingBasicLogger.log:Lorg/jboss/logging/Logger;
       4: getstatic     #4                  // Field FQCN:Ljava/lang/String;
       7: getstatic     #5                  // Field org/jboss/logging/Logger$Level.ERROR:Lorg/jboss/logging/Logger$Level;
      10: aconst_null
      11: aload_0
      12: invokevirtual #12                 // Method cannotRemoveUploadedFile$str:()Ljava/lang/String;
      15: aload_1
      16: invokevirtual #13                 // Method org/jboss/logging/Logger.logf:(Ljava/lang/String;Lorg/jboss/logging/Logger$Level;Ljava/lang/Throwable;Ljava/lang/String;Ljava/lang/Object;)V
      19: return

  protected java.lang.String cannotRemoveUploadedFile$str();
    Code:
       0: ldc           #14                 // String UT005005: Cannot remove uploaded file %s
       2: areturn

  public final void requestHeaderWasTooLarge(java.net.SocketAddress, int);
    Code:
       0: aload_0
       1: getfield      #3                  // Field org/jboss/logging/DelegatingBasicLogger.log:Lorg/jboss/logging/Logger;
       4: getstatic     #4                  // Field FQCN:Ljava/lang/String;
       7: getstatic     #15                 // Field org/jboss/logging/Logger$Level.DEBUG:Lorg/jboss/logging/Logger$Level;
      10: aconst_null
      11: aload_0
      12: invokevirtual #16                 // Method requestHeaderWasTooLarge$str:()Ljava/lang/String;
      15: aload_1
      16: iload_2
      17: invokestatic  #17                 // Method java/lang/Integer.valueOf:(I)Ljava/lang/Integer;
      20: invokevirtual #18                 // Method org/jboss/logging/Logger.logf:(Ljava/lang/String;Lorg/jboss/logging/Logger$Level;Ljava/lang/Throwable;Ljava/lang/String;Ljava/lang/Object;Ljava/lang/Object;)V
      23: return

  protected java.lang.String requestHeaderWasTooLarge$str();
    Code:
       0: ldc           #19                 // String UT005006: Connection from %s terminated as request header was larger than %s
       2: areturn

  public final void requestWasNotFullyConsumed();
    Code:
       0: aload_0
       1: getfield      #3                  // Field org/jboss/logging/DelegatingBasicLogger.log:Lorg/jboss/logging/Logger;
       4: getstatic     #4                  // Field FQCN:Ljava/lang/String;
       7: getstatic     #15                 // Field org/jboss/logging/Logger$Level.DEBUG:Lorg/jboss/logging/Logger$Level;
      10: aconst_null
      11: aload_0
      12: invokevirtual #20                 // Method requestWasNotFullyConsumed$str:()Ljava/lang/String;
      15: iconst_0
      16: anewarray     #7                  // class java/lang/Object
      19: invokevirtual #8                  // Method org/jboss/logging/Logger.logf:(Ljava/lang/String;Lorg/jboss/logging/Logger$Level;Ljava/lang/Throwable;Ljava/lang/String;[Ljava/lang/Object;)V
      22: return

  protected java.lang.String requestWasNotFullyConsumed$str();
    Code:
       0: ldc           #21                 // String UT005007: Request was not fully consumed
       2: areturn

  public final void invalidTokenReceived(java.lang.String, java.lang.String);
    Code:
       0: aload_0
       1: getfield      #3                  // Field org/jboss/logging/DelegatingBasicLogger.log:Lorg/jboss/logging/Logger;
       4: getstatic     #4                  // Field FQCN:Ljava/lang/String;
       7: getstatic     #15                 // Field org/jboss/logging/Logger$Level.DEBUG:Lorg/jboss/logging/Logger$Level;
      10: aconst_null
      11: aload_0
      12: invokevirtual #22                 // Method invalidTokenReceived$str:()Ljava/lang/String;
      15: aload_1
      16: aload_2
      17: invokevirtual #18                 // Method org/jboss/logging/Logger.logf:(Ljava/lang/String;Lorg/jboss/logging/Logger$Level;Ljava/lang/Throwable;Ljava/lang/String;Ljava/lang/Object;Ljava/lang/Object;)V
      20: return

  protected java.lang.String invalidTokenReceived$str();
    Code:
       0: ldc           #23                 // String UT005008: An invalid token \'%s\' with value \'%s\' has been received.
       2: areturn

  public final void missingAuthorizationToken(java.lang.String);
    Code:
       0: aload_0
       1: getfield      #3                  // Field org/jboss/logging/DelegatingBasicLogger.log:Lorg/jboss/logging/Logger;
       4: getstatic     #4                  // Field FQCN:Ljava/lang/String;
       7: getstatic     #15                 // Field org/jboss/logging/Logger$Level.DEBUG:Lorg/jboss/logging/Logger$Level;
      10: aconst_null
      11: aload_0
      12: invokevirtual #24                 // Method missingAuthorizationToken$str:()Ljava/lang/String;
      15: aload_1
      16: invokevirtual #13                 // Method org/jboss/logging/Logger.logf:(Ljava/lang/String;Lorg/jboss/logging/Logger$Level;Ljava/lang/Throwable;Ljava/lang/String;Ljava/lang/Object;)V
      19: return

  protected java.lang.String missingAuthorizationToken$str();
    Code:
       0: ldc           #25                 // String UT005009: A mandatory token %s is missing from the request.
       2: areturn

  public final void authenticationFailed(java.lang.String, java.lang.String);
    Code:
       0: aload_0
       1: getfield      #3                  // Field org/jboss/logging/DelegatingBasicLogger.log:Lorg/jboss/logging/Logger;
       4: getstatic     #4                  // Field FQCN:Ljava/lang/String;
       7: getstatic     #15                 // Field org/jboss/logging/Logger$Level.DEBUG:Lorg/jboss/logging/Logger$Level;
      10: aconst_null
      11: aload_0
      12: invokevirtual #26                 // Method authenticationFailed$str:()Ljava/lang/String;
      15: aload_1
      16: aload_2
      17: invokevirtual #18                 // Method org/jboss/logging/Logger.logf:(Ljava/lang/String;Lorg/jboss/logging/Logger$Level;Ljava/lang/Throwable;Ljava/lang/String;Ljava/lang/Object;Ljava/lang/Object;)V
      20: return

  protected java.lang.String authenticationFailed$str();
    Code:
       0: ldc           #27                 // String UT005010: Verification of authentication tokens for user \'%s\' has failed using mechanism \'%s\'.
       2: areturn

  public final void ignoringAjpRequestWithPrefixCode(byte);
    Code:
       0: aload_0
       1: getfield      #3                  // Field org/jboss/logging/DelegatingBasicLogger.log:Lorg/jboss/logging/Logger;
       4: getstatic     #4                  // Field FQCN:Ljava/lang/String;
       7: getstatic     #5                  // Field org/jboss/logging/Logger$Level.ERROR:Lorg/jboss/logging/Logger$Level;
      10: aconst_null
      11: aload_0
      12: invokevirtual #28                 // Method ignoringAjpRequestWithPrefixCode$str:()Ljava/lang/String;
      15: iload_1
      16: invokestatic  #29                 // Method java/lang/Byte.valueOf:(B)Ljava/lang/Byte;
      19: invokevirtual #13                 // Method org/jboss/logging/Logger.logf:(Ljava/lang/String;Lorg/jboss/logging/Logger$Level;Ljava/lang/Throwable;Ljava/lang/String;Ljava/lang/Object;)V
      22: return

  protected java.lang.String ignoringAjpRequestWithPrefixCode$str();
    Code:
       0: ldc           #30                 // String UT005011: Ignoring AJP request with prefix %s
       2: areturn

  public final void ioException(java.io.IOException);
    Code:
       0: aload_0
       1: getfield      #3                  // Field org/jboss/logging/DelegatingBasicLogger.log:Lorg/jboss/logging/Logger;
       4: getstatic     #4                  // Field FQCN:Ljava/lang/String;
       7: getstatic     #15                 // Field org/jboss/logging/Logger$Level.DEBUG:Lorg/jboss/logging/Logger$Level;
      10: aload_1
      11: aload_0
      12: invokevirtual #31                 // Method ioException$str:()Ljava/lang/String;
      15: iconst_0
      16: anewarray     #7                  // class java/lang/Object
      19: invokevirtual #8                  // Method org/jboss/logging/Logger.logf:(Ljava/lang/String;Lorg/jboss/logging/Logger$Level;Ljava/lang/Throwable;Ljava/lang/String;[Ljava/lang/Object;)V
      22: return

  protected java.lang.String ioException$str();
    Code:
       0: ldc           #32                 // String UT005013: An IOException occurred
       2: areturn

  public final void failedToParseRequest(java.lang.Throwable);
    Code:
       0: aload_0
       1: getfield      #3                  // Field org/jboss/logging/DelegatingBasicLogger.log:Lorg/jboss/logging/Logger;
       4: getstatic     #4                  // Field FQCN:Ljava/lang/String;
       7: getstatic     #15                 // Field org/jboss/logging/Logger$Level.DEBUG:Lorg/jboss/logging/Logger$Level;
      10: aload_1
      11: aload_0
      12: invokevirtual #33                 // Method failedToParseRequest$str:()Ljava/lang/String;
      15: iconst_0
      16: anewarray     #7                  // class java/lang/Object
      19: invokevirtual #8                  // Method org/jboss/logging/Logger.logf:(Ljava/lang/String;Lorg/jboss/logging/Logger$Level;Ljava/lang/Throwable;Ljava/lang/String;[Ljava/lang/Object;)V
      22: return

  protected java.lang.String failedToParseRequest$str();
    Code:
       0: ldc           #34                 // String UT005014: Failed to parse request
       2: areturn

  public final void errorRotatingAccessLog(java.io.IOException);
    Code:
       0: aload_0
       1: getfield      #3                  // Field org/jboss/logging/DelegatingBasicLogger.log:Lorg/jboss/logging/Logger;
       4: getstatic     #4                  // Field FQCN:Ljava/lang/String;
       7: getstatic     #5                  // Field org/jboss/logging/Logger$Level.ERROR:Lorg/jboss/logging/Logger$Level;
      10: aload_1
      11: aload_0
      12: invokevirtual #35                 // Method errorRotatingAccessLog$str:()Ljava/lang/String;
      15: iconst_0
      16: anewarray     #7                  // class java/lang/Object
      19: invokevirtual #8                  // Method org/jboss/logging/Logger.logf:(Ljava/lang/String;Lorg/jboss/logging/Logger$Level;Ljava/lang/Throwable;Ljava/lang/String;[Ljava/lang/Object;)V
      22: return

  protected java.lang.String errorRotatingAccessLog$str();
    Code:
       0: ldc           #36                 // String UT005015: Error rotating access log
       2: areturn

  public final void errorWritingAccessLog(java.io.IOException);
    Code:
       0: aload_0
       1: getfield      #3                  // Field org/jboss/logging/DelegatingBasicLogger.log:Lorg/jboss/logging/Logger;
       4: getstatic     #4                  // Field FQCN:Ljava/lang/String;
       7: getstatic     #5                  // Field org/jboss/logging/Logger$Level.ERROR:Lorg/jboss/logging/Logger$Level;
      10: aload_1
      11: aload_0
      12: invokevirtual #37                 // Method errorWritingAccessLog$str:()Ljava/lang/String;
      15: iconst_0
      16: anewarray     #7                  // class java/lang/Object
      19: invokevirtual #8                  // Method org/jboss/logging/Logger.logf:(Ljava/lang/String;Lorg/jboss/logging/Logger$Level;Ljava/lang/Throwable;Ljava/lang/String;[Ljava/lang/Object;)V
      22: return

  protected java.lang.String errorWritingAccessLog$str();
    Code:
       0: ldc           #38                 // String UT005016: Error writing access log
       2: areturn

  public final void unknownVariable(java.lang.String);
    Code:
       0: aload_0
       1: getfield      #3                  // Field org/jboss/logging/DelegatingBasicLogger.log:Lorg/jboss/logging/Logger;
       4: getstatic     #4                  // Field FQCN:Ljava/lang/String;
       7: getstatic     #5                  // Field org/jboss/logging/Logger$Level.ERROR:Lorg/jboss/logging/Logger$Level;
      10: aconst_null
      11: aload_0
      12: invokevirtual #39                 // Method unknownVariable$str:()Ljava/lang/String;
      15: aload_1
      16: invokevirtual #13                 // Method org/jboss/logging/Logger.logf:(Ljava/lang/String;Lorg/jboss/logging/Logger$Level;Ljava/lang/Throwable;Ljava/lang/String;Ljava/lang/Object;)V
      19: return

  protected java.lang.String unknownVariable$str();
    Code:
       0: ldc           #40                 // String UT005017: Unknown variable %s. For the literal percent character use two percent characters: \'%%\'
       2: areturn

  public final void exceptionInvokingCloseListener(io.undertow.server.ServerConnection$CloseListener, java.lang.Throwable);
    Code:
       0: aload_0
       1: getfield      #3                  // Field org/jboss/logging/DelegatingBasicLogger.log:Lorg/jboss/logging/Logger;
       4: getstatic     #4                  // Field FQCN:Ljava/lang/String;
       7: getstatic     #5                  // Field org/jboss/logging/Logger$Level.ERROR:Lorg/jboss/logging/Logger$Level;
      10: aload_2
      11: aload_0
      12: invokevirtual #41                 // Method exceptionInvokingCloseListener$str:()Ljava/lang/String;
      15: aload_1
      16: invokevirtual #13                 // Method org/jboss/logging/Logger.logf:(Ljava/lang/String;Lorg/jboss/logging/Logger$Level;Ljava/lang/Throwable;Ljava/lang/String;Ljava/lang/Object;)V
      19: return

  protected java.lang.String exceptionInvokingCloseListener$str();
    Code:
       0: ldc           #42                 // String UT005018: Exception invoking close listener %s
       2: areturn

  public final void errorWritingJDBCLog(java.lang.Exception);
    Code:
       0: aload_0
       1: getfield      #3                  // Field org/jboss/logging/DelegatingBasicLogger.log:Lorg/jboss/logging/Logger;
       4: getstatic     #4                  // Field FQCN:Ljava/lang/String;
       7: getstatic     #5                  // Field org/jboss/logging/Logger$Level.ERROR:Lorg/jboss/logging/Logger$Level;
      10: aload_1
      11: aload_0
      12: invokevirtual #43                 // Method errorWritingJDBCLog$str:()Ljava/lang/String;
      15: iconst_0
      16: anewarray     #7                  // class java/lang/Object
      19: invokevirtual #8                  // Method org/jboss/logging/Logger.logf:(Ljava/lang/String;Lorg/jboss/logging/Logger$Level;Ljava/lang/Throwable;Ljava/lang/String;[Ljava/lang/Object;)V
      22: return

  protected java.lang.String errorWritingJDBCLog$str();
    Code:
       0: ldc           #44                 // String UT005020: Error writing JDBC log
       2: areturn

  public final void exceptionGeneratingErrorPage(java.lang.Exception, java.lang.String);
    Code:
       0: aload_0
       1: getfield      #3                  // Field org/jboss/logging/DelegatingBasicLogger.log:Lorg/jboss/logging/Logger;
       4: getstatic     #4                  // Field FQCN:Ljava/lang/String;
       7: getstatic     #5                  // Field org/jboss/logging/Logger$Level.ERROR:Lorg/jboss/logging/Logger$Level;
      10: aload_1
      11: aload_0
      12: invokevirtual #45                 // Method exceptionGeneratingErrorPage$str:()Ljava/lang/String;
      15: aload_2
      16: invokevirtual #13                 // Method org/jboss/logging/Logger.logf:(Ljava/lang/String;Lorg/jboss/logging/Logger$Level;Ljava/lang/Throwable;Ljava/lang/String;Ljava/lang/Object;)V
      19: return

  protected java.lang.String exceptionGeneratingErrorPage$str();
    Code:
       0: ldc           #46                 // String UT005022: Exception generating error page %s
       2: areturn

  public final void exceptionHandlingRequest(java.lang.Throwable, java.lang.String);
    Code:
       0: aload_0
       1: getfield      #3                  // Field org/jboss/logging/DelegatingBasicLogger.log:Lorg/jboss/logging/Logger;
       4: getstatic     #4                  // Field FQCN:Ljava/lang/String;
       7: getstatic     #5                  // Field org/jboss/logging/Logger$Level.ERROR:Lorg/jboss/logging/Logger$Level;
      10: aload_1
      11: aload_0
      12: invokevirtual #47                 // Method exceptionHandlingRequest$str:()Ljava/lang/String;
      15: aload_2
      16: invokevirtual #13                 // Method org/jboss/logging/Logger.logf:(Ljava/lang/String;Lorg/jboss/logging/Logger$Level;Ljava/lang/Throwable;Ljava/lang/String;Ljava/lang/Object;)V
      19: return

  protected java.lang.String exceptionHandlingRequest$str();
    Code:
       0: ldc           #48                 // String UT005023: Exception handling request to %s
       2: areturn

  public final void couldNotRegisterChangeListener(java.lang.Exception);
    Code:
       0: aload_0
       1: getfield      #3                  // Field org/jboss/logging/DelegatingBasicLogger.log:Lorg/jboss/logging/Logger;
       4: getstatic     #4                  // Field FQCN:Ljava/lang/String;
       7: getstatic     #5                  // Field org/jboss/logging/Logger$Level.ERROR:Lorg/jboss/logging/Logger$Level;
      10: aload_1
      11: aload_0
      12: invokevirtual #49                 // Method couldNotRegisterChangeListener$str:()Ljava/lang/String;
      15: iconst_0
      16: anewarray     #7                  // class java/lang/Object
      19: invokevirtual #8                  // Method org/jboss/logging/Logger.logf:(Ljava/lang/String;Lorg/jboss/logging/Logger$Level;Ljava/lang/Throwable;Ljava/lang/String;[Ljava/lang/Object;)V
      22: return

  protected java.lang.String couldNotRegisterChangeListener$str();
    Code:
       0: ldc           #50                 // String UT005024: Could not register resource change listener for caching resource manager, automatic invalidation of cached resource will not work
       2: areturn

  public final void timingOutRequest(java.lang.String);
    Code:
       0: aload_0
       1: getfield      #3                  // Field org/jboss/logging/DelegatingBasicLogger.log:Lorg/jboss/logging/Logger;
       4: getstatic     #4                  // Field FQCN:Ljava/lang/String;
       7: getstatic     #5                  // Field org/jboss/logging/Logger$Level.ERROR:Lorg/jboss/logging/Logger$Level;
      10: aconst_null
      11: aload_0
      12: invokevirtual #51                 // Method timingOutRequest$str:()Ljava/lang/String;
      15: aload_1
      16: invokevirtual #13                 // Method org/jboss/logging/Logger.logf:(Ljava/lang/String;Lorg/jboss/logging/Logger$Level;Ljava/lang/Throwable;Ljava/lang/String;Ljava/lang/Object;)V
      19: return

  protected java.lang.String timingOutRequest$str();
    Code:
       0: ldc           #52                 // String UT005027: Timing out request to %s
       2: areturn

  public final void proxyRequestFailed(java.lang.String, java.lang.Exception);
    Code:
       0: aload_0
       1: getfield      #3                  // Field org/jboss/logging/DelegatingBasicLogger.log:Lorg/jboss/logging/Logger;
       4: getstatic     #4                  // Field FQCN:Ljava/lang/String;
       7: getstatic     #5                  // Field org/jboss/logging/Logger$Level.ERROR:Lorg/jboss/logging/Logger$Level;
      10: aload_2
      11: aload_0
      12: invokevirtual #53                 // Method proxyRequestFailed$str:()Ljava/lang/String;
      15: aload_1
      16: invokevirtual #13                 // Method org/jboss/logging/Logger.logf:(Ljava/lang/String;Lorg/jboss/logging/Logger$Level;Ljava/lang/Throwable;Ljava/lang/String;Ljava/lang/Object;)V
      19: return

  protected java.lang.String proxyRequestFailed$str();
    Code:
       0: ldc           #54                 // String UT005028: Proxy request to %s failed
       2: areturn

  public final void proxyFailedToConnectToBackend(java.lang.String, java.net.URI);
    Code:
       0: aload_0
       1: getfield      #3                  // Field org/jboss/logging/DelegatingBasicLogger.log:Lorg/jboss/logging/Logger;
       4: getstatic     #4                  // Field FQCN:Ljava/lang/String;
       7: getstatic     #5                  // Field org/jboss/logging/Logger$Level.ERROR:Lorg/jboss/logging/Logger$Level;
      10: aconst_null
      11: aload_0
      12: invokevirtual #55                 // Method proxyFailedToConnectToBackend$str:()Ljava/lang/String;
      15: aload_1
      16: aload_2
      17: invokevirtual #18                 // Method org/jboss/logging/Logger.logf:(Ljava/lang/String;Lorg/jboss/logging/Logger$Level;Ljava/lang/Throwable;Ljava/lang/String;Ljava/lang/Object;Ljava/lang/Object;)V
      20: return

  protected java.lang.String proxyFailedToConnectToBackend$str();
    Code:
       0: ldc           #56                 // String UT005031: Proxy request to %s could not connect to backend server %s
       2: areturn

  public final void listenerNotProgressing();
    Code:
       0: aload_0
       1: getfield      #3                  // Field org/jboss/logging/DelegatingBasicLogger.log:Lorg/jboss/logging/Logger;
       4: getstatic     #4                  // Field FQCN:Ljava/lang/String;
       7: getstatic     #5                  // Field org/jboss/logging/Logger$Level.ERROR:Lorg/jboss/logging/Logger$Level;
      10: aconst_null
      11: aload_0
      12: invokevirtual #57                 // Method listenerNotProgressing$str:()Ljava/lang/String;
      15: iconst_0
      16: anewarray     #7                  // class java/lang/Object
      19: invokevirtual #8                  // Method org/jboss/logging/Logger.logf:(Ljava/lang/String;Lorg/jboss/logging/Logger$Level;Ljava/lang/Throwable;Ljava/lang/String;[Ljava/lang/Object;)V
      22: return

  protected java.lang.String listenerNotProgressing$str();
    Code:
       0: ldc           #58                 // String UT005032: Listener not making progress on framed channel, closing channel to prevent infinite loop
       2: areturn

  public final void remoteEndpointFailedToSendInitialSettings(int);
    Code:
       0: aload_0
       1: getfield      #3                  // Field org/jboss/logging/DelegatingBasicLogger.log:Lorg/jboss/logging/Logger;
       4: getstatic     #4                  // Field FQCN:Ljava/lang/String;
       7: getstatic     #5                  // Field org/jboss/logging/Logger$Level.ERROR:Lorg/jboss/logging/Logger$Level;
      10: aconst_null
      11: aload_0
      12: invokevirtual #59                 // Method remoteEndpointFailedToSendInitialSettings$str:()Ljava/lang/String;
      15: iload_1
      16: invokestatic  #17                 // Method java/lang/Integer.valueOf:(I)Ljava/lang/Integer;
      19: invokevirtual #13                 // Method org/jboss/logging/Logger.logf:(Ljava/lang/String;Lorg/jboss/logging/Logger$Level;Ljava/lang/Throwable;Ljava/lang/String;Ljava/lang/Object;)V
      22: return

  protected java.lang.String remoteEndpointFailedToSendInitialSettings$str();
    Code:
       0: ldc           #60                 // String UT005034: Remote endpoint failed to send initial settings frame in HTTP2 connection, frame type %s
       2: areturn

  public final void parseRequestTimedOut(java.net.SocketAddress);
    Code:
       0: aload_0
       1: getfield      #3                  // Field org/jboss/logging/DelegatingBasicLogger.log:Lorg/jboss/logging/Logger;
       4: getstatic     #4                  // Field FQCN:Ljava/lang/String;
       7: getstatic     #15                 // Field org/jboss/logging/Logger$Level.DEBUG:Lorg/jboss/logging/Logger$Level;
      10: aconst_null
      11: aload_0
      12: invokevirtual #61                 // Method parseRequestTimedOut$str:()Ljava/lang/String;
      15: aload_1
      16: invokevirtual #13                 // Method org/jboss/logging/Logger.logf:(Ljava/lang/String;Lorg/jboss/logging/Logger$Level;Ljava/lang/Throwable;Ljava/lang/String;Ljava/lang/Object;)V
      19: return

  protected java.lang.String parseRequestTimedOut$str();
    Code:
       0: ldc           #62                 // String UT005035: Closing channel because of parse timeout for remote address %s
       2: areturn

  public final void noALPNFallback(java.net.SocketAddress);
    Code:
       0: aload_0
       1: getfield      #3                  // Field org/jboss/logging/DelegatingBasicLogger.log:Lorg/jboss/logging/Logger;
       4: getstatic     #4                  // Field FQCN:Ljava/lang/String;
       7: getstatic     #5                  // Field org/jboss/logging/Logger$Level.ERROR:Lorg/jboss/logging/Logger$Level;
      10: aconst_null
      11: aload_0
      12: invokevirtual #63                 // Method noALPNFallback$str:()Ljava/lang/String;
      15: aload_1
      16: invokevirtual #13                 // Method org/jboss/logging/Logger.logf:(Ljava/lang/String;Lorg/jboss/logging/Logger$Level;Ljava/lang/Throwable;Ljava/lang/String;Ljava/lang/Object;)V
      19: return

  protected java.lang.String noALPNFallback$str();
    Code:
       0: ldc           #64                 // String UT005036: ALPN negotiation failed for %s and no fallback defined, closing connection
       2: areturn

  public final void stickySessionCookieLengthTruncated(java.lang.String, java.lang.String);
    Code:
       0: aload_0
       1: getfield      #3                  // Field org/jboss/logging/DelegatingBasicLogger.log:Lorg/jboss/logging/Logger;
       4: getstatic     #4                  // Field FQCN:Ljava/lang/String;
       7: getstatic     #65                 // Field org/jboss/logging/Logger$Level.WARN:Lorg/jboss/logging/Logger$Level;
      10: aconst_null
      11: aload_0
      12: invokevirtual #66                 // Method stickySessionCookieLengthTruncated$str:()Ljava/lang/String;
      15: aload_1
      16: aload_2
      17: invokevirtual #18                 // Method org/jboss/logging/Logger.logf:(Ljava/lang/String;Lorg/jboss/logging/Logger$Level;Ljava/lang/Throwable;Ljava/lang/String;Ljava/lang/Object;Ljava/lang/Object;)V
      20: return

  protected java.lang.String stickySessionCookieLengthTruncated$str();
    Code:
       0: ldc           #67                 // String UT005037: Name of the cookie containing the session id, %s, had been too long and was truncated to: %s
       2: areturn

  public final void balancerCreated(int, java.lang.String, boolean, java.lang.String, java.lang.String, boolean, boolean, int, int);
    Code:
       0: aload_0
       1: getfield      #3                  // Field org/jboss/logging/DelegatingBasicLogger.log:Lorg/jboss/logging/Logger;
       4: getstatic     #4                  // Field FQCN:Ljava/lang/String;
       7: getstatic     #15                 // Field org/jboss/logging/Logger$Level.DEBUG:Lorg/jboss/logging/Logger$Level;
      10: aconst_null
      11: aload_0
      12: invokevirtual #68                 // Method balancerCreated$str:()Ljava/lang/String;
      15: bipush        9
      17: anewarray     #7                  // class java/lang/Object
      20: dup
      21: iconst_0
      22: iload_1
      23: invokestatic  #17                 // Method java/lang/Integer.valueOf:(I)Ljava/lang/Integer;
      26: aastore
      27: dup
      28: iconst_1
      29: aload_2
      30: aastore
      31: dup
      32: iconst_2
      33: iload_3
      34: invokestatic  #69                 // Method java/lang/Boolean.valueOf:(Z)Ljava/lang/Boolean;
      37: aastore
      38: dup
      39: iconst_3
      40: aload         4
      42: aastore
      43: dup
      44: iconst_4
      45: aload         5
      47: aastore
      48: dup
      49: iconst_5
      50: iload         6
      52: invokestatic  #69                 // Method java/lang/Boolean.valueOf:(Z)Ljava/lang/Boolean;
      55: aastore
      56: dup
      57: bipush        6
      59: iload         7
      61: invokestatic  #69                 // Method java/lang/Boolean.valueOf:(Z)Ljava/lang/Boolean;
      64: aastore
      65: dup
      66: bipush        7
      68: iload         8
      70: invokestatic  #17                 // Method java/lang/Integer.valueOf:(I)Ljava/lang/Integer;
      73: aastore
      74: dup
      75: bipush        8
      77: iload         9
      79: invokestatic  #17                 // Method java/lang/Integer.valueOf:(I)Ljava/lang/Integer;
      82: aastore
      83: invokevirtual #8                  // Method org/jboss/logging/Logger.logf:(Ljava/lang/String;Lorg/jboss/logging/Logger$Level;Ljava/lang/Throwable;Ljava/lang/String;[Ljava/lang/Object;)V
      86: return

  protected java.lang.String balancerCreated$str();
    Code:
       0: ldc           #70                 // String UT005038: Balancer created: id: %s, name: %s, stickySession: %s, stickySessionCookie: %s, stickySessionPath: %s, stickySessionRemove: %s, stickySessionForce: %s, waitWorker: %s, maxattempts: %s
       2: areturn

  public final void proxyAdvertisementsStarted(java.lang.String, int);
    Code:
       0: aload_0
       1: getfield      #3                  // Field org/jboss/logging/DelegatingBasicLogger.log:Lorg/jboss/logging/Logger;
       4: getstatic     #4                  // Field FQCN:Ljava/lang/String;
       7: getstatic     #71                 // Field org/jboss/logging/Logger$Level.INFO:Lorg/jboss/logging/Logger$Level;
      10: aconst_null
      11: aload_0
      12: invokevirtual #72                 // Method proxyAdvertisementsStarted$str:()Ljava/lang/String;
      15: aload_1
      16: iload_2
      17: invokestatic  #17                 // Method java/lang/Integer.valueOf:(I)Ljava/lang/Integer;
      20: invokevirtual #18                 // Method org/jboss/logging/Logger.logf:(Ljava/lang/String;Lorg/jboss/logging/Logger$Level;Ljava/lang/Throwable;Ljava/lang/String;Ljava/lang/Object;Ljava/lang/Object;)V
      23: return

  protected java.lang.String proxyAdvertisementsStarted$str();
    Code:
       0: ldc           #73                 // String UT005039: Undertow starts mod_cluster proxy advertisements on %s with frequency %s ms
       2: areturn

  public final void proxyAdvertiseMessagePayload(java.lang.String);
    Code:
       0: aload_0
       1: getfield      #3                  // Field org/jboss/logging/DelegatingBasicLogger.log:Lorg/jboss/logging/Logger;
       4: getstatic     #4                  // Field FQCN:Ljava/lang/String;
       7: getstatic     #15                 // Field org/jboss/logging/Logger$Level.DEBUG:Lorg/jboss/logging/Logger$Level;
      10: aconst_null
      11: aload_0
      12: invokevirtual #74                 // Method proxyAdvertiseMessagePayload$str:()Ljava/lang/String;
      15: aload_1
      16: invokevirtual #13                 // Method org/jboss/logging/Logger.logf:(Ljava/lang/String;Lorg/jboss/logging/Logger$Level;Ljava/lang/Throwable;Ljava/lang/String;Ljava/lang/Object;)V
      19: return

  protected java.lang.String proxyAdvertiseMessagePayload$str();
    Code:
       0: ldc           #75                 // String UT005040: Gonna send payload:\n%s
       2: areturn

  public final void proxyAdvertiseCannotSendMessage(java.lang.Exception, java.net.InetSocketAddress);
    Code:
       0: aload_0
       1: getfield      #3                  // Field org/jboss/logging/DelegatingBasicLogger.log:Lorg/jboss/logging/Logger;
       4: getstatic     #4                  // Field FQCN:Ljava/lang/String;
       7: getstatic     #5                  // Field org/jboss/logging/Logger$Level.ERROR:Lorg/jboss/logging/Logger$Level;
      10: aload_1
      11: aload_0
      12: invokevirtual #76                 // Method proxyAdvertiseCannotSendMessage$str:()Ljava/lang/String;
      15: aload_2
      16: invokevirtual #13                 // Method org/jboss/logging/Logger.logf:(Ljava/lang/String;Lorg/jboss/logging/Logger$Level;Ljava/lang/Throwable;Ljava/lang/String;Ljava/lang/Object;)V
      19: return

  protected java.lang.String proxyAdvertiseCannotSendMessage$str();
    Code:
       0: ldc           #77                 // String UT005041: Cannot send advertise message. Address: %s
       2: areturn

  public final void mcmpHandlerCreated();
    Code:
       0: aload_0
       1: getfield      #3                  // Field org/jboss/logging/DelegatingBasicLogger.log:Lorg/jboss/logging/Logger;
       4: getstatic     #4                  // Field FQCN:Ljava/lang/String;
       7: getstatic     #15                 // Field org/jboss/logging/Logger$Level.DEBUG:Lorg/jboss/logging/Logger$Level;
      10: aconst_null
      11: aload_0
      12: invokevirtual #78                 // Method mcmpHandlerCreated$str:()Ljava/lang/String;
      15: iconst_0
      16: anewarray     #7                  // class java/lang/Object
      19: invokevirtual #8                  // Method org/jboss/logging/Logger.logf:(Ljava/lang/String;Lorg/jboss/logging/Logger$Level;Ljava/lang/Throwable;Ljava/lang/String;[Ljava/lang/Object;)V
      22: return

  protected java.lang.String mcmpHandlerCreated$str();
    Code:
       0: ldc           #79                 // String UT005042: Undertow mod_cluster proxy MCMPHandler created
       2: areturn

  public final void mcmpProcessingError(java.lang.String, java.lang.String);
    Code:
       0: aload_0
       1: getfield      #3                  // Field org/jboss/logging/DelegatingBasicLogger.log:Lorg/jboss/logging/Logger;
       4: getstatic     #4                  // Field FQCN:Ljava/lang/String;
       7: getstatic     #5                  // Field org/jboss/logging/Logger$Level.ERROR:Lorg/jboss/logging/Logger$Level;
      10: aconst_null
      11: aload_0
      12: invokevirtual #80                 // Method mcmpProcessingError$str:()Ljava/lang/String;
      15: aload_1
      16: aload_2
      17: invokevirtual #18                 // Method org/jboss/logging/Logger.logf:(Ljava/lang/String;Lorg/jboss/logging/Logger$Level;Ljava/lang/Throwable;Ljava/lang/String;Ljava/lang/Object;Ljava/lang/Object;)V
      20: return

  protected java.lang.String mcmpProcessingError$str();
    Code:
       0: ldc           #81                 // String UT005043: Error in processing MCMP commands: Type:%s, Mess: %s
       2: areturn

  public final void removingNode(java.lang.String);
    Code:
       0: aload_0
       1: getfield      #3                  // Field org/jboss/logging/DelegatingBasicLogger.log:Lorg/jboss/logging/Logger;
       4: getstatic     #4                  // Field FQCN:Ljava/lang/String;
       7: getstatic     #71                 // Field org/jboss/logging/Logger$Level.INFO:Lorg/jboss/logging/Logger$Level;
      10: aconst_null
      11: aload_0
      12: invokevirtual #82                 // Method removingNode$str:()Ljava/lang/String;
      15: aload_1
      16: invokevirtual #13                 // Method org/jboss/logging/Logger.logf:(Ljava/lang/String;Lorg/jboss/logging/Logger$Level;Ljava/lang/Throwable;Ljava/lang/String;Ljava/lang/Object;)V
      19: return

  protected java.lang.String removingNode$str();
    Code:
       0: ldc           #83                 // String UT005044: Removing node %s
       2: areturn

  public final void registeringContext(java.lang.String, java.lang.String);
    Code:
       0: aload_0
       1: getfield      #3                  // Field org/jboss/logging/DelegatingBasicLogger.log:Lorg/jboss/logging/Logger;
       4: getstatic     #4                  // Field FQCN:Ljava/lang/String;
       7: getstatic     #71                 // Field org/jboss/logging/Logger$Level.INFO:Lorg/jboss/logging/Logger$Level;
      10: aconst_null
      11: aload_0
      12: invokevirtual #84                 // Method registeringContext2$str:()Ljava/lang/String;
      15: aload_1
      16: aload_2
      17: invokevirtual #18                 // Method org/jboss/logging/Logger.logf:(Ljava/lang/String;Lorg/jboss/logging/Logger$Level;Ljava/lang/Throwable;Ljava/lang/String;Ljava/lang/Object;Ljava/lang/Object;)V
      20: return

  protected java.lang.String registeringContext2$str();
    Code:
       0: ldc           #85                 // String UT005045: Registering context %s, for node %s
       2: areturn

  public final void registeringContext(java.lang.String, java.lang.String, java.util.List<java.lang.String>);
    Code:
       0: aload_0
       1: getfield      #3                  // Field org/jboss/logging/DelegatingBasicLogger.log:Lorg/jboss/logging/Logger;
       4: getstatic     #4                  // Field FQCN:Ljava/lang/String;
       7: getstatic     #15                 // Field org/jboss/logging/Logger$Level.DEBUG:Lorg/jboss/logging/Logger$Level;
      10: aconst_null
      11: aload_0
      12: invokevirtual #86                 // Method registeringContext3$str:()Ljava/lang/String;
      15: aload_1
      16: aload_2
      17: aload_3
      18: invokevirtual #87                 // Method org/jboss/logging/Logger.logf:(Ljava/lang/String;Lorg/jboss/logging/Logger$Level;Ljava/lang/Throwable;Ljava/lang/String;Ljava/lang/Object;Ljava/lang/Object;Ljava/lang/Object;)V
      21: return

  protected java.lang.String registeringContext3$str();
    Code:
       0: ldc           #88                 // String UT005046: Registering context %s, for node %s, with aliases %s
       2: areturn

  public final void unregisteringContext(java.lang.String, java.lang.String);
    Code:
       0: aload_0
       1: getfield      #3                  // Field org/jboss/logging/DelegatingBasicLogger.log:Lorg/jboss/logging/Logger;
       4: getstatic     #4                  // Field FQCN:Ljava/lang/String;
       7: getstatic     #71                 // Field org/jboss/logging/Logger$Level.INFO:Lorg/jboss/logging/Logger$Level;
      10: aconst_null
      11: aload_0
      12: invokevirtual #89                 // Method unregisteringContext$str:()Ljava/lang/String;
      15: aload_1
      16: aload_2
      17: invokevirtual #18                 // Method org/jboss/logging/Logger.logf:(Ljava/lang/String;Lorg/jboss/logging/Logger$Level;Ljava/lang/Throwable;Ljava/lang/String;Ljava/lang/Object;Ljava/lang/Object;)V
      20: return

  protected java.lang.String unregisteringContext$str();
    Code:
       0: ldc           #90                 // String UT005047: Unregistering context %s, from node %s
       2: areturn

  public final void nodeIsInError(java.lang.String);
    Code:
       0: aload_0
       1: getfield      #3                  // Field org/jboss/logging/DelegatingBasicLogger.log:Lorg/jboss/logging/Logger;
       4: getstatic     #4                  // Field FQCN:Ljava/lang/String;
       7: getstatic     #15                 // Field org/jboss/logging/Logger$Level.DEBUG:Lorg/jboss/logging/Logger$Level;
      10: aconst_null
      11: aload_0
      12: invokevirtual #91                 // Method nodeIsInError$str:()Ljava/lang/String;
      15: aload_1
      16: invokevirtual #13                 // Method org/jboss/logging/Logger.logf:(Ljava/lang/String;Lorg/jboss/logging/Logger$Level;Ljava/lang/Throwable;Ljava/lang/String;Ljava/lang/Object;)V
      19: return

  protected java.lang.String nodeIsInError$str();
    Code:
       0: ldc           #92                 // String UT005048: Node %s in error
       2: areturn

  public final void nodeConfigCreated(java.net.URI, java.lang.String, java.lang.String, java.lang.String, boolean, int, int, long, int, int, int, int, boolean);
    Code:
       0: aload_0
       1: getfield      #3                  // Field org/jboss/logging/DelegatingBasicLogger.log:Lorg/jboss/logging/Logger;
       4: getstatic     #4                  // Field FQCN:Ljava/lang/String;
       7: getstatic     #15                 // Field org/jboss/logging/Logger$Level.DEBUG:Lorg/jboss/logging/Logger$Level;
      10: aconst_null
      11: aload_0
      12: invokevirtual #93                 // Method nodeConfigCreated$str:()Ljava/lang/String;
      15: bipush        13
      17: anewarray     #7                  // class java/lang/Object
      20: dup
      21: iconst_0
      22: aload_1
      23: aastore
      24: dup
      25: iconst_1
      26: aload_2
      27: aastore
      28: dup
      29: iconst_2
      30: aload_3
      31: aastore
      32: dup
      33: iconst_3
      34: aload         4
      36: aastore
      37: dup
      38: iconst_4
      39: iload         5
      41: invokestatic  #69                 // Method java/lang/Boolean.valueOf:(Z)Ljava/lang/Boolean;
      44: aastore
      45: dup
      46: iconst_5
      47: iload         6
      49: invokestatic  #17                 // Method java/lang/Integer.valueOf:(I)Ljava/lang/Integer;
      52: aastore
      53: dup
      54: bipush        6
      56: iload         7
      58: invokestatic  #17                 // Method java/lang/Integer.valueOf:(I)Ljava/lang/Integer;
      61: aastore
      62: dup
      63: bipush        7
      65: lload         8
      67: invokestatic  #94                 // Method java/lang/Long.valueOf:(J)Ljava/lang/Long;
      70: aastore
      71: dup
      72: bipush        8
      74: iload         10
      76: invokestatic  #17                 // Method java/lang/Integer.valueOf:(I)Ljava/lang/Integer;
      79: aastore
      80: dup
      81: bipush        9
      83: iload         11
      85: invokestatic  #17                 // Method java/lang/Integer.valueOf:(I)Ljava/lang/Integer;
      88: aastore
      89: dup
      90: bipush        10
      92: iload         12
      94: invokestatic  #17                 // Method java/lang/Integer.valueOf:(I)Ljava/lang/Integer;
      97: aastore
      98: dup
      99: bipush        11
     101: iload         13
     103: invokestatic  #17                 // Method java/lang/Integer.valueOf:(I)Ljava/lang/Integer;
     106: aastore
     107: dup
     108: bipush        12
     110: iload         14
     112: invokestatic  #69                 // Method java/lang/Boolean.valueOf:(Z)Ljava/lang/Boolean;
     115: aastore
     116: invokevirtual #8                  // Method org/jboss/logging/Logger.logf:(Ljava/lang/String;Lorg/jboss/logging/Logger$Level;Ljava/lang/Throwable;Ljava/lang/String;[Ljava/lang/Object;)V
     119: return

  protected java.lang.String nodeConfigCreated$str();
    Code:
       0: ldc           #95                 // String UT005049: NodeConfig created: connectionURI: %s, balancer: %s, load balancing group: %s, jvmRoute: %s, flushPackets: %s, flushwait: %s, ping: %s,ttl: %s, timeout: %s, maxConnections: %s, cacheConnections: %s, requestQueueSize: %s, queueNewRequests: %s
       2: areturn

  public final void failedToProcessManagementReq(java.lang.Exception);
    Code:
       0: aload_0
       1: getfield      #3                  // Field org/jboss/logging/DelegatingBasicLogger.log:Lorg/jboss/logging/Logger;
       4: getstatic     #4                  // Field FQCN:Ljava/lang/String;
       7: getstatic     #5                  // Field org/jboss/logging/Logger$Level.ERROR:Lorg/jboss/logging/Logger$Level;
      10: aload_1
      11: aload_0
      12: invokevirtual #96                 // Method failedToProcessManagementReq$str:()Ljava/lang/String;
      15: iconst_0
      16: anewarray     #7                  // class java/lang/Object
      19: invokevirtual #8                  // Method org/jboss/logging/Logger.logf:(Ljava/lang/String;Lorg/jboss/logging/Logger$Level;Ljava/lang/Throwable;Ljava/lang/String;[Ljava/lang/Object;)V
      22: return

  protected java.lang.String failedToProcessManagementReq$str();
    Code:
       0: ldc           #97                 // String UT005050: Failed to process management request
       2: areturn

  public final void failedToSendPingResponse(java.lang.Exception);
    Code:
       0: aload_0
       1: getfield      #3                  // Field org/jboss/logging/DelegatingBasicLogger.log:Lorg/jboss/logging/Logger;
       4: getstatic     #4                  // Field FQCN:Ljava/lang/String;
       7: getstatic     #5                  // Field org/jboss/logging/Logger$Level.ERROR:Lorg/jboss/logging/Logger$Level;
      10: aload_1
      11: aload_0
      12: invokevirtual #98                 // Method failedToSendPingResponse$str:()Ljava/lang/String;
      15: iconst_0
      16: anewarray     #7                  // class java/lang/Object
      19: invokevirtual #8                  // Method org/jboss/logging/Logger.logf:(Ljava/lang/String;Lorg/jboss/logging/Logger$Level;Ljava/lang/Throwable;Ljava/lang/String;[Ljava/lang/Object;)V
      22: return

  protected java.lang.String failedToSendPingResponse$str();
    Code:
       0: ldc           #99                 // String UT005051: Failed to send ping response
       2: areturn

  public final void failedToSendPingResponseDBG(java.lang.Exception, java.lang.String, java.lang.String);
    Code:
       0: aload_0
       1: getfield      #3                  // Field org/jboss/logging/DelegatingBasicLogger.log:Lorg/jboss/logging/Logger;
       4: getstatic     #4                  // Field FQCN:Ljava/lang/String;
       7: getstatic     #15                 // Field org/jboss/logging/Logger$Level.DEBUG:Lorg/jboss/logging/Logger$Level;
      10: aload_1
      11: aload_0
      12: invokevirtual #100                // Method failedToSendPingResponseDBG$str:()Ljava/lang/String;
      15: aload_2
      16: aload_3
      17: invokevirtual #18                 // Method org/jboss/logging/Logger.logf:(Ljava/lang/String;Lorg/jboss/logging/Logger$Level;Ljava/lang/Throwable;Ljava/lang/String;Ljava/lang/Object;Ljava/lang/Object;)V
      20: return

  protected java.lang.String failedToSendPingResponseDBG$str();
    Code:
       0: ldc           #101                // String UT005052: Failed to send ping response, node.getJvmRoute(): %s, jvmRoute: %s
       2: areturn

  public final void registeringNode(java.lang.String, java.net.URI);
    Code:
       0: aload_0
       1: getfield      #3                  // Field org/jboss/logging/DelegatingBasicLogger.log:Lorg/jboss/logging/Logger;
       4: getstatic     #4                  // Field FQCN:Ljava/lang/String;
       7: getstatic     #71                 // Field org/jboss/logging/Logger$Level.INFO:Lorg/jboss/logging/Logger$Level;
      10: aconst_null
      11: aload_0
      12: invokevirtual #102                // Method registeringNode$str:()Ljava/lang/String;
      15: aload_1
      16: aload_2
      17: invokevirtual #18                 // Method org/jboss/logging/Logger.logf:(Ljava/lang/String;Lorg/jboss/logging/Logger$Level;Ljava/lang/Throwable;Ljava/lang/String;Ljava/lang/Object;Ljava/lang/Object;)V
      20: return

  protected java.lang.String registeringNode$str();
    Code:
       0: ldc           #103                // String UT005053: Registering node %s, connection: %s
       2: areturn

  public final void mcmpKeyValue(io.undertow.util.HttpString, java.lang.String);
    Code:
       0: aload_0
       1: getfield      #3                  // Field org/jboss/logging/DelegatingBasicLogger.log:Lorg/jboss/logging/Logger;
       4: getstatic     #4                  // Field FQCN:Ljava/lang/String;
       7: getstatic     #15                 // Field org/jboss/logging/Logger$Level.DEBUG:Lorg/jboss/logging/Logger$Level;
      10: aconst_null
      11: aload_0
      12: invokevirtual #104                // Method mcmpKeyValue$str:()Ljava/lang/String;
      15: aload_1
      16: aload_2
      17: invokevirtual #18                 // Method org/jboss/logging/Logger.logf:(Ljava/lang/String;Lorg/jboss/logging/Logger$Level;Ljava/lang/Throwable;Ljava/lang/String;Ljava/lang/Object;Ljava/lang/Object;)V
      20: return

  protected java.lang.String mcmpKeyValue$str();
    Code:
       0: ldc           #105                // String UT005054: MCMP processing, key: %s, value: %s
       2: areturn

  public final void httpClientPingTask(java.net.URI);
    Code:
       0: aload_0
       1: getfield      #3                  // Field org/jboss/logging/DelegatingBasicLogger.log:Lorg/jboss/logging/Logger;
       4: getstatic     #4                  // Field FQCN:Ljava/lang/String;
       7: getstatic     #15                 // Field org/jboss/logging/Logger$Level.DEBUG:Lorg/jboss/logging/Logger$Level;
      10: aconst_null
      11: aload_0
      12: invokevirtual #106                // Method httpClientPingTask$str:()Ljava/lang/String;
      15: aload_1
      16: invokevirtual #13                 // Method org/jboss/logging/Logger.logf:(Ljava/lang/String;Lorg/jboss/logging/Logger$Level;Ljava/lang/Throwable;Ljava/lang/String;Ljava/lang/Object;)V
      19: return

  protected java.lang.String httpClientPingTask$str();
    Code:
       0: ldc           #107                // String UT005055: HttpClientPingTask run for connection: %s
       2: areturn

  public final void receivedNodeLoad(java.lang.String, java.lang.String);
    Code:
       0: aload_0
       1: getfield      #3                  // Field org/jboss/logging/DelegatingBasicLogger.log:Lorg/jboss/logging/Logger;
       4: getstatic     #4                  // Field FQCN:Ljava/lang/String;
       7: getstatic     #15                 // Field org/jboss/logging/Logger$Level.DEBUG:Lorg/jboss/logging/Logger$Level;
      10: aconst_null
      11: aload_0
      12: invokevirtual #108                // Method receivedNodeLoad$str:()Ljava/lang/String;
      15: aload_1
      16: aload_2
      17: invokevirtual #18                 // Method org/jboss/logging/Logger.logf:(Ljava/lang/String;Lorg/jboss/logging/Logger$Level;Ljava/lang/Throwable;Ljava/lang/String;Ljava/lang/Object;Ljava/lang/Object;)V
      20: return

  protected java.lang.String receivedNodeLoad$str();
    Code:
       0: ldc           #109                // String UT005056: Received node load in STATUS message, node jvmRoute: %s, load: %s
       2: areturn

  public final void mcmpSendingResponse(java.net.InetSocketAddress, int, io.undertow.util.HeaderMap, java.lang.String);
    Code:
       0: aload_0
       1: getfield      #3                  // Field org/jboss/logging/DelegatingBasicLogger.log:Lorg/jboss/logging/Logger;
       4: getstatic     #4                  // Field FQCN:Ljava/lang/String;
       7: getstatic     #15                 // Field org/jboss/logging/Logger$Level.DEBUG:Lorg/jboss/logging/Logger$Level;
      10: aconst_null
      11: aload_0
      12: invokevirtual #110                // Method mcmpSendingResponse$str:()Ljava/lang/String;
      15: iconst_4
      16: anewarray     #7                  // class java/lang/Object
      19: dup
      20: iconst_0
      21: aload_1
      22: aastore
      23: dup
      24: iconst_1
      25: iload_2
      26: invokestatic  #17                 // Method java/lang/Integer.valueOf:(I)Ljava/lang/Integer;
      29: aastore
      30: dup
      31: iconst_2
      32: aload_3
      33: aastore
      34: dup
      35: iconst_3
      36: aload         4
      38: aastore
      39: invokevirtual #8                  // Method org/jboss/logging/Logger.logf:(Ljava/lang/String;Lorg/jboss/logging/Logger$Level;Ljava/lang/Throwable;Ljava/lang/String;[Ljava/lang/Object;)V
      42: return

  protected java.lang.String mcmpSendingResponse$str();
    Code:
       0: ldc           #111                // String UT005057: Sending MCMP response to destination: %s, HTTP status: %s, Headers: %s, response: %s
       2: areturn

  public final void potentialCrossTalking(java.net.InetAddress, java.lang.String, java.lang.String);
    Code:
       0: aload_0
       1: getfield      #3                  // Field org/jboss/logging/DelegatingBasicLogger.log:Lorg/jboss/logging/Logger;
       4: getstatic     #4                  // Field FQCN:Ljava/lang/String;
       7: getstatic     #65                 // Field org/jboss/logging/Logger$Level.WARN:Lorg/jboss/logging/Logger$Level;
      10: aconst_null
      11: aload_0
      12: invokevirtual #112                // Method potentialCrossTalking$str:()Ljava/lang/String;
      15: aload_1
      16: aload_2
      17: aload_3
      18: invokevirtual #87                 // Method org/jboss/logging/Logger.logf:(Ljava/lang/String;Lorg/jboss/logging/Logger$Level;Ljava/lang/Throwable;Ljava/lang/String;Ljava/lang/Object;Ljava/lang/Object;Ljava/lang/Object;)V
      21: return

  protected java.lang.String potentialCrossTalking$str();
    Code:
       0: ldc           #113                // String UT005058: Could not bind multicast socket to %s (%s address): %s; make sure your multicast address is of the same type as the IP stack (IPv4 or IPv6). Multicast socket will not be bound to an address, but this may lead to cross talking (see http://www.jboss.org/community/docs/DOC-9469 for details).
       2: areturn

  public final void oldStylePredicateSyntax(java.lang.String);
    Code:
       0: aload_0
       1: getfield      #3                  // Field org/jboss/logging/DelegatingBasicLogger.log:Lorg/jboss/logging/Logger;
       4: getstatic     #4                  // Field FQCN:Ljava/lang/String;
       7: getstatic     #65                 // Field org/jboss/logging/Logger$Level.WARN:Lorg/jboss/logging/Logger$Level;
      10: aconst_null
      11: aload_0
      12: invokevirtual #114                // Method oldStylePredicateSyntax$str:()Ljava/lang/String;
      15: aload_1
      16: invokevirtual #13                 // Method org/jboss/logging/Logger.logf:(Ljava/lang/String;Lorg/jboss/logging/Logger$Level;Ljava/lang/Throwable;Ljava/lang/String;Ljava/lang/Object;)V
      19: return

  protected java.lang.String oldStylePredicateSyntax$str();
    Code:
       0: ldc           #115                // String UT005060: Predicate %s uses old style square braces to define predicates, which will be removed in a future release. predicate[value] should be changed to predicate(value)
       2: areturn

  protected java.lang.String maxRestartsExceeded$str();
    Code:
       0: ldc           #116                // String UT005061: More than %s restarts detected, breaking assumed infinite loop
       2: areturn

  public final java.lang.IllegalStateException maxRestartsExceeded(int);
    Code:
       0: new           #117                // class java/lang/IllegalStateException
       3: dup
       4: aload_0
       5: invokevirtual #118                // Method getLoggingLocale:()Ljava/util/Locale;
       8: aload_0
       9: invokevirtual #119                // Method maxRestartsExceeded$str:()Ljava/lang/String;
      12: iconst_1
      13: anewarray     #7                  // class java/lang/Object
      16: dup
      17: iconst_0
      18: iload_1
      19: invokestatic  #17                 // Method java/lang/Integer.valueOf:(I)Ljava/lang/Integer;
      22: aastore
      23: invokestatic  #120                // Method java/lang/String.format:(Ljava/util/Locale;Ljava/lang/String;[Ljava/lang/Object;)Ljava/lang/String;
      26: invokespecial #121                // Method java/lang/IllegalStateException."<init>":(Ljava/lang/String;)V
      29: astore_2
      30: aload_2
      31: invokestatic  #122                // Method _copyStackTraceMinusOne:(Ljava/lang/Throwable;)V
      34: aload_2
      35: areturn

  private static void _copyStackTraceMinusOne(java.lang.Throwable);
    Code:
       0: aload_0
       1: invokevirtual #123                // Method java/lang/Throwable.getStackTrace:()[Ljava/lang/StackTraceElement;
       4: astore_1
       5: aload_0
       6: aload_1
       7: iconst_1
       8: aload_1
       9: arraylength
      10: invokestatic  #124                // Method java/util/Arrays.copyOfRange:([Ljava/lang/Object;II)[Ljava/lang/Object;
      13: checkcast     #125                // class "[Ljava/lang/StackTraceElement;"
      16: invokevirtual #126                // Method java/lang/Throwable.setStackTrace:([Ljava/lang/StackTraceElement;)V
      19: return

  public final void extendedAccessLogPatternParseError(java.lang.Throwable);
    Code:
       0: aload_0
       1: getfield      #3                  // Field org/jboss/logging/DelegatingBasicLogger.log:Lorg/jboss/logging/Logger;
       4: getstatic     #4                  // Field FQCN:Ljava/lang/String;
       7: getstatic     #5                  // Field org/jboss/logging/Logger$Level.ERROR:Lorg/jboss/logging/Logger$Level;
      10: aload_1
      11: aload_0
      12: invokevirtual #127                // Method extendedAccessLogPatternParseError$str:()Ljava/lang/String;
      15: iconst_0
      16: anewarray     #7                  // class java/lang/Object
      19: invokevirtual #8                  // Method org/jboss/logging/Logger.logf:(Ljava/lang/String;Lorg/jboss/logging/Logger$Level;Ljava/lang/Throwable;Ljava/lang/String;[Ljava/lang/Object;)V
      22: return

  protected java.lang.String extendedAccessLogPatternParseError$str();
    Code:
       0: ldc           #128                // String UT005062: Pattern parse error
       2: areturn

  public final void extendedAccessLogUnknownToken(java.lang.String);
    Code:
       0: aload_0
       1: getfield      #3                  // Field org/jboss/logging/DelegatingBasicLogger.log:Lorg/jboss/logging/Logger;
       4: getstatic     #4                  // Field FQCN:Ljava/lang/String;
       7: getstatic     #5                  // Field org/jboss/logging/Logger$Level.ERROR:Lorg/jboss/logging/Logger$Level;
      10: aconst_null
      11: aload_0
      12: invokevirtual #129                // Method extendedAccessLogUnknownToken$str:()Ljava/lang/String;
      15: aload_1
      16: invokevirtual #13                 // Method org/jboss/logging/Logger.logf:(Ljava/lang/String;Lorg/jboss/logging/Logger$Level;Ljava/lang/Throwable;Ljava/lang/String;Ljava/lang/Object;)V
      19: return

  protected java.lang.String extendedAccessLogUnknownToken$str();
    Code:
       0: ldc           #130                // String UT005063: Unable to decode with rest of chars starting: %s
       2: areturn

  public final void extendedAccessLogMissingClosing();
    Code:
       0: aload_0
       1: getfield      #3                  // Field org/jboss/logging/DelegatingBasicLogger.log:Lorg/jboss/logging/Logger;
       4: getstatic     #4                  // Field FQCN:Ljava/lang/String;
       7: getstatic     #5                  // Field org/jboss/logging/Logger$Level.ERROR:Lorg/jboss/logging/Logger$Level;
      10: aconst_null
      11: aload_0
      12: invokevirtual #131                // Method extendedAccessLogMissingClosing$str:()Ljava/lang/String;
      15: iconst_0
      16: anewarray     #7                  // class java/lang/Object
      19: invokevirtual #8                  // Method org/jboss/logging/Logger.logf:(Ljava/lang/String;Lorg/jboss/logging/Logger$Level;Ljava/lang/Throwable;Ljava/lang/String;[Ljava/lang/Object;)V
      22: return

  protected java.lang.String extendedAccessLogMissingClosing$str();
    Code:
       0: ldc           #132                // String UT005064: No closing ) found for in decode
       2: areturn

  public final void extendedAccessLogCannotDecode(java.lang.String);
    Code:
       0: aload_0
       1: getfield      #3                  // Field org/jboss/logging/DelegatingBasicLogger.log:Lorg/jboss/logging/Logger;
       4: getstatic     #4                  // Field FQCN:Ljava/lang/String;
       7: getstatic     #5                  // Field org/jboss/logging/Logger$Level.ERROR:Lorg/jboss/logging/Logger$Level;
      10: aconst_null
      11: aload_0
      12: invokevirtual #133                // Method extendedAccessLogCannotDecode$str:()Ljava/lang/String;
      15: aload_1
      16: invokevirtual #13                 // Method org/jboss/logging/Logger.logf:(Ljava/lang/String;Lorg/jboss/logging/Logger$Level;Ljava/lang/Throwable;Ljava/lang/String;Ljava/lang/Object;)V
      19: return

  protected java.lang.String extendedAccessLogCannotDecode$str();
    Code:
       0: ldc           #134                // String UT005065: The next characters couldn\'t be decoded: %s
       2: areturn

  public final void extendedAccessLogCannotDecodeXParamValue(java.lang.String);
    Code:
       0: aload_0
       1: getfield      #3                  // Field org/jboss/logging/DelegatingBasicLogger.log:Lorg/jboss/logging/Logger;
       4: getstatic     #4                  // Field FQCN:Ljava/lang/String;
       7: getstatic     #5                  // Field org/jboss/logging/Logger$Level.ERROR:Lorg/jboss/logging/Logger$Level;
      10: aconst_null
      11: aload_0
      12: invokevirtual #135                // Method extendedAccessLogCannotDecodeXParamValue$str:()Ljava/lang/String;
      15: aload_1
      16: invokevirtual #13                 // Method org/jboss/logging/Logger.logf:(Ljava/lang/String;Lorg/jboss/logging/Logger$Level;Ljava/lang/Throwable;Ljava/lang/String;Ljava/lang/Object;)V
      19: return

  protected java.lang.String extendedAccessLogCannotDecodeXParamValue$str();
    Code:
       0: ldc           #136                // String UT005066: X param for servlet request, couldn\'t decode value: %s
       2: areturn

  public final void extendedAccessLogBadXParam();
    Code:
       0: aload_0
       1: getfield      #3                  // Field org/jboss/logging/DelegatingBasicLogger.log:Lorg/jboss/logging/Logger;
       4: getstatic     #4                  // Field FQCN:Ljava/lang/String;
       7: getstatic     #5                  // Field org/jboss/logging/Logger$Level.ERROR:Lorg/jboss/logging/Logger$Level;
      10: aconst_null
      11: aload_0
      12: invokevirtual #137                // Method extendedAccessLogBadXParam$str:()Ljava/lang/String;
      15: iconst_0
      16: anewarray     #7                  // class java/lang/Object
      19: invokevirtual #8                  // Method org/jboss/logging/Logger.logf:(Ljava/lang/String;Lorg/jboss/logging/Logger$Level;Ljava/lang/Throwable;Ljava/lang/String;[Ljava/lang/Object;)V
      22: return

  protected java.lang.String extendedAccessLogBadXParam$str();
    Code:
       0: ldc           #138                // String UT005067: X param in wrong format. Needs to be \'x-#(...)\'
       2: areturn

  public final void extendedAccessLogEmptyPattern();
    Code:
       0: aload_0
       1: getfield      #3                  // Field org/jboss/logging/DelegatingBasicLogger.log:Lorg/jboss/logging/Logger;
       4: getstatic     #4                  // Field FQCN:Ljava/lang/String;
       7: getstatic     #71                 // Field org/jboss/logging/Logger$Level.INFO:Lorg/jboss/logging/Logger$Level;
      10: aconst_null
      11: aload_0
      12: invokevirtual #139                // Method extendedAccessLogEmptyPattern$str:()Ljava/lang/String;
      15: iconst_0
      16: anewarray     #7                  // class java/lang/Object
      19: invokevirtual #8                  // Method org/jboss/logging/Logger.logf:(Ljava/lang/String;Lorg/jboss/logging/Logger$Level;Ljava/lang/Throwable;Ljava/lang/String;[Ljava/lang/Object;)V
      22: return

  protected java.lang.String extendedAccessLogEmptyPattern$str();
    Code:
       0: ldc           #140                // String UT005068: Pattern was just empty or whitespace
       2: areturn

  public final void failedToWriteJdbcAccessLog(java.lang.Exception);
    Code:
       0: aload_0
       1: getfield      #3                  // Field org/jboss/logging/DelegatingBasicLogger.log:Lorg/jboss/logging/Logger;
       4: getstatic     #4                  // Field FQCN:Ljava/lang/String;
       7: getstatic     #5                  // Field org/jboss/logging/Logger$Level.ERROR:Lorg/jboss/logging/Logger$Level;
      10: aload_1
      11: aload_0
      12: invokevirtual #141                // Method failedToWriteJdbcAccessLog$str:()Ljava/lang/String;
      15: iconst_0
      16: anewarray     #7                  // class java/lang/Object
      19: invokevirtual #8                  // Method org/jboss/logging/Logger.logf:(Ljava/lang/String;Lorg/jboss/logging/Logger$Level;Ljava/lang/Throwable;Ljava/lang/String;[Ljava/lang/Object;)V
      22: return

  protected java.lang.String failedToWriteJdbcAccessLog$str();
    Code:
       0: ldc           #142                // String UT005069: Failed to write JDBC access log
       2: areturn

  public final void failedToWritePreCachedFile();
    Code:
       0: aload_0
       1: getfield      #3                  // Field org/jboss/logging/DelegatingBasicLogger.log:Lorg/jboss/logging/Logger;
       4: getstatic     #4                  // Field FQCN:Ljava/lang/String;
       7: getstatic     #5                  // Field org/jboss/logging/Logger$Level.ERROR:Lorg/jboss/logging/Logger$Level;
      10: aconst_null
      11: aload_0
      12: invokevirtual #143                // Method failedToWritePreCachedFile$str:()Ljava/lang/String;
      15: iconst_0
      16: anewarray     #7                  // class java/lang/Object
      19: invokevirtual #8                  // Method org/jboss/logging/Logger.logf:(Ljava/lang/String;Lorg/jboss/logging/Logger$Level;Ljava/lang/Throwable;Ljava/lang/String;[Ljava/lang/Object;)V
      22: return

  protected java.lang.String failedToWritePreCachedFile$str();
    Code:
       0: ldc           #144                // String UT005070: Failed to write pre-cached file
       2: areturn

  public final void undertowRequestFailed(java.lang.Throwable, io.undertow.server.HttpServerExchange);
    Code:
       0: aload_0
       1: getfield      #3                  // Field org/jboss/logging/DelegatingBasicLogger.log:Lorg/jboss/logging/Logger;
       4: getstatic     #4                  // Field FQCN:Ljava/lang/String;
       7: getstatic     #5                  // Field org/jboss/logging/Logger$Level.ERROR:Lorg/jboss/logging/Logger$Level;
      10: aload_1
      11: aload_0
      12: invokevirtual #145                // Method undertowRequestFailed$str:()Ljava/lang/String;
      15: aload_2
      16: invokevirtual #13                 // Method org/jboss/logging/Logger.logf:(Ljava/lang/String;Lorg/jboss/logging/Logger$Level;Ljava/lang/Throwable;Ljava/lang/String;Ljava/lang/Object;)V
      19: return

  protected java.lang.String undertowRequestFailed$str();
    Code:
       0: ldc           #146                // String UT005071: Undertow request failed %s
       2: areturn

  public final void stuckThreadDetected(java.lang.String, long, long, java.util.Date, java.lang.String, int, int, java.lang.Throwable);
    Code:
       0: aload_0
       1: getfield      #3                  // Field org/jboss/logging/DelegatingBasicLogger.log:Lorg/jboss/logging/Logger;
       4: getstatic     #4                  // Field FQCN:Ljava/lang/String;
       7: getstatic     #65                 // Field org/jboss/logging/Logger$Level.WARN:Lorg/jboss/logging/Logger$Level;
      10: aload         10
      12: aload_0
      13: invokevirtual #147                // Method stuckThreadDetected$str:()Ljava/lang/String;
      16: bipush        7
      18: anewarray     #7                  // class java/lang/Object
      21: dup
      22: iconst_0
      23: aload_1
      24: aastore
      25: dup
      26: iconst_1
      27: lload_2
      28: invokestatic  #94                 // Method java/lang/Long.valueOf:(J)Ljava/lang/Long;
      31: aastore
      32: dup
      33: iconst_2
      34: lload         4
      36: invokestatic  #94                 // Method java/lang/Long.valueOf:(J)Ljava/lang/Long;
      39: aastore
      40: dup
      41: iconst_3
      42: aload         6
      44: aastore
      45: dup
      46: iconst_4
      47: aload         7
      49: aastore
      50: dup
      51: iconst_5
      52: iload         8
      54: invokestatic  #17                 // Method java/lang/Integer.valueOf:(I)Ljava/lang/Integer;
      57: aastore
      58: dup
      59: bipush        6
      61: iload         9
      63: invokestatic  #17                 // Method java/lang/Integer.valueOf:(I)Ljava/lang/Integer;
      66: aastore
      67: invokevirtual #8                  // Method org/jboss/logging/Logger.logf:(Ljava/lang/String;Lorg/jboss/logging/Logger$Level;Ljava/lang/Throwable;Ljava/lang/String;[Ljava/lang/Object;)V
      70: return

  protected java.lang.String stuckThreadDetected$str();
    Code:
       0: ldc           #148                // String UT005072: Thread %s (id=%s) has been active for %s milliseconds (since %s) to serve the same request for %s and may be stuck (configured threshold for this StuckThreadDetectionValve is %s seconds). There is/are %s thread(s) in total that are monitored by this Valve and may be stuck.
       2: areturn

  public final void stuckThreadCompleted(java.lang.String, long, long, int);
    Code:
       0: aload_0
       1: getfield      #3                  // Field org/jboss/logging/DelegatingBasicLogger.log:Lorg/jboss/logging/Logger;
       4: getstatic     #4                  // Field FQCN:Ljava/lang/String;
       7: getstatic     #65                 // Field org/jboss/logging/Logger$Level.WARN:Lorg/jboss/logging/Logger$Level;
      10: aconst_null
      11: aload_0
      12: invokevirtual #149                // Method stuckThreadCompleted$str:()Ljava/lang/String;
      15: iconst_4
      16: anewarray     #7                  // class java/lang/Object
      19: dup
      20: iconst_0
      21: aload_1
      22: aastore
      23: dup
      24: iconst_1
      25: lload_2
      26: invokestatic  #94                 // Method java/lang/Long.valueOf:(J)Ljava/lang/Long;
      29: aastore
      30: dup
      31: iconst_2
      32: lload         4
      34: invokestatic  #94                 // Method java/lang/Long.valueOf:(J)Ljava/lang/Long;
      37: aastore
      38: dup
      39: iconst_3
      40: iload         6
      42: invokestatic  #17                 // Method java/lang/Integer.valueOf:(I)Ljava/lang/Integer;
      45: aastore
      46: invokevirtual #8                  // Method org/jboss/logging/Logger.logf:(Ljava/lang/String;Lorg/jboss/logging/Logger$Level;Ljava/lang/Throwable;Ljava/lang/String;[Ljava/lang/Object;)V
      49: return

  protected java.lang.String stuckThreadCompleted$str();
    Code:
       0: ldc           #150                // String UT005073: Thread %s (id=%s) was previously reported to be stuck but has completed. It was active for approximately %s milliseconds. There is/are still %s thread(s) that are monitored by this Valve and may be stuck.
       2: areturn

  public final void failedToInvokeFailedCallback(io.undertow.server.handlers.sse.ServerSentEventConnection$EventCallback, java.lang.Exception);
    Code:
       0: aload_0
       1: getfield      #3                  // Field org/jboss/logging/DelegatingBasicLogger.log:Lorg/jboss/logging/Logger;
       4: getstatic     #4                  // Field FQCN:Ljava/lang/String;
       7: getstatic     #5                  // Field org/jboss/logging/Logger$Level.ERROR:Lorg/jboss/logging/Logger$Level;
      10: aload_2
      11: aload_0
      12: invokevirtual #151                // Method failedToInvokeFailedCallback$str:()Ljava/lang/String;
      15: aload_1
      16: invokevirtual #13                 // Method org/jboss/logging/Logger.logf:(Ljava/lang/String;Lorg/jboss/logging/Logger$Level;Ljava/lang/Throwable;Ljava/lang/String;Ljava/lang/Object;)V
      19: return

  protected java.lang.String failedToInvokeFailedCallback$str();
    Code:
       0: ldc           #152                // String UT005074: Failed to invoke error callback %s for SSE task
       2: areturn

  protected java.lang.String unableToResolveModClusterManagementHost$str();
    Code:
       0: ldc           #153                // String UT005075: Unable to resolve mod_cluster management host\'s address for \'%s\'
       2: areturn

  public final java.lang.IllegalStateException unableToResolveModClusterManagementHost(java.lang.String);
    Code:
       0: new           #117                // class java/lang/IllegalStateException
       3: dup
       4: aload_0
       5: invokevirtual #118                // Method getLoggingLocale:()Ljava/util/Locale;
       8: aload_0
       9: invokevirtual #154                // Method unableToResolveModClusterManagementHost$str:()Ljava/lang/String;
      12: iconst_1
      13: anewarray     #7                  // class java/lang/Object
      16: dup
      17: iconst_0
      18: aload_1
      19: aastore
      20: invokestatic  #120                // Method java/lang/String.format:(Ljava/util/Locale;Ljava/lang/String;[Ljava/lang/Object;)Ljava/lang/String;
      23: invokespecial #121                // Method java/lang/IllegalStateException."<init>":(Ljava/lang/String;)V
      26: astore_2
      27: aload_2
      28: invokestatic  #122                // Method _copyStackTraceMinusOne:(Ljava/lang/Throwable;)V
      31: aload_2
      32: areturn

  public final void sslReadLoopDetected(io.undertow.protocols.ssl.SslConduit);
    Code:
       0: aload_0
       1: getfield      #3                  // Field org/jboss/logging/DelegatingBasicLogger.log:Lorg/jboss/logging/Logger;
       4: getstatic     #4                  // Field FQCN:Ljava/lang/String;
       7: getstatic     #5                  // Field org/jboss/logging/Logger$Level.ERROR:Lorg/jboss/logging/Logger$Level;
      10: aconst_null
      11: aload_0
      12: invokevirtual #155                // Method sslReadLoopDetected$str:()Ljava/lang/String;
      15: aload_1
      16: invokevirtual #13                 // Method org/jboss/logging/Logger.logf:(Ljava/lang/String;Lorg/jboss/logging/Logger$Level;Ljava/lang/Throwable;Ljava/lang/String;Ljava/lang/Object;)V
      19: return

  protected java.lang.String sslReadLoopDetected$str();
    Code:
       0: ldc           #156                // String UT005076: SSL read loop detected. This should not happen, please report this to the Undertow developers. Current state %s
       2: areturn

  public final void sslBufferOverflow(io.undertow.protocols.ssl.SslConduit);
    Code:
       0: aload_0
       1: getfield      #3                  // Field org/jboss/logging/DelegatingBasicLogger.log:Lorg/jboss/logging/Logger;
       4: getstatic     #4                  // Field FQCN:Ljava/lang/String;
       7: getstatic     #5                  // Field org/jboss/logging/Logger$Level.ERROR:Lorg/jboss/logging/Logger$Level;
      10: aconst_null
      11: aload_0
      12: invokevirtual #157                // Method sslBufferOverflow$str:()Ljava/lang/String;
      15: aload_1
      16: invokevirtual #13                 // Method org/jboss/logging/Logger.logf:(Ljava/lang/String;Lorg/jboss/logging/Logger$Level;Ljava/lang/Throwable;Ljava/lang/String;Ljava/lang/Object;)V
      19: return

  protected java.lang.String sslBufferOverflow$str();
    Code:
       0: ldc           #158                // String UT005077: SSL unwrap buffer overflow detected. This should not happen, please report this to the Undertow developers. Current state %s
       2: areturn

  public final void alpnConnectionFailed(org.xnio.ssl.SslConnection);
    Code:
       0: aload_0
       1: getfield      #3                  // Field org/jboss/logging/DelegatingBasicLogger.log:Lorg/jboss/logging/Logger;
       4: getstatic     #4                  // Field FQCN:Ljava/lang/String;
       7: getstatic     #5                  // Field org/jboss/logging/Logger$Level.ERROR:Lorg/jboss/logging/Logger$Level;
      10: aconst_null
      11: aload_0
      12: invokevirtual #159                // Method alpnConnectionFailed$str:()Ljava/lang/String;
      15: aload_1
      16: invokevirtual #13                 // Method org/jboss/logging/Logger.logf:(Ljava/lang/String;Lorg/jboss/logging/Logger$Level;Ljava/lang/Throwable;Ljava/lang/String;Ljava/lang/Object;)V
      19: return

  protected java.lang.String alpnConnectionFailed$str();
    Code:
       0: ldc           #160                // String UT005079: ALPN negotiation on %s failed
       2: areturn

  public final void resumedAndDispatched();
    Code:
       0: aload_0
       1: getfield      #3                  // Field org/jboss/logging/DelegatingBasicLogger.log:Lorg/jboss/logging/Logger;
       4: getstatic     #4                  // Field FQCN:Ljava/lang/String;
       7: getstatic     #5                  // Field org/jboss/logging/Logger$Level.ERROR:Lorg/jboss/logging/Logger$Level;
      10: aconst_null
      11: aload_0
      12: invokevirtual #161                // Method resumedAndDispatched$str:()Ljava/lang/String;
      15: iconst_0
      16: anewarray     #7                  // class java/lang/Object
      19: invokevirtual #8                  // Method org/jboss/logging/Logger.logf:(Ljava/lang/String;Lorg/jboss/logging/Logger$Level;Ljava/lang/Throwable;Ljava/lang/String;[Ljava/lang/Object;)V
      22: return

  protected java.lang.String resumedAndDispatched$str();
    Code:
       0: ldc           #162                // String UT005080: HttpServerExchange cannot have both async IO resumed and dispatch() called in the same cycle
       2: areturn

  public final void cannotProxyStartedRequest(io.undertow.server.HttpServerExchange);
    Code:
       0: aload_0
       1: getfield      #3                  // Field org/jboss/logging/DelegatingBasicLogger.log:Lorg/jboss/logging/Logger;
       4: getstatic     #4                  // Field FQCN:Ljava/lang/String;
       7: getstatic     #5                  // Field org/jboss/logging/Logger$Level.ERROR:Lorg/jboss/logging/Logger$Level;
      10: aconst_null
      11: aload_0
      12: invokevirtual #163                // Method cannotProxyStartedRequest$str:()Ljava/lang/String;
      15: aload_1
      16: invokevirtual #13                 // Method org/jboss/logging/Logger.logf:(Ljava/lang/String;Lorg/jboss/logging/Logger$Level;Ljava/lang/Throwable;Ljava/lang/String;Ljava/lang/Object;)V
      19: return

  protected java.lang.String cannotProxyStartedRequest$str();
    Code:
       0: ldc           #164                // String UT005081: Response has already been started, cannot proxy request %s
       2: areturn

  protected java.lang.String cannotUseWildcardAddressAsModClusterManagementHost$str();
    Code:
       0: ldc           #165                // String UT005082: Configured mod_cluster management host address cannot be a wildcard address (%s)!
       2: areturn

  public final java.lang.IllegalArgumentException cannotUseWildcardAddressAsModClusterManagementHost(java.lang.String);
    Code:
       0: new           #166                // class java/lang/IllegalArgumentException
       3: dup
       4: aload_0
       5: invokevirtual #118                // Method getLoggingLocale:()Ljava/util/Locale;
       8: aload_0
       9: invokevirtual #167                // Method cannotUseWildcardAddressAsModClusterManagementHost$str:()Ljava/lang/String;
      12: iconst_1
      13: anewarray     #7                  // class java/lang/Object
      16: dup
      17: iconst_0
      18: aload_1
      19: aastore
      20: invokestatic  #120                // Method java/lang/String.format:(Ljava/util/Locale;Ljava/lang/String;[Ljava/lang/Object;)Ljava/lang/String;
      23: invokespecial #168                // Method java/lang/IllegalArgumentException."<init>":(Ljava/lang/String;)V
      26: astore_2
      27: aload_2
      28: invokestatic  #122                // Method _copyStackTraceMinusOne:(Ljava/lang/Throwable;)V
      31: aload_2
      32: areturn

  protected java.lang.String unexpectedEndOfCompressedInput$str();
    Code:
       0: ldc           #169                // String UT005083: Unexpected end of compressed input
       2: areturn

  public final java.io.IOException unexpectedEndOfCompressedInput();
    Code:
       0: new           #170                // class java/io/IOException
       3: dup
       4: aload_0
       5: invokevirtual #118                // Method getLoggingLocale:()Ljava/util/Locale;
       8: aload_0
       9: invokevirtual #171                // Method unexpectedEndOfCompressedInput$str:()Ljava/lang/String;
      12: iconst_0
      13: anewarray     #7                  // class java/lang/Object
      16: invokestatic  #120                // Method java/lang/String.format:(Ljava/util/Locale;Ljava/lang/String;[Ljava/lang/Object;)Ljava/lang/String;
      19: invokespecial #172                // Method java/io/IOException."<init>":(Ljava/lang/String;)V
      22: astore_1
      23: aload_1
      24: invokestatic  #122                // Method _copyStackTraceMinusOne:(Ljava/lang/Throwable;)V
      27: aload_1
      28: areturn

  protected java.lang.String dataLargerThanContentLength$str();
    Code:
       0: ldc           #173                // String UT005084: Attempted to write %s bytes however content-length has been set to %s
       2: areturn

  public final java.io.IOException dataLargerThanContentLength(long, long);
    Code:
       0: new           #170                // class java/io/IOException
       3: dup
       4: aload_0
       5: invokevirtual #118                // Method getLoggingLocale:()Ljava/util/Locale;
       8: aload_0
       9: invokevirtual #174                // Method dataLargerThanContentLength$str:()Ljava/lang/String;
      12: iconst_2
      13: anewarray     #7                  // class java/lang/Object
      16: dup
      17: iconst_0
      18: lload_1
      19: invokestatic  #94                 // Method java/lang/Long.valueOf:(J)Ljava/lang/Long;
      22: aastore
      23: dup
      24: iconst_1
      25: lload_3
      26: invokestatic  #94                 // Method java/lang/Long.valueOf:(J)Ljava/lang/Long;
      29: aastore
      30: invokestatic  #120                // Method java/lang/String.format:(Ljava/util/Locale;Ljava/lang/String;[Ljava/lang/Object;)Ljava/lang/String;
      33: invokespecial #172                // Method java/io/IOException."<init>":(Ljava/lang/String;)V
      36: astore        5
      38: aload         5
      40: invokestatic  #122                // Method _copyStackTraceMinusOne:(Ljava/lang/Throwable;)V
      43: aload         5
      45: areturn

  public final void responseWasNotTerminated(io.undertow.server.ServerConnection, io.undertow.server.HttpServerExchange);
    Code:
       0: aload_0
       1: getfield      #3                  // Field org/jboss/logging/DelegatingBasicLogger.log:Lorg/jboss/logging/Logger;
       4: getstatic     #4                  // Field FQCN:Ljava/lang/String;
       7: getstatic     #15                 // Field org/jboss/logging/Logger$Level.DEBUG:Lorg/jboss/logging/Logger$Level;
      10: aconst_null
      11: aload_0
      12: invokevirtual #175                // Method responseWasNotTerminated$str:()Ljava/lang/String;
      15: aload_1
      16: aload_2
      17: invokevirtual #18                 // Method org/jboss/logging/Logger.logf:(Ljava/lang/String;Lorg/jboss/logging/Logger$Level;Ljava/lang/Throwable;Ljava/lang/String;Ljava/lang/Object;Ljava/lang/Object;)V
      20: return

  protected java.lang.String responseWasNotTerminated$str();
    Code:
       0: ldc           #176                // String UT005085: Connection %s for exchange %s was not closed cleanly, forcibly closing connection
       2: areturn

  public final void failedToAcceptSSLRequest(java.lang.Exception);
    Code:
       0: aload_0
       1: getfield      #3                  // Field org/jboss/logging/DelegatingBasicLogger.log:Lorg/jboss/logging/Logger;
       4: getstatic     #4                  // Field FQCN:Ljava/lang/String;
       7: getstatic     #5                  // Field org/jboss/logging/Logger$Level.ERROR:Lorg/jboss/logging/Logger$Level;
      10: aload_1
      11: aload_0
      12: invokevirtual #177                // Method failedToAcceptSSLRequest$str:()Ljava/lang/String;
      15: iconst_0
      16: anewarray     #7                  // class java/lang/Object
      19: invokevirtual #8                  // Method org/jboss/logging/Logger.logf:(Ljava/lang/String;Lorg/jboss/logging/Logger$Level;Ljava/lang/Throwable;Ljava/lang/String;[Ljava/lang/Object;)V
      22: return

  protected java.lang.String failedToAcceptSSLRequest$str();
    Code:
       0: ldc           #178                // String UT005086: Failed to accept SSL request
       2: areturn

  public final void closeAsyncFailed(java.io.IOException);
    Code:
       0: aload_0
       1: getfield      #3                  // Field org/jboss/logging/DelegatingBasicLogger.log:Lorg/jboss/logging/Logger;
       4: getstatic     #4                  // Field FQCN:Ljava/lang/String;
       7: getstatic     #5                  // Field org/jboss/logging/Logger$Level.ERROR:Lorg/jboss/logging/Logger$Level;
      10: aload_1
      11: aload_0
      12: invokevirtual #179                // Method closeAsyncFailed$str:()Ljava/lang/String;
      15: iconst_0
      16: anewarray     #7                  // class java/lang/Object
      19: invokevirtual #8                  // Method org/jboss/logging/Logger.logf:(Ljava/lang/String;Lorg/jboss/logging/Logger$Level;Ljava/lang/Throwable;Ljava/lang/String;[Ljava/lang/Object;)V
      22: return

  protected java.lang.String closeAsyncFailed$str();
    Code:
       0: ldc           #180                // String UT005088: Failed to execute ServletOutputStream.closeAsync() on IO thread
       2: areturn

  protected java.lang.String nullParameter$str();
    Code:
       0: ldc           #181                // String UT005089: Method parameter \'%s\' cannot be null
       2: areturn

  public final java.lang.IllegalArgumentException nullParameter(java.lang.String);
    Code:
       0: new           #166                // class java/lang/IllegalArgumentException
       3: dup
       4: aload_0
       5: invokevirtual #118                // Method getLoggingLocale:()Ljava/util/Locale;
       8: aload_0
       9: invokevirtual #182                // Method nullParameter$str:()Ljava/lang/String;
      12: iconst_1
      13: anewarray     #7                  // class java/lang/Object
      16: dup
      17: iconst_0
      18: aload_1
      19: aastore
      20: invokestatic  #120                // Method java/lang/String.format:(Ljava/util/Locale;Ljava/lang/String;[Ljava/lang/Object;)Ljava/lang/String;
      23: invokespecial #168                // Method java/lang/IllegalArgumentException."<init>":(Ljava/lang/String;)V
      26: astore_2
      27: aload_2
      28: invokestatic  #122                // Method _copyStackTraceMinusOne:(Ljava/lang/Throwable;)V
      31: aload_2
      32: areturn

  public final void handleUnexpectedFailure(java.lang.Throwable);
    Code:
       0: aload_0
       1: getfield      #3                  // Field org/jboss/logging/DelegatingBasicLogger.log:Lorg/jboss/logging/Logger;
       4: getstatic     #4                  // Field FQCN:Ljava/lang/String;
       7: getstatic     #5                  // Field org/jboss/logging/Logger$Level.ERROR:Lorg/jboss/logging/Logger$Level;
      10: aload_1
      11: aload_0
      12: invokevirtual #183                // Method handleUnexpectedFailure$str:()Ljava/lang/String;
      15: iconst_0
      16: anewarray     #7                  // class java/lang/Object
      19: invokevirtual #8                  // Method org/jboss/logging/Logger.logf:(Ljava/lang/String;Lorg/jboss/logging/Logger$Level;Ljava/lang/Throwable;Ljava/lang/String;[Ljava/lang/Object;)V
      22: return

  protected java.lang.String handleUnexpectedFailure$str();
    Code:
       0: ldc           #184                // String UT005090: Unexpected failure
       2: areturn

  public final void directBufferDeallocatorInitializationFailed(java.lang.Throwable);
    Code:
       0: aload_0
       1: getfield      #3                  // Field org/jboss/logging/DelegatingBasicLogger.log:Lorg/jboss/logging/Logger;
       4: getstatic     #4                  // Field FQCN:Ljava/lang/String;
       7: getstatic     #5                  // Field org/jboss/logging/Logger$Level.ERROR:Lorg/jboss/logging/Logger$Level;
      10: aload_1
      11: aload_0
      12: invokevirtual #185                // Method directBufferDeallocatorInitializationFailed$str:()Ljava/lang/String;
      15: iconst_0
      16: anewarray     #7                  // class java/lang/Object
      19: invokevirtual #8                  // Method org/jboss/logging/Logger.logf:(Ljava/lang/String;Lorg/jboss/logging/Logger$Level;Ljava/lang/Throwable;Ljava/lang/String;[Ljava/lang/Object;)V
      22: return

  protected java.lang.String directBufferDeallocatorInitializationFailed$str();
    Code:
       0: ldc           #186                // String UT005091: Failed to initialize DirectByteBufferDeallocator
       2: areturn

  public final void directBufferDeallocationFailed(java.lang.Throwable);
    Code:
       0: aload_0
       1: getfield      #3                  // Field org/jboss/logging/DelegatingBasicLogger.log:Lorg/jboss/logging/Logger;
       4: getstatic     #4                  // Field FQCN:Ljava/lang/String;
       7: getstatic     #15                 // Field org/jboss/logging/Logger$Level.DEBUG:Lorg/jboss/logging/Logger$Level;
      10: aload_1
      11: aload_0
      12: invokevirtual #187                // Method directBufferDeallocationFailed$str:()Ljava/lang/String;
      15: iconst_0
      16: anewarray     #7                  // class java/lang/Object
      19: invokevirtual #8                  // Method org/jboss/logging/Logger.logf:(Ljava/lang/String;Lorg/jboss/logging/Logger$Level;Ljava/lang/Throwable;Ljava/lang/String;[Ljava/lang/Object;)V
      22: return

  protected java.lang.String directBufferDeallocationFailed$str();
    Code:
       0: ldc           #188                // String UT005092: Failed to free direct buffer
       2: areturn

  public final void blockingReadTimedOut(org.xnio.channels.ReadTimeoutException);
    Code:
       0: aload_0
       1: getfield      #3                  // Field org/jboss/logging/DelegatingBasicLogger.log:Lorg/jboss/logging/Logger;
       4: getstatic     #4                  // Field FQCN:Ljava/lang/String;
       7: getstatic     #15                 // Field org/jboss/logging/Logger$Level.DEBUG:Lorg/jboss/logging/Logger$Level;
      10: aload_1
      11: aload_0
      12: invokevirtual #189                // Method blockingReadTimedOut$str:()Ljava/lang/String;
      15: iconst_0
      16: anewarray     #7                  // class java/lang/Object
      19: invokevirtual #8                  // Method org/jboss/logging/Logger.logf:(Ljava/lang/String;Lorg/jboss/logging/Logger$Level;Ljava/lang/Throwable;Ljava/lang/String;[Ljava/lang/Object;)V
      22: return

  protected java.lang.String blockingReadTimedOut$str();
    Code:
       0: ldc           #190                // String UT005093: Blocking read timed out
       2: areturn

  public final void blockingWriteTimedOut(org.xnio.channels.WriteTimeoutException);
    Code:
       0: aload_0
       1: getfield      #3                  // Field org/jboss/logging/DelegatingBasicLogger.log:Lorg/jboss/logging/Logger;
       4: getstatic     #4                  // Field FQCN:Ljava/lang/String;
       7: getstatic     #15                 // Field org/jboss/logging/Logger$Level.DEBUG:Lorg/jboss/logging/Logger$Level;
      10: aload_1
      11: aload_0
      12: invokevirtual #191                // Method blockingWriteTimedOut$str:()Ljava/lang/String;
      15: iconst_0
      16: anewarray     #7                  // class java/lang/Object
      19: invokevirtual #8                  // Method org/jboss/logging/Logger.logf:(Ljava/lang/String;Lorg/jboss/logging/Logger$Level;Ljava/lang/Throwable;Ljava/lang/String;[Ljava/lang/Object;)V
      22: return

  protected java.lang.String blockingWriteTimedOut$str();
    Code:
       0: ldc           #192                // String UT005094: Blocking write timed out
       2: areturn

  public final void sslEngineDelegatedTaskRejected(java.util.concurrent.RejectedExecutionException);
    Code:
       0: aload_0
       1: getfield      #3                  // Field org/jboss/logging/DelegatingBasicLogger.log:Lorg/jboss/logging/Logger;
       4: getstatic     #4                  // Field FQCN:Ljava/lang/String;
       7: getstatic     #15                 // Field org/jboss/logging/Logger$Level.DEBUG:Lorg/jboss/logging/Logger$Level;
      10: aload_1
      11: aload_0
      12: invokevirtual #193                // Method sslEngineDelegatedTaskRejected$str:()Ljava/lang/String;
      15: iconst_0
      16: anewarray     #7                  // class java/lang/Object
      19: invokevirtual #8                  // Method org/jboss/logging/Logger.logf:(Ljava/lang/String;Lorg/jboss/logging/Logger$Level;Ljava/lang/Throwable;Ljava/lang/String;[Ljava/lang/Object;)V
      22: return

  protected java.lang.String sslEngineDelegatedTaskRejected$str();
    Code:
       0: ldc           #194                // String UT005095: SSLEngine delegated task was rejected
       2: areturn

  public final void authenticationFailedFor(java.lang.String, io.undertow.server.HttpServerExchange, java.lang.Exception);
    Code:
       0: aload_0
       1: getfield      #3                  // Field org/jboss/logging/DelegatingBasicLogger.log:Lorg/jboss/logging/Logger;
       4: getstatic     #4                  // Field FQCN:Ljava/lang/String;
       7: getstatic     #15                 // Field org/jboss/logging/Logger$Level.DEBUG:Lorg/jboss/logging/Logger$Level;
      10: aload_3
      11: aload_0
      12: invokevirtual #195                // Method authenticationFailedFor$str:()Ljava/lang/String;
      15: aload_1
      16: aload_2
      17: invokevirtual #18                 // Method org/jboss/logging/Logger.logf:(Ljava/lang/String;Lorg/jboss/logging/Logger$Level;Ljava/lang/Throwable;Ljava/lang/String;Ljava/lang/Object;Ljava/lang/Object;)V
      20: return

  protected java.lang.String authenticationFailedFor$str();
    Code:
       0: ldc           #196                // String UT005096: Authentication failed for digest header %s in %s
       2: areturn

  public final void failedToObtainSubject(io.undertow.server.HttpServerExchange, java.security.GeneralSecurityException);
    Code:
       0: aload_0
       1: getfield      #3                  // Field org/jboss/logging/DelegatingBasicLogger.log:Lorg/jboss/logging/Logger;
       4: getstatic     #4                  // Field FQCN:Ljava/lang/String;
       7: getstatic     #15                 // Field org/jboss/logging/Logger$Level.DEBUG:Lorg/jboss/logging/Logger$Level;
      10: aload_2
      11: aload_0
      12: invokevirtual #197                // Method failedToObtainSubject$str:()Ljava/lang/String;
      15: aload_1
      16: invokevirtual #13                 // Method org/jboss/logging/Logger.logf:(Ljava/lang/String;Lorg/jboss/logging/Logger$Level;Ljava/lang/Throwable;Ljava/lang/String;Ljava/lang/Object;)V
      19: return

  protected java.lang.String failedToObtainSubject$str();
    Code:
       0: ldc           #198                // String UT005097: Failed to obtain subject for %s
       2: areturn

  public final void failedToNegotiateAtGSSAPI(io.undertow.server.HttpServerExchange, java.lang.Throwable);
    Code:
       0: aload_0
       1: getfield      #3                  // Field org/jboss/logging/DelegatingBasicLogger.log:Lorg/jboss/logging/Logger;
       4: getstatic     #4                  // Field FQCN:Ljava/lang/String;
       7: getstatic     #15                 // Field org/jboss/logging/Logger$Level.DEBUG:Lorg/jboss/logging/Logger$Level;
      10: aload_2
      11: aload_0
      12: invokevirtual #199                // Method failedToNegotiateAtGSSAPI$str:()Ljava/lang/String;
      15: aload_1
      16: invokevirtual #13                 // Method org/jboss/logging/Logger.logf:(Ljava/lang/String;Lorg/jboss/logging/Logger$Level;Ljava/lang/Throwable;Ljava/lang/String;Ljava/lang/Object;)V
      19: return

  protected java.lang.String failedToNegotiateAtGSSAPI$str();
    Code:
       0: ldc           #200                // String UT005098: GSSAPI negotiation failed for %s
       2: areturn

  public final void failedToCreateSSOForSession(java.lang.String);
    Code:
       0: aload_0
       1: getfield      #3                  // Field org/jboss/logging/DelegatingBasicLogger.log:Lorg/jboss/logging/Logger;
       4: getstatic     #4                  // Field FQCN:Ljava/lang/String;
       7: getstatic     #65                 // Field org/jboss/logging/Logger$Level.WARN:Lorg/jboss/logging/Logger$Level;
      10: aconst_null
      11: aload_0
      12: invokevirtual #201                // Method failedToCreateSSOForSession$str:()Ljava/lang/String;
      15: aload_1
      16: invokevirtual #13                 // Method org/jboss/logging/Logger.logf:(Ljava/lang/String;Lorg/jboss/logging/Logger$Level;Ljava/lang/Throwable;Ljava/lang/String;Ljava/lang/Object;)V
      19: return

  protected java.lang.String failedToCreateSSOForSession$str();
    Code:
       0: ldc           #202                // String UT005099: Failed to create SSO for session \'%s\'
       2: areturn

  public final void failedToListPathsForFile(java.nio.file.Path);
    Code:
       0: aload_0
       1: getfield      #3                  // Field org/jboss/logging/DelegatingBasicLogger.log:Lorg/jboss/logging/Logger;
       4: getstatic     #4                  // Field FQCN:Ljava/lang/String;
       7: getstatic     #15                 // Field org/jboss/logging/Logger$Level.DEBUG:Lorg/jboss/logging/Logger$Level;
      10: aconst_null
      11: aload_0
      12: invokevirtual #203                // Method failedToListPathsForFile$str:()Ljava/lang/String;
      15: aload_1
      16: invokevirtual #13                 // Method org/jboss/logging/Logger.logf:(Ljava/lang/String;Lorg/jboss/logging/Logger$Level;Ljava/lang/Throwable;Ljava/lang/String;Ljava/lang/Object;)V
      19: return

  protected java.lang.String failedToListPathsForFile$str();
    Code:
       0: ldc           #204                // String UT005100: Failed to list paths for \'%s\'
       2: areturn

  public final void noSourceToListResourcesFrom();
    Code:
       0: aload_0
       1: getfield      #3                  // Field org/jboss/logging/DelegatingBasicLogger.log:Lorg/jboss/logging/Logger;
       4: getstatic     #4                  // Field FQCN:Ljava/lang/String;
       7: getstatic     #15                 // Field org/jboss/logging/Logger$Level.DEBUG:Lorg/jboss/logging/Logger$Level;
      10: aconst_null
      11: aload_0
      12: invokevirtual #205                // Method noSourceToListResourcesFrom$str:()Ljava/lang/String;
      15: iconst_0
      16: anewarray     #7                  // class java/lang/Object
      19: invokevirtual #8                  // Method org/jboss/logging/Logger.logf:(Ljava/lang/String;Lorg/jboss/logging/Logger$Level;Ljava/lang/Throwable;Ljava/lang/String;[Ljava/lang/Object;)V
      22: return

  protected java.lang.String noSourceToListResourcesFrom$str();
    Code:
       0: ldc           #206                // String UT005101: No source to list resources from
       2: areturn

  public final void noFrameflushInTimeout(long);
    Code:
       0: aload_0
       1: getfield      #3                  // Field org/jboss/logging/DelegatingBasicLogger.log:Lorg/jboss/logging/Logger;
       4: getstatic     #4                  // Field FQCN:Ljava/lang/String;
       7: getstatic     #65                 // Field org/jboss/logging/Logger$Level.WARN:Lorg/jboss/logging/Logger$Level;
      10: aconst_null
      11: aload_0
      12: invokevirtual #207                // Method noFrameflushInTimeout$str:()Ljava/lang/String;
      15: lload_1
      16: invokestatic  #94                 // Method java/lang/Long.valueOf:(J)Ljava/lang/Long;
      19: invokevirtual #13                 // Method org/jboss/logging/Logger.logf:(Ljava/lang/String;Lorg/jboss/logging/Logger$Level;Ljava/lang/Throwable;Ljava/lang/String;Ljava/lang/Object;)V
      22: return

  protected java.lang.String noFrameflushInTimeout$str();
    Code:
       0: ldc           #208                // String UT005102: Flushing waiting in a frame more than %s miliseconds. The framed channel will be forcibly closed.
       2: areturn

  static {};
    Code:
       0: ldc           #209                // class io/undertow/UndertowLogger_$logger
       2: invokevirtual #210                // Method java/lang/Class.getName:()Ljava/lang/String;
       5: putstatic     #4                  // Field FQCN:Ljava/lang/String;
       8: getstatic     #211                // Field java/util/Locale.ROOT:Ljava/util/Locale;
      11: putstatic     #2                  // Field LOCALE:Ljava/util/Locale;
      14: return
}
