Compiled from "Regex.kt"
final class kotlin.text.Regex$findAll$2 extends kotlin.jvm.internal.FunctionReference implements kotlin.jvm.functions.Function1<kotlin.text.MatchResult, kotlin.text.MatchResult> {
  public static final kotlin.text.Regex$findAll$2 INSTANCE;

  public java.lang.Object invoke(java.lang.Object);
    Code:
       0: aload_0
       1: aload_1
       2: checkcast     #11                 // class kotlin/text/MatchResult
       5: invokevirtual #14                 // Method invoke:(Lkotlin/text/MatchResult;)Lkotlin/text/MatchResult;
       8: areturn

  public final kotlin.text.MatchResult invoke(kotlin.text.MatchResult);
    Code:
       0: aload_1
       1: ldc           #18                 // String p1
       3: invokestatic  #24                 // Method kotlin/jvm/internal/Intrinsics.checkParameterIsNotNull:(Ljava/lang/Object;Ljava/lang/String;)V
       6: aload_1
       7: invokeinterface #28,  1           // InterfaceMethod kotlin/text/MatchResult.next:()Lkotlin/text/MatchResult;
      12: areturn

  public final kotlin.reflect.KDeclarationContainer getOwner();
    Code:
       0: ldc           #11                 // class kotlin/text/MatchResult
       2: invokestatic  #39                 // Method kotlin/jvm/internal/Reflection.getOrCreateKotlinClass:(Ljava/lang/Class;)Lkotlin/reflect/KClass;
       5: areturn

  public final java.lang.String getName();
    Code:
       0: ldc           #42                 // String next
       2: areturn

  public final java.lang.String getSignature();
    Code:
       0: ldc           #45                 // String next()Lkotlin/text/MatchResult;
       2: areturn

  kotlin.text.Regex$findAll$2();
    Code:
       0: aload_0
       1: iconst_1
       2: invokespecial #50                 // Method kotlin/jvm/internal/FunctionReference."<init>":(I)V
       5: return

  static {};
    Code:
       0: new           #2                  // class kotlin/text/Regex$findAll$2
       3: dup
       4: invokespecial #71                 // Method "<init>":()V
       7: putstatic     #73                 // Field INSTANCE:Lkotlin/text/Regex$findAll$2;
      10: return
}
