Compiled from "TerminationCause.java"
public final class org.mobicents.protocols.ss7.map.api.service.lsm.TerminationCause extends java.lang.Enum<org.mobicents.protocols.ss7.map.api.service.lsm.TerminationCause> {
  public static final org.mobicents.protocols.ss7.map.api.service.lsm.TerminationCause normal;

  public static final org.mobicents.protocols.ss7.map.api.service.lsm.TerminationCause errorundefined;

  public static final org.mobicents.protocols.ss7.map.api.service.lsm.TerminationCause internalTimeout;

  public static final org.mobicents.protocols.ss7.map.api.service.lsm.TerminationCause congestion;

  public static final org.mobicents.protocols.ss7.map.api.service.lsm.TerminationCause mtlrRestart;

  public static final org.mobicents.protocols.ss7.map.api.service.lsm.TerminationCause privacyViolation;

  private final int cause;

  private static final org.mobicents.protocols.ss7.map.api.service.lsm.TerminationCause[] $VALUES;

  public static org.mobicents.protocols.ss7.map.api.service.lsm.TerminationCause[] values();
    Code:
       0: getstatic     #1                  // Field $VALUES:[Lorg/mobicents/protocols/ss7/map/api/service/lsm/TerminationCause;
       3: invokevirtual #2                  // Method "[Lorg/mobicents/protocols/ss7/map/api/service/lsm/TerminationCause;".clone:()Ljava/lang/Object;
       6: checkcast     #3                  // class "[Lorg/mobicents/protocols/ss7/map/api/service/lsm/TerminationCause;"
       9: areturn

  public static org.mobicents.protocols.ss7.map.api.service.lsm.TerminationCause valueOf(java.lang.String);
    Code:
       0: ldc_w         #4                  // class org/mobicents/protocols/ss7/map/api/service/lsm/TerminationCause
       3: aload_0
       4: invokestatic  #5                  // Method java/lang/Enum.valueOf:(Ljava/lang/Class;Ljava/lang/String;)Ljava/lang/Enum;
       7: checkcast     #4                  // class org/mobicents/protocols/ss7/map/api/service/lsm/TerminationCause
      10: areturn

  private org.mobicents.protocols.ss7.map.api.service.lsm.TerminationCause(int);
    Code:
       0: aload_0
       1: aload_1
       2: iload_2
       3: invokespecial #6                  // Method java/lang/Enum."<init>":(Ljava/lang/String;I)V
       6: aload_0
       7: iload_3
       8: putfield      #7                  // Field cause:I
      11: return

  public int getCause();
    Code:
       0: aload_0
       1: getfield      #7                  // Field cause:I
       4: ireturn

  public static org.mobicents.protocols.ss7.map.api.service.lsm.TerminationCause getTerminationCause(int);
    Code:
       0: iload_0
       1: tableswitch   { // 0 to 5
                     0: 40
                     1: 44
                     2: 48
                     3: 52
                     4: 56
                     5: 60
               default: 64
          }
      40: getstatic     #8                  // Field normal:Lorg/mobicents/protocols/ss7/map/api/service/lsm/TerminationCause;
      43: areturn
      44: getstatic     #9                  // Field errorundefined:Lorg/mobicents/protocols/ss7/map/api/service/lsm/TerminationCause;
      47: areturn
      48: getstatic     #10                 // Field internalTimeout:Lorg/mobicents/protocols/ss7/map/api/service/lsm/TerminationCause;
      51: areturn
      52: getstatic     #11                 // Field congestion:Lorg/mobicents/protocols/ss7/map/api/service/lsm/TerminationCause;
      55: areturn
      56: getstatic     #12                 // Field mtlrRestart:Lorg/mobicents/protocols/ss7/map/api/service/lsm/TerminationCause;
      59: areturn
      60: getstatic     #13                 // Field privacyViolation:Lorg/mobicents/protocols/ss7/map/api/service/lsm/TerminationCause;
      63: areturn
      64: aconst_null
      65: areturn

  static {};
    Code:
       0: new           #4                  // class org/mobicents/protocols/ss7/map/api/service/lsm/TerminationCause
       3: dup
       4: ldc           #14                 // String normal
       6: iconst_0
       7: iconst_0
       8: invokespecial #15                 // Method "<init>":(Ljava/lang/String;II)V
      11: putstatic     #8                  // Field normal:Lorg/mobicents/protocols/ss7/map/api/service/lsm/TerminationCause;
      14: new           #4                  // class org/mobicents/protocols/ss7/map/api/service/lsm/TerminationCause
      17: dup
      18: ldc           #16                 // String errorundefined
      20: iconst_1
      21: iconst_1
      22: invokespecial #15                 // Method "<init>":(Ljava/lang/String;II)V
      25: putstatic     #9                  // Field errorundefined:Lorg/mobicents/protocols/ss7/map/api/service/lsm/TerminationCause;
      28: new           #4                  // class org/mobicents/protocols/ss7/map/api/service/lsm/TerminationCause
      31: dup
      32: ldc           #17                 // String internalTimeout
      34: iconst_2
      35: iconst_2
      36: invokespecial #15                 // Method "<init>":(Ljava/lang/String;II)V
      39: putstatic     #10                 // Field internalTimeout:Lorg/mobicents/protocols/ss7/map/api/service/lsm/TerminationCause;
      42: new           #4                  // class org/mobicents/protocols/ss7/map/api/service/lsm/TerminationCause
      45: dup
      46: ldc           #18                 // String congestion
      48: iconst_3
      49: iconst_3
      50: invokespecial #15                 // Method "<init>":(Ljava/lang/String;II)V
      53: putstatic     #11                 // Field congestion:Lorg/mobicents/protocols/ss7/map/api/service/lsm/TerminationCause;
      56: new           #4                  // class org/mobicents/protocols/ss7/map/api/service/lsm/TerminationCause
      59: dup
      60: ldc           #19                 // String mtlrRestart
      62: iconst_4
      63: iconst_4
      64: invokespecial #15                 // Method "<init>":(Ljava/lang/String;II)V
      67: putstatic     #12                 // Field mtlrRestart:Lorg/mobicents/protocols/ss7/map/api/service/lsm/TerminationCause;
      70: new           #4                  // class org/mobicents/protocols/ss7/map/api/service/lsm/TerminationCause
      73: dup
      74: ldc           #20                 // String privacyViolation
      76: iconst_5
      77: iconst_5
      78: invokespecial #15                 // Method "<init>":(Ljava/lang/String;II)V
      81: putstatic     #13                 // Field privacyViolation:Lorg/mobicents/protocols/ss7/map/api/service/lsm/TerminationCause;
      84: bipush        6
      86: anewarray     #4                  // class org/mobicents/protocols/ss7/map/api/service/lsm/TerminationCause
      89: dup
      90: iconst_0
      91: getstatic     #8                  // Field normal:Lorg/mobicents/protocols/ss7/map/api/service/lsm/TerminationCause;
      94: aastore
      95: dup
      96: iconst_1
      97: getstatic     #9                  // Field errorundefined:Lorg/mobicents/protocols/ss7/map/api/service/lsm/TerminationCause;
     100: aastore
     101: dup
     102: iconst_2
     103: getstatic     #10                 // Field internalTimeout:Lorg/mobicents/protocols/ss7/map/api/service/lsm/TerminationCause;
     106: aastore
     107: dup
     108: iconst_3
     109: getstatic     #11                 // Field congestion:Lorg/mobicents/protocols/ss7/map/api/service/lsm/TerminationCause;
     112: aastore
     113: dup
     114: iconst_4
     115: getstatic     #12                 // Field mtlrRestart:Lorg/mobicents/protocols/ss7/map/api/service/lsm/TerminationCause;
     118: aastore
     119: dup
     120: iconst_5
     121: getstatic     #13                 // Field privacyViolation:Lorg/mobicents/protocols/ss7/map/api/service/lsm/TerminationCause;
     124: aastore
     125: putstatic     #1                  // Field $VALUES:[Lorg/mobicents/protocols/ss7/map/api/service/lsm/TerminationCause;
     128: return
}
