Compiled from "VelocityType.java"
public final class org.mobicents.protocols.ss7.map.api.service.lsm.VelocityType extends java.lang.Enum<org.mobicents.protocols.ss7.map.api.service.lsm.VelocityType> {
  public static final org.mobicents.protocols.ss7.map.api.service.lsm.VelocityType HorizontalVelocity;

  public static final org.mobicents.protocols.ss7.map.api.service.lsm.VelocityType HorizontalWithVerticalVelocity;

  public static final org.mobicents.protocols.ss7.map.api.service.lsm.VelocityType HorizontalVelocityWithUncertainty;

  public static final org.mobicents.protocols.ss7.map.api.service.lsm.VelocityType HorizontalWithVerticalVelocityAndUncertainty;

  private final int type;

  private static final org.mobicents.protocols.ss7.map.api.service.lsm.VelocityType[] $VALUES;

  public static org.mobicents.protocols.ss7.map.api.service.lsm.VelocityType[] values();
    Code:
       0: getstatic     #1                  // Field $VALUES:[Lorg/mobicents/protocols/ss7/map/api/service/lsm/VelocityType;
       3: invokevirtual #2                  // Method "[Lorg/mobicents/protocols/ss7/map/api/service/lsm/VelocityType;".clone:()Ljava/lang/Object;
       6: checkcast     #3                  // class "[Lorg/mobicents/protocols/ss7/map/api/service/lsm/VelocityType;"
       9: areturn

  public static org.mobicents.protocols.ss7.map.api.service.lsm.VelocityType valueOf(java.lang.String);
    Code:
       0: ldc_w         #4                  // class org/mobicents/protocols/ss7/map/api/service/lsm/VelocityType
       3: aload_0
       4: invokestatic  #5                  // Method java/lang/Enum.valueOf:(Ljava/lang/Class;Ljava/lang/String;)Ljava/lang/Enum;
       7: checkcast     #4                  // class org/mobicents/protocols/ss7/map/api/service/lsm/VelocityType
      10: areturn

  private org.mobicents.protocols.ss7.map.api.service.lsm.VelocityType(int);
    Code:
       0: aload_0
       1: aload_1
       2: iload_2
       3: invokespecial #6                  // Method java/lang/Enum."<init>":(Ljava/lang/String;I)V
       6: aload_0
       7: iload_3
       8: putfield      #7                  // Field type:I
      11: return

  public int getCode();
    Code:
       0: aload_0
       1: getfield      #7                  // Field type:I
       4: ireturn

  public static org.mobicents.protocols.ss7.map.api.service.lsm.VelocityType getInstance(int);
    Code:
       0: iload_0
       1: tableswitch   { // 0 to 3
                     0: 32
                     1: 36
                     2: 40
                     3: 44
               default: 48
          }
      32: getstatic     #8                  // Field HorizontalVelocity:Lorg/mobicents/protocols/ss7/map/api/service/lsm/VelocityType;
      35: areturn
      36: getstatic     #9                  // Field HorizontalWithVerticalVelocity:Lorg/mobicents/protocols/ss7/map/api/service/lsm/VelocityType;
      39: areturn
      40: getstatic     #10                 // Field HorizontalVelocityWithUncertainty:Lorg/mobicents/protocols/ss7/map/api/service/lsm/VelocityType;
      43: areturn
      44: getstatic     #11                 // Field HorizontalWithVerticalVelocityAndUncertainty:Lorg/mobicents/protocols/ss7/map/api/service/lsm/VelocityType;
      47: areturn
      48: aconst_null
      49: areturn

  static {};
    Code:
       0: new           #4                  // class org/mobicents/protocols/ss7/map/api/service/lsm/VelocityType
       3: dup
       4: ldc           #12                 // String HorizontalVelocity
       6: iconst_0
       7: iconst_0
       8: invokespecial #13                 // Method "<init>":(Ljava/lang/String;II)V
      11: putstatic     #8                  // Field HorizontalVelocity:Lorg/mobicents/protocols/ss7/map/api/service/lsm/VelocityType;
      14: new           #4                  // class org/mobicents/protocols/ss7/map/api/service/lsm/VelocityType
      17: dup
      18: ldc           #14                 // String HorizontalWithVerticalVelocity
      20: iconst_1
      21: iconst_1
      22: invokespecial #13                 // Method "<init>":(Ljava/lang/String;II)V
      25: putstatic     #9                  // Field HorizontalWithVerticalVelocity:Lorg/mobicents/protocols/ss7/map/api/service/lsm/VelocityType;
      28: new           #4                  // class org/mobicents/protocols/ss7/map/api/service/lsm/VelocityType
      31: dup
      32: ldc           #15                 // String HorizontalVelocityWithUncertainty
      34: iconst_2
      35: iconst_2
      36: invokespecial #13                 // Method "<init>":(Ljava/lang/String;II)V
      39: putstatic     #10                 // Field HorizontalVelocityWithUncertainty:Lorg/mobicents/protocols/ss7/map/api/service/lsm/VelocityType;
      42: new           #4                  // class org/mobicents/protocols/ss7/map/api/service/lsm/VelocityType
      45: dup
      46: ldc           #16                 // String HorizontalWithVerticalVelocityAndUncertainty
      48: iconst_3
      49: iconst_3
      50: invokespecial #13                 // Method "<init>":(Ljava/lang/String;II)V
      53: putstatic     #11                 // Field HorizontalWithVerticalVelocityAndUncertainty:Lorg/mobicents/protocols/ss7/map/api/service/lsm/VelocityType;
      56: iconst_4
      57: anewarray     #4                  // class org/mobicents/protocols/ss7/map/api/service/lsm/VelocityType
      60: dup
      61: iconst_0
      62: getstatic     #8                  // Field HorizontalVelocity:Lorg/mobicents/protocols/ss7/map/api/service/lsm/VelocityType;
      65: aastore
      66: dup
      67: iconst_1
      68: getstatic     #9                  // Field HorizontalWithVerticalVelocity:Lorg/mobicents/protocols/ss7/map/api/service/lsm/VelocityType;
      71: aastore
      72: dup
      73: iconst_2
      74: getstatic     #10                 // Field HorizontalVelocityWithUncertainty:Lorg/mobicents/protocols/ss7/map/api/service/lsm/VelocityType;
      77: aastore
      78: dup
      79: iconst_3
      80: getstatic     #11                 // Field HorizontalWithVerticalVelocityAndUncertainty:Lorg/mobicents/protocols/ss7/map/api/service/lsm/VelocityType;
      83: aastore
      84: putstatic     #1                  // Field $VALUES:[Lorg/mobicents/protocols/ss7/map/api/service/lsm/VelocityType;
      87: return
}
