Compiled from "FileData.java"
public class org.sonar.scanner.protocol.input.FileData {
  private final java.lang.String hash;

  private final java.lang.String revision;

  public org.sonar.scanner.protocol.input.FileData(java.lang.String, java.lang.String);
    Code:
       0: aload_0
       1: invokespecial #1                  // Method java/lang/Object."<init>":()V
       4: aload_0
       5: aload_1
       6: putfield      #2                  // Field hash:Ljava/lang/String;
       9: aload_0
      10: aload_2
      11: putfield      #3                  // Field revision:Ljava/lang/String;
      14: return

  public java.lang.String hash();
    Code:
       0: aload_0
       1: getfield      #2                  // Field hash:Ljava/lang/String;
       4: areturn

  public java.lang.String revision();
    Code:
       0: aload_0
       1: getfield      #3                  // Field revision:Ljava/lang/String;
       4: areturn
}
