Compiled from "DoneableIngressRule.java"
public class io.dekorate.deps.kubernetes.api.model.extensions.DoneableIngressRule extends io.dekorate.deps.kubernetes.api.model.extensions.IngressRuleFluentImpl<io.dekorate.deps.kubernetes.api.model.extensions.DoneableIngressRule> implements io.dekorate.deps.kubernetes.api.model.Doneable<io.dekorate.deps.kubernetes.api.model.extensions.IngressRule> {
  private final io.dekorate.deps.kubernetes.api.model.extensions.IngressRuleBuilder builder;

  private final io.dekorate.deps.kubernetes.api.builder.Function<io.dekorate.deps.kubernetes.api.model.extensions.IngressRule, io.dekorate.deps.kubernetes.api.model.extensions.IngressRule> function;

  public io.dekorate.deps.kubernetes.api.model.extensions.DoneableIngressRule(io.dekorate.deps.kubernetes.api.builder.Function<io.dekorate.deps.kubernetes.api.model.extensions.IngressRule, io.dekorate.deps.kubernetes.api.model.extensions.IngressRule>);
    Code:
       0: aload_0
       1: invokespecial #21                 // Method io/dekorate/deps/kubernetes/api/model/extensions/IngressRuleFluentImpl."<init>":()V
       4: aload_0
       5: new           #23                 // class io/dekorate/deps/kubernetes/api/model/extensions/IngressRuleBuilder
       8: dup
       9: aload_0
      10: invokespecial #26                 // Method io/dekorate/deps/kubernetes/api/model/extensions/IngressRuleBuilder."<init>":(Lio/dekorate/deps/kubernetes/api/model/extensions/IngressRuleFluent;)V
      13: putfield      #28                 // Field builder:Lio/dekorate/deps/kubernetes/api/model/extensions/IngressRuleBuilder;
      16: aload_0
      17: aload_1
      18: putfield      #30                 // Field function:Lio/dekorate/deps/kubernetes/api/builder/Function;
      21: return

  public io.dekorate.deps.kubernetes.api.model.extensions.DoneableIngressRule(io.dekorate.deps.kubernetes.api.model.extensions.IngressRule, io.dekorate.deps.kubernetes.api.builder.Function<io.dekorate.deps.kubernetes.api.model.extensions.IngressRule, io.dekorate.deps.kubernetes.api.model.extensions.IngressRule>);
    Code:
       0: aload_0
       1: aload_1
       2: invokespecial #37                 // Method io/dekorate/deps/kubernetes/api/model/extensions/IngressRuleFluentImpl."<init>":(Lio/dekorate/deps/kubernetes/api/model/extensions/IngressRule;)V
       5: aload_0
       6: new           #23                 // class io/dekorate/deps/kubernetes/api/model/extensions/IngressRuleBuilder
       9: dup
      10: aload_0
      11: aload_1
      12: invokespecial #40                 // Method io/dekorate/deps/kubernetes/api/model/extensions/IngressRuleBuilder."<init>":(Lio/dekorate/deps/kubernetes/api/model/extensions/IngressRuleFluent;Lio/dekorate/deps/kubernetes/api/model/extensions/IngressRule;)V
      15: putfield      #28                 // Field builder:Lio/dekorate/deps/kubernetes/api/model/extensions/IngressRuleBuilder;
      18: aload_0
      19: aload_2
      20: putfield      #30                 // Field function:Lio/dekorate/deps/kubernetes/api/builder/Function;
      23: return

  public io.dekorate.deps.kubernetes.api.model.extensions.DoneableIngressRule(io.dekorate.deps.kubernetes.api.model.extensions.IngressRule);
    Code:
       0: aload_0
       1: aload_1
       2: invokespecial #37                 // Method io/dekorate/deps/kubernetes/api/model/extensions/IngressRuleFluentImpl."<init>":(Lio/dekorate/deps/kubernetes/api/model/extensions/IngressRule;)V
       5: aload_0
       6: new           #23                 // class io/dekorate/deps/kubernetes/api/model/extensions/IngressRuleBuilder
       9: dup
      10: aload_0
      11: aload_1
      12: invokespecial #40                 // Method io/dekorate/deps/kubernetes/api/model/extensions/IngressRuleBuilder."<init>":(Lio/dekorate/deps/kubernetes/api/model/extensions/IngressRuleFluent;Lio/dekorate/deps/kubernetes/api/model/extensions/IngressRule;)V
      15: putfield      #28                 // Field builder:Lio/dekorate/deps/kubernetes/api/model/extensions/IngressRuleBuilder;
      18: aload_0
      19: new           #10                 // class io/dekorate/deps/kubernetes/api/model/extensions/DoneableIngressRule$1
      22: dup
      23: aload_0
      24: invokespecial #45                 // Method io/dekorate/deps/kubernetes/api/model/extensions/DoneableIngressRule$1."<init>":(Lio/dekorate/deps/kubernetes/api/model/extensions/DoneableIngressRule;)V
      27: putfield      #30                 // Field function:Lio/dekorate/deps/kubernetes/api/builder/Function;
      30: return

  public io.dekorate.deps.kubernetes.api.model.extensions.IngressRule done();
    Code:
       0: aload_0
       1: getfield      #30                 // Field function:Lio/dekorate/deps/kubernetes/api/builder/Function;
       4: aload_0
       5: getfield      #28                 // Field builder:Lio/dekorate/deps/kubernetes/api/model/extensions/IngressRuleBuilder;
       8: invokevirtual #50                 // Method io/dekorate/deps/kubernetes/api/model/extensions/IngressRuleBuilder.build:()Lio/dekorate/deps/kubernetes/api/model/extensions/IngressRule;
      11: invokeinterface #56,  2           // InterfaceMethod io/dekorate/deps/kubernetes/api/builder/Function.apply:(Ljava/lang/Object;)Ljava/lang/Object;
      16: checkcast     #58                 // class io/dekorate/deps/kubernetes/api/model/extensions/IngressRule
      19: areturn

  public java.lang.Object done();
    Code:
       0: aload_0
       1: invokevirtual #61                 // Method done:()Lio/dekorate/deps/kubernetes/api/model/extensions/IngressRule;
       4: areturn
}
