Compiled from "IngressBackendFluentImpl.java"
public class io.dekorate.deps.kubernetes.api.model.extensions.IngressBackendFluentImpl$ResourceNestedImpl<N> extends io.dekorate.deps.kubernetes.api.model.TypedLocalObjectReferenceFluentImpl<io.dekorate.deps.kubernetes.api.model.extensions.IngressBackendFluent$ResourceNested<N>> implements io.dekorate.deps.kubernetes.api.model.extensions.IngressBackendFluent$ResourceNested<N>, io.dekorate.deps.kubernetes.api.builder.Nested<N> {
  private final io.dekorate.deps.kubernetes.api.model.TypedLocalObjectReferenceBuilder builder;

  final io.dekorate.deps.kubernetes.api.model.extensions.IngressBackendFluentImpl this$0;

  io.dekorate.deps.kubernetes.api.model.extensions.IngressBackendFluentImpl$ResourceNestedImpl(io.dekorate.deps.kubernetes.api.model.extensions.IngressBackendFluentImpl, io.dekorate.deps.kubernetes.api.model.TypedLocalObjectReference);
    Code:
       0: aload_0
       1: aload_1
       2: putfield      #24                 // Field this$0:Lio/dekorate/deps/kubernetes/api/model/extensions/IngressBackendFluentImpl;
       5: aload_0
       6: invokespecial #27                 // Method io/dekorate/deps/kubernetes/api/model/TypedLocalObjectReferenceFluentImpl."<init>":()V
       9: aload_0
      10: new           #29                 // class io/dekorate/deps/kubernetes/api/model/TypedLocalObjectReferenceBuilder
      13: dup
      14: aload_0
      15: aload_2
      16: invokespecial #32                 // Method io/dekorate/deps/kubernetes/api/model/TypedLocalObjectReferenceBuilder."<init>":(Lio/dekorate/deps/kubernetes/api/model/TypedLocalObjectReferenceFluent;Lio/dekorate/deps/kubernetes/api/model/TypedLocalObjectReference;)V
      19: putfield      #34                 // Field builder:Lio/dekorate/deps/kubernetes/api/model/TypedLocalObjectReferenceBuilder;
      22: return

  io.dekorate.deps.kubernetes.api.model.extensions.IngressBackendFluentImpl$ResourceNestedImpl(io.dekorate.deps.kubernetes.api.model.extensions.IngressBackendFluentImpl);
    Code:
       0: aload_0
       1: aload_1
       2: putfield      #24                 // Field this$0:Lio/dekorate/deps/kubernetes/api/model/extensions/IngressBackendFluentImpl;
       5: aload_0
       6: invokespecial #27                 // Method io/dekorate/deps/kubernetes/api/model/TypedLocalObjectReferenceFluentImpl."<init>":()V
       9: aload_0
      10: new           #29                 // class io/dekorate/deps/kubernetes/api/model/TypedLocalObjectReferenceBuilder
      13: dup
      14: aload_0
      15: invokespecial #43                 // Method io/dekorate/deps/kubernetes/api/model/TypedLocalObjectReferenceBuilder."<init>":(Lio/dekorate/deps/kubernetes/api/model/TypedLocalObjectReferenceFluent;)V
      18: putfield      #34                 // Field builder:Lio/dekorate/deps/kubernetes/api/model/TypedLocalObjectReferenceBuilder;
      21: return

  public N and();
    Code:
       0: aload_0
       1: getfield      #24                 // Field this$0:Lio/dekorate/deps/kubernetes/api/model/extensions/IngressBackendFluentImpl;
       4: aload_0
       5: getfield      #34                 // Field builder:Lio/dekorate/deps/kubernetes/api/model/TypedLocalObjectReferenceBuilder;
       8: invokevirtual #50                 // Method io/dekorate/deps/kubernetes/api/model/TypedLocalObjectReferenceBuilder.build:()Lio/dekorate/deps/kubernetes/api/model/TypedLocalObjectReference;
      11: invokevirtual #54                 // Method io/dekorate/deps/kubernetes/api/model/extensions/IngressBackendFluentImpl.withResource:(Lio/dekorate/deps/kubernetes/api/model/TypedLocalObjectReference;)Lio/dekorate/deps/kubernetes/api/model/extensions/IngressBackendFluent;
      14: areturn

  public N endResource();
    Code:
       0: aload_0
       1: invokevirtual #57                 // Method and:()Ljava/lang/Object;
       4: areturn
}
