Compiled from "OMToStaxConverter.java"
public class org.apache.neethi.builders.converters.OMToStaxConverter extends org.apache.neethi.builders.converters.AbstractOMConverter implements org.apache.neethi.builders.converters.Converter<org.apache.axiom.om.OMElement, javax.xml.stream.XMLStreamReader> {
  public org.apache.neethi.builders.converters.OMToStaxConverter();
    Code:
       0: aload_0
       1: invokespecial #1                  // Method org/apache/neethi/builders/converters/AbstractOMConverter."<init>":()V
       4: return

  public javax.xml.stream.XMLStreamReader convert(org.apache.axiom.om.OMElement);
    Code:
       0: aload_1
       1: invokeinterface #2,  1            // InterfaceMethod org/apache/axiom/om/OMElement.getXMLStreamReader:()Ljavax/xml/stream/XMLStreamReader;
       6: areturn

  public java.lang.Object convert(java.lang.Object);
    Code:
       0: aload_0
       1: aload_1
       2: checkcast     #3                  // class org/apache/axiom/om/OMElement
       5: invokevirtual #4                  // Method convert:(Lorg/apache/axiom/om/OMElement;)Ljavax/xml/stream/XMLStreamReader;
       8: areturn

  public java.util.Iterator getChildren(java.lang.Object);
    Code:
       0: aload_0
       1: aload_1
       2: checkcast     #3                  // class org/apache/axiom/om/OMElement
       5: invokespecial #5                  // Method org/apache/neethi/builders/converters/AbstractOMConverter.getChildren:(Lorg/apache/axiom/om/OMElement;)Ljava/util/Iterator;
       8: areturn

  public java.util.Map getAttributes(java.lang.Object);
    Code:
       0: aload_0
       1: aload_1
       2: checkcast     #3                  // class org/apache/axiom/om/OMElement
       5: invokespecial #6                  // Method org/apache/neethi/builders/converters/AbstractOMConverter.getAttributes:(Lorg/apache/axiom/om/OMElement;)Ljava/util/Map;
       8: areturn

  public javax.xml.namespace.QName getQName(java.lang.Object);
    Code:
       0: aload_0
       1: aload_1
       2: checkcast     #3                  // class org/apache/axiom/om/OMElement
       5: invokespecial #7                  // Method org/apache/neethi/builders/converters/AbstractOMConverter.getQName:(Lorg/apache/axiom/om/OMElement;)Ljavax/xml/namespace/QName;
       8: areturn
}
