Compiled from "JsonMapFormatVisitor.java"
public class com.fasterxml.jackson.databind.jsonFormatVisitors.JsonMapFormatVisitor$Base implements com.fasterxml.jackson.databind.jsonFormatVisitors.JsonMapFormatVisitor {
  protected com.fasterxml.jackson.databind.SerializerProvider _provider;

  public com.fasterxml.jackson.databind.jsonFormatVisitors.JsonMapFormatVisitor$Base();
    Code:
       0: aload_0
       1: invokespecial #1                  // Method java/lang/Object."<init>":()V
       4: return

  public com.fasterxml.jackson.databind.jsonFormatVisitors.JsonMapFormatVisitor$Base(com.fasterxml.jackson.databind.SerializerProvider);
    Code:
       0: aload_0
       1: invokespecial #1                  // Method java/lang/Object."<init>":()V
       4: aload_0
       5: aload_1
       6: putfield      #2                  // Field _provider:Lcom/fasterxml/jackson/databind/SerializerProvider;
       9: return

  public com.fasterxml.jackson.databind.SerializerProvider getProvider();
    Code:
       0: aload_0
       1: getfield      #2                  // Field _provider:Lcom/fasterxml/jackson/databind/SerializerProvider;
       4: areturn

  public void setProvider(com.fasterxml.jackson.databind.SerializerProvider);
    Code:
       0: aload_0
       1: aload_1
       2: putfield      #2                  // Field _provider:Lcom/fasterxml/jackson/databind/SerializerProvider;
       5: return

  public void keyFormat(com.fasterxml.jackson.databind.jsonFormatVisitors.JsonFormatVisitable, com.fasterxml.jackson.databind.JavaType) throws com.fasterxml.jackson.databind.JsonMappingException;
    Code:
       0: return

  public void valueFormat(com.fasterxml.jackson.databind.jsonFormatVisitors.JsonFormatVisitable, com.fasterxml.jackson.databind.JavaType) throws com.fasterxml.jackson.databind.JsonMappingException;
    Code:
       0: return
}
