Compiled from "TrinoThriftBigintArray.java"
public final class io.trino.plugin.thrift.api.datatypes.TrinoThriftBigintArray implements io.trino.plugin.thrift.api.datatypes.TrinoThriftColumnData {
  private final boolean[] nulls;

  private final int[] sizes;

  private final io.trino.plugin.thrift.api.datatypes.TrinoThriftBigint values;

  public io.trino.plugin.thrift.api.datatypes.TrinoThriftBigintArray(boolean[], int[], io.trino.plugin.thrift.api.datatypes.TrinoThriftBigint);
    Code:
       0: aload_0
       1: invokespecial #1                  // Method java/lang/Object."<init>":()V
       4: aload_1
       5: aload_2
       6: invokestatic  #7                  // Method io/trino/plugin/thrift/api/datatypes/TrinoThriftTypeUtils.sameSizeIfPresent:([Z[I)Z
       9: ldc           #13                 // String nulls and values must be of the same size
      11: invokestatic  #15                 // Method com/google/common/base/Preconditions.checkArgument:(ZLjava/lang/Object;)V
      14: aload_1
      15: aload_2
      16: invokestatic  #21                 // Method io/trino/plugin/thrift/api/datatypes/TrinoThriftTypeUtils.totalSize:([Z[I)I
      19: aload_3
      20: invokestatic  #25                 // Method numberOfValues:(Lio/trino/plugin/thrift/api/datatypes/TrinoThriftBigint;)I
      23: if_icmpne     30
      26: iconst_1
      27: goto          31
      30: iconst_0
      31: ldc           #31                 // String total number of values doesn\'t match expected size
      33: invokestatic  #15                 // Method com/google/common/base/Preconditions.checkArgument:(ZLjava/lang/Object;)V
      36: aload_0
      37: aload_1
      38: putfield      #33                 // Field nulls:[Z
      41: aload_0
      42: aload_2
      43: putfield      #37                 // Field sizes:[I
      46: aload_0
      47: aload_3
      48: putfield      #41                 // Field values:Lio/trino/plugin/thrift/api/datatypes/TrinoThriftBigint;
      51: return

  public boolean[] getNulls();
    Code:
       0: aload_0
       1: getfield      #33                 // Field nulls:[Z
       4: areturn

  public int[] getSizes();
    Code:
       0: aload_0
       1: getfield      #37                 // Field sizes:[I
       4: areturn

  public io.trino.plugin.thrift.api.datatypes.TrinoThriftBigint getValues();
    Code:
       0: aload_0
       1: getfield      #41                 // Field values:Lio/trino/plugin/thrift/api/datatypes/TrinoThriftBigint;
       4: areturn

  public io.trino.spi.block.Block toBlock(io.trino.spi.type.Type);
    Code:
       0: aload_1
       1: invokeinterface #45,  1           // InterfaceMethod io/trino/spi/type/Type.getTypeParameters:()Ljava/util/List;
       6: invokeinterface #51,  1           // InterfaceMethod java/util/List.size:()I
      11: iconst_1
      12: if_icmpne     40
      15: getstatic     #57                 // Field io/trino/spi/type/BigintType.BIGINT:Lio/trino/spi/type/BigintType;
      18: aload_1
      19: invokeinterface #45,  1           // InterfaceMethod io/trino/spi/type/Type.getTypeParameters:()Ljava/util/List;
      24: iconst_0
      25: invokeinterface #63,  2           // InterfaceMethod java/util/List.get:(I)Ljava/lang/Object;
      30: invokevirtual #67                 // Method io/trino/spi/type/BigintType.equals:(Ljava/lang/Object;)Z
      33: ifeq          40
      36: iconst_1
      37: goto          41
      40: iconst_0
      41: ldc           #71                 // String type doesn\'t match: %s
      43: aload_1
      44: invokestatic  #73                 // Method com/google/common/base/Preconditions.checkArgument:(ZLjava/lang/String;Ljava/lang/Object;)V
      47: aload_0
      48: invokevirtual #76                 // Method numberOfRecords:()I
      51: istore_2
      52: iload_2
      53: aload_0
      54: getfield      #33                 // Field nulls:[Z
      57: ifnonnull     66
      60: iload_2
      61: newarray       boolean
      63: goto          70
      66: aload_0
      67: getfield      #33                 // Field nulls:[Z
      70: invokestatic  #79                 // Method java/util/Optional.of:(Ljava/lang/Object;)Ljava/util/Optional;
      73: aload_0
      74: getfield      #37                 // Field sizes:[I
      77: aload_0
      78: getfield      #33                 // Field nulls:[Z
      81: iload_2
      82: invokestatic  #85                 // Method io/trino/plugin/thrift/api/datatypes/TrinoThriftTypeUtils.calculateOffsets:([I[ZI)[I
      85: aload_0
      86: getfield      #41                 // Field values:Lio/trino/plugin/thrift/api/datatypes/TrinoThriftBigint;
      89: ifnull        105
      92: aload_0
      93: getfield      #41                 // Field values:Lio/trino/plugin/thrift/api/datatypes/TrinoThriftBigint;
      96: getstatic     #57                 // Field io/trino/spi/type/BigintType.BIGINT:Lio/trino/spi/type/BigintType;
      99: invokevirtual #89                 // Method io/trino/plugin/thrift/api/datatypes/TrinoThriftBigint.toBlock:(Lio/trino/spi/type/Type;)Lio/trino/spi/block/Block;
     102: goto          119
     105: new           #95                 // class io/trino/spi/block/LongArrayBlock
     108: dup
     109: iconst_0
     110: invokestatic  #97                 // Method java/util/Optional.empty:()Ljava/util/Optional;
     113: iconst_0
     114: newarray       long
     116: invokespecial #101                // Method io/trino/spi/block/LongArrayBlock."<init>":(ILjava/util/Optional;[J)V
     119: invokestatic  #104                // Method io/trino/spi/block/ArrayBlock.fromElementBlock:(ILjava/util/Optional;[ILio/trino/spi/block/Block;)Lio/trino/spi/block/Block;
     122: areturn

  public int numberOfRecords();
    Code:
       0: aload_0
       1: getfield      #33                 // Field nulls:[Z
       4: ifnull        13
       7: aload_0
       8: getfield      #33                 // Field nulls:[Z
      11: arraylength
      12: ireturn
      13: aload_0
      14: getfield      #37                 // Field sizes:[I
      17: ifnull        26
      20: aload_0
      21: getfield      #37                 // Field sizes:[I
      24: arraylength
      25: ireturn
      26: iconst_0
      27: ireturn

  public boolean equals(java.lang.Object);
    Code:
       0: aload_0
       1: aload_1
       2: if_acmpne     7
       5: iconst_1
       6: ireturn
       7: aload_1
       8: ifnull        22
      11: aload_0
      12: invokevirtual #110                // Method java/lang/Object.getClass:()Ljava/lang/Class;
      15: aload_1
      16: invokevirtual #110                // Method java/lang/Object.getClass:()Ljava/lang/Class;
      19: if_acmpeq     24
      22: iconst_0
      23: ireturn
      24: aload_1
      25: checkcast     #26                 // class io/trino/plugin/thrift/api/datatypes/TrinoThriftBigintArray
      28: astore_2
      29: aload_0
      30: getfield      #33                 // Field nulls:[Z
      33: aload_2
      34: getfield      #33                 // Field nulls:[Z
      37: invokestatic  #114                // Method java/util/Arrays.equals:([Z[Z)Z
      40: ifeq          75
      43: aload_0
      44: getfield      #37                 // Field sizes:[I
      47: aload_2
      48: getfield      #37                 // Field sizes:[I
      51: invokestatic  #119                // Method java/util/Arrays.equals:([I[I)Z
      54: ifeq          75
      57: aload_0
      58: getfield      #41                 // Field values:Lio/trino/plugin/thrift/api/datatypes/TrinoThriftBigint;
      61: aload_2
      62: getfield      #41                 // Field values:Lio/trino/plugin/thrift/api/datatypes/TrinoThriftBigint;
      65: invokestatic  #122                // Method java/util/Objects.equals:(Ljava/lang/Object;Ljava/lang/Object;)Z
      68: ifeq          75
      71: iconst_1
      72: goto          76
      75: iconst_0
      76: ireturn

  public int hashCode();
    Code:
       0: iconst_3
       1: anewarray     #2                  // class java/lang/Object
       4: dup
       5: iconst_0
       6: aload_0
       7: getfield      #33                 // Field nulls:[Z
      10: invokestatic  #127                // Method java/util/Arrays.hashCode:([Z)I
      13: invokestatic  #131                // Method java/lang/Integer.valueOf:(I)Ljava/lang/Integer;
      16: aastore
      17: dup
      18: iconst_1
      19: aload_0
      20: getfield      #37                 // Field sizes:[I
      23: invokestatic  #137                // Method java/util/Arrays.hashCode:([I)I
      26: invokestatic  #131                // Method java/lang/Integer.valueOf:(I)Ljava/lang/Integer;
      29: aastore
      30: dup
      31: iconst_2
      32: aload_0
      33: getfield      #41                 // Field values:Lio/trino/plugin/thrift/api/datatypes/TrinoThriftBigint;
      36: aastore
      37: invokestatic  #140                // Method java/util/Objects.hash:([Ljava/lang/Object;)I
      40: ireturn

  public java.lang.String toString();
    Code:
       0: aload_0
       1: invokestatic  #144                // Method com/google/common/base/MoreObjects.toStringHelper:(Ljava/lang/Object;)Lcom/google/common/base/MoreObjects$ToStringHelper;
       4: ldc           #150                // String numberOfRecords
       6: aload_0
       7: invokevirtual #76                 // Method numberOfRecords:()I
      10: invokevirtual #151                // Method com/google/common/base/MoreObjects$ToStringHelper.add:(Ljava/lang/String;I)Lcom/google/common/base/MoreObjects$ToStringHelper;
      13: invokevirtual #157                // Method com/google/common/base/MoreObjects$ToStringHelper.toString:()Ljava/lang/String;
      16: areturn

  public static io.trino.plugin.thrift.api.TrinoThriftBlock fromBlock(io.trino.spi.block.Block);
    Code:
       0: aload_0
       1: invokeinterface #161,  1          // InterfaceMethod io/trino/spi/block/Block.getPositionCount:()I
       6: istore_1
       7: iload_1
       8: ifne          25
      11: new           #26                 // class io/trino/plugin/thrift/api/datatypes/TrinoThriftBigintArray
      14: dup
      15: aconst_null
      16: aconst_null
      17: aconst_null
      18: invokespecial #166                // Method "<init>":([Z[ILio/trino/plugin/thrift/api/datatypes/TrinoThriftBigint;)V
      21: invokestatic  #169                // Method io/trino/plugin/thrift/api/TrinoThriftBlock.bigintArrayData:(Lio/trino/plugin/thrift/api/datatypes/TrinoThriftBigintArray;)Lio/trino/plugin/thrift/api/TrinoThriftBlock;
      24: areturn
      25: aload_0
      26: instanceof    #175                // class io/trino/spi/block/RunLengthEncodedBlock
      29: ifeq          65
      32: aload_0
      33: iconst_0
      34: invokeinterface #177,  2          // InterfaceMethod io/trino/spi/block/Block.isNull:(I)Z
      39: ifeq          65
      42: iload_1
      43: newarray       boolean
      45: astore_2
      46: aload_2
      47: iconst_1
      48: invokestatic  #181                // Method java/util/Arrays.fill:([ZZ)V
      51: new           #26                 // class io/trino/plugin/thrift/api/datatypes/TrinoThriftBigintArray
      54: dup
      55: aload_2
      56: aconst_null
      57: aconst_null
      58: invokespecial #166                // Method "<init>":([Z[ILio/trino/plugin/thrift/api/datatypes/TrinoThriftBigint;)V
      61: invokestatic  #169                // Method io/trino/plugin/thrift/api/TrinoThriftBlock.bigintArrayData:(Lio/trino/plugin/thrift/api/datatypes/TrinoThriftBigintArray;)Lio/trino/plugin/thrift/api/TrinoThriftBlock;
      64: areturn
      65: aload_0
      66: instanceof    #185                // class io/trino/spi/block/AbstractArrayBlock
      69: ldc           #187                // String block is not of an array type
      71: invokestatic  #15                 // Method com/google/common/base/Preconditions.checkArgument:(ZLjava/lang/Object;)V
      74: aload_0
      75: checkcast     #185                // class io/trino/spi/block/AbstractArrayBlock
      78: astore_2
      79: aconst_null
      80: astore_3
      81: aconst_null
      82: astore        4
      84: iconst_0
      85: istore        5
      87: iload         5
      89: iload_1
      90: if_icmpge     156
      93: aload_2
      94: iload         5
      96: invokevirtual #189                // Method io/trino/spi/block/AbstractArrayBlock.isNull:(I)Z
      99: ifeq          118
     102: aload_3
     103: ifnonnull     110
     106: iload_1
     107: newarray       boolean
     109: astore_3
     110: aload_3
     111: iload         5
     113: iconst_1
     114: bastore
     115: goto          150
     118: aload         4
     120: ifnonnull     128
     123: iload_1
     124: newarray       int
     126: astore        4
     128: aload         4
     130: iload         5
     132: aload_2
     133: invokedynamic #190,  0            // InvokeDynamic #0:apply:()Lio/trino/spi/block/AbstractArrayBlock$ArrayBlockFunction;
     138: iload         5
     140: invokevirtual #194                // Method io/trino/spi/block/AbstractArrayBlock.apply:(Lio/trino/spi/block/AbstractArrayBlock$ArrayBlockFunction;I)Ljava/lang/Object;
     143: checkcast     #132                // class java/lang/Integer
     146: invokevirtual #197                // Method java/lang/Integer.intValue:()I
     149: iastore
     150: iinc          5, 1
     153: goto          87
     156: aload_2
     157: invokedynamic #200,  0            // InvokeDynamic #1:apply:()Lio/trino/spi/block/AbstractArrayBlock$ArrayBlockFunction;
     162: iconst_0
     163: invokevirtual #194                // Method io/trino/spi/block/AbstractArrayBlock.apply:(Lio/trino/spi/block/AbstractArrayBlock$ArrayBlockFunction;I)Ljava/lang/Object;
     166: checkcast     #170                // class io/trino/plugin/thrift/api/TrinoThriftBlock
     169: invokevirtual #201                // Method io/trino/plugin/thrift/api/TrinoThriftBlock.getBigintData:()Lio/trino/plugin/thrift/api/datatypes/TrinoThriftBigint;
     172: astore        5
     174: aload         5
     176: ifnull        183
     179: iconst_1
     180: goto          184
     183: iconst_0
     184: ldc           #205                // String values must be present
     186: invokestatic  #207                // Method com/google/common/base/Preconditions.checkState:(ZLjava/lang/Object;)V
     189: aload_3
     190: aload         4
     192: invokestatic  #21                 // Method io/trino/plugin/thrift/api/datatypes/TrinoThriftTypeUtils.totalSize:([Z[I)I
     195: aload         5
     197: invokevirtual #210                // Method io/trino/plugin/thrift/api/datatypes/TrinoThriftBigint.numberOfRecords:()I
     200: if_icmpne     207
     203: iconst_1
     204: goto          208
     207: iconst_0
     208: ldc           #211                // String unexpected number of values
     210: invokestatic  #207                // Method com/google/common/base/Preconditions.checkState:(ZLjava/lang/Object;)V
     213: new           #26                 // class io/trino/plugin/thrift/api/datatypes/TrinoThriftBigintArray
     216: dup
     217: aload_3
     218: aload         4
     220: aload         5
     222: invokespecial #166                // Method "<init>":([Z[ILio/trino/plugin/thrift/api/datatypes/TrinoThriftBigint;)V
     225: invokestatic  #169                // Method io/trino/plugin/thrift/api/TrinoThriftBlock.bigintArrayData:(Lio/trino/plugin/thrift/api/datatypes/TrinoThriftBigintArray;)Lio/trino/plugin/thrift/api/TrinoThriftBlock;
     228: areturn

  private static int numberOfValues(io.trino.plugin.thrift.api.datatypes.TrinoThriftBigint);
    Code:
       0: aload_0
       1: ifnull        11
       4: aload_0
       5: invokevirtual #210                // Method io/trino/plugin/thrift/api/datatypes/TrinoThriftBigint.numberOfRecords:()I
       8: goto          12
      11: iconst_0
      12: ireturn

  private static io.trino.plugin.thrift.api.TrinoThriftBlock lambda$fromBlock$1(io.trino.spi.block.Block, int, int);
    Code:
       0: aload_0
       1: invokestatic  #213                // Method io/trino/plugin/thrift/api/datatypes/TrinoThriftBigint.fromBlock:(Lio/trino/spi/block/Block;)Lio/trino/plugin/thrift/api/TrinoThriftBlock;
       4: areturn

  private static java.lang.Integer lambda$fromBlock$0(io.trino.spi.block.Block, int, int);
    Code:
       0: iload_2
       1: invokestatic  #131                // Method java/lang/Integer.valueOf:(I)Ljava/lang/Integer;
       4: areturn
}
