Compiled from "GeographicalInformationImpl.java"
final class org.mobicents.protocols.ss7.map.service.mobility.subscriberInformation.GeographicalInformationImpl$1 extends javolution.xml.XMLFormat<org.mobicents.protocols.ss7.map.service.mobility.subscriberInformation.GeographicalInformationImpl> {
  org.mobicents.protocols.ss7.map.service.mobility.subscriberInformation.GeographicalInformationImpl$1(java.lang.Class);
    Code:
       0: aload_0
       1: aload_1
       2: invokespecial #1                  // Method javolution/xml/XMLFormat."<init>":(Ljava/lang/Class;)V
       5: return

  public void read(javolution.xml.XMLFormat$InputElement, org.mobicents.protocols.ss7.map.service.mobility.subscriberInformation.GeographicalInformationImpl) throws javolution.xml.stream.XMLStreamException;
    Code:
       0: aload_1
       1: ldc           #2                  // String typeOfShape
       3: invokestatic  #3                  // Method org/mobicents/protocols/ss7/map/service/mobility/subscriberInformation/GeographicalInformationImpl.access$000:()Ljava/lang/String;
       6: invokevirtual #4                  // Method javolution/xml/XMLFormat$InputElement.getAttribute:(Ljava/lang/String;Ljava/lang/String;)Ljava/lang/String;
       9: astore_3
      10: aconst_null
      11: astore        4
      13: aload_3
      14: ifnull        29
      17: ldc_w         #5                  // class org/mobicents/protocols/ss7/map/api/service/mobility/subscriberInformation/TypeOfShape
      20: aload_3
      21: invokestatic  #6                  // Method java/lang/Enum.valueOf:(Ljava/lang/Class;Ljava/lang/String;)Ljava/lang/Enum;
      24: checkcast     #5                  // class org/mobicents/protocols/ss7/map/api/service/mobility/subscriberInformation/TypeOfShape
      27: astore        4
      29: aload_1
      30: ldc           #7                  // String latitude
      32: dconst_0
      33: invokevirtual #8                  // Method javolution/xml/XMLFormat$InputElement.getAttribute:(Ljava/lang/String;D)D
      36: dstore        5
      38: aload_1
      39: ldc           #9                  // String longitude
      41: dconst_0
      42: invokevirtual #8                  // Method javolution/xml/XMLFormat$InputElement.getAttribute:(Ljava/lang/String;D)D
      45: dstore        7
      47: aload_1
      48: ldc           #10                 // String uncertainty
      50: dconst_0
      51: invokevirtual #8                  // Method javolution/xml/XMLFormat$InputElement.getAttribute:(Ljava/lang/String;D)D
      54: dstore        9
      56: aload_2
      57: aload         4
      59: dload         5
      61: dload         7
      63: dload         9
      65: invokevirtual #11                 // Method org/mobicents/protocols/ss7/map/service/mobility/subscriberInformation/GeographicalInformationImpl.setData:(Lorg/mobicents/protocols/ss7/map/api/service/mobility/subscriberInformation/TypeOfShape;DDD)V
      68: goto          85
      71: astore        11
      73: new           #13                 // class javolution/xml/stream/XMLStreamException
      76: dup
      77: ldc           #14                 // String MAPException when deserializing GeographicalInformation
      79: aload         11
      81: invokespecial #15                 // Method javolution/xml/stream/XMLStreamException."<init>":(Ljava/lang/String;Ljava/lang/Throwable;)V
      84: athrow
      85: return
    Exception table:
       from    to  target type
          56    68    71   Class org/mobicents/protocols/ss7/map/api/MAPException

  public void write(org.mobicents.protocols.ss7.map.service.mobility.subscriberInformation.GeographicalInformationImpl, javolution.xml.XMLFormat$OutputElement) throws javolution.xml.stream.XMLStreamException;
    Code:
       0: aload_1
       1: invokevirtual #16                 // Method org/mobicents/protocols/ss7/map/service/mobility/subscriberInformation/GeographicalInformationImpl.getTypeOfShape:()Lorg/mobicents/protocols/ss7/map/api/service/mobility/subscriberInformation/TypeOfShape;
       4: ifnull        20
       7: aload_2
       8: ldc           #2                  // String typeOfShape
      10: aload_1
      11: invokevirtual #16                 // Method org/mobicents/protocols/ss7/map/service/mobility/subscriberInformation/GeographicalInformationImpl.getTypeOfShape:()Lorg/mobicents/protocols/ss7/map/api/service/mobility/subscriberInformation/TypeOfShape;
      14: invokevirtual #17                 // Method org/mobicents/protocols/ss7/map/api/service/mobility/subscriberInformation/TypeOfShape.toString:()Ljava/lang/String;
      17: invokevirtual #18                 // Method javolution/xml/XMLFormat$OutputElement.setAttribute:(Ljava/lang/String;Ljava/lang/String;)V
      20: aload_2
      21: ldc           #7                  // String latitude
      23: aload_1
      24: invokevirtual #19                 // Method org/mobicents/protocols/ss7/map/service/mobility/subscriberInformation/GeographicalInformationImpl.getLatitude:()D
      27: invokevirtual #20                 // Method javolution/xml/XMLFormat$OutputElement.setAttribute:(Ljava/lang/String;D)V
      30: aload_2
      31: ldc           #9                  // String longitude
      33: aload_1
      34: invokevirtual #21                 // Method org/mobicents/protocols/ss7/map/service/mobility/subscriberInformation/GeographicalInformationImpl.getLongitude:()D
      37: invokevirtual #20                 // Method javolution/xml/XMLFormat$OutputElement.setAttribute:(Ljava/lang/String;D)V
      40: aload_2
      41: ldc           #10                 // String uncertainty
      43: aload_1
      44: invokevirtual #22                 // Method org/mobicents/protocols/ss7/map/service/mobility/subscriberInformation/GeographicalInformationImpl.getUncertainty:()D
      47: invokevirtual #20                 // Method javolution/xml/XMLFormat$OutputElement.setAttribute:(Ljava/lang/String;D)V
      50: return

  public void read(javolution.xml.XMLFormat$InputElement, java.lang.Object) throws javolution.xml.stream.XMLStreamException;
    Code:
       0: aload_0
       1: aload_1
       2: aload_2
       3: checkcast     #23                 // class org/mobicents/protocols/ss7/map/service/mobility/subscriberInformation/GeographicalInformationImpl
       6: invokevirtual #24                 // Method read:(Ljavolution/xml/XMLFormat$InputElement;Lorg/mobicents/protocols/ss7/map/service/mobility/subscriberInformation/GeographicalInformationImpl;)V
       9: return

  public void write(java.lang.Object, javolution.xml.XMLFormat$OutputElement) throws javolution.xml.stream.XMLStreamException;
    Code:
       0: aload_0
       1: aload_1
       2: checkcast     #23                 // class org/mobicents/protocols/ss7/map/service/mobility/subscriberInformation/GeographicalInformationImpl
       5: aload_2
       6: invokevirtual #25                 // Method write:(Lorg/mobicents/protocols/ss7/map/service/mobility/subscriberInformation/GeographicalInformationImpl;Ljavolution/xml/XMLFormat$OutputElement;)V
       9: return
}
