Compiled from "SubscriberStateImpl.java"
final class org.mobicents.protocols.ss7.map.service.mobility.subscriberInformation.SubscriberStateImpl$1 extends javolution.xml.XMLFormat<org.mobicents.protocols.ss7.map.service.mobility.subscriberInformation.SubscriberStateImpl> {
  org.mobicents.protocols.ss7.map.service.mobility.subscriberInformation.SubscriberStateImpl$1(java.lang.Class);
    Code:
       0: aload_0
       1: aload_1
       2: invokespecial #1                  // Method javolution/xml/XMLFormat."<init>":(Ljava/lang/Class;)V
       5: return

  public void read(javolution.xml.XMLFormat$InputElement, org.mobicents.protocols.ss7.map.service.mobility.subscriberInformation.SubscriberStateImpl) throws javolution.xml.stream.XMLStreamException;
    Code:
       0: aload_1
       1: ldc           #2                  // String subscriberStateChoice
       3: invokestatic  #3                  // Method org/mobicents/protocols/ss7/map/service/mobility/subscriberInformation/SubscriberStateImpl.access$000:()Ljava/lang/String;
       6: invokevirtual #4                  // Method javolution/xml/XMLFormat$InputElement.getAttribute:(Ljava/lang/String;Ljava/lang/String;)Ljava/lang/String;
       9: astore_3
      10: aconst_null
      11: astore        4
      13: aload_3
      14: ifnull        29
      17: ldc_w         #5                  // class org/mobicents/protocols/ss7/map/api/service/mobility/subscriberInformation/SubscriberStateChoice
      20: aload_3
      21: invokestatic  #6                  // Method java/lang/Enum.valueOf:(Ljava/lang/Class;Ljava/lang/String;)Ljava/lang/Enum;
      24: checkcast     #5                  // class org/mobicents/protocols/ss7/map/api/service/mobility/subscriberInformation/SubscriberStateChoice
      27: astore        4
      29: aload_1
      30: ldc           #7                  // String notReachableReason
      32: ldc_w         #8                  // class java/lang/String
      35: invokevirtual #9                  // Method javolution/xml/XMLFormat$InputElement.get:(Ljava/lang/String;Ljava/lang/Class;)Ljava/lang/Object;
      38: checkcast     #8                  // class java/lang/String
      41: astore        5
      43: aconst_null
      44: astore        6
      46: aload         5
      48: ifnull        64
      51: ldc_w         #10                 // class org/mobicents/protocols/ss7/map/api/service/mobility/subscriberInformation/NotReachableReason
      54: aload         5
      56: invokestatic  #6                  // Method java/lang/Enum.valueOf:(Ljava/lang/Class;Ljava/lang/String;)Ljava/lang/Enum;
      59: checkcast     #10                 // class org/mobicents/protocols/ss7/map/api/service/mobility/subscriberInformation/NotReachableReason
      62: astore        6
      64: aload_2
      65: aload         4
      67: aload         6
      69: invokevirtual #11                 // Method org/mobicents/protocols/ss7/map/service/mobility/subscriberInformation/SubscriberStateImpl.setData:(Lorg/mobicents/protocols/ss7/map/api/service/mobility/subscriberInformation/SubscriberStateChoice;Lorg/mobicents/protocols/ss7/map/api/service/mobility/subscriberInformation/NotReachableReason;)V
      72: return

  public void write(org.mobicents.protocols.ss7.map.service.mobility.subscriberInformation.SubscriberStateImpl, javolution.xml.XMLFormat$OutputElement) throws javolution.xml.stream.XMLStreamException;
    Code:
       0: aload_1
       1: invokestatic  #12                 // Method org/mobicents/protocols/ss7/map/service/mobility/subscriberInformation/SubscriberStateImpl.access$100:(Lorg/mobicents/protocols/ss7/map/service/mobility/subscriberInformation/SubscriberStateImpl;)Lorg/mobicents/protocols/ss7/map/api/service/mobility/subscriberInformation/SubscriberStateChoice;
       4: ifnull        20
       7: aload_2
       8: ldc           #2                  // String subscriberStateChoice
      10: aload_1
      11: invokestatic  #12                 // Method org/mobicents/protocols/ss7/map/service/mobility/subscriberInformation/SubscriberStateImpl.access$100:(Lorg/mobicents/protocols/ss7/map/service/mobility/subscriberInformation/SubscriberStateImpl;)Lorg/mobicents/protocols/ss7/map/api/service/mobility/subscriberInformation/SubscriberStateChoice;
      14: invokevirtual #13                 // Method org/mobicents/protocols/ss7/map/api/service/mobility/subscriberInformation/SubscriberStateChoice.toString:()Ljava/lang/String;
      17: invokevirtual #14                 // Method javolution/xml/XMLFormat$OutputElement.setAttribute:(Ljava/lang/String;Ljava/lang/String;)V
      20: aload_1
      21: invokestatic  #15                 // Method org/mobicents/protocols/ss7/map/service/mobility/subscriberInformation/SubscriberStateImpl.access$200:(Lorg/mobicents/protocols/ss7/map/service/mobility/subscriberInformation/SubscriberStateImpl;)Lorg/mobicents/protocols/ss7/map/api/service/mobility/subscriberInformation/NotReachableReason;
      24: ifnull        43
      27: aload_2
      28: aload_1
      29: invokestatic  #15                 // Method org/mobicents/protocols/ss7/map/service/mobility/subscriberInformation/SubscriberStateImpl.access$200:(Lorg/mobicents/protocols/ss7/map/service/mobility/subscriberInformation/SubscriberStateImpl;)Lorg/mobicents/protocols/ss7/map/api/service/mobility/subscriberInformation/NotReachableReason;
      32: invokevirtual #16                 // Method org/mobicents/protocols/ss7/map/api/service/mobility/subscriberInformation/NotReachableReason.toString:()Ljava/lang/String;
      35: ldc           #7                  // String notReachableReason
      37: ldc_w         #8                  // class java/lang/String
      40: invokevirtual #17                 // Method javolution/xml/XMLFormat$OutputElement.add:(Ljava/lang/Object;Ljava/lang/String;Ljava/lang/Class;)V
      43: return

  public void read(javolution.xml.XMLFormat$InputElement, java.lang.Object) throws javolution.xml.stream.XMLStreamException;
    Code:
       0: aload_0
       1: aload_1
       2: aload_2
       3: checkcast     #18                 // class org/mobicents/protocols/ss7/map/service/mobility/subscriberInformation/SubscriberStateImpl
       6: invokevirtual #19                 // Method read:(Ljavolution/xml/XMLFormat$InputElement;Lorg/mobicents/protocols/ss7/map/service/mobility/subscriberInformation/SubscriberStateImpl;)V
       9: return

  public void write(java.lang.Object, javolution.xml.XMLFormat$OutputElement) throws javolution.xml.stream.XMLStreamException;
    Code:
       0: aload_0
       1: aload_1
       2: checkcast     #18                 // class org/mobicents/protocols/ss7/map/service/mobility/subscriberInformation/SubscriberStateImpl
       5: aload_2
       6: invokevirtual #20                 // Method write:(Lorg/mobicents/protocols/ss7/map/service/mobility/subscriberInformation/SubscriberStateImpl;Ljavolution/xml/XMLFormat$OutputElement;)V
       9: return
}
