Compiled from "DailyRollingFileAppender.java"
public class org.apache.log4j.DailyRollingFileAppender extends org.apache.log4j.FileAppender {
  static final int TOP_OF_TROUBLE;

  static final int TOP_OF_MINUTE;

  static final int TOP_OF_HOUR;

  static final int HALF_DAY;

  static final int TOP_OF_DAY;

  static final int TOP_OF_WEEK;

  static final int TOP_OF_MONTH;

  private java.lang.String datePattern;

  private java.lang.String scheduledFilename;

  private long nextCheck;

  java.util.Date now;

  java.text.SimpleDateFormat sdf;

  org.apache.log4j.RollingCalendar rc;

  int checkPeriod;

  static final java.util.TimeZone gmtTimeZone;

  public org.apache.log4j.DailyRollingFileAppender();
    Code:
       0: aload_0
       1: invokespecial #1                  // Method org/apache/log4j/FileAppender."<init>":()V
       4: aload_0
       5: ldc           #2                  // String \'.\'yyyy-MM-dd
       7: putfield      #3                  // Field datePattern:Ljava/lang/String;
      10: aload_0
      11: invokestatic  #4                  // Method java/lang/System.currentTimeMillis:()J
      14: lconst_1
      15: lsub
      16: putfield      #5                  // Field nextCheck:J
      19: aload_0
      20: new           #6                  // class java/util/Date
      23: dup
      24: invokespecial #7                  // Method java/util/Date."<init>":()V
      27: putfield      #8                  // Field now:Ljava/util/Date;
      30: aload_0
      31: new           #9                  // class org/apache/log4j/RollingCalendar
      34: dup
      35: invokespecial #10                 // Method org/apache/log4j/RollingCalendar."<init>":()V
      38: putfield      #11                 // Field rc:Lorg/apache/log4j/RollingCalendar;
      41: aload_0
      42: iconst_m1
      43: putfield      #12                 // Field checkPeriod:I
      46: return

  public org.apache.log4j.DailyRollingFileAppender(org.apache.log4j.Layout, java.lang.String, java.lang.String) throws java.io.IOException;
    Code:
       0: aload_0
       1: aload_1
       2: aload_2
       3: iconst_1
       4: invokespecial #13                 // Method org/apache/log4j/FileAppender."<init>":(Lorg/apache/log4j/Layout;Ljava/lang/String;Z)V
       7: aload_0
       8: ldc           #2                  // String \'.\'yyyy-MM-dd
      10: putfield      #3                  // Field datePattern:Ljava/lang/String;
      13: aload_0
      14: invokestatic  #4                  // Method java/lang/System.currentTimeMillis:()J
      17: lconst_1
      18: lsub
      19: putfield      #5                  // Field nextCheck:J
      22: aload_0
      23: new           #6                  // class java/util/Date
      26: dup
      27: invokespecial #7                  // Method java/util/Date."<init>":()V
      30: putfield      #8                  // Field now:Ljava/util/Date;
      33: aload_0
      34: new           #9                  // class org/apache/log4j/RollingCalendar
      37: dup
      38: invokespecial #10                 // Method org/apache/log4j/RollingCalendar."<init>":()V
      41: putfield      #11                 // Field rc:Lorg/apache/log4j/RollingCalendar;
      44: aload_0
      45: iconst_m1
      46: putfield      #12                 // Field checkPeriod:I
      49: aload_0
      50: aload_3
      51: putfield      #3                  // Field datePattern:Ljava/lang/String;
      54: aload_0
      55: invokevirtual #14                 // Method activateOptions:()V
      58: return

  public void setDatePattern(java.lang.String);
    Code:
       0: aload_0
       1: aload_1
       2: putfield      #3                  // Field datePattern:Ljava/lang/String;
       5: return

  public java.lang.String getDatePattern();
    Code:
       0: aload_0
       1: getfield      #3                  // Field datePattern:Ljava/lang/String;
       4: areturn

  public void activateOptions();
    Code:
       0: aload_0
       1: invokespecial #15                 // Method org/apache/log4j/FileAppender.activateOptions:()V
       4: aload_0
       5: getfield      #3                  // Field datePattern:Ljava/lang/String;
       8: ifnull        118
      11: aload_0
      12: getfield      #16                 // Field org/apache/log4j/FileAppender.fileName:Ljava/lang/String;
      15: ifnull        118
      18: aload_0
      19: getfield      #8                  // Field now:Ljava/util/Date;
      22: invokestatic  #4                  // Method java/lang/System.currentTimeMillis:()J
      25: invokevirtual #17                 // Method java/util/Date.setTime:(J)V
      28: aload_0
      29: new           #18                 // class java/text/SimpleDateFormat
      32: dup
      33: aload_0
      34: getfield      #3                  // Field datePattern:Ljava/lang/String;
      37: invokespecial #19                 // Method java/text/SimpleDateFormat."<init>":(Ljava/lang/String;)V
      40: putfield      #20                 // Field sdf:Ljava/text/SimpleDateFormat;
      43: aload_0
      44: invokevirtual #21                 // Method computeCheckPeriod:()I
      47: istore_1
      48: aload_0
      49: iload_1
      50: invokevirtual #22                 // Method printPeriodicity:(I)V
      53: aload_0
      54: getfield      #11                 // Field rc:Lorg/apache/log4j/RollingCalendar;
      57: iload_1
      58: invokevirtual #23                 // Method org/apache/log4j/RollingCalendar.setType:(I)V
      61: new           #24                 // class java/io/File
      64: dup
      65: aload_0
      66: getfield      #16                 // Field org/apache/log4j/FileAppender.fileName:Ljava/lang/String;
      69: invokespecial #25                 // Method java/io/File."<init>":(Ljava/lang/String;)V
      72: astore_2
      73: aload_0
      74: new           #26                 // class java/lang/StringBuffer
      77: dup
      78: invokespecial #27                 // Method java/lang/StringBuffer."<init>":()V
      81: aload_0
      82: getfield      #16                 // Field org/apache/log4j/FileAppender.fileName:Ljava/lang/String;
      85: invokevirtual #28                 // Method java/lang/StringBuffer.append:(Ljava/lang/String;)Ljava/lang/StringBuffer;
      88: aload_0
      89: getfield      #20                 // Field sdf:Ljava/text/SimpleDateFormat;
      92: new           #6                  // class java/util/Date
      95: dup
      96: aload_2
      97: invokevirtual #29                 // Method java/io/File.lastModified:()J
     100: invokespecial #30                 // Method java/util/Date."<init>":(J)V
     103: invokevirtual #31                 // Method java/text/DateFormat.format:(Ljava/util/Date;)Ljava/lang/String;
     106: invokevirtual #28                 // Method java/lang/StringBuffer.append:(Ljava/lang/String;)Ljava/lang/StringBuffer;
     109: invokevirtual #32                 // Method java/lang/StringBuffer.toString:()Ljava/lang/String;
     112: putfield      #33                 // Field scheduledFilename:Ljava/lang/String;
     115: goto          148
     118: new           #26                 // class java/lang/StringBuffer
     121: dup
     122: invokespecial #27                 // Method java/lang/StringBuffer."<init>":()V
     125: ldc           #34                 // String Either File or DatePattern options are not set for appender [
     127: invokevirtual #28                 // Method java/lang/StringBuffer.append:(Ljava/lang/String;)Ljava/lang/StringBuffer;
     130: aload_0
     131: getfield      #35                 // Field org/apache/log4j/AppenderSkeleton.name:Ljava/lang/String;
     134: invokevirtual #28                 // Method java/lang/StringBuffer.append:(Ljava/lang/String;)Ljava/lang/StringBuffer;
     137: ldc           #36                 // String ].
     139: invokevirtual #28                 // Method java/lang/StringBuffer.append:(Ljava/lang/String;)Ljava/lang/StringBuffer;
     142: invokevirtual #32                 // Method java/lang/StringBuffer.toString:()Ljava/lang/String;
     145: invokestatic  #37                 // Method org/apache/log4j/helpers/LogLog.error:(Ljava/lang/String;)V
     148: return

  void printPeriodicity(int);
    Code:
       0: iload_1
       1: tableswitch   { // 0 to 5
                     0: 40
                     1: 73
                     2: 106
                     3: 139
                     4: 172
                     5: 205
               default: 238
          }
      40: new           #26                 // class java/lang/StringBuffer
      43: dup
      44: invokespecial #27                 // Method java/lang/StringBuffer."<init>":()V
      47: ldc           #38                 // String Appender [
      49: invokevirtual #28                 // Method java/lang/StringBuffer.append:(Ljava/lang/String;)Ljava/lang/StringBuffer;
      52: aload_0
      53: getfield      #35                 // Field org/apache/log4j/AppenderSkeleton.name:Ljava/lang/String;
      56: invokevirtual #28                 // Method java/lang/StringBuffer.append:(Ljava/lang/String;)Ljava/lang/StringBuffer;
      59: ldc           #39                 // String ] to be rolled every minute.
      61: invokevirtual #28                 // Method java/lang/StringBuffer.append:(Ljava/lang/String;)Ljava/lang/StringBuffer;
      64: invokevirtual #32                 // Method java/lang/StringBuffer.toString:()Ljava/lang/String;
      67: invokestatic  #40                 // Method org/apache/log4j/helpers/LogLog.debug:(Ljava/lang/String;)V
      70: goto          268
      73: new           #26                 // class java/lang/StringBuffer
      76: dup
      77: invokespecial #27                 // Method java/lang/StringBuffer."<init>":()V
      80: ldc           #38                 // String Appender [
      82: invokevirtual #28                 // Method java/lang/StringBuffer.append:(Ljava/lang/String;)Ljava/lang/StringBuffer;
      85: aload_0
      86: getfield      #35                 // Field org/apache/log4j/AppenderSkeleton.name:Ljava/lang/String;
      89: invokevirtual #28                 // Method java/lang/StringBuffer.append:(Ljava/lang/String;)Ljava/lang/StringBuffer;
      92: ldc           #41                 // String ] to be rolled on top of every hour.
      94: invokevirtual #28                 // Method java/lang/StringBuffer.append:(Ljava/lang/String;)Ljava/lang/StringBuffer;
      97: invokevirtual #32                 // Method java/lang/StringBuffer.toString:()Ljava/lang/String;
     100: invokestatic  #40                 // Method org/apache/log4j/helpers/LogLog.debug:(Ljava/lang/String;)V
     103: goto          268
     106: new           #26                 // class java/lang/StringBuffer
     109: dup
     110: invokespecial #27                 // Method java/lang/StringBuffer."<init>":()V
     113: ldc           #38                 // String Appender [
     115: invokevirtual #28                 // Method java/lang/StringBuffer.append:(Ljava/lang/String;)Ljava/lang/StringBuffer;
     118: aload_0
     119: getfield      #35                 // Field org/apache/log4j/AppenderSkeleton.name:Ljava/lang/String;
     122: invokevirtual #28                 // Method java/lang/StringBuffer.append:(Ljava/lang/String;)Ljava/lang/StringBuffer;
     125: ldc           #42                 // String ] to be rolled at midday and midnight.
     127: invokevirtual #28                 // Method java/lang/StringBuffer.append:(Ljava/lang/String;)Ljava/lang/StringBuffer;
     130: invokevirtual #32                 // Method java/lang/StringBuffer.toString:()Ljava/lang/String;
     133: invokestatic  #40                 // Method org/apache/log4j/helpers/LogLog.debug:(Ljava/lang/String;)V
     136: goto          268
     139: new           #26                 // class java/lang/StringBuffer
     142: dup
     143: invokespecial #27                 // Method java/lang/StringBuffer."<init>":()V
     146: ldc           #38                 // String Appender [
     148: invokevirtual #28                 // Method java/lang/StringBuffer.append:(Ljava/lang/String;)Ljava/lang/StringBuffer;
     151: aload_0
     152: getfield      #35                 // Field org/apache/log4j/AppenderSkeleton.name:Ljava/lang/String;
     155: invokevirtual #28                 // Method java/lang/StringBuffer.append:(Ljava/lang/String;)Ljava/lang/StringBuffer;
     158: ldc           #43                 // String ] to be rolled at midnight.
     160: invokevirtual #28                 // Method java/lang/StringBuffer.append:(Ljava/lang/String;)Ljava/lang/StringBuffer;
     163: invokevirtual #32                 // Method java/lang/StringBuffer.toString:()Ljava/lang/String;
     166: invokestatic  #40                 // Method org/apache/log4j/helpers/LogLog.debug:(Ljava/lang/String;)V
     169: goto          268
     172: new           #26                 // class java/lang/StringBuffer
     175: dup
     176: invokespecial #27                 // Method java/lang/StringBuffer."<init>":()V
     179: ldc           #38                 // String Appender [
     181: invokevirtual #28                 // Method java/lang/StringBuffer.append:(Ljava/lang/String;)Ljava/lang/StringBuffer;
     184: aload_0
     185: getfield      #35                 // Field org/apache/log4j/AppenderSkeleton.name:Ljava/lang/String;
     188: invokevirtual #28                 // Method java/lang/StringBuffer.append:(Ljava/lang/String;)Ljava/lang/StringBuffer;
     191: ldc           #44                 // String ] to be rolled at start of week.
     193: invokevirtual #28                 // Method java/lang/StringBuffer.append:(Ljava/lang/String;)Ljava/lang/StringBuffer;
     196: invokevirtual #32                 // Method java/lang/StringBuffer.toString:()Ljava/lang/String;
     199: invokestatic  #40                 // Method org/apache/log4j/helpers/LogLog.debug:(Ljava/lang/String;)V
     202: goto          268
     205: new           #26                 // class java/lang/StringBuffer
     208: dup
     209: invokespecial #27                 // Method java/lang/StringBuffer."<init>":()V
     212: ldc           #38                 // String Appender [
     214: invokevirtual #28                 // Method java/lang/StringBuffer.append:(Ljava/lang/String;)Ljava/lang/StringBuffer;
     217: aload_0
     218: getfield      #35                 // Field org/apache/log4j/AppenderSkeleton.name:Ljava/lang/String;
     221: invokevirtual #28                 // Method java/lang/StringBuffer.append:(Ljava/lang/String;)Ljava/lang/StringBuffer;
     224: ldc           #45                 // String ] to be rolled at start of every month.
     226: invokevirtual #28                 // Method java/lang/StringBuffer.append:(Ljava/lang/String;)Ljava/lang/StringBuffer;
     229: invokevirtual #32                 // Method java/lang/StringBuffer.toString:()Ljava/lang/String;
     232: invokestatic  #40                 // Method org/apache/log4j/helpers/LogLog.debug:(Ljava/lang/String;)V
     235: goto          268
     238: new           #26                 // class java/lang/StringBuffer
     241: dup
     242: invokespecial #27                 // Method java/lang/StringBuffer."<init>":()V
     245: ldc           #46                 // String Unknown periodicity for appender [
     247: invokevirtual #28                 // Method java/lang/StringBuffer.append:(Ljava/lang/String;)Ljava/lang/StringBuffer;
     250: aload_0
     251: getfield      #35                 // Field org/apache/log4j/AppenderSkeleton.name:Ljava/lang/String;
     254: invokevirtual #28                 // Method java/lang/StringBuffer.append:(Ljava/lang/String;)Ljava/lang/StringBuffer;
     257: ldc           #36                 // String ].
     259: invokevirtual #28                 // Method java/lang/StringBuffer.append:(Ljava/lang/String;)Ljava/lang/StringBuffer;
     262: invokevirtual #32                 // Method java/lang/StringBuffer.toString:()Ljava/lang/String;
     265: invokestatic  #47                 // Method org/apache/log4j/helpers/LogLog.warn:(Ljava/lang/String;)V
     268: return

  int computeCheckPeriod();
    Code:
       0: new           #9                  // class org/apache/log4j/RollingCalendar
       3: dup
       4: getstatic     #48                 // Field gmtTimeZone:Ljava/util/TimeZone;
       7: invokestatic  #49                 // Method java/util/Locale.getDefault:()Ljava/util/Locale;
      10: invokespecial #50                 // Method org/apache/log4j/RollingCalendar."<init>":(Ljava/util/TimeZone;Ljava/util/Locale;)V
      13: astore_1
      14: new           #6                  // class java/util/Date
      17: dup
      18: lconst_0
      19: invokespecial #30                 // Method java/util/Date."<init>":(J)V
      22: astore_2
      23: aload_0
      24: getfield      #3                  // Field datePattern:Ljava/lang/String;
      27: ifnull        122
      30: iconst_0
      31: istore_3
      32: iload_3
      33: iconst_5
      34: if_icmpgt     122
      37: new           #18                 // class java/text/SimpleDateFormat
      40: dup
      41: aload_0
      42: getfield      #3                  // Field datePattern:Ljava/lang/String;
      45: invokespecial #19                 // Method java/text/SimpleDateFormat."<init>":(Ljava/lang/String;)V
      48: astore        4
      50: aload         4
      52: getstatic     #48                 // Field gmtTimeZone:Ljava/util/TimeZone;
      55: invokevirtual #51                 // Method java/text/DateFormat.setTimeZone:(Ljava/util/TimeZone;)V
      58: aload         4
      60: aload_2
      61: invokevirtual #31                 // Method java/text/DateFormat.format:(Ljava/util/Date;)Ljava/lang/String;
      64: astore        5
      66: aload_1
      67: iload_3
      68: invokevirtual #23                 // Method org/apache/log4j/RollingCalendar.setType:(I)V
      71: new           #6                  // class java/util/Date
      74: dup
      75: aload_1
      76: aload_2
      77: invokevirtual #52                 // Method org/apache/log4j/RollingCalendar.getNextCheckMillis:(Ljava/util/Date;)J
      80: invokespecial #30                 // Method java/util/Date."<init>":(J)V
      83: astore        6
      85: aload         4
      87: aload         6
      89: invokevirtual #31                 // Method java/text/DateFormat.format:(Ljava/util/Date;)Ljava/lang/String;
      92: astore        7
      94: aload         5
      96: ifnull        116
      99: aload         7
     101: ifnull        116
     104: aload         5
     106: aload         7
     108: invokevirtual #53                 // Method java/lang/String.equals:(Ljava/lang/Object;)Z
     111: ifne          116
     114: iload_3
     115: ireturn
     116: iinc          3, 1
     119: goto          32
     122: iconst_m1
     123: ireturn

  void rollOver() throws java.io.IOException;
    Code:
       0: aload_0
       1: getfield      #3                  // Field datePattern:Ljava/lang/String;
       4: ifnonnull     19
       7: aload_0
       8: getfield      #54                 // Field org/apache/log4j/AppenderSkeleton.errorHandler:Lorg/apache/log4j/spi/ErrorHandler;
      11: ldc           #55                 // String Missing DatePattern option in rollOver().
      13: invokeinterface #56,  2           // InterfaceMethod org/apache/log4j/spi/ErrorHandler.error:(Ljava/lang/String;)V
      18: return
      19: new           #26                 // class java/lang/StringBuffer
      22: dup
      23: invokespecial #27                 // Method java/lang/StringBuffer."<init>":()V
      26: aload_0
      27: getfield      #16                 // Field org/apache/log4j/FileAppender.fileName:Ljava/lang/String;
      30: invokevirtual #28                 // Method java/lang/StringBuffer.append:(Ljava/lang/String;)Ljava/lang/StringBuffer;
      33: aload_0
      34: getfield      #20                 // Field sdf:Ljava/text/SimpleDateFormat;
      37: aload_0
      38: getfield      #8                  // Field now:Ljava/util/Date;
      41: invokevirtual #31                 // Method java/text/DateFormat.format:(Ljava/util/Date;)Ljava/lang/String;
      44: invokevirtual #28                 // Method java/lang/StringBuffer.append:(Ljava/lang/String;)Ljava/lang/StringBuffer;
      47: invokevirtual #32                 // Method java/lang/StringBuffer.toString:()Ljava/lang/String;
      50: astore_1
      51: aload_0
      52: getfield      #33                 // Field scheduledFilename:Ljava/lang/String;
      55: aload_1
      56: invokevirtual #53                 // Method java/lang/String.equals:(Ljava/lang/Object;)Z
      59: ifeq          63
      62: return
      63: aload_0
      64: invokevirtual #57                 // Method org/apache/log4j/FileAppender.closeFile:()V
      67: new           #24                 // class java/io/File
      70: dup
      71: aload_0
      72: getfield      #33                 // Field scheduledFilename:Ljava/lang/String;
      75: invokespecial #25                 // Method java/io/File."<init>":(Ljava/lang/String;)V
      78: astore_2
      79: aload_2
      80: invokevirtual #58                 // Method java/io/File.exists:()Z
      83: ifeq          91
      86: aload_2
      87: invokevirtual #59                 // Method java/io/File.delete:()Z
      90: pop
      91: new           #24                 // class java/io/File
      94: dup
      95: aload_0
      96: getfield      #16                 // Field org/apache/log4j/FileAppender.fileName:Ljava/lang/String;
      99: invokespecial #25                 // Method java/io/File."<init>":(Ljava/lang/String;)V
     102: astore_3
     103: aload_3
     104: aload_2
     105: invokevirtual #60                 // Method java/io/File.renameTo:(Ljava/io/File;)Z
     108: istore        4
     110: iload         4
     112: ifeq          150
     115: new           #26                 // class java/lang/StringBuffer
     118: dup
     119: invokespecial #27                 // Method java/lang/StringBuffer."<init>":()V
     122: aload_0
     123: getfield      #16                 // Field org/apache/log4j/FileAppender.fileName:Ljava/lang/String;
     126: invokevirtual #28                 // Method java/lang/StringBuffer.append:(Ljava/lang/String;)Ljava/lang/StringBuffer;
     129: ldc           #61                 // String  ->
     131: invokevirtual #28                 // Method java/lang/StringBuffer.append:(Ljava/lang/String;)Ljava/lang/StringBuffer;
     134: aload_0
     135: getfield      #33                 // Field scheduledFilename:Ljava/lang/String;
     138: invokevirtual #28                 // Method java/lang/StringBuffer.append:(Ljava/lang/String;)Ljava/lang/StringBuffer;
     141: invokevirtual #32                 // Method java/lang/StringBuffer.toString:()Ljava/lang/String;
     144: invokestatic  #40                 // Method org/apache/log4j/helpers/LogLog.debug:(Ljava/lang/String;)V
     147: goto          192
     150: new           #26                 // class java/lang/StringBuffer
     153: dup
     154: invokespecial #27                 // Method java/lang/StringBuffer."<init>":()V
     157: ldc           #62                 // String Failed to rename [
     159: invokevirtual #28                 // Method java/lang/StringBuffer.append:(Ljava/lang/String;)Ljava/lang/StringBuffer;
     162: aload_0
     163: getfield      #16                 // Field org/apache/log4j/FileAppender.fileName:Ljava/lang/String;
     166: invokevirtual #28                 // Method java/lang/StringBuffer.append:(Ljava/lang/String;)Ljava/lang/StringBuffer;
     169: ldc           #63                 // String ] to [
     171: invokevirtual #28                 // Method java/lang/StringBuffer.append:(Ljava/lang/String;)Ljava/lang/StringBuffer;
     174: aload_0
     175: getfield      #33                 // Field scheduledFilename:Ljava/lang/String;
     178: invokevirtual #28                 // Method java/lang/StringBuffer.append:(Ljava/lang/String;)Ljava/lang/StringBuffer;
     181: ldc           #36                 // String ].
     183: invokevirtual #28                 // Method java/lang/StringBuffer.append:(Ljava/lang/String;)Ljava/lang/StringBuffer;
     186: invokevirtual #32                 // Method java/lang/StringBuffer.toString:()Ljava/lang/String;
     189: invokestatic  #37                 // Method org/apache/log4j/helpers/LogLog.error:(Ljava/lang/String;)V
     192: aload_0
     193: aload_0
     194: getfield      #16                 // Field org/apache/log4j/FileAppender.fileName:Ljava/lang/String;
     197: iconst_1
     198: aload_0
     199: getfield      #64                 // Field org/apache/log4j/FileAppender.bufferedIO:Z
     202: aload_0
     203: getfield      #65                 // Field org/apache/log4j/FileAppender.bufferSize:I
     206: invokevirtual #66                 // Method org/apache/log4j/FileAppender.setFile:(Ljava/lang/String;ZZI)V
     209: goto          250
     212: astore        5
     214: aload_0
     215: getfield      #54                 // Field org/apache/log4j/AppenderSkeleton.errorHandler:Lorg/apache/log4j/spi/ErrorHandler;
     218: new           #26                 // class java/lang/StringBuffer
     221: dup
     222: invokespecial #27                 // Method java/lang/StringBuffer."<init>":()V
     225: ldc           #68                 // String setFile(
     227: invokevirtual #28                 // Method java/lang/StringBuffer.append:(Ljava/lang/String;)Ljava/lang/StringBuffer;
     230: aload_0
     231: getfield      #16                 // Field org/apache/log4j/FileAppender.fileName:Ljava/lang/String;
     234: invokevirtual #28                 // Method java/lang/StringBuffer.append:(Ljava/lang/String;)Ljava/lang/StringBuffer;
     237: ldc           #69                 // String , true) call failed.
     239: invokevirtual #28                 // Method java/lang/StringBuffer.append:(Ljava/lang/String;)Ljava/lang/StringBuffer;
     242: invokevirtual #32                 // Method java/lang/StringBuffer.toString:()Ljava/lang/String;
     245: invokeinterface #56,  2           // InterfaceMethod org/apache/log4j/spi/ErrorHandler.error:(Ljava/lang/String;)V
     250: aload_0
     251: aload_1
     252: putfield      #33                 // Field scheduledFilename:Ljava/lang/String;
     255: return
    Exception table:
       from    to  target type
         192   209   212   Class java/io/IOException

  protected void subAppend(org.apache.log4j.spi.LoggingEvent);
    Code:
       0: invokestatic  #4                  // Method java/lang/System.currentTimeMillis:()J
       3: lstore_2
       4: lload_2
       5: aload_0
       6: getfield      #5                  // Field nextCheck:J
       9: lcmp
      10: iflt          66
      13: aload_0
      14: getfield      #8                  // Field now:Ljava/util/Date;
      17: lload_2
      18: invokevirtual #17                 // Method java/util/Date.setTime:(J)V
      21: aload_0
      22: aload_0
      23: getfield      #11                 // Field rc:Lorg/apache/log4j/RollingCalendar;
      26: aload_0
      27: getfield      #8                  // Field now:Ljava/util/Date;
      30: invokevirtual #52                 // Method org/apache/log4j/RollingCalendar.getNextCheckMillis:(Ljava/util/Date;)J
      33: putfield      #5                  // Field nextCheck:J
      36: aload_0
      37: invokevirtual #70                 // Method rollOver:()V
      40: goto          66
      43: astore        4
      45: aload         4
      47: instanceof    #71                 // class java/io/InterruptedIOException
      50: ifeq          59
      53: invokestatic  #72                 // Method java/lang/Thread.currentThread:()Ljava/lang/Thread;
      56: invokevirtual #73                 // Method java/lang/Thread.interrupt:()V
      59: ldc           #74                 // String rollOver() failed.
      61: aload         4
      63: invokestatic  #75                 // Method org/apache/log4j/helpers/LogLog.error:(Ljava/lang/String;Ljava/lang/Throwable;)V
      66: aload_0
      67: aload_1
      68: invokespecial #76                 // Method org/apache/log4j/WriterAppender.subAppend:(Lorg/apache/log4j/spi/LoggingEvent;)V
      71: return
    Exception table:
       from    to  target type
          36    40    43   Class java/io/IOException

  static {};
    Code:
       0: ldc           #77                 // String GMT
       2: invokestatic  #78                 // Method java/util/TimeZone.getTimeZone:(Ljava/lang/String;)Ljava/util/TimeZone;
       5: putstatic     #48                 // Field gmtTimeZone:Ljava/util/TimeZone;
       8: return
}
