Compiled from "StandardJavaScriptSerializer.java"
final class org.thymeleaf.standard.serializer.StandardJavaScriptSerializer$JacksonThymeleafISO8601DateFormat extends java.text.DateFormat {
  private static final long serialVersionUID;

  private java.text.SimpleDateFormat dateFormat;

  org.thymeleaf.standard.serializer.StandardJavaScriptSerializer$JacksonThymeleafISO8601DateFormat();
    Code:
       0: aload_0
       1: invokespecial #1                  // Method java/text/DateFormat."<init>":()V
       4: aload_0
       5: new           #2                  // class java/text/SimpleDateFormat
       8: dup
       9: ldc           #3                  // String yyyy-MM-dd\'T\'HH:mm:ss.SSSZZZ
      11: invokespecial #4                  // Method java/text/SimpleDateFormat."<init>":(Ljava/lang/String;)V
      14: putfield      #5                  // Field dateFormat:Ljava/text/SimpleDateFormat;
      17: aload_0
      18: aload_0
      19: getfield      #5                  // Field dateFormat:Ljava/text/SimpleDateFormat;
      22: invokevirtual #6                  // Method java/text/SimpleDateFormat.getCalendar:()Ljava/util/Calendar;
      25: invokevirtual #7                  // Method setCalendar:(Ljava/util/Calendar;)V
      28: aload_0
      29: aload_0
      30: getfield      #5                  // Field dateFormat:Ljava/text/SimpleDateFormat;
      33: invokevirtual #8                  // Method java/text/SimpleDateFormat.getNumberFormat:()Ljava/text/NumberFormat;
      36: invokevirtual #9                  // Method setNumberFormat:(Ljava/text/NumberFormat;)V
      39: return

  public java.lang.StringBuffer format(java.util.Date, java.lang.StringBuffer, java.text.FieldPosition);
    Code:
       0: aload_0
       1: getfield      #5                  // Field dateFormat:Ljava/text/SimpleDateFormat;
       4: aload_1
       5: aload_2
       6: aload_3
       7: invokevirtual #10                 // Method java/text/SimpleDateFormat.format:(Ljava/util/Date;Ljava/lang/StringBuffer;Ljava/text/FieldPosition;)Ljava/lang/StringBuffer;
      10: astore        4
      12: aload         4
      14: bipush        26
      16: bipush        58
      18: invokevirtual #11                 // Method java/lang/StringBuffer.insert:(IC)Ljava/lang/StringBuffer;
      21: pop
      22: aload         4
      24: areturn

  public java.util.Date parse(java.lang.String, java.text.ParsePosition);
    Code:
       0: new           #12                 // class java/lang/UnsupportedOperationException
       3: dup
       4: ldc           #13                 // String JacksonThymeleafISO8601DateFormat should never be asked for a \'parse\' operation
       6: invokespecial #14                 // Method java/lang/UnsupportedOperationException."<init>":(Ljava/lang/String;)V
       9: athrow

  public java.lang.Object clone();
    Code:
       0: aload_0
       1: invokespecial #15                 // Method java/text/DateFormat.clone:()Ljava/lang/Object;
       4: checkcast     #16                 // class org/thymeleaf/standard/serializer/StandardJavaScriptSerializer$JacksonThymeleafISO8601DateFormat
       7: astore_1
       8: aload_1
       9: aload_0
      10: getfield      #5                  // Field dateFormat:Ljava/text/SimpleDateFormat;
      13: invokevirtual #17                 // Method java/text/SimpleDateFormat.clone:()Ljava/lang/Object;
      16: checkcast     #2                  // class java/text/SimpleDateFormat
      19: putfield      #5                  // Field dateFormat:Ljava/text/SimpleDateFormat;
      22: aload_1
      23: areturn
}
