Compiled from "ByteBufferPool.java"
final class org.xnio.ByteBufferPool$DefaultCache implements org.xnio.ByteBufferPool$Cache {
  final org.xnio.ByteBufferPool this$0;

  org.xnio.ByteBufferPool$DefaultCache(org.xnio.ByteBufferPool);
    Code:
       0: aload_0
       1: aload_1
       2: putfield      #17                 // Field this$0:Lorg/xnio/ByteBufferPool;
       5: aload_0
       6: invokespecial #20                 // Method java/lang/Object."<init>":()V
       9: return

  public void free(java.nio.ByteBuffer);
    Code:
       0: aload_0
       1: getfield      #17                 // Field this$0:Lorg/xnio/ByteBufferPool;
       4: aload_1
       5: invokevirtual #27                 // Method org/xnio/ByteBufferPool.freeMaster:(Ljava/nio/ByteBuffer;)V
       8: return

  public java.nio.ByteBuffer allocate();
    Code:
       0: aload_0
       1: getfield      #17                 // Field this$0:Lorg/xnio/ByteBufferPool;
       4: invokestatic  #35                 // Method org/xnio/ByteBufferPool.access$000:(Lorg/xnio/ByteBufferPool;)Ljava/nio/ByteBuffer;
       7: areturn

  public void flushBuffer(java.nio.ByteBuffer);
    Code:
       0: aload_0
       1: aload_1
       2: invokevirtual #38                 // Method free:(Ljava/nio/ByteBuffer;)V
       5: return

  public void destroy();
    Code:
       0: return

  public void flush();
    Code:
       0: return
}
