Compiled from "IoUtils.java"
public final class org.xnio.IoUtils {
  private static final java.util.concurrent.Executor NULL_EXECUTOR;

  private static final java.util.concurrent.Executor DIRECT_EXECUTOR;

  private static final java.io.Closeable NULL_CLOSEABLE;

  private static final org.xnio.Cancellable NULL_CANCELLABLE;

  private static final org.xnio.IoUtils$ResultNotifier RESULT_NOTIFIER;

  private static final org.xnio.IoFuture$Notifier<java.lang.Object, java.io.Closeable> ATTACHMENT_CLOSING_NOTIFIER;

  private static final org.xnio.IoFuture$Notifier<java.io.Closeable, java.lang.Void> CLOSING_NOTIFIER;

  private static final org.xnio.IoFuture$Notifier CHANNEL_LISTENER_NOTIFIER;

  private static final org.xnio.IoFuture$Notifier<java.lang.Object, java.util.concurrent.CountDownLatch> COUNT_DOWN_NOTIFIER;

  private static final org.xnio.IoUtils$ManagerNotifier MANAGER_NOTIFIER;

  private org.xnio.IoUtils();
    Code:
       0: aload_0
       1: invokespecial #71                 // Method java/lang/Object."<init>":()V
       4: return

  public static java.util.concurrent.Executor directExecutor();
    Code:
       0: getstatic     #77                 // Field DIRECT_EXECUTOR:Ljava/util/concurrent/Executor;
       3: areturn

  public static java.util.concurrent.Executor nullExecutor();
    Code:
       0: getstatic     #80                 // Field NULL_EXECUTOR:Ljava/util/concurrent/Executor;
       3: areturn

  public static java.io.Closeable nullCloseable();
    Code:
       0: getstatic     #84                 // Field NULL_CLOSEABLE:Ljava/io/Closeable;
       3: areturn

  public static void safeClose(java.lang.AutoCloseable);
    Code:
       0: aload_0
       1: ifnull        19
       4: getstatic     #96                 // Field org/xnio/_private/Messages.closeMsg:Lorg/xnio/_private/Messages;
       7: aload_0
       8: invokeinterface #100,  2          // InterfaceMethod org/xnio/_private/Messages.closingResource:(Ljava/lang/Object;)V
      13: aload_0
      14: invokeinterface #105,  1          // InterfaceMethod java/lang/AutoCloseable.close:()V
      19: goto          37
      22: astore_1
      23: goto          37
      26: astore_1
      27: getstatic     #96                 // Field org/xnio/_private/Messages.closeMsg:Lorg/xnio/_private/Messages;
      30: aload_1
      31: aload_0
      32: invokeinterface #109,  3          // InterfaceMethod org/xnio/_private/Messages.resourceCloseFailed:(Ljava/lang/Throwable;Ljava/lang/Object;)V
      37: return
    Exception table:
       from    to  target type
           0    19    22   Class java/nio/channels/ClosedChannelException
           0    19    26   Class java/lang/Throwable

  public static void safeClose(java.io.Closeable);
    Code:
       0: aload_0
       1: ifnull        19
       4: getstatic     #96                 // Field org/xnio/_private/Messages.closeMsg:Lorg/xnio/_private/Messages;
       7: aload_0
       8: invokeinterface #100,  2          // InterfaceMethod org/xnio/_private/Messages.closingResource:(Ljava/lang/Object;)V
      13: aload_0
      14: invokeinterface #117,  1          // InterfaceMethod java/io/Closeable.close:()V
      19: goto          51
      22: astore_1
      23: getstatic     #120                // Field org/xnio/_private/Messages.msg:Lorg/xnio/_private/Messages;
      26: ldc           #122                // String safeClose, ignoring ClosedChannelException exception
      28: iconst_0
      29: anewarray     #4                  // class java/lang/Object
      32: invokeinterface #126,  3          // InterfaceMethod org/xnio/_private/Messages.tracef:(Ljava/lang/String;[Ljava/lang/Object;)V
      37: goto          51
      40: astore_1
      41: getstatic     #96                 // Field org/xnio/_private/Messages.closeMsg:Lorg/xnio/_private/Messages;
      44: aload_1
      45: aload_0
      46: invokeinterface #109,  3          // InterfaceMethod org/xnio/_private/Messages.resourceCloseFailed:(Ljava/lang/Throwable;Ljava/lang/Object;)V
      51: return
    Exception table:
       from    to  target type
           0    19    22   Class java/nio/channels/ClosedChannelException
           0    19    40   Class java/lang/Throwable

  public static void safeClose(java.io.Closeable...);
    Code:
       0: aload_0
       1: astore_1
       2: aload_1
       3: arraylength
       4: istore_2
       5: iconst_0
       6: istore_3
       7: iload_3
       8: iload_2
       9: if_icmpge     28
      12: aload_1
      13: iload_3
      14: aaload
      15: astore        4
      17: aload         4
      19: invokestatic  #133                // Method safeClose:(Ljava/io/Closeable;)V
      22: iinc          3, 1
      25: goto          7
      28: return

  public static void safeClose(java.net.Socket);
    Code:
       0: aload_0
       1: ifnull        17
       4: getstatic     #96                 // Field org/xnio/_private/Messages.closeMsg:Lorg/xnio/_private/Messages;
       7: aload_0
       8: invokeinterface #100,  2          // InterfaceMethod org/xnio/_private/Messages.closingResource:(Ljava/lang/Object;)V
      13: aload_0
      14: invokevirtual #138                // Method java/net/Socket.close:()V
      17: goto          35
      20: astore_1
      21: goto          35
      24: astore_1
      25: getstatic     #96                 // Field org/xnio/_private/Messages.closeMsg:Lorg/xnio/_private/Messages;
      28: aload_1
      29: aload_0
      30: invokeinterface #109,  3          // InterfaceMethod org/xnio/_private/Messages.resourceCloseFailed:(Ljava/lang/Throwable;Ljava/lang/Object;)V
      35: return
    Exception table:
       from    to  target type
           0    17    20   Class java/nio/channels/ClosedChannelException
           0    17    24   Class java/lang/Throwable

  public static void safeClose(java.net.DatagramSocket);
    Code:
       0: aload_0
       1: ifnull        17
       4: getstatic     #96                 // Field org/xnio/_private/Messages.closeMsg:Lorg/xnio/_private/Messages;
       7: aload_0
       8: invokeinterface #100,  2          // InterfaceMethod org/xnio/_private/Messages.closingResource:(Ljava/lang/Object;)V
      13: aload_0
      14: invokevirtual #143                // Method java/net/DatagramSocket.close:()V
      17: goto          31
      20: astore_1
      21: getstatic     #96                 // Field org/xnio/_private/Messages.closeMsg:Lorg/xnio/_private/Messages;
      24: aload_1
      25: aload_0
      26: invokeinterface #109,  3          // InterfaceMethod org/xnio/_private/Messages.resourceCloseFailed:(Ljava/lang/Throwable;Ljava/lang/Object;)V
      31: return
    Exception table:
       from    to  target type
           0    17    20   Class java/lang/Throwable

  public static void safeClose(java.nio.channels.Selector);
    Code:
       0: aload_0
       1: ifnull        17
       4: getstatic     #96                 // Field org/xnio/_private/Messages.closeMsg:Lorg/xnio/_private/Messages;
       7: aload_0
       8: invokeinterface #100,  2          // InterfaceMethod org/xnio/_private/Messages.closingResource:(Ljava/lang/Object;)V
      13: aload_0
      14: invokevirtual #148                // Method java/nio/channels/Selector.close:()V
      17: goto          35
      20: astore_1
      21: goto          35
      24: astore_1
      25: getstatic     #96                 // Field org/xnio/_private/Messages.closeMsg:Lorg/xnio/_private/Messages;
      28: aload_1
      29: aload_0
      30: invokeinterface #109,  3          // InterfaceMethod org/xnio/_private/Messages.resourceCloseFailed:(Ljava/lang/Throwable;Ljava/lang/Object;)V
      35: return
    Exception table:
       from    to  target type
           0    17    20   Class java/nio/channels/ClosedChannelException
           0    17    24   Class java/lang/Throwable

  public static void safeClose(java.net.ServerSocket);
    Code:
       0: aload_0
       1: ifnull        17
       4: getstatic     #96                 // Field org/xnio/_private/Messages.closeMsg:Lorg/xnio/_private/Messages;
       7: aload_0
       8: invokeinterface #100,  2          // InterfaceMethod org/xnio/_private/Messages.closingResource:(Ljava/lang/Object;)V
      13: aload_0
      14: invokevirtual #153                // Method java/net/ServerSocket.close:()V
      17: goto          35
      20: astore_1
      21: goto          35
      24: astore_1
      25: getstatic     #96                 // Field org/xnio/_private/Messages.closeMsg:Lorg/xnio/_private/Messages;
      28: aload_1
      29: aload_0
      30: invokeinterface #109,  3          // InterfaceMethod org/xnio/_private/Messages.resourceCloseFailed:(Ljava/lang/Throwable;Ljava/lang/Object;)V
      35: return
    Exception table:
       from    to  target type
           0    17    20   Class java/nio/channels/ClosedChannelException
           0    17    24   Class java/lang/Throwable

  public static void safeClose(java.util.zip.ZipFile);
    Code:
       0: aload_0
       1: ifnull        17
       4: getstatic     #96                 // Field org/xnio/_private/Messages.closeMsg:Lorg/xnio/_private/Messages;
       7: aload_0
       8: invokeinterface #100,  2          // InterfaceMethod org/xnio/_private/Messages.closingResource:(Ljava/lang/Object;)V
      13: aload_0
      14: invokevirtual #158                // Method java/util/zip/ZipFile.close:()V
      17: goto          31
      20: astore_1
      21: getstatic     #96                 // Field org/xnio/_private/Messages.closeMsg:Lorg/xnio/_private/Messages;
      24: aload_1
      25: aload_0
      26: invokeinterface #109,  3          // InterfaceMethod org/xnio/_private/Messages.resourceCloseFailed:(Ljava/lang/Throwable;Ljava/lang/Object;)V
      31: return
    Exception table:
       from    to  target type
           0    17    20   Class java/lang/Throwable

  public static void safeClose(java.util.logging.Handler);
    Code:
       0: aload_0
       1: ifnull        17
       4: getstatic     #96                 // Field org/xnio/_private/Messages.closeMsg:Lorg/xnio/_private/Messages;
       7: aload_0
       8: invokeinterface #100,  2          // InterfaceMethod org/xnio/_private/Messages.closingResource:(Ljava/lang/Object;)V
      13: aload_0
      14: invokevirtual #163                // Method java/util/logging/Handler.close:()V
      17: goto          31
      20: astore_1
      21: getstatic     #96                 // Field org/xnio/_private/Messages.closeMsg:Lorg/xnio/_private/Messages;
      24: aload_1
      25: aload_0
      26: invokeinterface #109,  3          // InterfaceMethod org/xnio/_private/Messages.resourceCloseFailed:(Ljava/lang/Throwable;Ljava/lang/Object;)V
      31: return
    Exception table:
       from    to  target type
           0    17    20   Class java/lang/Throwable

  public static void safeClose(org.xnio.IoFuture<? extends java.io.Closeable>);
    Code:
       0: aload_0
       1: ifnull        20
       4: aload_0
       5: invokeinterface #170,  1          // InterfaceMethod org/xnio/IoFuture.cancel:()Lorg/xnio/IoFuture;
      10: invokestatic  #174                // Method closingNotifier:()Lorg/xnio/IoFuture$Notifier;
      13: aconst_null
      14: invokeinterface #178,  3          // InterfaceMethod org/xnio/IoFuture.addNotifier:(Lorg/xnio/IoFuture$Notifier;Ljava/lang/Object;)Lorg/xnio/IoFuture;
      19: pop
      20: return

  public static org.xnio.IoFuture$Notifier<java.lang.Object, java.io.Closeable> attachmentClosingNotifier();
    Code:
       0: getstatic     #185                // Field ATTACHMENT_CLOSING_NOTIFIER:Lorg/xnio/IoFuture$Notifier;
       3: areturn

  public static org.xnio.IoFuture$Notifier<java.io.Closeable, java.lang.Void> closingNotifier();
    Code:
       0: getstatic     #188                // Field CLOSING_NOTIFIER:Lorg/xnio/IoFuture$Notifier;
       3: areturn

  public static <T> org.xnio.IoFuture$Notifier<T, java.lang.Void> runnableNotifier(java.lang.Runnable);
    Code:
       0: new           #31                 // class org/xnio/IoUtils$7
       3: dup
       4: aload_0
       5: invokespecial #194                // Method org/xnio/IoUtils$7."<init>":(Ljava/lang/Runnable;)V
       8: areturn

  public static <T> org.xnio.IoFuture$Notifier<T, org.xnio.Result<T>> resultNotifier();
    Code:
       0: getstatic     #200                // Field RESULT_NOTIFIER:Lorg/xnio/IoUtils$ResultNotifier;
       3: areturn

  public static <T extends java.nio.channels.Channel> org.xnio.IoFuture$Notifier<T, org.xnio.ChannelListener<? super T>> channelListenerNotifier();
    Code:
       0: getstatic     #204                // Field CHANNEL_LISTENER_NOTIFIER:Lorg/xnio/IoFuture$Notifier;
       3: areturn

  public static <T> java.util.concurrent.Future<T> getFuture(org.xnio.IoFuture<T>);
    Code:
       0: new           #27                 // class org/xnio/IoUtils$9
       3: dup
       4: aload_0
       5: invokespecial #209                // Method org/xnio/IoUtils$9."<init>":(Lorg/xnio/IoFuture;)V
       8: areturn

  public static void awaitAll(org.xnio.IoFuture<?>...);
    Code:
       0: aload_0
       1: arraylength
       2: istore_1
       3: new           #218                // class java/util/concurrent/CountDownLatch
       6: dup
       7: iload_1
       8: invokespecial #221                // Method java/util/concurrent/CountDownLatch."<init>":(I)V
      11: astore_2
      12: aload_0
      13: astore_3
      14: aload_3
      15: arraylength
      16: istore        4
      18: iconst_0
      19: istore        5
      21: iload         5
      23: iload         4
      25: if_icmpge     52
      28: aload_3
      29: iload         5
      31: aaload
      32: astore        6
      34: aload         6
      36: getstatic     #225                // Field COUNT_DOWN_NOTIFIER:Lorg/xnio/IoFuture$Notifier;
      39: aload_2
      40: invokeinterface #178,  3          // InterfaceMethod org/xnio/IoFuture.addNotifier:(Lorg/xnio/IoFuture$Notifier;Ljava/lang/Object;)Lorg/xnio/IoFuture;
      45: pop
      46: iinc          5, 1
      49: goto          21
      52: iconst_0
      53: istore_3
      54: aload_2
      55: invokevirtual #229                // Method java/util/concurrent/CountDownLatch.getCount:()J
      58: lconst_0
      59: lcmp
      60: ifle          77
      63: aload_2
      64: invokevirtual #232                // Method java/util/concurrent/CountDownLatch.await:()V
      67: goto          54
      70: astore        4
      72: iconst_1
      73: istore_3
      74: goto          54
      77: iload_3
      78: ifeq          105
      81: invokestatic  #238                // Method java/lang/Thread.currentThread:()Ljava/lang/Thread;
      84: invokevirtual #241                // Method java/lang/Thread.interrupt:()V
      87: goto          105
      90: astore        7
      92: iload_3
      93: ifeq          102
      96: invokestatic  #238                // Method java/lang/Thread.currentThread:()Ljava/lang/Thread;
      99: invokevirtual #241                // Method java/lang/Thread.interrupt:()V
     102: aload         7
     104: athrow
     105: return
    Exception table:
       from    to  target type
          63    67    70   Class java/lang/InterruptedException
          54    77    90   any
          90    92    90   any

  public static void awaitAllInterruptibly(org.xnio.IoFuture<?>...) throws java.lang.InterruptedException;
    Code:
       0: aload_0
       1: arraylength
       2: istore_1
       3: new           #218                // class java/util/concurrent/CountDownLatch
       6: dup
       7: iload_1
       8: invokespecial #221                // Method java/util/concurrent/CountDownLatch."<init>":(I)V
      11: astore_2
      12: aload_0
      13: astore_3
      14: aload_3
      15: arraylength
      16: istore        4
      18: iconst_0
      19: istore        5
      21: iload         5
      23: iload         4
      25: if_icmpge     52
      28: aload_3
      29: iload         5
      31: aaload
      32: astore        6
      34: aload         6
      36: getstatic     #225                // Field COUNT_DOWN_NOTIFIER:Lorg/xnio/IoFuture$Notifier;
      39: aload_2
      40: invokeinterface #178,  3          // InterfaceMethod org/xnio/IoFuture.addNotifier:(Lorg/xnio/IoFuture$Notifier;Ljava/lang/Object;)Lorg/xnio/IoFuture;
      45: pop
      46: iinc          5, 1
      49: goto          21
      52: aload_2
      53: invokevirtual #232                // Method java/util/concurrent/CountDownLatch.await:()V
      56: return

  public static <I, O> org.xnio.IoFuture<? extends O> cast(org.xnio.IoFuture<I>, java.lang.Class<O>);
    Code:
       0: new           #22                 // class org/xnio/IoUtils$CastingIoFuture
       3: dup
       4: aload_0
       5: aload_1
       6: aconst_null
       7: invokespecial #260                // Method org/xnio/IoUtils$CastingIoFuture."<init>":(Lorg/xnio/IoFuture;Ljava/lang/Class;Lorg/xnio/IoUtils$1;)V
      10: areturn

  public static void safeShutdownReads(org.xnio.channels.SuspendableReadChannel);
    Code:
       0: aload_0
       1: ifnull        24
       4: aload_0
       5: invokeinterface #274,  1          // InterfaceMethod org/xnio/channels/SuspendableReadChannel.shutdownReads:()V
      10: goto          24
      13: astore_1
      14: getstatic     #96                 // Field org/xnio/_private/Messages.closeMsg:Lorg/xnio/_private/Messages;
      17: aconst_null
      18: aconst_null
      19: invokeinterface #277,  3          // InterfaceMethod org/xnio/_private/Messages.resourceReadShutdownFailed:(Ljava/lang/Throwable;Ljava/lang/Object;)V
      24: return
    Exception table:
       from    to  target type
           4    10    13   Class java/io/IOException

  public static long transfer(java.nio.channels.ReadableByteChannel, long, java.nio.ByteBuffer, java.nio.channels.WritableByteChannel) throws java.io.IOException;
    Code:
       0: lconst_0
       1: lstore        7
       3: aload_3
       4: iconst_0
       5: invokevirtual #288                // Method java/nio/ByteBuffer.limit:(I)Ljava/nio/Buffer;
       8: pop
       9: lload         7
      11: lload_1
      12: lcmp
      13: ifge          134
      16: aload_3
      17: invokevirtual #292                // Method java/nio/ByteBuffer.compact:()Ljava/nio/ByteBuffer;
      20: pop
      21: lload_1
      22: lload         7
      24: lsub
      25: aload_3
      26: invokevirtual #296                // Method java/nio/ByteBuffer.remaining:()I
      29: i2l
      30: lcmp
      31: ifge          44
      34: aload_3
      35: lload_1
      36: lload         7
      38: lsub
      39: l2i
      40: invokevirtual #288                // Method java/nio/ByteBuffer.limit:(I)Ljava/nio/Buffer;
      43: pop
      44: aload_0
      45: aload_3
      46: invokeinterface #302,  2          // InterfaceMethod java/nio/channels/ReadableByteChannel.read:(Ljava/nio/ByteBuffer;)I
      51: i2l
      52: lstore        5
      54: lload         5
      56: lconst_0
      57: lcmp
      58: ifgt          85
      61: lload         7
      63: lconst_0
      64: lcmp
      65: ifne          73
      68: lload         5
      70: goto          75
      73: lload         7
      75: lstore        9
      77: aload_3
      78: invokevirtual #308                // Method java/nio/ByteBuffer.flip:()Ljava/nio/Buffer;
      81: pop
      82: lload         9
      84: lreturn
      85: aload_3
      86: invokevirtual #308                // Method java/nio/ByteBuffer.flip:()Ljava/nio/Buffer;
      89: pop
      90: goto          103
      93: astore        11
      95: aload_3
      96: invokevirtual #308                // Method java/nio/ByteBuffer.flip:()Ljava/nio/Buffer;
      99: pop
     100: aload         11
     102: athrow
     103: aload         4
     105: aload_3
     106: invokeinterface #311,  2          // InterfaceMethod java/nio/channels/WritableByteChannel.write:(Ljava/nio/ByteBuffer;)I
     111: i2l
     112: lstore        5
     114: lload         5
     116: lconst_0
     117: lcmp
     118: ifne          124
     121: lload         7
     123: lreturn
     124: lload         7
     126: lload         5
     128: ladd
     129: lstore        7
     131: goto          9
     134: lload         7
     136: lreturn
    Exception table:
       from    to  target type
          21    77    93   any
          93    95    93   any

  public static <T> org.xnio.IoFuture$Notifier<T, org.xnio.FutureResult<T>> getManagerNotifier();
    Code:
       0: getstatic     #325                // Field MANAGER_NOTIFIER:Lorg/xnio/IoUtils$ManagerNotifier;
       3: areturn

  public static <T extends java.nio.channels.Channel> org.xnio.ChannelSource<T> getRetryingChannelSource(org.xnio.ChannelSource<T>, int) throws java.lang.IllegalArgumentException;
    Code:
       0: iload_1
       1: iconst_1
       2: if_icmpge     18
       5: getstatic     #120                // Field org/xnio/_private/Messages.msg:Lorg/xnio/_private/Messages;
       8: ldc_w         #332                // String maxTries
      11: iconst_1
      12: invokeinterface #336,  3          // InterfaceMethod org/xnio/_private/Messages.minRange:(Ljava/lang/String;I)Ljava/lang/IllegalArgumentException;
      17: athrow
      18: new           #13                 // class org/xnio/IoUtils$RetryingChannelSource
      21: dup
      22: iload_1
      23: aload_0
      24: invokespecial #339                // Method org/xnio/IoUtils$RetryingChannelSource."<init>":(ILorg/xnio/ChannelSource;)V
      27: areturn

  public static org.xnio.Cancellable closingCancellable(java.io.Closeable);
    Code:
       0: new           #10                 // class org/xnio/IoUtils$ClosingCancellable
       3: dup
       4: aload_0
       5: invokespecial #346                // Method org/xnio/IoUtils$ClosingCancellable."<init>":(Ljava/io/Closeable;)V
       8: areturn

  public static org.xnio.Cancellable nullCancellable();
    Code:
       0: getstatic     #351                // Field NULL_CANCELLABLE:Lorg/xnio/Cancellable;
       3: areturn

  public static java.util.Random getThreadLocalRandom();
    Code:
       0: invokestatic  #359                // Method java/util/concurrent/ThreadLocalRandom.current:()Ljava/util/concurrent/ThreadLocalRandom;
       3: areturn

  static {};
    Code:
       0: new           #43                 // class org/xnio/IoUtils$1
       3: dup
       4: invokespecial #361                // Method org/xnio/IoUtils$1."<init>":()V
       7: putstatic     #80                 // Field NULL_EXECUTOR:Ljava/util/concurrent/Executor;
      10: new           #41                 // class org/xnio/IoUtils$2
      13: dup
      14: invokespecial #362                // Method org/xnio/IoUtils$2."<init>":()V
      17: putstatic     #77                 // Field DIRECT_EXECUTOR:Ljava/util/concurrent/Executor;
      20: new           #39                 // class org/xnio/IoUtils$3
      23: dup
      24: invokespecial #363                // Method org/xnio/IoUtils$3."<init>":()V
      27: putstatic     #84                 // Field NULL_CLOSEABLE:Ljava/io/Closeable;
      30: new           #37                 // class org/xnio/IoUtils$4
      33: dup
      34: invokespecial #364                // Method org/xnio/IoUtils$4."<init>":()V
      37: putstatic     #351                // Field NULL_CANCELLABLE:Lorg/xnio/Cancellable;
      40: new           #7                  // class org/xnio/IoUtils$ResultNotifier
      43: dup
      44: aconst_null
      45: invokespecial #367                // Method org/xnio/IoUtils$ResultNotifier."<init>":(Lorg/xnio/IoUtils$1;)V
      48: putstatic     #200                // Field RESULT_NOTIFIER:Lorg/xnio/IoUtils$ResultNotifier;
      51: new           #35                 // class org/xnio/IoUtils$5
      54: dup
      55: invokespecial #368                // Method org/xnio/IoUtils$5."<init>":()V
      58: putstatic     #185                // Field ATTACHMENT_CLOSING_NOTIFIER:Lorg/xnio/IoFuture$Notifier;
      61: new           #33                 // class org/xnio/IoUtils$6
      64: dup
      65: invokespecial #369                // Method org/xnio/IoUtils$6."<init>":()V
      68: putstatic     #188                // Field CLOSING_NOTIFIER:Lorg/xnio/IoFuture$Notifier;
      71: new           #29                 // class org/xnio/IoUtils$8
      74: dup
      75: invokespecial #370                // Method org/xnio/IoUtils$8."<init>":()V
      78: putstatic     #204                // Field CHANNEL_LISTENER_NOTIFIER:Lorg/xnio/IoFuture$Notifier;
      81: new           #25                 // class org/xnio/IoUtils$10
      84: dup
      85: invokespecial #371                // Method org/xnio/IoUtils$10."<init>":()V
      88: putstatic     #225                // Field COUNT_DOWN_NOTIFIER:Lorg/xnio/IoFuture$Notifier;
      91: new           #19                 // class org/xnio/IoUtils$ManagerNotifier
      94: dup
      95: aconst_null
      96: invokespecial #372                // Method org/xnio/IoUtils$ManagerNotifier."<init>":(Lorg/xnio/IoUtils$1;)V
      99: putstatic     #325                // Field MANAGER_NOTIFIER:Lorg/xnio/IoUtils$ManagerNotifier;
     102: return
}
