Compiled from "Option.java"
public class org.xnio.Option$SetBuilder {
  private java.util.List<org.xnio.Option<?>> optionSet;

  org.xnio.Option$SetBuilder();
    Code:
       0: aload_0
       1: invokespecial #15                 // Method java/lang/Object."<init>":()V
       4: aload_0
       5: new           #17                 // class java/util/ArrayList
       8: dup
       9: invokespecial #18                 // Method java/util/ArrayList."<init>":()V
      12: putfield      #20                 // Field optionSet:Ljava/util/List;
      15: return

  public org.xnio.Option$SetBuilder add(org.xnio.Option<?>);
    Code:
       0: aload_1
       1: ifnonnull     15
       4: getstatic     #31                 // Field org/xnio/_private/Messages.msg:Lorg/xnio/_private/Messages;
       7: ldc           #33                 // String option
       9: invokeinterface #37,  2           // InterfaceMethod org/xnio/_private/Messages.nullParameter:(Ljava/lang/String;)Ljava/lang/IllegalArgumentException;
      14: athrow
      15: aload_0
      16: getfield      #20                 // Field optionSet:Ljava/util/List;
      19: aload_1
      20: invokeinterface #42,  2           // InterfaceMethod java/util/List.add:(Ljava/lang/Object;)Z
      25: pop
      26: aload_0
      27: areturn

  public org.xnio.Option$SetBuilder add(org.xnio.Option<?>, org.xnio.Option<?>);
    Code:
       0: aload_1
       1: ifnonnull     15
       4: getstatic     #31                 // Field org/xnio/_private/Messages.msg:Lorg/xnio/_private/Messages;
       7: ldc           #48                 // String option1
       9: invokeinterface #37,  2           // InterfaceMethod org/xnio/_private/Messages.nullParameter:(Ljava/lang/String;)Ljava/lang/IllegalArgumentException;
      14: athrow
      15: aload_2
      16: ifnonnull     30
      19: getstatic     #31                 // Field org/xnio/_private/Messages.msg:Lorg/xnio/_private/Messages;
      22: ldc           #50                 // String option2
      24: invokeinterface #37,  2           // InterfaceMethod org/xnio/_private/Messages.nullParameter:(Ljava/lang/String;)Ljava/lang/IllegalArgumentException;
      29: athrow
      30: aload_0
      31: getfield      #20                 // Field optionSet:Ljava/util/List;
      34: aload_1
      35: invokeinterface #42,  2           // InterfaceMethod java/util/List.add:(Ljava/lang/Object;)Z
      40: pop
      41: aload_0
      42: getfield      #20                 // Field optionSet:Ljava/util/List;
      45: aload_2
      46: invokeinterface #42,  2           // InterfaceMethod java/util/List.add:(Ljava/lang/Object;)Z
      51: pop
      52: aload_0
      53: areturn

  public org.xnio.Option$SetBuilder add(org.xnio.Option<?>, org.xnio.Option<?>, org.xnio.Option<?>);
    Code:
       0: aload_1
       1: ifnonnull     15
       4: getstatic     #31                 // Field org/xnio/_private/Messages.msg:Lorg/xnio/_private/Messages;
       7: ldc           #48                 // String option1
       9: invokeinterface #37,  2           // InterfaceMethod org/xnio/_private/Messages.nullParameter:(Ljava/lang/String;)Ljava/lang/IllegalArgumentException;
      14: athrow
      15: aload_2
      16: ifnonnull     30
      19: getstatic     #31                 // Field org/xnio/_private/Messages.msg:Lorg/xnio/_private/Messages;
      22: ldc           #50                 // String option2
      24: invokeinterface #37,  2           // InterfaceMethod org/xnio/_private/Messages.nullParameter:(Ljava/lang/String;)Ljava/lang/IllegalArgumentException;
      29: athrow
      30: aload_3
      31: ifnonnull     45
      34: getstatic     #31                 // Field org/xnio/_private/Messages.msg:Lorg/xnio/_private/Messages;
      37: ldc           #54                 // String option3
      39: invokeinterface #37,  2           // InterfaceMethod org/xnio/_private/Messages.nullParameter:(Ljava/lang/String;)Ljava/lang/IllegalArgumentException;
      44: athrow
      45: aload_0
      46: getfield      #20                 // Field optionSet:Ljava/util/List;
      49: aload_1
      50: invokeinterface #42,  2           // InterfaceMethod java/util/List.add:(Ljava/lang/Object;)Z
      55: pop
      56: aload_0
      57: getfield      #20                 // Field optionSet:Ljava/util/List;
      60: aload_2
      61: invokeinterface #42,  2           // InterfaceMethod java/util/List.add:(Ljava/lang/Object;)Z
      66: pop
      67: aload_0
      68: getfield      #20                 // Field optionSet:Ljava/util/List;
      71: aload_3
      72: invokeinterface #42,  2           // InterfaceMethod java/util/List.add:(Ljava/lang/Object;)Z
      77: pop
      78: aload_0
      79: areturn

  public org.xnio.Option$SetBuilder add(org.xnio.Option<?>...);
    Code:
       0: aload_1
       1: ifnonnull     15
       4: getstatic     #31                 // Field org/xnio/_private/Messages.msg:Lorg/xnio/_private/Messages;
       7: ldc           #58                 // String options
       9: invokeinterface #37,  2           // InterfaceMethod org/xnio/_private/Messages.nullParameter:(Ljava/lang/String;)Ljava/lang/IllegalArgumentException;
      14: athrow
      15: aload_1
      16: astore_2
      17: aload_2
      18: arraylength
      19: istore_3
      20: iconst_0
      21: istore        4
      23: iload         4
      25: iload_3
      26: if_icmpge     48
      29: aload_2
      30: iload         4
      32: aaload
      33: astore        5
      35: aload_0
      36: aload         5
      38: invokevirtual #62                 // Method add:(Lorg/xnio/Option;)Lorg/xnio/Option$SetBuilder;
      41: pop
      42: iinc          4, 1
      45: goto          23
      48: aload_0
      49: areturn

  public org.xnio.Option$SetBuilder addAll(java.util.Collection<org.xnio.Option<?>>);
    Code:
       0: aload_1
       1: ifnonnull     15
       4: getstatic     #31                 // Field org/xnio/_private/Messages.msg:Lorg/xnio/_private/Messages;
       7: ldc           #33                 // String option
       9: invokeinterface #37,  2           // InterfaceMethod org/xnio/_private/Messages.nullParameter:(Ljava/lang/String;)Ljava/lang/IllegalArgumentException;
      14: athrow
      15: aload_1
      16: invokeinterface #72,  1           // InterfaceMethod java/util/Collection.iterator:()Ljava/util/Iterator;
      21: astore_2
      22: aload_2
      23: invokeinterface #78,  1           // InterfaceMethod java/util/Iterator.hasNext:()Z
      28: ifeq          50
      31: aload_2
      32: invokeinterface #82,  1           // InterfaceMethod java/util/Iterator.next:()Ljava/lang/Object;
      37: checkcast     #7                  // class org/xnio/Option
      40: astore_3
      41: aload_0
      42: aload_3
      43: invokevirtual #62                 // Method add:(Lorg/xnio/Option;)Lorg/xnio/Option$SetBuilder;
      46: pop
      47: goto          22
      50: aload_0
      51: areturn

  public java.util.Set<org.xnio.Option<?>> create();
    Code:
       0: new           #89                 // class java/util/LinkedHashSet
       3: dup
       4: aload_0
       5: getfield      #20                 // Field optionSet:Ljava/util/List;
       8: invokespecial #92                 // Method java/util/LinkedHashSet."<init>":(Ljava/util/Collection;)V
      11: invokestatic  #98                 // Method java/util/Collections.unmodifiableSet:(Ljava/util/Set;)Ljava/util/Set;
      14: areturn
}
