Compiled from "Xnio.java"
final class org.xnio.Xnio$MBeanHolder$1 implements java.security.PrivilegedAction<javax.management.MBeanServer> {
  org.xnio.Xnio$MBeanHolder$1();
    Code:
       0: aload_0
       1: invokespecial #17                 // Method java/lang/Object."<init>":()V
       4: return

  public javax.management.MBeanServer run();
    Code:
       0: invokestatic  #26                 // Method java/lang/management/ManagementFactory.getPlatformMBeanServer:()Ljavax/management/MBeanServer;
       3: areturn

  public java.lang.Object run();
    Code:
       0: aload_0
       1: invokevirtual #29                 // Method run:()Ljavax/management/MBeanServer;
       4: areturn
}
