Compiled from "XnioWorker.java"
class org.xnio.XnioWorker$3 implements java.security.PrivilegedAction<java.lang.Object> {
  final org.xnio.XnioWorker this$0;

  org.xnio.XnioWorker$3(org.xnio.XnioWorker);
    Code:
       0: aload_0
       1: aload_1
       2: putfield      #22                 // Field this$0:Lorg/xnio/XnioWorker;
       5: aload_0
       6: invokespecial #24                 // Method java/lang/Object."<init>":()V
       9: return

  public java.lang.Object run();
    Code:
       0: aload_0
       1: getfield      #22                 // Field this$0:Lorg/xnio/XnioWorker;
       4: invokestatic  #32                 // Method org/xnio/XnioWorker.access$200:(Lorg/xnio/XnioWorker;)Lorg/xnio/XnioWorker$TaskPool;
       7: invokeinterface #35,  1           // InterfaceMethod org/xnio/XnioWorker$TaskPool.shutdown:()V
      12: aconst_null
      13: areturn
}
