Compiled from "CreateRuleResponse.scala"
public final class zio.aws.rbin.model.CreateRuleResponse$ implements scala.Serializable {
  public static zio.aws.rbin.model.CreateRuleResponse$ MODULE$;

  private zio.aws.core.BuilderHelper<software.amazon.awssdk.services.rbin.model.CreateRuleResponse> zio$aws$rbin$model$CreateRuleResponse$$zioAwsBuilderHelper;

  private volatile boolean bitmap$0;

  public static {};
    Code:
       0: new           #2                  // class zio/aws/rbin/model/CreateRuleResponse$
       3: invokespecial #27                 // Method "<init>":()V
       6: return

  public scala.Option<java.lang.String> $lessinit$greater$default$1();
    Code:
       0: getstatic     #35                 // Field scala/None$.MODULE$:Lscala/None$;
       3: areturn

  public scala.Option<zio.aws.rbin.model.RetentionPeriod> $lessinit$greater$default$2();
    Code:
       0: getstatic     #35                 // Field scala/None$.MODULE$:Lscala/None$;
       3: areturn

  public scala.Option<java.lang.String> $lessinit$greater$default$3();
    Code:
       0: getstatic     #35                 // Field scala/None$.MODULE$:Lscala/None$;
       3: areturn

  public scala.Option<scala.collection.Iterable<zio.aws.rbin.model.Tag>> $lessinit$greater$default$4();
    Code:
       0: getstatic     #35                 // Field scala/None$.MODULE$:Lscala/None$;
       3: areturn

  public scala.Option<zio.aws.rbin.model.ResourceType> $lessinit$greater$default$5();
    Code:
       0: getstatic     #35                 // Field scala/None$.MODULE$:Lscala/None$;
       3: areturn

  public scala.Option<scala.collection.Iterable<zio.aws.rbin.model.ResourceTag>> $lessinit$greater$default$6();
    Code:
       0: getstatic     #35                 // Field scala/None$.MODULE$:Lscala/None$;
       3: areturn

  public scala.Option<zio.aws.rbin.model.RuleStatus> $lessinit$greater$default$7();
    Code:
       0: getstatic     #35                 // Field scala/None$.MODULE$:Lscala/None$;
       3: areturn

  private zio.aws.core.BuilderHelper<software.amazon.awssdk.services.rbin.model.CreateRuleResponse> zioAwsBuilderHelper$lzycompute();
    Code:
       0: aload_0
       1: dup
       2: astore_1
       3: monitorenter
       4: aload_0
       5: getfield      #52                 // Field bitmap$0:Z
       8: ifne          26
      11: aload_0
      12: getstatic     #57                 // Field zio/aws/core/BuilderHelper$.MODULE$:Lzio/aws/core/BuilderHelper$;
      15: invokevirtual #60                 // Method zio/aws/core/BuilderHelper$.apply:()Lzio/aws/core/BuilderHelper;
      18: putfield      #62                 // Field zio$aws$rbin$model$CreateRuleResponse$$zioAwsBuilderHelper:Lzio/aws/core/BuilderHelper;
      21: aload_0
      22: iconst_1
      23: putfield      #52                 // Field bitmap$0:Z
      26: aload_1
      27: monitorexit
      28: goto          34
      31: aload_1
      32: monitorexit
      33: athrow
      34: aload_0
      35: getfield      #62                 // Field zio$aws$rbin$model$CreateRuleResponse$$zioAwsBuilderHelper:Lzio/aws/core/BuilderHelper;
      38: areturn
    Exception table:
       from    to  target type
           4    26    31   any

  public zio.aws.core.BuilderHelper<software.amazon.awssdk.services.rbin.model.CreateRuleResponse> zio$aws$rbin$model$CreateRuleResponse$$zioAwsBuilderHelper();
    Code:
       0: aload_0
       1: getfield      #52                 // Field bitmap$0:Z
       4: ifne          14
       7: aload_0
       8: invokespecial #66                 // Method zioAwsBuilderHelper$lzycompute:()Lzio/aws/core/BuilderHelper;
      11: goto          18
      14: aload_0
      15: getfield      #62                 // Field zio$aws$rbin$model$CreateRuleResponse$$zioAwsBuilderHelper:Lzio/aws/core/BuilderHelper;
      18: areturn

  public zio.aws.rbin.model.CreateRuleResponse$ReadOnly wrap(software.amazon.awssdk.services.rbin.model.CreateRuleResponse);
    Code:
       0: new           #14                 // class zio/aws/rbin/model/CreateRuleResponse$Wrapper
       3: dup
       4: aload_1
       5: invokespecial #74                 // Method zio/aws/rbin/model/CreateRuleResponse$Wrapper."<init>":(Lsoftware/amazon/awssdk/services/rbin/model/CreateRuleResponse;)V
       8: areturn

  public zio.aws.rbin.model.CreateRuleResponse apply(scala.Option<java.lang.String>, scala.Option<zio.aws.rbin.model.RetentionPeriod>, scala.Option<java.lang.String>, scala.Option<scala.collection.Iterable<zio.aws.rbin.model.Tag>>, scala.Option<zio.aws.rbin.model.ResourceType>, scala.Option<scala.collection.Iterable<zio.aws.rbin.model.ResourceTag>>, scala.Option<zio.aws.rbin.model.RuleStatus>);
    Code:
       0: new           #11                 // class zio/aws/rbin/model/CreateRuleResponse
       3: dup
       4: aload_1
       5: aload_2
       6: aload_3
       7: aload         4
       9: aload         5
      11: aload         6
      13: aload         7
      15: invokespecial #87                 // Method zio/aws/rbin/model/CreateRuleResponse."<init>":(Lscala/Option;Lscala/Option;Lscala/Option;Lscala/Option;Lscala/Option;Lscala/Option;Lscala/Option;)V
      18: areturn

  public scala.Option<java.lang.String> apply$default$1();
    Code:
       0: getstatic     #35                 // Field scala/None$.MODULE$:Lscala/None$;
       3: areturn

  public scala.Option<zio.aws.rbin.model.RetentionPeriod> apply$default$2();
    Code:
       0: getstatic     #35                 // Field scala/None$.MODULE$:Lscala/None$;
       3: areturn

  public scala.Option<java.lang.String> apply$default$3();
    Code:
       0: getstatic     #35                 // Field scala/None$.MODULE$:Lscala/None$;
       3: areturn

  public scala.Option<scala.collection.Iterable<zio.aws.rbin.model.Tag>> apply$default$4();
    Code:
       0: getstatic     #35                 // Field scala/None$.MODULE$:Lscala/None$;
       3: areturn

  public scala.Option<zio.aws.rbin.model.ResourceType> apply$default$5();
    Code:
       0: getstatic     #35                 // Field scala/None$.MODULE$:Lscala/None$;
       3: areturn

  public scala.Option<scala.collection.Iterable<zio.aws.rbin.model.ResourceTag>> apply$default$6();
    Code:
       0: getstatic     #35                 // Field scala/None$.MODULE$:Lscala/None$;
       3: areturn

  public scala.Option<zio.aws.rbin.model.RuleStatus> apply$default$7();
    Code:
       0: getstatic     #35                 // Field scala/None$.MODULE$:Lscala/None$;
       3: areturn

  public scala.Option<scala.Tuple7<scala.Option<java.lang.String>, scala.Option<zio.aws.rbin.model.RetentionPeriod>, scala.Option<java.lang.String>, scala.Option<scala.collection.Iterable<zio.aws.rbin.model.Tag>>, scala.Option<zio.aws.rbin.model.ResourceType>, scala.Option<scala.collection.Iterable<zio.aws.rbin.model.ResourceTag>>, scala.Option<zio.aws.rbin.model.RuleStatus>>> unapply(zio.aws.rbin.model.CreateRuleResponse);
    Code:
       0: aload_1
       1: ifnonnull     10
       4: getstatic     #35                 // Field scala/None$.MODULE$:Lscala/None$;
       7: goto          52
      10: new           #101                // class scala/Some
      13: dup
      14: new           #103                // class scala/Tuple7
      17: dup
      18: aload_1
      19: invokevirtual #105                // Method zio/aws/rbin/model/CreateRuleResponse.identifier:()Lscala/Option;
      22: aload_1
      23: invokevirtual #107                // Method zio/aws/rbin/model/CreateRuleResponse.retentionPeriod:()Lscala/Option;
      26: aload_1
      27: invokevirtual #109                // Method zio/aws/rbin/model/CreateRuleResponse.description:()Lscala/Option;
      30: aload_1
      31: invokevirtual #111                // Method zio/aws/rbin/model/CreateRuleResponse.tags:()Lscala/Option;
      34: aload_1
      35: invokevirtual #113                // Method zio/aws/rbin/model/CreateRuleResponse.resourceType:()Lscala/Option;
      38: aload_1
      39: invokevirtual #115                // Method zio/aws/rbin/model/CreateRuleResponse.resourceTags:()Lscala/Option;
      42: aload_1
      43: invokevirtual #117                // Method zio/aws/rbin/model/CreateRuleResponse.status:()Lscala/Option;
      46: invokespecial #120                // Method scala/Tuple7."<init>":(Ljava/lang/Object;Ljava/lang/Object;Ljava/lang/Object;Ljava/lang/Object;Ljava/lang/Object;Ljava/lang/Object;Ljava/lang/Object;)V
      49: invokespecial #123                // Method scala/Some."<init>":(Ljava/lang/Object;)V
      52: areturn

  private java.lang.Object readResolve();
    Code:
       0: getstatic     #130                // Field MODULE$:Lzio/aws/rbin/model/CreateRuleResponse$;
       3: areturn

  private zio.aws.rbin.model.CreateRuleResponse$();
    Code:
       0: aload_0
       1: invokespecial #131                // Method java/lang/Object."<init>":()V
       4: aload_0
       5: putstatic     #130                // Field MODULE$:Lzio/aws/rbin/model/CreateRuleResponse$;
       8: return
}
