Compiled from "TagResourceResponse.scala"
public final class zio.aws.rbin.model.TagResourceResponse$Wrapper implements zio.aws.rbin.model.TagResourceResponse$ReadOnly {
  public zio.aws.rbin.model.TagResourceResponse asEditable();
    Code:
       0: aload_0
       1: invokestatic  #17                 // InterfaceMethod zio/aws/rbin/model/TagResourceResponse$ReadOnly.asEditable$:(Lzio/aws/rbin/model/TagResourceResponse$ReadOnly;)Lzio/aws/rbin/model/TagResourceResponse;
       4: areturn

  public zio.aws.rbin.model.TagResourceResponse$Wrapper(software.amazon.awssdk.services.rbin.model.TagResourceResponse);
    Code:
       0: aload_0
       1: invokespecial #25                 // Method java/lang/Object."<init>":()V
       4: aload_0
       5: invokestatic  #29                 // InterfaceMethod zio/aws/rbin/model/TagResourceResponse$ReadOnly.$init$:(Lzio/aws/rbin/model/TagResourceResponse$ReadOnly;)V
       8: return
}
