public class org.bouncycastle.crypto.digests.Kangaroo$KangarooParameters implements org.bouncycastle.crypto.CipherParameters {
  private byte[] thePersonal;

  private long theMaxXofLen;

  public org.bouncycastle.crypto.digests.Kangaroo$KangarooParameters();
    Code:
       0: aload_0
       1: invokespecial #35                 // Method java/lang/Object."<init>":()V
       4: return

  public byte[] getPersonalisation();
    Code:
       0: aload_0
       1: getfield      #34                 // Field thePersonal:[B
       4: invokestatic  #36                 // Method org/bouncycastle/util/Arrays.clone:([B)[B
       7: areturn

  public long getMaxOutputLength();
    Code:
       0: aload_0
       1: getfield      #33                 // Field theMaxXofLen:J
       4: lreturn

  static byte[] access$002(org.bouncycastle.crypto.digests.Kangaroo$KangarooParameters, byte[]);
    Code:
       0: aload_0
       1: aload_1
       2: dup_x1
       3: putfield      #34                 // Field thePersonal:[B
       6: areturn

  static long access$102(org.bouncycastle.crypto.digests.Kangaroo$KangarooParameters, long);
    Code:
       0: aload_0
       1: lload_1
       2: dup2_x1
       3: putfield      #33                 // Field theMaxXofLen:J
       6: lreturn
}
