Compiled from "OperationStatus.scala"
public final class zio.aws.servicediscovery.model.OperationStatus$unknownToSdkVersion$ implements zio.aws.servicediscovery.model.OperationStatus,scala.Product,java.io.Serializable,scala.deriving.Mirror$Singleton {
  public static final zio.aws.servicediscovery.model.OperationStatus$unknownToSdkVersion$ MODULE$;

  public zio.aws.servicediscovery.model.OperationStatus$unknownToSdkVersion$();
    Code:
       0: aload_0
       1: invokespecial #23                 // Method java/lang/Object."<init>":()V
       4: return

  public static {};
    Code:
       0: new           #2                  // class zio/aws/servicediscovery/model/OperationStatus$unknownToSdkVersion$
       3: dup
       4: invokespecial #26                 // Method "<init>":()V
       7: putstatic     #28                 // Field MODULE$:Lzio/aws/servicediscovery/model/OperationStatus$unknownToSdkVersion$;
      10: return

  public scala.collection.Iterator productIterator();
    Code:
       0: aload_0
       1: invokestatic  #34                 // InterfaceMethod scala/Product.productIterator$:(Lscala/Product;)Lscala/collection/Iterator;
       4: areturn

  public scala.collection.Iterator productElementNames();
    Code:
       0: aload_0
       1: invokestatic  #38                 // InterfaceMethod scala/Product.productElementNames$:(Lscala/Product;)Lscala/collection/Iterator;
       4: areturn

  public scala.deriving.Mirror$Singleton fromProduct(scala.Product);
    Code:
       0: aload_0
       1: aload_1
       2: invokestatic  #45                 // InterfaceMethod scala/deriving/Mirror$Singleton.fromProduct$:(Lscala/deriving/Mirror$Singleton;Lscala/Product;)Lscala/deriving/Mirror$Singleton;
       5: areturn

  private java.lang.Object writeReplace();
    Code:
       0: new           #50                 // class scala/runtime/ModuleSerializationProxy
       3: dup
       4: ldc           #2                  // class zio/aws/servicediscovery/model/OperationStatus$unknownToSdkVersion$
       6: invokespecial #53                 // Method scala/runtime/ModuleSerializationProxy."<init>":(Ljava/lang/Class;)V
       9: areturn

  public int hashCode();
    Code:
       0: ldc           #56                 // int -1592929917
       2: ireturn

  public java.lang.String toString();
    Code:
       0: ldc           #60                 // String unknownToSdkVersion
       2: areturn

  public boolean canEqual(java.lang.Object);
    Code:
       0: aload_1
       1: instanceof    #2                  // class zio/aws/servicediscovery/model/OperationStatus$unknownToSdkVersion$
       4: ireturn

  public int productArity();
    Code:
       0: iconst_0
       1: ireturn

  public java.lang.String productPrefix();
    Code:
       0: ldc           #60                 // String unknownToSdkVersion
       2: areturn

  public java.lang.Object productElement(int);
    Code:
       0: iload_1
       1: istore_2
       2: new           #71                 // class java/lang/IndexOutOfBoundsException
       5: dup
       6: iload_1
       7: invokestatic  #77                 // Method scala/runtime/BoxesRunTime.boxToInteger:(I)Ljava/lang/Integer;
      10: invokevirtual #81                 // Method java/lang/Integer.toString:()Ljava/lang/String;
      13: invokespecial #84                 // Method java/lang/IndexOutOfBoundsException."<init>":(Ljava/lang/String;)V
      16: athrow

  public java.lang.String productElementName(int);
    Code:
       0: iload_1
       1: istore_2
       2: new           #71                 // class java/lang/IndexOutOfBoundsException
       5: dup
       6: iload_1
       7: invokestatic  #77                 // Method scala/runtime/BoxesRunTime.boxToInteger:(I)Ljava/lang/Integer;
      10: invokevirtual #81                 // Method java/lang/Integer.toString:()Ljava/lang/String;
      13: invokespecial #84                 // Method java/lang/IndexOutOfBoundsException."<init>":(Ljava/lang/String;)V
      16: athrow

  public software.amazon.awssdk.services.servicediscovery.model.OperationStatus unwrap();
    Code:
       0: getstatic     #95                 // Field software/amazon/awssdk/services/servicediscovery/model/OperationStatus.UNKNOWN_TO_SDK_VERSION:Lsoftware/amazon/awssdk/services/servicediscovery/model/OperationStatus;
       3: areturn

  public java.lang.Object fromProduct(scala.Product);
    Code:
       0: aload_0
       1: aload_1
       2: invokevirtual #98                 // Method fromProduct:(Lscala/Product;)Lscala/deriving/Mirror$Singleton;
       5: areturn
}
