Compiled from "package.scala"
public final class zio.aws.servicediscovery.model.package$primitives$Message$ extends zio.prelude.Subtype<java.lang.String> {
  public static final zio.aws.servicediscovery.model.package$primitives$Message$ MODULE$;

  public zio.aws.servicediscovery.model.package$primitives$Message$();
    Code:
       0: aload_0
       1: invokespecial #20                 // Method zio/prelude/Subtype."<init>":()V
       4: return

  public static {};
    Code:
       0: new           #2                  // class zio/aws/servicediscovery/model/package$primitives$Message$
       3: dup
       4: invokespecial #23                 // Method "<init>":()V
       7: putstatic     #25                 // Field MODULE$:Lzio/aws/servicediscovery/model/package$primitives$Message$;
      10: return

  private java.lang.Object writeReplace();
    Code:
       0: new           #29                 // class scala/runtime/ModuleSerializationProxy
       3: dup
       4: ldc           #2                  // class zio/aws/servicediscovery/model/package$primitives$Message$
       6: invokespecial #32                 // Method scala/runtime/ModuleSerializationProxy."<init>":(Ljava/lang/Class;)V
       9: areturn
}
