Compiled from "Service.scala"
public final class zio.aws.servicediscovery.model.Service$Wrapper implements zio.aws.servicediscovery.model.Service$ReadOnly {
  private final zio.prelude.data.Optional id;

  private final zio.prelude.data.Optional arn;

  private final zio.prelude.data.Optional name;

  private final zio.prelude.data.Optional namespaceId;

  private final zio.prelude.data.Optional description;

  private final zio.prelude.data.Optional instanceCount;

  private final zio.prelude.data.Optional dnsConfig;

  private final zio.prelude.data.Optional type;

  private final zio.prelude.data.Optional healthCheckConfig;

  private final zio.prelude.data.Optional healthCheckCustomConfig;

  private final zio.prelude.data.Optional createDate;

  private final zio.prelude.data.Optional creatorRequestId;

  public zio.aws.servicediscovery.model.Service$Wrapper(software.amazon.awssdk.services.servicediscovery.model.Service);
    Code:
       0: aload_0
       1: invokespecial #65                 // Method java/lang/Object."<init>":()V
       4: aload_0
       5: getstatic     #71                 // Field zio/aws/core/internal/package$.MODULE$:Lzio/aws/core/internal/package$;
       8: aload_1
       9: invokevirtual #76                 // Method software/amazon/awssdk/services/servicediscovery/model/Service.id:()Ljava/lang/String;
      12: invokevirtual #80                 // Method zio/aws/core/internal/package$.optionalFromNullable:(Ljava/lang/Object;)Lzio/prelude/data/Optional;
      15: aload_0
      16: invokedynamic #101,  0            // InvokeDynamic #0:apply:(Lzio/aws/servicediscovery/model/Service$Wrapper;)Lscala/Function1;
      21: invokeinterface #107,  2          // InterfaceMethod zio/prelude/data/Optional.map:(Lscala/Function1;)Lzio/prelude/data/Optional;
      26: putfield      #109                // Field id:Lzio/prelude/data/Optional;
      29: aload_0
      30: getstatic     #71                 // Field zio/aws/core/internal/package$.MODULE$:Lzio/aws/core/internal/package$;
      33: aload_1
      34: invokevirtual #111                // Method software/amazon/awssdk/services/servicediscovery/model/Service.arn:()Ljava/lang/String;
      37: invokevirtual #80                 // Method zio/aws/core/internal/package$.optionalFromNullable:(Ljava/lang/Object;)Lzio/prelude/data/Optional;
      40: aload_0
      41: invokedynamic #116,  0            // InvokeDynamic #1:apply:(Lzio/aws/servicediscovery/model/Service$Wrapper;)Lscala/Function1;
      46: invokeinterface #107,  2          // InterfaceMethod zio/prelude/data/Optional.map:(Lscala/Function1;)Lzio/prelude/data/Optional;
      51: putfield      #118                // Field arn:Lzio/prelude/data/Optional;
      54: aload_0
      55: getstatic     #71                 // Field zio/aws/core/internal/package$.MODULE$:Lzio/aws/core/internal/package$;
      58: aload_1
      59: invokevirtual #120                // Method software/amazon/awssdk/services/servicediscovery/model/Service.name:()Ljava/lang/String;
      62: invokevirtual #80                 // Method zio/aws/core/internal/package$.optionalFromNullable:(Ljava/lang/Object;)Lzio/prelude/data/Optional;
      65: aload_0
      66: invokedynamic #125,  0            // InvokeDynamic #2:apply:(Lzio/aws/servicediscovery/model/Service$Wrapper;)Lscala/Function1;
      71: invokeinterface #107,  2          // InterfaceMethod zio/prelude/data/Optional.map:(Lscala/Function1;)Lzio/prelude/data/Optional;
      76: putfield      #127                // Field name:Lzio/prelude/data/Optional;
      79: aload_0
      80: getstatic     #71                 // Field zio/aws/core/internal/package$.MODULE$:Lzio/aws/core/internal/package$;
      83: aload_1
      84: invokevirtual #129                // Method software/amazon/awssdk/services/servicediscovery/model/Service.namespaceId:()Ljava/lang/String;
      87: invokevirtual #80                 // Method zio/aws/core/internal/package$.optionalFromNullable:(Ljava/lang/Object;)Lzio/prelude/data/Optional;
      90: aload_0
      91: invokedynamic #134,  0            // InvokeDynamic #3:apply:(Lzio/aws/servicediscovery/model/Service$Wrapper;)Lscala/Function1;
      96: invokeinterface #107,  2          // InterfaceMethod zio/prelude/data/Optional.map:(Lscala/Function1;)Lzio/prelude/data/Optional;
     101: putfield      #136                // Field namespaceId:Lzio/prelude/data/Optional;
     104: aload_0
     105: getstatic     #71                 // Field zio/aws/core/internal/package$.MODULE$:Lzio/aws/core/internal/package$;
     108: aload_1
     109: invokevirtual #138                // Method software/amazon/awssdk/services/servicediscovery/model/Service.description:()Ljava/lang/String;
     112: invokevirtual #80                 // Method zio/aws/core/internal/package$.optionalFromNullable:(Ljava/lang/Object;)Lzio/prelude/data/Optional;
     115: aload_0
     116: invokedynamic #143,  0            // InvokeDynamic #4:apply:(Lzio/aws/servicediscovery/model/Service$Wrapper;)Lscala/Function1;
     121: invokeinterface #107,  2          // InterfaceMethod zio/prelude/data/Optional.map:(Lscala/Function1;)Lzio/prelude/data/Optional;
     126: putfield      #145                // Field description:Lzio/prelude/data/Optional;
     129: aload_0
     130: getstatic     #71                 // Field zio/aws/core/internal/package$.MODULE$:Lzio/aws/core/internal/package$;
     133: aload_1
     134: invokevirtual #148                // Method software/amazon/awssdk/services/servicediscovery/model/Service.instanceCount:()Ljava/lang/Integer;
     137: invokevirtual #80                 // Method zio/aws/core/internal/package$.optionalFromNullable:(Ljava/lang/Object;)Lzio/prelude/data/Optional;
     140: aload_0
     141: invokedynamic #155,  0            // InvokeDynamic #5:apply:(Lzio/aws/servicediscovery/model/Service$Wrapper;)Lscala/Function1;
     146: invokeinterface #107,  2          // InterfaceMethod zio/prelude/data/Optional.map:(Lscala/Function1;)Lzio/prelude/data/Optional;
     151: putfield      #157                // Field instanceCount:Lzio/prelude/data/Optional;
     154: aload_0
     155: getstatic     #71                 // Field zio/aws/core/internal/package$.MODULE$:Lzio/aws/core/internal/package$;
     158: aload_1
     159: invokevirtual #160                // Method software/amazon/awssdk/services/servicediscovery/model/Service.dnsConfig:()Lsoftware/amazon/awssdk/services/servicediscovery/model/DnsConfig;
     162: invokevirtual #80                 // Method zio/aws/core/internal/package$.optionalFromNullable:(Ljava/lang/Object;)Lzio/prelude/data/Optional;
     165: aload_0
     166: invokedynamic #167,  0            // InvokeDynamic #6:apply:(Lzio/aws/servicediscovery/model/Service$Wrapper;)Lscala/Function1;
     171: invokeinterface #107,  2          // InterfaceMethod zio/prelude/data/Optional.map:(Lscala/Function1;)Lzio/prelude/data/Optional;
     176: putfield      #169                // Field dnsConfig:Lzio/prelude/data/Optional;
     179: aload_0
     180: getstatic     #71                 // Field zio/aws/core/internal/package$.MODULE$:Lzio/aws/core/internal/package$;
     183: aload_1
     184: invokevirtual #172                // Method software/amazon/awssdk/services/servicediscovery/model/Service.type:()Lsoftware/amazon/awssdk/services/servicediscovery/model/ServiceType;
     187: invokevirtual #80                 // Method zio/aws/core/internal/package$.optionalFromNullable:(Ljava/lang/Object;)Lzio/prelude/data/Optional;
     190: aload_0
     191: invokedynamic #179,  0            // InvokeDynamic #7:apply:(Lzio/aws/servicediscovery/model/Service$Wrapper;)Lscala/Function1;
     196: invokeinterface #107,  2          // InterfaceMethod zio/prelude/data/Optional.map:(Lscala/Function1;)Lzio/prelude/data/Optional;
     201: putfield      #181                // Field type:Lzio/prelude/data/Optional;
     204: aload_0
     205: getstatic     #71                 // Field zio/aws/core/internal/package$.MODULE$:Lzio/aws/core/internal/package$;
     208: aload_1
     209: invokevirtual #184                // Method software/amazon/awssdk/services/servicediscovery/model/Service.healthCheckConfig:()Lsoftware/amazon/awssdk/services/servicediscovery/model/HealthCheckConfig;
     212: invokevirtual #80                 // Method zio/aws/core/internal/package$.optionalFromNullable:(Ljava/lang/Object;)Lzio/prelude/data/Optional;
     215: aload_0
     216: invokedynamic #191,  0            // InvokeDynamic #8:apply:(Lzio/aws/servicediscovery/model/Service$Wrapper;)Lscala/Function1;
     221: invokeinterface #107,  2          // InterfaceMethod zio/prelude/data/Optional.map:(Lscala/Function1;)Lzio/prelude/data/Optional;
     226: putfield      #193                // Field healthCheckConfig:Lzio/prelude/data/Optional;
     229: aload_0
     230: getstatic     #71                 // Field zio/aws/core/internal/package$.MODULE$:Lzio/aws/core/internal/package$;
     233: aload_1
     234: invokevirtual #196                // Method software/amazon/awssdk/services/servicediscovery/model/Service.healthCheckCustomConfig:()Lsoftware/amazon/awssdk/services/servicediscovery/model/HealthCheckCustomConfig;
     237: invokevirtual #80                 // Method zio/aws/core/internal/package$.optionalFromNullable:(Ljava/lang/Object;)Lzio/prelude/data/Optional;
     240: aload_0
     241: invokedynamic #203,  0            // InvokeDynamic #9:apply:(Lzio/aws/servicediscovery/model/Service$Wrapper;)Lscala/Function1;
     246: invokeinterface #107,  2          // InterfaceMethod zio/prelude/data/Optional.map:(Lscala/Function1;)Lzio/prelude/data/Optional;
     251: putfield      #205                // Field healthCheckCustomConfig:Lzio/prelude/data/Optional;
     254: aload_0
     255: getstatic     #71                 // Field zio/aws/core/internal/package$.MODULE$:Lzio/aws/core/internal/package$;
     258: aload_1
     259: invokevirtual #208                // Method software/amazon/awssdk/services/servicediscovery/model/Service.createDate:()Ljava/time/Instant;
     262: invokevirtual #80                 // Method zio/aws/core/internal/package$.optionalFromNullable:(Ljava/lang/Object;)Lzio/prelude/data/Optional;
     265: aload_0
     266: invokedynamic #215,  0            // InvokeDynamic #10:apply:(Lzio/aws/servicediscovery/model/Service$Wrapper;)Lscala/Function1;
     271: invokeinterface #107,  2          // InterfaceMethod zio/prelude/data/Optional.map:(Lscala/Function1;)Lzio/prelude/data/Optional;
     276: putfield      #217                // Field createDate:Lzio/prelude/data/Optional;
     279: aload_0
     280: getstatic     #71                 // Field zio/aws/core/internal/package$.MODULE$:Lzio/aws/core/internal/package$;
     283: aload_1
     284: invokevirtual #219                // Method software/amazon/awssdk/services/servicediscovery/model/Service.creatorRequestId:()Ljava/lang/String;
     287: invokevirtual #80                 // Method zio/aws/core/internal/package$.optionalFromNullable:(Ljava/lang/Object;)Lzio/prelude/data/Optional;
     290: aload_0
     291: invokedynamic #224,  0            // InvokeDynamic #11:apply:(Lzio/aws/servicediscovery/model/Service$Wrapper;)Lscala/Function1;
     296: invokeinterface #107,  2          // InterfaceMethod zio/prelude/data/Optional.map:(Lscala/Function1;)Lzio/prelude/data/Optional;
     301: putfield      #226                // Field creatorRequestId:Lzio/prelude/data/Optional;
     304: return

  public zio.aws.servicediscovery.model.Service asEditable();
    Code:
       0: aload_0
       1: invokestatic  #235                // InterfaceMethod zio/aws/servicediscovery/model/Service$ReadOnly.asEditable$:(Lzio/aws/servicediscovery/model/Service$ReadOnly;)Lzio/aws/servicediscovery/model/Service;
       4: areturn

  public zio.ZIO getId();
    Code:
       0: aload_0
       1: invokestatic  #241                // InterfaceMethod zio/aws/servicediscovery/model/Service$ReadOnly.getId$:(Lzio/aws/servicediscovery/model/Service$ReadOnly;)Lzio/ZIO;
       4: areturn

  public zio.ZIO getArn();
    Code:
       0: aload_0
       1: invokestatic  #245                // InterfaceMethod zio/aws/servicediscovery/model/Service$ReadOnly.getArn$:(Lzio/aws/servicediscovery/model/Service$ReadOnly;)Lzio/ZIO;
       4: areturn

  public zio.ZIO getName();
    Code:
       0: aload_0
       1: invokestatic  #249                // InterfaceMethod zio/aws/servicediscovery/model/Service$ReadOnly.getName$:(Lzio/aws/servicediscovery/model/Service$ReadOnly;)Lzio/ZIO;
       4: areturn

  public zio.ZIO getNamespaceId();
    Code:
       0: aload_0
       1: invokestatic  #253                // InterfaceMethod zio/aws/servicediscovery/model/Service$ReadOnly.getNamespaceId$:(Lzio/aws/servicediscovery/model/Service$ReadOnly;)Lzio/ZIO;
       4: areturn

  public zio.ZIO getDescription();
    Code:
       0: aload_0
       1: invokestatic  #257                // InterfaceMethod zio/aws/servicediscovery/model/Service$ReadOnly.getDescription$:(Lzio/aws/servicediscovery/model/Service$ReadOnly;)Lzio/ZIO;
       4: areturn

  public zio.ZIO getInstanceCount();
    Code:
       0: aload_0
       1: invokestatic  #261                // InterfaceMethod zio/aws/servicediscovery/model/Service$ReadOnly.getInstanceCount$:(Lzio/aws/servicediscovery/model/Service$ReadOnly;)Lzio/ZIO;
       4: areturn

  public zio.ZIO getDnsConfig();
    Code:
       0: aload_0
       1: invokestatic  #265                // InterfaceMethod zio/aws/servicediscovery/model/Service$ReadOnly.getDnsConfig$:(Lzio/aws/servicediscovery/model/Service$ReadOnly;)Lzio/ZIO;
       4: areturn

  public zio.ZIO getType();
    Code:
       0: aload_0
       1: invokestatic  #269                // InterfaceMethod zio/aws/servicediscovery/model/Service$ReadOnly.getType$:(Lzio/aws/servicediscovery/model/Service$ReadOnly;)Lzio/ZIO;
       4: areturn

  public zio.ZIO getHealthCheckConfig();
    Code:
       0: aload_0
       1: invokestatic  #273                // InterfaceMethod zio/aws/servicediscovery/model/Service$ReadOnly.getHealthCheckConfig$:(Lzio/aws/servicediscovery/model/Service$ReadOnly;)Lzio/ZIO;
       4: areturn

  public zio.ZIO getHealthCheckCustomConfig();
    Code:
       0: aload_0
       1: invokestatic  #277                // InterfaceMethod zio/aws/servicediscovery/model/Service$ReadOnly.getHealthCheckCustomConfig$:(Lzio/aws/servicediscovery/model/Service$ReadOnly;)Lzio/ZIO;
       4: areturn

  public zio.ZIO getCreateDate();
    Code:
       0: aload_0
       1: invokestatic  #281                // InterfaceMethod zio/aws/servicediscovery/model/Service$ReadOnly.getCreateDate$:(Lzio/aws/servicediscovery/model/Service$ReadOnly;)Lzio/ZIO;
       4: areturn

  public zio.ZIO getCreatorRequestId();
    Code:
       0: aload_0
       1: invokestatic  #285                // InterfaceMethod zio/aws/servicediscovery/model/Service$ReadOnly.getCreatorRequestId$:(Lzio/aws/servicediscovery/model/Service$ReadOnly;)Lzio/ZIO;
       4: areturn

  public zio.prelude.data.Optional<java.lang.String> id();
    Code:
       0: aload_0
       1: getfield      #109                // Field id:Lzio/prelude/data/Optional;
       4: areturn

  public zio.prelude.data.Optional<java.lang.String> arn();
    Code:
       0: aload_0
       1: getfield      #118                // Field arn:Lzio/prelude/data/Optional;
       4: areturn

  public zio.prelude.data.Optional<java.lang.String> name();
    Code:
       0: aload_0
       1: getfield      #127                // Field name:Lzio/prelude/data/Optional;
       4: areturn

  public zio.prelude.data.Optional<java.lang.String> namespaceId();
    Code:
       0: aload_0
       1: getfield      #136                // Field namespaceId:Lzio/prelude/data/Optional;
       4: areturn

  public zio.prelude.data.Optional<java.lang.String> description();
    Code:
       0: aload_0
       1: getfield      #145                // Field description:Lzio/prelude/data/Optional;
       4: areturn

  public zio.prelude.data.Optional<java.lang.Object> instanceCount();
    Code:
       0: aload_0
       1: getfield      #157                // Field instanceCount:Lzio/prelude/data/Optional;
       4: areturn

  public zio.prelude.data.Optional<zio.aws.servicediscovery.model.DnsConfig$ReadOnly> dnsConfig();
    Code:
       0: aload_0
       1: getfield      #169                // Field dnsConfig:Lzio/prelude/data/Optional;
       4: areturn

  public zio.prelude.data.Optional<zio.aws.servicediscovery.model.ServiceType> type();
    Code:
       0: aload_0
       1: getfield      #181                // Field type:Lzio/prelude/data/Optional;
       4: areturn

  public zio.prelude.data.Optional<zio.aws.servicediscovery.model.HealthCheckConfig$ReadOnly> healthCheckConfig();
    Code:
       0: aload_0
       1: getfield      #193                // Field healthCheckConfig:Lzio/prelude/data/Optional;
       4: areturn

  public zio.prelude.data.Optional<zio.aws.servicediscovery.model.HealthCheckCustomConfig$ReadOnly> healthCheckCustomConfig();
    Code:
       0: aload_0
       1: getfield      #205                // Field healthCheckCustomConfig:Lzio/prelude/data/Optional;
       4: areturn

  public zio.prelude.data.Optional<java.time.Instant> createDate();
    Code:
       0: aload_0
       1: getfield      #217                // Field createDate:Lzio/prelude/data/Optional;
       4: areturn

  public zio.prelude.data.Optional<java.lang.String> creatorRequestId();
    Code:
       0: aload_0
       1: getfield      #226                // Field creatorRequestId:Lzio/prelude/data/Optional;
       4: areturn

  private final java.lang.String $init$$$anonfun$1(java.lang.String);
    Code:
       0: getstatic     #297                // Field zio/aws/servicediscovery/model/package$primitives$ResourceId$.MODULE$:Lzio/aws/servicediscovery/model/package$primitives$ResourceId$;
       3: astore_2
       4: aload_1
       5: areturn

  private final java.lang.String $init$$$anonfun$2(java.lang.String);
    Code:
       0: getstatic     #302                // Field zio/aws/servicediscovery/model/package$primitives$Arn$.MODULE$:Lzio/aws/servicediscovery/model/package$primitives$Arn$;
       3: astore_2
       4: aload_1
       5: areturn

  private final java.lang.String $init$$$anonfun$3(java.lang.String);
    Code:
       0: getstatic     #305                // Field zio/aws/servicediscovery/model/package$primitives$ServiceName$.MODULE$:Lzio/aws/servicediscovery/model/package$primitives$ServiceName$;
       3: astore_2
       4: aload_1
       5: areturn

  private final java.lang.String $init$$$anonfun$4(java.lang.String);
    Code:
       0: getstatic     #297                // Field zio/aws/servicediscovery/model/package$primitives$ResourceId$.MODULE$:Lzio/aws/servicediscovery/model/package$primitives$ResourceId$;
       3: astore_2
       4: aload_1
       5: areturn

  private final java.lang.String $init$$$anonfun$5(java.lang.String);
    Code:
       0: getstatic     #308                // Field zio/aws/servicediscovery/model/package$primitives$ResourceDescription$.MODULE$:Lzio/aws/servicediscovery/model/package$primitives$ResourceDescription$;
       3: astore_2
       4: aload_1
       5: areturn

  private final int $init$$$anonfun$6(java.lang.Integer);
    Code:
       0: getstatic     #311                // Field zio/aws/servicediscovery/model/package$primitives$ResourceCount$.MODULE$:Lzio/aws/servicediscovery/model/package$primitives$ResourceCount$;
       3: astore_2
       4: getstatic     #316                // Field scala/Predef$.MODULE$:Lscala/Predef$;
       7: aload_1
       8: invokevirtual #319                // Method scala/Predef$.Integer2int:(Ljava/lang/Integer;)I
      11: ireturn

  private final zio.aws.servicediscovery.model.DnsConfig$ReadOnly $init$$$anonfun$7(software.amazon.awssdk.services.servicediscovery.model.DnsConfig);
    Code:
       0: getstatic     #325                // Field zio/aws/servicediscovery/model/DnsConfig$.MODULE$:Lzio/aws/servicediscovery/model/DnsConfig$;
       3: aload_1
       4: invokevirtual #328                // Method zio/aws/servicediscovery/model/DnsConfig$.wrap:(Lsoftware/amazon/awssdk/services/servicediscovery/model/DnsConfig;)Lzio/aws/servicediscovery/model/DnsConfig$ReadOnly;
       7: areturn

  private final zio.aws.servicediscovery.model.ServiceType $init$$$anonfun$8(software.amazon.awssdk.services.servicediscovery.model.ServiceType);
    Code:
       0: getstatic     #334                // Field zio/aws/servicediscovery/model/ServiceType$.MODULE$:Lzio/aws/servicediscovery/model/ServiceType$;
       3: aload_1
       4: invokevirtual #336                // Method zio/aws/servicediscovery/model/ServiceType$.wrap:(Lsoftware/amazon/awssdk/services/servicediscovery/model/ServiceType;)Lzio/aws/servicediscovery/model/ServiceType;
       7: areturn

  private final zio.aws.servicediscovery.model.HealthCheckConfig$ReadOnly $init$$$anonfun$9(software.amazon.awssdk.services.servicediscovery.model.HealthCheckConfig);
    Code:
       0: getstatic     #342                // Field zio/aws/servicediscovery/model/HealthCheckConfig$.MODULE$:Lzio/aws/servicediscovery/model/HealthCheckConfig$;
       3: aload_1
       4: invokevirtual #344                // Method zio/aws/servicediscovery/model/HealthCheckConfig$.wrap:(Lsoftware/amazon/awssdk/services/servicediscovery/model/HealthCheckConfig;)Lzio/aws/servicediscovery/model/HealthCheckConfig$ReadOnly;
       7: areturn

  private final zio.aws.servicediscovery.model.HealthCheckCustomConfig$ReadOnly $init$$$anonfun$10(software.amazon.awssdk.services.servicediscovery.model.HealthCheckCustomConfig);
    Code:
       0: getstatic     #350                // Field zio/aws/servicediscovery/model/HealthCheckCustomConfig$.MODULE$:Lzio/aws/servicediscovery/model/HealthCheckCustomConfig$;
       3: aload_1
       4: invokevirtual #352                // Method zio/aws/servicediscovery/model/HealthCheckCustomConfig$.wrap:(Lsoftware/amazon/awssdk/services/servicediscovery/model/HealthCheckCustomConfig;)Lzio/aws/servicediscovery/model/HealthCheckCustomConfig$ReadOnly;
       7: areturn

  private final java.time.Instant $init$$$anonfun$11(java.time.Instant);
    Code:
       0: getstatic     #356                // Field zio/aws/servicediscovery/model/package$primitives$Timestamp$.MODULE$:Lzio/aws/servicediscovery/model/package$primitives$Timestamp$;
       3: astore_2
       4: aload_1
       5: areturn

  private final java.lang.String $init$$$anonfun$12(java.lang.String);
    Code:
       0: getstatic     #297                // Field zio/aws/servicediscovery/model/package$primitives$ResourceId$.MODULE$:Lzio/aws/servicediscovery/model/package$primitives$ResourceId$;
       3: astore_2
       4: aload_1
       5: areturn

  private static java.lang.Object $deserializeLambda$(java.lang.invoke.SerializedLambda);
    Code:
       0: aload_0
       1: invokedynamic #369,  0            // InvokeDynamic #12:lambdaDeserialize:(Ljava/lang/invoke/SerializedLambda;)Ljava/lang/Object;
       6: areturn
}
