Compiled from "ServiceFilterName.scala"
public interface zio.aws.servicediscovery.model.ServiceFilterName {
  public static int ordinal(zio.aws.servicediscovery.model.ServiceFilterName);
    Code:
       0: getstatic     #19                 // Field zio/aws/servicediscovery/model/ServiceFilterName$.MODULE$:Lzio/aws/servicediscovery/model/ServiceFilterName$;
       3: aload_0
       4: invokevirtual #21                 // Method zio/aws/servicediscovery/model/ServiceFilterName$.ordinal:(Lzio/aws/servicediscovery/model/ServiceFilterName;)I
       7: ireturn

  public static zio.aws.servicediscovery.model.ServiceFilterName wrap(software.amazon.awssdk.services.servicediscovery.model.ServiceFilterName);
    Code:
       0: getstatic     #19                 // Field zio/aws/servicediscovery/model/ServiceFilterName$.MODULE$:Lzio/aws/servicediscovery/model/ServiceFilterName$;
       3: aload_0
       4: invokevirtual #25                 // Method zio/aws/servicediscovery/model/ServiceFilterName$.wrap:(Lsoftware/amazon/awssdk/services/servicediscovery/model/ServiceFilterName;)Lzio/aws/servicediscovery/model/ServiceFilterName;
       7: areturn

  public abstract software.amazon.awssdk.services.servicediscovery.model.ServiceFilterName unwrap();
}
