Compiled from "WebDriverTestContext.java"
class org.openqa.selenium.lift.WebDriverTestContext$2 extends org.openqa.selenium.support.ui.WebDriverWait {
  final long val$timeoutMillis;

  final org.openqa.selenium.lift.WebDriverTestContext this$0;

  org.openqa.selenium.lift.WebDriverTestContext$2(org.openqa.selenium.lift.WebDriverTestContext, org.openqa.selenium.WebDriver, org.openqa.selenium.support.ui.Clock, org.openqa.selenium.support.ui.Sleeper, long, long, long);
    Code:
       0: aload_0
       1: aload_1
       2: putfield      #1                  // Field this$0:Lorg/openqa/selenium/lift/WebDriverTestContext;
       5: aload_0
       6: lload         9
       8: putfield      #2                  // Field val$timeoutMillis:J
      11: aload_0
      12: aload_2
      13: aload_3
      14: aload         4
      16: lload         5
      18: lload         7
      20: invokespecial #3                  // Method org/openqa/selenium/support/ui/WebDriverWait."<init>":(Lorg/openqa/selenium/WebDriver;Lorg/openqa/selenium/support/ui/Clock;Lorg/openqa/selenium/support/ui/Sleeper;JJ)V
      23: return

  protected java.lang.RuntimeException timeoutException(java.lang.String, java.lang.Throwable);
    Code:
       0: new           #4                  // class java/lang/AssertionError
       3: dup
       4: new           #5                  // class java/lang/StringBuilder
       7: dup
       8: invokespecial #6                  // Method java/lang/StringBuilder."<init>":()V
      11: ldc           #7                  // String Element was not rendered within
      13: invokevirtual #8                  // Method java/lang/StringBuilder.append:(Ljava/lang/String;)Ljava/lang/StringBuilder;
      16: aload_0
      17: getfield      #2                  // Field val$timeoutMillis:J
      20: invokevirtual #9                  // Method java/lang/StringBuilder.append:(J)Ljava/lang/StringBuilder;
      23: ldc           #10                 // String ms
      25: invokevirtual #8                  // Method java/lang/StringBuilder.append:(Ljava/lang/String;)Ljava/lang/StringBuilder;
      28: invokevirtual #11                 // Method java/lang/StringBuilder.toString:()Ljava/lang/String;
      31: invokespecial #12                 // Method java/lang/AssertionError."<init>":(Ljava/lang/Object;)V
      34: athrow
}
