Compiled from "DocumentParser.java"
class com.vladsch.flexmark.internal.DocumentParser$CustomBlockParserDependencyHandler extends com.vladsch.flexmark.util.dependency.DependencyHandler<com.vladsch.flexmark.parser.block.CustomBlockParserFactory, com.vladsch.flexmark.internal.DocumentParser$CustomBlockParserDependencyStage, com.vladsch.flexmark.internal.DocumentParser$CustomBlockParserDependencies> {
  private com.vladsch.flexmark.internal.DocumentParser$CustomBlockParserDependencyHandler();
    Code:
       0: aload_0
       1: invokespecial #2                  // Method com/vladsch/flexmark/util/dependency/DependencyHandler."<init>":()V
       4: return

  protected java.lang.Class<? extends com.vladsch.flexmark.parser.block.CustomBlockParserFactory> getDependentClass(com.vladsch.flexmark.parser.block.CustomBlockParserFactory);
    Code:
       0: aload_1
       1: invokevirtual #3                  // Method java/lang/Object.getClass:()Ljava/lang/Class;
       4: areturn

  protected com.vladsch.flexmark.internal.DocumentParser$CustomBlockParserDependencies createResolvedDependencies(java.util.List<com.vladsch.flexmark.internal.DocumentParser$CustomBlockParserDependencyStage>);
    Code:
       0: new           #4                  // class com/vladsch/flexmark/internal/DocumentParser$CustomBlockParserDependencies
       3: dup
       4: aload_1
       5: invokespecial #5                  // Method com/vladsch/flexmark/internal/DocumentParser$CustomBlockParserDependencies."<init>":(Ljava/util/List;)V
       8: areturn

  protected com.vladsch.flexmark.internal.DocumentParser$CustomBlockParserDependencyStage createStage(java.util.List<com.vladsch.flexmark.parser.block.CustomBlockParserFactory>);
    Code:
       0: new           #6                  // class com/vladsch/flexmark/internal/DocumentParser$CustomBlockParserDependencyStage
       3: dup
       4: aload_1
       5: invokespecial #7                  // Method com/vladsch/flexmark/internal/DocumentParser$CustomBlockParserDependencyStage."<init>":(Ljava/util/List;)V
       8: areturn

  protected com.vladsch.flexmark.util.dependency.ResolvedDependencies createResolvedDependencies(java.util.List);
    Code:
       0: aload_0
       1: aload_1
       2: invokevirtual #8                  // Method createResolvedDependencies:(Ljava/util/List;)Lcom/vladsch/flexmark/internal/DocumentParser$CustomBlockParserDependencies;
       5: areturn

  protected java.lang.Class getDependentClass(com.vladsch.flexmark.util.dependency.Dependent);
    Code:
       0: aload_0
       1: aload_1
       2: checkcast     #9                  // class com/vladsch/flexmark/parser/block/CustomBlockParserFactory
       5: invokevirtual #10                 // Method getDependentClass:(Lcom/vladsch/flexmark/parser/block/CustomBlockParserFactory;)Ljava/lang/Class;
       8: areturn

  protected java.lang.Object createStage(java.util.List);
    Code:
       0: aload_0
       1: aload_1
       2: invokevirtual #11                 // Method createStage:(Ljava/util/List;)Lcom/vladsch/flexmark/internal/DocumentParser$CustomBlockParserDependencyStage;
       5: areturn

  com.vladsch.flexmark.internal.DocumentParser$CustomBlockParserDependencyHandler(com.vladsch.flexmark.internal.DocumentParser$1);
    Code:
       0: aload_0
       1: invokespecial #1                  // Method "<init>":()V
       4: return
}
