Compiled from "HtmlDeepParser.java"
public final class com.vladsch.flexmark.internal.HtmlDeepParser$HtmlMatch extends java.lang.Enum<com.vladsch.flexmark.internal.HtmlDeepParser$HtmlMatch> {
  public static final com.vladsch.flexmark.internal.HtmlDeepParser$HtmlMatch NONE;

  public static final com.vladsch.flexmark.internal.HtmlDeepParser$HtmlMatch SCRIPT;

  public static final com.vladsch.flexmark.internal.HtmlDeepParser$HtmlMatch STYLE;

  public static final com.vladsch.flexmark.internal.HtmlDeepParser$HtmlMatch OPEN_TAG;

  public static final com.vladsch.flexmark.internal.HtmlDeepParser$HtmlMatch CLOSE_TAG;

  public static final com.vladsch.flexmark.internal.HtmlDeepParser$HtmlMatch NON_TAG;

  public static final com.vladsch.flexmark.internal.HtmlDeepParser$HtmlMatch TEMPLATE;

  public static final com.vladsch.flexmark.internal.HtmlDeepParser$HtmlMatch COMMENT;

  public static final com.vladsch.flexmark.internal.HtmlDeepParser$HtmlMatch CDATA;

  public final java.util.regex.Pattern open;

  public final java.util.regex.Pattern close;

  public final boolean caseInsentive;

  private static final com.vladsch.flexmark.internal.HtmlDeepParser$HtmlMatch[] $VALUES;

  public static com.vladsch.flexmark.internal.HtmlDeepParser$HtmlMatch[] values();
    Code:
       0: getstatic     #1                  // Field $VALUES:[Lcom/vladsch/flexmark/internal/HtmlDeepParser$HtmlMatch;
       3: invokevirtual #2                  // Method "[Lcom/vladsch/flexmark/internal/HtmlDeepParser$HtmlMatch;".clone:()Ljava/lang/Object;
       6: checkcast     #3                  // class "[Lcom/vladsch/flexmark/internal/HtmlDeepParser$HtmlMatch;"
       9: areturn

  public static com.vladsch.flexmark.internal.HtmlDeepParser$HtmlMatch valueOf(java.lang.String);
    Code:
       0: ldc           #4                  // class com/vladsch/flexmark/internal/HtmlDeepParser$HtmlMatch
       2: aload_0
       3: invokestatic  #5                  // Method java/lang/Enum.valueOf:(Ljava/lang/Class;Ljava/lang/String;)Ljava/lang/Enum;
       6: checkcast     #4                  // class com/vladsch/flexmark/internal/HtmlDeepParser$HtmlMatch
       9: areturn

  private com.vladsch.flexmark.internal.HtmlDeepParser$HtmlMatch(java.lang.String, java.lang.String, boolean);
    Code:
       0: aload_0
       1: aload_1
       2: iload_2
       3: invokespecial #6                  // Method java/lang/Enum."<init>":(Ljava/lang/String;I)V
       6: aload_0
       7: aload_3
       8: ifnonnull     15
      11: aconst_null
      12: goto          29
      15: aload_3
      16: iload         5
      18: ifeq          25
      21: iconst_2
      22: goto          26
      25: iconst_0
      26: invokestatic  #8                  // Method java/util/regex/Pattern.compile:(Ljava/lang/String;I)Ljava/util/regex/Pattern;
      29: putfield      #9                  // Field open:Ljava/util/regex/Pattern;
      32: aload_0
      33: aload         4
      35: ifnonnull     42
      38: aconst_null
      39: goto          57
      42: aload         4
      44: iload         5
      46: ifeq          53
      49: iconst_2
      50: goto          54
      53: iconst_0
      54: invokestatic  #8                  // Method java/util/regex/Pattern.compile:(Ljava/lang/String;I)Ljava/util/regex/Pattern;
      57: putfield      #10                 // Field close:Ljava/util/regex/Pattern;
      60: aload_0
      61: iload         5
      63: putfield      #11                 // Field caseInsentive:Z
      66: return

  static {};
    Code:
       0: new           #4                  // class com/vladsch/flexmark/internal/HtmlDeepParser$HtmlMatch
       3: dup
       4: ldc           #12                 // String NONE
       6: iconst_0
       7: aconst_null
       8: aconst_null
       9: iconst_0
      10: invokespecial #13                 // Method "<init>":(Ljava/lang/String;ILjava/lang/String;Ljava/lang/String;Z)V
      13: putstatic     #14                 // Field NONE:Lcom/vladsch/flexmark/internal/HtmlDeepParser$HtmlMatch;
      16: new           #4                  // class com/vladsch/flexmark/internal/HtmlDeepParser$HtmlMatch
      19: dup
      20: ldc           #15                 // String SCRIPT
      22: iconst_1
      23: ldc           #16                 // String <(script)(?:\\s|>|$)
      25: ldc           #17                 // String </script>
      27: iconst_1
      28: invokespecial #13                 // Method "<init>":(Ljava/lang/String;ILjava/lang/String;Ljava/lang/String;Z)V
      31: putstatic     #18                 // Field SCRIPT:Lcom/vladsch/flexmark/internal/HtmlDeepParser$HtmlMatch;
      34: new           #4                  // class com/vladsch/flexmark/internal/HtmlDeepParser$HtmlMatch
      37: dup
      38: ldc           #19                 // String STYLE
      40: iconst_2
      41: ldc           #20                 // String <(style)(?:\\s|>|$)
      43: ldc           #21                 // String </style>
      45: iconst_1
      46: invokespecial #13                 // Method "<init>":(Ljava/lang/String;ILjava/lang/String;Ljava/lang/String;Z)V
      49: putstatic     #22                 // Field STYLE:Lcom/vladsch/flexmark/internal/HtmlDeepParser$HtmlMatch;
      52: new           #4                  // class com/vladsch/flexmark/internal/HtmlDeepParser$HtmlMatch
      55: dup
      56: ldc           #23                 // String OPEN_TAG
      58: iconst_3
      59: ldc           #24                 // String <([A-Za-z][A-Za-z0-9-]*)
      61: ldc           #25                 // String <|/>|\\s/>|>
      63: iconst_1
      64: invokespecial #13                 // Method "<init>":(Ljava/lang/String;ILjava/lang/String;Ljava/lang/String;Z)V
      67: putstatic     #26                 // Field OPEN_TAG:Lcom/vladsch/flexmark/internal/HtmlDeepParser$HtmlMatch;
      70: new           #4                  // class com/vladsch/flexmark/internal/HtmlDeepParser$HtmlMatch
      73: dup
      74: ldc           #27                 // String CLOSE_TAG
      76: iconst_4
      77: ldc           #28                 // String </([A-Za-z][A-Za-z0-9-]*)>
      79: aconst_null
      80: iconst_1
      81: invokespecial #13                 // Method "<init>":(Ljava/lang/String;ILjava/lang/String;Ljava/lang/String;Z)V
      84: putstatic     #29                 // Field CLOSE_TAG:Lcom/vladsch/flexmark/internal/HtmlDeepParser$HtmlMatch;
      87: new           #4                  // class com/vladsch/flexmark/internal/HtmlDeepParser$HtmlMatch
      90: dup
      91: ldc           #30                 // String NON_TAG
      93: iconst_5
      94: ldc           #31                 // String <(![A-Z])
      96: ldc           #32                 // String >
      98: iconst_0
      99: invokespecial #13                 // Method "<init>":(Ljava/lang/String;ILjava/lang/String;Ljava/lang/String;Z)V
     102: putstatic     #33                 // Field NON_TAG:Lcom/vladsch/flexmark/internal/HtmlDeepParser$HtmlMatch;
     105: new           #4                  // class com/vladsch/flexmark/internal/HtmlDeepParser$HtmlMatch
     108: dup
     109: ldc           #34                 // String TEMPLATE
     111: bipush        6
     113: ldc           #35                 // String <([?])
     115: ldc           #36                 // String \\?>
     117: iconst_0
     118: invokespecial #13                 // Method "<init>":(Ljava/lang/String;ILjava/lang/String;Ljava/lang/String;Z)V
     121: putstatic     #37                 // Field TEMPLATE:Lcom/vladsch/flexmark/internal/HtmlDeepParser$HtmlMatch;
     124: new           #4                  // class com/vladsch/flexmark/internal/HtmlDeepParser$HtmlMatch
     127: dup
     128: ldc           #38                 // String COMMENT
     130: bipush        7
     132: ldc           #39                 // String <(!--)
     134: ldc           #40                 // String -->
     136: iconst_0
     137: invokespecial #13                 // Method "<init>":(Ljava/lang/String;ILjava/lang/String;Ljava/lang/String;Z)V
     140: putstatic     #41                 // Field COMMENT:Lcom/vladsch/flexmark/internal/HtmlDeepParser$HtmlMatch;
     143: new           #4                  // class com/vladsch/flexmark/internal/HtmlDeepParser$HtmlMatch
     146: dup
     147: ldc           #42                 // String CDATA
     149: bipush        8
     151: ldc           #43                 // String <!\\[(CDATA)\\[
     153: ldc           #44                 // String \\]\\]>
     155: iconst_0
     156: invokespecial #13                 // Method "<init>":(Ljava/lang/String;ILjava/lang/String;Ljava/lang/String;Z)V
     159: putstatic     #45                 // Field CDATA:Lcom/vladsch/flexmark/internal/HtmlDeepParser$HtmlMatch;
     162: bipush        9
     164: anewarray     #4                  // class com/vladsch/flexmark/internal/HtmlDeepParser$HtmlMatch
     167: dup
     168: iconst_0
     169: getstatic     #14                 // Field NONE:Lcom/vladsch/flexmark/internal/HtmlDeepParser$HtmlMatch;
     172: aastore
     173: dup
     174: iconst_1
     175: getstatic     #18                 // Field SCRIPT:Lcom/vladsch/flexmark/internal/HtmlDeepParser$HtmlMatch;
     178: aastore
     179: dup
     180: iconst_2
     181: getstatic     #22                 // Field STYLE:Lcom/vladsch/flexmark/internal/HtmlDeepParser$HtmlMatch;
     184: aastore
     185: dup
     186: iconst_3
     187: getstatic     #26                 // Field OPEN_TAG:Lcom/vladsch/flexmark/internal/HtmlDeepParser$HtmlMatch;
     190: aastore
     191: dup
     192: iconst_4
     193: getstatic     #29                 // Field CLOSE_TAG:Lcom/vladsch/flexmark/internal/HtmlDeepParser$HtmlMatch;
     196: aastore
     197: dup
     198: iconst_5
     199: getstatic     #33                 // Field NON_TAG:Lcom/vladsch/flexmark/internal/HtmlDeepParser$HtmlMatch;
     202: aastore
     203: dup
     204: bipush        6
     206: getstatic     #37                 // Field TEMPLATE:Lcom/vladsch/flexmark/internal/HtmlDeepParser$HtmlMatch;
     209: aastore
     210: dup
     211: bipush        7
     213: getstatic     #41                 // Field COMMENT:Lcom/vladsch/flexmark/internal/HtmlDeepParser$HtmlMatch;
     216: aastore
     217: dup
     218: bipush        8
     220: getstatic     #45                 // Field CDATA:Lcom/vladsch/flexmark/internal/HtmlDeepParser$HtmlMatch;
     223: aastore
     224: putstatic     #1                  // Field $VALUES:[Lcom/vladsch/flexmark/internal/HtmlDeepParser$HtmlMatch;
     227: return
}
