Compiled from "InlineParserImpl.java"
class com.vladsch.flexmark.internal.InlineParserImpl$InlineParserExtensionDependencyHandler extends com.vladsch.flexmark.util.dependency.DependencyHandler<com.vladsch.flexmark.parser.InlineParserExtensionFactory, com.vladsch.flexmark.internal.InlineParserImpl$InlineParserDependencyStage, com.vladsch.flexmark.internal.InlineParserImpl$InlineParserExtensionDependencies> {
  com.vladsch.flexmark.internal.InlineParserImpl$InlineParserExtensionDependencyHandler();
    Code:
       0: aload_0
       1: invokespecial #1                  // Method com/vladsch/flexmark/util/dependency/DependencyHandler."<init>":()V
       4: return

  protected java.lang.Class<? extends com.vladsch.flexmark.parser.InlineParserExtensionFactory> getDependentClass(com.vladsch.flexmark.parser.InlineParserExtensionFactory);
    Code:
       0: aload_1
       1: invokevirtual #2                  // Method java/lang/Object.getClass:()Ljava/lang/Class;
       4: areturn

  protected com.vladsch.flexmark.internal.InlineParserImpl$InlineParserExtensionDependencies createResolvedDependencies(java.util.List<com.vladsch.flexmark.internal.InlineParserImpl$InlineParserDependencyStage>);
    Code:
       0: new           #3                  // class com/vladsch/flexmark/internal/InlineParserImpl$InlineParserExtensionDependencies
       3: dup
       4: aload_1
       5: invokespecial #4                  // Method com/vladsch/flexmark/internal/InlineParserImpl$InlineParserExtensionDependencies."<init>":(Ljava/util/List;)V
       8: areturn

  protected com.vladsch.flexmark.internal.InlineParserImpl$InlineParserDependencyStage createStage(java.util.List<com.vladsch.flexmark.parser.InlineParserExtensionFactory>);
    Code:
       0: new           #5                  // class com/vladsch/flexmark/internal/InlineParserImpl$InlineParserDependencyStage
       3: dup
       4: aload_1
       5: invokespecial #6                  // Method com/vladsch/flexmark/internal/InlineParserImpl$InlineParserDependencyStage."<init>":(Ljava/util/List;)V
       8: areturn

  protected com.vladsch.flexmark.util.dependency.ResolvedDependencies createResolvedDependencies(java.util.List);
    Code:
       0: aload_0
       1: aload_1
       2: invokevirtual #7                  // Method createResolvedDependencies:(Ljava/util/List;)Lcom/vladsch/flexmark/internal/InlineParserImpl$InlineParserExtensionDependencies;
       5: areturn

  protected java.lang.Class getDependentClass(com.vladsch.flexmark.util.dependency.Dependent);
    Code:
       0: aload_0
       1: aload_1
       2: checkcast     #8                  // class com/vladsch/flexmark/parser/InlineParserExtensionFactory
       5: invokevirtual #9                  // Method getDependentClass:(Lcom/vladsch/flexmark/parser/InlineParserExtensionFactory;)Ljava/lang/Class;
       8: areturn

  protected java.lang.Object createStage(java.util.List);
    Code:
       0: aload_0
       1: aload_1
       2: invokevirtual #10                 // Method createStage:(Ljava/util/List;)Lcom/vladsch/flexmark/internal/InlineParserImpl$InlineParserDependencyStage;
       5: areturn
}
