Compiled from "ReflectJavaAnnotationArguments.kt"
public final class kotlin.reflect.jvm.internal.structure.ReflectJavaClassObjectAnnotationArgument extends kotlin.reflect.jvm.internal.structure.ReflectJavaAnnotationArgument implements kotlin.reflect.jvm.internal.impl.load.java.structure.JavaClassObjectAnnotationArgument {
  private final java.lang.Class<?> klass;

  public kotlin.reflect.jvm.internal.impl.load.java.structure.JavaType getReferencedType();
    Code:
       0: getstatic     #15                 // Field kotlin/reflect/jvm/internal/structure/ReflectJavaType.Factory:Lkotlin/reflect/jvm/internal/structure/ReflectJavaType$Factory;
       3: aload_0
       4: getfield      #14                 // Field klass:Ljava/lang/Class;
       7: checkcast     #6                  // class java/lang/reflect/Type
      10: invokevirtual #18                 // Method kotlin/reflect/jvm/internal/structure/ReflectJavaType$Factory.create:(Ljava/lang/reflect/Type;)Lkotlin/reflect/jvm/internal/structure/ReflectJavaType;
      13: checkcast     #9                  // class kotlin/reflect/jvm/internal/impl/load/java/structure/JavaType
      16: areturn

  public kotlin.reflect.jvm.internal.structure.ReflectJavaClassObjectAnnotationArgument(kotlin.reflect.jvm.internal.impl.name.Name, java.lang.Class<?>);
    Code:
       0: aload_2
       1: ldc           #5                  // String klass
       3: invokestatic  #16                 // Method kotlin/jvm/internal/Intrinsics.checkParameterIsNotNull:(Ljava/lang/Object;Ljava/lang/String;)V
       6: aload_0
       7: aload_1
       8: invokespecial #17                 // Method kotlin/reflect/jvm/internal/structure/ReflectJavaAnnotationArgument."<init>":(Lkotlin/reflect/jvm/internal/impl/name/Name;)V
      11: aload_0
      12: aload_2
      13: putfield      #14                 // Field klass:Ljava/lang/Class;
      16: return
}
