Compiled from "ReflectJavaConstructor.kt"
public final class kotlin.reflect.jvm.internal.structure.ReflectJavaConstructor extends kotlin.reflect.jvm.internal.structure.ReflectJavaMember implements kotlin.reflect.jvm.internal.impl.load.java.structure.JavaConstructor {
  private final java.lang.reflect.Constructor<?> member;

  public java.util.List<kotlin.reflect.jvm.internal.impl.load.java.structure.JavaValueParameter> getValueParameters();
    Code:
       0: aload_0
       1: invokevirtual #53                 // Method getMember:()Ljava/lang/reflect/Constructor;
       4: invokevirtual #43                 // Method java/lang/reflect/Constructor.getGenericParameterTypes:()[Ljava/lang/reflect/Type;
       7: astore_1
       8: aload_1
       9: dup
      10: ldc           #12                 // String types
      12: invokestatic  #51                 // Method kotlin/jvm/internal/Intrinsics.checkExpressionValueIsNotNull:(Ljava/lang/Object;Ljava/lang/String;)V
      15: astore_2
      16: aload_2
      17: arraylength
      18: ifne          25
      21: iconst_1
      22: goto          26
      25: iconst_0
      26: ifeq          33
      29: invokestatic  #50                 // Method kotlin/collections/CollectionsKt.emptyList:()Ljava/util/List;
      32: areturn
      33: aload_0
      34: invokevirtual #53                 // Method getMember:()Ljava/lang/reflect/Constructor;
      37: invokevirtual #42                 // Method java/lang/reflect/Constructor.getDeclaringClass:()Ljava/lang/Class;
      40: astore_2
      41: aload_2
      42: dup
      43: ldc           #7                  // String klass
      45: invokestatic  #51                 // Method kotlin/jvm/internal/Intrinsics.checkExpressionValueIsNotNull:(Ljava/lang/Object;Ljava/lang/String;)V
      48: invokevirtual #35                 // Method java/lang/Class.getDeclaringClass:()Ljava/lang/Class;
      51: ifnull        89
      54: aload_2
      55: invokevirtual #36                 // Method java/lang/Class.getModifiers:()I
      58: invokestatic  #47                 // Method java/lang/reflect/Modifier.isStatic:(I)Z
      61: ifne          89
      64: aload_1
      65: astore        4
      67: iconst_1
      68: istore        5
      70: aload_1
      71: arraylength
      72: istore        6
      74: aload         4
      76: iload         5
      78: iload         6
      80: invokestatic  #49                 // Method kotlin/collections/ArraysKt.copyOfRange:([Ljava/lang/Object;II)[Ljava/lang/Object;
      83: checkcast     #14                 // class "[Ljava/lang/reflect/Type;"
      86: goto          90
      89: aload_1
      90: astore_3
      91: aload_0
      92: invokevirtual #53                 // Method getMember:()Ljava/lang/reflect/Constructor;
      95: invokevirtual #44                 // Method java/lang/reflect/Constructor.getParameterAnnotations:()[[Ljava/lang/annotation/Annotation;
      98: astore        4
     100: aload         4
     102: checkcast     #13                 // class "[Ljava/lang/Object;"
     105: arraylength
     106: aload_3
     107: arraylength
     108: if_icmpge     144
     111: new           #18                 // class java/lang/IllegalStateException
     114: dup
     115: new           #19                 // class java/lang/StringBuilder
     118: dup
     119: invokespecial #38                 // Method java/lang/StringBuilder."<init>":()V
     122: ldc           #5                  // String Illegal generic signature:
     124: invokevirtual #40                 // Method java/lang/StringBuilder.append:(Ljava/lang/String;)Ljava/lang/StringBuilder;
     127: aload_0
     128: invokevirtual #53                 // Method getMember:()Ljava/lang/reflect/Constructor;
     131: invokevirtual #39                 // Method java/lang/StringBuilder.append:(Ljava/lang/Object;)Ljava/lang/StringBuilder;
     134: invokevirtual #41                 // Method java/lang/StringBuilder.toString:()Ljava/lang/String;
     137: invokespecial #37                 // Method java/lang/IllegalStateException."<init>":(Ljava/lang/String;)V
     140: checkcast     #20                 // class java/lang/Throwable
     143: athrow
     144: aload         4
     146: checkcast     #13                 // class "[Ljava/lang/Object;"
     149: arraylength
     150: aload_3
     151: arraylength
     152: if_icmple     202
     155: aload         4
     157: dup
     158: ldc           #6                  // String annotations
     160: invokestatic  #51                 // Method kotlin/jvm/internal/Intrinsics.checkExpressionValueIsNotNull:(Ljava/lang/Object;Ljava/lang/String;)V
     163: checkcast     #13                 // class "[Ljava/lang/Object;"
     166: astore        6
     168: aload         4
     170: checkcast     #13                 // class "[Ljava/lang/Object;"
     173: arraylength
     174: aload_3
     175: arraylength
     176: isub
     177: istore        7
     179: aload         4
     181: checkcast     #13                 // class "[Ljava/lang/Object;"
     184: arraylength
     185: istore        8
     187: aload         6
     189: iload         7
     191: iload         8
     193: invokestatic  #49                 // Method kotlin/collections/ArraysKt.copyOfRange:([Ljava/lang/Object;II)[Ljava/lang/Object;
     196: checkcast     #16                 // class "[[Ljava/lang/annotation/Annotation;"
     199: goto          204
     202: aload         4
     204: astore        5
     206: aload_0
     207: aload_3
     208: dup
     209: ldc           #11                 // String realTypes
     211: invokestatic  #51                 // Method kotlin/jvm/internal/Intrinsics.checkExpressionValueIsNotNull:(Ljava/lang/Object;Ljava/lang/String;)V
     214: aload         5
     216: dup
     217: ldc           #10                 // String realAnnotations
     219: invokestatic  #51                 // Method kotlin/jvm/internal/Intrinsics.checkExpressionValueIsNotNull:(Ljava/lang/Object;Ljava/lang/String;)V
     222: aload_0
     223: invokevirtual #53                 // Method getMember:()Ljava/lang/reflect/Constructor;
     226: invokevirtual #46                 // Method java/lang/reflect/Constructor.isVarArgs:()Z
     229: invokevirtual #54                 // Method getValueParameters:([Ljava/lang/reflect/Type;[[Ljava/lang/annotation/Annotation;Z)Ljava/util/List;
     232: areturn

  public java.util.List<kotlin.reflect.jvm.internal.structure.ReflectJavaTypeParameter> getTypeParameters();
    Code:
       0: aload_0
       1: invokevirtual #53                 // Method getMember:()Ljava/lang/reflect/Constructor;
       4: invokevirtual #45                 // Method java/lang/reflect/Constructor.getTypeParameters:()[Ljava/lang/reflect/TypeVariable;
       7: dup
       8: ldc           #9                  // String member.typeParameters
      10: invokestatic  #51                 // Method kotlin/jvm/internal/Intrinsics.checkExpressionValueIsNotNull:(Ljava/lang/Object;Ljava/lang/String;)V
      13: astore_1
      14: aload_1
      15: astore_2
      16: new           #24                 // class java/util/ArrayList
      19: dup
      20: aload_1
      21: arraylength
      22: invokespecial #48                 // Method java/util/ArrayList."<init>":(I)V
      25: checkcast     #25                 // class java/util/Collection
      28: astore_3
      29: aload_2
      30: astore        4
      32: aload         4
      34: arraylength
      35: istore        5
      37: iconst_0
      38: istore        6
      40: iload         6
      42: iload         5
      44: if_icmpge     88
      47: aload         4
      49: iload         6
      51: aaload
      52: astore        7
      54: aload_3
      55: aload         7
      57: astore        8
      59: astore        12
      61: new           #33                 // class kotlin/reflect/jvm/internal/structure/ReflectJavaTypeParameter
      64: dup
      65: aload         8
      67: invokespecial #56                 // Method kotlin/reflect/jvm/internal/structure/ReflectJavaTypeParameter."<init>":(Ljava/lang/reflect/TypeVariable;)V
      70: astore        13
      72: aload         12
      74: aload         13
      76: invokeinterface #57,  2           // InterfaceMethod java/util/Collection.add:(Ljava/lang/Object;)Z
      81: pop
      82: iinc          6, 1
      85: goto          40
      88: aload_3
      89: checkcast     #26                 // class java/util/List
      92: areturn

  public java.lang.reflect.Constructor<?> getMember();
    Code:
       0: aload_0
       1: getfield      #34                 // Field member:Ljava/lang/reflect/Constructor;
       4: areturn

  public java.lang.reflect.Member getMember();
    Code:
       0: aload_0
       1: invokevirtual #53                 // Method getMember:()Ljava/lang/reflect/Constructor;
       4: checkcast     #22                 // class java/lang/reflect/Member
       7: areturn

  public kotlin.reflect.jvm.internal.structure.ReflectJavaConstructor(java.lang.reflect.Constructor<?>);
    Code:
       0: aload_1
       1: ldc           #8                  // String member
       3: invokestatic  #52                 // Method kotlin/jvm/internal/Intrinsics.checkParameterIsNotNull:(Ljava/lang/Object;Ljava/lang/String;)V
       6: aload_0
       7: invokespecial #55                 // Method kotlin/reflect/jvm/internal/structure/ReflectJavaMember."<init>":()V
      10: aload_0
      11: aload_1
      12: putfield      #34                 // Field member:Ljava/lang/reflect/Constructor;
      15: return
}
