Compiled from "ValueExtractorManager.java"
public class org.hibernate.validator.internal.engine.valueextraction.ValueExtractorManager {
  public static final java.util.Set<org.hibernate.validator.internal.engine.valueextraction.ValueExtractorDescriptor> SPEC_DEFINED_EXTRACTORS;

  private final java.util.Map<org.hibernate.validator.internal.engine.valueextraction.ValueExtractorDescriptor$Key, org.hibernate.validator.internal.engine.valueextraction.ValueExtractorDescriptor> registeredValueExtractors;

  private final org.hibernate.validator.internal.engine.valueextraction.ValueExtractorResolver valueExtractorResolver;

  public org.hibernate.validator.internal.engine.valueextraction.ValueExtractorManager(java.util.Set<javax.validation.valueextraction.ValueExtractor<?>>);
    Code:
       0: aload_0
       1: invokespecial #1                  // Method java/lang/Object."<init>":()V
       4: new           #2                  // class java/util/LinkedHashMap
       7: dup
       8: invokespecial #3                  // Method java/util/LinkedHashMap."<init>":()V
      11: astore_2
      12: getstatic     #4                  // Field SPEC_DEFINED_EXTRACTORS:Ljava/util/Set;
      15: invokeinterface #5,  1            // InterfaceMethod java/util/Set.iterator:()Ljava/util/Iterator;
      20: astore_3
      21: aload_3
      22: invokeinterface #6,  1            // InterfaceMethod java/util/Iterator.hasNext:()Z
      27: ifeq          56
      30: aload_3
      31: invokeinterface #7,  1            // InterfaceMethod java/util/Iterator.next:()Ljava/lang/Object;
      36: checkcast     #8                  // class org/hibernate/validator/internal/engine/valueextraction/ValueExtractorDescriptor
      39: astore        4
      41: aload_2
      42: aload         4
      44: invokevirtual #9                  // Method org/hibernate/validator/internal/engine/valueextraction/ValueExtractorDescriptor.getKey:()Lorg/hibernate/validator/internal/engine/valueextraction/ValueExtractorDescriptor$Key;
      47: aload         4
      49: invokevirtual #10                 // Method java/util/LinkedHashMap.put:(Ljava/lang/Object;Ljava/lang/Object;)Ljava/lang/Object;
      52: pop
      53: goto          21
      56: aload_1
      57: invokeinterface #5,  1            // InterfaceMethod java/util/Set.iterator:()Ljava/util/Iterator;
      62: astore_3
      63: aload_3
      64: invokeinterface #6,  1            // InterfaceMethod java/util/Iterator.hasNext:()Z
      69: ifeq          109
      72: aload_3
      73: invokeinterface #7,  1            // InterfaceMethod java/util/Iterator.next:()Ljava/lang/Object;
      78: checkcast     #11                 // class javax/validation/valueextraction/ValueExtractor
      81: astore        4
      83: new           #8                  // class org/hibernate/validator/internal/engine/valueextraction/ValueExtractorDescriptor
      86: dup
      87: aload         4
      89: invokespecial #12                 // Method org/hibernate/validator/internal/engine/valueextraction/ValueExtractorDescriptor."<init>":(Ljavax/validation/valueextraction/ValueExtractor;)V
      92: astore        5
      94: aload_2
      95: aload         5
      97: invokevirtual #9                  // Method org/hibernate/validator/internal/engine/valueextraction/ValueExtractorDescriptor.getKey:()Lorg/hibernate/validator/internal/engine/valueextraction/ValueExtractorDescriptor$Key;
     100: aload         5
     102: invokevirtual #10                 // Method java/util/LinkedHashMap.put:(Ljava/lang/Object;Ljava/lang/Object;)Ljava/lang/Object;
     105: pop
     106: goto          63
     109: aload_0
     110: aload_2
     111: invokestatic  #13                 // Method java/util/Collections.unmodifiableMap:(Ljava/util/Map;)Ljava/util/Map;
     114: putfield      #14                 // Field registeredValueExtractors:Ljava/util/Map;
     117: aload_0
     118: new           #15                 // class org/hibernate/validator/internal/engine/valueextraction/ValueExtractorResolver
     121: dup
     122: new           #16                 // class java/util/HashSet
     125: dup
     126: aload_0
     127: getfield      #14                 // Field registeredValueExtractors:Ljava/util/Map;
     130: invokeinterface #17,  1           // InterfaceMethod java/util/Map.values:()Ljava/util/Collection;
     135: invokespecial #18                 // Method java/util/HashSet."<init>":(Ljava/util/Collection;)V
     138: invokespecial #19                 // Method org/hibernate/validator/internal/engine/valueextraction/ValueExtractorResolver."<init>":(Ljava/util/Set;)V
     141: putfield      #20                 // Field valueExtractorResolver:Lorg/hibernate/validator/internal/engine/valueextraction/ValueExtractorResolver;
     144: return

  public org.hibernate.validator.internal.engine.valueextraction.ValueExtractorManager(org.hibernate.validator.internal.engine.valueextraction.ValueExtractorManager, java.util.Map<org.hibernate.validator.internal.engine.valueextraction.ValueExtractorDescriptor$Key, org.hibernate.validator.internal.engine.valueextraction.ValueExtractorDescriptor>);
    Code:
       0: aload_0
       1: invokespecial #1                  // Method java/lang/Object."<init>":()V
       4: new           #2                  // class java/util/LinkedHashMap
       7: dup
       8: aload_1
       9: getfield      #14                 // Field registeredValueExtractors:Ljava/util/Map;
      12: invokespecial #21                 // Method java/util/LinkedHashMap."<init>":(Ljava/util/Map;)V
      15: astore_3
      16: aload_3
      17: aload_2
      18: invokevirtual #22                 // Method java/util/LinkedHashMap.putAll:(Ljava/util/Map;)V
      21: aload_0
      22: aload_3
      23: invokestatic  #13                 // Method java/util/Collections.unmodifiableMap:(Ljava/util/Map;)Ljava/util/Map;
      26: putfield      #14                 // Field registeredValueExtractors:Ljava/util/Map;
      29: aload_0
      30: new           #15                 // class org/hibernate/validator/internal/engine/valueextraction/ValueExtractorResolver
      33: dup
      34: new           #16                 // class java/util/HashSet
      37: dup
      38: aload_0
      39: getfield      #14                 // Field registeredValueExtractors:Ljava/util/Map;
      42: invokeinterface #17,  1           // InterfaceMethod java/util/Map.values:()Ljava/util/Collection;
      47: invokespecial #18                 // Method java/util/HashSet."<init>":(Ljava/util/Collection;)V
      50: invokespecial #19                 // Method org/hibernate/validator/internal/engine/valueextraction/ValueExtractorResolver."<init>":(Ljava/util/Set;)V
      53: putfield      #20                 // Field valueExtractorResolver:Lorg/hibernate/validator/internal/engine/valueextraction/ValueExtractorResolver;
      56: return

  public static java.util.Set<javax.validation.valueextraction.ValueExtractor<?>> getDefaultValueExtractors();
    Code:
       0: getstatic     #4                  // Field SPEC_DEFINED_EXTRACTORS:Ljava/util/Set;
       3: invokeinterface #23,  1           // InterfaceMethod java/util/Set.stream:()Ljava/util/stream/Stream;
       8: invokedynamic #24,  0             // InvokeDynamic #0:apply:()Ljava/util/function/Function;
      13: invokeinterface #25,  2           // InterfaceMethod java/util/stream/Stream.map:(Ljava/util/function/Function;)Ljava/util/stream/Stream;
      18: invokestatic  #26                 // Method java/util/stream/Collectors.toSet:()Ljava/util/stream/Collector;
      21: invokedynamic #27,  0             // InvokeDynamic #1:apply:()Ljava/util/function/Function;
      26: invokestatic  #28                 // Method java/util/stream/Collectors.collectingAndThen:(Ljava/util/stream/Collector;Ljava/util/function/Function;)Ljava/util/stream/Collector;
      29: invokeinterface #29,  2           // InterfaceMethod java/util/stream/Stream.collect:(Ljava/util/stream/Collector;)Ljava/lang/Object;
      34: checkcast     #30                 // class java/util/Set
      37: areturn

  public org.hibernate.validator.internal.engine.valueextraction.ValueExtractorDescriptor getMaximallySpecificAndRuntimeContainerElementCompliantValueExtractor(java.lang.reflect.Type, java.lang.reflect.TypeVariable<?>, java.lang.Class<?>, java.util.Collection<org.hibernate.validator.internal.engine.valueextraction.ValueExtractorDescriptor>);
    Code:
       0: aload         4
       2: invokeinterface #31,  1           // InterfaceMethod java/util/Collection.size:()I
       7: iconst_1
       8: if_icmpne     27
      11: aload         4
      13: invokeinterface #32,  1           // InterfaceMethod java/util/Collection.iterator:()Ljava/util/Iterator;
      18: invokeinterface #7,  1            // InterfaceMethod java/util/Iterator.next:()Ljava/lang/Object;
      23: checkcast     #8                  // class org/hibernate/validator/internal/engine/valueextraction/ValueExtractorDescriptor
      26: areturn
      27: aload         4
      29: invokeinterface #33,  1           // InterfaceMethod java/util/Collection.isEmpty:()Z
      34: ifne          50
      37: aload_0
      38: getfield      #20                 // Field valueExtractorResolver:Lorg/hibernate/validator/internal/engine/valueextraction/ValueExtractorResolver;
      41: aload_1
      42: aload_2
      43: aload_3
      44: aload         4
      46: invokevirtual #34                 // Method org/hibernate/validator/internal/engine/valueextraction/ValueExtractorResolver.getMaximallySpecificAndRuntimeContainerElementCompliantValueExtractor:(Ljava/lang/reflect/Type;Ljava/lang/reflect/TypeVariable;Ljava/lang/Class;Ljava/util/Collection;)Lorg/hibernate/validator/internal/engine/valueextraction/ValueExtractorDescriptor;
      49: areturn
      50: aload_0
      51: getfield      #20                 // Field valueExtractorResolver:Lorg/hibernate/validator/internal/engine/valueextraction/ValueExtractorResolver;
      54: aload_1
      55: aload_2
      56: aload_3
      57: aload_0
      58: getfield      #14                 // Field registeredValueExtractors:Ljava/util/Map;
      61: invokeinterface #17,  1           // InterfaceMethod java/util/Map.values:()Ljava/util/Collection;
      66: invokevirtual #34                 // Method org/hibernate/validator/internal/engine/valueextraction/ValueExtractorResolver.getMaximallySpecificAndRuntimeContainerElementCompliantValueExtractor:(Ljava/lang/reflect/Type;Ljava/lang/reflect/TypeVariable;Ljava/lang/Class;Ljava/util/Collection;)Lorg/hibernate/validator/internal/engine/valueextraction/ValueExtractorDescriptor;
      69: areturn

  public org.hibernate.validator.internal.engine.valueextraction.ValueExtractorResolver getResolver();
    Code:
       0: aload_0
       1: getfield      #20                 // Field valueExtractorResolver:Lorg/hibernate/validator/internal/engine/valueextraction/ValueExtractorResolver;
       4: areturn

  public int hashCode();
    Code:
       0: bipush        31
       2: istore_1
       3: iconst_1
       4: istore_2
       5: bipush        31
       7: iload_2
       8: imul
       9: aload_0
      10: getfield      #14                 // Field registeredValueExtractors:Ljava/util/Map;
      13: ifnonnull     20
      16: iconst_0
      17: goto          29
      20: aload_0
      21: getfield      #14                 // Field registeredValueExtractors:Ljava/util/Map;
      24: invokeinterface #35,  1           // InterfaceMethod java/util/Map.hashCode:()I
      29: iadd
      30: istore_2
      31: iload_2
      32: ireturn

  public boolean equals(java.lang.Object);
    Code:
       0: aload_0
       1: aload_1
       2: if_acmpne     7
       5: iconst_1
       6: ireturn
       7: aload_1
       8: ifnonnull     13
      11: iconst_0
      12: ireturn
      13: aload_0
      14: invokevirtual #36                 // Method java/lang/Object.getClass:()Ljava/lang/Class;
      17: aload_1
      18: invokevirtual #36                 // Method java/lang/Object.getClass:()Ljava/lang/Class;
      21: if_acmpeq     26
      24: iconst_0
      25: ireturn
      26: aload_1
      27: checkcast     #37                 // class org/hibernate/validator/internal/engine/valueextraction/ValueExtractorManager
      30: astore_2
      31: aload_0
      32: getfield      #14                 // Field registeredValueExtractors:Ljava/util/Map;
      35: aload_2
      36: getfield      #14                 // Field registeredValueExtractors:Ljava/util/Map;
      39: invokeinterface #38,  2           // InterfaceMethod java/util/Map.equals:(Ljava/lang/Object;)Z
      44: ireturn

  private static boolean isJavaFxInClasspath();
    Code:
       0: ldc           #39                 // String javafx.beans.value.ObservableValue
       2: iconst_0
       3: invokestatic  #40                 // Method isClassPresent:(Ljava/lang/String;Z)Z
       6: ireturn

  private static boolean isClassPresent(java.lang.String, boolean);
    Code:
       0: aload_0
       1: ldc           #37                 // class org/hibernate/validator/internal/engine/valueextraction/ValueExtractorManager
       3: invokevirtual #41                 // Method java/lang/Class.getClassLoader:()Ljava/lang/ClassLoader;
       6: iload_1
       7: invokestatic  #42                 // Method org/hibernate/validator/internal/util/privilegedactions/LoadClass.action:(Ljava/lang/String;Ljava/lang/ClassLoader;Z)Lorg/hibernate/validator/internal/util/privilegedactions/LoadClass;
      10: invokestatic  #43                 // Method run:(Ljava/security/PrivilegedAction;)Ljava/lang/Object;
      13: pop
      14: iconst_1
      15: ireturn
      16: astore_2
      17: iconst_0
      18: ireturn
    Exception table:
       from    to  target type
           0    15    16   Class javax/validation/ValidationException

  public void clear();
    Code:
       0: aload_0
       1: getfield      #20                 // Field valueExtractorResolver:Lorg/hibernate/validator/internal/engine/valueextraction/ValueExtractorResolver;
       4: invokevirtual #45                 // Method org/hibernate/validator/internal/engine/valueextraction/ValueExtractorResolver.clear:()V
       7: return

  private static <T> T run(java.security.PrivilegedAction<T>);
    Code:
       0: invokestatic  #46                 // Method java/lang/System.getSecurityManager:()Ljava/lang/SecurityManager;
       3: ifnull        13
       6: aload_0
       7: invokestatic  #47                 // Method java/security/AccessController.doPrivileged:(Ljava/security/PrivilegedAction;)Ljava/lang/Object;
      10: goto          19
      13: aload_0
      14: invokeinterface #48,  1           // InterfaceMethod java/security/PrivilegedAction.run:()Ljava/lang/Object;
      19: areturn

  private static javax.validation.valueextraction.ValueExtractor lambda$getDefaultValueExtractors$0(org.hibernate.validator.internal.engine.valueextraction.ValueExtractorDescriptor);
    Code:
       0: aload_0
       1: invokevirtual #49                 // Method org/hibernate/validator/internal/engine/valueextraction/ValueExtractorDescriptor.getValueExtractor:()Ljavax/validation/valueextraction/ValueExtractor;
       4: areturn

  static {};
    Code:
       0: new           #50                 // class java/util/LinkedHashSet
       3: dup
       4: invokespecial #51                 // Method java/util/LinkedHashSet."<init>":()V
       7: astore_0
       8: invokestatic  #52                 // Method isJavaFxInClasspath:()Z
      11: ifeq          86
      14: aload_0
      15: getstatic     #53                 // Field org/hibernate/validator/internal/engine/valueextraction/ObservableValueValueExtractor.DESCRIPTOR:Lorg/hibernate/validator/internal/engine/valueextraction/ValueExtractorDescriptor;
      18: invokevirtual #54                 // Method java/util/LinkedHashSet.add:(Ljava/lang/Object;)Z
      21: pop
      22: aload_0
      23: getstatic     #55                 // Field org/hibernate/validator/internal/engine/valueextraction/ListPropertyValueExtractor.DESCRIPTOR:Lorg/hibernate/validator/internal/engine/valueextraction/ValueExtractorDescriptor;
      26: invokevirtual #54                 // Method java/util/LinkedHashSet.add:(Ljava/lang/Object;)Z
      29: pop
      30: aload_0
      31: getstatic     #56                 // Field org/hibernate/validator/internal/engine/valueextraction/ReadOnlyListPropertyValueExtractor.DESCRIPTOR:Lorg/hibernate/validator/internal/engine/valueextraction/ValueExtractorDescriptor;
      34: invokevirtual #54                 // Method java/util/LinkedHashSet.add:(Ljava/lang/Object;)Z
      37: pop
      38: aload_0
      39: getstatic     #57                 // Field org/hibernate/validator/internal/engine/valueextraction/MapPropertyValueExtractor.DESCRIPTOR:Lorg/hibernate/validator/internal/engine/valueextraction/ValueExtractorDescriptor;
      42: invokevirtual #54                 // Method java/util/LinkedHashSet.add:(Ljava/lang/Object;)Z
      45: pop
      46: aload_0
      47: getstatic     #58                 // Field org/hibernate/validator/internal/engine/valueextraction/ReadOnlyMapPropertyValueExtractor.DESCRIPTOR:Lorg/hibernate/validator/internal/engine/valueextraction/ValueExtractorDescriptor;
      50: invokevirtual #54                 // Method java/util/LinkedHashSet.add:(Ljava/lang/Object;)Z
      53: pop
      54: aload_0
      55: getstatic     #59                 // Field org/hibernate/validator/internal/engine/valueextraction/MapPropertyKeyExtractor.DESCRIPTOR:Lorg/hibernate/validator/internal/engine/valueextraction/ValueExtractorDescriptor;
      58: invokevirtual #54                 // Method java/util/LinkedHashSet.add:(Ljava/lang/Object;)Z
      61: pop
      62: aload_0
      63: getstatic     #60                 // Field org/hibernate/validator/internal/engine/valueextraction/ReadOnlyMapPropertyKeyExtractor.DESCRIPTOR:Lorg/hibernate/validator/internal/engine/valueextraction/ValueExtractorDescriptor;
      66: invokevirtual #54                 // Method java/util/LinkedHashSet.add:(Ljava/lang/Object;)Z
      69: pop
      70: aload_0
      71: getstatic     #61                 // Field org/hibernate/validator/internal/engine/valueextraction/SetPropertyValueExtractor.DESCRIPTOR:Lorg/hibernate/validator/internal/engine/valueextraction/ValueExtractorDescriptor;
      74: invokevirtual #54                 // Method java/util/LinkedHashSet.add:(Ljava/lang/Object;)Z
      77: pop
      78: aload_0
      79: getstatic     #62                 // Field org/hibernate/validator/internal/engine/valueextraction/ReadOnlySetPropertyValueExtractor.DESCRIPTOR:Lorg/hibernate/validator/internal/engine/valueextraction/ValueExtractorDescriptor;
      82: invokevirtual #54                 // Method java/util/LinkedHashSet.add:(Ljava/lang/Object;)Z
      85: pop
      86: aload_0
      87: getstatic     #63                 // Field org/hibernate/validator/internal/engine/valueextraction/ByteArrayValueExtractor.DESCRIPTOR:Lorg/hibernate/validator/internal/engine/valueextraction/ValueExtractorDescriptor;
      90: invokevirtual #54                 // Method java/util/LinkedHashSet.add:(Ljava/lang/Object;)Z
      93: pop
      94: aload_0
      95: getstatic     #64                 // Field org/hibernate/validator/internal/engine/valueextraction/ShortArrayValueExtractor.DESCRIPTOR:Lorg/hibernate/validator/internal/engine/valueextraction/ValueExtractorDescriptor;
      98: invokevirtual #54                 // Method java/util/LinkedHashSet.add:(Ljava/lang/Object;)Z
     101: pop
     102: aload_0
     103: getstatic     #65                 // Field org/hibernate/validator/internal/engine/valueextraction/IntArrayValueExtractor.DESCRIPTOR:Lorg/hibernate/validator/internal/engine/valueextraction/ValueExtractorDescriptor;
     106: invokevirtual #54                 // Method java/util/LinkedHashSet.add:(Ljava/lang/Object;)Z
     109: pop
     110: aload_0
     111: getstatic     #66                 // Field org/hibernate/validator/internal/engine/valueextraction/LongArrayValueExtractor.DESCRIPTOR:Lorg/hibernate/validator/internal/engine/valueextraction/ValueExtractorDescriptor;
     114: invokevirtual #54                 // Method java/util/LinkedHashSet.add:(Ljava/lang/Object;)Z
     117: pop
     118: aload_0
     119: getstatic     #67                 // Field org/hibernate/validator/internal/engine/valueextraction/FloatArrayValueExtractor.DESCRIPTOR:Lorg/hibernate/validator/internal/engine/valueextraction/ValueExtractorDescriptor;
     122: invokevirtual #54                 // Method java/util/LinkedHashSet.add:(Ljava/lang/Object;)Z
     125: pop
     126: aload_0
     127: getstatic     #68                 // Field org/hibernate/validator/internal/engine/valueextraction/DoubleArrayValueExtractor.DESCRIPTOR:Lorg/hibernate/validator/internal/engine/valueextraction/ValueExtractorDescriptor;
     130: invokevirtual #54                 // Method java/util/LinkedHashSet.add:(Ljava/lang/Object;)Z
     133: pop
     134: aload_0
     135: getstatic     #69                 // Field org/hibernate/validator/internal/engine/valueextraction/CharArrayValueExtractor.DESCRIPTOR:Lorg/hibernate/validator/internal/engine/valueextraction/ValueExtractorDescriptor;
     138: invokevirtual #54                 // Method java/util/LinkedHashSet.add:(Ljava/lang/Object;)Z
     141: pop
     142: aload_0
     143: getstatic     #70                 // Field org/hibernate/validator/internal/engine/valueextraction/BooleanArrayValueExtractor.DESCRIPTOR:Lorg/hibernate/validator/internal/engine/valueextraction/ValueExtractorDescriptor;
     146: invokevirtual #54                 // Method java/util/LinkedHashSet.add:(Ljava/lang/Object;)Z
     149: pop
     150: aload_0
     151: getstatic     #71                 // Field org/hibernate/validator/internal/engine/valueextraction/ObjectArrayValueExtractor.DESCRIPTOR:Lorg/hibernate/validator/internal/engine/valueextraction/ValueExtractorDescriptor;
     154: invokevirtual #54                 // Method java/util/LinkedHashSet.add:(Ljava/lang/Object;)Z
     157: pop
     158: aload_0
     159: getstatic     #72                 // Field org/hibernate/validator/internal/engine/valueextraction/ListValueExtractor.DESCRIPTOR:Lorg/hibernate/validator/internal/engine/valueextraction/ValueExtractorDescriptor;
     162: invokevirtual #54                 // Method java/util/LinkedHashSet.add:(Ljava/lang/Object;)Z
     165: pop
     166: aload_0
     167: getstatic     #73                 // Field org/hibernate/validator/internal/engine/valueextraction/MapValueExtractor.DESCRIPTOR:Lorg/hibernate/validator/internal/engine/valueextraction/ValueExtractorDescriptor;
     170: invokevirtual #54                 // Method java/util/LinkedHashSet.add:(Ljava/lang/Object;)Z
     173: pop
     174: aload_0
     175: getstatic     #74                 // Field org/hibernate/validator/internal/engine/valueextraction/MapKeyExtractor.DESCRIPTOR:Lorg/hibernate/validator/internal/engine/valueextraction/ValueExtractorDescriptor;
     178: invokevirtual #54                 // Method java/util/LinkedHashSet.add:(Ljava/lang/Object;)Z
     181: pop
     182: aload_0
     183: getstatic     #75                 // Field org/hibernate/validator/internal/engine/valueextraction/IterableValueExtractor.DESCRIPTOR:Lorg/hibernate/validator/internal/engine/valueextraction/ValueExtractorDescriptor;
     186: invokevirtual #54                 // Method java/util/LinkedHashSet.add:(Ljava/lang/Object;)Z
     189: pop
     190: aload_0
     191: getstatic     #76                 // Field org/hibernate/validator/internal/engine/valueextraction/OptionalValueExtractor.DESCRIPTOR:Lorg/hibernate/validator/internal/engine/valueextraction/ValueExtractorDescriptor;
     194: invokevirtual #54                 // Method java/util/LinkedHashSet.add:(Ljava/lang/Object;)Z
     197: pop
     198: aload_0
     199: getstatic     #77                 // Field org/hibernate/validator/internal/engine/valueextraction/OptionalIntValueExtractor.DESCRIPTOR:Lorg/hibernate/validator/internal/engine/valueextraction/ValueExtractorDescriptor;
     202: invokevirtual #54                 // Method java/util/LinkedHashSet.add:(Ljava/lang/Object;)Z
     205: pop
     206: aload_0
     207: getstatic     #78                 // Field org/hibernate/validator/internal/engine/valueextraction/OptionalDoubleValueExtractor.DESCRIPTOR:Lorg/hibernate/validator/internal/engine/valueextraction/ValueExtractorDescriptor;
     210: invokevirtual #54                 // Method java/util/LinkedHashSet.add:(Ljava/lang/Object;)Z
     213: pop
     214: aload_0
     215: getstatic     #79                 // Field org/hibernate/validator/internal/engine/valueextraction/OptionalLongValueExtractor.DESCRIPTOR:Lorg/hibernate/validator/internal/engine/valueextraction/ValueExtractorDescriptor;
     218: invokevirtual #54                 // Method java/util/LinkedHashSet.add:(Ljava/lang/Object;)Z
     221: pop
     222: aload_0
     223: invokestatic  #80                 // Method java/util/Collections.unmodifiableSet:(Ljava/util/Set;)Ljava/util/Set;
     226: putstatic     #4                  // Field SPEC_DEFINED_EXTRACTORS:Ljava/util/Set;
     229: return
}
