Compiled from "MultiMavenResolver.java"
public class org.wildfly.swarm.bootstrap.modules.MultiMavenResolver implements org.jboss.modules.maven.MavenResolver {
  private java.util.List<org.jboss.modules.maven.MavenResolver> resolvers;

  public org.wildfly.swarm.bootstrap.modules.MultiMavenResolver();
    Code:
       0: aload_0
       1: invokespecial #1                  // Method java/lang/Object."<init>":()V
       4: aload_0
       5: new           #2                  // class java/util/ArrayList
       8: dup
       9: invokespecial #3                  // Method java/util/ArrayList."<init>":()V
      12: putfield      #4                  // Field resolvers:Ljava/util/List;
      15: return

  public void addResolver(org.jboss.modules.maven.MavenResolver);
    Code:
       0: aload_0
       1: getfield      #4                  // Field resolvers:Ljava/util/List;
       4: aload_1
       5: invokeinterface #5,  2            // InterfaceMethod java/util/List.add:(Ljava/lang/Object;)Z
      10: pop
      11: return

  public java.io.File resolveArtifact(org.jboss.modules.maven.ArtifactCoordinates, java.lang.String) throws java.io.IOException;
    Code:
       0: aload_0
       1: getfield      #4                  // Field resolvers:Ljava/util/List;
       4: invokeinterface #6,  1            // InterfaceMethod java/util/List.iterator:()Ljava/util/Iterator;
       9: astore_3
      10: aload_3
      11: invokeinterface #7,  1            // InterfaceMethod java/util/Iterator.hasNext:()Z
      16: ifeq          52
      19: aload_3
      20: invokeinterface #8,  1            // InterfaceMethod java/util/Iterator.next:()Ljava/lang/Object;
      25: checkcast     #9                  // class org/jboss/modules/maven/MavenResolver
      28: astore        4
      30: aload         4
      32: aload_1
      33: aload_2
      34: invokeinterface #10,  3           // InterfaceMethod org/jboss/modules/maven/MavenResolver.resolveArtifact:(Lorg/jboss/modules/maven/ArtifactCoordinates;Ljava/lang/String;)Ljava/io/File;
      39: astore        5
      41: aload         5
      43: ifnull        49
      46: aload         5
      48: areturn
      49: goto          10
      52: aconst_null
      53: areturn
}
