Compiled from "JavaVisibilities.kt"
public final class kotlin.reflect.jvm.internal.impl.descriptors.java.JavaVisibilities {
  public static final kotlin.reflect.jvm.internal.impl.descriptors.java.JavaVisibilities INSTANCE;

  private kotlin.reflect.jvm.internal.impl.descriptors.java.JavaVisibilities();
    Code:
       0: aload_0
       1: invokespecial #7                  // Method java/lang/Object."<init>":()V
       4: return

  static {};
    Code:
       0: new           #2                  // class kotlin/reflect/jvm/internal/impl/descriptors/java/JavaVisibilities
       3: dup
       4: invokespecial #8                  // Method "<init>":()V
       7: putstatic     #6                  // Field INSTANCE:Lkotlin/reflect/jvm/internal/impl/descriptors/java/JavaVisibilities;
      10: return
}
