Compiled from "JavaBigIntegerParser.java"
public class com.fasterxml.jackson.core.io.doubleparser.JavaBigIntegerParser {
  private static final com.fasterxml.jackson.core.io.doubleparser.JavaBigIntegerFromByteArray BYTE_ARRAY_PARSER;

  private static final com.fasterxml.jackson.core.io.doubleparser.JavaBigIntegerFromCharArray CHAR_ARRAY_PARSER;

  private static final com.fasterxml.jackson.core.io.doubleparser.JavaBigIntegerFromCharSequence CHAR_SEQUENCE_PARSER;

  private com.fasterxml.jackson.core.io.doubleparser.JavaBigIntegerParser();
    Code:
       0: aload_0
       1: invokespecial #15                 // Method java/lang/Object."<init>":()V
       4: return

  public static java.math.BigInteger parseBigInteger(java.lang.CharSequence);
    Code:
       0: getstatic     #21                 // Field CHAR_SEQUENCE_PARSER:Lcom/fasterxml/jackson/core/io/doubleparser/JavaBigIntegerFromCharSequence;
       3: aload_0
       4: iconst_0
       5: aload_0
       6: invokeinterface #27,  1           // InterfaceMethod java/lang/CharSequence.length:()I
      11: bipush        10
      13: invokevirtual #33                 // Method com/fasterxml/jackson/core/io/doubleparser/JavaBigIntegerFromCharSequence.parseBigIntegerLiteral:(Ljava/lang/CharSequence;III)Ljava/math/BigInteger;
      16: areturn

  public static java.math.BigInteger parseBigInteger(java.lang.CharSequence, int);
    Code:
       0: getstatic     #21                 // Field CHAR_SEQUENCE_PARSER:Lcom/fasterxml/jackson/core/io/doubleparser/JavaBigIntegerFromCharSequence;
       3: aload_0
       4: iconst_0
       5: aload_0
       6: invokeinterface #27,  1           // InterfaceMethod java/lang/CharSequence.length:()I
      11: iload_1
      12: invokevirtual #33                 // Method com/fasterxml/jackson/core/io/doubleparser/JavaBigIntegerFromCharSequence.parseBigIntegerLiteral:(Ljava/lang/CharSequence;III)Ljava/math/BigInteger;
      15: areturn

  public static java.math.BigInteger parseBigInteger(java.lang.CharSequence, int, int);
    Code:
       0: getstatic     #21                 // Field CHAR_SEQUENCE_PARSER:Lcom/fasterxml/jackson/core/io/doubleparser/JavaBigIntegerFromCharSequence;
       3: aload_0
       4: iload_1
       5: iload_2
       6: bipush        10
       8: invokevirtual #33                 // Method com/fasterxml/jackson/core/io/doubleparser/JavaBigIntegerFromCharSequence.parseBigIntegerLiteral:(Ljava/lang/CharSequence;III)Ljava/math/BigInteger;
      11: areturn

  public static java.math.BigInteger parseBigInteger(java.lang.CharSequence, int, int, int);
    Code:
       0: getstatic     #21                 // Field CHAR_SEQUENCE_PARSER:Lcom/fasterxml/jackson/core/io/doubleparser/JavaBigIntegerFromCharSequence;
       3: aload_0
       4: iload_1
       5: iload_2
       6: iload_3
       7: invokevirtual #33                 // Method com/fasterxml/jackson/core/io/doubleparser/JavaBigIntegerFromCharSequence.parseBigIntegerLiteral:(Ljava/lang/CharSequence;III)Ljava/math/BigInteger;
      10: areturn

  public static java.math.BigInteger parseBigInteger(byte[]);
    Code:
       0: getstatic     #43                 // Field BYTE_ARRAY_PARSER:Lcom/fasterxml/jackson/core/io/doubleparser/JavaBigIntegerFromByteArray;
       3: aload_0
       4: iconst_0
       5: aload_0
       6: arraylength
       7: bipush        10
       9: invokevirtual #48                 // Method com/fasterxml/jackson/core/io/doubleparser/JavaBigIntegerFromByteArray.parseBigIntegerLiteral:([BIII)Ljava/math/BigInteger;
      12: areturn

  public static java.math.BigInteger parseBigInteger(byte[], int);
    Code:
       0: getstatic     #43                 // Field BYTE_ARRAY_PARSER:Lcom/fasterxml/jackson/core/io/doubleparser/JavaBigIntegerFromByteArray;
       3: aload_0
       4: iconst_0
       5: aload_0
       6: arraylength
       7: iload_1
       8: invokevirtual #48                 // Method com/fasterxml/jackson/core/io/doubleparser/JavaBigIntegerFromByteArray.parseBigIntegerLiteral:([BIII)Ljava/math/BigInteger;
      11: areturn

  public static java.math.BigInteger parseBigInteger(byte[], int, int);
    Code:
       0: getstatic     #43                 // Field BYTE_ARRAY_PARSER:Lcom/fasterxml/jackson/core/io/doubleparser/JavaBigIntegerFromByteArray;
       3: aload_0
       4: iload_1
       5: iload_2
       6: bipush        10
       8: invokevirtual #48                 // Method com/fasterxml/jackson/core/io/doubleparser/JavaBigIntegerFromByteArray.parseBigIntegerLiteral:([BIII)Ljava/math/BigInteger;
      11: areturn

  public static java.math.BigInteger parseBigInteger(byte[], int, int, int);
    Code:
       0: getstatic     #43                 // Field BYTE_ARRAY_PARSER:Lcom/fasterxml/jackson/core/io/doubleparser/JavaBigIntegerFromByteArray;
       3: aload_0
       4: iload_1
       5: iload_2
       6: iload_3
       7: invokevirtual #48                 // Method com/fasterxml/jackson/core/io/doubleparser/JavaBigIntegerFromByteArray.parseBigIntegerLiteral:([BIII)Ljava/math/BigInteger;
      10: areturn

  public static java.math.BigInteger parseBigInteger(char[]);
    Code:
       0: getstatic     #54                 // Field CHAR_ARRAY_PARSER:Lcom/fasterxml/jackson/core/io/doubleparser/JavaBigIntegerFromCharArray;
       3: aload_0
       4: iconst_0
       5: aload_0
       6: arraylength
       7: bipush        10
       9: invokevirtual #59                 // Method com/fasterxml/jackson/core/io/doubleparser/JavaBigIntegerFromCharArray.parseBigIntegerLiteral:([CIII)Ljava/math/BigInteger;
      12: areturn

  public static java.math.BigInteger parseBigInteger(char[], int);
    Code:
       0: getstatic     #54                 // Field CHAR_ARRAY_PARSER:Lcom/fasterxml/jackson/core/io/doubleparser/JavaBigIntegerFromCharArray;
       3: aload_0
       4: iconst_0
       5: aload_0
       6: arraylength
       7: iload_1
       8: invokevirtual #59                 // Method com/fasterxml/jackson/core/io/doubleparser/JavaBigIntegerFromCharArray.parseBigIntegerLiteral:([CIII)Ljava/math/BigInteger;
      11: areturn

  public static java.math.BigInteger parseBigInteger(char[], int, int);
    Code:
       0: getstatic     #54                 // Field CHAR_ARRAY_PARSER:Lcom/fasterxml/jackson/core/io/doubleparser/JavaBigIntegerFromCharArray;
       3: aload_0
       4: iload_1
       5: iload_2
       6: bipush        10
       8: invokevirtual #59                 // Method com/fasterxml/jackson/core/io/doubleparser/JavaBigIntegerFromCharArray.parseBigIntegerLiteral:([CIII)Ljava/math/BigInteger;
      11: areturn

  public static java.math.BigInteger parseBigInteger(char[], int, int, int);
    Code:
       0: getstatic     #54                 // Field CHAR_ARRAY_PARSER:Lcom/fasterxml/jackson/core/io/doubleparser/JavaBigIntegerFromCharArray;
       3: aload_0
       4: iload_1
       5: iload_2
       6: iload_3
       7: invokevirtual #59                 // Method com/fasterxml/jackson/core/io/doubleparser/JavaBigIntegerFromCharArray.parseBigIntegerLiteral:([CIII)Ljava/math/BigInteger;
      10: areturn

  static {};
    Code:
       0: new           #45                 // class com/fasterxml/jackson/core/io/doubleparser/JavaBigIntegerFromByteArray
       3: dup
       4: invokespecial #64                 // Method com/fasterxml/jackson/core/io/doubleparser/JavaBigIntegerFromByteArray."<init>":()V
       7: putstatic     #43                 // Field BYTE_ARRAY_PARSER:Lcom/fasterxml/jackson/core/io/doubleparser/JavaBigIntegerFromByteArray;
      10: new           #56                 // class com/fasterxml/jackson/core/io/doubleparser/JavaBigIntegerFromCharArray
      13: dup
      14: invokespecial #65                 // Method com/fasterxml/jackson/core/io/doubleparser/JavaBigIntegerFromCharArray."<init>":()V
      17: putstatic     #54                 // Field CHAR_ARRAY_PARSER:Lcom/fasterxml/jackson/core/io/doubleparser/JavaBigIntegerFromCharArray;
      20: new           #29                 // class com/fasterxml/jackson/core/io/doubleparser/JavaBigIntegerFromCharSequence
      23: dup
      24: invokespecial #66                 // Method com/fasterxml/jackson/core/io/doubleparser/JavaBigIntegerFromCharSequence."<init>":()V
      27: putstatic     #21                 // Field CHAR_SEQUENCE_PARSER:Lcom/fasterxml/jackson/core/io/doubleparser/JavaBigIntegerFromCharSequence;
      30: return
}
