Compiled from "XMLUtils.java"
public final class org.xwiki.filter.xml.internal.XMLUtils {
  public static final java.util.regex.Pattern INDEX_PATTERN;

  private static final java.util.Map<java.lang.Class<?>, java.lang.Object> DEFAULTS;

  private static final java.util.Set<java.lang.Class<?>> SIMPLECLASSES;

  private org.xwiki.filter.xml.internal.XMLUtils();
    Code:
       0: aload_0
       1: invokespecial #1                  // Method java/lang/Object."<init>":()V
       4: return

  public static boolean isSimpleType(java.lang.reflect.Type);
    Code:
       0: iconst_0
       1: istore_1
       2: aload_0
       3: instanceof    #2                  // class java/lang/Class
       6: ifeq          55
       9: aload_0
      10: checkcast     #2                  // class java/lang/Class
      13: astore_2
      14: getstatic     #3                  // Field SIMPLECLASSES:Ljava/util/Set;
      17: aload_2
      18: invokeinterface #4,  2            // InterfaceMethod java/util/Set.contains:(Ljava/lang/Object;)Z
      23: ifne          49
      26: ldc           #5                  // class java/lang/Number
      28: aload_2
      29: invokevirtual #6                  // Method java/lang/Class.isAssignableFrom:(Ljava/lang/Class;)Z
      32: ifne          49
      35: aload_2
      36: invokevirtual #7                  // Method java/lang/Class.isPrimitive:()Z
      39: ifne          49
      42: aload_2
      43: invokevirtual #8                  // Method java/lang/Class.isEnum:()Z
      46: ifeq          53
      49: iconst_1
      50: goto          54
      53: iconst_0
      54: istore_1
      55: iload_1
      56: ireturn

  public static java.lang.Object emptyValue(java.lang.Class<?>);
    Code:
       0: aconst_null
       1: astore_1
       2: getstatic     #9                  // Field DEFAULTS:Ljava/util/Map;
       5: aload_0
       6: invokeinterface #10,  2           // InterfaceMethod java/util/Map.containsKey:(Ljava/lang/Object;)Z
      11: ifeq          27
      14: getstatic     #9                  // Field DEFAULTS:Ljava/util/Map;
      17: aload_0
      18: invokeinterface #11,  2           // InterfaceMethod java/util/Map.get:(Ljava/lang/Object;)Ljava/lang/Object;
      23: astore_1
      24: goto          36
      27: aload_0
      28: invokevirtual #12                 // Method java/lang/Class.newInstance:()Ljava/lang/Object;
      31: astore_1
      32: goto          36
      35: astore_2
      36: aload_1
      37: areturn
    Exception table:
       from    to  target type
          27    32    35   Class java/lang/Exception

  static {};
    Code:
       0: ldc           #14                 // String _(\\d+)
       2: invokestatic  #15                 // Method java/util/regex/Pattern.compile:(Ljava/lang/String;)Ljava/util/regex/Pattern;
       5: putstatic     #16                 // Field INDEX_PATTERN:Ljava/util/regex/Pattern;
       8: new           #17                 // class java/util/HashMap
      11: dup
      12: invokespecial #18                 // Method java/util/HashMap."<init>":()V
      15: putstatic     #9                  // Field DEFAULTS:Ljava/util/Map;
      18: getstatic     #9                  // Field DEFAULTS:Ljava/util/Map;
      21: getstatic     #19                 // Field java/lang/Boolean.TYPE:Ljava/lang/Class;
      24: iconst_0
      25: invokestatic  #20                 // Method java/lang/Boolean.valueOf:(Z)Ljava/lang/Boolean;
      28: invokeinterface #21,  3           // InterfaceMethod java/util/Map.put:(Ljava/lang/Object;Ljava/lang/Object;)Ljava/lang/Object;
      33: pop
      34: getstatic     #9                  // Field DEFAULTS:Ljava/util/Map;
      37: getstatic     #22                 // Field java/lang/Character.TYPE:Ljava/lang/Class;
      40: iconst_0
      41: invokestatic  #23                 // Method java/lang/Character.valueOf:(C)Ljava/lang/Character;
      44: invokeinterface #21,  3           // InterfaceMethod java/util/Map.put:(Ljava/lang/Object;Ljava/lang/Object;)Ljava/lang/Object;
      49: pop
      50: getstatic     #9                  // Field DEFAULTS:Ljava/util/Map;
      53: getstatic     #24                 // Field java/lang/Byte.TYPE:Ljava/lang/Class;
      56: iconst_0
      57: invokestatic  #25                 // Method java/lang/Byte.valueOf:(B)Ljava/lang/Byte;
      60: invokeinterface #21,  3           // InterfaceMethod java/util/Map.put:(Ljava/lang/Object;Ljava/lang/Object;)Ljava/lang/Object;
      65: pop
      66: getstatic     #9                  // Field DEFAULTS:Ljava/util/Map;
      69: getstatic     #26                 // Field java/lang/Short.TYPE:Ljava/lang/Class;
      72: iconst_0
      73: invokestatic  #27                 // Method java/lang/Short.valueOf:(S)Ljava/lang/Short;
      76: invokeinterface #21,  3           // InterfaceMethod java/util/Map.put:(Ljava/lang/Object;Ljava/lang/Object;)Ljava/lang/Object;
      81: pop
      82: getstatic     #9                  // Field DEFAULTS:Ljava/util/Map;
      85: getstatic     #28                 // Field java/lang/Integer.TYPE:Ljava/lang/Class;
      88: iconst_0
      89: invokestatic  #29                 // Method java/lang/Integer.valueOf:(I)Ljava/lang/Integer;
      92: invokeinterface #21,  3           // InterfaceMethod java/util/Map.put:(Ljava/lang/Object;Ljava/lang/Object;)Ljava/lang/Object;
      97: pop
      98: getstatic     #9                  // Field DEFAULTS:Ljava/util/Map;
     101: getstatic     #30                 // Field java/lang/Long.TYPE:Ljava/lang/Class;
     104: lconst_0
     105: invokestatic  #31                 // Method java/lang/Long.valueOf:(J)Ljava/lang/Long;
     108: invokeinterface #21,  3           // InterfaceMethod java/util/Map.put:(Ljava/lang/Object;Ljava/lang/Object;)Ljava/lang/Object;
     113: pop
     114: getstatic     #9                  // Field DEFAULTS:Ljava/util/Map;
     117: getstatic     #32                 // Field java/lang/Float.TYPE:Ljava/lang/Class;
     120: fconst_0
     121: invokestatic  #33                 // Method java/lang/Float.valueOf:(F)Ljava/lang/Float;
     124: invokeinterface #21,  3           // InterfaceMethod java/util/Map.put:(Ljava/lang/Object;Ljava/lang/Object;)Ljava/lang/Object;
     129: pop
     130: getstatic     #9                  // Field DEFAULTS:Ljava/util/Map;
     133: getstatic     #34                 // Field java/lang/Double.TYPE:Ljava/lang/Class;
     136: dconst_0
     137: invokestatic  #35                 // Method java/lang/Double.valueOf:(D)Ljava/lang/Double;
     140: invokeinterface #21,  3           // InterfaceMethod java/util/Map.put:(Ljava/lang/Object;Ljava/lang/Object;)Ljava/lang/Object;
     145: pop
     146: getstatic     #9                  // Field DEFAULTS:Ljava/util/Map;
     149: ldc           #36                 // class java/util/Map
     151: new           #37                 // class java/util/LinkedHashMap
     154: dup
     155: invokespecial #38                 // Method java/util/LinkedHashMap."<init>":()V
     158: invokeinterface #21,  3           // InterfaceMethod java/util/Map.put:(Ljava/lang/Object;Ljava/lang/Object;)Ljava/lang/Object;
     163: pop
     164: getstatic     #9                  // Field DEFAULTS:Ljava/util/Map;
     167: ldc           #39                 // class java/util/Set
     169: new           #40                 // class java/util/LinkedHashSet
     172: dup
     173: invokespecial #41                 // Method java/util/LinkedHashSet."<init>":()V
     176: invokeinterface #21,  3           // InterfaceMethod java/util/Map.put:(Ljava/lang/Object;Ljava/lang/Object;)Ljava/lang/Object;
     181: pop
     182: getstatic     #9                  // Field DEFAULTS:Ljava/util/Map;
     185: ldc           #42                 // class java/util/List
     187: new           #43                 // class java/util/ArrayList
     190: dup
     191: invokespecial #44                 // Method java/util/ArrayList."<init>":()V
     194: invokeinterface #21,  3           // InterfaceMethod java/util/Map.put:(Ljava/lang/Object;Ljava/lang/Object;)Ljava/lang/Object;
     199: pop
     200: getstatic     #9                  // Field DEFAULTS:Ljava/util/Map;
     203: ldc           #45                 // class java/util/Collection
     205: new           #43                 // class java/util/ArrayList
     208: dup
     209: invokespecial #44                 // Method java/util/ArrayList."<init>":()V
     212: invokeinterface #21,  3           // InterfaceMethod java/util/Map.put:(Ljava/lang/Object;Ljava/lang/Object;)Ljava/lang/Object;
     217: pop
     218: new           #46                 // class java/util/HashSet
     221: dup
     222: iconst_4
     223: anewarray     #2                  // class java/lang/Class
     226: dup
     227: iconst_0
     228: ldc           #47                 // class java/lang/String
     230: aastore
     231: dup
     232: iconst_1
     233: ldc           #48                 // class java/lang/Character
     235: aastore
     236: dup
     237: iconst_2
     238: ldc           #49                 // class java/lang/Boolean
     240: aastore
     241: dup
     242: iconst_3
     243: ldc           #50                 // class "[B"
     245: aastore
     246: invokestatic  #51                 // Method java/util/Arrays.asList:([Ljava/lang/Object;)Ljava/util/List;
     249: invokespecial #52                 // Method java/util/HashSet."<init>":(Ljava/util/Collection;)V
     252: putstatic     #3                  // Field SIMPLECLASSES:Ljava/util/Set;
     255: return
}
