Compiled from "SuiteMethodBuilder.java"
public class org.junit.internal.builders.SuiteMethodBuilder extends org.junit.runners.model.RunnerBuilder {
  public org.junit.internal.builders.SuiteMethodBuilder();
    Code:
       0: aload_0
       1: invokespecial #1                  // Method org/junit/runners/model/RunnerBuilder."<init>":()V
       4: return

  public org.junit.runner.Runner runnerForClass(java.lang.Class<?>) throws java.lang.Throwable;
    Code:
       0: aload_0
       1: aload_1
       2: invokevirtual #2                  // Method hasSuiteMethod:(Ljava/lang/Class;)Z
       5: ifeq          17
       8: new           #3                  // class org/junit/internal/runners/SuiteMethod
      11: dup
      12: aload_1
      13: invokespecial #4                  // Method org/junit/internal/runners/SuiteMethod."<init>":(Ljava/lang/Class;)V
      16: areturn
      17: aconst_null
      18: areturn

  public boolean hasSuiteMethod(java.lang.Class<?>);
    Code:
       0: aload_1
       1: ldc           #5                  // String suite
       3: iconst_0
       4: anewarray     #6                  // class java/lang/Class
       7: invokevirtual #7                  // Method java/lang/Class.getMethod:(Ljava/lang/String;[Ljava/lang/Class;)Ljava/lang/reflect/Method;
      10: pop
      11: goto          17
      14: astore_2
      15: iconst_0
      16: ireturn
      17: iconst_1
      18: ireturn
    Exception table:
       from    to  target type
           0    11    14   Class java/lang/NoSuchMethodException
}
