Compiled from "DefaultMessageSplitter.java"
public class org.springframework.integration.splitter.DefaultMessageSplitter extends org.springframework.integration.splitter.AbstractMessageSplitter {
  private volatile java.lang.String delimiters;

  public org.springframework.integration.splitter.DefaultMessageSplitter();
    Code:
       0: aload_0
       1: invokespecial #1                  // Method org/springframework/integration/splitter/AbstractMessageSplitter."<init>":()V
       4: return

  public void setDelimiters(java.lang.String);
    Code:
       0: aload_0
       1: aload_1
       2: putfield      #2                  // Field delimiters:Ljava/lang/String;
       5: return

  protected final java.lang.Object splitMessage(org.springframework.messaging.Message<?>);
    Code:
       0: aload_1
       1: invokeinterface #3,  1            // InterfaceMethod org/springframework/messaging/Message.getPayload:()Ljava/lang/Object;
       6: astore_2
       7: aload_2
       8: instanceof    #4                  // class java/lang/String
      11: ifeq          71
      14: aload_0
      15: getfield      #2                  // Field delimiters:Ljava/lang/String;
      18: ifnull        71
      21: new           #5                  // class java/util/ArrayList
      24: dup
      25: invokespecial #6                  // Method java/util/ArrayList."<init>":()V
      28: astore_3
      29: new           #7                  // class java/util/StringTokenizer
      32: dup
      33: aload_2
      34: checkcast     #4                  // class java/lang/String
      37: aload_0
      38: getfield      #2                  // Field delimiters:Ljava/lang/String;
      41: invokespecial #8                  // Method java/util/StringTokenizer."<init>":(Ljava/lang/String;Ljava/lang/String;)V
      44: astore        4
      46: aload         4
      48: invokevirtual #9                  // Method java/util/StringTokenizer.hasMoreElements:()Z
      51: ifeq          69
      54: aload_3
      55: aload         4
      57: invokevirtual #10                 // Method java/util/StringTokenizer.nextToken:()Ljava/lang/String;
      60: invokeinterface #11,  2           // InterfaceMethod java/util/List.add:(Ljava/lang/Object;)Z
      65: pop
      66: goto          46
      69: aload_3
      70: areturn
      71: aload_2
      72: areturn
}
