public class com.ibm.wsdl.extensions.soap12.SOAP12OperationImpl implements javax.wsdl.extensions.soap12.SOAP12Operation {
  protected javax.xml.namespace.QName elementType;

  protected java.lang.Boolean required;

  protected java.lang.String soapActionURI;

  protected java.lang.Boolean soapActionRequired;

  protected java.lang.String style;

  public static final long serialVersionUID;

  public com.ibm.wsdl.extensions.soap12.SOAP12OperationImpl();
    Code:
       0: aload_0
       1: invokespecial #1                  // Method java/lang/Object."<init>":()V
       4: aload_0
       5: getstatic     #2                  // Field com/ibm/wsdl/extensions/soap12/SOAP12Constants.Q_ELEM_SOAP_OPERATION:Ljavax/xml/namespace/QName;
       8: putfield      #3                  // Field elementType:Ljavax/xml/namespace/QName;
      11: aload_0
      12: aconst_null
      13: putfield      #4                  // Field required:Ljava/lang/Boolean;
      16: aload_0
      17: aconst_null
      18: putfield      #5                  // Field soapActionURI:Ljava/lang/String;
      21: aload_0
      22: aconst_null
      23: putfield      #6                  // Field soapActionRequired:Ljava/lang/Boolean;
      26: aload_0
      27: aconst_null
      28: putfield      #7                  // Field style:Ljava/lang/String;
      31: return

  public void setElementType(javax.xml.namespace.QName);
    Code:
       0: aload_0
       1: aload_1
       2: putfield      #3                  // Field elementType:Ljavax/xml/namespace/QName;
       5: return

  public javax.xml.namespace.QName getElementType();
    Code:
       0: aload_0
       1: getfield      #3                  // Field elementType:Ljavax/xml/namespace/QName;
       4: areturn

  public void setRequired(java.lang.Boolean);
    Code:
       0: aload_0
       1: aload_1
       2: putfield      #4                  // Field required:Ljava/lang/Boolean;
       5: return

  public java.lang.Boolean getRequired();
    Code:
       0: aload_0
       1: getfield      #4                  // Field required:Ljava/lang/Boolean;
       4: areturn

  public void setSoapActionURI(java.lang.String);
    Code:
       0: aload_0
       1: aload_1
       2: putfield      #5                  // Field soapActionURI:Ljava/lang/String;
       5: return

  public java.lang.String getSoapActionURI();
    Code:
       0: aload_0
       1: getfield      #5                  // Field soapActionURI:Ljava/lang/String;
       4: areturn

  public void setSoapActionRequired(java.lang.Boolean);
    Code:
       0: aload_0
       1: aload_1
       2: putfield      #6                  // Field soapActionRequired:Ljava/lang/Boolean;
       5: return

  public java.lang.Boolean getSoapActionRequired();
    Code:
       0: aload_0
       1: getfield      #6                  // Field soapActionRequired:Ljava/lang/Boolean;
       4: areturn

  public void setStyle(java.lang.String);
    Code:
       0: aload_0
       1: aload_1
       2: putfield      #7                  // Field style:Ljava/lang/String;
       5: return

  public java.lang.String getStyle();
    Code:
       0: aload_0
       1: getfield      #7                  // Field style:Ljava/lang/String;
       4: areturn

  public java.lang.String toString();
    Code:
       0: new           #8                  // class java/lang/StringBuffer
       3: dup
       4: invokespecial #9                  // Method java/lang/StringBuffer."<init>":()V
       7: astore_1
       8: aload_1
       9: new           #8                  // class java/lang/StringBuffer
      12: dup
      13: invokespecial #9                  // Method java/lang/StringBuffer."<init>":()V
      16: ldc           #10                 // String SOAPOperation (
      18: invokevirtual #11                 // Method java/lang/StringBuffer.append:(Ljava/lang/String;)Ljava/lang/StringBuffer;
      21: aload_0
      22: getfield      #3                  // Field elementType:Ljavax/xml/namespace/QName;
      25: invokevirtual #12                 // Method java/lang/StringBuffer.append:(Ljava/lang/Object;)Ljava/lang/StringBuffer;
      28: ldc           #13                 // String ):
      30: invokevirtual #11                 // Method java/lang/StringBuffer.append:(Ljava/lang/String;)Ljava/lang/StringBuffer;
      33: invokevirtual #14                 // Method java/lang/StringBuffer.toString:()Ljava/lang/String;
      36: invokevirtual #11                 // Method java/lang/StringBuffer.append:(Ljava/lang/String;)Ljava/lang/StringBuffer;
      39: pop
      40: aload_1
      41: new           #8                  // class java/lang/StringBuffer
      44: dup
      45: invokespecial #9                  // Method java/lang/StringBuffer."<init>":()V
      48: ldc           #15                 // String \nrequired=
      50: invokevirtual #11                 // Method java/lang/StringBuffer.append:(Ljava/lang/String;)Ljava/lang/StringBuffer;
      53: aload_0
      54: getfield      #4                  // Field required:Ljava/lang/Boolean;
      57: invokevirtual #12                 // Method java/lang/StringBuffer.append:(Ljava/lang/Object;)Ljava/lang/StringBuffer;
      60: invokevirtual #14                 // Method java/lang/StringBuffer.toString:()Ljava/lang/String;
      63: invokevirtual #11                 // Method java/lang/StringBuffer.append:(Ljava/lang/String;)Ljava/lang/StringBuffer;
      66: pop
      67: aload_0
      68: getfield      #5                  // Field soapActionURI:Ljava/lang/String;
      71: ifnull        101
      74: aload_1
      75: new           #8                  // class java/lang/StringBuffer
      78: dup
      79: invokespecial #9                  // Method java/lang/StringBuffer."<init>":()V
      82: ldc           #16                 // String \nsoapActionURI=
      84: invokevirtual #11                 // Method java/lang/StringBuffer.append:(Ljava/lang/String;)Ljava/lang/StringBuffer;
      87: aload_0
      88: getfield      #5                  // Field soapActionURI:Ljava/lang/String;
      91: invokevirtual #11                 // Method java/lang/StringBuffer.append:(Ljava/lang/String;)Ljava/lang/StringBuffer;
      94: invokevirtual #14                 // Method java/lang/StringBuffer.toString:()Ljava/lang/String;
      97: invokevirtual #11                 // Method java/lang/StringBuffer.append:(Ljava/lang/String;)Ljava/lang/StringBuffer;
     100: pop
     101: aload_0
     102: getfield      #6                  // Field soapActionRequired:Ljava/lang/Boolean;
     105: ifnull        135
     108: aload_1
     109: new           #8                  // class java/lang/StringBuffer
     112: dup
     113: invokespecial #9                  // Method java/lang/StringBuffer."<init>":()V
     116: ldc           #17                 // String \nsoapActionRequired=
     118: invokevirtual #11                 // Method java/lang/StringBuffer.append:(Ljava/lang/String;)Ljava/lang/StringBuffer;
     121: aload_0
     122: getfield      #6                  // Field soapActionRequired:Ljava/lang/Boolean;
     125: invokevirtual #12                 // Method java/lang/StringBuffer.append:(Ljava/lang/Object;)Ljava/lang/StringBuffer;
     128: invokevirtual #14                 // Method java/lang/StringBuffer.toString:()Ljava/lang/String;
     131: invokevirtual #11                 // Method java/lang/StringBuffer.append:(Ljava/lang/String;)Ljava/lang/StringBuffer;
     134: pop
     135: aload_0
     136: getfield      #7                  // Field style:Ljava/lang/String;
     139: ifnull        169
     142: aload_1
     143: new           #8                  // class java/lang/StringBuffer
     146: dup
     147: invokespecial #9                  // Method java/lang/StringBuffer."<init>":()V
     150: ldc           #18                 // String \nstyle=
     152: invokevirtual #11                 // Method java/lang/StringBuffer.append:(Ljava/lang/String;)Ljava/lang/StringBuffer;
     155: aload_0
     156: getfield      #7                  // Field style:Ljava/lang/String;
     159: invokevirtual #11                 // Method java/lang/StringBuffer.append:(Ljava/lang/String;)Ljava/lang/StringBuffer;
     162: invokevirtual #14                 // Method java/lang/StringBuffer.toString:()Ljava/lang/String;
     165: invokevirtual #11                 // Method java/lang/StringBuffer.append:(Ljava/lang/String;)Ljava/lang/StringBuffer;
     168: pop
     169: aload_1
     170: invokevirtual #14                 // Method java/lang/StringBuffer.toString:()Ljava/lang/String;
     173: areturn
}
