Compiled from "ResponseMessageBuilder.java"
class springfox.documentation.builders.ResponseMessageBuilder$1 implements com.google.common.collect.Maps$EntryTransformer<java.lang.String, springfox.documentation.schema.ModelReference, springfox.documentation.service.Header> {
  final springfox.documentation.builders.ResponseMessageBuilder this$0;

  springfox.documentation.builders.ResponseMessageBuilder$1(springfox.documentation.builders.ResponseMessageBuilder);
    Code:
       0: aload_0
       1: aload_1
       2: putfield      #1                  // Field this$0:Lspringfox/documentation/builders/ResponseMessageBuilder;
       5: aload_0
       6: invokespecial #2                  // Method java/lang/Object."<init>":()V
       9: return

  public springfox.documentation.service.Header transformEntry(java.lang.String, springfox.documentation.schema.ModelReference);
    Code:
       0: new           #3                  // class springfox/documentation/service/Header
       3: dup
       4: aload_1
       5: ldc           #4                  // String
       7: aload_2
       8: invokespecial #5                  // Method springfox/documentation/service/Header."<init>":(Ljava/lang/String;Ljava/lang/String;Lspringfox/documentation/schema/ModelReference;)V
      11: areturn

  public java.lang.Object transformEntry(java.lang.Object, java.lang.Object);
    Code:
       0: aload_0
       1: aload_1
       2: checkcast     #6                  // class java/lang/String
       5: aload_2
       6: checkcast     #7                  // class springfox/documentation/schema/ModelReference
       9: invokevirtual #8                  // Method transformEntry:(Ljava/lang/String;Lspringfox/documentation/schema/ModelReference;)Lspringfox/documentation/service/Header;
      12: areturn
}
