Compiled from "TokenEndpointBuilder.java"
public class springfox.documentation.builders.TokenEndpointBuilder {
  private java.lang.String url;

  private java.lang.String tokenName;

  public springfox.documentation.builders.TokenEndpointBuilder();
    Code:
       0: aload_0
       1: invokespecial #1                  // Method java/lang/Object."<init>":()V
       4: return

  public springfox.documentation.builders.TokenEndpointBuilder url(java.lang.String);
    Code:
       0: aload_0
       1: aload_1
       2: aload_0
       3: getfield      #2                  // Field url:Ljava/lang/String;
       6: invokestatic  #3                  // Method springfox/documentation/builders/BuilderDefaults.defaultIfAbsent:(Ljava/lang/Object;Ljava/lang/Object;)Ljava/lang/Object;
       9: checkcast     #4                  // class java/lang/String
      12: putfield      #2                  // Field url:Ljava/lang/String;
      15: aload_0
      16: areturn

  public springfox.documentation.builders.TokenEndpointBuilder tokenName(java.lang.String);
    Code:
       0: aload_0
       1: aload_1
       2: aload_0
       3: getfield      #5                  // Field tokenName:Ljava/lang/String;
       6: invokestatic  #3                  // Method springfox/documentation/builders/BuilderDefaults.defaultIfAbsent:(Ljava/lang/Object;Ljava/lang/Object;)Ljava/lang/Object;
       9: checkcast     #4                  // class java/lang/String
      12: putfield      #5                  // Field tokenName:Ljava/lang/String;
      15: aload_0
      16: areturn

  public springfox.documentation.service.TokenEndpoint build();
    Code:
       0: new           #6                  // class springfox/documentation/service/TokenEndpoint
       3: dup
       4: aload_0
       5: getfield      #2                  // Field url:Ljava/lang/String;
       8: aload_0
       9: getfield      #5                  // Field tokenName:Ljava/lang/String;
      12: invokespecial #7                  // Method springfox/documentation/service/TokenEndpoint."<init>":(Ljava/lang/String;Ljava/lang/String;)V
      15: areturn
}
