Compiled from "JSPSetting.java"
public class org.wildfly.swarm.config.undertow.servlet_container.JSPSetting<T extends org.wildfly.swarm.config.undertow.servlet_container.JSPSetting<T>> extends java.util.HashMap {
  private java.lang.String key;

  private java.beans.PropertyChangeSupport pcs;

  private java.lang.Integer checkInterval;

  private java.lang.Boolean development;

  private java.lang.Boolean disabled;

  private java.lang.Boolean displaySourceFragment;

  private java.lang.Boolean dumpSmap;

  private java.lang.Boolean errorOnUseBeanInvalidClassAttribute;

  private java.lang.Boolean generateStringsAsCharArrays;

  private java.lang.String javaEncoding;

  private java.lang.Boolean keepGenerated;

  private java.lang.Boolean mappedFile;

  private java.lang.Integer modificationTestInterval;

  private java.lang.Boolean optimizeScriptlets;

  private java.lang.Boolean recompileOnFail;

  private java.lang.String scratchDir;

  private java.lang.Boolean smap;

  private java.lang.String sourceVm;

  private java.lang.Boolean tagPooling;

  private java.lang.String targetVm;

  private java.lang.Boolean trimSpaces;

  private java.lang.Boolean xPoweredBy;

  public org.wildfly.swarm.config.undertow.servlet_container.JSPSetting();
    Code:
       0: aload_0
       1: invokespecial #1                  // Method java/util/HashMap."<init>":()V
       4: aload_0
       5: ldc           #2                  // String jsp
       7: putfield      #3                  // Field key:Ljava/lang/String;
      10: aload_0
      11: new           #4                  // class java/beans/PropertyChangeSupport
      14: dup
      15: aload_0
      16: invokespecial #5                  // Method java/beans/PropertyChangeSupport."<init>":(Ljava/lang/Object;)V
      19: putfield      #6                  // Field pcs:Ljava/beans/PropertyChangeSupport;
      22: return

  public java.lang.String getKey();
    Code:
       0: aload_0
       1: getfield      #3                  // Field key:Ljava/lang/String;
       4: areturn

  public void addPropertyChangeListener(java.beans.PropertyChangeListener);
    Code:
       0: aconst_null
       1: aload_0
       2: getfield      #6                  // Field pcs:Ljava/beans/PropertyChangeSupport;
       5: if_acmpne     20
       8: aload_0
       9: new           #4                  // class java/beans/PropertyChangeSupport
      12: dup
      13: aload_0
      14: invokespecial #5                  // Method java/beans/PropertyChangeSupport."<init>":(Ljava/lang/Object;)V
      17: putfield      #6                  // Field pcs:Ljava/beans/PropertyChangeSupport;
      20: aload_0
      21: getfield      #6                  // Field pcs:Ljava/beans/PropertyChangeSupport;
      24: aload_1
      25: invokevirtual #7                  // Method java/beans/PropertyChangeSupport.addPropertyChangeListener:(Ljava/beans/PropertyChangeListener;)V
      28: return

  public void removePropertyChangeListener(java.beans.PropertyChangeListener);
    Code:
       0: aload_0
       1: getfield      #6                  // Field pcs:Ljava/beans/PropertyChangeSupport;
       4: ifnull        15
       7: aload_0
       8: getfield      #6                  // Field pcs:Ljava/beans/PropertyChangeSupport;
      11: aload_1
      12: invokevirtual #8                  // Method java/beans/PropertyChangeSupport.removePropertyChangeListener:(Ljava/beans/PropertyChangeListener;)V
      15: return

  public java.lang.Integer checkInterval();
    Code:
       0: aload_0
       1: getfield      #9                  // Field checkInterval:Ljava/lang/Integer;
       4: areturn

  public T checkInterval(java.lang.Integer);
    Code:
       0: aload_0
       1: getfield      #9                  // Field checkInterval:Ljava/lang/Integer;
       4: astore_2
       5: aload_0
       6: aload_1
       7: putfield      #9                  // Field checkInterval:Ljava/lang/Integer;
      10: aload_0
      11: getfield      #6                  // Field pcs:Ljava/beans/PropertyChangeSupport;
      14: ifnull        28
      17: aload_0
      18: getfield      #6                  // Field pcs:Ljava/beans/PropertyChangeSupport;
      21: ldc           #10                 // String checkInterval
      23: aload_2
      24: aload_1
      25: invokevirtual #11                 // Method java/beans/PropertyChangeSupport.firePropertyChange:(Ljava/lang/String;Ljava/lang/Object;Ljava/lang/Object;)V
      28: aload_0
      29: areturn

  public java.lang.Boolean development();
    Code:
       0: aload_0
       1: getfield      #12                 // Field development:Ljava/lang/Boolean;
       4: areturn

  public T development(java.lang.Boolean);
    Code:
       0: aload_0
       1: getfield      #12                 // Field development:Ljava/lang/Boolean;
       4: astore_2
       5: aload_0
       6: aload_1
       7: putfield      #12                 // Field development:Ljava/lang/Boolean;
      10: aload_0
      11: getfield      #6                  // Field pcs:Ljava/beans/PropertyChangeSupport;
      14: ifnull        28
      17: aload_0
      18: getfield      #6                  // Field pcs:Ljava/beans/PropertyChangeSupport;
      21: ldc           #13                 // String development
      23: aload_2
      24: aload_1
      25: invokevirtual #11                 // Method java/beans/PropertyChangeSupport.firePropertyChange:(Ljava/lang/String;Ljava/lang/Object;Ljava/lang/Object;)V
      28: aload_0
      29: areturn

  public java.lang.Boolean disabled();
    Code:
       0: aload_0
       1: getfield      #14                 // Field disabled:Ljava/lang/Boolean;
       4: areturn

  public T disabled(java.lang.Boolean);
    Code:
       0: aload_0
       1: getfield      #14                 // Field disabled:Ljava/lang/Boolean;
       4: astore_2
       5: aload_0
       6: aload_1
       7: putfield      #14                 // Field disabled:Ljava/lang/Boolean;
      10: aload_0
      11: getfield      #6                  // Field pcs:Ljava/beans/PropertyChangeSupport;
      14: ifnull        28
      17: aload_0
      18: getfield      #6                  // Field pcs:Ljava/beans/PropertyChangeSupport;
      21: ldc           #15                 // String disabled
      23: aload_2
      24: aload_1
      25: invokevirtual #11                 // Method java/beans/PropertyChangeSupport.firePropertyChange:(Ljava/lang/String;Ljava/lang/Object;Ljava/lang/Object;)V
      28: aload_0
      29: areturn

  public java.lang.Boolean displaySourceFragment();
    Code:
       0: aload_0
       1: getfield      #16                 // Field displaySourceFragment:Ljava/lang/Boolean;
       4: areturn

  public T displaySourceFragment(java.lang.Boolean);
    Code:
       0: aload_0
       1: getfield      #16                 // Field displaySourceFragment:Ljava/lang/Boolean;
       4: astore_2
       5: aload_0
       6: aload_1
       7: putfield      #16                 // Field displaySourceFragment:Ljava/lang/Boolean;
      10: aload_0
      11: getfield      #6                  // Field pcs:Ljava/beans/PropertyChangeSupport;
      14: ifnull        28
      17: aload_0
      18: getfield      #6                  // Field pcs:Ljava/beans/PropertyChangeSupport;
      21: ldc           #17                 // String displaySourceFragment
      23: aload_2
      24: aload_1
      25: invokevirtual #11                 // Method java/beans/PropertyChangeSupport.firePropertyChange:(Ljava/lang/String;Ljava/lang/Object;Ljava/lang/Object;)V
      28: aload_0
      29: areturn

  public java.lang.Boolean dumpSmap();
    Code:
       0: aload_0
       1: getfield      #18                 // Field dumpSmap:Ljava/lang/Boolean;
       4: areturn

  public T dumpSmap(java.lang.Boolean);
    Code:
       0: aload_0
       1: getfield      #18                 // Field dumpSmap:Ljava/lang/Boolean;
       4: astore_2
       5: aload_0
       6: aload_1
       7: putfield      #18                 // Field dumpSmap:Ljava/lang/Boolean;
      10: aload_0
      11: getfield      #6                  // Field pcs:Ljava/beans/PropertyChangeSupport;
      14: ifnull        28
      17: aload_0
      18: getfield      #6                  // Field pcs:Ljava/beans/PropertyChangeSupport;
      21: ldc           #19                 // String dumpSmap
      23: aload_2
      24: aload_1
      25: invokevirtual #11                 // Method java/beans/PropertyChangeSupport.firePropertyChange:(Ljava/lang/String;Ljava/lang/Object;Ljava/lang/Object;)V
      28: aload_0
      29: areturn

  public java.lang.Boolean errorOnUseBeanInvalidClassAttribute();
    Code:
       0: aload_0
       1: getfield      #20                 // Field errorOnUseBeanInvalidClassAttribute:Ljava/lang/Boolean;
       4: areturn

  public T errorOnUseBeanInvalidClassAttribute(java.lang.Boolean);
    Code:
       0: aload_0
       1: getfield      #20                 // Field errorOnUseBeanInvalidClassAttribute:Ljava/lang/Boolean;
       4: astore_2
       5: aload_0
       6: aload_1
       7: putfield      #20                 // Field errorOnUseBeanInvalidClassAttribute:Ljava/lang/Boolean;
      10: aload_0
      11: getfield      #6                  // Field pcs:Ljava/beans/PropertyChangeSupport;
      14: ifnull        28
      17: aload_0
      18: getfield      #6                  // Field pcs:Ljava/beans/PropertyChangeSupport;
      21: ldc           #21                 // String errorOnUseBeanInvalidClassAttribute
      23: aload_2
      24: aload_1
      25: invokevirtual #11                 // Method java/beans/PropertyChangeSupport.firePropertyChange:(Ljava/lang/String;Ljava/lang/Object;Ljava/lang/Object;)V
      28: aload_0
      29: areturn

  public java.lang.Boolean generateStringsAsCharArrays();
    Code:
       0: aload_0
       1: getfield      #22                 // Field generateStringsAsCharArrays:Ljava/lang/Boolean;
       4: areturn

  public T generateStringsAsCharArrays(java.lang.Boolean);
    Code:
       0: aload_0
       1: getfield      #22                 // Field generateStringsAsCharArrays:Ljava/lang/Boolean;
       4: astore_2
       5: aload_0
       6: aload_1
       7: putfield      #22                 // Field generateStringsAsCharArrays:Ljava/lang/Boolean;
      10: aload_0
      11: getfield      #6                  // Field pcs:Ljava/beans/PropertyChangeSupport;
      14: ifnull        28
      17: aload_0
      18: getfield      #6                  // Field pcs:Ljava/beans/PropertyChangeSupport;
      21: ldc           #23                 // String generateStringsAsCharArrays
      23: aload_2
      24: aload_1
      25: invokevirtual #11                 // Method java/beans/PropertyChangeSupport.firePropertyChange:(Ljava/lang/String;Ljava/lang/Object;Ljava/lang/Object;)V
      28: aload_0
      29: areturn

  public java.lang.String javaEncoding();
    Code:
       0: aload_0
       1: getfield      #24                 // Field javaEncoding:Ljava/lang/String;
       4: areturn

  public T javaEncoding(java.lang.String);
    Code:
       0: aload_0
       1: getfield      #24                 // Field javaEncoding:Ljava/lang/String;
       4: astore_2
       5: aload_0
       6: aload_1
       7: putfield      #24                 // Field javaEncoding:Ljava/lang/String;
      10: aload_0
      11: getfield      #6                  // Field pcs:Ljava/beans/PropertyChangeSupport;
      14: ifnull        28
      17: aload_0
      18: getfield      #6                  // Field pcs:Ljava/beans/PropertyChangeSupport;
      21: ldc           #25                 // String javaEncoding
      23: aload_2
      24: aload_1
      25: invokevirtual #11                 // Method java/beans/PropertyChangeSupport.firePropertyChange:(Ljava/lang/String;Ljava/lang/Object;Ljava/lang/Object;)V
      28: aload_0
      29: areturn

  public java.lang.Boolean keepGenerated();
    Code:
       0: aload_0
       1: getfield      #26                 // Field keepGenerated:Ljava/lang/Boolean;
       4: areturn

  public T keepGenerated(java.lang.Boolean);
    Code:
       0: aload_0
       1: getfield      #26                 // Field keepGenerated:Ljava/lang/Boolean;
       4: astore_2
       5: aload_0
       6: aload_1
       7: putfield      #26                 // Field keepGenerated:Ljava/lang/Boolean;
      10: aload_0
      11: getfield      #6                  // Field pcs:Ljava/beans/PropertyChangeSupport;
      14: ifnull        28
      17: aload_0
      18: getfield      #6                  // Field pcs:Ljava/beans/PropertyChangeSupport;
      21: ldc           #27                 // String keepGenerated
      23: aload_2
      24: aload_1
      25: invokevirtual #11                 // Method java/beans/PropertyChangeSupport.firePropertyChange:(Ljava/lang/String;Ljava/lang/Object;Ljava/lang/Object;)V
      28: aload_0
      29: areturn

  public java.lang.Boolean mappedFile();
    Code:
       0: aload_0
       1: getfield      #28                 // Field mappedFile:Ljava/lang/Boolean;
       4: areturn

  public T mappedFile(java.lang.Boolean);
    Code:
       0: aload_0
       1: getfield      #28                 // Field mappedFile:Ljava/lang/Boolean;
       4: astore_2
       5: aload_0
       6: aload_1
       7: putfield      #28                 // Field mappedFile:Ljava/lang/Boolean;
      10: aload_0
      11: getfield      #6                  // Field pcs:Ljava/beans/PropertyChangeSupport;
      14: ifnull        28
      17: aload_0
      18: getfield      #6                  // Field pcs:Ljava/beans/PropertyChangeSupport;
      21: ldc           #29                 // String mappedFile
      23: aload_2
      24: aload_1
      25: invokevirtual #11                 // Method java/beans/PropertyChangeSupport.firePropertyChange:(Ljava/lang/String;Ljava/lang/Object;Ljava/lang/Object;)V
      28: aload_0
      29: areturn

  public java.lang.Integer modificationTestInterval();
    Code:
       0: aload_0
       1: getfield      #30                 // Field modificationTestInterval:Ljava/lang/Integer;
       4: areturn

  public T modificationTestInterval(java.lang.Integer);
    Code:
       0: aload_0
       1: getfield      #30                 // Field modificationTestInterval:Ljava/lang/Integer;
       4: astore_2
       5: aload_0
       6: aload_1
       7: putfield      #30                 // Field modificationTestInterval:Ljava/lang/Integer;
      10: aload_0
      11: getfield      #6                  // Field pcs:Ljava/beans/PropertyChangeSupport;
      14: ifnull        28
      17: aload_0
      18: getfield      #6                  // Field pcs:Ljava/beans/PropertyChangeSupport;
      21: ldc           #31                 // String modificationTestInterval
      23: aload_2
      24: aload_1
      25: invokevirtual #11                 // Method java/beans/PropertyChangeSupport.firePropertyChange:(Ljava/lang/String;Ljava/lang/Object;Ljava/lang/Object;)V
      28: aload_0
      29: areturn

  public java.lang.Boolean optimizeScriptlets();
    Code:
       0: aload_0
       1: getfield      #32                 // Field optimizeScriptlets:Ljava/lang/Boolean;
       4: areturn

  public T optimizeScriptlets(java.lang.Boolean);
    Code:
       0: aload_0
       1: getfield      #32                 // Field optimizeScriptlets:Ljava/lang/Boolean;
       4: astore_2
       5: aload_0
       6: aload_1
       7: putfield      #32                 // Field optimizeScriptlets:Ljava/lang/Boolean;
      10: aload_0
      11: getfield      #6                  // Field pcs:Ljava/beans/PropertyChangeSupport;
      14: ifnull        28
      17: aload_0
      18: getfield      #6                  // Field pcs:Ljava/beans/PropertyChangeSupport;
      21: ldc           #33                 // String optimizeScriptlets
      23: aload_2
      24: aload_1
      25: invokevirtual #11                 // Method java/beans/PropertyChangeSupport.firePropertyChange:(Ljava/lang/String;Ljava/lang/Object;Ljava/lang/Object;)V
      28: aload_0
      29: areturn

  public java.lang.Boolean recompileOnFail();
    Code:
       0: aload_0
       1: getfield      #34                 // Field recompileOnFail:Ljava/lang/Boolean;
       4: areturn

  public T recompileOnFail(java.lang.Boolean);
    Code:
       0: aload_0
       1: getfield      #34                 // Field recompileOnFail:Ljava/lang/Boolean;
       4: astore_2
       5: aload_0
       6: aload_1
       7: putfield      #34                 // Field recompileOnFail:Ljava/lang/Boolean;
      10: aload_0
      11: getfield      #6                  // Field pcs:Ljava/beans/PropertyChangeSupport;
      14: ifnull        28
      17: aload_0
      18: getfield      #6                  // Field pcs:Ljava/beans/PropertyChangeSupport;
      21: ldc           #35                 // String recompileOnFail
      23: aload_2
      24: aload_1
      25: invokevirtual #11                 // Method java/beans/PropertyChangeSupport.firePropertyChange:(Ljava/lang/String;Ljava/lang/Object;Ljava/lang/Object;)V
      28: aload_0
      29: areturn

  public java.lang.String scratchDir();
    Code:
       0: aload_0
       1: getfield      #36                 // Field scratchDir:Ljava/lang/String;
       4: areturn

  public T scratchDir(java.lang.String);
    Code:
       0: aload_0
       1: getfield      #36                 // Field scratchDir:Ljava/lang/String;
       4: astore_2
       5: aload_0
       6: aload_1
       7: putfield      #36                 // Field scratchDir:Ljava/lang/String;
      10: aload_0
      11: getfield      #6                  // Field pcs:Ljava/beans/PropertyChangeSupport;
      14: ifnull        28
      17: aload_0
      18: getfield      #6                  // Field pcs:Ljava/beans/PropertyChangeSupport;
      21: ldc           #37                 // String scratchDir
      23: aload_2
      24: aload_1
      25: invokevirtual #11                 // Method java/beans/PropertyChangeSupport.firePropertyChange:(Ljava/lang/String;Ljava/lang/Object;Ljava/lang/Object;)V
      28: aload_0
      29: areturn

  public java.lang.Boolean smap();
    Code:
       0: aload_0
       1: getfield      #38                 // Field smap:Ljava/lang/Boolean;
       4: areturn

  public T smap(java.lang.Boolean);
    Code:
       0: aload_0
       1: getfield      #38                 // Field smap:Ljava/lang/Boolean;
       4: astore_2
       5: aload_0
       6: aload_1
       7: putfield      #38                 // Field smap:Ljava/lang/Boolean;
      10: aload_0
      11: getfield      #6                  // Field pcs:Ljava/beans/PropertyChangeSupport;
      14: ifnull        28
      17: aload_0
      18: getfield      #6                  // Field pcs:Ljava/beans/PropertyChangeSupport;
      21: ldc           #39                 // String smap
      23: aload_2
      24: aload_1
      25: invokevirtual #11                 // Method java/beans/PropertyChangeSupport.firePropertyChange:(Ljava/lang/String;Ljava/lang/Object;Ljava/lang/Object;)V
      28: aload_0
      29: areturn

  public java.lang.String sourceVm();
    Code:
       0: aload_0
       1: getfield      #40                 // Field sourceVm:Ljava/lang/String;
       4: areturn

  public T sourceVm(java.lang.String);
    Code:
       0: aload_0
       1: getfield      #40                 // Field sourceVm:Ljava/lang/String;
       4: astore_2
       5: aload_0
       6: aload_1
       7: putfield      #40                 // Field sourceVm:Ljava/lang/String;
      10: aload_0
      11: getfield      #6                  // Field pcs:Ljava/beans/PropertyChangeSupport;
      14: ifnull        28
      17: aload_0
      18: getfield      #6                  // Field pcs:Ljava/beans/PropertyChangeSupport;
      21: ldc           #41                 // String sourceVm
      23: aload_2
      24: aload_1
      25: invokevirtual #11                 // Method java/beans/PropertyChangeSupport.firePropertyChange:(Ljava/lang/String;Ljava/lang/Object;Ljava/lang/Object;)V
      28: aload_0
      29: areturn

  public java.lang.Boolean tagPooling();
    Code:
       0: aload_0
       1: getfield      #42                 // Field tagPooling:Ljava/lang/Boolean;
       4: areturn

  public T tagPooling(java.lang.Boolean);
    Code:
       0: aload_0
       1: getfield      #42                 // Field tagPooling:Ljava/lang/Boolean;
       4: astore_2
       5: aload_0
       6: aload_1
       7: putfield      #42                 // Field tagPooling:Ljava/lang/Boolean;
      10: aload_0
      11: getfield      #6                  // Field pcs:Ljava/beans/PropertyChangeSupport;
      14: ifnull        28
      17: aload_0
      18: getfield      #6                  // Field pcs:Ljava/beans/PropertyChangeSupport;
      21: ldc           #43                 // String tagPooling
      23: aload_2
      24: aload_1
      25: invokevirtual #11                 // Method java/beans/PropertyChangeSupport.firePropertyChange:(Ljava/lang/String;Ljava/lang/Object;Ljava/lang/Object;)V
      28: aload_0
      29: areturn

  public java.lang.String targetVm();
    Code:
       0: aload_0
       1: getfield      #44                 // Field targetVm:Ljava/lang/String;
       4: areturn

  public T targetVm(java.lang.String);
    Code:
       0: aload_0
       1: getfield      #44                 // Field targetVm:Ljava/lang/String;
       4: astore_2
       5: aload_0
       6: aload_1
       7: putfield      #44                 // Field targetVm:Ljava/lang/String;
      10: aload_0
      11: getfield      #6                  // Field pcs:Ljava/beans/PropertyChangeSupport;
      14: ifnull        28
      17: aload_0
      18: getfield      #6                  // Field pcs:Ljava/beans/PropertyChangeSupport;
      21: ldc           #45                 // String targetVm
      23: aload_2
      24: aload_1
      25: invokevirtual #11                 // Method java/beans/PropertyChangeSupport.firePropertyChange:(Ljava/lang/String;Ljava/lang/Object;Ljava/lang/Object;)V
      28: aload_0
      29: areturn

  public java.lang.Boolean trimSpaces();
    Code:
       0: aload_0
       1: getfield      #46                 // Field trimSpaces:Ljava/lang/Boolean;
       4: areturn

  public T trimSpaces(java.lang.Boolean);
    Code:
       0: aload_0
       1: getfield      #46                 // Field trimSpaces:Ljava/lang/Boolean;
       4: astore_2
       5: aload_0
       6: aload_1
       7: putfield      #46                 // Field trimSpaces:Ljava/lang/Boolean;
      10: aload_0
      11: getfield      #6                  // Field pcs:Ljava/beans/PropertyChangeSupport;
      14: ifnull        28
      17: aload_0
      18: getfield      #6                  // Field pcs:Ljava/beans/PropertyChangeSupport;
      21: ldc           #47                 // String trimSpaces
      23: aload_2
      24: aload_1
      25: invokevirtual #11                 // Method java/beans/PropertyChangeSupport.firePropertyChange:(Ljava/lang/String;Ljava/lang/Object;Ljava/lang/Object;)V
      28: aload_0
      29: areturn

  public java.lang.Boolean xPoweredBy();
    Code:
       0: aload_0
       1: getfield      #48                 // Field xPoweredBy:Ljava/lang/Boolean;
       4: areturn

  public T xPoweredBy(java.lang.Boolean);
    Code:
       0: aload_0
       1: getfield      #48                 // Field xPoweredBy:Ljava/lang/Boolean;
       4: astore_2
       5: aload_0
       6: aload_1
       7: putfield      #48                 // Field xPoweredBy:Ljava/lang/Boolean;
      10: aload_0
      11: getfield      #6                  // Field pcs:Ljava/beans/PropertyChangeSupport;
      14: ifnull        28
      17: aload_0
      18: getfield      #6                  // Field pcs:Ljava/beans/PropertyChangeSupport;
      21: ldc           #49                 // String xPoweredBy
      23: aload_2
      24: aload_1
      25: invokevirtual #11                 // Method java/beans/PropertyChangeSupport.firePropertyChange:(Ljava/lang/String;Ljava/lang/Object;Ljava/lang/Object;)V
      28: aload_0
      29: areturn
}
