Compiled from "AbstractAWSDirectoryService.java"
public class com.amazonaws.services.directory.AbstractAWSDirectoryService implements com.amazonaws.services.directory.AWSDirectoryService {
  protected com.amazonaws.services.directory.AbstractAWSDirectoryService();
    Code:
       0: aload_0
       1: invokespecial #1                  // Method java/lang/Object."<init>":()V
       4: return

  public void setEndpoint(java.lang.String);
    Code:
       0: new           #2                  // class java/lang/UnsupportedOperationException
       3: dup
       4: invokespecial #3                  // Method java/lang/UnsupportedOperationException."<init>":()V
       7: athrow

  public void setRegion(com.amazonaws.regions.Region);
    Code:
       0: new           #2                  // class java/lang/UnsupportedOperationException
       3: dup
       4: invokespecial #3                  // Method java/lang/UnsupportedOperationException."<init>":()V
       7: athrow

  public com.amazonaws.services.directory.model.AddTagsToResourceResult addTagsToResource(com.amazonaws.services.directory.model.AddTagsToResourceRequest);
    Code:
       0: new           #2                  // class java/lang/UnsupportedOperationException
       3: dup
       4: invokespecial #3                  // Method java/lang/UnsupportedOperationException."<init>":()V
       7: athrow

  public com.amazonaws.services.directory.model.ConnectDirectoryResult connectDirectory(com.amazonaws.services.directory.model.ConnectDirectoryRequest);
    Code:
       0: new           #2                  // class java/lang/UnsupportedOperationException
       3: dup
       4: invokespecial #3                  // Method java/lang/UnsupportedOperationException."<init>":()V
       7: athrow

  public com.amazonaws.services.directory.model.CreateAliasResult createAlias(com.amazonaws.services.directory.model.CreateAliasRequest);
    Code:
       0: new           #2                  // class java/lang/UnsupportedOperationException
       3: dup
       4: invokespecial #3                  // Method java/lang/UnsupportedOperationException."<init>":()V
       7: athrow

  public com.amazonaws.services.directory.model.CreateComputerResult createComputer(com.amazonaws.services.directory.model.CreateComputerRequest);
    Code:
       0: new           #2                  // class java/lang/UnsupportedOperationException
       3: dup
       4: invokespecial #3                  // Method java/lang/UnsupportedOperationException."<init>":()V
       7: athrow

  public com.amazonaws.services.directory.model.CreateConditionalForwarderResult createConditionalForwarder(com.amazonaws.services.directory.model.CreateConditionalForwarderRequest);
    Code:
       0: new           #2                  // class java/lang/UnsupportedOperationException
       3: dup
       4: invokespecial #3                  // Method java/lang/UnsupportedOperationException."<init>":()V
       7: athrow

  public com.amazonaws.services.directory.model.CreateDirectoryResult createDirectory(com.amazonaws.services.directory.model.CreateDirectoryRequest);
    Code:
       0: new           #2                  // class java/lang/UnsupportedOperationException
       3: dup
       4: invokespecial #3                  // Method java/lang/UnsupportedOperationException."<init>":()V
       7: athrow

  public com.amazonaws.services.directory.model.CreateMicrosoftADResult createMicrosoftAD(com.amazonaws.services.directory.model.CreateMicrosoftADRequest);
    Code:
       0: new           #2                  // class java/lang/UnsupportedOperationException
       3: dup
       4: invokespecial #3                  // Method java/lang/UnsupportedOperationException."<init>":()V
       7: athrow

  public com.amazonaws.services.directory.model.CreateSnapshotResult createSnapshot(com.amazonaws.services.directory.model.CreateSnapshotRequest);
    Code:
       0: new           #2                  // class java/lang/UnsupportedOperationException
       3: dup
       4: invokespecial #3                  // Method java/lang/UnsupportedOperationException."<init>":()V
       7: athrow

  public com.amazonaws.services.directory.model.CreateTrustResult createTrust(com.amazonaws.services.directory.model.CreateTrustRequest);
    Code:
       0: new           #2                  // class java/lang/UnsupportedOperationException
       3: dup
       4: invokespecial #3                  // Method java/lang/UnsupportedOperationException."<init>":()V
       7: athrow

  public com.amazonaws.services.directory.model.DeleteConditionalForwarderResult deleteConditionalForwarder(com.amazonaws.services.directory.model.DeleteConditionalForwarderRequest);
    Code:
       0: new           #2                  // class java/lang/UnsupportedOperationException
       3: dup
       4: invokespecial #3                  // Method java/lang/UnsupportedOperationException."<init>":()V
       7: athrow

  public com.amazonaws.services.directory.model.DeleteDirectoryResult deleteDirectory(com.amazonaws.services.directory.model.DeleteDirectoryRequest);
    Code:
       0: new           #2                  // class java/lang/UnsupportedOperationException
       3: dup
       4: invokespecial #3                  // Method java/lang/UnsupportedOperationException."<init>":()V
       7: athrow

  public com.amazonaws.services.directory.model.DeleteSnapshotResult deleteSnapshot(com.amazonaws.services.directory.model.DeleteSnapshotRequest);
    Code:
       0: new           #2                  // class java/lang/UnsupportedOperationException
       3: dup
       4: invokespecial #3                  // Method java/lang/UnsupportedOperationException."<init>":()V
       7: athrow

  public com.amazonaws.services.directory.model.DeleteTrustResult deleteTrust(com.amazonaws.services.directory.model.DeleteTrustRequest);
    Code:
       0: new           #2                  // class java/lang/UnsupportedOperationException
       3: dup
       4: invokespecial #3                  // Method java/lang/UnsupportedOperationException."<init>":()V
       7: athrow

  public com.amazonaws.services.directory.model.DeregisterEventTopicResult deregisterEventTopic(com.amazonaws.services.directory.model.DeregisterEventTopicRequest);
    Code:
       0: new           #2                  // class java/lang/UnsupportedOperationException
       3: dup
       4: invokespecial #3                  // Method java/lang/UnsupportedOperationException."<init>":()V
       7: athrow

  public com.amazonaws.services.directory.model.DescribeConditionalForwardersResult describeConditionalForwarders(com.amazonaws.services.directory.model.DescribeConditionalForwardersRequest);
    Code:
       0: new           #2                  // class java/lang/UnsupportedOperationException
       3: dup
       4: invokespecial #3                  // Method java/lang/UnsupportedOperationException."<init>":()V
       7: athrow

  public com.amazonaws.services.directory.model.DescribeDirectoriesResult describeDirectories(com.amazonaws.services.directory.model.DescribeDirectoriesRequest);
    Code:
       0: new           #2                  // class java/lang/UnsupportedOperationException
       3: dup
       4: invokespecial #3                  // Method java/lang/UnsupportedOperationException."<init>":()V
       7: athrow

  public com.amazonaws.services.directory.model.DescribeDirectoriesResult describeDirectories();
    Code:
       0: aload_0
       1: new           #4                  // class com/amazonaws/services/directory/model/DescribeDirectoriesRequest
       4: dup
       5: invokespecial #5                  // Method com/amazonaws/services/directory/model/DescribeDirectoriesRequest."<init>":()V
       8: invokevirtual #6                  // Method describeDirectories:(Lcom/amazonaws/services/directory/model/DescribeDirectoriesRequest;)Lcom/amazonaws/services/directory/model/DescribeDirectoriesResult;
      11: areturn

  public com.amazonaws.services.directory.model.DescribeEventTopicsResult describeEventTopics(com.amazonaws.services.directory.model.DescribeEventTopicsRequest);
    Code:
       0: new           #2                  // class java/lang/UnsupportedOperationException
       3: dup
       4: invokespecial #3                  // Method java/lang/UnsupportedOperationException."<init>":()V
       7: athrow

  public com.amazonaws.services.directory.model.DescribeSnapshotsResult describeSnapshots(com.amazonaws.services.directory.model.DescribeSnapshotsRequest);
    Code:
       0: new           #2                  // class java/lang/UnsupportedOperationException
       3: dup
       4: invokespecial #3                  // Method java/lang/UnsupportedOperationException."<init>":()V
       7: athrow

  public com.amazonaws.services.directory.model.DescribeSnapshotsResult describeSnapshots();
    Code:
       0: aload_0
       1: new           #7                  // class com/amazonaws/services/directory/model/DescribeSnapshotsRequest
       4: dup
       5: invokespecial #8                  // Method com/amazonaws/services/directory/model/DescribeSnapshotsRequest."<init>":()V
       8: invokevirtual #9                  // Method describeSnapshots:(Lcom/amazonaws/services/directory/model/DescribeSnapshotsRequest;)Lcom/amazonaws/services/directory/model/DescribeSnapshotsResult;
      11: areturn

  public com.amazonaws.services.directory.model.DescribeTrustsResult describeTrusts(com.amazonaws.services.directory.model.DescribeTrustsRequest);
    Code:
       0: new           #2                  // class java/lang/UnsupportedOperationException
       3: dup
       4: invokespecial #3                  // Method java/lang/UnsupportedOperationException."<init>":()V
       7: athrow

  public com.amazonaws.services.directory.model.DisableRadiusResult disableRadius(com.amazonaws.services.directory.model.DisableRadiusRequest);
    Code:
       0: new           #2                  // class java/lang/UnsupportedOperationException
       3: dup
       4: invokespecial #3                  // Method java/lang/UnsupportedOperationException."<init>":()V
       7: athrow

  public com.amazonaws.services.directory.model.DisableSsoResult disableSso(com.amazonaws.services.directory.model.DisableSsoRequest);
    Code:
       0: new           #2                  // class java/lang/UnsupportedOperationException
       3: dup
       4: invokespecial #3                  // Method java/lang/UnsupportedOperationException."<init>":()V
       7: athrow

  public com.amazonaws.services.directory.model.EnableRadiusResult enableRadius(com.amazonaws.services.directory.model.EnableRadiusRequest);
    Code:
       0: new           #2                  // class java/lang/UnsupportedOperationException
       3: dup
       4: invokespecial #3                  // Method java/lang/UnsupportedOperationException."<init>":()V
       7: athrow

  public com.amazonaws.services.directory.model.EnableSsoResult enableSso(com.amazonaws.services.directory.model.EnableSsoRequest);
    Code:
       0: new           #2                  // class java/lang/UnsupportedOperationException
       3: dup
       4: invokespecial #3                  // Method java/lang/UnsupportedOperationException."<init>":()V
       7: athrow

  public com.amazonaws.services.directory.model.GetDirectoryLimitsResult getDirectoryLimits(com.amazonaws.services.directory.model.GetDirectoryLimitsRequest);
    Code:
       0: new           #2                  // class java/lang/UnsupportedOperationException
       3: dup
       4: invokespecial #3                  // Method java/lang/UnsupportedOperationException."<init>":()V
       7: athrow

  public com.amazonaws.services.directory.model.GetDirectoryLimitsResult getDirectoryLimits();
    Code:
       0: aload_0
       1: new           #10                 // class com/amazonaws/services/directory/model/GetDirectoryLimitsRequest
       4: dup
       5: invokespecial #11                 // Method com/amazonaws/services/directory/model/GetDirectoryLimitsRequest."<init>":()V
       8: invokevirtual #12                 // Method getDirectoryLimits:(Lcom/amazonaws/services/directory/model/GetDirectoryLimitsRequest;)Lcom/amazonaws/services/directory/model/GetDirectoryLimitsResult;
      11: areturn

  public com.amazonaws.services.directory.model.GetSnapshotLimitsResult getSnapshotLimits(com.amazonaws.services.directory.model.GetSnapshotLimitsRequest);
    Code:
       0: new           #2                  // class java/lang/UnsupportedOperationException
       3: dup
       4: invokespecial #3                  // Method java/lang/UnsupportedOperationException."<init>":()V
       7: athrow

  public com.amazonaws.services.directory.model.ListTagsForResourceResult listTagsForResource(com.amazonaws.services.directory.model.ListTagsForResourceRequest);
    Code:
       0: new           #2                  // class java/lang/UnsupportedOperationException
       3: dup
       4: invokespecial #3                  // Method java/lang/UnsupportedOperationException."<init>":()V
       7: athrow

  public com.amazonaws.services.directory.model.RegisterEventTopicResult registerEventTopic(com.amazonaws.services.directory.model.RegisterEventTopicRequest);
    Code:
       0: new           #2                  // class java/lang/UnsupportedOperationException
       3: dup
       4: invokespecial #3                  // Method java/lang/UnsupportedOperationException."<init>":()V
       7: athrow

  public com.amazonaws.services.directory.model.RemoveTagsFromResourceResult removeTagsFromResource(com.amazonaws.services.directory.model.RemoveTagsFromResourceRequest);
    Code:
       0: new           #2                  // class java/lang/UnsupportedOperationException
       3: dup
       4: invokespecial #3                  // Method java/lang/UnsupportedOperationException."<init>":()V
       7: athrow

  public com.amazonaws.services.directory.model.RestoreFromSnapshotResult restoreFromSnapshot(com.amazonaws.services.directory.model.RestoreFromSnapshotRequest);
    Code:
       0: new           #2                  // class java/lang/UnsupportedOperationException
       3: dup
       4: invokespecial #3                  // Method java/lang/UnsupportedOperationException."<init>":()V
       7: athrow

  public com.amazonaws.services.directory.model.UpdateConditionalForwarderResult updateConditionalForwarder(com.amazonaws.services.directory.model.UpdateConditionalForwarderRequest);
    Code:
       0: new           #2                  // class java/lang/UnsupportedOperationException
       3: dup
       4: invokespecial #3                  // Method java/lang/UnsupportedOperationException."<init>":()V
       7: athrow

  public com.amazonaws.services.directory.model.UpdateRadiusResult updateRadius(com.amazonaws.services.directory.model.UpdateRadiusRequest);
    Code:
       0: new           #2                  // class java/lang/UnsupportedOperationException
       3: dup
       4: invokespecial #3                  // Method java/lang/UnsupportedOperationException."<init>":()V
       7: athrow

  public com.amazonaws.services.directory.model.VerifyTrustResult verifyTrust(com.amazonaws.services.directory.model.VerifyTrustRequest);
    Code:
       0: new           #2                  // class java/lang/UnsupportedOperationException
       3: dup
       4: invokespecial #3                  // Method java/lang/UnsupportedOperationException."<init>":()V
       7: athrow

  public void shutdown();
    Code:
       0: new           #2                  // class java/lang/UnsupportedOperationException
       3: dup
       4: invokespecial #3                  // Method java/lang/UnsupportedOperationException."<init>":()V
       7: athrow

  public com.amazonaws.ResponseMetadata getCachedResponseMetadata(com.amazonaws.AmazonWebServiceRequest);
    Code:
       0: new           #2                  // class java/lang/UnsupportedOperationException
       3: dup
       4: invokespecial #3                  // Method java/lang/UnsupportedOperationException."<init>":()V
       7: athrow
}
