Compiled from "ArgumentState.java"
class org.jboss.as.cli.parsing.command.ArgumentState$1 implements org.jboss.as.cli.parsing.CharacterHandler {
  final org.jboss.as.cli.parsing.command.ArgumentState this$0;

  org.jboss.as.cli.parsing.command.ArgumentState$1(org.jboss.as.cli.parsing.command.ArgumentState);
    Code:
       0: aload_0
       1: aload_1
       2: putfield      #1                  // Field this$0:Lorg/jboss/as/cli/parsing/command/ArgumentState;
       5: aload_0
       6: invokespecial #2                  // Method java/lang/Object."<init>":()V
       9: return

  public void handle(org.jboss.as.cli.parsing.ParsingContext) throws org.jboss.as.cli.CommandFormatException;
    Code:
       0: aload_1
       1: iconst_1
       2: iconst_1
       3: invokeinterface #3,  3            // InterfaceMethod org/jboss/as/cli/parsing/ParsingContext.resolveExpression:(ZZ)V
       8: getstatic     #4                  // Field org/jboss/as/cli/parsing/WordCharacterHandler.IGNORE_LB_ESCAPE_ON:Lorg/jboss/as/cli/parsing/WordCharacterHandler;
      11: aload_1
      12: invokevirtual #5                  // Method org/jboss/as/cli/parsing/WordCharacterHandler.handle:(Lorg/jboss/as/cli/parsing/ParsingContext;)V
      15: return
}
