Compiled from "CommandNameState.java"
public class org.jboss.as.cli.parsing.command.CommandNameState extends org.jboss.as.cli.parsing.ExpressionBaseState {
  public static final org.jboss.as.cli.parsing.command.CommandNameState INSTANCE;

  public static final java.lang.String ID;

  org.jboss.as.cli.parsing.command.CommandNameState();
    Code:
       0: aload_0
       1: ldc           #2                  // String OP_NAME
       3: invokespecial #3                  // Method org/jboss/as/cli/parsing/ExpressionBaseState."<init>":(Ljava/lang/String;)V
       6: aload_0
       7: iconst_1
       8: invokevirtual #4                  // Method setLeaveOnWhitespace:(Z)V
      11: aload_0
      12: new           #5                  // class org/jboss/as/cli/parsing/command/CommandNameState$1
      15: dup
      16: aload_0
      17: invokespecial #6                  // Method org/jboss/as/cli/parsing/command/CommandNameState$1."<init>":(Lorg/jboss/as/cli/parsing/command/CommandNameState;)V
      20: invokevirtual #7                  // Method setEnterHandler:(Lorg/jboss/as/cli/parsing/CharacterHandler;)V
      23: aload_0
      24: getstatic     #8                  // Field org/jboss/as/cli/parsing/WordCharacterHandler.LB_LEAVE_ESCAPE_ON:Lorg/jboss/as/cli/parsing/WordCharacterHandler;
      27: invokevirtual #9                  // Method setDefaultHandler:(Lorg/jboss/as/cli/parsing/CharacterHandler;)V
      30: return

  static {};
    Code:
       0: new           #1                  // class org/jboss/as/cli/parsing/command/CommandNameState
       3: dup
       4: invokespecial #10                 // Method "<init>":()V
       7: putstatic     #11                 // Field INSTANCE:Lorg/jboss/as/cli/parsing/command/CommandNameState;
      10: return
}
