Compiled from "ServingCheckDataImpl.java"
public class org.mobicents.protocols.ss7.map.dialog.ServingCheckDataImpl implements org.mobicents.protocols.ss7.map.api.dialog.ServingCheckData {
  private org.mobicents.protocols.ss7.map.api.dialog.ServingCheckResult result;

  private org.mobicents.protocols.ss7.tcap.asn.ApplicationContextName alternativeApplicationContext;

  public org.mobicents.protocols.ss7.map.dialog.ServingCheckDataImpl(org.mobicents.protocols.ss7.map.api.dialog.ServingCheckResult);
    Code:
       0: aload_0
       1: invokespecial #1                  // Method java/lang/Object."<init>":()V
       4: aload_0
       5: aconst_null
       6: putfield      #2                  // Field alternativeApplicationContext:Lorg/mobicents/protocols/ss7/tcap/asn/ApplicationContextName;
       9: aload_0
      10: aload_1
      11: putfield      #3                  // Field result:Lorg/mobicents/protocols/ss7/map/api/dialog/ServingCheckResult;
      14: return

  public org.mobicents.protocols.ss7.map.dialog.ServingCheckDataImpl(org.mobicents.protocols.ss7.map.api.dialog.ServingCheckResult, org.mobicents.protocols.ss7.tcap.asn.ApplicationContextName);
    Code:
       0: aload_0
       1: invokespecial #1                  // Method java/lang/Object."<init>":()V
       4: aload_0
       5: aconst_null
       6: putfield      #2                  // Field alternativeApplicationContext:Lorg/mobicents/protocols/ss7/tcap/asn/ApplicationContextName;
       9: aload_0
      10: aload_1
      11: putfield      #3                  // Field result:Lorg/mobicents/protocols/ss7/map/api/dialog/ServingCheckResult;
      14: aload_0
      15: aload_2
      16: putfield      #2                  // Field alternativeApplicationContext:Lorg/mobicents/protocols/ss7/tcap/asn/ApplicationContextName;
      19: return

  public org.mobicents.protocols.ss7.map.api.dialog.ServingCheckResult getResult();
    Code:
       0: aload_0
       1: getfield      #3                  // Field result:Lorg/mobicents/protocols/ss7/map/api/dialog/ServingCheckResult;
       4: areturn

  public org.mobicents.protocols.ss7.tcap.asn.ApplicationContextName getAlternativeApplicationContext();
    Code:
       0: aload_0
       1: getfield      #2                  // Field alternativeApplicationContext:Lorg/mobicents/protocols/ss7/tcap/asn/ApplicationContextName;
       4: areturn
}
