Compiled from "IntegerValueTypeConstructor.kt"
public final class kotlin.reflect.jvm.internal.impl.resolve.constants.IntegerValueTypeConstructor implements kotlin.reflect.jvm.internal.impl.types.TypeConstructor {
  private final long value;

  private final kotlin.reflect.jvm.internal.impl.descriptors.ModuleDescriptor module;

  private final java.util.ArrayList<kotlin.reflect.jvm.internal.impl.types.KotlinType> supertypes;

  public java.util.Collection<kotlin.reflect.jvm.internal.impl.types.KotlinType> getSupertypes();
    Code:
       0: aload_0
       1: getfield      #15                 // Field supertypes:Ljava/util/ArrayList;
       4: checkcast     #5                  // class java/util/Collection
       7: areturn

  public java.util.List<kotlin.reflect.jvm.internal.impl.descriptors.TypeParameterDescriptor> getParameters();
    Code:
       0: invokestatic  #22                 // Method kotlin/collections/CollectionsKt.emptyList:()Ljava/util/List;
       3: areturn

  public boolean isDenotable();
    Code:
       0: iconst_0
       1: ireturn

  public java.lang.Void getDeclarationDescriptor();
    Code:
       0: aconst_null
       1: areturn

  public kotlin.reflect.jvm.internal.impl.builtins.KotlinBuiltIns getBuiltIns();
    Code:
       0: aload_0
       1: getfield      #14                 // Field module:Lkotlin/reflect/jvm/internal/impl/descriptors/ModuleDescriptor;
       4: invokeinterface #25,  1           // InterfaceMethod kotlin/reflect/jvm/internal/impl/descriptors/ModuleDescriptor.getBuiltIns:()Lkotlin/reflect/jvm/internal/impl/builtins/KotlinBuiltIns;
       9: areturn

  public kotlin.reflect.jvm.internal.impl.types.TypeConstructor refine(kotlin.reflect.jvm.internal.impl.types.checker.KotlinTypeRefiner);
    Code:
       0: aload_1
       1: ldc           #2                  // String kotlinTypeRefiner
       3: invokestatic  #23                 // Method kotlin/jvm/internal/Intrinsics.checkNotNullParameter:(Ljava/lang/Object;Ljava/lang/String;)V
       6: aload_0
       7: checkcast     #13                 // class kotlin/reflect/jvm/internal/impl/types/TypeConstructor
      10: areturn

  public java.lang.String toString();
    Code:
       0: new           #4                  // class java/lang/StringBuilder
       3: dup
       4: invokespecial #17                 // Method java/lang/StringBuilder."<init>":()V
       7: ldc           #1                  // String IntegerValueType(
       9: invokevirtual #20                 // Method java/lang/StringBuilder.append:(Ljava/lang/String;)Ljava/lang/StringBuilder;
      12: aload_0
      13: getfield      #16                 // Field value:J
      16: invokevirtual #19                 // Method java/lang/StringBuilder.append:(J)Ljava/lang/StringBuilder;
      19: bipush        41
      21: invokevirtual #18                 // Method java/lang/StringBuilder.append:(C)Ljava/lang/StringBuilder;
      24: invokevirtual #21                 // Method java/lang/StringBuilder.toString:()Ljava/lang/String;
      27: areturn

  public kotlin.reflect.jvm.internal.impl.descriptors.ClassifierDescriptor getDeclarationDescriptor();
    Code:
       0: aload_0
       1: invokevirtual #24                 // Method getDeclarationDescriptor:()Ljava/lang/Void;
       4: checkcast     #10                 // class kotlin/reflect/jvm/internal/impl/descriptors/ClassifierDescriptor
       7: areturn
}
