Compiled from "V1Span.java"
public final class zipkin2.v1.V1Span {
  static final zipkin2.Endpoint EMPTY_ENDPOINT;

  final long traceIdHigh;

  final long traceId;

  final long id;

  final java.lang.String name;

  final long parentId;

  final long timestamp;

  final long duration;

  final java.util.List<zipkin2.v1.V1Annotation> annotations;

  final java.util.List<zipkin2.v1.V1BinaryAnnotation> binaryAnnotations;

  final java.lang.Boolean debug;

  public long traceIdHigh();
    Code:
       0: aload_0
       1: getfield      #34                 // Field traceIdHigh:J
       4: lreturn

  public long traceId();
    Code:
       0: aload_0
       1: getfield      #38                 // Field traceId:J
       4: lreturn

  public long id();
    Code:
       0: aload_0
       1: getfield      #40                 // Field id:J
       4: lreturn

  public java.lang.String name();
    Code:
       0: aload_0
       1: getfield      #43                 // Field name:Ljava/lang/String;
       4: areturn

  public long parentId();
    Code:
       0: aload_0
       1: getfield      #45                 // Field parentId:J
       4: lreturn

  public long timestamp();
    Code:
       0: aload_0
       1: getfield      #47                 // Field timestamp:J
       4: lreturn

  public long duration();
    Code:
       0: aload_0
       1: getfield      #49                 // Field duration:J
       4: lreturn

  public java.util.List<zipkin2.v1.V1Annotation> annotations();
    Code:
       0: aload_0
       1: getfield      #53                 // Field annotations:Ljava/util/List;
       4: areturn

  public java.util.List<zipkin2.v1.V1BinaryAnnotation> binaryAnnotations();
    Code:
       0: aload_0
       1: getfield      #56                 // Field binaryAnnotations:Ljava/util/List;
       4: areturn

  public java.lang.Boolean debug();
    Code:
       0: aload_0
       1: getfield      #59                 // Field debug:Ljava/lang/Boolean;
       4: areturn

  public java.util.Set<java.lang.String> serviceNames();
    Code:
       0: new           #64                 // class java/util/LinkedHashSet
       3: dup
       4: invokespecial #68                 // Method java/util/LinkedHashSet."<init>":()V
       7: astore_1
       8: aload_0
       9: getfield      #53                 // Field annotations:Ljava/util/List;
      12: invokeinterface #74,  1           // InterfaceMethod java/util/List.iterator:()Ljava/util/Iterator;
      17: astore_2
      18: aload_2
      19: invokeinterface #82,  1           // InterfaceMethod java/util/Iterator.hasNext:()Z
      24: ifeq          77
      27: aload_2
      28: invokeinterface #86,  1           // InterfaceMethod java/util/Iterator.next:()Ljava/lang/Object;
      33: checkcast     #88                 // class zipkin2/v1/V1Annotation
      36: astore_3
      37: aload_3
      38: getfield      #91                 // Field zipkin2/v1/V1Annotation.endpoint:Lzipkin2/Endpoint;
      41: ifnonnull     47
      44: goto          18
      47: aload_3
      48: getfield      #91                 // Field zipkin2/v1/V1Annotation.endpoint:Lzipkin2/Endpoint;
      51: invokevirtual #94                 // Method zipkin2/Endpoint.serviceName:()Ljava/lang/String;
      54: ifnonnull     60
      57: goto          18
      60: aload_1
      61: aload_3
      62: getfield      #91                 // Field zipkin2/v1/V1Annotation.endpoint:Lzipkin2/Endpoint;
      65: invokevirtual #94                 // Method zipkin2/Endpoint.serviceName:()Ljava/lang/String;
      68: invokeinterface #98,  2           // InterfaceMethod java/util/Set.add:(Ljava/lang/Object;)Z
      73: pop
      74: goto          18
      77: aload_0
      78: getfield      #56                 // Field binaryAnnotations:Ljava/util/List;
      81: invokeinterface #74,  1           // InterfaceMethod java/util/List.iterator:()Ljava/util/Iterator;
      86: astore_2
      87: aload_2
      88: invokeinterface #82,  1           // InterfaceMethod java/util/Iterator.hasNext:()Z
      93: ifeq          146
      96: aload_2
      97: invokeinterface #86,  1           // InterfaceMethod java/util/Iterator.next:()Ljava/lang/Object;
     102: checkcast     #100                // class zipkin2/v1/V1BinaryAnnotation
     105: astore_3
     106: aload_3
     107: getfield      #101                // Field zipkin2/v1/V1BinaryAnnotation.endpoint:Lzipkin2/Endpoint;
     110: ifnonnull     116
     113: goto          87
     116: aload_3
     117: getfield      #101                // Field zipkin2/v1/V1BinaryAnnotation.endpoint:Lzipkin2/Endpoint;
     120: invokevirtual #94                 // Method zipkin2/Endpoint.serviceName:()Ljava/lang/String;
     123: ifnonnull     129
     126: goto          87
     129: aload_1
     130: aload_3
     131: getfield      #101                // Field zipkin2/v1/V1BinaryAnnotation.endpoint:Lzipkin2/Endpoint;
     134: invokevirtual #94                 // Method zipkin2/Endpoint.serviceName:()Ljava/lang/String;
     137: invokeinterface #98,  2           // InterfaceMethod java/util/Set.add:(Ljava/lang/Object;)Z
     142: pop
     143: goto          87
     146: aload_1
     147: areturn

  zipkin2.v1.V1Span(zipkin2.v1.V1Span$Builder);
    Code:
       0: aload_0
       1: invokespecial #109                // Method java/lang/Object."<init>":()V
       4: aload_1
       5: getfield      #110                // Field zipkin2/v1/V1Span$Builder.traceId:J
       8: lconst_0
       9: lcmp
      10: ifne          23
      13: new           #112                // class java/lang/IllegalArgumentException
      16: dup
      17: ldc           #114                // String traceId == 0
      19: invokespecial #117                // Method java/lang/IllegalArgumentException."<init>":(Ljava/lang/String;)V
      22: athrow
      23: aload_1
      24: getfield      #118                // Field zipkin2/v1/V1Span$Builder.id:J
      27: lconst_0
      28: lcmp
      29: ifne          42
      32: new           #112                // class java/lang/IllegalArgumentException
      35: dup
      36: ldc           #120                // String id == 0
      38: invokespecial #117                // Method java/lang/IllegalArgumentException."<init>":(Ljava/lang/String;)V
      41: athrow
      42: aload_0
      43: aload_1
      44: getfield      #110                // Field zipkin2/v1/V1Span$Builder.traceId:J
      47: putfield      #38                 // Field traceId:J
      50: aload_0
      51: aload_1
      52: getfield      #121                // Field zipkin2/v1/V1Span$Builder.traceIdHigh:J
      55: putfield      #34                 // Field traceIdHigh:J
      58: aload_0
      59: aload_1
      60: getfield      #122                // Field zipkin2/v1/V1Span$Builder.name:Ljava/lang/String;
      63: putfield      #43                 // Field name:Ljava/lang/String;
      66: aload_0
      67: aload_1
      68: getfield      #118                // Field zipkin2/v1/V1Span$Builder.id:J
      71: putfield      #40                 // Field id:J
      74: aload_0
      75: aload_1
      76: getfield      #123                // Field zipkin2/v1/V1Span$Builder.parentId:J
      79: putfield      #45                 // Field parentId:J
      82: aload_0
      83: aload_1
      84: getfield      #124                // Field zipkin2/v1/V1Span$Builder.timestamp:J
      87: putfield      #47                 // Field timestamp:J
      90: aload_0
      91: aload_1
      92: getfield      #125                // Field zipkin2/v1/V1Span$Builder.duration:J
      95: putfield      #49                 // Field duration:J
      98: aload_0
      99: aload_1
     100: getfield      #128                // Field zipkin2/v1/V1Span$Builder.annotations:Ljava/util/ArrayList;
     103: invokestatic  #132                // Method sortedList:(Ljava/util/List;)Ljava/util/List;
     106: putfield      #53                 // Field annotations:Ljava/util/List;
     109: aload_0
     110: aload_1
     111: getfield      #134                // Field zipkin2/v1/V1Span$Builder.binaryAnnotations:Ljava/util/ArrayList;
     114: invokestatic  #132                // Method sortedList:(Ljava/util/List;)Ljava/util/List;
     117: putfield      #56                 // Field binaryAnnotations:Ljava/util/List;
     120: aload_0
     121: aload_1
     122: getfield      #135                // Field zipkin2/v1/V1Span$Builder.debug:Ljava/lang/Boolean;
     125: putfield      #59                 // Field debug:Ljava/lang/Boolean;
     128: return

  public static zipkin2.v1.V1Span$Builder newBuilder();
    Code:
       0: new           #8                  // class zipkin2/v1/V1Span$Builder
       3: dup
       4: invokespecial #140                // Method zipkin2/v1/V1Span$Builder."<init>":()V
       7: areturn

  public boolean equals(java.lang.Object);
    Code:
       0: aload_1
       1: aload_0
       2: if_acmpne     7
       5: iconst_1
       6: ireturn
       7: aload_1
       8: instanceof    #2                  // class zipkin2/v1/V1Span
      11: ifne          16
      14: iconst_0
      15: ireturn
      16: aload_1
      17: checkcast     #2                  // class zipkin2/v1/V1Span
      20: astore_2
      21: aload_0
      22: getfield      #34                 // Field traceIdHigh:J
      25: aload_2
      26: getfield      #34                 // Field traceIdHigh:J
      29: lcmp
      30: ifne          191
      33: aload_0
      34: getfield      #38                 // Field traceId:J
      37: aload_2
      38: getfield      #38                 // Field traceId:J
      41: lcmp
      42: ifne          191
      45: aload_0
      46: getfield      #43                 // Field name:Ljava/lang/String;
      49: ifnonnull     62
      52: aload_2
      53: getfield      #43                 // Field name:Ljava/lang/String;
      56: ifnonnull     191
      59: goto          76
      62: aload_0
      63: getfield      #43                 // Field name:Ljava/lang/String;
      66: aload_2
      67: getfield      #43                 // Field name:Ljava/lang/String;
      70: invokevirtual #145                // Method java/lang/String.equals:(Ljava/lang/Object;)Z
      73: ifeq          191
      76: aload_0
      77: getfield      #40                 // Field id:J
      80: aload_2
      81: getfield      #40                 // Field id:J
      84: lcmp
      85: ifne          191
      88: aload_0
      89: getfield      #45                 // Field parentId:J
      92: aload_2
      93: getfield      #45                 // Field parentId:J
      96: lcmp
      97: ifne          191
     100: aload_0
     101: getfield      #47                 // Field timestamp:J
     104: aload_2
     105: getfield      #47                 // Field timestamp:J
     108: lcmp
     109: ifne          191
     112: aload_0
     113: getfield      #49                 // Field duration:J
     116: aload_2
     117: getfield      #49                 // Field duration:J
     120: lcmp
     121: ifne          191
     124: aload_0
     125: getfield      #53                 // Field annotations:Ljava/util/List;
     128: aload_2
     129: getfield      #53                 // Field annotations:Ljava/util/List;
     132: invokeinterface #146,  2          // InterfaceMethod java/util/List.equals:(Ljava/lang/Object;)Z
     137: ifeq          191
     140: aload_0
     141: getfield      #56                 // Field binaryAnnotations:Ljava/util/List;
     144: aload_2
     145: getfield      #56                 // Field binaryAnnotations:Ljava/util/List;
     148: invokeinterface #146,  2          // InterfaceMethod java/util/List.equals:(Ljava/lang/Object;)Z
     153: ifeq          191
     156: aload_0
     157: getfield      #59                 // Field debug:Ljava/lang/Boolean;
     160: ifnonnull     173
     163: aload_2
     164: getfield      #59                 // Field debug:Ljava/lang/Boolean;
     167: ifnonnull     191
     170: goto          187
     173: aload_0
     174: getfield      #59                 // Field debug:Ljava/lang/Boolean;
     177: aload_2
     178: getfield      #59                 // Field debug:Ljava/lang/Boolean;
     181: invokevirtual #149                // Method java/lang/Boolean.equals:(Ljava/lang/Object;)Z
     184: ifeq          191
     187: iconst_1
     188: goto          192
     191: iconst_0
     192: ireturn

  public int hashCode();
    Code:
       0: iconst_1
       1: istore_1
       2: iload_1
       3: ldc           #155                // int 1000003
       5: imul
       6: istore_1
       7: iload_1
       8: iload_1
       9: i2l
      10: aload_0
      11: getfield      #34                 // Field traceIdHigh:J
      14: bipush        32
      16: lushr
      17: aload_0
      18: getfield      #34                 // Field traceIdHigh:J
      21: lxor
      22: lxor
      23: l2i
      24: ixor
      25: istore_1
      26: iload_1
      27: ldc           #155                // int 1000003
      29: imul
      30: istore_1
      31: iload_1
      32: iload_1
      33: i2l
      34: aload_0
      35: getfield      #38                 // Field traceId:J
      38: bipush        32
      40: lushr
      41: aload_0
      42: getfield      #38                 // Field traceId:J
      45: lxor
      46: lxor
      47: l2i
      48: ixor
      49: istore_1
      50: iload_1
      51: ldc           #155                // int 1000003
      53: imul
      54: istore_1
      55: iload_1
      56: aload_0
      57: getfield      #43                 // Field name:Ljava/lang/String;
      60: ifnonnull     67
      63: iconst_0
      64: goto          74
      67: aload_0
      68: getfield      #43                 // Field name:Ljava/lang/String;
      71: invokevirtual #157                // Method java/lang/String.hashCode:()I
      74: ixor
      75: istore_1
      76: iload_1
      77: ldc           #155                // int 1000003
      79: imul
      80: istore_1
      81: iload_1
      82: iload_1
      83: i2l
      84: aload_0
      85: getfield      #40                 // Field id:J
      88: bipush        32
      90: lushr
      91: aload_0
      92: getfield      #40                 // Field id:J
      95: lxor
      96: lxor
      97: l2i
      98: ixor
      99: istore_1
     100: iload_1
     101: ldc           #155                // int 1000003
     103: imul
     104: istore_1
     105: iload_1
     106: iload_1
     107: i2l
     108: aload_0
     109: getfield      #45                 // Field parentId:J
     112: bipush        32
     114: lushr
     115: aload_0
     116: getfield      #45                 // Field parentId:J
     119: lxor
     120: lxor
     121: l2i
     122: ixor
     123: istore_1
     124: iload_1
     125: ldc           #155                // int 1000003
     127: imul
     128: istore_1
     129: iload_1
     130: iload_1
     131: i2l
     132: aload_0
     133: getfield      #47                 // Field timestamp:J
     136: bipush        32
     138: lushr
     139: aload_0
     140: getfield      #47                 // Field timestamp:J
     143: lxor
     144: lxor
     145: l2i
     146: ixor
     147: istore_1
     148: iload_1
     149: ldc           #155                // int 1000003
     151: imul
     152: istore_1
     153: iload_1
     154: iload_1
     155: i2l
     156: aload_0
     157: getfield      #49                 // Field duration:J
     160: bipush        32
     162: lushr
     163: aload_0
     164: getfield      #49                 // Field duration:J
     167: lxor
     168: lxor
     169: l2i
     170: ixor
     171: istore_1
     172: iload_1
     173: ldc           #155                // int 1000003
     175: imul
     176: istore_1
     177: iload_1
     178: aload_0
     179: getfield      #53                 // Field annotations:Ljava/util/List;
     182: invokeinterface #158,  1          // InterfaceMethod java/util/List.hashCode:()I
     187: ixor
     188: istore_1
     189: iload_1
     190: ldc           #155                // int 1000003
     192: imul
     193: istore_1
     194: iload_1
     195: aload_0
     196: getfield      #56                 // Field binaryAnnotations:Ljava/util/List;
     199: invokeinterface #158,  1          // InterfaceMethod java/util/List.hashCode:()I
     204: ixor
     205: istore_1
     206: iload_1
     207: ldc           #155                // int 1000003
     209: imul
     210: istore_1
     211: iload_1
     212: aload_0
     213: getfield      #59                 // Field debug:Ljava/lang/Boolean;
     216: ifnonnull     223
     219: iconst_0
     220: goto          230
     223: aload_0
     224: getfield      #59                 // Field debug:Ljava/lang/Boolean;
     227: invokevirtual #159                // Method java/lang/Boolean.hashCode:()I
     230: ixor
     231: istore_1
     232: iload_1
     233: ireturn

  static <T extends java.lang.Comparable<T>> java.util.List<T> sortedList(java.util.List<T>);
    Code:
       0: aload_0
       1: ifnonnull     8
       4: invokestatic  #167                // Method java/util/Collections.emptyList:()Ljava/util/List;
       7: areturn
       8: aload_0
       9: invokestatic  #171                // Method java/util/Collections.sort:(Ljava/util/List;)V
      12: new           #173                // class java/util/ArrayList
      15: dup
      16: aload_0
      17: invokespecial #176                // Method java/util/ArrayList."<init>":(Ljava/util/Collection;)V
      20: invokestatic  #179                // Method java/util/Collections.unmodifiableList:(Ljava/util/List;)Ljava/util/List;
      23: areturn

  static {};
    Code:
       0: invokestatic  #185                // Method zipkin2/Endpoint.newBuilder:()Lzipkin2/Endpoint$Builder;
       3: invokevirtual #189                // Method zipkin2/Endpoint$Builder.build:()Lzipkin2/Endpoint;
       6: putstatic     #191                // Field EMPTY_ENDPOINT:Lzipkin2/Endpoint;
       9: return
}
