Compiled from "NoMuxHandler.java"
public class org.jgroups.blocks.mux.NoMuxHandler implements java.io.Serializable {
  private static final long serialVersionUID;

  private short id;

  public org.jgroups.blocks.mux.NoMuxHandler(short);
    Code:
       0: aload_0
       1: invokespecial #1                  // Method java/lang/Object."<init>":()V
       4: aload_0
       5: iload_1
       6: putfield      #2                  // Field id:S
       9: return

  public short getId();
    Code:
       0: aload_0
       1: getfield      #2                  // Field id:S
       4: ireturn

  public boolean equals(java.lang.Object);
    Code:
       0: aload_1
       1: ifnull        11
       4: aload_1
       5: instanceof    #3                  // class org/jgroups/blocks/mux/NoMuxHandler
       8: ifne          13
      11: iconst_0
      12: ireturn
      13: aload_1
      14: checkcast     #3                  // class org/jgroups/blocks/mux/NoMuxHandler
      17: astore_2
      18: aload_0
      19: getfield      #2                  // Field id:S
      22: aload_2
      23: getfield      #2                  // Field id:S
      26: if_icmpne     33
      29: iconst_1
      30: goto          34
      33: iconst_0
      34: ireturn

  public int hashCode();
    Code:
       0: aload_0
       1: getfield      #2                  // Field id:S
       4: ireturn
}
