public interface org.bouncycastle.asn1.cmp.CMPObjectIdentifiers {
  public static final org.bouncycastle.asn1.ASN1ObjectIdentifier passwordBasedMac;

  public static final org.bouncycastle.asn1.ASN1ObjectIdentifier dhBasedMac;

  public static final org.bouncycastle.asn1.ASN1ObjectIdentifier it_caProtEncCert;

  public static final org.bouncycastle.asn1.ASN1ObjectIdentifier it_signKeyPairTypes;

  public static final org.bouncycastle.asn1.ASN1ObjectIdentifier it_encKeyPairTypes;

  public static final org.bouncycastle.asn1.ASN1ObjectIdentifier it_preferredSymAlg;

  public static final org.bouncycastle.asn1.ASN1ObjectIdentifier it_caKeyUpdateInfo;

  public static final org.bouncycastle.asn1.ASN1ObjectIdentifier it_currentCRL;

  public static final org.bouncycastle.asn1.ASN1ObjectIdentifier it_unsupportedOIDs;

  public static final org.bouncycastle.asn1.ASN1ObjectIdentifier it_keyPairParamReq;

  public static final org.bouncycastle.asn1.ASN1ObjectIdentifier it_keyPairParamRep;

  public static final org.bouncycastle.asn1.ASN1ObjectIdentifier it_revPassphrase;

  public static final org.bouncycastle.asn1.ASN1ObjectIdentifier it_implicitConfirm;

  public static final org.bouncycastle.asn1.ASN1ObjectIdentifier it_confirmWaitTime;

  public static final org.bouncycastle.asn1.ASN1ObjectIdentifier it_origPKIMessage;

  public static final org.bouncycastle.asn1.ASN1ObjectIdentifier it_suppLangTags;

  public static final org.bouncycastle.asn1.ASN1ObjectIdentifier id_pkip;

  public static final org.bouncycastle.asn1.ASN1ObjectIdentifier id_regCtrl;

  public static final org.bouncycastle.asn1.ASN1ObjectIdentifier id_regInfo;

  public static final org.bouncycastle.asn1.ASN1ObjectIdentifier regCtrl_regToken;

  public static final org.bouncycastle.asn1.ASN1ObjectIdentifier regCtrl_authenticator;

  public static final org.bouncycastle.asn1.ASN1ObjectIdentifier regCtrl_pkiPublicationInfo;

  public static final org.bouncycastle.asn1.ASN1ObjectIdentifier regCtrl_pkiArchiveOptions;

  public static final org.bouncycastle.asn1.ASN1ObjectIdentifier regCtrl_oldCertID;

  public static final org.bouncycastle.asn1.ASN1ObjectIdentifier regCtrl_protocolEncrKey;

  public static final org.bouncycastle.asn1.ASN1ObjectIdentifier regCtrl_altCertTemplate;

  public static final org.bouncycastle.asn1.ASN1ObjectIdentifier regInfo_utf8Pairs;

  public static final org.bouncycastle.asn1.ASN1ObjectIdentifier regInfo_certReq;

  public static final org.bouncycastle.asn1.ASN1ObjectIdentifier ct_encKeyWithID;

  static {};
    Code:
       0: new           #95                 // class org/bouncycastle/asn1/ASN1ObjectIdentifier
       3: dup
       4: ldc           #1                  // String 1.2.840.113533.7.66.13
       6: invokespecial #158                // Method org/bouncycastle/asn1/ASN1ObjectIdentifier."<init>":(Ljava/lang/String;)V
       9: putstatic     #148                // Field passwordBasedMac:Lorg/bouncycastle/asn1/ASN1ObjectIdentifier;
      12: new           #95                 // class org/bouncycastle/asn1/ASN1ObjectIdentifier
      15: dup
      16: ldc           #2                  // String 1.2.840.113533.7.66.30
      18: invokespecial #158                // Method org/bouncycastle/asn1/ASN1ObjectIdentifier."<init>":(Ljava/lang/String;)V
      21: putstatic     #130                // Field dhBasedMac:Lorg/bouncycastle/asn1/ASN1ObjectIdentifier;
      24: new           #95                 // class org/bouncycastle/asn1/ASN1ObjectIdentifier
      27: dup
      28: ldc           #4                  // String 1.3.6.1.5.5.7.4.1
      30: invokespecial #158                // Method org/bouncycastle/asn1/ASN1ObjectIdentifier."<init>":(Ljava/lang/String;)V
      33: putstatic     #135                // Field it_caProtEncCert:Lorg/bouncycastle/asn1/ASN1ObjectIdentifier;
      36: new           #95                 // class org/bouncycastle/asn1/ASN1ObjectIdentifier
      39: dup
      40: ldc           #12                 // String 1.3.6.1.5.5.7.4.2
      42: invokespecial #158                // Method org/bouncycastle/asn1/ASN1ObjectIdentifier."<init>":(Ljava/lang/String;)V
      45: putstatic     #145                // Field it_signKeyPairTypes:Lorg/bouncycastle/asn1/ASN1ObjectIdentifier;
      48: new           #95                 // class org/bouncycastle/asn1/ASN1ObjectIdentifier
      51: dup
      52: ldc           #13                 // String 1.3.6.1.5.5.7.4.3
      54: invokespecial #158                // Method org/bouncycastle/asn1/ASN1ObjectIdentifier."<init>":(Ljava/lang/String;)V
      57: putstatic     #138                // Field it_encKeyPairTypes:Lorg/bouncycastle/asn1/ASN1ObjectIdentifier;
      60: new           #95                 // class org/bouncycastle/asn1/ASN1ObjectIdentifier
      63: dup
      64: ldc           #14                 // String 1.3.6.1.5.5.7.4.4
      66: invokespecial #158                // Method org/bouncycastle/asn1/ASN1ObjectIdentifier."<init>":(Ljava/lang/String;)V
      69: putstatic     #143                // Field it_preferredSymAlg:Lorg/bouncycastle/asn1/ASN1ObjectIdentifier;
      72: new           #95                 // class org/bouncycastle/asn1/ASN1ObjectIdentifier
      75: dup
      76: ldc           #15                 // String 1.3.6.1.5.5.7.4.5
      78: invokespecial #158                // Method org/bouncycastle/asn1/ASN1ObjectIdentifier."<init>":(Ljava/lang/String;)V
      81: putstatic     #134                // Field it_caKeyUpdateInfo:Lorg/bouncycastle/asn1/ASN1ObjectIdentifier;
      84: new           #95                 // class org/bouncycastle/asn1/ASN1ObjectIdentifier
      87: dup
      88: ldc           #16                 // String 1.3.6.1.5.5.7.4.6
      90: invokespecial #158                // Method org/bouncycastle/asn1/ASN1ObjectIdentifier."<init>":(Ljava/lang/String;)V
      93: putstatic     #137                // Field it_currentCRL:Lorg/bouncycastle/asn1/ASN1ObjectIdentifier;
      96: new           #95                 // class org/bouncycastle/asn1/ASN1ObjectIdentifier
      99: dup
     100: ldc           #17                 // String 1.3.6.1.5.5.7.4.7
     102: invokespecial #158                // Method org/bouncycastle/asn1/ASN1ObjectIdentifier."<init>":(Ljava/lang/String;)V
     105: putstatic     #147                // Field it_unsupportedOIDs:Lorg/bouncycastle/asn1/ASN1ObjectIdentifier;
     108: new           #95                 // class org/bouncycastle/asn1/ASN1ObjectIdentifier
     111: dup
     112: ldc           #5                  // String 1.3.6.1.5.5.7.4.10
     114: invokespecial #158                // Method org/bouncycastle/asn1/ASN1ObjectIdentifier."<init>":(Ljava/lang/String;)V
     117: putstatic     #141                // Field it_keyPairParamReq:Lorg/bouncycastle/asn1/ASN1ObjectIdentifier;
     120: new           #95                 // class org/bouncycastle/asn1/ASN1ObjectIdentifier
     123: dup
     124: ldc           #6                  // String 1.3.6.1.5.5.7.4.11
     126: invokespecial #158                // Method org/bouncycastle/asn1/ASN1ObjectIdentifier."<init>":(Ljava/lang/String;)V
     129: putstatic     #140                // Field it_keyPairParamRep:Lorg/bouncycastle/asn1/ASN1ObjectIdentifier;
     132: new           #95                 // class org/bouncycastle/asn1/ASN1ObjectIdentifier
     135: dup
     136: ldc           #7                  // String 1.3.6.1.5.5.7.4.12
     138: invokespecial #158                // Method org/bouncycastle/asn1/ASN1ObjectIdentifier."<init>":(Ljava/lang/String;)V
     141: putstatic     #144                // Field it_revPassphrase:Lorg/bouncycastle/asn1/ASN1ObjectIdentifier;
     144: new           #95                 // class org/bouncycastle/asn1/ASN1ObjectIdentifier
     147: dup
     148: ldc           #8                  // String 1.3.6.1.5.5.7.4.13
     150: invokespecial #158                // Method org/bouncycastle/asn1/ASN1ObjectIdentifier."<init>":(Ljava/lang/String;)V
     153: putstatic     #139                // Field it_implicitConfirm:Lorg/bouncycastle/asn1/ASN1ObjectIdentifier;
     156: new           #95                 // class org/bouncycastle/asn1/ASN1ObjectIdentifier
     159: dup
     160: ldc           #9                  // String 1.3.6.1.5.5.7.4.14
     162: invokespecial #158                // Method org/bouncycastle/asn1/ASN1ObjectIdentifier."<init>":(Ljava/lang/String;)V
     165: putstatic     #136                // Field it_confirmWaitTime:Lorg/bouncycastle/asn1/ASN1ObjectIdentifier;
     168: new           #95                 // class org/bouncycastle/asn1/ASN1ObjectIdentifier
     171: dup
     172: ldc           #10                 // String 1.3.6.1.5.5.7.4.15
     174: invokespecial #158                // Method org/bouncycastle/asn1/ASN1ObjectIdentifier."<init>":(Ljava/lang/String;)V
     177: putstatic     #142                // Field it_origPKIMessage:Lorg/bouncycastle/asn1/ASN1ObjectIdentifier;
     180: new           #95                 // class org/bouncycastle/asn1/ASN1ObjectIdentifier
     183: dup
     184: ldc           #11                 // String 1.3.6.1.5.5.7.4.16
     186: invokespecial #158                // Method org/bouncycastle/asn1/ASN1ObjectIdentifier."<init>":(Ljava/lang/String;)V
     189: putstatic     #146                // Field it_suppLangTags:Lorg/bouncycastle/asn1/ASN1ObjectIdentifier;
     192: new           #95                 // class org/bouncycastle/asn1/ASN1ObjectIdentifier
     195: dup
     196: ldc           #18                 // String 1.3.6.1.5.5.7.5
     198: invokespecial #158                // Method org/bouncycastle/asn1/ASN1ObjectIdentifier."<init>":(Ljava/lang/String;)V
     201: putstatic     #131                // Field id_pkip:Lorg/bouncycastle/asn1/ASN1ObjectIdentifier;
     204: new           #95                 // class org/bouncycastle/asn1/ASN1ObjectIdentifier
     207: dup
     208: ldc           #19                 // String 1.3.6.1.5.5.7.5.1
     210: invokespecial #158                // Method org/bouncycastle/asn1/ASN1ObjectIdentifier."<init>":(Ljava/lang/String;)V
     213: putstatic     #132                // Field id_regCtrl:Lorg/bouncycastle/asn1/ASN1ObjectIdentifier;
     216: new           #95                 // class org/bouncycastle/asn1/ASN1ObjectIdentifier
     219: dup
     220: ldc           #27                 // String 1.3.6.1.5.5.7.5.2
     222: invokespecial #158                // Method org/bouncycastle/asn1/ASN1ObjectIdentifier."<init>":(Ljava/lang/String;)V
     225: putstatic     #133                // Field id_regInfo:Lorg/bouncycastle/asn1/ASN1ObjectIdentifier;
     228: new           #95                 // class org/bouncycastle/asn1/ASN1ObjectIdentifier
     231: dup
     232: ldc           #20                 // String 1.3.6.1.5.5.7.5.1.1
     234: invokespecial #158                // Method org/bouncycastle/asn1/ASN1ObjectIdentifier."<init>":(Ljava/lang/String;)V
     237: putstatic     #155                // Field regCtrl_regToken:Lorg/bouncycastle/asn1/ASN1ObjectIdentifier;
     240: new           #95                 // class org/bouncycastle/asn1/ASN1ObjectIdentifier
     243: dup
     244: ldc           #21                 // String 1.3.6.1.5.5.7.5.1.2
     246: invokespecial #158                // Method org/bouncycastle/asn1/ASN1ObjectIdentifier."<init>":(Ljava/lang/String;)V
     249: putstatic     #150                // Field regCtrl_authenticator:Lorg/bouncycastle/asn1/ASN1ObjectIdentifier;
     252: new           #95                 // class org/bouncycastle/asn1/ASN1ObjectIdentifier
     255: dup
     256: ldc           #22                 // String 1.3.6.1.5.5.7.5.1.3
     258: invokespecial #158                // Method org/bouncycastle/asn1/ASN1ObjectIdentifier."<init>":(Ljava/lang/String;)V
     261: putstatic     #153                // Field regCtrl_pkiPublicationInfo:Lorg/bouncycastle/asn1/ASN1ObjectIdentifier;
     264: new           #95                 // class org/bouncycastle/asn1/ASN1ObjectIdentifier
     267: dup
     268: ldc           #23                 // String 1.3.6.1.5.5.7.5.1.4
     270: invokespecial #158                // Method org/bouncycastle/asn1/ASN1ObjectIdentifier."<init>":(Ljava/lang/String;)V
     273: putstatic     #152                // Field regCtrl_pkiArchiveOptions:Lorg/bouncycastle/asn1/ASN1ObjectIdentifier;
     276: new           #95                 // class org/bouncycastle/asn1/ASN1ObjectIdentifier
     279: dup
     280: ldc           #24                 // String 1.3.6.1.5.5.7.5.1.5
     282: invokespecial #158                // Method org/bouncycastle/asn1/ASN1ObjectIdentifier."<init>":(Ljava/lang/String;)V
     285: putstatic     #151                // Field regCtrl_oldCertID:Lorg/bouncycastle/asn1/ASN1ObjectIdentifier;
     288: new           #95                 // class org/bouncycastle/asn1/ASN1ObjectIdentifier
     291: dup
     292: ldc           #25                 // String 1.3.6.1.5.5.7.5.1.6
     294: invokespecial #158                // Method org/bouncycastle/asn1/ASN1ObjectIdentifier."<init>":(Ljava/lang/String;)V
     297: putstatic     #154                // Field regCtrl_protocolEncrKey:Lorg/bouncycastle/asn1/ASN1ObjectIdentifier;
     300: new           #95                 // class org/bouncycastle/asn1/ASN1ObjectIdentifier
     303: dup
     304: ldc           #26                 // String 1.3.6.1.5.5.7.5.1.7
     306: invokespecial #158                // Method org/bouncycastle/asn1/ASN1ObjectIdentifier."<init>":(Ljava/lang/String;)V
     309: putstatic     #149                // Field regCtrl_altCertTemplate:Lorg/bouncycastle/asn1/ASN1ObjectIdentifier;
     312: new           #95                 // class org/bouncycastle/asn1/ASN1ObjectIdentifier
     315: dup
     316: ldc           #28                 // String 1.3.6.1.5.5.7.5.2.1
     318: invokespecial #158                // Method org/bouncycastle/asn1/ASN1ObjectIdentifier."<init>":(Ljava/lang/String;)V
     321: putstatic     #157                // Field regInfo_utf8Pairs:Lorg/bouncycastle/asn1/ASN1ObjectIdentifier;
     324: new           #95                 // class org/bouncycastle/asn1/ASN1ObjectIdentifier
     327: dup
     328: ldc           #29                 // String 1.3.6.1.5.5.7.5.2.2
     330: invokespecial #158                // Method org/bouncycastle/asn1/ASN1ObjectIdentifier."<init>":(Ljava/lang/String;)V
     333: putstatic     #156                // Field regInfo_certReq:Lorg/bouncycastle/asn1/ASN1ObjectIdentifier;
     336: new           #95                 // class org/bouncycastle/asn1/ASN1ObjectIdentifier
     339: dup
     340: ldc           #3                  // String 1.2.840.113549.1.9.16.1.21
     342: invokespecial #158                // Method org/bouncycastle/asn1/ASN1ObjectIdentifier."<init>":(Ljava/lang/String;)V
     345: putstatic     #129                // Field ct_encKeyWithID:Lorg/bouncycastle/asn1/ASN1ObjectIdentifier;
     348: return
}
