Compiled from "SimpleRunnableQueue.java"
class com.mchange.v2.async.SimpleRunnableQueue$TaskThread extends java.lang.Thread {
  final com.mchange.v2.async.SimpleRunnableQueue this$0;

  com.mchange.v2.async.SimpleRunnableQueue$TaskThread(com.mchange.v2.async.SimpleRunnableQueue);
    Code:
       0: aload_0
       1: aload_1
       2: putfield      #2                  // Field this$0:Lcom/mchange/v2/async/SimpleRunnableQueue;
       5: aload_0
       6: ldc           #3                  // String SimpleRunnableQueue.TaskThread
       8: invokespecial #4                  // Method java/lang/Thread."<init>":(Ljava/lang/String;)V
      11: return

  public void run();
    Code:
       0: aload_0
       1: invokevirtual #5                  // Method isInterrupted:()Z
       4: ifne          70
       7: aload_0
       8: getfield      #2                  // Field this$0:Lcom/mchange/v2/async/SimpleRunnableQueue;
      11: invokestatic  #6                  // Method com/mchange/v2/async/SimpleRunnableQueue.access$000:(Lcom/mchange/v2/async/SimpleRunnableQueue;)V
      14: aload_0
      15: getfield      #2                  // Field this$0:Lcom/mchange/v2/async/SimpleRunnableQueue;
      18: invokestatic  #7                  // Method com/mchange/v2/async/SimpleRunnableQueue.access$100:(Lcom/mchange/v2/async/SimpleRunnableQueue;)Ljava/lang/Runnable;
      21: astore_1
      22: aload_1
      23: invokeinterface #8,  1            // InterfaceMethod java/lang/Runnable.run:()V
      28: goto          67
      31: astore_2
      32: getstatic     #10                 // Field java/lang/System.err:Ljava/io/PrintStream;
      35: new           #11                 // class java/lang/StringBuilder
      38: dup
      39: invokespecial #12                 // Method java/lang/StringBuilder."<init>":()V
      42: aload_0
      43: invokevirtual #13                 // Method java/lang/Object.getClass:()Ljava/lang/Class;
      46: invokevirtual #14                 // Method java/lang/Class.getName:()Ljava/lang/String;
      49: invokevirtual #15                 // Method java/lang/StringBuilder.append:(Ljava/lang/String;)Ljava/lang/StringBuilder;
      52: ldc           #16                 // String  -- Unexpected exception in task!
      54: invokevirtual #15                 // Method java/lang/StringBuilder.append:(Ljava/lang/String;)Ljava/lang/StringBuilder;
      57: invokevirtual #17                 // Method java/lang/StringBuilder.toString:()Ljava/lang/String;
      60: invokevirtual #18                 // Method java/io/PrintStream.println:(Ljava/lang/String;)V
      63: aload_2
      64: invokevirtual #19                 // Method java/lang/Exception.printStackTrace:()V
      67: goto          0
      70: aload_0
      71: getfield      #2                  // Field this$0:Lcom/mchange/v2/async/SimpleRunnableQueue;
      74: aconst_null
      75: invokestatic  #20                 // Method com/mchange/v2/async/SimpleRunnableQueue.access$202:(Lcom/mchange/v2/async/SimpleRunnableQueue;Ljava/util/List;)Ljava/util/List;
      78: pop
      79: aload_0
      80: getfield      #2                  // Field this$0:Lcom/mchange/v2/async/SimpleRunnableQueue;
      83: aconst_null
      84: invokestatic  #21                 // Method com/mchange/v2/async/SimpleRunnableQueue.access$302:(Lcom/mchange/v2/async/SimpleRunnableQueue;Ljava/lang/Thread;)Ljava/lang/Thread;
      87: pop
      88: goto          134
      91: astore_1
      92: aload_0
      93: getfield      #2                  // Field this$0:Lcom/mchange/v2/async/SimpleRunnableQueue;
      96: aconst_null
      97: invokestatic  #20                 // Method com/mchange/v2/async/SimpleRunnableQueue.access$202:(Lcom/mchange/v2/async/SimpleRunnableQueue;Ljava/util/List;)Ljava/util/List;
     100: pop
     101: aload_0
     102: getfield      #2                  // Field this$0:Lcom/mchange/v2/async/SimpleRunnableQueue;
     105: aconst_null
     106: invokestatic  #21                 // Method com/mchange/v2/async/SimpleRunnableQueue.access$302:(Lcom/mchange/v2/async/SimpleRunnableQueue;Ljava/lang/Thread;)Ljava/lang/Thread;
     109: pop
     110: goto          134
     113: astore_3
     114: aload_0
     115: getfield      #2                  // Field this$0:Lcom/mchange/v2/async/SimpleRunnableQueue;
     118: aconst_null
     119: invokestatic  #20                 // Method com/mchange/v2/async/SimpleRunnableQueue.access$202:(Lcom/mchange/v2/async/SimpleRunnableQueue;Ljava/util/List;)Ljava/util/List;
     122: pop
     123: aload_0
     124: getfield      #2                  // Field this$0:Lcom/mchange/v2/async/SimpleRunnableQueue;
     127: aconst_null
     128: invokestatic  #21                 // Method com/mchange/v2/async/SimpleRunnableQueue.access$302:(Lcom/mchange/v2/async/SimpleRunnableQueue;Ljava/lang/Thread;)Ljava/lang/Thread;
     131: pop
     132: aload_3
     133: athrow
     134: return
    Exception table:
       from    to  target type
          22    28    31   Class java/lang/Exception
           0    70    91   Class java/lang/InterruptedException
           0    70   113   any
}
