Compiled from "Configurable.java"
class javolution.lang.Configurable$ConfigurableXMLFormat extends javolution.xml.XMLFormat {
  javolution.lang.Configurable$ConfigurableXMLFormat();
    Code:
       0: aload_0
       1: aconst_null
       2: invokespecial #1                  // Method javolution/xml/XMLFormat."<init>":(Ljava/lang/Class;)V
       5: return

  public java.lang.Object newInstance(java.lang.Class, javolution.xml.XMLFormat$InputElement) throws javolution.xml.stream.XMLStreamException;
    Code:
       0: aload_2
       1: ldc           #2                  // String name
       3: ldc           #3                  // String
       5: invokevirtual #4                  // Method javolution/xml/XMLFormat$InputElement.getAttribute:(Ljava/lang/String;Ljava/lang/String;)Ljava/lang/String;
       8: invokestatic  #5                  // Method javolution/lang/Configurable.getInstance:(Ljava/lang/String;)Ljavolution/lang/Configurable;
      11: areturn

  public void write(java.lang.Object, javolution.xml.XMLFormat$OutputElement) throws javolution.xml.stream.XMLStreamException;
    Code:
       0: new           #6                  // class java/lang/UnsupportedOperationException
       3: dup
       4: invokespecial #7                  // Method java/lang/UnsupportedOperationException."<init>":()V
       7: athrow

  public void read(javolution.xml.XMLFormat$InputElement, java.lang.Object) throws javolution.xml.stream.XMLStreamException;
    Code:
       0: aload_1
       1: ldc           #8                  // String Value
       3: invokevirtual #9                  // Method javolution/xml/XMLFormat$InputElement.get:(Ljava/lang/String;)Ljava/lang/Object;
       6: astore_3
       7: aload_3
       8: ifnonnull     12
      11: return
      12: aload_2
      13: checkcast     #10                 // class javolution/lang/Configurable
      16: aload_3
      17: invokestatic  #11                 // Method javolution/lang/Configurable.configure:(Ljavolution/lang/Configurable;Ljava/lang/Object;)V
      20: return
}
