Compiled from "Configurable.java"
public class javolution.lang.Configurable<T> {
  private T _value;

  private final T _default;

  private final java.lang.Class _container;

  public javolution.lang.Configurable(T);
    Code:
       0: aload_0
       1: invokespecial #1                  // Method java/lang/Object."<init>":()V
       4: aload_1
       5: ifnonnull     18
       8: new           #2                  // class java/lang/IllegalArgumentException
      11: dup
      12: ldc           #3                  // String Default value cannot be null
      14: invokespecial #4                  // Method java/lang/IllegalArgumentException."<init>":(Ljava/lang/String;)V
      17: athrow
      18: aload_0
      19: aload_1
      20: putfield      #5                  // Field _default:Ljava/lang/Object;
      23: aload_0
      24: aload_1
      25: putfield      #6                  // Field _value:Ljava/lang/Object;
      28: aload_0
      29: invokestatic  #7                  // Method findContainer:()Ljava/lang/Class;
      32: putfield      #8                  // Field _container:Ljava/lang/Class;
      35: return

  private static java.lang.Class findContainer();
    Code:
       0: new           #9                  // class java/lang/Throwable
       3: dup
       4: invokespecial #10                 // Method java/lang/Throwable."<init>":()V
       7: invokevirtual #11                 // Method java/lang/Throwable.getStackTrace:()[Ljava/lang/StackTraceElement;
      10: astore_0
      11: aload_0
      12: iconst_2
      13: aaload
      14: invokevirtual #12                 // Method java/lang/StackTraceElement.getClassName:()Ljava/lang/String;
      17: astore_1
      18: aload_1
      19: ldc           #13                 // String $
      21: invokevirtual #14                 // Method java/lang/String.indexOf:(Ljava/lang/String;)I
      24: istore_2
      25: iload_2
      26: iflt          36
      29: aload_1
      30: iconst_0
      31: iload_2
      32: invokevirtual #15                 // Method java/lang/String.substring:(II)Ljava/lang/String;
      35: astore_1
      36: aload_1
      37: invokestatic  #16                 // Method java/lang/Class.forName:(Ljava/lang/String;)Ljava/lang/Class;
      40: areturn
      41: astore_0
      42: aload_0
      43: invokestatic  #17                 // Method javolution/context/LogContext.error:(Ljava/lang/Throwable;)V
      46: aconst_null
      47: areturn
    Exception table:
       from    to  target type
           0    40    41   Class java/lang/Throwable

  public T get();
    Code:
       0: aload_0
       1: getfield      #6                  // Field _value:Ljava/lang/Object;
       4: areturn

  public T getDefault();
    Code:
       0: aload_0
       1: getfield      #5                  // Field _default:Ljava/lang/Object;
       4: areturn

  public java.lang.Class getContainer();
    Code:
       0: aload_0
       1: getfield      #8                  // Field _container:Ljava/lang/Class;
       4: areturn

  public java.lang.String getName();
    Code:
       0: aload_0
       1: getfield      #8                  // Field _container:Ljava/lang/Class;
       4: ifnonnull     9
       7: aconst_null
       8: areturn
       9: aload_0
      10: getfield      #8                  // Field _container:Ljava/lang/Class;
      13: invokevirtual #18                 // Method java/lang/Class.getDeclaredFields:()[Ljava/lang/reflect/Field;
      16: astore_1
      17: iconst_0
      18: istore_2
      19: iload_2
      20: aload_1
      21: arraylength
      22: if_icmpge     87
      25: aload_1
      26: iload_2
      27: aaload
      28: astore_3
      29: aload_3
      30: invokevirtual #19                 // Method java/lang/reflect/Field.getModifiers:()I
      33: invokestatic  #20                 // Method java/lang/reflect/Modifier.isPublic:(I)Z
      36: ifeq          81
      39: aload_3
      40: aconst_null
      41: invokevirtual #21                 // Method java/lang/reflect/Field.get:(Ljava/lang/Object;)Ljava/lang/Object;
      44: aload_0
      45: if_acmpne     81
      48: new           #22                 // class java/lang/StringBuilder
      51: dup
      52: invokespecial #23                 // Method java/lang/StringBuilder."<init>":()V
      55: aload_0
      56: getfield      #8                  // Field _container:Ljava/lang/Class;
      59: invokevirtual #24                 // Method java/lang/Class.getName:()Ljava/lang/String;
      62: invokevirtual #25                 // Method java/lang/StringBuilder.append:(Ljava/lang/String;)Ljava/lang/StringBuilder;
      65: bipush        35
      67: invokevirtual #26                 // Method java/lang/StringBuilder.append:(C)Ljava/lang/StringBuilder;
      70: aload_3
      71: invokevirtual #27                 // Method java/lang/reflect/Field.getName:()Ljava/lang/String;
      74: invokevirtual #25                 // Method java/lang/StringBuilder.append:(Ljava/lang/String;)Ljava/lang/StringBuilder;
      77: invokevirtual #28                 // Method java/lang/StringBuilder.toString:()Ljava/lang/String;
      80: areturn
      81: iinc          2, 1
      84: goto          19
      87: goto          95
      90: astore_1
      91: aload_1
      92: invokestatic  #17                 // Method javolution/context/LogContext.error:(Ljava/lang/Throwable;)V
      95: aconst_null
      96: areturn
    Exception table:
       from    to  target type
           9    80    90   Class java/lang/Throwable
          81    87    90   Class java/lang/Throwable

  protected void notifyChange(T, T) throws java.lang.UnsupportedOperationException;
    Code:
       0: return

  public java.lang.String toString();
    Code:
       0: aload_0
       1: getfield      #6                  // Field _value:Ljava/lang/Object;
       4: invokestatic  #29                 // Method java/lang/String.valueOf:(Ljava/lang/Object;)Ljava/lang/String;
       7: areturn

  public static javolution.lang.Configurable getInstance(java.lang.String);
    Code:
       0: aload_0
       1: bipush        35
       3: invokevirtual #30                 // Method java/lang/String.lastIndexOf:(I)I
       6: istore_1
       7: iload_1
       8: ifge          13
      11: aconst_null
      12: areturn
      13: aload_0
      14: iconst_0
      15: iload_1
      16: invokevirtual #15                 // Method java/lang/String.substring:(II)Ljava/lang/String;
      19: astore_2
      20: aload_0
      21: iload_1
      22: iconst_1
      23: iadd
      24: invokevirtual #31                 // Method java/lang/String.substring:(I)Ljava/lang/String;
      27: astore_3
      28: invokestatic  #32                 // Method javolution/lang/Reflection.getInstance:()Ljavolution/lang/Reflection;
      31: aload_2
      32: invokevirtual #33                 // Method javolution/lang/Reflection.getClass:(Ljava/lang/String;)Ljava/lang/Class;
      35: astore        4
      37: aload         4
      39: ifnonnull     71
      42: new           #22                 // class java/lang/StringBuilder
      45: dup
      46: invokespecial #23                 // Method java/lang/StringBuilder."<init>":()V
      49: ldc           #34                 // String Class
      51: invokevirtual #25                 // Method java/lang/StringBuilder.append:(Ljava/lang/String;)Ljava/lang/StringBuilder;
      54: aload_2
      55: invokevirtual #25                 // Method java/lang/StringBuilder.append:(Ljava/lang/String;)Ljava/lang/StringBuilder;
      58: ldc           #35                 // String  not found
      60: invokevirtual #25                 // Method java/lang/StringBuilder.append:(Ljava/lang/String;)Ljava/lang/StringBuilder;
      63: invokevirtual #28                 // Method java/lang/StringBuilder.toString:()Ljava/lang/String;
      66: invokestatic  #36                 // Method javolution/context/LogContext.warning:(Ljava/lang/CharSequence;)V
      69: aconst_null
      70: areturn
      71: aload         4
      73: aload_3
      74: invokevirtual #37                 // Method java/lang/Class.getDeclaredField:(Ljava/lang/String;)Ljava/lang/reflect/Field;
      77: aconst_null
      78: invokevirtual #21                 // Method java/lang/reflect/Field.get:(Ljava/lang/Object;)Ljava/lang/Object;
      81: checkcast     #38                 // class javolution/lang/Configurable
      84: astore        5
      86: aload         5
      88: ifnonnull     118
      91: new           #22                 // class java/lang/StringBuilder
      94: dup
      95: invokespecial #23                 // Method java/lang/StringBuilder."<init>":()V
      98: ldc           #39                 // String Configurable
     100: invokevirtual #25                 // Method java/lang/StringBuilder.append:(Ljava/lang/String;)Ljava/lang/StringBuilder;
     103: aload_0
     104: invokevirtual #25                 // Method java/lang/StringBuilder.append:(Ljava/lang/String;)Ljava/lang/StringBuilder;
     107: ldc           #35                 // String  not found
     109: invokevirtual #25                 // Method java/lang/StringBuilder.append:(Ljava/lang/String;)Ljava/lang/StringBuilder;
     112: invokevirtual #28                 // Method java/lang/StringBuilder.toString:()Ljava/lang/String;
     115: invokestatic  #36                 // Method javolution/context/LogContext.warning:(Ljava/lang/CharSequence;)V
     118: aload         5
     120: areturn
     121: astore        5
     123: aload         5
     125: invokestatic  #17                 // Method javolution/context/LogContext.error:(Ljava/lang/Throwable;)V
     128: aconst_null
     129: areturn
    Exception table:
       from    to  target type
          71   120   121   Class java/lang/Exception

  public static <T> void configure(javolution.lang.Configurable<T>, T) throws java.lang.SecurityException;
    Code:
       0: aload_1
       1: ifnonnull     14
       4: new           #2                  // class java/lang/IllegalArgumentException
       7: dup
       8: ldc           #3                  // String Default value cannot be null
      10: invokespecial #4                  // Method java/lang/IllegalArgumentException."<init>":(Ljava/lang/String;)V
      13: athrow
      14: invokestatic  #41                 // Method javolution/context/SecurityContext.getCurrentSecurityContext:()Ljavolution/context/SecurityContext;
      17: astore_2
      18: aload_2
      19: aload_0
      20: invokevirtual #42                 // Method javolution/context/SecurityContext.isConfigurable:(Ljavolution/lang/Configurable;)Z
      23: ifne          36
      26: new           #43                 // class java/lang/SecurityException
      29: dup
      30: ldc           #44                 // String Configuration disallowed by SecurityContext
      32: invokespecial #45                 // Method java/lang/SecurityException."<init>":(Ljava/lang/String;)V
      35: athrow
      36: aload_0
      37: getfield      #6                  // Field _value:Ljava/lang/Object;
      40: astore_3
      41: aload_1
      42: aload_3
      43: invokevirtual #46                 // Method java/lang/Object.equals:(Ljava/lang/Object;)Z
      46: ifne          94
      49: new           #22                 // class java/lang/StringBuilder
      52: dup
      53: invokespecial #23                 // Method java/lang/StringBuilder."<init>":()V
      56: ldc           #39                 // String Configurable
      58: invokevirtual #25                 // Method java/lang/StringBuilder.append:(Ljava/lang/String;)Ljava/lang/StringBuilder;
      61: aload_0
      62: invokevirtual #47                 // Method getName:()Ljava/lang/String;
      65: invokevirtual #25                 // Method java/lang/StringBuilder.append:(Ljava/lang/String;)Ljava/lang/StringBuilder;
      68: ldc           #48                 // String  set to
      70: invokevirtual #25                 // Method java/lang/StringBuilder.append:(Ljava/lang/String;)Ljava/lang/StringBuilder;
      73: aload_1
      74: invokevirtual #49                 // Method java/lang/StringBuilder.append:(Ljava/lang/Object;)Ljava/lang/StringBuilder;
      77: invokevirtual #28                 // Method java/lang/StringBuilder.toString:()Ljava/lang/String;
      80: invokestatic  #50                 // Method javolution/context/LogContext.info:(Ljava/lang/CharSequence;)V
      83: aload_0
      84: aload_1
      85: putfield      #6                  // Field _value:Ljava/lang/Object;
      88: aload_0
      89: aload_3
      90: aload_1
      91: invokevirtual #51                 // Method notifyChange:(Ljava/lang/Object;Ljava/lang/Object;)V
      94: return

  public static void read(java.util.Properties);
    Code:
       0: aload_0
       1: invokevirtual #52                 // Method java/util/Properties.keys:()Ljava/util/Enumeration;
       4: astore_1
       5: aload_1
       6: invokeinterface #53,  1           // InterfaceMethod java/util/Enumeration.hasMoreElements:()Z
      11: ifeq          116
      14: aload_1
      15: invokeinterface #54,  1           // InterfaceMethod java/util/Enumeration.nextElement:()Ljava/lang/Object;
      20: checkcast     #55                 // class java/lang/String
      23: astore_2
      24: aload_0
      25: aload_2
      26: invokevirtual #56                 // Method java/util/Properties.getProperty:(Ljava/lang/String;)Ljava/lang/String;
      29: astore_3
      30: aload_2
      31: invokestatic  #57                 // Method getInstance:(Ljava/lang/String;)Ljavolution/lang/Configurable;
      34: astore        4
      36: aload         4
      38: ifnonnull     44
      41: goto          5
      44: aload         4
      46: invokevirtual #58                 // Method getDefault:()Ljava/lang/Object;
      49: invokevirtual #59                 // Method java/lang/Object.getClass:()Ljava/lang/Class;
      52: astore        5
      54: aload         5
      56: invokestatic  #60                 // Method javolution/text/TextFormat.getInstance:(Ljava/lang/Class;)Ljavolution/text/TextFormat;
      59: astore        6
      61: aload         6
      63: invokevirtual #61                 // Method javolution/text/TextFormat.isParsingSupported:()Z
      66: ifne          95
      69: new           #22                 // class java/lang/StringBuilder
      72: dup
      73: invokespecial #23                 // Method java/lang/StringBuilder."<init>":()V
      76: ldc           #62                 // String Cannot find suitable TextFormat to parse instances of
      78: invokevirtual #25                 // Method java/lang/StringBuilder.append:(Ljava/lang/String;)Ljava/lang/StringBuilder;
      81: aload         5
      83: invokevirtual #49                 // Method java/lang/StringBuilder.append:(Ljava/lang/Object;)Ljava/lang/StringBuilder;
      86: invokevirtual #28                 // Method java/lang/StringBuilder.toString:()Ljava/lang/String;
      89: invokestatic  #63                 // Method javolution/context/LogContext.error:(Ljava/lang/CharSequence;)V
      92: goto          5
      95: aload         6
      97: aload_3
      98: invokestatic  #64                 // Method toCsq:(Ljava/lang/Object;)Ljava/lang/CharSequence;
     101: invokevirtual #65                 // Method javolution/text/TextFormat.parse:(Ljava/lang/CharSequence;)Ljava/lang/Object;
     104: astore        7
     106: aload         4
     108: aload         7
     110: invokestatic  #66                 // Method configure:(Ljavolution/lang/Configurable;Ljava/lang/Object;)V
     113: goto          5
     116: return

  public static void read(java.io.InputStream);
    Code:
       0: aload_0
       1: invokestatic  #67                 // Method javolution/xml/XMLObjectReader.newInstance:(Ljava/io/InputStream;)Ljavolution/xml/XMLObjectReader;
       4: astore_1
       5: new           #68                 // class javolution/lang/Configurable$1
       8: dup
       9: invokespecial #69                 // Method javolution/lang/Configurable$1."<init>":()V
      12: astore_2
      13: aload_2
      14: ldc_w         #38                 // class javolution/lang/Configurable
      17: ldc           #70                 // String Configurable
      19: invokevirtual #71                 // Method javolution/xml/XMLBinding.setAlias:(Ljava/lang/Class;Ljava/lang/String;)V
      22: aload_1
      23: aload_2
      24: invokevirtual #72                 // Method javolution/xml/XMLObjectReader.setBinding:(Ljavolution/xml/XMLBinding;)Ljavolution/xml/XMLObjectReader;
      27: pop
      28: aload_1
      29: ldc           #73                 // String Configuration
      31: ldc_w         #74                 // class javolution/util/FastTable
      34: invokevirtual #75                 // Method javolution/xml/XMLObjectReader.read:(Ljava/lang/String;Ljava/lang/Class;)Ljava/lang/Object;
      37: pop
      38: goto          46
      41: astore_1
      42: aload_1
      43: invokestatic  #17                 // Method javolution/context/LogContext.error:(Ljava/lang/Throwable;)V
      46: return
    Exception table:
       from    to  target type
           0    38    41   Class java/lang/Exception

  private static java.lang.CharSequence toCsq(java.lang.Object);
    Code:
       0: aload_0
       1: checkcast     #76                 // class java/lang/CharSequence
       4: areturn
}
