Compiled from "Reflection.java"
abstract class javolution.lang.Reflection$Default$BaseConstructor implements javolution.lang.Reflection$Constructor {
  private final java.lang.Class[] _parameterTypes;

  protected javolution.lang.Reflection$Default$BaseConstructor(java.lang.Class[]);
    Code:
       0: aload_0
       1: invokespecial #1                  // Method java/lang/Object."<init>":()V
       4: aload_0
       5: aload_1
       6: putfield      #2                  // Field _parameterTypes:[Ljava/lang/Class;
       9: return

  public java.lang.Class[] getParameterTypes();
    Code:
       0: aload_0
       1: getfield      #2                  // Field _parameterTypes:[Ljava/lang/Class;
       4: areturn

  protected abstract java.lang.Object allocate(java.lang.Object[]);

  public final java.lang.Object newInstance();
    Code:
       0: aload_0
       1: getfield      #2                  // Field _parameterTypes:[Ljava/lang/Class;
       4: arraylength
       5: ifeq          39
       8: new           #3                  // class java/lang/IllegalArgumentException
      11: dup
      12: new           #4                  // class java/lang/StringBuilder
      15: dup
      16: invokespecial #5                  // Method java/lang/StringBuilder."<init>":()V
      19: ldc           #6                  // String Expected number of parameters is
      21: invokevirtual #7                  // Method java/lang/StringBuilder.append:(Ljava/lang/String;)Ljava/lang/StringBuilder;
      24: aload_0
      25: getfield      #2                  // Field _parameterTypes:[Ljava/lang/Class;
      28: arraylength
      29: invokevirtual #8                  // Method java/lang/StringBuilder.append:(I)Ljava/lang/StringBuilder;
      32: invokevirtual #9                  // Method java/lang/StringBuilder.toString:()Ljava/lang/String;
      35: invokespecial #10                 // Method java/lang/IllegalArgumentException."<init>":(Ljava/lang/String;)V
      38: athrow
      39: aload_0
      40: invokestatic  #11                 // Method javolution/lang/Reflection.access$200:()[Ljava/lang/Object;
      43: invokevirtual #12                 // Method allocate:([Ljava/lang/Object;)Ljava/lang/Object;
      46: areturn

  public final java.lang.Object newInstance(java.lang.Object);
    Code:
       0: aload_0
       1: getfield      #2                  // Field _parameterTypes:[Ljava/lang/Class;
       4: arraylength
       5: iconst_1
       6: if_icmpeq     40
       9: new           #3                  // class java/lang/IllegalArgumentException
      12: dup
      13: new           #4                  // class java/lang/StringBuilder
      16: dup
      17: invokespecial #5                  // Method java/lang/StringBuilder."<init>":()V
      20: ldc           #6                  // String Expected number of parameters is
      22: invokevirtual #7                  // Method java/lang/StringBuilder.append:(Ljava/lang/String;)Ljava/lang/StringBuilder;
      25: aload_0
      26: getfield      #2                  // Field _parameterTypes:[Ljava/lang/Class;
      29: arraylength
      30: invokevirtual #8                  // Method java/lang/StringBuilder.append:(I)Ljava/lang/StringBuilder;
      33: invokevirtual #9                  // Method java/lang/StringBuilder.toString:()Ljava/lang/String;
      36: invokespecial #10                 // Method java/lang/IllegalArgumentException."<init>":(Ljava/lang/String;)V
      39: athrow
      40: iconst_1
      41: anewarray     #13                 // class java/lang/Object
      44: dup
      45: iconst_0
      46: aload_1
      47: aastore
      48: astore_2
      49: aload_0
      50: aload_2
      51: invokevirtual #12                 // Method allocate:([Ljava/lang/Object;)Ljava/lang/Object;
      54: areturn

  public final java.lang.Object newInstance(java.lang.Object, java.lang.Object);
    Code:
       0: aload_0
       1: getfield      #2                  // Field _parameterTypes:[Ljava/lang/Class;
       4: arraylength
       5: iconst_2
       6: if_icmpeq     40
       9: new           #3                  // class java/lang/IllegalArgumentException
      12: dup
      13: new           #4                  // class java/lang/StringBuilder
      16: dup
      17: invokespecial #5                  // Method java/lang/StringBuilder."<init>":()V
      20: ldc           #6                  // String Expected number of parameters is
      22: invokevirtual #7                  // Method java/lang/StringBuilder.append:(Ljava/lang/String;)Ljava/lang/StringBuilder;
      25: aload_0
      26: getfield      #2                  // Field _parameterTypes:[Ljava/lang/Class;
      29: arraylength
      30: invokevirtual #8                  // Method java/lang/StringBuilder.append:(I)Ljava/lang/StringBuilder;
      33: invokevirtual #9                  // Method java/lang/StringBuilder.toString:()Ljava/lang/String;
      36: invokespecial #10                 // Method java/lang/IllegalArgumentException."<init>":(Ljava/lang/String;)V
      39: athrow
      40: iconst_2
      41: anewarray     #13                 // class java/lang/Object
      44: dup
      45: iconst_0
      46: aload_1
      47: aastore
      48: dup
      49: iconst_1
      50: aload_2
      51: aastore
      52: astore_3
      53: aload_0
      54: aload_3
      55: invokevirtual #12                 // Method allocate:([Ljava/lang/Object;)Ljava/lang/Object;
      58: areturn

  public final java.lang.Object newInstance(java.lang.Object, java.lang.Object, java.lang.Object);
    Code:
       0: aload_0
       1: getfield      #2                  // Field _parameterTypes:[Ljava/lang/Class;
       4: arraylength
       5: iconst_3
       6: if_icmpeq     40
       9: new           #3                  // class java/lang/IllegalArgumentException
      12: dup
      13: new           #4                  // class java/lang/StringBuilder
      16: dup
      17: invokespecial #5                  // Method java/lang/StringBuilder."<init>":()V
      20: ldc           #6                  // String Expected number of parameters is
      22: invokevirtual #7                  // Method java/lang/StringBuilder.append:(Ljava/lang/String;)Ljava/lang/StringBuilder;
      25: aload_0
      26: getfield      #2                  // Field _parameterTypes:[Ljava/lang/Class;
      29: arraylength
      30: invokevirtual #8                  // Method java/lang/StringBuilder.append:(I)Ljava/lang/StringBuilder;
      33: invokevirtual #9                  // Method java/lang/StringBuilder.toString:()Ljava/lang/String;
      36: invokespecial #10                 // Method java/lang/IllegalArgumentException."<init>":(Ljava/lang/String;)V
      39: athrow
      40: iconst_3
      41: anewarray     #13                 // class java/lang/Object
      44: dup
      45: iconst_0
      46: aload_1
      47: aastore
      48: dup
      49: iconst_1
      50: aload_2
      51: aastore
      52: dup
      53: iconst_2
      54: aload_3
      55: aastore
      56: astore        4
      58: aload_0
      59: aload         4
      61: invokevirtual #12                 // Method allocate:([Ljava/lang/Object;)Ljava/lang/Object;
      64: areturn

  public final java.lang.Object newInstance(java.lang.Object...);
    Code:
       0: aload_0
       1: getfield      #2                  // Field _parameterTypes:[Ljava/lang/Class;
       4: arraylength
       5: aload_1
       6: arraylength
       7: if_icmpeq     41
      10: new           #3                  // class java/lang/IllegalArgumentException
      13: dup
      14: new           #4                  // class java/lang/StringBuilder
      17: dup
      18: invokespecial #5                  // Method java/lang/StringBuilder."<init>":()V
      21: ldc           #6                  // String Expected number of parameters is
      23: invokevirtual #7                  // Method java/lang/StringBuilder.append:(Ljava/lang/String;)Ljava/lang/StringBuilder;
      26: aload_0
      27: getfield      #2                  // Field _parameterTypes:[Ljava/lang/Class;
      30: arraylength
      31: invokevirtual #8                  // Method java/lang/StringBuilder.append:(I)Ljava/lang/StringBuilder;
      34: invokevirtual #9                  // Method java/lang/StringBuilder.toString:()Ljava/lang/String;
      37: invokespecial #10                 // Method java/lang/IllegalArgumentException."<init>":(Ljava/lang/String;)V
      40: athrow
      41: aload_0
      42: aload_1
      43: invokevirtual #12                 // Method allocate:([Ljava/lang/Object;)Ljava/lang/Object;
      46: areturn
}
