Compiled from "MAPParsingComponentExceptionReason.java"
public final class org.mobicents.protocols.ss7.map.api.MAPParsingComponentExceptionReason extends java.lang.Enum<org.mobicents.protocols.ss7.map.api.MAPParsingComponentExceptionReason> {
  public static final org.mobicents.protocols.ss7.map.api.MAPParsingComponentExceptionReason UnrecognizedOperation;

  public static final org.mobicents.protocols.ss7.map.api.MAPParsingComponentExceptionReason MistypedParameter;

  private static final org.mobicents.protocols.ss7.map.api.MAPParsingComponentExceptionReason[] $VALUES;

  public static org.mobicents.protocols.ss7.map.api.MAPParsingComponentExceptionReason[] values();
    Code:
       0: getstatic     #1                  // Field $VALUES:[Lorg/mobicents/protocols/ss7/map/api/MAPParsingComponentExceptionReason;
       3: invokevirtual #2                  // Method "[Lorg/mobicents/protocols/ss7/map/api/MAPParsingComponentExceptionReason;".clone:()Ljava/lang/Object;
       6: checkcast     #3                  // class "[Lorg/mobicents/protocols/ss7/map/api/MAPParsingComponentExceptionReason;"
       9: areturn

  public static org.mobicents.protocols.ss7.map.api.MAPParsingComponentExceptionReason valueOf(java.lang.String);
    Code:
       0: ldc_w         #4                  // class org/mobicents/protocols/ss7/map/api/MAPParsingComponentExceptionReason
       3: aload_0
       4: invokestatic  #5                  // Method java/lang/Enum.valueOf:(Ljava/lang/Class;Ljava/lang/String;)Ljava/lang/Enum;
       7: checkcast     #4                  // class org/mobicents/protocols/ss7/map/api/MAPParsingComponentExceptionReason
      10: areturn

  private org.mobicents.protocols.ss7.map.api.MAPParsingComponentExceptionReason();
    Code:
       0: aload_0
       1: aload_1
       2: iload_2
       3: invokespecial #6                  // Method java/lang/Enum."<init>":(Ljava/lang/String;I)V
       6: return

  static {};
    Code:
       0: new           #4                  // class org/mobicents/protocols/ss7/map/api/MAPParsingComponentExceptionReason
       3: dup
       4: ldc           #7                  // String UnrecognizedOperation
       6: iconst_0
       7: invokespecial #8                  // Method "<init>":(Ljava/lang/String;I)V
      10: putstatic     #9                  // Field UnrecognizedOperation:Lorg/mobicents/protocols/ss7/map/api/MAPParsingComponentExceptionReason;
      13: new           #4                  // class org/mobicents/protocols/ss7/map/api/MAPParsingComponentExceptionReason
      16: dup
      17: ldc           #10                 // String MistypedParameter
      19: iconst_1
      20: invokespecial #8                  // Method "<init>":(Ljava/lang/String;I)V
      23: putstatic     #11                 // Field MistypedParameter:Lorg/mobicents/protocols/ss7/map/api/MAPParsingComponentExceptionReason;
      26: iconst_2
      27: anewarray     #4                  // class org/mobicents/protocols/ss7/map/api/MAPParsingComponentExceptionReason
      30: dup
      31: iconst_0
      32: getstatic     #9                  // Field UnrecognizedOperation:Lorg/mobicents/protocols/ss7/map/api/MAPParsingComponentExceptionReason;
      35: aastore
      36: dup
      37: iconst_1
      38: getstatic     #11                 // Field MistypedParameter:Lorg/mobicents/protocols/ss7/map/api/MAPParsingComponentExceptionReason;
      41: aastore
      42: putstatic     #1                  // Field $VALUES:[Lorg/mobicents/protocols/ss7/map/api/MAPParsingComponentExceptionReason;
      45: return
}
