Compiled from "ClassPath.java"
abstract class org.apache.jena.ext.com.google.common.reflect.ClassPath$Scanner {
  private final java.util.Set<java.io.File> scannedUris;

  org.apache.jena.ext.com.google.common.reflect.ClassPath$Scanner();
    Code:
       0: aload_0
       1: invokespecial #30                 // Method java/lang/Object."<init>":()V
       4: aload_0
       5: invokestatic  #36                 // Method org/apache/jena/ext/com/google/common/collect/Sets.newHashSet:()Ljava/util/HashSet;
       8: putfield      #38                 // Field scannedUris:Ljava/util/Set;
      11: return

  public final void scan(java.lang.ClassLoader) throws java.io.IOException;
    Code:
       0: aload_1
       1: invokestatic  #48                 // Method getClassPathEntries:(Ljava/lang/ClassLoader;)Lorg/apache/jena/ext/com/google/common/collect/ImmutableMap;
       4: invokevirtual #54                 // Method org/apache/jena/ext/com/google/common/collect/ImmutableMap.entrySet:()Lorg/apache/jena/ext/com/google/common/collect/ImmutableSet;
       7: invokevirtual #58                 // Method org/apache/jena/ext/com/google/common/collect/ImmutableSet.iterator:()Lorg/apache/jena/ext/com/google/common/collect/UnmodifiableIterator;
      10: astore_2
      11: aload_2
      12: invokeinterface #64,  1           // InterfaceMethod java/util/Iterator.hasNext:()Z
      17: ifeq          55
      20: aload_2
      21: invokeinterface #68,  1           // InterfaceMethod java/util/Iterator.next:()Ljava/lang/Object;
      26: checkcast     #10                 // class java/util/Map$Entry
      29: astore_3
      30: aload_0
      31: aload_3
      32: invokeinterface #71,  1           // InterfaceMethod java/util/Map$Entry.getKey:()Ljava/lang/Object;
      37: checkcast     #73                 // class java/io/File
      40: aload_3
      41: invokeinterface #76,  1           // InterfaceMethod java/util/Map$Entry.getValue:()Ljava/lang/Object;
      46: checkcast     #78                 // class java/lang/ClassLoader
      49: invokevirtual #81                 // Method scan:(Ljava/io/File;Ljava/lang/ClassLoader;)V
      52: goto          11
      55: return

  protected abstract void scanDirectory(java.lang.ClassLoader, java.io.File) throws java.io.IOException;

  protected abstract void scanJarFile(java.lang.ClassLoader, java.util.jar.JarFile) throws java.io.IOException;

  final void scan(java.io.File, java.lang.ClassLoader) throws java.io.IOException;
    Code:
       0: aload_0
       1: getfield      #38                 // Field scannedUris:Ljava/util/Set;
       4: aload_1
       5: invokevirtual #95                 // Method java/io/File.getCanonicalFile:()Ljava/io/File;
       8: invokeinterface #101,  2          // InterfaceMethod java/util/Set.add:(Ljava/lang/Object;)Z
      13: ifeq          22
      16: aload_0
      17: aload_1
      18: aload_2
      19: invokespecial #104                // Method scanFrom:(Ljava/io/File;Ljava/lang/ClassLoader;)V
      22: return

  private void scanFrom(java.io.File, java.lang.ClassLoader) throws java.io.IOException;
    Code:
       0: aload_1
       1: invokevirtual #111                // Method java/io/File.exists:()Z
       4: ifne          8
       7: return
       8: goto          47
      11: astore_3
      12: invokestatic  #115                // Method org/apache/jena/ext/com/google/common/reflect/ClassPath.access$100:()Ljava/util/logging/Logger;
      15: new           #117                // class java/lang/StringBuilder
      18: dup
      19: invokespecial #118                // Method java/lang/StringBuilder."<init>":()V
      22: ldc           #120                // String Cannot access
      24: invokevirtual #124                // Method java/lang/StringBuilder.append:(Ljava/lang/String;)Ljava/lang/StringBuilder;
      27: aload_1
      28: invokevirtual #127                // Method java/lang/StringBuilder.append:(Ljava/lang/Object;)Ljava/lang/StringBuilder;
      31: ldc           #129                // String :
      33: invokevirtual #124                // Method java/lang/StringBuilder.append:(Ljava/lang/String;)Ljava/lang/StringBuilder;
      36: aload_3
      37: invokevirtual #127                // Method java/lang/StringBuilder.append:(Ljava/lang/Object;)Ljava/lang/StringBuilder;
      40: invokevirtual #133                // Method java/lang/StringBuilder.toString:()Ljava/lang/String;
      43: invokevirtual #139                // Method java/util/logging/Logger.warning:(Ljava/lang/String;)V
      46: return
      47: aload_1
      48: invokevirtual #142                // Method java/io/File.isDirectory:()Z
      51: ifeq          63
      54: aload_0
      55: aload_2
      56: aload_1
      57: invokevirtual #144                // Method scanDirectory:(Ljava/lang/ClassLoader;Ljava/io/File;)V
      60: goto          69
      63: aload_0
      64: aload_1
      65: aload_2
      66: invokespecial #147                // Method scanJar:(Ljava/io/File;Ljava/lang/ClassLoader;)V
      69: return
    Exception table:
       from    to  target type
           0     7    11   Class java/lang/SecurityException

  private void scanJar(java.io.File, java.lang.ClassLoader) throws java.io.IOException;
    Code:
       0: new           #151                // class java/util/jar/JarFile
       3: dup
       4: aload_1
       5: invokespecial #154                // Method java/util/jar/JarFile."<init>":(Ljava/io/File;)V
       8: astore_3
       9: goto          15
      12: astore        4
      14: return
      15: aload_1
      16: aload_3
      17: invokevirtual #158                // Method java/util/jar/JarFile.getManifest:()Ljava/util/jar/Manifest;
      20: invokestatic  #162                // Method getClassPathFromManifest:(Ljava/io/File;Ljava/util/jar/Manifest;)Lorg/apache/jena/ext/com/google/common/collect/ImmutableSet;
      23: invokevirtual #58                 // Method org/apache/jena/ext/com/google/common/collect/ImmutableSet.iterator:()Lorg/apache/jena/ext/com/google/common/collect/UnmodifiableIterator;
      26: astore        4
      28: aload         4
      30: invokeinterface #64,  1           // InterfaceMethod java/util/Iterator.hasNext:()Z
      35: ifeq          60
      38: aload         4
      40: invokeinterface #68,  1           // InterfaceMethod java/util/Iterator.next:()Ljava/lang/Object;
      45: checkcast     #73                 // class java/io/File
      48: astore        5
      50: aload_0
      51: aload         5
      53: aload_2
      54: invokevirtual #81                 // Method scan:(Ljava/io/File;Ljava/lang/ClassLoader;)V
      57: goto          28
      60: aload_0
      61: aload_2
      62: aload_3
      63: invokevirtual #164                // Method scanJarFile:(Ljava/lang/ClassLoader;Ljava/util/jar/JarFile;)V
      66: aload_3
      67: invokevirtual #167                // Method java/util/jar/JarFile.close:()V
      70: goto          92
      73: astore        4
      75: goto          92
      78: astore        6
      80: aload_3
      81: invokevirtual #167                // Method java/util/jar/JarFile.close:()V
      84: goto          89
      87: astore        7
      89: aload         6
      91: athrow
      92: return
    Exception table:
       from    to  target type
           0     9    12   Class java/io/IOException
          66    70    73   Class java/io/IOException
          15    66    78   any
          80    84    87   Class java/io/IOException
          78    80    78   any

  static org.apache.jena.ext.com.google.common.collect.ImmutableSet<java.io.File> getClassPathFromManifest(java.io.File, java.util.jar.Manifest);
    Code:
       0: aload_1
       1: ifnonnull     8
       4: invokestatic  #179                // Method org/apache/jena/ext/com/google/common/collect/ImmutableSet.of:()Lorg/apache/jena/ext/com/google/common/collect/ImmutableSet;
       7: areturn
       8: invokestatic  #183                // Method org/apache/jena/ext/com/google/common/collect/ImmutableSet.builder:()Lorg/apache/jena/ext/com/google/common/collect/ImmutableSet$Builder;
      11: astore_2
      12: aload_1
      13: invokevirtual #189                // Method java/util/jar/Manifest.getMainAttributes:()Ljava/util/jar/Attributes;
      16: getstatic     #193                // Field java/util/jar/Attributes$Name.CLASS_PATH:Ljava/util/jar/Attributes$Name;
      19: invokevirtual #194                // Method java/util/jar/Attributes$Name.toString:()Ljava/lang/String;
      22: invokevirtual #197                // Method java/util/jar/Attributes.getValue:(Ljava/lang/String;)Ljava/lang/String;
      25: astore_3
      26: aload_3
      27: ifnull        141
      30: invokestatic  #201                // Method org/apache/jena/ext/com/google/common/reflect/ClassPath.access$200:()Lorg/apache/jena/ext/com/google/common/base/Splitter;
      33: aload_3
      34: invokevirtual #207                // Method org/apache/jena/ext/com/google/common/base/Splitter.split:(Ljava/lang/CharSequence;)Ljava/lang/Iterable;
      37: invokeinterface #212,  1          // InterfaceMethod java/lang/Iterable.iterator:()Ljava/util/Iterator;
      42: astore        4
      44: aload         4
      46: invokeinterface #64,  1           // InterfaceMethod java/util/Iterator.hasNext:()Z
      51: ifeq          141
      54: aload         4
      56: invokeinterface #68,  1           // InterfaceMethod java/util/Iterator.next:()Ljava/lang/Object;
      61: checkcast     #214                // class java/lang/String
      64: astore        5
      66: aload_0
      67: aload         5
      69: invokestatic  #218                // Method getClassPathEntry:(Ljava/io/File;Ljava/lang/String;)Ljava/net/URL;
      72: astore        6
      74: goto          108
      77: astore        7
      79: invokestatic  #115                // Method org/apache/jena/ext/com/google/common/reflect/ClassPath.access$100:()Ljava/util/logging/Logger;
      82: new           #117                // class java/lang/StringBuilder
      85: dup
      86: invokespecial #118                // Method java/lang/StringBuilder."<init>":()V
      89: ldc           #220                // String Invalid Class-Path entry:
      91: invokevirtual #124                // Method java/lang/StringBuilder.append:(Ljava/lang/String;)Ljava/lang/StringBuilder;
      94: aload         5
      96: invokevirtual #124                // Method java/lang/StringBuilder.append:(Ljava/lang/String;)Ljava/lang/StringBuilder;
      99: invokevirtual #133                // Method java/lang/StringBuilder.toString:()Ljava/lang/String;
     102: invokevirtual #139                // Method java/util/logging/Logger.warning:(Ljava/lang/String;)V
     105: goto          44
     108: aload         6
     110: invokevirtual #225                // Method java/net/URL.getProtocol:()Ljava/lang/String;
     113: ldc           #226                // String file
     115: invokevirtual #229                // Method java/lang/String.equals:(Ljava/lang/Object;)Z
     118: ifeq          138
     121: aload_2
     122: new           #73                 // class java/io/File
     125: dup
     126: aload         6
     128: invokevirtual #232                // Method java/net/URL.getFile:()Ljava/lang/String;
     131: invokespecial #234                // Method java/io/File."<init>":(Ljava/lang/String;)V
     134: invokevirtual #237                // Method org/apache/jena/ext/com/google/common/collect/ImmutableSet$Builder.add:(Ljava/lang/Object;)Lorg/apache/jena/ext/com/google/common/collect/ImmutableSet$Builder;
     137: pop
     138: goto          44
     141: aload_2
     142: invokevirtual #240                // Method org/apache/jena/ext/com/google/common/collect/ImmutableSet$Builder.build:()Lorg/apache/jena/ext/com/google/common/collect/ImmutableSet;
     145: areturn
    Exception table:
       from    to  target type
          66    74    77   Class java/net/MalformedURLException

  static org.apache.jena.ext.com.google.common.collect.ImmutableMap<java.io.File, java.lang.ClassLoader> getClassPathEntries(java.lang.ClassLoader);
    Code:
       0: invokestatic  #255                // Method org/apache/jena/ext/com/google/common/collect/Maps.newLinkedHashMap:()Ljava/util/LinkedHashMap;
       3: astore_1
       4: aload_0
       5: invokevirtual #259                // Method java/lang/ClassLoader.getParent:()Ljava/lang/ClassLoader;
       8: astore_2
       9: aload_2
      10: ifnull        21
      13: aload_1
      14: aload_2
      15: invokestatic  #48                 // Method getClassPathEntries:(Ljava/lang/ClassLoader;)Lorg/apache/jena/ext/com/google/common/collect/ImmutableMap;
      18: invokevirtual #265                // Method java/util/LinkedHashMap.putAll:(Ljava/util/Map;)V
      21: aload_0
      22: instanceof    #267                // class java/net/URLClassLoader
      25: ifeq          111
      28: aload_0
      29: checkcast     #267                // class java/net/URLClassLoader
      32: astore_3
      33: aload_3
      34: invokevirtual #271                // Method java/net/URLClassLoader.getURLs:()[Ljava/net/URL;
      37: astore        4
      39: aload         4
      41: arraylength
      42: istore        5
      44: iconst_0
      45: istore        6
      47: iload         6
      49: iload         5
      51: if_icmpge     111
      54: aload         4
      56: iload         6
      58: aaload
      59: astore        7
      61: aload         7
      63: invokevirtual #225                // Method java/net/URL.getProtocol:()Ljava/lang/String;
      66: ldc           #226                // String file
      68: invokevirtual #229                // Method java/lang/String.equals:(Ljava/lang/Object;)Z
      71: ifeq          105
      74: new           #73                 // class java/io/File
      77: dup
      78: aload         7
      80: invokevirtual #232                // Method java/net/URL.getFile:()Ljava/lang/String;
      83: invokespecial #234                // Method java/io/File."<init>":(Ljava/lang/String;)V
      86: astore        8
      88: aload_1
      89: aload         8
      91: invokevirtual #276                // Method java/util/LinkedHashMap.containsKey:(Ljava/lang/Object;)Z
      94: ifne          105
      97: aload_1
      98: aload         8
     100: aload_0
     101: invokevirtual #280                // Method java/util/LinkedHashMap.put:(Ljava/lang/Object;Ljava/lang/Object;)Ljava/lang/Object;
     104: pop
     105: iinc          6, 1
     108: goto          47
     111: aload_1
     112: invokestatic  #284                // Method org/apache/jena/ext/com/google/common/collect/ImmutableMap.copyOf:(Ljava/util/Map;)Lorg/apache/jena/ext/com/google/common/collect/ImmutableMap;
     115: areturn

  static java.net.URL getClassPathEntry(java.io.File, java.lang.String) throws java.net.MalformedURLException;
    Code:
       0: new           #222                // class java/net/URL
       3: dup
       4: aload_0
       5: invokevirtual #294                // Method java/io/File.toURI:()Ljava/net/URI;
       8: invokevirtual #300                // Method java/net/URI.toURL:()Ljava/net/URL;
      11: aload_1
      12: invokespecial #303                // Method java/net/URL."<init>":(Ljava/net/URL;Ljava/lang/String;)V
      15: areturn
}
