Compiled from "AuthenticationTrustResolverImpl.java"
public class org.springframework.security.authentication.AuthenticationTrustResolverImpl implements org.springframework.security.authentication.AuthenticationTrustResolver {
  private java.lang.Class<? extends org.springframework.security.core.Authentication> anonymousClass;

  private java.lang.Class<? extends org.springframework.security.core.Authentication> rememberMeClass;

  public org.springframework.security.authentication.AuthenticationTrustResolverImpl();
    Code:
       0: aload_0
       1: invokespecial #1                  // Method java/lang/Object."<init>":()V
       4: aload_0
       5: ldc           #2                  // class org/springframework/security/authentication/AnonymousAuthenticationToken
       7: putfield      #3                  // Field anonymousClass:Ljava/lang/Class;
      10: aload_0
      11: ldc           #4                  // class org/springframework/security/authentication/RememberMeAuthenticationToken
      13: putfield      #5                  // Field rememberMeClass:Ljava/lang/Class;
      16: return

  java.lang.Class<? extends org.springframework.security.core.Authentication> getAnonymousClass();
    Code:
       0: aload_0
       1: getfield      #3                  // Field anonymousClass:Ljava/lang/Class;
       4: areturn

  java.lang.Class<? extends org.springframework.security.core.Authentication> getRememberMeClass();
    Code:
       0: aload_0
       1: getfield      #5                  // Field rememberMeClass:Ljava/lang/Class;
       4: areturn

  public boolean isAnonymous(org.springframework.security.core.Authentication);
    Code:
       0: aload_0
       1: getfield      #3                  // Field anonymousClass:Ljava/lang/Class;
       4: ifnull        11
       7: aload_1
       8: ifnonnull     13
      11: iconst_0
      12: ireturn
      13: aload_0
      14: getfield      #3                  // Field anonymousClass:Ljava/lang/Class;
      17: aload_1
      18: invokevirtual #6                  // Method java/lang/Object.getClass:()Ljava/lang/Class;
      21: invokevirtual #7                  // Method java/lang/Class.isAssignableFrom:(Ljava/lang/Class;)Z
      24: ireturn

  public boolean isRememberMe(org.springframework.security.core.Authentication);
    Code:
       0: aload_0
       1: getfield      #5                  // Field rememberMeClass:Ljava/lang/Class;
       4: ifnull        11
       7: aload_1
       8: ifnonnull     13
      11: iconst_0
      12: ireturn
      13: aload_0
      14: getfield      #5                  // Field rememberMeClass:Ljava/lang/Class;
      17: aload_1
      18: invokevirtual #6                  // Method java/lang/Object.getClass:()Ljava/lang/Class;
      21: invokevirtual #7                  // Method java/lang/Class.isAssignableFrom:(Ljava/lang/Class;)Z
      24: ireturn

  public void setAnonymousClass(java.lang.Class<? extends org.springframework.security.core.Authentication>);
    Code:
       0: aload_0
       1: aload_1
       2: putfield      #3                  // Field anonymousClass:Ljava/lang/Class;
       5: return

  public void setRememberMeClass(java.lang.Class<? extends org.springframework.security.core.Authentication>);
    Code:
       0: aload_0
       1: aload_1
       2: putfield      #5                  // Field rememberMeClass:Ljava/lang/Class;
       5: return
}
