Compiled from "UsernamePasswordAuthenticationToken.java"
public class org.springframework.security.authentication.UsernamePasswordAuthenticationToken extends org.springframework.security.authentication.AbstractAuthenticationToken {
  private static final long serialVersionUID;

  private final java.lang.Object principal;

  private java.lang.Object credentials;

  public org.springframework.security.authentication.UsernamePasswordAuthenticationToken(java.lang.Object, java.lang.Object);
    Code:
       0: aload_0
       1: aconst_null
       2: invokespecial #2                  // Method org/springframework/security/authentication/AbstractAuthenticationToken."<init>":(Ljava/util/Collection;)V
       5: aload_0
       6: aload_1
       7: putfield      #3                  // Field principal:Ljava/lang/Object;
      10: aload_0
      11: aload_2
      12: putfield      #4                  // Field credentials:Ljava/lang/Object;
      15: aload_0
      16: iconst_0
      17: invokevirtual #5                  // Method setAuthenticated:(Z)V
      20: return

  public org.springframework.security.authentication.UsernamePasswordAuthenticationToken(java.lang.Object, java.lang.Object, java.util.Collection<? extends org.springframework.security.core.GrantedAuthority>);
    Code:
       0: aload_0
       1: aload_3
       2: invokespecial #2                  // Method org/springframework/security/authentication/AbstractAuthenticationToken."<init>":(Ljava/util/Collection;)V
       5: aload_0
       6: aload_1
       7: putfield      #3                  // Field principal:Ljava/lang/Object;
      10: aload_0
      11: aload_2
      12: putfield      #4                  // Field credentials:Ljava/lang/Object;
      15: aload_0
      16: iconst_1
      17: invokespecial #6                  // Method org/springframework/security/authentication/AbstractAuthenticationToken.setAuthenticated:(Z)V
      20: return

  public java.lang.Object getCredentials();
    Code:
       0: aload_0
       1: getfield      #4                  // Field credentials:Ljava/lang/Object;
       4: areturn

  public java.lang.Object getPrincipal();
    Code:
       0: aload_0
       1: getfield      #3                  // Field principal:Ljava/lang/Object;
       4: areturn

  public void setAuthenticated(boolean) throws java.lang.IllegalArgumentException;
    Code:
       0: iload_1
       1: ifeq          14
       4: new           #7                  // class java/lang/IllegalArgumentException
       7: dup
       8: ldc           #8                  // String Cannot set this token to trusted - use constructor which takes a GrantedAuthority list instead
      10: invokespecial #9                  // Method java/lang/IllegalArgumentException."<init>":(Ljava/lang/String;)V
      13: athrow
      14: aload_0
      15: iconst_0
      16: invokespecial #6                  // Method org/springframework/security/authentication/AbstractAuthenticationToken.setAuthenticated:(Z)V
      19: return

  public void eraseCredentials();
    Code:
       0: aload_0
       1: invokespecial #10                 // Method org/springframework/security/authentication/AbstractAuthenticationToken.eraseCredentials:()V
       4: aload_0
       5: aconst_null
       6: putfield      #4                  // Field credentials:Ljava/lang/Object;
       9: return
}
