public class org.bouncycastle.asn1.pkcs.RSASSAPSSparams extends org.bouncycastle.asn1.ASN1Object {
  private org.bouncycastle.asn1.x509.AlgorithmIdentifier hashAlgorithm;

  private org.bouncycastle.asn1.x509.AlgorithmIdentifier maskGenAlgorithm;

  private org.bouncycastle.asn1.ASN1Integer saltLength;

  private org.bouncycastle.asn1.ASN1Integer trailerField;

  public static final org.bouncycastle.asn1.x509.AlgorithmIdentifier DEFAULT_HASH_ALGORITHM;

  public static final org.bouncycastle.asn1.x509.AlgorithmIdentifier DEFAULT_MASK_GEN_FUNCTION;

  public static final org.bouncycastle.asn1.ASN1Integer DEFAULT_SALT_LENGTH;

  public static final org.bouncycastle.asn1.ASN1Integer DEFAULT_TRAILER_FIELD;

  public static org.bouncycastle.asn1.pkcs.RSASSAPSSparams getInstance(java.lang.Object);
    Code:
       0: aload_0
       1: instanceof    #58                 // class org/bouncycastle/asn1/pkcs/RSASSAPSSparams
       4: ifeq          12
       7: aload_0
       8: checkcast     #58                 // class org/bouncycastle/asn1/pkcs/RSASSAPSSparams
      11: areturn
      12: aload_0
      13: ifnull        28
      16: new           #58                 // class org/bouncycastle/asn1/pkcs/RSASSAPSSparams
      19: dup
      20: aload_0
      21: invokestatic  #131                // Method org/bouncycastle/asn1/ASN1Sequence.getInstance:(Ljava/lang/Object;)Lorg/bouncycastle/asn1/ASN1Sequence;
      24: invokespecial #135                // Method "<init>":(Lorg/bouncycastle/asn1/ASN1Sequence;)V
      27: areturn
      28: aconst_null
      29: areturn

  public org.bouncycastle.asn1.pkcs.RSASSAPSSparams();
    Code:
       0: aload_0
       1: invokespecial #128                // Method org/bouncycastle/asn1/ASN1Object."<init>":()V
       4: aload_0
       5: getstatic     #117                // Field DEFAULT_HASH_ALGORITHM:Lorg/bouncycastle/asn1/x509/AlgorithmIdentifier;
       8: putfield      #119                // Field hashAlgorithm:Lorg/bouncycastle/asn1/x509/AlgorithmIdentifier;
      11: aload_0
      12: getstatic     #118                // Field DEFAULT_MASK_GEN_FUNCTION:Lorg/bouncycastle/asn1/x509/AlgorithmIdentifier;
      15: putfield      #120                // Field maskGenAlgorithm:Lorg/bouncycastle/asn1/x509/AlgorithmIdentifier;
      18: aload_0
      19: getstatic     #113                // Field DEFAULT_SALT_LENGTH:Lorg/bouncycastle/asn1/ASN1Integer;
      22: putfield      #115                // Field saltLength:Lorg/bouncycastle/asn1/ASN1Integer;
      25: aload_0
      26: getstatic     #114                // Field DEFAULT_TRAILER_FIELD:Lorg/bouncycastle/asn1/ASN1Integer;
      29: putfield      #116                // Field trailerField:Lorg/bouncycastle/asn1/ASN1Integer;
      32: return

  public org.bouncycastle.asn1.pkcs.RSASSAPSSparams(org.bouncycastle.asn1.x509.AlgorithmIdentifier, org.bouncycastle.asn1.x509.AlgorithmIdentifier, org.bouncycastle.asn1.ASN1Integer, org.bouncycastle.asn1.ASN1Integer);
    Code:
       0: aload_0
       1: invokespecial #128                // Method org/bouncycastle/asn1/ASN1Object."<init>":()V
       4: aload_0
       5: aload_1
       6: putfield      #119                // Field hashAlgorithm:Lorg/bouncycastle/asn1/x509/AlgorithmIdentifier;
       9: aload_0
      10: aload_2
      11: putfield      #120                // Field maskGenAlgorithm:Lorg/bouncycastle/asn1/x509/AlgorithmIdentifier;
      14: aload_0
      15: aload_3
      16: putfield      #115                // Field saltLength:Lorg/bouncycastle/asn1/ASN1Integer;
      19: aload_0
      20: aload         4
      22: putfield      #116                // Field trailerField:Lorg/bouncycastle/asn1/ASN1Integer;
      25: return

  private org.bouncycastle.asn1.pkcs.RSASSAPSSparams(org.bouncycastle.asn1.ASN1Sequence);
    Code:
       0: aload_0
       1: invokespecial #128                // Method org/bouncycastle/asn1/ASN1Object."<init>":()V
       4: aload_0
       5: getstatic     #117                // Field DEFAULT_HASH_ALGORITHM:Lorg/bouncycastle/asn1/x509/AlgorithmIdentifier;
       8: putfield      #119                // Field hashAlgorithm:Lorg/bouncycastle/asn1/x509/AlgorithmIdentifier;
      11: aload_0
      12: getstatic     #118                // Field DEFAULT_MASK_GEN_FUNCTION:Lorg/bouncycastle/asn1/x509/AlgorithmIdentifier;
      15: putfield      #120                // Field maskGenAlgorithm:Lorg/bouncycastle/asn1/x509/AlgorithmIdentifier;
      18: aload_0
      19: getstatic     #113                // Field DEFAULT_SALT_LENGTH:Lorg/bouncycastle/asn1/ASN1Integer;
      22: putfield      #115                // Field saltLength:Lorg/bouncycastle/asn1/ASN1Integer;
      25: aload_0
      26: getstatic     #114                // Field DEFAULT_TRAILER_FIELD:Lorg/bouncycastle/asn1/ASN1Integer;
      29: putfield      #116                // Field trailerField:Lorg/bouncycastle/asn1/ASN1Integer;
      32: iconst_0
      33: istore_2
      34: iload_2
      35: aload_1
      36: invokevirtual #129                // Method org/bouncycastle/asn1/ASN1Sequence.size:()I
      39: if_icmpeq     148
      42: aload_1
      43: iload_2
      44: invokevirtual #130                // Method org/bouncycastle/asn1/ASN1Sequence.getObjectAt:(I)Lorg/bouncycastle/asn1/ASN1Encodable;
      47: checkcast     #52                 // class org/bouncycastle/asn1/ASN1TaggedObject
      50: astore_3
      51: aload_3
      52: invokevirtual #132                // Method org/bouncycastle/asn1/ASN1TaggedObject.getTagNo:()I
      55: tableswitch   { // 0 to 3
                     0: 84
                     1: 96
                     2: 108
                     3: 120
               default: 132
          }
      84: aload_0
      85: aload_3
      86: iconst_1
      87: invokestatic  #138                // Method org/bouncycastle/asn1/x509/AlgorithmIdentifier.getInstance:(Lorg/bouncycastle/asn1/ASN1TaggedObject;Z)Lorg/bouncycastle/asn1/x509/AlgorithmIdentifier;
      90: putfield      #119                // Field hashAlgorithm:Lorg/bouncycastle/asn1/x509/AlgorithmIdentifier;
      93: goto          142
      96: aload_0
      97: aload_3
      98: iconst_1
      99: invokestatic  #138                // Method org/bouncycastle/asn1/x509/AlgorithmIdentifier.getInstance:(Lorg/bouncycastle/asn1/ASN1TaggedObject;Z)Lorg/bouncycastle/asn1/x509/AlgorithmIdentifier;
     102: putfield      #120                // Field maskGenAlgorithm:Lorg/bouncycastle/asn1/x509/AlgorithmIdentifier;
     105: goto          142
     108: aload_0
     109: aload_3
     110: iconst_1
     111: invokestatic  #127                // Method org/bouncycastle/asn1/ASN1Integer.getInstance:(Lorg/bouncycastle/asn1/ASN1TaggedObject;Z)Lorg/bouncycastle/asn1/ASN1Integer;
     114: putfield      #115                // Field saltLength:Lorg/bouncycastle/asn1/ASN1Integer;
     117: goto          142
     120: aload_0
     121: aload_3
     122: iconst_1
     123: invokestatic  #127                // Method org/bouncycastle/asn1/ASN1Integer.getInstance:(Lorg/bouncycastle/asn1/ASN1TaggedObject;Z)Lorg/bouncycastle/asn1/ASN1Integer;
     126: putfield      #116                // Field trailerField:Lorg/bouncycastle/asn1/ASN1Integer;
     129: goto          142
     132: new           #47                 // class java/lang/IllegalArgumentException
     135: dup
     136: ldc           #1                  // String unknown tag
     138: invokespecial #121                // Method java/lang/IllegalArgumentException."<init>":(Ljava/lang/String;)V
     141: athrow
     142: iinc          2, 1
     145: goto          34
     148: return

  public org.bouncycastle.asn1.x509.AlgorithmIdentifier getHashAlgorithm();
    Code:
       0: aload_0
       1: getfield      #119                // Field hashAlgorithm:Lorg/bouncycastle/asn1/x509/AlgorithmIdentifier;
       4: areturn

  public org.bouncycastle.asn1.x509.AlgorithmIdentifier getMaskGenAlgorithm();
    Code:
       0: aload_0
       1: getfield      #120                // Field maskGenAlgorithm:Lorg/bouncycastle/asn1/x509/AlgorithmIdentifier;
       4: areturn

  public java.math.BigInteger getSaltLength();
    Code:
       0: aload_0
       1: getfield      #115                // Field saltLength:Lorg/bouncycastle/asn1/ASN1Integer;
       4: invokevirtual #125                // Method org/bouncycastle/asn1/ASN1Integer.getValue:()Ljava/math/BigInteger;
       7: areturn

  public java.math.BigInteger getTrailerField();
    Code:
       0: aload_0
       1: getfield      #116                // Field trailerField:Lorg/bouncycastle/asn1/ASN1Integer;
       4: invokevirtual #125                // Method org/bouncycastle/asn1/ASN1Integer.getValue:()Ljava/math/BigInteger;
       7: areturn

  public org.bouncycastle.asn1.ASN1Primitive toASN1Primitive();
    Code:
       0: new           #48                 // class org/bouncycastle/asn1/ASN1EncodableVector
       3: dup
       4: iconst_4
       5: invokespecial #122                // Method org/bouncycastle/asn1/ASN1EncodableVector."<init>":(I)V
       8: astore_1
       9: aload_0
      10: getfield      #119                // Field hashAlgorithm:Lorg/bouncycastle/asn1/x509/AlgorithmIdentifier;
      13: getstatic     #117                // Field DEFAULT_HASH_ALGORITHM:Lorg/bouncycastle/asn1/x509/AlgorithmIdentifier;
      16: invokevirtual #136                // Method org/bouncycastle/asn1/x509/AlgorithmIdentifier.equals:(Ljava/lang/Object;)Z
      19: ifne          39
      22: aload_1
      23: new           #55                 // class org/bouncycastle/asn1/DERTaggedObject
      26: dup
      27: iconst_1
      28: iconst_0
      29: aload_0
      30: getfield      #119                // Field hashAlgorithm:Lorg/bouncycastle/asn1/x509/AlgorithmIdentifier;
      33: invokespecial #134                // Method org/bouncycastle/asn1/DERTaggedObject."<init>":(ZILorg/bouncycastle/asn1/ASN1Encodable;)V
      36: invokevirtual #123                // Method org/bouncycastle/asn1/ASN1EncodableVector.add:(Lorg/bouncycastle/asn1/ASN1Encodable;)V
      39: aload_0
      40: getfield      #120                // Field maskGenAlgorithm:Lorg/bouncycastle/asn1/x509/AlgorithmIdentifier;
      43: getstatic     #118                // Field DEFAULT_MASK_GEN_FUNCTION:Lorg/bouncycastle/asn1/x509/AlgorithmIdentifier;
      46: invokevirtual #136                // Method org/bouncycastle/asn1/x509/AlgorithmIdentifier.equals:(Ljava/lang/Object;)Z
      49: ifne          69
      52: aload_1
      53: new           #55                 // class org/bouncycastle/asn1/DERTaggedObject
      56: dup
      57: iconst_1
      58: iconst_1
      59: aload_0
      60: getfield      #120                // Field maskGenAlgorithm:Lorg/bouncycastle/asn1/x509/AlgorithmIdentifier;
      63: invokespecial #134                // Method org/bouncycastle/asn1/DERTaggedObject."<init>":(ZILorg/bouncycastle/asn1/ASN1Encodable;)V
      66: invokevirtual #123                // Method org/bouncycastle/asn1/ASN1EncodableVector.add:(Lorg/bouncycastle/asn1/ASN1Encodable;)V
      69: aload_0
      70: getfield      #115                // Field saltLength:Lorg/bouncycastle/asn1/ASN1Integer;
      73: getstatic     #113                // Field DEFAULT_SALT_LENGTH:Lorg/bouncycastle/asn1/ASN1Integer;
      76: invokevirtual #126                // Method org/bouncycastle/asn1/ASN1Integer.equals:(Lorg/bouncycastle/asn1/ASN1Primitive;)Z
      79: ifne          99
      82: aload_1
      83: new           #55                 // class org/bouncycastle/asn1/DERTaggedObject
      86: dup
      87: iconst_1
      88: iconst_2
      89: aload_0
      90: getfield      #115                // Field saltLength:Lorg/bouncycastle/asn1/ASN1Integer;
      93: invokespecial #134                // Method org/bouncycastle/asn1/DERTaggedObject."<init>":(ZILorg/bouncycastle/asn1/ASN1Encodable;)V
      96: invokevirtual #123                // Method org/bouncycastle/asn1/ASN1EncodableVector.add:(Lorg/bouncycastle/asn1/ASN1Encodable;)V
      99: aload_0
     100: getfield      #116                // Field trailerField:Lorg/bouncycastle/asn1/ASN1Integer;
     103: getstatic     #114                // Field DEFAULT_TRAILER_FIELD:Lorg/bouncycastle/asn1/ASN1Integer;
     106: invokevirtual #126                // Method org/bouncycastle/asn1/ASN1Integer.equals:(Lorg/bouncycastle/asn1/ASN1Primitive;)Z
     109: ifne          129
     112: aload_1
     113: new           #55                 // class org/bouncycastle/asn1/DERTaggedObject
     116: dup
     117: iconst_1
     118: iconst_3
     119: aload_0
     120: getfield      #116                // Field trailerField:Lorg/bouncycastle/asn1/ASN1Integer;
     123: invokespecial #134                // Method org/bouncycastle/asn1/DERTaggedObject."<init>":(ZILorg/bouncycastle/asn1/ASN1Encodable;)V
     126: invokevirtual #123                // Method org/bouncycastle/asn1/ASN1EncodableVector.add:(Lorg/bouncycastle/asn1/ASN1Encodable;)V
     129: new           #54                 // class org/bouncycastle/asn1/DERSequence
     132: dup
     133: aload_1
     134: invokespecial #133                // Method org/bouncycastle/asn1/DERSequence."<init>":(Lorg/bouncycastle/asn1/ASN1EncodableVector;)V
     137: areturn

  static {};
    Code:
       0: new           #59                 // class org/bouncycastle/asn1/x509/AlgorithmIdentifier
       3: dup
       4: getstatic     #111                // Field org/bouncycastle/asn1/oiw/OIWObjectIdentifiers.idSHA1:Lorg/bouncycastle/asn1/ASN1ObjectIdentifier;
       7: getstatic     #110                // Field org/bouncycastle/asn1/DERNull.INSTANCE:Lorg/bouncycastle/asn1/DERNull;
      10: invokespecial #137                // Method org/bouncycastle/asn1/x509/AlgorithmIdentifier."<init>":(Lorg/bouncycastle/asn1/ASN1ObjectIdentifier;Lorg/bouncycastle/asn1/ASN1Encodable;)V
      13: putstatic     #117                // Field DEFAULT_HASH_ALGORITHM:Lorg/bouncycastle/asn1/x509/AlgorithmIdentifier;
      16: new           #59                 // class org/bouncycastle/asn1/x509/AlgorithmIdentifier
      19: dup
      20: getstatic     #112                // Field org/bouncycastle/asn1/pkcs/PKCSObjectIdentifiers.id_mgf1:Lorg/bouncycastle/asn1/ASN1ObjectIdentifier;
      23: getstatic     #117                // Field DEFAULT_HASH_ALGORITHM:Lorg/bouncycastle/asn1/x509/AlgorithmIdentifier;
      26: invokespecial #137                // Method org/bouncycastle/asn1/x509/AlgorithmIdentifier."<init>":(Lorg/bouncycastle/asn1/ASN1ObjectIdentifier;Lorg/bouncycastle/asn1/ASN1Encodable;)V
      29: putstatic     #118                // Field DEFAULT_MASK_GEN_FUNCTION:Lorg/bouncycastle/asn1/x509/AlgorithmIdentifier;
      32: new           #49                 // class org/bouncycastle/asn1/ASN1Integer
      35: dup
      36: ldc2_w        #45                 // long 20l
      39: invokespecial #124                // Method org/bouncycastle/asn1/ASN1Integer."<init>":(J)V
      42: putstatic     #113                // Field DEFAULT_SALT_LENGTH:Lorg/bouncycastle/asn1/ASN1Integer;
      45: new           #49                 // class org/bouncycastle/asn1/ASN1Integer
      48: dup
      49: lconst_1
      50: invokespecial #124                // Method org/bouncycastle/asn1/ASN1Integer."<init>":(J)V
      53: putstatic     #114                // Field DEFAULT_TRAILER_FIELD:Lorg/bouncycastle/asn1/ASN1Integer;
      56: return
}
