public class org.bouncycastle.asn1.pkcs.EncryptionScheme extends org.bouncycastle.asn1.ASN1Object {
  private org.bouncycastle.asn1.x509.AlgorithmIdentifier algId;

  public org.bouncycastle.asn1.pkcs.EncryptionScheme(org.bouncycastle.asn1.ASN1ObjectIdentifier);
    Code:
       0: aload_0
       1: invokespecial #37                 // Method org/bouncycastle/asn1/ASN1Object."<init>":()V
       4: aload_0
       5: new           #15                 // class org/bouncycastle/asn1/x509/AlgorithmIdentifier
       8: dup
       9: aload_1
      10: invokespecial #42                 // Method org/bouncycastle/asn1/x509/AlgorithmIdentifier."<init>":(Lorg/bouncycastle/asn1/ASN1ObjectIdentifier;)V
      13: putfield      #36                 // Field algId:Lorg/bouncycastle/asn1/x509/AlgorithmIdentifier;
      16: return

  public org.bouncycastle.asn1.pkcs.EncryptionScheme(org.bouncycastle.asn1.ASN1ObjectIdentifier, org.bouncycastle.asn1.ASN1Encodable);
    Code:
       0: aload_0
       1: invokespecial #37                 // Method org/bouncycastle/asn1/ASN1Object."<init>":()V
       4: aload_0
       5: new           #15                 // class org/bouncycastle/asn1/x509/AlgorithmIdentifier
       8: dup
       9: aload_1
      10: aload_2
      11: invokespecial #44                 // Method org/bouncycastle/asn1/x509/AlgorithmIdentifier."<init>":(Lorg/bouncycastle/asn1/ASN1ObjectIdentifier;Lorg/bouncycastle/asn1/ASN1Encodable;)V
      14: putfield      #36                 // Field algId:Lorg/bouncycastle/asn1/x509/AlgorithmIdentifier;
      17: return

  private org.bouncycastle.asn1.pkcs.EncryptionScheme(org.bouncycastle.asn1.ASN1Sequence);
    Code:
       0: aload_0
       1: invokespecial #37                 // Method org/bouncycastle/asn1/ASN1Object."<init>":()V
       4: aload_0
       5: aload_1
       6: invokestatic  #45                 // Method org/bouncycastle/asn1/x509/AlgorithmIdentifier.getInstance:(Ljava/lang/Object;)Lorg/bouncycastle/asn1/x509/AlgorithmIdentifier;
       9: putfield      #36                 // Field algId:Lorg/bouncycastle/asn1/x509/AlgorithmIdentifier;
      12: return

  public static org.bouncycastle.asn1.pkcs.EncryptionScheme getInstance(java.lang.Object);
    Code:
       0: aload_0
       1: instanceof    #14                 // class org/bouncycastle/asn1/pkcs/EncryptionScheme
       4: ifeq          12
       7: aload_0
       8: checkcast     #14                 // class org/bouncycastle/asn1/pkcs/EncryptionScheme
      11: areturn
      12: aload_0
      13: ifnull        28
      16: new           #14                 // class org/bouncycastle/asn1/pkcs/EncryptionScheme
      19: dup
      20: aload_0
      21: invokestatic  #38                 // Method org/bouncycastle/asn1/ASN1Sequence.getInstance:(Ljava/lang/Object;)Lorg/bouncycastle/asn1/ASN1Sequence;
      24: invokespecial #39                 // Method "<init>":(Lorg/bouncycastle/asn1/ASN1Sequence;)V
      27: areturn
      28: aconst_null
      29: areturn

  public org.bouncycastle.asn1.ASN1ObjectIdentifier getAlgorithm();
    Code:
       0: aload_0
       1: getfield      #36                 // Field algId:Lorg/bouncycastle/asn1/x509/AlgorithmIdentifier;
       4: invokevirtual #41                 // Method org/bouncycastle/asn1/x509/AlgorithmIdentifier.getAlgorithm:()Lorg/bouncycastle/asn1/ASN1ObjectIdentifier;
       7: areturn

  public org.bouncycastle.asn1.ASN1Encodable getParameters();
    Code:
       0: aload_0
       1: getfield      #36                 // Field algId:Lorg/bouncycastle/asn1/x509/AlgorithmIdentifier;
       4: invokevirtual #40                 // Method org/bouncycastle/asn1/x509/AlgorithmIdentifier.getParameters:()Lorg/bouncycastle/asn1/ASN1Encodable;
       7: areturn

  public org.bouncycastle.asn1.ASN1Primitive toASN1Primitive();
    Code:
       0: aload_0
       1: getfield      #36                 // Field algId:Lorg/bouncycastle/asn1/x509/AlgorithmIdentifier;
       4: invokevirtual #43                 // Method org/bouncycastle/asn1/x509/AlgorithmIdentifier.toASN1Primitive:()Lorg/bouncycastle/asn1/ASN1Primitive;
       7: areturn
}
