Compiled from "CharEscaperBuilder.java"
public final class org.apache.curator.shaded.com.google.common.escape.CharEscaperBuilder {
  private final java.util.Map<java.lang.Character, java.lang.String> map;

  private int max;

  public org.apache.curator.shaded.com.google.common.escape.CharEscaperBuilder();
    Code:
       0: aload_0
       1: invokespecial #24                 // Method java/lang/Object."<init>":()V
       4: aload_0
       5: iconst_m1
       6: putfield      #26                 // Field max:I
       9: aload_0
      10: new           #28                 // class java/util/HashMap
      13: dup
      14: invokespecial #29                 // Method java/util/HashMap."<init>":()V
      17: putfield      #31                 // Field map:Ljava/util/Map;
      20: return

  public org.apache.curator.shaded.com.google.common.escape.CharEscaperBuilder addEscape(char, java.lang.String);
    Code:
       0: aload_0
       1: getfield      #31                 // Field map:Ljava/util/Map;
       4: iload_1
       5: invokestatic  #41                 // Method java/lang/Character.valueOf:(C)Ljava/lang/Character;
       8: aload_2
       9: invokestatic  #47                 // Method org/apache/curator/shaded/com/google/common/base/Preconditions.checkNotNull:(Ljava/lang/Object;)Ljava/lang/Object;
      12: invokeinterface #51,  3           // InterfaceMethod java/util/Map.put:(Ljava/lang/Object;Ljava/lang/Object;)Ljava/lang/Object;
      17: pop
      18: iload_1
      19: aload_0
      20: getfield      #26                 // Field max:I
      23: if_icmple     31
      26: aload_0
      27: iload_1
      28: putfield      #26                 // Field max:I
      31: aload_0
      32: areturn

  public org.apache.curator.shaded.com.google.common.escape.CharEscaperBuilder addEscapes(char[], java.lang.String);
    Code:
       0: aload_2
       1: invokestatic  #47                 // Method org/apache/curator/shaded/com/google/common/base/Preconditions.checkNotNull:(Ljava/lang/Object;)Ljava/lang/Object;
       4: pop
       5: aload_1
       6: astore_3
       7: aload_3
       8: arraylength
       9: istore        4
      11: iconst_0
      12: istore        5
      14: iload         5
      16: iload         4
      18: if_icmpge     41
      21: aload_3
      22: iload         5
      24: caload
      25: istore        6
      27: aload_0
      28: iload         6
      30: aload_2
      31: invokevirtual #61                 // Method addEscape:(CLjava/lang/String;)Lorg/apache/curator/shaded/com/google/common/escape/CharEscaperBuilder;
      34: pop
      35: iinc          5, 1
      38: goto          14
      41: aload_0
      42: areturn

  public char[][] toArray();
    Code:
       0: aload_0
       1: getfield      #26                 // Field max:I
       4: iconst_1
       5: iadd
       6: anewarray     #59                 // class "[C"
       9: astore_1
      10: aload_0
      11: getfield      #31                 // Field map:Ljava/util/Map;
      14: invokeinterface #71,  1           // InterfaceMethod java/util/Map.entrySet:()Ljava/util/Set;
      19: invokeinterface #77,  1           // InterfaceMethod java/util/Set.iterator:()Ljava/util/Iterator;
      24: astore_2
      25: aload_2
      26: invokeinterface #85,  1           // InterfaceMethod java/util/Iterator.hasNext:()Z
      31: ifeq          73
      34: aload_2
      35: invokeinterface #89,  1           // InterfaceMethod java/util/Iterator.next:()Ljava/lang/Object;
      40: checkcast     #12                 // class java/util/Map$Entry
      43: astore_3
      44: aload_1
      45: aload_3
      46: invokeinterface #92,  1           // InterfaceMethod java/util/Map$Entry.getKey:()Ljava/lang/Object;
      51: checkcast     #37                 // class java/lang/Character
      54: invokevirtual #96                 // Method java/lang/Character.charValue:()C
      57: aload_3
      58: invokeinterface #99,  1           // InterfaceMethod java/util/Map$Entry.getValue:()Ljava/lang/Object;
      63: checkcast     #101                // class java/lang/String
      66: invokevirtual #105                // Method java/lang/String.toCharArray:()[C
      69: aastore
      70: goto          25
      73: aload_1
      74: areturn

  public org.apache.curator.shaded.com.google.common.escape.Escaper toEscaper();
    Code:
       0: new           #9                  // class org/apache/curator/shaded/com/google/common/escape/CharEscaperBuilder$CharArrayDecorator
       3: dup
       4: aload_0
       5: invokevirtual #114                // Method toArray:()[[C
       8: invokespecial #117                // Method org/apache/curator/shaded/com/google/common/escape/CharEscaperBuilder$CharArrayDecorator."<init>":([[C)V
      11: areturn
}
