Compiled from "AbortOnFailure.java"
public class org.elasticsearch.hadoop.handler.impl.AbortOnFailure<I extends org.elasticsearch.hadoop.handler.Exceptional, O, C extends org.elasticsearch.hadoop.handler.ErrorCollector<O>> implements org.elasticsearch.hadoop.handler.ErrorHandler<I, O, C> {
  public org.elasticsearch.hadoop.handler.impl.AbortOnFailure();
    Code:
       0: aload_0
       1: invokespecial #1                  // Method java/lang/Object."<init>":()V
       4: return

  public static <I extends org.elasticsearch.hadoop.handler.Exceptional, O, C extends org.elasticsearch.hadoop.handler.ErrorCollector<O>> org.elasticsearch.hadoop.handler.impl.AbortOnFailure<I, O, C> create();
    Code:
       0: new           #7                  // class org/elasticsearch/hadoop/handler/impl/AbortOnFailure
       3: dup
       4: invokespecial #9                  // Method "<init>":()V
       7: areturn

  public void init(java.util.Properties);
    Code:
       0: return

  public void close();
    Code:
       0: return

  public org.elasticsearch.hadoop.handler.HandlerResult onError(I, C) throws java.lang.Exception;
    Code:
       0: getstatic     #10                 // Field org/elasticsearch/hadoop/handler/HandlerResult.ABORT:Lorg/elasticsearch/hadoop/handler/HandlerResult;
       3: areturn
}
