Compiled from "LogRenderer.java"
public abstract class org.elasticsearch.hadoop.handler.impl.LogRenderer<I extends org.elasticsearch.hadoop.handler.Exceptional> {
  public org.elasticsearch.hadoop.handler.impl.LogRenderer();
    Code:
       0: aload_0
       1: invokespecial #1                  // Method java/lang/Object."<init>":()V
       4: return

  public java.lang.String renderLog(I);
    Code:
       0: aload_1
       1: invokeinterface #7,  1            // InterfaceMethod org/elasticsearch/hadoop/handler/Exceptional.previousHandlerMessages:()Ljava/util/List;
       6: astore_2
       7: aload_2
       8: invokeinterface #13,  1           // InterfaceMethod java/util/List.isEmpty:()Z
      13: ifne          82
      16: new           #19                 // class java/lang/StringBuilder
      19: dup
      20: ldc           #21                 // String Previous handler messages:
      22: invokespecial #23                 // Method java/lang/StringBuilder."<init>":(Ljava/lang/String;)V
      25: astore        4
      27: aload_2
      28: invokeinterface #26,  1           // InterfaceMethod java/util/List.iterator:()Ljava/util/Iterator;
      33: astore        5
      35: aload         5
      37: invokeinterface #30,  1           // InterfaceMethod java/util/Iterator.hasNext:()Z
      42: ifeq          73
      45: aload         5
      47: invokeinterface #35,  1           // InterfaceMethod java/util/Iterator.next:()Ljava/lang/Object;
      52: checkcast     #39                 // class java/lang/String
      55: astore        6
      57: aload         4
      59: ldc           #41                 // String \n\t
      61: invokevirtual #43                 // Method java/lang/StringBuilder.append:(Ljava/lang/String;)Ljava/lang/StringBuilder;
      64: aload         6
      66: invokevirtual #43                 // Method java/lang/StringBuilder.append:(Ljava/lang/String;)Ljava/lang/StringBuilder;
      69: pop
      70: goto          35
      73: aload         4
      75: invokevirtual #47                 // Method java/lang/StringBuilder.toString:()Ljava/lang/String;
      78: astore_3
      79: goto          85
      82: ldc           #51                 // String
      84: astore_3
      85: aload_0
      86: aload_1
      87: invokevirtual #53                 // Method convert:(Lorg/elasticsearch/hadoop/handler/Exceptional;)Ljava/lang/String;
      90: astore        4
      92: new           #19                 // class java/lang/StringBuilder
      95: dup
      96: invokespecial #59                 // Method java/lang/StringBuilder."<init>":()V
      99: aload         4
     101: invokevirtual #43                 // Method java/lang/StringBuilder.append:(Ljava/lang/String;)Ljava/lang/StringBuilder;
     104: ldc           #60                 // String \n
     106: invokevirtual #43                 // Method java/lang/StringBuilder.append:(Ljava/lang/String;)Ljava/lang/StringBuilder;
     109: aload_3
     110: invokevirtual #43                 // Method java/lang/StringBuilder.append:(Ljava/lang/String;)Ljava/lang/StringBuilder;
     113: invokevirtual #47                 // Method java/lang/StringBuilder.toString:()Ljava/lang/String;
     116: areturn

  public abstract java.lang.String convert(I);
}
