Compiled from "DatasetGraphCopyAdd.java"
class org.apache.jena.sparql.core.DatasetGraphCopyAdd extends org.apache.jena.sparql.core.DatasetGraphWrapper {
  public org.apache.jena.sparql.core.DatasetGraphCopyAdd(boolean, org.apache.jena.sparql.core.DatasetGraph);
    Code:
       0: aload_0
       1: aload_2
       2: invokespecial #1                  // Method org/apache/jena/sparql/core/DatasetGraphWrapper."<init>":(Lorg/apache/jena/sparql/core/DatasetGraph;)V
       5: return

  public void addGraph(org.apache.jena.graph.Node, org.apache.jena.graph.Graph);
    Code:
       0: aload_2
       1: aconst_null
       2: aconst_null
       3: aconst_null
       4: invokeinterface #2,  4            // InterfaceMethod org/apache/jena/graph/Graph.find:(Lorg/apache/jena/graph/Node;Lorg/apache/jena/graph/Node;Lorg/apache/jena/graph/Node;)Lorg/apache/jena/util/iterator/ExtendedIterator;
       9: aload_0
      10: aload_1
      11: invokedynamic #3,  0              // InvokeDynamic #0:accept:(Lorg/apache/jena/sparql/core/DatasetGraphCopyAdd;Lorg/apache/jena/graph/Node;)Ljava/util/function/Consumer;
      16: invokeinterface #4,  2            // InterfaceMethod org/apache/jena/util/iterator/ExtendedIterator.forEachRemaining:(Ljava/util/function/Consumer;)V
      21: return

  private void lambda$addGraph$0(org.apache.jena.graph.Node, org.apache.jena.graph.Triple);
    Code:
       0: aload_1
       1: aload_2
       2: invokestatic  #5                  // Method org/apache/jena/sparql/core/Quad.create:(Lorg/apache/jena/graph/Node;Lorg/apache/jena/graph/Triple;)Lorg/apache/jena/sparql/core/Quad;
       5: astore_3
       6: aload_0
       7: aload_3
       8: invokespecial #6                  // Method org/apache/jena/sparql/core/DatasetGraphWrapper.add:(Lorg/apache/jena/sparql/core/Quad;)V
      11: return
}
