Compiled from "ModelImpl.java"
public class io.swagger.models.ModelImpl extends io.swagger.models.AbstractModel {
  public static final java.lang.String OBJECT;

  private java.lang.String type;

  private java.lang.String format;

  private java.lang.String name;

  private java.util.List<java.lang.String> required;

  private java.util.Map<java.lang.String, io.swagger.models.properties.Property> properties;

  private java.lang.Boolean allowEmptyValue;

  private java.lang.Boolean uniqueItems;

  private boolean isSimple;

  private java.lang.String description;

  private java.lang.Object example;

  private io.swagger.models.properties.Property additionalProperties;

  private java.lang.String discriminator;

  private io.swagger.models.Xml xml;

  private java.lang.String defaultValue;

  private java.util.List<java.lang.String> _enum;

  private java.math.BigDecimal minimum;

  private java.math.BigDecimal maximum;

  public io.swagger.models.ModelImpl();
    Code:
       0: aload_0
       1: invokespecial #1                  // Method io/swagger/models/AbstractModel."<init>":()V
       4: aload_0
       5: iconst_0
       6: putfield      #2                  // Field isSimple:Z
       9: return

  public io.swagger.models.ModelImpl _enum(java.util.List<java.lang.String>);
    Code:
       0: aload_0
       1: aload_1
       2: putfield      #3                  // Field _enum:Ljava/util/List;
       5: aload_0
       6: areturn

  public io.swagger.models.ModelImpl _enum(java.lang.String);
    Code:
       0: aload_0
       1: getfield      #3                  // Field _enum:Ljava/util/List;
       4: ifnonnull     18
       7: aload_0
       8: new           #4                  // class java/util/ArrayList
      11: dup
      12: invokespecial #5                  // Method java/util/ArrayList."<init>":()V
      15: putfield      #3                  // Field _enum:Ljava/util/List;
      18: aload_0
      19: getfield      #3                  // Field _enum:Ljava/util/List;
      22: aload_1
      23: invokeinterface #6,  2            // InterfaceMethod java/util/List.add:(Ljava/lang/Object;)Z
      28: pop
      29: aload_0
      30: areturn

  public java.util.List<java.lang.String> getEnum();
    Code:
       0: aload_0
       1: getfield      #3                  // Field _enum:Ljava/util/List;
       4: areturn

  public void setEnum(java.util.List<java.lang.String>);
    Code:
       0: aload_0
       1: aload_1
       2: putfield      #3                  // Field _enum:Ljava/util/List;
       5: return

  public io.swagger.models.ModelImpl discriminator(java.lang.String);
    Code:
       0: aload_0
       1: aload_1
       2: invokevirtual #7                  // Method setDiscriminator:(Ljava/lang/String;)V
       5: aload_0
       6: areturn

  public io.swagger.models.ModelImpl type(java.lang.String);
    Code:
       0: aload_0
       1: aload_1
       2: invokevirtual #8                  // Method setType:(Ljava/lang/String;)V
       5: aload_0
       6: areturn

  public io.swagger.models.ModelImpl format(java.lang.String);
    Code:
       0: aload_0
       1: aload_1
       2: invokevirtual #9                  // Method setFormat:(Ljava/lang/String;)V
       5: aload_0
       6: areturn

  public io.swagger.models.ModelImpl name(java.lang.String);
    Code:
       0: aload_0
       1: aload_1
       2: invokevirtual #10                 // Method setName:(Ljava/lang/String;)V
       5: aload_0
       6: areturn

  public io.swagger.models.ModelImpl uniqueItems(java.lang.Boolean);
    Code:
       0: aload_0
       1: aload_1
       2: invokevirtual #11                 // Method setUniqueItems:(Ljava/lang/Boolean;)V
       5: aload_0
       6: areturn

  public io.swagger.models.ModelImpl allowEmptyValue(java.lang.Boolean);
    Code:
       0: aload_0
       1: aload_1
       2: invokevirtual #12                 // Method setAllowEmptyValue:(Ljava/lang/Boolean;)V
       5: aload_0
       6: areturn

  public io.swagger.models.ModelImpl description(java.lang.String);
    Code:
       0: aload_0
       1: aload_1
       2: invokevirtual #13                 // Method setDescription:(Ljava/lang/String;)V
       5: aload_0
       6: areturn

  public io.swagger.models.ModelImpl property(java.lang.String, io.swagger.models.properties.Property);
    Code:
       0: aload_0
       1: aload_1
       2: aload_2
       3: invokevirtual #14                 // Method addProperty:(Ljava/lang/String;Lio/swagger/models/properties/Property;)V
       6: aload_0
       7: areturn

  public io.swagger.models.ModelImpl example(java.lang.Object);
    Code:
       0: aload_0
       1: aload_1
       2: invokevirtual #15                 // Method setExample:(Ljava/lang/Object;)V
       5: aload_0
       6: areturn

  public io.swagger.models.ModelImpl additionalProperties(io.swagger.models.properties.Property);
    Code:
       0: aload_0
       1: aload_1
       2: invokevirtual #16                 // Method setAdditionalProperties:(Lio/swagger/models/properties/Property;)V
       5: aload_0
       6: areturn

  public io.swagger.models.ModelImpl required(java.lang.String);
    Code:
       0: aload_0
       1: aload_1
       2: invokevirtual #17                 // Method addRequired:(Ljava/lang/String;)V
       5: aload_0
       6: areturn

  public io.swagger.models.ModelImpl xml(io.swagger.models.Xml);
    Code:
       0: aload_0
       1: aload_1
       2: invokevirtual #18                 // Method setXml:(Lio/swagger/models/Xml;)V
       5: aload_0
       6: areturn

  public io.swagger.models.ModelImpl minimum(java.math.BigDecimal);
    Code:
       0: aload_0
       1: aload_1
       2: putfield      #19                 // Field minimum:Ljava/math/BigDecimal;
       5: aload_0
       6: areturn

  public io.swagger.models.ModelImpl maximum(java.math.BigDecimal);
    Code:
       0: aload_0
       1: aload_1
       2: putfield      #20                 // Field maximum:Ljava/math/BigDecimal;
       5: aload_0
       6: areturn

  public java.lang.String getDiscriminator();
    Code:
       0: aload_0
       1: getfield      #21                 // Field discriminator:Ljava/lang/String;
       4: areturn

  public void setDiscriminator(java.lang.String);
    Code:
       0: aload_0
       1: aload_1
       2: putfield      #21                 // Field discriminator:Ljava/lang/String;
       5: return

  public java.lang.String getName();
    Code:
       0: aload_0
       1: getfield      #22                 // Field name:Ljava/lang/String;
       4: areturn

  public void setName(java.lang.String);
    Code:
       0: aload_0
       1: aload_1
       2: putfield      #22                 // Field name:Ljava/lang/String;
       5: return

  public java.lang.String getDescription();
    Code:
       0: aload_0
       1: getfield      #23                 // Field description:Ljava/lang/String;
       4: areturn

  public void setDescription(java.lang.String);
    Code:
       0: aload_0
       1: aload_1
       2: putfield      #23                 // Field description:Ljava/lang/String;
       5: return

  public boolean isSimple();
    Code:
       0: aload_0
       1: getfield      #2                  // Field isSimple:Z
       4: ireturn

  public void setSimple(boolean);
    Code:
       0: aload_0
       1: iload_1
       2: putfield      #2                  // Field isSimple:Z
       5: return

  public io.swagger.models.properties.Property getAdditionalProperties();
    Code:
       0: aload_0
       1: getfield      #24                 // Field additionalProperties:Lio/swagger/models/properties/Property;
       4: areturn

  public void setAdditionalProperties(io.swagger.models.properties.Property);
    Code:
       0: aload_0
       1: ldc           #25                 // String object
       3: invokevirtual #26                 // Method type:(Ljava/lang/String;)Lio/swagger/models/ModelImpl;
       6: pop
       7: aload_0
       8: aload_1
       9: putfield      #24                 // Field additionalProperties:Lio/swagger/models/properties/Property;
      12: return

  public java.lang.Boolean getAllowEmptyValue();
    Code:
       0: aload_0
       1: getfield      #27                 // Field allowEmptyValue:Ljava/lang/Boolean;
       4: areturn

  public void setAllowEmptyValue(java.lang.Boolean);
    Code:
       0: aload_1
       1: ifnull        9
       4: aload_0
       5: aload_1
       6: putfield      #27                 // Field allowEmptyValue:Ljava/lang/Boolean;
       9: return

  public java.lang.String getType();
    Code:
       0: aload_0
       1: getfield      #28                 // Field type:Ljava/lang/String;
       4: areturn

  public void setType(java.lang.String);
    Code:
       0: aload_0
       1: aload_1
       2: putfield      #28                 // Field type:Ljava/lang/String;
       5: return

  public java.lang.String getFormat();
    Code:
       0: aload_0
       1: getfield      #29                 // Field format:Ljava/lang/String;
       4: areturn

  public void setFormat(java.lang.String);
    Code:
       0: aload_0
       1: aload_1
       2: putfield      #29                 // Field format:Ljava/lang/String;
       5: return

  public void addRequired(java.lang.String);
    Code:
       0: aload_0
       1: getfield      #30                 // Field required:Ljava/util/List;
       4: ifnonnull     18
       7: aload_0
       8: new           #4                  // class java/util/ArrayList
      11: dup
      12: invokespecial #5                  // Method java/util/ArrayList."<init>":()V
      15: putfield      #30                 // Field required:Ljava/util/List;
      18: aload_0
      19: getfield      #30                 // Field required:Ljava/util/List;
      22: aload_1
      23: invokeinterface #6,  2            // InterfaceMethod java/util/List.add:(Ljava/lang/Object;)Z
      28: pop
      29: aload_0
      30: getfield      #31                 // Field properties:Ljava/util/Map;
      33: aload_1
      34: invokeinterface #32,  2           // InterfaceMethod java/util/Map.get:(Ljava/lang/Object;)Ljava/lang/Object;
      39: checkcast     #33                 // class io/swagger/models/properties/Property
      42: astore_2
      43: aload_2
      44: ifnull        54
      47: aload_2
      48: iconst_1
      49: invokeinterface #34,  2           // InterfaceMethod io/swagger/models/properties/Property.setRequired:(Z)V
      54: return

  public java.util.List<java.lang.String> getRequired();
    Code:
       0: new           #4                  // class java/util/ArrayList
       3: dup
       4: invokespecial #5                  // Method java/util/ArrayList."<init>":()V
       7: astore_1
       8: aload_0
       9: getfield      #31                 // Field properties:Ljava/util/Map;
      12: ifnull        90
      15: aload_0
      16: getfield      #31                 // Field properties:Ljava/util/Map;
      19: invokeinterface #35,  1           // InterfaceMethod java/util/Map.keySet:()Ljava/util/Set;
      24: invokeinterface #36,  1           // InterfaceMethod java/util/Set.iterator:()Ljava/util/Iterator;
      29: astore_2
      30: aload_2
      31: invokeinterface #37,  1           // InterfaceMethod java/util/Iterator.hasNext:()Z
      36: ifeq          90
      39: aload_2
      40: invokeinterface #38,  1           // InterfaceMethod java/util/Iterator.next:()Ljava/lang/Object;
      45: checkcast     #39                 // class java/lang/String
      48: astore_3
      49: aload_0
      50: getfield      #31                 // Field properties:Ljava/util/Map;
      53: aload_3
      54: invokeinterface #32,  2           // InterfaceMethod java/util/Map.get:(Ljava/lang/Object;)Ljava/lang/Object;
      59: checkcast     #33                 // class io/swagger/models/properties/Property
      62: astore        4
      64: aload         4
      66: ifnull        87
      69: aload         4
      71: invokeinterface #40,  1           // InterfaceMethod io/swagger/models/properties/Property.getRequired:()Z
      76: ifeq          87
      79: aload_1
      80: aload_3
      81: invokeinterface #6,  2            // InterfaceMethod java/util/List.add:(Ljava/lang/Object;)Z
      86: pop
      87: goto          30
      90: aload_1
      91: invokestatic  #41                 // Method java/util/Collections.sort:(Ljava/util/List;)V
      94: aload_1
      95: invokeinterface #42,  1           // InterfaceMethod java/util/List.size:()I
     100: ifle          105
     103: aload_1
     104: areturn
     105: aconst_null
     106: areturn

  public void setRequired(java.util.List<java.lang.String>);
    Code:
       0: aload_0
       1: aload_1
       2: putfield      #30                 // Field required:Ljava/util/List;
       5: aload_0
       6: getfield      #31                 // Field properties:Ljava/util/Map;
       9: ifnull        69
      12: aload_1
      13: invokeinterface #43,  1           // InterfaceMethod java/util/List.iterator:()Ljava/util/Iterator;
      18: astore_2
      19: aload_2
      20: invokeinterface #37,  1           // InterfaceMethod java/util/Iterator.hasNext:()Z
      25: ifeq          69
      28: aload_2
      29: invokeinterface #38,  1           // InterfaceMethod java/util/Iterator.next:()Ljava/lang/Object;
      34: checkcast     #39                 // class java/lang/String
      37: astore_3
      38: aload_0
      39: getfield      #31                 // Field properties:Ljava/util/Map;
      42: aload_3
      43: invokeinterface #32,  2           // InterfaceMethod java/util/Map.get:(Ljava/lang/Object;)Ljava/lang/Object;
      48: checkcast     #33                 // class io/swagger/models/properties/Property
      51: astore        4
      53: aload         4
      55: ifnull        66
      58: aload         4
      60: iconst_1
      61: invokeinterface #34,  2           // InterfaceMethod io/swagger/models/properties/Property.setRequired:(Z)V
      66: goto          19
      69: return

  public void addProperty(java.lang.String, io.swagger.models.properties.Property);
    Code:
       0: aload_2
       1: ifnonnull     5
       4: return
       5: aload_0
       6: getfield      #31                 // Field properties:Ljava/util/Map;
       9: ifnonnull     23
      12: aload_0
      13: new           #44                 // class java/util/LinkedHashMap
      16: dup
      17: invokespecial #45                 // Method java/util/LinkedHashMap."<init>":()V
      20: putfield      #31                 // Field properties:Ljava/util/Map;
      23: aload_0
      24: getfield      #30                 // Field required:Ljava/util/List;
      27: ifnull        79
      30: aload_0
      31: getfield      #30                 // Field required:Ljava/util/List;
      34: invokeinterface #43,  1           // InterfaceMethod java/util/List.iterator:()Ljava/util/Iterator;
      39: astore_3
      40: aload_3
      41: invokeinterface #37,  1           // InterfaceMethod java/util/Iterator.hasNext:()Z
      46: ifeq          79
      49: aload_3
      50: invokeinterface #38,  1           // InterfaceMethod java/util/Iterator.next:()Ljava/lang/Object;
      55: checkcast     #39                 // class java/lang/String
      58: astore        4
      60: aload_1
      61: aload         4
      63: invokevirtual #46                 // Method java/lang/String.equals:(Ljava/lang/Object;)Z
      66: ifeq          76
      69: aload_2
      70: iconst_1
      71: invokeinterface #34,  2           // InterfaceMethod io/swagger/models/properties/Property.setRequired:(Z)V
      76: goto          40
      79: aload_0
      80: getfield      #31                 // Field properties:Ljava/util/Map;
      83: aload_1
      84: aload_2
      85: invokeinterface #47,  3           // InterfaceMethod java/util/Map.put:(Ljava/lang/Object;Ljava/lang/Object;)Ljava/lang/Object;
      90: pop
      91: return

  public java.util.Map<java.lang.String, io.swagger.models.properties.Property> getProperties();
    Code:
       0: aload_0
       1: getfield      #31                 // Field properties:Ljava/util/Map;
       4: areturn

  public void setProperties(java.util.Map<java.lang.String, io.swagger.models.properties.Property>);
    Code:
       0: aload_1
       1: ifnull        53
       4: aload_1
       5: invokeinterface #35,  1           // InterfaceMethod java/util/Map.keySet:()Ljava/util/Set;
      10: invokeinterface #36,  1           // InterfaceMethod java/util/Set.iterator:()Ljava/util/Iterator;
      15: astore_2
      16: aload_2
      17: invokeinterface #37,  1           // InterfaceMethod java/util/Iterator.hasNext:()Z
      22: ifeq          53
      25: aload_2
      26: invokeinterface #38,  1           // InterfaceMethod java/util/Iterator.next:()Ljava/lang/Object;
      31: checkcast     #39                 // class java/lang/String
      34: astore_3
      35: aload_0
      36: aload_3
      37: aload_1
      38: aload_3
      39: invokeinterface #32,  2           // InterfaceMethod java/util/Map.get:(Ljava/lang/Object;)Ljava/lang/Object;
      44: checkcast     #33                 // class io/swagger/models/properties/Property
      47: invokevirtual #14                 // Method addProperty:(Ljava/lang/String;Lio/swagger/models/properties/Property;)V
      50: goto          16
      53: return

  public java.lang.Object getExample();
    Code:
       0: aload_0
       1: getfield      #48                 // Field example:Ljava/lang/Object;
       4: ifnonnull     7
       7: aload_0
       8: getfield      #48                 // Field example:Ljava/lang/Object;
      11: areturn

  public void setExample(java.lang.Object);
    Code:
       0: aload_0
       1: aload_1
       2: putfield      #48                 // Field example:Ljava/lang/Object;
       5: return

  public io.swagger.models.Xml getXml();
    Code:
       0: aload_0
       1: getfield      #49                 // Field xml:Lio/swagger/models/Xml;
       4: areturn

  public void setXml(io.swagger.models.Xml);
    Code:
       0: aload_0
       1: aload_1
       2: putfield      #49                 // Field xml:Lio/swagger/models/Xml;
       5: return

  public java.lang.Object getDefaultValue();
    Code:
       0: aload_0
       1: getfield      #50                 // Field defaultValue:Ljava/lang/String;
       4: ifnonnull     9
       7: aconst_null
       8: areturn
       9: ldc           #51                 // String integer
      11: aload_0
      12: getfield      #28                 // Field type:Ljava/lang/String;
      15: invokevirtual #46                 // Method java/lang/String.equals:(Ljava/lang/Object;)Z
      18: ifeq          33
      21: new           #52                 // class java/lang/Integer
      24: dup
      25: aload_0
      26: getfield      #50                 // Field defaultValue:Ljava/lang/String;
      29: invokespecial #53                 // Method java/lang/Integer."<init>":(Ljava/lang/String;)V
      32: areturn
      33: ldc           #54                 // String number
      35: aload_0
      36: getfield      #28                 // Field type:Ljava/lang/String;
      39: invokevirtual #46                 // Method java/lang/String.equals:(Ljava/lang/Object;)Z
      42: ifeq          57
      45: new           #55                 // class java/math/BigDecimal
      48: dup
      49: aload_0
      50: getfield      #50                 // Field defaultValue:Ljava/lang/String;
      53: invokespecial #56                 // Method java/math/BigDecimal."<init>":(Ljava/lang/String;)V
      56: areturn
      57: goto          63
      60: astore_1
      61: aconst_null
      62: areturn
      63: aload_0
      64: getfield      #50                 // Field defaultValue:Ljava/lang/String;
      67: areturn
    Exception table:
       from    to  target type
           9    32    60   Class java/lang/Exception
          33    56    60   Class java/lang/Exception

  public void setDefaultValue(java.lang.String);
    Code:
       0: aload_0
       1: aload_1
       2: putfield      #50                 // Field defaultValue:Ljava/lang/String;
       5: return

  public java.math.BigDecimal getMinimum();
    Code:
       0: aload_0
       1: getfield      #19                 // Field minimum:Ljava/math/BigDecimal;
       4: areturn

  public void setMinimum(java.math.BigDecimal);
    Code:
       0: aload_0
       1: aload_1
       2: putfield      #19                 // Field minimum:Ljava/math/BigDecimal;
       5: return

  public java.math.BigDecimal getMaximum();
    Code:
       0: aload_0
       1: getfield      #20                 // Field maximum:Ljava/math/BigDecimal;
       4: areturn

  public void setMaximum(java.math.BigDecimal);
    Code:
       0: aload_0
       1: aload_1
       2: putfield      #20                 // Field maximum:Ljava/math/BigDecimal;
       5: return

  public java.lang.Boolean getUniqueItems();
    Code:
       0: aload_0
       1: getfield      #58                 // Field uniqueItems:Ljava/lang/Boolean;
       4: areturn

  public boolean equals(java.lang.Object);
    Code:
       0: aload_0
       1: aload_1
       2: if_acmpne     7
       5: iconst_1
       6: ireturn
       7: aload_1
       8: instanceof    #59                 // class io/swagger/models/ModelImpl
      11: ifne          16
      14: iconst_0
      15: ireturn
      16: aload_0
      17: aload_1
      18: invokespecial #60                 // Method io/swagger/models/AbstractModel.equals:(Ljava/lang/Object;)Z
      21: ifne          26
      24: iconst_0
      25: ireturn
      26: aload_1
      27: checkcast     #59                 // class io/swagger/models/ModelImpl
      30: astore_2
      31: aload_0
      32: getfield      #2                  // Field isSimple:Z
      35: aload_2
      36: getfield      #2                  // Field isSimple:Z
      39: if_icmpeq     44
      42: iconst_0
      43: ireturn
      44: aload_0
      45: getfield      #28                 // Field type:Ljava/lang/String;
      48: ifnull        68
      51: aload_0
      52: getfield      #28                 // Field type:Ljava/lang/String;
      55: aload_2
      56: getfield      #28                 // Field type:Ljava/lang/String;
      59: invokevirtual #46                 // Method java/lang/String.equals:(Ljava/lang/Object;)Z
      62: ifne          77
      65: goto          75
      68: aload_2
      69: getfield      #28                 // Field type:Ljava/lang/String;
      72: ifnull        77
      75: iconst_0
      76: ireturn
      77: aload_0
      78: getfield      #29                 // Field format:Ljava/lang/String;
      81: ifnull        101
      84: aload_0
      85: getfield      #29                 // Field format:Ljava/lang/String;
      88: aload_2
      89: getfield      #29                 // Field format:Ljava/lang/String;
      92: invokevirtual #46                 // Method java/lang/String.equals:(Ljava/lang/Object;)Z
      95: ifne          110
      98: goto          108
     101: aload_2
     102: getfield      #29                 // Field format:Ljava/lang/String;
     105: ifnull        110
     108: iconst_0
     109: ireturn
     110: aload_0
     111: getfield      #22                 // Field name:Ljava/lang/String;
     114: ifnull        134
     117: aload_0
     118: getfield      #22                 // Field name:Ljava/lang/String;
     121: aload_2
     122: getfield      #22                 // Field name:Ljava/lang/String;
     125: invokevirtual #46                 // Method java/lang/String.equals:(Ljava/lang/Object;)Z
     128: ifne          143
     131: goto          141
     134: aload_2
     135: getfield      #22                 // Field name:Ljava/lang/String;
     138: ifnull        143
     141: iconst_0
     142: ireturn
     143: aload_0
     144: getfield      #30                 // Field required:Ljava/util/List;
     147: ifnull        169
     150: aload_0
     151: getfield      #30                 // Field required:Ljava/util/List;
     154: aload_2
     155: getfield      #30                 // Field required:Ljava/util/List;
     158: invokeinterface #61,  2           // InterfaceMethod java/util/List.equals:(Ljava/lang/Object;)Z
     163: ifne          178
     166: goto          176
     169: aload_2
     170: getfield      #30                 // Field required:Ljava/util/List;
     173: ifnull        178
     176: iconst_0
     177: ireturn
     178: aload_0
     179: getfield      #31                 // Field properties:Ljava/util/Map;
     182: ifnull        204
     185: aload_0
     186: getfield      #31                 // Field properties:Ljava/util/Map;
     189: aload_2
     190: getfield      #31                 // Field properties:Ljava/util/Map;
     193: invokeinterface #62,  2           // InterfaceMethod java/util/Map.equals:(Ljava/lang/Object;)Z
     198: ifne          213
     201: goto          211
     204: aload_2
     205: getfield      #31                 // Field properties:Ljava/util/Map;
     208: ifnull        213
     211: iconst_0
     212: ireturn
     213: aload_0
     214: getfield      #27                 // Field allowEmptyValue:Ljava/lang/Boolean;
     217: ifnull        237
     220: aload_0
     221: getfield      #27                 // Field allowEmptyValue:Ljava/lang/Boolean;
     224: aload_2
     225: getfield      #27                 // Field allowEmptyValue:Ljava/lang/Boolean;
     228: invokevirtual #63                 // Method java/lang/Boolean.equals:(Ljava/lang/Object;)Z
     231: ifne          246
     234: goto          244
     237: aload_2
     238: getfield      #27                 // Field allowEmptyValue:Ljava/lang/Boolean;
     241: ifnull        246
     244: iconst_0
     245: ireturn
     246: aload_0
     247: getfield      #58                 // Field uniqueItems:Ljava/lang/Boolean;
     250: ifnull        270
     253: aload_0
     254: getfield      #58                 // Field uniqueItems:Ljava/lang/Boolean;
     257: aload_2
     258: getfield      #58                 // Field uniqueItems:Ljava/lang/Boolean;
     261: invokevirtual #63                 // Method java/lang/Boolean.equals:(Ljava/lang/Object;)Z
     264: ifne          279
     267: goto          277
     270: aload_2
     271: getfield      #58                 // Field uniqueItems:Ljava/lang/Boolean;
     274: ifnull        279
     277: iconst_0
     278: ireturn
     279: aload_0
     280: getfield      #23                 // Field description:Ljava/lang/String;
     283: ifnull        303
     286: aload_0
     287: getfield      #23                 // Field description:Ljava/lang/String;
     290: aload_2
     291: getfield      #23                 // Field description:Ljava/lang/String;
     294: invokevirtual #46                 // Method java/lang/String.equals:(Ljava/lang/Object;)Z
     297: ifne          312
     300: goto          310
     303: aload_2
     304: getfield      #23                 // Field description:Ljava/lang/String;
     307: ifnull        312
     310: iconst_0
     311: ireturn
     312: aload_0
     313: getfield      #48                 // Field example:Ljava/lang/Object;
     316: ifnull        336
     319: aload_0
     320: getfield      #48                 // Field example:Ljava/lang/Object;
     323: aload_2
     324: getfield      #48                 // Field example:Ljava/lang/Object;
     327: invokevirtual #64                 // Method java/lang/Object.equals:(Ljava/lang/Object;)Z
     330: ifne          345
     333: goto          343
     336: aload_2
     337: getfield      #48                 // Field example:Ljava/lang/Object;
     340: ifnull        345
     343: iconst_0
     344: ireturn
     345: aload_0
     346: getfield      #24                 // Field additionalProperties:Lio/swagger/models/properties/Property;
     349: ifnull        369
     352: aload_0
     353: getfield      #24                 // Field additionalProperties:Lio/swagger/models/properties/Property;
     356: aload_2
     357: getfield      #24                 // Field additionalProperties:Lio/swagger/models/properties/Property;
     360: invokevirtual #64                 // Method java/lang/Object.equals:(Ljava/lang/Object;)Z
     363: ifne          378
     366: goto          376
     369: aload_2
     370: getfield      #24                 // Field additionalProperties:Lio/swagger/models/properties/Property;
     373: ifnull        378
     376: iconst_0
     377: ireturn
     378: aload_0
     379: getfield      #21                 // Field discriminator:Ljava/lang/String;
     382: ifnull        402
     385: aload_0
     386: getfield      #21                 // Field discriminator:Ljava/lang/String;
     389: aload_2
     390: getfield      #21                 // Field discriminator:Ljava/lang/String;
     393: invokevirtual #46                 // Method java/lang/String.equals:(Ljava/lang/Object;)Z
     396: ifne          411
     399: goto          409
     402: aload_2
     403: getfield      #21                 // Field discriminator:Ljava/lang/String;
     406: ifnull        411
     409: iconst_0
     410: ireturn
     411: aload_0
     412: getfield      #49                 // Field xml:Lio/swagger/models/Xml;
     415: ifnull        435
     418: aload_0
     419: getfield      #49                 // Field xml:Lio/swagger/models/Xml;
     422: aload_2
     423: getfield      #49                 // Field xml:Lio/swagger/models/Xml;
     426: invokevirtual #65                 // Method io/swagger/models/Xml.equals:(Ljava/lang/Object;)Z
     429: ifne          444
     432: goto          442
     435: aload_2
     436: getfield      #49                 // Field xml:Lio/swagger/models/Xml;
     439: ifnull        444
     442: iconst_0
     443: ireturn
     444: aload_0
     445: getfield      #50                 // Field defaultValue:Ljava/lang/String;
     448: ifnull        468
     451: aload_0
     452: getfield      #50                 // Field defaultValue:Ljava/lang/String;
     455: aload_2
     456: getfield      #50                 // Field defaultValue:Ljava/lang/String;
     459: invokevirtual #46                 // Method java/lang/String.equals:(Ljava/lang/Object;)Z
     462: ifne          477
     465: goto          475
     468: aload_2
     469: getfield      #50                 // Field defaultValue:Ljava/lang/String;
     472: ifnull        477
     475: iconst_0
     476: ireturn
     477: aload_0
     478: getfield      #3                  // Field _enum:Ljava/util/List;
     481: ifnull        503
     484: aload_0
     485: getfield      #3                  // Field _enum:Ljava/util/List;
     488: aload_2
     489: getfield      #3                  // Field _enum:Ljava/util/List;
     492: invokeinterface #61,  2           // InterfaceMethod java/util/List.equals:(Ljava/lang/Object;)Z
     497: ifne          512
     500: goto          510
     503: aload_2
     504: getfield      #3                  // Field _enum:Ljava/util/List;
     507: ifnull        512
     510: iconst_0
     511: ireturn
     512: aload_0
     513: getfield      #19                 // Field minimum:Ljava/math/BigDecimal;
     516: ifnull        536
     519: aload_0
     520: getfield      #19                 // Field minimum:Ljava/math/BigDecimal;
     523: aload_2
     524: getfield      #19                 // Field minimum:Ljava/math/BigDecimal;
     527: invokevirtual #66                 // Method java/math/BigDecimal.equals:(Ljava/lang/Object;)Z
     530: ifne          545
     533: goto          543
     536: aload_2
     537: getfield      #19                 // Field minimum:Ljava/math/BigDecimal;
     540: ifnull        545
     543: iconst_0
     544: ireturn
     545: aload_0
     546: getfield      #20                 // Field maximum:Ljava/math/BigDecimal;
     549: ifnull        566
     552: aload_0
     553: getfield      #20                 // Field maximum:Ljava/math/BigDecimal;
     556: aload_2
     557: getfield      #20                 // Field maximum:Ljava/math/BigDecimal;
     560: invokevirtual #66                 // Method java/math/BigDecimal.equals:(Ljava/lang/Object;)Z
     563: goto          578
     566: aload_2
     567: getfield      #20                 // Field maximum:Ljava/math/BigDecimal;
     570: ifnonnull     577
     573: iconst_1
     574: goto          578
     577: iconst_0
     578: ireturn

  public int hashCode();
    Code:
       0: aload_0
       1: invokespecial #67                 // Method io/swagger/models/AbstractModel.hashCode:()I
       4: istore_1
       5: bipush        31
       7: iload_1
       8: imul
       9: aload_0
      10: getfield      #28                 // Field type:Ljava/lang/String;
      13: ifnull        26
      16: aload_0
      17: getfield      #28                 // Field type:Ljava/lang/String;
      20: invokevirtual #68                 // Method java/lang/String.hashCode:()I
      23: goto          27
      26: iconst_0
      27: iadd
      28: istore_1
      29: bipush        31
      31: iload_1
      32: imul
      33: aload_0
      34: getfield      #29                 // Field format:Ljava/lang/String;
      37: ifnull        50
      40: aload_0
      41: getfield      #29                 // Field format:Ljava/lang/String;
      44: invokevirtual #68                 // Method java/lang/String.hashCode:()I
      47: goto          51
      50: iconst_0
      51: iadd
      52: istore_1
      53: bipush        31
      55: iload_1
      56: imul
      57: aload_0
      58: getfield      #22                 // Field name:Ljava/lang/String;
      61: ifnull        74
      64: aload_0
      65: getfield      #22                 // Field name:Ljava/lang/String;
      68: invokevirtual #68                 // Method java/lang/String.hashCode:()I
      71: goto          75
      74: iconst_0
      75: iadd
      76: istore_1
      77: bipush        31
      79: iload_1
      80: imul
      81: aload_0
      82: getfield      #30                 // Field required:Ljava/util/List;
      85: ifnull        100
      88: aload_0
      89: getfield      #30                 // Field required:Ljava/util/List;
      92: invokeinterface #69,  1           // InterfaceMethod java/util/List.hashCode:()I
      97: goto          101
     100: iconst_0
     101: iadd
     102: istore_1
     103: bipush        31
     105: iload_1
     106: imul
     107: aload_0
     108: getfield      #31                 // Field properties:Ljava/util/Map;
     111: ifnull        126
     114: aload_0
     115: getfield      #31                 // Field properties:Ljava/util/Map;
     118: invokeinterface #70,  1           // InterfaceMethod java/util/Map.hashCode:()I
     123: goto          127
     126: iconst_0
     127: iadd
     128: istore_1
     129: bipush        31
     131: iload_1
     132: imul
     133: aload_0
     134: getfield      #27                 // Field allowEmptyValue:Ljava/lang/Boolean;
     137: ifnull        150
     140: aload_0
     141: getfield      #27                 // Field allowEmptyValue:Ljava/lang/Boolean;
     144: invokevirtual #71                 // Method java/lang/Boolean.hashCode:()I
     147: goto          151
     150: iconst_0
     151: iadd
     152: istore_1
     153: bipush        31
     155: iload_1
     156: imul
     157: aload_0
     158: getfield      #58                 // Field uniqueItems:Ljava/lang/Boolean;
     161: ifnull        174
     164: aload_0
     165: getfield      #58                 // Field uniqueItems:Ljava/lang/Boolean;
     168: invokevirtual #71                 // Method java/lang/Boolean.hashCode:()I
     171: goto          175
     174: iconst_0
     175: iadd
     176: istore_1
     177: bipush        31
     179: iload_1
     180: imul
     181: aload_0
     182: getfield      #2                  // Field isSimple:Z
     185: ifeq          192
     188: iconst_1
     189: goto          193
     192: iconst_0
     193: iadd
     194: istore_1
     195: bipush        31
     197: iload_1
     198: imul
     199: aload_0
     200: getfield      #23                 // Field description:Ljava/lang/String;
     203: ifnull        216
     206: aload_0
     207: getfield      #23                 // Field description:Ljava/lang/String;
     210: invokevirtual #68                 // Method java/lang/String.hashCode:()I
     213: goto          217
     216: iconst_0
     217: iadd
     218: istore_1
     219: bipush        31
     221: iload_1
     222: imul
     223: aload_0
     224: getfield      #48                 // Field example:Ljava/lang/Object;
     227: ifnull        240
     230: aload_0
     231: getfield      #48                 // Field example:Ljava/lang/Object;
     234: invokevirtual #72                 // Method java/lang/Object.hashCode:()I
     237: goto          241
     240: iconst_0
     241: iadd
     242: istore_1
     243: bipush        31
     245: iload_1
     246: imul
     247: aload_0
     248: getfield      #24                 // Field additionalProperties:Lio/swagger/models/properties/Property;
     251: ifnull        264
     254: aload_0
     255: getfield      #24                 // Field additionalProperties:Lio/swagger/models/properties/Property;
     258: invokevirtual #72                 // Method java/lang/Object.hashCode:()I
     261: goto          265
     264: iconst_0
     265: iadd
     266: istore_1
     267: bipush        31
     269: iload_1
     270: imul
     271: aload_0
     272: getfield      #21                 // Field discriminator:Ljava/lang/String;
     275: ifnull        288
     278: aload_0
     279: getfield      #21                 // Field discriminator:Ljava/lang/String;
     282: invokevirtual #68                 // Method java/lang/String.hashCode:()I
     285: goto          289
     288: iconst_0
     289: iadd
     290: istore_1
     291: bipush        31
     293: iload_1
     294: imul
     295: aload_0
     296: getfield      #49                 // Field xml:Lio/swagger/models/Xml;
     299: ifnull        312
     302: aload_0
     303: getfield      #49                 // Field xml:Lio/swagger/models/Xml;
     306: invokevirtual #73                 // Method io/swagger/models/Xml.hashCode:()I
     309: goto          313
     312: iconst_0
     313: iadd
     314: istore_1
     315: bipush        31
     317: iload_1
     318: imul
     319: aload_0
     320: getfield      #50                 // Field defaultValue:Ljava/lang/String;
     323: ifnull        336
     326: aload_0
     327: getfield      #50                 // Field defaultValue:Ljava/lang/String;
     330: invokevirtual #68                 // Method java/lang/String.hashCode:()I
     333: goto          337
     336: iconst_0
     337: iadd
     338: istore_1
     339: bipush        31
     341: iload_1
     342: imul
     343: aload_0
     344: getfield      #3                  // Field _enum:Ljava/util/List;
     347: ifnull        362
     350: aload_0
     351: getfield      #3                  // Field _enum:Ljava/util/List;
     354: invokeinterface #69,  1           // InterfaceMethod java/util/List.hashCode:()I
     359: goto          363
     362: iconst_0
     363: iadd
     364: istore_1
     365: bipush        31
     367: iload_1
     368: imul
     369: aload_0
     370: getfield      #19                 // Field minimum:Ljava/math/BigDecimal;
     373: ifnull        386
     376: aload_0
     377: getfield      #19                 // Field minimum:Ljava/math/BigDecimal;
     380: invokevirtual #74                 // Method java/math/BigDecimal.hashCode:()I
     383: goto          387
     386: iconst_0
     387: iadd
     388: istore_1
     389: bipush        31
     391: iload_1
     392: imul
     393: aload_0
     394: getfield      #20                 // Field maximum:Ljava/math/BigDecimal;
     397: ifnull        410
     400: aload_0
     401: getfield      #20                 // Field maximum:Ljava/math/BigDecimal;
     404: invokevirtual #74                 // Method java/math/BigDecimal.hashCode:()I
     407: goto          411
     410: iconst_0
     411: iadd
     412: istore_1
     413: iload_1
     414: ireturn

  public void setUniqueItems(java.lang.Boolean);
    Code:
       0: aload_0
       1: aload_1
       2: putfield      #58                 // Field uniqueItems:Ljava/lang/Boolean;
       5: return

  public java.lang.Object clone();
    Code:
       0: new           #59                 // class io/swagger/models/ModelImpl
       3: dup
       4: invokespecial #75                 // Method "<init>":()V
       7: astore_1
       8: aload_0
       9: aload_1
      10: invokespecial #76                 // Method io/swagger/models/AbstractModel.cloneTo:(Ljava/lang/Object;)V
      13: aload_1
      14: aload_0
      15: getfield      #28                 // Field type:Ljava/lang/String;
      18: putfield      #28                 // Field type:Ljava/lang/String;
      21: aload_1
      22: aload_0
      23: getfield      #22                 // Field name:Ljava/lang/String;
      26: putfield      #22                 // Field name:Ljava/lang/String;
      29: aload_1
      30: aload_0
      31: getfield      #30                 // Field required:Ljava/util/List;
      34: putfield      #30                 // Field required:Ljava/util/List;
      37: aload_0
      38: getfield      #31                 // Field properties:Ljava/util/Map;
      41: ifnull        59
      44: aload_1
      45: new           #44                 // class java/util/LinkedHashMap
      48: dup
      49: aload_0
      50: getfield      #31                 // Field properties:Ljava/util/Map;
      53: invokespecial #77                 // Method java/util/LinkedHashMap."<init>":(Ljava/util/Map;)V
      56: putfield      #31                 // Field properties:Ljava/util/Map;
      59: aload_1
      60: aload_0
      61: getfield      #2                  // Field isSimple:Z
      64: putfield      #2                  // Field isSimple:Z
      67: aload_1
      68: aload_0
      69: getfield      #23                 // Field description:Ljava/lang/String;
      72: putfield      #23                 // Field description:Ljava/lang/String;
      75: aload_1
      76: aload_0
      77: getfield      #48                 // Field example:Ljava/lang/Object;
      80: putfield      #48                 // Field example:Ljava/lang/Object;
      83: aload_1
      84: aload_0
      85: getfield      #24                 // Field additionalProperties:Lio/swagger/models/properties/Property;
      88: putfield      #24                 // Field additionalProperties:Lio/swagger/models/properties/Property;
      91: aload_1
      92: aload_0
      93: getfield      #21                 // Field discriminator:Ljava/lang/String;
      96: putfield      #21                 // Field discriminator:Ljava/lang/String;
      99: aload_1
     100: aload_0
     101: getfield      #49                 // Field xml:Lio/swagger/models/Xml;
     104: putfield      #49                 // Field xml:Lio/swagger/models/Xml;
     107: aload_1
     108: aload_0
     109: getfield      #50                 // Field defaultValue:Ljava/lang/String;
     112: putfield      #50                 // Field defaultValue:Ljava/lang/String;
     115: aload_1
     116: aload_0
     117: getfield      #19                 // Field minimum:Ljava/math/BigDecimal;
     120: putfield      #19                 // Field minimum:Ljava/math/BigDecimal;
     123: aload_1
     124: aload_0
     125: getfield      #20                 // Field maximum:Ljava/math/BigDecimal;
     128: putfield      #20                 // Field maximum:Ljava/math/BigDecimal;
     131: aload_1
     132: areturn
}
