Compiled from "FXCanvas.java"
class javafx.embed.swt.FXCanvas$2 implements org.eclipse.swt.events.MouseListener {
  final javafx.embed.swt.FXCanvas this$0;

  javafx.embed.swt.FXCanvas$2(javafx.embed.swt.FXCanvas);
    Code:
       0: aload_0
       1: aload_1
       2: putfield      #1                  // Field this$0:Ljavafx/embed/swt/FXCanvas;
       5: aload_0
       6: invokespecial #2                  // Method java/lang/Object."<init>":()V
       9: return

  public void mouseDoubleClick(org.eclipse.swt.events.MouseEvent);
    Code:
       0: return

  public void mouseDown(org.eclipse.swt.events.MouseEvent);
    Code:
       0: aload_1
       1: getfield      #3                  // Field org/eclipse/swt/events/MouseEvent.button:I
       4: iconst_3
       5: if_icmple     9
       8: return
       9: aload_0
      10: getfield      #1                  // Field this$0:Ljavafx/embed/swt/FXCanvas;
      13: aload_1
      14: iconst_0
      15: invokestatic  #5                  // Method javafx/embed/swt/FXCanvas.access$200:(Ljavafx/embed/swt/FXCanvas;Lorg/eclipse/swt/events/MouseEvent;I)V
      18: return

  public void mouseUp(org.eclipse.swt.events.MouseEvent);
    Code:
       0: aload_1
       1: getfield      #3                  // Field org/eclipse/swt/events/MouseEvent.button:I
       4: iconst_3
       5: if_icmple     9
       8: return
       9: aload_0
      10: getfield      #1                  // Field this$0:Ljavafx/embed/swt/FXCanvas;
      13: aload_1
      14: iconst_1
      15: invokestatic  #5                  // Method javafx/embed/swt/FXCanvas.access$200:(Ljavafx/embed/swt/FXCanvas;Lorg/eclipse/swt/events/MouseEvent;I)V
      18: return
}
