Compiled from "FXCanvas.java"
public class javafx.embed.swt.FXCanvas extends org.eclipse.swt.widgets.Canvas {
  private static final javafx.util.FXPermission FXCANVAS_PERMISSION;

  private javafx.embed.swt.FXCanvas$HostContainer hostContainer;

  private volatile com.sun.javafx.stage.EmbeddedWindow stage;

  private volatile javafx.scene.Scene scene;

  private com.sun.javafx.embed.EmbeddedStageInterface stagePeer;

  private com.sun.javafx.embed.EmbeddedSceneInterface scenePeer;

  private int pWidth;

  private int pHeight;

  private volatile int pPreferredWidth;

  private volatile int pPreferredHeight;

  private java.nio.IntBuffer pixelsBuf;

  org.eclipse.swt.widgets.Listener moveFilter;

  private org.eclipse.swt.dnd.DropTarget dropTarget;

  static org.eclipse.swt.dnd.Transfer[] StandardTransfers;

  static org.eclipse.swt.dnd.Transfer[] CustomTransfers;

  private static java.lang.reflect.Field windowField;

  private static java.lang.reflect.Method windowMethod;

  private static java.lang.reflect.Method screenMethod;

  private static java.lang.reflect.Method backingScaleFactorMethod;

  private static java.lang.reflect.Method swtDPIUtilMethod;

  static java.util.ArrayList<org.eclipse.swt.dnd.DropTarget> targets;

  double lastScaleFactor;

  int lastWidth;

  int lastHeight;

  java.nio.IntBuffer lastPixelsBuf;

  double totalScrollX;

  double totalScrollY;

  private boolean gestureActive;

  private boolean panGestureInertiaActive;

  private org.eclipse.swt.events.GestureEvent lastGestureEvent;

  private java.util.Stack<java.lang.Integer> nestedGestures;

  private long inertiaTime;

  private double inertiaXScroll;

  private double inertiaYScroll;

  private double lastTotalZoom;

  private double lastTotalAngle;

  private double getScaleFactor();
    Code:
       0: invokestatic  #15                 // Method org/eclipse/swt/SWT.getPlatform:()Ljava/lang/String;
       3: ldc           #16                 // String cocoa
       5: invokevirtual #17                 // Method java/lang/String.equals:(Ljava/lang/Object;)Z
       8: ifeq          78
      11: getstatic     #18                 // Field windowField:Ljava/lang/reflect/Field;
      14: ifnull        29
      17: getstatic     #19                 // Field screenMethod:Ljava/lang/reflect/Method;
      20: ifnull        29
      23: getstatic     #20                 // Field backingScaleFactorMethod:Ljava/lang/reflect/Method;
      26: ifnonnull     31
      29: dconst_1
      30: dreturn
      31: getstatic     #18                 // Field windowField:Ljava/lang/reflect/Field;
      34: aload_0
      35: invokevirtual #21                 // Method getShell:()Lorg/eclipse/swt/widgets/Shell;
      38: invokevirtual #22                 // Method java/lang/reflect/Field.get:(Ljava/lang/Object;)Ljava/lang/Object;
      41: astore_1
      42: getstatic     #19                 // Field screenMethod:Ljava/lang/reflect/Method;
      45: aload_1
      46: iconst_0
      47: anewarray     #23                 // class java/lang/Object
      50: invokevirtual #24                 // Method java/lang/reflect/Method.invoke:(Ljava/lang/Object;[Ljava/lang/Object;)Ljava/lang/Object;
      53: astore_2
      54: getstatic     #20                 // Field backingScaleFactorMethod:Ljava/lang/reflect/Method;
      57: aload_2
      58: iconst_0
      59: anewarray     #23                 // class java/lang/Object
      62: invokevirtual #24                 // Method java/lang/reflect/Method.invoke:(Ljava/lang/Object;[Ljava/lang/Object;)Ljava/lang/Object;
      65: astore_3
      66: aload_3
      67: checkcast     #25                 // class java/lang/Double
      70: invokevirtual #26                 // Method java/lang/Double.doubleValue:()D
      73: dreturn
      74: astore_1
      75: goto          123
      78: invokestatic  #15                 // Method org/eclipse/swt/SWT.getPlatform:()Ljava/lang/String;
      81: ldc           #28                 // String win32
      83: invokevirtual #17                 // Method java/lang/String.equals:(Ljava/lang/Object;)Z
      86: ifeq          123
      89: getstatic     #29                 // Field swtDPIUtilMethod:Ljava/lang/reflect/Method;
      92: ifnonnull     97
      95: dconst_1
      96: dreturn
      97: getstatic     #29                 // Field swtDPIUtilMethod:Ljava/lang/reflect/Method;
     100: aconst_null
     101: iconst_0
     102: anewarray     #23                 // class java/lang/Object
     105: invokevirtual #24                 // Method java/lang/reflect/Method.invoke:(Ljava/lang/Object;[Ljava/lang/Object;)Ljava/lang/Object;
     108: checkcast     #30                 // class java/lang/Integer
     111: astore_1
     112: aload_1
     113: invokevirtual #31                 // Method java/lang/Integer.intValue:()I
     116: i2d
     117: ldc2_w        #32                 // double 100.0d
     120: ddiv
     121: dreturn
     122: astore_1
     123: dconst_1
     124: dreturn
    Exception table:
       from    to  target type
          31    73    74   Class java/lang/Exception
          97   121   122   Class java/lang/Exception

  static org.eclipse.swt.dnd.Transfer[] getAllTransfers();
    Code:
       0: getstatic     #34                 // Field StandardTransfers:[Lorg/eclipse/swt/dnd/Transfer;
       3: arraylength
       4: getstatic     #35                 // Field CustomTransfers:[Lorg/eclipse/swt/dnd/Transfer;
       7: arraylength
       8: iadd
       9: anewarray     #36                 // class org/eclipse/swt/dnd/Transfer
      12: astore_0
      13: getstatic     #34                 // Field StandardTransfers:[Lorg/eclipse/swt/dnd/Transfer;
      16: iconst_0
      17: aload_0
      18: iconst_0
      19: getstatic     #34                 // Field StandardTransfers:[Lorg/eclipse/swt/dnd/Transfer;
      22: arraylength
      23: invokestatic  #37                 // Method java/lang/System.arraycopy:(Ljava/lang/Object;ILjava/lang/Object;II)V
      26: getstatic     #35                 // Field CustomTransfers:[Lorg/eclipse/swt/dnd/Transfer;
      29: iconst_0
      30: aload_0
      31: getstatic     #34                 // Field StandardTransfers:[Lorg/eclipse/swt/dnd/Transfer;
      34: arraylength
      35: getstatic     #35                 // Field CustomTransfers:[Lorg/eclipse/swt/dnd/Transfer;
      38: arraylength
      39: invokestatic  #37                 // Method java/lang/System.arraycopy:(Ljava/lang/Object;ILjava/lang/Object;II)V
      42: aload_0
      43: areturn

  static org.eclipse.swt.dnd.Transfer getCustomTransfer(java.lang.String);
    Code:
       0: iconst_0
       1: istore_1
       2: iload_1
       3: getstatic     #35                 // Field CustomTransfers:[Lorg/eclipse/swt/dnd/Transfer;
       6: arraylength
       7: if_icmpge     40
      10: getstatic     #35                 // Field CustomTransfers:[Lorg/eclipse/swt/dnd/Transfer;
      13: iload_1
      14: aaload
      15: checkcast     #38                 // class javafx/embed/swt/CustomTransfer
      18: invokevirtual #39                 // Method javafx/embed/swt/CustomTransfer.getMime:()Ljava/lang/String;
      21: aload_0
      22: invokevirtual #17                 // Method java/lang/String.equals:(Ljava/lang/Object;)Z
      25: ifeq          34
      28: getstatic     #35                 // Field CustomTransfers:[Lorg/eclipse/swt/dnd/Transfer;
      31: iload_1
      32: aaload
      33: areturn
      34: iinc          1, 1
      37: goto          2
      40: new           #38                 // class javafx/embed/swt/CustomTransfer
      43: dup
      44: aload_0
      45: aload_0
      46: invokespecial #40                 // Method javafx/embed/swt/CustomTransfer."<init>":(Ljava/lang/String;Ljava/lang/String;)V
      49: astore_1
      50: getstatic     #35                 // Field CustomTransfers:[Lorg/eclipse/swt/dnd/Transfer;
      53: arraylength
      54: iconst_1
      55: iadd
      56: anewarray     #36                 // class org/eclipse/swt/dnd/Transfer
      59: astore_2
      60: getstatic     #35                 // Field CustomTransfers:[Lorg/eclipse/swt/dnd/Transfer;
      63: iconst_0
      64: aload_2
      65: iconst_0
      66: getstatic     #35                 // Field CustomTransfers:[Lorg/eclipse/swt/dnd/Transfer;
      69: arraylength
      70: invokestatic  #37                 // Method java/lang/System.arraycopy:(Ljava/lang/Object;ILjava/lang/Object;II)V
      73: aload_2
      74: getstatic     #35                 // Field CustomTransfers:[Lorg/eclipse/swt/dnd/Transfer;
      77: arraylength
      78: aload_1
      79: aastore
      80: aload_2
      81: putstatic     #35                 // Field CustomTransfers:[Lorg/eclipse/swt/dnd/Transfer;
      84: aload_1
      85: areturn

  public javafx.embed.swt.FXCanvas(org.eclipse.swt.widgets.Composite, int);
    Code:
       0: aload_0
       1: aload_1
       2: iload_2
       3: ldc           #42                 // int 262144
       5: ior
       6: invokespecial #43                 // Method org/eclipse/swt/widgets/Canvas."<init>":(Lorg/eclipse/swt/widgets/Composite;I)V
       9: aload_0
      10: iconst_0
      11: putfield      #7                  // Field pWidth:I
      14: aload_0
      15: iconst_0
      16: putfield      #6                  // Field pHeight:I
      19: aload_0
      20: iconst_m1
      21: putfield      #2                  // Field pPreferredWidth:I
      24: aload_0
      25: iconst_m1
      26: putfield      #1                  // Field pPreferredHeight:I
      29: aload_0
      30: aconst_null
      31: putfield      #44                 // Field pixelsBuf:Ljava/nio/IntBuffer;
      34: aload_0
      35: aload_0
      36: invokedynamic #45,  0             // InvokeDynamic #0:handleEvent:(Ljavafx/embed/swt/FXCanvas;)Lorg/eclipse/swt/widgets/Listener;
      41: putfield      #46                 // Field moveFilter:Lorg/eclipse/swt/widgets/Listener;
      44: aload_0
      45: dconst_1
      46: putfield      #47                 // Field lastScaleFactor:D
      49: aload_0
      50: aconst_null
      51: putfield      #48                 // Field lastPixelsBuf:Ljava/nio/IntBuffer;
      54: aload_0
      55: dconst_0
      56: putfield      #49                 // Field totalScrollX:D
      59: aload_0
      60: dconst_0
      61: putfield      #50                 // Field totalScrollY:D
      64: aload_0
      65: iconst_0
      66: putfield      #51                 // Field gestureActive:Z
      69: aload_0
      70: iconst_0
      71: putfield      #52                 // Field panGestureInertiaActive:Z
      74: aload_0
      75: new           #53                 // class java/util/Stack
      78: dup
      79: invokespecial #54                 // Method java/util/Stack."<init>":()V
      82: putfield      #55                 // Field nestedGestures:Ljava/util/Stack;
      85: aload_0
      86: lconst_0
      87: putfield      #56                 // Field inertiaTime:J
      90: aload_0
      91: dconst_0
      92: putfield      #57                 // Field inertiaXScroll:D
      95: aload_0
      96: dconst_0
      97: putfield      #58                 // Field inertiaYScroll:D
     100: aload_0
     101: dconst_0
     102: putfield      #59                 // Field lastTotalZoom:D
     105: aload_0
     106: dconst_0
     107: putfield      #60                 // Field lastTotalAngle:D
     110: aload_0
     111: invokestatic  #61                 // Method org/eclipse/swt/widgets/Display.getAppName:()Ljava/lang/String;
     114: invokespecial #62                 // Method setApplicationName:(Ljava/lang/String;)V
     117: aload_0
     118: new           #63                 // class javafx/embed/swt/FXCanvas$HostContainer
     121: dup
     122: aload_0
     123: aconst_null
     124: invokespecial #64                 // Method javafx/embed/swt/FXCanvas$HostContainer."<init>":(Ljavafx/embed/swt/FXCanvas;Ljavafx/embed/swt/FXCanvas$1;)V
     127: putfield      #65                 // Field hostContainer:Ljavafx/embed/swt/FXCanvas$HostContainer;
     130: aload_0
     131: invokespecial #66                 // Method registerEventListeners:()V
     134: aload_1
     135: invokevirtual #67                 // Method org/eclipse/swt/widgets/Composite.getDisplay:()Lorg/eclipse/swt/widgets/Display;
     138: astore_3
     139: aload_3
     140: bipush        10
     142: aload_0
     143: getfield      #46                 // Field moveFilter:Lorg/eclipse/swt/widgets/Listener;
     146: invokevirtual #68                 // Method org/eclipse/swt/widgets/Display.addFilter:(ILorg/eclipse/swt/widgets/Listener;)V
     149: return

  public static javafx.embed.swt.FXCanvas getFXCanvas(javafx.scene.Scene);
    Code:
       0: aload_0
       1: invokevirtual #69                 // Method javafx/scene/Scene.getWindow:()Ljavafx/stage/Window;
       4: astore_1
       5: aload_1
       6: ifnull        39
       9: aload_1
      10: instanceof    #70                 // class com/sun/javafx/stage/EmbeddedWindow
      13: ifeq          39
      16: aload_1
      17: checkcast     #70                 // class com/sun/javafx/stage/EmbeddedWindow
      20: invokevirtual #71                 // Method com/sun/javafx/stage/EmbeddedWindow.getHost:()Lcom/sun/javafx/embed/HostInterface;
      23: astore_2
      24: aload_2
      25: instanceof    #63                 // class javafx/embed/swt/FXCanvas$HostContainer
      28: ifeq          39
      31: aload_2
      32: checkcast     #63                 // class javafx/embed/swt/FXCanvas$HostContainer
      35: getfield      #72                 // Field javafx/embed/swt/FXCanvas$HostContainer.fxCanvas:Ljavafx/embed/swt/FXCanvas;
      38: areturn
      39: aconst_null
      40: areturn

  private static void initFx();
    Code:
       0: lconst_0
       1: lstore_0
       2: ldc           #73                 // class org/eclipse/swt/widgets/Display
       4: ldc           #74                 // String eventProc
       6: invokevirtual #75                 // Method java/lang/Class.getDeclaredField:(Ljava/lang/String;)Ljava/lang/reflect/Field;
       9: astore_2
      10: aload_2
      11: iconst_1
      12: invokevirtual #76                 // Method java/lang/reflect/Field.setAccessible:(Z)V
      15: aload_2
      16: invokevirtual #77                 // Method java/lang/reflect/Field.getType:()Ljava/lang/Class;
      19: getstatic     #78                 // Field java/lang/Integer.TYPE:Ljava/lang/Class;
      22: if_acmpne     37
      25: aload_2
      26: invokestatic  #79                 // Method org/eclipse/swt/widgets/Display.getDefault:()Lorg/eclipse/swt/widgets/Display;
      29: invokevirtual #80                 // Method java/lang/reflect/Field.getInt:(Ljava/lang/Object;)I
      32: i2l
      33: lstore_0
      34: goto          55
      37: aload_2
      38: invokevirtual #77                 // Method java/lang/reflect/Field.getType:()Ljava/lang/Class;
      41: getstatic     #81                 // Field java/lang/Long.TYPE:Ljava/lang/Class;
      44: if_acmpne     55
      47: aload_2
      48: invokestatic  #79                 // Method org/eclipse/swt/widgets/Display.getDefault:()Lorg/eclipse/swt/widgets/Display;
      51: invokevirtual #82                 // Method java/lang/reflect/Field.getLong:(Ljava/lang/Object;)J
      54: lstore_0
      55: goto          59
      58: astore_2
      59: lload_0
      60: invokestatic  #84                 // Method java/lang/String.valueOf:(J)Ljava/lang/String;
      63: astore_2
      64: aload_2
      65: invokedynamic #85,  0             // InvokeDynamic #1:run:(Ljava/lang/String;)Ljava/security/PrivilegedAction;
      70: invokestatic  #86                 // Method java/security/AccessController.doPrivileged:(Ljava/security/PrivilegedAction;)Ljava/lang/Object;
      73: pop
      74: new           #87                 // class java/util/concurrent/CountDownLatch
      77: dup
      78: iconst_1
      79: invokespecial #88                 // Method java/util/concurrent/CountDownLatch."<init>":(I)V
      82: astore_3
      83: aload_3
      84: invokedynamic #89,  0             // InvokeDynamic #2:run:(Ljava/util/concurrent/CountDownLatch;)Ljava/security/PrivilegedAction;
      89: aconst_null
      90: iconst_1
      91: anewarray     #90                 // class java/security/Permission
      94: dup
      95: iconst_0
      96: getstatic     #91                 // Field FXCANVAS_PERMISSION:Ljavafx/util/FXPermission;
      99: aastore
     100: invokestatic  #92                 // Method java/security/AccessController.doPrivileged:(Ljava/security/PrivilegedAction;Ljava/security/AccessControlContext;[Ljava/security/Permission;)Ljava/lang/Object;
     103: pop
     104: aload_3
     105: invokevirtual #93                 // Method java/util/concurrent/CountDownLatch.await:()V
     108: goto          123
     111: astore        4
     113: new           #95                 // class java/lang/RuntimeException
     116: dup
     117: aload         4
     119: invokespecial #96                 // Method java/lang/RuntimeException."<init>":(Ljava/lang/Throwable;)V
     122: athrow
     123: return
    Exception table:
       from    to  target type
           2    55    58   Class java/lang/Throwable
         104   108   111   Class java/lang/InterruptedException

  private void setApplicationName(java.lang.String);
    Code:
       0: aload_1
       1: invokedynamic #97,  0             // InvokeDynamic #3:run:(Ljava/lang/String;)Ljava/lang/Runnable;
       6: invokestatic  #98                 // Method javafx/application/Platform.runLater:(Ljava/lang/Runnable;)V
       9: return

  public void reskin(int);
    Code:
       0: aload_0
       1: iload_1
       2: invokespecial #99                 // Method org/eclipse/swt/widgets/Canvas.reskin:(I)V
       5: iload_1
       6: iconst_1
       7: if_icmpne     14
      10: aload_0
      11: invokespecial #12                 // Method sendMoveEventToFX:()V
      14: return

  org.eclipse.swt.dnd.DropTarget getDropTarget();
    Code:
       0: aload_0
       1: getfield      #100                // Field dropTarget:Lorg/eclipse/swt/dnd/DropTarget;
       4: areturn

  void setDropTarget(org.eclipse.swt.dnd.DropTarget);
    Code:
       0: aload_0
       1: getfield      #100                // Field dropTarget:Lorg/eclipse/swt/dnd/DropTarget;
       4: ifnull        25
       7: getstatic     #101                // Field targets:Ljava/util/ArrayList;
      10: aload_0
      11: getfield      #100                // Field dropTarget:Lorg/eclipse/swt/dnd/DropTarget;
      14: invokevirtual #102                // Method java/util/ArrayList.remove:(Ljava/lang/Object;)Z
      17: pop
      18: aload_0
      19: getfield      #100                // Field dropTarget:Lorg/eclipse/swt/dnd/DropTarget;
      22: invokevirtual #103                // Method org/eclipse/swt/dnd/DropTarget.dispose:()V
      25: aload_0
      26: aload_1
      27: putfield      #100                // Field dropTarget:Lorg/eclipse/swt/dnd/DropTarget;
      30: aload_0
      31: getfield      #100                // Field dropTarget:Lorg/eclipse/swt/dnd/DropTarget;
      34: ifnull        48
      37: getstatic     #101                // Field targets:Ljava/util/ArrayList;
      40: aload_0
      41: getfield      #100                // Field dropTarget:Lorg/eclipse/swt/dnd/DropTarget;
      44: invokevirtual #104                // Method java/util/ArrayList.add:(Ljava/lang/Object;)Z
      47: pop
      48: return

  static void updateDropTarget();
    Code:
       0: getstatic     #101                // Field targets:Ljava/util/ArrayList;
       3: invokevirtual #105                // Method java/util/ArrayList.iterator:()Ljava/util/Iterator;
       6: astore_0
       7: aload_0
       8: invokeinterface #106,  1          // InterfaceMethod java/util/Iterator.hasNext:()Z
      13: ifeq          36
      16: aload_0
      17: invokeinterface #107,  1          // InterfaceMethod java/util/Iterator.next:()Ljava/lang/Object;
      22: checkcast     #108                // class org/eclipse/swt/dnd/DropTarget
      25: astore_1
      26: aload_1
      27: invokestatic  #109                // Method getAllTransfers:()[Lorg/eclipse/swt/dnd/Transfer;
      30: invokevirtual #110                // Method org/eclipse/swt/dnd/DropTarget.setTransfer:([Lorg/eclipse/swt/dnd/Transfer;)V
      33: goto          7
      36: return

  public org.eclipse.swt.graphics.Point computeSize(int, int, boolean);
    Code:
       0: aload_0
       1: invokevirtual #111                // Method checkWidget:()V
       4: iload_1
       5: iconst_m1
       6: if_icmpne     46
       9: iload_2
      10: iconst_m1
      11: if_icmpne     46
      14: aload_0
      15: getfield      #2                  // Field pPreferredWidth:I
      18: iconst_m1
      19: if_icmpeq     46
      22: aload_0
      23: getfield      #1                  // Field pPreferredHeight:I
      26: iconst_m1
      27: if_icmpeq     46
      30: new           #112                // class org/eclipse/swt/graphics/Point
      33: dup
      34: aload_0
      35: getfield      #2                  // Field pPreferredWidth:I
      38: aload_0
      39: getfield      #1                  // Field pPreferredHeight:I
      42: invokespecial #113                // Method org/eclipse/swt/graphics/Point."<init>":(II)V
      45: areturn
      46: aload_0
      47: iload_1
      48: iload_2
      49: iload_3
      50: invokespecial #114                // Method org/eclipse/swt/widgets/Canvas.computeSize:(IIZ)Lorg/eclipse/swt/graphics/Point;
      53: areturn

  public javafx.scene.Scene getScene();
    Code:
       0: aload_0
       1: invokevirtual #111                // Method checkWidget:()V
       4: aload_0
       5: getfield      #115                // Field scene:Ljavafx/scene/Scene;
       8: areturn

  public void setScene(javafx.scene.Scene);
    Code:
       0: aload_0
       1: invokevirtual #111                // Method checkWidget:()V
       4: aload_0
       5: getfield      #116                // Field stage:Lcom/sun/javafx/stage/EmbeddedWindow;
       8: ifnonnull     37
      11: aload_1
      12: ifnull        37
      15: aload_0
      16: new           #70                 // class com/sun/javafx/stage/EmbeddedWindow
      19: dup
      20: aload_0
      21: getfield      #65                 // Field hostContainer:Ljavafx/embed/swt/FXCanvas$HostContainer;
      24: invokespecial #117                // Method com/sun/javafx/stage/EmbeddedWindow."<init>":(Lcom/sun/javafx/embed/HostInterface;)V
      27: putfield      #116                // Field stage:Lcom/sun/javafx/stage/EmbeddedWindow;
      30: aload_0
      31: getfield      #116                // Field stage:Lcom/sun/javafx/stage/EmbeddedWindow;
      34: invokevirtual #118                // Method com/sun/javafx/stage/EmbeddedWindow.show:()V
      37: aload_0
      38: aload_1
      39: putfield      #115                // Field scene:Ljavafx/scene/Scene;
      42: aload_0
      43: getfield      #116                // Field stage:Lcom/sun/javafx/stage/EmbeddedWindow;
      46: ifnull        57
      49: aload_0
      50: getfield      #116                // Field stage:Lcom/sun/javafx/stage/EmbeddedWindow;
      53: aload_1
      54: invokevirtual #119                // Method com/sun/javafx/stage/EmbeddedWindow.setScene:(Ljavafx/scene/Scene;)V
      57: aload_0
      58: getfield      #116                // Field stage:Lcom/sun/javafx/stage/EmbeddedWindow;
      61: ifnull        80
      64: aload_1
      65: ifnonnull     80
      68: aload_0
      69: getfield      #116                // Field stage:Lcom/sun/javafx/stage/EmbeddedWindow;
      72: invokevirtual #120                // Method com/sun/javafx/stage/EmbeddedWindow.hide:()V
      75: aload_0
      76: aconst_null
      77: putfield      #116                // Field stage:Lcom/sun/javafx/stage/EmbeddedWindow;
      80: return

  private void registerEventListeners();
    Code:
       0: aload_0
       1: new           #121                // class javafx/embed/swt/FXCanvas$1
       4: dup
       5: aload_0
       6: invokespecial #122                // Method javafx/embed/swt/FXCanvas$1."<init>":(Ljavafx/embed/swt/FXCanvas;)V
       9: invokevirtual #123                // Method addDisposeListener:(Lorg/eclipse/swt/events/DisposeListener;)V
      12: aload_0
      13: aload_0
      14: invokedynamic #124,  0            // InvokeDynamic #4:paintControl:(Ljavafx/embed/swt/FXCanvas;)Lorg/eclipse/swt/events/PaintListener;
      19: invokevirtual #125                // Method addPaintListener:(Lorg/eclipse/swt/events/PaintListener;)V
      22: aload_0
      23: new           #126                // class javafx/embed/swt/FXCanvas$2
      26: dup
      27: aload_0
      28: invokespecial #127                // Method javafx/embed/swt/FXCanvas$2."<init>":(Ljavafx/embed/swt/FXCanvas;)V
      31: invokevirtual #128                // Method addMouseListener:(Lorg/eclipse/swt/events/MouseListener;)V
      34: aload_0
      35: aload_0
      36: invokedynamic #129,  0            // InvokeDynamic #5:mouseMove:(Ljavafx/embed/swt/FXCanvas;)Lorg/eclipse/swt/events/MouseMoveListener;
      41: invokevirtual #130                // Method addMouseMoveListener:(Lorg/eclipse/swt/events/MouseMoveListener;)V
      44: aload_0
      45: bipush        37
      47: aload_0
      48: invokedynamic #131,  0            // InvokeDynamic #6:handleEvent:(Ljavafx/embed/swt/FXCanvas;)Lorg/eclipse/swt/widgets/Listener;
      53: invokevirtual #132                // Method addListener:(ILorg/eclipse/swt/widgets/Listener;)V
      56: aload_0
      57: bipush        38
      59: aload_0
      60: invokedynamic #133,  0            // InvokeDynamic #7:handleEvent:(Ljavafx/embed/swt/FXCanvas;)Lorg/eclipse/swt/widgets/Listener;
      65: invokevirtual #132                // Method addListener:(ILorg/eclipse/swt/widgets/Listener;)V
      68: aload_0
      69: new           #134                // class javafx/embed/swt/FXCanvas$3
      72: dup
      73: aload_0
      74: invokespecial #135                // Method javafx/embed/swt/FXCanvas$3."<init>":(Ljavafx/embed/swt/FXCanvas;)V
      77: invokevirtual #136                // Method addMouseTrackListener:(Lorg/eclipse/swt/events/MouseTrackListener;)V
      80: aload_0
      81: new           #137                // class javafx/embed/swt/FXCanvas$4
      84: dup
      85: aload_0
      86: invokespecial #138                // Method javafx/embed/swt/FXCanvas$4."<init>":(Ljavafx/embed/swt/FXCanvas;)V
      89: invokevirtual #139                // Method addControlListener:(Lorg/eclipse/swt/events/ControlListener;)V
      92: aload_0
      93: new           #140                // class javafx/embed/swt/FXCanvas$5
      96: dup
      97: aload_0
      98: invokespecial #141                // Method javafx/embed/swt/FXCanvas$5."<init>":(Ljavafx/embed/swt/FXCanvas;)V
     101: invokevirtual #142                // Method addFocusListener:(Lorg/eclipse/swt/events/FocusListener;)V
     104: aload_0
     105: new           #143                // class javafx/embed/swt/FXCanvas$6
     108: dup
     109: aload_0
     110: invokespecial #144                // Method javafx/embed/swt/FXCanvas$6."<init>":(Ljavafx/embed/swt/FXCanvas;)V
     113: invokevirtual #145                // Method addKeyListener:(Lorg/eclipse/swt/events/KeyListener;)V
     116: aload_0
     117: aload_0
     118: invokedynamic #146,  0            // InvokeDynamic #8:gesture:(Ljavafx/embed/swt/FXCanvas;)Lorg/eclipse/swt/events/GestureListener;
     123: invokevirtual #147                // Method addGestureListener:(Lorg/eclipse/swt/events/GestureListener;)V
     126: aload_0
     127: aload_0
     128: invokedynamic #148,  0            // InvokeDynamic #9:menuDetected:(Ljavafx/embed/swt/FXCanvas;)Lorg/eclipse/swt/events/MenuDetectListener;
     133: invokevirtual #149                // Method addMenuDetectListener:(Lorg/eclipse/swt/events/MenuDetectListener;)V
     136: return

  private void widgetDisposed(org.eclipse.swt.events.DisposeEvent);
    Code:
       0: aload_0
       1: aconst_null
       2: invokevirtual #150                // Method setDropTarget:(Lorg/eclipse/swt/dnd/DropTarget;)V
       5: aload_0
       6: getfield      #116                // Field stage:Lcom/sun/javafx/stage/EmbeddedWindow;
       9: ifnull        19
      12: aload_0
      13: getfield      #116                // Field stage:Lcom/sun/javafx/stage/EmbeddedWindow;
      16: invokevirtual #120                // Method com/sun/javafx/stage/EmbeddedWindow.hide:()V
      19: return

  private void paintControl(org.eclipse.swt.events.PaintEvent);
    Code:
       0: aload_0
       1: getfield      #5                  // Field scenePeer:Lcom/sun/javafx/embed/EmbeddedSceneInterface;
       4: ifnull        14
       7: aload_0
       8: getfield      #44                 // Field pixelsBuf:Ljava/nio/IntBuffer;
      11: ifnonnull     15
      14: return
      15: aload_0
      16: invokespecial #4                  // Method getScaleFactor:()D
      19: dstore_2
      20: aload_0
      21: getfield      #47                 // Field lastScaleFactor:D
      24: dload_2
      25: dcmpl
      26: ifeq          52
      29: aload_0
      30: dload_2
      31: invokespecial #3                  // Method resizePixelBuffer:(D)V
      34: aload_0
      35: dload_2
      36: putfield      #47                 // Field lastScaleFactor:D
      39: aload_0
      40: getfield      #5                  // Field scenePeer:Lcom/sun/javafx/embed/EmbeddedSceneInterface;
      43: dload_2
      44: d2f
      45: dload_2
      46: d2f
      47: invokeinterface #151,  3          // InterfaceMethod com/sun/javafx/embed/EmbeddedSceneInterface.setPixelScaleFactors:(FF)V
      52: aload_0
      53: getfield      #44                 // Field pixelsBuf:Ljava/nio/IntBuffer;
      56: astore        4
      58: aload_0
      59: getfield      #7                  // Field pWidth:I
      62: istore        5
      64: aload_0
      65: getfield      #6                  // Field pHeight:I
      68: istore        6
      70: aload_0
      71: getfield      #5                  // Field scenePeer:Lcom/sun/javafx/embed/EmbeddedSceneInterface;
      74: aload_0
      75: getfield      #44                 // Field pixelsBuf:Ljava/nio/IntBuffer;
      78: aload_0
      79: getfield      #7                  // Field pWidth:I
      82: aload_0
      83: getfield      #6                  // Field pHeight:I
      86: invokeinterface #152,  4          // InterfaceMethod com/sun/javafx/embed/EmbeddedSceneInterface.getPixels:(Ljava/nio/IntBuffer;II)Z
      91: ifeq          130
      94: aload_0
      95: aload_0
      96: getfield      #7                  // Field pWidth:I
      99: dup_x1
     100: putfield      #153                // Field lastWidth:I
     103: istore        5
     105: aload_0
     106: aload_0
     107: getfield      #6                  // Field pHeight:I
     110: dup_x1
     111: putfield      #154                // Field lastHeight:I
     114: istore        6
     116: aload_0
     117: aload_0
     118: getfield      #44                 // Field pixelsBuf:Ljava/nio/IntBuffer;
     121: dup_x1
     122: putfield      #48                 // Field lastPixelsBuf:Ljava/nio/IntBuffer;
     125: astore        4
     127: goto          156
     130: aload_0
     131: getfield      #48                 // Field lastPixelsBuf:Ljava/nio/IntBuffer;
     134: ifnonnull     138
     137: return
     138: aload_0
     139: getfield      #153                // Field lastWidth:I
     142: istore        5
     144: aload_0
     145: getfield      #154                // Field lastHeight:I
     148: istore        6
     150: aload_0
     151: getfield      #48                 // Field lastPixelsBuf:Ljava/nio/IntBuffer;
     154: astore        4
     156: iload         5
     158: i2d
     159: dload_2
     160: dmul
     161: invokestatic  #155                // Method java/lang/Math.round:(D)J
     164: l2i
     165: istore        5
     167: iload         6
     169: i2d
     170: dload_2
     171: dmul
     172: invokestatic  #155                // Method java/lang/Math.round:(D)J
     175: l2i
     176: istore        6
     178: aconst_null
     179: astore        7
     181: ldc           #28                 // String win32
     183: invokestatic  #15                 // Method org/eclipse/swt/SWT.getPlatform:()Ljava/lang/String;
     186: invokevirtual #17                 // Method java/lang/String.equals:(Ljava/lang/Object;)Z
     189: ifeq          360
     192: new           #156                // class org/eclipse/swt/graphics/PaletteData
     195: dup
     196: ldc           #157                // int 65280
     198: ldc           #158                // int 16711680
     200: ldc           #159                // int -16777216
     202: invokespecial #160                // Method org/eclipse/swt/graphics/PaletteData."<init>":(III)V
     205: astore        8
     207: iload         5
     209: iconst_4
     210: imul
     211: istore        9
     213: iload         9
     215: iload         6
     217: imul
     218: newarray       byte
     220: astore        10
     222: aload         4
     224: invokevirtual #161                // Method java/nio/IntBuffer.array:()[I
     227: astore        11
     229: iconst_0
     230: istore        12
     232: iconst_0
     233: istore        13
     235: iconst_0
     236: istore        14
     238: iload         14
     240: iload         6
     242: if_icmpge     337
     245: iconst_0
     246: istore        15
     248: iload         15
     250: iload         5
     252: if_icmpge     331
     255: aload         11
     257: iload         13
     259: iinc          13, 1
     262: iaload
     263: istore        16
     265: aload         10
     267: iload         12
     269: iinc          12, 1
     272: iload         16
     274: sipush        255
     277: iand
     278: i2b
     279: bastore
     280: aload         10
     282: iload         12
     284: iinc          12, 1
     287: iload         16
     289: bipush        8
     291: ishr
     292: sipush        255
     295: iand
     296: i2b
     297: bastore
     298: aload         10
     300: iload         12
     302: iinc          12, 1
     305: iload         16
     307: bipush        16
     309: ishr
     310: sipush        255
     313: iand
     314: i2b
     315: bastore
     316: aload         10
     318: iload         12
     320: iinc          12, 1
     323: iconst_0
     324: bastore
     325: iinc          15, 1
     328: goto          248
     331: iinc          14, 1
     334: goto          238
     337: new           #162                // class org/eclipse/swt/graphics/ImageData
     340: dup
     341: iload         5
     343: iload         6
     345: bipush        32
     347: aload         8
     349: iconst_4
     350: aload         10
     352: invokespecial #163                // Method org/eclipse/swt/graphics/ImageData."<init>":(IIILorg/eclipse/swt/graphics/PaletteData;I[B)V
     355: astore        7
     357: goto          434
     360: iload         5
     362: iload         6
     364: imul
     365: aload         4
     367: invokevirtual #161                // Method java/nio/IntBuffer.array:()[I
     370: arraylength
     371: if_icmple     383
     374: getstatic     #164                // Field java/lang/System.err:Ljava/io/PrintStream;
     377: ldc           #165                // String FXCanvas.paintControl: scale mismatch!
     379: invokevirtual #166                // Method java/io/PrintStream.println:(Ljava/lang/String;)V
     382: return
     383: new           #156                // class org/eclipse/swt/graphics/PaletteData
     386: dup
     387: ldc           #158                // int 16711680
     389: ldc           #157                // int 65280
     391: sipush        255
     394: invokespecial #160                // Method org/eclipse/swt/graphics/PaletteData."<init>":(III)V
     397: astore        8
     399: new           #162                // class org/eclipse/swt/graphics/ImageData
     402: dup
     403: iload         5
     405: iload         6
     407: bipush        32
     409: aload         8
     411: invokespecial #167                // Method org/eclipse/swt/graphics/ImageData."<init>":(IIILorg/eclipse/swt/graphics/PaletteData;)V
     414: astore        7
     416: aload         7
     418: iconst_0
     419: iconst_0
     420: iload         5
     422: iload         6
     424: imul
     425: aload         4
     427: invokevirtual #161                // Method java/nio/IntBuffer.array:()[I
     430: iconst_0
     431: invokevirtual #168                // Method org/eclipse/swt/graphics/ImageData.setPixels:(III[II)V
     434: new           #169                // class org/eclipse/swt/graphics/Image
     437: dup
     438: invokestatic  #79                 // Method org/eclipse/swt/widgets/Display.getDefault:()Lorg/eclipse/swt/widgets/Display;
     441: aload         7
     443: invokespecial #170                // Method org/eclipse/swt/graphics/Image."<init>":(Lorg/eclipse/swt/graphics/Device;Lorg/eclipse/swt/graphics/ImageData;)V
     446: astore        8
     448: aload_1
     449: getfield      #171                // Field org/eclipse/swt/events/PaintEvent.gc:Lorg/eclipse/swt/graphics/GC;
     452: aload         8
     454: iconst_0
     455: iconst_0
     456: iload         5
     458: iload         6
     460: iconst_0
     461: iconst_0
     462: aload_0
     463: getfield      #7                  // Field pWidth:I
     466: aload_0
     467: getfield      #6                  // Field pHeight:I
     470: invokevirtual #172                // Method org/eclipse/swt/graphics/GC.drawImage:(Lorg/eclipse/swt/graphics/Image;IIIIIIII)V
     473: aload         8
     475: invokevirtual #173                // Method org/eclipse/swt/graphics/Image.dispose:()V
     478: return

  private void sendMoveEventToFX();
    Code:
       0: aload_0
       1: getfield      #8                  // Field stagePeer:Lcom/sun/javafx/embed/EmbeddedStageInterface;
       4: ifnonnull     8
       7: return
       8: aload_0
       9: invokevirtual #174                // Method getClientArea:()Lorg/eclipse/swt/graphics/Rectangle;
      12: astore_1
      13: aload_0
      14: aload_1
      15: getfield      #175                // Field org/eclipse/swt/graphics/Rectangle.x:I
      18: aload_1
      19: getfield      #176                // Field org/eclipse/swt/graphics/Rectangle.y:I
      22: invokevirtual #177                // Method toDisplay:(II)Lorg/eclipse/swt/graphics/Point;
      25: astore_2
      26: aload_0
      27: getfield      #8                  // Field stagePeer:Lcom/sun/javafx/embed/EmbeddedStageInterface;
      30: aload_2
      31: getfield      #178                // Field org/eclipse/swt/graphics/Point.x:I
      34: aload_2
      35: getfield      #179                // Field org/eclipse/swt/graphics/Point.y:I
      38: invokeinterface #180,  3          // InterfaceMethod com/sun/javafx/embed/EmbeddedStageInterface.setLocation:(II)V
      43: return

  private void sendMouseEventToFX(org.eclipse.swt.events.MouseEvent, int);
    Code:
       0: aload_0
       1: getfield      #5                  // Field scenePeer:Lcom/sun/javafx/embed/EmbeddedSceneInterface;
       4: ifnonnull     8
       7: return
       8: aload_0
       9: aload_1
      10: getfield      #181                // Field org/eclipse/swt/events/MouseEvent.x:I
      13: aload_1
      14: getfield      #182                // Field org/eclipse/swt/events/MouseEvent.y:I
      17: invokevirtual #177                // Method toDisplay:(II)Lorg/eclipse/swt/graphics/Point;
      20: astore_3
      21: aload_1
      22: getfield      #183                // Field org/eclipse/swt/events/MouseEvent.stateMask:I
      25: ldc           #184                // int 524288
      27: iand
      28: ifeq          35
      31: iconst_1
      32: goto          36
      35: iconst_0
      36: istore        4
      38: aload_1
      39: getfield      #183                // Field org/eclipse/swt/events/MouseEvent.stateMask:I
      42: ldc           #185                // int 1048576
      44: iand
      45: ifeq          52
      48: iconst_1
      49: goto          53
      52: iconst_0
      53: istore        5
      55: aload_1
      56: getfield      #183                // Field org/eclipse/swt/events/MouseEvent.stateMask:I
      59: ldc           #186                // int 2097152
      61: iand
      62: ifeq          69
      65: iconst_1
      66: goto          70
      69: iconst_0
      70: istore        6
      72: aload_1
      73: getfield      #183                // Field org/eclipse/swt/events/MouseEvent.stateMask:I
      76: ldc           #187                // int 131072
      78: iand
      79: ifeq          86
      82: iconst_1
      83: goto          87
      86: iconst_0
      87: istore        7
      89: aload_1
      90: getfield      #183                // Field org/eclipse/swt/events/MouseEvent.stateMask:I
      93: ldc           #42                 // int 262144
      95: iand
      96: ifeq          103
      99: iconst_1
     100: goto          104
     103: iconst_0
     104: istore        8
     106: aload_1
     107: getfield      #183                // Field org/eclipse/swt/events/MouseEvent.stateMask:I
     110: ldc           #188                // int 65536
     112: iand
     113: ifeq          120
     116: iconst_1
     117: goto          121
     120: iconst_0
     121: istore        9
     123: aload_1
     124: getfield      #183                // Field org/eclipse/swt/events/MouseEvent.stateMask:I
     127: ldc           #189                // int 4194304
     129: iand
     130: ifeq          137
     133: iconst_1
     134: goto          138
     137: iconst_0
     138: istore        10
     140: aload_1
     141: getfield      #190                // Field org/eclipse/swt/events/MouseEvent.button:I
     144: istore        11
     146: iload_2
     147: tableswitch   { // 0 to 6
                     0: 188
                     1: 245
                     2: 302
                     3: 303
                     4: 303
                     5: 303
                     6: 303
               default: 356
          }
     188: iload         4
     190: aload_1
     191: getfield      #190                // Field org/eclipse/swt/events/MouseEvent.button:I
     194: iconst_1
     195: if_icmpne     202
     198: iconst_1
     199: goto          203
     202: iconst_0
     203: ior
     204: istore        4
     206: iload         5
     208: aload_1
     209: getfield      #190                // Field org/eclipse/swt/events/MouseEvent.button:I
     212: iconst_2
     213: if_icmpne     220
     216: iconst_1
     217: goto          221
     220: iconst_0
     221: ior
     222: istore        5
     224: iload         6
     226: aload_1
     227: getfield      #190                // Field org/eclipse/swt/events/MouseEvent.button:I
     230: iconst_3
     231: if_icmpne     238
     234: iconst_1
     235: goto          239
     238: iconst_0
     239: ior
     240: istore        6
     242: goto          356
     245: iload         4
     247: aload_1
     248: getfield      #190                // Field org/eclipse/swt/events/MouseEvent.button:I
     251: iconst_1
     252: if_icmpeq     259
     255: iconst_1
     256: goto          260
     259: iconst_0
     260: iand
     261: istore        4
     263: iload         5
     265: aload_1
     266: getfield      #190                // Field org/eclipse/swt/events/MouseEvent.button:I
     269: iconst_2
     270: if_icmpeq     277
     273: iconst_1
     274: goto          278
     277: iconst_0
     278: iand
     279: istore        5
     281: iload         6
     283: aload_1
     284: getfield      #190                // Field org/eclipse/swt/events/MouseEvent.button:I
     287: iconst_3
     288: if_icmpeq     295
     291: iconst_1
     292: goto          296
     295: iconst_0
     296: iand
     297: istore        6
     299: goto          356
     302: return
     303: iload         11
     305: ifne          356
     308: aload_1
     309: getfield      #183                // Field org/eclipse/swt/events/MouseEvent.stateMask:I
     312: ldc           #184                // int 524288
     314: iand
     315: ifeq          324
     318: iconst_1
     319: istore        11
     321: goto          356
     324: aload_1
     325: getfield      #183                // Field org/eclipse/swt/events/MouseEvent.stateMask:I
     328: ldc           #185                // int 1048576
     330: iand
     331: ifeq          340
     334: iconst_2
     335: istore        11
     337: goto          356
     340: aload_1
     341: getfield      #183                // Field org/eclipse/swt/events/MouseEvent.stateMask:I
     344: ldc           #186                // int 2097152
     346: iand
     347: ifeq          356
     350: iconst_3
     351: istore        11
     353: goto          356
     356: aload_0
     357: getfield      #5                  // Field scenePeer:Lcom/sun/javafx/embed/EmbeddedSceneInterface;
     360: iload_2
     361: iload         11
     363: aload_1
     364: getfield      #183                // Field org/eclipse/swt/events/MouseEvent.stateMask:I
     367: invokestatic  #191                // Method javafx/embed/swt/SWTEvents.mouseButtonToEmbedMouseButton:(II)I
     370: iload         4
     372: iload         5
     374: iload         6
     376: aload_1
     377: getfield      #181                // Field org/eclipse/swt/events/MouseEvent.x:I
     380: aload_1
     381: getfield      #182                // Field org/eclipse/swt/events/MouseEvent.y:I
     384: aload_3
     385: getfield      #178                // Field org/eclipse/swt/graphics/Point.x:I
     388: aload_3
     389: getfield      #179                // Field org/eclipse/swt/graphics/Point.y:I
     392: iload         7
     394: iload         8
     396: iload         9
     398: iload         10
     400: iconst_0
     401: invokeinterface #192,  15         // InterfaceMethod com/sun/javafx/embed/EmbeddedSceneInterface.mouseEvent:(IIZZZIIIIZZZZZ)V
     406: return

  private void sendScrollEventToFX(int, double, double, int, int, int, boolean);
    Code:
       0: aload_0
       1: getfield      #5                  // Field scenePeer:Lcom/sun/javafx/embed/EmbeddedSceneInterface;
       4: ifnonnull     8
       7: return
       8: ldc2_w        #193                // double 5.0d
      11: dstore        10
      13: iload_1
      14: bipush        8
      16: if_icmpeq     25
      19: iload_1
      20: bipush        7
      22: if_icmpne     44
      25: ldc2_w        #196                // double 40.0d
      28: dstore        10
      30: aload_0
      31: dload_2
      32: putfield      #49                 // Field totalScrollX:D
      35: aload_0
      36: dload         4
      38: putfield      #50                 // Field totalScrollY:D
      41: goto          129
      44: ldc           #16                 // String cocoa
      46: invokestatic  #15                 // Method org/eclipse/swt/SWT.getPlatform:()Ljava/lang/String;
      49: invokevirtual #17                 // Method java/lang/String.equals:(Ljava/lang/Object;)Z
      52: ifeq          72
      55: invokestatic  #198                // Method org/eclipse/swt/SWT.getVersion:()I
      58: sipush        4600
      61: if_icmpge     72
      64: dload         10
      66: ldc2_w        #199                // double -1.0d
      69: dmul
      70: dstore        10
      72: iload_1
      73: ifne          89
      76: aload_0
      77: dconst_0
      78: putfield      #49                 // Field totalScrollX:D
      81: aload_0
      82: dconst_0
      83: putfield      #50                 // Field totalScrollY:D
      86: goto          129
      89: iload         9
      91: ifeq          108
      94: aload_0
      95: dload_2
      96: putfield      #49                 // Field totalScrollX:D
      99: aload_0
     100: dload         4
     102: putfield      #50                 // Field totalScrollY:D
     105: goto          129
     108: aload_0
     109: dup
     110: getfield      #49                 // Field totalScrollX:D
     113: dload_2
     114: dadd
     115: putfield      #49                 // Field totalScrollX:D
     118: aload_0
     119: dup
     120: getfield      #50                 // Field totalScrollY:D
     123: dload         4
     125: dadd
     126: putfield      #50                 // Field totalScrollY:D
     129: aload_0
     130: iload         6
     132: iload         7
     134: invokevirtual #177                // Method toDisplay:(II)Lorg/eclipse/swt/graphics/Point;
     137: astore        12
     139: aload_0
     140: getfield      #5                  // Field scenePeer:Lcom/sun/javafx/embed/EmbeddedSceneInterface;
     143: iload_1
     144: dload_2
     145: dload         4
     147: aload_0
     148: getfield      #49                 // Field totalScrollX:D
     151: aload_0
     152: getfield      #50                 // Field totalScrollY:D
     155: dload         10
     157: dload         10
     159: iload         6
     161: i2d
     162: iload         7
     164: i2d
     165: aload         12
     167: getfield      #178                // Field org/eclipse/swt/graphics/Point.x:I
     170: i2d
     171: aload         12
     173: getfield      #179                // Field org/eclipse/swt/graphics/Point.y:I
     176: i2d
     177: iload         8
     179: ldc           #187                // int 131072
     181: iand
     182: ifeq          189
     185: iconst_1
     186: goto          190
     189: iconst_0
     190: iload         8
     192: ldc           #42                 // int 262144
     194: iand
     195: ifeq          202
     198: iconst_1
     199: goto          203
     202: iconst_0
     203: iload         8
     205: ldc           #188                // int 65536
     207: iand
     208: ifeq          215
     211: iconst_1
     212: goto          216
     215: iconst_0
     216: iload         8
     218: ldc           #189                // int 4194304
     220: iand
     221: ifeq          228
     224: iconst_1
     225: goto          229
     228: iconst_0
     229: iload         9
     231: invokeinterface #201,  27         // InterfaceMethod com/sun/javafx/embed/EmbeddedSceneInterface.scrollEvent:(IDDDDDDDDDDZZZZZ)V
     236: return

  private void sendKeyEventToFX(org.eclipse.swt.events.KeyEvent, int);
    Code:
       0: aload_0
       1: getfield      #5                  // Field scenePeer:Lcom/sun/javafx/embed/EmbeddedSceneInterface;
       4: ifnonnull     8
       7: return
       8: aload_1
       9: getfield      #202                // Field org/eclipse/swt/events/KeyEvent.stateMask:I
      12: istore_3
      13: iload_2
      14: iconst_1
      15: if_icmpne     77
      18: aload_1
      19: getfield      #203                // Field org/eclipse/swt/events/KeyEvent.keyCode:I
      22: ldc           #187                // int 131072
      24: if_icmpne     32
      27: iload_3
      28: ldc           #187                // int 131072
      30: ior
      31: istore_3
      32: aload_1
      33: getfield      #203                // Field org/eclipse/swt/events/KeyEvent.keyCode:I
      36: ldc           #42                 // int 262144
      38: if_icmpne     46
      41: iload_3
      42: ldc           #42                 // int 262144
      44: ior
      45: istore_3
      46: aload_1
      47: getfield      #203                // Field org/eclipse/swt/events/KeyEvent.keyCode:I
      50: ldc           #188                // int 65536
      52: if_icmpne     60
      55: iload_3
      56: ldc           #188                // int 65536
      58: ior
      59: istore_3
      60: aload_1
      61: getfield      #203                // Field org/eclipse/swt/events/KeyEvent.keyCode:I
      64: ldc           #189                // int 4194304
      66: if_icmpne     133
      69: iload_3
      70: ldc           #189                // int 4194304
      72: ior
      73: istore_3
      74: goto          133
      77: aload_1
      78: getfield      #203                // Field org/eclipse/swt/events/KeyEvent.keyCode:I
      81: ldc           #187                // int 131072
      83: if_icmpne     91
      86: iload_3
      87: ldc           #204                // int -131073
      89: iand
      90: istore_3
      91: aload_1
      92: getfield      #203                // Field org/eclipse/swt/events/KeyEvent.keyCode:I
      95: ldc           #42                 // int 262144
      97: if_icmpne     105
     100: iload_3
     101: ldc           #205                // int -262145
     103: iand
     104: istore_3
     105: aload_1
     106: getfield      #203                // Field org/eclipse/swt/events/KeyEvent.keyCode:I
     109: ldc           #188                // int 65536
     111: if_icmpne     119
     114: iload_3
     115: ldc           #206                // int -65537
     117: iand
     118: istore_3
     119: aload_1
     120: getfield      #203                // Field org/eclipse/swt/events/KeyEvent.keyCode:I
     123: ldc           #189                // int 4194304
     125: if_icmpne     133
     128: iload_3
     129: ldc           #207                // int -4194305
     131: iand
     132: istore_3
     133: aload_1
     134: getfield      #203                // Field org/eclipse/swt/events/KeyEvent.keyCode:I
     137: invokestatic  #208                // Method javafx/embed/swt/SWTEvents.keyCodeToEmbedKeyCode:(I)I
     140: istore        4
     142: aload_0
     143: getfield      #5                  // Field scenePeer:Lcom/sun/javafx/embed/EmbeddedSceneInterface;
     146: iload_2
     147: invokestatic  #209                // Method javafx/embed/swt/SWTEvents.keyIDToEmbedKeyType:(I)I
     150: iload         4
     152: iconst_0
     153: newarray       char
     155: iload_3
     156: invokestatic  #210                // Method javafx/embed/swt/SWTEvents.keyModifiersToEmbedKeyModifiers:(I)I
     159: invokeinterface #211,  5          // InterfaceMethod com/sun/javafx/embed/EmbeddedSceneInterface.keyEvent:(II[CI)V
     164: aload_1
     165: getfield      #212                // Field org/eclipse/swt/events/KeyEvent.character:C
     168: ifeq          208
     171: iload_2
     172: iconst_1
     173: if_icmpne     208
     176: iconst_1
     177: newarray       char
     179: dup
     180: iconst_0
     181: aload_1
     182: getfield      #212                // Field org/eclipse/swt/events/KeyEvent.character:C
     185: castore
     186: astore        5
     188: aload_0
     189: getfield      #5                  // Field scenePeer:Lcom/sun/javafx/embed/EmbeddedSceneInterface;
     192: iconst_2
     193: aload_1
     194: getfield      #203                // Field org/eclipse/swt/events/KeyEvent.keyCode:I
     197: aload         5
     199: iload_3
     200: invokestatic  #210                // Method javafx/embed/swt/SWTEvents.keyModifiersToEmbedKeyModifiers:(I)I
     203: invokeinterface #211,  5          // InterfaceMethod com/sun/javafx/embed/EmbeddedSceneInterface.keyEvent:(II[CI)V
     208: return

  private void sendGestureEventToFX(org.eclipse.swt.events.GestureEvent);
    Code:
       0: aload_0
       1: getfield      #5                  // Field scenePeer:Lcom/sun/javafx/embed/EmbeddedSceneInterface;
       4: ifnonnull     8
       7: return
       8: aload_1
       9: getfield      #213                // Field org/eclipse/swt/events/GestureEvent.detail:I
      12: lookupswitch  { // 6
                     2: 72
                     4: 406
                     8: 348
                    16: 398
                    32: 85
                    64: 135
               default: 559
          }
      72: aload_0
      73: iconst_1
      74: putfield      #51                 // Field gestureActive:Z
      77: aload_0
      78: iconst_0
      79: putfield      #52                 // Field panGestureInertiaActive:Z
      82: goto          559
      85: aload_0
      86: getfield      #51                 // Field gestureActive:Z
      89: ifeq          126
      92: aload_0
      93: getfield      #55                 // Field nestedGestures:Ljava/util/Stack;
      96: bipush        32
      98: invokestatic  #214                // Method java/lang/Integer.valueOf:(I)Ljava/lang/Integer;
     101: invokevirtual #215                // Method java/util/Stack.contains:(Ljava/lang/Object;)Z
     104: ifne          126
     107: aload_0
     108: iconst_0
     109: aload_1
     110: invokespecial #216                // Method sendZoomEventToFX:(ILorg/eclipse/swt/events/GestureEvent;)V
     113: aload_0
     114: getfield      #55                 // Field nestedGestures:Ljava/util/Stack;
     117: bipush        32
     119: invokestatic  #214                // Method java/lang/Integer.valueOf:(I)Ljava/lang/Integer;
     122: invokevirtual #217                // Method java/util/Stack.push:(Ljava/lang/Object;)Ljava/lang/Object;
     125: pop
     126: aload_0
     127: iconst_1
     128: aload_1
     129: invokespecial #216                // Method sendZoomEventToFX:(ILorg/eclipse/swt/events/GestureEvent;)V
     132: goto          559
     135: aload_0
     136: getfield      #51                 // Field gestureActive:Z
     139: ifeq          198
     142: aload_0
     143: getfield      #55                 // Field nestedGestures:Ljava/util/Stack;
     146: bipush        64
     148: invokestatic  #214                // Method java/lang/Integer.valueOf:(I)Ljava/lang/Integer;
     151: invokevirtual #215                // Method java/util/Stack.contains:(Ljava/lang/Object;)Z
     154: ifne          198
     157: aload_0
     158: iconst_0
     159: aload_1
     160: getfield      #218                // Field org/eclipse/swt/events/GestureEvent.xDirection:I
     163: i2d
     164: aload_1
     165: getfield      #219                // Field org/eclipse/swt/events/GestureEvent.yDirection:I
     168: i2d
     169: aload_1
     170: getfield      #220                // Field org/eclipse/swt/events/GestureEvent.x:I
     173: aload_1
     174: getfield      #221                // Field org/eclipse/swt/events/GestureEvent.y:I
     177: aload_1
     178: getfield      #222                // Field org/eclipse/swt/events/GestureEvent.stateMask:I
     181: iconst_0
     182: invokespecial #223                // Method sendScrollEventToFX:(IDDIIIZ)V
     185: aload_0
     186: getfield      #55                 // Field nestedGestures:Ljava/util/Stack;
     189: bipush        64
     191: invokestatic  #214                // Method java/lang/Integer.valueOf:(I)Ljava/lang/Integer;
     194: invokevirtual #217                // Method java/util/Stack.push:(Ljava/lang/Object;)Ljava/lang/Object;
     197: pop
     198: aload_0
     199: getfield      #52                 // Field panGestureInertiaActive:Z
     202: ifeq          228
     205: aload_1
     206: getfield      #224                // Field org/eclipse/swt/events/GestureEvent.time:I
     209: aload_0
     210: getfield      #225                // Field lastGestureEvent:Lorg/eclipse/swt/events/GestureEvent;
     213: getfield      #224                // Field org/eclipse/swt/events/GestureEvent.time:I
     216: sipush        250
     219: iadd
     220: if_icmple     228
     223: aload_0
     224: iconst_0
     225: putfield      #52                 // Field panGestureInertiaActive:Z
     228: aload_0
     229: getfield      #51                 // Field gestureActive:Z
     232: ifne          242
     235: aload_0
     236: getfield      #52                 // Field panGestureInertiaActive:Z
     239: ifeq          559
     242: aload_1
     243: getfield      #218                // Field org/eclipse/swt/events/GestureEvent.xDirection:I
     246: i2d
     247: dstore_2
     248: aload_1
     249: getfield      #219                // Field org/eclipse/swt/events/GestureEvent.yDirection:I
     252: i2d
     253: dstore        4
     255: aload_0
     256: getfield      #52                 // Field panGestureInertiaActive:Z
     259: ifeq          321
     262: dload_2
     263: dconst_0
     264: dcmpl
     265: ifne          321
     268: dload         4
     270: dconst_0
     271: dcmpl
     272: ifne          321
     275: dconst_0
     276: dconst_1
     277: aload_1
     278: getfield      #224                // Field org/eclipse/swt/events/GestureEvent.time:I
     281: i2l
     282: aload_0
     283: getfield      #56                 // Field inertiaTime:J
     286: lsub
     287: l2d
     288: ldc2_w        #226                // double 1500.0d
     291: ddiv
     292: invokestatic  #228                // Method java/lang/Math.min:(DD)D
     295: invokestatic  #229                // Method java/lang/Math.max:(DD)D
     298: dstore        6
     300: dconst_1
     301: dload         6
     303: dsub
     304: aload_0
     305: getfield      #57                 // Field inertiaXScroll:D
     308: dmul
     309: dstore_2
     310: dconst_1
     311: dload         6
     313: dsub
     314: aload_0
     315: getfield      #58                 // Field inertiaYScroll:D
     318: dmul
     319: dstore        4
     321: aload_0
     322: iconst_1
     323: dload_2
     324: dload         4
     326: aload_1
     327: getfield      #220                // Field org/eclipse/swt/events/GestureEvent.x:I
     330: aload_1
     331: getfield      #221                // Field org/eclipse/swt/events/GestureEvent.y:I
     334: aload_1
     335: getfield      #222                // Field org/eclipse/swt/events/GestureEvent.stateMask:I
     338: aload_0
     339: getfield      #52                 // Field panGestureInertiaActive:Z
     342: invokespecial #223                // Method sendScrollEventToFX:(IDDIIIZ)V
     345: goto          559
     348: aload_0
     349: getfield      #51                 // Field gestureActive:Z
     352: ifeq          389
     355: aload_0
     356: getfield      #55                 // Field nestedGestures:Ljava/util/Stack;
     359: bipush        8
     361: invokestatic  #214                // Method java/lang/Integer.valueOf:(I)Ljava/lang/Integer;
     364: invokevirtual #215                // Method java/util/Stack.contains:(Ljava/lang/Object;)Z
     367: ifne          389
     370: aload_0
     371: iconst_0
     372: aload_1
     373: invokespecial #230                // Method sendRotateEventToFX:(ILorg/eclipse/swt/events/GestureEvent;)V
     376: aload_0
     377: getfield      #55                 // Field nestedGestures:Ljava/util/Stack;
     380: bipush        8
     382: invokestatic  #214                // Method java/lang/Integer.valueOf:(I)Ljava/lang/Integer;
     385: invokevirtual #217                // Method java/util/Stack.push:(Ljava/lang/Object;)Ljava/lang/Object;
     388: pop
     389: aload_0
     390: iconst_1
     391: aload_1
     392: invokespecial #230                // Method sendRotateEventToFX:(ILorg/eclipse/swt/events/GestureEvent;)V
     395: goto          559
     398: aload_0
     399: aload_1
     400: invokespecial #231                // Method sendSwipeEventToFX:(Lorg/eclipse/swt/events/GestureEvent;)V
     403: goto          559
     406: aload_0
     407: getfield      #55                 // Field nestedGestures:Ljava/util/Stack;
     410: invokevirtual #232                // Method java/util/Stack.isEmpty:()Z
     413: ifne          551
     416: aload_0
     417: getfield      #55                 // Field nestedGestures:Ljava/util/Stack;
     420: invokevirtual #233                // Method java/util/Stack.pop:()Ljava/lang/Object;
     423: checkcast     #30                 // class java/lang/Integer
     426: invokevirtual #31                 // Method java/lang/Integer.intValue:()I
     429: lookupswitch  { // 3
                     8: 542
                    32: 464
                    64: 473
               default: 548
          }
     464: aload_0
     465: iconst_2
     466: aload_1
     467: invokespecial #216                // Method sendZoomEventToFX:(ILorg/eclipse/swt/events/GestureEvent;)V
     470: goto          548
     473: aload_0
     474: iconst_2
     475: aload_1
     476: getfield      #218                // Field org/eclipse/swt/events/GestureEvent.xDirection:I
     479: i2d
     480: aload_1
     481: getfield      #219                // Field org/eclipse/swt/events/GestureEvent.yDirection:I
     484: i2d
     485: aload_1
     486: getfield      #220                // Field org/eclipse/swt/events/GestureEvent.x:I
     489: aload_1
     490: getfield      #221                // Field org/eclipse/swt/events/GestureEvent.y:I
     493: aload_1
     494: getfield      #222                // Field org/eclipse/swt/events/GestureEvent.stateMask:I
     497: iconst_0
     498: invokespecial #223                // Method sendScrollEventToFX:(IDDIIIZ)V
     501: aload_0
     502: aload_0
     503: getfield      #225                // Field lastGestureEvent:Lorg/eclipse/swt/events/GestureEvent;
     506: getfield      #218                // Field org/eclipse/swt/events/GestureEvent.xDirection:I
     509: i2d
     510: putfield      #57                 // Field inertiaXScroll:D
     513: aload_0
     514: aload_0
     515: getfield      #225                // Field lastGestureEvent:Lorg/eclipse/swt/events/GestureEvent;
     518: getfield      #219                // Field org/eclipse/swt/events/GestureEvent.yDirection:I
     521: i2d
     522: putfield      #58                 // Field inertiaYScroll:D
     525: aload_0
     526: aload_1
     527: getfield      #224                // Field org/eclipse/swt/events/GestureEvent.time:I
     530: i2l
     531: putfield      #56                 // Field inertiaTime:J
     534: aload_0
     535: iconst_1
     536: putfield      #52                 // Field panGestureInertiaActive:Z
     539: goto          548
     542: aload_0
     543: iconst_2
     544: aload_1
     545: invokespecial #230                // Method sendRotateEventToFX:(ILorg/eclipse/swt/events/GestureEvent;)V
     548: goto          406
     551: aload_0
     552: iconst_0
     553: putfield      #51                 // Field gestureActive:Z
     556: goto          559
     559: aload_0
     560: aload_1
     561: putfield      #225                // Field lastGestureEvent:Lorg/eclipse/swt/events/GestureEvent;
     564: return

  private void sendZoomEventToFX(int, org.eclipse.swt.events.GestureEvent);
    Code:
       0: aload_0
       1: aload_2
       2: getfield      #220                // Field org/eclipse/swt/events/GestureEvent.x:I
       5: aload_2
       6: getfield      #221                // Field org/eclipse/swt/events/GestureEvent.y:I
       9: invokevirtual #177                // Method toDisplay:(II)Lorg/eclipse/swt/graphics/Point;
      12: astore_3
      13: aload_2
      14: getfield      #234                // Field org/eclipse/swt/events/GestureEvent.magnification:D
      17: dstore        4
      19: iload_1
      20: ifne          34
      23: aload_0
      24: dconst_1
      25: dup2_x1
      26: putfield      #59                 // Field lastTotalZoom:D
      29: dstore        4
      31: goto          45
      34: iload_1
      35: iconst_2
      36: if_icmpne     45
      39: aload_0
      40: getfield      #59                 // Field lastTotalZoom:D
      43: dstore        4
      45: iload_1
      46: iconst_2
      47: if_icmpne     54
      50: dconst_1
      51: goto          61
      54: dload         4
      56: aload_0
      57: getfield      #59                 // Field lastTotalZoom:D
      60: ddiv
      61: dstore        6
      63: aload_0
      64: dload         4
      66: putfield      #59                 // Field lastTotalZoom:D
      69: aload_0
      70: getfield      #5                  // Field scenePeer:Lcom/sun/javafx/embed/EmbeddedSceneInterface;
      73: iload_1
      74: dload         6
      76: dload         4
      78: aload_2
      79: getfield      #220                // Field org/eclipse/swt/events/GestureEvent.x:I
      82: i2d
      83: aload_2
      84: getfield      #221                // Field org/eclipse/swt/events/GestureEvent.y:I
      87: i2d
      88: aload_3
      89: getfield      #178                // Field org/eclipse/swt/graphics/Point.x:I
      92: i2d
      93: aload_3
      94: getfield      #179                // Field org/eclipse/swt/graphics/Point.y:I
      97: i2d
      98: aload_2
      99: getfield      #222                // Field org/eclipse/swt/events/GestureEvent.stateMask:I
     102: ldc           #187                // int 131072
     104: iand
     105: ifeq          112
     108: iconst_1
     109: goto          113
     112: iconst_0
     113: aload_2
     114: getfield      #222                // Field org/eclipse/swt/events/GestureEvent.stateMask:I
     117: ldc           #42                 // int 262144
     119: iand
     120: ifeq          127
     123: iconst_1
     124: goto          128
     127: iconst_0
     128: aload_2
     129: getfield      #222                // Field org/eclipse/swt/events/GestureEvent.stateMask:I
     132: ldc           #188                // int 65536
     134: iand
     135: ifeq          142
     138: iconst_1
     139: goto          143
     142: iconst_0
     143: aload_2
     144: getfield      #222                // Field org/eclipse/swt/events/GestureEvent.stateMask:I
     147: ldc           #189                // int 4194304
     149: iand
     150: ifeq          157
     153: iconst_1
     154: goto          158
     157: iconst_0
     158: aload_0
     159: getfield      #51                 // Field gestureActive:Z
     162: ifne          169
     165: iconst_1
     166: goto          170
     169: iconst_0
     170: invokeinterface #235,  19         // InterfaceMethod com/sun/javafx/embed/EmbeddedSceneInterface.zoomEvent:(IDDDDDDZZZZZ)V
     175: return

  private void sendRotateEventToFX(int, org.eclipse.swt.events.GestureEvent);
    Code:
       0: aload_0
       1: aload_2
       2: getfield      #220                // Field org/eclipse/swt/events/GestureEvent.x:I
       5: aload_2
       6: getfield      #221                // Field org/eclipse/swt/events/GestureEvent.y:I
       9: invokevirtual #177                // Method toDisplay:(II)Lorg/eclipse/swt/graphics/Point;
      12: astore_3
      13: aload_2
      14: getfield      #236                // Field org/eclipse/swt/events/GestureEvent.rotation:D
      17: dneg
      18: dstore        4
      20: iload_1
      21: ifne          35
      24: aload_0
      25: dconst_0
      26: dup2_x1
      27: putfield      #60                 // Field lastTotalAngle:D
      30: dstore        4
      32: goto          46
      35: iload_1
      36: iconst_2
      37: if_icmpne     46
      40: aload_0
      41: getfield      #60                 // Field lastTotalAngle:D
      44: dstore        4
      46: iload_1
      47: iconst_2
      48: if_icmpne     55
      51: dconst_0
      52: goto          62
      55: dload         4
      57: aload_0
      58: getfield      #60                 // Field lastTotalAngle:D
      61: dsub
      62: dstore        6
      64: aload_0
      65: dload         4
      67: putfield      #60                 // Field lastTotalAngle:D
      70: aload_0
      71: getfield      #5                  // Field scenePeer:Lcom/sun/javafx/embed/EmbeddedSceneInterface;
      74: iload_1
      75: dload         6
      77: dload         4
      79: aload_2
      80: getfield      #220                // Field org/eclipse/swt/events/GestureEvent.x:I
      83: i2d
      84: aload_2
      85: getfield      #221                // Field org/eclipse/swt/events/GestureEvent.y:I
      88: i2d
      89: aload_3
      90: getfield      #178                // Field org/eclipse/swt/graphics/Point.x:I
      93: i2d
      94: aload_3
      95: getfield      #179                // Field org/eclipse/swt/graphics/Point.y:I
      98: i2d
      99: aload_2
     100: getfield      #222                // Field org/eclipse/swt/events/GestureEvent.stateMask:I
     103: ldc           #187                // int 131072
     105: iand
     106: ifeq          113
     109: iconst_1
     110: goto          114
     113: iconst_0
     114: aload_2
     115: getfield      #222                // Field org/eclipse/swt/events/GestureEvent.stateMask:I
     118: ldc           #42                 // int 262144
     120: iand
     121: ifeq          128
     124: iconst_1
     125: goto          129
     128: iconst_0
     129: aload_2
     130: getfield      #222                // Field org/eclipse/swt/events/GestureEvent.stateMask:I
     133: ldc           #188                // int 65536
     135: iand
     136: ifeq          143
     139: iconst_1
     140: goto          144
     143: iconst_0
     144: aload_2
     145: getfield      #222                // Field org/eclipse/swt/events/GestureEvent.stateMask:I
     148: ldc           #189                // int 4194304
     150: iand
     151: ifeq          158
     154: iconst_1
     155: goto          159
     158: iconst_0
     159: aload_0
     160: getfield      #51                 // Field gestureActive:Z
     163: ifne          170
     166: iconst_1
     167: goto          171
     170: iconst_0
     171: invokeinterface #237,  19         // InterfaceMethod com/sun/javafx/embed/EmbeddedSceneInterface.rotateEvent:(IDDDDDDZZZZZ)V
     176: return

  private void sendSwipeEventToFX(org.eclipse.swt.events.GestureEvent);
    Code:
       0: aload_0
       1: aload_1
       2: getfield      #220                // Field org/eclipse/swt/events/GestureEvent.x:I
       5: aload_1
       6: getfield      #221                // Field org/eclipse/swt/events/GestureEvent.y:I
       9: invokevirtual #177                // Method toDisplay:(II)Lorg/eclipse/swt/graphics/Point;
      12: astore_2
      13: iconst_m1
      14: istore_3
      15: aload_1
      16: getfield      #219                // Field org/eclipse/swt/events/GestureEvent.yDirection:I
      19: ifle          27
      22: iconst_0
      23: istore_3
      24: goto          60
      27: aload_1
      28: getfield      #219                // Field org/eclipse/swt/events/GestureEvent.yDirection:I
      31: ifge          39
      34: iconst_1
      35: istore_3
      36: goto          60
      39: aload_1
      40: getfield      #218                // Field org/eclipse/swt/events/GestureEvent.xDirection:I
      43: ifle          51
      46: iconst_3
      47: istore_3
      48: goto          60
      51: aload_1
      52: getfield      #218                // Field org/eclipse/swt/events/GestureEvent.xDirection:I
      55: ifge          60
      58: iconst_2
      59: istore_3
      60: aload_0
      61: getfield      #5                  // Field scenePeer:Lcom/sun/javafx/embed/EmbeddedSceneInterface;
      64: iload_3
      65: aload_1
      66: getfield      #220                // Field org/eclipse/swt/events/GestureEvent.x:I
      69: i2d
      70: aload_1
      71: getfield      #221                // Field org/eclipse/swt/events/GestureEvent.y:I
      74: i2d
      75: aload_2
      76: getfield      #178                // Field org/eclipse/swt/graphics/Point.x:I
      79: i2d
      80: aload_2
      81: getfield      #179                // Field org/eclipse/swt/graphics/Point.y:I
      84: i2d
      85: aload_1
      86: getfield      #222                // Field org/eclipse/swt/events/GestureEvent.stateMask:I
      89: ldc           #187                // int 131072
      91: iand
      92: ifeq          99
      95: iconst_1
      96: goto          100
      99: iconst_0
     100: aload_1
     101: getfield      #222                // Field org/eclipse/swt/events/GestureEvent.stateMask:I
     104: ldc           #42                 // int 262144
     106: iand
     107: ifeq          114
     110: iconst_1
     111: goto          115
     114: iconst_0
     115: aload_1
     116: getfield      #222                // Field org/eclipse/swt/events/GestureEvent.stateMask:I
     119: ldc           #188                // int 65536
     121: iand
     122: ifeq          129
     125: iconst_1
     126: goto          130
     129: iconst_0
     130: aload_1
     131: getfield      #222                // Field org/eclipse/swt/events/GestureEvent.stateMask:I
     134: ldc           #189                // int 4194304
     136: iand
     137: ifeq          144
     140: iconst_1
     141: goto          145
     144: iconst_0
     145: invokeinterface #238,  14         // InterfaceMethod com/sun/javafx/embed/EmbeddedSceneInterface.swipeEvent:(IDDDDZZZZ)V
     150: return

  private void sendMenuEventToFX(org.eclipse.swt.events.MenuDetectEvent);
    Code:
       0: aload_0
       1: getfield      #5                  // Field scenePeer:Lcom/sun/javafx/embed/EmbeddedSceneInterface;
       4: ifnonnull     8
       7: return
       8: aload_0
       9: aload_1
      10: getfield      #239                // Field org/eclipse/swt/events/MenuDetectEvent.x:I
      13: aload_1
      14: getfield      #240                // Field org/eclipse/swt/events/MenuDetectEvent.y:I
      17: invokevirtual #241                // Method toControl:(II)Lorg/eclipse/swt/graphics/Point;
      20: astore_2
      21: aload_0
      22: getfield      #5                  // Field scenePeer:Lcom/sun/javafx/embed/EmbeddedSceneInterface;
      25: aload_2
      26: getfield      #178                // Field org/eclipse/swt/graphics/Point.x:I
      29: aload_2
      30: getfield      #179                // Field org/eclipse/swt/graphics/Point.y:I
      33: aload_1
      34: getfield      #239                // Field org/eclipse/swt/events/MenuDetectEvent.x:I
      37: aload_1
      38: getfield      #240                // Field org/eclipse/swt/events/MenuDetectEvent.y:I
      41: iconst_0
      42: invokeinterface #242,  6          // InterfaceMethod com/sun/javafx/embed/EmbeddedSceneInterface.menuEvent:(IIIIZ)V
      47: return

  private void sendResizeEventToFX();
    Code:
       0: aload_0
       1: invokevirtual #243                // Method redraw:()V
       4: aload_0
       5: invokevirtual #244                // Method update:()V
       8: aload_0
       9: aload_0
      10: invokevirtual #174                // Method getClientArea:()Lorg/eclipse/swt/graphics/Rectangle;
      13: getfield      #245                // Field org/eclipse/swt/graphics/Rectangle.width:I
      16: putfield      #7                  // Field pWidth:I
      19: aload_0
      20: aload_0
      21: invokevirtual #174                // Method getClientArea:()Lorg/eclipse/swt/graphics/Rectangle;
      24: getfield      #246                // Field org/eclipse/swt/graphics/Rectangle.height:I
      27: putfield      #6                  // Field pHeight:I
      30: aload_0
      31: aload_0
      32: getfield      #47                 // Field lastScaleFactor:D
      35: invokespecial #3                  // Method resizePixelBuffer:(D)V
      38: aload_0
      39: getfield      #5                  // Field scenePeer:Lcom/sun/javafx/embed/EmbeddedSceneInterface;
      42: ifnonnull     46
      45: return
      46: aload_0
      47: getfield      #8                  // Field stagePeer:Lcom/sun/javafx/embed/EmbeddedStageInterface;
      50: aload_0
      51: getfield      #7                  // Field pWidth:I
      54: aload_0
      55: getfield      #6                  // Field pHeight:I
      58: invokeinterface #247,  3          // InterfaceMethod com/sun/javafx/embed/EmbeddedStageInterface.setSize:(II)V
      63: aload_0
      64: getfield      #5                  // Field scenePeer:Lcom/sun/javafx/embed/EmbeddedSceneInterface;
      67: aload_0
      68: getfield      #7                  // Field pWidth:I
      71: aload_0
      72: getfield      #6                  // Field pHeight:I
      75: invokeinterface #248,  3          // InterfaceMethod com/sun/javafx/embed/EmbeddedSceneInterface.setSize:(II)V
      80: return

  private void resizePixelBuffer(double);
    Code:
       0: aload_0
       1: aconst_null
       2: putfield      #48                 // Field lastPixelsBuf:Ljava/nio/IntBuffer;
       5: aload_0
       6: getfield      #7                  // Field pWidth:I
       9: ifle          19
      12: aload_0
      13: getfield      #6                  // Field pHeight:I
      16: ifgt          27
      19: aload_0
      20: aconst_null
      21: putfield      #44                 // Field pixelsBuf:Ljava/nio/IntBuffer;
      24: goto          95
      27: aload_0
      28: aload_0
      29: getfield      #7                  // Field pWidth:I
      32: i2d
      33: dload_1
      34: dmul
      35: invokestatic  #155                // Method java/lang/Math.round:(D)J
      38: l2i
      39: aload_0
      40: getfield      #6                  // Field pHeight:I
      43: i2d
      44: dload_1
      45: dmul
      46: invokestatic  #155                // Method java/lang/Math.round:(D)J
      49: l2i
      50: imul
      51: invokestatic  #249                // Method java/nio/IntBuffer.allocate:(I)Ljava/nio/IntBuffer;
      54: putfield      #44                 // Field pixelsBuf:Ljava/nio/IntBuffer;
      57: aload_0
      58: invokevirtual #250                // Method getBackground:()Lorg/eclipse/swt/graphics/Color;
      61: invokevirtual #251                // Method org/eclipse/swt/graphics/Color.getRGB:()Lorg/eclipse/swt/graphics/RGB;
      64: astore_3
      65: aload_0
      66: getfield      #44                 // Field pixelsBuf:Ljava/nio/IntBuffer;
      69: invokevirtual #161                // Method java/nio/IntBuffer.array:()[I
      72: aload_3
      73: getfield      #252                // Field org/eclipse/swt/graphics/RGB.red:I
      76: bipush        16
      78: ishl
      79: aload_3
      80: getfield      #253                // Field org/eclipse/swt/graphics/RGB.green:I
      83: bipush        8
      85: ishl
      86: ior
      87: aload_3
      88: getfield      #254                // Field org/eclipse/swt/graphics/RGB.blue:I
      91: ior
      92: invokestatic  #255                // Method java/util/Arrays.fill:([II)V
      95: return

  private void sendFocusEventToFX(org.eclipse.swt.events.FocusEvent, boolean);
    Code:
       0: aload_0
       1: getfield      #116                // Field stage:Lcom/sun/javafx/stage/EmbeddedWindow;
       4: ifnull        14
       7: aload_0
       8: getfield      #8                  // Field stagePeer:Lcom/sun/javafx/embed/EmbeddedStageInterface;
      11: ifnonnull     15
      14: return
      15: iload_2
      16: ifeq          23
      19: iconst_0
      20: goto          24
      23: iconst_3
      24: istore_3
      25: aload_0
      26: getfield      #8                  // Field stagePeer:Lcom/sun/javafx/embed/EmbeddedStageInterface;
      29: iload_2
      30: iload_3
      31: invokeinterface #256,  3          // InterfaceMethod com/sun/javafx/embed/EmbeddedStageInterface.setFocused:(ZI)V
      36: return

  private void lambda$registerEventListeners$12(org.eclipse.swt.events.MenuDetectEvent);
    Code:
       0: aload_0
       1: aload_1
       2: invokedynamic #257,  0            // InvokeDynamic #10:run:(Ljavafx/embed/swt/FXCanvas;Lorg/eclipse/swt/events/MenuDetectEvent;)Ljava/lang/Runnable;
       7: astore_2
       8: ldc           #16                 // String cocoa
      10: invokestatic  #15                 // Method org/eclipse/swt/SWT.getPlatform:()Ljava/lang/String;
      13: invokevirtual #17                 // Method java/lang/String.equals:(Ljava/lang/Object;)Z
      16: ifeq          30
      19: aload_0
      20: invokevirtual #258                // Method getDisplay:()Lorg/eclipse/swt/widgets/Display;
      23: aload_2
      24: invokevirtual #259                // Method org/eclipse/swt/widgets/Display.asyncExec:(Ljava/lang/Runnable;)V
      27: goto          36
      30: aload_2
      31: invokeinterface #260,  1          // InterfaceMethod java/lang/Runnable.run:()V
      36: return

  private void lambda$registerEventListeners$11(org.eclipse.swt.events.MenuDetectEvent);
    Code:
       0: aload_0
       1: invokevirtual #261                // Method isDisposed:()Z
       4: ifeq          8
       7: return
       8: aload_0
       9: aload_1
      10: invokespecial #262                // Method sendMenuEventToFX:(Lorg/eclipse/swt/events/MenuDetectEvent;)V
      13: return

  private void lambda$registerEventListeners$10(org.eclipse.swt.events.GestureEvent);
    Code:
       0: aload_0
       1: aload_1
       2: invokespecial #263                // Method sendGestureEventToFX:(Lorg/eclipse/swt/events/GestureEvent;)V
       5: return

  private void lambda$registerEventListeners$9(org.eclipse.swt.widgets.Event);
    Code:
       0: aload_0
       1: getfield      #51                 // Field gestureActive:Z
       4: ifne          59
       7: aload_0
       8: getfield      #52                 // Field panGestureInertiaActive:Z
      11: ifeq          35
      14: aload_0
      15: getfield      #225                // Field lastGestureEvent:Lorg/eclipse/swt/events/GestureEvent;
      18: ifnull        35
      21: aload_1
      22: getfield      #264                // Field org/eclipse/swt/widgets/Event.time:I
      25: aload_0
      26: getfield      #225                // Field lastGestureEvent:Lorg/eclipse/swt/events/GestureEvent;
      29: getfield      #224                // Field org/eclipse/swt/events/GestureEvent.time:I
      32: if_icmpeq     59
      35: aload_0
      36: bipush        8
      38: aload_1
      39: invokestatic  #265                // Method javafx/embed/swt/SWTEvents.getWheelRotation:(Lorg/eclipse/swt/widgets/Event;)D
      42: dconst_0
      43: aload_1
      44: getfield      #266                // Field org/eclipse/swt/widgets/Event.x:I
      47: aload_1
      48: getfield      #267                // Field org/eclipse/swt/widgets/Event.y:I
      51: aload_1
      52: getfield      #268                // Field org/eclipse/swt/widgets/Event.stateMask:I
      55: iconst_0
      56: invokespecial #223                // Method sendScrollEventToFX:(IDDIIIZ)V
      59: return

  private void lambda$registerEventListeners$8(org.eclipse.swt.widgets.Event);
    Code:
       0: aload_0
       1: getfield      #51                 // Field gestureActive:Z
       4: ifne          59
       7: aload_0
       8: getfield      #52                 // Field panGestureInertiaActive:Z
      11: ifeq          35
      14: aload_0
      15: getfield      #225                // Field lastGestureEvent:Lorg/eclipse/swt/events/GestureEvent;
      18: ifnull        35
      21: aload_1
      22: getfield      #264                // Field org/eclipse/swt/widgets/Event.time:I
      25: aload_0
      26: getfield      #225                // Field lastGestureEvent:Lorg/eclipse/swt/events/GestureEvent;
      29: getfield      #224                // Field org/eclipse/swt/events/GestureEvent.time:I
      32: if_icmpeq     59
      35: aload_0
      36: bipush        7
      38: dconst_0
      39: aload_1
      40: invokestatic  #265                // Method javafx/embed/swt/SWTEvents.getWheelRotation:(Lorg/eclipse/swt/widgets/Event;)D
      43: aload_1
      44: getfield      #266                // Field org/eclipse/swt/widgets/Event.x:I
      47: aload_1
      48: getfield      #267                // Field org/eclipse/swt/widgets/Event.y:I
      51: aload_1
      52: getfield      #268                // Field org/eclipse/swt/widgets/Event.stateMask:I
      55: iconst_0
      56: invokespecial #223                // Method sendScrollEventToFX:(IDDIIIZ)V
      59: return

  private void lambda$registerEventListeners$7(org.eclipse.swt.events.MouseEvent);
    Code:
       0: aload_1
       1: getfield      #183                // Field org/eclipse/swt/events/MouseEvent.stateMask:I
       4: getstatic     #269                // Field org/eclipse/swt/SWT.BUTTON_MASK:I
       7: iand
       8: ifeq          41
      11: aload_1
      12: getfield      #183                // Field org/eclipse/swt/events/MouseEvent.stateMask:I
      15: ldc_w         #270                // int 3670016
      18: iand
      19: ifeq          32
      22: aload_0
      23: aload_1
      24: bipush        6
      26: invokespecial #13                 // Method sendMouseEventToFX:(Lorg/eclipse/swt/events/MouseEvent;I)V
      29: goto          47
      32: aload_0
      33: aload_1
      34: iconst_5
      35: invokespecial #13                 // Method sendMouseEventToFX:(Lorg/eclipse/swt/events/MouseEvent;I)V
      38: goto          47
      41: aload_0
      42: aload_1
      43: iconst_5
      44: invokespecial #13                 // Method sendMouseEventToFX:(Lorg/eclipse/swt/events/MouseEvent;I)V
      47: return

  private void lambda$registerEventListeners$6(org.eclipse.swt.events.PaintEvent);
    Code:
       0: aload_0
       1: aload_1
       2: invokespecial #271                // Method paintControl:(Lorg/eclipse/swt/events/PaintEvent;)V
       5: return

  private static void lambda$setApplicationName$5(java.lang.String);
    Code:
       0: invokestatic  #272                // Method com/sun/glass/ui/Application.GetApplication:()Lcom/sun/glass/ui/Application;
       3: aload_0
       4: invokevirtual #273                // Method com/sun/glass/ui/Application.setName:(Ljava/lang/String;)V
       7: return

  private static java.lang.Void lambda$initFx$4(java.util.concurrent.CountDownLatch);
    Code:
       0: aload_0
       1: invokedynamic #274,  0            // InvokeDynamic #11:run:(Ljava/util/concurrent/CountDownLatch;)Ljava/lang/Runnable;
       6: invokestatic  #275                // Method javafx/application/Platform.startup:(Ljava/lang/Runnable;)V
       9: aconst_null
      10: areturn

  private static void lambda$initFx$3(java.util.concurrent.CountDownLatch);
    Code:
       0: aload_0
       1: invokevirtual #276                // Method java/util/concurrent/CountDownLatch.countDown:()V
       4: return

  private static java.lang.Void lambda$initFx$2(java.lang.String);
    Code:
       0: ldc_w         #277                // String com.sun.javafx.application.type
       3: ldc_w         #278                // String FXCanvas
       6: invokestatic  #279                // Method java/lang/System.setProperty:(Ljava/lang/String;Ljava/lang/String;)Ljava/lang/String;
       9: pop
      10: ldc_w         #280                // String javafx.embed.isEventThread
      13: ldc_w         #281                // String true
      16: invokestatic  #279                // Method java/lang/System.setProperty:(Ljava/lang/String;Ljava/lang/String;)Ljava/lang/String;
      19: pop
      20: getstatic     #29                 // Field swtDPIUtilMethod:Ljava/lang/reflect/Method;
      23: ifnonnull     49
      26: ldc_w         #282                // String glass.win.uiScale
      29: ldc_w         #283                // String 100%
      32: invokestatic  #279                // Method java/lang/System.setProperty:(Ljava/lang/String;Ljava/lang/String;)Ljava/lang/String;
      35: pop
      36: ldc_w         #284                // String glass.win.renderScale
      39: ldc_w         #283                // String 100%
      42: invokestatic  #279                // Method java/lang/System.setProperty:(Ljava/lang/String;Ljava/lang/String;)Ljava/lang/String;
      45: pop
      46: goto          100
      49: bipush        100
      51: invokestatic  #214                // Method java/lang/Integer.valueOf:(I)Ljava/lang/Integer;
      54: astore_1
      55: getstatic     #29                 // Field swtDPIUtilMethod:Ljava/lang/reflect/Method;
      58: aconst_null
      59: iconst_0
      60: anewarray     #23                 // class java/lang/Object
      63: invokevirtual #24                 // Method java/lang/reflect/Method.invoke:(Ljava/lang/Object;[Ljava/lang/Object;)Ljava/lang/Object;
      66: checkcast     #30                 // class java/lang/Integer
      69: astore_1
      70: goto          74
      73: astore_2
      74: ldc_w         #282                // String glass.win.uiScale
      77: aload_1
      78: invokedynamic #285,  0            // InvokeDynamic #12:makeConcatWithConstants:(Ljava/lang/Integer;)Ljava/lang/String;
      83: invokestatic  #279                // Method java/lang/System.setProperty:(Ljava/lang/String;Ljava/lang/String;)Ljava/lang/String;
      86: pop
      87: ldc_w         #284                // String glass.win.renderScale
      90: aload_1
      91: invokedynamic #285,  0            // InvokeDynamic #12:makeConcatWithConstants:(Ljava/lang/Integer;)Ljava/lang/String;
      96: invokestatic  #279                // Method java/lang/System.setProperty:(Ljava/lang/String;Ljava/lang/String;)Ljava/lang/String;
      99: pop
     100: ldc_w         #286                // String javafx.embed.eventProc
     103: aload_0
     104: invokestatic  #279                // Method java/lang/System.setProperty:(Ljava/lang/String;Ljava/lang/String;)Ljava/lang/String;
     107: pop
     108: aconst_null
     109: areturn
    Exception table:
       from    to  target type
          55    70    73   Class java/lang/Exception

  private static java.lang.String lambda$static$1();
    Code:
       0: ldc_w         #287                // String swt.autoScale
       3: invokestatic  #288                // Method java/lang/System.getProperty:(Ljava/lang/String;)Ljava/lang/String;
       6: areturn

  private void lambda$new$0(org.eclipse.swt.widgets.Event);
    Code:
       0: aload_0
       1: astore_2
       2: aload_2
       3: ifnull        29
       6: aload_2
       7: aload_1
       8: getfield      #289                // Field org/eclipse/swt/widgets/Event.widget:Lorg/eclipse/swt/widgets/Widget;
      11: if_acmpne     21
      14: aload_0
      15: invokespecial #12                 // Method sendMoveEventToFX:()V
      18: goto          29
      21: aload_2
      22: invokevirtual #290                // Method org/eclipse/swt/widgets/Control.getParent:()Lorg/eclipse/swt/widgets/Composite;
      25: astore_2
      26: goto          2
      29: return

  static void access$100(javafx.embed.swt.FXCanvas, org.eclipse.swt.events.DisposeEvent);
    Code:
       0: aload_0
       1: aload_1
       2: invokespecial #14                 // Method widgetDisposed:(Lorg/eclipse/swt/events/DisposeEvent;)V
       5: return

  static void access$200(javafx.embed.swt.FXCanvas, org.eclipse.swt.events.MouseEvent, int);
    Code:
       0: aload_0
       1: aload_1
       2: iload_2
       3: invokespecial #13                 // Method sendMouseEventToFX:(Lorg/eclipse/swt/events/MouseEvent;I)V
       6: return

  static void access$300(javafx.embed.swt.FXCanvas);
    Code:
       0: aload_0
       1: invokespecial #12                 // Method sendMoveEventToFX:()V
       4: return

  static void access$400(javafx.embed.swt.FXCanvas);
    Code:
       0: aload_0
       1: invokespecial #11                 // Method sendResizeEventToFX:()V
       4: return

  static void access$500(javafx.embed.swt.FXCanvas, org.eclipse.swt.events.FocusEvent, boolean);
    Code:
       0: aload_0
       1: aload_1
       2: iload_2
       3: invokespecial #10                 // Method sendFocusEventToFX:(Lorg/eclipse/swt/events/FocusEvent;Z)V
       6: return

  static void access$600(javafx.embed.swt.FXCanvas, org.eclipse.swt.events.KeyEvent, int);
    Code:
       0: aload_0
       1: aload_1
       2: iload_2
       3: invokespecial #9                  // Method sendKeyEventToFX:(Lorg/eclipse/swt/events/KeyEvent;I)V
       6: return

  static com.sun.javafx.embed.EmbeddedStageInterface access$702(javafx.embed.swt.FXCanvas, com.sun.javafx.embed.EmbeddedStageInterface);
    Code:
       0: aload_0
       1: aload_1
       2: dup_x1
       3: putfield      #8                  // Field stagePeer:Lcom/sun/javafx/embed/EmbeddedStageInterface;
       6: areturn

  static com.sun.javafx.embed.EmbeddedStageInterface access$700(javafx.embed.swt.FXCanvas);
    Code:
       0: aload_0
       1: getfield      #8                  // Field stagePeer:Lcom/sun/javafx/embed/EmbeddedStageInterface;
       4: areturn

  static int access$800(javafx.embed.swt.FXCanvas);
    Code:
       0: aload_0
       1: getfield      #7                  // Field pWidth:I
       4: ireturn

  static int access$900(javafx.embed.swt.FXCanvas);
    Code:
       0: aload_0
       1: getfield      #6                  // Field pHeight:I
       4: ireturn

  static com.sun.javafx.embed.EmbeddedSceneInterface access$1002(javafx.embed.swt.FXCanvas, com.sun.javafx.embed.EmbeddedSceneInterface);
    Code:
       0: aload_0
       1: aload_1
       2: dup_x1
       3: putfield      #5                  // Field scenePeer:Lcom/sun/javafx/embed/EmbeddedSceneInterface;
       6: areturn

  static com.sun.javafx.embed.EmbeddedSceneInterface access$1000(javafx.embed.swt.FXCanvas);
    Code:
       0: aload_0
       1: getfield      #5                  // Field scenePeer:Lcom/sun/javafx/embed/EmbeddedSceneInterface;
       4: areturn

  static double access$1100(javafx.embed.swt.FXCanvas);
    Code:
       0: aload_0
       1: invokespecial #4                  // Method getScaleFactor:()D
       4: dreturn

  static void access$1200(javafx.embed.swt.FXCanvas, double);
    Code:
       0: aload_0
       1: dload_1
       2: invokespecial #3                  // Method resizePixelBuffer:(D)V
       5: return

  static int access$1302(javafx.embed.swt.FXCanvas, int);
    Code:
       0: aload_0
       1: iload_1
       2: dup_x1
       3: putfield      #2                  // Field pPreferredWidth:I
       6: ireturn

  static int access$1402(javafx.embed.swt.FXCanvas, int);
    Code:
       0: aload_0
       1: iload_1
       2: dup_x1
       3: putfield      #1                  // Field pPreferredHeight:I
       6: ireturn

  static {};
    Code:
       0: new           #291                // class javafx/util/FXPermission
       3: dup
       4: ldc_w         #292                // String accessFXCanvasInternals
       7: invokespecial #293                // Method javafx/util/FXPermission."<init>":(Ljava/lang/String;)V
      10: putstatic     #91                 // Field FXCANVAS_PERMISSION:Ljavafx/util/FXPermission;
      13: bipush        6
      15: anewarray     #36                 // class org/eclipse/swt/dnd/Transfer
      18: dup
      19: iconst_0
      20: invokestatic  #294                // Method org/eclipse/swt/dnd/TextTransfer.getInstance:()Lorg/eclipse/swt/dnd/TextTransfer;
      23: aastore
      24: dup
      25: iconst_1
      26: invokestatic  #295                // Method org/eclipse/swt/dnd/RTFTransfer.getInstance:()Lorg/eclipse/swt/dnd/RTFTransfer;
      29: aastore
      30: dup
      31: iconst_2
      32: invokestatic  #296                // Method org/eclipse/swt/dnd/HTMLTransfer.getInstance:()Lorg/eclipse/swt/dnd/HTMLTransfer;
      35: aastore
      36: dup
      37: iconst_3
      38: invokestatic  #297                // Method org/eclipse/swt/dnd/URLTransfer.getInstance:()Lorg/eclipse/swt/dnd/URLTransfer;
      41: aastore
      42: dup
      43: iconst_4
      44: invokestatic  #298                // Method org/eclipse/swt/dnd/ImageTransfer.getInstance:()Lorg/eclipse/swt/dnd/ImageTransfer;
      47: aastore
      48: dup
      49: iconst_5
      50: invokestatic  #299                // Method org/eclipse/swt/dnd/FileTransfer.getInstance:()Lorg/eclipse/swt/dnd/FileTransfer;
      53: aastore
      54: putstatic     #34                 // Field StandardTransfers:[Lorg/eclipse/swt/dnd/Transfer;
      57: iconst_0
      58: anewarray     #36                 // class org/eclipse/swt/dnd/Transfer
      61: putstatic     #35                 // Field CustomTransfers:[Lorg/eclipse/swt/dnd/Transfer;
      64: invokestatic  #15                 // Method org/eclipse/swt/SWT.getPlatform:()Ljava/lang/String;
      67: ldc           #16                 // String cocoa
      69: invokevirtual #17                 // Method java/lang/String.equals:(Ljava/lang/Object;)Z
      72: ifeq          185
      75: ldc_w         #300                // class org/eclipse/swt/widgets/Shell
      78: ldc_w         #301                // String window
      81: invokevirtual #75                 // Method java/lang/Class.getDeclaredField:(Ljava/lang/String;)Ljava/lang/reflect/Field;
      84: putstatic     #18                 // Field windowField:Ljava/lang/reflect/Field;
      87: getstatic     #18                 // Field windowField:Ljava/lang/reflect/Field;
      90: iconst_1
      91: invokevirtual #76                 // Method java/lang/reflect/Field.setAccessible:(Z)V
      94: ldc_w         #302                // String org.eclipse.swt.internal.cocoa.NSView
      97: invokestatic  #303                // Method java/lang/Class.forName:(Ljava/lang/String;)Ljava/lang/Class;
     100: astore_0
     101: aload_0
     102: ldc_w         #301                // String window
     105: iconst_0
     106: anewarray     #304                // class java/lang/Class
     109: invokevirtual #305                // Method java/lang/Class.getDeclaredMethod:(Ljava/lang/String;[Ljava/lang/Class;)Ljava/lang/reflect/Method;
     112: putstatic     #306                // Field windowMethod:Ljava/lang/reflect/Method;
     115: getstatic     #306                // Field windowMethod:Ljava/lang/reflect/Method;
     118: iconst_1
     119: invokevirtual #307                // Method java/lang/reflect/Method.setAccessible:(Z)V
     122: ldc_w         #308                // String org.eclipse.swt.internal.cocoa.NSWindow
     125: invokestatic  #303                // Method java/lang/Class.forName:(Ljava/lang/String;)Ljava/lang/Class;
     128: astore_1
     129: aload_1
     130: ldc_w         #309                // String screen
     133: iconst_0
     134: anewarray     #304                // class java/lang/Class
     137: invokevirtual #305                // Method java/lang/Class.getDeclaredMethod:(Ljava/lang/String;[Ljava/lang/Class;)Ljava/lang/reflect/Method;
     140: putstatic     #19                 // Field screenMethod:Ljava/lang/reflect/Method;
     143: getstatic     #19                 // Field screenMethod:Ljava/lang/reflect/Method;
     146: iconst_1
     147: invokevirtual #307                // Method java/lang/reflect/Method.setAccessible:(Z)V
     150: ldc_w         #310                // String org.eclipse.swt.internal.cocoa.NSScreen
     153: invokestatic  #303                // Method java/lang/Class.forName:(Ljava/lang/String;)Ljava/lang/Class;
     156: astore_2
     157: aload_2
     158: ldc_w         #311                // String backingScaleFactor
     161: iconst_0
     162: anewarray     #304                // class java/lang/Class
     165: invokevirtual #305                // Method java/lang/Class.getDeclaredMethod:(Ljava/lang/String;[Ljava/lang/Class;)Ljava/lang/reflect/Method;
     168: putstatic     #20                 // Field backingScaleFactorMethod:Ljava/lang/reflect/Method;
     171: getstatic     #20                 // Field backingScaleFactorMethod:Ljava/lang/reflect/Method;
     174: iconst_1
     175: invokevirtual #307                // Method java/lang/reflect/Method.setAccessible:(Z)V
     178: goto          247
     181: astore_0
     182: goto          247
     185: invokestatic  #15                 // Method org/eclipse/swt/SWT.getPlatform:()Ljava/lang/String;
     188: ldc           #28                 // String win32
     190: invokevirtual #17                 // Method java/lang/String.equals:(Ljava/lang/Object;)Z
     193: ifeq          247
     196: invokedynamic #312,  0            // InvokeDynamic #13:run:()Ljava/security/PrivilegedAction;
     201: invokestatic  #86                 // Method java/security/AccessController.doPrivileged:(Ljava/security/PrivilegedAction;)Ljava/lang/Object;
     204: checkcast     #313                // class java/lang/String
     207: astore_0
     208: aload_0
     209: ifnull        222
     212: ldc_w         #314                // String false
     215: aload_0
     216: invokevirtual #315                // Method java/lang/String.equalsIgnoreCase:(Ljava/lang/String;)Z
     219: ifne          243
     222: ldc_w         #316                // String org.eclipse.swt.internal.DPIUtil
     225: invokestatic  #303                // Method java/lang/Class.forName:(Ljava/lang/String;)Ljava/lang/Class;
     228: astore_1
     229: aload_1
     230: ldc_w         #317                // String getDeviceZoom
     233: iconst_0
     234: anewarray     #304                // class java/lang/Class
     237: invokevirtual #318                // Method java/lang/Class.getMethod:(Ljava/lang/String;[Ljava/lang/Class;)Ljava/lang/reflect/Method;
     240: putstatic     #29                 // Field swtDPIUtilMethod:Ljava/lang/reflect/Method;
     243: goto          247
     246: astore_0
     247: invokestatic  #319                // Method initFx:()V
     250: new           #320                // class java/util/ArrayList
     253: dup
     254: invokespecial #321                // Method java/util/ArrayList."<init>":()V
     257: putstatic     #101                // Field targets:Ljava/util/ArrayList;
     260: return
    Exception table:
       from    to  target type
          75   178   181   Class java/lang/Exception
         196   243   246   Class java/lang/Exception
}
