Compiled from "InferredOWLClassHierarchyProvider.java"
public class org.protege.editor.owl.model.hierarchy.cls.InferredOWLClassHierarchyProvider extends org.protege.editor.owl.model.hierarchy.AbstractOWLObjectHierarchyProvider<org.semanticweb.owlapi.model.OWLClass> {
  private final org.protege.editor.owl.model.OWLModelManager owlModelManager;

  private final org.semanticweb.owlapi.model.OWLClass owlThing;

  private final org.semanticweb.owlapi.model.OWLClass owlNothing;

  private org.protege.editor.owl.model.event.OWLModelManagerListener owlModelManagerListener;

  public org.protege.editor.owl.model.hierarchy.cls.InferredOWLClassHierarchyProvider(org.protege.editor.owl.model.OWLModelManager, org.semanticweb.owlapi.model.OWLOntologyManager);
    Code:
       0: aload_0
       1: aload_2
       2: invokespecial #1                  // Method org/protege/editor/owl/model/hierarchy/AbstractOWLObjectHierarchyProvider."<init>":(Lorg/semanticweb/owlapi/model/OWLOntologyManager;)V
       5: aload_0
       6: aload_0
       7: invokedynamic #2,  0              // InvokeDynamic #0:handleChange:(Lorg/protege/editor/owl/model/hierarchy/cls/InferredOWLClassHierarchyProvider;)Lorg/protege/editor/owl/model/event/OWLModelManagerListener;
      12: putfield      #3                  // Field owlModelManagerListener:Lorg/protege/editor/owl/model/event/OWLModelManagerListener;
      15: aload_0
      16: aload_1
      17: putfield      #4                  // Field owlModelManager:Lorg/protege/editor/owl/model/OWLModelManager;
      20: aload_0
      21: aload_1
      22: invokeinterface #5,  1            // InterfaceMethod org/protege/editor/owl/model/OWLModelManager.getOWLDataFactory:()Lorg/semanticweb/owlapi/model/OWLDataFactory;
      27: invokeinterface #6,  1            // InterfaceMethod org/semanticweb/owlapi/model/OWLDataFactory.getOWLThing:()Lorg/semanticweb/owlapi/model/OWLClass;
      32: putfield      #7                  // Field owlThing:Lorg/semanticweb/owlapi/model/OWLClass;
      35: aload_0
      36: aload_1
      37: invokeinterface #5,  1            // InterfaceMethod org/protege/editor/owl/model/OWLModelManager.getOWLDataFactory:()Lorg/semanticweb/owlapi/model/OWLDataFactory;
      42: invokeinterface #8,  1            // InterfaceMethod org/semanticweb/owlapi/model/OWLDataFactory.getOWLNothing:()Lorg/semanticweb/owlapi/model/OWLClass;
      47: putfield      #9                  // Field owlNothing:Lorg/semanticweb/owlapi/model/OWLClass;
      50: aload_1
      51: aload_0
      52: getfield      #3                  // Field owlModelManagerListener:Lorg/protege/editor/owl/model/event/OWLModelManagerListener;
      55: invokeinterface #10,  2           // InterfaceMethod org/protege/editor/owl/model/OWLModelManager.addListener:(Lorg/protege/editor/owl/model/event/OWLModelManagerListener;)V
      60: return

  public void rebuild();
    Code:
       0: return

  public void dispose();
    Code:
       0: aload_0
       1: invokespecial #11                 // Method org/protege/editor/owl/model/hierarchy/AbstractOWLObjectHierarchyProvider.dispose:()V
       4: aload_0
       5: getfield      #4                  // Field owlModelManager:Lorg/protege/editor/owl/model/OWLModelManager;
       8: aload_0
       9: getfield      #3                  // Field owlModelManagerListener:Lorg/protege/editor/owl/model/event/OWLModelManagerListener;
      12: invokeinterface #12,  2           // InterfaceMethod org/protege/editor/owl/model/OWLModelManager.removeListener:(Lorg/protege/editor/owl/model/event/OWLModelManagerListener;)V
      17: return

  public java.util.Set<org.semanticweb.owlapi.model.OWLClass> getRoots();
    Code:
       0: aload_0
       1: getfield      #7                  // Field owlThing:Lorg/semanticweb/owlapi/model/OWLClass;
       4: invokestatic  #13                 // Method java/util/Collections.singleton:(Ljava/lang/Object;)Ljava/util/Set;
       7: areturn

  protected org.semanticweb.owlapi.reasoner.OWLReasoner getReasoner();
    Code:
       0: aload_0
       1: getfield      #4                  // Field owlModelManager:Lorg/protege/editor/owl/model/OWLModelManager;
       4: invokeinterface #14,  1           // InterfaceMethod org/protege/editor/owl/model/OWLModelManager.getOWLReasonerManager:()Lorg/protege/editor/owl/model/inference/OWLReasonerManager;
       9: invokeinterface #15,  1           // InterfaceMethod org/protege/editor/owl/model/inference/OWLReasonerManager.getCurrentReasoner:()Lorg/semanticweb/owlapi/reasoner/OWLReasoner;
      14: areturn

  public java.util.Set<org.semanticweb.owlapi.model.OWLClass> getUnfilteredChildren(org.semanticweb.owlapi.model.OWLClass);
    Code:
       0: aload_0
       1: invokevirtual #16                 // Method getReasoner:()Lorg/semanticweb/owlapi/reasoner/OWLReasoner;
       4: invokeinterface #17,  1           // InterfaceMethod org/semanticweb/owlapi/reasoner/OWLReasoner.isConsistent:()Z
       9: ifne          16
      12: invokestatic  #18                 // Method java/util/Collections.emptySet:()Ljava/util/Set;
      15: areturn
      16: aload_0
      17: invokevirtual #16                 // Method getReasoner:()Lorg/semanticweb/owlapi/reasoner/OWLReasoner;
      20: aload_1
      21: iconst_1
      22: invokeinterface #19,  3           // InterfaceMethod org/semanticweb/owlapi/reasoner/OWLReasoner.getSubClasses:(Lorg/semanticweb/owlapi/model/OWLClassExpression;Z)Lorg/semanticweb/owlapi/reasoner/NodeSet;
      27: invokeinterface #20,  1           // InterfaceMethod org/semanticweb/owlapi/reasoner/NodeSet.getFlattened:()Ljava/util/Set;
      32: astore_2
      33: aload_1
      34: invokeinterface #21,  1           // InterfaceMethod org/semanticweb/owlapi/model/OWLClass.isOWLThing:()Z
      39: ifeq          78
      42: aload_0
      43: getfield      #4                  // Field owlModelManager:Lorg/protege/editor/owl/model/OWLModelManager;
      46: invokeinterface #22,  1           // InterfaceMethod org/protege/editor/owl/model/OWLModelManager.getReasoner:()Lorg/semanticweb/owlapi/reasoner/OWLReasoner;
      51: invokeinterface #23,  1           // InterfaceMethod org/semanticweb/owlapi/reasoner/OWLReasoner.getUnsatisfiableClasses:()Lorg/semanticweb/owlapi/reasoner/Node;
      56: invokeinterface #24,  1           // InterfaceMethod org/semanticweb/owlapi/reasoner/Node.isSingleton:()Z
      61: ifne          78
      64: aload_2
      65: aload_0
      66: getfield      #9                  // Field owlNothing:Lorg/semanticweb/owlapi/model/OWLClass;
      69: invokeinterface #25,  2           // InterfaceMethod java/util/Set.add:(Ljava/lang/Object;)Z
      74: pop
      75: goto          172
      78: aload_1
      79: invokeinterface #26,  1           // InterfaceMethod org/semanticweb/owlapi/model/OWLClass.isOWLNothing:()Z
      84: ifeq          115
      87: aload_2
      88: aload_0
      89: invokevirtual #16                 // Method getReasoner:()Lorg/semanticweb/owlapi/reasoner/OWLReasoner;
      92: invokeinterface #23,  1           // InterfaceMethod org/semanticweb/owlapi/reasoner/OWLReasoner.getUnsatisfiableClasses:()Lorg/semanticweb/owlapi/reasoner/Node;
      97: aload_0
      98: getfield      #9                  // Field owlNothing:Lorg/semanticweb/owlapi/model/OWLClass;
     101: invokeinterface #27,  2           // InterfaceMethod org/semanticweb/owlapi/reasoner/Node.getEntitiesMinus:(Lorg/semanticweb/owlapi/model/OWLObject;)Ljava/util/Set;
     106: invokeinterface #28,  2           // InterfaceMethod java/util/Set.addAll:(Ljava/util/Collection;)Z
     111: pop
     112: goto          172
     115: aload_2
     116: aload_0
     117: getfield      #9                  // Field owlNothing:Lorg/semanticweb/owlapi/model/OWLClass;
     120: invokeinterface #29,  2           // InterfaceMethod java/util/Set.remove:(Ljava/lang/Object;)Z
     125: pop
     126: aload_2
     127: invokeinterface #30,  1           // InterfaceMethod java/util/Set.iterator:()Ljava/util/Iterator;
     132: astore_3
     133: aload_3
     134: invokeinterface #31,  1           // InterfaceMethod java/util/Iterator.hasNext:()Z
     139: ifeq          172
     142: aload_0
     143: invokevirtual #16                 // Method getReasoner:()Lorg/semanticweb/owlapi/reasoner/OWLReasoner;
     146: aload_3
     147: invokeinterface #32,  1           // InterfaceMethod java/util/Iterator.next:()Ljava/lang/Object;
     152: checkcast     #33                 // class org/semanticweb/owlapi/model/OWLClassExpression
     155: invokeinterface #34,  2           // InterfaceMethod org/semanticweb/owlapi/reasoner/OWLReasoner.isSatisfiable:(Lorg/semanticweb/owlapi/model/OWLClassExpression;)Z
     160: ifne          133
     163: aload_3
     164: invokeinterface #35,  1           // InterfaceMethod java/util/Iterator.remove:()V
     169: goto          133
     172: aload_2
     173: areturn

  public java.util.Set<org.semanticweb.owlapi.model.OWLClass> getDescendants(org.semanticweb.owlapi.model.OWLClass);
    Code:
       0: aload_0
       1: invokevirtual #16                 // Method getReasoner:()Lorg/semanticweb/owlapi/reasoner/OWLReasoner;
       4: invokeinterface #17,  1           // InterfaceMethod org/semanticweb/owlapi/reasoner/OWLReasoner.isConsistent:()Z
       9: ifne          16
      12: invokestatic  #18                 // Method java/util/Collections.emptySet:()Ljava/util/Set;
      15: areturn
      16: aload_0
      17: invokevirtual #16                 // Method getReasoner:()Lorg/semanticweb/owlapi/reasoner/OWLReasoner;
      20: aload_1
      21: iconst_0
      22: invokeinterface #19,  3           // InterfaceMethod org/semanticweb/owlapi/reasoner/OWLReasoner.getSubClasses:(Lorg/semanticweb/owlapi/model/OWLClassExpression;Z)Lorg/semanticweb/owlapi/reasoner/NodeSet;
      27: invokeinterface #20,  1           // InterfaceMethod org/semanticweb/owlapi/reasoner/NodeSet.getFlattened:()Ljava/util/Set;
      32: areturn

  public java.util.Set<org.semanticweb.owlapi.model.OWLClass> getParents(org.semanticweb.owlapi.model.OWLClass);
    Code:
       0: aload_0
       1: invokevirtual #16                 // Method getReasoner:()Lorg/semanticweb/owlapi/reasoner/OWLReasoner;
       4: invokeinterface #17,  1           // InterfaceMethod org/semanticweb/owlapi/reasoner/OWLReasoner.isConsistent:()Z
       9: ifne          16
      12: invokestatic  #18                 // Method java/util/Collections.emptySet:()Ljava/util/Set;
      15: areturn
      16: aload_1
      17: invokeinterface #26,  1           // InterfaceMethod org/semanticweb/owlapi/model/OWLClass.isOWLNothing:()Z
      22: ifeq          33
      25: aload_0
      26: getfield      #7                  // Field owlThing:Lorg/semanticweb/owlapi/model/OWLClass;
      29: invokestatic  #13                 // Method java/util/Collections.singleton:(Ljava/lang/Object;)Ljava/util/Set;
      32: areturn
      33: aload_0
      34: invokevirtual #16                 // Method getReasoner:()Lorg/semanticweb/owlapi/reasoner/OWLReasoner;
      37: aload_1
      38: invokeinterface #34,  2           // InterfaceMethod org/semanticweb/owlapi/reasoner/OWLReasoner.isSatisfiable:(Lorg/semanticweb/owlapi/model/OWLClassExpression;)Z
      43: ifne          54
      46: aload_0
      47: getfield      #9                  // Field owlNothing:Lorg/semanticweb/owlapi/model/OWLClass;
      50: invokestatic  #13                 // Method java/util/Collections.singleton:(Ljava/lang/Object;)Ljava/util/Set;
      53: areturn
      54: aload_0
      55: invokevirtual #16                 // Method getReasoner:()Lorg/semanticweb/owlapi/reasoner/OWLReasoner;
      58: aload_1
      59: iconst_1
      60: invokeinterface #36,  3           // InterfaceMethod org/semanticweb/owlapi/reasoner/OWLReasoner.getSuperClasses:(Lorg/semanticweb/owlapi/model/OWLClassExpression;Z)Lorg/semanticweb/owlapi/reasoner/NodeSet;
      65: invokeinterface #20,  1           // InterfaceMethod org/semanticweb/owlapi/reasoner/NodeSet.getFlattened:()Ljava/util/Set;
      70: astore_2
      71: aload_2
      72: aload_1
      73: invokeinterface #29,  2           // InterfaceMethod java/util/Set.remove:(Ljava/lang/Object;)Z
      78: pop
      79: aload_2
      80: areturn

  public java.util.Set<org.semanticweb.owlapi.model.OWLClass> getAncestors(org.semanticweb.owlapi.model.OWLClass);
    Code:
       0: aload_0
       1: invokevirtual #16                 // Method getReasoner:()Lorg/semanticweb/owlapi/reasoner/OWLReasoner;
       4: invokeinterface #17,  1           // InterfaceMethod org/semanticweb/owlapi/reasoner/OWLReasoner.isConsistent:()Z
       9: ifne          16
      12: invokestatic  #18                 // Method java/util/Collections.emptySet:()Ljava/util/Set;
      15: areturn
      16: aload_0
      17: invokevirtual #16                 // Method getReasoner:()Lorg/semanticweb/owlapi/reasoner/OWLReasoner;
      20: aload_1
      21: iconst_0
      22: invokeinterface #36,  3           // InterfaceMethod org/semanticweb/owlapi/reasoner/OWLReasoner.getSuperClasses:(Lorg/semanticweb/owlapi/model/OWLClassExpression;Z)Lorg/semanticweb/owlapi/reasoner/NodeSet;
      27: invokeinterface #20,  1           // InterfaceMethod org/semanticweb/owlapi/reasoner/NodeSet.getFlattened:()Ljava/util/Set;
      32: areturn

  public java.util.Set<org.semanticweb.owlapi.model.OWLClass> getEquivalents(org.semanticweb.owlapi.model.OWLClass);
    Code:
       0: aload_0
       1: invokevirtual #16                 // Method getReasoner:()Lorg/semanticweb/owlapi/reasoner/OWLReasoner;
       4: invokeinterface #17,  1           // InterfaceMethod org/semanticweb/owlapi/reasoner/OWLReasoner.isConsistent:()Z
       9: ifne          16
      12: invokestatic  #18                 // Method java/util/Collections.emptySet:()Ljava/util/Set;
      15: areturn
      16: aload_0
      17: invokevirtual #16                 // Method getReasoner:()Lorg/semanticweb/owlapi/reasoner/OWLReasoner;
      20: aload_1
      21: invokeinterface #34,  2           // InterfaceMethod org/semanticweb/owlapi/reasoner/OWLReasoner.isSatisfiable:(Lorg/semanticweb/owlapi/model/OWLClassExpression;)Z
      26: ifne          33
      29: invokestatic  #18                 // Method java/util/Collections.emptySet:()Ljava/util/Set;
      32: areturn
      33: aload_0
      34: invokevirtual #16                 // Method getReasoner:()Lorg/semanticweb/owlapi/reasoner/OWLReasoner;
      37: aload_1
      38: invokeinterface #37,  2           // InterfaceMethod org/semanticweb/owlapi/reasoner/OWLReasoner.getEquivalentClasses:(Lorg/semanticweb/owlapi/model/OWLClassExpression;)Lorg/semanticweb/owlapi/reasoner/Node;
      43: aload_1
      44: invokeinterface #27,  2           // InterfaceMethod org/semanticweb/owlapi/reasoner/Node.getEntitiesMinus:(Lorg/semanticweb/owlapi/model/OWLObject;)Ljava/util/Set;
      49: areturn

  public boolean containsReference(org.semanticweb.owlapi.model.OWLClass);
    Code:
       0: iconst_0
       1: ireturn

  protected void addRoot(org.semanticweb.owlapi.model.OWLClass);
    Code:
       0: return

  protected void removeRoot(org.semanticweb.owlapi.model.OWLClass);
    Code:
       0: return

  protected java.util.Set<org.semanticweb.owlapi.model.OWLClass> getOrphanRoots(org.semanticweb.owlapi.model.OWLClass);
    Code:
       0: invokestatic  #18                 // Method java/util/Collections.emptySet:()Ljava/util/Set;
       3: areturn

  public void setOntologies(java.util.Set<org.semanticweb.owlapi.model.OWLOntology>);
    Code:
       0: return

  public java.util.Set getDescendants(org.semanticweb.owlapi.model.OWLObject);
    Code:
       0: aload_0
       1: aload_1
       2: checkcast     #38                 // class org/semanticweb/owlapi/model/OWLClass
       5: invokevirtual #39                 // Method getDescendants:(Lorg/semanticweb/owlapi/model/OWLClass;)Ljava/util/Set;
       8: areturn

  public java.util.Collection getUnfilteredChildren(org.semanticweb.owlapi.model.OWLObject);
    Code:
       0: aload_0
       1: aload_1
       2: checkcast     #38                 // class org/semanticweb/owlapi/model/OWLClass
       5: invokevirtual #40                 // Method getUnfilteredChildren:(Lorg/semanticweb/owlapi/model/OWLClass;)Ljava/util/Set;
       8: areturn

  public java.util.Set getAncestors(org.semanticweb.owlapi.model.OWLObject);
    Code:
       0: aload_0
       1: aload_1
       2: checkcast     #38                 // class org/semanticweb/owlapi/model/OWLClass
       5: invokevirtual #41                 // Method getAncestors:(Lorg/semanticweb/owlapi/model/OWLClass;)Ljava/util/Set;
       8: areturn

  public boolean containsReference(org.semanticweb.owlapi.model.OWLObject);
    Code:
       0: aload_0
       1: aload_1
       2: checkcast     #38                 // class org/semanticweb/owlapi/model/OWLClass
       5: invokevirtual #42                 // Method containsReference:(Lorg/semanticweb/owlapi/model/OWLClass;)Z
       8: ireturn

  public java.util.Set getEquivalents(org.semanticweb.owlapi.model.OWLObject);
    Code:
       0: aload_0
       1: aload_1
       2: checkcast     #38                 // class org/semanticweb/owlapi/model/OWLClass
       5: invokevirtual #43                 // Method getEquivalents:(Lorg/semanticweb/owlapi/model/OWLClass;)Ljava/util/Set;
       8: areturn

  public java.util.Set getParents(org.semanticweb.owlapi.model.OWLObject);
    Code:
       0: aload_0
       1: aload_1
       2: checkcast     #38                 // class org/semanticweb/owlapi/model/OWLClass
       5: invokevirtual #44                 // Method getParents:(Lorg/semanticweb/owlapi/model/OWLClass;)Ljava/util/Set;
       8: areturn

  private void lambda$new$0(org.protege.editor.owl.model.event.OWLModelManagerChangeEvent);
    Code:
       0: aload_1
       1: getstatic     #45                 // Field org/protege/editor/owl/model/event/EventType.REASONER_CHANGED:Lorg/protege/editor/owl/model/event/EventType;
       4: invokevirtual #46                 // Method org/protege/editor/owl/model/event/OWLModelManagerChangeEvent.isType:(Lorg/protege/editor/owl/model/event/EventType;)Z
       7: ifne          40
      10: aload_1
      11: getstatic     #47                 // Field org/protege/editor/owl/model/event/EventType.ACTIVE_ONTOLOGY_CHANGED:Lorg/protege/editor/owl/model/event/EventType;
      14: invokevirtual #46                 // Method org/protege/editor/owl/model/event/OWLModelManagerChangeEvent.isType:(Lorg/protege/editor/owl/model/event/EventType;)Z
      17: ifne          40
      20: aload_1
      21: getstatic     #48                 // Field org/protege/editor/owl/model/event/EventType.ONTOLOGY_CLASSIFIED:Lorg/protege/editor/owl/model/event/EventType;
      24: invokevirtual #46                 // Method org/protege/editor/owl/model/event/OWLModelManagerChangeEvent.isType:(Lorg/protege/editor/owl/model/event/EventType;)Z
      27: ifne          40
      30: aload_1
      31: getstatic     #49                 // Field org/protege/editor/owl/model/event/EventType.ONTOLOGY_RELOADED:Lorg/protege/editor/owl/model/event/EventType;
      34: invokevirtual #46                 // Method org/protege/editor/owl/model/event/OWLModelManagerChangeEvent.isType:(Lorg/protege/editor/owl/model/event/EventType;)Z
      37: ifeq          44
      40: aload_0
      41: invokevirtual #50                 // Method fireHierarchyChanged:()V
      44: return
}
