Compiled from "CtClassType.java"
class javassist.CtClassType extends javassist.CtClass {
  javassist.ClassPool classPool;

  boolean wasChanged;

  private boolean wasFrozen;

  boolean wasPruned;

  boolean gcConstPool;

  javassist.bytecode.ClassFile classfile;

  byte[] rawClassfile;

  private java.lang.ref.Reference<javassist.CtMember$Cache> memberCache;

  private javassist.compiler.AccessorMaker accessors;

  private javassist.FieldInitLink fieldInitializers;

  private java.util.Map<javassist.CtMethod, java.lang.String> hiddenMethods;

  private int uniqueNumberSeed;

  private boolean doPruning;

  private int getCount;

  private static final int GET_THRESHOLD;

  javassist.CtClassType(java.lang.String, javassist.ClassPool);
    Code:
       0: aload_0
       1: aload_1
       2: invokespecial #1                  // Method javassist/CtClass."<init>":(Ljava/lang/String;)V
       5: aload_0
       6: getstatic     #2                  // Field javassist/ClassPool.doPruning:Z
       9: putfield      #3                  // Field doPruning:Z
      12: aload_0
      13: aload_2
      14: putfield      #4                  // Field classPool:Ljavassist/ClassPool;
      17: aload_0
      18: aload_0
      19: aload_0
      20: aload_0
      21: iconst_0
      22: dup_x1
      23: putfield      #5                  // Field gcConstPool:Z
      26: dup_x1
      27: putfield      #6                  // Field wasPruned:Z
      30: dup_x1
      31: putfield      #7                  // Field wasFrozen:Z
      34: putfield      #8                  // Field wasChanged:Z
      37: aload_0
      38: aconst_null
      39: putfield      #9                  // Field classfile:Ljavassist/bytecode/ClassFile;
      42: aload_0
      43: aconst_null
      44: putfield      #10                 // Field rawClassfile:[B
      47: aload_0
      48: aconst_null
      49: putfield      #11                 // Field memberCache:Ljava/lang/ref/Reference;
      52: aload_0
      53: aconst_null
      54: putfield      #12                 // Field accessors:Ljavassist/compiler/AccessorMaker;
      57: aload_0
      58: aconst_null
      59: putfield      #13                 // Field fieldInitializers:Ljavassist/FieldInitLink;
      62: aload_0
      63: aconst_null
      64: putfield      #14                 // Field hiddenMethods:Ljava/util/Map;
      67: aload_0
      68: iconst_0
      69: putfield      #15                 // Field uniqueNumberSeed:I
      72: aload_0
      73: iconst_0
      74: putfield      #16                 // Field getCount:I
      77: return

  javassist.CtClassType(java.io.InputStream, javassist.ClassPool) throws java.io.IOException;
    Code:
       0: aload_0
       1: aconst_null
       2: checkcast     #17                 // class java/lang/String
       5: aload_2
       6: invokespecial #18                 // Method "<init>":(Ljava/lang/String;Ljavassist/ClassPool;)V
       9: aload_0
      10: new           #19                 // class javassist/bytecode/ClassFile
      13: dup
      14: new           #20                 // class java/io/DataInputStream
      17: dup
      18: aload_1
      19: invokespecial #21                 // Method java/io/DataInputStream."<init>":(Ljava/io/InputStream;)V
      22: invokespecial #22                 // Method javassist/bytecode/ClassFile."<init>":(Ljava/io/DataInputStream;)V
      25: putfield      #9                  // Field classfile:Ljavassist/bytecode/ClassFile;
      28: aload_0
      29: aload_0
      30: getfield      #9                  // Field classfile:Ljavassist/bytecode/ClassFile;
      33: invokevirtual #23                 // Method javassist/bytecode/ClassFile.getName:()Ljava/lang/String;
      36: putfield      #24                 // Field qualifiedName:Ljava/lang/String;
      39: return

  javassist.CtClassType(javassist.bytecode.ClassFile, javassist.ClassPool);
    Code:
       0: aload_0
       1: aconst_null
       2: checkcast     #17                 // class java/lang/String
       5: aload_2
       6: invokespecial #18                 // Method "<init>":(Ljava/lang/String;Ljavassist/ClassPool;)V
       9: aload_0
      10: aload_1
      11: putfield      #9                  // Field classfile:Ljavassist/bytecode/ClassFile;
      14: aload_0
      15: aload_0
      16: getfield      #9                  // Field classfile:Ljavassist/bytecode/ClassFile;
      19: invokevirtual #23                 // Method javassist/bytecode/ClassFile.getName:()Ljava/lang/String;
      22: putfield      #24                 // Field qualifiedName:Ljava/lang/String;
      25: return

  protected void extendToString(java.lang.StringBuffer);
    Code:
       0: aload_0
       1: getfield      #8                  // Field wasChanged:Z
       4: ifeq          14
       7: aload_1
       8: ldc           #25                 // String changed
      10: invokevirtual #26                 // Method java/lang/StringBuffer.append:(Ljava/lang/String;)Ljava/lang/StringBuffer;
      13: pop
      14: aload_0
      15: getfield      #7                  // Field wasFrozen:Z
      18: ifeq          28
      21: aload_1
      22: ldc           #27                 // String frozen
      24: invokevirtual #26                 // Method java/lang/StringBuffer.append:(Ljava/lang/String;)Ljava/lang/StringBuffer;
      27: pop
      28: aload_0
      29: getfield      #6                  // Field wasPruned:Z
      32: ifeq          42
      35: aload_1
      36: ldc           #28                 // String pruned
      38: invokevirtual #26                 // Method java/lang/StringBuffer.append:(Ljava/lang/String;)Ljava/lang/StringBuffer;
      41: pop
      42: aload_1
      43: aload_0
      44: invokevirtual #29                 // Method getModifiers:()I
      47: invokestatic  #30                 // Method javassist/Modifier.toString:(I)Ljava/lang/String;
      50: invokevirtual #26                 // Method java/lang/StringBuffer.append:(Ljava/lang/String;)Ljava/lang/StringBuffer;
      53: pop
      54: aload_1
      55: ldc           #31                 // String  class
      57: invokevirtual #26                 // Method java/lang/StringBuffer.append:(Ljava/lang/String;)Ljava/lang/StringBuffer;
      60: pop
      61: aload_1
      62: aload_0
      63: invokevirtual #32                 // Method getName:()Ljava/lang/String;
      66: invokevirtual #26                 // Method java/lang/StringBuffer.append:(Ljava/lang/String;)Ljava/lang/StringBuffer;
      69: pop
      70: aload_0
      71: invokevirtual #33                 // Method getSuperclass:()Ljavassist/CtClass;
      74: astore_2
      75: aload_2
      76: ifnull        120
      79: aload_2
      80: invokevirtual #34                 // Method javassist/CtClass.getName:()Ljava/lang/String;
      83: astore_3
      84: aload_3
      85: ldc           #35                 // String java.lang.Object
      87: invokevirtual #36                 // Method java/lang/String.equals:(Ljava/lang/Object;)Z
      90: ifne          120
      93: aload_1
      94: new           #37                 // class java/lang/StringBuilder
      97: dup
      98: invokespecial #38                 // Method java/lang/StringBuilder."<init>":()V
     101: ldc           #39                 // String  extends
     103: invokevirtual #40                 // Method java/lang/StringBuilder.append:(Ljava/lang/String;)Ljava/lang/StringBuilder;
     106: aload_2
     107: invokevirtual #34                 // Method javassist/CtClass.getName:()Ljava/lang/String;
     110: invokevirtual #40                 // Method java/lang/StringBuilder.append:(Ljava/lang/String;)Ljava/lang/StringBuilder;
     113: invokevirtual #41                 // Method java/lang/StringBuilder.toString:()Ljava/lang/String;
     116: invokevirtual #26                 // Method java/lang/StringBuffer.append:(Ljava/lang/String;)Ljava/lang/StringBuffer;
     119: pop
     120: goto          131
     123: astore_2
     124: aload_1
     125: ldc           #43                 // String  extends ??
     127: invokevirtual #26                 // Method java/lang/StringBuffer.append:(Ljava/lang/String;)Ljava/lang/StringBuffer;
     130: pop
     131: aload_0
     132: invokevirtual #44                 // Method getInterfaces:()[Ljavassist/CtClass;
     135: astore_2
     136: aload_2
     137: arraylength
     138: ifle          148
     141: aload_1
     142: ldc           #45                 // String  implements
     144: invokevirtual #26                 // Method java/lang/StringBuffer.append:(Ljava/lang/String;)Ljava/lang/StringBuffer;
     147: pop
     148: iconst_0
     149: istore_3
     150: iload_3
     151: aload_2
     152: arraylength
     153: if_icmpge     180
     156: aload_1
     157: aload_2
     158: iload_3
     159: aaload
     160: invokevirtual #34                 // Method javassist/CtClass.getName:()Ljava/lang/String;
     163: invokevirtual #26                 // Method java/lang/StringBuffer.append:(Ljava/lang/String;)Ljava/lang/StringBuffer;
     166: pop
     167: aload_1
     168: ldc           #46                 // String ,
     170: invokevirtual #26                 // Method java/lang/StringBuffer.append:(Ljava/lang/String;)Ljava/lang/StringBuffer;
     173: pop
     174: iinc          3, 1
     177: goto          150
     180: goto          191
     183: astore_2
     184: aload_1
     185: ldc           #43                 // String  extends ??
     187: invokevirtual #26                 // Method java/lang/StringBuffer.append:(Ljava/lang/String;)Ljava/lang/StringBuffer;
     190: pop
     191: aload_0
     192: invokevirtual #47                 // Method getMembers:()Ljavassist/CtMember$Cache;
     195: astore_2
     196: aload_0
     197: aload_1
     198: ldc           #48                 // String  fields=
     200: aload_2
     201: invokevirtual #49                 // Method javassist/CtMember$Cache.fieldHead:()Ljavassist/CtMember;
     204: aload_2
     205: invokevirtual #50                 // Method javassist/CtMember$Cache.lastField:()Ljavassist/CtMember;
     208: invokespecial #51                 // Method exToString:(Ljava/lang/StringBuffer;Ljava/lang/String;Ljavassist/CtMember;Ljavassist/CtMember;)V
     211: aload_0
     212: aload_1
     213: ldc           #52                 // String  constructors=
     215: aload_2
     216: invokevirtual #53                 // Method javassist/CtMember$Cache.consHead:()Ljavassist/CtMember;
     219: aload_2
     220: invokevirtual #54                 // Method javassist/CtMember$Cache.lastCons:()Ljavassist/CtMember;
     223: invokespecial #51                 // Method exToString:(Ljava/lang/StringBuffer;Ljava/lang/String;Ljavassist/CtMember;Ljavassist/CtMember;)V
     226: aload_0
     227: aload_1
     228: ldc           #55                 // String  methods=
     230: aload_2
     231: invokevirtual #56                 // Method javassist/CtMember$Cache.methodHead:()Ljavassist/CtMember;
     234: aload_2
     235: invokevirtual #57                 // Method javassist/CtMember$Cache.lastMethod:()Ljavassist/CtMember;
     238: invokespecial #51                 // Method exToString:(Ljava/lang/StringBuffer;Ljava/lang/String;Ljavassist/CtMember;Ljavassist/CtMember;)V
     241: return
    Exception table:
       from    to  target type
          70   120   123   Class javassist/NotFoundException
         131   180   183   Class javassist/NotFoundException

  private void exToString(java.lang.StringBuffer, java.lang.String, javassist.CtMember, javassist.CtMember);
    Code:
       0: aload_1
       1: aload_2
       2: invokevirtual #26                 // Method java/lang/StringBuffer.append:(Ljava/lang/String;)Ljava/lang/StringBuffer;
       5: pop
       6: aload_3
       7: aload         4
       9: if_acmpeq     33
      12: aload_3
      13: invokevirtual #58                 // Method javassist/CtMember.next:()Ljavassist/CtMember;
      16: astore_3
      17: aload_1
      18: aload_3
      19: invokevirtual #59                 // Method java/lang/StringBuffer.append:(Ljava/lang/Object;)Ljava/lang/StringBuffer;
      22: pop
      23: aload_1
      24: ldc           #46                 // String ,
      26: invokevirtual #26                 // Method java/lang/StringBuffer.append:(Ljava/lang/String;)Ljava/lang/StringBuffer;
      29: pop
      30: goto          6
      33: return

  public javassist.compiler.AccessorMaker getAccessorMaker();
    Code:
       0: aload_0
       1: getfield      #12                 // Field accessors:Ljavassist/compiler/AccessorMaker;
       4: ifnonnull     19
       7: aload_0
       8: new           #60                 // class javassist/compiler/AccessorMaker
      11: dup
      12: aload_0
      13: invokespecial #61                 // Method javassist/compiler/AccessorMaker."<init>":(Ljavassist/CtClass;)V
      16: putfield      #12                 // Field accessors:Ljavassist/compiler/AccessorMaker;
      19: aload_0
      20: getfield      #12                 // Field accessors:Ljavassist/compiler/AccessorMaker;
      23: areturn

  public javassist.bytecode.ClassFile getClassFile2();
    Code:
       0: aload_0
       1: iconst_1
       2: invokevirtual #62                 // Method getClassFile3:(Z)Ljavassist/bytecode/ClassFile;
       5: areturn

  public javassist.bytecode.ClassFile getClassFile3(boolean);
    Code:
       0: aload_0
       1: getfield      #9                  // Field classfile:Ljavassist/bytecode/ClassFile;
       4: astore_2
       5: aload_2
       6: ifnull        11
       9: aload_2
      10: areturn
      11: iload_1
      12: ifeq          22
      15: aload_0
      16: getfield      #4                  // Field classPool:Ljavassist/ClassPool;
      19: invokevirtual #63                 // Method javassist/ClassPool.compress:()V
      22: aload_0
      23: getfield      #10                 // Field rawClassfile:[B
      26: ifnull        85
      29: new           #19                 // class javassist/bytecode/ClassFile
      32: dup
      33: new           #20                 // class java/io/DataInputStream
      36: dup
      37: new           #64                 // class java/io/ByteArrayInputStream
      40: dup
      41: aload_0
      42: getfield      #10                 // Field rawClassfile:[B
      45: invokespecial #65                 // Method java/io/ByteArrayInputStream."<init>":([B)V
      48: invokespecial #21                 // Method java/io/DataInputStream."<init>":(Ljava/io/InputStream;)V
      51: invokespecial #22                 // Method javassist/bytecode/ClassFile."<init>":(Ljava/io/DataInputStream;)V
      54: astore_3
      55: aload_0
      56: aconst_null
      57: putfield      #10                 // Field rawClassfile:[B
      60: aload_0
      61: iconst_2
      62: putfield      #16                 // Field getCount:I
      65: aload_0
      66: aload_3
      67: invokespecial #67                 // Method setClassFile:(Ljavassist/bytecode/ClassFile;)Ljavassist/bytecode/ClassFile;
      70: areturn
      71: astore_3
      72: new           #69                 // class java/lang/RuntimeException
      75: dup
      76: aload_3
      77: invokevirtual #70                 // Method java/io/IOException.toString:()Ljava/lang/String;
      80: aload_3
      81: invokespecial #71                 // Method java/lang/RuntimeException."<init>":(Ljava/lang/String;Ljava/lang/Throwable;)V
      84: athrow
      85: aconst_null
      86: astore_3
      87: aload_0
      88: getfield      #4                  // Field classPool:Ljavassist/ClassPool;
      91: aload_0
      92: invokevirtual #32                 // Method getName:()Ljava/lang/String;
      95: invokevirtual #72                 // Method javassist/ClassPool.openClassfile:(Ljava/lang/String;)Ljava/io/InputStream;
      98: astore_3
      99: aload_3
     100: ifnonnull     115
     103: new           #42                 // class javassist/NotFoundException
     106: dup
     107: aload_0
     108: invokevirtual #32                 // Method getName:()Ljava/lang/String;
     111: invokespecial #73                 // Method javassist/NotFoundException."<init>":(Ljava/lang/String;)V
     114: athrow
     115: new           #74                 // class java/io/BufferedInputStream
     118: dup
     119: aload_3
     120: invokespecial #75                 // Method java/io/BufferedInputStream."<init>":(Ljava/io/InputStream;)V
     123: astore_3
     124: new           #19                 // class javassist/bytecode/ClassFile
     127: dup
     128: new           #20                 // class java/io/DataInputStream
     131: dup
     132: aload_3
     133: invokespecial #21                 // Method java/io/DataInputStream."<init>":(Ljava/io/InputStream;)V
     136: invokespecial #22                 // Method javassist/bytecode/ClassFile."<init>":(Ljava/io/DataInputStream;)V
     139: astore        4
     141: aload         4
     143: invokevirtual #23                 // Method javassist/bytecode/ClassFile.getName:()Ljava/lang/String;
     146: aload_0
     147: getfield      #24                 // Field qualifiedName:Ljava/lang/String;
     150: invokevirtual #36                 // Method java/lang/String.equals:(Ljava/lang/Object;)Z
     153: ifne          223
     156: new           #69                 // class java/lang/RuntimeException
     159: dup
     160: new           #37                 // class java/lang/StringBuilder
     163: dup
     164: invokespecial #38                 // Method java/lang/StringBuilder."<init>":()V
     167: ldc           #76                 // String cannot find
     169: invokevirtual #40                 // Method java/lang/StringBuilder.append:(Ljava/lang/String;)Ljava/lang/StringBuilder;
     172: aload_0
     173: getfield      #24                 // Field qualifiedName:Ljava/lang/String;
     176: invokevirtual #40                 // Method java/lang/StringBuilder.append:(Ljava/lang/String;)Ljava/lang/StringBuilder;
     179: ldc           #77                 // String :
     181: invokevirtual #40                 // Method java/lang/StringBuilder.append:(Ljava/lang/String;)Ljava/lang/StringBuilder;
     184: aload         4
     186: invokevirtual #23                 // Method javassist/bytecode/ClassFile.getName:()Ljava/lang/String;
     189: invokevirtual #40                 // Method java/lang/StringBuilder.append:(Ljava/lang/String;)Ljava/lang/StringBuilder;
     192: ldc           #78                 // String  found in
     194: invokevirtual #40                 // Method java/lang/StringBuilder.append:(Ljava/lang/String;)Ljava/lang/StringBuilder;
     197: aload_0
     198: getfield      #24                 // Field qualifiedName:Ljava/lang/String;
     201: bipush        46
     203: bipush        47
     205: invokevirtual #79                 // Method java/lang/String.replace:(CC)Ljava/lang/String;
     208: invokevirtual #40                 // Method java/lang/StringBuilder.append:(Ljava/lang/String;)Ljava/lang/StringBuilder;
     211: ldc           #80                 // String .class
     213: invokevirtual #40                 // Method java/lang/StringBuilder.append:(Ljava/lang/String;)Ljava/lang/StringBuilder;
     216: invokevirtual #41                 // Method java/lang/StringBuilder.toString:()Ljava/lang/String;
     219: invokespecial #81                 // Method java/lang/RuntimeException."<init>":(Ljava/lang/String;)V
     222: athrow
     223: aload_0
     224: aload         4
     226: invokespecial #67                 // Method setClassFile:(Ljavassist/bytecode/ClassFile;)Ljavassist/bytecode/ClassFile;
     229: astore        5
     231: aload_3
     232: ifnull        244
     235: aload_3
     236: invokevirtual #82                 // Method java/io/InputStream.close:()V
     239: goto          244
     242: astore        6
     244: aload         5
     246: areturn
     247: astore        4
     249: new           #69                 // class java/lang/RuntimeException
     252: dup
     253: aload         4
     255: invokevirtual #83                 // Method javassist/NotFoundException.toString:()Ljava/lang/String;
     258: aload         4
     260: invokespecial #71                 // Method java/lang/RuntimeException."<init>":(Ljava/lang/String;Ljava/lang/Throwable;)V
     263: athrow
     264: astore        4
     266: new           #69                 // class java/lang/RuntimeException
     269: dup
     270: aload         4
     272: invokevirtual #70                 // Method java/io/IOException.toString:()Ljava/lang/String;
     275: aload         4
     277: invokespecial #71                 // Method java/lang/RuntimeException."<init>":(Ljava/lang/String;Ljava/lang/Throwable;)V
     280: athrow
     281: astore        7
     283: aload_3
     284: ifnull        296
     287: aload_3
     288: invokevirtual #82                 // Method java/io/InputStream.close:()V
     291: goto          296
     294: astore        8
     296: aload         7
     298: athrow
    Exception table:
       from    to  target type
          29    70    71   Class java/io/IOException
         235   239   242   Class java/io/IOException
          87   231   247   Class javassist/NotFoundException
          87   231   264   Class java/io/IOException
          87   231   281   any
         287   291   294   Class java/io/IOException
         247   283   281   any

  final void incGetCounter();
    Code:
       0: aload_0
       1: dup
       2: getfield      #16                 // Field getCount:I
       5: iconst_1
       6: iadd
       7: putfield      #16                 // Field getCount:I
      10: return

  void compress();
    Code:
       0: aload_0
       1: getfield      #16                 // Field getCount:I
       4: iconst_2
       5: if_icmpge     46
       8: aload_0
       9: invokevirtual #84                 // Method isModified:()Z
      12: ifne          28
      15: getstatic     #85                 // Field javassist/ClassPool.releaseUnmodifiedClassFile:Z
      18: ifeq          28
      21: aload_0
      22: invokespecial #86                 // Method removeClassFile:()V
      25: goto          46
      28: aload_0
      29: invokevirtual #87                 // Method isFrozen:()Z
      32: ifeq          46
      35: aload_0
      36: getfield      #6                  // Field wasPruned:Z
      39: ifne          46
      42: aload_0
      43: invokespecial #88                 // Method saveClassFile:()V
      46: aload_0
      47: iconst_0
      48: putfield      #16                 // Field getCount:I
      51: return

  private synchronized void saveClassFile();
    Code:
       0: aload_0
       1: getfield      #9                  // Field classfile:Ljavassist/bytecode/ClassFile;
       4: ifnull        14
       7: aload_0
       8: invokevirtual #89                 // Method hasMemberCache:()Ljavassist/CtMember$Cache;
      11: ifnull        15
      14: return
      15: new           #90                 // class java/io/ByteArrayOutputStream
      18: dup
      19: invokespecial #91                 // Method java/io/ByteArrayOutputStream."<init>":()V
      22: astore_1
      23: new           #92                 // class java/io/DataOutputStream
      26: dup
      27: aload_1
      28: invokespecial #93                 // Method java/io/DataOutputStream."<init>":(Ljava/io/OutputStream;)V
      31: astore_2
      32: aload_0
      33: getfield      #9                  // Field classfile:Ljavassist/bytecode/ClassFile;
      36: aload_2
      37: invokevirtual #94                 // Method javassist/bytecode/ClassFile.write:(Ljava/io/DataOutputStream;)V
      40: aload_1
      41: invokevirtual #95                 // Method java/io/ByteArrayOutputStream.close:()V
      44: aload_0
      45: aload_1
      46: invokevirtual #96                 // Method java/io/ByteArrayOutputStream.toByteArray:()[B
      49: putfield      #10                 // Field rawClassfile:[B
      52: aload_0
      53: aconst_null
      54: putfield      #9                  // Field classfile:Ljavassist/bytecode/ClassFile;
      57: goto          61
      60: astore_3
      61: return
    Exception table:
       from    to  target type
          32    57    60   Class java/io/IOException

  private synchronized void removeClassFile();
    Code:
       0: aload_0
       1: getfield      #9                  // Field classfile:Ljavassist/bytecode/ClassFile;
       4: ifnull        26
       7: aload_0
       8: invokevirtual #84                 // Method isModified:()Z
      11: ifne          26
      14: aload_0
      15: invokevirtual #89                 // Method hasMemberCache:()Ljavassist/CtMember$Cache;
      18: ifnonnull     26
      21: aload_0
      22: aconst_null
      23: putfield      #9                  // Field classfile:Ljavassist/bytecode/ClassFile;
      26: return

  private synchronized javassist.bytecode.ClassFile setClassFile(javassist.bytecode.ClassFile);
    Code:
       0: aload_0
       1: getfield      #9                  // Field classfile:Ljavassist/bytecode/ClassFile;
       4: ifnonnull     12
       7: aload_0
       8: aload_1
       9: putfield      #9                  // Field classfile:Ljavassist/bytecode/ClassFile;
      12: aload_0
      13: getfield      #9                  // Field classfile:Ljavassist/bytecode/ClassFile;
      16: areturn

  public javassist.ClassPool getClassPool();
    Code:
       0: aload_0
       1: getfield      #4                  // Field classPool:Ljavassist/ClassPool;
       4: areturn

  void setClassPool(javassist.ClassPool);
    Code:
       0: aload_0
       1: aload_1
       2: putfield      #4                  // Field classPool:Ljavassist/ClassPool;
       5: return

  public java.net.URL getURL() throws javassist.NotFoundException;
    Code:
       0: aload_0
       1: getfield      #4                  // Field classPool:Ljavassist/ClassPool;
       4: aload_0
       5: invokevirtual #32                 // Method getName:()Ljava/lang/String;
       8: invokevirtual #97                 // Method javassist/ClassPool.find:(Ljava/lang/String;)Ljava/net/URL;
      11: astore_1
      12: aload_1
      13: ifnonnull     28
      16: new           #42                 // class javassist/NotFoundException
      19: dup
      20: aload_0
      21: invokevirtual #32                 // Method getName:()Ljava/lang/String;
      24: invokespecial #73                 // Method javassist/NotFoundException."<init>":(Ljava/lang/String;)V
      27: athrow
      28: aload_1
      29: areturn

  public boolean isModified();
    Code:
       0: aload_0
       1: getfield      #8                  // Field wasChanged:Z
       4: ireturn

  public boolean isFrozen();
    Code:
       0: aload_0
       1: getfield      #7                  // Field wasFrozen:Z
       4: ireturn

  public void freeze();
    Code:
       0: aload_0
       1: iconst_1
       2: putfield      #7                  // Field wasFrozen:Z
       5: return

  void checkModify() throws java.lang.RuntimeException;
    Code:
       0: aload_0
       1: invokevirtual #87                 // Method isFrozen:()Z
       4: ifeq          66
       7: new           #37                 // class java/lang/StringBuilder
      10: dup
      11: invokespecial #38                 // Method java/lang/StringBuilder."<init>":()V
      14: aload_0
      15: invokevirtual #32                 // Method getName:()Ljava/lang/String;
      18: invokevirtual #40                 // Method java/lang/StringBuilder.append:(Ljava/lang/String;)Ljava/lang/StringBuilder;
      21: ldc           #98                 // String  class is frozen
      23: invokevirtual #40                 // Method java/lang/StringBuilder.append:(Ljava/lang/String;)Ljava/lang/StringBuilder;
      26: invokevirtual #41                 // Method java/lang/StringBuilder.toString:()Ljava/lang/String;
      29: astore_1
      30: aload_0
      31: getfield      #6                  // Field wasPruned:Z
      34: ifeq          57
      37: new           #37                 // class java/lang/StringBuilder
      40: dup
      41: invokespecial #38                 // Method java/lang/StringBuilder."<init>":()V
      44: aload_1
      45: invokevirtual #40                 // Method java/lang/StringBuilder.append:(Ljava/lang/String;)Ljava/lang/StringBuilder;
      48: ldc           #99                 // String  and pruned
      50: invokevirtual #40                 // Method java/lang/StringBuilder.append:(Ljava/lang/String;)Ljava/lang/StringBuilder;
      53: invokevirtual #41                 // Method java/lang/StringBuilder.toString:()Ljava/lang/String;
      56: astore_1
      57: new           #69                 // class java/lang/RuntimeException
      60: dup
      61: aload_1
      62: invokespecial #81                 // Method java/lang/RuntimeException."<init>":(Ljava/lang/String;)V
      65: athrow
      66: aload_0
      67: iconst_1
      68: putfield      #8                  // Field wasChanged:Z
      71: return

  public void defrost();
    Code:
       0: aload_0
       1: ldc           #100                // String defrost
       3: invokespecial #101                // Method checkPruned:(Ljava/lang/String;)V
       6: aload_0
       7: iconst_0
       8: putfield      #7                  // Field wasFrozen:Z
      11: return

  public boolean subtypeOf(javassist.CtClass) throws javassist.NotFoundException;
    Code:
       0: aload_1
       1: invokevirtual #34                 // Method javassist/CtClass.getName:()Ljava/lang/String;
       4: astore_3
       5: aload_0
       6: aload_1
       7: if_acmpeq     21
      10: aload_0
      11: invokevirtual #32                 // Method getName:()Ljava/lang/String;
      14: aload_3
      15: invokevirtual #36                 // Method java/lang/String.equals:(Ljava/lang/Object;)Z
      18: ifeq          23
      21: iconst_1
      22: ireturn
      23: aload_0
      24: invokevirtual #102                // Method getClassFile2:()Ljavassist/bytecode/ClassFile;
      27: astore        4
      29: aload         4
      31: invokevirtual #103                // Method javassist/bytecode/ClassFile.getSuperclass:()Ljava/lang/String;
      34: astore        5
      36: aload         5
      38: ifnull        52
      41: aload         5
      43: aload_3
      44: invokevirtual #36                 // Method java/lang/String.equals:(Ljava/lang/Object;)Z
      47: ifeq          52
      50: iconst_1
      51: ireturn
      52: aload         4
      54: invokevirtual #104                // Method javassist/bytecode/ClassFile.getInterfaces:()[Ljava/lang/String;
      57: astore        6
      59: aload         6
      61: arraylength
      62: istore        7
      64: iconst_0
      65: istore_2
      66: iload_2
      67: iload         7
      69: if_icmpge     91
      72: aload         6
      74: iload_2
      75: aaload
      76: aload_3
      77: invokevirtual #36                 // Method java/lang/String.equals:(Ljava/lang/Object;)Z
      80: ifeq          85
      83: iconst_1
      84: ireturn
      85: iinc          2, 1
      88: goto          66
      91: aload         5
      93: ifnull        114
      96: aload_0
      97: getfield      #4                  // Field classPool:Ljavassist/ClassPool;
     100: aload         5
     102: invokevirtual #105                // Method javassist/ClassPool.get:(Ljava/lang/String;)Ljavassist/CtClass;
     105: aload_1
     106: invokevirtual #106                // Method javassist/CtClass.subtypeOf:(Ljavassist/CtClass;)Z
     109: ifeq          114
     112: iconst_1
     113: ireturn
     114: iconst_0
     115: istore_2
     116: iload_2
     117: iload         7
     119: if_icmpge     148
     122: aload_0
     123: getfield      #4                  // Field classPool:Ljavassist/ClassPool;
     126: aload         6
     128: iload_2
     129: aaload
     130: invokevirtual #105                // Method javassist/ClassPool.get:(Ljava/lang/String;)Ljavassist/CtClass;
     133: aload_1
     134: invokevirtual #106                // Method javassist/CtClass.subtypeOf:(Ljavassist/CtClass;)Z
     137: ifeq          142
     140: iconst_1
     141: ireturn
     142: iinc          2, 1
     145: goto          116
     148: iconst_0
     149: ireturn

  public void setName(java.lang.String) throws java.lang.RuntimeException;
    Code:
       0: aload_0
       1: invokevirtual #32                 // Method getName:()Ljava/lang/String;
       4: astore_2
       5: aload_1
       6: aload_2
       7: invokevirtual #36                 // Method java/lang/String.equals:(Ljava/lang/Object;)Z
      10: ifeq          14
      13: return
      14: aload_0
      15: getfield      #4                  // Field classPool:Ljavassist/ClassPool;
      18: aload_1
      19: invokevirtual #107                // Method javassist/ClassPool.checkNotFrozen:(Ljava/lang/String;)V
      22: aload_0
      23: invokevirtual #102                // Method getClassFile2:()Ljavassist/bytecode/ClassFile;
      26: astore_3
      27: aload_0
      28: aload_1
      29: invokespecial #108                // Method javassist/CtClass.setName:(Ljava/lang/String;)V
      32: aload_3
      33: aload_1
      34: invokevirtual #109                // Method javassist/bytecode/ClassFile.setName:(Ljava/lang/String;)V
      37: aload_0
      38: invokespecial #110                // Method nameReplaced:()V
      41: aload_0
      42: getfield      #4                  // Field classPool:Ljavassist/ClassPool;
      45: aload_2
      46: aload_0
      47: invokevirtual #111                // Method javassist/ClassPool.classNameChanged:(Ljava/lang/String;Ljavassist/CtClass;)V
      50: return

  public java.lang.String getGenericSignature();
    Code:
       0: aload_0
       1: invokevirtual #102                // Method getClassFile2:()Ljavassist/bytecode/ClassFile;
       4: ldc           #113                // String Signature
       6: invokevirtual #114                // Method javassist/bytecode/ClassFile.getAttribute:(Ljava/lang/String;)Ljavassist/bytecode/AttributeInfo;
       9: checkcast     #112                // class javassist/bytecode/SignatureAttribute
      12: astore_1
      13: aload_1
      14: ifnonnull     21
      17: aconst_null
      18: goto          25
      21: aload_1
      22: invokevirtual #115                // Method javassist/bytecode/SignatureAttribute.getSignature:()Ljava/lang/String;
      25: areturn

  public void setGenericSignature(java.lang.String);
    Code:
       0: aload_0
       1: invokevirtual #116                // Method getClassFile:()Ljavassist/bytecode/ClassFile;
       4: astore_2
       5: new           #112                // class javassist/bytecode/SignatureAttribute
       8: dup
       9: aload_2
      10: invokevirtual #117                // Method javassist/bytecode/ClassFile.getConstPool:()Ljavassist/bytecode/ConstPool;
      13: aload_1
      14: invokespecial #118                // Method javassist/bytecode/SignatureAttribute."<init>":(Ljavassist/bytecode/ConstPool;Ljava/lang/String;)V
      17: astore_3
      18: aload_2
      19: aload_3
      20: invokevirtual #119                // Method javassist/bytecode/ClassFile.addAttribute:(Ljavassist/bytecode/AttributeInfo;)V
      23: return

  public void replaceClassName(javassist.ClassMap) throws java.lang.RuntimeException;
    Code:
       0: aload_0
       1: invokevirtual #32                 // Method getName:()Ljava/lang/String;
       4: astore_2
       5: aload_1
       6: aload_2
       7: invokestatic  #120                // Method javassist/bytecode/Descriptor.toJvmName:(Ljava/lang/String;)Ljava/lang/String;
      10: invokevirtual #121                // Method javassist/ClassMap.get:(Ljava/lang/Object;)Ljava/lang/String;
      13: astore_3
      14: aload_3
      15: ifnull        31
      18: aload_3
      19: invokestatic  #122                // Method javassist/bytecode/Descriptor.toJavaName:(Ljava/lang/String;)Ljava/lang/String;
      22: astore_3
      23: aload_0
      24: getfield      #4                  // Field classPool:Ljavassist/ClassPool;
      27: aload_3
      28: invokevirtual #107                // Method javassist/ClassPool.checkNotFrozen:(Ljava/lang/String;)V
      31: aload_0
      32: aload_1
      33: invokespecial #123                // Method javassist/CtClass.replaceClassName:(Ljavassist/ClassMap;)V
      36: aload_0
      37: invokevirtual #102                // Method getClassFile2:()Ljavassist/bytecode/ClassFile;
      40: astore        4
      42: aload         4
      44: aload_1
      45: invokevirtual #124                // Method javassist/bytecode/ClassFile.renameClass:(Ljava/util/Map;)V
      48: aload_0
      49: invokespecial #110                // Method nameReplaced:()V
      52: aload_3
      53: ifnull        70
      56: aload_0
      57: aload_3
      58: invokespecial #108                // Method javassist/CtClass.setName:(Ljava/lang/String;)V
      61: aload_0
      62: getfield      #4                  // Field classPool:Ljavassist/ClassPool;
      65: aload_2
      66: aload_0
      67: invokevirtual #111                // Method javassist/ClassPool.classNameChanged:(Ljava/lang/String;Ljavassist/CtClass;)V
      70: return

  public void replaceClassName(java.lang.String, java.lang.String) throws java.lang.RuntimeException;
    Code:
       0: aload_0
       1: invokevirtual #32                 // Method getName:()Ljava/lang/String;
       4: astore_3
       5: aload_3
       6: aload_1
       7: invokevirtual #36                 // Method java/lang/String.equals:(Ljava/lang/Object;)Z
      10: ifeq          21
      13: aload_0
      14: aload_2
      15: invokevirtual #125                // Method setName:(Ljava/lang/String;)V
      18: goto          40
      21: aload_0
      22: aload_1
      23: aload_2
      24: invokespecial #126                // Method javassist/CtClass.replaceClassName:(Ljava/lang/String;Ljava/lang/String;)V
      27: aload_0
      28: invokevirtual #102                // Method getClassFile2:()Ljavassist/bytecode/ClassFile;
      31: aload_1
      32: aload_2
      33: invokevirtual #127                // Method javassist/bytecode/ClassFile.renameClass:(Ljava/lang/String;Ljava/lang/String;)V
      36: aload_0
      37: invokespecial #110                // Method nameReplaced:()V
      40: return

  public boolean isInterface();
    Code:
       0: aload_0
       1: invokevirtual #29                 // Method getModifiers:()I
       4: invokestatic  #128                // Method javassist/Modifier.isInterface:(I)Z
       7: ireturn

  public boolean isAnnotation();
    Code:
       0: aload_0
       1: invokevirtual #29                 // Method getModifiers:()I
       4: invokestatic  #129                // Method javassist/Modifier.isAnnotation:(I)Z
       7: ireturn

  public boolean isEnum();
    Code:
       0: aload_0
       1: invokevirtual #29                 // Method getModifiers:()I
       4: invokestatic  #130                // Method javassist/Modifier.isEnum:(I)Z
       7: ireturn

  public int getModifiers();
    Code:
       0: aload_0
       1: invokevirtual #102                // Method getClassFile2:()Ljavassist/bytecode/ClassFile;
       4: astore_1
       5: aload_1
       6: invokevirtual #131                // Method javassist/bytecode/ClassFile.getAccessFlags:()I
       9: istore_2
      10: iload_2
      11: bipush        32
      13: invokestatic  #133                // Method javassist/bytecode/AccessFlag.clear:(II)I
      16: istore_2
      17: aload_1
      18: invokevirtual #134                // Method javassist/bytecode/ClassFile.getInnerAccessFlags:()I
      21: istore_3
      22: iload_3
      23: iconst_m1
      24: if_icmpeq     80
      27: iload_3
      28: bipush        8
      30: iand
      31: ifeq          39
      34: iload_2
      35: bipush        8
      37: ior
      38: istore_2
      39: iload_3
      40: iconst_1
      41: iand
      42: ifeq          52
      45: iload_2
      46: iconst_1
      47: ior
      48: istore_2
      49: goto          80
      52: iload_2
      53: bipush        -2
      55: iand
      56: istore_2
      57: iload_3
      58: iconst_4
      59: iand
      60: ifeq          70
      63: iload_2
      64: iconst_4
      65: ior
      66: istore_2
      67: goto          80
      70: iload_3
      71: iconst_2
      72: iand
      73: ifeq          80
      76: iload_2
      77: iconst_2
      78: ior
      79: istore_2
      80: iload_2
      81: invokestatic  #135                // Method javassist/bytecode/AccessFlag.toModifier:(I)I
      84: ireturn

  public javassist.CtClass[] getNestedClasses() throws javassist.NotFoundException;
    Code:
       0: aload_0
       1: invokevirtual #102                // Method getClassFile2:()Ljavassist/bytecode/ClassFile;
       4: astore_1
       5: aload_1
       6: ldc           #137                // String InnerClasses
       8: invokevirtual #114                // Method javassist/bytecode/ClassFile.getAttribute:(Ljava/lang/String;)Ljavassist/bytecode/AttributeInfo;
      11: checkcast     #136                // class javassist/bytecode/InnerClassesAttribute
      14: astore_2
      15: aload_2
      16: ifnonnull     24
      19: iconst_0
      20: anewarray     #138                // class javassist/CtClass
      23: areturn
      24: new           #37                 // class java/lang/StringBuilder
      27: dup
      28: invokespecial #38                 // Method java/lang/StringBuilder."<init>":()V
      31: aload_1
      32: invokevirtual #23                 // Method javassist/bytecode/ClassFile.getName:()Ljava/lang/String;
      35: invokevirtual #40                 // Method java/lang/StringBuilder.append:(Ljava/lang/String;)Ljava/lang/StringBuilder;
      38: ldc           #139                // String $
      40: invokevirtual #40                 // Method java/lang/StringBuilder.append:(Ljava/lang/String;)Ljava/lang/StringBuilder;
      43: invokevirtual #41                 // Method java/lang/StringBuilder.toString:()Ljava/lang/String;
      46: astore_3
      47: aload_2
      48: invokevirtual #140                // Method javassist/bytecode/InnerClassesAttribute.tableLength:()I
      51: istore        4
      53: new           #141                // class java/util/ArrayList
      56: dup
      57: iload         4
      59: invokespecial #142                // Method java/util/ArrayList."<init>":(I)V
      62: astore        5
      64: iconst_0
      65: istore        6
      67: iload         6
      69: iload         4
      71: if_icmpge     133
      74: aload_2
      75: iload         6
      77: invokevirtual #143                // Method javassist/bytecode/InnerClassesAttribute.innerClass:(I)Ljava/lang/String;
      80: astore        7
      82: aload         7
      84: ifnull        127
      87: aload         7
      89: aload_3
      90: invokevirtual #144                // Method java/lang/String.startsWith:(Ljava/lang/String;)Z
      93: ifeq          127
      96: aload         7
      98: bipush        36
     100: invokevirtual #145                // Method java/lang/String.lastIndexOf:(I)I
     103: aload_3
     104: invokevirtual #146                // Method java/lang/String.length:()I
     107: if_icmpge     127
     110: aload         5
     112: aload_0
     113: getfield      #4                  // Field classPool:Ljavassist/ClassPool;
     116: aload         7
     118: invokevirtual #105                // Method javassist/ClassPool.get:(Ljava/lang/String;)Ljavassist/CtClass;
     121: invokeinterface #147,  2          // InterfaceMethod java/util/List.add:(Ljava/lang/Object;)Z
     126: pop
     127: iinc          6, 1
     130: goto          67
     133: aload         5
     135: aload         5
     137: invokeinterface #148,  1          // InterfaceMethod java/util/List.size:()I
     142: anewarray     #138                // class javassist/CtClass
     145: invokeinterface #149,  2          // InterfaceMethod java/util/List.toArray:([Ljava/lang/Object;)[Ljava/lang/Object;
     150: checkcast     #150                // class "[Ljavassist/CtClass;"
     153: areturn

  public void setModifiers(int);
    Code:
       0: aload_0
       1: invokevirtual #151                // Method checkModify:()V
       4: iload_1
       5: aload_0
       6: invokevirtual #32                 // Method getName:()Ljava/lang/String;
       9: aload_0
      10: iconst_1
      11: invokestatic  #152                // Method updateInnerEntry:(ILjava/lang/String;Ljavassist/CtClass;Z)V
      14: aload_0
      15: invokevirtual #102                // Method getClassFile2:()Ljavassist/bytecode/ClassFile;
      18: astore_2
      19: aload_2
      20: iload_1
      21: bipush        -9
      23: iand
      24: invokestatic  #154                // Method javassist/bytecode/AccessFlag.of:(I)I
      27: invokevirtual #155                // Method javassist/bytecode/ClassFile.setAccessFlags:(I)V
      30: return

  private static void updateInnerEntry(int, java.lang.String, javassist.CtClass, boolean);
    Code:
       0: aload_2
       1: invokevirtual #156                // Method javassist/CtClass.getClassFile2:()Ljavassist/bytecode/ClassFile;
       4: astore        4
       6: aload         4
       8: ldc           #137                // String InnerClasses
      10: invokevirtual #114                // Method javassist/bytecode/ClassFile.getAttribute:(Ljava/lang/String;)Ljavassist/bytecode/AttributeInfo;
      13: checkcast     #136                // class javassist/bytecode/InnerClassesAttribute
      16: astore        5
      18: aload         5
      20: ifnull        157
      23: iload_0
      24: bipush        -9
      26: iand
      27: istore        6
      29: aload         5
      31: aload_1
      32: invokevirtual #157                // Method javassist/bytecode/InnerClassesAttribute.find:(Ljava/lang/String;)I
      35: istore        7
      37: iload         7
      39: iflt          157
      42: aload         5
      44: iload         7
      46: invokevirtual #158                // Method javassist/bytecode/InnerClassesAttribute.accessFlags:(I)I
      49: bipush        8
      51: iand
      52: istore        8
      54: iload         8
      56: ifne          66
      59: iload_0
      60: invokestatic  #159                // Method javassist/Modifier.isStatic:(I)Z
      63: ifne          157
      66: aload_2
      67: invokevirtual #160                // Method javassist/CtClass.checkModify:()V
      70: aload         5
      72: iload         7
      74: iload         6
      76: invokestatic  #154                // Method javassist/bytecode/AccessFlag.of:(I)I
      79: iload         8
      81: ior
      82: invokevirtual #161                // Method javassist/bytecode/InnerClassesAttribute.setAccessFlags:(II)V
      85: aload         5
      87: iload         7
      89: invokevirtual #162                // Method javassist/bytecode/InnerClassesAttribute.outerClass:(I)Ljava/lang/String;
      92: astore        9
      94: aload         9
      96: ifnull        156
      99: iload_3
     100: ifeq          156
     103: aload_2
     104: invokevirtual #163                // Method javassist/CtClass.getClassPool:()Ljavassist/ClassPool;
     107: aload         9
     109: invokevirtual #105                // Method javassist/ClassPool.get:(Ljava/lang/String;)Ljavassist/CtClass;
     112: astore        10
     114: iload         6
     116: aload_1
     117: aload         10
     119: iconst_0
     120: invokestatic  #152                // Method updateInnerEntry:(ILjava/lang/String;Ljavassist/CtClass;Z)V
     123: goto          156
     126: astore        10
     128: new           #69                 // class java/lang/RuntimeException
     131: dup
     132: new           #37                 // class java/lang/StringBuilder
     135: dup
     136: invokespecial #38                 // Method java/lang/StringBuilder."<init>":()V
     139: ldc           #164                // String cannot find the declaring class:
     141: invokevirtual #40                 // Method java/lang/StringBuilder.append:(Ljava/lang/String;)Ljava/lang/StringBuilder;
     144: aload         9
     146: invokevirtual #40                 // Method java/lang/StringBuilder.append:(Ljava/lang/String;)Ljava/lang/StringBuilder;
     149: invokevirtual #41                 // Method java/lang/StringBuilder.toString:()Ljava/lang/String;
     152: invokespecial #81                 // Method java/lang/RuntimeException."<init>":(Ljava/lang/String;)V
     155: athrow
     156: return
     157: iload_0
     158: invokestatic  #159                // Method javassist/Modifier.isStatic:(I)Z
     161: ifeq          199
     164: new           #69                 // class java/lang/RuntimeException
     167: dup
     168: new           #37                 // class java/lang/StringBuilder
     171: dup
     172: invokespecial #38                 // Method java/lang/StringBuilder."<init>":()V
     175: ldc           #165                // String cannot change
     177: invokevirtual #40                 // Method java/lang/StringBuilder.append:(Ljava/lang/String;)Ljava/lang/StringBuilder;
     180: aload_1
     181: invokestatic  #122                // Method javassist/bytecode/Descriptor.toJavaName:(Ljava/lang/String;)Ljava/lang/String;
     184: invokevirtual #40                 // Method java/lang/StringBuilder.append:(Ljava/lang/String;)Ljava/lang/StringBuilder;
     187: ldc           #166                // String  into a static class
     189: invokevirtual #40                 // Method java/lang/StringBuilder.append:(Ljava/lang/String;)Ljava/lang/StringBuilder;
     192: invokevirtual #41                 // Method java/lang/StringBuilder.toString:()Ljava/lang/String;
     195: invokespecial #81                 // Method java/lang/RuntimeException."<init>":(Ljava/lang/String;)V
     198: athrow
     199: return
    Exception table:
       from    to  target type
         103   123   126   Class javassist/NotFoundException

  public boolean hasAnnotation(java.lang.String);
    Code:
       0: aload_0
       1: invokevirtual #102                // Method getClassFile2:()Ljavassist/bytecode/ClassFile;
       4: astore_2
       5: aload_2
       6: ldc           #168                // String RuntimeInvisibleAnnotations
       8: invokevirtual #114                // Method javassist/bytecode/ClassFile.getAttribute:(Ljava/lang/String;)Ljavassist/bytecode/AttributeInfo;
      11: checkcast     #167                // class javassist/bytecode/AnnotationsAttribute
      14: astore_3
      15: aload_2
      16: ldc           #169                // String RuntimeVisibleAnnotations
      18: invokevirtual #114                // Method javassist/bytecode/ClassFile.getAttribute:(Ljava/lang/String;)Ljavassist/bytecode/AttributeInfo;
      21: checkcast     #167                // class javassist/bytecode/AnnotationsAttribute
      24: astore        4
      26: aload_1
      27: aload_0
      28: invokevirtual #170                // Method getClassPool:()Ljavassist/ClassPool;
      31: aload_3
      32: aload         4
      34: invokestatic  #171                // Method hasAnnotationType:(Ljava/lang/String;Ljavassist/ClassPool;Ljavassist/bytecode/AnnotationsAttribute;Ljavassist/bytecode/AnnotationsAttribute;)Z
      37: ireturn

  static boolean hasAnnotationType(java.lang.Class<?>, javassist.ClassPool, javassist.bytecode.AnnotationsAttribute, javassist.bytecode.AnnotationsAttribute);
    Code:
       0: aload_0
       1: invokevirtual #172                // Method java/lang/Class.getName:()Ljava/lang/String;
       4: aload_1
       5: aload_2
       6: aload_3
       7: invokestatic  #171                // Method hasAnnotationType:(Ljava/lang/String;Ljavassist/ClassPool;Ljavassist/bytecode/AnnotationsAttribute;Ljavassist/bytecode/AnnotationsAttribute;)Z
      10: ireturn

  static boolean hasAnnotationType(java.lang.String, javassist.ClassPool, javassist.bytecode.AnnotationsAttribute, javassist.bytecode.AnnotationsAttribute);
    Code:
       0: aload_2
       1: ifnonnull     10
       4: aconst_null
       5: astore        4
       7: goto          16
      10: aload_2
      11: invokevirtual #173                // Method javassist/bytecode/AnnotationsAttribute.getAnnotations:()[Ljavassist/bytecode/annotation/Annotation;
      14: astore        4
      16: aload_3
      17: ifnonnull     26
      20: aconst_null
      21: astore        5
      23: goto          32
      26: aload_3
      27: invokevirtual #173                // Method javassist/bytecode/AnnotationsAttribute.getAnnotations:()[Ljavassist/bytecode/annotation/Annotation;
      30: astore        5
      32: aload         4
      34: ifnull        71
      37: iconst_0
      38: istore        6
      40: iload         6
      42: aload         4
      44: arraylength
      45: if_icmpge     71
      48: aload         4
      50: iload         6
      52: aaload
      53: invokevirtual #174                // Method javassist/bytecode/annotation/Annotation.getTypeName:()Ljava/lang/String;
      56: aload_0
      57: invokevirtual #36                 // Method java/lang/String.equals:(Ljava/lang/Object;)Z
      60: ifeq          65
      63: iconst_1
      64: ireturn
      65: iinc          6, 1
      68: goto          40
      71: aload         5
      73: ifnull        110
      76: iconst_0
      77: istore        6
      79: iload         6
      81: aload         5
      83: arraylength
      84: if_icmpge     110
      87: aload         5
      89: iload         6
      91: aaload
      92: invokevirtual #174                // Method javassist/bytecode/annotation/Annotation.getTypeName:()Ljava/lang/String;
      95: aload_0
      96: invokevirtual #36                 // Method java/lang/String.equals:(Ljava/lang/Object;)Z
      99: ifeq          104
     102: iconst_1
     103: ireturn
     104: iinc          6, 1
     107: goto          79
     110: iconst_0
     111: ireturn

  public java.lang.Object getAnnotation(java.lang.Class<?>) throws java.lang.ClassNotFoundException;
    Code:
       0: aload_0
       1: invokevirtual #102                // Method getClassFile2:()Ljavassist/bytecode/ClassFile;
       4: astore_2
       5: aload_2
       6: ldc           #168                // String RuntimeInvisibleAnnotations
       8: invokevirtual #114                // Method javassist/bytecode/ClassFile.getAttribute:(Ljava/lang/String;)Ljavassist/bytecode/AttributeInfo;
      11: checkcast     #167                // class javassist/bytecode/AnnotationsAttribute
      14: astore_3
      15: aload_2
      16: ldc           #169                // String RuntimeVisibleAnnotations
      18: invokevirtual #114                // Method javassist/bytecode/ClassFile.getAttribute:(Ljava/lang/String;)Ljavassist/bytecode/AttributeInfo;
      21: checkcast     #167                // class javassist/bytecode/AnnotationsAttribute
      24: astore        4
      26: aload_1
      27: aload_0
      28: invokevirtual #170                // Method getClassPool:()Ljavassist/ClassPool;
      31: aload_3
      32: aload         4
      34: invokestatic  #175                // Method getAnnotationType:(Ljava/lang/Class;Ljavassist/ClassPool;Ljavassist/bytecode/AnnotationsAttribute;Ljavassist/bytecode/AnnotationsAttribute;)Ljava/lang/Object;
      37: areturn

  static java.lang.Object getAnnotationType(java.lang.Class<?>, javassist.ClassPool, javassist.bytecode.AnnotationsAttribute, javassist.bytecode.AnnotationsAttribute) throws java.lang.ClassNotFoundException;
    Code:
       0: aload_2
       1: ifnonnull     10
       4: aconst_null
       5: astore        4
       7: goto          16
      10: aload_2
      11: invokevirtual #173                // Method javassist/bytecode/AnnotationsAttribute.getAnnotations:()[Ljavassist/bytecode/annotation/Annotation;
      14: astore        4
      16: aload_3
      17: ifnonnull     26
      20: aconst_null
      21: astore        5
      23: goto          32
      26: aload_3
      27: invokevirtual #173                // Method javassist/bytecode/AnnotationsAttribute.getAnnotations:()[Ljavassist/bytecode/annotation/Annotation;
      30: astore        5
      32: aload_0
      33: invokevirtual #172                // Method java/lang/Class.getName:()Ljava/lang/String;
      36: astore        6
      38: aload         4
      40: ifnull        86
      43: iconst_0
      44: istore        7
      46: iload         7
      48: aload         4
      50: arraylength
      51: if_icmpge     86
      54: aload         4
      56: iload         7
      58: aaload
      59: invokevirtual #174                // Method javassist/bytecode/annotation/Annotation.getTypeName:()Ljava/lang/String;
      62: aload         6
      64: invokevirtual #36                 // Method java/lang/String.equals:(Ljava/lang/Object;)Z
      67: ifeq          80
      70: aload         4
      72: iload         7
      74: aaload
      75: aload_1
      76: invokestatic  #176                // Method toAnnoType:(Ljavassist/bytecode/annotation/Annotation;Ljavassist/ClassPool;)Ljava/lang/Object;
      79: areturn
      80: iinc          7, 1
      83: goto          46
      86: aload         5
      88: ifnull        134
      91: iconst_0
      92: istore        7
      94: iload         7
      96: aload         5
      98: arraylength
      99: if_icmpge     134
     102: aload         5
     104: iload         7
     106: aaload
     107: invokevirtual #174                // Method javassist/bytecode/annotation/Annotation.getTypeName:()Ljava/lang/String;
     110: aload         6
     112: invokevirtual #36                 // Method java/lang/String.equals:(Ljava/lang/Object;)Z
     115: ifeq          128
     118: aload         5
     120: iload         7
     122: aaload
     123: aload_1
     124: invokestatic  #176                // Method toAnnoType:(Ljavassist/bytecode/annotation/Annotation;Ljavassist/ClassPool;)Ljava/lang/Object;
     127: areturn
     128: iinc          7, 1
     131: goto          94
     134: aconst_null
     135: areturn

  public java.lang.Object[] getAnnotations() throws java.lang.ClassNotFoundException;
    Code:
       0: aload_0
       1: iconst_0
       2: invokespecial #177                // Method getAnnotations:(Z)[Ljava/lang/Object;
       5: areturn

  public java.lang.Object[] getAvailableAnnotations();
    Code:
       0: aload_0
       1: iconst_1
       2: invokespecial #177                // Method getAnnotations:(Z)[Ljava/lang/Object;
       5: areturn
       6: astore_1
       7: new           #69                 // class java/lang/RuntimeException
      10: dup
      11: ldc           #179                // String Unexpected exception
      13: aload_1
      14: invokespecial #71                 // Method java/lang/RuntimeException."<init>":(Ljava/lang/String;Ljava/lang/Throwable;)V
      17: athrow
    Exception table:
       from    to  target type
           0     5     6   Class java/lang/ClassNotFoundException

  private java.lang.Object[] getAnnotations(boolean) throws java.lang.ClassNotFoundException;
    Code:
       0: aload_0
       1: invokevirtual #102                // Method getClassFile2:()Ljavassist/bytecode/ClassFile;
       4: astore_2
       5: aload_2
       6: ldc           #168                // String RuntimeInvisibleAnnotations
       8: invokevirtual #114                // Method javassist/bytecode/ClassFile.getAttribute:(Ljava/lang/String;)Ljavassist/bytecode/AttributeInfo;
      11: checkcast     #167                // class javassist/bytecode/AnnotationsAttribute
      14: astore_3
      15: aload_2
      16: ldc           #169                // String RuntimeVisibleAnnotations
      18: invokevirtual #114                // Method javassist/bytecode/ClassFile.getAttribute:(Ljava/lang/String;)Ljavassist/bytecode/AttributeInfo;
      21: checkcast     #167                // class javassist/bytecode/AnnotationsAttribute
      24: astore        4
      26: iload_1
      27: aload_0
      28: invokevirtual #170                // Method getClassPool:()Ljavassist/ClassPool;
      31: aload_3
      32: aload         4
      34: invokestatic  #180                // Method toAnnotationType:(ZLjavassist/ClassPool;Ljavassist/bytecode/AnnotationsAttribute;Ljavassist/bytecode/AnnotationsAttribute;)[Ljava/lang/Object;
      37: areturn

  static java.lang.Object[] toAnnotationType(boolean, javassist.ClassPool, javassist.bytecode.AnnotationsAttribute, javassist.bytecode.AnnotationsAttribute) throws java.lang.ClassNotFoundException;
    Code:
       0: aload_2
       1: ifnonnull     13
       4: aconst_null
       5: astore        4
       7: iconst_0
       8: istore        6
      10: goto          24
      13: aload_2
      14: invokevirtual #173                // Method javassist/bytecode/AnnotationsAttribute.getAnnotations:()[Ljavassist/bytecode/annotation/Annotation;
      17: astore        4
      19: aload         4
      21: arraylength
      22: istore        6
      24: aload_3
      25: ifnonnull     37
      28: aconst_null
      29: astore        5
      31: iconst_0
      32: istore        7
      34: goto          48
      37: aload_3
      38: invokevirtual #173                // Method javassist/bytecode/AnnotationsAttribute.getAnnotations:()[Ljavassist/bytecode/annotation/Annotation;
      41: astore        5
      43: aload         5
      45: arraylength
      46: istore        7
      48: iload_0
      49: ifne          128
      52: iload         6
      54: iload         7
      56: iadd
      57: anewarray     #181                // class java/lang/Object
      60: astore        8
      62: iconst_0
      63: istore        9
      65: iload         9
      67: iload         6
      69: if_icmpge     92
      72: aload         8
      74: iload         9
      76: aload         4
      78: iload         9
      80: aaload
      81: aload_1
      82: invokestatic  #176                // Method toAnnoType:(Ljavassist/bytecode/annotation/Annotation;Ljavassist/ClassPool;)Ljava/lang/Object;
      85: aastore
      86: iinc          9, 1
      89: goto          65
      92: iconst_0
      93: istore        9
      95: iload         9
      97: iload         7
      99: if_icmpge     125
     102: aload         8
     104: iload         9
     106: iload         6
     108: iadd
     109: aload         5
     111: iload         9
     113: aaload
     114: aload_1
     115: invokestatic  #176                // Method toAnnoType:(Ljavassist/bytecode/annotation/Annotation;Ljavassist/ClassPool;)Ljava/lang/Object;
     118: aastore
     119: iinc          9, 1
     122: goto          95
     125: aload         8
     127: areturn
     128: new           #141                // class java/util/ArrayList
     131: dup
     132: invokespecial #182                // Method java/util/ArrayList."<init>":()V
     135: astore        8
     137: iconst_0
     138: istore        9
     140: iload         9
     142: iload         6
     144: if_icmpge     175
     147: aload         8
     149: aload         4
     151: iload         9
     153: aaload
     154: aload_1
     155: invokestatic  #176                // Method toAnnoType:(Ljavassist/bytecode/annotation/Annotation;Ljavassist/ClassPool;)Ljava/lang/Object;
     158: invokeinterface #147,  2          // InterfaceMethod java/util/List.add:(Ljava/lang/Object;)Z
     163: pop
     164: goto          169
     167: astore        10
     169: iinc          9, 1
     172: goto          140
     175: iconst_0
     176: istore        9
     178: iload         9
     180: iload         7
     182: if_icmpge     213
     185: aload         8
     187: aload         5
     189: iload         9
     191: aaload
     192: aload_1
     193: invokestatic  #176                // Method toAnnoType:(Ljavassist/bytecode/annotation/Annotation;Ljavassist/ClassPool;)Ljava/lang/Object;
     196: invokeinterface #147,  2          // InterfaceMethod java/util/List.add:(Ljava/lang/Object;)Z
     201: pop
     202: goto          207
     205: astore        10
     207: iinc          9, 1
     210: goto          178
     213: aload         8
     215: invokeinterface #183,  1          // InterfaceMethod java/util/List.toArray:()[Ljava/lang/Object;
     220: areturn
    Exception table:
       from    to  target type
         147   164   167   Class java/lang/ClassNotFoundException
         185   202   205   Class java/lang/ClassNotFoundException

  static java.lang.Object[][] toAnnotationType(boolean, javassist.ClassPool, javassist.bytecode.ParameterAnnotationsAttribute, javassist.bytecode.ParameterAnnotationsAttribute, javassist.bytecode.MethodInfo) throws java.lang.ClassNotFoundException;
    Code:
       0: iconst_0
       1: istore        5
       3: aload_2
       4: ifnull        16
       7: aload_2
       8: invokevirtual #184                // Method javassist/bytecode/ParameterAnnotationsAttribute.numParameters:()I
      11: istore        5
      13: goto          39
      16: aload_3
      17: ifnull        29
      20: aload_3
      21: invokevirtual #184                // Method javassist/bytecode/ParameterAnnotationsAttribute.numParameters:()I
      24: istore        5
      26: goto          39
      29: aload         4
      31: invokevirtual #185                // Method javassist/bytecode/MethodInfo.getDescriptor:()Ljava/lang/String;
      34: invokestatic  #186                // Method javassist/bytecode/Descriptor.numOfParameters:(Ljava/lang/String;)I
      37: istore        5
      39: iload         5
      41: anewarray     #187                // class "[Ljava/lang/Object;"
      44: astore        6
      46: iconst_0
      47: istore        7
      49: iload         7
      51: iload         5
      53: if_icmpge     302
      56: aload_2
      57: ifnonnull     69
      60: aconst_null
      61: astore        8
      63: iconst_0
      64: istore        10
      66: goto          83
      69: aload_2
      70: invokevirtual #188                // Method javassist/bytecode/ParameterAnnotationsAttribute.getAnnotations:()[[Ljavassist/bytecode/annotation/Annotation;
      73: iload         7
      75: aaload
      76: astore        8
      78: aload         8
      80: arraylength
      81: istore        10
      83: aload_3
      84: ifnonnull     96
      87: aconst_null
      88: astore        9
      90: iconst_0
      91: istore        11
      93: goto          110
      96: aload_3
      97: invokevirtual #188                // Method javassist/bytecode/ParameterAnnotationsAttribute.getAnnotations:()[[Ljavassist/bytecode/annotation/Annotation;
     100: iload         7
     102: aaload
     103: astore        9
     105: aload         9
     107: arraylength
     108: istore        11
     110: iload_0
     111: ifne          199
     114: aload         6
     116: iload         7
     118: iload         10
     120: iload         11
     122: iadd
     123: anewarray     #181                // class java/lang/Object
     126: aastore
     127: iconst_0
     128: istore        12
     130: iload         12
     132: iload         10
     134: if_icmpge     160
     137: aload         6
     139: iload         7
     141: aaload
     142: iload         12
     144: aload         8
     146: iload         12
     148: aaload
     149: aload_1
     150: invokestatic  #176                // Method toAnnoType:(Ljavassist/bytecode/annotation/Annotation;Ljavassist/ClassPool;)Ljava/lang/Object;
     153: aastore
     154: iinc          12, 1
     157: goto          130
     160: iconst_0
     161: istore        12
     163: iload         12
     165: iload         11
     167: if_icmpge     196
     170: aload         6
     172: iload         7
     174: aaload
     175: iload         12
     177: iload         10
     179: iadd
     180: aload         9
     182: iload         12
     184: aaload
     185: aload_1
     186: invokestatic  #176                // Method toAnnoType:(Ljavassist/bytecode/annotation/Annotation;Ljavassist/ClassPool;)Ljava/lang/Object;
     189: aastore
     190: iinc          12, 1
     193: goto          163
     196: goto          296
     199: new           #141                // class java/util/ArrayList
     202: dup
     203: invokespecial #182                // Method java/util/ArrayList."<init>":()V
     206: astore        12
     208: iconst_0
     209: istore        13
     211: iload         13
     213: iload         10
     215: if_icmpge     246
     218: aload         12
     220: aload         8
     222: iload         13
     224: aaload
     225: aload_1
     226: invokestatic  #176                // Method toAnnoType:(Ljavassist/bytecode/annotation/Annotation;Ljavassist/ClassPool;)Ljava/lang/Object;
     229: invokeinterface #147,  2          // InterfaceMethod java/util/List.add:(Ljava/lang/Object;)Z
     234: pop
     235: goto          240
     238: astore        14
     240: iinc          13, 1
     243: goto          211
     246: iconst_0
     247: istore        13
     249: iload         13
     251: iload         11
     253: if_icmpge     284
     256: aload         12
     258: aload         9
     260: iload         13
     262: aaload
     263: aload_1
     264: invokestatic  #176                // Method toAnnoType:(Ljavassist/bytecode/annotation/Annotation;Ljavassist/ClassPool;)Ljava/lang/Object;
     267: invokeinterface #147,  2          // InterfaceMethod java/util/List.add:(Ljava/lang/Object;)Z
     272: pop
     273: goto          278
     276: astore        14
     278: iinc          13, 1
     281: goto          249
     284: aload         6
     286: iload         7
     288: aload         12
     290: invokeinterface #183,  1          // InterfaceMethod java/util/List.toArray:()[Ljava/lang/Object;
     295: aastore
     296: iinc          7, 1
     299: goto          49
     302: aload         6
     304: areturn
    Exception table:
       from    to  target type
         218   235   238   Class java/lang/ClassNotFoundException
         256   273   276   Class java/lang/ClassNotFoundException

  private static java.lang.Object toAnnoType(javassist.bytecode.annotation.Annotation, javassist.ClassPool) throws java.lang.ClassNotFoundException;
    Code:
       0: aload_1
       1: invokevirtual #189                // Method javassist/ClassPool.getClassLoader:()Ljava/lang/ClassLoader;
       4: astore_2
       5: aload_0
       6: aload_2
       7: aload_1
       8: invokevirtual #190                // Method javassist/bytecode/annotation/Annotation.toAnnotationType:(Ljava/lang/ClassLoader;Ljavassist/ClassPool;)Ljava/lang/Object;
      11: areturn
      12: astore_2
      13: aload_1
      14: invokevirtual #191                // Method java/lang/Object.getClass:()Ljava/lang/Class;
      17: invokevirtual #192                // Method java/lang/Class.getClassLoader:()Ljava/lang/ClassLoader;
      20: astore_3
      21: aload_0
      22: aload_3
      23: aload_1
      24: invokevirtual #190                // Method javassist/bytecode/annotation/Annotation.toAnnotationType:(Ljava/lang/ClassLoader;Ljavassist/ClassPool;)Ljava/lang/Object;
      27: areturn
      28: astore        4
      30: aload_1
      31: aload_0
      32: invokevirtual #174                // Method javassist/bytecode/annotation/Annotation.getTypeName:()Ljava/lang/String;
      35: invokevirtual #105                // Method javassist/ClassPool.get:(Ljava/lang/String;)Ljavassist/CtClass;
      38: invokevirtual #193                // Method javassist/CtClass.toClass:()Ljava/lang/Class;
      41: astore        5
      43: aload         5
      45: invokevirtual #192                // Method java/lang/Class.getClassLoader:()Ljava/lang/ClassLoader;
      48: aload         5
      50: aload_1
      51: aload_0
      52: invokestatic  #194                // Method javassist/bytecode/annotation/AnnotationImpl.make:(Ljava/lang/ClassLoader;Ljava/lang/Class;Ljavassist/ClassPool;Ljavassist/bytecode/annotation/Annotation;)Ljava/lang/Object;
      55: areturn
      56: astore        5
      58: new           #178                // class java/lang/ClassNotFoundException
      61: dup
      62: aload_0
      63: invokevirtual #174                // Method javassist/bytecode/annotation/Annotation.getTypeName:()Ljava/lang/String;
      66: invokespecial #196                // Method java/lang/ClassNotFoundException."<init>":(Ljava/lang/String;)V
      69: athrow
    Exception table:
       from    to  target type
           0    11    12   Class java/lang/ClassNotFoundException
          21    27    28   Class java/lang/ClassNotFoundException
          30    55    56   Class java/lang/Throwable

  public boolean subclassOf(javassist.CtClass);
    Code:
       0: aload_1
       1: ifnonnull     6
       4: iconst_0
       5: ireturn
       6: aload_1
       7: invokevirtual #34                 // Method javassist/CtClass.getName:()Ljava/lang/String;
      10: astore_2
      11: aload_0
      12: astore_3
      13: aload_3
      14: ifnull        38
      17: aload_3
      18: invokevirtual #34                 // Method javassist/CtClass.getName:()Ljava/lang/String;
      21: aload_2
      22: invokevirtual #36                 // Method java/lang/String.equals:(Ljava/lang/Object;)Z
      25: ifeq          30
      28: iconst_1
      29: ireturn
      30: aload_3
      31: invokevirtual #197                // Method javassist/CtClass.getSuperclass:()Ljavassist/CtClass;
      34: astore_3
      35: goto          13
      38: goto          43
      41: astore        4
      43: iconst_0
      44: ireturn
    Exception table:
       from    to  target type
          13    29    41   Class java/lang/Exception
          30    38    41   Class java/lang/Exception

  public javassist.CtClass getSuperclass() throws javassist.NotFoundException;
    Code:
       0: aload_0
       1: invokevirtual #102                // Method getClassFile2:()Ljavassist/bytecode/ClassFile;
       4: invokevirtual #103                // Method javassist/bytecode/ClassFile.getSuperclass:()Ljava/lang/String;
       7: astore_1
       8: aload_1
       9: ifnonnull     14
      12: aconst_null
      13: areturn
      14: aload_0
      15: getfield      #4                  // Field classPool:Ljavassist/ClassPool;
      18: aload_1
      19: invokevirtual #105                // Method javassist/ClassPool.get:(Ljava/lang/String;)Ljavassist/CtClass;
      22: areturn

  public void setSuperclass(javassist.CtClass) throws javassist.CannotCompileException;
    Code:
       0: aload_0
       1: invokevirtual #151                // Method checkModify:()V
       4: aload_0
       5: invokevirtual #199                // Method isInterface:()Z
       8: ifeq          19
      11: aload_0
      12: aload_1
      13: invokevirtual #200                // Method addInterface:(Ljavassist/CtClass;)V
      16: goto          30
      19: aload_0
      20: invokevirtual #102                // Method getClassFile2:()Ljavassist/bytecode/ClassFile;
      23: aload_1
      24: invokevirtual #34                 // Method javassist/CtClass.getName:()Ljava/lang/String;
      27: invokevirtual #201                // Method javassist/bytecode/ClassFile.setSuperclass:(Ljava/lang/String;)V
      30: return

  public javassist.CtClass[] getInterfaces() throws javassist.NotFoundException;
    Code:
       0: aload_0
       1: invokevirtual #102                // Method getClassFile2:()Ljavassist/bytecode/ClassFile;
       4: invokevirtual #104                // Method javassist/bytecode/ClassFile.getInterfaces:()[Ljava/lang/String;
       7: astore_1
       8: aload_1
       9: arraylength
      10: istore_2
      11: iload_2
      12: anewarray     #138                // class javassist/CtClass
      15: astore_3
      16: iconst_0
      17: istore        4
      19: iload         4
      21: iload_2
      22: if_icmpge     46
      25: aload_3
      26: iload         4
      28: aload_0
      29: getfield      #4                  // Field classPool:Ljavassist/ClassPool;
      32: aload_1
      33: iload         4
      35: aaload
      36: invokevirtual #105                // Method javassist/ClassPool.get:(Ljava/lang/String;)Ljavassist/CtClass;
      39: aastore
      40: iinc          4, 1
      43: goto          19
      46: aload_3
      47: areturn

  public void setInterfaces(javassist.CtClass[]);
    Code:
       0: aload_0
       1: invokevirtual #151                // Method checkModify:()V
       4: aload_1
       5: ifnonnull     16
       8: iconst_0
       9: anewarray     #17                 // class java/lang/String
      12: astore_2
      13: goto          50
      16: aload_1
      17: arraylength
      18: istore_3
      19: iload_3
      20: anewarray     #17                 // class java/lang/String
      23: astore_2
      24: iconst_0
      25: istore        4
      27: iload         4
      29: iload_3
      30: if_icmpge     50
      33: aload_2
      34: iload         4
      36: aload_1
      37: iload         4
      39: aaload
      40: invokevirtual #34                 // Method javassist/CtClass.getName:()Ljava/lang/String;
      43: aastore
      44: iinc          4, 1
      47: goto          27
      50: aload_0
      51: invokevirtual #102                // Method getClassFile2:()Ljavassist/bytecode/ClassFile;
      54: aload_2
      55: invokevirtual #202                // Method javassist/bytecode/ClassFile.setInterfaces:([Ljava/lang/String;)V
      58: return

  public void addInterface(javassist.CtClass);
    Code:
       0: aload_0
       1: invokevirtual #151                // Method checkModify:()V
       4: aload_1
       5: ifnull        19
       8: aload_0
       9: invokevirtual #102                // Method getClassFile2:()Ljavassist/bytecode/ClassFile;
      12: aload_1
      13: invokevirtual #34                 // Method javassist/CtClass.getName:()Ljava/lang/String;
      16: invokevirtual #203                // Method javassist/bytecode/ClassFile.addInterface:(Ljava/lang/String;)V
      19: return

  public javassist.CtClass getDeclaringClass() throws javassist.NotFoundException;
    Code:
       0: aload_0
       1: invokevirtual #102                // Method getClassFile2:()Ljavassist/bytecode/ClassFile;
       4: astore_1
       5: aload_1
       6: ldc           #137                // String InnerClasses
       8: invokevirtual #114                // Method javassist/bytecode/ClassFile.getAttribute:(Ljava/lang/String;)Ljavassist/bytecode/AttributeInfo;
      11: checkcast     #136                // class javassist/bytecode/InnerClassesAttribute
      14: astore_2
      15: aload_2
      16: ifnonnull     21
      19: aconst_null
      20: areturn
      21: aload_0
      22: invokevirtual #32                 // Method getName:()Ljava/lang/String;
      25: astore_3
      26: aload_2
      27: invokevirtual #140                // Method javassist/bytecode/InnerClassesAttribute.tableLength:()I
      30: istore        4
      32: iconst_0
      33: istore        5
      35: iload         5
      37: iload         4
      39: if_icmpge     113
      42: aload_3
      43: aload_2
      44: iload         5
      46: invokevirtual #143                // Method javassist/bytecode/InnerClassesAttribute.innerClass:(I)Ljava/lang/String;
      49: invokevirtual #36                 // Method java/lang/String.equals:(Ljava/lang/Object;)Z
      52: ifeq          107
      55: aload_2
      56: iload         5
      58: invokevirtual #162                // Method javassist/bytecode/InnerClassesAttribute.outerClass:(I)Ljava/lang/String;
      61: astore        6
      63: aload         6
      65: ifnull        78
      68: aload_0
      69: getfield      #4                  // Field classPool:Ljavassist/ClassPool;
      72: aload         6
      74: invokevirtual #105                // Method javassist/ClassPool.get:(Ljava/lang/String;)Ljavassist/CtClass;
      77: areturn
      78: aload_1
      79: ldc           #205                // String EnclosingMethod
      81: invokevirtual #114                // Method javassist/bytecode/ClassFile.getAttribute:(Ljava/lang/String;)Ljavassist/bytecode/AttributeInfo;
      84: checkcast     #204                // class javassist/bytecode/EnclosingMethodAttribute
      87: astore        7
      89: aload         7
      91: ifnull        107
      94: aload_0
      95: getfield      #4                  // Field classPool:Ljavassist/ClassPool;
      98: aload         7
     100: invokevirtual #206                // Method javassist/bytecode/EnclosingMethodAttribute.className:()Ljava/lang/String;
     103: invokevirtual #105                // Method javassist/ClassPool.get:(Ljava/lang/String;)Ljavassist/CtClass;
     106: areturn
     107: iinc          5, 1
     110: goto          35
     113: aconst_null
     114: areturn

  public javassist.CtBehavior getEnclosingBehavior() throws javassist.NotFoundException;
    Code:
       0: aload_0
       1: invokevirtual #102                // Method getClassFile2:()Ljavassist/bytecode/ClassFile;
       4: astore_1
       5: aload_1
       6: ldc           #205                // String EnclosingMethod
       8: invokevirtual #114                // Method javassist/bytecode/ClassFile.getAttribute:(Ljava/lang/String;)Ljavassist/bytecode/AttributeInfo;
      11: checkcast     #204                // class javassist/bytecode/EnclosingMethodAttribute
      14: astore_2
      15: aload_2
      16: ifnonnull     21
      19: aconst_null
      20: areturn
      21: aload_0
      22: getfield      #4                  // Field classPool:Ljavassist/ClassPool;
      25: aload_2
      26: invokevirtual #206                // Method javassist/bytecode/EnclosingMethodAttribute.className:()Ljava/lang/String;
      29: invokevirtual #105                // Method javassist/ClassPool.get:(Ljava/lang/String;)Ljavassist/CtClass;
      32: astore_3
      33: aload_2
      34: invokevirtual #207                // Method javassist/bytecode/EnclosingMethodAttribute.methodName:()Ljava/lang/String;
      37: astore        4
      39: ldc           #209                // String <init>
      41: aload         4
      43: invokevirtual #36                 // Method java/lang/String.equals:(Ljava/lang/Object;)Z
      46: ifeq          58
      49: aload_3
      50: aload_2
      51: invokevirtual #210                // Method javassist/bytecode/EnclosingMethodAttribute.methodDescriptor:()Ljava/lang/String;
      54: invokevirtual #211                // Method javassist/CtClass.getConstructor:(Ljava/lang/String;)Ljavassist/CtConstructor;
      57: areturn
      58: ldc           #212                // String <clinit>
      60: aload         4
      62: invokevirtual #36                 // Method java/lang/String.equals:(Ljava/lang/Object;)Z
      65: ifeq          73
      68: aload_3
      69: invokevirtual #213                // Method javassist/CtClass.getClassInitializer:()Ljavassist/CtConstructor;
      72: areturn
      73: aload_3
      74: aload         4
      76: aload_2
      77: invokevirtual #210                // Method javassist/bytecode/EnclosingMethodAttribute.methodDescriptor:()Ljava/lang/String;
      80: invokevirtual #214                // Method javassist/CtClass.getMethod:(Ljava/lang/String;Ljava/lang/String;)Ljavassist/CtMethod;
      83: areturn

  public javassist.CtClass makeNestedClass(java.lang.String, boolean);
    Code:
       0: iload_2
       1: ifne          14
       4: new           #69                 // class java/lang/RuntimeException
       7: dup
       8: ldc           #215                // String sorry, only nested static class is supported
      10: invokespecial #81                 // Method java/lang/RuntimeException."<init>":(Ljava/lang/String;)V
      13: athrow
      14: aload_0
      15: invokevirtual #151                // Method checkModify:()V
      18: aload_0
      19: getfield      #4                  // Field classPool:Ljavassist/ClassPool;
      22: new           #37                 // class java/lang/StringBuilder
      25: dup
      26: invokespecial #38                 // Method java/lang/StringBuilder."<init>":()V
      29: aload_0
      30: invokevirtual #32                 // Method getName:()Ljava/lang/String;
      33: invokevirtual #40                 // Method java/lang/StringBuilder.append:(Ljava/lang/String;)Ljava/lang/StringBuilder;
      36: ldc           #139                // String $
      38: invokevirtual #40                 // Method java/lang/StringBuilder.append:(Ljava/lang/String;)Ljava/lang/StringBuilder;
      41: aload_1
      42: invokevirtual #40                 // Method java/lang/StringBuilder.append:(Ljava/lang/String;)Ljava/lang/StringBuilder;
      45: invokevirtual #41                 // Method java/lang/StringBuilder.toString:()Ljava/lang/String;
      48: invokevirtual #216                // Method javassist/ClassPool.makeNestedClass:(Ljava/lang/String;)Ljavassist/CtClass;
      51: astore_3
      52: aload_0
      53: invokevirtual #102                // Method getClassFile2:()Ljavassist/bytecode/ClassFile;
      56: astore        4
      58: aload_3
      59: invokevirtual #156                // Method javassist/CtClass.getClassFile2:()Ljavassist/bytecode/ClassFile;
      62: astore        5
      64: aload         4
      66: ldc           #137                // String InnerClasses
      68: invokevirtual #114                // Method javassist/bytecode/ClassFile.getAttribute:(Ljava/lang/String;)Ljavassist/bytecode/AttributeInfo;
      71: checkcast     #136                // class javassist/bytecode/InnerClassesAttribute
      74: astore        6
      76: aload         6
      78: ifnonnull     102
      81: new           #136                // class javassist/bytecode/InnerClassesAttribute
      84: dup
      85: aload         4
      87: invokevirtual #117                // Method javassist/bytecode/ClassFile.getConstPool:()Ljavassist/bytecode/ConstPool;
      90: invokespecial #217                // Method javassist/bytecode/InnerClassesAttribute."<init>":(Ljavassist/bytecode/ConstPool;)V
      93: astore        6
      95: aload         4
      97: aload         6
      99: invokevirtual #119                // Method javassist/bytecode/ClassFile.addAttribute:(Ljavassist/bytecode/AttributeInfo;)V
     102: aload         6
     104: aload_3
     105: invokevirtual #34                 // Method javassist/CtClass.getName:()Ljava/lang/String;
     108: aload_0
     109: invokevirtual #32                 // Method getName:()Ljava/lang/String;
     112: aload_1
     113: aload         5
     115: invokevirtual #131                // Method javassist/bytecode/ClassFile.getAccessFlags:()I
     118: bipush        -33
     120: iand
     121: bipush        8
     123: ior
     124: invokevirtual #218                // Method javassist/bytecode/InnerClassesAttribute.append:(Ljava/lang/String;Ljava/lang/String;Ljava/lang/String;I)V
     127: aload         5
     129: aload         6
     131: aload         5
     133: invokevirtual #117                // Method javassist/bytecode/ClassFile.getConstPool:()Ljavassist/bytecode/ConstPool;
     136: aconst_null
     137: invokevirtual #219                // Method javassist/bytecode/InnerClassesAttribute.copy:(Ljavassist/bytecode/ConstPool;Ljava/util/Map;)Ljavassist/bytecode/AttributeInfo;
     140: invokevirtual #119                // Method javassist/bytecode/ClassFile.addAttribute:(Ljavassist/bytecode/AttributeInfo;)V
     143: aload_3
     144: areturn

  private void nameReplaced();
    Code:
       0: aload_0
       1: invokevirtual #89                 // Method hasMemberCache:()Ljavassist/CtMember$Cache;
       4: astore_1
       5: aload_1
       6: ifnull        36
       9: aload_1
      10: invokevirtual #56                 // Method javassist/CtMember$Cache.methodHead:()Ljavassist/CtMember;
      13: astore_2
      14: aload_1
      15: invokevirtual #57                 // Method javassist/CtMember$Cache.lastMethod:()Ljavassist/CtMember;
      18: astore_3
      19: aload_2
      20: aload_3
      21: if_acmpeq     36
      24: aload_2
      25: invokevirtual #58                 // Method javassist/CtMember.next:()Ljavassist/CtMember;
      28: astore_2
      29: aload_2
      30: invokevirtual #220                // Method javassist/CtMember.nameReplaced:()V
      33: goto          19
      36: return

  protected javassist.CtMember$Cache hasMemberCache();
    Code:
       0: aload_0
       1: getfield      #11                 // Field memberCache:Ljava/lang/ref/Reference;
       4: ifnull        18
       7: aload_0
       8: getfield      #11                 // Field memberCache:Ljava/lang/ref/Reference;
      11: invokevirtual #221                // Method java/lang/ref/Reference.get:()Ljava/lang/Object;
      14: checkcast     #222                // class javassist/CtMember$Cache
      17: areturn
      18: aconst_null
      19: areturn

  protected synchronized javassist.CtMember$Cache getMembers();
    Code:
       0: aconst_null
       1: astore_1
       2: aload_0
       3: getfield      #11                 // Field memberCache:Ljava/lang/ref/Reference;
       6: ifnull        24
       9: aload_0
      10: getfield      #11                 // Field memberCache:Ljava/lang/ref/Reference;
      13: invokevirtual #221                // Method java/lang/ref/Reference.get:()Ljava/lang/Object;
      16: checkcast     #222                // class javassist/CtMember$Cache
      19: dup
      20: astore_1
      21: ifnonnull     55
      24: new           #222                // class javassist/CtMember$Cache
      27: dup
      28: aload_0
      29: invokespecial #223                // Method javassist/CtMember$Cache."<init>":(Ljavassist/CtClassType;)V
      32: astore_1
      33: aload_0
      34: aload_1
      35: invokespecial #224                // Method makeFieldCache:(Ljavassist/CtMember$Cache;)V
      38: aload_0
      39: aload_1
      40: invokespecial #225                // Method makeBehaviorCache:(Ljavassist/CtMember$Cache;)V
      43: aload_0
      44: new           #226                // class java/lang/ref/WeakReference
      47: dup
      48: aload_1
      49: invokespecial #227                // Method java/lang/ref/WeakReference."<init>":(Ljava/lang/Object;)V
      52: putfield      #11                 // Field memberCache:Ljava/lang/ref/Reference;
      55: aload_1
      56: areturn

  private void makeFieldCache(javassist.CtMember$Cache);
    Code:
       0: aload_0
       1: iconst_0
       2: invokevirtual #62                 // Method getClassFile3:(Z)Ljavassist/bytecode/ClassFile;
       5: invokevirtual #228                // Method javassist/bytecode/ClassFile.getFields:()Ljava/util/List;
       8: astore_2
       9: aload_2
      10: invokeinterface #229,  1          // InterfaceMethod java/util/List.iterator:()Ljava/util/Iterator;
      15: astore_3
      16: aload_3
      17: invokeinterface #230,  1          // InterfaceMethod java/util/Iterator.hasNext:()Z
      22: ifeq          53
      25: aload_3
      26: invokeinterface #231,  1          // InterfaceMethod java/util/Iterator.next:()Ljava/lang/Object;
      31: checkcast     #232                // class javassist/bytecode/FieldInfo
      34: astore        4
      36: aload_1
      37: new           #233                // class javassist/CtField
      40: dup
      41: aload         4
      43: aload_0
      44: invokespecial #234                // Method javassist/CtField."<init>":(Ljavassist/bytecode/FieldInfo;Ljavassist/CtClass;)V
      47: invokevirtual #235                // Method javassist/CtMember$Cache.addField:(Ljavassist/CtMember;)V
      50: goto          16
      53: return

  private void makeBehaviorCache(javassist.CtMember$Cache);
    Code:
       0: aload_0
       1: iconst_0
       2: invokevirtual #62                 // Method getClassFile3:(Z)Ljavassist/bytecode/ClassFile;
       5: invokevirtual #236                // Method javassist/bytecode/ClassFile.getMethods:()Ljava/util/List;
       8: astore_2
       9: aload_2
      10: invokeinterface #229,  1          // InterfaceMethod java/util/List.iterator:()Ljava/util/Iterator;
      15: astore_3
      16: aload_3
      17: invokeinterface #230,  1          // InterfaceMethod java/util/Iterator.hasNext:()Z
      22: ifeq          78
      25: aload_3
      26: invokeinterface #231,  1          // InterfaceMethod java/util/Iterator.next:()Ljava/lang/Object;
      31: checkcast     #208                // class javassist/bytecode/MethodInfo
      34: astore        4
      36: aload         4
      38: invokevirtual #237                // Method javassist/bytecode/MethodInfo.isMethod:()Z
      41: ifeq          61
      44: aload_1
      45: new           #238                // class javassist/CtMethod
      48: dup
      49: aload         4
      51: aload_0
      52: invokespecial #239                // Method javassist/CtMethod."<init>":(Ljavassist/bytecode/MethodInfo;Ljavassist/CtClass;)V
      55: invokevirtual #240                // Method javassist/CtMember$Cache.addMethod:(Ljavassist/CtMember;)V
      58: goto          75
      61: aload_1
      62: new           #241                // class javassist/CtConstructor
      65: dup
      66: aload         4
      68: aload_0
      69: invokespecial #242                // Method javassist/CtConstructor."<init>":(Ljavassist/bytecode/MethodInfo;Ljavassist/CtClass;)V
      72: invokevirtual #243                // Method javassist/CtMember$Cache.addConstructor:(Ljavassist/CtMember;)V
      75: goto          16
      78: return

  public javassist.CtField[] getFields();
    Code:
       0: new           #141                // class java/util/ArrayList
       3: dup
       4: invokespecial #182                // Method java/util/ArrayList."<init>":()V
       7: astore_1
       8: aload_1
       9: aload_0
      10: invokestatic  #244                // Method getFields:(Ljava/util/List;Ljavassist/CtClass;)V
      13: aload_1
      14: aload_1
      15: invokeinterface #148,  1          // InterfaceMethod java/util/List.size:()I
      20: anewarray     #233                // class javassist/CtField
      23: invokeinterface #149,  2          // InterfaceMethod java/util/List.toArray:([Ljava/lang/Object;)[Ljava/lang/Object;
      28: checkcast     #245                // class "[Ljavassist/CtField;"
      31: areturn

  private static void getFields(java.util.List<javassist.CtMember>, javassist.CtClass);
    Code:
       0: aload_1
       1: ifnonnull     5
       4: return
       5: aload_0
       6: aload_1
       7: invokevirtual #197                // Method javassist/CtClass.getSuperclass:()Ljavassist/CtClass;
      10: invokestatic  #244                // Method getFields:(Ljava/util/List;Ljavassist/CtClass;)V
      13: goto          17
      16: astore_2
      17: aload_1
      18: invokevirtual #246                // Method javassist/CtClass.getInterfaces:()[Ljavassist/CtClass;
      21: astore_2
      22: aload_2
      23: astore_3
      24: aload_3
      25: arraylength
      26: istore        4
      28: iconst_0
      29: istore        5
      31: iload         5
      33: iload         4
      35: if_icmpge     56
      38: aload_3
      39: iload         5
      41: aaload
      42: astore        6
      44: aload_0
      45: aload         6
      47: invokestatic  #244                // Method getFields:(Ljava/util/List;Ljavassist/CtClass;)V
      50: iinc          5, 1
      53: goto          31
      56: goto          60
      59: astore_2
      60: aload_1
      61: checkcast     #66                 // class javassist/CtClassType
      64: invokevirtual #47                 // Method getMembers:()Ljavassist/CtMember$Cache;
      67: astore_2
      68: aload_2
      69: invokevirtual #49                 // Method javassist/CtMember$Cache.fieldHead:()Ljavassist/CtMember;
      72: astore_3
      73: aload_2
      74: invokevirtual #50                 // Method javassist/CtMember$Cache.lastField:()Ljavassist/CtMember;
      77: astore        4
      79: aload_3
      80: aload         4
      82: if_acmpeq     111
      85: aload_3
      86: invokevirtual #58                 // Method javassist/CtMember.next:()Ljavassist/CtMember;
      89: astore_3
      90: aload_3
      91: invokevirtual #247                // Method javassist/CtMember.getModifiers:()I
      94: invokestatic  #248                // Method javassist/Modifier.isPrivate:(I)Z
      97: ifne          79
     100: aload_0
     101: aload_3
     102: invokeinterface #147,  2          // InterfaceMethod java/util/List.add:(Ljava/lang/Object;)Z
     107: pop
     108: goto          79
     111: return
    Exception table:
       from    to  target type
           5    13    16   Class javassist/NotFoundException
          17    56    59   Class javassist/NotFoundException

  public javassist.CtField getField(java.lang.String, java.lang.String) throws javassist.NotFoundException;
    Code:
       0: aload_0
       1: aload_1
       2: aload_2
       3: invokevirtual #249                // Method getField2:(Ljava/lang/String;Ljava/lang/String;)Ljavassist/CtField;
       6: astore_3
       7: aload_0
       8: aload_3
       9: aload_1
      10: aload_2
      11: invokespecial #250                // Method checkGetField:(Ljavassist/CtField;Ljava/lang/String;Ljava/lang/String;)Ljavassist/CtField;
      14: areturn

  private javassist.CtField checkGetField(javassist.CtField, java.lang.String, java.lang.String) throws javassist.NotFoundException;
    Code:
       0: aload_1
       1: ifnonnull     90
       4: new           #37                 // class java/lang/StringBuilder
       7: dup
       8: invokespecial #38                 // Method java/lang/StringBuilder."<init>":()V
      11: ldc           #251                // String field:
      13: invokevirtual #40                 // Method java/lang/StringBuilder.append:(Ljava/lang/String;)Ljava/lang/StringBuilder;
      16: aload_2
      17: invokevirtual #40                 // Method java/lang/StringBuilder.append:(Ljava/lang/String;)Ljava/lang/StringBuilder;
      20: invokevirtual #41                 // Method java/lang/StringBuilder.toString:()Ljava/lang/String;
      23: astore        4
      25: aload_3
      26: ifnull        55
      29: new           #37                 // class java/lang/StringBuilder
      32: dup
      33: invokespecial #38                 // Method java/lang/StringBuilder."<init>":()V
      36: aload         4
      38: invokevirtual #40                 // Method java/lang/StringBuilder.append:(Ljava/lang/String;)Ljava/lang/StringBuilder;
      41: ldc           #252                // String  type
      43: invokevirtual #40                 // Method java/lang/StringBuilder.append:(Ljava/lang/String;)Ljava/lang/StringBuilder;
      46: aload_3
      47: invokevirtual #40                 // Method java/lang/StringBuilder.append:(Ljava/lang/String;)Ljava/lang/StringBuilder;
      50: invokevirtual #41                 // Method java/lang/StringBuilder.toString:()Ljava/lang/String;
      53: astore        4
      55: new           #42                 // class javassist/NotFoundException
      58: dup
      59: new           #37                 // class java/lang/StringBuilder
      62: dup
      63: invokespecial #38                 // Method java/lang/StringBuilder."<init>":()V
      66: aload         4
      68: invokevirtual #40                 // Method java/lang/StringBuilder.append:(Ljava/lang/String;)Ljava/lang/StringBuilder;
      71: ldc           #253                // String  in
      73: invokevirtual #40                 // Method java/lang/StringBuilder.append:(Ljava/lang/String;)Ljava/lang/StringBuilder;
      76: aload_0
      77: invokevirtual #32                 // Method getName:()Ljava/lang/String;
      80: invokevirtual #40                 // Method java/lang/StringBuilder.append:(Ljava/lang/String;)Ljava/lang/StringBuilder;
      83: invokevirtual #41                 // Method java/lang/StringBuilder.toString:()Ljava/lang/String;
      86: invokespecial #73                 // Method javassist/NotFoundException."<init>":(Ljava/lang/String;)V
      89: athrow
      90: aload_1
      91: areturn

  javassist.CtField getField2(java.lang.String, java.lang.String);
    Code:
       0: aload_0
       1: aload_1
       2: aload_2
       3: invokespecial #254                // Method getDeclaredField2:(Ljava/lang/String;Ljava/lang/String;)Ljavassist/CtField;
       6: astore_3
       7: aload_3
       8: ifnull        13
      11: aload_3
      12: areturn
      13: aload_0
      14: invokevirtual #44                 // Method getInterfaces:()[Ljavassist/CtClass;
      17: astore        4
      19: aload         4
      21: astore        5
      23: aload         5
      25: arraylength
      26: istore        6
      28: iconst_0
      29: istore        7
      31: iload         7
      33: iload         6
      35: if_icmpge     68
      38: aload         5
      40: iload         7
      42: aaload
      43: astore        8
      45: aload         8
      47: aload_1
      48: aload_2
      49: invokevirtual #255                // Method javassist/CtClass.getField2:(Ljava/lang/String;Ljava/lang/String;)Ljavassist/CtField;
      52: astore        9
      54: aload         9
      56: ifnull        62
      59: aload         9
      61: areturn
      62: iinc          7, 1
      65: goto          31
      68: aload_0
      69: invokevirtual #33                 // Method getSuperclass:()Ljavassist/CtClass;
      72: astore        5
      74: aload         5
      76: ifnull        87
      79: aload         5
      81: aload_1
      82: aload_2
      83: invokevirtual #255                // Method javassist/CtClass.getField2:(Ljava/lang/String;Ljava/lang/String;)Ljavassist/CtField;
      86: areturn
      87: goto          92
      90: astore        4
      92: aconst_null
      93: areturn
    Exception table:
       from    to  target type
          13    61    90   Class javassist/NotFoundException
          62    86    90   Class javassist/NotFoundException

  public javassist.CtField[] getDeclaredFields();
    Code:
       0: aload_0
       1: invokevirtual #47                 // Method getMembers:()Ljavassist/CtMember$Cache;
       4: astore_1
       5: aload_1
       6: invokevirtual #49                 // Method javassist/CtMember$Cache.fieldHead:()Ljavassist/CtMember;
       9: astore_2
      10: aload_1
      11: invokevirtual #50                 // Method javassist/CtMember$Cache.lastField:()Ljavassist/CtMember;
      14: astore_3
      15: aload_2
      16: aload_3
      17: invokestatic  #256                // Method javassist/CtMember$Cache.count:(Ljavassist/CtMember;Ljavassist/CtMember;)I
      20: istore        4
      22: iload         4
      24: anewarray     #233                // class javassist/CtField
      27: astore        5
      29: iconst_0
      30: istore        6
      32: aload_2
      33: aload_3
      34: if_acmpeq     57
      37: aload_2
      38: invokevirtual #58                 // Method javassist/CtMember.next:()Ljavassist/CtMember;
      41: astore_2
      42: aload         5
      44: iload         6
      46: iinc          6, 1
      49: aload_2
      50: checkcast     #233                // class javassist/CtField
      53: aastore
      54: goto          32
      57: aload         5
      59: areturn

  public javassist.CtField getDeclaredField(java.lang.String) throws javassist.NotFoundException;
    Code:
       0: aload_0
       1: aload_1
       2: aconst_null
       3: invokevirtual #257                // Method getDeclaredField:(Ljava/lang/String;Ljava/lang/String;)Ljavassist/CtField;
       6: areturn

  public javassist.CtField getDeclaredField(java.lang.String, java.lang.String) throws javassist.NotFoundException;
    Code:
       0: aload_0
       1: aload_1
       2: aload_2
       3: invokespecial #254                // Method getDeclaredField2:(Ljava/lang/String;Ljava/lang/String;)Ljavassist/CtField;
       6: astore_3
       7: aload_0
       8: aload_3
       9: aload_1
      10: aload_2
      11: invokespecial #250                // Method checkGetField:(Ljavassist/CtField;Ljava/lang/String;Ljava/lang/String;)Ljavassist/CtField;
      14: areturn

  private javassist.CtField getDeclaredField2(java.lang.String, java.lang.String);
    Code:
       0: aload_0
       1: invokevirtual #47                 // Method getMembers:()Ljavassist/CtMember$Cache;
       4: astore_3
       5: aload_3
       6: invokevirtual #49                 // Method javassist/CtMember$Cache.fieldHead:()Ljavassist/CtMember;
       9: astore        4
      11: aload_3
      12: invokevirtual #50                 // Method javassist/CtMember$Cache.lastField:()Ljavassist/CtMember;
      15: astore        5
      17: aload         4
      19: aload         5
      21: if_acmpeq     65
      24: aload         4
      26: invokevirtual #58                 // Method javassist/CtMember.next:()Ljavassist/CtMember;
      29: astore        4
      31: aload         4
      33: invokevirtual #258                // Method javassist/CtMember.getName:()Ljava/lang/String;
      36: aload_1
      37: invokevirtual #36                 // Method java/lang/String.equals:(Ljava/lang/Object;)Z
      40: ifeq          17
      43: aload_2
      44: ifnull        59
      47: aload_2
      48: aload         4
      50: invokevirtual #259                // Method javassist/CtMember.getSignature:()Ljava/lang/String;
      53: invokevirtual #36                 // Method java/lang/String.equals:(Ljava/lang/Object;)Z
      56: ifeq          17
      59: aload         4
      61: checkcast     #233                // class javassist/CtField
      64: areturn
      65: aconst_null
      66: areturn

  public javassist.CtBehavior[] getDeclaredBehaviors();
    Code:
       0: aload_0
       1: invokevirtual #47                 // Method getMembers:()Ljavassist/CtMember$Cache;
       4: astore_1
       5: aload_1
       6: invokevirtual #53                 // Method javassist/CtMember$Cache.consHead:()Ljavassist/CtMember;
       9: astore_2
      10: aload_1
      11: invokevirtual #54                 // Method javassist/CtMember$Cache.lastCons:()Ljavassist/CtMember;
      14: astore_3
      15: aload_2
      16: aload_3
      17: invokestatic  #256                // Method javassist/CtMember$Cache.count:(Ljavassist/CtMember;Ljavassist/CtMember;)I
      20: istore        4
      22: aload_1
      23: invokevirtual #56                 // Method javassist/CtMember$Cache.methodHead:()Ljavassist/CtMember;
      26: astore        5
      28: aload_1
      29: invokevirtual #57                 // Method javassist/CtMember$Cache.lastMethod:()Ljavassist/CtMember;
      32: astore        6
      34: aload         5
      36: aload         6
      38: invokestatic  #256                // Method javassist/CtMember$Cache.count:(Ljavassist/CtMember;Ljavassist/CtMember;)I
      41: istore        7
      43: iload         4
      45: iload         7
      47: iadd
      48: anewarray     #260                // class javassist/CtBehavior
      51: astore        8
      53: iconst_0
      54: istore        9
      56: aload_2
      57: aload_3
      58: if_acmpeq     81
      61: aload_2
      62: invokevirtual #58                 // Method javassist/CtMember.next:()Ljavassist/CtMember;
      65: astore_2
      66: aload         8
      68: iload         9
      70: iinc          9, 1
      73: aload_2
      74: checkcast     #260                // class javassist/CtBehavior
      77: aastore
      78: goto          56
      81: aload         5
      83: aload         6
      85: if_acmpeq     111
      88: aload         5
      90: invokevirtual #58                 // Method javassist/CtMember.next:()Ljavassist/CtMember;
      93: astore        5
      95: aload         8
      97: iload         9
      99: iinc          9, 1
     102: aload         5
     104: checkcast     #260                // class javassist/CtBehavior
     107: aastore
     108: goto          81
     111: aload         8
     113: areturn

  public javassist.CtConstructor[] getConstructors();
    Code:
       0: aload_0
       1: invokevirtual #47                 // Method getMembers:()Ljavassist/CtMember$Cache;
       4: astore_1
       5: aload_1
       6: invokevirtual #53                 // Method javassist/CtMember$Cache.consHead:()Ljavassist/CtMember;
       9: astore_2
      10: aload_1
      11: invokevirtual #54                 // Method javassist/CtMember$Cache.lastCons:()Ljavassist/CtMember;
      14: astore_3
      15: iconst_0
      16: istore        4
      18: aload_2
      19: astore        5
      21: aload         5
      23: aload_3
      24: if_acmpeq     51
      27: aload         5
      29: invokevirtual #58                 // Method javassist/CtMember.next:()Ljavassist/CtMember;
      32: astore        5
      34: aload         5
      36: checkcast     #241                // class javassist/CtConstructor
      39: invokestatic  #261                // Method isPubCons:(Ljavassist/CtConstructor;)Z
      42: ifeq          21
      45: iinc          4, 1
      48: goto          21
      51: iload         4
      53: anewarray     #241                // class javassist/CtConstructor
      56: astore        6
      58: iconst_0
      59: istore        7
      61: aload_2
      62: astore        5
      64: aload         5
      66: aload_3
      67: if_acmpeq     105
      70: aload         5
      72: invokevirtual #58                 // Method javassist/CtMember.next:()Ljavassist/CtMember;
      75: astore        5
      77: aload         5
      79: checkcast     #241                // class javassist/CtConstructor
      82: astore        8
      84: aload         8
      86: invokestatic  #261                // Method isPubCons:(Ljavassist/CtConstructor;)Z
      89: ifeq          102
      92: aload         6
      94: iload         7
      96: iinc          7, 1
      99: aload         8
     101: aastore
     102: goto          64
     105: aload         6
     107: areturn

  private static boolean isPubCons(javassist.CtConstructor);
    Code:
       0: aload_0
       1: invokevirtual #262                // Method javassist/CtConstructor.getModifiers:()I
       4: invokestatic  #248                // Method javassist/Modifier.isPrivate:(I)Z
       7: ifne          21
      10: aload_0
      11: invokevirtual #263                // Method javassist/CtConstructor.isConstructor:()Z
      14: ifeq          21
      17: iconst_1
      18: goto          22
      21: iconst_0
      22: ireturn

  public javassist.CtConstructor getConstructor(java.lang.String) throws javassist.NotFoundException;
    Code:
       0: aload_0
       1: invokevirtual #47                 // Method getMembers:()Ljavassist/CtMember$Cache;
       4: astore_2
       5: aload_2
       6: invokevirtual #53                 // Method javassist/CtMember$Cache.consHead:()Ljavassist/CtMember;
       9: astore_3
      10: aload_2
      11: invokevirtual #54                 // Method javassist/CtMember$Cache.lastCons:()Ljavassist/CtMember;
      14: astore        4
      16: aload_3
      17: aload         4
      19: if_acmpeq     62
      22: aload_3
      23: invokevirtual #58                 // Method javassist/CtMember.next:()Ljavassist/CtMember;
      26: astore_3
      27: aload_3
      28: checkcast     #241                // class javassist/CtConstructor
      31: astore        5
      33: aload         5
      35: invokevirtual #264                // Method javassist/CtConstructor.getMethodInfo2:()Ljavassist/bytecode/MethodInfo;
      38: invokevirtual #185                // Method javassist/bytecode/MethodInfo.getDescriptor:()Ljava/lang/String;
      41: aload_1
      42: invokevirtual #36                 // Method java/lang/String.equals:(Ljava/lang/Object;)Z
      45: ifeq          59
      48: aload         5
      50: invokevirtual #263                // Method javassist/CtConstructor.isConstructor:()Z
      53: ifeq          59
      56: aload         5
      58: areturn
      59: goto          16
      62: aload_0
      63: aload_1
      64: invokespecial #211                // Method javassist/CtClass.getConstructor:(Ljava/lang/String;)Ljavassist/CtConstructor;
      67: areturn

  public javassist.CtConstructor[] getDeclaredConstructors();
    Code:
       0: aload_0
       1: invokevirtual #47                 // Method getMembers:()Ljavassist/CtMember$Cache;
       4: astore_1
       5: aload_1
       6: invokevirtual #53                 // Method javassist/CtMember$Cache.consHead:()Ljavassist/CtMember;
       9: astore_2
      10: aload_1
      11: invokevirtual #54                 // Method javassist/CtMember$Cache.lastCons:()Ljavassist/CtMember;
      14: astore_3
      15: iconst_0
      16: istore        4
      18: aload_2
      19: astore        5
      21: aload         5
      23: aload_3
      24: if_acmpeq     55
      27: aload         5
      29: invokevirtual #58                 // Method javassist/CtMember.next:()Ljavassist/CtMember;
      32: astore        5
      34: aload         5
      36: checkcast     #241                // class javassist/CtConstructor
      39: astore        6
      41: aload         6
      43: invokevirtual #263                // Method javassist/CtConstructor.isConstructor:()Z
      46: ifeq          52
      49: iinc          4, 1
      52: goto          21
      55: iload         4
      57: anewarray     #241                // class javassist/CtConstructor
      60: astore        6
      62: iconst_0
      63: istore        7
      65: aload_2
      66: astore        5
      68: aload         5
      70: aload_3
      71: if_acmpeq     109
      74: aload         5
      76: invokevirtual #58                 // Method javassist/CtMember.next:()Ljavassist/CtMember;
      79: astore        5
      81: aload         5
      83: checkcast     #241                // class javassist/CtConstructor
      86: astore        8
      88: aload         8
      90: invokevirtual #263                // Method javassist/CtConstructor.isConstructor:()Z
      93: ifeq          106
      96: aload         6
      98: iload         7
     100: iinc          7, 1
     103: aload         8
     105: aastore
     106: goto          68
     109: aload         6
     111: areturn

  public javassist.CtConstructor getClassInitializer();
    Code:
       0: aload_0
       1: invokevirtual #47                 // Method getMembers:()Ljavassist/CtMember$Cache;
       4: astore_1
       5: aload_1
       6: invokevirtual #53                 // Method javassist/CtMember$Cache.consHead:()Ljavassist/CtMember;
       9: astore_2
      10: aload_1
      11: invokevirtual #54                 // Method javassist/CtMember$Cache.lastCons:()Ljavassist/CtMember;
      14: astore_3
      15: aload_2
      16: aload_3
      17: if_acmpeq     45
      20: aload_2
      21: invokevirtual #58                 // Method javassist/CtMember.next:()Ljavassist/CtMember;
      24: astore_2
      25: aload_2
      26: checkcast     #241                // class javassist/CtConstructor
      29: astore        4
      31: aload         4
      33: invokevirtual #265                // Method javassist/CtConstructor.isClassInitializer:()Z
      36: ifeq          42
      39: aload         4
      41: areturn
      42: goto          15
      45: aconst_null
      46: areturn

  public javassist.CtMethod[] getMethods();
    Code:
       0: new           #266                // class java/util/HashMap
       3: dup
       4: invokespecial #267                // Method java/util/HashMap."<init>":()V
       7: astore_1
       8: aload_1
       9: aload_0
      10: invokestatic  #268                // Method getMethods0:(Ljava/util/Map;Ljavassist/CtClass;)V
      13: aload_1
      14: invokeinterface #269,  1          // InterfaceMethod java/util/Map.values:()Ljava/util/Collection;
      19: aload_1
      20: invokeinterface #270,  1          // InterfaceMethod java/util/Map.size:()I
      25: anewarray     #238                // class javassist/CtMethod
      28: invokeinterface #271,  2          // InterfaceMethod java/util/Collection.toArray:([Ljava/lang/Object;)[Ljava/lang/Object;
      33: checkcast     #272                // class "[Ljavassist/CtMethod;"
      36: areturn

  private static void getMethods0(java.util.Map<java.lang.String, javassist.CtMember>, javassist.CtClass);
    Code:
       0: aload_1
       1: invokevirtual #246                // Method javassist/CtClass.getInterfaces:()[Ljavassist/CtClass;
       4: astore_2
       5: aload_2
       6: astore_3
       7: aload_3
       8: arraylength
       9: istore        4
      11: iconst_0
      12: istore        5
      14: iload         5
      16: iload         4
      18: if_icmpge     39
      21: aload_3
      22: iload         5
      24: aaload
      25: astore        6
      27: aload_0
      28: aload         6
      30: invokestatic  #268                // Method getMethods0:(Ljava/util/Map;Ljavassist/CtClass;)V
      33: iinc          5, 1
      36: goto          14
      39: goto          43
      42: astore_2
      43: aload_1
      44: invokevirtual #197                // Method javassist/CtClass.getSuperclass:()Ljavassist/CtClass;
      47: astore_2
      48: aload_2
      49: ifnull        57
      52: aload_0
      53: aload_2
      54: invokestatic  #268                // Method getMethods0:(Ljava/util/Map;Ljavassist/CtClass;)V
      57: goto          61
      60: astore_2
      61: aload_1
      62: instanceof    #66                 // class javassist/CtClassType
      65: ifeq          126
      68: aload_1
      69: checkcast     #66                 // class javassist/CtClassType
      72: invokevirtual #47                 // Method getMembers:()Ljavassist/CtMember$Cache;
      75: astore_2
      76: aload_2
      77: invokevirtual #56                 // Method javassist/CtMember$Cache.methodHead:()Ljavassist/CtMember;
      80: astore_3
      81: aload_2
      82: invokevirtual #57                 // Method javassist/CtMember$Cache.lastMethod:()Ljavassist/CtMember;
      85: astore        4
      87: aload_3
      88: aload         4
      90: if_acmpeq     126
      93: aload_3
      94: invokevirtual #58                 // Method javassist/CtMember.next:()Ljavassist/CtMember;
      97: astore_3
      98: aload_3
      99: invokevirtual #247                // Method javassist/CtMember.getModifiers:()I
     102: invokestatic  #248                // Method javassist/Modifier.isPrivate:(I)Z
     105: ifne          87
     108: aload_0
     109: aload_3
     110: checkcast     #238                // class javassist/CtMethod
     113: invokevirtual #273                // Method javassist/CtMethod.getStringRep:()Ljava/lang/String;
     116: aload_3
     117: invokeinterface #274,  3          // InterfaceMethod java/util/Map.put:(Ljava/lang/Object;Ljava/lang/Object;)Ljava/lang/Object;
     122: pop
     123: goto          87
     126: return
    Exception table:
       from    to  target type
           0    39    42   Class javassist/NotFoundException
          43    57    60   Class javassist/NotFoundException

  public javassist.CtMethod getMethod(java.lang.String, java.lang.String) throws javassist.NotFoundException;
    Code:
       0: aload_0
       1: aload_1
       2: aload_2
       3: invokestatic  #275                // Method getMethod0:(Ljavassist/CtClass;Ljava/lang/String;Ljava/lang/String;)Ljavassist/CtMethod;
       6: astore_3
       7: aload_3
       8: ifnull        13
      11: aload_3
      12: areturn
      13: new           #42                 // class javassist/NotFoundException
      16: dup
      17: new           #37                 // class java/lang/StringBuilder
      20: dup
      21: invokespecial #38                 // Method java/lang/StringBuilder."<init>":()V
      24: aload_1
      25: invokevirtual #40                 // Method java/lang/StringBuilder.append:(Ljava/lang/String;)Ljava/lang/StringBuilder;
      28: ldc_w         #276                // String (..) is not found in
      31: invokevirtual #40                 // Method java/lang/StringBuilder.append:(Ljava/lang/String;)Ljava/lang/StringBuilder;
      34: aload_0
      35: invokevirtual #32                 // Method getName:()Ljava/lang/String;
      38: invokevirtual #40                 // Method java/lang/StringBuilder.append:(Ljava/lang/String;)Ljava/lang/StringBuilder;
      41: invokevirtual #41                 // Method java/lang/StringBuilder.toString:()Ljava/lang/String;
      44: invokespecial #73                 // Method javassist/NotFoundException."<init>":(Ljava/lang/String;)V
      47: athrow

  private static javassist.CtMethod getMethod0(javassist.CtClass, java.lang.String, java.lang.String);
    Code:
       0: aload_0
       1: instanceof    #66                 // class javassist/CtClassType
       4: ifeq          77
       7: aload_0
       8: checkcast     #66                 // class javassist/CtClassType
      11: invokevirtual #47                 // Method getMembers:()Ljavassist/CtMember$Cache;
      14: astore_3
      15: aload_3
      16: invokevirtual #56                 // Method javassist/CtMember$Cache.methodHead:()Ljavassist/CtMember;
      19: astore        4
      21: aload_3
      22: invokevirtual #57                 // Method javassist/CtMember$Cache.lastMethod:()Ljavassist/CtMember;
      25: astore        5
      27: aload         4
      29: aload         5
      31: if_acmpeq     77
      34: aload         4
      36: invokevirtual #58                 // Method javassist/CtMember.next:()Ljavassist/CtMember;
      39: astore        4
      41: aload         4
      43: invokevirtual #258                // Method javassist/CtMember.getName:()Ljava/lang/String;
      46: aload_1
      47: invokevirtual #36                 // Method java/lang/String.equals:(Ljava/lang/Object;)Z
      50: ifeq          27
      53: aload         4
      55: checkcast     #238                // class javassist/CtMethod
      58: invokevirtual #277                // Method javassist/CtMethod.getMethodInfo2:()Ljavassist/bytecode/MethodInfo;
      61: invokevirtual #185                // Method javassist/bytecode/MethodInfo.getDescriptor:()Ljava/lang/String;
      64: aload_2
      65: invokevirtual #36                 // Method java/lang/String.equals:(Ljava/lang/Object;)Z
      68: ifeq          27
      71: aload         4
      73: checkcast     #238                // class javassist/CtMethod
      76: areturn
      77: aload_0
      78: invokevirtual #197                // Method javassist/CtClass.getSuperclass:()Ljavassist/CtClass;
      81: astore_3
      82: aload_3
      83: ifnull        102
      86: aload_3
      87: aload_1
      88: aload_2
      89: invokestatic  #275                // Method getMethod0:(Ljavassist/CtClass;Ljava/lang/String;Ljava/lang/String;)Ljavassist/CtMethod;
      92: astore        4
      94: aload         4
      96: ifnull        102
      99: aload         4
     101: areturn
     102: goto          106
     105: astore_3
     106: aload_0
     107: invokevirtual #246                // Method javassist/CtClass.getInterfaces:()[Ljavassist/CtClass;
     110: astore_3
     111: aload_3
     112: astore        4
     114: aload         4
     116: arraylength
     117: istore        5
     119: iconst_0
     120: istore        6
     122: iload         6
     124: iload         5
     126: if_icmpge     159
     129: aload         4
     131: iload         6
     133: aaload
     134: astore        7
     136: aload         7
     138: aload_1
     139: aload_2
     140: invokestatic  #275                // Method getMethod0:(Ljavassist/CtClass;Ljava/lang/String;Ljava/lang/String;)Ljavassist/CtMethod;
     143: astore        8
     145: aload         8
     147: ifnull        153
     150: aload         8
     152: areturn
     153: iinc          6, 1
     156: goto          122
     159: goto          163
     162: astore_3
     163: aconst_null
     164: areturn
    Exception table:
       from    to  target type
          77   101   105   Class javassist/NotFoundException
         106   152   162   Class javassist/NotFoundException
         153   159   162   Class javassist/NotFoundException

  public javassist.CtMethod[] getDeclaredMethods();
    Code:
       0: aload_0
       1: invokevirtual #47                 // Method getMembers:()Ljavassist/CtMember$Cache;
       4: astore_1
       5: aload_1
       6: invokevirtual #56                 // Method javassist/CtMember$Cache.methodHead:()Ljavassist/CtMember;
       9: astore_2
      10: aload_1
      11: invokevirtual #57                 // Method javassist/CtMember$Cache.lastMethod:()Ljavassist/CtMember;
      14: astore_3
      15: new           #141                // class java/util/ArrayList
      18: dup
      19: invokespecial #182                // Method java/util/ArrayList."<init>":()V
      22: astore        4
      24: aload_2
      25: aload_3
      26: if_acmpeq     46
      29: aload_2
      30: invokevirtual #58                 // Method javassist/CtMember.next:()Ljavassist/CtMember;
      33: astore_2
      34: aload         4
      36: aload_2
      37: invokeinterface #147,  2          // InterfaceMethod java/util/List.add:(Ljava/lang/Object;)Z
      42: pop
      43: goto          24
      46: aload         4
      48: aload         4
      50: invokeinterface #148,  1          // InterfaceMethod java/util/List.size:()I
      55: anewarray     #238                // class javassist/CtMethod
      58: invokeinterface #149,  2          // InterfaceMethod java/util/List.toArray:([Ljava/lang/Object;)[Ljava/lang/Object;
      63: checkcast     #272                // class "[Ljavassist/CtMethod;"
      66: areturn

  public javassist.CtMethod[] getDeclaredMethods(java.lang.String) throws javassist.NotFoundException;
    Code:
       0: aload_0
       1: invokevirtual #47                 // Method getMembers:()Ljavassist/CtMember$Cache;
       4: astore_2
       5: aload_2
       6: invokevirtual #56                 // Method javassist/CtMember$Cache.methodHead:()Ljavassist/CtMember;
       9: astore_3
      10: aload_2
      11: invokevirtual #57                 // Method javassist/CtMember$Cache.lastMethod:()Ljavassist/CtMember;
      14: astore        4
      16: new           #141                // class java/util/ArrayList
      19: dup
      20: invokespecial #182                // Method java/util/ArrayList."<init>":()V
      23: astore        5
      25: aload_3
      26: aload         4
      28: if_acmpeq     59
      31: aload_3
      32: invokevirtual #58                 // Method javassist/CtMember.next:()Ljavassist/CtMember;
      35: astore_3
      36: aload_3
      37: invokevirtual #258                // Method javassist/CtMember.getName:()Ljava/lang/String;
      40: aload_1
      41: invokevirtual #36                 // Method java/lang/String.equals:(Ljava/lang/Object;)Z
      44: ifeq          25
      47: aload         5
      49: aload_3
      50: invokeinterface #147,  2          // InterfaceMethod java/util/List.add:(Ljava/lang/Object;)Z
      55: pop
      56: goto          25
      59: aload         5
      61: aload         5
      63: invokeinterface #148,  1          // InterfaceMethod java/util/List.size:()I
      68: anewarray     #238                // class javassist/CtMethod
      71: invokeinterface #149,  2          // InterfaceMethod java/util/List.toArray:([Ljava/lang/Object;)[Ljava/lang/Object;
      76: checkcast     #272                // class "[Ljavassist/CtMethod;"
      79: areturn

  public javassist.CtMethod getDeclaredMethod(java.lang.String) throws javassist.NotFoundException;
    Code:
       0: aload_0
       1: invokevirtual #47                 // Method getMembers:()Ljavassist/CtMember$Cache;
       4: astore_2
       5: aload_2
       6: invokevirtual #56                 // Method javassist/CtMember$Cache.methodHead:()Ljavassist/CtMember;
       9: astore_3
      10: aload_2
      11: invokevirtual #57                 // Method javassist/CtMember$Cache.lastMethod:()Ljavassist/CtMember;
      14: astore        4
      16: aload_3
      17: aload         4
      19: if_acmpeq     43
      22: aload_3
      23: invokevirtual #58                 // Method javassist/CtMember.next:()Ljavassist/CtMember;
      26: astore_3
      27: aload_3
      28: invokevirtual #258                // Method javassist/CtMember.getName:()Ljava/lang/String;
      31: aload_1
      32: invokevirtual #36                 // Method java/lang/String.equals:(Ljava/lang/Object;)Z
      35: ifeq          16
      38: aload_3
      39: checkcast     #238                // class javassist/CtMethod
      42: areturn
      43: new           #42                 // class javassist/NotFoundException
      46: dup
      47: new           #37                 // class java/lang/StringBuilder
      50: dup
      51: invokespecial #38                 // Method java/lang/StringBuilder."<init>":()V
      54: aload_1
      55: invokevirtual #40                 // Method java/lang/StringBuilder.append:(Ljava/lang/String;)Ljava/lang/StringBuilder;
      58: ldc_w         #276                // String (..) is not found in
      61: invokevirtual #40                 // Method java/lang/StringBuilder.append:(Ljava/lang/String;)Ljava/lang/StringBuilder;
      64: aload_0
      65: invokevirtual #32                 // Method getName:()Ljava/lang/String;
      68: invokevirtual #40                 // Method java/lang/StringBuilder.append:(Ljava/lang/String;)Ljava/lang/StringBuilder;
      71: invokevirtual #41                 // Method java/lang/StringBuilder.toString:()Ljava/lang/String;
      74: invokespecial #73                 // Method javassist/NotFoundException."<init>":(Ljava/lang/String;)V
      77: athrow

  public javassist.CtMethod getDeclaredMethod(java.lang.String, javassist.CtClass[]) throws javassist.NotFoundException;
    Code:
       0: aload_2
       1: invokestatic  #278                // Method javassist/bytecode/Descriptor.ofParameters:([Ljavassist/CtClass;)Ljava/lang/String;
       4: astore_3
       5: aload_0
       6: invokevirtual #47                 // Method getMembers:()Ljavassist/CtMember$Cache;
       9: astore        4
      11: aload         4
      13: invokevirtual #56                 // Method javassist/CtMember$Cache.methodHead:()Ljavassist/CtMember;
      16: astore        5
      18: aload         4
      20: invokevirtual #57                 // Method javassist/CtMember$Cache.lastMethod:()Ljavassist/CtMember;
      23: astore        6
      25: aload         5
      27: aload         6
      29: if_acmpeq     75
      32: aload         5
      34: invokevirtual #58                 // Method javassist/CtMember.next:()Ljavassist/CtMember;
      37: astore        5
      39: aload         5
      41: invokevirtual #258                // Method javassist/CtMember.getName:()Ljava/lang/String;
      44: aload_1
      45: invokevirtual #36                 // Method java/lang/String.equals:(Ljava/lang/Object;)Z
      48: ifeq          25
      51: aload         5
      53: checkcast     #238                // class javassist/CtMethod
      56: invokevirtual #277                // Method javassist/CtMethod.getMethodInfo2:()Ljavassist/bytecode/MethodInfo;
      59: invokevirtual #185                // Method javassist/bytecode/MethodInfo.getDescriptor:()Ljava/lang/String;
      62: aload_3
      63: invokevirtual #144                // Method java/lang/String.startsWith:(Ljava/lang/String;)Z
      66: ifeq          25
      69: aload         5
      71: checkcast     #238                // class javassist/CtMethod
      74: areturn
      75: new           #42                 // class javassist/NotFoundException
      78: dup
      79: new           #37                 // class java/lang/StringBuilder
      82: dup
      83: invokespecial #38                 // Method java/lang/StringBuilder."<init>":()V
      86: aload_1
      87: invokevirtual #40                 // Method java/lang/StringBuilder.append:(Ljava/lang/String;)Ljava/lang/StringBuilder;
      90: ldc_w         #276                // String (..) is not found in
      93: invokevirtual #40                 // Method java/lang/StringBuilder.append:(Ljava/lang/String;)Ljava/lang/StringBuilder;
      96: aload_0
      97: invokevirtual #32                 // Method getName:()Ljava/lang/String;
     100: invokevirtual #40                 // Method java/lang/StringBuilder.append:(Ljava/lang/String;)Ljava/lang/StringBuilder;
     103: invokevirtual #41                 // Method java/lang/StringBuilder.toString:()Ljava/lang/String;
     106: invokespecial #73                 // Method javassist/NotFoundException."<init>":(Ljava/lang/String;)V
     109: athrow

  public void addField(javassist.CtField, java.lang.String) throws javassist.CannotCompileException;
    Code:
       0: aload_0
       1: aload_1
       2: aload_2
       3: invokestatic  #279                // Method javassist/CtField$Initializer.byExpr:(Ljava/lang/String;)Ljavassist/CtField$Initializer;
       6: invokevirtual #280                // Method addField:(Ljavassist/CtField;Ljavassist/CtField$Initializer;)V
       9: return

  public void addField(javassist.CtField, javassist.CtField$Initializer) throws javassist.CannotCompileException;
    Code:
       0: aload_0
       1: invokevirtual #151                // Method checkModify:()V
       4: aload_1
       5: invokevirtual #281                // Method javassist/CtField.getDeclaringClass:()Ljavassist/CtClass;
       8: aload_0
       9: if_acmpeq     23
      12: new           #282                // class javassist/CannotCompileException
      15: dup
      16: ldc_w         #283                // String cannot add
      19: invokespecial #284                // Method javassist/CannotCompileException."<init>":(Ljava/lang/String;)V
      22: athrow
      23: aload_2
      24: ifnonnull     32
      27: aload_1
      28: invokevirtual #285                // Method javassist/CtField.getInit:()Ljavassist/CtField$Initializer;
      31: astore_2
      32: aload_2
      33: ifnull        114
      36: aload_2
      37: aload_1
      38: invokevirtual #286                // Method javassist/CtField.getSignature:()Ljava/lang/String;
      41: invokevirtual #287                // Method javassist/CtField$Initializer.check:(Ljava/lang/String;)V
      44: aload_1
      45: invokevirtual #288                // Method javassist/CtField.getModifiers:()I
      48: istore_3
      49: iload_3
      50: invokestatic  #159                // Method javassist/Modifier.isStatic:(I)Z
      53: ifeq          114
      56: iload_3
      57: invokestatic  #289                // Method javassist/Modifier.isFinal:(I)Z
      60: ifeq          114
      63: aload_0
      64: invokevirtual #102                // Method getClassFile2:()Ljavassist/bytecode/ClassFile;
      67: invokevirtual #117                // Method javassist/bytecode/ClassFile.getConstPool:()Ljavassist/bytecode/ConstPool;
      70: astore        4
      72: aload_2
      73: aload         4
      75: aload_1
      76: invokevirtual #290                // Method javassist/CtField.getType:()Ljavassist/CtClass;
      79: invokevirtual #291                // Method javassist/CtField$Initializer.getConstantValue:(Ljavassist/bytecode/ConstPool;Ljavassist/CtClass;)I
      82: istore        5
      84: iload         5
      86: ifeq          109
      89: aload_1
      90: invokevirtual #292                // Method javassist/CtField.getFieldInfo2:()Ljavassist/bytecode/FieldInfo;
      93: new           #293                // class javassist/bytecode/ConstantAttribute
      96: dup
      97: aload         4
      99: iload         5
     101: invokespecial #294                // Method javassist/bytecode/ConstantAttribute."<init>":(Ljavassist/bytecode/ConstPool;I)V
     104: invokevirtual #295                // Method javassist/bytecode/FieldInfo.addAttribute:(Ljavassist/bytecode/AttributeInfo;)V
     107: aconst_null
     108: astore_2
     109: goto          114
     112: astore        4
     114: aload_0
     115: invokevirtual #47                 // Method getMembers:()Ljavassist/CtMember$Cache;
     118: aload_1
     119: invokevirtual #235                // Method javassist/CtMember$Cache.addField:(Ljavassist/CtMember;)V
     122: aload_0
     123: invokevirtual #102                // Method getClassFile2:()Ljavassist/bytecode/ClassFile;
     126: aload_1
     127: invokevirtual #292                // Method javassist/CtField.getFieldInfo2:()Ljavassist/bytecode/FieldInfo;
     130: invokevirtual #296                // Method javassist/bytecode/ClassFile.addField:(Ljavassist/bytecode/FieldInfo;)V
     133: aload_2
     134: ifnull        190
     137: new           #297                // class javassist/FieldInitLink
     140: dup
     141: aload_1
     142: aload_2
     143: invokespecial #298                // Method javassist/FieldInitLink."<init>":(Ljavassist/CtField;Ljavassist/CtField$Initializer;)V
     146: astore_3
     147: aload_0
     148: getfield      #13                 // Field fieldInitializers:Ljavassist/FieldInitLink;
     151: astore        4
     153: aload         4
     155: ifnonnull     166
     158: aload_0
     159: aload_3
     160: putfield      #13                 // Field fieldInitializers:Ljavassist/FieldInitLink;
     163: goto          190
     166: aload         4
     168: getfield      #299                // Field javassist/FieldInitLink.next:Ljavassist/FieldInitLink;
     171: ifnull        184
     174: aload         4
     176: getfield      #299                // Field javassist/FieldInitLink.next:Ljavassist/FieldInitLink;
     179: astore        4
     181: goto          166
     184: aload         4
     186: aload_3
     187: putfield      #299                // Field javassist/FieldInitLink.next:Ljavassist/FieldInitLink;
     190: return
    Exception table:
       from    to  target type
          63   109   112   Class javassist/NotFoundException

  public void removeField(javassist.CtField) throws javassist.NotFoundException;
    Code:
       0: aload_0
       1: invokevirtual #151                // Method checkModify:()V
       4: aload_1
       5: invokevirtual #292                // Method javassist/CtField.getFieldInfo2:()Ljavassist/bytecode/FieldInfo;
       8: astore_2
       9: aload_0
      10: invokevirtual #102                // Method getClassFile2:()Ljavassist/bytecode/ClassFile;
      13: astore_3
      14: aload_3
      15: invokevirtual #228                // Method javassist/bytecode/ClassFile.getFields:()Ljava/util/List;
      18: aload_2
      19: invokeinterface #300,  2          // InterfaceMethod java/util/List.remove:(Ljava/lang/Object;)Z
      24: ifeq          43
      27: aload_0
      28: invokevirtual #47                 // Method getMembers:()Ljavassist/CtMember$Cache;
      31: aload_1
      32: invokevirtual #301                // Method javassist/CtMember$Cache.remove:(Ljavassist/CtMember;)V
      35: aload_0
      36: iconst_1
      37: putfield      #5                  // Field gcConstPool:Z
      40: goto          55
      43: new           #42                 // class javassist/NotFoundException
      46: dup
      47: aload_1
      48: invokevirtual #302                // Method javassist/CtField.toString:()Ljava/lang/String;
      51: invokespecial #73                 // Method javassist/NotFoundException."<init>":(Ljava/lang/String;)V
      54: athrow
      55: return

  public javassist.CtConstructor makeClassInitializer() throws javassist.CannotCompileException;
    Code:
       0: aload_0
       1: invokevirtual #303                // Method getClassInitializer:()Ljavassist/CtConstructor;
       4: astore_1
       5: aload_1
       6: ifnull        11
       9: aload_1
      10: areturn
      11: aload_0
      12: invokevirtual #151                // Method checkModify:()V
      15: aload_0
      16: invokevirtual #102                // Method getClassFile2:()Ljavassist/bytecode/ClassFile;
      19: astore_2
      20: new           #304                // class javassist/bytecode/Bytecode
      23: dup
      24: aload_2
      25: invokevirtual #117                // Method javassist/bytecode/ClassFile.getConstPool:()Ljavassist/bytecode/ConstPool;
      28: iconst_0
      29: iconst_0
      30: invokespecial #305                // Method javassist/bytecode/Bytecode."<init>":(Ljavassist/bytecode/ConstPool;II)V
      33: astore_3
      34: aload_0
      35: aload_2
      36: aload_3
      37: iconst_0
      38: iconst_0
      39: invokespecial #306                // Method modifyClassConstructor:(Ljavassist/bytecode/ClassFile;Ljavassist/bytecode/Bytecode;II)V
      42: aload_0
      43: invokevirtual #303                // Method getClassInitializer:()Ljavassist/CtConstructor;
      46: areturn

  public void addConstructor(javassist.CtConstructor) throws javassist.CannotCompileException;
    Code:
       0: aload_0
       1: invokevirtual #151                // Method checkModify:()V
       4: aload_1
       5: invokevirtual #307                // Method javassist/CtConstructor.getDeclaringClass:()Ljavassist/CtClass;
       8: aload_0
       9: if_acmpeq     23
      12: new           #282                // class javassist/CannotCompileException
      15: dup
      16: ldc_w         #283                // String cannot add
      19: invokespecial #284                // Method javassist/CannotCompileException."<init>":(Ljava/lang/String;)V
      22: athrow
      23: aload_0
      24: invokevirtual #47                 // Method getMembers:()Ljavassist/CtMember$Cache;
      27: aload_1
      28: invokevirtual #243                // Method javassist/CtMember$Cache.addConstructor:(Ljavassist/CtMember;)V
      31: aload_0
      32: invokevirtual #102                // Method getClassFile2:()Ljavassist/bytecode/ClassFile;
      35: aload_1
      36: invokevirtual #264                // Method javassist/CtConstructor.getMethodInfo2:()Ljavassist/bytecode/MethodInfo;
      39: invokevirtual #308                // Method javassist/bytecode/ClassFile.addMethod:(Ljavassist/bytecode/MethodInfo;)V
      42: return

  public void removeConstructor(javassist.CtConstructor) throws javassist.NotFoundException;
    Code:
       0: aload_0
       1: invokevirtual #151                // Method checkModify:()V
       4: aload_1
       5: invokevirtual #264                // Method javassist/CtConstructor.getMethodInfo2:()Ljavassist/bytecode/MethodInfo;
       8: astore_2
       9: aload_0
      10: invokevirtual #102                // Method getClassFile2:()Ljavassist/bytecode/ClassFile;
      13: astore_3
      14: aload_3
      15: invokevirtual #236                // Method javassist/bytecode/ClassFile.getMethods:()Ljava/util/List;
      18: aload_2
      19: invokeinterface #300,  2          // InterfaceMethod java/util/List.remove:(Ljava/lang/Object;)Z
      24: ifeq          43
      27: aload_0
      28: invokevirtual #47                 // Method getMembers:()Ljavassist/CtMember$Cache;
      31: aload_1
      32: invokevirtual #301                // Method javassist/CtMember$Cache.remove:(Ljavassist/CtMember;)V
      35: aload_0
      36: iconst_1
      37: putfield      #5                  // Field gcConstPool:Z
      40: goto          55
      43: new           #42                 // class javassist/NotFoundException
      46: dup
      47: aload_1
      48: invokevirtual #309                // Method javassist/CtConstructor.toString:()Ljava/lang/String;
      51: invokespecial #73                 // Method javassist/NotFoundException."<init>":(Ljava/lang/String;)V
      54: athrow
      55: return

  public void addMethod(javassist.CtMethod) throws javassist.CannotCompileException;
    Code:
       0: aload_0
       1: invokevirtual #151                // Method checkModify:()V
       4: aload_1
       5: invokevirtual #310                // Method javassist/CtMethod.getDeclaringClass:()Ljavassist/CtClass;
       8: aload_0
       9: if_acmpeq     23
      12: new           #282                // class javassist/CannotCompileException
      15: dup
      16: ldc_w         #311                // String bad declaring class
      19: invokespecial #284                // Method javassist/CannotCompileException."<init>":(Ljava/lang/String;)V
      22: athrow
      23: aload_1
      24: invokevirtual #312                // Method javassist/CtMethod.getModifiers:()I
      27: istore_2
      28: aload_0
      29: invokevirtual #29                 // Method getModifiers:()I
      32: sipush        512
      35: iand
      36: ifeq          91
      39: iload_2
      40: invokestatic  #313                // Method javassist/Modifier.isProtected:(I)Z
      43: ifne          53
      46: iload_2
      47: invokestatic  #248                // Method javassist/Modifier.isPrivate:(I)Z
      50: ifeq          84
      53: new           #282                // class javassist/CannotCompileException
      56: dup
      57: new           #37                 // class java/lang/StringBuilder
      60: dup
      61: invokespecial #38                 // Method java/lang/StringBuilder."<init>":()V
      64: ldc_w         #314                // String an interface method must be public:
      67: invokevirtual #40                 // Method java/lang/StringBuilder.append:(Ljava/lang/String;)Ljava/lang/StringBuilder;
      70: aload_1
      71: invokevirtual #315                // Method javassist/CtMethod.toString:()Ljava/lang/String;
      74: invokevirtual #40                 // Method java/lang/StringBuilder.append:(Ljava/lang/String;)Ljava/lang/StringBuilder;
      77: invokevirtual #41                 // Method java/lang/StringBuilder.toString:()Ljava/lang/String;
      80: invokespecial #284                // Method javassist/CannotCompileException."<init>":(Ljava/lang/String;)V
      83: athrow
      84: aload_1
      85: iload_2
      86: iconst_1
      87: ior
      88: invokevirtual #316                // Method javassist/CtMethod.setModifiers:(I)V
      91: aload_0
      92: invokevirtual #47                 // Method getMembers:()Ljavassist/CtMember$Cache;
      95: aload_1
      96: invokevirtual #240                // Method javassist/CtMember$Cache.addMethod:(Ljavassist/CtMember;)V
      99: aload_0
     100: invokevirtual #102                // Method getClassFile2:()Ljavassist/bytecode/ClassFile;
     103: aload_1
     104: invokevirtual #277                // Method javassist/CtMethod.getMethodInfo2:()Ljavassist/bytecode/MethodInfo;
     107: invokevirtual #308                // Method javassist/bytecode/ClassFile.addMethod:(Ljavassist/bytecode/MethodInfo;)V
     110: iload_2
     111: sipush        1024
     114: iand
     115: ifeq          130
     118: aload_0
     119: aload_0
     120: invokevirtual #29                 // Method getModifiers:()I
     123: sipush        1024
     126: ior
     127: invokevirtual #317                // Method setModifiers:(I)V
     130: return

  public void removeMethod(javassist.CtMethod) throws javassist.NotFoundException;
    Code:
       0: aload_0
       1: invokevirtual #151                // Method checkModify:()V
       4: aload_1
       5: invokevirtual #277                // Method javassist/CtMethod.getMethodInfo2:()Ljavassist/bytecode/MethodInfo;
       8: astore_2
       9: aload_0
      10: invokevirtual #102                // Method getClassFile2:()Ljavassist/bytecode/ClassFile;
      13: astore_3
      14: aload_3
      15: invokevirtual #236                // Method javassist/bytecode/ClassFile.getMethods:()Ljava/util/List;
      18: aload_2
      19: invokeinterface #300,  2          // InterfaceMethod java/util/List.remove:(Ljava/lang/Object;)Z
      24: ifeq          43
      27: aload_0
      28: invokevirtual #47                 // Method getMembers:()Ljavassist/CtMember$Cache;
      31: aload_1
      32: invokevirtual #301                // Method javassist/CtMember$Cache.remove:(Ljavassist/CtMember;)V
      35: aload_0
      36: iconst_1
      37: putfield      #5                  // Field gcConstPool:Z
      40: goto          55
      43: new           #42                 // class javassist/NotFoundException
      46: dup
      47: aload_1
      48: invokevirtual #315                // Method javassist/CtMethod.toString:()Ljava/lang/String;
      51: invokespecial #73                 // Method javassist/NotFoundException."<init>":(Ljava/lang/String;)V
      54: athrow
      55: return

  public byte[] getAttribute(java.lang.String);
    Code:
       0: aload_0
       1: invokevirtual #102                // Method getClassFile2:()Ljavassist/bytecode/ClassFile;
       4: aload_1
       5: invokevirtual #114                // Method javassist/bytecode/ClassFile.getAttribute:(Ljava/lang/String;)Ljavassist/bytecode/AttributeInfo;
       8: astore_2
       9: aload_2
      10: ifnonnull     15
      13: aconst_null
      14: areturn
      15: aload_2
      16: invokevirtual #318                // Method javassist/bytecode/AttributeInfo.get:()[B
      19: areturn

  public void setAttribute(java.lang.String, byte[]);
    Code:
       0: aload_0
       1: invokevirtual #151                // Method checkModify:()V
       4: aload_0
       5: invokevirtual #102                // Method getClassFile2:()Ljavassist/bytecode/ClassFile;
       8: astore_3
       9: aload_3
      10: new           #319                // class javassist/bytecode/AttributeInfo
      13: dup
      14: aload_3
      15: invokevirtual #117                // Method javassist/bytecode/ClassFile.getConstPool:()Ljavassist/bytecode/ConstPool;
      18: aload_1
      19: aload_2
      20: invokespecial #320                // Method javassist/bytecode/AttributeInfo."<init>":(Ljavassist/bytecode/ConstPool;Ljava/lang/String;[B)V
      23: invokevirtual #119                // Method javassist/bytecode/ClassFile.addAttribute:(Ljavassist/bytecode/AttributeInfo;)V
      26: return

  public void instrument(javassist.CodeConverter) throws javassist.CannotCompileException;
    Code:
       0: aload_0
       1: invokevirtual #151                // Method checkModify:()V
       4: aload_0
       5: invokevirtual #102                // Method getClassFile2:()Ljavassist/bytecode/ClassFile;
       8: astore_2
       9: aload_2
      10: invokevirtual #117                // Method javassist/bytecode/ClassFile.getConstPool:()Ljavassist/bytecode/ConstPool;
      13: astore_3
      14: aload_2
      15: invokevirtual #236                // Method javassist/bytecode/ClassFile.getMethods:()Ljava/util/List;
      18: astore        4
      20: aload         4
      22: aload         4
      24: invokeinterface #148,  1          // InterfaceMethod java/util/List.size:()I
      29: anewarray     #208                // class javassist/bytecode/MethodInfo
      32: invokeinterface #149,  2          // InterfaceMethod java/util/List.toArray:([Ljava/lang/Object;)[Ljava/lang/Object;
      37: checkcast     #321                // class "[Ljavassist/bytecode/MethodInfo;"
      40: astore        5
      42: aload         5
      44: arraylength
      45: istore        6
      47: iconst_0
      48: istore        7
      50: iload         7
      52: iload         6
      54: if_icmpge     78
      57: aload         5
      59: iload         7
      61: aaload
      62: astore        8
      64: aload_1
      65: aload_0
      66: aload         8
      68: aload_3
      69: invokevirtual #322                // Method javassist/CodeConverter.doit:(Ljavassist/CtClass;Ljavassist/bytecode/MethodInfo;Ljavassist/bytecode/ConstPool;)V
      72: iinc          7, 1
      75: goto          50
      78: return

  public void instrument(javassist.expr.ExprEditor) throws javassist.CannotCompileException;
    Code:
       0: aload_0
       1: invokevirtual #151                // Method checkModify:()V
       4: aload_0
       5: invokevirtual #102                // Method getClassFile2:()Ljavassist/bytecode/ClassFile;
       8: astore_2
       9: aload_2
      10: invokevirtual #236                // Method javassist/bytecode/ClassFile.getMethods:()Ljava/util/List;
      13: astore_3
      14: aload_3
      15: aload_3
      16: invokeinterface #148,  1          // InterfaceMethod java/util/List.size:()I
      21: anewarray     #208                // class javassist/bytecode/MethodInfo
      24: invokeinterface #149,  2          // InterfaceMethod java/util/List.toArray:([Ljava/lang/Object;)[Ljava/lang/Object;
      29: checkcast     #321                // class "[Ljavassist/bytecode/MethodInfo;"
      32: astore        4
      34: aload         4
      36: arraylength
      37: istore        5
      39: iconst_0
      40: istore        6
      42: iload         6
      44: iload         5
      46: if_icmpge     70
      49: aload         4
      51: iload         6
      53: aaload
      54: astore        7
      56: aload_1
      57: aload_0
      58: aload         7
      60: invokevirtual #323                // Method javassist/expr/ExprEditor.doit:(Ljavassist/CtClass;Ljavassist/bytecode/MethodInfo;)Z
      63: pop
      64: iinc          6, 1
      67: goto          42
      70: return

  public void prune();
    Code:
       0: aload_0
       1: getfield      #6                  // Field wasPruned:Z
       4: ifeq          8
       7: return
       8: aload_0
       9: aload_0
      10: iconst_1
      11: dup_x1
      12: putfield      #7                  // Field wasFrozen:Z
      15: putfield      #6                  // Field wasPruned:Z
      18: aload_0
      19: invokevirtual #102                // Method getClassFile2:()Ljavassist/bytecode/ClassFile;
      22: invokevirtual #324                // Method javassist/bytecode/ClassFile.prune:()V
      25: return

  public void rebuildClassFile();
    Code:
       0: aload_0
       1: iconst_1
       2: putfield      #5                  // Field gcConstPool:Z
       5: return

  public void toBytecode(java.io.DataOutputStream) throws javassist.CannotCompileException, java.io.IOException;
    Code:
       0: aload_0
       1: invokevirtual #84                 // Method isModified:()Z
       4: ifeq          89
       7: aload_0
       8: ldc_w         #325                // String toBytecode
      11: invokespecial #101                // Method checkPruned:(Ljava/lang/String;)V
      14: aload_0
      15: invokevirtual #102                // Method getClassFile2:()Ljavassist/bytecode/ClassFile;
      18: astore_2
      19: aload_0
      20: getfield      #5                  // Field gcConstPool:Z
      23: ifeq          35
      26: aload_2
      27: invokevirtual #326                // Method javassist/bytecode/ClassFile.compact:()V
      30: aload_0
      31: iconst_0
      32: putfield      #5                  // Field gcConstPool:Z
      35: aload_0
      36: aload_2
      37: invokespecial #327                // Method modifyClassConstructor:(Ljavassist/bytecode/ClassFile;)V
      40: aload_0
      41: aload_2
      42: invokespecial #328                // Method modifyConstructors:(Ljavassist/bytecode/ClassFile;)V
      45: getstatic     #329                // Field debugDump:Ljava/lang/String;
      48: ifnull        56
      51: aload_0
      52: aload_2
      53: invokespecial #330                // Method dumpClassFile:(Ljavassist/bytecode/ClassFile;)V
      56: aload_2
      57: aload_1
      58: invokevirtual #94                 // Method javassist/bytecode/ClassFile.write:(Ljava/io/DataOutputStream;)V
      61: aload_1
      62: invokevirtual #331                // Method java/io/DataOutputStream.flush:()V
      65: aload_0
      66: aconst_null
      67: putfield      #13                 // Field fieldInitializers:Ljavassist/FieldInitLink;
      70: aload_0
      71: getfield      #3                  // Field doPruning:Z
      74: ifeq          86
      77: aload_2
      78: invokevirtual #324                // Method javassist/bytecode/ClassFile.prune:()V
      81: aload_0
      82: iconst_1
      83: putfield      #6                  // Field wasPruned:Z
      86: goto          101
      89: aload_0
      90: getfield      #4                  // Field classPool:Ljavassist/ClassPool;
      93: aload_0
      94: invokevirtual #32                 // Method getName:()Ljava/lang/String;
      97: aload_1
      98: invokevirtual #332                // Method javassist/ClassPool.writeClassfile:(Ljava/lang/String;Ljava/io/OutputStream;)V
     101: aload_0
     102: iconst_0
     103: putfield      #16                 // Field getCount:I
     106: aload_0
     107: iconst_1
     108: putfield      #7                  // Field wasFrozen:Z
     111: goto          134
     114: astore_2
     115: new           #282                // class javassist/CannotCompileException
     118: dup
     119: aload_2
     120: invokespecial #333                // Method javassist/CannotCompileException."<init>":(Ljavassist/NotFoundException;)V
     123: athrow
     124: astore_2
     125: new           #282                // class javassist/CannotCompileException
     128: dup
     129: aload_2
     130: invokespecial #334                // Method javassist/CannotCompileException."<init>":(Ljava/lang/Throwable;)V
     133: athrow
     134: return
    Exception table:
       from    to  target type
           0   111   114   Class javassist/NotFoundException
           0   111   124   Class java/io/IOException

  private void dumpClassFile(javassist.bytecode.ClassFile) throws java.io.IOException;
    Code:
       0: aload_0
       1: getstatic     #329                // Field debugDump:Ljava/lang/String;
       4: invokevirtual #335                // Method makeFileOutput:(Ljava/lang/String;)Ljava/io/DataOutputStream;
       7: astore_2
       8: aload_1
       9: aload_2
      10: invokevirtual #94                 // Method javassist/bytecode/ClassFile.write:(Ljava/io/DataOutputStream;)V
      13: aload_2
      14: invokevirtual #336                // Method java/io/DataOutputStream.close:()V
      17: goto          27
      20: astore_3
      21: aload_2
      22: invokevirtual #336                // Method java/io/DataOutputStream.close:()V
      25: aload_3
      26: athrow
      27: return
    Exception table:
       from    to  target type
           8    13    20   any

  private void checkPruned(java.lang.String);
    Code:
       0: aload_0
       1: getfield      #6                  // Field wasPruned:Z
       4: ifeq          48
       7: new           #69                 // class java/lang/RuntimeException
      10: dup
      11: new           #37                 // class java/lang/StringBuilder
      14: dup
      15: invokespecial #38                 // Method java/lang/StringBuilder."<init>":()V
      18: aload_1
      19: invokevirtual #40                 // Method java/lang/StringBuilder.append:(Ljava/lang/String;)Ljava/lang/StringBuilder;
      22: ldc_w         #337                // String ():
      25: invokevirtual #40                 // Method java/lang/StringBuilder.append:(Ljava/lang/String;)Ljava/lang/StringBuilder;
      28: aload_0
      29: invokevirtual #32                 // Method getName:()Ljava/lang/String;
      32: invokevirtual #40                 // Method java/lang/StringBuilder.append:(Ljava/lang/String;)Ljava/lang/StringBuilder;
      35: ldc_w         #338                // String  was pruned.
      38: invokevirtual #40                 // Method java/lang/StringBuilder.append:(Ljava/lang/String;)Ljava/lang/StringBuilder;
      41: invokevirtual #41                 // Method java/lang/StringBuilder.toString:()Ljava/lang/String;
      44: invokespecial #81                 // Method java/lang/RuntimeException."<init>":(Ljava/lang/String;)V
      47: athrow
      48: return

  public boolean stopPruning(boolean);
    Code:
       0: aload_0
       1: getfield      #3                  // Field doPruning:Z
       4: ifne          11
       7: iconst_1
       8: goto          12
      11: iconst_0
      12: istore_2
      13: aload_0
      14: iload_1
      15: ifne          22
      18: iconst_1
      19: goto          23
      22: iconst_0
      23: putfield      #3                  // Field doPruning:Z
      26: iload_2
      27: ireturn

  private void modifyClassConstructor(javassist.bytecode.ClassFile) throws javassist.CannotCompileException, javassist.NotFoundException;
    Code:
       0: aload_0
       1: getfield      #13                 // Field fieldInitializers:Ljavassist/FieldInitLink;
       4: ifnonnull     8
       7: return
       8: new           #304                // class javassist/bytecode/Bytecode
      11: dup
      12: aload_1
      13: invokevirtual #117                // Method javassist/bytecode/ClassFile.getConstPool:()Ljavassist/bytecode/ConstPool;
      16: iconst_0
      17: iconst_0
      18: invokespecial #305                // Method javassist/bytecode/Bytecode."<init>":(Ljavassist/bytecode/ConstPool;II)V
      21: astore_2
      22: new           #339                // class javassist/compiler/Javac
      25: dup
      26: aload_2
      27: aload_0
      28: invokespecial #340                // Method javassist/compiler/Javac."<init>":(Ljavassist/bytecode/Bytecode;Ljavassist/CtClass;)V
      31: astore_3
      32: iconst_0
      33: istore        4
      35: iconst_0
      36: istore        5
      38: aload_0
      39: getfield      #13                 // Field fieldInitializers:Ljavassist/FieldInitLink;
      42: astore        6
      44: aload         6
      46: ifnull        113
      49: aload         6
      51: getfield      #341                // Field javassist/FieldInitLink.field:Ljavassist/CtField;
      54: astore        7
      56: aload         7
      58: invokevirtual #288                // Method javassist/CtField.getModifiers:()I
      61: invokestatic  #159                // Method javassist/Modifier.isStatic:(I)Z
      64: ifeq          103
      67: iconst_1
      68: istore        5
      70: aload         6
      72: getfield      #342                // Field javassist/FieldInitLink.init:Ljavassist/CtField$Initializer;
      75: aload         7
      77: invokevirtual #290                // Method javassist/CtField.getType:()Ljavassist/CtClass;
      80: aload         7
      82: invokevirtual #343                // Method javassist/CtField.getName:()Ljava/lang/String;
      85: aload_2
      86: aload_3
      87: invokevirtual #344                // Method javassist/CtField$Initializer.compileIfStatic:(Ljavassist/CtClass;Ljava/lang/String;Ljavassist/bytecode/Bytecode;Ljavassist/compiler/Javac;)I
      90: istore        8
      92: iload         4
      94: iload         8
      96: if_icmpge     103
      99: iload         8
     101: istore        4
     103: aload         6
     105: getfield      #299                // Field javassist/FieldInitLink.next:Ljavassist/FieldInitLink;
     108: astore        6
     110: goto          44
     113: iload         5
     115: ifeq          127
     118: aload_0
     119: aload_1
     120: aload_2
     121: iload         4
     123: iconst_0
     124: invokespecial #306                // Method modifyClassConstructor:(Ljavassist/bytecode/ClassFile;Ljavassist/bytecode/Bytecode;II)V
     127: return

  private void modifyClassConstructor(javassist.bytecode.ClassFile, javassist.bytecode.Bytecode, int, int) throws javassist.CannotCompileException;
    Code:
       0: aload_1
       1: invokevirtual #345                // Method javassist/bytecode/ClassFile.getStaticInitializer:()Ljavassist/bytecode/MethodInfo;
       4: astore        5
       6: aload         5
       8: ifnonnull     98
      11: aload_2
      12: sipush        177
      15: invokevirtual #346                // Method javassist/bytecode/Bytecode.add:(I)V
      18: aload_2
      19: iload_3
      20: invokevirtual #347                // Method javassist/bytecode/Bytecode.setMaxStack:(I)V
      23: aload_2
      24: iload         4
      26: invokevirtual #348                // Method javassist/bytecode/Bytecode.setMaxLocals:(I)V
      29: new           #208                // class javassist/bytecode/MethodInfo
      32: dup
      33: aload_1
      34: invokevirtual #117                // Method javassist/bytecode/ClassFile.getConstPool:()Ljavassist/bytecode/ConstPool;
      37: ldc           #212                // String <clinit>
      39: ldc_w         #349                // String ()V
      42: invokespecial #350                // Method javassist/bytecode/MethodInfo."<init>":(Ljavassist/bytecode/ConstPool;Ljava/lang/String;Ljava/lang/String;)V
      45: astore        5
      47: aload         5
      49: bipush        8
      51: invokevirtual #351                // Method javassist/bytecode/MethodInfo.setAccessFlags:(I)V
      54: aload         5
      56: aload_2
      57: invokevirtual #352                // Method javassist/bytecode/Bytecode.toCodeAttribute:()Ljavassist/bytecode/CodeAttribute;
      60: invokevirtual #353                // Method javassist/bytecode/MethodInfo.setCodeAttribute:(Ljavassist/bytecode/CodeAttribute;)V
      63: aload_1
      64: aload         5
      66: invokevirtual #308                // Method javassist/bytecode/ClassFile.addMethod:(Ljavassist/bytecode/MethodInfo;)V
      69: aload_0
      70: invokevirtual #89                 // Method hasMemberCache:()Ljavassist/CtMember$Cache;
      73: astore        6
      75: aload         6
      77: ifnull        95
      80: aload         6
      82: new           #241                // class javassist/CtConstructor
      85: dup
      86: aload         5
      88: aload_0
      89: invokespecial #242                // Method javassist/CtConstructor."<init>":(Ljavassist/bytecode/MethodInfo;Ljavassist/CtClass;)V
      92: invokevirtual #243                // Method javassist/CtMember$Cache.addConstructor:(Ljavassist/CtMember;)V
      95: goto          205
      98: aload         5
     100: invokevirtual #354                // Method javassist/bytecode/MethodInfo.getCodeAttribute:()Ljavassist/bytecode/CodeAttribute;
     103: astore        6
     105: aload         6
     107: ifnonnull     121
     110: new           #282                // class javassist/CannotCompileException
     113: dup
     114: ldc_w         #355                // String empty <clinit>
     117: invokespecial #284                // Method javassist/CannotCompileException."<init>":(Ljava/lang/String;)V
     120: athrow
     121: aload         6
     123: invokevirtual #356                // Method javassist/bytecode/CodeAttribute.iterator:()Ljavassist/bytecode/CodeIterator;
     126: astore        7
     128: aload         7
     130: aload_2
     131: invokevirtual #357                // Method javassist/bytecode/Bytecode.get:()[B
     134: invokevirtual #358                // Method javassist/bytecode/CodeIterator.insertEx:([B)I
     137: istore        8
     139: aload         7
     141: aload_2
     142: invokevirtual #359                // Method javassist/bytecode/Bytecode.getExceptionTable:()Ljavassist/bytecode/ExceptionTable;
     145: iload         8
     147: invokevirtual #360                // Method javassist/bytecode/CodeIterator.insert:(Ljavassist/bytecode/ExceptionTable;I)V
     150: aload         6
     152: invokevirtual #361                // Method javassist/bytecode/CodeAttribute.getMaxStack:()I
     155: istore        9
     157: iload         9
     159: iload_3
     160: if_icmpge     169
     163: aload         6
     165: iload_3
     166: invokevirtual #362                // Method javassist/bytecode/CodeAttribute.setMaxStack:(I)V
     169: aload         6
     171: invokevirtual #363                // Method javassist/bytecode/CodeAttribute.getMaxLocals:()I
     174: istore        10
     176: iload         10
     178: iload         4
     180: if_icmpge     190
     183: aload         6
     185: iload         4
     187: invokevirtual #364                // Method javassist/bytecode/CodeAttribute.setMaxLocals:(I)V
     190: goto          205
     193: astore        7
     195: new           #282                // class javassist/CannotCompileException
     198: dup
     199: aload         7
     201: invokespecial #334                // Method javassist/CannotCompileException."<init>":(Ljava/lang/Throwable;)V
     204: athrow
     205: aload         5
     207: aload_0
     208: getfield      #4                  // Field classPool:Ljavassist/ClassPool;
     211: aload_1
     212: invokevirtual #366                // Method javassist/bytecode/MethodInfo.rebuildStackMapIf6:(Ljavassist/ClassPool;Ljavassist/bytecode/ClassFile;)V
     215: goto          230
     218: astore        6
     220: new           #282                // class javassist/CannotCompileException
     223: dup
     224: aload         6
     226: invokespecial #334                // Method javassist/CannotCompileException."<init>":(Ljava/lang/Throwable;)V
     229: athrow
     230: return
    Exception table:
       from    to  target type
         121   190   193   Class javassist/bytecode/BadBytecode
         205   215   218   Class javassist/bytecode/BadBytecode

  private void modifyConstructors(javassist.bytecode.ClassFile) throws javassist.CannotCompileException, javassist.NotFoundException;
    Code:
       0: aload_0
       1: getfield      #13                 // Field fieldInitializers:Ljavassist/FieldInitLink;
       4: ifnonnull     8
       7: return
       8: aload_1
       9: invokevirtual #117                // Method javassist/bytecode/ClassFile.getConstPool:()Ljavassist/bytecode/ConstPool;
      12: astore_2
      13: aload_1
      14: invokevirtual #236                // Method javassist/bytecode/ClassFile.getMethods:()Ljava/util/List;
      17: astore_3
      18: aload_3
      19: invokeinterface #229,  1          // InterfaceMethod java/util/List.iterator:()Ljava/util/Iterator;
      24: astore        4
      26: aload         4
      28: invokeinterface #230,  1          // InterfaceMethod java/util/Iterator.hasNext:()Z
      33: ifeq          145
      36: aload         4
      38: invokeinterface #231,  1          // InterfaceMethod java/util/Iterator.next:()Ljava/lang/Object;
      43: checkcast     #208                // class javassist/bytecode/MethodInfo
      46: astore        5
      48: aload         5
      50: invokevirtual #367                // Method javassist/bytecode/MethodInfo.isConstructor:()Z
      53: ifeq          142
      56: aload         5
      58: invokevirtual #354                // Method javassist/bytecode/MethodInfo.getCodeAttribute:()Ljavassist/bytecode/CodeAttribute;
      61: astore        6
      63: aload         6
      65: ifnull        142
      68: new           #304                // class javassist/bytecode/Bytecode
      71: dup
      72: aload_2
      73: iconst_0
      74: aload         6
      76: invokevirtual #363                // Method javassist/bytecode/CodeAttribute.getMaxLocals:()I
      79: invokespecial #305                // Method javassist/bytecode/Bytecode."<init>":(Ljavassist/bytecode/ConstPool;II)V
      82: astore        7
      84: aload         5
      86: invokevirtual #185                // Method javassist/bytecode/MethodInfo.getDescriptor:()Ljava/lang/String;
      89: aload_0
      90: getfield      #4                  // Field classPool:Ljavassist/ClassPool;
      93: invokestatic  #368                // Method javassist/bytecode/Descriptor.getParameterTypes:(Ljava/lang/String;Ljavassist/ClassPool;)[Ljavassist/CtClass;
      96: astore        8
      98: aload_0
      99: aload         7
     101: aload         8
     103: invokespecial #369                // Method makeFieldInitializer:(Ljavassist/bytecode/Bytecode;[Ljavassist/CtClass;)I
     106: istore        9
     108: aload         6
     110: aload         7
     112: iload         9
     114: invokestatic  #370                // Method insertAuxInitializer:(Ljavassist/bytecode/CodeAttribute;Ljavassist/bytecode/Bytecode;I)V
     117: aload         5
     119: aload_0
     120: getfield      #4                  // Field classPool:Ljavassist/ClassPool;
     123: aload_1
     124: invokevirtual #366                // Method javassist/bytecode/MethodInfo.rebuildStackMapIf6:(Ljavassist/ClassPool;Ljavassist/bytecode/ClassFile;)V
     127: goto          142
     130: astore        7
     132: new           #282                // class javassist/CannotCompileException
     135: dup
     136: aload         7
     138: invokespecial #334                // Method javassist/CannotCompileException."<init>":(Ljava/lang/Throwable;)V
     141: athrow
     142: goto          26
     145: return
    Exception table:
       from    to  target type
          68   127   130   Class javassist/bytecode/BadBytecode

  private static void insertAuxInitializer(javassist.bytecode.CodeAttribute, javassist.bytecode.Bytecode, int) throws javassist.bytecode.BadBytecode;
    Code:
       0: aload_0
       1: invokevirtual #356                // Method javassist/bytecode/CodeAttribute.iterator:()Ljavassist/bytecode/CodeIterator;
       4: astore_3
       5: aload_3
       6: invokevirtual #371                // Method javassist/bytecode/CodeIterator.skipSuperConstructor:()I
       9: istore        4
      11: iload         4
      13: ifge          28
      16: aload_3
      17: invokevirtual #372                // Method javassist/bytecode/CodeIterator.skipThisConstructor:()I
      20: istore        4
      22: iload         4
      24: iflt          28
      27: return
      28: aload_3
      29: aload_1
      30: invokevirtual #357                // Method javassist/bytecode/Bytecode.get:()[B
      33: invokevirtual #358                // Method javassist/bytecode/CodeIterator.insertEx:([B)I
      36: istore        5
      38: aload_3
      39: aload_1
      40: invokevirtual #359                // Method javassist/bytecode/Bytecode.getExceptionTable:()Ljavassist/bytecode/ExceptionTable;
      43: iload         5
      45: invokevirtual #360                // Method javassist/bytecode/CodeIterator.insert:(Ljavassist/bytecode/ExceptionTable;I)V
      48: aload_0
      49: invokevirtual #361                // Method javassist/bytecode/CodeAttribute.getMaxStack:()I
      52: istore        6
      54: iload         6
      56: iload_2
      57: if_icmpge     65
      60: aload_0
      61: iload_2
      62: invokevirtual #362                // Method javassist/bytecode/CodeAttribute.setMaxStack:(I)V
      65: return

  private int makeFieldInitializer(javassist.bytecode.Bytecode, javassist.CtClass[]) throws javassist.CannotCompileException, javassist.NotFoundException;
    Code:
       0: iconst_0
       1: istore_3
       2: new           #339                // class javassist/compiler/Javac
       5: dup
       6: aload_1
       7: aload_0
       8: invokespecial #340                // Method javassist/compiler/Javac."<init>":(Ljavassist/bytecode/Bytecode;Ljavassist/CtClass;)V
      11: astore        4
      13: aload         4
      15: aload_2
      16: iconst_0
      17: invokevirtual #373                // Method javassist/compiler/Javac.recordParams:([Ljavassist/CtClass;Z)I
      20: pop
      21: goto          36
      24: astore        5
      26: new           #282                // class javassist/CannotCompileException
      29: dup
      30: aload         5
      32: invokespecial #375                // Method javassist/CannotCompileException."<init>":(Ljavassist/compiler/CompileError;)V
      35: athrow
      36: aload_0
      37: getfield      #13                 // Field fieldInitializers:Ljavassist/FieldInitLink;
      40: astore        5
      42: aload         5
      44: ifnull        108
      47: aload         5
      49: getfield      #341                // Field javassist/FieldInitLink.field:Ljavassist/CtField;
      52: astore        6
      54: aload         6
      56: invokevirtual #288                // Method javassist/CtField.getModifiers:()I
      59: invokestatic  #159                // Method javassist/Modifier.isStatic:(I)Z
      62: ifne          98
      65: aload         5
      67: getfield      #342                // Field javassist/FieldInitLink.init:Ljavassist/CtField$Initializer;
      70: aload         6
      72: invokevirtual #290                // Method javassist/CtField.getType:()Ljavassist/CtClass;
      75: aload         6
      77: invokevirtual #343                // Method javassist/CtField.getName:()Ljava/lang/String;
      80: aload_1
      81: aload_2
      82: aload         4
      84: invokevirtual #376                // Method javassist/CtField$Initializer.compile:(Ljavassist/CtClass;Ljava/lang/String;Ljavassist/bytecode/Bytecode;[Ljavassist/CtClass;Ljavassist/compiler/Javac;)I
      87: istore        7
      89: iload_3
      90: iload         7
      92: if_icmpge     98
      95: iload         7
      97: istore_3
      98: aload         5
     100: getfield      #299                // Field javassist/FieldInitLink.next:Ljavassist/FieldInitLink;
     103: astore        5
     105: goto          42
     108: iload_3
     109: ireturn
    Exception table:
       from    to  target type
          13    21    24   Class javassist/compiler/CompileError

  java.util.Map<javassist.CtMethod, java.lang.String> getHiddenMethods();
    Code:
       0: aload_0
       1: getfield      #14                 // Field hiddenMethods:Ljava/util/Map;
       4: ifnonnull     18
       7: aload_0
       8: new           #377                // class java/util/Hashtable
      11: dup
      12: invokespecial #378                // Method java/util/Hashtable."<init>":()V
      15: putfield      #14                 // Field hiddenMethods:Ljava/util/Map;
      18: aload_0
      19: getfield      #14                 // Field hiddenMethods:Ljava/util/Map;
      22: areturn

  int getUniqueNumber();
    Code:
       0: aload_0
       1: dup
       2: getfield      #15                 // Field uniqueNumberSeed:I
       5: dup_x1
       6: iconst_1
       7: iadd
       8: putfield      #15                 // Field uniqueNumberSeed:I
      11: ireturn

  public java.lang.String makeUniqueName(java.lang.String);
    Code:
       0: new           #266                // class java/util/HashMap
       3: dup
       4: invokespecial #267                // Method java/util/HashMap."<init>":()V
       7: astore_2
       8: aload_0
       9: aload_2
      10: invokespecial #379                // Method makeMemberList:(Ljava/util/Map;)V
      13: aload_2
      14: invokeinterface #380,  1          // InterfaceMethod java/util/Map.keySet:()Ljava/util/Set;
      19: astore_3
      20: aload_3
      21: invokeinterface #381,  1          // InterfaceMethod java/util/Set.size:()I
      26: anewarray     #17                 // class java/lang/String
      29: astore        4
      31: aload_3
      32: aload         4
      34: invokeinterface #382,  2          // InterfaceMethod java/util/Set.toArray:([Ljava/lang/Object;)[Ljava/lang/Object;
      39: pop
      40: aload_1
      41: aload         4
      43: invokestatic  #383                // Method notFindInArray:(Ljava/lang/String;[Ljava/lang/String;)Z
      46: ifeq          51
      49: aload_1
      50: areturn
      51: bipush        100
      53: istore        5
      55: iload         5
      57: sipush        999
      60: if_icmple     74
      63: new           #69                 // class java/lang/RuntimeException
      66: dup
      67: ldc_w         #384                // String too many unique name
      70: invokespecial #81                 // Method java/lang/RuntimeException."<init>":(Ljava/lang/String;)V
      73: athrow
      74: new           #37                 // class java/lang/StringBuilder
      77: dup
      78: invokespecial #38                 // Method java/lang/StringBuilder."<init>":()V
      81: aload_1
      82: invokevirtual #40                 // Method java/lang/StringBuilder.append:(Ljava/lang/String;)Ljava/lang/StringBuilder;
      85: iload         5
      87: iinc          5, 1
      90: invokevirtual #385                // Method java/lang/StringBuilder.append:(I)Ljava/lang/StringBuilder;
      93: invokevirtual #41                 // Method java/lang/StringBuilder.toString:()Ljava/lang/String;
      96: astore        6
      98: aload         6
     100: aload         4
     102: invokestatic  #383                // Method notFindInArray:(Ljava/lang/String;[Ljava/lang/String;)Z
     105: ifeq          55
     108: aload         6
     110: areturn

  private static boolean notFindInArray(java.lang.String, java.lang.String[]);
    Code:
       0: aload_1
       1: arraylength
       2: istore_2
       3: iconst_0
       4: istore_3
       5: iload_3
       6: iload_2
       7: if_icmpge     28
      10: aload_1
      11: iload_3
      12: aaload
      13: aload_0
      14: invokevirtual #144                // Method java/lang/String.startsWith:(Ljava/lang/String;)Z
      17: ifeq          22
      20: iconst_0
      21: ireturn
      22: iinc          3, 1
      25: goto          5
      28: iconst_1
      29: ireturn

  private void makeMemberList(java.util.Map<java.lang.Object, javassist.CtClassType>);
    Code:
       0: aload_0
       1: invokevirtual #29                 // Method getModifiers:()I
       4: istore_2
       5: iload_2
       6: invokestatic  #386                // Method javassist/Modifier.isAbstract:(I)Z
       9: ifne          19
      12: iload_2
      13: invokestatic  #128                // Method javassist/Modifier.isInterface:(I)Z
      16: ifeq          81
      19: aload_0
      20: invokevirtual #44                 // Method getInterfaces:()[Ljavassist/CtClass;
      23: astore_3
      24: aload_3
      25: astore        4
      27: aload         4
      29: arraylength
      30: istore        5
      32: iconst_0
      33: istore        6
      35: iload         6
      37: iload         5
      39: if_icmpge     77
      42: aload         4
      44: iload         6
      46: aaload
      47: astore        7
      49: aload         7
      51: ifnull        71
      54: aload         7
      56: instanceof    #66                 // class javassist/CtClassType
      59: ifeq          71
      62: aload         7
      64: checkcast     #66                 // class javassist/CtClassType
      67: aload_1
      68: invokespecial #379                // Method makeMemberList:(Ljava/util/Map;)V
      71: iinc          6, 1
      74: goto          35
      77: goto          81
      80: astore_3
      81: aload_0
      82: invokevirtual #33                 // Method getSuperclass:()Ljavassist/CtClass;
      85: astore_3
      86: aload_3
      87: ifnull        105
      90: aload_3
      91: instanceof    #66                 // class javassist/CtClassType
      94: ifeq          105
      97: aload_3
      98: checkcast     #66                 // class javassist/CtClassType
     101: aload_1
     102: invokespecial #379                // Method makeMemberList:(Ljava/util/Map;)V
     105: goto          109
     108: astore_3
     109: aload_0
     110: invokevirtual #102                // Method getClassFile2:()Ljavassist/bytecode/ClassFile;
     113: invokevirtual #236                // Method javassist/bytecode/ClassFile.getMethods:()Ljava/util/List;
     116: astore_3
     117: aload_3
     118: invokeinterface #229,  1          // InterfaceMethod java/util/List.iterator:()Ljava/util/Iterator;
     123: astore        4
     125: aload         4
     127: invokeinterface #230,  1          // InterfaceMethod java/util/Iterator.hasNext:()Z
     132: ifeq          163
     135: aload         4
     137: invokeinterface #231,  1          // InterfaceMethod java/util/Iterator.next:()Ljava/lang/Object;
     142: checkcast     #208                // class javassist/bytecode/MethodInfo
     145: astore        5
     147: aload_1
     148: aload         5
     150: invokevirtual #387                // Method javassist/bytecode/MethodInfo.getName:()Ljava/lang/String;
     153: aload_0
     154: invokeinterface #274,  3          // InterfaceMethod java/util/Map.put:(Ljava/lang/Object;Ljava/lang/Object;)Ljava/lang/Object;
     159: pop
     160: goto          125
     163: aload_0
     164: invokevirtual #102                // Method getClassFile2:()Ljavassist/bytecode/ClassFile;
     167: invokevirtual #228                // Method javassist/bytecode/ClassFile.getFields:()Ljava/util/List;
     170: astore        4
     172: aload         4
     174: invokeinterface #229,  1          // InterfaceMethod java/util/List.iterator:()Ljava/util/Iterator;
     179: astore        5
     181: aload         5
     183: invokeinterface #230,  1          // InterfaceMethod java/util/Iterator.hasNext:()Z
     188: ifeq          219
     191: aload         5
     193: invokeinterface #231,  1          // InterfaceMethod java/util/Iterator.next:()Ljava/lang/Object;
     198: checkcast     #232                // class javassist/bytecode/FieldInfo
     201: astore        6
     203: aload_1
     204: aload         6
     206: invokevirtual #388                // Method javassist/bytecode/FieldInfo.getName:()Ljava/lang/String;
     209: aload_0
     210: invokeinterface #274,  3          // InterfaceMethod java/util/Map.put:(Ljava/lang/Object;Ljava/lang/Object;)Ljava/lang/Object;
     215: pop
     216: goto          181
     219: return
    Exception table:
       from    to  target type
          19    77    80   Class javassist/NotFoundException
          81   105   108   Class javassist/NotFoundException
}
