Compiled from "CtNewWrappedMethod.java"
class javassist.CtNewWrappedMethod {
  private static final java.lang.String addedWrappedMethod;

  javassist.CtNewWrappedMethod();
    Code:
       0: aload_0
       1: invokespecial #1                  // Method java/lang/Object."<init>":()V
       4: return

  public static javassist.CtMethod wrapped(javassist.CtClass, java.lang.String, javassist.CtClass[], javassist.CtClass[], javassist.CtMethod, javassist.CtMethod$ConstParameter, javassist.CtClass) throws javassist.CannotCompileException;
    Code:
       0: new           #2                  // class javassist/CtMethod
       3: dup
       4: aload_0
       5: aload_1
       6: aload_2
       7: aload         6
       9: invokespecial #3                  // Method javassist/CtMethod."<init>":(Ljavassist/CtClass;Ljava/lang/String;[Ljavassist/CtClass;Ljavassist/CtClass;)V
      12: astore        7
      14: aload         7
      16: aload         4
      18: invokevirtual #4                  // Method javassist/CtMethod.getModifiers:()I
      21: invokevirtual #5                  // Method javassist/CtMethod.setModifiers:(I)V
      24: aload         7
      26: aload_3
      27: invokevirtual #6                  // Method javassist/CtMethod.setExceptionTypes:([Ljavassist/CtClass;)V
      30: goto          45
      33: astore        8
      35: new           #8                  // class javassist/CannotCompileException
      38: dup
      39: aload         8
      41: invokespecial #9                  // Method javassist/CannotCompileException."<init>":(Ljavassist/NotFoundException;)V
      44: athrow
      45: aload         6
      47: aload         6
      49: invokevirtual #10                 // Method javassist/CtClass.getClassFile2:()Ljavassist/bytecode/ClassFile;
      52: aload         4
      54: aload_2
      55: aload_0
      56: aload         5
      58: invokestatic  #11                 // Method makeBody:(Ljavassist/CtClass;Ljavassist/bytecode/ClassFile;Ljavassist/CtMethod;[Ljavassist/CtClass;Ljavassist/CtClass;Ljavassist/CtMethod$ConstParameter;)Ljavassist/bytecode/Bytecode;
      61: astore        8
      63: aload         7
      65: invokevirtual #12                 // Method javassist/CtMethod.getMethodInfo2:()Ljavassist/bytecode/MethodInfo;
      68: astore        9
      70: aload         9
      72: aload         8
      74: invokevirtual #13                 // Method javassist/bytecode/Bytecode.toCodeAttribute:()Ljavassist/bytecode/CodeAttribute;
      77: invokevirtual #14                 // Method javassist/bytecode/MethodInfo.setCodeAttribute:(Ljavassist/bytecode/CodeAttribute;)V
      80: aload         7
      82: areturn
    Exception table:
       from    to  target type
          24    30    33   Class javassist/NotFoundException

  static javassist.bytecode.Bytecode makeBody(javassist.CtClass, javassist.bytecode.ClassFile, javassist.CtMethod, javassist.CtClass[], javassist.CtClass, javassist.CtMethod$ConstParameter) throws javassist.CannotCompileException;
    Code:
       0: aload_2
       1: invokevirtual #4                  // Method javassist/CtMethod.getModifiers:()I
       4: invokestatic  #15                 // Method javassist/Modifier.isStatic:(I)Z
       7: istore        6
       9: new           #16                 // class javassist/bytecode/Bytecode
      12: dup
      13: aload_1
      14: invokevirtual #17                 // Method javassist/bytecode/ClassFile.getConstPool:()Ljavassist/bytecode/ConstPool;
      17: iconst_0
      18: iconst_0
      19: invokespecial #18                 // Method javassist/bytecode/Bytecode."<init>":(Ljavassist/bytecode/ConstPool;II)V
      22: astore        7
      24: aload_0
      25: aload_1
      26: aload_2
      27: iload         6
      29: aload_3
      30: aload         4
      32: aload         5
      34: aload         7
      36: invokestatic  #19                 // Method makeBody0:(Ljavassist/CtClass;Ljavassist/bytecode/ClassFile;Ljavassist/CtMethod;Z[Ljavassist/CtClass;Ljavassist/CtClass;Ljavassist/CtMethod$ConstParameter;Ljavassist/bytecode/Bytecode;)I
      39: istore        8
      41: aload         7
      43: iload         8
      45: invokevirtual #20                 // Method javassist/bytecode/Bytecode.setMaxStack:(I)V
      48: aload         7
      50: iload         6
      52: aload_3
      53: iconst_0
      54: invokevirtual #21                 // Method javassist/bytecode/Bytecode.setMaxLocals:(Z[Ljavassist/CtClass;I)V
      57: aload         7
      59: areturn

  protected static int makeBody0(javassist.CtClass, javassist.bytecode.ClassFile, javassist.CtMethod, boolean, javassist.CtClass[], javassist.CtClass, javassist.CtMethod$ConstParameter, javassist.bytecode.Bytecode) throws javassist.CannotCompileException;
    Code:
       0: aload_0
       1: instanceof    #22                 // class javassist/CtClassType
       4: ifne          37
       7: new           #8                  // class javassist/CannotCompileException
      10: dup
      11: new           #23                 // class java/lang/StringBuilder
      14: dup
      15: invokespecial #24                 // Method java/lang/StringBuilder."<init>":()V
      18: ldc           #25                 // String bad declaring class
      20: invokevirtual #26                 // Method java/lang/StringBuilder.append:(Ljava/lang/String;)Ljava/lang/StringBuilder;
      23: aload_0
      24: invokevirtual #27                 // Method javassist/CtClass.getName:()Ljava/lang/String;
      27: invokevirtual #26                 // Method java/lang/StringBuilder.append:(Ljava/lang/String;)Ljava/lang/StringBuilder;
      30: invokevirtual #28                 // Method java/lang/StringBuilder.toString:()Ljava/lang/String;
      33: invokespecial #29                 // Method javassist/CannotCompileException."<init>":(Ljava/lang/String;)V
      36: athrow
      37: iload_3
      38: ifne          47
      41: aload         7
      43: iconst_0
      44: invokevirtual #30                 // Method javassist/bytecode/Bytecode.addAload:(I)V
      47: aload         7
      49: aload         4
      51: iload_3
      52: ifeq          59
      55: iconst_0
      56: goto          60
      59: iconst_1
      60: invokestatic  #31                 // Method compileParameterList:(Ljavassist/bytecode/Bytecode;[Ljavassist/CtClass;I)I
      63: istore        8
      65: aload         6
      67: ifnonnull     81
      70: iconst_0
      71: istore        9
      73: invokestatic  #32                 // Method javassist/CtMethod$ConstParameter.defaultDescriptor:()Ljava/lang/String;
      76: astore        10
      78: goto          97
      81: aload         6
      83: aload         7
      85: invokevirtual #33                 // Method javassist/CtMethod$ConstParameter.compile:(Ljavassist/bytecode/Bytecode;)I
      88: istore        9
      90: aload         6
      92: invokevirtual #34                 // Method javassist/CtMethod$ConstParameter.descriptor:()Ljava/lang/String;
      95: astore        10
      97: aload_2
      98: aload         10
     100: invokestatic  #35                 // Method checkSignature:(Ljavassist/CtMethod;Ljava/lang/String;)V
     103: aload_0
     104: checkcast     #22                 // class javassist/CtClassType
     107: aload_1
     108: aload_2
     109: invokestatic  #36                 // Method addBodyMethod:(Ljavassist/CtClassType;Ljavassist/bytecode/ClassFile;Ljavassist/CtMethod;)Ljava/lang/String;
     112: astore        11
     114: goto          129
     117: astore        12
     119: new           #8                  // class javassist/CannotCompileException
     122: dup
     123: aload         12
     125: invokespecial #38                 // Method javassist/CannotCompileException."<init>":(Ljava/lang/Throwable;)V
     128: athrow
     129: iload_3
     130: ifeq          148
     133: aload         7
     135: getstatic     #39                 // Field javassist/bytecode/Bytecode.THIS:Ljavassist/CtClass;
     138: aload         11
     140: aload         10
     142: invokevirtual #40                 // Method javassist/bytecode/Bytecode.addInvokestatic:(Ljavassist/CtClass;Ljava/lang/String;Ljava/lang/String;)V
     145: goto          160
     148: aload         7
     150: getstatic     #39                 // Field javassist/bytecode/Bytecode.THIS:Ljavassist/CtClass;
     153: aload         11
     155: aload         10
     157: invokevirtual #41                 // Method javassist/bytecode/Bytecode.addInvokespecial:(Ljavassist/CtClass;Ljava/lang/String;Ljava/lang/String;)V
     160: aload         7
     162: aload         5
     164: invokestatic  #42                 // Method compileReturn:(Ljavassist/bytecode/Bytecode;Ljavassist/CtClass;)V
     167: iload         8
     169: iload         9
     171: iconst_2
     172: iadd
     173: if_icmpge     182
     176: iload         9
     178: iconst_2
     179: iadd
     180: istore        8
     182: iload         8
     184: ireturn
    Exception table:
       from    to  target type
         103   114   117   Class javassist/bytecode/BadBytecode

  private static void checkSignature(javassist.CtMethod, java.lang.String) throws javassist.CannotCompileException;
    Code:
       0: aload_1
       1: aload_0
       2: invokevirtual #12                 // Method javassist/CtMethod.getMethodInfo2:()Ljavassist/bytecode/MethodInfo;
       5: invokevirtual #43                 // Method javassist/bytecode/MethodInfo.getDescriptor:()Ljava/lang/String;
       8: invokevirtual #44                 // Method java/lang/String.equals:(Ljava/lang/Object;)Z
      11: ifne          59
      14: new           #8                  // class javassist/CannotCompileException
      17: dup
      18: new           #23                 // class java/lang/StringBuilder
      21: dup
      22: invokespecial #24                 // Method java/lang/StringBuilder."<init>":()V
      25: ldc           #45                 // String wrapped method with a bad signature:
      27: invokevirtual #26                 // Method java/lang/StringBuilder.append:(Ljava/lang/String;)Ljava/lang/StringBuilder;
      30: aload_0
      31: invokevirtual #46                 // Method javassist/CtMethod.getDeclaringClass:()Ljavassist/CtClass;
      34: invokevirtual #27                 // Method javassist/CtClass.getName:()Ljava/lang/String;
      37: invokevirtual #26                 // Method java/lang/StringBuilder.append:(Ljava/lang/String;)Ljava/lang/StringBuilder;
      40: bipush        46
      42: invokevirtual #47                 // Method java/lang/StringBuilder.append:(C)Ljava/lang/StringBuilder;
      45: aload_0
      46: invokevirtual #48                 // Method javassist/CtMethod.getName:()Ljava/lang/String;
      49: invokevirtual #26                 // Method java/lang/StringBuilder.append:(Ljava/lang/String;)Ljava/lang/StringBuilder;
      52: invokevirtual #28                 // Method java/lang/StringBuilder.toString:()Ljava/lang/String;
      55: invokespecial #29                 // Method javassist/CannotCompileException."<init>":(Ljava/lang/String;)V
      58: athrow
      59: return

  private static java.lang.String addBodyMethod(javassist.CtClassType, javassist.bytecode.ClassFile, javassist.CtMethod) throws javassist.bytecode.BadBytecode, javassist.CannotCompileException;
    Code:
       0: aload_0
       1: invokevirtual #49                 // Method javassist/CtClassType.getHiddenMethods:()Ljava/util/Map;
       4: astore_3
       5: aload_3
       6: aload_2
       7: invokeinterface #50,  2           // InterfaceMethod java/util/Map.get:(Ljava/lang/Object;)Ljava/lang/Object;
      12: checkcast     #51                 // class java/lang/String
      15: astore        4
      17: aload         4
      19: ifnonnull     177
      22: new           #23                 // class java/lang/StringBuilder
      25: dup
      26: invokespecial #24                 // Method java/lang/StringBuilder."<init>":()V
      29: ldc           #53                 // String _added_m$
      31: invokevirtual #26                 // Method java/lang/StringBuilder.append:(Ljava/lang/String;)Ljava/lang/StringBuilder;
      34: aload_0
      35: invokevirtual #54                 // Method javassist/CtClassType.getUniqueNumber:()I
      38: invokevirtual #55                 // Method java/lang/StringBuilder.append:(I)Ljava/lang/StringBuilder;
      41: invokevirtual #28                 // Method java/lang/StringBuilder.toString:()Ljava/lang/String;
      44: astore        4
      46: aload_1
      47: aload         4
      49: invokevirtual #56                 // Method javassist/bytecode/ClassFile.getMethod:(Ljava/lang/String;)Ljavassist/bytecode/MethodInfo;
      52: ifnonnull     22
      55: new           #57                 // class javassist/ClassMap
      58: dup
      59: invokespecial #58                 // Method javassist/ClassMap."<init>":()V
      62: astore        5
      64: aload         5
      66: aload_2
      67: invokevirtual #46                 // Method javassist/CtMethod.getDeclaringClass:()Ljavassist/CtClass;
      70: invokevirtual #27                 // Method javassist/CtClass.getName:()Ljava/lang/String;
      73: aload_0
      74: invokevirtual #59                 // Method javassist/CtClassType.getName:()Ljava/lang/String;
      77: invokevirtual #60                 // Method javassist/ClassMap.put:(Ljava/lang/String;Ljava/lang/String;)Ljava/lang/String;
      80: pop
      81: new           #61                 // class javassist/bytecode/MethodInfo
      84: dup
      85: aload_1
      86: invokevirtual #17                 // Method javassist/bytecode/ClassFile.getConstPool:()Ljavassist/bytecode/ConstPool;
      89: aload         4
      91: aload_2
      92: invokevirtual #12                 // Method javassist/CtMethod.getMethodInfo2:()Ljavassist/bytecode/MethodInfo;
      95: aload         5
      97: invokespecial #62                 // Method javassist/bytecode/MethodInfo."<init>":(Ljavassist/bytecode/ConstPool;Ljava/lang/String;Ljavassist/bytecode/MethodInfo;Ljava/util/Map;)V
     100: astore        6
     102: aload         6
     104: invokevirtual #63                 // Method javassist/bytecode/MethodInfo.getAccessFlags:()I
     107: istore        7
     109: aload         6
     111: iload         7
     113: invokestatic  #64                 // Method javassist/bytecode/AccessFlag.setPrivate:(I)I
     116: invokevirtual #65                 // Method javassist/bytecode/MethodInfo.setAccessFlags:(I)V
     119: aload         6
     121: new           #66                 // class javassist/bytecode/SyntheticAttribute
     124: dup
     125: aload_1
     126: invokevirtual #17                 // Method javassist/bytecode/ClassFile.getConstPool:()Ljavassist/bytecode/ConstPool;
     129: invokespecial #67                 // Method javassist/bytecode/SyntheticAttribute."<init>":(Ljavassist/bytecode/ConstPool;)V
     132: invokevirtual #68                 // Method javassist/bytecode/MethodInfo.addAttribute:(Ljavassist/bytecode/AttributeInfo;)V
     135: aload_1
     136: aload         6
     138: invokevirtual #69                 // Method javassist/bytecode/ClassFile.addMethod:(Ljavassist/bytecode/MethodInfo;)V
     141: aload_3
     142: aload_2
     143: aload         4
     145: invokeinterface #70,  3           // InterfaceMethod java/util/Map.put:(Ljava/lang/Object;Ljava/lang/Object;)Ljava/lang/Object;
     150: pop
     151: aload_0
     152: invokevirtual #71                 // Method javassist/CtClassType.hasMemberCache:()Ljavassist/CtMember$Cache;
     155: astore        8
     157: aload         8
     159: ifnull        177
     162: aload         8
     164: new           #2                  // class javassist/CtMethod
     167: dup
     168: aload         6
     170: aload_0
     171: invokespecial #72                 // Method javassist/CtMethod."<init>":(Ljavassist/bytecode/MethodInfo;Ljavassist/CtClass;)V
     174: invokevirtual #73                 // Method javassist/CtMember$Cache.addMethod:(Ljavassist/CtMember;)V
     177: aload         4
     179: areturn

  static int compileParameterList(javassist.bytecode.Bytecode, javassist.CtClass[], int);
    Code:
       0: aload_0
       1: aload_1
       2: iload_2
       3: invokestatic  #74                 // Method javassist/compiler/JvstCodeGen.compileParameterList:(Ljavassist/bytecode/Bytecode;[Ljavassist/CtClass;I)I
       6: ireturn

  private static void compileReturn(javassist.bytecode.Bytecode, javassist.CtClass);
    Code:
       0: aload_1
       1: invokevirtual #75                 // Method javassist/CtClass.isPrimitive:()Z
       4: ifeq          53
       7: aload_1
       8: checkcast     #76                 // class javassist/CtPrimitiveType
      11: astore_2
      12: aload_2
      13: getstatic     #77                 // Field javassist/CtClass.voidType:Ljavassist/CtClass;
      16: if_acmpeq     42
      19: aload_2
      20: invokevirtual #78                 // Method javassist/CtPrimitiveType.getWrapperName:()Ljava/lang/String;
      23: astore_3
      24: aload_0
      25: aload_3
      26: invokevirtual #79                 // Method javassist/bytecode/Bytecode.addCheckcast:(Ljava/lang/String;)V
      29: aload_0
      30: aload_3
      31: aload_2
      32: invokevirtual #80                 // Method javassist/CtPrimitiveType.getGetMethodName:()Ljava/lang/String;
      35: aload_2
      36: invokevirtual #81                 // Method javassist/CtPrimitiveType.getGetMethodDescriptor:()Ljava/lang/String;
      39: invokevirtual #82                 // Method javassist/bytecode/Bytecode.addInvokevirtual:(Ljava/lang/String;Ljava/lang/String;Ljava/lang/String;)V
      42: aload_0
      43: aload_2
      44: invokevirtual #83                 // Method javassist/CtPrimitiveType.getReturnOp:()I
      47: invokevirtual #84                 // Method javassist/bytecode/Bytecode.addOpcode:(I)V
      50: goto          65
      53: aload_0
      54: aload_1
      55: invokevirtual #85                 // Method javassist/bytecode/Bytecode.addCheckcast:(Ljavassist/CtClass;)V
      58: aload_0
      59: sipush        176
      62: invokevirtual #84                 // Method javassist/bytecode/Bytecode.addOpcode:(I)V
      65: return
}
