Compiled from "KeyValue.java"
public interface org.opensaml.xml.signature.KeyValue extends org.opensaml.xml.validation.ValidatingXMLObject {
  public static final java.lang.String DEFAULT_ELEMENT_LOCAL_NAME;

  public static final javax.xml.namespace.QName DEFAULT_ELEMENT_NAME;

  public static final java.lang.String TYPE_LOCAL_NAME;

  public static final javax.xml.namespace.QName TYPE_NAME;

  public abstract org.opensaml.xml.signature.DSAKeyValue getDSAKeyValue();

  public abstract void setDSAKeyValue(org.opensaml.xml.signature.DSAKeyValue);

  public abstract org.opensaml.xml.signature.RSAKeyValue getRSAKeyValue();

  public abstract void setRSAKeyValue(org.opensaml.xml.signature.RSAKeyValue);

  public abstract org.opensaml.xml.XMLObject getUnknownXMLObject();

  public abstract void setUnknownXMLObject(org.opensaml.xml.XMLObject);

  static {};
    Code:
       0: new           #1                  // class javax/xml/namespace/QName
       3: dup
       4: ldc           #2                  // String http://www.w3.org/2000/09/xmldsig#
       6: ldc           #3                  // String KeyValue
       8: ldc           #4                  // String ds
      10: invokespecial #5                  // Method javax/xml/namespace/QName."<init>":(Ljava/lang/String;Ljava/lang/String;Ljava/lang/String;)V
      13: putstatic     #6                  // Field DEFAULT_ELEMENT_NAME:Ljavax/xml/namespace/QName;
      16: new           #1                  // class javax/xml/namespace/QName
      19: dup
      20: ldc           #2                  // String http://www.w3.org/2000/09/xmldsig#
      22: ldc           #7                  // String KeyValueType
      24: ldc           #4                  // String ds
      26: invokespecial #5                  // Method javax/xml/namespace/QName."<init>":(Ljava/lang/String;Ljava/lang/String;Ljava/lang/String;)V
      29: putstatic     #8                  // Field TYPE_NAME:Ljavax/xml/namespace/QName;
      32: return
}
