Compiled from "ResourceBundleViewResolver.java"
public class org.springframework.web.servlet.view.ResourceBundleViewResolver extends org.springframework.web.servlet.view.AbstractCachingViewResolver implements org.springframework.core.Ordered,org.springframework.beans.factory.InitializingBean,org.springframework.beans.factory.DisposableBean {
  public static final java.lang.String DEFAULT_BASENAME;

  private int order;

  private java.lang.String[] basenames;

  private java.lang.ClassLoader bundleClassLoader;

  private java.lang.String defaultParentView;

  private java.util.Locale[] localesToInitialize;

  private final java.util.Map<java.util.Locale, org.springframework.beans.factory.BeanFactory> localeCache;

  private final java.util.Map<java.util.List<java.util.ResourceBundle>, org.springframework.context.ConfigurableApplicationContext> bundleCache;

  public org.springframework.web.servlet.view.ResourceBundleViewResolver();
    Code:
       0: aload_0
       1: invokespecial #1                  // Method org/springframework/web/servlet/view/AbstractCachingViewResolver."<init>":()V
       4: aload_0
       5: ldc           #3                  // int 2147483647
       7: putfield      #4                  // Field order:I
      10: aload_0
      11: iconst_1
      12: anewarray     #5                  // class java/lang/String
      15: dup
      16: iconst_0
      17: ldc           #7                  // String views
      19: aastore
      20: putfield      #8                  // Field basenames:[Ljava/lang/String;
      23: aload_0
      24: invokestatic  #9                  // Method java/lang/Thread.currentThread:()Ljava/lang/Thread;
      27: invokevirtual #10                 // Method java/lang/Thread.getContextClassLoader:()Ljava/lang/ClassLoader;
      30: putfield      #11                 // Field bundleClassLoader:Ljava/lang/ClassLoader;
      33: aload_0
      34: new           #12                 // class java/util/HashMap
      37: dup
      38: invokespecial #13                 // Method java/util/HashMap."<init>":()V
      41: putfield      #14                 // Field localeCache:Ljava/util/Map;
      44: aload_0
      45: new           #12                 // class java/util/HashMap
      48: dup
      49: invokespecial #13                 // Method java/util/HashMap."<init>":()V
      52: putfield      #15                 // Field bundleCache:Ljava/util/Map;
      55: return

  public void setOrder(int);
    Code:
       0: aload_0
       1: iload_1
       2: putfield      #4                  // Field order:I
       5: return

  public int getOrder();
    Code:
       0: aload_0
       1: getfield      #4                  // Field order:I
       4: ireturn

  public void setBasename(java.lang.String);
    Code:
       0: aload_0
       1: iconst_1
       2: anewarray     #5                  // class java/lang/String
       5: dup
       6: iconst_0
       7: aload_1
       8: aastore
       9: invokevirtual #16                 // Method setBasenames:([Ljava/lang/String;)V
      12: return

  public void setBasenames(java.lang.String...);
    Code:
       0: aload_0
       1: aload_1
       2: putfield      #8                  // Field basenames:[Ljava/lang/String;
       5: return

  public void setBundleClassLoader(java.lang.ClassLoader);
    Code:
       0: aload_0
       1: aload_1
       2: putfield      #11                 // Field bundleClassLoader:Ljava/lang/ClassLoader;
       5: return

  protected java.lang.ClassLoader getBundleClassLoader();
    Code:
       0: aload_0
       1: getfield      #11                 // Field bundleClassLoader:Ljava/lang/ClassLoader;
       4: areturn

  public void setDefaultParentView(java.lang.String);
    Code:
       0: aload_0
       1: aload_1
       2: putfield      #17                 // Field defaultParentView:Ljava/lang/String;
       5: return

  public void setLocalesToInitialize(java.util.Locale...);
    Code:
       0: aload_0
       1: aload_1
       2: putfield      #18                 // Field localesToInitialize:[Ljava/util/Locale;
       5: return

  public void afterPropertiesSet() throws org.springframework.beans.BeansException;
    Code:
       0: aload_0
       1: getfield      #18                 // Field localesToInitialize:[Ljava/util/Locale;
       4: ifnull        40
       7: aload_0
       8: getfield      #18                 // Field localesToInitialize:[Ljava/util/Locale;
      11: astore_1
      12: aload_1
      13: arraylength
      14: istore_2
      15: iconst_0
      16: istore_3
      17: iload_3
      18: iload_2
      19: if_icmpge     40
      22: aload_1
      23: iload_3
      24: aaload
      25: astore        4
      27: aload_0
      28: aload         4
      30: invokevirtual #19                 // Method initFactory:(Ljava/util/Locale;)Lorg/springframework/beans/factory/BeanFactory;
      33: pop
      34: iinc          3, 1
      37: goto          17
      40: return

  protected org.springframework.web.servlet.View loadView(java.lang.String, java.util.Locale) throws java.lang.Exception;
    Code:
       0: aload_0
       1: aload_2
       2: invokevirtual #19                 // Method initFactory:(Ljava/util/Locale;)Lorg/springframework/beans/factory/BeanFactory;
       5: astore_3
       6: aload_3
       7: aload_1
       8: ldc           #20                 // class org/springframework/web/servlet/View
      10: invokeinterface #21,  3           // InterfaceMethod org/springframework/beans/factory/BeanFactory.getBean:(Ljava/lang/String;Ljava/lang/Class;)Ljava/lang/Object;
      15: checkcast     #20                 // class org/springframework/web/servlet/View
      18: areturn
      19: astore        4
      21: aconst_null
      22: areturn
    Exception table:
       from    to  target type
           6    18    19   Class org/springframework/beans/factory/NoSuchBeanDefinitionException

  protected synchronized org.springframework.beans.factory.BeanFactory initFactory(java.util.Locale) throws org.springframework.beans.BeansException;
    Code:
       0: aload_0
       1: invokevirtual #23                 // Method isCache:()Z
       4: ifeq          27
       7: aload_0
       8: getfield      #14                 // Field localeCache:Ljava/util/Map;
      11: aload_1
      12: invokeinterface #24,  2           // InterfaceMethod java/util/Map.get:(Ljava/lang/Object;)Ljava/lang/Object;
      17: checkcast     #25                 // class org/springframework/beans/factory/BeanFactory
      20: astore_2
      21: aload_2
      22: ifnull        27
      25: aload_2
      26: areturn
      27: new           #26                 // class java/util/LinkedList
      30: dup
      31: invokespecial #27                 // Method java/util/LinkedList."<init>":()V
      34: astore_2
      35: aload_0
      36: getfield      #8                  // Field basenames:[Ljava/lang/String;
      39: astore_3
      40: aload_3
      41: arraylength
      42: istore        4
      44: iconst_0
      45: istore        5
      47: iload         5
      49: iload         4
      51: if_icmpge     84
      54: aload_3
      55: iload         5
      57: aaload
      58: astore        6
      60: aload_0
      61: aload         6
      63: aload_1
      64: invokevirtual #28                 // Method getBundle:(Ljava/lang/String;Ljava/util/Locale;)Ljava/util/ResourceBundle;
      67: astore        7
      69: aload_2
      70: aload         7
      72: invokeinterface #29,  2           // InterfaceMethod java/util/List.add:(Ljava/lang/Object;)Z
      77: pop
      78: iinc          5, 1
      81: goto          47
      84: aload_0
      85: invokevirtual #23                 // Method isCache:()Z
      88: ifeq          123
      91: aload_0
      92: getfield      #15                 // Field bundleCache:Ljava/util/Map;
      95: aload_2
      96: invokeinterface #24,  2           // InterfaceMethod java/util/Map.get:(Ljava/lang/Object;)Ljava/lang/Object;
     101: checkcast     #25                 // class org/springframework/beans/factory/BeanFactory
     104: astore_3
     105: aload_3
     106: ifnull        123
     109: aload_0
     110: getfield      #14                 // Field localeCache:Ljava/util/Map;
     113: aload_1
     114: aload_3
     115: invokeinterface #30,  3           // InterfaceMethod java/util/Map.put:(Ljava/lang/Object;Ljava/lang/Object;)Ljava/lang/Object;
     120: pop
     121: aload_3
     122: areturn
     123: new           #31                 // class org/springframework/web/context/support/GenericWebApplicationContext
     126: dup
     127: invokespecial #32                 // Method org/springframework/web/context/support/GenericWebApplicationContext."<init>":()V
     130: astore_3
     131: aload_3
     132: aload_0
     133: invokevirtual #33                 // Method getApplicationContext:()Lorg/springframework/context/ApplicationContext;
     136: invokevirtual #34                 // Method org/springframework/web/context/support/GenericWebApplicationContext.setParent:(Lorg/springframework/context/ApplicationContext;)V
     139: aload_3
     140: aload_0
     141: invokevirtual #35                 // Method getServletContext:()Ljavax/servlet/ServletContext;
     144: invokevirtual #36                 // Method org/springframework/web/context/support/GenericWebApplicationContext.setServletContext:(Ljavax/servlet/ServletContext;)V
     147: new           #37                 // class org/springframework/beans/factory/support/PropertiesBeanDefinitionReader
     150: dup
     151: aload_3
     152: invokespecial #38                 // Method org/springframework/beans/factory/support/PropertiesBeanDefinitionReader."<init>":(Lorg/springframework/beans/factory/support/BeanDefinitionRegistry;)V
     155: astore        4
     157: aload         4
     159: aload_0
     160: getfield      #17                 // Field defaultParentView:Ljava/lang/String;
     163: invokevirtual #39                 // Method org/springframework/beans/factory/support/PropertiesBeanDefinitionReader.setDefaultParentBean:(Ljava/lang/String;)V
     166: aload_2
     167: invokeinterface #40,  1           // InterfaceMethod java/util/List.iterator:()Ljava/util/Iterator;
     172: astore        5
     174: aload         5
     176: invokeinterface #41,  1           // InterfaceMethod java/util/Iterator.hasNext:()Z
     181: ifeq          207
     184: aload         5
     186: invokeinterface #42,  1           // InterfaceMethod java/util/Iterator.next:()Ljava/lang/Object;
     191: checkcast     #43                 // class java/util/ResourceBundle
     194: astore        6
     196: aload         4
     198: aload         6
     200: invokevirtual #44                 // Method org/springframework/beans/factory/support/PropertiesBeanDefinitionReader.registerBeanDefinitions:(Ljava/util/ResourceBundle;)I
     203: pop
     204: goto          174
     207: aload_3
     208: invokevirtual #45                 // Method org/springframework/web/context/support/GenericWebApplicationContext.refresh:()V
     211: aload_0
     212: invokevirtual #23                 // Method isCache:()Z
     215: ifeq          242
     218: aload_0
     219: getfield      #14                 // Field localeCache:Ljava/util/Map;
     222: aload_1
     223: aload_3
     224: invokeinterface #30,  3           // InterfaceMethod java/util/Map.put:(Ljava/lang/Object;Ljava/lang/Object;)Ljava/lang/Object;
     229: pop
     230: aload_0
     231: getfield      #15                 // Field bundleCache:Ljava/util/Map;
     234: aload_2
     235: aload_3
     236: invokeinterface #30,  3           // InterfaceMethod java/util/Map.put:(Ljava/lang/Object;Ljava/lang/Object;)Ljava/lang/Object;
     241: pop
     242: aload_3
     243: areturn

  protected java.util.ResourceBundle getBundle(java.lang.String, java.util.Locale) throws java.util.MissingResourceException;
    Code:
       0: aload_1
       1: aload_2
       2: aload_0
       3: invokevirtual #46                 // Method getBundleClassLoader:()Ljava/lang/ClassLoader;
       6: invokestatic  #47                 // Method java/util/ResourceBundle.getBundle:(Ljava/lang/String;Ljava/util/Locale;Ljava/lang/ClassLoader;)Ljava/util/ResourceBundle;
       9: areturn

  public void destroy() throws org.springframework.beans.BeansException;
    Code:
       0: aload_0
       1: getfield      #15                 // Field bundleCache:Ljava/util/Map;
       4: invokeinterface #48,  1           // InterfaceMethod java/util/Map.values:()Ljava/util/Collection;
       9: invokeinterface #49,  1           // InterfaceMethod java/util/Collection.iterator:()Ljava/util/Iterator;
      14: astore_1
      15: aload_1
      16: invokeinterface #41,  1           // InterfaceMethod java/util/Iterator.hasNext:()Z
      21: ifeq          43
      24: aload_1
      25: invokeinterface #42,  1           // InterfaceMethod java/util/Iterator.next:()Ljava/lang/Object;
      30: checkcast     #50                 // class org/springframework/context/ConfigurableApplicationContext
      33: astore_2
      34: aload_2
      35: invokeinterface #51,  1           // InterfaceMethod org/springframework/context/ConfigurableApplicationContext.close:()V
      40: goto          15
      43: aload_0
      44: getfield      #14                 // Field localeCache:Ljava/util/Map;
      47: invokeinterface #52,  1           // InterfaceMethod java/util/Map.clear:()V
      52: aload_0
      53: getfield      #15                 // Field bundleCache:Ljava/util/Map;
      56: invokeinterface #52,  1           // InterfaceMethod java/util/Map.clear:()V
      61: return
}
