Compiled from "AbstractIterableMap.java"
public abstract class org.apache.commons.collections4.map.AbstractIterableMap<K, V> implements org.apache.commons.collections4.IterableMap<K, V> {
  public org.apache.commons.collections4.map.AbstractIterableMap();
    Code:
       0: aload_0
       1: invokespecial #1                  // Method java/lang/Object."<init>":()V
       4: return

  public org.apache.commons.collections4.MapIterator<K, V> mapIterator();
    Code:
       0: new           #2                  // class org/apache/commons/collections4/map/EntrySetToMapIteratorAdapter
       3: dup
       4: aload_0
       5: invokevirtual #3                  // Method entrySet:()Ljava/util/Set;
       8: invokespecial #4                  // Method org/apache/commons/collections4/map/EntrySetToMapIteratorAdapter."<init>":(Ljava/util/Set;)V
      11: areturn
}
