Compiled from "HttpNIOConnPoolFactory.java"
class org.apache.http.impl.nio.conn.HttpNIOConnPoolFactory implements org.apache.http.nio.pool.NIOConnFactory<org.apache.http.conn.routing.HttpRoute, org.apache.http.nio.reactor.IOSession> {
  org.apache.http.impl.nio.conn.HttpNIOConnPoolFactory();
    Code:
       0: aload_0
       1: invokespecial #1                  // Method java/lang/Object."<init>":()V
       4: return

  public org.apache.http.nio.reactor.IOSession create(org.apache.http.conn.routing.HttpRoute, org.apache.http.nio.reactor.IOSession) throws java.io.IOException;
    Code:
       0: aload_2
       1: areturn

  public java.lang.Object create(java.lang.Object, org.apache.http.nio.reactor.IOSession) throws java.io.IOException;
    Code:
       0: aload_0
       1: aload_1
       2: checkcast     #2                  // class org/apache/http/conn/routing/HttpRoute
       5: aload_2
       6: invokevirtual #3                  // Method create:(Lorg/apache/http/conn/routing/HttpRoute;Lorg/apache/http/nio/reactor/IOSession;)Lorg/apache/http/nio/reactor/IOSession;
       9: areturn
}
