Compiled from "CachedAtomicInteger.java"
public class org.apache.curator.framework.recipes.atomic.CachedAtomicInteger {
  private final org.apache.curator.framework.recipes.atomic.DistributedAtomicInteger number;

  private final int cacheFactor;

  private org.apache.curator.framework.recipes.atomic.AtomicValue<java.lang.Integer> currentValue;

  private int currentIndex;

  public org.apache.curator.framework.recipes.atomic.CachedAtomicInteger(org.apache.curator.framework.recipes.atomic.DistributedAtomicInteger, int);
    Code:
       0: aload_0
       1: invokespecial #18                 // Method java/lang/Object."<init>":()V
       4: aload_0
       5: aconst_null
       6: putfield      #20                 // Field currentValue:Lorg/apache/curator/framework/recipes/atomic/AtomicValue;
       9: aload_0
      10: iconst_0
      11: putfield      #22                 // Field currentIndex:I
      14: aload_0
      15: aload_1
      16: putfield      #24                 // Field number:Lorg/apache/curator/framework/recipes/atomic/DistributedAtomicInteger;
      19: aload_0
      20: iload_2
      21: putfield      #26                 // Field cacheFactor:I
      24: return

  public org.apache.curator.framework.recipes.atomic.AtomicValue<java.lang.Integer> next() throws java.lang.Exception;
    Code:
       0: new           #35                 // class org/apache/curator/framework/recipes/atomic/MutableAtomicValue
       3: dup
       4: iconst_0
       5: invokestatic  #41                 // Method java/lang/Integer.valueOf:(I)Ljava/lang/Integer;
       8: iconst_0
       9: invokestatic  #41                 // Method java/lang/Integer.valueOf:(I)Ljava/lang/Integer;
      12: invokespecial #44                 // Method org/apache/curator/framework/recipes/atomic/MutableAtomicValue."<init>":(Ljava/lang/Object;Ljava/lang/Object;)V
      15: astore_1
      16: aload_0
      17: getfield      #20                 // Field currentValue:Lorg/apache/curator/framework/recipes/atomic/AtomicValue;
      20: ifnonnull     70
      23: aload_0
      24: aload_0
      25: getfield      #24                 // Field number:Lorg/apache/curator/framework/recipes/atomic/DistributedAtomicInteger;
      28: aload_0
      29: getfield      #26                 // Field cacheFactor:I
      32: invokestatic  #41                 // Method java/lang/Integer.valueOf:(I)Ljava/lang/Integer;
      35: invokevirtual #50                 // Method org/apache/curator/framework/recipes/atomic/DistributedAtomicInteger.add:(Ljava/lang/Integer;)Lorg/apache/curator/framework/recipes/atomic/AtomicValue;
      38: putfield      #20                 // Field currentValue:Lorg/apache/curator/framework/recipes/atomic/AtomicValue;
      41: aload_0
      42: getfield      #20                 // Field currentValue:Lorg/apache/curator/framework/recipes/atomic/AtomicValue;
      45: invokeinterface #56,  1           // InterfaceMethod org/apache/curator/framework/recipes/atomic/AtomicValue.succeeded:()Z
      50: ifne          65
      53: aload_0
      54: aconst_null
      55: putfield      #20                 // Field currentValue:Lorg/apache/curator/framework/recipes/atomic/AtomicValue;
      58: aload_1
      59: iconst_0
      60: putfield      #59                 // Field org/apache/curator/framework/recipes/atomic/MutableAtomicValue.succeeded:Z
      63: aload_1
      64: areturn
      65: aload_0
      66: iconst_0
      67: putfield      #22                 // Field currentIndex:I
      70: aload_1
      71: iconst_1
      72: putfield      #59                 // Field org/apache/curator/framework/recipes/atomic/MutableAtomicValue.succeeded:Z
      75: aload_1
      76: aload_0
      77: getfield      #20                 // Field currentValue:Lorg/apache/curator/framework/recipes/atomic/AtomicValue;
      80: invokeinterface #63,  1           // InterfaceMethod org/apache/curator/framework/recipes/atomic/AtomicValue.preValue:()Ljava/lang/Object;
      85: checkcast     #37                 // class java/lang/Integer
      88: invokevirtual #67                 // Method java/lang/Integer.intValue:()I
      91: aload_0
      92: getfield      #22                 // Field currentIndex:I
      95: iadd
      96: invokestatic  #41                 // Method java/lang/Integer.valueOf:(I)Ljava/lang/Integer;
      99: putfield      #70                 // Field org/apache/curator/framework/recipes/atomic/MutableAtomicValue.preValue:Ljava/lang/Object;
     102: aload_1
     103: aload_1
     104: getfield      #70                 // Field org/apache/curator/framework/recipes/atomic/MutableAtomicValue.preValue:Ljava/lang/Object;
     107: checkcast     #37                 // class java/lang/Integer
     110: invokevirtual #67                 // Method java/lang/Integer.intValue:()I
     113: iconst_1
     114: iadd
     115: invokestatic  #41                 // Method java/lang/Integer.valueOf:(I)Ljava/lang/Integer;
     118: putfield      #73                 // Field org/apache/curator/framework/recipes/atomic/MutableAtomicValue.postValue:Ljava/lang/Object;
     121: aload_0
     122: dup
     123: getfield      #22                 // Field currentIndex:I
     126: iconst_1
     127: iadd
     128: dup_x1
     129: putfield      #22                 // Field currentIndex:I
     132: aload_0
     133: getfield      #26                 // Field cacheFactor:I
     136: if_icmplt     144
     139: aload_0
     140: aconst_null
     141: putfield      #20                 // Field currentValue:Lorg/apache/curator/framework/recipes/atomic/AtomicValue;
     144: aload_1
     145: areturn
}
