Compiled from "DistributedAtomicInteger.java"
class org.apache.curator.framework.recipes.atomic.DistributedAtomicInteger$1 implements org.apache.curator.framework.recipes.atomic.MakeValue {
  final java.lang.Integer val$addAmount;

  final org.apache.curator.framework.recipes.atomic.DistributedAtomicInteger this$0;

  org.apache.curator.framework.recipes.atomic.DistributedAtomicInteger$1(org.apache.curator.framework.recipes.atomic.DistributedAtomicInteger, java.lang.Integer);
    Code:
       0: aload_0
       1: aload_1
       2: putfield      #20                 // Field this$0:Lorg/apache/curator/framework/recipes/atomic/DistributedAtomicInteger;
       5: aload_0
       6: aload_2
       7: putfield      #22                 // Field val$addAmount:Ljava/lang/Integer;
      10: aload_0
      11: invokespecial #25                 // Method java/lang/Object."<init>":()V
      14: return

  public byte[] makeFrom(byte[]);
    Code:
       0: aload_1
       1: ifnull        15
       4: aload_0
       5: getfield      #20                 // Field this$0:Lorg/apache/curator/framework/recipes/atomic/DistributedAtomicInteger;
       8: aload_1
       9: invokevirtual #33                 // Method org/apache/curator/framework/recipes/atomic/DistributedAtomicInteger.bytesToValue:([B)I
      12: goto          16
      15: iconst_0
      16: istore_2
      17: iload_2
      18: aload_0
      19: getfield      #22                 // Field val$addAmount:Ljava/lang/Integer;
      22: invokevirtual #39                 // Method java/lang/Integer.intValue:()I
      25: iadd
      26: istore_3
      27: aload_0
      28: getfield      #20                 // Field this$0:Lorg/apache/curator/framework/recipes/atomic/DistributedAtomicInteger;
      31: iload_3
      32: invokestatic  #43                 // Method java/lang/Integer.valueOf:(I)Ljava/lang/Integer;
      35: invokevirtual #47                 // Method org/apache/curator/framework/recipes/atomic/DistributedAtomicInteger.valueToBytes:(Ljava/lang/Integer;)[B
      38: areturn
}
