Compiled from "DistributedAtomicLong.java"
class org.apache.curator.framework.recipes.atomic.DistributedAtomicLong$1 implements org.apache.curator.framework.recipes.atomic.MakeValue {
  final java.lang.Long val$addAmount;

  final org.apache.curator.framework.recipes.atomic.DistributedAtomicLong this$0;

  org.apache.curator.framework.recipes.atomic.DistributedAtomicLong$1(org.apache.curator.framework.recipes.atomic.DistributedAtomicLong, java.lang.Long);
    Code:
       0: aload_0
       1: aload_1
       2: putfield      #20                 // Field this$0:Lorg/apache/curator/framework/recipes/atomic/DistributedAtomicLong;
       5: aload_0
       6: aload_2
       7: putfield      #22                 // Field val$addAmount:Ljava/lang/Long;
      10: aload_0
      11: invokespecial #25                 // Method java/lang/Object."<init>":()V
      14: return

  public byte[] makeFrom(byte[]);
    Code:
       0: aload_1
       1: ifnull        15
       4: aload_0
       5: getfield      #20                 // Field this$0:Lorg/apache/curator/framework/recipes/atomic/DistributedAtomicLong;
       8: aload_1
       9: invokevirtual #33                 // Method org/apache/curator/framework/recipes/atomic/DistributedAtomicLong.bytesToValue:([B)J
      12: goto          16
      15: lconst_0
      16: lstore_2
      17: lload_2
      18: aload_0
      19: getfield      #22                 // Field val$addAmount:Ljava/lang/Long;
      22: invokevirtual #39                 // Method java/lang/Long.longValue:()J
      25: ladd
      26: lstore        4
      28: aload_0
      29: getfield      #20                 // Field this$0:Lorg/apache/curator/framework/recipes/atomic/DistributedAtomicLong;
      32: lload         4
      34: invokestatic  #43                 // Method java/lang/Long.valueOf:(J)Ljava/lang/Long;
      37: invokevirtual #47                 // Method org/apache/curator/framework/recipes/atomic/DistributedAtomicLong.valueToBytes:(Ljava/lang/Long;)[B
      40: areturn
}
