Compiled from "JobFluentImpl.java"
public class io.dekorate.deps.kubernetes.api.model.batch.JobFluentImpl$StatusNestedImpl<N> extends io.dekorate.deps.kubernetes.api.model.batch.JobStatusFluentImpl<io.dekorate.deps.kubernetes.api.model.batch.JobFluent$StatusNested<N>> implements io.dekorate.deps.kubernetes.api.model.batch.JobFluent$StatusNested<N>, io.dekorate.deps.kubernetes.api.builder.Nested<N> {
  private final io.dekorate.deps.kubernetes.api.model.batch.JobStatusBuilder builder;

  final io.dekorate.deps.kubernetes.api.model.batch.JobFluentImpl this$0;

  io.dekorate.deps.kubernetes.api.model.batch.JobFluentImpl$StatusNestedImpl(io.dekorate.deps.kubernetes.api.model.batch.JobFluentImpl, io.dekorate.deps.kubernetes.api.model.batch.JobStatus);
    Code:
       0: aload_0
       1: aload_1
       2: putfield      #24                 // Field this$0:Lio/dekorate/deps/kubernetes/api/model/batch/JobFluentImpl;
       5: aload_0
       6: invokespecial #27                 // Method io/dekorate/deps/kubernetes/api/model/batch/JobStatusFluentImpl."<init>":()V
       9: aload_0
      10: new           #29                 // class io/dekorate/deps/kubernetes/api/model/batch/JobStatusBuilder
      13: dup
      14: aload_0
      15: aload_2
      16: invokespecial #32                 // Method io/dekorate/deps/kubernetes/api/model/batch/JobStatusBuilder."<init>":(Lio/dekorate/deps/kubernetes/api/model/batch/JobStatusFluent;Lio/dekorate/deps/kubernetes/api/model/batch/JobStatus;)V
      19: putfield      #34                 // Field builder:Lio/dekorate/deps/kubernetes/api/model/batch/JobStatusBuilder;
      22: return

  io.dekorate.deps.kubernetes.api.model.batch.JobFluentImpl$StatusNestedImpl(io.dekorate.deps.kubernetes.api.model.batch.JobFluentImpl);
    Code:
       0: aload_0
       1: aload_1
       2: putfield      #24                 // Field this$0:Lio/dekorate/deps/kubernetes/api/model/batch/JobFluentImpl;
       5: aload_0
       6: invokespecial #27                 // Method io/dekorate/deps/kubernetes/api/model/batch/JobStatusFluentImpl."<init>":()V
       9: aload_0
      10: new           #29                 // class io/dekorate/deps/kubernetes/api/model/batch/JobStatusBuilder
      13: dup
      14: aload_0
      15: invokespecial #43                 // Method io/dekorate/deps/kubernetes/api/model/batch/JobStatusBuilder."<init>":(Lio/dekorate/deps/kubernetes/api/model/batch/JobStatusFluent;)V
      18: putfield      #34                 // Field builder:Lio/dekorate/deps/kubernetes/api/model/batch/JobStatusBuilder;
      21: return

  public N and();
    Code:
       0: aload_0
       1: getfield      #24                 // Field this$0:Lio/dekorate/deps/kubernetes/api/model/batch/JobFluentImpl;
       4: aload_0
       5: getfield      #34                 // Field builder:Lio/dekorate/deps/kubernetes/api/model/batch/JobStatusBuilder;
       8: invokevirtual #50                 // Method io/dekorate/deps/kubernetes/api/model/batch/JobStatusBuilder.build:()Lio/dekorate/deps/kubernetes/api/model/batch/JobStatus;
      11: invokevirtual #54                 // Method io/dekorate/deps/kubernetes/api/model/batch/JobFluentImpl.withStatus:(Lio/dekorate/deps/kubernetes/api/model/batch/JobStatus;)Lio/dekorate/deps/kubernetes/api/model/batch/JobFluent;
      14: areturn

  public N endStatus();
    Code:
       0: aload_0
       1: invokevirtual #57                 // Method and:()Ljava/lang/Object;
       4: areturn
}
