Compiled from "ClassSpaceScanner.java"
public final class org.sonatype.guice.bean.scanners.ClassSpaceScanner {
  private static final int ASM_FLAGS;

  private final org.sonatype.guice.bean.scanners.ClassFinder finder;

  private final org.sonatype.guice.bean.reflect.ClassSpace space;

  public org.sonatype.guice.bean.scanners.ClassSpaceScanner(org.sonatype.guice.bean.reflect.ClassSpace);
    Code:
       0: aload_0
       1: aconst_null
       2: aload_1
       3: invokespecial #1                  // Method "<init>":(Lorg/sonatype/guice/bean/scanners/ClassFinder;Lorg/sonatype/guice/bean/reflect/ClassSpace;)V
       6: return

  public org.sonatype.guice.bean.scanners.ClassSpaceScanner(org.sonatype.guice.bean.scanners.ClassFinder, org.sonatype.guice.bean.reflect.ClassSpace);
    Code:
       0: aload_0
       1: invokespecial #2                  // Method java/lang/Object."<init>":()V
       4: aload_0
       5: aload_1
       6: putfield      #3                  // Field finder:Lorg/sonatype/guice/bean/scanners/ClassFinder;
       9: aload_0
      10: aload_2
      11: putfield      #4                  // Field space:Lorg/sonatype/guice/bean/reflect/ClassSpace;
      14: return

  public void accept(org.sonatype.guice.bean.scanners.ClassSpaceVisitor);
    Code:
       0: aload_1
       1: aload_0
       2: getfield      #4                  // Field space:Lorg/sonatype/guice/bean/reflect/ClassSpace;
       5: invokeinterface #5,  2            // InterfaceMethod org/sonatype/guice/bean/scanners/ClassSpaceVisitor.visit:(Lorg/sonatype/guice/bean/reflect/ClassSpace;)V
      10: aconst_null
      11: aload_0
      12: getfield      #3                  // Field finder:Lorg/sonatype/guice/bean/scanners/ClassFinder;
      15: if_acmpeq     34
      18: aload_0
      19: getfield      #3                  // Field finder:Lorg/sonatype/guice/bean/scanners/ClassFinder;
      22: aload_0
      23: getfield      #4                  // Field space:Lorg/sonatype/guice/bean/reflect/ClassSpace;
      26: invokeinterface #6,  2            // InterfaceMethod org/sonatype/guice/bean/scanners/ClassFinder.findClasses:(Lorg/sonatype/guice/bean/reflect/ClassSpace;)Ljava/util/Enumeration;
      31: goto          47
      34: aload_0
      35: getfield      #4                  // Field space:Lorg/sonatype/guice/bean/reflect/ClassSpace;
      38: aconst_null
      39: ldc           #7                  // String *.class
      41: iconst_1
      42: invokeinterface #8,  4            // InterfaceMethod org/sonatype/guice/bean/reflect/ClassSpace.findEntries:(Ljava/lang/String;Ljava/lang/String;Z)Ljava/util/Enumeration;
      47: astore_2
      48: aload_2
      49: invokeinterface #9,  1            // InterfaceMethod java/util/Enumeration.hasMoreElements:()Z
      54: ifeq          91
      57: aload_2
      58: invokeinterface #10,  1           // InterfaceMethod java/util/Enumeration.nextElement:()Ljava/lang/Object;
      63: checkcast     #11                 // class java/net/URL
      66: astore_3
      67: aload_1
      68: aload_3
      69: invokeinterface #12,  2           // InterfaceMethod org/sonatype/guice/bean/scanners/ClassSpaceVisitor.visitClass:(Ljava/net/URL;)Lorg/sonatype/guice/bean/scanners/asm/ClassVisitor;
      74: astore        4
      76: aconst_null
      77: aload         4
      79: if_acmpeq     88
      82: aload         4
      84: aload_3
      85: invokestatic  #13                 // Method accept:(Lorg/sonatype/guice/bean/scanners/asm/ClassVisitor;Ljava/net/URL;)V
      88: goto          48
      91: aload_1
      92: invokeinterface #14,  1           // InterfaceMethod org/sonatype/guice/bean/scanners/ClassSpaceVisitor.visitEnd:()V
      97: return

  public static void accept(org.sonatype.guice.bean.scanners.asm.ClassVisitor, java.net.URL);
    Code:
       0: aconst_null
       1: aload_1
       2: if_acmpne     6
       5: return
       6: aload_1
       7: invokevirtual #15                 // Method java/net/URL.openStream:()Ljava/io/InputStream;
      10: astore_2
      11: new           #16                 // class org/sonatype/guice/bean/scanners/asm/ClassReader
      14: dup
      15: aload_2
      16: invokespecial #17                 // Method org/sonatype/guice/bean/scanners/asm/ClassReader."<init>":(Ljava/io/InputStream;)V
      19: aload_0
      20: bipush        7
      22: invokevirtual #18                 // Method org/sonatype/guice/bean/scanners/asm/ClassReader.accept:(Lorg/sonatype/guice/bean/scanners/asm/ClassVisitor;I)V
      25: aload_2
      26: invokevirtual #19                 // Method java/io/InputStream.close:()V
      29: goto          39
      32: astore_3
      33: aload_2
      34: invokevirtual #19                 // Method java/io/InputStream.close:()V
      37: aload_3
      38: athrow
      39: goto          54
      42: astore_2
      43: goto          54
      46: astore_2
      47: ldc           #22                 // String Problem scanning: {}
      49: aload_1
      50: aload_2
      51: invokestatic  #23                 // Method org/sonatype/guice/bean/reflect/Logs.debug:(Ljava/lang/String;Ljava/lang/Object;Ljava/lang/Object;)V
      54: return
    Exception table:
       from    to  target type
          11    25    32   any
          32    33    32   any
           6    39    42   Class java/lang/ArrayIndexOutOfBoundsException
           6    39    46   Class java/lang/Exception

  public static boolean verify(org.sonatype.guice.bean.reflect.ClassSpace, java.lang.Class<?>...);
    Code:
       0: aload_1
       1: astore_2
       2: aload_2
       3: arraylength
       4: istore_3
       5: iconst_0
       6: istore        4
       8: iload         4
      10: iload_3
      11: if_icmpge     90
      14: aload_2
      15: iload         4
      17: aaload
      18: astore        5
      20: aload_0
      21: aload         5
      23: invokevirtual #24                 // Method java/lang/Class.getName:()Ljava/lang/String;
      26: invokeinterface #25,  2           // InterfaceMethod org/sonatype/guice/bean/reflect/ClassSpace.loadClass:(Ljava/lang/String;)Ljava/lang/Class;
      31: astore        6
      33: aload         6
      35: aload         5
      37: if_acmpeq     63
      40: ldc           #26                 // String Inconsistent ClassLoader for: {} in: {}
      42: aload         5
      44: aload_0
      45: invokestatic  #27                 // Method org/sonatype/guice/bean/reflect/Logs.warn:(Ljava/lang/String;Ljava/lang/Object;Ljava/lang/Object;)V
      48: ldc           #28                 // String Expected: {} saw: {}
      50: aload         5
      52: invokevirtual #29                 // Method java/lang/Class.getClassLoader:()Ljava/lang/ClassLoader;
      55: aload         6
      57: invokevirtual #29                 // Method java/lang/Class.getClassLoader:()Ljava/lang/ClassLoader;
      60: invokestatic  #27                 // Method org/sonatype/guice/bean/reflect/Logs.warn:(Ljava/lang/String;Ljava/lang/Object;Ljava/lang/Object;)V
      63: goto          84
      66: astore        6
      68: aload         5
      70: invokevirtual #31                 // Method java/lang/Class.isAnnotation:()Z
      73: ifeq          84
      76: ldc           #32                 // String Potential problem: {} is not visible from: {}
      78: aload         5
      80: aload_0
      81: invokestatic  #23                 // Method org/sonatype/guice/bean/reflect/Logs.debug:(Ljava/lang/String;Ljava/lang/Object;Ljava/lang/Object;)V
      84: iinc          4, 1
      87: goto          8
      90: iconst_1
      91: ireturn
    Exception table:
       from    to  target type
          20    63    66   Class java/lang/TypeNotPresentException
}
