Compiled from "AutoValue_TraceParams.java"
final class io.opencensus.trace.config.AutoValue_TraceParams extends io.opencensus.trace.config.TraceParams {
  private final io.opencensus.trace.Sampler sampler;

  private final int maxNumberOfAttributes;

  private final int maxNumberOfAnnotations;

  private final int maxNumberOfMessageEvents;

  private final int maxNumberOfLinks;

  private io.opencensus.trace.config.AutoValue_TraceParams(io.opencensus.trace.Sampler, int, int, int, int);
    Code:
       0: aload_0
       1: invokespecial #2                  // Method io/opencensus/trace/config/TraceParams."<init>":()V
       4: aload_0
       5: aload_1
       6: putfield      #3                  // Field sampler:Lio/opencensus/trace/Sampler;
       9: aload_0
      10: iload_2
      11: putfield      #4                  // Field maxNumberOfAttributes:I
      14: aload_0
      15: iload_3
      16: putfield      #5                  // Field maxNumberOfAnnotations:I
      19: aload_0
      20: iload         4
      22: putfield      #6                  // Field maxNumberOfMessageEvents:I
      25: aload_0
      26: iload         5
      28: putfield      #7                  // Field maxNumberOfLinks:I
      31: return

  public io.opencensus.trace.Sampler getSampler();
    Code:
       0: aload_0
       1: getfield      #3                  // Field sampler:Lio/opencensus/trace/Sampler;
       4: areturn

  public int getMaxNumberOfAttributes();
    Code:
       0: aload_0
       1: getfield      #4                  // Field maxNumberOfAttributes:I
       4: ireturn

  public int getMaxNumberOfAnnotations();
    Code:
       0: aload_0
       1: getfield      #5                  // Field maxNumberOfAnnotations:I
       4: ireturn

  public int getMaxNumberOfMessageEvents();
    Code:
       0: aload_0
       1: getfield      #6                  // Field maxNumberOfMessageEvents:I
       4: ireturn

  public int getMaxNumberOfLinks();
    Code:
       0: aload_0
       1: getfield      #7                  // Field maxNumberOfLinks:I
       4: ireturn

  public java.lang.String toString();
    Code:
       0: new           #8                  // class java/lang/StringBuilder
       3: dup
       4: invokespecial #9                  // Method java/lang/StringBuilder."<init>":()V
       7: ldc           #10                 // String TraceParams{sampler=
       9: invokevirtual #11                 // Method java/lang/StringBuilder.append:(Ljava/lang/String;)Ljava/lang/StringBuilder;
      12: aload_0
      13: getfield      #3                  // Field sampler:Lio/opencensus/trace/Sampler;
      16: invokevirtual #12                 // Method java/lang/StringBuilder.append:(Ljava/lang/Object;)Ljava/lang/StringBuilder;
      19: ldc           #13                 // String , maxNumberOfAttributes=
      21: invokevirtual #11                 // Method java/lang/StringBuilder.append:(Ljava/lang/String;)Ljava/lang/StringBuilder;
      24: aload_0
      25: getfield      #4                  // Field maxNumberOfAttributes:I
      28: invokevirtual #14                 // Method java/lang/StringBuilder.append:(I)Ljava/lang/StringBuilder;
      31: ldc           #15                 // String , maxNumberOfAnnotations=
      33: invokevirtual #11                 // Method java/lang/StringBuilder.append:(Ljava/lang/String;)Ljava/lang/StringBuilder;
      36: aload_0
      37: getfield      #5                  // Field maxNumberOfAnnotations:I
      40: invokevirtual #14                 // Method java/lang/StringBuilder.append:(I)Ljava/lang/StringBuilder;
      43: ldc           #16                 // String , maxNumberOfMessageEvents=
      45: invokevirtual #11                 // Method java/lang/StringBuilder.append:(Ljava/lang/String;)Ljava/lang/StringBuilder;
      48: aload_0
      49: getfield      #6                  // Field maxNumberOfMessageEvents:I
      52: invokevirtual #14                 // Method java/lang/StringBuilder.append:(I)Ljava/lang/StringBuilder;
      55: ldc           #17                 // String , maxNumberOfLinks=
      57: invokevirtual #11                 // Method java/lang/StringBuilder.append:(Ljava/lang/String;)Ljava/lang/StringBuilder;
      60: aload_0
      61: getfield      #7                  // Field maxNumberOfLinks:I
      64: invokevirtual #14                 // Method java/lang/StringBuilder.append:(I)Ljava/lang/StringBuilder;
      67: ldc           #18                 // String }
      69: invokevirtual #11                 // Method java/lang/StringBuilder.append:(Ljava/lang/String;)Ljava/lang/StringBuilder;
      72: invokevirtual #19                 // Method java/lang/StringBuilder.toString:()Ljava/lang/String;
      75: areturn

  public boolean equals(java.lang.Object);
    Code:
       0: aload_1
       1: aload_0
       2: if_acmpne     7
       5: iconst_1
       6: ireturn
       7: aload_1
       8: instanceof    #20                 // class io/opencensus/trace/config/TraceParams
      11: ifeq          83
      14: aload_1
      15: checkcast     #20                 // class io/opencensus/trace/config/TraceParams
      18: astore_2
      19: aload_0
      20: getfield      #3                  // Field sampler:Lio/opencensus/trace/Sampler;
      23: aload_2
      24: invokevirtual #21                 // Method io/opencensus/trace/config/TraceParams.getSampler:()Lio/opencensus/trace/Sampler;
      27: invokevirtual #22                 // Method java/lang/Object.equals:(Ljava/lang/Object;)Z
      30: ifeq          81
      33: aload_0
      34: getfield      #4                  // Field maxNumberOfAttributes:I
      37: aload_2
      38: invokevirtual #23                 // Method io/opencensus/trace/config/TraceParams.getMaxNumberOfAttributes:()I
      41: if_icmpne     81
      44: aload_0
      45: getfield      #5                  // Field maxNumberOfAnnotations:I
      48: aload_2
      49: invokevirtual #24                 // Method io/opencensus/trace/config/TraceParams.getMaxNumberOfAnnotations:()I
      52: if_icmpne     81
      55: aload_0
      56: getfield      #6                  // Field maxNumberOfMessageEvents:I
      59: aload_2
      60: invokevirtual #25                 // Method io/opencensus/trace/config/TraceParams.getMaxNumberOfMessageEvents:()I
      63: if_icmpne     81
      66: aload_0
      67: getfield      #7                  // Field maxNumberOfLinks:I
      70: aload_2
      71: invokevirtual #26                 // Method io/opencensus/trace/config/TraceParams.getMaxNumberOfLinks:()I
      74: if_icmpne     81
      77: iconst_1
      78: goto          82
      81: iconst_0
      82: ireturn
      83: iconst_0
      84: ireturn

  public int hashCode();
    Code:
       0: iconst_1
       1: istore_1
       2: iload_1
       3: ldc           #27                 // int 1000003
       5: imul
       6: istore_1
       7: iload_1
       8: aload_0
       9: getfield      #3                  // Field sampler:Lio/opencensus/trace/Sampler;
      12: invokevirtual #28                 // Method java/lang/Object.hashCode:()I
      15: ixor
      16: istore_1
      17: iload_1
      18: ldc           #27                 // int 1000003
      20: imul
      21: istore_1
      22: iload_1
      23: aload_0
      24: getfield      #4                  // Field maxNumberOfAttributes:I
      27: ixor
      28: istore_1
      29: iload_1
      30: ldc           #27                 // int 1000003
      32: imul
      33: istore_1
      34: iload_1
      35: aload_0
      36: getfield      #5                  // Field maxNumberOfAnnotations:I
      39: ixor
      40: istore_1
      41: iload_1
      42: ldc           #27                 // int 1000003
      44: imul
      45: istore_1
      46: iload_1
      47: aload_0
      48: getfield      #6                  // Field maxNumberOfMessageEvents:I
      51: ixor
      52: istore_1
      53: iload_1
      54: ldc           #27                 // int 1000003
      56: imul
      57: istore_1
      58: iload_1
      59: aload_0
      60: getfield      #7                  // Field maxNumberOfLinks:I
      63: ixor
      64: istore_1
      65: iload_1
      66: ireturn

  public io.opencensus.trace.config.TraceParams$Builder toBuilder();
    Code:
       0: new           #29                 // class io/opencensus/trace/config/AutoValue_TraceParams$Builder
       3: dup
       4: aload_0
       5: aconst_null
       6: invokespecial #30                 // Method io/opencensus/trace/config/AutoValue_TraceParams$Builder."<init>":(Lio/opencensus/trace/config/TraceParams;Lio/opencensus/trace/config/AutoValue_TraceParams$1;)V
       9: areturn

  io.opencensus.trace.config.AutoValue_TraceParams(io.opencensus.trace.Sampler, int, int, int, int, io.opencensus.trace.config.AutoValue_TraceParams$1);
    Code:
       0: aload_0
       1: aload_1
       2: iload_2
       3: iload_3
       4: iload         4
       6: iload         5
       8: invokespecial #1                  // Method "<init>":(Lio/opencensus/trace/Sampler;IIII)V
      11: return
}
