Compiled from "JSON.java"
public class org.apache.jena.atlas.json.JSON {
  private static final boolean useJavaCC;

  public org.apache.jena.atlas.json.JSON();
    Code:
       0: aload_0
       1: invokespecial #2                  // Method java/lang/Object."<init>":()V
       4: return

  public static org.apache.jena.atlas.json.JsonObject parse(java.io.InputStream);
    Code:
       0: new           #3                  // class org/apache/jena/atlas/json/io/JSONMaker
       3: dup
       4: invokespecial #4                  // Method org/apache/jena/atlas/json/io/JSONMaker."<init>":()V
       7: astore_1
       8: aload_0
       9: aload_1
      10: invokestatic  #5                  // Method _parse:(Ljava/io/InputStream;Lorg/apache/jena/atlas/json/io/JSONMaker;)V
      13: aload_1
      14: invokevirtual #6                  // Method org/apache/jena/atlas/json/io/JSONMaker.jsonValue:()Lorg/apache/jena/atlas/json/JsonValue;
      17: checkcast     #7                  // class org/apache/jena/atlas/json/JsonObject
      20: areturn

  public static org.apache.jena.atlas.json.JsonObject parse(java.lang.String);
    Code:
       0: new           #8                  // class java/io/StringReader
       3: dup
       4: aload_0
       5: invokespecial #9                  // Method java/io/StringReader."<init>":(Ljava/lang/String;)V
       8: invokestatic  #10                 // Method _parse:(Ljava/io/Reader;)Lorg/apache/jena/atlas/json/JsonObject;
      11: areturn

  public static org.apache.jena.atlas.json.JsonValue parseAny(java.io.InputStream);
    Code:
       0: new           #3                  // class org/apache/jena/atlas/json/io/JSONMaker
       3: dup
       4: invokespecial #4                  // Method org/apache/jena/atlas/json/io/JSONMaker."<init>":()V
       7: astore_1
       8: aload_0
       9: aload_1
      10: invokestatic  #11                 // Method _parseAny:(Ljava/io/InputStream;Lorg/apache/jena/atlas/json/io/JSONMaker;)V
      13: aload_1
      14: invokevirtual #6                  // Method org/apache/jena/atlas/json/io/JSONMaker.jsonValue:()Lorg/apache/jena/atlas/json/JsonValue;
      17: areturn

  public static org.apache.jena.atlas.json.JsonValue parseAny(java.lang.String);
    Code:
       0: new           #8                  // class java/io/StringReader
       3: dup
       4: aload_0
       5: invokespecial #9                  // Method java/io/StringReader."<init>":(Ljava/lang/String;)V
       8: invokestatic  #12                 // Method _parseAny:(Ljava/io/Reader;)Lorg/apache/jena/atlas/json/JsonValue;
      11: areturn

  public static org.apache.jena.atlas.json.JsonObject read(java.lang.String);
    Code:
       0: aload_0
       1: invokestatic  #13                 // Method org/apache/jena/atlas/io/IO.openFileEx:(Ljava/lang/String;)Ljava/io/InputStream;
       4: astore_1
       5: aconst_null
       6: astore_2
       7: aload_1
       8: invokestatic  #14                 // Method parse:(Ljava/io/InputStream;)Lorg/apache/jena/atlas/json/JsonObject;
      11: astore_3
      12: aload_1
      13: ifnull        42
      16: aload_2
      17: ifnull        38
      20: aload_1
      21: invokevirtual #15                 // Method java/io/InputStream.close:()V
      24: goto          42
      27: astore        4
      29: aload_2
      30: aload         4
      32: invokevirtual #17                 // Method java/lang/Throwable.addSuppressed:(Ljava/lang/Throwable;)V
      35: goto          42
      38: aload_1
      39: invokevirtual #15                 // Method java/io/InputStream.close:()V
      42: aload_3
      43: areturn
      44: astore_3
      45: aload_3
      46: astore_2
      47: aload_3
      48: athrow
      49: astore        5
      51: aload_1
      52: ifnull        81
      55: aload_2
      56: ifnull        77
      59: aload_1
      60: invokevirtual #15                 // Method java/io/InputStream.close:()V
      63: goto          81
      66: astore        6
      68: aload_2
      69: aload         6
      71: invokevirtual #17                 // Method java/lang/Throwable.addSuppressed:(Ljava/lang/Throwable;)V
      74: goto          81
      77: aload_1
      78: invokevirtual #15                 // Method java/io/InputStream.close:()V
      81: aload         5
      83: athrow
      84: astore_1
      85: new           #19                 // class java/lang/StringBuilder
      88: dup
      89: invokespecial #20                 // Method java/lang/StringBuilder."<init>":()V
      92: ldc           #21                 // String File not found:
      94: invokevirtual #22                 // Method java/lang/StringBuilder.append:(Ljava/lang/String;)Ljava/lang/StringBuilder;
      97: aload_0
      98: invokevirtual #22                 // Method java/lang/StringBuilder.append:(Ljava/lang/String;)Ljava/lang/StringBuilder;
     101: invokevirtual #23                 // Method java/lang/StringBuilder.toString:()Ljava/lang/String;
     104: aload_1
     105: invokestatic  #24                 // Method org/apache/jena/atlas/io/IO.exception:(Ljava/lang/String;Ljava/io/IOException;)V
     108: aconst_null
     109: areturn
     110: astore_1
     111: new           #19                 // class java/lang/StringBuilder
     114: dup
     115: invokespecial #20                 // Method java/lang/StringBuilder."<init>":()V
     118: ldc           #26                 // String IOException:
     120: invokevirtual #22                 // Method java/lang/StringBuilder.append:(Ljava/lang/String;)Ljava/lang/StringBuilder;
     123: aload_0
     124: invokevirtual #22                 // Method java/lang/StringBuilder.append:(Ljava/lang/String;)Ljava/lang/StringBuilder;
     127: invokevirtual #23                 // Method java/lang/StringBuilder.toString:()Ljava/lang/String;
     130: aload_1
     131: invokestatic  #24                 // Method org/apache/jena/atlas/io/IO.exception:(Ljava/lang/String;Ljava/io/IOException;)V
     134: aconst_null
     135: areturn
    Exception table:
       from    to  target type
          20    24    27   Class java/lang/Throwable
           7    12    44   Class java/lang/Throwable
           7    12    49   any
          59    63    66   Class java/lang/Throwable
          44    51    49   any
           0    42    84   Class java/io/FileNotFoundException
          44    84    84   Class java/io/FileNotFoundException
           0    42   110   Class java/io/IOException
          44    84   110   Class java/io/IOException

  public static org.apache.jena.atlas.json.JsonValue readAny(java.lang.String);
    Code:
       0: aload_0
       1: invokestatic  #13                 // Method org/apache/jena/atlas/io/IO.openFileEx:(Ljava/lang/String;)Ljava/io/InputStream;
       4: astore_1
       5: aconst_null
       6: astore_2
       7: aload_1
       8: invokestatic  #27                 // Method parseAny:(Ljava/io/InputStream;)Lorg/apache/jena/atlas/json/JsonValue;
      11: astore_3
      12: aload_1
      13: ifnull        42
      16: aload_2
      17: ifnull        38
      20: aload_1
      21: invokevirtual #15                 // Method java/io/InputStream.close:()V
      24: goto          42
      27: astore        4
      29: aload_2
      30: aload         4
      32: invokevirtual #17                 // Method java/lang/Throwable.addSuppressed:(Ljava/lang/Throwable;)V
      35: goto          42
      38: aload_1
      39: invokevirtual #15                 // Method java/io/InputStream.close:()V
      42: aload_3
      43: areturn
      44: astore_3
      45: aload_3
      46: astore_2
      47: aload_3
      48: athrow
      49: astore        5
      51: aload_1
      52: ifnull        81
      55: aload_2
      56: ifnull        77
      59: aload_1
      60: invokevirtual #15                 // Method java/io/InputStream.close:()V
      63: goto          81
      66: astore        6
      68: aload_2
      69: aload         6
      71: invokevirtual #17                 // Method java/lang/Throwable.addSuppressed:(Ljava/lang/Throwable;)V
      74: goto          81
      77: aload_1
      78: invokevirtual #15                 // Method java/io/InputStream.close:()V
      81: aload         5
      83: athrow
      84: astore_1
      85: new           #28                 // class java/lang/RuntimeException
      88: dup
      89: new           #19                 // class java/lang/StringBuilder
      92: dup
      93: invokespecial #20                 // Method java/lang/StringBuilder."<init>":()V
      96: ldc           #21                 // String File not found:
      98: invokevirtual #22                 // Method java/lang/StringBuilder.append:(Ljava/lang/String;)Ljava/lang/StringBuilder;
     101: aload_0
     102: invokevirtual #22                 // Method java/lang/StringBuilder.append:(Ljava/lang/String;)Ljava/lang/StringBuilder;
     105: invokevirtual #23                 // Method java/lang/StringBuilder.toString:()Ljava/lang/String;
     108: aload_1
     109: invokespecial #29                 // Method java/lang/RuntimeException."<init>":(Ljava/lang/String;Ljava/lang/Throwable;)V
     112: athrow
     113: astore_1
     114: new           #19                 // class java/lang/StringBuilder
     117: dup
     118: invokespecial #20                 // Method java/lang/StringBuilder."<init>":()V
     121: ldc           #26                 // String IOException:
     123: invokevirtual #22                 // Method java/lang/StringBuilder.append:(Ljava/lang/String;)Ljava/lang/StringBuilder;
     126: aload_0
     127: invokevirtual #22                 // Method java/lang/StringBuilder.append:(Ljava/lang/String;)Ljava/lang/StringBuilder;
     130: invokevirtual #23                 // Method java/lang/StringBuilder.toString:()Ljava/lang/String;
     133: aload_1
     134: invokestatic  #24                 // Method org/apache/jena/atlas/io/IO.exception:(Ljava/lang/String;Ljava/io/IOException;)V
     137: aconst_null
     138: areturn
    Exception table:
       from    to  target type
          20    24    27   Class java/lang/Throwable
           7    12    44   Class java/lang/Throwable
           7    12    49   any
          59    63    66   Class java/lang/Throwable
          44    51    49   any
           0    42    84   Class java/io/FileNotFoundException
          44    84    84   Class java/io/FileNotFoundException
           0    42   113   Class java/io/IOException
          44    84   113   Class java/io/IOException

  private static org.apache.jena.atlas.json.JsonObject _parse(java.io.Reader);
    Code:
       0: new           #3                  // class org/apache/jena/atlas/json/io/JSONMaker
       3: dup
       4: invokespecial #4                  // Method org/apache/jena/atlas/json/io/JSONMaker."<init>":()V
       7: astore_1
       8: aload_0
       9: aload_1
      10: invokestatic  #30                 // Method _parse:(Ljava/io/Reader;Lorg/apache/jena/atlas/json/io/JSONMaker;)V
      13: aload_1
      14: invokevirtual #6                  // Method org/apache/jena/atlas/json/io/JSONMaker.jsonValue:()Lorg/apache/jena/atlas/json/JsonValue;
      17: checkcast     #7                  // class org/apache/jena/atlas/json/JsonObject
      20: areturn

  private static org.apache.jena.atlas.json.JsonValue _parseAny(java.io.Reader);
    Code:
       0: new           #3                  // class org/apache/jena/atlas/json/io/JSONMaker
       3: dup
       4: invokespecial #4                  // Method org/apache/jena/atlas/json/io/JSONMaker."<init>":()V
       7: astore_1
       8: aload_0
       9: aload_1
      10: invokestatic  #31                 // Method _parseAny:(Ljava/io/Reader;Lorg/apache/jena/atlas/json/io/JSONMaker;)V
      13: aload_1
      14: invokevirtual #6                  // Method org/apache/jena/atlas/json/io/JSONMaker.jsonValue:()Lorg/apache/jena/atlas/json/JsonValue;
      17: areturn

  private static void _parse(java.io.Reader, org.apache.jena.atlas.json.io.JSONMaker);
    Code:
       0: aload_0
       1: aload_1
       2: invokestatic  #32                 // Method org/apache/jena/atlas/json/io/parser/JSONParser.parse:(Ljava/io/Reader;Lorg/apache/jena/atlas/json/io/JSONHandler;)V
       5: return

  private static void _parseAny(java.io.Reader, org.apache.jena.atlas.json.io.JSONMaker);
    Code:
       0: aload_0
       1: aload_1
       2: invokestatic  #33                 // Method org/apache/jena/atlas/json/io/parser/JSONParser.parseAny:(Ljava/io/Reader;Lorg/apache/jena/atlas/json/io/JSONHandler;)V
       5: return

  private static void _parse(java.io.InputStream, org.apache.jena.atlas.json.io.JSONMaker);
    Code:
       0: aload_0
       1: aload_1
       2: invokestatic  #34                 // Method org/apache/jena/atlas/json/io/parser/JSONParser.parse:(Ljava/io/InputStream;Lorg/apache/jena/atlas/json/io/JSONHandler;)V
       5: return

  private static void _parseAny(java.io.InputStream, org.apache.jena.atlas.json.io.JSONMaker);
    Code:
       0: aload_0
       1: aload_1
       2: invokestatic  #35                 // Method org/apache/jena/atlas/json/io/parser/JSONParser.parseAny:(Ljava/io/InputStream;Lorg/apache/jena/atlas/json/io/JSONHandler;)V
       5: return

  public static java.lang.String toString(org.apache.jena.atlas.json.JsonValue);
    Code:
       0: new           #36                 // class org/apache/jena/atlas/io/IndentedLineBuffer
       3: dup
       4: invokespecial #37                 // Method org/apache/jena/atlas/io/IndentedLineBuffer."<init>":()V
       7: astore_1
       8: aconst_null
       9: astore_2
      10: aload_1
      11: aload_0
      12: invokestatic  #38                 // Method write:(Lorg/apache/jena/atlas/io/IndentedWriter;Lorg/apache/jena/atlas/json/JsonValue;)V
      15: aload_1
      16: invokevirtual #39                 // Method org/apache/jena/atlas/io/IndentedLineBuffer.asString:()Ljava/lang/String;
      19: astore_3
      20: aload_1
      21: ifnull        50
      24: aload_2
      25: ifnull        46
      28: aload_1
      29: invokevirtual #40                 // Method org/apache/jena/atlas/io/IndentedLineBuffer.close:()V
      32: goto          50
      35: astore        4
      37: aload_2
      38: aload         4
      40: invokevirtual #17                 // Method java/lang/Throwable.addSuppressed:(Ljava/lang/Throwable;)V
      43: goto          50
      46: aload_1
      47: invokevirtual #40                 // Method org/apache/jena/atlas/io/IndentedLineBuffer.close:()V
      50: aload_3
      51: areturn
      52: astore_3
      53: aload_3
      54: astore_2
      55: aload_3
      56: athrow
      57: astore        5
      59: aload_1
      60: ifnull        89
      63: aload_2
      64: ifnull        85
      67: aload_1
      68: invokevirtual #40                 // Method org/apache/jena/atlas/io/IndentedLineBuffer.close:()V
      71: goto          89
      74: astore        6
      76: aload_2
      77: aload         6
      79: invokevirtual #17                 // Method java/lang/Throwable.addSuppressed:(Ljava/lang/Throwable;)V
      82: goto          89
      85: aload_1
      86: invokevirtual #40                 // Method org/apache/jena/atlas/io/IndentedLineBuffer.close:()V
      89: aload         5
      91: athrow
    Exception table:
       from    to  target type
          28    32    35   Class java/lang/Throwable
          10    20    52   Class java/lang/Throwable
          10    20    57   any
          67    71    74   Class java/lang/Throwable
          52    59    57   any

  public static java.lang.String toStringFlat(org.apache.jena.atlas.json.JsonValue);
    Code:
       0: new           #36                 // class org/apache/jena/atlas/io/IndentedLineBuffer
       3: dup
       4: invokespecial #37                 // Method org/apache/jena/atlas/io/IndentedLineBuffer."<init>":()V
       7: astore_1
       8: aconst_null
       9: astore_2
      10: aload_1
      11: iconst_1
      12: invokevirtual #41                 // Method org/apache/jena/atlas/io/IndentedLineBuffer.setFlatMode:(Z)V
      15: aload_1
      16: aload_0
      17: invokestatic  #38                 // Method write:(Lorg/apache/jena/atlas/io/IndentedWriter;Lorg/apache/jena/atlas/json/JsonValue;)V
      20: aload_1
      21: invokevirtual #39                 // Method org/apache/jena/atlas/io/IndentedLineBuffer.asString:()Ljava/lang/String;
      24: astore_3
      25: aload_1
      26: ifnull        55
      29: aload_2
      30: ifnull        51
      33: aload_1
      34: invokevirtual #40                 // Method org/apache/jena/atlas/io/IndentedLineBuffer.close:()V
      37: goto          55
      40: astore        4
      42: aload_2
      43: aload         4
      45: invokevirtual #17                 // Method java/lang/Throwable.addSuppressed:(Ljava/lang/Throwable;)V
      48: goto          55
      51: aload_1
      52: invokevirtual #40                 // Method org/apache/jena/atlas/io/IndentedLineBuffer.close:()V
      55: aload_3
      56: areturn
      57: astore_3
      58: aload_3
      59: astore_2
      60: aload_3
      61: athrow
      62: astore        5
      64: aload_1
      65: ifnull        94
      68: aload_2
      69: ifnull        90
      72: aload_1
      73: invokevirtual #40                 // Method org/apache/jena/atlas/io/IndentedLineBuffer.close:()V
      76: goto          94
      79: astore        6
      81: aload_2
      82: aload         6
      84: invokevirtual #17                 // Method java/lang/Throwable.addSuppressed:(Ljava/lang/Throwable;)V
      87: goto          94
      90: aload_1
      91: invokevirtual #40                 // Method org/apache/jena/atlas/io/IndentedLineBuffer.close:()V
      94: aload         5
      96: athrow
    Exception table:
       from    to  target type
          33    37    40   Class java/lang/Throwable
          10    25    57   Class java/lang/Throwable
          10    25    62   any
          72    76    79   Class java/lang/Throwable
          57    64    62   any

  public static void write(java.io.OutputStream, org.apache.jena.atlas.json.JsonValue);
    Code:
       0: new           #42                 // class org/apache/jena/atlas/io/IndentedWriter
       3: dup
       4: aload_0
       5: invokespecial #43                 // Method org/apache/jena/atlas/io/IndentedWriter."<init>":(Ljava/io/OutputStream;)V
       8: astore_2
       9: aload_2
      10: aload_1
      11: invokestatic  #38                 // Method write:(Lorg/apache/jena/atlas/io/IndentedWriter;Lorg/apache/jena/atlas/json/JsonValue;)V
      14: aload_2
      15: invokevirtual #44                 // Method org/apache/jena/atlas/io/IndentedWriter.flush:()V
      18: return

  public static void write(org.apache.jena.atlas.io.IndentedWriter, org.apache.jena.atlas.json.JsonValue);
    Code:
       0: aload_0
       1: invokevirtual #45                 // Method org/apache/jena/atlas/io/IndentedWriter.getRow:()I
       4: istore_2
       5: new           #46                 // class org/apache/jena/atlas/json/io/JsonWriter
       8: dup
       9: aload_0
      10: invokespecial #47                 // Method org/apache/jena/atlas/json/io/JsonWriter."<init>":(Lorg/apache/jena/atlas/io/IndentedWriter;)V
      13: astore_3
      14: aload_3
      15: invokevirtual #48                 // Method org/apache/jena/atlas/json/io/JsonWriter.startOutput:()V
      18: aload_1
      19: aload_3
      20: invokevirtual #49                 // Method org/apache/jena/atlas/json/JsonValue.visit:(Lorg/apache/jena/atlas/json/JsonVisitor;)V
      23: aload_3
      24: invokevirtual #50                 // Method org/apache/jena/atlas/json/io/JsonWriter.finishOutput:()V
      27: aload_0
      28: invokevirtual #51                 // Method org/apache/jena/atlas/io/IndentedWriter.inFlatMode:()Z
      31: ifne          46
      34: aload_0
      35: invokevirtual #45                 // Method org/apache/jena/atlas/io/IndentedWriter.getRow:()I
      38: iload_2
      39: if_icmple     46
      42: aload_0
      43: invokevirtual #52                 // Method org/apache/jena/atlas/io/IndentedWriter.ensureStartOfLine:()V
      46: return

  public static void write(org.apache.jena.atlas.json.JsonValue);
    Code:
       0: getstatic     #53                 // Field org/apache/jena/atlas/io/IndentedWriter.stdout:Lorg/apache/jena/atlas/io/IndentedWriter;
       3: aload_0
       4: invokestatic  #38                 // Method write:(Lorg/apache/jena/atlas/io/IndentedWriter;Lorg/apache/jena/atlas/json/JsonValue;)V
       7: return

  public static org.apache.jena.atlas.json.JsonValue copy(org.apache.jena.atlas.json.JsonValue);
    Code:
       0: aload_0
       1: invokestatic  #54                 // Method org/apache/jena/atlas/json/JsonBuilder.copy:(Lorg/apache/jena/atlas/json/JsonValue;)Lorg/apache/jena/atlas/json/JsonValue;
       4: areturn

  public static org.apache.jena.atlas.json.JsonObject buildObject(java.util.function.Consumer<org.apache.jena.atlas.json.JsonBuilder>);
    Code:
       0: aload_0
       1: invokestatic  #55                 // Method org/apache/jena/atlas/json/JsonBuilder.buildObject:(Ljava/util/function/Consumer;)Lorg/apache/jena/atlas/json/JsonObject;
       4: areturn
}
