Compiled from "PathTranslatingPostProcessor.java"
class org.apache.maven.model.interpolation.PathTranslatingPostProcessor implements org.codehaus.plexus.interpolation.InterpolationPostProcessor {
  private final java.util.Collection<java.lang.String> unprefixedPathKeys;

  private final java.io.File projectDir;

  private final org.apache.maven.model.path.PathTranslator pathTranslator;

  private final java.util.List<java.lang.String> expressionPrefixes;

  public org.apache.maven.model.interpolation.PathTranslatingPostProcessor(java.util.List<java.lang.String>, java.util.Collection<java.lang.String>, java.io.File, org.apache.maven.model.path.PathTranslator);
    Code:
       0: aload_0
       1: invokespecial #1                  // Method java/lang/Object."<init>":()V
       4: aload_0
       5: aload_1
       6: putfield      #2                  // Field expressionPrefixes:Ljava/util/List;
       9: aload_0
      10: aload_2
      11: putfield      #3                  // Field unprefixedPathKeys:Ljava/util/Collection;
      14: aload_0
      15: aload_3
      16: putfield      #4                  // Field projectDir:Ljava/io/File;
      19: aload_0
      20: aload         4
      22: putfield      #5                  // Field pathTranslator:Lorg/apache/maven/model/path/PathTranslator;
      25: return

  public java.lang.Object execute(java.lang.String, java.lang.Object);
    Code:
       0: aload_2
       1: ifnull        45
       4: aload_1
       5: aload_0
       6: getfield      #2                  // Field expressionPrefixes:Ljava/util/List;
       9: iconst_1
      10: invokestatic  #6                  // Method org/codehaus/plexus/interpolation/util/ValueSourceUtils.trimPrefix:(Ljava/lang/String;Ljava/util/Collection;Z)Ljava/lang/String;
      13: astore_1
      14: aload_0
      15: getfield      #3                  // Field unprefixedPathKeys:Ljava/util/Collection;
      18: aload_1
      19: invokeinterface #7,  2            // InterfaceMethod java/util/Collection.contains:(Ljava/lang/Object;)Z
      24: ifeq          45
      27: aload_0
      28: getfield      #5                  // Field pathTranslator:Lorg/apache/maven/model/path/PathTranslator;
      31: aload_2
      32: invokestatic  #8                  // Method java/lang/String.valueOf:(Ljava/lang/Object;)Ljava/lang/String;
      35: aload_0
      36: getfield      #4                  // Field projectDir:Ljava/io/File;
      39: invokeinterface #9,  3            // InterfaceMethod org/apache/maven/model/path/PathTranslator.alignToBaseDirectory:(Ljava/lang/String;Ljava/io/File;)Ljava/lang/String;
      44: areturn
      45: aconst_null
      46: areturn
}
