Compiled from "CommaSeparatedList.java"
public class net.jangaroo.jooc.ast.CommaSeparatedList<T extends net.jangaroo.jooc.ast.AstNode> extends net.jangaroo.jooc.ast.Expr {
  private T head;

  private net.jangaroo.jooc.JooSymbol symComma;

  private net.jangaroo.jooc.ast.CommaSeparatedList<T> tail;

  public net.jangaroo.jooc.ast.CommaSeparatedList(T);
    Code:
       0: aload_0
       1: aload_1
       2: aconst_null
       3: aconst_null
       4: invokespecial #1                  // Method "<init>":(Lnet/jangaroo/jooc/ast/AstNode;Lnet/jangaroo/jooc/JooSymbol;Lnet/jangaroo/jooc/ast/CommaSeparatedList;)V
       7: return

  public net.jangaroo.jooc.ast.CommaSeparatedList(T, net.jangaroo.jooc.JooSymbol, net.jangaroo.jooc.ast.CommaSeparatedList<T>);
    Code:
       0: aload_0
       1: invokespecial #2                  // Method net/jangaroo/jooc/ast/Expr."<init>":()V
       4: aload_0
       5: aload_1
       6: putfield      #3                  // Field head:Lnet/jangaroo/jooc/ast/AstNode;
       9: aload_0
      10: aload_2
      11: putfield      #4                  // Field symComma:Lnet/jangaroo/jooc/JooSymbol;
      14: aload_0
      15: aload_3
      16: putfield      #5                  // Field tail:Lnet/jangaroo/jooc/ast/CommaSeparatedList;
      19: return

  public java.util.List<? extends net.jangaroo.jooc.ast.AstNode> getChildren();
    Code:
       0: aload_0
       1: iconst_3
       2: anewarray     #6                  // class java/lang/Object
       5: dup
       6: iconst_0
       7: aload_0
       8: invokespecial #7                  // Method net/jangaroo/jooc/ast/Expr.getChildren:()Ljava/util/List;
      11: aastore
      12: dup
      13: iconst_1
      14: aload_0
      15: getfield      #3                  // Field head:Lnet/jangaroo/jooc/ast/AstNode;
      18: aastore
      19: dup
      20: iconst_2
      21: aload_0
      22: getfield      #5                  // Field tail:Lnet/jangaroo/jooc/ast/CommaSeparatedList;
      25: aastore
      26: invokevirtual #8                  // Method makeChildren:([Ljava/lang/Object;)Ljava/util/List;
      29: areturn

  public void visit(net.jangaroo.jooc.ast.AstVisitor) throws java.io.IOException;
    Code:
       0: aload_1
       1: aload_0
       2: invokeinterface #9,  2            // InterfaceMethod net/jangaroo/jooc/ast/AstVisitor.visitCommaSeparatedList:(Lnet/jangaroo/jooc/ast/CommaSeparatedList;)V
       7: return

  public void scope(net.jangaroo.jooc.Scope);
    Code:
       0: aload_0
       1: invokevirtual #10                 // Method getHead:()Lnet/jangaroo/jooc/ast/AstNode;
       4: ifnull        17
       7: aload_0
       8: invokevirtual #10                 // Method getHead:()Lnet/jangaroo/jooc/ast/AstNode;
      11: aload_1
      12: invokeinterface #11,  2           // InterfaceMethod net/jangaroo/jooc/ast/AstNode.scope:(Lnet/jangaroo/jooc/Scope;)V
      17: aload_0
      18: invokevirtual #12                 // Method getTail:()Lnet/jangaroo/jooc/ast/CommaSeparatedList;
      21: ifnull        32
      24: aload_0
      25: invokevirtual #12                 // Method getTail:()Lnet/jangaroo/jooc/ast/CommaSeparatedList;
      28: aload_1
      29: invokevirtual #13                 // Method scope:(Lnet/jangaroo/jooc/Scope;)V
      32: return

  public void analyze(net.jangaroo.jooc.ast.AstNode);
    Code:
       0: aload_0
       1: aload_1
       2: invokespecial #14                 // Method net/jangaroo/jooc/ast/Expr.analyze:(Lnet/jangaroo/jooc/ast/AstNode;)V
       5: aload_0
       6: invokevirtual #10                 // Method getHead:()Lnet/jangaroo/jooc/ast/AstNode;
       9: ifnull        22
      12: aload_0
      13: invokevirtual #10                 // Method getHead:()Lnet/jangaroo/jooc/ast/AstNode;
      16: aload_0
      17: invokeinterface #15,  2           // InterfaceMethod net/jangaroo/jooc/ast/AstNode.analyze:(Lnet/jangaroo/jooc/ast/AstNode;)V
      22: aload_0
      23: invokevirtual #12                 // Method getTail:()Lnet/jangaroo/jooc/ast/CommaSeparatedList;
      26: ifnull        37
      29: aload_0
      30: invokevirtual #12                 // Method getTail:()Lnet/jangaroo/jooc/ast/CommaSeparatedList;
      33: aload_0
      34: invokevirtual #16                 // Method analyze:(Lnet/jangaroo/jooc/ast/AstNode;)V
      37: return

  public net.jangaroo.jooc.JooSymbol getSymbol();
    Code:
       0: aload_0
       1: invokevirtual #10                 // Method getHead:()Lnet/jangaroo/jooc/ast/AstNode;
       4: ifnull        19
       7: aload_0
       8: invokevirtual #10                 // Method getHead:()Lnet/jangaroo/jooc/ast/AstNode;
      11: invokeinterface #17,  1           // InterfaceMethod net/jangaroo/jooc/ast/AstNode.getSymbol:()Lnet/jangaroo/jooc/JooSymbol;
      16: goto          23
      19: aload_0
      20: invokevirtual #18                 // Method getSymComma:()Lnet/jangaroo/jooc/JooSymbol;
      23: areturn

  public T getHead();
    Code:
       0: aload_0
       1: getfield      #3                  // Field head:Lnet/jangaroo/jooc/ast/AstNode;
       4: areturn

  public net.jangaroo.jooc.JooSymbol getSymComma();
    Code:
       0: aload_0
       1: getfield      #4                  // Field symComma:Lnet/jangaroo/jooc/JooSymbol;
       4: areturn

  public net.jangaroo.jooc.ast.CommaSeparatedList<T> getTail();
    Code:
       0: aload_0
       1: getfield      #5                  // Field tail:Lnet/jangaroo/jooc/ast/CommaSeparatedList;
       4: areturn

  public boolean isStandAloneConstant();
    Code:
       0: aload_0
       1: getfield      #3                  // Field head:Lnet/jangaroo/jooc/ast/AstNode;
       4: instanceof    #19                 // class net/jangaroo/jooc/ast/Expr
       7: ifeq          23
      10: aload_0
      11: getfield      #3                  // Field head:Lnet/jangaroo/jooc/ast/AstNode;
      14: checkcast     #19                 // class net/jangaroo/jooc/ast/Expr
      17: invokevirtual #20                 // Method net/jangaroo/jooc/ast/Expr.isStandAloneConstant:()Z
      20: ifne          46
      23: aload_0
      24: getfield      #3                  // Field head:Lnet/jangaroo/jooc/ast/AstNode;
      27: instanceof    #21                 // class net/jangaroo/jooc/ast/ObjectField
      30: ifeq          67
      33: aload_0
      34: getfield      #3                  // Field head:Lnet/jangaroo/jooc/ast/AstNode;
      37: checkcast     #21                 // class net/jangaroo/jooc/ast/ObjectField
      40: invokevirtual #22                 // Method net/jangaroo/jooc/ast/ObjectField.isStandAloneConstant:()Z
      43: ifeq          67
      46: aload_0
      47: getfield      #5                  // Field tail:Lnet/jangaroo/jooc/ast/CommaSeparatedList;
      50: ifnull        63
      53: aload_0
      54: getfield      #5                  // Field tail:Lnet/jangaroo/jooc/ast/CommaSeparatedList;
      57: invokevirtual #23                 // Method isStandAloneConstant:()Z
      60: ifeq          67
      63: iconst_1
      64: goto          68
      67: iconst_0
      68: ireturn
}
