Compiled from "ImportDirective.java"
public class net.jangaroo.jooc.ast.ImportDirective extends net.jangaroo.jooc.ast.Directive {
  private static final net.jangaroo.jooc.JooSymbol IMPORT_SYMBOL;

  private static final net.jangaroo.jooc.JooSymbol DOT_SYMBOL;

  private net.jangaroo.jooc.JooSymbol importKeyword;

  private net.jangaroo.jooc.ast.Ide ide;

  private net.jangaroo.jooc.JooSymbol symSemicolon;

  private final boolean explicit;

  public net.jangaroo.jooc.ast.ImportDirective(net.jangaroo.jooc.ast.Ide, java.lang.String);
    Code:
       0: aload_0
       1: aload_1
       2: invokestatic  #1                  // Method createImportDirective:(Lnet/jangaroo/jooc/ast/Ide;)Lnet/jangaroo/jooc/JooSymbol;
       5: aload_1
       6: new           #2                  // class net/jangaroo/jooc/JooSymbol
       9: dup
      10: aload_2
      11: invokespecial #3                  // Method net/jangaroo/jooc/JooSymbol."<init>":(Ljava/lang/String;)V
      14: invokestatic  #4                  // Method createIde:(Lnet/jangaroo/jooc/ast/Ide;Lnet/jangaroo/jooc/JooSymbol;)Lnet/jangaroo/jooc/ast/Ide;
      17: iconst_0
      18: invokespecial #5                  // Method "<init>":(Lnet/jangaroo/jooc/JooSymbol;Lnet/jangaroo/jooc/ast/Ide;Z)V
      21: return

  private static net.jangaroo.jooc.JooSymbol createImportDirective(net.jangaroo.jooc.ast.Ide);
    Code:
       0: aload_0
       1: ifnonnull     8
       4: getstatic     #6                  // Field IMPORT_SYMBOL:Lnet/jangaroo/jooc/JooSymbol;
       7: areturn
       8: aload_0
       9: invokevirtual #7                  // Method net/jangaroo/jooc/ast/Ide.getSymbol:()Lnet/jangaroo/jooc/JooSymbol;
      12: astore_1
      13: new           #2                  // class net/jangaroo/jooc/JooSymbol
      16: dup
      17: bipush        19
      19: aload_1
      20: invokevirtual #9                  // Method net/jangaroo/jooc/JooSymbol.getFileName:()Ljava/lang/String;
      23: aload_1
      24: invokevirtual #10                 // Method net/jangaroo/jooc/JooSymbol.getLine:()I
      27: aload_1
      28: invokevirtual #11                 // Method net/jangaroo/jooc/JooSymbol.getColumn:()I
      31: ldc           #12                 // String
      33: ldc           #13                 // String import
      35: invokespecial #14                 // Method net/jangaroo/jooc/JooSymbol."<init>":(ILjava/lang/String;IILjava/lang/String;Ljava/lang/String;)V
      38: areturn

  public net.jangaroo.jooc.ast.ImportDirective(net.jangaroo.jooc.JooSymbol, net.jangaroo.jooc.ast.Ide, net.jangaroo.jooc.JooSymbol);
    Code:
       0: aload_0
       1: aload_1
       2: aload_2
       3: iconst_1
       4: invokespecial #5                  // Method "<init>":(Lnet/jangaroo/jooc/JooSymbol;Lnet/jangaroo/jooc/ast/Ide;Z)V
       7: aload_0
       8: aload_3
       9: putfield      #15                 // Field symSemicolon:Lnet/jangaroo/jooc/JooSymbol;
      12: return

  private net.jangaroo.jooc.ast.ImportDirective(net.jangaroo.jooc.JooSymbol, net.jangaroo.jooc.ast.Ide, boolean);
    Code:
       0: aload_0
       1: invokespecial #16                 // Method net/jangaroo/jooc/ast/Directive."<init>":()V
       4: aload_0
       5: aload_1
       6: putfield      #17                 // Field importKeyword:Lnet/jangaroo/jooc/JooSymbol;
       9: aload_0
      10: aload_2
      11: putfield      #18                 // Field ide:Lnet/jangaroo/jooc/ast/Ide;
      14: aload_0
      15: iload_3
      16: putfield      #19                 // Field explicit:Z
      19: return

  public java.util.List<? extends net.jangaroo.jooc.ast.AstNode> getChildren();
    Code:
       0: aload_0
       1: iconst_2
       2: anewarray     #20                 // class java/lang/Object
       5: dup
       6: iconst_0
       7: aload_0
       8: invokespecial #21                 // Method net/jangaroo/jooc/ast/Directive.getChildren:()Ljava/util/List;
      11: aastore
      12: dup
      13: iconst_1
      14: aload_0
      15: getfield      #18                 // Field ide:Lnet/jangaroo/jooc/ast/Ide;
      18: aastore
      19: invokevirtual #22                 // Method makeChildren:([Ljava/lang/Object;)Ljava/util/List;
      22: areturn

  private static net.jangaroo.jooc.ast.Ide createIde(net.jangaroo.jooc.ast.Ide, net.jangaroo.jooc.JooSymbol);
    Code:
       0: aload_0
       1: ifnonnull     15
       4: new           #23                 // class net/jangaroo/jooc/ast/Ide
       7: dup
       8: aload_1
       9: invokespecial #24                 // Method net/jangaroo/jooc/ast/Ide."<init>":(Lnet/jangaroo/jooc/JooSymbol;)V
      12: goto          27
      15: new           #25                 // class net/jangaroo/jooc/ast/QualifiedIde
      18: dup
      19: aload_0
      20: getstatic     #26                 // Field DOT_SYMBOL:Lnet/jangaroo/jooc/JooSymbol;
      23: aload_1
      24: invokespecial #27                 // Method net/jangaroo/jooc/ast/QualifiedIde."<init>":(Lnet/jangaroo/jooc/ast/Ide;Lnet/jangaroo/jooc/JooSymbol;Lnet/jangaroo/jooc/JooSymbol;)V
      27: areturn

  public void visit(net.jangaroo.jooc.ast.AstVisitor) throws java.io.IOException;
    Code:
       0: aload_1
       1: aload_0
       2: invokeinterface #28,  2           // InterfaceMethod net/jangaroo/jooc/ast/AstVisitor.visitImportDirective:(Lnet/jangaroo/jooc/ast/ImportDirective;)V
       7: return

  public void scope(net.jangaroo.jooc.Scope);
    Code:
       0: aload_0
       1: invokevirtual #29                 // Method getIde:()Lnet/jangaroo/jooc/ast/Ide;
       4: aload_1
       5: invokevirtual #30                 // Method net/jangaroo/jooc/ast/Ide.scope:(Lnet/jangaroo/jooc/Scope;)V
       8: aload_1
       9: aload_0
      10: invokeinterface #31,  2           // InterfaceMethod net/jangaroo/jooc/Scope.addImport:(Lnet/jangaroo/jooc/ast/ImportDirective;)V
      15: return

  public void analyze(net.jangaroo.jooc.ast.AstNode);
    Code:
       0: aload_0
       1: aload_1
       2: invokespecial #32                 // Method net/jangaroo/jooc/ast/Directive.analyze:(Lnet/jangaroo/jooc/ast/AstNode;)V
       5: ldc           #33                 // String *
       7: aload_0
       8: invokevirtual #29                 // Method getIde:()Lnet/jangaroo/jooc/ast/Ide;
      11: invokevirtual #34                 // Method net/jangaroo/jooc/ast/Ide.getName:()Ljava/lang/String;
      14: invokevirtual #35                 // Method java/lang/String.equals:(Ljava/lang/Object;)Z
      17: ifne          37
      20: aload_0
      21: invokevirtual #29                 // Method getIde:()Lnet/jangaroo/jooc/ast/Ide;
      24: invokevirtual #36                 // Method net/jangaroo/jooc/ast/Ide.getScope:()Lnet/jangaroo/jooc/Scope;
      27: invokeinterface #37,  1           // InterfaceMethod net/jangaroo/jooc/Scope.getCompiler:()Lnet/jangaroo/jooc/JangarooParser;
      32: aload_0
      33: invokevirtual #38                 // Method net/jangaroo/jooc/JangarooParser.resolveImport:(Lnet/jangaroo/jooc/ast/ImportDirective;)Lnet/jangaroo/jooc/ast/IdeDeclaration;
      36: pop
      37: return

  public java.lang.String getQualifiedName();
    Code:
       0: aload_0
       1: invokevirtual #29                 // Method getIde:()Lnet/jangaroo/jooc/ast/Ide;
       4: invokevirtual #39                 // Method net/jangaroo/jooc/ast/Ide.getQualifiedNameStr:()Ljava/lang/String;
       7: areturn

  public net.jangaroo.jooc.JooSymbol getSymbol();
    Code:
       0: aload_0
       1: invokevirtual #40                 // Method getImportKeyword:()Lnet/jangaroo/jooc/JooSymbol;
       4: areturn

  public boolean equals(java.lang.Object);
    Code:
       0: aload_0
       1: aload_1
       2: if_acmpne     7
       5: iconst_1
       6: ireturn
       7: aload_1
       8: ifnull        22
      11: aload_0
      12: invokevirtual #41                 // Method java/lang/Object.getClass:()Ljava/lang/Class;
      15: aload_1
      16: invokevirtual #41                 // Method java/lang/Object.getClass:()Ljava/lang/Class;
      19: if_acmpeq     24
      22: iconst_0
      23: ireturn
      24: aload_1
      25: checkcast     #42                 // class net/jangaroo/jooc/ast/ImportDirective
      28: astore_2
      29: aload_0
      30: invokevirtual #43                 // Method isExplicit:()Z
      33: aload_2
      34: invokevirtual #43                 // Method isExplicit:()Z
      37: if_icmpeq     42
      40: iconst_0
      41: ireturn
      42: aload_0
      43: invokevirtual #29                 // Method getIde:()Lnet/jangaroo/jooc/ast/Ide;
      46: ifnull        66
      49: aload_0
      50: invokevirtual #29                 // Method getIde:()Lnet/jangaroo/jooc/ast/Ide;
      53: aload_2
      54: invokevirtual #29                 // Method getIde:()Lnet/jangaroo/jooc/ast/Ide;
      57: invokevirtual #44                 // Method net/jangaroo/jooc/ast/Ide.equals:(Ljava/lang/Object;)Z
      60: ifne          75
      63: goto          73
      66: aload_2
      67: invokevirtual #29                 // Method getIde:()Lnet/jangaroo/jooc/ast/Ide;
      70: ifnull        75
      73: iconst_0
      74: ireturn
      75: iconst_1
      76: ireturn

  public int hashCode();
    Code:
       0: aload_0
       1: invokevirtual #29                 // Method getIde:()Lnet/jangaroo/jooc/ast/Ide;
       4: ifnull        17
       7: aload_0
       8: invokevirtual #29                 // Method getIde:()Lnet/jangaroo/jooc/ast/Ide;
      11: invokevirtual #45                 // Method net/jangaroo/jooc/ast/Ide.hashCode:()I
      14: goto          18
      17: iconst_0
      18: istore_1
      19: bipush        31
      21: iload_1
      22: imul
      23: aload_0
      24: invokevirtual #43                 // Method isExplicit:()Z
      27: ifeq          34
      30: iconst_1
      31: goto          35
      34: iconst_0
      35: iadd
      36: istore_1
      37: iload_1
      38: ireturn

  public net.jangaroo.jooc.JooSymbol getImportKeyword();
    Code:
       0: aload_0
       1: getfield      #17                 // Field importKeyword:Lnet/jangaroo/jooc/JooSymbol;
       4: areturn

  public net.jangaroo.jooc.ast.Ide getIde();
    Code:
       0: aload_0
       1: getfield      #18                 // Field ide:Lnet/jangaroo/jooc/ast/Ide;
       4: areturn

  public net.jangaroo.jooc.JooSymbol getSymSemicolon();
    Code:
       0: aload_0
       1: getfield      #15                 // Field symSemicolon:Lnet/jangaroo/jooc/JooSymbol;
       4: areturn

  public boolean isExplicit();
    Code:
       0: aload_0
       1: getfield      #19                 // Field explicit:Z
       4: ireturn

  public java.lang.String toString();
    Code:
       0: new           #46                 // class java/lang/StringBuilder
       3: dup
       4: invokespecial #47                 // Method java/lang/StringBuilder."<init>":()V
       7: ldc           #48                 // String ImportDirective{ide=
       9: invokevirtual #49                 // Method java/lang/StringBuilder.append:(Ljava/lang/String;)Ljava/lang/StringBuilder;
      12: aload_0
      13: getfield      #18                 // Field ide:Lnet/jangaroo/jooc/ast/Ide;
      16: invokevirtual #50                 // Method java/lang/StringBuilder.append:(Ljava/lang/Object;)Ljava/lang/StringBuilder;
      19: bipush        125
      21: invokevirtual #51                 // Method java/lang/StringBuilder.append:(C)Ljava/lang/StringBuilder;
      24: invokevirtual #52                 // Method java/lang/StringBuilder.toString:()Ljava/lang/String;
      27: areturn

  static {};
    Code:
       0: new           #2                  // class net/jangaroo/jooc/JooSymbol
       3: dup
       4: bipush        19
       6: ldc           #13                 // String import
       8: invokespecial #53                 // Method net/jangaroo/jooc/JooSymbol."<init>":(ILjava/lang/String;)V
      11: putstatic     #6                  // Field IMPORT_SYMBOL:Lnet/jangaroo/jooc/JooSymbol;
      14: new           #2                  // class net/jangaroo/jooc/JooSymbol
      17: dup
      18: bipush        73
      20: ldc           #54                 // String .
      22: invokespecial #53                 // Method net/jangaroo/jooc/JooSymbol."<init>":(ILjava/lang/String;)V
      25: putstatic     #26                 // Field DOT_SYMBOL:Lnet/jangaroo/jooc/JooSymbol;
      28: return
}
