Compiled from "ParenthesizedExpr.java"
public class net.jangaroo.jooc.ast.ParenthesizedExpr<E extends net.jangaroo.jooc.ast.Expr> extends net.jangaroo.jooc.ast.Expr {
  private net.jangaroo.jooc.JooSymbol lParen;

  private E expr;

  private net.jangaroo.jooc.JooSymbol rParen;

  public net.jangaroo.jooc.ast.ParenthesizedExpr(net.jangaroo.jooc.JooSymbol, E, net.jangaroo.jooc.JooSymbol);
    Code:
       0: aload_0
       1: invokespecial #1                  // Method net/jangaroo/jooc/ast/Expr."<init>":()V
       4: aload_0
       5: aload_1
       6: putfield      #2                  // Field lParen:Lnet/jangaroo/jooc/JooSymbol;
       9: aload_0
      10: aload_2
      11: putfield      #3                  // Field expr:Lnet/jangaroo/jooc/ast/Expr;
      14: aload_0
      15: aload_3
      16: putfield      #4                  // Field rParen:Lnet/jangaroo/jooc/JooSymbol;
      19: return

  public java.util.List<? extends net.jangaroo.jooc.ast.AstNode> getChildren();
    Code:
       0: aload_0
       1: iconst_2
       2: anewarray     #5                  // class java/lang/Object
       5: dup
       6: iconst_0
       7: aload_0
       8: invokespecial #6                  // Method net/jangaroo/jooc/ast/Expr.getChildren:()Ljava/util/List;
      11: aastore
      12: dup
      13: iconst_1
      14: aload_0
      15: getfield      #3                  // Field expr:Lnet/jangaroo/jooc/ast/Expr;
      18: aastore
      19: invokevirtual #7                  // Method makeChildren:([Ljava/lang/Object;)Ljava/util/List;
      22: areturn

  public void visit(net.jangaroo.jooc.ast.AstVisitor) throws java.io.IOException;
    Code:
       0: aload_1
       1: aload_0
       2: invokeinterface #8,  2            // InterfaceMethod net/jangaroo/jooc/ast/AstVisitor.visitParenthesizedExpr:(Lnet/jangaroo/jooc/ast/ParenthesizedExpr;)V
       7: return

  public void scope(net.jangaroo.jooc.Scope);
    Code:
       0: aload_0
       1: invokevirtual #9                  // Method getExpr:()Lnet/jangaroo/jooc/ast/Expr;
       4: ifnull        15
       7: aload_0
       8: invokevirtual #9                  // Method getExpr:()Lnet/jangaroo/jooc/ast/Expr;
      11: aload_1
      12: invokevirtual #10                 // Method net/jangaroo/jooc/ast/Expr.scope:(Lnet/jangaroo/jooc/Scope;)V
      15: return

  public void analyze(net.jangaroo.jooc.ast.AstNode);
    Code:
       0: aload_0
       1: aload_1
       2: invokespecial #11                 // Method net/jangaroo/jooc/ast/Expr.analyze:(Lnet/jangaroo/jooc/ast/AstNode;)V
       5: aload_0
       6: invokevirtual #9                  // Method getExpr:()Lnet/jangaroo/jooc/ast/Expr;
       9: astore_2
      10: aload_2
      11: ifnull        27
      14: aload_2
      15: aload_0
      16: invokevirtual #11                 // Method net/jangaroo/jooc/ast/Expr.analyze:(Lnet/jangaroo/jooc/ast/AstNode;)V
      19: aload_0
      20: aload_2
      21: invokevirtual #12                 // Method net/jangaroo/jooc/ast/Expr.getType:()Lnet/jangaroo/jooc/types/ExpressionType;
      24: invokevirtual #13                 // Method setType:(Lnet/jangaroo/jooc/types/ExpressionType;)V
      27: return

  public net.jangaroo.jooc.JooSymbol getSymbol();
    Code:
       0: aload_0
       1: invokevirtual #14                 // Method getLParen:()Lnet/jangaroo/jooc/JooSymbol;
       4: areturn

  public net.jangaroo.jooc.JooSymbol getLParen();
    Code:
       0: aload_0
       1: getfield      #2                  // Field lParen:Lnet/jangaroo/jooc/JooSymbol;
       4: areturn

  public E getExpr();
    Code:
       0: aload_0
       1: getfield      #3                  // Field expr:Lnet/jangaroo/jooc/ast/Expr;
       4: areturn

  public net.jangaroo.jooc.JooSymbol getRParen();
    Code:
       0: aload_0
       1: getfield      #4                  // Field rParen:Lnet/jangaroo/jooc/JooSymbol;
       4: areturn

  public boolean isStandAloneConstant();
    Code:
       0: aload_0
       1: getfield      #3                  // Field expr:Lnet/jangaroo/jooc/ast/Expr;
       4: ifnull        17
       7: aload_0
       8: getfield      #3                  // Field expr:Lnet/jangaroo/jooc/ast/Expr;
      11: invokevirtual #15                 // Method net/jangaroo/jooc/ast/Expr.isStandAloneConstant:()Z
      14: ifeq          21
      17: iconst_1
      18: goto          22
      21: iconst_0
      22: ireturn
}
