Compiled from "SuperConstructorCallStatement.java"
public class net.jangaroo.jooc.ast.SuperConstructorCallStatement extends net.jangaroo.jooc.ast.Statement {
  private net.jangaroo.jooc.ast.Expr fun;

  private net.jangaroo.jooc.ast.ParenthesizedExpr<net.jangaroo.jooc.ast.CommaSeparatedList<net.jangaroo.jooc.ast.Expr>> args;

  private net.jangaroo.jooc.JooSymbol symSemicolon;

  private net.jangaroo.jooc.ast.ClassDeclaration classDeclaration;

  public net.jangaroo.jooc.ast.SuperConstructorCallStatement(net.jangaroo.jooc.JooSymbol, net.jangaroo.jooc.JooSymbol, net.jangaroo.jooc.ast.CommaSeparatedList<net.jangaroo.jooc.ast.Expr>, net.jangaroo.jooc.JooSymbol, net.jangaroo.jooc.JooSymbol);
    Code:
       0: aload_0
       1: invokespecial #1                  // Method net/jangaroo/jooc/ast/Statement."<init>":()V
       4: aload_0
       5: new           #2                  // class net/jangaroo/jooc/ast/IdeExpr
       8: dup
       9: aload_1
      10: invokespecial #3                  // Method net/jangaroo/jooc/ast/IdeExpr."<init>":(Lnet/jangaroo/jooc/JooSymbol;)V
      13: putfield      #4                  // Field fun:Lnet/jangaroo/jooc/ast/Expr;
      16: aload_0
      17: new           #5                  // class net/jangaroo/jooc/ast/ParenthesizedExpr
      20: dup
      21: aload_2
      22: aload_3
      23: aload         4
      25: invokespecial #6                  // Method net/jangaroo/jooc/ast/ParenthesizedExpr."<init>":(Lnet/jangaroo/jooc/JooSymbol;Lnet/jangaroo/jooc/ast/Expr;Lnet/jangaroo/jooc/JooSymbol;)V
      28: putfield      #7                  // Field args:Lnet/jangaroo/jooc/ast/ParenthesizedExpr;
      31: aload_0
      32: aload         5
      34: putfield      #8                  // Field symSemicolon:Lnet/jangaroo/jooc/JooSymbol;
      37: return

  public java.util.List<? extends net.jangaroo.jooc.ast.AstNode> getChildren();
    Code:
       0: aload_0
       1: iconst_3
       2: anewarray     #9                  // class java/lang/Object
       5: dup
       6: iconst_0
       7: aload_0
       8: invokespecial #10                 // Method net/jangaroo/jooc/ast/Statement.getChildren:()Ljava/util/List;
      11: aastore
      12: dup
      13: iconst_1
      14: aload_0
      15: getfield      #4                  // Field fun:Lnet/jangaroo/jooc/ast/Expr;
      18: aastore
      19: dup
      20: iconst_2
      21: aload_0
      22: getfield      #7                  // Field args:Lnet/jangaroo/jooc/ast/ParenthesizedExpr;
      25: aastore
      26: invokevirtual #11                 // Method makeChildren:([Ljava/lang/Object;)Ljava/util/List;
      29: areturn

  public void visit(net.jangaroo.jooc.ast.AstVisitor) throws java.io.IOException;
    Code:
       0: aload_1
       1: aload_0
       2: invokeinterface #12,  2           // InterfaceMethod net/jangaroo/jooc/ast/AstVisitor.visitSuperConstructorCallStatement:(Lnet/jangaroo/jooc/ast/SuperConstructorCallStatement;)V
       7: return

  public void scope(net.jangaroo.jooc.Scope);
    Code:
       0: aload_0
       1: invokevirtual #13                 // Method getFun:()Lnet/jangaroo/jooc/ast/Expr;
       4: aload_1
       5: invokevirtual #14                 // Method net/jangaroo/jooc/ast/Expr.scope:(Lnet/jangaroo/jooc/Scope;)V
       8: aload_0
       9: invokevirtual #15                 // Method getArgs:()Lnet/jangaroo/jooc/ast/ParenthesizedExpr;
      12: ifnull        23
      15: aload_0
      16: invokevirtual #15                 // Method getArgs:()Lnet/jangaroo/jooc/ast/ParenthesizedExpr;
      19: aload_1
      20: invokevirtual #16                 // Method net/jangaroo/jooc/ast/ParenthesizedExpr.scope:(Lnet/jangaroo/jooc/Scope;)V
      23: aload_0
      24: aload_1
      25: invokeinterface #17,  1           // InterfaceMethod net/jangaroo/jooc/Scope.getClassDeclaration:()Lnet/jangaroo/jooc/ast/ClassDeclaration;
      30: invokevirtual #18                 // Method setClassDeclaration:(Lnet/jangaroo/jooc/ast/ClassDeclaration;)V
      33: aload_1
      34: invokeinterface #19,  1           // InterfaceMethod net/jangaroo/jooc/Scope.getMethodDeclaration:()Lnet/jangaroo/jooc/ast/FunctionDeclaration;
      39: astore_2
      40: aload_2
      41: ifnull        51
      44: aload_2
      45: invokevirtual #20                 // Method net/jangaroo/jooc/ast/FunctionDeclaration.isConstructor:()Z
      48: ifne          61
      51: aload_0
      52: invokevirtual #21                 // Method getSymbol:()Lnet/jangaroo/jooc/JooSymbol;
      55: ldc           #22                 // String must only call super constructor from constructor method
      57: invokestatic  #23                 // Method net/jangaroo/jooc/JangarooParser.error:(Lnet/jangaroo/jooc/api/FilePosition;Ljava/lang/String;)Lnet/jangaroo/jooc/CompilerError;
      60: athrow
      61: aload_2
      62: invokevirtual #24                 // Method net/jangaroo/jooc/ast/FunctionDeclaration.containsSuperConstructorCall:()Z
      65: ifeq          78
      68: aload_0
      69: invokevirtual #21                 // Method getSymbol:()Lnet/jangaroo/jooc/JooSymbol;
      72: ldc           #25                 // String must not call super constructor twice
      74: invokestatic  #23                 // Method net/jangaroo/jooc/JangarooParser.error:(Lnet/jangaroo/jooc/api/FilePosition;Ljava/lang/String;)Lnet/jangaroo/jooc/CompilerError;
      77: athrow
      78: aload_2
      79: iconst_1
      80: invokevirtual #26                 // Method net/jangaroo/jooc/ast/FunctionDeclaration.setContainsSuperConstructorCall:(Z)V
      83: return

  public void analyze(net.jangaroo.jooc.ast.AstNode);
    Code:
       0: aload_0
       1: aload_1
       2: invokespecial #27                 // Method net/jangaroo/jooc/ast/Statement.analyze:(Lnet/jangaroo/jooc/ast/AstNode;)V
       5: aload_0
       6: invokevirtual #13                 // Method getFun:()Lnet/jangaroo/jooc/ast/Expr;
       9: aload_0
      10: invokevirtual #28                 // Method net/jangaroo/jooc/ast/Expr.analyze:(Lnet/jangaroo/jooc/ast/AstNode;)V
      13: aload_0
      14: invokevirtual #15                 // Method getArgs:()Lnet/jangaroo/jooc/ast/ParenthesizedExpr;
      17: ifnull        28
      20: aload_0
      21: invokevirtual #15                 // Method getArgs:()Lnet/jangaroo/jooc/ast/ParenthesizedExpr;
      24: aload_0
      25: invokevirtual #29                 // Method net/jangaroo/jooc/ast/ParenthesizedExpr.analyze:(Lnet/jangaroo/jooc/ast/AstNode;)V
      28: return

  public net.jangaroo.jooc.JooSymbol getSymbol();
    Code:
       0: aload_0
       1: invokevirtual #13                 // Method getFun:()Lnet/jangaroo/jooc/ast/Expr;
       4: invokevirtual #30                 // Method net/jangaroo/jooc/ast/Expr.getSymbol:()Lnet/jangaroo/jooc/JooSymbol;
       7: areturn

  public net.jangaroo.jooc.ast.Expr getFun();
    Code:
       0: aload_0
       1: getfield      #4                  // Field fun:Lnet/jangaroo/jooc/ast/Expr;
       4: areturn

  public net.jangaroo.jooc.ast.ParenthesizedExpr<net.jangaroo.jooc.ast.CommaSeparatedList<net.jangaroo.jooc.ast.Expr>> getArgs();
    Code:
       0: aload_0
       1: getfield      #7                  // Field args:Lnet/jangaroo/jooc/ast/ParenthesizedExpr;
       4: areturn

  public net.jangaroo.jooc.JooSymbol getSymSemicolon();
    Code:
       0: aload_0
       1: getfield      #8                  // Field symSemicolon:Lnet/jangaroo/jooc/JooSymbol;
       4: areturn

  public net.jangaroo.jooc.ast.ClassDeclaration getClassDeclaration();
    Code:
       0: aload_0
       1: getfield      #31                 // Field classDeclaration:Lnet/jangaroo/jooc/ast/ClassDeclaration;
       4: areturn

  public void setClassDeclaration(net.jangaroo.jooc.ast.ClassDeclaration);
    Code:
       0: aload_0
       1: aload_1
       2: putfield      #31                 // Field classDeclaration:Lnet/jangaroo/jooc/ast/ClassDeclaration;
       5: return
}
