Compiled from "JdbcTokenRepositoryImpl.java"
public class org.springframework.security.web.authentication.rememberme.JdbcTokenRepositoryImpl extends org.springframework.jdbc.core.support.JdbcDaoSupport implements org.springframework.security.web.authentication.rememberme.PersistentTokenRepository {
  public static final java.lang.String CREATE_TABLE_SQL;

  public static final java.lang.String DEF_TOKEN_BY_SERIES_SQL;

  public static final java.lang.String DEF_INSERT_TOKEN_SQL;

  public static final java.lang.String DEF_UPDATE_TOKEN_SQL;

  public static final java.lang.String DEF_REMOVE_USER_TOKENS_SQL;

  private java.lang.String tokensBySeriesSql;

  private java.lang.String insertTokenSql;

  private java.lang.String updateTokenSql;

  private java.lang.String removeUserTokensSql;

  private boolean createTableOnStartup;

  public org.springframework.security.web.authentication.rememberme.JdbcTokenRepositoryImpl();
    Code:
       0: aload_0
       1: invokespecial #1                  // Method org/springframework/jdbc/core/support/JdbcDaoSupport."<init>":()V
       4: aload_0
       5: ldc           #3                  // String select username,series,token,last_used from persistent_logins where series = ?
       7: putfield      #4                  // Field tokensBySeriesSql:Ljava/lang/String;
      10: aload_0
      11: ldc           #5                  // String insert into persistent_logins (username, series, token, last_used) values(?,?,?,?)
      13: putfield      #6                  // Field insertTokenSql:Ljava/lang/String;
      16: aload_0
      17: ldc           #7                  // String update persistent_logins set token = ?, last_used = ? where series = ?
      19: putfield      #8                  // Field updateTokenSql:Ljava/lang/String;
      22: aload_0
      23: ldc           #9                  // String delete from persistent_logins where username = ?
      25: putfield      #10                 // Field removeUserTokensSql:Ljava/lang/String;
      28: return

  protected void initDao();
    Code:
       0: aload_0
       1: getfield      #11                 // Field createTableOnStartup:Z
       4: ifeq          16
       7: aload_0
       8: invokevirtual #12                 // Method getJdbcTemplate:()Lorg/springframework/jdbc/core/JdbcTemplate;
      11: ldc           #13                 // String create table persistent_logins (username varchar(64) not null, series varchar(64) primary key, token varchar(64) not null, last_used timestamp not null)
      13: invokevirtual #14                 // Method org/springframework/jdbc/core/JdbcTemplate.execute:(Ljava/lang/String;)V
      16: return

  public void createNewToken(org.springframework.security.web.authentication.rememberme.PersistentRememberMeToken);
    Code:
       0: aload_0
       1: invokevirtual #12                 // Method getJdbcTemplate:()Lorg/springframework/jdbc/core/JdbcTemplate;
       4: aload_0
       5: getfield      #6                  // Field insertTokenSql:Ljava/lang/String;
       8: iconst_4
       9: anewarray     #15                 // class java/lang/Object
      12: dup
      13: iconst_0
      14: aload_1
      15: invokevirtual #16                 // Method org/springframework/security/web/authentication/rememberme/PersistentRememberMeToken.getUsername:()Ljava/lang/String;
      18: aastore
      19: dup
      20: iconst_1
      21: aload_1
      22: invokevirtual #17                 // Method org/springframework/security/web/authentication/rememberme/PersistentRememberMeToken.getSeries:()Ljava/lang/String;
      25: aastore
      26: dup
      27: iconst_2
      28: aload_1
      29: invokevirtual #18                 // Method org/springframework/security/web/authentication/rememberme/PersistentRememberMeToken.getTokenValue:()Ljava/lang/String;
      32: aastore
      33: dup
      34: iconst_3
      35: aload_1
      36: invokevirtual #19                 // Method org/springframework/security/web/authentication/rememberme/PersistentRememberMeToken.getDate:()Ljava/util/Date;
      39: aastore
      40: invokevirtual #20                 // Method org/springframework/jdbc/core/JdbcTemplate.update:(Ljava/lang/String;[Ljava/lang/Object;)I
      43: pop
      44: return

  public void updateToken(java.lang.String, java.lang.String, java.util.Date);
    Code:
       0: aload_0
       1: invokevirtual #12                 // Method getJdbcTemplate:()Lorg/springframework/jdbc/core/JdbcTemplate;
       4: aload_0
       5: getfield      #8                  // Field updateTokenSql:Ljava/lang/String;
       8: iconst_3
       9: anewarray     #15                 // class java/lang/Object
      12: dup
      13: iconst_0
      14: aload_2
      15: aastore
      16: dup
      17: iconst_1
      18: aload_3
      19: aastore
      20: dup
      21: iconst_2
      22: aload_1
      23: aastore
      24: invokevirtual #20                 // Method org/springframework/jdbc/core/JdbcTemplate.update:(Ljava/lang/String;[Ljava/lang/Object;)I
      27: pop
      28: return

  public org.springframework.security.web.authentication.rememberme.PersistentRememberMeToken getTokenForSeries(java.lang.String);
    Code:
       0: aload_0
       1: invokevirtual #12                 // Method getJdbcTemplate:()Lorg/springframework/jdbc/core/JdbcTemplate;
       4: aload_0
       5: getfield      #4                  // Field tokensBySeriesSql:Ljava/lang/String;
       8: invokedynamic #21,  0             // InvokeDynamic #0:mapRow:()Lorg/springframework/jdbc/core/RowMapper;
      13: iconst_1
      14: anewarray     #15                 // class java/lang/Object
      17: dup
      18: iconst_0
      19: aload_1
      20: aastore
      21: invokevirtual #22                 // Method org/springframework/jdbc/core/JdbcTemplate.queryForObject:(Ljava/lang/String;Lorg/springframework/jdbc/core/RowMapper;[Ljava/lang/Object;)Ljava/lang/Object;
      24: checkcast     #23                 // class org/springframework/security/web/authentication/rememberme/PersistentRememberMeToken
      27: areturn
      28: astore_2
      29: aload_0
      30: getfield      #25                 // Field logger:Lorg/apache/commons/logging/Log;
      33: invokeinterface #26,  1           // InterfaceMethod org/apache/commons/logging/Log.isDebugEnabled:()Z
      38: ifeq          75
      41: aload_0
      42: getfield      #25                 // Field logger:Lorg/apache/commons/logging/Log;
      45: new           #27                 // class java/lang/StringBuilder
      48: dup
      49: invokespecial #28                 // Method java/lang/StringBuilder."<init>":()V
      52: ldc           #29                 // String Querying token for series \'
      54: invokevirtual #30                 // Method java/lang/StringBuilder.append:(Ljava/lang/String;)Ljava/lang/StringBuilder;
      57: aload_1
      58: invokevirtual #30                 // Method java/lang/StringBuilder.append:(Ljava/lang/String;)Ljava/lang/StringBuilder;
      61: ldc           #31                 // String \' returned no results.
      63: invokevirtual #30                 // Method java/lang/StringBuilder.append:(Ljava/lang/String;)Ljava/lang/StringBuilder;
      66: invokevirtual #32                 // Method java/lang/StringBuilder.toString:()Ljava/lang/String;
      69: aload_2
      70: invokeinterface #33,  3           // InterfaceMethod org/apache/commons/logging/Log.debug:(Ljava/lang/Object;Ljava/lang/Throwable;)V
      75: goto          145
      78: astore_2
      79: aload_0
      80: getfield      #25                 // Field logger:Lorg/apache/commons/logging/Log;
      83: new           #27                 // class java/lang/StringBuilder
      86: dup
      87: invokespecial #28                 // Method java/lang/StringBuilder."<init>":()V
      90: ldc           #29                 // String Querying token for series \'
      92: invokevirtual #30                 // Method java/lang/StringBuilder.append:(Ljava/lang/String;)Ljava/lang/StringBuilder;
      95: aload_1
      96: invokevirtual #30                 // Method java/lang/StringBuilder.append:(Ljava/lang/String;)Ljava/lang/StringBuilder;
      99: ldc           #35                 // String \' returned more than one value. Series should be unique
     101: invokevirtual #30                 // Method java/lang/StringBuilder.append:(Ljava/lang/String;)Ljava/lang/StringBuilder;
     104: invokevirtual #32                 // Method java/lang/StringBuilder.toString:()Ljava/lang/String;
     107: invokeinterface #36,  2           // InterfaceMethod org/apache/commons/logging/Log.error:(Ljava/lang/Object;)V
     112: goto          145
     115: astore_2
     116: aload_0
     117: getfield      #25                 // Field logger:Lorg/apache/commons/logging/Log;
     120: new           #27                 // class java/lang/StringBuilder
     123: dup
     124: invokespecial #28                 // Method java/lang/StringBuilder."<init>":()V
     127: ldc           #38                 // String Failed to load token for series
     129: invokevirtual #30                 // Method java/lang/StringBuilder.append:(Ljava/lang/String;)Ljava/lang/StringBuilder;
     132: aload_1
     133: invokevirtual #30                 // Method java/lang/StringBuilder.append:(Ljava/lang/String;)Ljava/lang/StringBuilder;
     136: invokevirtual #32                 // Method java/lang/StringBuilder.toString:()Ljava/lang/String;
     139: aload_2
     140: invokeinterface #39,  3           // InterfaceMethod org/apache/commons/logging/Log.error:(Ljava/lang/Object;Ljava/lang/Throwable;)V
     145: aconst_null
     146: areturn
    Exception table:
       from    to  target type
           0    27    28   Class org/springframework/dao/EmptyResultDataAccessException
           0    27    78   Class org/springframework/dao/IncorrectResultSizeDataAccessException
           0    27   115   Class org/springframework/dao/DataAccessException

  public void removeUserTokens(java.lang.String);
    Code:
       0: aload_0
       1: invokevirtual #12                 // Method getJdbcTemplate:()Lorg/springframework/jdbc/core/JdbcTemplate;
       4: aload_0
       5: getfield      #10                 // Field removeUserTokensSql:Ljava/lang/String;
       8: iconst_1
       9: anewarray     #15                 // class java/lang/Object
      12: dup
      13: iconst_0
      14: aload_1
      15: aastore
      16: invokevirtual #20                 // Method org/springframework/jdbc/core/JdbcTemplate.update:(Ljava/lang/String;[Ljava/lang/Object;)I
      19: pop
      20: return

  public void setCreateTableOnStartup(boolean);
    Code:
       0: aload_0
       1: iload_1
       2: putfield      #11                 // Field createTableOnStartup:Z
       5: return

  private static org.springframework.security.web.authentication.rememberme.PersistentRememberMeToken lambda$getTokenForSeries$0(java.sql.ResultSet, int) throws java.sql.SQLException;
    Code:
       0: new           #23                 // class org/springframework/security/web/authentication/rememberme/PersistentRememberMeToken
       3: dup
       4: aload_0
       5: iconst_1
       6: invokeinterface #40,  2           // InterfaceMethod java/sql/ResultSet.getString:(I)Ljava/lang/String;
      11: aload_0
      12: iconst_2
      13: invokeinterface #40,  2           // InterfaceMethod java/sql/ResultSet.getString:(I)Ljava/lang/String;
      18: aload_0
      19: iconst_3
      20: invokeinterface #40,  2           // InterfaceMethod java/sql/ResultSet.getString:(I)Ljava/lang/String;
      25: aload_0
      26: iconst_4
      27: invokeinterface #41,  2           // InterfaceMethod java/sql/ResultSet.getTimestamp:(I)Ljava/sql/Timestamp;
      32: invokespecial #42                 // Method org/springframework/security/web/authentication/rememberme/PersistentRememberMeToken."<init>":(Ljava/lang/String;Ljava/lang/String;Ljava/lang/String;Ljava/util/Date;)V
      35: areturn
}
