Compiled from "VerifyingVisitor.java"
class org.picocontainer.visitors.VerifyingVisitor$ComponentAdapterCollector implements org.picocontainer.PicoVisitor {
  final org.picocontainer.visitors.VerifyingVisitor this$0;

  private org.picocontainer.visitors.VerifyingVisitor$ComponentAdapterCollector(org.picocontainer.visitors.VerifyingVisitor);
    Code:
       0: aload_0
       1: aload_1
       2: putfield      #18                 // Field this$0:Lorg/picocontainer/visitors/VerifyingVisitor;
       5: aload_0
       6: invokespecial #21                 // Method java/lang/Object."<init>":()V
       9: return

  public java.lang.Object traverse(java.lang.Object);
    Code:
       0: aconst_null
       1: areturn

  public boolean visitContainer(org.picocontainer.PicoContainer);
    Code:
       0: iconst_1
       1: ireturn

  public void visitComponentAdapter(org.picocontainer.ComponentAdapter);
    Code:
       0: aload_0
       1: getfield      #18                 // Field this$0:Lorg/picocontainer/visitors/VerifyingVisitor;
       4: invokestatic  #37                 // Method org/picocontainer/visitors/VerifyingVisitor.access$100:(Lorg/picocontainer/visitors/VerifyingVisitor;)Ljava/util/Set;
       7: aload_1
       8: invokeinterface #43,  2           // InterfaceMethod java/util/Set.add:(Ljava/lang/Object;)Z
      13: pop
      14: return

  public void visitComponentFactory(org.picocontainer.ComponentFactory);
    Code:
       0: aload_0
       1: getfield      #18                 // Field this$0:Lorg/picocontainer/visitors/VerifyingVisitor;
       4: invokestatic  #50                 // Method org/picocontainer/visitors/VerifyingVisitor.access$200:(Lorg/picocontainer/visitors/VerifyingVisitor;)Ljava/util/Set;
       7: aload_1
       8: invokeinterface #43,  2           // InterfaceMethod java/util/Set.add:(Ljava/lang/Object;)Z
      13: pop
      14: return

  public void visitParameter(org.picocontainer.Parameter);
    Code:
       0: return

  org.picocontainer.visitors.VerifyingVisitor$ComponentAdapterCollector(org.picocontainer.visitors.VerifyingVisitor, org.picocontainer.visitors.VerifyingVisitor$1);
    Code:
       0: aload_0
       1: aload_1
       2: invokespecial #59                 // Method "<init>":(Lorg/picocontainer/visitors/VerifyingVisitor;)V
       5: return
}
