Compiled from "GroupSequenceProviderCheck.java"
public class org.hibernate.validator.ap.checks.GroupSequenceProviderCheck extends org.hibernate.validator.ap.checks.AbstractConstraintCheck {
  private final javax.lang.model.util.Types typeUtils;

  private final org.hibernate.validator.ap.util.AnnotationApiHelper annotationApiHelper;

  private final javax.lang.model.type.TypeMirror defaultGroupSequenceProviderType;

  public org.hibernate.validator.ap.checks.GroupSequenceProviderCheck(org.hibernate.validator.ap.util.AnnotationApiHelper, javax.lang.model.util.Types);
    Code:
       0: aload_0
       1: invokespecial #3                  // Method org/hibernate/validator/ap/checks/AbstractConstraintCheck."<init>":()V
       4: aload_0
       5: aload_2
       6: putfield      #2                  // Field typeUtils:Ljavax/lang/model/util/Types;
       9: aload_0
      10: aload_1
      11: putfield      #4                  // Field annotationApiHelper:Lorg/hibernate/validator/ap/util/AnnotationApiHelper;
      14: aload_0
      15: aload_1
      16: ldc           #5                  // String org.hibernate.validator.spi.group.DefaultGroupSequenceProvider
      18: invokevirtual #6                  // Method org/hibernate/validator/ap/util/AnnotationApiHelper.getDeclaredTypeByName:(Ljava/lang/String;)Ljavax/lang/model/type/DeclaredType;
      21: putfield      #1                  // Field defaultGroupSequenceProviderType:Ljavax/lang/model/type/TypeMirror;
      24: return

  public java.util.Set<org.hibernate.validator.ap.checks.ConstraintCheckError> checkNonAnnotationType(javax.lang.model.element.TypeElement, javax.lang.model.element.AnnotationMirror);
    Code:
       0: invokestatic  #7                  // Method org/hibernate/validator/ap/util/CollectionHelper.newHashSet:()Ljava/util/HashSet;
       3: astore_3
       4: aload_3
       5: aload_0
       6: aload_1
       7: aload_2
       8: invokespecial #8                  // Method checkHostingElement:(Ljavax/lang/model/element/TypeElement;Ljavax/lang/model/element/AnnotationMirror;)Ljava/util/Set;
      11: invokeinterface #9,  2            // InterfaceMethod java/util/Set.addAll:(Ljava/util/Collection;)Z
      16: pop
      17: aload_3
      18: aload_0
      19: aload_1
      20: aload_2
      21: invokespecial #10                 // Method checkAnnotationValue:(Ljavax/lang/model/element/TypeElement;Ljavax/lang/model/element/AnnotationMirror;)Ljava/util/Set;
      24: invokeinterface #9,  2            // InterfaceMethod java/util/Set.addAll:(Ljava/util/Collection;)Z
      29: pop
      30: aload_3
      31: areturn

  private java.util.Set<org.hibernate.validator.ap.checks.ConstraintCheckError> checkHostingElement(javax.lang.model.element.TypeElement, javax.lang.model.element.AnnotationMirror);
    Code:
       0: aload_1
       1: invokeinterface #11,  1           // InterfaceMethod javax/lang/model/element/TypeElement.getKind:()Ljavax/lang/model/element/ElementKind;
       6: invokevirtual #12                 // Method javax/lang/model/element/ElementKind.isClass:()Z
       9: ifne          38
      12: iconst_1
      13: anewarray     #13                 // class org/hibernate/validator/ap/checks/ConstraintCheckError
      16: dup
      17: iconst_0
      18: new           #13                 // class org/hibernate/validator/ap/checks/ConstraintCheckError
      21: dup
      22: aload_1
      23: aload_2
      24: ldc           #14                 // String GROUP_SEQUENCE_PROVIDER_ANNOTATION_MUST_BE_DEFINED_ON_A_CLASS
      26: iconst_0
      27: anewarray     #15                 // class java/lang/Object
      30: invokespecial #16                 // Method org/hibernate/validator/ap/checks/ConstraintCheckError."<init>":(Ljavax/lang/model/element/Element;Ljavax/lang/model/element/AnnotationMirror;Ljava/lang/String;[Ljava/lang/Object;)V
      33: aastore
      34: invokestatic  #17                 // Method org/hibernate/validator/ap/util/CollectionHelper.asSet:([Ljava/lang/Object;)Ljava/util/Set;
      37: areturn
      38: aload_0
      39: getfield      #4                  // Field annotationApiHelper:Lorg/hibernate/validator/ap/util/AnnotationApiHelper;
      42: aload_1
      43: invokeinterface #18,  1           // InterfaceMethod javax/lang/model/element/TypeElement.getAnnotationMirrors:()Ljava/util/List;
      48: ldc           #19                 // String javax.validation.GroupSequence
      50: invokevirtual #20                 // Method org/hibernate/validator/ap/util/AnnotationApiHelper.getMirror:(Ljava/util/List;Ljava/lang/String;)Ljavax/lang/model/element/AnnotationMirror;
      53: ifnull        82
      56: iconst_1
      57: anewarray     #13                 // class org/hibernate/validator/ap/checks/ConstraintCheckError
      60: dup
      61: iconst_0
      62: new           #13                 // class org/hibernate/validator/ap/checks/ConstraintCheckError
      65: dup
      66: aload_1
      67: aload_2
      68: ldc           #21                 // String GROUP_SEQUENCE_PROVIDER_ANNOTATION_NOT_ALLOWED_ON_CLASS_WITH_GROUP_SEQUENCE_ANNOTATION
      70: iconst_0
      71: anewarray     #15                 // class java/lang/Object
      74: invokespecial #16                 // Method org/hibernate/validator/ap/checks/ConstraintCheckError."<init>":(Ljavax/lang/model/element/Element;Ljavax/lang/model/element/AnnotationMirror;Ljava/lang/String;[Ljava/lang/Object;)V
      77: aastore
      78: invokestatic  #17                 // Method org/hibernate/validator/ap/util/CollectionHelper.asSet:([Ljava/lang/Object;)Ljava/util/Set;
      81: areturn
      82: invokestatic  #22                 // Method java/util/Collections.emptySet:()Ljava/util/Set;
      85: areturn

  private java.util.Set<org.hibernate.validator.ap.checks.ConstraintCheckError> checkAnnotationValue(javax.lang.model.element.TypeElement, javax.lang.model.element.AnnotationMirror);
    Code:
       0: invokestatic  #7                  // Method org/hibernate/validator/ap/util/CollectionHelper.newHashSet:()Ljava/util/HashSet;
       3: astore_3
       4: aload_0
       5: getfield      #4                  // Field annotationApiHelper:Lorg/hibernate/validator/ap/util/AnnotationApiHelper;
       8: aload_2
       9: ldc           #23                 // String value
      11: invokevirtual #24                 // Method org/hibernate/validator/ap/util/AnnotationApiHelper.getAnnotationValue:(Ljavax/lang/model/element/AnnotationMirror;Ljava/lang/String;)Ljavax/lang/model/element/AnnotationValue;
      14: astore        4
      16: aload         4
      18: invokeinterface #25,  1           // InterfaceMethod javax/lang/model/element/AnnotationValue.getValue:()Ljava/lang/Object;
      23: checkcast     #26                 // class javax/lang/model/type/TypeMirror
      26: astore        5
      28: aload_0
      29: getfield      #2                  // Field typeUtils:Ljavax/lang/model/util/Types;
      32: aload         5
      34: invokeinterface #27,  2           // InterfaceMethod javax/lang/model/util/Types.asElement:(Ljavax/lang/model/type/TypeMirror;)Ljavax/lang/model/element/Element;
      39: checkcast     #28                 // class javax/lang/model/element/TypeElement
      42: astore        6
      44: aload         6
      46: invokeinterface #11,  1           // InterfaceMethod javax/lang/model/element/TypeElement.getKind:()Ljavax/lang/model/element/ElementKind;
      51: invokevirtual #29                 // Method javax/lang/model/element/ElementKind.isInterface:()Z
      54: ifne          75
      57: aload         6
      59: invokeinterface #30,  1           // InterfaceMethod javax/lang/model/element/TypeElement.getModifiers:()Ljava/util/Set;
      64: getstatic     #31                 // Field javax/lang/model/element/Modifier.ABSTRACT:Ljavax/lang/model/element/Modifier;
      67: invokeinterface #32,  2           // InterfaceMethod java/util/Set.contains:(Ljava/lang/Object;)Z
      72: ifeq          100
      75: aload_3
      76: new           #13                 // class org/hibernate/validator/ap/checks/ConstraintCheckError
      79: dup
      80: aload_1
      81: aload_2
      82: ldc           #33                 // String GROUP_SEQUENCE_PROVIDER_ANNOTATION_VALUE_MUST_BE_AN_IMPLEMENTATION_CLASS
      84: iconst_0
      85: anewarray     #15                 // class java/lang/Object
      88: invokespecial #16                 // Method org/hibernate/validator/ap/checks/ConstraintCheckError."<init>":(Ljavax/lang/model/element/Element;Ljavax/lang/model/element/AnnotationMirror;Ljava/lang/String;[Ljava/lang/Object;)V
      91: invokeinterface #34,  2           // InterfaceMethod java/util/Set.add:(Ljava/lang/Object;)Z
      96: pop
      97: goto          136
     100: aload_0
     101: aload         6
     103: invokespecial #35                 // Method hasPublicDefaultConstructor:(Ljavax/lang/model/element/TypeElement;)Z
     106: ifne          136
     109: aload_3
     110: new           #13                 // class org/hibernate/validator/ap/checks/ConstraintCheckError
     113: dup
     114: aload_1
     115: aload_2
     116: ldc           #36                 // String GROUP_SEQUENCE_PROVIDER_ANNOTATION_VALUE_CLASS_MUST_HAVE_DEFAULT_CONSTRUCTOR
     118: iconst_1
     119: anewarray     #15                 // class java/lang/Object
     122: dup
     123: iconst_0
     124: aload         5
     126: aastore
     127: invokespecial #16                 // Method org/hibernate/validator/ap/checks/ConstraintCheckError."<init>":(Ljavax/lang/model/element/Element;Ljavax/lang/model/element/AnnotationMirror;Ljava/lang/String;[Ljava/lang/Object;)V
     130: invokeinterface #34,  2           // InterfaceMethod java/util/Set.add:(Ljava/lang/Object;)Z
     135: pop
     136: aload_0
     137: aload         5
     139: invokespecial #37                 // Method retrieveGenericProviderType:(Ljavax/lang/model/type/TypeMirror;)Ljavax/lang/model/type/TypeMirror;
     142: astore        7
     144: aload_0
     145: getfield      #2                  // Field typeUtils:Ljavax/lang/model/util/Types;
     148: aload_1
     149: invokeinterface #38,  1           // InterfaceMethod javax/lang/model/element/TypeElement.asType:()Ljavax/lang/model/type/TypeMirror;
     154: aload         7
     156: invokeinterface #39,  3           // InterfaceMethod javax/lang/model/util/Types.isSubtype:(Ljavax/lang/model/type/TypeMirror;Ljavax/lang/model/type/TypeMirror;)Z
     161: ifne          200
     164: aload_3
     165: new           #13                 // class org/hibernate/validator/ap/checks/ConstraintCheckError
     168: dup
     169: aload_1
     170: aload_2
     171: ldc           #40                 // String GROUP_SEQUENCE_PROVIDER_ANNOTATION_VALUE_DEFINED_PROVIDER_CLASS_WITH_WRONG_TYPE
     173: iconst_2
     174: anewarray     #15                 // class java/lang/Object
     177: dup
     178: iconst_0
     179: aload         7
     181: aastore
     182: dup
     183: iconst_1
     184: aload_1
     185: invokeinterface #38,  1           // InterfaceMethod javax/lang/model/element/TypeElement.asType:()Ljavax/lang/model/type/TypeMirror;
     190: aastore
     191: invokespecial #16                 // Method org/hibernate/validator/ap/checks/ConstraintCheckError."<init>":(Ljavax/lang/model/element/Element;Ljavax/lang/model/element/AnnotationMirror;Ljava/lang/String;[Ljava/lang/Object;)V
     194: invokeinterface #34,  2           // InterfaceMethod java/util/Set.add:(Ljava/lang/Object;)Z
     199: pop
     200: aload_3
     201: areturn

  private boolean hasPublicDefaultConstructor(javax.lang.model.element.TypeElement);
    Code:
       0: aload_1
       1: new           #41                 // class org/hibernate/validator/ap/checks/GroupSequenceProviderCheck$1
       4: dup
       5: aload_0
       6: getstatic     #42                 // Field java/lang/Boolean.FALSE:Ljava/lang/Boolean;
       9: invokespecial #43                 // Method org/hibernate/validator/ap/checks/GroupSequenceProviderCheck$1."<init>":(Lorg/hibernate/validator/ap/checks/GroupSequenceProviderCheck;Ljava/lang/Boolean;)V
      12: aconst_null
      13: invokeinterface #44,  3           // InterfaceMethod javax/lang/model/element/TypeElement.accept:(Ljavax/lang/model/element/ElementVisitor;Ljava/lang/Object;)Ljava/lang/Object;
      18: checkcast     #45                 // class java/lang/Boolean
      21: invokevirtual #46                 // Method java/lang/Boolean.booleanValue:()Z
      24: ireturn

  private javax.lang.model.type.TypeMirror retrieveGenericProviderType(javax.lang.model.type.TypeMirror);
    Code:
       0: aload_1
       1: new           #47                 // class org/hibernate/validator/ap/checks/GroupSequenceProviderCheck$2
       4: dup
       5: aload_0
       6: invokespecial #48                 // Method org/hibernate/validator/ap/checks/GroupSequenceProviderCheck$2."<init>":(Lorg/hibernate/validator/ap/checks/GroupSequenceProviderCheck;)V
       9: aconst_null
      10: invokeinterface #49,  3           // InterfaceMethod javax/lang/model/type/TypeMirror.accept:(Ljavax/lang/model/type/TypeVisitor;Ljava/lang/Object;)Ljava/lang/Object;
      15: checkcast     #26                 // class javax/lang/model/type/TypeMirror
      18: areturn

  static javax.lang.model.util.Types access$000(org.hibernate.validator.ap.checks.GroupSequenceProviderCheck);
    Code:
       0: aload_0
       1: getfield      #2                  // Field typeUtils:Ljavax/lang/model/util/Types;
       4: areturn

  static javax.lang.model.type.TypeMirror access$100(org.hibernate.validator.ap.checks.GroupSequenceProviderCheck);
    Code:
       0: aload_0
       1: getfield      #1                  // Field defaultGroupSequenceProviderType:Ljavax/lang/model/type/TypeMirror;
       4: areturn
}
