Compiled from "MethodDelegationBinder.java"
public class net.bytebuddy.implementation.bind.MethodDelegationBinder$Processor implements net.bytebuddy.implementation.bind.MethodDelegationBinder$Record {
  private static final int ONLY;

  private static final int LEFT;

  private static final int RIGHT;

  private final java.util.List<? extends net.bytebuddy.implementation.bind.MethodDelegationBinder$Record> records;

  private final net.bytebuddy.implementation.bind.MethodDelegationBinder$AmbiguityResolver ambiguityResolver;

  public net.bytebuddy.implementation.bind.MethodDelegationBinder$Processor(java.util.List<? extends net.bytebuddy.implementation.bind.MethodDelegationBinder$Record>, net.bytebuddy.implementation.bind.MethodDelegationBinder$AmbiguityResolver);
    Code:
       0: aload_0
       1: invokespecial #49                 // Method java/lang/Object."<init>":()V
       4: aload_0
       5: aload_1
       6: putfield      #51                 // Field records:Ljava/util/List;
       9: aload_0
      10: aload_2
      11: putfield      #53                 // Field ambiguityResolver:Lnet/bytebuddy/implementation/bind/MethodDelegationBinder$AmbiguityResolver;
      14: return

  public net.bytebuddy.implementation.bind.MethodDelegationBinder$MethodBinding bind(net.bytebuddy.implementation.Implementation$Target, net.bytebuddy.description.method.MethodDescription, net.bytebuddy.implementation.bind.MethodDelegationBinder$TerminationHandler, net.bytebuddy.implementation.bind.MethodDelegationBinder$MethodInvoker, net.bytebuddy.implementation.bytecode.assign.Assigner);
    Code:
       0: new           #59                 // class java/util/ArrayList
       3: dup
       4: invokespecial #60                 // Method java/util/ArrayList."<init>":()V
       7: astore        6
       9: aload_0
      10: getfield      #51                 // Field records:Ljava/util/List;
      13: invokeinterface #66,  1           // InterfaceMethod java/util/List.iterator:()Ljava/util/Iterator;
      18: astore        7
      20: aload         7
      22: invokeinterface #72,  1           // InterfaceMethod java/util/Iterator.hasNext:()Z
      27: ifeq          81
      30: aload         7
      32: invokeinterface #76,  1           // InterfaceMethod java/util/Iterator.next:()Ljava/lang/Object;
      37: checkcast     #6                  // class net/bytebuddy/implementation/bind/MethodDelegationBinder$Record
      40: astore        8
      42: aload         8
      44: aload_1
      45: aload_2
      46: aload_3
      47: aload         4
      49: aload         5
      51: invokeinterface #78,  6           // InterfaceMethod net/bytebuddy/implementation/bind/MethodDelegationBinder$Record.bind:(Lnet/bytebuddy/implementation/Implementation$Target;Lnet/bytebuddy/description/method/MethodDescription;Lnet/bytebuddy/implementation/bind/MethodDelegationBinder$TerminationHandler;Lnet/bytebuddy/implementation/bind/MethodDelegationBinder$MethodInvoker;Lnet/bytebuddy/implementation/bytecode/assign/Assigner;)Lnet/bytebuddy/implementation/bind/MethodDelegationBinder$MethodBinding;
      56: astore        9
      58: aload         9
      60: invokeinterface #81,  1           // InterfaceMethod net/bytebuddy/implementation/bind/MethodDelegationBinder$MethodBinding.isValid:()Z
      65: ifeq          78
      68: aload         6
      70: aload         9
      72: invokeinterface #85,  2           // InterfaceMethod java/util/List.add:(Ljava/lang/Object;)Z
      77: pop
      78: goto          20
      81: aload         6
      83: invokeinterface #88,  1           // InterfaceMethod java/util/List.isEmpty:()Z
      88: ifeq          130
      91: new           #90                 // class java/lang/IllegalArgumentException
      94: dup
      95: new           #92                 // class java/lang/StringBuilder
      98: dup
      99: invokespecial #93                 // Method java/lang/StringBuilder."<init>":()V
     102: ldc           #95                 // String None of
     104: invokevirtual #99                 // Method java/lang/StringBuilder.append:(Ljava/lang/String;)Ljava/lang/StringBuilder;
     107: aload_0
     108: getfield      #51                 // Field records:Ljava/util/List;
     111: invokevirtual #102                // Method java/lang/StringBuilder.append:(Ljava/lang/Object;)Ljava/lang/StringBuilder;
     114: ldc           #104                // String  allows for delegation from
     116: invokevirtual #99                 // Method java/lang/StringBuilder.append:(Ljava/lang/String;)Ljava/lang/StringBuilder;
     119: aload_2
     120: invokevirtual #102                // Method java/lang/StringBuilder.append:(Ljava/lang/Object;)Ljava/lang/StringBuilder;
     123: invokevirtual #108                // Method java/lang/StringBuilder.toString:()Ljava/lang/String;
     126: invokespecial #111                // Method java/lang/IllegalArgumentException."<init>":(Ljava/lang/String;)V
     129: athrow
     130: aload_0
     131: aload_2
     132: aload         6
     134: invokespecial #115                // Method resolve:(Lnet/bytebuddy/description/method/MethodDescription;Ljava/util/List;)Lnet/bytebuddy/implementation/bind/MethodDelegationBinder$MethodBinding;
     137: areturn

  private net.bytebuddy.implementation.bind.MethodDelegationBinder$MethodBinding resolve(net.bytebuddy.description.method.MethodDescription, java.util.List<net.bytebuddy.implementation.bind.MethodDelegationBinder$MethodBinding>);
    Code:
       0: aload_2
       1: invokeinterface #135,  1          // InterfaceMethod java/util/List.size:()I
       6: lookupswitch  { // 2
                     1: 32
                     2: 43
               default: 175
          }
      32: aload_2
      33: iconst_0
      34: invokeinterface #139,  2          // InterfaceMethod java/util/List.get:(I)Ljava/lang/Object;
      39: checkcast     #27                 // class net/bytebuddy/implementation/bind/MethodDelegationBinder$MethodBinding
      42: areturn
      43: aload_2
      44: iconst_0
      45: invokeinterface #139,  2          // InterfaceMethod java/util/List.get:(I)Ljava/lang/Object;
      50: checkcast     #27                 // class net/bytebuddy/implementation/bind/MethodDelegationBinder$MethodBinding
      53: astore_3
      54: aload_2
      55: iconst_1
      56: invokeinterface #139,  2          // InterfaceMethod java/util/List.get:(I)Ljava/lang/Object;
      61: checkcast     #27                 // class net/bytebuddy/implementation/bind/MethodDelegationBinder$MethodBinding
      64: astore        4
      66: getstatic     #143                // Field net/bytebuddy/implementation/bind/MethodDelegationBinder$1.$SwitchMap$net$bytebuddy$implementation$bind$MethodDelegationBinder$AmbiguityResolver$Resolution:[I
      69: aload_0
      70: getfield      #53                 // Field ambiguityResolver:Lnet/bytebuddy/implementation/bind/MethodDelegationBinder$AmbiguityResolver;
      73: aload_1
      74: aload_3
      75: aload         4
      77: invokeinterface #146,  4          // InterfaceMethod net/bytebuddy/implementation/bind/MethodDelegationBinder$AmbiguityResolver.resolve:(Lnet/bytebuddy/description/method/MethodDescription;Lnet/bytebuddy/implementation/bind/MethodDelegationBinder$MethodBinding;Lnet/bytebuddy/implementation/bind/MethodDelegationBinder$MethodBinding;)Lnet/bytebuddy/implementation/bind/MethodDelegationBinder$AmbiguityResolver$Resolution;
      82: invokevirtual #149                // Method net/bytebuddy/implementation/bind/MethodDelegationBinder$AmbiguityResolver$Resolution.ordinal:()I
      85: iaload
      86: tableswitch   { // 1 to 4
                     1: 121
                     2: 121
                     3: 116
                     4: 118
               default: 167
          }
     116: aload_3
     117: areturn
     118: aload         4
     120: areturn
     121: new           #90                 // class java/lang/IllegalArgumentException
     124: dup
     125: new           #92                 // class java/lang/StringBuilder
     128: dup
     129: invokespecial #93                 // Method java/lang/StringBuilder."<init>":()V
     132: ldc           #151                // String Cannot resolve ambiguous delegation of
     134: invokevirtual #99                 // Method java/lang/StringBuilder.append:(Ljava/lang/String;)Ljava/lang/StringBuilder;
     137: aload_1
     138: invokevirtual #102                // Method java/lang/StringBuilder.append:(Ljava/lang/Object;)Ljava/lang/StringBuilder;
     141: ldc           #153                // String  to
     143: invokevirtual #99                 // Method java/lang/StringBuilder.append:(Ljava/lang/String;)Ljava/lang/StringBuilder;
     146: aload_3
     147: invokevirtual #102                // Method java/lang/StringBuilder.append:(Ljava/lang/Object;)Ljava/lang/StringBuilder;
     150: ldc           #155                // String  or
     152: invokevirtual #99                 // Method java/lang/StringBuilder.append:(Ljava/lang/String;)Ljava/lang/StringBuilder;
     155: aload         4
     157: invokevirtual #102                // Method java/lang/StringBuilder.append:(Ljava/lang/Object;)Ljava/lang/StringBuilder;
     160: invokevirtual #108                // Method java/lang/StringBuilder.toString:()Ljava/lang/String;
     163: invokespecial #111                // Method java/lang/IllegalArgumentException."<init>":(Ljava/lang/String;)V
     166: athrow
     167: new           #157                // class java/lang/AssertionError
     170: dup
     171: invokespecial #158                // Method java/lang/AssertionError."<init>":()V
     174: athrow
     175: aload_2
     176: iconst_0
     177: invokeinterface #139,  2          // InterfaceMethod java/util/List.get:(I)Ljava/lang/Object;
     182: checkcast     #27                 // class net/bytebuddy/implementation/bind/MethodDelegationBinder$MethodBinding
     185: astore_3
     186: aload_2
     187: iconst_1
     188: invokeinterface #139,  2          // InterfaceMethod java/util/List.get:(I)Ljava/lang/Object;
     193: checkcast     #27                 // class net/bytebuddy/implementation/bind/MethodDelegationBinder$MethodBinding
     196: astore        4
     198: getstatic     #143                // Field net/bytebuddy/implementation/bind/MethodDelegationBinder$1.$SwitchMap$net$bytebuddy$implementation$bind$MethodDelegationBinder$AmbiguityResolver$Resolution:[I
     201: aload_0
     202: getfield      #53                 // Field ambiguityResolver:Lnet/bytebuddy/implementation/bind/MethodDelegationBinder$AmbiguityResolver;
     205: aload_1
     206: aload_3
     207: aload         4
     209: invokeinterface #146,  4          // InterfaceMethod net/bytebuddy/implementation/bind/MethodDelegationBinder$AmbiguityResolver.resolve:(Lnet/bytebuddy/description/method/MethodDescription;Lnet/bytebuddy/implementation/bind/MethodDelegationBinder$MethodBinding;Lnet/bytebuddy/implementation/bind/MethodDelegationBinder$MethodBinding;)Lnet/bytebuddy/implementation/bind/MethodDelegationBinder$AmbiguityResolver$Resolution;
     214: invokevirtual #149                // Method net/bytebuddy/implementation/bind/MethodDelegationBinder$AmbiguityResolver$Resolution.ordinal:()I
     217: iaload
     218: tableswitch   { // 1 to 4
                     1: 278
                     2: 278
                     3: 248
                     4: 263
               default: 425
          }
     248: aload_2
     249: iconst_1
     250: invokeinterface #161,  2          // InterfaceMethod java/util/List.remove:(I)Ljava/lang/Object;
     255: pop
     256: aload_0
     257: aload_1
     258: aload_2
     259: invokespecial #115                // Method resolve:(Lnet/bytebuddy/description/method/MethodDescription;Ljava/util/List;)Lnet/bytebuddy/implementation/bind/MethodDelegationBinder$MethodBinding;
     262: areturn
     263: aload_2
     264: iconst_0
     265: invokeinterface #161,  2          // InterfaceMethod java/util/List.remove:(I)Ljava/lang/Object;
     270: pop
     271: aload_0
     272: aload_1
     273: aload_2
     274: invokespecial #115                // Method resolve:(Lnet/bytebuddy/description/method/MethodDescription;Ljava/util/List;)Lnet/bytebuddy/implementation/bind/MethodDelegationBinder$MethodBinding;
     277: areturn
     278: aload_2
     279: iconst_1
     280: invokeinterface #161,  2          // InterfaceMethod java/util/List.remove:(I)Ljava/lang/Object;
     285: pop
     286: aload_2
     287: iconst_0
     288: invokeinterface #161,  2          // InterfaceMethod java/util/List.remove:(I)Ljava/lang/Object;
     293: pop
     294: aload_0
     295: aload_1
     296: aload_2
     297: invokespecial #115                // Method resolve:(Lnet/bytebuddy/description/method/MethodDescription;Ljava/util/List;)Lnet/bytebuddy/implementation/bind/MethodDelegationBinder$MethodBinding;
     300: astore        5
     302: getstatic     #143                // Field net/bytebuddy/implementation/bind/MethodDelegationBinder$1.$SwitchMap$net$bytebuddy$implementation$bind$MethodDelegationBinder$AmbiguityResolver$Resolution:[I
     305: aload_0
     306: getfield      #53                 // Field ambiguityResolver:Lnet/bytebuddy/implementation/bind/MethodDelegationBinder$AmbiguityResolver;
     309: aload_1
     310: aload_3
     311: aload         5
     313: invokeinterface #146,  4          // InterfaceMethod net/bytebuddy/implementation/bind/MethodDelegationBinder$AmbiguityResolver.resolve:(Lnet/bytebuddy/description/method/MethodDescription;Lnet/bytebuddy/implementation/bind/MethodDelegationBinder$MethodBinding;Lnet/bytebuddy/implementation/bind/MethodDelegationBinder$MethodBinding;)Lnet/bytebuddy/implementation/bind/MethodDelegationBinder$AmbiguityResolver$Resolution;
     318: aload_0
     319: getfield      #53                 // Field ambiguityResolver:Lnet/bytebuddy/implementation/bind/MethodDelegationBinder$AmbiguityResolver;
     322: aload_1
     323: aload         4
     325: aload         5
     327: invokeinterface #146,  4          // InterfaceMethod net/bytebuddy/implementation/bind/MethodDelegationBinder$AmbiguityResolver.resolve:(Lnet/bytebuddy/description/method/MethodDescription;Lnet/bytebuddy/implementation/bind/MethodDelegationBinder$MethodBinding;Lnet/bytebuddy/implementation/bind/MethodDelegationBinder$MethodBinding;)Lnet/bytebuddy/implementation/bind/MethodDelegationBinder$AmbiguityResolver$Resolution;
     332: invokevirtual #165                // Method net/bytebuddy/implementation/bind/MethodDelegationBinder$AmbiguityResolver$Resolution.merge:(Lnet/bytebuddy/implementation/bind/MethodDelegationBinder$AmbiguityResolver$Resolution;)Lnet/bytebuddy/implementation/bind/MethodDelegationBinder$AmbiguityResolver$Resolution;
     335: invokevirtual #149                // Method net/bytebuddy/implementation/bind/MethodDelegationBinder$AmbiguityResolver$Resolution.ordinal:()I
     338: iaload
     339: tableswitch   { // 1 to 4
                     1: 371
                     2: 371
                     3: 371
                     4: 368
               default: 417
          }
     368: aload         5
     370: areturn
     371: new           #90                 // class java/lang/IllegalArgumentException
     374: dup
     375: new           #92                 // class java/lang/StringBuilder
     378: dup
     379: invokespecial #93                 // Method java/lang/StringBuilder."<init>":()V
     382: ldc           #151                // String Cannot resolve ambiguous delegation of
     384: invokevirtual #99                 // Method java/lang/StringBuilder.append:(Ljava/lang/String;)Ljava/lang/StringBuilder;
     387: aload_1
     388: invokevirtual #102                // Method java/lang/StringBuilder.append:(Ljava/lang/Object;)Ljava/lang/StringBuilder;
     391: ldc           #153                // String  to
     393: invokevirtual #99                 // Method java/lang/StringBuilder.append:(Ljava/lang/String;)Ljava/lang/StringBuilder;
     396: aload_3
     397: invokevirtual #102                // Method java/lang/StringBuilder.append:(Ljava/lang/Object;)Ljava/lang/StringBuilder;
     400: ldc           #155                // String  or
     402: invokevirtual #99                 // Method java/lang/StringBuilder.append:(Ljava/lang/String;)Ljava/lang/StringBuilder;
     405: aload         4
     407: invokevirtual #102                // Method java/lang/StringBuilder.append:(Ljava/lang/Object;)Ljava/lang/StringBuilder;
     410: invokevirtual #108                // Method java/lang/StringBuilder.toString:()Ljava/lang/String;
     413: invokespecial #111                // Method java/lang/IllegalArgumentException."<init>":(Ljava/lang/String;)V
     416: athrow
     417: new           #157                // class java/lang/AssertionError
     420: dup
     421: invokespecial #158                // Method java/lang/AssertionError."<init>":()V
     424: athrow
     425: new           #167                // class java/lang/IllegalStateException
     428: dup
     429: new           #92                 // class java/lang/StringBuilder
     432: dup
     433: invokespecial #93                 // Method java/lang/StringBuilder."<init>":()V
     436: ldc           #169                // String Unexpected targets:
     438: invokevirtual #99                 // Method java/lang/StringBuilder.append:(Ljava/lang/String;)Ljava/lang/StringBuilder;
     441: aload_2
     442: invokevirtual #102                // Method java/lang/StringBuilder.append:(Ljava/lang/Object;)Ljava/lang/StringBuilder;
     445: invokevirtual #108                // Method java/lang/StringBuilder.toString:()Ljava/lang/String;
     448: invokespecial #170                // Method java/lang/IllegalStateException."<init>":(Ljava/lang/String;)V
     451: athrow

  public boolean equals(java.lang.Object);
    Code:
       0: aload_1
       1: aload_0
       2: if_acmpne     7
       5: iconst_1
       6: ireturn
       7: aload_1
       8: instanceof    #2                  // class net/bytebuddy/implementation/bind/MethodDelegationBinder$Processor
      11: ifne          16
      14: iconst_0
      15: ireturn
      16: aload_1
      17: checkcast     #2                  // class net/bytebuddy/implementation/bind/MethodDelegationBinder$Processor
      20: astore_2
      21: aload_2
      22: aload_0
      23: invokevirtual #177                // Method canEqual:(Ljava/lang/Object;)Z
      26: ifne          31
      29: iconst_0
      30: ireturn
      31: aload_0
      32: getfield      #51                 // Field records:Ljava/util/List;
      35: astore_3
      36: aload_2
      37: getfield      #51                 // Field records:Ljava/util/List;
      40: astore        4
      42: aload_3
      43: ifnonnull     54
      46: aload         4
      48: ifnull        65
      51: goto          63
      54: aload_3
      55: aload         4
      57: invokevirtual #179                // Method java/lang/Object.equals:(Ljava/lang/Object;)Z
      60: ifne          65
      63: iconst_0
      64: ireturn
      65: aload_0
      66: getfield      #53                 // Field ambiguityResolver:Lnet/bytebuddy/implementation/bind/MethodDelegationBinder$AmbiguityResolver;
      69: astore        5
      71: aload_2
      72: getfield      #53                 // Field ambiguityResolver:Lnet/bytebuddy/implementation/bind/MethodDelegationBinder$AmbiguityResolver;
      75: astore        6
      77: aload         5
      79: ifnonnull     90
      82: aload         6
      84: ifnull        102
      87: goto          100
      90: aload         5
      92: aload         6
      94: invokevirtual #179                // Method java/lang/Object.equals:(Ljava/lang/Object;)Z
      97: ifne          102
     100: iconst_0
     101: ireturn
     102: iconst_1
     103: ireturn

  protected boolean canEqual(java.lang.Object);
    Code:
       0: aload_1
       1: instanceof    #2                  // class net/bytebuddy/implementation/bind/MethodDelegationBinder$Processor
       4: ireturn

  public int hashCode();
    Code:
       0: bipush        59
       2: istore_1
       3: iconst_1
       4: istore_2
       5: aload_0
       6: getfield      #51                 // Field records:Ljava/util/List;
       9: astore_3
      10: iload_2
      11: bipush        59
      13: imul
      14: aload_3
      15: ifnonnull     23
      18: bipush        43
      20: goto          27
      23: aload_3
      24: invokevirtual #189                // Method java/lang/Object.hashCode:()I
      27: iadd
      28: istore_2
      29: aload_0
      30: getfield      #53                 // Field ambiguityResolver:Lnet/bytebuddy/implementation/bind/MethodDelegationBinder$AmbiguityResolver;
      33: astore        4
      35: iload_2
      36: bipush        59
      38: imul
      39: aload         4
      41: ifnonnull     49
      44: bipush        43
      46: goto          54
      49: aload         4
      51: invokevirtual #189                // Method java/lang/Object.hashCode:()I
      54: iadd
      55: istore_2
      56: iload_2
      57: ireturn
}
