Compiled from "EntityBeanHomeViewConfigurator.java"
public class org.jboss.as.ejb3.component.entity.EntityBeanHomeViewConfigurator implements org.jboss.as.ee.component.ViewConfigurator {
  public org.jboss.as.ejb3.component.entity.EntityBeanHomeViewConfigurator();
    Code:
       0: aload_0
       1: invokespecial #1                  // Method java/lang/Object."<init>":()V
       4: return

  public void configure(org.jboss.as.server.deployment.DeploymentPhaseContext, org.jboss.as.ee.component.ComponentConfiguration, org.jboss.as.ee.component.ViewDescription, org.jboss.as.ee.component.ViewConfiguration) throws org.jboss.as.server.deployment.DeploymentUnitProcessingException;
    Code:
       0: aload_1
       1: invokeinterface #2,  1            // InterfaceMethod org/jboss/as/server/deployment/DeploymentPhaseContext.getDeploymentUnit:()Lorg/jboss/as/server/deployment/DeploymentUnit;
       6: astore        5
       8: aload         5
      10: getstatic     #3                  // Field org/jboss/as/server/deployment/Attachments.REFLECTION_INDEX:Lorg/jboss/as/server/deployment/AttachmentKey;
      13: invokeinterface #4,  2            // InterfaceMethod org/jboss/as/server/deployment/DeploymentUnit.getAttachment:(Lorg/jboss/as/server/deployment/AttachmentKey;)Ljava/lang/Object;
      18: checkcast     #5                  // class org/jboss/as/server/deployment/reflect/DeploymentReflectionIndex
      21: astore        6
      23: aload         4
      25: invokestatic  #6                  // Method org/jboss/invocation/Interceptors.getTerminalInterceptorFactory:()Lorg/jboss/invocation/InterceptorFactory;
      28: sipush        512
      31: invokevirtual #8                  // Method org/jboss/as/ee/component/ViewConfiguration.addClientPostConstructInterceptor:(Lorg/jboss/invocation/InterceptorFactory;I)V
      34: aload         4
      36: invokestatic  #6                  // Method org/jboss/invocation/Interceptors.getTerminalInterceptorFactory:()Lorg/jboss/invocation/InterceptorFactory;
      39: sipush        512
      42: invokevirtual #10                 // Method org/jboss/as/ee/component/ViewConfiguration.addClientPreDestroyInterceptor:(Lorg/jboss/invocation/InterceptorFactory;I)V
      45: ldc           #11                 // class org/jboss/as/ejb3/component/EjbHomeViewDescription
      47: aload_3
      48: invokevirtual #12                 // Method java/lang/Class.cast:(Ljava/lang/Object;)Ljava/lang/Object;
      51: checkcast     #11                 // class org/jboss/as/ejb3/component/EjbHomeViewDescription
      54: invokevirtual #13                 // Method org/jboss/as/ejb3/component/EjbHomeViewDescription.getMethodIntf:()Lorg/jboss/as/ejb3/component/MethodIntf;
      57: getstatic     #14                 // Field org/jboss/as/ejb3/component/MethodIntf.LOCAL_HOME:Lorg/jboss/as/ejb3/component/MethodIntf;
      60: if_acmpne     67
      63: iconst_1
      64: goto          68
      67: iconst_0
      68: istore        7
      70: aload_2
      71: invokevirtual #15                 // Method org/jboss/as/ee/component/ComponentConfiguration.getComponentDescription:()Lorg/jboss/as/ee/component/ComponentDescription;
      74: checkcast     #16                 // class org/jboss/as/ejb3/component/entity/EntityBeanComponentDescription
      77: astore        8
      79: iload         7
      81: ifeq          92
      84: aload         8
      86: invokevirtual #17                 // Method org/jboss/as/ejb3/component/entity/EntityBeanComponentDescription.getEjbLocalView:()Lorg/jboss/as/ejb3/component/EJBViewDescription;
      89: goto          97
      92: aload         8
      94: invokevirtual #18                 // Method org/jboss/as/ejb3/component/entity/EntityBeanComponentDescription.getEjbRemoteView:()Lorg/jboss/as/ejb3/component/EJBViewDescription;
      97: astore        9
      99: aload         4
     101: invokevirtual #19                 // Method org/jboss/as/ee/component/ViewConfiguration.getProxyFactory:()Lorg/jboss/invocation/proxy/ProxyFactory;
     104: invokevirtual #20                 // Method org/jboss/invocation/proxy/ProxyFactory.getCachedMethods:()Ljava/util/List;
     107: invokeinterface #21,  1           // InterfaceMethod java/util/List.iterator:()Ljava/util/Iterator;
     112: astore        10
     114: aload         10
     116: invokeinterface #22,  1           // InterfaceMethod java/util/Iterator.hasNext:()Z
     121: ifeq          822
     124: aload         10
     126: invokeinterface #23,  1           // InterfaceMethod java/util/Iterator.next:()Ljava/lang/Object;
     131: checkcast     #24                 // class java/lang/reflect/Method
     134: astore        11
     136: aload         4
     138: aload         11
     140: getstatic     #25                 // Field org/jboss/as/ee/component/ViewDescription.CLIENT_DISPATCHER_INTERCEPTOR_FACTORY:Lorg/jboss/invocation/ImmediateInterceptorFactory;
     143: sipush        1536
     146: invokevirtual #27                 // Method org/jboss/as/ee/component/ViewConfiguration.addClientInterceptor:(Ljava/lang/reflect/Method;Lorg/jboss/invocation/InterceptorFactory;I)V
     149: aload         11
     151: invokevirtual #28                 // Method java/lang/reflect/Method.getName:()Ljava/lang/String;
     154: ldc           #29                 // String equals
     156: invokevirtual #30                 // Method java/lang/String.equals:(Ljava/lang/Object;)Z
     159: ifeq          200
     162: aload         11
     164: invokevirtual #31                 // Method java/lang/reflect/Method.getParameterTypes:()[Ljava/lang/Class;
     167: arraylength
     168: iconst_1
     169: if_icmpne     200
     172: aload         11
     174: invokevirtual #31                 // Method java/lang/reflect/Method.getParameterTypes:()[Ljava/lang/Class;
     177: iconst_0
     178: aaload
     179: ldc           #32                 // class java/lang/Object
     181: if_acmpne     200
     184: aload         4
     186: aload         11
     188: getstatic     #33                 // Field org/jboss/as/ejb3/component/interceptors/ComponentTypeIdentityInterceptorFactory.INSTANCE:Lorg/jboss/as/ejb3/component/interceptors/ComponentTypeIdentityInterceptorFactory;
     191: sipush        1024
     194: invokevirtual #27                 // Method org/jboss/as/ee/component/ViewConfiguration.addClientInterceptor:(Ljava/lang/reflect/Method;Lorg/jboss/invocation/InterceptorFactory;I)V
     197: goto          819
     200: aload         11
     202: invokevirtual #28                 // Method java/lang/reflect/Method.getName:()Ljava/lang/String;
     205: ldc           #34                 // String hashCode
     207: invokevirtual #30                 // Method java/lang/String.equals:(Ljava/lang/Object;)Z
     210: ifeq          238
     213: aload         11
     215: invokevirtual #31                 // Method java/lang/reflect/Method.getParameterTypes:()[Ljava/lang/Class;
     218: arraylength
     219: ifne          238
     222: aload         4
     224: aload         11
     226: getstatic     #33                 // Field org/jboss/as/ejb3/component/interceptors/ComponentTypeIdentityInterceptorFactory.INSTANCE:Lorg/jboss/as/ejb3/component/interceptors/ComponentTypeIdentityInterceptorFactory;
     229: sipush        1024
     232: invokevirtual #27                 // Method org/jboss/as/ee/component/ViewConfiguration.addClientInterceptor:(Ljava/lang/reflect/Method;Lorg/jboss/invocation/InterceptorFactory;I)V
     235: goto          819
     238: aload         11
     240: invokevirtual #28                 // Method java/lang/reflect/Method.getName:()Ljava/lang/String;
     243: ldc           #35                 // String toString
     245: invokevirtual #30                 // Method java/lang/String.equals:(Ljava/lang/Object;)Z
     248: ifeq          263
     251: aload         11
     253: invokevirtual #31                 // Method java/lang/reflect/Method.getParameterTypes:()[Ljava/lang/Class;
     256: arraylength
     257: ifne          263
     260: goto          819
     263: aload         11
     265: invokevirtual #28                 // Method java/lang/reflect/Method.getName:()Ljava/lang/String;
     268: ldc           #36                 // String create
     270: invokevirtual #37                 // Method java/lang/String.startsWith:(Ljava/lang/String;)Z
     273: ifeq          382
     276: aload_0
     277: ldc           #36                 // String create
     279: ldc           #38                 // String ejbCreate
     281: aload         8
     283: invokevirtual #39                 // Method org/jboss/as/ejb3/component/entity/EntityBeanComponentDescription.getPrimaryKeyType:()Ljava/lang/String;
     286: aload_2
     287: invokevirtual #40                 // Method org/jboss/as/ee/component/ComponentConfiguration.getComponentClass:()Ljava/lang/Class;
     290: aload         6
     292: aload         11
     294: aload_2
     295: invokevirtual #41                 // Method org/jboss/as/ee/component/ComponentConfiguration.getComponentName:()Ljava/lang/String;
     298: invokespecial #42                 // Method resolveEjbMethod:(Ljava/lang/String;Ljava/lang/String;Ljava/lang/String;Ljava/lang/Class;Lorg/jboss/as/server/deployment/reflect/DeploymentReflectionIndex;Ljava/lang/reflect/Method;Ljava/lang/String;)Ljava/lang/reflect/Method;
     301: astore        12
     303: aload_0
     304: ldc           #36                 // String create
     306: ldc           #43                 // String ejbPostCreate
     308: getstatic     #44                 // Field java/lang/Void.TYPE:Ljava/lang/Class;
     311: invokevirtual #45                 // Method java/lang/Class.getName:()Ljava/lang/String;
     314: aload_2
     315: invokevirtual #40                 // Method org/jboss/as/ee/component/ComponentConfiguration.getComponentClass:()Ljava/lang/Class;
     318: aload         6
     320: aload         11
     322: aload_2
     323: invokevirtual #41                 // Method org/jboss/as/ee/component/ComponentConfiguration.getComponentName:()Ljava/lang/String;
     326: invokespecial #42                 // Method resolveEjbMethod:(Ljava/lang/String;Ljava/lang/String;Ljava/lang/String;Ljava/lang/Class;Lorg/jboss/as/server/deployment/reflect/DeploymentReflectionIndex;Ljava/lang/reflect/Method;Ljava/lang/String;)Ljava/lang/reflect/Method;
     329: astore        13
     331: new           #46                 // class org/jboss/as/ejb3/component/entity/interceptors/EntityBeanHomeCreateInterceptorFactory
     334: dup
     335: aload         12
     337: aload         13
     339: invokespecial #47                 // Method org/jboss/as/ejb3/component/entity/interceptors/EntityBeanHomeCreateInterceptorFactory."<init>":(Ljava/lang/reflect/Method;Ljava/lang/reflect/Method;)V
     342: astore        14
     344: aload         4
     346: invokevirtual #48                 // Method org/jboss/as/ee/component/ViewConfiguration.getDependencies:()Ljava/util/List;
     349: new           #49                 // class org/jboss/as/ejb3/component/entity/EntityBeanHomeViewConfigurator$1
     352: dup
     353: aload_0
     354: aload         9
     356: aload         14
     358: invokespecial #50                 // Method org/jboss/as/ejb3/component/entity/EntityBeanHomeViewConfigurator$1."<init>":(Lorg/jboss/as/ejb3/component/entity/EntityBeanHomeViewConfigurator;Lorg/jboss/as/ejb3/component/EJBViewDescription;Lorg/jboss/as/ejb3/component/entity/interceptors/EntityBeanHomeCreateInterceptorFactory;)V
     361: invokeinterface #51,  2           // InterfaceMethod java/util/List.add:(Ljava/lang/Object;)Z
     366: pop
     367: aload         4
     369: aload         11
     371: aload         14
     373: sipush        1536
     376: invokevirtual #53                 // Method org/jboss/as/ee/component/ViewConfiguration.addViewInterceptor:(Ljava/lang/reflect/Method;Lorg/jboss/invocation/InterceptorFactory;I)V
     379: goto          819
     382: aload         11
     384: invokevirtual #28                 // Method java/lang/reflect/Method.getName:()Ljava/lang/String;
     387: ldc           #54                 // String find
     389: invokevirtual #37                 // Method java/lang/String.startsWith:(Ljava/lang/String;)Z
     392: ifeq          490
     395: aload_0
     396: aload_2
     397: invokevirtual #40                 // Method org/jboss/as/ee/component/ComponentConfiguration.getComponentClass:()Ljava/lang/Class;
     400: aload         6
     402: aload         11
     404: aload_2
     405: invokevirtual #41                 // Method org/jboss/as/ee/component/ComponentConfiguration.getComponentName:()Ljava/lang/String;
     408: aload         8
     410: invokevirtual #55                 // Method org/jboss/as/ejb3/component/entity/EntityBeanComponentDescription.getPersistenceType:()Lorg/jboss/metadata/ejb/spec/PersistenceType;
     413: invokevirtual #56                 // Method resolveEjbFinderMethod:(Ljava/lang/Class;Lorg/jboss/as/server/deployment/reflect/DeploymentReflectionIndex;Ljava/lang/reflect/Method;Ljava/lang/String;Lorg/jboss/metadata/ejb/spec/PersistenceType;)Ljava/lang/reflect/Method;
     416: astore        12
     418: aload         12
     420: invokevirtual #57                 // Method java/lang/reflect/Method.getModifiers:()I
     423: invokestatic  #58                 // Method java/lang/reflect/Modifier.isPublic:(I)Z
     426: ifne          442
     429: getstatic     #59                 // Field org/jboss/as/ejb3/logging/EjbLogger.ROOT_LOGGER:Lorg/jboss/as/ejb3/logging/EjbLogger;
     432: ldc           #60                 // String ejbFind
     434: aload         12
     436: invokeinterface #61,  3           // InterfaceMethod org/jboss/as/ejb3/logging/EjbLogger.ejbMethodMustBePublic:(Ljava/lang/String;Ljava/lang/reflect/Method;)Lorg/jboss/as/server/deployment/DeploymentUnitProcessingException;
     441: athrow
     442: aload_0
     443: aload         12
     445: iload         7
     447: invokevirtual #62                 // Method createHomeFindInterceptorFactory:(Ljava/lang/reflect/Method;Z)Lorg/jboss/as/ejb3/component/entity/interceptors/EntityBeanHomeFinderInterceptorFactory;
     450: astore        13
     452: aload         4
     454: invokevirtual #48                 // Method org/jboss/as/ee/component/ViewConfiguration.getDependencies:()Ljava/util/List;
     457: new           #63                 // class org/jboss/as/ejb3/component/entity/EntityBeanHomeViewConfigurator$2
     460: dup
     461: aload_0
     462: aload         9
     464: aload         13
     466: invokespecial #64                 // Method org/jboss/as/ejb3/component/entity/EntityBeanHomeViewConfigurator$2."<init>":(Lorg/jboss/as/ejb3/component/entity/EntityBeanHomeViewConfigurator;Lorg/jboss/as/ejb3/component/EJBViewDescription;Lorg/jboss/as/ejb3/component/entity/interceptors/EntityBeanHomeFinderInterceptorFactory;)V
     469: invokeinterface #51,  2           // InterfaceMethod java/util/List.add:(Ljava/lang/Object;)Z
     474: pop
     475: aload         4
     477: aload         11
     479: aload         13
     481: sipush        2560
     484: invokevirtual #53                 // Method org/jboss/as/ee/component/ViewConfiguration.addViewInterceptor:(Ljava/lang/reflect/Method;Lorg/jboss/invocation/InterceptorFactory;I)V
     487: goto          819
     490: aload         11
     492: invokevirtual #28                 // Method java/lang/reflect/Method.getName:()Ljava/lang/String;
     495: ldc           #65                 // String remove
     497: invokevirtual #30                 // Method java/lang/String.equals:(Ljava/lang/Object;)Z
     500: ifeq          551
     503: aload         11
     505: invokevirtual #31                 // Method java/lang/reflect/Method.getParameterTypes:()[Ljava/lang/Class;
     508: arraylength
     509: iconst_1
     510: if_icmpne     551
     513: aload         11
     515: invokevirtual #31                 // Method java/lang/reflect/Method.getParameterTypes:()[Ljava/lang/Class;
     518: iconst_0
     519: aaload
     520: ldc           #32                 // class java/lang/Object
     522: if_acmpne     551
     525: aload         4
     527: aload         11
     529: iload         7
     531: ifne          538
     534: iconst_1
     535: goto          539
     538: iconst_0
     539: invokestatic  #66                 // Method org/jboss/as/ejb3/component/entity/interceptors/EntityBeanHomeRemoveInterceptorFactory.instance:(Z)Lorg/jboss/invocation/InterceptorFactory;
     542: sipush        2560
     545: invokevirtual #53                 // Method org/jboss/as/ee/component/ViewConfiguration.addViewInterceptor:(Ljava/lang/reflect/Method;Lorg/jboss/invocation/InterceptorFactory;I)V
     548: goto          819
     551: aload         11
     553: invokevirtual #28                 // Method java/lang/reflect/Method.getName:()Ljava/lang/String;
     556: ldc           #65                 // String remove
     558: invokevirtual #30                 // Method java/lang/String.equals:(Ljava/lang/Object;)Z
     561: ifeq          602
     564: aload         11
     566: invokevirtual #31                 // Method java/lang/reflect/Method.getParameterTypes:()[Ljava/lang/Class;
     569: arraylength
     570: iconst_1
     571: if_icmpne     602
     574: aload         11
     576: invokevirtual #31                 // Method java/lang/reflect/Method.getParameterTypes:()[Ljava/lang/Class;
     579: iconst_0
     580: aaload
     581: ldc           #67                 // class javax/ejb/Handle
     583: if_acmpne     602
     586: aload         4
     588: aload         11
     590: getstatic     #68                 // Field org/jboss/as/ejb3/component/entity/interceptors/EntityBeanHomeRemoveByHandleInterceptorFactory.INSTANCE:Lorg/jboss/as/ejb3/component/entity/interceptors/EntityBeanHomeRemoveByHandleInterceptorFactory;
     593: sipush        2560
     596: invokevirtual #53                 // Method org/jboss/as/ee/component/ViewConfiguration.addViewInterceptor:(Ljava/lang/reflect/Method;Lorg/jboss/invocation/InterceptorFactory;I)V
     599: goto          819
     602: aload         11
     604: invokevirtual #28                 // Method java/lang/reflect/Method.getName:()Ljava/lang/String;
     607: ldc           #69                 // String getEJBMetaData
     609: invokevirtual #30                 // Method java/lang/String.equals:(Ljava/lang/Object;)Z
     612: ifeq          733
     615: aload         11
     617: invokevirtual #31                 // Method java/lang/reflect/Method.getParameterTypes:()[Ljava/lang/Class;
     620: arraylength
     621: ifne          733
     624: aload         9
     626: invokevirtual #70                 // Method org/jboss/as/ejb3/component/EJBViewDescription.getViewClassName:()Ljava/lang/String;
     629: aload         5
     631: invokestatic  #71                 // Method org/jboss/as/ee/utils/ClassLoadingUtils.loadClass:(Ljava/lang/String;Lorg/jboss/as/server/deployment/DeploymentUnit;)Ljava/lang/Class;
     634: astore        12
     636: aload         8
     638: invokevirtual #39                 // Method org/jboss/as/ejb3/component/entity/EntityBeanComponentDescription.getPrimaryKeyType:()Ljava/lang/String;
     641: aload         5
     643: invokestatic  #71                 // Method org/jboss/as/ee/utils/ClassLoadingUtils.loadClass:(Ljava/lang/String;Lorg/jboss/as/server/deployment/DeploymentUnit;)Ljava/lang/Class;
     646: astore        13
     648: goto          669
     651: astore        14
     653: getstatic     #59                 // Field org/jboss/as/ejb3/logging/EjbLogger.ROOT_LOGGER:Lorg/jboss/as/ejb3/logging/EjbLogger;
     656: aload         14
     658: aload         8
     660: invokevirtual #73                 // Method org/jboss/as/ejb3/component/entity/EntityBeanComponentDescription.getComponentName:()Ljava/lang/String;
     663: invokeinterface #74,  3           // InterfaceMethod org/jboss/as/ejb3/logging/EjbLogger.failedToLoadViewClassForComponent:(Ljava/lang/Exception;Ljava/lang/String;)Ljava/lang/RuntimeException;
     668: athrow
     669: new           #75                 // class org/jboss/as/ejb3/component/interceptors/EjbMetadataInterceptor
     672: dup
     673: aload         12
     675: aload         4
     677: invokevirtual #76                 // Method org/jboss/as/ee/component/ViewConfiguration.getViewClass:()Ljava/lang/Class;
     680: aload         13
     682: iconst_0
     683: iconst_0
     684: invokespecial #77                 // Method org/jboss/as/ejb3/component/interceptors/EjbMetadataInterceptor."<init>":(Ljava/lang/Class;Ljava/lang/Class;Ljava/lang/Class;ZZ)V
     687: astore        14
     689: aload_2
     690: invokevirtual #78                 // Method org/jboss/as/ee/component/ComponentConfiguration.getStartDependencies:()Ljava/util/List;
     693: new           #79                 // class org/jboss/as/ejb3/component/entity/EntityBeanHomeViewConfigurator$3
     696: dup
     697: aload_0
     698: aload         4
     700: aload         14
     702: invokespecial #80                 // Method org/jboss/as/ejb3/component/entity/EntityBeanHomeViewConfigurator$3."<init>":(Lorg/jboss/as/ejb3/component/entity/EntityBeanHomeViewConfigurator;Lorg/jboss/as/ee/component/ViewConfiguration;Lorg/jboss/as/ejb3/component/interceptors/EjbMetadataInterceptor;)V
     705: invokeinterface #51,  2           // InterfaceMethod java/util/List.add:(Ljava/lang/Object;)Z
     710: pop
     711: aload         4
     713: aload         11
     715: new           #81                 // class org/jboss/invocation/ImmediateInterceptorFactory
     718: dup
     719: aload         14
     721: invokespecial #82                 // Method org/jboss/invocation/ImmediateInterceptorFactory."<init>":(Lorg/jboss/invocation/Interceptor;)V
     724: sipush        1536
     727: invokevirtual #53                 // Method org/jboss/as/ee/component/ViewConfiguration.addViewInterceptor:(Ljava/lang/reflect/Method;Lorg/jboss/invocation/InterceptorFactory;I)V
     730: goto          819
     733: aload         11
     735: invokevirtual #28                 // Method java/lang/reflect/Method.getName:()Ljava/lang/String;
     738: ldc           #83                 // String getHomeHandle
     740: invokevirtual #30                 // Method java/lang/String.equals:(Ljava/lang/Object;)Z
     743: ifeq          758
     746: aload         11
     748: invokevirtual #31                 // Method java/lang/reflect/Method.getParameterTypes:()[Ljava/lang/Class;
     751: arraylength
     752: ifne          758
     755: goto          819
     758: aload_0
     759: aload_2
     760: invokevirtual #40                 // Method org/jboss/as/ee/component/ComponentConfiguration.getComponentClass:()Ljava/lang/Class;
     763: aload         6
     765: aload         11
     767: aload_2
     768: invokevirtual #41                 // Method org/jboss/as/ee/component/ComponentConfiguration.getComponentName:()Ljava/lang/String;
     771: invokevirtual #84                 // Method resolveEjbHomeBusinessMethod:(Ljava/lang/Class;Lorg/jboss/as/server/deployment/reflect/DeploymentReflectionIndex;Ljava/lang/reflect/Method;Ljava/lang/String;)Ljava/lang/reflect/Method;
     774: astore        12
     776: aload         12
     778: invokevirtual #57                 // Method java/lang/reflect/Method.getModifiers:()I
     781: invokestatic  #58                 // Method java/lang/reflect/Modifier.isPublic:(I)Z
     784: ifne          800
     787: getstatic     #59                 // Field org/jboss/as/ejb3/logging/EjbLogger.ROOT_LOGGER:Lorg/jboss/as/ejb3/logging/EjbLogger;
     790: ldc           #85                 // String ejbHome
     792: aload         12
     794: invokeinterface #61,  3           // InterfaceMethod org/jboss/as/ejb3/logging/EjbLogger.ejbMethodMustBePublic:(Ljava/lang/String;Ljava/lang/reflect/Method;)Lorg/jboss/as/server/deployment/DeploymentUnitProcessingException;
     799: athrow
     800: aload         4
     802: aload         11
     804: new           #86                 // class org/jboss/as/ejb3/component/entity/interceptors/EntityBeanHomeMethodInterceptorFactory
     807: dup
     808: aload         12
     810: invokespecial #87                 // Method org/jboss/as/ejb3/component/entity/interceptors/EntityBeanHomeMethodInterceptorFactory."<init>":(Ljava/lang/reflect/Method;)V
     813: sipush        2560
     816: invokevirtual #53                 // Method org/jboss/as/ee/component/ViewConfiguration.addViewInterceptor:(Ljava/lang/reflect/Method;Lorg/jboss/invocation/InterceptorFactory;I)V
     819: goto          114
     822: return
    Exception table:
       from    to  target type
         624   648   651   Class java/lang/ClassNotFoundException

  protected org.jboss.as.ejb3.component.entity.interceptors.EntityBeanHomeFinderInterceptorFactory createHomeFindInterceptorFactory(java.lang.reflect.Method, boolean);
    Code:
       0: new           #88                 // class org/jboss/as/ejb3/component/entity/interceptors/EntityBeanHomeFinderInterceptorFactory
       3: dup
       4: aload_1
       5: invokespecial #89                 // Method org/jboss/as/ejb3/component/entity/interceptors/EntityBeanHomeFinderInterceptorFactory."<init>":(Ljava/lang/reflect/Method;)V
       8: areturn

  private java.lang.reflect.Method resolveEjbMethod(java.lang.String, java.lang.String, java.lang.String, java.lang.Class<?>, org.jboss.as.server.deployment.reflect.DeploymentReflectionIndex, java.lang.reflect.Method, java.lang.String) throws org.jboss.as.server.deployment.DeploymentUnitProcessingException;
    Code:
       0: aload         6
       2: invokevirtual #28                 // Method java/lang/reflect/Method.getName:()Ljava/lang/String;
       5: aload_1
       6: aload_2
       7: invokevirtual #90                 // Method java/lang/String.replaceFirst:(Ljava/lang/String;Ljava/lang/String;)Ljava/lang/String;
      10: astore        8
      12: aload         4
      14: astore        9
      16: aload         9
      18: ldc           #32                 // class java/lang/Object
      20: if_acmpeq     68
      23: aload         5
      25: aload         9
      27: invokevirtual #91                 // Method org/jboss/as/server/deployment/reflect/DeploymentReflectionIndex.getClassIndex:(Ljava/lang/Class;)Lorg/jboss/as/server/deployment/reflect/ClassReflectionIndex;
      30: astore        10
      32: aload         10
      34: aload_3
      35: aload         8
      37: aload         6
      39: invokevirtual #31                 // Method java/lang/reflect/Method.getParameterTypes:()[Ljava/lang/Class;
      42: invokestatic  #92                 // Method namesOf:([Ljava/lang/Class;)[Ljava/lang/String;
      45: invokevirtual #93                 // Method org/jboss/as/server/deployment/reflect/ClassReflectionIndex.getMethod:(Ljava/lang/String;Ljava/lang/String;[Ljava/lang/String;)Ljava/lang/reflect/Method;
      48: astore        11
      50: aload         11
      52: ifnull        58
      55: aload         11
      57: areturn
      58: aload         9
      60: invokevirtual #94                 // Method java/lang/Class.getSuperclass:()Ljava/lang/Class;
      63: astore        9
      65: goto          16
      68: getstatic     #59                 // Field org/jboss/as/ejb3/logging/EjbLogger.ROOT_LOGGER:Lorg/jboss/as/ejb3/logging/EjbLogger;
      71: aload_2
      72: aload         6
      74: aload         7
      76: invokeinterface #95,  4           // InterfaceMethod org/jboss/as/ejb3/logging/EjbLogger.failToResolveMethodForHomeInterface:(Ljava/lang/String;Ljava/lang/reflect/Method;Ljava/lang/String;)Lorg/jboss/as/server/deployment/DeploymentUnitProcessingException;
      81: athrow

  protected java.lang.reflect.Method resolveEjbFinderMethod(java.lang.Class<?>, org.jboss.as.server.deployment.reflect.DeploymentReflectionIndex, java.lang.reflect.Method, java.lang.String, org.jboss.metadata.ejb.spec.PersistenceType) throws org.jboss.as.server.deployment.DeploymentUnitProcessingException;
    Code:
       0: aload_3
       1: invokevirtual #28                 // Method java/lang/reflect/Method.getName:()Ljava/lang/String;
       4: ldc           #54                 // String find
       6: ldc           #60                 // String ejbFind
       8: invokevirtual #90                 // Method java/lang/String.replaceFirst:(Ljava/lang/String;Ljava/lang/String;)Ljava/lang/String;
      11: astore        6
      13: aload_1
      14: astore        7
      16: aload         7
      18: ldc           #32                 // class java/lang/Object
      20: if_acmpeq     80
      23: aload_2
      24: aload         7
      26: invokevirtual #91                 // Method org/jboss/as/server/deployment/reflect/DeploymentReflectionIndex.getClassIndex:(Ljava/lang/Class;)Lorg/jboss/as/server/deployment/reflect/ClassReflectionIndex;
      29: astore        8
      31: aload         8
      33: aload         6
      35: aload_3
      36: invokevirtual #31                 // Method java/lang/reflect/Method.getParameterTypes:()[Ljava/lang/Class;
      39: invokevirtual #96                 // Method org/jboss/as/server/deployment/reflect/ClassReflectionIndex.getMethods:(Ljava/lang/String;[Ljava/lang/Class;)Ljava/util/Collection;
      42: astore        9
      44: aload         9
      46: invokeinterface #97,  1           // InterfaceMethod java/util/Collection.isEmpty:()Z
      51: ifne          70
      54: aload         9
      56: invokeinterface #98,  1           // InterfaceMethod java/util/Collection.iterator:()Ljava/util/Iterator;
      61: invokeinterface #23,  1           // InterfaceMethod java/util/Iterator.next:()Ljava/lang/Object;
      66: checkcast     #24                 // class java/lang/reflect/Method
      69: areturn
      70: aload         7
      72: invokevirtual #94                 // Method java/lang/Class.getSuperclass:()Ljava/lang/Class;
      75: astore        7
      77: goto          16
      80: getstatic     #99                 // Field org/jboss/metadata/ejb/spec/PersistenceType.Bean:Lorg/jboss/metadata/ejb/spec/PersistenceType;
      83: aload         5
      85: if_acmpne     102
      88: getstatic     #59                 // Field org/jboss/as/ejb3/logging/EjbLogger.ROOT_LOGGER:Lorg/jboss/as/ejb3/logging/EjbLogger;
      91: ldc           #60                 // String ejbFind
      93: aload_3
      94: aload         4
      96: invokeinterface #95,  4           // InterfaceMethod org/jboss/as/ejb3/logging/EjbLogger.failToResolveMethodForHomeInterface:(Ljava/lang/String;Ljava/lang/reflect/Method;Ljava/lang/String;)Lorg/jboss/as/server/deployment/DeploymentUnitProcessingException;
     101: athrow
     102: aload_3
     103: areturn

  protected java.lang.reflect.Method resolveEjbHomeBusinessMethod(java.lang.Class<?>, org.jboss.as.server.deployment.reflect.DeploymentReflectionIndex, java.lang.reflect.Method, java.lang.String) throws org.jboss.as.server.deployment.DeploymentUnitProcessingException;
    Code:
       0: new           #100                // class java/lang/StringBuilder
       3: dup
       4: invokespecial #101                // Method java/lang/StringBuilder."<init>":()V
       7: ldc           #85                 // String ejbHome
       9: invokevirtual #102                // Method java/lang/StringBuilder.append:(Ljava/lang/String;)Ljava/lang/StringBuilder;
      12: aload_3
      13: invokevirtual #28                 // Method java/lang/reflect/Method.getName:()Ljava/lang/String;
      16: iconst_0
      17: invokevirtual #103                // Method java/lang/String.charAt:(I)C
      20: invokestatic  #104                // Method java/lang/Character.toUpperCase:(C)C
      23: invokevirtual #105                // Method java/lang/StringBuilder.append:(C)Ljava/lang/StringBuilder;
      26: aload_3
      27: invokevirtual #28                 // Method java/lang/reflect/Method.getName:()Ljava/lang/String;
      30: iconst_1
      31: invokevirtual #106                // Method java/lang/String.substring:(I)Ljava/lang/String;
      34: invokevirtual #102                // Method java/lang/StringBuilder.append:(Ljava/lang/String;)Ljava/lang/StringBuilder;
      37: invokevirtual #107                // Method java/lang/StringBuilder.toString:()Ljava/lang/String;
      40: astore        5
      42: aload_1
      43: astore        6
      45: aload         6
      47: ldc           #32                 // class java/lang/Object
      49: if_acmpeq     109
      52: aload_2
      53: aload         6
      55: invokevirtual #91                 // Method org/jboss/as/server/deployment/reflect/DeploymentReflectionIndex.getClassIndex:(Ljava/lang/Class;)Lorg/jboss/as/server/deployment/reflect/ClassReflectionIndex;
      58: astore        7
      60: aload         7
      62: aload         5
      64: aload_3
      65: invokevirtual #31                 // Method java/lang/reflect/Method.getParameterTypes:()[Ljava/lang/Class;
      68: invokevirtual #96                 // Method org/jboss/as/server/deployment/reflect/ClassReflectionIndex.getMethods:(Ljava/lang/String;[Ljava/lang/Class;)Ljava/util/Collection;
      71: astore        8
      73: aload         8
      75: invokeinterface #97,  1           // InterfaceMethod java/util/Collection.isEmpty:()Z
      80: ifne          99
      83: aload         8
      85: invokeinterface #98,  1           // InterfaceMethod java/util/Collection.iterator:()Ljava/util/Iterator;
      90: invokeinterface #23,  1           // InterfaceMethod java/util/Iterator.next:()Ljava/lang/Object;
      95: checkcast     #24                 // class java/lang/reflect/Method
      98: areturn
      99: aload         6
     101: invokevirtual #94                 // Method java/lang/Class.getSuperclass:()Ljava/lang/Class;
     104: astore        6
     106: goto          45
     109: getstatic     #59                 // Field org/jboss/as/ejb3/logging/EjbLogger.ROOT_LOGGER:Lorg/jboss/as/ejb3/logging/EjbLogger;
     112: ldc           #85                 // String ejbHome
     114: aload_3
     115: aload         4
     117: invokeinterface #95,  4           // InterfaceMethod org/jboss/as/ejb3/logging/EjbLogger.failToResolveMethodForHomeInterface:(Ljava/lang/String;Ljava/lang/reflect/Method;Ljava/lang/String;)Lorg/jboss/as/server/deployment/DeploymentUnitProcessingException;
     122: athrow

  private static java.lang.String[] namesOf(java.lang.Class<?>[]);
    Code:
       0: aload_0
       1: arraylength
       2: anewarray     #108                // class java/lang/String
       5: astore_1
       6: iconst_0
       7: istore_2
       8: aload_0
       9: arraylength
      10: istore_3
      11: iload_2
      12: iload_3
      13: if_icmpge     31
      16: aload_1
      17: iload_2
      18: aload_0
      19: iload_2
      20: aaload
      21: invokevirtual #45                 // Method java/lang/Class.getName:()Ljava/lang/String;
      24: aastore
      25: iinc          2, 1
      28: goto          11
      31: aload_1
      32: areturn
}
