Compiled from "AbstractNotificationContext.java"
abstract class org.sejda.core.notification.context.AbstractNotificationContext implements org.sejda.core.notification.context.NotificationContext {
  private static final org.slf4j.Logger LOG;

  private final org.sejda.core.notification.context.EventListenerHoldingStrategy holder;

  private final org.sejda.core.notification.strategy.NotificationStrategy strategy;

  protected org.sejda.core.notification.context.AbstractNotificationContext(org.sejda.core.notification.context.EventListenerHoldingStrategy);
    Code:
       0: aload_0
       1: invokespecial #1                  // Method java/lang/Object."<init>":()V
       4: aload_0
       5: aload_1
       6: putfield      #2                  // Field holder:Lorg/sejda/core/notification/context/EventListenerHoldingStrategy;
       9: aload_0
      10: aload_0
      11: invokespecial #3                  // Method getStrategy:()Lorg/sejda/core/notification/strategy/NotificationStrategy;
      14: putfield      #4                  // Field strategy:Lorg/sejda/core/notification/strategy/NotificationStrategy;
      17: return

  public void notifyListeners(org.sejda.model.notification.event.AbstractNotificationEvent);
    Code:
       0: aload_0
       1: getfield      #2                  // Field holder:Lorg/sejda/core/notification/context/EventListenerHoldingStrategy;
       4: dup
       5: astore_2
       6: monitorenter
       7: aload_0
       8: getfield      #2                  // Field holder:Lorg/sejda/core/notification/context/EventListenerHoldingStrategy;
      11: invokeinterface #5,  1            // InterfaceMethod org/sejda/core/notification/context/EventListenerHoldingStrategy.size:()I
      16: ifle          70
      19: aload_0
      20: getfield      #2                  // Field holder:Lorg/sejda/core/notification/context/EventListenerHoldingStrategy;
      23: aload_1
      24: invokeinterface #6,  2            // InterfaceMethod org/sejda/core/notification/context/EventListenerHoldingStrategy.get:(Lorg/sejda/model/notification/event/AbstractNotificationEvent;)Ljava/util/List;
      29: invokeinterface #7,  1            // InterfaceMethod java/util/List.iterator:()Ljava/util/Iterator;
      34: astore_3
      35: aload_3
      36: invokeinterface #8,  1            // InterfaceMethod java/util/Iterator.hasNext:()Z
      41: ifeq          70
      44: aload_3
      45: invokeinterface #9,  1            // InterfaceMethod java/util/Iterator.next:()Ljava/lang/Object;
      50: checkcast     #10                 // class org/sejda/model/notification/EventListener
      53: astore        4
      55: aload_0
      56: getfield      #4                  // Field strategy:Lorg/sejda/core/notification/strategy/NotificationStrategy;
      59: aload         4
      61: aload_1
      62: invokeinterface #11,  3           // InterfaceMethod org/sejda/core/notification/strategy/NotificationStrategy.notifyListener:(Lorg/sejda/model/notification/EventListener;Lorg/sejda/model/notification/event/AbstractNotificationEvent;)V
      67: goto          35
      70: aload_2
      71: monitorexit
      72: goto          82
      75: astore        5
      77: aload_2
      78: monitorexit
      79: aload         5
      81: athrow
      82: return
    Exception table:
       from    to  target type
           7    72    75   any
          75    79    75   any

  public <T extends org.sejda.model.notification.event.AbstractNotificationEvent> void addListener(org.sejda.model.notification.EventListener<T>);
    Code:
       0: aload_0
       1: getfield      #2                  // Field holder:Lorg/sejda/core/notification/context/EventListenerHoldingStrategy;
       4: dup
       5: astore_2
       6: monitorenter
       7: getstatic     #12                 // Field LOG:Lorg/slf4j/Logger;
      10: ldc           #13                 // String Adding event listener: {}
      12: aload_1
      13: invokeinterface #14,  3           // InterfaceMethod org/slf4j/Logger.trace:(Ljava/lang/String;Ljava/lang/Object;)V
      18: aload_0
      19: getfield      #2                  // Field holder:Lorg/sejda/core/notification/context/EventListenerHoldingStrategy;
      22: aload_1
      23: invokeinterface #15,  2           // InterfaceMethod org/sejda/core/notification/context/EventListenerHoldingStrategy.add:(Lorg/sejda/model/notification/EventListener;)V
      28: aload_2
      29: monitorexit
      30: goto          38
      33: astore_3
      34: aload_2
      35: monitorexit
      36: aload_3
      37: athrow
      38: return
    Exception table:
       from    to  target type
           7    30    33   any
          33    36    33   any

  public <T extends org.sejda.model.notification.event.AbstractNotificationEvent> void addListener(java.lang.Class<T>, org.sejda.model.notification.EventListener<T>);
    Code:
       0: aload_0
       1: getfield      #2                  // Field holder:Lorg/sejda/core/notification/context/EventListenerHoldingStrategy;
       4: dup
       5: astore_3
       6: monitorenter
       7: getstatic     #12                 // Field LOG:Lorg/slf4j/Logger;
      10: ldc           #16                 // String Adding event listener {} on event {}
      12: aload_2
      13: aload_1
      14: invokeinterface #17,  4           // InterfaceMethod org/slf4j/Logger.trace:(Ljava/lang/String;Ljava/lang/Object;Ljava/lang/Object;)V
      19: aload_0
      20: getfield      #2                  // Field holder:Lorg/sejda/core/notification/context/EventListenerHoldingStrategy;
      23: aload_1
      24: aload_2
      25: invokeinterface #18,  3           // InterfaceMethod org/sejda/core/notification/context/EventListenerHoldingStrategy.add:(Ljava/lang/Class;Lorg/sejda/model/notification/EventListener;)V
      30: aload_3
      31: monitorexit
      32: goto          42
      35: astore        4
      37: aload_3
      38: monitorexit
      39: aload         4
      41: athrow
      42: return
    Exception table:
       from    to  target type
           7    32    35   any
          35    39    35   any

  public <T extends org.sejda.model.notification.event.AbstractNotificationEvent> boolean removeListener(org.sejda.model.notification.EventListener<T>);
    Code:
       0: aload_0
       1: getfield      #2                  // Field holder:Lorg/sejda/core/notification/context/EventListenerHoldingStrategy;
       4: dup
       5: astore_2
       6: monitorenter
       7: getstatic     #12                 // Field LOG:Lorg/slf4j/Logger;
      10: ldc           #19                 // String Removing event listener: {}
      12: aload_1
      13: invokeinterface #14,  3           // InterfaceMethod org/slf4j/Logger.trace:(Ljava/lang/String;Ljava/lang/Object;)V
      18: aload_0
      19: getfield      #2                  // Field holder:Lorg/sejda/core/notification/context/EventListenerHoldingStrategy;
      22: aload_1
      23: invokeinterface #20,  2           // InterfaceMethod org/sejda/core/notification/context/EventListenerHoldingStrategy.remove:(Lorg/sejda/model/notification/EventListener;)Z
      28: aload_2
      29: monitorexit
      30: ireturn
      31: astore_3
      32: aload_2
      33: monitorexit
      34: aload_3
      35: athrow
    Exception table:
       from    to  target type
           7    30    31   any
          31    34    31   any

  public void clearListeners();
    Code:
       0: aload_0
       1: getfield      #2                  // Field holder:Lorg/sejda/core/notification/context/EventListenerHoldingStrategy;
       4: dup
       5: astore_1
       6: monitorenter
       7: aload_0
       8: getfield      #2                  // Field holder:Lorg/sejda/core/notification/context/EventListenerHoldingStrategy;
      11: invokeinterface #21,  1           // InterfaceMethod org/sejda/core/notification/context/EventListenerHoldingStrategy.clear:()V
      16: aload_1
      17: monitorexit
      18: goto          26
      21: astore_2
      22: aload_1
      23: monitorexit
      24: aload_2
      25: athrow
      26: return
    Exception table:
       from    to  target type
           7    18    21   any
          21    24    21   any

  public int size();
    Code:
       0: aload_0
       1: getfield      #2                  // Field holder:Lorg/sejda/core/notification/context/EventListenerHoldingStrategy;
       4: invokeinterface #5,  1            // InterfaceMethod org/sejda/core/notification/context/EventListenerHoldingStrategy.size:()I
       9: ireturn

  private org.sejda.core.notification.strategy.NotificationStrategy getStrategy();
    Code:
       0: new           #22                 // class org/sejda/core/context/DefaultSejdaContext
       3: dup
       4: invokespecial #23                 // Method org/sejda/core/context/DefaultSejdaContext."<init>":()V
       7: invokevirtual #24                 // Method org/sejda/core/context/DefaultSejdaContext.getNotificationStrategy:()Ljava/lang/Class;
      10: invokevirtual #25                 // Method java/lang/Class.newInstance:()Ljava/lang/Object;
      13: checkcast     #26                 // class org/sejda/core/notification/strategy/NotificationStrategy
      16: areturn
      17: astore_1
      18: getstatic     #12                 // Field LOG:Lorg/slf4j/Logger;
      21: ldc           #28                 // String An error occur while instantiating a new NotificationStrategy. Default strategy will be used.
      23: aload_1
      24: invokeinterface #29,  3           // InterfaceMethod org/slf4j/Logger.warn:(Ljava/lang/String;Ljava/lang/Throwable;)V
      29: goto          44
      32: astore_1
      33: getstatic     #12                 // Field LOG:Lorg/slf4j/Logger;
      36: ldc           #31                 // String Unable to access constructor for the configured NotificationStrategy. Default strategy will be used.
      38: aload_1
      39: invokeinterface #29,  3           // InterfaceMethod org/slf4j/Logger.warn:(Ljava/lang/String;Ljava/lang/Throwable;)V
      44: new           #32                 // class org/sejda/core/notification/strategy/SyncNotificationStrategy
      47: dup
      48: invokespecial #33                 // Method org/sejda/core/notification/strategy/SyncNotificationStrategy."<init>":()V
      51: areturn
    Exception table:
       from    to  target type
           0    16    17   Class java/lang/InstantiationException
           0    16    32   Class java/lang/IllegalAccessException

  static {};
    Code:
       0: ldc           #34                 // class org/sejda/core/notification/context/AbstractNotificationContext
       2: invokestatic  #35                 // Method org/slf4j/LoggerFactory.getLogger:(Ljava/lang/Class;)Lorg/slf4j/Logger;
       5: putstatic     #12                 // Field LOG:Lorg/slf4j/Logger;
       8: return
}
