Compiled from "FluxSink.java"
public final class reactor.core.publisher.FluxSink$OverflowStrategy extends java.lang.Enum<reactor.core.publisher.FluxSink$OverflowStrategy> {
  public static final reactor.core.publisher.FluxSink$OverflowStrategy IGNORE;

  public static final reactor.core.publisher.FluxSink$OverflowStrategy ERROR;

  public static final reactor.core.publisher.FluxSink$OverflowStrategy DROP;

  public static final reactor.core.publisher.FluxSink$OverflowStrategy LATEST;

  public static final reactor.core.publisher.FluxSink$OverflowStrategy BUFFER;

  private static final reactor.core.publisher.FluxSink$OverflowStrategy[] $VALUES;

  public static reactor.core.publisher.FluxSink$OverflowStrategy[] values();
    Code:
       0: getstatic     #1                  // Field $VALUES:[Lreactor/core/publisher/FluxSink$OverflowStrategy;
       3: invokevirtual #2                  // Method "[Lreactor/core/publisher/FluxSink$OverflowStrategy;".clone:()Ljava/lang/Object;
       6: checkcast     #3                  // class "[Lreactor/core/publisher/FluxSink$OverflowStrategy;"
       9: areturn

  public static reactor.core.publisher.FluxSink$OverflowStrategy valueOf(java.lang.String);
    Code:
       0: ldc           #4                  // class reactor/core/publisher/FluxSink$OverflowStrategy
       2: aload_0
       3: invokestatic  #5                  // Method java/lang/Enum.valueOf:(Ljava/lang/Class;Ljava/lang/String;)Ljava/lang/Enum;
       6: checkcast     #4                  // class reactor/core/publisher/FluxSink$OverflowStrategy
       9: areturn

  private reactor.core.publisher.FluxSink$OverflowStrategy();
    Code:
       0: aload_0
       1: aload_1
       2: iload_2
       3: invokespecial #6                  // Method java/lang/Enum."<init>":(Ljava/lang/String;I)V
       6: return

  static {};
    Code:
       0: new           #4                  // class reactor/core/publisher/FluxSink$OverflowStrategy
       3: dup
       4: ldc           #7                  // String IGNORE
       6: iconst_0
       7: invokespecial #8                  // Method "<init>":(Ljava/lang/String;I)V
      10: putstatic     #9                  // Field IGNORE:Lreactor/core/publisher/FluxSink$OverflowStrategy;
      13: new           #4                  // class reactor/core/publisher/FluxSink$OverflowStrategy
      16: dup
      17: ldc           #10                 // String ERROR
      19: iconst_1
      20: invokespecial #8                  // Method "<init>":(Ljava/lang/String;I)V
      23: putstatic     #11                 // Field ERROR:Lreactor/core/publisher/FluxSink$OverflowStrategy;
      26: new           #4                  // class reactor/core/publisher/FluxSink$OverflowStrategy
      29: dup
      30: ldc           #12                 // String DROP
      32: iconst_2
      33: invokespecial #8                  // Method "<init>":(Ljava/lang/String;I)V
      36: putstatic     #13                 // Field DROP:Lreactor/core/publisher/FluxSink$OverflowStrategy;
      39: new           #4                  // class reactor/core/publisher/FluxSink$OverflowStrategy
      42: dup
      43: ldc           #14                 // String LATEST
      45: iconst_3
      46: invokespecial #8                  // Method "<init>":(Ljava/lang/String;I)V
      49: putstatic     #15                 // Field LATEST:Lreactor/core/publisher/FluxSink$OverflowStrategy;
      52: new           #4                  // class reactor/core/publisher/FluxSink$OverflowStrategy
      55: dup
      56: ldc           #16                 // String BUFFER
      58: iconst_4
      59: invokespecial #8                  // Method "<init>":(Ljava/lang/String;I)V
      62: putstatic     #17                 // Field BUFFER:Lreactor/core/publisher/FluxSink$OverflowStrategy;
      65: iconst_5
      66: anewarray     #4                  // class reactor/core/publisher/FluxSink$OverflowStrategy
      69: dup
      70: iconst_0
      71: getstatic     #9                  // Field IGNORE:Lreactor/core/publisher/FluxSink$OverflowStrategy;
      74: aastore
      75: dup
      76: iconst_1
      77: getstatic     #11                 // Field ERROR:Lreactor/core/publisher/FluxSink$OverflowStrategy;
      80: aastore
      81: dup
      82: iconst_2
      83: getstatic     #13                 // Field DROP:Lreactor/core/publisher/FluxSink$OverflowStrategy;
      86: aastore
      87: dup
      88: iconst_3
      89: getstatic     #15                 // Field LATEST:Lreactor/core/publisher/FluxSink$OverflowStrategy;
      92: aastore
      93: dup
      94: iconst_4
      95: getstatic     #17                 // Field BUFFER:Lreactor/core/publisher/FluxSink$OverflowStrategy;
      98: aastore
      99: putstatic     #1                  // Field $VALUES:[Lreactor/core/publisher/FluxSink$OverflowStrategy;
     102: return
}
