Compiled from "FluxOnAssembly.java"
class reactor.core.publisher.FluxOnAssembly$SnapshotStackException extends java.lang.Exception {
  public reactor.core.publisher.FluxOnAssembly$SnapshotStackException(java.lang.String);
    Code:
       0: aload_0
       1: aload_1
       2: invokespecial #1                  // Method java/lang/Exception."<init>":(Ljava/lang/String;)V
       5: return

  public synchronized java.lang.Throwable fillInStackTrace();
    Code:
       0: aload_0
       1: areturn

  public java.lang.String toString();
    Code:
       0: aload_0
       1: invokevirtual #2                  // Method getMessage:()Ljava/lang/String;
       4: areturn
}
