Compiled from "InnerConsumer.java"
interface reactor.core.publisher.InnerConsumer<I> extends reactor.core.CoreSubscriber<I>, reactor.core.Scannable {
  public default java.lang.String stepName();
    Code:
       0: aload_0
       1: invokevirtual #1                  // Method java/lang/Object.getClass:()Ljava/lang/Class;
       4: invokevirtual #2                  // Method java/lang/Class.getSimpleName:()Ljava/lang/String;
       7: astore_1
       8: aload_1
       9: ldc           #3                  // String @
      11: invokevirtual #4                  // Method java/lang/String.contains:(Ljava/lang/CharSequence;)Z
      14: ifeq          49
      17: aload_1
      18: ldc           #5                  // String $
      20: invokevirtual #4                  // Method java/lang/String.contains:(Ljava/lang/CharSequence;)Z
      23: ifeq          49
      26: aload_1
      27: iconst_0
      28: aload_1
      29: bipush        36
      31: invokevirtual #6                  // Method java/lang/String.indexOf:(I)I
      34: invokevirtual #7                  // Method java/lang/String.substring:(II)Ljava/lang/String;
      37: aload_1
      38: bipush        46
      40: invokevirtual #8                  // Method java/lang/String.lastIndexOf:(I)I
      43: iconst_1
      44: iadd
      45: invokevirtual #9                  // Method java/lang/String.substring:(I)Ljava/lang/String;
      48: astore_1
      49: getstatic     #10                 // Field OPERATOR_NAME_UNRELATED_WORDS_PATTERN:Ljava/util/regex/Pattern;
      52: aload_1
      53: invokevirtual #11                 // Method java/util/regex/Pattern.matcher:(Ljava/lang/CharSequence;)Ljava/util/regex/Matcher;
      56: ldc           #12                 // String
      58: invokevirtual #13                 // Method java/util/regex/Matcher.replaceAll:(Ljava/lang/String;)Ljava/lang/String;
      61: astore_2
      62: aload_2
      63: invokevirtual #14                 // Method java/lang/String.isEmpty:()Z
      66: ifne          100
      69: new           #15                 // class java/lang/StringBuilder
      72: dup
      73: invokespecial #16                 // Method java/lang/StringBuilder."<init>":()V
      76: aload_2
      77: iconst_0
      78: iconst_1
      79: invokevirtual #7                  // Method java/lang/String.substring:(II)Ljava/lang/String;
      82: invokevirtual #17                 // Method java/lang/String.toLowerCase:()Ljava/lang/String;
      85: invokevirtual #18                 // Method java/lang/StringBuilder.append:(Ljava/lang/String;)Ljava/lang/StringBuilder;
      88: aload_2
      89: iconst_1
      90: invokevirtual #9                  // Method java/lang/String.substring:(I)Ljava/lang/String;
      93: invokevirtual #18                 // Method java/lang/StringBuilder.append:(Ljava/lang/String;)Ljava/lang/StringBuilder;
      96: invokevirtual #19                 // Method java/lang/StringBuilder.toString:()Ljava/lang/String;
      99: areturn
     100: aload_2
     101: areturn
}
