Compiled from "MonoNever.java"
final class reactor.core.publisher.MonoNever extends reactor.core.publisher.Mono<java.lang.Object> implements reactor.core.publisher.SourceProducer<java.lang.Object> {
  static final reactor.core.publisher.Mono<java.lang.Object> INSTANCE;

  reactor.core.publisher.MonoNever();
    Code:
       0: aload_0
       1: invokespecial #1                  // Method reactor/core/publisher/Mono."<init>":()V
       4: return

  public void subscribe(reactor.core.CoreSubscriber<? super java.lang.Object>);
    Code:
       0: aload_1
       1: invokestatic  #2                  // Method reactor/core/publisher/Operators.emptySubscription:()Lorg/reactivestreams/Subscription;
       4: invokeinterface #3,  2            // InterfaceMethod reactor/core/CoreSubscriber.onSubscribe:(Lorg/reactivestreams/Subscription;)V
       9: return

  public java.lang.Object scanUnsafe(reactor.core.Scannable$Attr);
    Code:
       0: aconst_null
       1: areturn

  static <T> reactor.core.publisher.Mono<T> instance();
    Code:
       0: getstatic     #4                  // Field INSTANCE:Lreactor/core/publisher/Mono;
       3: areturn

  static {};
    Code:
       0: new           #5                  // class reactor/core/publisher/MonoNever
       3: dup
       4: invokespecial #6                  // Method "<init>":()V
       7: putstatic     #4                  // Field INSTANCE:Lreactor/core/publisher/Mono;
      10: return
}
