Compiled from "AndroidPlatform.java"
class io.dekorate.deps.okhttp3.internal.platform.AndroidPlatform extends io.dekorate.deps.okhttp3.internal.platform.Platform {
  private static final int MAX_LOG_LENGTH;

  private final java.lang.Class<?> sslParametersClass;

  private final io.dekorate.deps.okhttp3.internal.platform.OptionalMethod<java.net.Socket> setUseSessionTickets;

  private final io.dekorate.deps.okhttp3.internal.platform.OptionalMethod<java.net.Socket> setHostname;

  private final io.dekorate.deps.okhttp3.internal.platform.OptionalMethod<java.net.Socket> getAlpnSelectedProtocol;

  private final io.dekorate.deps.okhttp3.internal.platform.OptionalMethod<java.net.Socket> setAlpnProtocols;

  private final io.dekorate.deps.okhttp3.internal.platform.AndroidPlatform$CloseGuard closeGuard;

  io.dekorate.deps.okhttp3.internal.platform.AndroidPlatform(java.lang.Class<?>, io.dekorate.deps.okhttp3.internal.platform.OptionalMethod<java.net.Socket>, io.dekorate.deps.okhttp3.internal.platform.OptionalMethod<java.net.Socket>, io.dekorate.deps.okhttp3.internal.platform.OptionalMethod<java.net.Socket>, io.dekorate.deps.okhttp3.internal.platform.OptionalMethod<java.net.Socket>);
    Code:
       0: aload_0
       1: invokespecial #39                 // Method io/dekorate/deps/okhttp3/internal/platform/Platform."<init>":()V
       4: aload_0
       5: invokestatic  #43                 // Method io/dekorate/deps/okhttp3/internal/platform/AndroidPlatform$CloseGuard.get:()Lio/dekorate/deps/okhttp3/internal/platform/AndroidPlatform$CloseGuard;
       8: putfield      #45                 // Field closeGuard:Lio/dekorate/deps/okhttp3/internal/platform/AndroidPlatform$CloseGuard;
      11: aload_0
      12: aload_1
      13: putfield      #47                 // Field sslParametersClass:Ljava/lang/Class;
      16: aload_0
      17: aload_2
      18: putfield      #49                 // Field setUseSessionTickets:Lio/dekorate/deps/okhttp3/internal/platform/OptionalMethod;
      21: aload_0
      22: aload_3
      23: putfield      #51                 // Field setHostname:Lio/dekorate/deps/okhttp3/internal/platform/OptionalMethod;
      26: aload_0
      27: aload         4
      29: putfield      #53                 // Field getAlpnSelectedProtocol:Lio/dekorate/deps/okhttp3/internal/platform/OptionalMethod;
      32: aload_0
      33: aload         5
      35: putfield      #55                 // Field setAlpnProtocols:Lio/dekorate/deps/okhttp3/internal/platform/OptionalMethod;
      38: return

  public void connectSocket(java.net.Socket, java.net.InetSocketAddress, int) throws java.io.IOException;
    Code:
       0: aload_1
       1: aload_2
       2: iload_3
       3: invokevirtual #73                 // Method java/net/Socket.connect:(Ljava/net/SocketAddress;I)V
       6: goto          91
       9: astore        4
      11: aload         4
      13: invokestatic  #79                 // Method io/dekorate/deps/okhttp3/internal/Util.isAndroidGetsocknameError:(Ljava/lang/AssertionError;)Z
      16: ifeq          29
      19: new           #61                 // class java/io/IOException
      22: dup
      23: aload         4
      25: invokespecial #82                 // Method java/io/IOException."<init>":(Ljava/lang/Throwable;)V
      28: athrow
      29: aload         4
      31: athrow
      32: astore        4
      34: new           #61                 // class java/io/IOException
      37: dup
      38: ldc           #86                 // String Exception in connect
      40: invokespecial #89                 // Method java/io/IOException."<init>":(Ljava/lang/String;)V
      43: astore        5
      45: aload         5
      47: aload         4
      49: invokevirtual #93                 // Method java/io/IOException.initCause:(Ljava/lang/Throwable;)Ljava/lang/Throwable;
      52: pop
      53: aload         5
      55: athrow
      56: astore        4
      58: getstatic     #96                 // Field android/os/Build$VERSION.SDK_INT:I
      61: bipush        26
      63: if_icmpne     88
      66: new           #61                 // class java/io/IOException
      69: dup
      70: ldc           #86                 // String Exception in connect
      72: invokespecial #89                 // Method java/io/IOException."<init>":(Ljava/lang/String;)V
      75: astore        5
      77: aload         5
      79: aload         4
      81: invokevirtual #93                 // Method java/io/IOException.initCause:(Ljava/lang/Throwable;)Ljava/lang/Throwable;
      84: pop
      85: aload         5
      87: athrow
      88: aload         4
      90: athrow
      91: return
    Exception table:
       from    to  target type
           0     6     9   Class java/lang/AssertionError
           0     6    32   Class java/lang/SecurityException
           0     6    56   Class java/lang/ClassCastException

  protected javax.net.ssl.X509TrustManager trustManager(javax.net.ssl.SSLSocketFactory);
    Code:
       0: aload_1
       1: aload_0
       2: getfield      #47                 // Field sslParametersClass:Ljava/lang/Class;
       5: ldc           #114                // String sslParameters
       7: invokestatic  #118                // Method readFieldOrNull:(Ljava/lang/Object;Ljava/lang/Class;Ljava/lang/String;)Ljava/lang/Object;
      10: astore_2
      11: aload_2
      12: ifnonnull     47
      15: ldc           #120                // String com.google.android.gms.org.conscrypt.SSLParametersImpl
      17: iconst_0
      18: aload_1
      19: invokevirtual #126                // Method java/lang/Object.getClass:()Ljava/lang/Class;
      22: invokevirtual #132                // Method java/lang/Class.getClassLoader:()Ljava/lang/ClassLoader;
      25: invokestatic  #136                // Method java/lang/Class.forName:(Ljava/lang/String;ZLjava/lang/ClassLoader;)Ljava/lang/Class;
      28: astore_3
      29: aload_1
      30: aload_3
      31: ldc           #114                // String sslParameters
      33: invokestatic  #118                // Method readFieldOrNull:(Ljava/lang/Object;Ljava/lang/Class;Ljava/lang/String;)Ljava/lang/Object;
      36: astore_2
      37: goto          47
      40: astore_3
      41: aload_0
      42: aload_1
      43: invokespecial #140                // Method io/dekorate/deps/okhttp3/internal/platform/Platform.trustManager:(Ljavax/net/ssl/SSLSocketFactory;)Ljavax/net/ssl/X509TrustManager;
      46: areturn
      47: aload_2
      48: ldc           #142                // class javax/net/ssl/X509TrustManager
      50: ldc           #144                // String x509TrustManager
      52: invokestatic  #118                // Method readFieldOrNull:(Ljava/lang/Object;Ljava/lang/Class;Ljava/lang/String;)Ljava/lang/Object;
      55: checkcast     #142                // class javax/net/ssl/X509TrustManager
      58: astore_3
      59: aload_3
      60: ifnull        65
      63: aload_3
      64: areturn
      65: aload_2
      66: ldc           #142                // class javax/net/ssl/X509TrustManager
      68: ldc           #145                // String trustManager
      70: invokestatic  #118                // Method readFieldOrNull:(Ljava/lang/Object;Ljava/lang/Class;Ljava/lang/String;)Ljava/lang/Object;
      73: checkcast     #142                // class javax/net/ssl/X509TrustManager
      76: areturn
    Exception table:
       from    to  target type
          15    37    40   Class java/lang/ClassNotFoundException

  public void configureTlsExtensions(javax.net.ssl.SSLSocket, java.lang.String, java.util.List<io.dekorate.deps.okhttp3.Protocol>);
    Code:
       0: aload_2
       1: ifnull        41
       4: aload_0
       5: getfield      #49                 // Field setUseSessionTickets:Lio/dekorate/deps/okhttp3/internal/platform/OptionalMethod;
       8: aload_1
       9: iconst_1
      10: anewarray     #122                // class java/lang/Object
      13: dup
      14: iconst_0
      15: iconst_1
      16: invokestatic  #161                // Method java/lang/Boolean.valueOf:(Z)Ljava/lang/Boolean;
      19: aastore
      20: invokevirtual #167                // Method io/dekorate/deps/okhttp3/internal/platform/OptionalMethod.invokeOptionalWithoutCheckedException:(Ljava/lang/Object;[Ljava/lang/Object;)Ljava/lang/Object;
      23: pop
      24: aload_0
      25: getfield      #51                 // Field setHostname:Lio/dekorate/deps/okhttp3/internal/platform/OptionalMethod;
      28: aload_1
      29: iconst_1
      30: anewarray     #122                // class java/lang/Object
      33: dup
      34: iconst_0
      35: aload_2
      36: aastore
      37: invokevirtual #167                // Method io/dekorate/deps/okhttp3/internal/platform/OptionalMethod.invokeOptionalWithoutCheckedException:(Ljava/lang/Object;[Ljava/lang/Object;)Ljava/lang/Object;
      40: pop
      41: aload_0
      42: getfield      #55                 // Field setAlpnProtocols:Lio/dekorate/deps/okhttp3/internal/platform/OptionalMethod;
      45: ifnull        83
      48: aload_0
      49: getfield      #55                 // Field setAlpnProtocols:Lio/dekorate/deps/okhttp3/internal/platform/OptionalMethod;
      52: aload_1
      53: invokevirtual #171                // Method io/dekorate/deps/okhttp3/internal/platform/OptionalMethod.isSupported:(Ljava/lang/Object;)Z
      56: ifeq          83
      59: iconst_1
      60: anewarray     #122                // class java/lang/Object
      63: dup
      64: iconst_0
      65: aload_3
      66: invokestatic  #175                // Method concatLengthPrefixed:(Ljava/util/List;)[B
      69: aastore
      70: astore        4
      72: aload_0
      73: getfield      #55                 // Field setAlpnProtocols:Lio/dekorate/deps/okhttp3/internal/platform/OptionalMethod;
      76: aload_1
      77: aload         4
      79: invokevirtual #178                // Method io/dekorate/deps/okhttp3/internal/platform/OptionalMethod.invokeWithoutCheckedException:(Ljava/lang/Object;[Ljava/lang/Object;)Ljava/lang/Object;
      82: pop
      83: return

  public java.lang.String getSelectedProtocol(javax.net.ssl.SSLSocket);
    Code:
       0: aload_0
       1: getfield      #53                 // Field getAlpnSelectedProtocol:Lio/dekorate/deps/okhttp3/internal/platform/OptionalMethod;
       4: ifnonnull     9
       7: aconst_null
       8: areturn
       9: aload_0
      10: getfield      #53                 // Field getAlpnSelectedProtocol:Lio/dekorate/deps/okhttp3/internal/platform/OptionalMethod;
      13: aload_1
      14: invokevirtual #171                // Method io/dekorate/deps/okhttp3/internal/platform/OptionalMethod.isSupported:(Ljava/lang/Object;)Z
      17: ifne          22
      20: aconst_null
      21: areturn
      22: aload_0
      23: getfield      #53                 // Field getAlpnSelectedProtocol:Lio/dekorate/deps/okhttp3/internal/platform/OptionalMethod;
      26: aload_1
      27: iconst_0
      28: anewarray     #122                // class java/lang/Object
      31: invokevirtual #178                // Method io/dekorate/deps/okhttp3/internal/platform/OptionalMethod.invokeWithoutCheckedException:(Ljava/lang/Object;[Ljava/lang/Object;)Ljava/lang/Object;
      34: checkcast     #191                // class "[B"
      37: astore_2
      38: aload_2
      39: ifnull        56
      42: new           #193                // class java/lang/String
      45: dup
      46: aload_2
      47: getstatic     #197                // Field io/dekorate/deps/okhttp3/internal/Util.UTF_8:Ljava/nio/charset/Charset;
      50: invokespecial #200                // Method java/lang/String."<init>":([BLjava/nio/charset/Charset;)V
      53: goto          57
      56: aconst_null
      57: areturn

  public void log(int, java.lang.String, java.lang.Throwable);
    Code:
       0: iload_1
       1: iconst_5
       2: if_icmpne     9
       5: iconst_5
       6: goto          10
       9: iconst_3
      10: istore        4
      12: aload_3
      13: ifnull        43
      16: new           #205                // class java/lang/StringBuilder
      19: dup
      20: invokespecial #206                // Method java/lang/StringBuilder."<init>":()V
      23: aload_2
      24: invokevirtual #210                // Method java/lang/StringBuilder.append:(Ljava/lang/String;)Ljava/lang/StringBuilder;
      27: bipush        10
      29: invokevirtual #213                // Method java/lang/StringBuilder.append:(C)Ljava/lang/StringBuilder;
      32: aload_3
      33: invokestatic  #219                // Method android/util/Log.getStackTraceString:(Ljava/lang/Throwable;)Ljava/lang/String;
      36: invokevirtual #210                // Method java/lang/StringBuilder.append:(Ljava/lang/String;)Ljava/lang/StringBuilder;
      39: invokevirtual #223                // Method java/lang/StringBuilder.toString:()Ljava/lang/String;
      42: astore_2
      43: iconst_0
      44: istore        5
      46: aload_2
      47: invokevirtual #227                // Method java/lang/String.length:()I
      50: istore        6
      52: iload         5
      54: iload         6
      56: if_icmpge     130
      59: aload_2
      60: bipush        10
      62: iload         5
      64: invokevirtual #231                // Method java/lang/String.indexOf:(II)I
      67: istore        7
      69: iload         7
      71: iconst_m1
      72: if_icmpeq     80
      75: iload         7
      77: goto          82
      80: iload         6
      82: istore        7
      84: iload         7
      86: iload         5
      88: sipush        4000
      91: iadd
      92: invokestatic  #236                // Method java/lang/Math.min:(II)I
      95: istore        8
      97: iload         4
      99: ldc           #238                // String OkHttp
     101: aload_2
     102: iload         5
     104: iload         8
     106: invokevirtual #242                // Method java/lang/String.substring:(II)Ljava/lang/String;
     109: invokestatic  #246                // Method android/util/Log.println:(ILjava/lang/String;Ljava/lang/String;)I
     112: pop
     113: iload         8
     115: istore        5
     117: iload         5
     119: iload         7
     121: if_icmplt     84
     124: iinc          5, 1
     127: goto          52
     130: return

  public java.lang.Object getStackTraceForCloseable(java.lang.String);
    Code:
       0: aload_0
       1: getfield      #45                 // Field closeGuard:Lio/dekorate/deps/okhttp3/internal/platform/AndroidPlatform$CloseGuard;
       4: aload_1
       5: invokevirtual #259                // Method io/dekorate/deps/okhttp3/internal/platform/AndroidPlatform$CloseGuard.createAndOpen:(Ljava/lang/String;)Ljava/lang/Object;
       8: areturn

  public void logCloseableLeak(java.lang.String, java.lang.Object);
    Code:
       0: aload_0
       1: getfield      #45                 // Field closeGuard:Lio/dekorate/deps/okhttp3/internal/platform/AndroidPlatform$CloseGuard;
       4: aload_2
       5: invokevirtual #265                // Method io/dekorate/deps/okhttp3/internal/platform/AndroidPlatform$CloseGuard.warnIfOpen:(Ljava/lang/Object;)Z
       8: istore_3
       9: iload_3
      10: ifne          20
      13: aload_0
      14: iconst_5
      15: aload_1
      16: aconst_null
      17: invokevirtual #267                // Method log:(ILjava/lang/String;Ljava/lang/Throwable;)V
      20: return

  public boolean isCleartextTrafficPermitted(java.lang.String);
    Code:
       0: getstatic     #96                 // Field android/os/Build$VERSION.SDK_INT:I
       3: bipush        23
       5: if_icmpge     14
       8: aload_0
       9: aload_1
      10: invokespecial #282                // Method io/dekorate/deps/okhttp3/internal/platform/Platform.isCleartextTrafficPermitted:(Ljava/lang/String;)Z
      13: ireturn
      14: ldc_w         #284                // String android.security.NetworkSecurityPolicy
      17: invokestatic  #287                // Method java/lang/Class.forName:(Ljava/lang/String;)Ljava/lang/Class;
      20: astore_2
      21: aload_2
      22: ldc_w         #289                // String getInstance
      25: iconst_0
      26: anewarray     #128                // class java/lang/Class
      29: invokevirtual #293                // Method java/lang/Class.getMethod:(Ljava/lang/String;[Ljava/lang/Class;)Ljava/lang/reflect/Method;
      32: astore_3
      33: aload_3
      34: aconst_null
      35: iconst_0
      36: anewarray     #122                // class java/lang/Object
      39: invokevirtual #298                // Method java/lang/reflect/Method.invoke:(Ljava/lang/Object;[Ljava/lang/Object;)Ljava/lang/Object;
      42: astore        4
      44: aload_0
      45: aload_1
      46: aload_2
      47: aload         4
      49: invokespecial #302                // Method api24IsCleartextTrafficPermitted:(Ljava/lang/String;Ljava/lang/Class;Ljava/lang/Object;)Z
      52: ireturn
      53: astore_2
      54: aload_0
      55: aload_1
      56: invokespecial #282                // Method io/dekorate/deps/okhttp3/internal/platform/Platform.isCleartextTrafficPermitted:(Ljava/lang/String;)Z
      59: ireturn
      60: astore_2
      61: ldc_w         #308                // String unable to determine cleartext support
      64: aload_2
      65: invokestatic  #312                // Method io/dekorate/deps/okhttp3/internal/Util.assertionError:(Ljava/lang/String;Ljava/lang/Exception;)Ljava/lang/AssertionError;
      68: athrow
    Exception table:
       from    to  target type
          14    52    53   Class java/lang/ClassNotFoundException
          14    52    53   Class java/lang/NoSuchMethodException
          14    52    60   Class java/lang/IllegalAccessException
          14    52    60   Class java/lang/IllegalArgumentException
          14    52    60   Class java/lang/reflect/InvocationTargetException

  private boolean api24IsCleartextTrafficPermitted(java.lang.String, java.lang.Class<?>, java.lang.Object) throws java.lang.reflect.InvocationTargetException, java.lang.IllegalAccessException;
    Code:
       0: aload_2
       1: ldc_w         #320                // String isCleartextTrafficPermitted
       4: iconst_1
       5: anewarray     #128                // class java/lang/Class
       8: dup
       9: iconst_0
      10: ldc           #193                // class java/lang/String
      12: aastore
      13: invokevirtual #293                // Method java/lang/Class.getMethod:(Ljava/lang/String;[Ljava/lang/Class;)Ljava/lang/reflect/Method;
      16: astore        4
      18: aload         4
      20: aload_3
      21: iconst_1
      22: anewarray     #122                // class java/lang/Object
      25: dup
      26: iconst_0
      27: aload_1
      28: aastore
      29: invokevirtual #298                // Method java/lang/reflect/Method.invoke:(Ljava/lang/Object;[Ljava/lang/Object;)Ljava/lang/Object;
      32: checkcast     #157                // class java/lang/Boolean
      35: invokevirtual #324                // Method java/lang/Boolean.booleanValue:()Z
      38: ireturn
      39: astore        4
      41: aload_0
      42: aload_1
      43: aload_2
      44: aload_3
      45: invokespecial #327                // Method api23IsCleartextTrafficPermitted:(Ljava/lang/String;Ljava/lang/Class;Ljava/lang/Object;)Z
      48: ireturn
    Exception table:
       from    to  target type
           0    38    39   Class java/lang/NoSuchMethodException

  private boolean api23IsCleartextTrafficPermitted(java.lang.String, java.lang.Class<?>, java.lang.Object) throws java.lang.reflect.InvocationTargetException, java.lang.IllegalAccessException;
    Code:
       0: aload_2
       1: ldc_w         #320                // String isCleartextTrafficPermitted
       4: iconst_0
       5: anewarray     #128                // class java/lang/Class
       8: invokevirtual #293                // Method java/lang/Class.getMethod:(Ljava/lang/String;[Ljava/lang/Class;)Ljava/lang/reflect/Method;
      11: astore        4
      13: aload         4
      15: aload_3
      16: iconst_0
      17: anewarray     #122                // class java/lang/Object
      20: invokevirtual #298                // Method java/lang/reflect/Method.invoke:(Ljava/lang/Object;[Ljava/lang/Object;)Ljava/lang/Object;
      23: checkcast     #157                // class java/lang/Boolean
      26: invokevirtual #324                // Method java/lang/Boolean.booleanValue:()Z
      29: ireturn
      30: astore        4
      32: aload_0
      33: aload_1
      34: invokespecial #282                // Method io/dekorate/deps/okhttp3/internal/platform/Platform.isCleartextTrafficPermitted:(Ljava/lang/String;)Z
      37: ireturn
    Exception table:
       from    to  target type
           0    29    30   Class java/lang/NoSuchMethodException

  private static boolean supportsAlpn();
    Code:
       0: ldc_w         #332                // String GMSCore_OpenSSL
       3: invokestatic  #338                // Method java/security/Security.getProvider:(Ljava/lang/String;)Ljava/security/Provider;
       6: ifnull        11
       9: iconst_1
      10: ireturn
      11: ldc_w         #340                // String android.net.Network
      14: invokestatic  #287                // Method java/lang/Class.forName:(Ljava/lang/String;)Ljava/lang/Class;
      17: pop
      18: iconst_1
      19: ireturn
      20: astore_0
      21: iconst_0
      22: ireturn
    Exception table:
       from    to  target type
          11    19    20   Class java/lang/ClassNotFoundException

  public io.dekorate.deps.okhttp3.internal.tls.CertificateChainCleaner buildCertificateChainCleaner(javax.net.ssl.X509TrustManager);
    Code:
       0: ldc_w         #344                // String android.net.http.X509TrustManagerExtensions
       3: invokestatic  #287                // Method java/lang/Class.forName:(Ljava/lang/String;)Ljava/lang/Class;
       6: astore_2
       7: aload_2
       8: iconst_1
       9: anewarray     #128                // class java/lang/Class
      12: dup
      13: iconst_0
      14: ldc           #142                // class javax/net/ssl/X509TrustManager
      16: aastore
      17: invokevirtual #348                // Method java/lang/Class.getConstructor:([Ljava/lang/Class;)Ljava/lang/reflect/Constructor;
      20: astore_3
      21: aload_3
      22: iconst_1
      23: anewarray     #122                // class java/lang/Object
      26: dup
      27: iconst_0
      28: aload_1
      29: aastore
      30: invokevirtual #354                // Method java/lang/reflect/Constructor.newInstance:([Ljava/lang/Object;)Ljava/lang/Object;
      33: astore        4
      35: aload_2
      36: ldc_w         #356                // String checkServerTrusted
      39: iconst_3
      40: anewarray     #128                // class java/lang/Class
      43: dup
      44: iconst_0
      45: ldc_w         #358                // class "[Ljava/security/cert/X509Certificate;"
      48: aastore
      49: dup
      50: iconst_1
      51: ldc           #193                // class java/lang/String
      53: aastore
      54: dup
      55: iconst_2
      56: ldc           #193                // class java/lang/String
      58: aastore
      59: invokevirtual #293                // Method java/lang/Class.getMethod:(Ljava/lang/String;[Ljava/lang/Class;)Ljava/lang/reflect/Method;
      62: astore        5
      64: new           #13                 // class io/dekorate/deps/okhttp3/internal/platform/AndroidPlatform$AndroidCertificateChainCleaner
      67: dup
      68: aload         4
      70: aload         5
      72: invokespecial #361                // Method io/dekorate/deps/okhttp3/internal/platform/AndroidPlatform$AndroidCertificateChainCleaner."<init>":(Ljava/lang/Object;Ljava/lang/reflect/Method;)V
      75: areturn
      76: astore_2
      77: aload_0
      78: aload_1
      79: invokespecial #363                // Method io/dekorate/deps/okhttp3/internal/platform/Platform.buildCertificateChainCleaner:(Ljavax/net/ssl/X509TrustManager;)Lio/dekorate/deps/okhttp3/internal/tls/CertificateChainCleaner;
      82: areturn
    Exception table:
       from    to  target type
           0    75    76   Class java/lang/Exception

  public static io.dekorate.deps.okhttp3.internal.platform.Platform buildIfSupported();
    Code:
       0: ldc_w         #372                // String com.android.org.conscrypt.SSLParametersImpl
       3: invokestatic  #287                // Method java/lang/Class.forName:(Ljava/lang/String;)Ljava/lang/Class;
       6: astore_0
       7: goto          18
      10: astore_1
      11: ldc_w         #374                // String org.apache.harmony.xnet.provider.jsse.SSLParametersImpl
      14: invokestatic  #287                // Method java/lang/Class.forName:(Ljava/lang/String;)Ljava/lang/Class;
      17: astore_0
      18: new           #163                // class io/dekorate/deps/okhttp3/internal/platform/OptionalMethod
      21: dup
      22: aconst_null
      23: ldc_w         #375                // String setUseSessionTickets
      26: iconst_1
      27: anewarray     #128                // class java/lang/Class
      30: dup
      31: iconst_0
      32: getstatic     #378                // Field java/lang/Boolean.TYPE:Ljava/lang/Class;
      35: aastore
      36: invokespecial #381                // Method io/dekorate/deps/okhttp3/internal/platform/OptionalMethod."<init>":(Ljava/lang/Class;Ljava/lang/String;[Ljava/lang/Class;)V
      39: astore_1
      40: new           #163                // class io/dekorate/deps/okhttp3/internal/platform/OptionalMethod
      43: dup
      44: aconst_null
      45: ldc_w         #382                // String setHostname
      48: iconst_1
      49: anewarray     #128                // class java/lang/Class
      52: dup
      53: iconst_0
      54: ldc           #193                // class java/lang/String
      56: aastore
      57: invokespecial #381                // Method io/dekorate/deps/okhttp3/internal/platform/OptionalMethod."<init>":(Ljava/lang/Class;Ljava/lang/String;[Ljava/lang/Class;)V
      60: astore_2
      61: aconst_null
      62: astore_3
      63: aconst_null
      64: astore        4
      66: invokestatic  #384                // Method supportsAlpn:()Z
      69: ifeq          111
      72: new           #163                // class io/dekorate/deps/okhttp3/internal/platform/OptionalMethod
      75: dup
      76: ldc           #191                // class "[B"
      78: ldc_w         #385                // String getAlpnSelectedProtocol
      81: iconst_0
      82: anewarray     #128                // class java/lang/Class
      85: invokespecial #381                // Method io/dekorate/deps/okhttp3/internal/platform/OptionalMethod."<init>":(Ljava/lang/Class;Ljava/lang/String;[Ljava/lang/Class;)V
      88: astore_3
      89: new           #163                // class io/dekorate/deps/okhttp3/internal/platform/OptionalMethod
      92: dup
      93: aconst_null
      94: ldc_w         #386                // String setAlpnProtocols
      97: iconst_1
      98: anewarray     #128                // class java/lang/Class
     101: dup
     102: iconst_0
     103: ldc           #191                // class "[B"
     105: aastore
     106: invokespecial #381                // Method io/dekorate/deps/okhttp3/internal/platform/OptionalMethod."<init>":(Ljava/lang/Class;Ljava/lang/String;[Ljava/lang/Class;)V
     109: astore        4
     111: new           #2                  // class io/dekorate/deps/okhttp3/internal/platform/AndroidPlatform
     114: dup
     115: aload_0
     116: aload_1
     117: aload_2
     118: aload_3
     119: aload         4
     121: invokespecial #388                // Method "<init>":(Ljava/lang/Class;Lio/dekorate/deps/okhttp3/internal/platform/OptionalMethod;Lio/dekorate/deps/okhttp3/internal/platform/OptionalMethod;Lio/dekorate/deps/okhttp3/internal/platform/OptionalMethod;Lio/dekorate/deps/okhttp3/internal/platform/OptionalMethod;)V
     124: areturn
     125: astore_0
     126: aconst_null
     127: areturn
    Exception table:
       from    to  target type
           0     7    10   Class java/lang/ClassNotFoundException
           0   124   125   Class java/lang/ClassNotFoundException

  public io.dekorate.deps.okhttp3.internal.tls.TrustRootIndex buildTrustRootIndex(javax.net.ssl.X509TrustManager);
    Code:
       0: aload_1
       1: invokevirtual #126                // Method java/lang/Object.getClass:()Ljava/lang/Class;
       4: ldc_w         #392                // String findTrustAnchorByIssuerAndSignature
       7: iconst_1
       8: anewarray     #128                // class java/lang/Class
      11: dup
      12: iconst_0
      13: ldc_w         #394                // class java/security/cert/X509Certificate
      16: aastore
      17: invokevirtual #397                // Method java/lang/Class.getDeclaredMethod:(Ljava/lang/String;[Ljava/lang/Class;)Ljava/lang/reflect/Method;
      20: astore_2
      21: aload_2
      22: iconst_1
      23: invokevirtual #401                // Method java/lang/reflect/Method.setAccessible:(Z)V
      26: new           #7                  // class io/dekorate/deps/okhttp3/internal/platform/AndroidPlatform$AndroidTrustRootIndex
      29: dup
      30: aload_1
      31: aload_2
      32: invokespecial #404                // Method io/dekorate/deps/okhttp3/internal/platform/AndroidPlatform$AndroidTrustRootIndex."<init>":(Ljavax/net/ssl/X509TrustManager;Ljava/lang/reflect/Method;)V
      35: areturn
      36: astore_2
      37: aload_0
      38: aload_1
      39: invokespecial #406                // Method io/dekorate/deps/okhttp3/internal/platform/Platform.buildTrustRootIndex:(Ljavax/net/ssl/X509TrustManager;)Lio/dekorate/deps/okhttp3/internal/tls/TrustRootIndex;
      42: areturn
    Exception table:
       from    to  target type
           0    35    36   Class java/lang/NoSuchMethodException

  public javax.net.ssl.SSLContext getSSLContext();
    Code:
       0: getstatic     #96                 // Field android/os/Build$VERSION.SDK_INT:I
       3: bipush        16
       5: if_icmplt     20
       8: getstatic     #96                 // Field android/os/Build$VERSION.SDK_INT:I
      11: bipush        22
      13: if_icmpge     20
      16: iconst_1
      17: goto          21
      20: iconst_0
      21: istore_1
      22: goto          28
      25: astore_2
      26: iconst_1
      27: istore_1
      28: iload_1
      29: ifeq          40
      32: ldc_w         #415                // String TLSv1.2
      35: invokestatic  #420                // Method javax/net/ssl/SSLContext.getInstance:(Ljava/lang/String;)Ljavax/net/ssl/SSLContext;
      38: areturn
      39: astore_2
      40: ldc_w         #422                // String TLS
      43: invokestatic  #420                // Method javax/net/ssl/SSLContext.getInstance:(Ljava/lang/String;)Ljavax/net/ssl/SSLContext;
      46: areturn
      47: astore_2
      48: new           #424                // class java/lang/IllegalStateException
      51: dup
      52: ldc_w         #426                // String No TLS provider
      55: aload_2
      56: invokespecial #429                // Method java/lang/IllegalStateException."<init>":(Ljava/lang/String;Ljava/lang/Throwable;)V
      59: athrow
    Exception table:
       from    to  target type
           0    22    25   Class java/lang/NoClassDefFoundError
          32    38    39   Class java/security/NoSuchAlgorithmException
          40    46    47   Class java/security/NoSuchAlgorithmException
}
