Compiled from "Assertion.java"
public interface org.opensaml.saml2.core.Assertion extends org.opensaml.common.SignableSAMLObject,org.opensaml.saml2.core.Evidentiary {
  public static final java.lang.String DEFAULT_ELEMENT_LOCAL_NAME;

  public static final javax.xml.namespace.QName DEFAULT_ELEMENT_NAME;

  public static final java.lang.String TYPE_LOCAL_NAME;

  public static final javax.xml.namespace.QName TYPE_NAME;

  public static final java.lang.String VERSION_ATTRIB_NAME;

  public static final java.lang.String ISSUE_INSTANT_ATTRIB_NAME;

  public static final java.lang.String ID_ATTRIB_NAME;

  public abstract org.opensaml.common.SAMLVersion getVersion();

  public abstract void setVersion(org.opensaml.common.SAMLVersion);

  public abstract org.joda.time.DateTime getIssueInstant();

  public abstract void setIssueInstant(org.joda.time.DateTime);

  public abstract java.lang.String getID();

  public abstract void setID(java.lang.String);

  public abstract org.opensaml.saml2.core.Issuer getIssuer();

  public abstract void setIssuer(org.opensaml.saml2.core.Issuer);

  public abstract org.opensaml.saml2.core.Subject getSubject();

  public abstract void setSubject(org.opensaml.saml2.core.Subject);

  public abstract org.opensaml.saml2.core.Conditions getConditions();

  public abstract void setConditions(org.opensaml.saml2.core.Conditions);

  public abstract org.opensaml.saml2.core.Advice getAdvice();

  public abstract void setAdvice(org.opensaml.saml2.core.Advice);

  public abstract java.util.List<org.opensaml.saml2.core.Statement> getStatements();

  public abstract java.util.List<org.opensaml.saml2.core.Statement> getStatements(javax.xml.namespace.QName);

  public abstract java.util.List<org.opensaml.saml2.core.AuthnStatement> getAuthnStatements();

  public abstract java.util.List<org.opensaml.saml2.core.AuthzDecisionStatement> getAuthzDecisionStatements();

  public abstract java.util.List<org.opensaml.saml2.core.AttributeStatement> getAttributeStatements();

  static {};
    Code:
       0: new           #1                  // class javax/xml/namespace/QName
       3: dup
       4: ldc           #2                  // String urn:oasis:names:tc:SAML:2.0:assertion
       6: ldc           #3                  // String Assertion
       8: ldc           #4                  // String saml2
      10: invokespecial #5                  // Method javax/xml/namespace/QName."<init>":(Ljava/lang/String;Ljava/lang/String;Ljava/lang/String;)V
      13: putstatic     #6                  // Field DEFAULT_ELEMENT_NAME:Ljavax/xml/namespace/QName;
      16: new           #1                  // class javax/xml/namespace/QName
      19: dup
      20: ldc           #2                  // String urn:oasis:names:tc:SAML:2.0:assertion
      22: ldc           #7                  // String AssertionType
      24: ldc           #4                  // String saml2
      26: invokespecial #5                  // Method javax/xml/namespace/QName."<init>":(Ljava/lang/String;Ljava/lang/String;Ljava/lang/String;)V
      29: putstatic     #8                  // Field TYPE_NAME:Ljavax/xml/namespace/QName;
      32: return
}
