Compiled from "HttpClientExchange.java"
class io.undertow.client.http.HttpClientExchange$2 extends io.undertow.channels.DetachableStreamSourceChannel {
  final io.undertow.client.http.HttpClientExchange this$0;

  io.undertow.client.http.HttpClientExchange$2(io.undertow.client.http.HttpClientExchange, org.xnio.channels.StreamSourceChannel);
    Code:
       0: aload_0
       1: aload_1
       2: putfield      #2                  // Field this$0:Lio/undertow/client/http/HttpClientExchange;
       5: aload_0
       6: aload_2
       7: invokespecial #3                  // Method io/undertow/channels/DetachableStreamSourceChannel."<init>":(Lorg/xnio/channels/StreamSourceChannel;)V
      10: return

  protected boolean isFinished();
    Code:
       0: aload_0
       1: getfield      #2                  // Field this$0:Lio/undertow/client/http/HttpClientExchange;
       4: invokestatic  #4                  // Method io/undertow/client/http/HttpClientExchange.access$000:(Lio/undertow/client/http/HttpClientExchange;)I
       7: iconst_2
       8: invokestatic  #5                  // Method org/xnio/Bits.anyAreSet:(II)Z
      11: ireturn
}
