Compiled from "PinpointingMessageHandler.java"
class org.aspectj.bridge.context.PinpointingMessageHandler$MessageIssued extends java.lang.RuntimeException {
  private static final long serialVersionUID;

  private org.aspectj.bridge.context.PinpointingMessageHandler$MessageIssued();
    Code:
       0: aload_0
       1: invokespecial #2                  // Method java/lang/RuntimeException."<init>":()V
       4: return

  public java.lang.String getMessage();
    Code:
       0: ldc           #3                  // String message issued...
       2: areturn

  org.aspectj.bridge.context.PinpointingMessageHandler$MessageIssued(org.aspectj.bridge.context.PinpointingMessageHandler$1);
    Code:
       0: aload_0
       1: invokespecial #1                  // Method "<init>":()V
       4: return
}
