Compiled from "WebApplicationHandleProvider.java"
public class net.contextfw.web.application.internal.providers.WebApplicationHandleProvider implements com.google.inject.Provider<net.contextfw.web.application.WebApplicationHandle> {
  public net.contextfw.web.application.internal.providers.WebApplicationHandleProvider();
    Code:
       0: aload_0
       1: invokespecial #1                  // Method java/lang/Object."<init>":()V
       4: return

  public net.contextfw.web.application.WebApplicationHandle get();
    Code:
       0: invokestatic  #2                  // Method net/contextfw/web/application/internal/scope/WebApplicationScopedBeans.getCurrentInstance:()Lnet/contextfw/web/application/internal/scope/WebApplicationScopedBeans;
       3: invokevirtual #3                  // Method net/contextfw/web/application/internal/scope/WebApplicationScopedBeans.getBeans:()Ljava/util/Map;
       6: ldc_w         #4                  // class net/contextfw/web/application/WebApplicationHandle
       9: invokestatic  #5                  // Method com/google/inject/Key.get:(Ljava/lang/Class;)Lcom/google/inject/Key;
      12: invokeinterface #6,  2            // InterfaceMethod java/util/Map.get:(Ljava/lang/Object;)Ljava/lang/Object;
      17: checkcast     #4                  // class net/contextfw/web/application/WebApplicationHandle
      20: areturn

  public java.lang.Object get();
    Code:
       0: aload_0
       1: invokevirtual #7                  // Method get:()Lnet/contextfw/web/application/WebApplicationHandle;
       4: areturn
}
