Compiled from "DelegatingMethodSecurityMetadataSource.java"
public final class org.springframework.security.access.method.DelegatingMethodSecurityMetadataSource extends org.springframework.security.access.method.AbstractMethodSecurityMetadataSource {
  private static final java.util.List<org.springframework.security.access.ConfigAttribute> NULL_CONFIG_ATTRIBUTE;

  private final java.util.List<org.springframework.security.access.method.MethodSecurityMetadataSource> methodSecurityMetadataSources;

  private final java.util.Map<org.springframework.security.access.method.DelegatingMethodSecurityMetadataSource$DefaultCacheKey, java.util.Collection<org.springframework.security.access.ConfigAttribute>> attributeCache;

  public org.springframework.security.access.method.DelegatingMethodSecurityMetadataSource(java.util.List<org.springframework.security.access.method.MethodSecurityMetadataSource>);
    Code:
       0: aload_0
       1: invokespecial #1                  // Method org/springframework/security/access/method/AbstractMethodSecurityMetadataSource."<init>":()V
       4: aload_0
       5: new           #2                  // class java/util/HashMap
       8: dup
       9: invokespecial #3                  // Method java/util/HashMap."<init>":()V
      12: putfield      #4                  // Field attributeCache:Ljava/util/Map;
      15: aload_1
      16: ldc           #5                  // String MethodSecurityMetadataSources cannot be null
      18: invokestatic  #6                  // Method org/springframework/util/Assert.notNull:(Ljava/lang/Object;Ljava/lang/String;)V
      21: aload_0
      22: aload_1
      23: putfield      #7                  // Field methodSecurityMetadataSources:Ljava/util/List;
      26: return

  public java.util.Collection<org.springframework.security.access.ConfigAttribute> getAttributes(java.lang.reflect.Method, java.lang.Class<?>);
    Code:
       0: new           #8                  // class org/springframework/security/access/method/DelegatingMethodSecurityMetadataSource$DefaultCacheKey
       3: dup
       4: aload_1
       5: aload_2
       6: invokespecial #9                  // Method org/springframework/security/access/method/DelegatingMethodSecurityMetadataSource$DefaultCacheKey."<init>":(Ljava/lang/reflect/Method;Ljava/lang/Class;)V
       9: astore_3
      10: aload_0
      11: getfield      #4                  // Field attributeCache:Ljava/util/Map;
      14: dup
      15: astore        4
      17: monitorenter
      18: aload_0
      19: getfield      #4                  // Field attributeCache:Ljava/util/Map;
      22: aload_3
      23: invokeinterface #10,  2           // InterfaceMethod java/util/Map.get:(Ljava/lang/Object;)Ljava/lang/Object;
      28: checkcast     #11                 // class java/util/Collection
      31: astore        5
      33: aload         5
      35: ifnull        44
      38: aload         5
      40: aload         4
      42: monitorexit
      43: areturn
      44: aconst_null
      45: astore        6
      47: aload_0
      48: getfield      #7                  // Field methodSecurityMetadataSources:Ljava/util/List;
      51: invokeinterface #12,  1           // InterfaceMethod java/util/List.iterator:()Ljava/util/Iterator;
      56: astore        7
      58: aload         7
      60: invokeinterface #13,  1           // InterfaceMethod java/util/Iterator.hasNext:()Z
      65: ifeq          112
      68: aload         7
      70: invokeinterface #14,  1           // InterfaceMethod java/util/Iterator.next:()Ljava/lang/Object;
      75: checkcast     #15                 // class org/springframework/security/access/method/MethodSecurityMetadataSource
      78: astore        8
      80: aload         8
      82: aload_1
      83: aload_2
      84: invokeinterface #16,  3           // InterfaceMethod org/springframework/security/access/method/MethodSecurityMetadataSource.getAttributes:(Ljava/lang/reflect/Method;Ljava/lang/Class;)Ljava/util/Collection;
      89: astore        6
      91: aload         6
      93: ifnull        109
      96: aload         6
      98: invokeinterface #17,  1           // InterfaceMethod java/util/Collection.isEmpty:()Z
     103: ifne          109
     106: goto          112
     109: goto          58
     112: aload         6
     114: ifnull        127
     117: aload         6
     119: invokeinterface #17,  1           // InterfaceMethod java/util/Collection.isEmpty:()Z
     124: ifeq          148
     127: aload_0
     128: getfield      #4                  // Field attributeCache:Ljava/util/Map;
     131: aload_3
     132: getstatic     #18                 // Field NULL_CONFIG_ATTRIBUTE:Ljava/util/List;
     135: invokeinterface #19,  3           // InterfaceMethod java/util/Map.put:(Ljava/lang/Object;Ljava/lang/Object;)Ljava/lang/Object;
     140: pop
     141: getstatic     #18                 // Field NULL_CONFIG_ATTRIBUTE:Ljava/util/List;
     144: aload         4
     146: monitorexit
     147: areturn
     148: aload_0
     149: getfield      #20                 // Field logger:Lorg/apache/commons/logging/Log;
     152: invokeinterface #21,  1           // InterfaceMethod org/apache/commons/logging/Log.isDebugEnabled:()Z
     157: ifeq          198
     160: aload_0
     161: getfield      #20                 // Field logger:Lorg/apache/commons/logging/Log;
     164: new           #22                 // class java/lang/StringBuilder
     167: dup
     168: invokespecial #23                 // Method java/lang/StringBuilder."<init>":()V
     171: ldc           #24                 // String Caching method [
     173: invokevirtual #25                 // Method java/lang/StringBuilder.append:(Ljava/lang/String;)Ljava/lang/StringBuilder;
     176: aload_3
     177: invokevirtual #26                 // Method java/lang/StringBuilder.append:(Ljava/lang/Object;)Ljava/lang/StringBuilder;
     180: ldc           #27                 // String ] with attributes
     182: invokevirtual #25                 // Method java/lang/StringBuilder.append:(Ljava/lang/String;)Ljava/lang/StringBuilder;
     185: aload         6
     187: invokevirtual #26                 // Method java/lang/StringBuilder.append:(Ljava/lang/Object;)Ljava/lang/StringBuilder;
     190: invokevirtual #28                 // Method java/lang/StringBuilder.toString:()Ljava/lang/String;
     193: invokeinterface #29,  2           // InterfaceMethod org/apache/commons/logging/Log.debug:(Ljava/lang/Object;)V
     198: aload_0
     199: getfield      #4                  // Field attributeCache:Ljava/util/Map;
     202: aload_3
     203: aload         6
     205: invokeinterface #19,  3           // InterfaceMethod java/util/Map.put:(Ljava/lang/Object;Ljava/lang/Object;)Ljava/lang/Object;
     210: pop
     211: aload         6
     213: aload         4
     215: monitorexit
     216: areturn
     217: astore        9
     219: aload         4
     221: monitorexit
     222: aload         9
     224: athrow
    Exception table:
       from    to  target type
          18    43   217   any
          44   147   217   any
         148   216   217   any
         217   222   217   any

  public java.util.Collection<org.springframework.security.access.ConfigAttribute> getAllConfigAttributes();
    Code:
       0: new           #30                 // class java/util/HashSet
       3: dup
       4: invokespecial #31                 // Method java/util/HashSet."<init>":()V
       7: astore_1
       8: aload_0
       9: getfield      #7                  // Field methodSecurityMetadataSources:Ljava/util/List;
      12: invokeinterface #12,  1           // InterfaceMethod java/util/List.iterator:()Ljava/util/Iterator;
      17: astore_2
      18: aload_2
      19: invokeinterface #13,  1           // InterfaceMethod java/util/Iterator.hasNext:()Z
      24: ifeq          62
      27: aload_2
      28: invokeinterface #14,  1           // InterfaceMethod java/util/Iterator.next:()Ljava/lang/Object;
      33: checkcast     #15                 // class org/springframework/security/access/method/MethodSecurityMetadataSource
      36: astore_3
      37: aload_3
      38: invokeinterface #32,  1           // InterfaceMethod org/springframework/security/access/method/MethodSecurityMetadataSource.getAllConfigAttributes:()Ljava/util/Collection;
      43: astore        4
      45: aload         4
      47: ifnull        59
      50: aload_1
      51: aload         4
      53: invokeinterface #33,  2           // InterfaceMethod java/util/Set.addAll:(Ljava/util/Collection;)Z
      58: pop
      59: goto          18
      62: aload_1
      63: areturn

  public java.util.List<org.springframework.security.access.method.MethodSecurityMetadataSource> getMethodSecurityMetadataSources();
    Code:
       0: aload_0
       1: getfield      #7                  // Field methodSecurityMetadataSources:Ljava/util/List;
       4: areturn

  static {};
    Code:
       0: invokestatic  #34                 // Method java/util/Collections.emptyList:()Ljava/util/List;
       3: putstatic     #18                 // Field NULL_CONFIG_ATTRIBUTE:Ljava/util/List;
       6: return
}
