Compiled from "Operations.java"
public final class org.jboss.as.clustering.controller.Operations {
  private static final java.lang.String INDEX;

  private static final java.lang.String KEY;

  public static org.jboss.as.controller.PathAddress getPathAddress(org.jboss.dmr.ModelNode);
    Code:
       0: aload_0
       1: ldc           #2                  // String address
       3: invokevirtual #3                  // Method org/jboss/dmr/ModelNode.require:(Ljava/lang/String;)Lorg/jboss/dmr/ModelNode;
       6: invokestatic  #4                  // Method org/jboss/as/controller/PathAddress.pathAddress:(Lorg/jboss/dmr/ModelNode;)Lorg/jboss/as/controller/PathAddress;
       9: areturn

  public static void setPathAddress(org.jboss.dmr.ModelNode, org.jboss.as.controller.PathAddress);
    Code:
       0: aload_0
       1: ldc           #2                  // String address
       3: invokevirtual #5                  // Method org/jboss/dmr/ModelNode.get:(Ljava/lang/String;)Lorg/jboss/dmr/ModelNode;
       6: aload_1
       7: invokevirtual #6                  // Method org/jboss/as/controller/PathAddress.toModelNode:()Lorg/jboss/dmr/ModelNode;
      10: invokevirtual #7                  // Method org/jboss/dmr/ModelNode.set:(Lorg/jboss/dmr/ModelNode;)Lorg/jboss/dmr/ModelNode;
      13: pop
      14: return

  public static java.lang.String getName(org.jboss.dmr.ModelNode);
    Code:
       0: aload_0
       1: ldc           #8                  // String operation
       3: invokevirtual #3                  // Method org/jboss/dmr/ModelNode.require:(Ljava/lang/String;)Lorg/jboss/dmr/ModelNode;
       6: invokevirtual #9                  // Method org/jboss/dmr/ModelNode.asString:()Ljava/lang/String;
       9: areturn

  public static java.lang.String getAttributeName(org.jboss.dmr.ModelNode);
    Code:
       0: aload_0
       1: ldc           #10                 // String name
       3: invokevirtual #3                  // Method org/jboss/dmr/ModelNode.require:(Ljava/lang/String;)Lorg/jboss/dmr/ModelNode;
       6: invokevirtual #9                  // Method org/jboss/dmr/ModelNode.asString:()Ljava/lang/String;
       9: areturn

  public static org.jboss.dmr.ModelNode getAttributeValue(org.jboss.dmr.ModelNode);
    Code:
       0: aload_0
       1: ldc           #11                 // String value
       3: invokevirtual #12                 // Method org/jboss/dmr/ModelNode.hasDefined:(Ljava/lang/String;)Z
       6: ifeq          18
       9: aload_0
      10: ldc           #11                 // String value
      12: invokevirtual #5                  // Method org/jboss/dmr/ModelNode.get:(Ljava/lang/String;)Lorg/jboss/dmr/ModelNode;
      15: goto          25
      18: new           #13                 // class org/jboss/dmr/ModelNode
      21: dup
      22: invokespecial #14                 // Method org/jboss/dmr/ModelNode."<init>":()V
      25: areturn

  public static org.jboss.dmr.ModelNode createCompositeOperation(java.util.List<org.jboss.dmr.ModelNode>);
    Code:
       0: ldc           #15                 // String composite
       2: getstatic     #16                 // Field org/jboss/as/controller/PathAddress.EMPTY_ADDRESS:Lorg/jboss/as/controller/PathAddress;
       5: invokestatic  #17                 // Method org/jboss/as/controller/operations/common/Util.createOperation:(Ljava/lang/String;Lorg/jboss/as/controller/PathAddress;)Lorg/jboss/dmr/ModelNode;
       8: astore_1
       9: aload_1
      10: ldc           #18                 // String steps
      12: invokevirtual #5                  // Method org/jboss/dmr/ModelNode.get:(Ljava/lang/String;)Lorg/jboss/dmr/ModelNode;
      15: astore_2
      16: aload_0
      17: invokeinterface #19,  1           // InterfaceMethod java/util/List.iterator:()Ljava/util/Iterator;
      22: astore_3
      23: aload_3
      24: invokeinterface #20,  1           // InterfaceMethod java/util/Iterator.hasNext:()Z
      29: ifeq          53
      32: aload_3
      33: invokeinterface #21,  1           // InterfaceMethod java/util/Iterator.next:()Ljava/lang/Object;
      38: checkcast     #13                 // class org/jboss/dmr/ModelNode
      41: astore        4
      43: aload_2
      44: aload         4
      46: invokevirtual #22                 // Method org/jboss/dmr/ModelNode.add:(Lorg/jboss/dmr/ModelNode;)Lorg/jboss/dmr/ModelNode;
      49: pop
      50: goto          23
      53: aload_1
      54: areturn

  public static org.jboss.dmr.ModelNode createCompositeOperation(org.jboss.dmr.ModelNode...);
    Code:
       0: aload_0
       1: invokestatic  #23                 // Method java/util/Arrays.asList:([Ljava/lang/Object;)Ljava/util/List;
       4: invokestatic  #24                 // Method createCompositeOperation:(Ljava/util/List;)Lorg/jboss/dmr/ModelNode;
       7: areturn

  public static org.jboss.dmr.ModelNode createAddOperation(org.jboss.as.controller.PathAddress, java.util.Map<org.jboss.as.clustering.controller.Attribute, org.jboss.dmr.ModelNode>);
    Code:
       0: aload_0
       1: invokestatic  #25                 // Method org/jboss/as/controller/operations/common/Util.createAddOperation:(Lorg/jboss/as/controller/PathAddress;)Lorg/jboss/dmr/ModelNode;
       4: astore_2
       5: aload_1
       6: invokeinterface #26,  1           // InterfaceMethod java/util/Map.entrySet:()Ljava/util/Set;
      11: invokeinterface #27,  1           // InterfaceMethod java/util/Set.iterator:()Ljava/util/Iterator;
      16: astore_3
      17: aload_3
      18: invokeinterface #20,  1           // InterfaceMethod java/util/Iterator.hasNext:()Z
      23: ifeq          79
      26: aload_3
      27: invokeinterface #21,  1           // InterfaceMethod java/util/Iterator.next:()Ljava/lang/Object;
      32: checkcast     #28                 // class java/util/Map$Entry
      35: astore        4
      37: aload_2
      38: aload         4
      40: invokeinterface #29,  1           // InterfaceMethod java/util/Map$Entry.getKey:()Ljava/lang/Object;
      45: checkcast     #30                 // class org/jboss/as/clustering/controller/Attribute
      48: invokeinterface #31,  1           // InterfaceMethod org/jboss/as/clustering/controller/Attribute.getDefinition:()Ljava/lang/Object;
      53: checkcast     #32                 // class org/jboss/as/controller/AttributeDefinition
      56: invokevirtual #33                 // Method org/jboss/as/controller/AttributeDefinition.getName:()Ljava/lang/String;
      59: invokevirtual #5                  // Method org/jboss/dmr/ModelNode.get:(Ljava/lang/String;)Lorg/jboss/dmr/ModelNode;
      62: aload         4
      64: invokeinterface #34,  1           // InterfaceMethod java/util/Map$Entry.getValue:()Ljava/lang/Object;
      69: checkcast     #13                 // class org/jboss/dmr/ModelNode
      72: invokevirtual #7                  // Method org/jboss/dmr/ModelNode.set:(Lorg/jboss/dmr/ModelNode;)Lorg/jboss/dmr/ModelNode;
      75: pop
      76: goto          17
      79: aload_2
      80: areturn

  public static org.jboss.dmr.ModelNode createAddOperation(org.jboss.as.controller.PathAddress, int);
    Code:
       0: aload_0
       1: iload_1
       2: invokestatic  #35                 // Method java/util/Collections.emptyMap:()Ljava/util/Map;
       5: invokestatic  #36                 // Method createAddOperation:(Lorg/jboss/as/controller/PathAddress;ILjava/util/Map;)Lorg/jboss/dmr/ModelNode;
       8: areturn

  public static org.jboss.dmr.ModelNode createAddOperation(org.jboss.as.controller.PathAddress, int, java.util.Map<org.jboss.as.clustering.controller.Attribute, org.jboss.dmr.ModelNode>);
    Code:
       0: aload_0
       1: invokestatic  #25                 // Method org/jboss/as/controller/operations/common/Util.createAddOperation:(Lorg/jboss/as/controller/PathAddress;)Lorg/jboss/dmr/ModelNode;
       4: astore_3
       5: aload_3
       6: ldc           #37                 // String add-index
       8: invokevirtual #5                  // Method org/jboss/dmr/ModelNode.get:(Ljava/lang/String;)Lorg/jboss/dmr/ModelNode;
      11: iload_1
      12: invokevirtual #38                 // Method org/jboss/dmr/ModelNode.set:(I)Lorg/jboss/dmr/ModelNode;
      15: pop
      16: aload_2
      17: invokeinterface #26,  1           // InterfaceMethod java/util/Map.entrySet:()Ljava/util/Set;
      22: invokeinterface #27,  1           // InterfaceMethod java/util/Set.iterator:()Ljava/util/Iterator;
      27: astore        4
      29: aload         4
      31: invokeinterface #20,  1           // InterfaceMethod java/util/Iterator.hasNext:()Z
      36: ifeq          93
      39: aload         4
      41: invokeinterface #21,  1           // InterfaceMethod java/util/Iterator.next:()Ljava/lang/Object;
      46: checkcast     #28                 // class java/util/Map$Entry
      49: astore        5
      51: aload_3
      52: aload         5
      54: invokeinterface #29,  1           // InterfaceMethod java/util/Map$Entry.getKey:()Ljava/lang/Object;
      59: checkcast     #30                 // class org/jboss/as/clustering/controller/Attribute
      62: invokeinterface #31,  1           // InterfaceMethod org/jboss/as/clustering/controller/Attribute.getDefinition:()Ljava/lang/Object;
      67: checkcast     #32                 // class org/jboss/as/controller/AttributeDefinition
      70: invokevirtual #33                 // Method org/jboss/as/controller/AttributeDefinition.getName:()Ljava/lang/String;
      73: invokevirtual #5                  // Method org/jboss/dmr/ModelNode.get:(Ljava/lang/String;)Lorg/jboss/dmr/ModelNode;
      76: aload         5
      78: invokeinterface #34,  1           // InterfaceMethod java/util/Map$Entry.getValue:()Ljava/lang/Object;
      83: checkcast     #13                 // class org/jboss/dmr/ModelNode
      86: invokevirtual #7                  // Method org/jboss/dmr/ModelNode.set:(Lorg/jboss/dmr/ModelNode;)Lorg/jboss/dmr/ModelNode;
      89: pop
      90: goto          29
      93: aload_3
      94: areturn

  public static org.jboss.dmr.ModelNode createReadAttributeOperation(org.jboss.as.controller.PathAddress, org.jboss.as.clustering.controller.Attribute);
    Code:
       0: ldc           #39                 // String read-attribute
       2: aload_0
       3: aload_1
       4: invokestatic  #40                 // Method createAttributeOperation:(Ljava/lang/String;Lorg/jboss/as/controller/PathAddress;Lorg/jboss/as/clustering/controller/Attribute;)Lorg/jboss/dmr/ModelNode;
       7: areturn

  public static org.jboss.dmr.ModelNode createWriteAttributeOperation(org.jboss.as.controller.PathAddress, org.jboss.as.clustering.controller.Attribute, org.jboss.dmr.ModelNode);
    Code:
       0: ldc           #41                 // String write-attribute
       2: aload_0
       3: aload_1
       4: invokestatic  #40                 // Method createAttributeOperation:(Ljava/lang/String;Lorg/jboss/as/controller/PathAddress;Lorg/jboss/as/clustering/controller/Attribute;)Lorg/jboss/dmr/ModelNode;
       7: astore_3
       8: aload_3
       9: ldc           #11                 // String value
      11: invokevirtual #5                  // Method org/jboss/dmr/ModelNode.get:(Ljava/lang/String;)Lorg/jboss/dmr/ModelNode;
      14: aload_2
      15: invokevirtual #7                  // Method org/jboss/dmr/ModelNode.set:(Lorg/jboss/dmr/ModelNode;)Lorg/jboss/dmr/ModelNode;
      18: pop
      19: aload_3
      20: areturn

  public static org.jboss.dmr.ModelNode createUndefineAttributeOperation(org.jboss.as.controller.PathAddress, org.jboss.as.clustering.controller.Attribute);
    Code:
       0: ldc           #42                 // String undefine-attribute
       2: aload_0
       3: aload_1
       4: invokestatic  #40                 // Method createAttributeOperation:(Ljava/lang/String;Lorg/jboss/as/controller/PathAddress;Lorg/jboss/as/clustering/controller/Attribute;)Lorg/jboss/dmr/ModelNode;
       7: areturn

  private static org.jboss.dmr.ModelNode createAttributeOperation(java.lang.String, org.jboss.as.controller.PathAddress, org.jboss.as.clustering.controller.Attribute);
    Code:
       0: aload_0
       1: aload_1
       2: invokestatic  #17                 // Method org/jboss/as/controller/operations/common/Util.createOperation:(Ljava/lang/String;Lorg/jboss/as/controller/PathAddress;)Lorg/jboss/dmr/ModelNode;
       5: astore_3
       6: aload_3
       7: ldc           #10                 // String name
       9: invokevirtual #5                  // Method org/jboss/dmr/ModelNode.get:(Ljava/lang/String;)Lorg/jboss/dmr/ModelNode;
      12: aload_2
      13: invokeinterface #31,  1           // InterfaceMethod org/jboss/as/clustering/controller/Attribute.getDefinition:()Ljava/lang/Object;
      18: checkcast     #32                 // class org/jboss/as/controller/AttributeDefinition
      21: invokevirtual #33                 // Method org/jboss/as/controller/AttributeDefinition.getName:()Ljava/lang/String;
      24: invokevirtual #43                 // Method org/jboss/dmr/ModelNode.set:(Ljava/lang/String;)Lorg/jboss/dmr/ModelNode;
      27: pop
      28: aload_3
      29: areturn

  public static org.jboss.dmr.ModelNode createDescribeOperation(org.jboss.as.controller.PathAddress);
    Code:
       0: ldc           #44                 // String describe
       2: aload_0
       3: invokestatic  #17                 // Method org/jboss/as/controller/operations/common/Util.createOperation:(Ljava/lang/String;Lorg/jboss/as/controller/PathAddress;)Lorg/jboss/dmr/ModelNode;
       6: areturn

  public static org.jboss.dmr.ModelNode createReadResourceOperation(org.jboss.as.controller.PathAddress);
    Code:
       0: ldc           #45                 // String read-resource
       2: aload_0
       3: invokestatic  #17                 // Method org/jboss/as/controller/operations/common/Util.createOperation:(Ljava/lang/String;Lorg/jboss/as/controller/PathAddress;)Lorg/jboss/dmr/ModelNode;
       6: areturn

  public static org.jboss.dmr.ModelNode createListAddOperation(org.jboss.as.controller.PathAddress, org.jboss.as.clustering.controller.Attribute, java.lang.String);
    Code:
       0: getstatic     #46                 // Field org/jboss/as/controller/operations/global/ListOperations.LIST_ADD_DEFINITION:Lorg/jboss/as/controller/OperationDefinition;
       3: aload_0
       4: aload_1
       5: aload_2
       6: invokestatic  #47                 // Method createListElementOperation:(Lorg/jboss/as/controller/OperationDefinition;Lorg/jboss/as/controller/PathAddress;Lorg/jboss/as/clustering/controller/Attribute;Ljava/lang/String;)Lorg/jboss/dmr/ModelNode;
       9: areturn

  public static org.jboss.dmr.ModelNode createListRemoveOperation(org.jboss.as.controller.PathAddress, org.jboss.as.clustering.controller.Attribute, java.lang.String);
    Code:
       0: getstatic     #48                 // Field org/jboss/as/controller/operations/global/ListOperations.LIST_REMOVE_DEFINITION:Lorg/jboss/as/controller/OperationDefinition;
       3: aload_0
       4: aload_1
       5: aload_2
       6: invokestatic  #47                 // Method createListElementOperation:(Lorg/jboss/as/controller/OperationDefinition;Lorg/jboss/as/controller/PathAddress;Lorg/jboss/as/clustering/controller/Attribute;Ljava/lang/String;)Lorg/jboss/dmr/ModelNode;
       9: areturn

  public static org.jboss.dmr.ModelNode createListRemoveOperation(org.jboss.as.controller.PathAddress, org.jboss.as.clustering.controller.Attribute, int);
    Code:
       0: getstatic     #48                 // Field org/jboss/as/controller/operations/global/ListOperations.LIST_REMOVE_DEFINITION:Lorg/jboss/as/controller/OperationDefinition;
       3: aload_0
       4: aload_1
       5: iload_2
       6: invokestatic  #49                 // Method createListElementOperation:(Lorg/jboss/as/controller/OperationDefinition;Lorg/jboss/as/controller/PathAddress;Lorg/jboss/as/clustering/controller/Attribute;I)Lorg/jboss/dmr/ModelNode;
       9: areturn

  public static org.jboss.dmr.ModelNode createListGetOperation(org.jboss.as.controller.PathAddress, org.jboss.as.clustering.controller.Attribute, int);
    Code:
       0: getstatic     #50                 // Field org/jboss/as/controller/operations/global/ListOperations.LIST_GET_DEFINITION:Lorg/jboss/as/controller/OperationDefinition;
       3: aload_0
       4: aload_1
       5: iload_2
       6: invokestatic  #49                 // Method createListElementOperation:(Lorg/jboss/as/controller/OperationDefinition;Lorg/jboss/as/controller/PathAddress;Lorg/jboss/as/clustering/controller/Attribute;I)Lorg/jboss/dmr/ModelNode;
       9: areturn

  private static org.jboss.dmr.ModelNode createListElementOperation(org.jboss.as.controller.OperationDefinition, org.jboss.as.controller.PathAddress, org.jboss.as.clustering.controller.Attribute, java.lang.String);
    Code:
       0: aload_0
       1: invokevirtual #51                 // Method org/jboss/as/controller/OperationDefinition.getName:()Ljava/lang/String;
       4: aload_1
       5: aload_2
       6: invokestatic  #40                 // Method createAttributeOperation:(Ljava/lang/String;Lorg/jboss/as/controller/PathAddress;Lorg/jboss/as/clustering/controller/Attribute;)Lorg/jboss/dmr/ModelNode;
       9: astore        4
      11: aload         4
      13: ldc           #11                 // String value
      15: invokevirtual #5                  // Method org/jboss/dmr/ModelNode.get:(Ljava/lang/String;)Lorg/jboss/dmr/ModelNode;
      18: aload_3
      19: invokevirtual #43                 // Method org/jboss/dmr/ModelNode.set:(Ljava/lang/String;)Lorg/jboss/dmr/ModelNode;
      22: pop
      23: aload         4
      25: areturn

  private static org.jboss.dmr.ModelNode createListElementOperation(org.jboss.as.controller.OperationDefinition, org.jboss.as.controller.PathAddress, org.jboss.as.clustering.controller.Attribute, int);
    Code:
       0: aload_0
       1: invokevirtual #51                 // Method org/jboss/as/controller/OperationDefinition.getName:()Ljava/lang/String;
       4: aload_1
       5: aload_2
       6: invokestatic  #40                 // Method createAttributeOperation:(Ljava/lang/String;Lorg/jboss/as/controller/PathAddress;Lorg/jboss/as/clustering/controller/Attribute;)Lorg/jboss/dmr/ModelNode;
       9: astore        4
      11: aload         4
      13: ldc           #53                 // String index
      15: invokevirtual #5                  // Method org/jboss/dmr/ModelNode.get:(Ljava/lang/String;)Lorg/jboss/dmr/ModelNode;
      18: new           #13                 // class org/jboss/dmr/ModelNode
      21: dup
      22: iload_3
      23: invokespecial #54                 // Method org/jboss/dmr/ModelNode."<init>":(I)V
      26: invokevirtual #7                  // Method org/jboss/dmr/ModelNode.set:(Lorg/jboss/dmr/ModelNode;)Lorg/jboss/dmr/ModelNode;
      29: pop
      30: aload         4
      32: areturn

  public static org.jboss.dmr.ModelNode createMapGetOperation(org.jboss.as.controller.PathAddress, org.jboss.as.clustering.controller.Attribute, java.lang.String);
    Code:
       0: getstatic     #55                 // Field org/jboss/as/controller/operations/global/MapOperations.MAP_GET_DEFINITION:Lorg/jboss/as/controller/OperationDefinition;
       3: aload_0
       4: aload_1
       5: aload_2
       6: invokestatic  #56                 // Method createMapEntryOperation:(Lorg/jboss/as/controller/OperationDefinition;Lorg/jboss/as/controller/PathAddress;Lorg/jboss/as/clustering/controller/Attribute;Ljava/lang/String;)Lorg/jboss/dmr/ModelNode;
       9: areturn

  public static org.jboss.dmr.ModelNode createMapPutOperation(org.jboss.as.controller.PathAddress, org.jboss.as.clustering.controller.Attribute, java.lang.String, java.lang.String);
    Code:
       0: getstatic     #57                 // Field org/jboss/as/controller/operations/global/MapOperations.MAP_PUT_DEFINITION:Lorg/jboss/as/controller/OperationDefinition;
       3: aload_0
       4: aload_1
       5: aload_2
       6: invokestatic  #56                 // Method createMapEntryOperation:(Lorg/jboss/as/controller/OperationDefinition;Lorg/jboss/as/controller/PathAddress;Lorg/jboss/as/clustering/controller/Attribute;Ljava/lang/String;)Lorg/jboss/dmr/ModelNode;
       9: astore        4
      11: aload         4
      13: ldc           #11                 // String value
      15: invokevirtual #5                  // Method org/jboss/dmr/ModelNode.get:(Ljava/lang/String;)Lorg/jboss/dmr/ModelNode;
      18: aload_3
      19: invokevirtual #43                 // Method org/jboss/dmr/ModelNode.set:(Ljava/lang/String;)Lorg/jboss/dmr/ModelNode;
      22: pop
      23: aload         4
      25: areturn

  public static org.jboss.dmr.ModelNode createMapRemoveOperation(org.jboss.as.controller.PathAddress, org.jboss.as.clustering.controller.Attribute, java.lang.String);
    Code:
       0: getstatic     #58                 // Field org/jboss/as/controller/operations/global/MapOperations.MAP_REMOVE_DEFINITION:Lorg/jboss/as/controller/OperationDefinition;
       3: aload_0
       4: aload_1
       5: aload_2
       6: invokestatic  #56                 // Method createMapEntryOperation:(Lorg/jboss/as/controller/OperationDefinition;Lorg/jboss/as/controller/PathAddress;Lorg/jboss/as/clustering/controller/Attribute;Ljava/lang/String;)Lorg/jboss/dmr/ModelNode;
       9: areturn

  public static org.jboss.dmr.ModelNode createMapClearOperation(org.jboss.as.controller.PathAddress, org.jboss.as.clustering.controller.Attribute);
    Code:
       0: getstatic     #59                 // Field org/jboss/as/controller/operations/global/MapOperations.MAP_CLEAR_DEFINITION:Lorg/jboss/as/controller/OperationDefinition;
       3: aload_0
       4: invokestatic  #60                 // Method org/jboss/as/controller/operations/common/Util.createOperation:(Lorg/jboss/as/controller/OperationDefinition;Lorg/jboss/as/controller/PathAddress;)Lorg/jboss/dmr/ModelNode;
       7: astore_2
       8: aload_2
       9: ldc           #10                 // String name
      11: invokevirtual #5                  // Method org/jboss/dmr/ModelNode.get:(Ljava/lang/String;)Lorg/jboss/dmr/ModelNode;
      14: aload_1
      15: invokeinterface #31,  1           // InterfaceMethod org/jboss/as/clustering/controller/Attribute.getDefinition:()Ljava/lang/Object;
      20: checkcast     #32                 // class org/jboss/as/controller/AttributeDefinition
      23: invokevirtual #33                 // Method org/jboss/as/controller/AttributeDefinition.getName:()Ljava/lang/String;
      26: invokevirtual #43                 // Method org/jboss/dmr/ModelNode.set:(Ljava/lang/String;)Lorg/jboss/dmr/ModelNode;
      29: pop
      30: aload_2
      31: areturn

  private static org.jboss.dmr.ModelNode createMapEntryOperation(org.jboss.as.controller.OperationDefinition, org.jboss.as.controller.PathAddress, org.jboss.as.clustering.controller.Attribute, java.lang.String);
    Code:
       0: aload_0
       1: invokevirtual #51                 // Method org/jboss/as/controller/OperationDefinition.getName:()Ljava/lang/String;
       4: aload_1
       5: aload_2
       6: invokestatic  #40                 // Method createAttributeOperation:(Ljava/lang/String;Lorg/jboss/as/controller/PathAddress;Lorg/jboss/as/clustering/controller/Attribute;)Lorg/jboss/dmr/ModelNode;
       9: astore        4
      11: aload         4
      13: ldc           #61                 // String key
      15: invokevirtual #5                  // Method org/jboss/dmr/ModelNode.get:(Ljava/lang/String;)Lorg/jboss/dmr/ModelNode;
      18: aload_3
      19: invokevirtual #43                 // Method org/jboss/dmr/ModelNode.set:(Ljava/lang/String;)Lorg/jboss/dmr/ModelNode;
      22: pop
      23: aload         4
      25: areturn

  public static java.util.Set<java.lang.String> getAllWriteAttributeOperationNames();
    Code:
       0: new           #62                 // class java/util/HashSet
       3: dup
       4: invokespecial #63                 // Method java/util/HashSet."<init>":()V
       7: astore_0
       8: aload_0
       9: getstatic     #64                 // Field org/jboss/as/controller/operations/global/MapOperations.MAP_OPERATION_NAMES:Ljava/util/Set;
      12: invokeinterface #65,  2           // InterfaceMethod java/util/Set.addAll:(Ljava/util/Collection;)Z
      17: pop
      18: aload_0
      19: getstatic     #55                 // Field org/jboss/as/controller/operations/global/MapOperations.MAP_GET_DEFINITION:Lorg/jboss/as/controller/OperationDefinition;
      22: invokevirtual #51                 // Method org/jboss/as/controller/OperationDefinition.getName:()Ljava/lang/String;
      25: invokeinterface #66,  2           // InterfaceMethod java/util/Set.remove:(Ljava/lang/Object;)Z
      30: pop
      31: aload_0
      32: ldc           #41                 // String write-attribute
      34: invokeinterface #67,  2           // InterfaceMethod java/util/Set.add:(Ljava/lang/Object;)Z
      39: pop
      40: aload_0
      41: ldc           #42                 // String undefine-attribute
      43: invokeinterface #67,  2           // InterfaceMethod java/util/Set.add:(Ljava/lang/Object;)Z
      48: pop
      49: aload_0
      50: areturn

  private org.jboss.as.clustering.controller.Operations();
    Code:
       0: aload_0
       1: invokespecial #68                 // Method java/lang/Object."<init>":()V
       4: return
}
