Compiled from "SimpleResourceServiceHandler.java"
public class org.jboss.as.clustering.controller.SimpleResourceServiceHandler<T> implements org.jboss.as.clustering.controller.ResourceServiceHandler {
  private final org.jboss.as.clustering.controller.ResourceServiceBuilderFactory<T> builderFactory;

  public org.jboss.as.clustering.controller.SimpleResourceServiceHandler(org.jboss.as.clustering.controller.ResourceServiceBuilderFactory<T>);
    Code:
       0: aload_0
       1: invokespecial #1                  // Method java/lang/Object."<init>":()V
       4: aload_0
       5: aload_1
       6: putfield      #2                  // Field builderFactory:Lorg/jboss/as/clustering/controller/ResourceServiceBuilderFactory;
       9: return

  public void installServices(org.jboss.as.controller.OperationContext, org.jboss.dmr.ModelNode) throws org.jboss.as.controller.OperationFailedException;
    Code:
       0: aload_0
       1: getfield      #2                  // Field builderFactory:Lorg/jboss/as/clustering/controller/ResourceServiceBuilderFactory;
       4: aload_1
       5: invokeinterface #3,  1            // InterfaceMethod org/jboss/as/controller/OperationContext.getCurrentAddress:()Lorg/jboss/as/controller/PathAddress;
      10: invokeinterface #4,  2            // InterfaceMethod org/jboss/as/clustering/controller/ResourceServiceBuilderFactory.createBuilder:(Lorg/jboss/as/controller/PathAddress;)Lorg/jboss/as/clustering/controller/ResourceServiceBuilder;
      15: aload_1
      16: aload_2
      17: invokeinterface #5,  3            // InterfaceMethod org/jboss/as/clustering/controller/ResourceServiceBuilder.configure:(Lorg/jboss/as/controller/OperationContext;Lorg/jboss/dmr/ModelNode;)Lorg/wildfly/clustering/service/Builder;
      22: aload_1
      23: invokeinterface #6,  1            // InterfaceMethod org/jboss/as/controller/OperationContext.getServiceTarget:()Lorg/jboss/msc/service/ServiceTarget;
      28: invokeinterface #7,  2            // InterfaceMethod org/wildfly/clustering/service/Builder.build:(Lorg/jboss/msc/service/ServiceTarget;)Lorg/jboss/msc/service/ServiceBuilder;
      33: invokeinterface #8,  1            // InterfaceMethod org/jboss/msc/service/ServiceBuilder.install:()Lorg/jboss/msc/service/ServiceController;
      38: pop
      39: return

  public void removeServices(org.jboss.as.controller.OperationContext, org.jboss.dmr.ModelNode) throws org.jboss.as.controller.OperationFailedException;
    Code:
       0: aload_1
       1: aload_0
       2: getfield      #2                  // Field builderFactory:Lorg/jboss/as/clustering/controller/ResourceServiceBuilderFactory;
       5: aload_1
       6: invokeinterface #3,  1            // InterfaceMethod org/jboss/as/controller/OperationContext.getCurrentAddress:()Lorg/jboss/as/controller/PathAddress;
      11: invokeinterface #4,  2            // InterfaceMethod org/jboss/as/clustering/controller/ResourceServiceBuilderFactory.createBuilder:(Lorg/jboss/as/controller/PathAddress;)Lorg/jboss/as/clustering/controller/ResourceServiceBuilder;
      16: invokeinterface #9,  1            // InterfaceMethod org/jboss/as/clustering/controller/ResourceServiceBuilder.getServiceName:()Lorg/jboss/msc/service/ServiceName;
      21: invokeinterface #10,  2           // InterfaceMethod org/jboss/as/controller/OperationContext.removeService:(Lorg/jboss/msc/service/ServiceName;)Lorg/jboss/msc/service/ServiceController;
      26: pop
      27: return
}
