Compiled from "KQueueRecvByteAllocatorHandle.java"
final class io.netty.channel.kqueue.KQueueRecvByteAllocatorHandle implements io.netty.channel.RecvByteBufAllocator$ExtendedHandle {
  private final io.netty.channel.RecvByteBufAllocator$ExtendedHandle delegate;

  private final io.netty.util.UncheckedBooleanSupplier defaultMaybeMoreDataSupplier;

  private boolean overrideGuess;

  private boolean readEOF;

  private long numberBytesPending;

  io.netty.channel.kqueue.KQueueRecvByteAllocatorHandle(io.netty.channel.RecvByteBufAllocator$ExtendedHandle);
    Code:
       0: aload_0
       1: invokespecial #1                  // Method java/lang/Object."<init>":()V
       4: aload_0
       5: new           #2                  // class io/netty/channel/kqueue/KQueueRecvByteAllocatorHandle$1
       8: dup
       9: aload_0
      10: invokespecial #3                  // Method io/netty/channel/kqueue/KQueueRecvByteAllocatorHandle$1."<init>":(Lio/netty/channel/kqueue/KQueueRecvByteAllocatorHandle;)V
      13: putfield      #4                  // Field defaultMaybeMoreDataSupplier:Lio/netty/util/UncheckedBooleanSupplier;
      16: aload_0
      17: aload_1
      18: ldc           #5                  // String handle
      20: invokestatic  #6                  // Method io/netty/util/internal/ObjectUtil.checkNotNull:(Ljava/lang/Object;Ljava/lang/String;)Ljava/lang/Object;
      23: checkcast     #7                  // class io/netty/channel/RecvByteBufAllocator$ExtendedHandle
      26: putfield      #8                  // Field delegate:Lio/netty/channel/RecvByteBufAllocator$ExtendedHandle;
      29: return

  public int guess();
    Code:
       0: aload_0
       1: getfield      #9                  // Field overrideGuess:Z
       4: ifeq          14
       7: aload_0
       8: invokespecial #10                 // Method guess0:()I
      11: goto          23
      14: aload_0
      15: getfield      #8                  // Field delegate:Lio/netty/channel/RecvByteBufAllocator$ExtendedHandle;
      18: invokeinterface #11,  1           // InterfaceMethod io/netty/channel/RecvByteBufAllocator$ExtendedHandle.guess:()I
      23: ireturn

  public void reset(io.netty.channel.ChannelConfig);
    Code:
       0: aload_0
       1: aload_1
       2: checkcast     #12                 // class io/netty/channel/kqueue/KQueueChannelConfig
       5: invokevirtual #13                 // Method io/netty/channel/kqueue/KQueueChannelConfig.getRcvAllocTransportProvidesGuess:()Z
       8: putfield      #9                  // Field overrideGuess:Z
      11: aload_0
      12: getfield      #8                  // Field delegate:Lio/netty/channel/RecvByteBufAllocator$ExtendedHandle;
      15: aload_1
      16: invokeinterface #14,  2           // InterfaceMethod io/netty/channel/RecvByteBufAllocator$ExtendedHandle.reset:(Lio/netty/channel/ChannelConfig;)V
      21: return

  public void incMessagesRead(int);
    Code:
       0: aload_0
       1: getfield      #8                  // Field delegate:Lio/netty/channel/RecvByteBufAllocator$ExtendedHandle;
       4: iload_1
       5: invokeinterface #15,  2           // InterfaceMethod io/netty/channel/RecvByteBufAllocator$ExtendedHandle.incMessagesRead:(I)V
      10: return

  public io.netty.buffer.ByteBuf allocate(io.netty.buffer.ByteBufAllocator);
    Code:
       0: aload_0
       1: getfield      #9                  // Field overrideGuess:Z
       4: ifeq          20
       7: aload_1
       8: aload_0
       9: invokespecial #10                 // Method guess0:()I
      12: invokeinterface #16,  2           // InterfaceMethod io/netty/buffer/ByteBufAllocator.ioBuffer:(I)Lio/netty/buffer/ByteBuf;
      17: goto          30
      20: aload_0
      21: getfield      #8                  // Field delegate:Lio/netty/channel/RecvByteBufAllocator$ExtendedHandle;
      24: aload_1
      25: invokeinterface #17,  2           // InterfaceMethod io/netty/channel/RecvByteBufAllocator$ExtendedHandle.allocate:(Lio/netty/buffer/ByteBufAllocator;)Lio/netty/buffer/ByteBuf;
      30: areturn

  public void lastBytesRead(int);
    Code:
       0: aload_0
       1: iload_1
       2: ifge          9
       5: lconst_0
       6: goto          20
       9: lconst_0
      10: aload_0
      11: getfield      #18                 // Field numberBytesPending:J
      14: iload_1
      15: i2l
      16: lsub
      17: invokestatic  #19                 // Method java/lang/Math.max:(JJ)J
      20: putfield      #18                 // Field numberBytesPending:J
      23: aload_0
      24: getfield      #8                  // Field delegate:Lio/netty/channel/RecvByteBufAllocator$ExtendedHandle;
      27: iload_1
      28: invokeinterface #20,  2           // InterfaceMethod io/netty/channel/RecvByteBufAllocator$ExtendedHandle.lastBytesRead:(I)V
      33: return

  public int lastBytesRead();
    Code:
       0: aload_0
       1: getfield      #8                  // Field delegate:Lio/netty/channel/RecvByteBufAllocator$ExtendedHandle;
       4: invokeinterface #21,  1           // InterfaceMethod io/netty/channel/RecvByteBufAllocator$ExtendedHandle.lastBytesRead:()I
       9: ireturn

  public void attemptedBytesRead(int);
    Code:
       0: aload_0
       1: getfield      #8                  // Field delegate:Lio/netty/channel/RecvByteBufAllocator$ExtendedHandle;
       4: iload_1
       5: invokeinterface #22,  2           // InterfaceMethod io/netty/channel/RecvByteBufAllocator$ExtendedHandle.attemptedBytesRead:(I)V
      10: return

  public int attemptedBytesRead();
    Code:
       0: aload_0
       1: getfield      #8                  // Field delegate:Lio/netty/channel/RecvByteBufAllocator$ExtendedHandle;
       4: invokeinterface #23,  1           // InterfaceMethod io/netty/channel/RecvByteBufAllocator$ExtendedHandle.attemptedBytesRead:()I
       9: ireturn

  public void readComplete();
    Code:
       0: aload_0
       1: getfield      #8                  // Field delegate:Lio/netty/channel/RecvByteBufAllocator$ExtendedHandle;
       4: invokeinterface #24,  1           // InterfaceMethod io/netty/channel/RecvByteBufAllocator$ExtendedHandle.readComplete:()V
       9: return

  public boolean continueReading(io.netty.util.UncheckedBooleanSupplier);
    Code:
       0: aload_0
       1: getfield      #8                  // Field delegate:Lio/netty/channel/RecvByteBufAllocator$ExtendedHandle;
       4: aload_1
       5: invokeinterface #25,  2           // InterfaceMethod io/netty/channel/RecvByteBufAllocator$ExtendedHandle.continueReading:(Lio/netty/util/UncheckedBooleanSupplier;)Z
      10: ireturn

  public boolean continueReading();
    Code:
       0: aload_0
       1: getfield      #8                  // Field delegate:Lio/netty/channel/RecvByteBufAllocator$ExtendedHandle;
       4: aload_0
       5: getfield      #4                  // Field defaultMaybeMoreDataSupplier:Lio/netty/util/UncheckedBooleanSupplier;
       8: invokeinterface #25,  2           // InterfaceMethod io/netty/channel/RecvByteBufAllocator$ExtendedHandle.continueReading:(Lio/netty/util/UncheckedBooleanSupplier;)Z
      13: ireturn

  void readEOF();
    Code:
       0: aload_0
       1: iconst_1
       2: putfield      #26                 // Field readEOF:Z
       5: return

  void numberBytesPending(long);
    Code:
       0: aload_0
       1: lload_1
       2: putfield      #18                 // Field numberBytesPending:J
       5: return

  boolean maybeMoreDataToRead();
    Code:
       0: aload_0
       1: getfield      #18                 // Field numberBytesPending:J
       4: lconst_0
       5: lcmp
       6: ifne          16
       9: aload_0
      10: getfield      #26                 // Field readEOF:Z
      13: ifeq          20
      16: iconst_1
      17: goto          21
      20: iconst_0
      21: ireturn

  private int guess0();
    Code:
       0: aload_0
       1: getfield      #18                 // Field numberBytesPending:J
       4: ldc2_w        #28                 // long 2147483647l
       7: invokestatic  #30                 // Method java/lang/Math.min:(JJ)J
      10: l2i
      11: ireturn
}
