Compiled from "CarbonStuckThreadDetectionValve.java"
public class org.wso2.carbon.tomcat.ext.valves.CarbonStuckThreadDetectionValve extends org.apache.catalina.valves.ValveBase {
  private static final org.apache.commons.logging.Log log;

  private static final org.apache.tomcat.util.res.StringManager sm;

  private static final java.lang.String CORRELATION_ID_MDC;

  private final java.util.concurrent.atomic.AtomicInteger stuckCount;

  private int threshold;

  private java.util.concurrent.ConcurrentHashMap<java.lang.Long, org.wso2.carbon.tomcat.ext.valves.CarbonStuckThreadDetectionValve$MonitoredThread> activeThreads;

  public org.wso2.carbon.tomcat.ext.valves.CarbonStuckThreadDetectionValve();
    Code:
       0: aload_0
       1: iconst_1
       2: invokespecial #1                  // Method org/apache/catalina/valves/ValveBase."<init>":(Z)V
       5: aload_0
       6: new           #2                  // class java/util/concurrent/atomic/AtomicInteger
       9: dup
      10: iconst_0
      11: invokespecial #3                  // Method java/util/concurrent/atomic/AtomicInteger."<init>":(I)V
      14: putfield      #4                  // Field stuckCount:Ljava/util/concurrent/atomic/AtomicInteger;
      17: aload_0
      18: sipush        600
      21: putfield      #5                  // Field threshold:I
      24: aload_0
      25: new           #6                  // class java/util/concurrent/ConcurrentHashMap
      28: dup
      29: invokespecial #7                  // Method java/util/concurrent/ConcurrentHashMap."<init>":()V
      32: putfield      #8                  // Field activeThreads:Ljava/util/concurrent/ConcurrentHashMap;
      35: return

  public void setThreshold(int);
    Code:
       0: aload_0
       1: iload_1
       2: putfield      #5                  // Field threshold:I
       5: return

  protected void initInternal() throws org.apache.catalina.LifecycleException;
    Code:
       0: aload_0
       1: invokespecial #9                  // Method org/apache/catalina/valves/ValveBase.initInternal:()V
       4: getstatic     #10                 // Field log:Lorg/apache/commons/logging/Log;
       7: invokeinterface #11,  1           // InterfaceMethod org/apache/commons/logging/Log.isDebugEnabled:()Z
      12: ifeq          50
      15: getstatic     #10                 // Field log:Lorg/apache/commons/logging/Log;
      18: new           #12                 // class java/lang/StringBuilder
      21: dup
      22: invokespecial #13                 // Method java/lang/StringBuilder."<init>":()V
      25: ldc           #14                 // String Monitoring stuck threads with threshold =
      27: invokevirtual #15                 // Method java/lang/StringBuilder.append:(Ljava/lang/String;)Ljava/lang/StringBuilder;
      30: aload_0
      31: getfield      #5                  // Field threshold:I
      34: invokevirtual #16                 // Method java/lang/StringBuilder.append:(I)Ljava/lang/StringBuilder;
      37: ldc           #17                 // String  sec
      39: invokevirtual #15                 // Method java/lang/StringBuilder.append:(Ljava/lang/String;)Ljava/lang/StringBuilder;
      42: invokevirtual #18                 // Method java/lang/StringBuilder.toString:()Ljava/lang/String;
      45: invokeinterface #19,  2           // InterfaceMethod org/apache/commons/logging/Log.debug:(Ljava/lang/Object;)V
      50: return

  private void handleStuckThread(org.wso2.carbon.tomcat.ext.valves.CarbonStuckThreadDetectionValve$MonitoredThread, long, int);
    Code:
       0: getstatic     #20                 // Field sm:Lorg/apache/tomcat/util/res/StringManager;
       3: ldc           #21                 // String stuckThreadDetectionValve.notifyStuckThreadDetected
       5: bipush        6
       7: anewarray     #22                 // class java/lang/Object
      10: dup
      11: iconst_0
      12: aload_1
      13: invokevirtual #23                 // Method org/wso2/carbon/tomcat/ext/valves/CarbonStuckThreadDetectionValve$MonitoredThread.getThread:()Ljava/lang/Thread;
      16: invokevirtual #24                 // Method java/lang/Thread.getName:()Ljava/lang/String;
      19: aastore
      20: dup
      21: iconst_1
      22: lload_2
      23: invokestatic  #25                 // Method java/lang/Long.valueOf:(J)Ljava/lang/Long;
      26: aastore
      27: dup
      28: iconst_2
      29: aload_1
      30: invokevirtual #26                 // Method org/wso2/carbon/tomcat/ext/valves/CarbonStuckThreadDetectionValve$MonitoredThread.getStartTime:()Ljava/util/Date;
      33: aastore
      34: dup
      35: iconst_3
      36: iload         4
      38: invokestatic  #27                 // Method java/lang/Integer.valueOf:(I)Ljava/lang/Integer;
      41: aastore
      42: dup
      43: iconst_4
      44: aload_1
      45: invokevirtual #28                 // Method org/wso2/carbon/tomcat/ext/valves/CarbonStuckThreadDetectionValve$MonitoredThread.getRequestUri:()Ljava/lang/String;
      48: aastore
      49: dup
      50: iconst_5
      51: aload_0
      52: getfield      #5                  // Field threshold:I
      55: invokestatic  #27                 // Method java/lang/Integer.valueOf:(I)Ljava/lang/Integer;
      58: aastore
      59: invokevirtual #29                 // Method org/apache/tomcat/util/res/StringManager.getString:(Ljava/lang/String;[Ljava/lang/Object;)Ljava/lang/String;
      62: astore        5
      64: new           #12                 // class java/lang/StringBuilder
      67: dup
      68: invokespecial #13                 // Method java/lang/StringBuilder."<init>":()V
      71: aload         5
      73: invokevirtual #15                 // Method java/lang/StringBuilder.append:(Ljava/lang/String;)Ljava/lang/StringBuilder;
      76: ldc           #30                 // String , tenantDomain=
      78: invokevirtual #15                 // Method java/lang/StringBuilder.append:(Ljava/lang/String;)Ljava/lang/StringBuilder;
      81: aload_1
      82: invokevirtual #31                 // Method org/wso2/carbon/tomcat/ext/valves/CarbonStuckThreadDetectionValve$MonitoredThread.getTenantDomain:()Ljava/lang/String;
      85: invokevirtual #15                 // Method java/lang/StringBuilder.append:(Ljava/lang/String;)Ljava/lang/StringBuilder;
      88: invokevirtual #18                 // Method java/lang/StringBuilder.toString:()Ljava/lang/String;
      91: astore        5
      93: aload_1
      94: invokevirtual #32                 // Method org/wso2/carbon/tomcat/ext/valves/CarbonStuckThreadDetectionValve$MonitoredThread.getCorrelationId:()Ljava/lang/String;
      97: invokestatic  #33                 // Method org/apache/commons/lang/StringUtils.isNotEmpty:(Ljava/lang/String;)Z
     100: ifeq          132
     103: new           #12                 // class java/lang/StringBuilder
     106: dup
     107: invokespecial #13                 // Method java/lang/StringBuilder."<init>":()V
     110: aload         5
     112: invokevirtual #15                 // Method java/lang/StringBuilder.append:(Ljava/lang/String;)Ljava/lang/StringBuilder;
     115: ldc           #34                 // String , correlation-id=
     117: invokevirtual #15                 // Method java/lang/StringBuilder.append:(Ljava/lang/String;)Ljava/lang/StringBuilder;
     120: aload_1
     121: invokevirtual #32                 // Method org/wso2/carbon/tomcat/ext/valves/CarbonStuckThreadDetectionValve$MonitoredThread.getCorrelationId:()Ljava/lang/String;
     124: invokevirtual #15                 // Method java/lang/StringBuilder.append:(Ljava/lang/String;)Ljava/lang/StringBuilder;
     127: invokevirtual #18                 // Method java/lang/StringBuilder.toString:()Ljava/lang/String;
     130: astore        5
     132: new           #35                 // class java/lang/Throwable
     135: dup
     136: invokespecial #36                 // Method java/lang/Throwable."<init>":()V
     139: astore        6
     141: aload         6
     143: aload_1
     144: invokevirtual #23                 // Method org/wso2/carbon/tomcat/ext/valves/CarbonStuckThreadDetectionValve$MonitoredThread.getThread:()Ljava/lang/Thread;
     147: invokevirtual #37                 // Method java/lang/Thread.getStackTrace:()[Ljava/lang/StackTraceElement;
     150: invokevirtual #38                 // Method java/lang/Throwable.setStackTrace:([Ljava/lang/StackTraceElement;)V
     153: getstatic     #10                 // Field log:Lorg/apache/commons/logging/Log;
     156: aload         5
     158: aload         6
     160: invokeinterface #39,  3           // InterfaceMethod org/apache/commons/logging/Log.warn:(Ljava/lang/Object;Ljava/lang/Throwable;)V
     165: aload_1
     166: invokevirtual #23                 // Method org/wso2/carbon/tomcat/ext/valves/CarbonStuckThreadDetectionValve$MonitoredThread.getThread:()Ljava/lang/Thread;
     169: invokevirtual #40                 // Method java/lang/Thread.interrupt:()V
     172: aload_1
     173: invokevirtual #23                 // Method org/wso2/carbon/tomcat/ext/valves/CarbonStuckThreadDetectionValve$MonitoredThread.getThread:()Ljava/lang/Thread;
     176: invokevirtual #41                 // Method java/lang/Thread.stop:()V
     179: aload_0
     180: getfield      #8                  // Field activeThreads:Ljava/util/concurrent/ConcurrentHashMap;
     183: aload_1
     184: invokevirtual #23                 // Method org/wso2/carbon/tomcat/ext/valves/CarbonStuckThreadDetectionValve$MonitoredThread.getThread:()Ljava/lang/Thread;
     187: invokevirtual #42                 // Method java/lang/Thread.getId:()J
     190: invokestatic  #25                 // Method java/lang/Long.valueOf:(J)Ljava/lang/Long;
     193: invokevirtual #43                 // Method java/util/concurrent/ConcurrentHashMap.remove:(Ljava/lang/Object;)Ljava/lang/Object;
     196: pop
     197: return

  public void invoke(org.apache.catalina.connector.Request, org.apache.catalina.connector.Response) throws java.io.IOException, javax.servlet.ServletException;
    Code:
       0: aload_0
       1: getfield      #5                  // Field threshold:I
       4: ifgt          19
       7: aload_0
       8: invokevirtual #44                 // Method getNext:()Lorg/apache/catalina/Valve;
      11: aload_1
      12: aload_2
      13: invokeinterface #45,  3           // InterfaceMethod org/apache/catalina/Valve.invoke:(Lorg/apache/catalina/connector/Request;Lorg/apache/catalina/connector/Response;)V
      18: return
      19: invokestatic  #46                 // Method java/lang/Thread.currentThread:()Ljava/lang/Thread;
      22: invokevirtual #42                 // Method java/lang/Thread.getId:()J
      25: invokestatic  #25                 // Method java/lang/Long.valueOf:(J)Ljava/lang/Long;
      28: astore_3
      29: aload_1
      30: invokevirtual #47                 // Method org/apache/catalina/connector/Request.getRequestURL:()Ljava/lang/StringBuffer;
      33: astore        4
      35: aload_1
      36: invokevirtual #48                 // Method org/apache/catalina/connector/Request.getQueryString:()Ljava/lang/String;
      39: ifnull        60
      42: aload         4
      44: ldc           #49                 // String ?
      46: invokevirtual #50                 // Method java/lang/StringBuffer.append:(Ljava/lang/String;)Ljava/lang/StringBuffer;
      49: pop
      50: aload         4
      52: aload_1
      53: invokevirtual #48                 // Method org/apache/catalina/connector/Request.getQueryString:()Ljava/lang/String;
      56: invokevirtual #50                 // Method java/lang/StringBuffer.append:(Ljava/lang/String;)Ljava/lang/StringBuffer;
      59: pop
      60: aload_1
      61: invokestatic  #51                 // Method org/wso2/carbon/tomcat/ext/internal/Utils.getTenantDomain:(Ljavax/servlet/http/HttpServletRequest;)Ljava/lang/String;
      64: astore        5
      66: new           #52                 // class org/wso2/carbon/tomcat/ext/valves/CarbonStuckThreadDetectionValve$MonitoredThread
      69: dup
      70: invokestatic  #46                 // Method java/lang/Thread.currentThread:()Ljava/lang/Thread;
      73: aload         4
      75: invokevirtual #53                 // Method java/lang/StringBuffer.toString:()Ljava/lang/String;
      78: aload         5
      80: invokestatic  #54                 // Method getCorrelation:()Ljava/lang/String;
      83: invokespecial #55                 // Method org/wso2/carbon/tomcat/ext/valves/CarbonStuckThreadDetectionValve$MonitoredThread."<init>":(Ljava/lang/Thread;Ljava/lang/String;Ljava/lang/String;Ljava/lang/String;)V
      86: astore        6
      88: aload_0
      89: getfield      #8                  // Field activeThreads:Ljava/util/concurrent/ConcurrentHashMap;
      92: aload_3
      93: aload         6
      95: invokevirtual #56                 // Method java/util/concurrent/ConcurrentHashMap.put:(Ljava/lang/Object;Ljava/lang/Object;)Ljava/lang/Object;
      98: pop
      99: aload_0
     100: invokevirtual #44                 // Method getNext:()Lorg/apache/catalina/Valve;
     103: aload_1
     104: aload_2
     105: invokeinterface #45,  3           // InterfaceMethod org/apache/catalina/Valve.invoke:(Lorg/apache/catalina/connector/Request;Lorg/apache/catalina/connector/Response;)V
     110: aload_0
     111: getfield      #8                  // Field activeThreads:Ljava/util/concurrent/ConcurrentHashMap;
     114: aload_3
     115: invokevirtual #43                 // Method java/util/concurrent/ConcurrentHashMap.remove:(Ljava/lang/Object;)Ljava/lang/Object;
     118: pop
     119: goto          136
     122: astore        7
     124: aload_0
     125: getfield      #8                  // Field activeThreads:Ljava/util/concurrent/ConcurrentHashMap;
     128: aload_3
     129: invokevirtual #43                 // Method java/util/concurrent/ConcurrentHashMap.remove:(Ljava/lang/Object;)Ljava/lang/Object;
     132: pop
     133: aload         7
     135: athrow
     136: return
    Exception table:
       from    to  target type
          99   110   122   any
         122   124   122   any

  public void backgroundProcess();
    Code:
       0: aload_0
       1: invokespecial #57                 // Method org/apache/catalina/valves/ValveBase.backgroundProcess:()V
       4: aload_0
       5: getfield      #5                  // Field threshold:I
       8: i2l
       9: ldc2_w        #58                 // long 1000l
      12: lmul
      13: lstore_1
      14: aload_0
      15: getfield      #8                  // Field activeThreads:Ljava/util/concurrent/ConcurrentHashMap;
      18: invokevirtual #60                 // Method java/util/concurrent/ConcurrentHashMap.values:()Ljava/util/Collection;
      21: invokeinterface #61,  1           // InterfaceMethod java/util/Collection.iterator:()Ljava/util/Iterator;
      26: astore_3
      27: aload_3
      28: invokeinterface #62,  1           // InterfaceMethod java/util/Iterator.hasNext:()Z
      33: ifeq          91
      36: aload_3
      37: invokeinterface #63,  1           // InterfaceMethod java/util/Iterator.next:()Ljava/lang/Object;
      42: checkcast     #52                 // class org/wso2/carbon/tomcat/ext/valves/CarbonStuckThreadDetectionValve$MonitoredThread
      45: astore        4
      47: aload         4
      49: invokevirtual #64                 // Method org/wso2/carbon/tomcat/ext/valves/CarbonStuckThreadDetectionValve$MonitoredThread.getActiveTimeInMillis:()J
      52: lstore        5
      54: lload         5
      56: lload_1
      57: lcmp
      58: iflt          88
      61: aload         4
      63: invokevirtual #65                 // Method org/wso2/carbon/tomcat/ext/valves/CarbonStuckThreadDetectionValve$MonitoredThread.markAsStuckIfStillRunning:()Z
      66: ifeq          88
      69: aload_0
      70: getfield      #4                  // Field stuckCount:Ljava/util/concurrent/atomic/AtomicInteger;
      73: invokevirtual #66                 // Method java/util/concurrent/atomic/AtomicInteger.incrementAndGet:()I
      76: istore        7
      78: aload_0
      79: aload         4
      81: lload         5
      83: iload         7
      85: invokespecial #67                 // Method handleStuckThread:(Lorg/wso2/carbon/tomcat/ext/valves/CarbonStuckThreadDetectionValve$MonitoredThread;JI)V
      88: goto          27
      91: return

  public static boolean isCorrelationIDPresent();
    Code:
       0: ldc           #69                 // String Correlation-ID
       2: invokestatic  #70                 // Method org/slf4j/MDC.get:(Ljava/lang/String;)Ljava/lang/String;
       5: ifnull        12
       8: iconst_1
       9: goto          13
      12: iconst_0
      13: ireturn

  public static java.lang.String getCorrelation();
    Code:
       0: aconst_null
       1: astore_0
       2: invokestatic  #71                 // Method isCorrelationIDPresent:()Z
       5: ifeq          14
       8: ldc           #69                 // String Correlation-ID
      10: invokestatic  #70                 // Method org/slf4j/MDC.get:(Ljava/lang/String;)Ljava/lang/String;
      13: astore_0
      14: aload_0
      15: areturn

  static {};
    Code:
       0: ldc           #68                 // class org/wso2/carbon/tomcat/ext/valves/CarbonStuckThreadDetectionValve
       2: invokestatic  #72                 // Method org/apache/commons/logging/LogFactory.getLog:(Ljava/lang/Class;)Lorg/apache/commons/logging/Log;
       5: putstatic     #10                 // Field log:Lorg/apache/commons/logging/Log;
       8: ldc           #74                 // String org.apache.catalina.valves
      10: invokestatic  #75                 // Method org/apache/tomcat/util/res/StringManager.getManager:(Ljava/lang/String;)Lorg/apache/tomcat/util/res/StringManager;
      13: putstatic     #20                 // Field sm:Lorg/apache/tomcat/util/res/StringManager;
      16: return
}
