Compiled from "HttpTrace.java"
public final class org.springframework.boot.actuate.trace.http.HttpTrace$Request {
  private final java.lang.String method;

  private final java.net.URI uri;

  private final java.util.Map<java.lang.String, java.util.List<java.lang.String>> headers;

  private final java.lang.String remoteAddress;

  private org.springframework.boot.actuate.trace.http.HttpTrace$Request(org.springframework.boot.actuate.trace.http.TraceableRequest);
    Code:
       0: aload_0
       1: aload_1
       2: invokeinterface #2,  1            // InterfaceMethod org/springframework/boot/actuate/trace/http/TraceableRequest.getMethod:()Ljava/lang/String;
       7: aload_1
       8: invokeinterface #3,  1            // InterfaceMethod org/springframework/boot/actuate/trace/http/TraceableRequest.getUri:()Ljava/net/URI;
      13: aload_1
      14: invokeinterface #4,  1            // InterfaceMethod org/springframework/boot/actuate/trace/http/TraceableRequest.getHeaders:()Ljava/util/Map;
      19: aload_1
      20: invokeinterface #5,  1            // InterfaceMethod org/springframework/boot/actuate/trace/http/TraceableRequest.getRemoteAddress:()Ljava/lang/String;
      25: invokespecial #6                  // Method "<init>":(Ljava/lang/String;Ljava/net/URI;Ljava/util/Map;Ljava/lang/String;)V
      28: return

  public org.springframework.boot.actuate.trace.http.HttpTrace$Request(java.lang.String, java.net.URI, java.util.Map<java.lang.String, java.util.List<java.lang.String>>, java.lang.String);
    Code:
       0: aload_0
       1: invokespecial #7                  // Method java/lang/Object."<init>":()V
       4: aload_0
       5: aload_1
       6: putfield      #8                  // Field method:Ljava/lang/String;
       9: aload_0
      10: aload_2
      11: putfield      #9                  // Field uri:Ljava/net/URI;
      14: aload_0
      15: new           #10                 // class java/util/LinkedHashMap
      18: dup
      19: aload_3
      20: invokespecial #11                 // Method java/util/LinkedHashMap."<init>":(Ljava/util/Map;)V
      23: putfield      #12                 // Field headers:Ljava/util/Map;
      26: aload_0
      27: aload         4
      29: putfield      #13                 // Field remoteAddress:Ljava/lang/String;
      32: return

  public java.lang.String getMethod();
    Code:
       0: aload_0
       1: getfield      #8                  // Field method:Ljava/lang/String;
       4: areturn

  public java.net.URI getUri();
    Code:
       0: aload_0
       1: getfield      #9                  // Field uri:Ljava/net/URI;
       4: areturn

  public java.util.Map<java.lang.String, java.util.List<java.lang.String>> getHeaders();
    Code:
       0: aload_0
       1: getfield      #12                 // Field headers:Ljava/util/Map;
       4: areturn

  public java.lang.String getRemoteAddress();
    Code:
       0: aload_0
       1: getfield      #13                 // Field remoteAddress:Ljava/lang/String;
       4: areturn

  org.springframework.boot.actuate.trace.http.HttpTrace$Request(org.springframework.boot.actuate.trace.http.TraceableRequest, org.springframework.boot.actuate.trace.http.HttpTrace$1);
    Code:
       0: aload_0
       1: aload_1
       2: invokespecial #1                  // Method "<init>":(Lorg/springframework/boot/actuate/trace/http/TraceableRequest;)V
       5: return
}
