Compiled from "Edge.scala"
public final class zio.aws.xray.model.Edge$Wrapper implements zio.aws.xray.model.Edge$ReadOnly {
  private final zio.prelude.data.Optional referenceId;

  private final zio.prelude.data.Optional startTime;

  private final zio.prelude.data.Optional endTime;

  private final zio.prelude.data.Optional summaryStatistics;

  private final zio.prelude.data.Optional responseTimeHistogram;

  private final zio.prelude.data.Optional aliases;

  public zio.aws.xray.model.Edge$Wrapper(software.amazon.awssdk.services.xray.model.Edge);
    Code:
       0: aload_0
       1: invokespecial #49                 // Method java/lang/Object."<init>":()V
       4: aload_0
       5: getstatic     #55                 // Field zio/aws/core/internal/package$.MODULE$:Lzio/aws/core/internal/package$;
       8: aload_1
       9: invokevirtual #60                 // Method software/amazon/awssdk/services/xray/model/Edge.referenceId:()Ljava/lang/Integer;
      12: invokevirtual #64                 // Method zio/aws/core/internal/package$.optionalFromNullable:(Ljava/lang/Object;)Lzio/prelude/data/Optional;
      15: aload_0
      16: invokedynamic #85,  0             // InvokeDynamic #0:apply:(Lzio/aws/xray/model/Edge$Wrapper;)Lscala/Function1;
      21: invokeinterface #91,  2           // InterfaceMethod zio/prelude/data/Optional.map:(Lscala/Function1;)Lzio/prelude/data/Optional;
      26: putfield      #93                 // Field referenceId:Lzio/prelude/data/Optional;
      29: aload_0
      30: getstatic     #55                 // Field zio/aws/core/internal/package$.MODULE$:Lzio/aws/core/internal/package$;
      33: aload_1
      34: invokevirtual #96                 // Method software/amazon/awssdk/services/xray/model/Edge.startTime:()Ljava/time/Instant;
      37: invokevirtual #64                 // Method zio/aws/core/internal/package$.optionalFromNullable:(Ljava/lang/Object;)Lzio/prelude/data/Optional;
      40: aload_0
      41: invokedynamic #103,  0            // InvokeDynamic #1:apply:(Lzio/aws/xray/model/Edge$Wrapper;)Lscala/Function1;
      46: invokeinterface #91,  2           // InterfaceMethod zio/prelude/data/Optional.map:(Lscala/Function1;)Lzio/prelude/data/Optional;
      51: putfield      #105                // Field startTime:Lzio/prelude/data/Optional;
      54: aload_0
      55: getstatic     #55                 // Field zio/aws/core/internal/package$.MODULE$:Lzio/aws/core/internal/package$;
      58: aload_1
      59: invokevirtual #107                // Method software/amazon/awssdk/services/xray/model/Edge.endTime:()Ljava/time/Instant;
      62: invokevirtual #64                 // Method zio/aws/core/internal/package$.optionalFromNullable:(Ljava/lang/Object;)Lzio/prelude/data/Optional;
      65: aload_0
      66: invokedynamic #112,  0            // InvokeDynamic #2:apply:(Lzio/aws/xray/model/Edge$Wrapper;)Lscala/Function1;
      71: invokeinterface #91,  2           // InterfaceMethod zio/prelude/data/Optional.map:(Lscala/Function1;)Lzio/prelude/data/Optional;
      76: putfield      #114                // Field endTime:Lzio/prelude/data/Optional;
      79: aload_0
      80: getstatic     #55                 // Field zio/aws/core/internal/package$.MODULE$:Lzio/aws/core/internal/package$;
      83: aload_1
      84: invokevirtual #117                // Method software/amazon/awssdk/services/xray/model/Edge.summaryStatistics:()Lsoftware/amazon/awssdk/services/xray/model/EdgeStatistics;
      87: invokevirtual #64                 // Method zio/aws/core/internal/package$.optionalFromNullable:(Ljava/lang/Object;)Lzio/prelude/data/Optional;
      90: aload_0
      91: invokedynamic #124,  0            // InvokeDynamic #3:apply:(Lzio/aws/xray/model/Edge$Wrapper;)Lscala/Function1;
      96: invokeinterface #91,  2           // InterfaceMethod zio/prelude/data/Optional.map:(Lscala/Function1;)Lzio/prelude/data/Optional;
     101: putfield      #126                // Field summaryStatistics:Lzio/prelude/data/Optional;
     104: aload_0
     105: getstatic     #55                 // Field zio/aws/core/internal/package$.MODULE$:Lzio/aws/core/internal/package$;
     108: aload_1
     109: invokevirtual #129                // Method software/amazon/awssdk/services/xray/model/Edge.responseTimeHistogram:()Ljava/util/List;
     112: invokevirtual #64                 // Method zio/aws/core/internal/package$.optionalFromNullable:(Ljava/lang/Object;)Lzio/prelude/data/Optional;
     115: aload_0
     116: invokedynamic #136,  0            // InvokeDynamic #4:apply:(Lzio/aws/xray/model/Edge$Wrapper;)Lscala/Function1;
     121: invokeinterface #91,  2           // InterfaceMethod zio/prelude/data/Optional.map:(Lscala/Function1;)Lzio/prelude/data/Optional;
     126: putfield      #138                // Field responseTimeHistogram:Lzio/prelude/data/Optional;
     129: aload_0
     130: getstatic     #55                 // Field zio/aws/core/internal/package$.MODULE$:Lzio/aws/core/internal/package$;
     133: aload_1
     134: invokevirtual #140                // Method software/amazon/awssdk/services/xray/model/Edge.aliases:()Ljava/util/List;
     137: invokevirtual #64                 // Method zio/aws/core/internal/package$.optionalFromNullable:(Ljava/lang/Object;)Lzio/prelude/data/Optional;
     140: aload_0
     141: invokedynamic #145,  0            // InvokeDynamic #5:apply:(Lzio/aws/xray/model/Edge$Wrapper;)Lscala/Function1;
     146: invokeinterface #91,  2           // InterfaceMethod zio/prelude/data/Optional.map:(Lscala/Function1;)Lzio/prelude/data/Optional;
     151: putfield      #147                // Field aliases:Lzio/prelude/data/Optional;
     154: return

  public zio.aws.xray.model.Edge asEditable();
    Code:
       0: aload_0
       1: invokestatic  #156                // InterfaceMethod zio/aws/xray/model/Edge$ReadOnly.asEditable$:(Lzio/aws/xray/model/Edge$ReadOnly;)Lzio/aws/xray/model/Edge;
       4: areturn

  public zio.ZIO getReferenceId();
    Code:
       0: aload_0
       1: invokestatic  #162                // InterfaceMethod zio/aws/xray/model/Edge$ReadOnly.getReferenceId$:(Lzio/aws/xray/model/Edge$ReadOnly;)Lzio/ZIO;
       4: areturn

  public zio.ZIO getStartTime();
    Code:
       0: aload_0
       1: invokestatic  #166                // InterfaceMethod zio/aws/xray/model/Edge$ReadOnly.getStartTime$:(Lzio/aws/xray/model/Edge$ReadOnly;)Lzio/ZIO;
       4: areturn

  public zio.ZIO getEndTime();
    Code:
       0: aload_0
       1: invokestatic  #170                // InterfaceMethod zio/aws/xray/model/Edge$ReadOnly.getEndTime$:(Lzio/aws/xray/model/Edge$ReadOnly;)Lzio/ZIO;
       4: areturn

  public zio.ZIO getSummaryStatistics();
    Code:
       0: aload_0
       1: invokestatic  #174                // InterfaceMethod zio/aws/xray/model/Edge$ReadOnly.getSummaryStatistics$:(Lzio/aws/xray/model/Edge$ReadOnly;)Lzio/ZIO;
       4: areturn

  public zio.ZIO getResponseTimeHistogram();
    Code:
       0: aload_0
       1: invokestatic  #178                // InterfaceMethod zio/aws/xray/model/Edge$ReadOnly.getResponseTimeHistogram$:(Lzio/aws/xray/model/Edge$ReadOnly;)Lzio/ZIO;
       4: areturn

  public zio.ZIO getAliases();
    Code:
       0: aload_0
       1: invokestatic  #182                // InterfaceMethod zio/aws/xray/model/Edge$ReadOnly.getAliases$:(Lzio/aws/xray/model/Edge$ReadOnly;)Lzio/ZIO;
       4: areturn

  public zio.prelude.data.Optional<java.lang.Object> referenceId();
    Code:
       0: aload_0
       1: getfield      #93                 // Field referenceId:Lzio/prelude/data/Optional;
       4: areturn

  public zio.prelude.data.Optional<java.time.Instant> startTime();
    Code:
       0: aload_0
       1: getfield      #105                // Field startTime:Lzio/prelude/data/Optional;
       4: areturn

  public zio.prelude.data.Optional<java.time.Instant> endTime();
    Code:
       0: aload_0
       1: getfield      #114                // Field endTime:Lzio/prelude/data/Optional;
       4: areturn

  public zio.prelude.data.Optional<zio.aws.xray.model.EdgeStatistics$ReadOnly> summaryStatistics();
    Code:
       0: aload_0
       1: getfield      #126                // Field summaryStatistics:Lzio/prelude/data/Optional;
       4: areturn

  public zio.prelude.data.Optional<scala.collection.immutable.List<zio.aws.xray.model.HistogramEntry$ReadOnly>> responseTimeHistogram();
    Code:
       0: aload_0
       1: getfield      #138                // Field responseTimeHistogram:Lzio/prelude/data/Optional;
       4: areturn

  public zio.prelude.data.Optional<scala.collection.immutable.List<zio.aws.xray.model.Alias$ReadOnly>> aliases();
    Code:
       0: aload_0
       1: getfield      #147                // Field aliases:Lzio/prelude/data/Optional;
       4: areturn

  private final int $init$$$anonfun$1(java.lang.Integer);
    Code:
       0: getstatic     #194                // Field scala/Predef$.MODULE$:Lscala/Predef$;
       3: aload_1
       4: invokevirtual #197                // Method scala/Predef$.Integer2int:(Ljava/lang/Integer;)I
       7: ireturn

  private final java.time.Instant $init$$$anonfun$2(java.time.Instant);
    Code:
       0: getstatic     #201                // Field zio/aws/xray/model/package$primitives$Timestamp$.MODULE$:Lzio/aws/xray/model/package$primitives$Timestamp$;
       3: astore_2
       4: aload_1
       5: areturn

  private final java.time.Instant $init$$$anonfun$3(java.time.Instant);
    Code:
       0: getstatic     #201                // Field zio/aws/xray/model/package$primitives$Timestamp$.MODULE$:Lzio/aws/xray/model/package$primitives$Timestamp$;
       3: astore_2
       4: aload_1
       5: areturn

  private final zio.aws.xray.model.EdgeStatistics$ReadOnly $init$$$anonfun$4(software.amazon.awssdk.services.xray.model.EdgeStatistics);
    Code:
       0: getstatic     #208                // Field zio/aws/xray/model/EdgeStatistics$.MODULE$:Lzio/aws/xray/model/EdgeStatistics$;
       3: aload_1
       4: invokevirtual #211                // Method zio/aws/xray/model/EdgeStatistics$.wrap:(Lsoftware/amazon/awssdk/services/xray/model/EdgeStatistics;)Lzio/aws/xray/model/EdgeStatistics$ReadOnly;
       7: areturn

  private final zio.aws.xray.model.HistogramEntry$ReadOnly $init$$$anonfun$5$$anonfun$1(software.amazon.awssdk.services.xray.model.HistogramEntry);
    Code:
       0: getstatic     #220                // Field zio/aws/xray/model/HistogramEntry$.MODULE$:Lzio/aws/xray/model/HistogramEntry$;
       3: aload_1
       4: invokevirtual #222                // Method zio/aws/xray/model/HistogramEntry$.wrap:(Lsoftware/amazon/awssdk/services/xray/model/HistogramEntry;)Lzio/aws/xray/model/HistogramEntry$ReadOnly;
       7: areturn

  private final scala.collection.immutable.List $init$$$anonfun$5(java.util.List);
    Code:
       0: getstatic     #228                // Field scala/jdk/CollectionConverters$.MODULE$:Lscala/jdk/CollectionConverters$;
       3: aload_1
       4: invokevirtual #231                // Method scala/jdk/CollectionConverters$.ListHasAsScala:(Ljava/util/List;)Lscala/collection/convert/AsScalaExtensions$ListHasAsScala;
       7: invokevirtual #235                // Method scala/collection/convert/AsScalaExtensions$ListHasAsScala.asScala:()Lscala/collection/mutable/Buffer;
      10: aload_0
      11: invokedynamic #240,  0            // InvokeDynamic #6:apply:(Lzio/aws/xray/model/Edge$Wrapper;)Lscala/Function1;
      16: invokeinterface #245,  2          // InterfaceMethod scala/collection/mutable/Buffer.map:(Lscala/Function1;)Ljava/lang/Object;
      21: checkcast     #247                // class scala/collection/IterableOnceOps
      24: invokeinterface #251,  1          // InterfaceMethod scala/collection/IterableOnceOps.toList:()Lscala/collection/immutable/List;
      29: areturn

  private final zio.aws.xray.model.Alias$ReadOnly $init$$$anonfun$6$$anonfun$1(software.amazon.awssdk.services.xray.model.Alias);
    Code:
       0: getstatic     #259                // Field zio/aws/xray/model/Alias$.MODULE$:Lzio/aws/xray/model/Alias$;
       3: aload_1
       4: invokevirtual #261                // Method zio/aws/xray/model/Alias$.wrap:(Lsoftware/amazon/awssdk/services/xray/model/Alias;)Lzio/aws/xray/model/Alias$ReadOnly;
       7: areturn

  private final scala.collection.immutable.List $init$$$anonfun$6(java.util.List);
    Code:
       0: getstatic     #228                // Field scala/jdk/CollectionConverters$.MODULE$:Lscala/jdk/CollectionConverters$;
       3: aload_1
       4: invokevirtual #231                // Method scala/jdk/CollectionConverters$.ListHasAsScala:(Ljava/util/List;)Lscala/collection/convert/AsScalaExtensions$ListHasAsScala;
       7: invokevirtual #235                // Method scala/collection/convert/AsScalaExtensions$ListHasAsScala.asScala:()Lscala/collection/mutable/Buffer;
      10: aload_0
      11: invokedynamic #267,  0            // InvokeDynamic #7:apply:(Lzio/aws/xray/model/Edge$Wrapper;)Lscala/Function1;
      16: invokeinterface #245,  2          // InterfaceMethod scala/collection/mutable/Buffer.map:(Lscala/Function1;)Ljava/lang/Object;
      21: checkcast     #247                // class scala/collection/IterableOnceOps
      24: invokeinterface #251,  1          // InterfaceMethod scala/collection/IterableOnceOps.toList:()Lscala/collection/immutable/List;
      29: areturn

  private static java.lang.Object $deserializeLambda$(java.lang.invoke.SerializedLambda);
    Code:
       0: aload_0
       1: invokedynamic #279,  0            // InvokeDynamic #8:lambdaDeserialize:(Ljava/lang/invoke/SerializedLambda;)Ljava/lang/Object;
       6: areturn
}
