Compiled from "ErrorRootCauseService.scala"
public interface zio.aws.xray.model.ErrorRootCauseService$ReadOnly {
  public static zio.aws.xray.model.ErrorRootCauseService asEditable$(zio.aws.xray.model.ErrorRootCauseService$ReadOnly);
    Code:
       0: aload_0
       1: invokespecial #19                 // InterfaceMethod asEditable:()Lzio/aws/xray/model/ErrorRootCauseService;
       4: areturn

  public default zio.aws.xray.model.ErrorRootCauseService asEditable();
    Code:
       0: getstatic     #26                 // Field zio/aws/xray/model/ErrorRootCauseService$.MODULE$:Lzio/aws/xray/model/ErrorRootCauseService$;
       3: aload_0
       4: invokeinterface #30,  1           // InterfaceMethod name:()Lzio/prelude/data/Optional;
       9: aload_0
      10: invokedynamic #51,  0             // InvokeDynamic #0:apply:(Lzio/aws/xray/model/ErrorRootCauseService$ReadOnly;)Lscala/Function1;
      15: invokeinterface #57,  2           // InterfaceMethod zio/prelude/data/Optional.map:(Lscala/Function1;)Lzio/prelude/data/Optional;
      20: aload_0
      21: invokeinterface #60,  1           // InterfaceMethod names:()Lzio/prelude/data/Optional;
      26: aload_0
      27: invokedynamic #67,  0             // InvokeDynamic #1:apply:(Lzio/aws/xray/model/ErrorRootCauseService$ReadOnly;)Lscala/Function1;
      32: invokeinterface #57,  2           // InterfaceMethod zio/prelude/data/Optional.map:(Lscala/Function1;)Lzio/prelude/data/Optional;
      37: aload_0
      38: invokeinterface #70,  1           // InterfaceMethod type:()Lzio/prelude/data/Optional;
      43: aload_0
      44: invokedynamic #75,  0             // InvokeDynamic #2:apply:(Lzio/aws/xray/model/ErrorRootCauseService$ReadOnly;)Lscala/Function1;
      49: invokeinterface #57,  2           // InterfaceMethod zio/prelude/data/Optional.map:(Lscala/Function1;)Lzio/prelude/data/Optional;
      54: aload_0
      55: invokeinterface #78,  1           // InterfaceMethod accountId:()Lzio/prelude/data/Optional;
      60: aload_0
      61: invokedynamic #83,  0             // InvokeDynamic #3:apply:(Lzio/aws/xray/model/ErrorRootCauseService$ReadOnly;)Lscala/Function1;
      66: invokeinterface #57,  2           // InterfaceMethod zio/prelude/data/Optional.map:(Lscala/Function1;)Lzio/prelude/data/Optional;
      71: aload_0
      72: invokeinterface #86,  1           // InterfaceMethod entityPath:()Lzio/prelude/data/Optional;
      77: aload_0
      78: invokedynamic #91,  0             // InvokeDynamic #4:apply:(Lzio/aws/xray/model/ErrorRootCauseService$ReadOnly;)Lscala/Function1;
      83: invokeinterface #57,  2           // InterfaceMethod zio/prelude/data/Optional.map:(Lscala/Function1;)Lzio/prelude/data/Optional;
      88: aload_0
      89: invokeinterface #94,  1           // InterfaceMethod inferred:()Lzio/prelude/data/Optional;
      94: aload_0
      95: invokedynamic #101,  0            // InvokeDynamic #5:apply:(Lzio/aws/xray/model/ErrorRootCauseService$ReadOnly;)Lscala/Function1;
     100: invokeinterface #57,  2           // InterfaceMethod zio/prelude/data/Optional.map:(Lscala/Function1;)Lzio/prelude/data/Optional;
     105: invokevirtual #104                // Method zio/aws/xray/model/ErrorRootCauseService$.apply:(Lzio/prelude/data/Optional;Lzio/prelude/data/Optional;Lzio/prelude/data/Optional;Lzio/prelude/data/Optional;Lzio/prelude/data/Optional;Lzio/prelude/data/Optional;)Lzio/aws/xray/model/ErrorRootCauseService;
     108: areturn

  public abstract zio.prelude.data.Optional<java.lang.String> name();

  public abstract zio.prelude.data.Optional<scala.collection.immutable.List<java.lang.String>> names();

  public abstract zio.prelude.data.Optional<java.lang.String> type();

  public abstract zio.prelude.data.Optional<java.lang.String> accountId();

  public abstract zio.prelude.data.Optional<scala.collection.immutable.List<zio.aws.xray.model.ErrorRootCauseEntity$ReadOnly>> entityPath();

  public abstract zio.prelude.data.Optional<java.lang.Object> inferred();

  public static zio.ZIO getName$(zio.aws.xray.model.ErrorRootCauseService$ReadOnly);
    Code:
       0: aload_0
       1: invokespecial #115                // InterfaceMethod getName:()Lzio/ZIO;
       4: areturn

  public default zio.ZIO<java.lang.Object, zio.aws.core.AwsError, java.lang.String> getName();
    Code:
       0: getstatic     #121                // Field zio/aws/core/AwsError$.MODULE$:Lzio/aws/core/AwsError$;
       3: ldc           #122                // String name
       5: aload_0
       6: invokedynamic #132,  0            // InvokeDynamic #6:apply:(Lzio/aws/xray/model/ErrorRootCauseService$ReadOnly;)Lscala/Function0;
      11: invokevirtual #136                // Method zio/aws/core/AwsError$.unwrapOptionField:(Ljava/lang/String;Lscala/Function0;)Lzio/ZIO;
      14: areturn

  public static zio.ZIO getNames$(zio.aws.xray.model.ErrorRootCauseService$ReadOnly);
    Code:
       0: aload_0
       1: invokespecial #140                // InterfaceMethod getNames:()Lzio/ZIO;
       4: areturn

  public default zio.ZIO<java.lang.Object, zio.aws.core.AwsError, scala.collection.immutable.List<java.lang.String>> getNames();
    Code:
       0: getstatic     #121                // Field zio/aws/core/AwsError$.MODULE$:Lzio/aws/core/AwsError$;
       3: ldc           #142                // String names
       5: aload_0
       6: invokedynamic #147,  0            // InvokeDynamic #7:apply:(Lzio/aws/xray/model/ErrorRootCauseService$ReadOnly;)Lscala/Function0;
      11: invokevirtual #136                // Method zio/aws/core/AwsError$.unwrapOptionField:(Ljava/lang/String;Lscala/Function0;)Lzio/ZIO;
      14: areturn

  public static zio.ZIO getType$(zio.aws.xray.model.ErrorRootCauseService$ReadOnly);
    Code:
       0: aload_0
       1: invokespecial #151                // InterfaceMethod getType:()Lzio/ZIO;
       4: areturn

  public default zio.ZIO<java.lang.Object, zio.aws.core.AwsError, java.lang.String> getType();
    Code:
       0: getstatic     #121                // Field zio/aws/core/AwsError$.MODULE$:Lzio/aws/core/AwsError$;
       3: ldc           #152                // String type
       5: aload_0
       6: invokedynamic #157,  0            // InvokeDynamic #8:apply:(Lzio/aws/xray/model/ErrorRootCauseService$ReadOnly;)Lscala/Function0;
      11: invokevirtual #136                // Method zio/aws/core/AwsError$.unwrapOptionField:(Ljava/lang/String;Lscala/Function0;)Lzio/ZIO;
      14: areturn

  public static zio.ZIO getAccountId$(zio.aws.xray.model.ErrorRootCauseService$ReadOnly);
    Code:
       0: aload_0
       1: invokespecial #161                // InterfaceMethod getAccountId:()Lzio/ZIO;
       4: areturn

  public default zio.ZIO<java.lang.Object, zio.aws.core.AwsError, java.lang.String> getAccountId();
    Code:
       0: getstatic     #121                // Field zio/aws/core/AwsError$.MODULE$:Lzio/aws/core/AwsError$;
       3: ldc           #162                // String accountId
       5: aload_0
       6: invokedynamic #167,  0            // InvokeDynamic #9:apply:(Lzio/aws/xray/model/ErrorRootCauseService$ReadOnly;)Lscala/Function0;
      11: invokevirtual #136                // Method zio/aws/core/AwsError$.unwrapOptionField:(Ljava/lang/String;Lscala/Function0;)Lzio/ZIO;
      14: areturn

  public static zio.ZIO getEntityPath$(zio.aws.xray.model.ErrorRootCauseService$ReadOnly);
    Code:
       0: aload_0
       1: invokespecial #171                // InterfaceMethod getEntityPath:()Lzio/ZIO;
       4: areturn

  public default zio.ZIO<java.lang.Object, zio.aws.core.AwsError, scala.collection.immutable.List<zio.aws.xray.model.ErrorRootCauseEntity$ReadOnly>> getEntityPath();
    Code:
       0: getstatic     #121                // Field zio/aws/core/AwsError$.MODULE$:Lzio/aws/core/AwsError$;
       3: ldc           #173                // String entityPath
       5: aload_0
       6: invokedynamic #178,  0            // InvokeDynamic #10:apply:(Lzio/aws/xray/model/ErrorRootCauseService$ReadOnly;)Lscala/Function0;
      11: invokevirtual #136                // Method zio/aws/core/AwsError$.unwrapOptionField:(Ljava/lang/String;Lscala/Function0;)Lzio/ZIO;
      14: areturn

  public static zio.ZIO getInferred$(zio.aws.xray.model.ErrorRootCauseService$ReadOnly);
    Code:
       0: aload_0
       1: invokespecial #182                // InterfaceMethod getInferred:()Lzio/ZIO;
       4: areturn

  public default zio.ZIO<java.lang.Object, zio.aws.core.AwsError, java.lang.Object> getInferred();
    Code:
       0: getstatic     #121                // Field zio/aws/core/AwsError$.MODULE$:Lzio/aws/core/AwsError$;
       3: ldc           #184                // String inferred
       5: aload_0
       6: invokedynamic #189,  0            // InvokeDynamic #11:apply:(Lzio/aws/xray/model/ErrorRootCauseService$ReadOnly;)Lscala/Function0;
      11: invokevirtual #136                // Method zio/aws/core/AwsError$.unwrapOptionField:(Ljava/lang/String;Lscala/Function0;)Lzio/ZIO;
      14: areturn

  private java.lang.String asEditable$$anonfun$1(java.lang.String);
    Code:
       0: aload_1
       1: areturn

  private scala.collection.immutable.List asEditable$$anonfun$2(scala.collection.immutable.List);
    Code:
       0: aload_1
       1: areturn

  private java.lang.String asEditable$$anonfun$3(java.lang.String);
    Code:
       0: aload_1
       1: areturn

  private java.lang.String asEditable$$anonfun$4(java.lang.String);
    Code:
       0: aload_1
       1: areturn

  private zio.aws.xray.model.ErrorRootCauseEntity asEditable$$anonfun$5$$anonfun$1(zio.aws.xray.model.ErrorRootCauseEntity$ReadOnly);
    Code:
       0: aload_1
       1: invokeinterface #198,  1          // InterfaceMethod zio/aws/xray/model/ErrorRootCauseEntity$ReadOnly.asEditable:()Lzio/aws/xray/model/ErrorRootCauseEntity;
       6: areturn

  private scala.collection.immutable.List asEditable$$anonfun$5(scala.collection.immutable.List);
    Code:
       0: aload_1
       1: aload_0
       2: invokedynamic #204,  0            // InvokeDynamic #12:apply:(Lzio/aws/xray/model/ErrorRootCauseService$ReadOnly;)Lscala/Function1;
       7: invokevirtual #209                // Method scala/collection/immutable/List.map:(Lscala/Function1;)Lscala/collection/immutable/List;
      10: areturn

  private boolean asEditable$$anonfun$6(boolean);
    Code:
       0: iload_1
       1: ireturn

  private boolean asEditable$$anonfun$adapted$1(java.lang.Object);
    Code:
       0: aload_0
       1: aload_1
       2: invokestatic  #217                // Method scala/runtime/BoxesRunTime.unboxToBoolean:(Ljava/lang/Object;)Z
       5: invokespecial #219                // InterfaceMethod asEditable$$anonfun$6:(Z)Z
       8: ireturn

  private zio.prelude.data.Optional getName$$anonfun$1();
    Code:
       0: aload_0
       1: invokeinterface #30,  1           // InterfaceMethod name:()Lzio/prelude/data/Optional;
       6: areturn

  private zio.prelude.data.Optional getNames$$anonfun$1();
    Code:
       0: aload_0
       1: invokeinterface #60,  1           // InterfaceMethod names:()Lzio/prelude/data/Optional;
       6: areturn

  private zio.prelude.data.Optional getType$$anonfun$1();
    Code:
       0: aload_0
       1: invokeinterface #70,  1           // InterfaceMethod type:()Lzio/prelude/data/Optional;
       6: areturn

  private zio.prelude.data.Optional getAccountId$$anonfun$1();
    Code:
       0: aload_0
       1: invokeinterface #78,  1           // InterfaceMethod accountId:()Lzio/prelude/data/Optional;
       6: areturn

  private zio.prelude.data.Optional getEntityPath$$anonfun$1();
    Code:
       0: aload_0
       1: invokeinterface #86,  1           // InterfaceMethod entityPath:()Lzio/prelude/data/Optional;
       6: areturn

  private zio.prelude.data.Optional getInferred$$anonfun$1();
    Code:
       0: aload_0
       1: invokeinterface #94,  1           // InterfaceMethod inferred:()Lzio/prelude/data/Optional;
       6: areturn

  private static java.lang.Object $deserializeLambda$(java.lang.invoke.SerializedLambda);
    Code:
       0: aload_0
       1: invokedynamic #232,  0            // InvokeDynamic #13:lambdaDeserialize:(Ljava/lang/invoke/SerializedLambda;)Ljava/lang/Object;
       6: areturn
}
